// 
// Decompiled by Procyon v0.6.0
// 

public final class aaiw implements aahl
{
    private volatile boolean A;
    private final int B;
    private final int C;
    private final abwe D;
    private final acjq E;
    private final aefs F;
    zbx a;
    final adgg b;
    final adgg c;
    private final aaks d;
    private final aahk e;
    private final aage f;
    private final vku g;
    private final aadf h;
    private final String i;
    private final String j;
    private final String k;
    private final byte[] l;
    private final String m;
    private yhm n;
    private yhm o;
    private final aaiz p;
    private final aajd q;
    private final aajd r;
    private final aacd s;
    private final oco t;
    private final int u;
    private final int v;
    private final String w;
    private final aajb x;
    private final ykv y;
    private final zby z;
    
    public aaiw(final aahk e, final aage f, final vku g, final oco t, final aefs f2, final aadf h, final adgg b, final adgg c, final aajb x, final acjq e2, final aacd s, final zby z, final aaks d, final ykv y, final abwe d2, final byte[] array, final byte[] array2, final byte[] array3, final byte[] array4, final byte[] array5, final byte[] array6, final byte[] array7, final byte[] array8) {
        this.e = e;
        this.f = f;
        this.g = g;
        this.t = t;
        this.F = f2;
        this.h = h;
        this.b = b;
        this.c = c;
        this.x = x;
        this.E = e2;
        this.s = s;
        this.z = z;
        this.d = d;
        this.y = y;
        this.D = d2;
        final int d3 = aahc.d(h.f);
        this.u = d3;
        this.v = d3;
        final int aj = aahc.aj(h.f);
        this.B = aj;
        this.C = aj;
        this.w = aahc.q(h.f);
        this.i = h.a;
        this.j = f2.cw();
        this.k = aahc.u(h.f);
        this.l = aahc.af(h.f);
        this.q = new aajd();
        this.r = new aajd();
        this.p = new aaiz(t, f.d(), new aaiu(this, 0));
        this.m = aahc.t(h.f);
    }
    
    private final aach c() {
        final aach g = this.h.g;
        aahc.z(g, this.q.a() + this.r.a());
        aahc.N(g, this.q.b() + this.r.b());
        return g;
    }
    
    private final void d(final aahm aahm) {
        if (aahm.a) {
            final Throwable cause = aahm.getCause();
            if (cause != null) {
                final String m = this.m;
                final String message = aahm.getMessage();
                final StringBuilder sb = new StringBuilder("[Offline] pudl task cotn [");
                sb.append(m);
                sb.append("] failed: ");
                sb.append(message);
                tut.d(sb.toString(), cause);
            }
            else {
                final String i = this.m;
                final String message2 = aahm.getMessage();
                final StringBuilder sb2 = new StringBuilder("[Offline] pudl task cotn [");
                sb2.append(i);
                sb2.append("] failed, unknown cause: ");
                sb2.append(message2);
                tut.d(sb2.toString(), (Throwable)new IllegalArgumentException());
            }
        }
        else {
            final String j = this.m;
            final String message3 = aahm.getMessage();
            final StringBuilder sb3 = new StringBuilder("[Offline] pudl task cotn [");
            sb3.append(j);
            sb3.append("]: ");
            sb3.append(message3);
            tut.l(sb3.toString());
        }
        final zbx a = this.a;
        if (a != null) {
            a.g();
        }
        this.e.d(this.i, aahm, this.c());
    }
    
    private static final boolean e(final aacu aacu, final boolean b) {
        boolean b2 = true;
        if (!b) {
            if (aacu != null) {
                if (aacu.i()) {
                    return false;
                }
                b2 = b2;
            }
            else {
                b2 = false;
            }
        }
        return b2;
    }
    
    @Override
    public final void a(final int n) {
        boolean b = true;
        this.A = true;
        final yhm n2 = this.n;
        if ((n & 0x180) != 0x0) {
            b = false;
        }
        if (n2 != null) {
            n2.a(b);
        }
        final yhm o = this.o;
        if (o != null) {
            o.a(b);
        }
    }
    
    public final void b(final long n, final double n2, final boolean b) {
        this.e.b(this.i, n, n2, b);
    }
    
    @Override
    public final void run() {
        // 
        // This method could not be decompiled.
        // 
        // Original Bytecode:
        // 
        //     2: invokestatic    android/os/Process.setThreadPriority:(I)V
        //     5: aload_0        
        //     6: getfield        aaiw.f:Laage;
        //     9: invokeinterface aage.B:()Lzxm;
        //    14: astore          25
        //    16: aload_0        
        //    17: getfield        aaiw.h:Laadf;
        //    20: getfield        aadf.i:Z
        //    23: ifne            41
        //    26: aload           25
        //    28: ifnull          34
        //    31: goto            41
        //    34: ldc_w           "[Offline] Couldn't get db helper due to initialization or non-active store."
        //    37: invokestatic    tut.b:(Ljava/lang/String;)V
        //    40: return         
        //    41: aload_0        
        //    42: getfield        aaiw.A:Z
        //    45: ifeq            51
        //    48: goto            4942
        //    51: aload_0        
        //    52: getfield        aaiw.k:Ljava/lang/String;
        //    55: invokestatic    android/text/TextUtils.isEmpty:(Ljava/lang/CharSequence;)Z
        //    58: ifeq            90
        //    61: new             Ljava/lang/IllegalArgumentException;
        //    64: astore          13
        //    66: aload           13
        //    68: invokespecial   java/lang/IllegalArgumentException.<init>:()V
        //    71: aload_0        
        //    72: ldc_w           "No videoid specified on video transfer."
        //    75: aload           13
        //    77: getstatic       aacn.d:Laacn;
        //    80: getstatic       amxs.a:Lamxs;
        //    83: invokestatic    aahm.a:(Ljava/lang/String;Ljava/lang/Exception;Laacn;Lamxs;)Laahm;
        //    86: invokespecial   aaiw.d:(Laahm;)V
        //    89: return         
        //    90: aload_0        
        //    91: getfield        aaiw.f:Laage;
        //    94: invokeinterface aage.f:()Laabr;
        //    99: astore          13
        //   101: aload_0        
        //   102: getfield        aaiw.h:Laadf;
        //   105: astore          14
        //   107: aload           14
        //   109: getfield        aadf.i:Z
        //   112: ifeq            118
        //   115: goto            203
        //   118: aload           14
        //   120: getfield        aadf.f:Laach;
        //   123: invokestatic    aahc.s:(Laach;)Ljava/lang/String;
        //   126: astore          14
        //   128: aload_0        
        //   129: getfield        aaiw.d:Laaks;
        //   132: getfield        aaks.c:Lvbs;
        //   135: ldc2_w          45367078
        //   138: invokevirtual   vbs.f:(J)Z
        //   141: ifeq            149
        //   144: aload           14
        //   146: ifnull          203
        //   149: aload_0        
        //   150: getfield        aaiw.d:Laaks;
        //   153: invokevirtual   aaks.n:()Z
        //   156: ifeq            164
        //   159: aload           14
        //   161: ifnonnull       203
        //   164: aload           25
        //   166: ifnull          203
        //   169: aload           13
        //   171: ifnull          203
        //   174: aload           25
        //   176: aload           13
        //   178: aload_0        
        //   179: getfield        aaiw.h:Laadf;
        //   182: invokestatic    aajb.f:(Lzxm;Laabs;Laadf;)V
        //   185: goto            203
        //   188: astore          13
        //   190: goto            4095
        //   193: astore          13
        //   195: goto            4165
        //   198: astore          13
        //   200: goto            4181
        //   203: aload_0        
        //   204: getfield        aaiw.f:Laage;
        //   207: invokeinterface aage.d:()Lzyd;
        //   212: astore          16
        //   214: aload_0        
        //   215: getfield        aaiw.d:Laaks;
        //   218: invokevirtual   aaks.l:()Z
        //   221: istore          11
        //   223: iload           11
        //   225: ifeq            370
        //   228: aload_0        
        //   229: getfield        aaiw.x:Laajb;
        //   232: astore          15
        //   234: aload_0        
        //   235: getfield        aaiw.h:Laadf;
        //   238: getfield        aadf.j:Lznz;
        //   241: astore          13
        //   243: aload_0        
        //   244: getfield        aaiw.k:Ljava/lang/String;
        //   247: astore          14
        //   249: aload           13
        //   251: invokeinterface znz.z:()Z
        //   256: ifeq            265
        //   259: aconst_null    
        //   260: astore          13
        //   262: goto            331
        //   265: aload           15
        //   267: getfield        aajb.i:Ljava/lang/Object;
        //   270: aload           13
        //   272: invokeinterface vfn.a:(Lznz;)Lvfm;
        //   277: aload           14
        //   279: invokestatic    aajb.b:(Ljava/lang/String;)Ljava/lang/String;
        //   282: invokeinterface vfm.g:(Ljava/lang/String;)Laskj;
        //   287: ldc_w           Lanff;.class
        //   290: invokevirtual   askj.j:(Ljava/lang/Class;)Laskj;
        //   293: invokevirtual   askj.af:()Ljava/lang/Object;
        //   296: checkcast       Lanff;
        //   299: astore          13
        //   301: aload           13
        //   303: ifnull          259
        //   306: aload           13
        //   308: invokevirtual   anff.i:()Z
        //   311: ifne            317
        //   314: goto            259
        //   317: aload           13
        //   319: invokevirtual   anff.getPlayerResponseBytes:()Lahbt;
        //   322: invokevirtual   ahbt.I:()[B
        //   325: lconst_0       
        //   326: invokestatic    com/google/android/libraries/youtube/innertube/model/player/PlayerResponseModelImpl.af:([BJ)Lcom/google/android/libraries/youtube/innertube/model/player/PlayerResponseModel;
        //   329: astore          13
        //   331: aload           13
        //   333: ifnonnull       367
        //   336: aload_0        
        //   337: getfield        aaiw.e:Laahk;
        //   340: aload_0        
        //   341: getfield        aaiw.i:Ljava/lang/String;
        //   344: ldc_w           "PlayerResponse doesn't exist"
        //   347: aconst_null    
        //   348: getstatic       aacn.h:Laacn;
        //   351: getstatic       amxs.e:Lamxs;
        //   354: invokestatic    aahm.a:(Ljava/lang/String;Ljava/lang/Exception;Laacn;Lamxs;)Laahm;
        //   357: aload_0        
        //   358: invokespecial   aaiw.c:()Laach;
        //   361: invokeinterface aahk.d:(Ljava/lang/String;Laahm;Laach;)V
        //   366: return         
        //   367: goto            454
        //   370: aload_0        
        //   371: getfield        aaiw.x:Laajb;
        //   374: aload_0        
        //   375: getfield        aaiw.k:Ljava/lang/String;
        //   378: aload_0        
        //   379: getfield        aaiw.l:[B
        //   382: aload_0        
        //   383: getfield        aaiw.h:Laadf;
        //   386: iconst_2       
        //   387: invokevirtual   aajb.h:(Ljava/lang/String;[BLaadf;I)Lcom/google/android/libraries/youtube/innertube/model/player/PlayerResponseModel;
        //   390: astore          13
        //   392: aload_0        
        //   393: getfield        aaiw.h:Laadf;
        //   396: getfield        aadf.i:Z
        //   399: istore          11
        //   401: iload           11
        //   403: ifne            454
        //   406: aload           25
        //   408: ifnull          454
        //   411: aload           25
        //   413: aload_0        
        //   414: getfield        aaiw.k:Ljava/lang/String;
        //   417: invokevirtual   zxm.q:(Ljava/lang/String;)Lcom/google/android/libraries/youtube/innertube/model/player/PlayerResponseModel;
        //   420: ifnonnull       454
        //   423: aload_0        
        //   424: getfield        aaiw.i:Ljava/lang/String;
        //   427: aload_0        
        //   428: getfield        aaiw.k:Ljava/lang/String;
        //   431: aload           13
        //   433: aload           25
        //   435: aload_0        
        //   436: getfield        aaiw.t:Loco;
        //   439: invokeinterface oco.c:()J
        //   444: aload_0        
        //   445: getfield        aaiw.g:Lvku;
        //   448: invokestatic    aajb.e:(Ljava/lang/String;Ljava/lang/String;Lcom/google/android/libraries/youtube/innertube/model/player/PlayerResponseModel;Lzxm;JLvku;)V
        //   451: goto            454
        //   454: aload_0        
        //   455: getfield        aaiw.i:Ljava/lang/String;
        //   458: aload           13
        //   460: invokestatic    aajb.i:(Ljava/lang/String;Lcom/google/android/libraries/youtube/innertube/model/player/PlayerResponseModel;)V
        //   463: aload_0        
        //   464: getfield        aaiw.f:Laage;
        //   467: invokeinterface aage.g:()Laaga;
        //   472: astore          17
        //   474: aload_0        
        //   475: getfield        aaiw.k:Ljava/lang/String;
        //   478: astore          15
        //   480: aload_0        
        //   481: getfield        aaiw.v:I
        //   484: invokestatic    aakx.c:(I)Lamze;
        //   487: pop            
        //   488: getstatic       vby.a:[B
        //   491: astore          14
        //   493: aload           17
        //   495: aload           15
        //   497: aload           13
        //   499: invokeinterface aaga.j:(Ljava/lang/String;Lcom/google/android/libraries/youtube/innertube/model/player/PlayerResponseModel;)Ljava/lang/String;
        //   504: astore          19
        //   506: aload           19
        //   508: invokestatic    android/text/TextUtils.isEmpty:(Ljava/lang/CharSequence;)Z
        //   511: istore          11
        //   513: iload           11
        //   515: ifne            550
        //   518: aload_0        
        //   519: getfield        aaiw.x:Laajb;
        //   522: aload           19
        //   524: aload_0        
        //   525: getfield        aaiw.l:[B
        //   528: aload_0        
        //   529: getfield        aaiw.h:Laadf;
        //   532: iconst_1       
        //   533: invokevirtual   aajb.h:(Ljava/lang/String;[BLaadf;I)Lcom/google/android/libraries/youtube/innertube/model/player/PlayerResponseModel;
        //   536: astore          17
        //   538: aload_0        
        //   539: getfield        aaiw.i:Ljava/lang/String;
        //   542: aload           17
        //   544: invokestatic    aajb.i:(Ljava/lang/String;Lcom/google/android/libraries/youtube/innertube/model/player/PlayerResponseModel;)V
        //   547: goto            553
        //   550: aconst_null    
        //   551: astore          17
        //   553: aload_0        
        //   554: getfield        aaiw.h:Laadf;
        //   557: getfield        aadf.i:Z
        //   560: istore          11
        //   562: iload           11
        //   564: ifne            593
        //   567: aload           25
        //   569: ifnull          593
        //   572: aload_0        
        //   573: getfield        aaiw.x:Laajb;
        //   576: aload_0        
        //   577: getfield        aaiw.i:Ljava/lang/String;
        //   580: aload_0        
        //   581: getfield        aaiw.k:Ljava/lang/String;
        //   584: aload           25
        //   586: aload_0        
        //   587: getfield        aaiw.e:Laahk;
        //   590: invokevirtual   aajb.d:(Ljava/lang/String;Ljava/lang/String;Lzxm;Laahk;)V
        //   593: aload           13
        //   595: invokeinterface com/google/android/libraries/youtube/innertube/model/player/PlayerResponseModel.n:()Lcom/google/android/libraries/youtube/innertube/model/media/VideoStreamingData;
        //   600: astore          18
        //   602: aload_0        
        //   603: getfield        aaiw.x:Laajb;
        //   606: astore          20
        //   608: aload_0        
        //   609: getfield        aaiw.u:I
        //   612: istore_2       
        //   613: iload_2        
        //   614: istore_1       
        //   615: iload_2        
        //   616: ifne            705
        //   619: aload           13
        //   621: ifnull          703
        //   624: aload           13
        //   626: invokeinterface com/google/android/libraries/youtube/innertube/model/player/PlayerResponseModel.y:()Lakyz;
        //   631: getfield        akyz.k:Lakyp;
        //   634: astore          15
        //   636: aload           15
        //   638: astore          14
        //   640: aload           15
        //   642: ifnonnull       650
        //   645: getstatic       akyp.a:Lakyp;
        //   648: astore          14
        //   650: aload           14
        //   652: getfield        akyp.b:Lahyc;
        //   655: astore          15
        //   657: aload           15
        //   659: astore          14
        //   661: aload           15
        //   663: ifnonnull       671
        //   666: getstatic       ahyc.a:Lahyc;
        //   669: astore          14
        //   671: aload           14
        //   673: getfield        ahyc.b:I
        //   676: invokestatic    adzw.cc:(I)I
        //   679: istore_1       
        //   680: iload_1        
        //   681: ifne            687
        //   684: goto            703
        //   687: iload_1        
        //   688: iconst_3       
        //   689: if_icmpne       703
        //   692: getstatic       amze.c:Lamze;
        //   695: iconst_0       
        //   696: invokestatic    aakx.a:(Lamze;I)I
        //   699: istore_1       
        //   700: goto            705
        //   703: iconst_0       
        //   704: istore_1       
        //   705: aload_0        
        //   706: getfield        aaiw.B:I
        //   709: istore_2       
        //   710: aload_0        
        //   711: getfield        aaiw.w:Ljava/lang/String;
        //   714: astore          21
        //   716: aload_0        
        //   717: getfield        aaiw.k:Ljava/lang/String;
        //   720: astore          14
        //   722: aload           13
        //   724: invokeinterface com/google/android/libraries/youtube/innertube/model/player/PlayerResponseModel.m:()Lcom/google/android/libraries/youtube/innertube/model/media/PlayerConfigModel;
        //   729: astore          15
        //   731: aload           20
        //   733: iload_1        
        //   734: iload_2        
        //   735: aload           21
        //   737: aload           14
        //   739: aload           18
        //   741: aload           15
        //   743: aload           16
        //   745: invokevirtual   aajb.g:(IILjava/lang/String;Ljava/lang/String;Lcom/google/android/libraries/youtube/innertube/model/media/VideoStreamingData;Lcom/google/android/libraries/youtube/innertube/model/media/PlayerConfigModel;Lzyd;)Laacv;
        //   748: astore          15
        //   750: aload           16
        //   752: aload_0        
        //   753: getfield        aaiw.k:Ljava/lang/String;
        //   756: aload           15
        //   758: invokeinterface zyd.c:(Ljava/lang/String;Laacv;)V
        //   763: aload_0        
        //   764: getfield        aaiw.z:Lzby;
        //   767: astore          20
        //   769: aload           13
        //   771: invokeinterface com/google/android/libraries/youtube/innertube/model/player/PlayerResponseModel.o:()Lcom/google/android/libraries/youtube/innertube/model/player/PlaybackTrackingModel;
        //   776: getfield        com/google/android/libraries/youtube/innertube/model/player/PlaybackTrackingModel.f:Lcom/google/android/libraries/youtube/innertube/model/player/TrackingUrlModel;
        //   779: astore          21
        //   781: aload_0        
        //   782: getfield        aaiw.j:Ljava/lang/String;
        //   785: astore          14
        //   787: aload_0        
        //   788: getfield        aaiw.m:Ljava/lang/String;
        //   791: astore          22
        //   793: aload_0        
        //   794: getfield        aaiw.h:Laadf;
        //   797: getfield        aadf.f:Laach;
        //   800: invokestatic    aahc.ak:(Laach;)I
        //   803: bipush          6
        //   805: if_icmpne       813
        //   808: iconst_2       
        //   809: istore_1       
        //   810: goto            815
        //   813: iconst_1       
        //   814: istore_1       
        //   815: aload           20
        //   817: aload           21
        //   819: aload           14
        //   821: aconst_null    
        //   822: aload           22
        //   824: iload_1        
        //   825: invokestatic    java/lang/Integer.valueOf:(I)Ljava/lang/Integer;
        //   828: aload_0        
        //   829: getfield        aaiw.k:Ljava/lang/String;
        //   832: aload           18
        //   834: iconst_0       
        //   835: aload           13
        //   837: invokeinterface com/google/android/libraries/youtube/innertube/model/player/PlayerResponseModel.m:()Lcom/google/android/libraries/youtube/innertube/model/media/PlayerConfigModel;
        //   842: invokevirtual   zby.b:(Lcom/google/android/libraries/youtube/innertube/model/player/TrackingUrlModel;Ljava/lang/String;Lapuo;Ljava/lang/String;Ljava/lang/Integer;Ljava/lang/String;Lcom/google/android/libraries/youtube/innertube/model/media/VideoStreamingData;ZLcom/google/android/libraries/youtube/innertube/model/media/PlayerConfigModel;)Lzbx;
        //   845: astore          14
        //   847: aload_0        
        //   848: aload           14
        //   850: putfield        aaiw.a:Lzbx;
        //   853: aload           14
        //   855: ifnull          917
        //   858: aload_0        
        //   859: getfield        aaiw.y:Lykv;
        //   862: astore          21
        //   864: aload           21
        //   866: getfield        ykv.d:Ltkq;
        //   869: invokeinterface tkq.r:()Z
        //   874: ifne            917
        //   877: aload           21
        //   879: getfield        ykv.c:Landroid/os/Handler;
        //   882: astore          18
        //   884: new             Lybl;
        //   887: astore          20
        //   889: aload           20
        //   891: aload           21
        //   893: aload           14
        //   895: iconst_3       
        //   896: invokespecial   ybl.<init>:(Lykv;Lzbx;I)V
        //   899: aload           18
        //   901: aload           20
        //   903: invokevirtual   android/os/Handler.post:(Ljava/lang/Runnable;)Z
        //   906: pop            
        //   907: goto            917
        //   910: astore          14
        //   912: getstatic       zde.a:Lzde;
        //   915: astore          14
        //   917: aload_0        
        //   918: getfield        aaiw.h:Laadf;
        //   921: getfield        aadf.f:Laach;
        //   924: invokestatic    aahc.ab:(Laach;)Z
        //   927: istore          11
        //   929: iload           11
        //   931: ifeq            956
        //   934: aload_0        
        //   935: getfield        aaiw.a:Lzbx;
        //   938: astore          14
        //   940: aload           14
        //   942: ifnull          956
        //   945: aload           14
        //   947: ldc_w           "cat"
        //   950: ldc_w           "unmetered_5g"
        //   953: invokevirtual   zbx.B:(Ljava/lang/String;Ljava/lang/String;)V
        //   956: aload           17
        //   958: ifnull          1005
        //   961: aload           19
        //   963: ifnull          1005
        //   966: aload_0        
        //   967: getfield        aaiw.x:Laajb;
        //   970: aload_0        
        //   971: getfield        aaiw.v:I
        //   974: aload_0        
        //   975: getfield        aaiw.C:I
        //   978: aconst_null    
        //   979: aload           19
        //   981: aload           17
        //   983: invokeinterface com/google/android/libraries/youtube/innertube/model/player/PlayerResponseModel.n:()Lcom/google/android/libraries/youtube/innertube/model/media/VideoStreamingData;
        //   988: aload           17
        //   990: invokeinterface com/google/android/libraries/youtube/innertube/model/player/PlayerResponseModel.m:()Lcom/google/android/libraries/youtube/innertube/model/media/PlayerConfigModel;
        //   995: aload           16
        //   997: invokevirtual   aajb.g:(IILjava/lang/String;Ljava/lang/String;Lcom/google/android/libraries/youtube/innertube/model/media/VideoStreamingData;Lcom/google/android/libraries/youtube/innertube/model/media/PlayerConfigModel;Lzyd;)Laacv;
        //  1000: astore          18
        //  1002: goto            1008
        //  1005: aconst_null    
        //  1006: astore          18
        //  1008: new             Ljava/util/HashSet;
        //  1011: astore          20
        //  1013: aload           20
        //  1015: invokespecial   java/util/HashSet.<init>:()V
        //  1018: new             Ljava/util/ArrayList;
        //  1021: astore          14
        //  1023: aload           14
        //  1025: invokespecial   java/util/ArrayList.<init>:()V
        //  1028: aload_0        
        //  1029: getfield        aaiw.D:Labwe;
        //  1032: astore          21
        //  1034: aload           21
        //  1036: aload           13
        //  1038: invokevirtual   abwe.k:(Lcom/google/android/libraries/youtube/innertube/model/player/PlayerResponseModel;)Ljava/util/List;
        //  1041: astore          22
        //  1043: aload           22
        //  1045: invokeinterface java/util/List.iterator:()Ljava/util/Iterator;
        //  1050: astore          21
        //  1052: aload           21
        //  1054: invokeinterface java/util/Iterator.hasNext:()Z
        //  1059: istore          11
        //  1061: iload           11
        //  1063: ifeq            1092
        //  1066: aload           20
        //  1068: aload           21
        //  1070: invokeinterface java/util/Iterator.next:()Ljava/lang/Object;
        //  1075: checkcast       Lcom/google/android/libraries/youtube/innertube/model/player/PlayerResponseModel;
        //  1078: invokeinterface com/google/android/libraries/youtube/innertube/model/player/PlayerResponseModel.K:()Ljava/lang/String;
        //  1083: invokeinterface java/util/Set.add:(Ljava/lang/Object;)Z
        //  1088: pop            
        //  1089: goto            1052
        //  1092: aload           16
        //  1094: aload           20
        //  1096: aload_0        
        //  1097: getfield        aaiw.k:Ljava/lang/String;
        //  1100: invokeinterface zyd.d:(Ljava/util/Set;Ljava/lang/String;)V
        //  1105: aload           22
        //  1107: invokeinterface java/util/List.iterator:()Ljava/util/Iterator;
        //  1112: astore          20
        //  1114: aload           13
        //  1116: astore          21
        //  1118: aload           20
        //  1120: invokeinterface java/util/Iterator.hasNext:()Z
        //  1125: istore          11
        //  1127: iload           11
        //  1129: ifeq            1199
        //  1132: aload           20
        //  1134: invokeinterface java/util/Iterator.next:()Ljava/lang/Object;
        //  1139: checkcast       Lcom/google/android/libraries/youtube/innertube/model/player/PlayerResponseModel;
        //  1142: astore          13
        //  1144: aload           14
        //  1146: aload           13
        //  1148: aload_0        
        //  1149: getfield        aaiw.x:Laajb;
        //  1152: aload_0        
        //  1153: getfield        aaiw.u:I
        //  1156: aload_0        
        //  1157: getfield        aaiw.B:I
        //  1160: aconst_null    
        //  1161: aload           13
        //  1163: invokeinterface com/google/android/libraries/youtube/innertube/model/player/PlayerResponseModel.K:()Ljava/lang/String;
        //  1168: aload           13
        //  1170: invokeinterface com/google/android/libraries/youtube/innertube/model/player/PlayerResponseModel.n:()Lcom/google/android/libraries/youtube/innertube/model/media/VideoStreamingData;
        //  1175: aload           13
        //  1177: invokeinterface com/google/android/libraries/youtube/innertube/model/player/PlayerResponseModel.m:()Lcom/google/android/libraries/youtube/innertube/model/media/PlayerConfigModel;
        //  1182: aload           16
        //  1184: invokevirtual   aajb.g:(IILjava/lang/String;Ljava/lang/String;Lcom/google/android/libraries/youtube/innertube/model/media/VideoStreamingData;Lcom/google/android/libraries/youtube/innertube/model/media/PlayerConfigModel;Lzyd;)Laacv;
        //  1187: invokestatic    afbi.a:(Ljava/lang/Object;Ljava/lang/Object;)Lafbi;
        //  1190: invokeinterface java/util/List.add:(Ljava/lang/Object;)Z
        //  1195: pop            
        //  1196: goto            1118
        //  1199: aload           15
        //  1201: getfield        aacv.c:J
        //  1204: lstore          9
        //  1206: aload           15
        //  1208: getfield        aacv.d:J
        //  1211: lstore          7
        //  1213: lload           9
        //  1215: lstore          5
        //  1217: lload           7
        //  1219: lstore_3       
        //  1220: aload           18
        //  1222: ifnull          1246
        //  1225: lload           9
        //  1227: aload           18
        //  1229: getfield        aacv.c:J
        //  1232: ladd           
        //  1233: lstore          5
        //  1235: aload           18
        //  1237: getfield        aacv.d:J
        //  1240: lstore_3       
        //  1241: lload           7
        //  1243: lload_3        
        //  1244: ladd           
        //  1245: lstore_3       
        //  1246: aload           14
        //  1248: invokeinterface java/util/List.iterator:()Ljava/util/Iterator;
        //  1253: astore          13
        //  1255: aload           13
        //  1257: invokeinterface java/util/Iterator.hasNext:()Z
        //  1262: istore          11
        //  1264: iload           11
        //  1266: ifeq            1312
        //  1269: aload           13
        //  1271: invokeinterface java/util/Iterator.next:()Ljava/lang/Object;
        //  1276: checkcast       Lafbi;
        //  1279: getfield        afbi.b:Ljava/lang/Object;
        //  1282: checkcast       Laacv;
        //  1285: astore          16
        //  1287: lload           5
        //  1289: aload           16
        //  1291: getfield        aacv.c:J
        //  1294: ladd           
        //  1295: lstore          5
        //  1297: aload           16
        //  1299: getfield        aacv.d:J
        //  1302: lstore          7
        //  1304: lload_3        
        //  1305: lload           7
        //  1307: ladd           
        //  1308: lstore_3       
        //  1309: goto            1255
        //  1312: lload_3        
        //  1313: lload           5
        //  1315: lcmp           
        //  1316: ifle            1325
        //  1319: iconst_1       
        //  1320: istore          11
        //  1322: goto            1328
        //  1325: iconst_0       
        //  1326: istore          11
        //  1328: aload_0        
        //  1329: getfield        aaiw.p:Laaiz;
        //  1332: astore          13
        //  1334: aload           13
        //  1336: lload_3        
        //  1337: putfield        aaiz.c:J
        //  1340: aload           13
        //  1342: lconst_0       
        //  1343: putfield        aaiz.b:J
        //  1346: aload_0        
        //  1347: getfield        aaiw.e:Laahk;
        //  1350: aload_0        
        //  1351: getfield        aaiw.i:Ljava/lang/String;
        //  1354: lload_3        
        //  1355: invokeinterface aahk.c:(Ljava/lang/String;J)V
        //  1360: aload           15
        //  1362: astore          13
        //  1364: aload_0        
        //  1365: lload           5
        //  1367: dconst_0       
        //  1368: iload           11
        //  1370: invokevirtual   aaiw.b:(JDZ)V
        //  1373: iload           11
        //  1375: istore          12
        //  1377: aload           13
        //  1379: astore          20
        //  1381: aload           14
        //  1383: invokeinterface java/util/List.isEmpty:()Z
        //  1388: ifne            1764
        //  1391: aload           14
        //  1393: invokeinterface java/util/List.iterator:()Ljava/util/Iterator;
        //  1398: astore          14
        //  1400: iload           11
        //  1402: istore          12
        //  1404: aload           13
        //  1406: astore          20
        //  1408: aload           14
        //  1410: invokeinterface java/util/Iterator.hasNext:()Z
        //  1415: ifeq            1764
        //  1418: aload           14
        //  1420: invokeinterface java/util/Iterator.next:()Ljava/lang/Object;
        //  1425: checkcast       Lafbi;
        //  1428: astore          15
        //  1430: aload           15
        //  1432: getfield        afbi.a:Ljava/lang/Object;
        //  1435: checkcast       Lcom/google/android/libraries/youtube/innertube/model/player/PlayerResponseModel;
        //  1438: astore          22
        //  1440: aload           15
        //  1442: getfield        afbi.b:Ljava/lang/Object;
        //  1445: checkcast       Laacv;
        //  1448: astore          20
        //  1450: aload_0        
        //  1451: getfield        aaiw.b:Ladgg;
        //  1454: invokevirtual   adgg.az:()Ladgg;
        //  1457: astore          23
        //  1459: aload           23
        //  1461: invokevirtual   adgg.V:()Lafbh;
        //  1464: invokevirtual   afbh.f:()Ljava/lang/Object;
        //  1467: checkcast       Ljava/lang/String;
        //  1470: astore          16
        //  1472: aload_0        
        //  1473: getfield        aaiw.n:Lyhm;
        //  1476: astore          15
        //  1478: aload           15
        //  1480: ifnonnull       1514
        //  1483: aload           23
        //  1485: getfield        adgg.a:Ljava/lang/Object;
        //  1488: checkcast       Laaiq;
        //  1491: invokevirtual   aaiq.a:()Lyhm;
        //  1494: astore          15
        //  1496: aload           15
        //  1498: aload_0        
        //  1499: getfield        aaiw.p:Laaiz;
        //  1502: putfield        yhm.b:Lyhl;
        //  1505: aload_0        
        //  1506: aload           15
        //  1508: putfield        aaiw.n:Lyhm;
        //  1511: goto            1514
        //  1514: aload           22
        //  1516: invokeinterface com/google/android/libraries/youtube/innertube/model/player/PlayerResponseModel.K:()Ljava/lang/String;
        //  1521: astore          22
        //  1523: aload_0        
        //  1524: getfield        aaiw.p:Laaiz;
        //  1527: aload           22
        //  1529: putfield        aaiz.a:Ljava/lang/String;
        //  1532: aload           20
        //  1534: getfield        aacv.a:Laacu;
        //  1537: astore          23
        //  1539: aload           23
        //  1541: ifnull          1638
        //  1544: aload_0        
        //  1545: getfield        aaiw.i:Ljava/lang/String;
        //  1548: astore          28
        //  1550: aload_0        
        //  1551: getfield        aaiw.j:Ljava/lang/String;
        //  1554: astore          27
        //  1556: aload           23
        //  1558: invokevirtual   aacu.b:()J
        //  1561: lstore          5
        //  1563: aload_0        
        //  1564: getfield        aaiw.f:Laage;
        //  1567: invokeinterface aage.d:()Lzyd;
        //  1572: astore          26
        //  1574: aload_0        
        //  1575: getfield        aaiw.q:Laajd;
        //  1578: astore          24
        //  1580: aload           22
        //  1582: aload           28
        //  1584: aload           27
        //  1586: aload           15
        //  1588: aload           23
        //  1590: lload           5
        //  1592: aload           26
        //  1594: aload           16
        //  1596: aload           24
        //  1598: getfield        aajd.c:Lzch;
        //  1601: aload           24
        //  1603: getfield        aajd.a:Lzch;
        //  1606: aload_0        
        //  1607: getfield        aaiw.E:Lacjq;
        //  1610: invokestatic    aajb.o:(Ljava/lang/String;Ljava/lang/String;Ljava/lang/String;Lyhm;Laacu;JLzyd;Ljava/lang/String;Lzch;Lzch;Lacjq;)V
        //  1613: aload_0        
        //  1614: getfield        aaiw.p:Laaiz;
        //  1617: astore          24
        //  1619: aload           24
        //  1621: aload           24
        //  1623: getfield        aaiz.b:J
        //  1626: aload           23
        //  1628: invokevirtual   aacu.b:()J
        //  1631: ladd           
        //  1632: putfield        aaiz.b:J
        //  1635: goto            1638
        //  1638: aload_0        
        //  1639: getfield        aaiw.A:Z
        //  1642: ifeq            1648
        //  1645: goto            1751
        //  1648: aload           20
        //  1650: getfield        aacv.b:Laacu;
        //  1653: astore          20
        //  1655: aload           20
        //  1657: ifnull          1751
        //  1660: aload_0        
        //  1661: getfield        aaiw.i:Ljava/lang/String;
        //  1664: astore          23
        //  1666: aload_0        
        //  1667: getfield        aaiw.j:Ljava/lang/String;
        //  1670: astore          27
        //  1672: aload           20
        //  1674: invokevirtual   aacu.b:()J
        //  1677: lstore          5
        //  1679: aload_0        
        //  1680: getfield        aaiw.f:Laage;
        //  1683: invokeinterface aage.d:()Lzyd;
        //  1688: astore          24
        //  1690: aload_0        
        //  1691: getfield        aaiw.q:Laajd;
        //  1694: astore          26
        //  1696: aload           22
        //  1698: aload           23
        //  1700: aload           27
        //  1702: aload           15
        //  1704: aload           20
        //  1706: lload           5
        //  1708: aload           24
        //  1710: aload           16
        //  1712: aload           26
        //  1714: getfield        aajd.d:Lzch;
        //  1717: aload           26
        //  1719: getfield        aajd.b:Lzch;
        //  1722: aload_0        
        //  1723: getfield        aaiw.E:Lacjq;
        //  1726: invokestatic    aajb.o:(Ljava/lang/String;Ljava/lang/String;Ljava/lang/String;Lyhm;Laacu;JLzyd;Ljava/lang/String;Lzch;Lzch;Lacjq;)V
        //  1729: aload_0        
        //  1730: getfield        aaiw.p:Laaiz;
        //  1733: astore          15
        //  1735: aload           15
        //  1737: aload           15
        //  1739: getfield        aaiz.b:J
        //  1742: aload           20
        //  1744: invokevirtual   aacu.b:()J
        //  1747: ladd           
        //  1748: putfield        aaiz.b:J
        //  1751: aload_0        
        //  1752: getfield        aaiw.A:Z
        //  1755: ifeq            1761
        //  1758: goto            4942
        //  1761: goto            1400
        //  1764: aload_0        
        //  1765: getfield        aaiw.k:Ljava/lang/String;
        //  1768: astore          13
        //  1770: aload_0        
        //  1771: getfield        aaiw.f:Laage;
        //  1774: invokeinterface aage.f:()Laabr;
        //  1779: astore          26
        //  1781: aload           26
        //  1783: ifnull          2932
        //  1786: aload_0        
        //  1787: getfield        aaiw.h:Laadf;
        //  1790: getfield        aadf.i:Z
        //  1793: ifne            1823
        //  1796: aload_0        
        //  1797: getfield        aaiw.d:Laaks;
        //  1800: invokevirtual   aaks.c:()Lzxc;
        //  1803: invokevirtual   zxc.c:()Z
        //  1806: ifeq            1812
        //  1809: goto            1823
        //  1812: aload           13
        //  1814: astore          16
        //  1816: aload           16
        //  1818: astore          13
        //  1820: goto            2549
        //  1823: aload_0        
        //  1824: getfield        aaiw.x:Laajb;
        //  1827: astore          14
        //  1829: aload_0        
        //  1830: getfield        aaiw.h:Laadf;
        //  1833: getfield        aadf.j:Lznz;
        //  1836: astore          15
        //  1838: aload           21
        //  1840: invokeinterface com/google/android/libraries/youtube/innertube/model/player/PlayerResponseModel.K:()Ljava/lang/String;
        //  1845: astore          27
        //  1847: aload           15
        //  1849: invokeinterface znz.z:()Z
        //  1854: ifeq            1860
        //  1857: goto            1812
        //  1860: aload           14
        //  1862: getfield        aajb.i:Ljava/lang/Object;
        //  1865: aload           15
        //  1867: invokeinterface vfn.a:(Lznz;)Lvfm;
        //  1872: astore          28
        //  1874: aload           14
        //  1876: getfield        aajb.f:Ljava/lang/Object;
        //  1879: astore          15
        //  1881: aload           14
        //  1883: getfield        aajb.h:Ljava/lang/Object;
        //  1886: checkcast       Labsv;
        //  1889: astore          16
        //  1891: aload           15
        //  1893: checkcast       Landroid/content/Context;
        //  1896: astore          22
        //  1898: aload           13
        //  1900: astore          14
        //  1902: aload           13
        //  1904: astore          15
        //  1906: aload           21
        //  1908: aload           22
        //  1910: aload           16
        //  1912: invokestatic    abut.g:(Lcom/google/android/libraries/youtube/innertube/model/player/PlayerResponseModel;Landroid/content/Context;Labsv;)Labut;
        //  1915: astore          23
        //  1917: aload           13
        //  1919: astore          16
        //  1921: aload           23
        //  1923: ifnull          1816
        //  1926: aload           13
        //  1928: astore          14
        //  1930: aload           13
        //  1932: astore          15
        //  1934: aload           28
        //  1936: aload           13
        //  1938: invokestatic    aajb.c:(Ljava/lang/String;)Ljava/lang/String;
        //  1941: invokeinterface vfm.g:(Ljava/lang/String;)Laskj;
        //  1946: ldc_w           Laozo;.class
        //  1949: invokevirtual   askj.j:(Ljava/lang/Class;)Laskj;
        //  1952: invokevirtual   askj.af:()Ljava/lang/Object;
        //  1955: checkcast       Laozo;
        //  1958: astore          24
        //  1960: aload           13
        //  1962: astore          16
        //  1964: aload           24
        //  1966: ifnull          1816
        //  1969: aload           13
        //  1971: astore          14
        //  1973: aload           13
        //  1975: astore          15
        //  1977: aload           24
        //  1979: getfield        aozo.b:Laozp;
        //  1982: getfield        aozp.n:Lahdp;
        //  1985: astore          22
        //  1987: aload           13
        //  1989: astore          14
        //  1991: aload           13
        //  1993: astore          15
        //  1995: aload           23
        //  1997: invokevirtual   abut.f:()Ljava/util/List;
        //  2000: astore          23
        //  2002: aload           13
        //  2004: astore          16
        //  2006: aload           13
        //  2008: astore          14
        //  2010: aload           13
        //  2012: astore          15
        //  2014: aload           23
        //  2016: invokeinterface java/util/List.isEmpty:()Z
        //  2021: ifne            1816
        //  2024: aload           13
        //  2026: astore          14
        //  2028: aload           13
        //  2030: astore          15
        //  2032: aload           23
        //  2034: invokeinterface java/util/List.iterator:()Ljava/util/Iterator;
        //  2039: astore          23
        //  2041: aload           13
        //  2043: astore          16
        //  2045: aload           13
        //  2047: astore          14
        //  2049: aload           13
        //  2051: astore          15
        //  2053: aload           23
        //  2055: invokeinterface java/util/Iterator.hasNext:()Z
        //  2060: ifeq            1816
        //  2063: aload           13
        //  2065: astore          14
        //  2067: aload           13
        //  2069: astore          15
        //  2071: aload           23
        //  2073: invokeinterface java/util/Iterator.next:()Ljava/lang/Object;
        //  2078: checkcast       Lcom/google/android/libraries/youtube/player/subtitles/model/SubtitleTrack;
        //  2081: astore          16
        //  2083: aload           13
        //  2085: astore          14
        //  2087: aload           13
        //  2089: astore          15
        //  2091: sipush          225
        //  2094: aload           16
        //  2096: invokevirtual   com/google/android/libraries/youtube/player/subtitles/model/SubtitleTrack.k:()Ljava/lang/String;
        //  2099: aload           16
        //  2101: invokevirtual   com/google/android/libraries/youtube/player/subtitles/model/SubtitleTrack.l:()Ljava/lang/String;
        //  2104: invokevirtual   java/lang/String.concat:(Ljava/lang/String;)Ljava/lang/String;
        //  2107: invokestatic    vht.h:(ILjava/lang/String;)Ljava/lang/String;
        //  2110: astore          29
        //  2112: aload           13
        //  2114: astore          14
        //  2116: aload           13
        //  2118: astore          15
        //  2120: aload           22
        //  2122: aload           29
        //  2124: invokeinterface java/util/List.contains:(Ljava/lang/Object;)Z
        //  2129: ifne            2497
        //  2132: aload           13
        //  2134: astore          14
        //  2136: aload           13
        //  2138: astore          15
        //  2140: aload           16
        //  2142: invokevirtual   com/google/android/libraries/youtube/player/subtitles/model/SubtitleTrack.t:()Z
        //  2145: ifne            2497
        //  2148: aload           13
        //  2150: astore          14
        //  2152: aload           13
        //  2154: astore          15
        //  2156: aload           26
        //  2158: aload           27
        //  2160: aload           16
        //  2162: invokeinterface aabs.n:(Ljava/lang/String;Lcom/google/android/libraries/youtube/player/subtitles/model/SubtitleTrack;)Ljava/lang/String;
        //  2167: astore          30
        //  2169: aload           13
        //  2171: astore          14
        //  2173: aload           13
        //  2175: astore          15
        //  2177: aload           29
        //  2179: invokevirtual   java/lang/Object.getClass:()Ljava/lang/Class;
        //  2182: pop            
        //  2183: aload           13
        //  2185: astore          14
        //  2187: aload           13
        //  2189: astore          15
        //  2191: aload           29
        //  2193: invokevirtual   java/lang/String.isEmpty:()Z
        //  2196: iconst_1       
        //  2197: ixor           
        //  2198: ldc_w           "key cannot be empty"
        //  2201: invokestatic    adme.U:(ZLjava/lang/Object;)V
        //  2204: aload           13
        //  2206: astore          14
        //  2208: aload           13
        //  2210: astore          15
        //  2212: getstatic       aige.a:Laige;
        //  2215: invokevirtual   ahcz.createBuilder:()Lahcr;
        //  2218: astore          31
        //  2220: aload           13
        //  2222: astore          14
        //  2224: aload           13
        //  2226: astore          15
        //  2228: aload           31
        //  2230: invokevirtual   ahcr.copyOnWrite:()V
        //  2233: aload           13
        //  2235: astore          14
        //  2237: aload           13
        //  2239: astore          15
        //  2241: aload           31
        //  2243: getfield        ahcr.instance:Lahcz;
        //  2246: checkcast       Laige;
        //  2249: astore          16
        //  2251: aload           13
        //  2253: astore          14
        //  2255: aload           16
        //  2257: aload           16
        //  2259: getfield        aige.b:I
        //  2262: iconst_1       
        //  2263: ior            
        //  2264: putfield        aige.b:I
        //  2267: aload           16
        //  2269: aload           29
        //  2271: putfield        aige.c:Ljava/lang/String;
        //  2274: new             Laigb;
        //  2277: astore          16
        //  2279: aload           16
        //  2281: aload           31
        //  2283: invokespecial   aigb.<init>:(Lahcr;)V
        //  2286: aload           16
        //  2288: getfield        aigb.a:Lahcr;
        //  2291: astore          15
        //  2293: aload           15
        //  2295: invokevirtual   ahcr.copyOnWrite:()V
        //  2298: aload           15
        //  2300: getfield        ahcr.instance:Lahcz;
        //  2303: checkcast       Laige;
        //  2306: astore          15
        //  2308: aload           30
        //  2310: invokevirtual   java/lang/Object.getClass:()Ljava/lang/Class;
        //  2313: pop            
        //  2314: aload           15
        //  2316: aload           15
        //  2318: getfield        aige.b:I
        //  2321: iconst_2       
        //  2322: ior            
        //  2323: putfield        aige.b:I
        //  2326: aload           15
        //  2328: aload           30
        //  2330: putfield        aige.d:Ljava/lang/String;
        //  2333: aload           24
        //  2335: invokevirtual   aozo.f:()Laozm;
        //  2338: astore          24
        //  2340: iconst_1       
        //  2341: anewarray       Ljava/lang/String;
        //  2344: astore          15
        //  2346: aload           15
        //  2348: iconst_0       
        //  2349: aload           29
        //  2351: aastore        
        //  2352: iconst_0       
        //  2353: istore_1       
        //  2354: iload_1        
        //  2355: ifgt            2438
        //  2358: aload           15
        //  2360: iload_1        
        //  2361: aaload         
        //  2362: astore          29
        //  2364: aload           24
        //  2366: getfield        aozm.a:Lahct;
        //  2369: astore          30
        //  2371: aload           30
        //  2373: invokevirtual   ahcr.copyOnWrite:()V
        //  2376: aload           30
        //  2378: getfield        ahct.instance:Lahcz;
        //  2381: checkcast       Laozp;
        //  2384: astore          30
        //  2386: aload           29
        //  2388: invokevirtual   java/lang/Object.getClass:()Ljava/lang/Class;
        //  2391: pop            
        //  2392: aload           30
        //  2394: getfield        aozp.n:Lahdp;
        //  2397: astore          31
        //  2399: aload           31
        //  2401: invokeinterface ahdp.c:()Z
        //  2406: ifne            2419
        //  2409: aload           30
        //  2411: aload           31
        //  2413: invokestatic    ahcz.mutableCopy:(Lahdp;)Lahdp;
        //  2416: putfield        aozp.n:Lahdp;
        //  2419: aload           30
        //  2421: getfield        aozp.n:Lahdp;
        //  2424: aload           29
        //  2426: invokeinterface ahdp.add:(Ljava/lang/Object;)Z
        //  2431: pop            
        //  2432: iinc            1, 1
        //  2435: goto            2354
        //  2438: aload           24
        //  2440: aload           28
        //  2442: invokevirtual   aozm.b:(Lvgx;)Laozo;
        //  2445: astore          24
        //  2447: aload           28
        //  2449: invokeinterface vfm.d:()Lvhe;
        //  2454: astore          15
        //  2456: aload           15
        //  2458: aload           16
        //  2460: invokeinterface vhe.j:(Lvgs;)V
        //  2465: aload           15
        //  2467: aload           24
        //  2469: invokeinterface vhe.d:(Lvgv;)V
        //  2474: aload           15
        //  2476: invokeinterface vhe.b:()Lasjy;
        //  2481: invokevirtual   asjy.X:()V
        //  2484: goto            2497
        //  2487: astore          13
        //  2489: goto            2529
        //  2492: astore          13
        //  2494: goto            2529
        //  2497: goto            2041
        //  2500: astore          13
        //  2502: goto            2529
        //  2505: astore          13
        //  2507: aload           15
        //  2509: astore          14
        //  2511: goto            2529
        //  2514: astore          15
        //  2516: goto            2521
        //  2519: astore          15
        //  2521: aload           13
        //  2523: astore          14
        //  2525: aload           15
        //  2527: astore          13
        //  2529: ldc_w           "[Offline] Failed saving video subtitles entities "
        //  2532: aload           27
        //  2534: invokestatic    java/lang/String.valueOf:(Ljava/lang/Object;)Ljava/lang/String;
        //  2537: invokevirtual   java/lang/String.concat:(Ljava/lang/String;)Ljava/lang/String;
        //  2540: aload           13
        //  2542: invokestatic    tut.n:(Ljava/lang/String;Ljava/lang/Throwable;)V
        //  2545: aload           14
        //  2547: astore          13
        //  2549: aload           13
        //  2551: astore          14
        //  2553: aload           25
        //  2555: ifnull          2985
        //  2558: aload           13
        //  2560: astore          14
        //  2562: aload_0        
        //  2563: getfield        aaiw.d:Laaks;
        //  2566: invokevirtual   aaks.c:()Lzxc;
        //  2569: invokevirtual   zxc.d:()Z
        //  2572: ifeq            2985
        //  2575: aload_0        
        //  2576: getfield        aaiw.x:Laajb;
        //  2579: astore          16
        //  2581: aload           21
        //  2583: invokeinterface com/google/android/libraries/youtube/innertube/model/player/PlayerResponseModel.K:()Ljava/lang/String;
        //  2588: astore          15
        //  2590: aload           16
        //  2592: getfield        aajb.f:Ljava/lang/Object;
        //  2595: astore          14
        //  2597: aload           16
        //  2599: getfield        aajb.h:Ljava/lang/Object;
        //  2602: checkcast       Labsv;
        //  2605: astore          16
        //  2607: aload           21
        //  2609: aload           14
        //  2611: checkcast       Landroid/content/Context;
        //  2614: aload           16
        //  2616: invokestatic    abut.g:(Lcom/google/android/libraries/youtube/innertube/model/player/PlayerResponseModel;Landroid/content/Context;Labsv;)Labut;
        //  2619: astore          14
        //  2621: aload           14
        //  2623: ifnonnull       2633
        //  2626: aload           13
        //  2628: astore          14
        //  2630: goto            2985
        //  2633: aload           14
        //  2635: invokevirtual   abut.f:()Ljava/util/List;
        //  2638: astore          21
        //  2640: aload           25
        //  2642: aload           15
        //  2644: invokevirtual   zxm.i:(Ljava/lang/String;)Ljava/util/List;
        //  2647: astore          16
        //  2649: aload           13
        //  2651: astore          14
        //  2653: aload           21
        //  2655: invokeinterface java/util/List.isEmpty:()Z
        //  2660: ifne            2985
        //  2663: aload           21
        //  2665: invokeinterface java/util/List.iterator:()Ljava/util/Iterator;
        //  2670: astore          21
        //  2672: aload           13
        //  2674: astore          14
        //  2676: aload           21
        //  2678: invokeinterface java/util/Iterator.hasNext:()Z
        //  2683: ifeq            2985
        //  2686: aload           21
        //  2688: invokeinterface java/util/Iterator.next:()Ljava/lang/Object;
        //  2693: checkcast       Lcom/google/android/libraries/youtube/player/subtitles/model/SubtitleTrack;
        //  2696: astore          24
        //  2698: aload           16
        //  2700: aload           24
        //  2702: invokeinterface java/util/List.contains:(Ljava/lang/Object;)Z
        //  2707: ifne            2672
        //  2710: aload           24
        //  2712: invokevirtual   com/google/android/libraries/youtube/player/subtitles/model/SubtitleTrack.t:()Z
        //  2715: ifne            2672
        //  2718: aload           24
        //  2720: invokevirtual   com/google/android/libraries/youtube/player/subtitles/model/SubtitleTrack.r:()Z
        //  2723: ifne            2672
        //  2726: aload           26
        //  2728: aload           15
        //  2730: aload           24
        //  2732: invokeinterface aabs.n:(Ljava/lang/String;Lcom/google/android/libraries/youtube/player/subtitles/model/SubtitleTrack;)Ljava/lang/String;
        //  2737: astore          22
        //  2739: invokestatic    com/google/android/libraries/youtube/player/subtitles/model/SubtitleTrack.o:()Labur;
        //  2742: astore          14
        //  2744: aload           24
        //  2746: invokevirtual   com/google/android/libraries/youtube/player/subtitles/model/SubtitleTrack.d:()Ljava/lang/CharSequence;
        //  2749: astore          23
        //  2751: aload           23
        //  2753: ifnull          2766
        //  2756: aload           14
        //  2758: aload           23
        //  2760: invokevirtual   java/lang/Object.toString:()Ljava/lang/String;
        //  2763: putfield        abur.b:Ljava/lang/CharSequence;
        //  2766: aload           14
        //  2768: aload           24
        //  2770: invokevirtual   com/google/android/libraries/youtube/player/subtitles/model/SubtitleTrack.e:()Ljava/lang/String;
        //  2773: invokevirtual   abur.f:(Ljava/lang/String;)V
        //  2776: aload           14
        //  2778: aload           24
        //  2780: invokevirtual   com/google/android/libraries/youtube/player/subtitles/model/SubtitleTrack.k:()Ljava/lang/String;
        //  2783: invokevirtual   abur.k:(Ljava/lang/String;)V
        //  2786: aload           14
        //  2788: aload           24
        //  2790: invokevirtual   com/google/android/libraries/youtube/player/subtitles/model/SubtitleTrack.l:()Ljava/lang/String;
        //  2793: invokevirtual   abur.l:(Ljava/lang/String;)V
        //  2796: aload           14
        //  2798: aload           24
        //  2800: invokevirtual   com/google/android/libraries/youtube/player/subtitles/model/SubtitleTrack.j:()Ljava/lang/String;
        //  2803: invokevirtual   abur.j:(Ljava/lang/String;)V
        //  2806: aload           14
        //  2808: aload           24
        //  2810: invokevirtual   com/google/android/libraries/youtube/player/subtitles/model/SubtitleTrack.f:()Ljava/lang/String;
        //  2813: invokevirtual   abur.g:(Ljava/lang/String;)V
        //  2816: aload           14
        //  2818: aload           24
        //  2820: invokevirtual   com/google/android/libraries/youtube/player/subtitles/model/SubtitleTrack.i:()Ljava/lang/String;
        //  2823: invokevirtual   abur.i:(Ljava/lang/String;)V
        //  2826: aload           14
        //  2828: aload           24
        //  2830: invokevirtual   com/google/android/libraries/youtube/player/subtitles/model/SubtitleTrack.b:()I
        //  2833: invokevirtual   abur.c:(I)V
        //  2836: aload           14
        //  2838: aload           24
        //  2840: invokevirtual   com/google/android/libraries/youtube/player/subtitles/model/SubtitleTrack.h:()Ljava/lang/String;
        //  2843: invokevirtual   abur.h:(Ljava/lang/String;)V
        //  2846: aload           14
        //  2848: iconst_1       
        //  2849: invokevirtual   abur.d:(Z)V
        //  2852: aload           14
        //  2854: aload           22
        //  2856: putfield        abur.a:Ljava/lang/String;
        //  2859: aload           25
        //  2861: aload           14
        //  2863: invokevirtual   abur.a:()Lcom/google/android/libraries/youtube/player/subtitles/model/SubtitleTrack;
        //  2866: invokevirtual   zxm.Y:(Lcom/google/android/libraries/youtube/player/subtitles/model/SubtitleTrack;)V
        //  2869: goto            2672
        //  2872: astore          14
        //  2874: goto            2884
        //  2877: astore          14
        //  2879: goto            2884
        //  2882: astore          14
        //  2884: getstatic       zng.b:Lzng;
        //  2887: getstatic       znf.B:Lznf;
        //  2890: ldc_w           "Offline caption download exception: "
        //  2893: aload           14
        //  2895: invokevirtual   java/lang/Exception.getMessage:()Ljava/lang/String;
        //  2898: invokestatic    java/lang/String.valueOf:(Ljava/lang/Object;)Ljava/lang/String;
        //  2901: invokevirtual   java/lang/String.concat:(Ljava/lang/String;)Ljava/lang/String;
        //  2904: aload           14
        //  2906: invokestatic    znh.c:(Lzng;Lznf;Ljava/lang/String;Ljava/lang/Throwable;)V
        //  2909: ldc_w           "[Offline] Failed saving video subtitles "
        //  2912: aload           15
        //  2914: invokestatic    java/lang/String.valueOf:(Ljava/lang/Object;)Ljava/lang/String;
        //  2917: invokevirtual   java/lang/String.concat:(Ljava/lang/String;)Ljava/lang/String;
        //  2920: aload           14
        //  2922: invokestatic    tut.n:(Ljava/lang/String;Ljava/lang/Throwable;)V
        //  2925: aload           13
        //  2927: astore          14
        //  2929: goto            2985
        //  2932: aload_0        
        //  2933: getfield        aaiw.m:Ljava/lang/String;
        //  2936: astore          14
        //  2938: new             Ljava/lang/StringBuilder;
        //  2941: astore          15
        //  2943: aload           15
        //  2945: invokespecial   java/lang/StringBuilder.<init>:()V
        //  2948: aload           15
        //  2950: ldc             "[Offline] pudl task cotn ["
        //  2952: invokevirtual   java/lang/StringBuilder.append:(Ljava/lang/String;)Ljava/lang/StringBuilder;
        //  2955: pop            
        //  2956: aload           15
        //  2958: aload           14
        //  2960: invokevirtual   java/lang/StringBuilder.append:(Ljava/lang/String;)Ljava/lang/StringBuilder;
        //  2963: pop            
        //  2964: aload           15
        //  2966: ldc_w           "] subtitle failed, no filestore"
        //  2969: invokevirtual   java/lang/StringBuilder.append:(Ljava/lang/String;)Ljava/lang/StringBuilder;
        //  2972: pop            
        //  2973: aload           15
        //  2975: invokevirtual   java/lang/StringBuilder.toString:()Ljava/lang/String;
        //  2978: invokestatic    tut.b:(Ljava/lang/String;)V
        //  2981: aload           13
        //  2983: astore          14
        //  2985: aload_0        
        //  2986: getfield        aaiw.F:Laefs;
        //  2989: invokevirtual   aefs.cw:()Ljava/lang/String;
        //  2992: astore          15
        //  2994: aload_0        
        //  2995: getfield        aaiw.e:Laahk;
        //  2998: astore          13
        //  3000: aload_0        
        //  3001: getfield        aaiw.i:Ljava/lang/String;
        //  3004: astore          16
        //  3006: bipush          18
        //  3008: invokestatic    aaht.a:(I)Laahs;
        //  3011: astore          21
        //  3013: aload           21
        //  3015: aload           16
        //  3017: invokevirtual   aahs.f:(Ljava/lang/String;)V
        //  3020: aload           21
        //  3022: invokevirtual   aahs.a:()Laaht;
        //  3025: astore          16
        //  3027: aload           13
        //  3029: checkcast       Laahu;
        //  3032: aload           16
        //  3034: invokevirtual   aahu.k:(Laaht;)V
        //  3037: aload           18
        //  3039: ifnull          3541
        //  3042: aload           19
        //  3044: ifnull          3541
        //  3047: aload           17
        //  3049: ifnull          3541
        //  3052: aload_0        
        //  3053: getfield        aaiw.c:Ladgg;
        //  3056: invokevirtual   adgg.az:()Ladgg;
        //  3059: astore          17
        //  3061: aload           17
        //  3063: invokevirtual   adgg.V:()Lafbh;
        //  3066: invokevirtual   afbh.f:()Ljava/lang/Object;
        //  3069: checkcast       Ljava/lang/String;
        //  3072: astore          16
        //  3074: aload_0        
        //  3075: getfield        aaiw.o:Lyhm;
        //  3078: astore          13
        //  3080: aload           13
        //  3082: ifnonnull       3116
        //  3085: aload           17
        //  3087: getfield        adgg.a:Ljava/lang/Object;
        //  3090: checkcast       Laaiq;
        //  3093: invokevirtual   aaiq.a:()Lyhm;
        //  3096: astore          13
        //  3098: aload           13
        //  3100: aload_0        
        //  3101: getfield        aaiw.p:Laaiz;
        //  3104: putfield        yhm.b:Lyhl;
        //  3107: aload_0        
        //  3108: aload           13
        //  3110: putfield        aaiw.o:Lyhm;
        //  3113: goto            3116
        //  3116: getstatic       amxv.a:Lamxv;
        //  3119: invokevirtual   ahcz.createBuilder:()Lahcr;
        //  3122: astore          17
        //  3124: aload           17
        //  3126: invokevirtual   ahcr.copyOnWrite:()V
        //  3129: aload           17
        //  3131: getfield        ahcr.instance:Lahcz;
        //  3134: checkcast       Lamxv;
        //  3137: astore          21
        //  3139: aload           21
        //  3141: aload           21
        //  3143: getfield        amxv.b:I
        //  3146: iconst_1       
        //  3147: ior            
        //  3148: putfield        amxv.b:I
        //  3151: aload           21
        //  3153: aload           19
        //  3155: putfield        amxv.d:Ljava/lang/String;
        //  3158: aload           17
        //  3160: invokevirtual   ahcr.copyOnWrite:()V
        //  3163: aload           17
        //  3165: getfield        ahcr.instance:Lahcz;
        //  3168: checkcast       Lamxv;
        //  3171: astore          21
        //  3173: aload           21
        //  3175: iconst_1       
        //  3176: putfield        amxv.h:I
        //  3179: aload           21
        //  3181: aload           21
        //  3183: getfield        amxv.b:I
        //  3186: bipush          16
        //  3188: ior            
        //  3189: putfield        amxv.b:I
        //  3192: aload           17
        //  3194: invokevirtual   ahcr.copyOnWrite:()V
        //  3197: aload           17
        //  3199: getfield        ahcr.instance:Lahcz;
        //  3202: checkcast       Lamxv;
        //  3205: astore          21
        //  3207: aload           15
        //  3209: invokevirtual   java/lang/Object.getClass:()Ljava/lang/Class;
        //  3212: pop            
        //  3213: aload           21
        //  3215: aload           21
        //  3217: getfield        amxv.b:I
        //  3220: iconst_2       
        //  3221: ior            
        //  3222: putfield        amxv.b:I
        //  3225: aload           21
        //  3227: aload           15
        //  3229: putfield        amxv.e:Ljava/lang/String;
        //  3232: aload           17
        //  3234: invokevirtual   ahcr.copyOnWrite:()V
        //  3237: aload           17
        //  3239: getfield        ahcr.instance:Lahcz;
        //  3242: checkcast       Lamxv;
        //  3245: astore          21
        //  3247: aload           21
        //  3249: aload           21
        //  3251: getfield        amxv.b:I
        //  3254: ldc_w           32768
        //  3257: ior            
        //  3258: putfield        amxv.b:I
        //  3261: aload           21
        //  3263: iconst_1       
        //  3264: putfield        amxv.q:Z
        //  3267: aload           17
        //  3269: invokevirtual   ahcr.build:()Lahcz;
        //  3272: checkcast       Lamxv;
        //  3275: astore          17
        //  3277: aload_0        
        //  3278: getfield        aaiw.s:Laacd;
        //  3281: aload           17
        //  3283: invokeinterface aacd.b:(Lamxv;)V
        //  3288: aload_0        
        //  3289: getfield        aaiw.p:Laaiz;
        //  3292: aload           19
        //  3294: putfield        aaiz.a:Ljava/lang/String;
        //  3297: aload           18
        //  3299: getfield        aacv.a:Laacu;
        //  3302: astore          17
        //  3304: aload           17
        //  3306: iload           12
        //  3308: invokestatic    aaiw.e:(Laacu;Z)Z
        //  3311: istore          11
        //  3313: aload           17
        //  3315: ifnull          3409
        //  3318: aload_0        
        //  3319: getfield        aaiw.i:Ljava/lang/String;
        //  3322: astore          24
        //  3324: aload_0        
        //  3325: getfield        aaiw.j:Ljava/lang/String;
        //  3328: astore          21
        //  3330: aload           17
        //  3332: invokevirtual   aacu.b:()J
        //  3335: lstore          5
        //  3337: aload_0        
        //  3338: getfield        aaiw.f:Laage;
        //  3341: invokeinterface aage.d:()Lzyd;
        //  3346: astore          22
        //  3348: aload_0        
        //  3349: getfield        aaiw.r:Laajd;
        //  3352: astore          23
        //  3354: aload           19
        //  3356: aload           24
        //  3358: aload           21
        //  3360: aload           13
        //  3362: aload           17
        //  3364: lload           5
        //  3366: aload           22
        //  3368: aload           16
        //  3370: aload           23
        //  3372: getfield        aajd.c:Lzch;
        //  3375: aload           23
        //  3377: getfield        aajd.a:Lzch;
        //  3380: aload_0        
        //  3381: getfield        aaiw.E:Lacjq;
        //  3384: invokestatic    aajb.o:(Ljava/lang/String;Ljava/lang/String;Ljava/lang/String;Lyhm;Laacu;JLzyd;Ljava/lang/String;Lzch;Lzch;Lacjq;)V
        //  3387: aload_0        
        //  3388: getfield        aaiw.p:Laaiz;
        //  3391: astore          21
        //  3393: aload           21
        //  3395: aload           21
        //  3397: getfield        aaiz.b:J
        //  3400: aload           17
        //  3402: invokevirtual   aacu.b:()J
        //  3405: ladd           
        //  3406: putfield        aaiz.b:J
        //  3409: aload_0        
        //  3410: getfield        aaiw.A:Z
        //  3413: ifeq            3419
        //  3416: goto            4073
        //  3419: aload           18
        //  3421: getfield        aacv.b:Laacu;
        //  3424: astore          17
        //  3426: aload           17
        //  3428: iload           11
        //  3430: invokestatic    aaiw.e:(Laacu;Z)Z
        //  3433: istore          11
        //  3435: aload           17
        //  3437: ifnull          3531
        //  3440: aload_0        
        //  3441: getfield        aaiw.i:Ljava/lang/String;
        //  3444: astore          23
        //  3446: aload_0        
        //  3447: getfield        aaiw.j:Ljava/lang/String;
        //  3450: astore          22
        //  3452: aload           17
        //  3454: invokevirtual   aacu.b:()J
        //  3457: lstore          5
        //  3459: aload_0        
        //  3460: getfield        aaiw.f:Laage;
        //  3463: invokeinterface aage.d:()Lzyd;
        //  3468: astore          18
        //  3470: aload_0        
        //  3471: getfield        aaiw.r:Laajd;
        //  3474: astore          21
        //  3476: aload           19
        //  3478: aload           23
        //  3480: aload           22
        //  3482: aload           13
        //  3484: aload           17
        //  3486: lload           5
        //  3488: aload           18
        //  3490: aload           16
        //  3492: aload           21
        //  3494: getfield        aajd.d:Lzch;
        //  3497: aload           21
        //  3499: getfield        aajd.b:Lzch;
        //  3502: aload_0        
        //  3503: getfield        aaiw.E:Lacjq;
        //  3506: invokestatic    aajb.o:(Ljava/lang/String;Ljava/lang/String;Ljava/lang/String;Lyhm;Laacu;JLzyd;Ljava/lang/String;Lzch;Lzch;Lacjq;)V
        //  3509: aload_0        
        //  3510: getfield        aaiw.p:Laaiz;
        //  3513: astore          13
        //  3515: aload           13
        //  3517: aload           13
        //  3519: getfield        aaiz.b:J
        //  3522: aload           17
        //  3524: invokevirtual   aacu.b:()J
        //  3527: ladd           
        //  3528: putfield        aaiz.b:J
        //  3531: aload_0        
        //  3532: getfield        aaiw.A:Z
        //  3535: ifne            4073
        //  3538: goto            3545
        //  3541: iload           12
        //  3543: istore          11
        //  3545: aload           19
        //  3547: ifnull          3737
        //  3550: aload           25
        //  3552: ifnull          3737
        //  3555: aload           25
        //  3557: aload           19
        //  3559: getstatic       aacn.b:Laacn;
        //  3562: invokevirtual   zxm.F:(Ljava/lang/String;Laacn;)V
        //  3565: getstatic       amxv.a:Lamxv;
        //  3568: invokevirtual   ahcz.createBuilder:()Lahcr;
        //  3571: astore          13
        //  3573: aload           13
        //  3575: invokevirtual   ahcr.copyOnWrite:()V
        //  3578: aload           13
        //  3580: getfield        ahcr.instance:Lahcz;
        //  3583: checkcast       Lamxv;
        //  3586: astore          16
        //  3588: aload           16
        //  3590: aload           16
        //  3592: getfield        amxv.b:I
        //  3595: iconst_1       
        //  3596: ior            
        //  3597: putfield        amxv.b:I
        //  3600: aload           16
        //  3602: aload           19
        //  3604: putfield        amxv.d:Ljava/lang/String;
        //  3607: aload           13
        //  3609: invokevirtual   ahcr.copyOnWrite:()V
        //  3612: aload           13
        //  3614: getfield        ahcr.instance:Lahcz;
        //  3617: checkcast       Lamxv;
        //  3620: astore          16
        //  3622: aload           16
        //  3624: aload           16
        //  3626: getfield        amxv.b:I
        //  3629: ldc_w           32768
        //  3632: ior            
        //  3633: putfield        amxv.b:I
        //  3636: aload           16
        //  3638: iconst_1       
        //  3639: putfield        amxv.q:Z
        //  3642: aload           13
        //  3644: invokevirtual   ahcr.copyOnWrite:()V
        //  3647: aload           13
        //  3649: getfield        ahcr.instance:Lahcz;
        //  3652: checkcast       Lamxv;
        //  3655: astore          16
        //  3657: aload           16
        //  3659: iconst_4       
        //  3660: putfield        amxv.h:I
        //  3663: aload           16
        //  3665: aload           16
        //  3667: getfield        amxv.b:I
        //  3670: bipush          16
        //  3672: ior            
        //  3673: putfield        amxv.b:I
        //  3676: aload           13
        //  3678: invokevirtual   ahcr.copyOnWrite:()V
        //  3681: aload           13
        //  3683: getfield        ahcr.instance:Lahcz;
        //  3686: checkcast       Lamxv;
        //  3689: astore          16
        //  3691: aload           15
        //  3693: invokevirtual   java/lang/Object.getClass:()Ljava/lang/Class;
        //  3696: pop            
        //  3697: aload           16
        //  3699: aload           16
        //  3701: getfield        amxv.b:I
        //  3704: iconst_2       
        //  3705: ior            
        //  3706: putfield        amxv.b:I
        //  3709: aload           16
        //  3711: aload           15
        //  3713: putfield        amxv.e:Ljava/lang/String;
        //  3716: aload           13
        //  3718: invokevirtual   ahcr.build:()Lahcz;
        //  3721: checkcast       Lamxv;
        //  3724: astore          13
        //  3726: aload_0        
        //  3727: getfield        aaiw.s:Laacd;
        //  3730: aload           13
        //  3732: invokeinterface aacd.b:(Lamxv;)V
        //  3737: aload_0        
        //  3738: getfield        aaiw.b:Ladgg;
        //  3741: invokevirtual   adgg.az:()Ladgg;
        //  3744: astore          16
        //  3746: aload           16
        //  3748: invokevirtual   adgg.V:()Lafbh;
        //  3751: invokevirtual   afbh.f:()Ljava/lang/Object;
        //  3754: checkcast       Ljava/lang/String;
        //  3757: astore          15
        //  3759: aload_0        
        //  3760: getfield        aaiw.n:Lyhm;
        //  3763: astore          13
        //  3765: aload           13
        //  3767: ifnonnull       3801
        //  3770: aload           16
        //  3772: getfield        adgg.a:Ljava/lang/Object;
        //  3775: checkcast       Laaiq;
        //  3778: invokevirtual   aaiq.a:()Lyhm;
        //  3781: astore          13
        //  3783: aload           13
        //  3785: aload_0        
        //  3786: getfield        aaiw.p:Laaiz;
        //  3789: putfield        yhm.b:Lyhl;
        //  3792: aload_0        
        //  3793: aload           13
        //  3795: putfield        aaiw.n:Lyhm;
        //  3798: goto            3801
        //  3801: aload_0        
        //  3802: getfield        aaiw.p:Laaiz;
        //  3805: aload           14
        //  3807: putfield        aaiz.a:Ljava/lang/String;
        //  3810: aload           20
        //  3812: getfield        aacv.b:Laacu;
        //  3815: astore          16
        //  3817: aload           16
        //  3819: iload           11
        //  3821: invokestatic    aaiw.e:(Laacu;Z)Z
        //  3824: istore          11
        //  3826: aload           16
        //  3828: ifnull          3922
        //  3831: aload_0        
        //  3832: getfield        aaiw.i:Ljava/lang/String;
        //  3835: astore          21
        //  3837: aload_0        
        //  3838: getfield        aaiw.j:Ljava/lang/String;
        //  3841: astore          18
        //  3843: aload           16
        //  3845: invokevirtual   aacu.b:()J
        //  3848: lstore          5
        //  3850: aload_0        
        //  3851: getfield        aaiw.f:Laage;
        //  3854: invokeinterface aage.d:()Lzyd;
        //  3859: astore          19
        //  3861: aload_0        
        //  3862: getfield        aaiw.q:Laajd;
        //  3865: astore          17
        //  3867: aload           14
        //  3869: aload           21
        //  3871: aload           18
        //  3873: aload           13
        //  3875: aload           16
        //  3877: lload           5
        //  3879: aload           19
        //  3881: aload           15
        //  3883: aload           17
        //  3885: getfield        aajd.d:Lzch;
        //  3888: aload           17
        //  3890: getfield        aajd.b:Lzch;
        //  3893: aload_0        
        //  3894: getfield        aaiw.E:Lacjq;
        //  3897: invokestatic    aajb.o:(Ljava/lang/String;Ljava/lang/String;Ljava/lang/String;Lyhm;Laacu;JLzyd;Ljava/lang/String;Lzch;Lzch;Lacjq;)V
        //  3900: aload_0        
        //  3901: getfield        aaiw.p:Laaiz;
        //  3904: astore          17
        //  3906: aload           17
        //  3908: aload           17
        //  3910: getfield        aaiz.b:J
        //  3913: aload           16
        //  3915: invokevirtual   aacu.b:()J
        //  3918: ladd           
        //  3919: putfield        aaiz.b:J
        //  3922: aload_0        
        //  3923: getfield        aaiw.A:Z
        //  3926: ifne            4073
        //  3929: aload           20
        //  3931: getfield        aacv.a:Laacu;
        //  3934: astore          16
        //  3936: aload           16
        //  3938: iload           11
        //  3940: invokestatic    aaiw.e:(Laacu;Z)Z
        //  3943: istore          11
        //  3945: aload           16
        //  3947: ifnull          4041
        //  3950: aload_0        
        //  3951: getfield        aaiw.i:Ljava/lang/String;
        //  3954: astore          20
        //  3956: aload_0        
        //  3957: getfield        aaiw.j:Ljava/lang/String;
        //  3960: astore          19
        //  3962: aload           16
        //  3964: invokevirtual   aacu.b:()J
        //  3967: lstore          5
        //  3969: aload_0        
        //  3970: getfield        aaiw.f:Laage;
        //  3973: invokeinterface aage.d:()Lzyd;
        //  3978: astore          17
        //  3980: aload_0        
        //  3981: getfield        aaiw.q:Laajd;
        //  3984: astore          18
        //  3986: aload           14
        //  3988: aload           20
        //  3990: aload           19
        //  3992: aload           13
        //  3994: aload           16
        //  3996: lload           5
        //  3998: aload           17
        //  4000: aload           15
        //  4002: aload           18
        //  4004: getfield        aajd.c:Lzch;
        //  4007: aload           18
        //  4009: getfield        aajd.a:Lzch;
        //  4012: aload_0        
        //  4013: getfield        aaiw.E:Lacjq;
        //  4016: invokestatic    aajb.o:(Ljava/lang/String;Ljava/lang/String;Ljava/lang/String;Lyhm;Laacu;JLzyd;Ljava/lang/String;Lzch;Lzch;Lacjq;)V
        //  4019: aload_0        
        //  4020: getfield        aaiw.p:Laaiz;
        //  4023: astore          13
        //  4025: aload           13
        //  4027: aload           13
        //  4029: getfield        aaiz.b:J
        //  4032: aload           16
        //  4034: invokevirtual   aacu.b:()J
        //  4037: ladd           
        //  4038: putfield        aaiz.b:J
        //  4041: aload_0        
        //  4042: getfield        aaiw.A:Z
        //  4045: ifne            4073
        //  4048: aload_0        
        //  4049: lload_3        
        //  4050: dconst_0       
        //  4051: iload           11
        //  4053: invokevirtual   aaiw.b:(JDZ)V
        //  4056: aload_0        
        //  4057: getfield        aaiw.e:Laahk;
        //  4060: aload_0        
        //  4061: getfield        aaiw.i:Ljava/lang/String;
        //  4064: aload_0        
        //  4065: invokespecial   aaiw.c:()Laach;
        //  4068: invokeinterface aahk.a:(Ljava/lang/String;Laach;)V
        //  4073: aload_0        
        //  4074: getfield        aaiw.a:Lzbx;
        //  4077: astore          13
        //  4079: aload           13
        //  4081: ifnull          4942
        //  4084: aload           13
        //  4086: invokevirtual   zbx.g:()V
        //  4089: return         
        //  4090: astore          13
        //  4092: goto            4181
        //  4095: aload_0        
        //  4096: getfield        aaiw.m:Ljava/lang/String;
        //  4099: astore          14
        //  4101: new             Ljava/lang/StringBuilder;
        //  4104: astore          15
        //  4106: aload           15
        //  4108: invokespecial   java/lang/StringBuilder.<init>:()V
        //  4111: aload           15
        //  4113: ldc             "[Offline] pudl task cotn ["
        //  4115: invokevirtual   java/lang/StringBuilder.append:(Ljava/lang/String;)Ljava/lang/StringBuilder;
        //  4118: pop            
        //  4119: aload           15
        //  4121: aload           14
        //  4123: invokevirtual   java/lang/StringBuilder.append:(Ljava/lang/String;)Ljava/lang/StringBuilder;
        //  4126: pop            
        //  4127: aload           15
        //  4129: ldc_w           "] error while downloading video"
        //  4132: invokevirtual   java/lang/StringBuilder.append:(Ljava/lang/String;)Ljava/lang/StringBuilder;
        //  4135: pop            
        //  4136: aload           15
        //  4138: invokevirtual   java/lang/StringBuilder.toString:()Ljava/lang/String;
        //  4141: aload           13
        //  4143: invokestatic    tut.d:(Ljava/lang/String;Ljava/lang/Throwable;)V
        //  4146: aload_0        
        //  4147: ldc_w           "Error encountered while downloading the video"
        //  4150: aload           13
        //  4152: getstatic       aacn.d:Laacn;
        //  4155: getstatic       amxs.w:Lamxs;
        //  4158: invokestatic    aahm.b:(Ljava/lang/String;Ljava/lang/Exception;Laacn;Lamxs;)Laahm;
        //  4161: invokespecial   aaiw.d:(Laahm;)V
        //  4164: return         
        //  4165: aload_0        
        //  4166: aload_0        
        //  4167: getfield        aaiw.x:Laajb;
        //  4170: aload           13
        //  4172: invokevirtual   aajb.a:(Ljava/io/IOException;)Laahm;
        //  4175: invokespecial   aaiw.d:(Laahm;)V
        //  4178: return         
        //  4179: astore          13
        //  4181: aload_0        
        //  4182: getfield        aaiw.d:Laaks;
        //  4185: invokevirtual   aaks.l:()Z
        //  4188: ifeq            4974
        //  4191: aload_0        
        //  4192: getfield        aaiw.x:Laajb;
        //  4195: astore          13
        //  4197: aload_0        
        //  4198: getfield        aaiw.h:Laadf;
        //  4201: getfield        aadf.j:Lznz;
        //  4204: astore          14
        //  4206: aload_0        
        //  4207: getfield        aaiw.k:Ljava/lang/String;
        //  4210: astore          15
        //  4212: aload           13
        //  4214: getfield        aajb.i:Ljava/lang/Object;
        //  4217: aload           14
        //  4219: invokeinterface vfn.a:(Lznz;)Lvfm;
        //  4224: astore          16
        //  4226: aload           16
        //  4228: aload           15
        //  4230: invokestatic    aajb.c:(Ljava/lang/String;)Ljava/lang/String;
        //  4233: invokeinterface vfm.g:(Ljava/lang/String;)Laskj;
        //  4238: ldc_w           Laozo;.class
        //  4241: invokevirtual   askj.j:(Ljava/lang/Class;)Laskj;
        //  4244: invokevirtual   askj.af:()Ljava/lang/Object;
        //  4247: checkcast       Laozo;
        //  4250: astore          14
        //  4252: aload           14
        //  4254: ifnonnull       4260
        //  4257: goto            4943
        //  4260: aload           16
        //  4262: invokeinterface vfm.d:()Lvhe;
        //  4267: astore          16
        //  4269: aload           14
        //  4271: invokevirtual   aozo.f:()Laozm;
        //  4274: astore          14
        //  4276: aload           14
        //  4278: getstatic       aozk.h:Laozk;
        //  4281: invokevirtual   aozm.g:(Laozk;)V
        //  4284: aload           16
        //  4286: aload           14
        //  4288: invokeinterface vhe.j:(Lvgs;)V
        //  4293: aload           16
        //  4295: invokeinterface vhe.b:()Lasjy;
        //  4300: invokevirtual   asjy.X:()V
        //  4303: aload           13
        //  4305: getfield        aajb.j:Ljava/lang/Object;
        //  4308: invokeinterface atnb.a:()Ljava/lang/Object;
        //  4313: checkcast       Laaed;
        //  4316: astore          14
        //  4318: getstatic       amwq.a:Lamwq;
        //  4321: invokevirtual   ahcz.createBuilder:()Lahcr;
        //  4324: astore          13
        //  4326: aload           13
        //  4328: invokevirtual   ahcr.copyOnWrite:()V
        //  4331: aload           13
        //  4333: getfield        ahcr.instance:Lahcz;
        //  4336: checkcast       Lamwq;
        //  4339: astore          16
        //  4341: aload           16
        //  4343: iconst_1       
        //  4344: putfield        amwq.c:I
        //  4347: aload           16
        //  4349: aload           16
        //  4351: getfield        amwq.b:I
        //  4354: iconst_1       
        //  4355: ior            
        //  4356: putfield        amwq.b:I
        //  4359: aload           15
        //  4361: invokestatic    aajb.b:(Ljava/lang/String;)Ljava/lang/String;
        //  4364: astore          16
        //  4366: aload           13
        //  4368: invokevirtual   ahcr.copyOnWrite:()V
        //  4371: aload           13
        //  4373: getfield        ahcr.instance:Lahcz;
        //  4376: checkcast       Lamwq;
        //  4379: astore          17
        //  4381: aload           16
        //  4383: invokevirtual   java/lang/Object.getClass:()Ljava/lang/Class;
        //  4386: pop            
        //  4387: aload           17
        //  4389: aload           17
        //  4391: getfield        amwq.b:I
        //  4394: iconst_2       
        //  4395: ior            
        //  4396: putfield        amwq.b:I
        //  4399: aload           17
        //  4401: aload           16
        //  4403: putfield        amwq.d:Ljava/lang/String;
        //  4406: getstatic       amwo.b:Lamwo;
        //  4409: invokevirtual   ahcz.createBuilder:()Lahcr;
        //  4412: checkcast       Lahct;
        //  4415: astore          16
        //  4417: aload           16
        //  4419: getstatic       amwn.c:Lamwn;
        //  4422: invokevirtual   ahct.p:(Lamwn;)V
        //  4425: aload           16
        //  4427: invokevirtual   ahcr.copyOnWrite:()V
        //  4430: aload           16
        //  4432: getfield        ahct.instance:Lahcz;
        //  4435: checkcast       Lamwo;
        //  4438: astore          17
        //  4440: aload           17
        //  4442: invokevirtual   amwo.d:()V
        //  4445: aload           17
        //  4447: getfield        amwo.f:Lahdh;
        //  4450: bipush          15
        //  4452: invokeinterface ahdh.g:(I)V
        //  4457: getstatic       anfc.b:Lahcx;
        //  4460: astore          18
        //  4462: getstatic       anfc.a:Lanfc;
        //  4465: invokevirtual   ahcz.createBuilder:()Lahcr;
        //  4468: astore          17
        //  4470: aload           17
        //  4472: invokevirtual   ahcr.copyOnWrite:()V
        //  4475: aload           17
        //  4477: getfield        ahcr.instance:Lahcz;
        //  4480: checkcast       Lanfc;
        //  4483: astore          19
        //  4485: aload           19
        //  4487: aload           19
        //  4489: getfield        anfc.c:I
        //  4492: bipush          16
        //  4494: ior            
        //  4495: putfield        anfc.c:I
        //  4498: aload           19
        //  4500: iconst_1       
        //  4501: putfield        anfc.g:Z
        //  4504: aload           16
        //  4506: aload           18
        //  4508: aload           17
        //  4510: invokevirtual   ahcr.build:()Lahcz;
        //  4513: checkcast       Lanfc;
        //  4516: invokevirtual   ahct.e:(Lahci;Ljava/lang/Object;)V
        //  4519: aload           16
        //  4521: invokevirtual   ahcr.build:()Lahcz;
        //  4524: checkcast       Lamwo;
        //  4527: astore          16
        //  4529: aload           13
        //  4531: invokevirtual   ahcr.copyOnWrite:()V
        //  4534: aload           13
        //  4536: getfield        ahcr.instance:Lahcz;
        //  4539: checkcast       Lamwq;
        //  4542: astore          17
        //  4544: aload           16
        //  4546: invokevirtual   java/lang/Object.getClass:()Ljava/lang/Class;
        //  4549: pop            
        //  4550: aload           17
        //  4552: aload           16
        //  4554: putfield        amwq.e:Lamwo;
        //  4557: aload           17
        //  4559: aload           17
        //  4561: getfield        amwq.b:I
        //  4564: iconst_4       
        //  4565: ior            
        //  4566: putfield        amwq.b:I
        //  4569: getstatic       amwq.a:Lamwq;
        //  4572: invokevirtual   ahcz.createBuilder:()Lahcr;
        //  4575: astore          16
        //  4577: aload           16
        //  4579: invokevirtual   ahcr.copyOnWrite:()V
        //  4582: aload           16
        //  4584: getfield        ahcr.instance:Lahcz;
        //  4587: checkcast       Lamwq;
        //  4590: astore          17
        //  4592: aload           17
        //  4594: iconst_4       
        //  4595: putfield        amwq.c:I
        //  4598: aload           17
        //  4600: aload           17
        //  4602: getfield        amwq.b:I
        //  4605: iconst_1       
        //  4606: ior            
        //  4607: putfield        amwq.b:I
        //  4610: aload           15
        //  4612: invokestatic    aajb.c:(Ljava/lang/String;)Ljava/lang/String;
        //  4615: astore          17
        //  4617: aload           16
        //  4619: invokevirtual   ahcr.copyOnWrite:()V
        //  4622: aload           16
        //  4624: getfield        ahcr.instance:Lahcz;
        //  4627: checkcast       Lamwq;
        //  4630: astore          15
        //  4632: aload           17
        //  4634: invokevirtual   java/lang/Object.getClass:()Ljava/lang/Class;
        //  4637: pop            
        //  4638: aload           15
        //  4640: aload           15
        //  4642: getfield        amwq.b:I
        //  4645: iconst_2       
        //  4646: ior            
        //  4647: putfield        amwq.b:I
        //  4650: aload           15
        //  4652: aload           17
        //  4654: putfield        amwq.d:Ljava/lang/String;
        //  4657: getstatic       amwo.b:Lamwo;
        //  4660: invokevirtual   ahcz.createBuilder:()Lahcr;
        //  4663: checkcast       Lahct;
        //  4666: astore          15
        //  4668: getstatic       aozj.b:Lahcx;
        //  4671: astore          17
        //  4673: getstatic       aozj.a:Laozj;
        //  4676: invokevirtual   ahcz.createBuilder:()Lahcr;
        //  4679: astore          19
        //  4681: aload           19
        //  4683: invokevirtual   ahcr.copyOnWrite:()V
        //  4686: aload           19
        //  4688: getfield        ahcr.instance:Lahcz;
        //  4691: checkcast       Laozj;
        //  4694: astore          18
        //  4696: aload           18
        //  4698: aload           18
        //  4700: getfield        aozj.c:I
        //  4703: iconst_4       
        //  4704: ior            
        //  4705: putfield        aozj.c:I
        //  4708: aload           18
        //  4710: iconst_1       
        //  4711: putfield        aozj.f:Z
        //  4714: aload           15
        //  4716: aload           17
        //  4718: aload           19
        //  4720: invokevirtual   ahcr.build:()Lahcz;
        //  4723: checkcast       Laozj;
        //  4726: invokevirtual   ahct.e:(Lahci;Ljava/lang/Object;)V
        //  4729: aload           15
        //  4731: invokevirtual   ahcr.build:()Lahcz;
        //  4734: checkcast       Lamwo;
        //  4737: astore          15
        //  4739: aload           16
        //  4741: invokevirtual   ahcr.copyOnWrite:()V
        //  4744: aload           16
        //  4746: getfield        ahcr.instance:Lahcz;
        //  4749: checkcast       Lamwq;
        //  4752: astore          17
        //  4754: aload           15
        //  4756: invokevirtual   java/lang/Object.getClass:()Ljava/lang/Class;
        //  4759: pop            
        //  4760: aload           17
        //  4762: aload           15
        //  4764: putfield        amwq.e:Lamwo;
        //  4767: aload           17
        //  4769: aload           17
        //  4771: getfield        amwq.b:I
        //  4774: iconst_4       
        //  4775: ior            
        //  4776: putfield        amwq.b:I
        //  4779: aload           16
        //  4781: invokevirtual   ahcr.build:()Lahcz;
        //  4784: checkcast       Lamwq;
        //  4787: astore          17
        //  4789: aload           13
        //  4791: invokevirtual   ahcr.copyOnWrite:()V
        //  4794: aload           13
        //  4796: getfield        ahcr.instance:Lahcz;
        //  4799: checkcast       Lamwq;
        //  4802: astore          15
        //  4804: aload           17
        //  4806: invokevirtual   java/lang/Object.getClass:()Ljava/lang/Class;
        //  4809: pop            
        //  4810: aload           15
        //  4812: getfield        amwq.g:Lahdp;
        //  4815: astore          16
        //  4817: aload           16
        //  4819: invokeinterface ahdp.c:()Z
        //  4824: ifne            4837
        //  4827: aload           15
        //  4829: aload           16
        //  4831: invokestatic    ahcz.mutableCopy:(Lahdp;)Lahdp;
        //  4834: putfield        amwq.g:Lahdp;
        //  4837: aload           15
        //  4839: getfield        amwq.g:Lahdp;
        //  4842: aload           17
        //  4844: invokeinterface ahdp.add:(Ljava/lang/Object;)Z
        //  4849: pop            
        //  4850: aload           14
        //  4852: aload           13
        //  4854: invokevirtual   ahcr.build:()Lahcz;
        //  4857: checkcast       Lamwq;
        //  4860: invokevirtual   aaed.a:(Lamwq;)Laskp;
        //  4863: pop            
        //  4864: aload_0        
        //  4865: getfield        aaiw.e:Laahk;
        //  4868: astore          14
        //  4870: aload_0        
        //  4871: getfield        aaiw.i:Ljava/lang/String;
        //  4874: astore          15
        //  4876: aload           14
        //  4878: checkcast       Laahu;
        //  4881: getfield        aahu.l:Labwe;
        //  4884: aload           15
        //  4886: invokevirtual   abwe.m:(Ljava/lang/String;)Laaha;
        //  4889: astore          13
        //  4891: aload           13
        //  4893: ifnull          4942
        //  4896: aload           13
        //  4898: getstatic       aozk.h:Laozk;
        //  4901: putfield        aaha.j:Laozk;
        //  4904: aload           14
        //  4906: checkcast       Laahu;
        //  4909: getfield        aahu.c:Laaif;
        //  4912: aload           15
        //  4914: invokevirtual   aaif.b:(Ljava/lang/String;)Laahl;
        //  4917: pop            
        //  4918: aload           14
        //  4920: checkcast       Laahu;
        //  4923: getfield        aahu.f:Ljava/util/Set;
        //  4926: aload           15
        //  4928: invokeinterface java/util/Set.remove:(Ljava/lang/Object;)Z
        //  4933: pop            
        //  4934: aload           14
        //  4936: checkcast       Laahu;
        //  4939: invokevirtual   aahu.m:()V
        //  4942: return         
        //  4943: aload_0        
        //  4944: getfield        aaiw.e:Laahk;
        //  4947: aload_0        
        //  4948: getfield        aaiw.i:Ljava/lang/String;
        //  4951: ldc_w           "Internal error. Couldn't enqueue a player response refetch"
        //  4954: aconst_null    
        //  4955: getstatic       aacn.h:Laacn;
        //  4958: getstatic       amxs.t:Lamxs;
        //  4961: invokestatic    aahm.a:(Ljava/lang/String;Ljava/lang/Exception;Laacn;Lamxs;)Laahm;
        //  4964: aload_0        
        //  4965: invokespecial   aaiw.c:()Laach;
        //  4968: invokeinterface aahk.d:(Ljava/lang/String;Laahm;Laach;)V
        //  4973: return         
        //  4974: aload_0        
        //  4975: aload_0        
        //  4976: getfield        aaiw.x:Laajb;
        //  4979: aload           13
        //  4981: invokevirtual   aajb.a:(Ljava/io/IOException;)Laahm;
        //  4984: invokespecial   aaiw.d:(Laahm;)V
        //  4987: return         
        //  4988: astore          13
        //  4990: aload_0        
        //  4991: aload           13
        //  4993: invokespecial   aaiw.d:(Laahm;)V
        //  4996: return         
        //  4997: astore          13
        //  4999: aload_0        
        //  5000: getfield        aaiw.m:Ljava/lang/String;
        //  5003: astore          14
        //  5005: new             Ljava/lang/StringBuilder;
        //  5008: dup            
        //  5009: ldc             "[Offline] pudl task cotn ["
        //  5011: invokespecial   java/lang/StringBuilder.<init>:(Ljava/lang/String;)V
        //  5014: astore          15
        //  5016: aload           15
        //  5018: aload           14
        //  5020: invokevirtual   java/lang/StringBuilder.append:(Ljava/lang/String;)Ljava/lang/StringBuilder;
        //  5023: pop            
        //  5024: aload           15
        //  5026: ldc_w           "] error while pinning video"
        //  5029: invokevirtual   java/lang/StringBuilder.append:(Ljava/lang/String;)Ljava/lang/StringBuilder;
        //  5032: pop            
        //  5033: aload           15
        //  5035: invokevirtual   java/lang/StringBuilder.toString:()Ljava/lang/String;
        //  5038: aload           13
        //  5040: invokestatic    tut.d:(Ljava/lang/String;Ljava/lang/Throwable;)V
        //  5043: getstatic       zng.b:Lzng;
        //  5046: getstatic       znf.B:Lznf;
        //  5049: ldc_w           "VideoAd pin exception: "
        //  5052: aload           13
        //  5054: invokevirtual   java/lang/Exception.getMessage:()Ljava/lang/String;
        //  5057: invokestatic    java/lang/String.valueOf:(Ljava/lang/Object;)Ljava/lang/String;
        //  5060: invokevirtual   java/lang/String.concat:(Ljava/lang/String;)Ljava/lang/String;
        //  5063: aload           13
        //  5065: invokestatic    znh.c:(Lzng;Lznf;Ljava/lang/String;Ljava/lang/Throwable;)V
        //  5068: aload_0        
        //  5069: ldc_w           "Error encountered while pinning the video"
        //  5072: aload           13
        //  5074: getstatic       aacn.d:Laacn;
        //  5077: getstatic       amxs.a:Lamxs;
        //  5080: invokestatic    aahm.b:(Ljava/lang/String;Ljava/lang/Exception;Laacn;Lamxs;)Laahm;
        //  5083: invokespecial   aaiw.d:(Laahm;)V
        //  5086: return         
        //  5087: astore          13
        //  5089: goto            203
        //  5092: astore          13
        //  5094: goto            4943
        //    Exceptions:
        //  Try           Handler
        //  Start  End    Start  End    Type                                     
        //  -----  -----  -----  -----  -----------------------------------------
        //  5      26     4997   5087   Ljava/lang/Exception;
        //  34     40     4997   5087   Ljava/lang/Exception;
        //  41     48     4997   5087   Ljava/lang/Exception;
        //  51     89     4997   5087   Ljava/lang/Exception;
        //  90     115    5087   5092   Laahm;
        //  90     115    198    203    Laaix;
        //  90     115    193    4179   Ljava/io/IOException;
        //  90     115    188    4165   Ljava/lang/InterruptedException;
        //  90     115    4997   5087   Ljava/lang/Exception;
        //  118    144    5087   5092   Laahm;
        //  118    144    198    203    Laaix;
        //  118    144    193    4179   Ljava/io/IOException;
        //  118    144    188    4165   Ljava/lang/InterruptedException;
        //  118    144    4997   5087   Ljava/lang/Exception;
        //  149    159    5087   5092   Laahm;
        //  149    159    198    203    Laaix;
        //  149    159    193    4179   Ljava/io/IOException;
        //  149    159    188    4165   Ljava/lang/InterruptedException;
        //  149    159    4997   5087   Ljava/lang/Exception;
        //  174    185    5087   5092   Laahm;
        //  174    185    198    203    Laaix;
        //  174    185    193    4179   Ljava/io/IOException;
        //  174    185    188    4165   Ljava/lang/InterruptedException;
        //  174    185    4997   5087   Ljava/lang/Exception;
        //  203    223    4988   4997   Laahm;
        //  203    223    4179   4181   Laaix;
        //  203    223    193    4179   Ljava/io/IOException;
        //  203    223    188    4165   Ljava/lang/InterruptedException;
        //  203    223    4997   5087   Ljava/lang/Exception;
        //  228    259    4988   4997   Laahm;
        //  228    259    198    203    Laaix;
        //  228    259    193    4179   Ljava/io/IOException;
        //  228    259    188    4165   Ljava/lang/InterruptedException;
        //  228    259    4997   5087   Ljava/lang/Exception;
        //  265    301    4988   4997   Laahm;
        //  265    301    198    203    Laaix;
        //  265    301    193    4179   Ljava/io/IOException;
        //  265    301    188    4165   Ljava/lang/InterruptedException;
        //  265    301    4997   5087   Ljava/lang/Exception;
        //  306    314    4988   4997   Laahm;
        //  306    314    198    203    Laaix;
        //  306    314    193    4179   Ljava/io/IOException;
        //  306    314    188    4165   Ljava/lang/InterruptedException;
        //  306    314    4997   5087   Ljava/lang/Exception;
        //  317    331    4988   4997   Laahm;
        //  317    331    198    203    Laaix;
        //  317    331    193    4179   Ljava/io/IOException;
        //  317    331    188    4165   Ljava/lang/InterruptedException;
        //  317    331    4997   5087   Ljava/lang/Exception;
        //  336    366    4988   4997   Laahm;
        //  336    366    198    203    Laaix;
        //  336    366    193    4179   Ljava/io/IOException;
        //  336    366    188    4165   Ljava/lang/InterruptedException;
        //  336    366    4997   5087   Ljava/lang/Exception;
        //  370    401    4988   4997   Laahm;
        //  370    401    4179   4181   Laaix;
        //  370    401    193    4179   Ljava/io/IOException;
        //  370    401    188    4165   Ljava/lang/InterruptedException;
        //  370    401    4997   5087   Ljava/lang/Exception;
        //  411    451    4988   4997   Laahm;
        //  411    451    198    203    Laaix;
        //  411    451    193    4179   Ljava/io/IOException;
        //  411    451    188    4165   Ljava/lang/InterruptedException;
        //  411    451    4997   5087   Ljava/lang/Exception;
        //  454    513    4988   4997   Laahm;
        //  454    513    4179   4181   Laaix;
        //  454    513    193    4179   Ljava/io/IOException;
        //  454    513    188    4165   Ljava/lang/InterruptedException;
        //  454    513    4997   5087   Ljava/lang/Exception;
        //  518    547    4988   4997   Laahm;
        //  518    547    198    203    Laaix;
        //  518    547    193    4179   Ljava/io/IOException;
        //  518    547    188    4165   Ljava/lang/InterruptedException;
        //  518    547    4997   5087   Ljava/lang/Exception;
        //  553    562    4988   4997   Laahm;
        //  553    562    4179   4181   Laaix;
        //  553    562    193    4179   Ljava/io/IOException;
        //  553    562    188    4165   Ljava/lang/InterruptedException;
        //  553    562    4997   5087   Ljava/lang/Exception;
        //  572    593    4988   4997   Laahm;
        //  572    593    198    203    Laaix;
        //  572    593    193    4179   Ljava/io/IOException;
        //  572    593    188    4165   Ljava/lang/InterruptedException;
        //  572    593    4997   5087   Ljava/lang/Exception;
        //  593    613    4988   4997   Laahm;
        //  593    613    4179   4181   Laaix;
        //  593    613    193    4179   Ljava/io/IOException;
        //  593    613    188    4165   Ljava/lang/InterruptedException;
        //  593    613    4997   5087   Ljava/lang/Exception;
        //  624    636    4988   4997   Laahm;
        //  624    636    198    203    Laaix;
        //  624    636    193    4179   Ljava/io/IOException;
        //  624    636    188    4165   Ljava/lang/InterruptedException;
        //  624    636    4997   5087   Ljava/lang/Exception;
        //  645    650    4988   4997   Laahm;
        //  645    650    198    203    Laaix;
        //  645    650    193    4179   Ljava/io/IOException;
        //  645    650    188    4165   Ljava/lang/InterruptedException;
        //  645    650    4997   5087   Ljava/lang/Exception;
        //  650    657    4988   4997   Laahm;
        //  650    657    198    203    Laaix;
        //  650    657    193    4179   Ljava/io/IOException;
        //  650    657    188    4165   Ljava/lang/InterruptedException;
        //  650    657    4997   5087   Ljava/lang/Exception;
        //  666    671    4988   4997   Laahm;
        //  666    671    198    203    Laaix;
        //  666    671    193    4179   Ljava/io/IOException;
        //  666    671    188    4165   Ljava/lang/InterruptedException;
        //  666    671    4997   5087   Ljava/lang/Exception;
        //  671    680    4988   4997   Laahm;
        //  671    680    198    203    Laaix;
        //  671    680    193    4179   Ljava/io/IOException;
        //  671    680    188    4165   Ljava/lang/InterruptedException;
        //  671    680    4997   5087   Ljava/lang/Exception;
        //  692    700    4988   4997   Laahm;
        //  692    700    198    203    Laaix;
        //  692    700    193    4179   Ljava/io/IOException;
        //  692    700    188    4165   Ljava/lang/InterruptedException;
        //  692    700    4997   5087   Ljava/lang/Exception;
        //  705    731    4988   4997   Laahm;
        //  705    731    4179   4181   Laaix;
        //  705    731    193    4179   Ljava/io/IOException;
        //  705    731    188    4165   Ljava/lang/InterruptedException;
        //  705    731    4997   5087   Ljava/lang/Exception;
        //  731    808    4988   4997   Laahm;
        //  731    808    4179   4181   Laaix;
        //  731    808    193    4179   Ljava/io/IOException;
        //  731    808    188    4165   Ljava/lang/InterruptedException;
        //  731    808    4997   5087   Ljava/lang/Exception;
        //  815    853    4988   4997   Laahm;
        //  815    853    4179   4181   Laaix;
        //  815    853    193    4179   Ljava/io/IOException;
        //  815    853    188    4165   Ljava/lang/InterruptedException;
        //  815    853    4997   5087   Ljava/lang/Exception;
        //  858    864    4988   4997   Laahm;
        //  858    864    198    203    Laaix;
        //  858    864    193    4179   Ljava/io/IOException;
        //  858    864    188    4165   Ljava/lang/InterruptedException;
        //  858    864    4997   5087   Ljava/lang/Exception;
        //  864    907    910    917    Ljava/lang/RuntimeException;
        //  864    907    198    203    Laaix;
        //  864    907    193    4179   Ljava/io/IOException;
        //  864    907    188    4165   Ljava/lang/InterruptedException;
        //  864    907    4997   5087   Ljava/lang/Exception;
        //  912    917    4988   4997   Laahm;
        //  912    917    198    203    Laaix;
        //  912    917    193    4179   Ljava/io/IOException;
        //  912    917    188    4165   Ljava/lang/InterruptedException;
        //  912    917    4997   5087   Ljava/lang/Exception;
        //  917    929    4988   4997   Laahm;
        //  917    929    4179   4181   Laaix;
        //  917    929    193    4179   Ljava/io/IOException;
        //  917    929    188    4165   Ljava/lang/InterruptedException;
        //  917    929    4997   5087   Ljava/lang/Exception;
        //  934    940    4988   4997   Laahm;
        //  934    940    198    203    Laaix;
        //  934    940    193    4179   Ljava/io/IOException;
        //  934    940    188    4165   Ljava/lang/InterruptedException;
        //  934    940    4997   5087   Ljava/lang/Exception;
        //  945    956    4988   4997   Laahm;
        //  945    956    198    203    Laaix;
        //  945    956    193    4179   Ljava/io/IOException;
        //  945    956    188    4165   Ljava/lang/InterruptedException;
        //  945    956    4997   5087   Ljava/lang/Exception;
        //  966    1002   4988   4997   Laahm;
        //  966    1002   198    203    Laaix;
        //  966    1002   193    4179   Ljava/io/IOException;
        //  966    1002   188    4165   Ljava/lang/InterruptedException;
        //  966    1002   4997   5087   Ljava/lang/Exception;
        //  1008   1034   4988   4997   Laahm;
        //  1008   1034   4179   4181   Laaix;
        //  1008   1034   193    4179   Ljava/io/IOException;
        //  1008   1034   188    4165   Ljava/lang/InterruptedException;
        //  1008   1034   4997   5087   Ljava/lang/Exception;
        //  1034   1052   4988   4997   Laahm;
        //  1034   1052   4179   4181   Laaix;
        //  1034   1052   193    4179   Ljava/io/IOException;
        //  1034   1052   188    4165   Ljava/lang/InterruptedException;
        //  1034   1052   4997   5087   Ljava/lang/Exception;
        //  1052   1061   4988   4997   Laahm;
        //  1052   1061   4179   4181   Laaix;
        //  1052   1061   193    4179   Ljava/io/IOException;
        //  1052   1061   188    4165   Ljava/lang/InterruptedException;
        //  1052   1061   4997   5087   Ljava/lang/Exception;
        //  1066   1089   4988   4997   Laahm;
        //  1066   1089   198    203    Laaix;
        //  1066   1089   193    4179   Ljava/io/IOException;
        //  1066   1089   188    4165   Ljava/lang/InterruptedException;
        //  1066   1089   4997   5087   Ljava/lang/Exception;
        //  1092   1114   4988   4997   Laahm;
        //  1092   1114   4179   4181   Laaix;
        //  1092   1114   193    4179   Ljava/io/IOException;
        //  1092   1114   188    4165   Ljava/lang/InterruptedException;
        //  1092   1114   4997   5087   Ljava/lang/Exception;
        //  1118   1127   4988   4997   Laahm;
        //  1118   1127   4179   4181   Laaix;
        //  1118   1127   193    4179   Ljava/io/IOException;
        //  1118   1127   188    4165   Ljava/lang/InterruptedException;
        //  1118   1127   4997   5087   Ljava/lang/Exception;
        //  1132   1196   4988   4997   Laahm;
        //  1132   1196   198    203    Laaix;
        //  1132   1196   193    4179   Ljava/io/IOException;
        //  1132   1196   188    4165   Ljava/lang/InterruptedException;
        //  1132   1196   4997   5087   Ljava/lang/Exception;
        //  1199   1213   4988   4997   Laahm;
        //  1199   1213   4179   4181   Laaix;
        //  1199   1213   193    4179   Ljava/io/IOException;
        //  1199   1213   188    4165   Ljava/lang/InterruptedException;
        //  1199   1213   4997   5087   Ljava/lang/Exception;
        //  1225   1241   4988   4997   Laahm;
        //  1225   1241   198    203    Laaix;
        //  1225   1241   193    4179   Ljava/io/IOException;
        //  1225   1241   188    4165   Ljava/lang/InterruptedException;
        //  1225   1241   4997   5087   Ljava/lang/Exception;
        //  1246   1255   4988   4997   Laahm;
        //  1246   1255   4179   4181   Laaix;
        //  1246   1255   193    4179   Ljava/io/IOException;
        //  1246   1255   188    4165   Ljava/lang/InterruptedException;
        //  1246   1255   4997   5087   Ljava/lang/Exception;
        //  1255   1264   4988   4997   Laahm;
        //  1255   1264   4179   4181   Laaix;
        //  1255   1264   193    4179   Ljava/io/IOException;
        //  1255   1264   188    4165   Ljava/lang/InterruptedException;
        //  1255   1264   4997   5087   Ljava/lang/Exception;
        //  1269   1304   4988   4997   Laahm;
        //  1269   1304   198    203    Laaix;
        //  1269   1304   193    4179   Ljava/io/IOException;
        //  1269   1304   188    4165   Ljava/lang/InterruptedException;
        //  1269   1304   4997   5087   Ljava/lang/Exception;
        //  1328   1360   4988   4997   Laahm;
        //  1328   1360   4179   4181   Laaix;
        //  1328   1360   193    4179   Ljava/io/IOException;
        //  1328   1360   188    4165   Ljava/lang/InterruptedException;
        //  1328   1360   4997   5087   Ljava/lang/Exception;
        //  1364   1373   4988   4997   Laahm;
        //  1364   1373   4090   4095   Laaix;
        //  1364   1373   193    4179   Ljava/io/IOException;
        //  1364   1373   188    4165   Ljava/lang/InterruptedException;
        //  1364   1373   4997   5087   Ljava/lang/Exception;
        //  1381   1400   4988   4997   Laahm;
        //  1381   1400   4090   4095   Laaix;
        //  1381   1400   193    4179   Ljava/io/IOException;
        //  1381   1400   188    4165   Ljava/lang/InterruptedException;
        //  1381   1400   4997   5087   Ljava/lang/Exception;
        //  1408   1478   4988   4997   Laahm;
        //  1408   1478   4090   4095   Laaix;
        //  1408   1478   193    4179   Ljava/io/IOException;
        //  1408   1478   188    4165   Ljava/lang/InterruptedException;
        //  1408   1478   4997   5087   Ljava/lang/Exception;
        //  1483   1511   4988   4997   Laahm;
        //  1483   1511   4090   4095   Laaix;
        //  1483   1511   193    4179   Ljava/io/IOException;
        //  1483   1511   188    4165   Ljava/lang/InterruptedException;
        //  1483   1511   4997   5087   Ljava/lang/Exception;
        //  1514   1539   4988   4997   Laahm;
        //  1514   1539   4090   4095   Laaix;
        //  1514   1539   193    4179   Ljava/io/IOException;
        //  1514   1539   188    4165   Ljava/lang/InterruptedException;
        //  1514   1539   4997   5087   Ljava/lang/Exception;
        //  1544   1635   4988   4997   Laahm;
        //  1544   1635   4090   4095   Laaix;
        //  1544   1635   193    4179   Ljava/io/IOException;
        //  1544   1635   188    4165   Ljava/lang/InterruptedException;
        //  1544   1635   4997   5087   Ljava/lang/Exception;
        //  1638   1645   4988   4997   Laahm;
        //  1638   1645   4090   4095   Laaix;
        //  1638   1645   193    4179   Ljava/io/IOException;
        //  1638   1645   188    4165   Ljava/lang/InterruptedException;
        //  1638   1645   4997   5087   Ljava/lang/Exception;
        //  1648   1655   4988   4997   Laahm;
        //  1648   1655   4090   4095   Laaix;
        //  1648   1655   193    4179   Ljava/io/IOException;
        //  1648   1655   188    4165   Ljava/lang/InterruptedException;
        //  1648   1655   4997   5087   Ljava/lang/Exception;
        //  1660   1751   4988   4997   Laahm;
        //  1660   1751   4090   4095   Laaix;
        //  1660   1751   193    4179   Ljava/io/IOException;
        //  1660   1751   188    4165   Ljava/lang/InterruptedException;
        //  1660   1751   4997   5087   Ljava/lang/Exception;
        //  1751   1758   4988   4997   Laahm;
        //  1751   1758   4090   4095   Laaix;
        //  1751   1758   193    4179   Ljava/io/IOException;
        //  1751   1758   188    4165   Ljava/lang/InterruptedException;
        //  1751   1758   4997   5087   Ljava/lang/Exception;
        //  1764   1781   4988   4997   Laahm;
        //  1764   1781   4090   4095   Laaix;
        //  1764   1781   193    4179   Ljava/io/IOException;
        //  1764   1781   188    4165   Ljava/lang/InterruptedException;
        //  1764   1781   4997   5087   Ljava/lang/Exception;
        //  1786   1809   4988   4997   Laahm;
        //  1786   1809   4090   4095   Laaix;
        //  1786   1809   193    4179   Ljava/io/IOException;
        //  1786   1809   188    4165   Ljava/lang/InterruptedException;
        //  1786   1809   4997   5087   Ljava/lang/Exception;
        //  1823   1857   4988   4997   Laahm;
        //  1823   1857   4090   4095   Laaix;
        //  1823   1857   193    4179   Ljava/io/IOException;
        //  1823   1857   188    4165   Ljava/lang/InterruptedException;
        //  1823   1857   4997   5087   Ljava/lang/Exception;
        //  1860   1874   4988   4997   Laahm;
        //  1860   1874   4090   4095   Laaix;
        //  1860   1874   193    4179   Ljava/io/IOException;
        //  1860   1874   188    4165   Ljava/lang/InterruptedException;
        //  1860   1874   4997   5087   Ljava/lang/Exception;
        //  1874   1898   2519   2521   Ljava/io/IOException;
        //  1874   1898   2514   2519   Ljava/util/concurrent/ExecutionException;
        //  1874   1898   4988   4997   Laahm;
        //  1874   1898   188    4165   Ljava/lang/InterruptedException;
        //  1874   1898   4997   5087   Ljava/lang/Exception;
        //  1906   1917   2505   2514   Ljava/io/IOException;
        //  1906   1917   2500   2505   Ljava/util/concurrent/ExecutionException;
        //  1906   1917   4988   4997   Laahm;
        //  1906   1917   188    4165   Ljava/lang/InterruptedException;
        //  1906   1917   4997   5087   Ljava/lang/Exception;
        //  1934   1960   2505   2514   Ljava/io/IOException;
        //  1934   1960   2500   2505   Ljava/util/concurrent/ExecutionException;
        //  1934   1960   4988   4997   Laahm;
        //  1934   1960   188    4165   Ljava/lang/InterruptedException;
        //  1934   1960   4997   5087   Ljava/lang/Exception;
        //  1977   1987   2505   2514   Ljava/io/IOException;
        //  1977   1987   2500   2505   Ljava/util/concurrent/ExecutionException;
        //  1977   1987   4988   4997   Laahm;
        //  1977   1987   188    4165   Ljava/lang/InterruptedException;
        //  1977   1987   4997   5087   Ljava/lang/Exception;
        //  1995   2002   2505   2514   Ljava/io/IOException;
        //  1995   2002   2500   2505   Ljava/util/concurrent/ExecutionException;
        //  1995   2002   4988   4997   Laahm;
        //  1995   2002   188    4165   Ljava/lang/InterruptedException;
        //  1995   2002   4997   5087   Ljava/lang/Exception;
        //  2014   2024   2505   2514   Ljava/io/IOException;
        //  2014   2024   2500   2505   Ljava/util/concurrent/ExecutionException;
        //  2014   2024   4988   4997   Laahm;
        //  2014   2024   188    4165   Ljava/lang/InterruptedException;
        //  2014   2024   4997   5087   Ljava/lang/Exception;
        //  2032   2041   2505   2514   Ljava/io/IOException;
        //  2032   2041   2500   2505   Ljava/util/concurrent/ExecutionException;
        //  2032   2041   4988   4997   Laahm;
        //  2032   2041   188    4165   Ljava/lang/InterruptedException;
        //  2032   2041   4997   5087   Ljava/lang/Exception;
        //  2053   2063   2505   2514   Ljava/io/IOException;
        //  2053   2063   2500   2505   Ljava/util/concurrent/ExecutionException;
        //  2053   2063   4988   4997   Laahm;
        //  2053   2063   188    4165   Ljava/lang/InterruptedException;
        //  2053   2063   4997   5087   Ljava/lang/Exception;
        //  2071   2083   2505   2514   Ljava/io/IOException;
        //  2071   2083   2500   2505   Ljava/util/concurrent/ExecutionException;
        //  2071   2083   4988   4997   Laahm;
        //  2071   2083   188    4165   Ljava/lang/InterruptedException;
        //  2071   2083   4997   5087   Ljava/lang/Exception;
        //  2091   2112   2505   2514   Ljava/io/IOException;
        //  2091   2112   2500   2505   Ljava/util/concurrent/ExecutionException;
        //  2091   2112   4988   4997   Laahm;
        //  2091   2112   188    4165   Ljava/lang/InterruptedException;
        //  2091   2112   4997   5087   Ljava/lang/Exception;
        //  2120   2132   2505   2514   Ljava/io/IOException;
        //  2120   2132   2500   2505   Ljava/util/concurrent/ExecutionException;
        //  2120   2132   4988   4997   Laahm;
        //  2120   2132   188    4165   Ljava/lang/InterruptedException;
        //  2120   2132   4997   5087   Ljava/lang/Exception;
        //  2140   2148   2505   2514   Ljava/io/IOException;
        //  2140   2148   2500   2505   Ljava/util/concurrent/ExecutionException;
        //  2140   2148   4988   4997   Laahm;
        //  2140   2148   188    4165   Ljava/lang/InterruptedException;
        //  2140   2148   4997   5087   Ljava/lang/Exception;
        //  2156   2169   2505   2514   Ljava/io/IOException;
        //  2156   2169   2500   2505   Ljava/util/concurrent/ExecutionException;
        //  2156   2169   4988   4997   Laahm;
        //  2156   2169   188    4165   Ljava/lang/InterruptedException;
        //  2156   2169   4997   5087   Ljava/lang/Exception;
        //  2177   2183   2505   2514   Ljava/io/IOException;
        //  2177   2183   2500   2505   Ljava/util/concurrent/ExecutionException;
        //  2177   2183   4988   4997   Laahm;
        //  2177   2183   188    4165   Ljava/lang/InterruptedException;
        //  2177   2183   4997   5087   Ljava/lang/Exception;
        //  2191   2204   2505   2514   Ljava/io/IOException;
        //  2191   2204   2500   2505   Ljava/util/concurrent/ExecutionException;
        //  2191   2204   4988   4997   Laahm;
        //  2191   2204   188    4165   Ljava/lang/InterruptedException;
        //  2191   2204   4997   5087   Ljava/lang/Exception;
        //  2212   2220   2505   2514   Ljava/io/IOException;
        //  2212   2220   2500   2505   Ljava/util/concurrent/ExecutionException;
        //  2212   2220   4988   4997   Laahm;
        //  2212   2220   188    4165   Ljava/lang/InterruptedException;
        //  2212   2220   4997   5087   Ljava/lang/Exception;
        //  2228   2233   2505   2514   Ljava/io/IOException;
        //  2228   2233   2500   2505   Ljava/util/concurrent/ExecutionException;
        //  2228   2233   4988   4997   Laahm;
        //  2228   2233   188    4165   Ljava/lang/InterruptedException;
        //  2228   2233   4997   5087   Ljava/lang/Exception;
        //  2241   2251   2505   2514   Ljava/io/IOException;
        //  2241   2251   2500   2505   Ljava/util/concurrent/ExecutionException;
        //  2241   2251   4988   4997   Laahm;
        //  2241   2251   188    4165   Ljava/lang/InterruptedException;
        //  2241   2251   4997   5087   Ljava/lang/Exception;
        //  2255   2346   2492   2497   Ljava/io/IOException;
        //  2255   2346   2487   2492   Ljava/util/concurrent/ExecutionException;
        //  2255   2346   4988   4997   Laahm;
        //  2255   2346   188    4165   Ljava/lang/InterruptedException;
        //  2255   2346   4997   5087   Ljava/lang/Exception;
        //  2364   2419   2492   2497   Ljava/io/IOException;
        //  2364   2419   2487   2492   Ljava/util/concurrent/ExecutionException;
        //  2364   2419   4988   4997   Laahm;
        //  2364   2419   188    4165   Ljava/lang/InterruptedException;
        //  2364   2419   4997   5087   Ljava/lang/Exception;
        //  2419   2432   2492   2497   Ljava/io/IOException;
        //  2419   2432   2487   2492   Ljava/util/concurrent/ExecutionException;
        //  2419   2432   4988   4997   Laahm;
        //  2419   2432   188    4165   Ljava/lang/InterruptedException;
        //  2419   2432   4997   5087   Ljava/lang/Exception;
        //  2438   2484   2492   2497   Ljava/io/IOException;
        //  2438   2484   2487   2492   Ljava/util/concurrent/ExecutionException;
        //  2438   2484   4988   4997   Laahm;
        //  2438   2484   188    4165   Ljava/lang/InterruptedException;
        //  2438   2484   4997   5087   Ljava/lang/Exception;
        //  2529   2545   4988   4997   Laahm;
        //  2529   2545   4090   4095   Laaix;
        //  2529   2545   193    4179   Ljava/io/IOException;
        //  2529   2545   188    4165   Ljava/lang/InterruptedException;
        //  2529   2545   4997   5087   Ljava/lang/Exception;
        //  2562   2590   4988   4997   Laahm;
        //  2562   2590   4090   4095   Laaix;
        //  2562   2590   193    4179   Ljava/io/IOException;
        //  2562   2590   188    4165   Ljava/lang/InterruptedException;
        //  2562   2590   4997   5087   Ljava/lang/Exception;
        //  2590   2621   2882   2884   Ljava/io/IOException;
        //  2590   2621   2877   2882   Ljava/util/concurrent/ExecutionException;
        //  2590   2621   2872   2877   Ljava/lang/RuntimeException;
        //  2590   2621   188    4165   Ljava/lang/InterruptedException;
        //  2590   2621   4997   5087   Ljava/lang/Exception;
        //  2633   2649   2882   2884   Ljava/io/IOException;
        //  2633   2649   2877   2882   Ljava/util/concurrent/ExecutionException;
        //  2633   2649   2872   2877   Ljava/lang/RuntimeException;
        //  2633   2649   188    4165   Ljava/lang/InterruptedException;
        //  2633   2649   4997   5087   Ljava/lang/Exception;
        //  2653   2672   2882   2884   Ljava/io/IOException;
        //  2653   2672   2877   2882   Ljava/util/concurrent/ExecutionException;
        //  2653   2672   2872   2877   Ljava/lang/RuntimeException;
        //  2653   2672   188    4165   Ljava/lang/InterruptedException;
        //  2653   2672   4997   5087   Ljava/lang/Exception;
        //  2676   2751   2882   2884   Ljava/io/IOException;
        //  2676   2751   2877   2882   Ljava/util/concurrent/ExecutionException;
        //  2676   2751   2872   2877   Ljava/lang/RuntimeException;
        //  2676   2751   188    4165   Ljava/lang/InterruptedException;
        //  2676   2751   4997   5087   Ljava/lang/Exception;
        //  2756   2766   2882   2884   Ljava/io/IOException;
        //  2756   2766   2877   2882   Ljava/util/concurrent/ExecutionException;
        //  2756   2766   2872   2877   Ljava/lang/RuntimeException;
        //  2756   2766   188    4165   Ljava/lang/InterruptedException;
        //  2756   2766   4997   5087   Ljava/lang/Exception;
        //  2766   2869   2882   2884   Ljava/io/IOException;
        //  2766   2869   2877   2882   Ljava/util/concurrent/ExecutionException;
        //  2766   2869   2872   2877   Ljava/lang/RuntimeException;
        //  2766   2869   188    4165   Ljava/lang/InterruptedException;
        //  2766   2869   4997   5087   Ljava/lang/Exception;
        //  2884   2925   4988   4997   Laahm;
        //  2884   2925   4090   4095   Laaix;
        //  2884   2925   193    4179   Ljava/io/IOException;
        //  2884   2925   188    4165   Ljava/lang/InterruptedException;
        //  2884   2925   4997   5087   Ljava/lang/Exception;
        //  2932   2981   4988   4997   Laahm;
        //  2932   2981   4090   4095   Laaix;
        //  2932   2981   193    4179   Ljava/io/IOException;
        //  2932   2981   188    4165   Ljava/lang/InterruptedException;
        //  2932   2981   4997   5087   Ljava/lang/Exception;
        //  2985   3037   4988   4997   Laahm;
        //  2985   3037   4090   4095   Laaix;
        //  2985   3037   193    4179   Ljava/io/IOException;
        //  2985   3037   188    4165   Ljava/lang/InterruptedException;
        //  2985   3037   4997   5087   Ljava/lang/Exception;
        //  3052   3080   4988   4997   Laahm;
        //  3052   3080   4090   4095   Laaix;
        //  3052   3080   193    4179   Ljava/io/IOException;
        //  3052   3080   188    4165   Ljava/lang/InterruptedException;
        //  3052   3080   4997   5087   Ljava/lang/Exception;
        //  3085   3113   4988   4997   Laahm;
        //  3085   3113   4090   4095   Laaix;
        //  3085   3113   193    4179   Ljava/io/IOException;
        //  3085   3113   188    4165   Ljava/lang/InterruptedException;
        //  3085   3113   4997   5087   Ljava/lang/Exception;
        //  3116   3313   4988   4997   Laahm;
        //  3116   3313   4090   4095   Laaix;
        //  3116   3313   193    4179   Ljava/io/IOException;
        //  3116   3313   188    4165   Ljava/lang/InterruptedException;
        //  3116   3313   4997   5087   Ljava/lang/Exception;
        //  3318   3409   4988   4997   Laahm;
        //  3318   3409   4090   4095   Laaix;
        //  3318   3409   193    4179   Ljava/io/IOException;
        //  3318   3409   188    4165   Ljava/lang/InterruptedException;
        //  3318   3409   4997   5087   Ljava/lang/Exception;
        //  3409   3416   4988   4997   Laahm;
        //  3409   3416   4090   4095   Laaix;
        //  3409   3416   193    4179   Ljava/io/IOException;
        //  3409   3416   188    4165   Ljava/lang/InterruptedException;
        //  3409   3416   4997   5087   Ljava/lang/Exception;
        //  3419   3435   4988   4997   Laahm;
        //  3419   3435   4090   4095   Laaix;
        //  3419   3435   193    4179   Ljava/io/IOException;
        //  3419   3435   188    4165   Ljava/lang/InterruptedException;
        //  3419   3435   4997   5087   Ljava/lang/Exception;
        //  3440   3531   4988   4997   Laahm;
        //  3440   3531   4090   4095   Laaix;
        //  3440   3531   193    4179   Ljava/io/IOException;
        //  3440   3531   188    4165   Ljava/lang/InterruptedException;
        //  3440   3531   4997   5087   Ljava/lang/Exception;
        //  3531   3538   4988   4997   Laahm;
        //  3531   3538   4090   4095   Laaix;
        //  3531   3538   193    4179   Ljava/io/IOException;
        //  3531   3538   188    4165   Ljava/lang/InterruptedException;
        //  3531   3538   4997   5087   Ljava/lang/Exception;
        //  3555   3737   4988   4997   Laahm;
        //  3555   3737   4090   4095   Laaix;
        //  3555   3737   193    4179   Ljava/io/IOException;
        //  3555   3737   188    4165   Ljava/lang/InterruptedException;
        //  3555   3737   4997   5087   Ljava/lang/Exception;
        //  3737   3765   4988   4997   Laahm;
        //  3737   3765   4090   4095   Laaix;
        //  3737   3765   193    4179   Ljava/io/IOException;
        //  3737   3765   188    4165   Ljava/lang/InterruptedException;
        //  3737   3765   4997   5087   Ljava/lang/Exception;
        //  3770   3798   4988   4997   Laahm;
        //  3770   3798   4090   4095   Laaix;
        //  3770   3798   193    4179   Ljava/io/IOException;
        //  3770   3798   188    4165   Ljava/lang/InterruptedException;
        //  3770   3798   4997   5087   Ljava/lang/Exception;
        //  3801   3826   4988   4997   Laahm;
        //  3801   3826   4090   4095   Laaix;
        //  3801   3826   193    4179   Ljava/io/IOException;
        //  3801   3826   188    4165   Ljava/lang/InterruptedException;
        //  3801   3826   4997   5087   Ljava/lang/Exception;
        //  3831   3922   4988   4997   Laahm;
        //  3831   3922   4090   4095   Laaix;
        //  3831   3922   193    4179   Ljava/io/IOException;
        //  3831   3922   188    4165   Ljava/lang/InterruptedException;
        //  3831   3922   4997   5087   Ljava/lang/Exception;
        //  3922   3945   4988   4997   Laahm;
        //  3922   3945   4090   4095   Laaix;
        //  3922   3945   193    4179   Ljava/io/IOException;
        //  3922   3945   188    4165   Ljava/lang/InterruptedException;
        //  3922   3945   4997   5087   Ljava/lang/Exception;
        //  3950   4041   4988   4997   Laahm;
        //  3950   4041   4090   4095   Laaix;
        //  3950   4041   193    4179   Ljava/io/IOException;
        //  3950   4041   188    4165   Ljava/lang/InterruptedException;
        //  3950   4041   4997   5087   Ljava/lang/Exception;
        //  4041   4073   4988   4997   Laahm;
        //  4041   4073   4090   4095   Laaix;
        //  4041   4073   193    4179   Ljava/io/IOException;
        //  4041   4073   188    4165   Ljava/lang/InterruptedException;
        //  4041   4073   4997   5087   Ljava/lang/Exception;
        //  4073   4079   4988   4997   Laahm;
        //  4073   4079   4090   4095   Laaix;
        //  4073   4079   193    4179   Ljava/io/IOException;
        //  4073   4079   188    4165   Ljava/lang/InterruptedException;
        //  4073   4079   4997   5087   Ljava/lang/Exception;
        //  4084   4089   4988   4997   Laahm;
        //  4084   4089   4090   4095   Laaix;
        //  4084   4089   193    4179   Ljava/io/IOException;
        //  4084   4089   188    4165   Ljava/lang/InterruptedException;
        //  4084   4089   4997   5087   Ljava/lang/Exception;
        //  4095   4164   4997   5087   Ljava/lang/Exception;
        //  4165   4178   4997   5087   Ljava/lang/Exception;
        //  4181   4252   4997   5087   Ljava/lang/Exception;
        //  4260   4303   4997   5087   Ljava/lang/Exception;
        //  4303   4837   5092   5097   Laaee;
        //  4303   4837   4997   5087   Ljava/lang/Exception;
        //  4837   4864   5092   5097   Laaee;
        //  4837   4864   4997   5087   Ljava/lang/Exception;
        //  4864   4891   4997   5087   Ljava/lang/Exception;
        //  4896   4942   4997   5087   Ljava/lang/Exception;
        //  4943   4973   4997   5087   Ljava/lang/Exception;
        //  4974   4987   4997   5087   Ljava/lang/Exception;
        //  4990   4996   4997   5087   Ljava/lang/Exception;
        // 
        // The error that occurred was:
        // 
        // java.lang.IndexOutOfBoundsException: Index: 2162, Size: 2162
        //     at java.util.ArrayList.rangeCheck(Unknown Source)
        //     at java.util.ArrayList.get(Unknown Source)
        //     at com.strobel.decompiler.ast.AstBuilder.convertToAst(AstBuilder.java:3362)
        //     at com.strobel.decompiler.ast.AstBuilder.build(AstBuilder.java:112)
        //     at com.strobel.decompiler.languages.java.ast.AstMethodBodyBuilder.createMethodBody(AstMethodBodyBuilder.java:203)
        //     at com.strobel.decompiler.languages.java.ast.AstMethodBodyBuilder.createMethodBody(AstMethodBodyBuilder.java:93)
        //     at com.strobel.decompiler.languages.java.ast.AstBuilder.createMethodBody(AstBuilder.java:868)
        //     at com.strobel.decompiler.languages.java.ast.AstBuilder.createMethod(AstBuilder.java:761)
        //     at com.strobel.decompiler.languages.java.ast.AstBuilder.addTypeMembers(AstBuilder.java:638)
        //     at com.strobel.decompiler.languages.java.ast.AstBuilder.createTypeCore(AstBuilder.java:605)
        //     at com.strobel.decompiler.languages.java.ast.AstBuilder.createTypeNoCache(AstBuilder.java:195)
        //     at com.strobel.decompiler.languages.java.ast.AstBuilder.createType(AstBuilder.java:162)
        //     at com.strobel.decompiler.languages.java.ast.AstBuilder.addType(AstBuilder.java:137)
        //     at com.strobel.decompiler.languages.java.JavaLanguage.buildAst(JavaLanguage.java:71)
        //     at com.strobel.decompiler.languages.java.JavaLanguage.decompileType(JavaLanguage.java:59)
        //     at com.strobel.decompiler.DecompilerDriver.decompileType(DecompilerDriver.java:333)
        //     at com.strobel.decompiler.DecompilerDriver.decompileJar(DecompilerDriver.java:254)
        //     at com.strobel.decompiler.DecompilerDriver.main(DecompilerDriver.java:129)
        // 
        throw new IllegalStateException("An error occurred while decompiling this method.");
    }
}
