import java.util.Arrays;
import java.util.ArrayList;
import java.util.HashSet;
import java.lang.ref.WeakReference;

// 
// Decompiled by Procyon v0.6.0
// 

public final class acu extends ada
{
    public final ade a;
    public WeakReference aA;
    public WeakReference aB;
    public WeakReference aC;
    public WeakReference aD;
    final HashSet aE;
    public final adb aF;
    public adt aG;
    public final ajc aH;
    public int ar;
    public int as;
    public int at;
    public int au;
    public acr[] av;
    public acr[] aw;
    public int ax;
    public boolean ay;
    public boolean az;
    public int b;
    public boolean c;
    public final acl d;
    
    public acu() {
        this.aH = new ajc(this);
        this.a = new ade(this);
        this.aG = null;
        this.c = false;
        this.d = new acl();
        this.at = 0;
        this.au = 0;
        this.av = new acr[4];
        this.aw = new acr[4];
        this.ax = 257;
        this.ay = false;
        this.az = false;
        this.aA = null;
        this.aB = null;
        this.aC = null;
        this.aD = null;
        this.aE = new HashSet();
        this.aF = new adb();
    }
    
    public static void X(final act act, final adt adt, final adb adb) {
        if (adt == null) {
            return;
        }
        if (act.ah != 8 && !(act instanceof acw) && !(act instanceof acq)) {
            adb.i = act.M();
            adb.j = act.N();
            adb.a = act.j();
            adb.b = act.h();
            adb.g = false;
            adb.h = 0;
            final boolean b = adb.i == 3;
            final boolean b2 = adb.j == 3;
            final boolean b3 = b && act.X > 0.0f;
            final boolean b4 = b2 && act.X > 0.0f;
            int n;
            if ((n = (b ? 1 : 0)) != 0) {
                n = (b ? 1 : 0);
                if (act.F(0)) {
                    n = (b ? 1 : 0);
                    if (act.s == 0) {
                        n = (b ? 1 : 0);
                        if (!b3) {
                            adb.i = 2;
                            if (b2 && act.t == 0) {
                                adb.i = 1;
                            }
                            n = 0;
                        }
                    }
                }
            }
            boolean b5;
            if (b5 = b2) {
                b5 = b2;
                if (act.F(1)) {
                    b5 = b2;
                    if (act.t == 0) {
                        b5 = b2;
                        if (!b4) {
                            adb.j = 2;
                            if (n != 0 && act.s == 0) {
                                adb.j = 1;
                            }
                            b5 = false;
                        }
                    }
                }
            }
            if (act.e()) {
                adb.i = 1;
                n = 0;
            }
            if (act.f()) {
                adb.j = 1;
                b5 = false;
            }
            if (b3) {
                if (act.u[0] == 4) {
                    adb.i = 1;
                }
                else if (!b5) {
                    int n2;
                    if (adb.j == 1) {
                        n2 = adb.b;
                    }
                    else {
                        adb.i = 2;
                        adt.a(act, adb);
                        n2 = adb.d;
                    }
                    adb.i = 1;
                    adb.a = (int)(act.X * n2);
                }
            }
            if (b4) {
                if (act.u[1] == 4) {
                    adb.j = 1;
                }
                else if (n == 0) {
                    int n3;
                    if (adb.i == 1) {
                        n3 = adb.a;
                    }
                    else {
                        adb.j = 2;
                        adt.a(act, adb);
                        n3 = adb.c;
                    }
                    adb.j = 1;
                    if (act.Y == -1) {
                        adb.b = (int)(n3 / act.X);
                    }
                    else {
                        adb.b = (int)(act.X * n3);
                    }
                }
            }
            adt.a(act, adb);
            act.C(adb.c);
            act.x(adb.d);
            act.F = adb.f;
            act.u(adb.e);
            adb.h = 0;
            final boolean g = adb.g;
            return;
        }
        adb.c = 0;
        adb.d = 0;
    }
    
    private final void Z(final acs acs, final aco aco) {
        this.d.g(aco, this.d.b(acs), 0, 5);
    }
    
    private final void aa(final acs acs, final aco aco) {
        this.d.g(this.d.b(acs), aco, 0, 5);
    }
    
    private final void ab() {
        this.at = 0;
        this.au = 0;
    }
    
    public final void D(final boolean b, final boolean b2) {
        super.D(b, b2);
        for (int size = this.aI.size(), i = 0; i < size; ++i) {
            ((act)this.aI.get(i)).D(b, b2);
        }
    }
    
    @Override
    public final void T() {
        // 
        // This method could not be decompiled.
        // 
        // Original Bytecode:
        // 
        //     1: iconst_0       
        //     2: putfield        acu.Z:I
        //     5: aload_0        
        //     6: iconst_0       
        //     7: putfield        acu.aa:I
        //    10: aload_0        
        //    11: iconst_0       
        //    12: putfield        acu.ay:Z
        //    15: aload_0        
        //    16: iconst_0       
        //    17: putfield        acu.az:Z
        //    20: aload_0        
        //    21: getfield        acu.aI:Ljava/util/ArrayList;
        //    24: invokevirtual   java/util/ArrayList.size:()I
        //    27: istore_3       
        //    28: iconst_0       
        //    29: aload_0        
        //    30: invokevirtual   act.j:()I
        //    33: invokestatic    java/lang/Math.max:(II)I
        //    36: istore          5
        //    38: iconst_0       
        //    39: aload_0        
        //    40: invokevirtual   act.h:()I
        //    43: invokestatic    java/lang/Math.max:(II)I
        //    46: istore_2       
        //    47: aload_0        
        //    48: getfield        acu.aq:[I
        //    51: astore          17
        //    53: aload           17
        //    55: iconst_1       
        //    56: iaload         
        //    57: istore          6
        //    59: aload           17
        //    61: iconst_0       
        //    62: iaload         
        //    63: istore          4
        //    65: aload_0        
        //    66: getfield        acu.b:I
        //    69: ifne            1156
        //    72: aload_0        
        //    73: getfield        acu.ax:I
        //    76: iconst_1       
        //    77: invokestatic    acy.b:(II)Z
        //    80: ifeq            1156
        //    83: aload_0        
        //    84: getfield        acu.aG:Ladt;
        //    87: astore          17
        //    89: aload_0        
        //    90: invokevirtual   act.M:()I
        //    93: istore          7
        //    95: aload_0        
        //    96: invokevirtual   act.N:()I
        //    99: istore          12
        //   101: iconst_0       
        //   102: putstatic       adh.b:I
        //   105: iconst_0       
        //   106: putstatic       adh.c:I
        //   109: aload_0        
        //   110: invokevirtual   act.t:()V
        //   113: aload_0        
        //   114: getfield        ada.aI:Ljava/util/ArrayList;
        //   117: astore          18
        //   119: aload           18
        //   121: invokevirtual   java/util/ArrayList.size:()I
        //   124: istore          11
        //   126: iconst_0       
        //   127: istore_1       
        //   128: iload_1        
        //   129: iload           11
        //   131: if_icmpge       152
        //   134: aload           18
        //   136: iload_1        
        //   137: invokevirtual   java/util/ArrayList.get:(I)Ljava/lang/Object;
        //   140: checkcast       Lact;
        //   143: invokevirtual   act.t:()V
        //   146: iinc            1, 1
        //   149: goto            128
        //   152: aload_0        
        //   153: getfield        acu.c:Z
        //   156: istore          15
        //   158: iload           7
        //   160: iconst_1       
        //   161: if_icmpne       176
        //   164: aload_0        
        //   165: iconst_0       
        //   166: aload_0        
        //   167: invokevirtual   act.j:()I
        //   170: invokevirtual   act.v:(II)V
        //   173: goto            189
        //   176: aload_0        
        //   177: getfield        act.J:Lacs;
        //   180: iconst_0       
        //   181: invokevirtual   acs.e:(I)V
        //   184: aload_0        
        //   185: iconst_0       
        //   186: putfield        act.Z:I
        //   189: iconst_0       
        //   190: istore          7
        //   192: iconst_0       
        //   193: istore          8
        //   195: iconst_0       
        //   196: istore_1       
        //   197: iload           7
        //   199: iload           11
        //   201: if_icmpge       394
        //   204: aload           18
        //   206: iload           7
        //   208: invokevirtual   java/util/ArrayList.get:(I)Ljava/lang/Object;
        //   211: checkcast       Lact;
        //   214: astore          19
        //   216: aload           19
        //   218: instanceof      Lacw;
        //   221: ifeq            341
        //   224: aload           19
        //   226: checkcast       Lacw;
        //   229: astore          19
        //   231: iload           8
        //   233: istore          9
        //   235: iload_1        
        //   236: istore          10
        //   238: aload           19
        //   240: getfield        acw.ar:I
        //   243: iconst_1       
        //   244: if_icmpne       381
        //   247: aload           19
        //   249: getfield        acw.b:I
        //   252: istore          8
        //   254: iload           8
        //   256: iconst_m1      
        //   257: if_icmpeq       276
        //   260: aload           19
        //   262: iload           8
        //   264: invokevirtual   acw.a:(I)V
        //   267: iconst_1       
        //   268: istore          9
        //   270: iload_1        
        //   271: istore          10
        //   273: goto            381
        //   276: aload           19
        //   278: getfield        acw.c:I
        //   281: iconst_m1      
        //   282: if_icmpeq       310
        //   285: aload_0        
        //   286: invokevirtual   act.e:()Z
        //   289: ifeq            310
        //   292: aload           19
        //   294: aload_0        
        //   295: invokevirtual   act.j:()I
        //   298: aload           19
        //   300: getfield        acw.c:I
        //   303: isub           
        //   304: invokevirtual   acw.a:(I)V
        //   307: goto            267
        //   310: aload_0        
        //   311: invokevirtual   act.e:()Z
        //   314: ifeq            267
        //   317: aload           19
        //   319: aload           19
        //   321: getfield        acw.a:F
        //   324: aload_0        
        //   325: invokevirtual   act.j:()I
        //   328: i2f            
        //   329: fmul           
        //   330: ldc_w           0.5
        //   333: fadd           
        //   334: f2i            
        //   335: invokevirtual   acw.a:(I)V
        //   338: goto            267
        //   341: iload           8
        //   343: istore          9
        //   345: iload_1        
        //   346: istore          10
        //   348: aload           19
        //   350: instanceof      Lacq;
        //   353: ifeq            381
        //   356: iload           8
        //   358: istore          9
        //   360: iload_1        
        //   361: istore          10
        //   363: aload           19
        //   365: checkcast       Lacq;
        //   368: invokevirtual   acq.a:()I
        //   371: ifne            381
        //   374: iconst_1       
        //   375: istore          10
        //   377: iload           8
        //   379: istore          9
        //   381: iinc            7, 1
        //   384: iload           9
        //   386: istore          8
        //   388: iload           10
        //   390: istore_1       
        //   391: goto            197
        //   394: iload           8
        //   396: ifeq            464
        //   399: iconst_0       
        //   400: istore          7
        //   402: iload           7
        //   404: iload           11
        //   406: if_icmpge       464
        //   409: aload           18
        //   411: iload           7
        //   413: invokevirtual   java/util/ArrayList.get:(I)Ljava/lang/Object;
        //   416: checkcast       Lact;
        //   419: astore          19
        //   421: aload           19
        //   423: instanceof      Lacw;
        //   426: ifeq            458
        //   429: aload           19
        //   431: checkcast       Lacw;
        //   434: astore          19
        //   436: aload           19
        //   438: getfield        acw.ar:I
        //   441: iconst_1       
        //   442: if_icmpne       458
        //   445: iconst_0       
        //   446: aload           19
        //   448: aload           17
        //   450: iload           15
        //   452: invokestatic    adh.a:(ILact;Ladt;Z)V
        //   455: goto            458
        //   458: iinc            7, 1
        //   461: goto            402
        //   464: iconst_0       
        //   465: istore          7
        //   467: iconst_0       
        //   468: aload_0        
        //   469: aload           17
        //   471: iload           15
        //   473: invokestatic    adh.a:(ILact;Ladt;Z)V
        //   476: iload_1        
        //   477: ifeq            538
        //   480: iconst_0       
        //   481: istore_1       
        //   482: iload_1        
        //   483: iload           11
        //   485: if_icmpge       538
        //   488: aload           18
        //   490: iload_1        
        //   491: invokevirtual   java/util/ArrayList.get:(I)Ljava/lang/Object;
        //   494: checkcast       Lact;
        //   497: astore          19
        //   499: aload           19
        //   501: instanceof      Lacq;
        //   504: ifeq            532
        //   507: aload           19
        //   509: checkcast       Lacq;
        //   512: astore          19
        //   514: aload           19
        //   516: invokevirtual   acq.a:()I
        //   519: ifne            532
        //   522: aload           19
        //   524: aload           17
        //   526: iconst_0       
        //   527: iload           15
        //   529: invokestatic    adh.d:(Lacq;Ladt;IZ)V
        //   532: iinc            1, 1
        //   535: goto            482
        //   538: iload           12
        //   540: iconst_1       
        //   541: if_icmpne       561
        //   544: aload_0        
        //   545: iconst_0       
        //   546: aload_0        
        //   547: invokevirtual   act.h:()I
        //   550: invokevirtual   act.w:(II)V
        //   553: iconst_0       
        //   554: istore          8
        //   556: iconst_0       
        //   557: istore_1       
        //   558: goto            582
        //   561: aload_0        
        //   562: getfield        act.K:Lacs;
        //   565: iconst_0       
        //   566: invokevirtual   acs.e:(I)V
        //   569: aload_0        
        //   570: iconst_0       
        //   571: putfield        act.aa:I
        //   574: iconst_0       
        //   575: istore          8
        //   577: iconst_0       
        //   578: istore_1       
        //   579: iconst_0       
        //   580: istore          7
        //   582: iload           7
        //   584: iload           11
        //   586: if_icmpge       779
        //   589: aload           18
        //   591: iload           7
        //   593: invokevirtual   java/util/ArrayList.get:(I)Ljava/lang/Object;
        //   596: checkcast       Lact;
        //   599: astore          19
        //   601: aload           19
        //   603: instanceof      Lacw;
        //   606: ifeq            725
        //   609: aload           19
        //   611: checkcast       Lacw;
        //   614: astore          19
        //   616: iload           8
        //   618: istore          10
        //   620: iload_1        
        //   621: istore          9
        //   623: aload           19
        //   625: getfield        acw.ar:I
        //   628: ifne            766
        //   631: aload           19
        //   633: getfield        acw.b:I
        //   636: istore          8
        //   638: iload           8
        //   640: iconst_m1      
        //   641: if_icmpeq       660
        //   644: aload           19
        //   646: iload           8
        //   648: invokevirtual   acw.a:(I)V
        //   651: iconst_1       
        //   652: istore          10
        //   654: iload_1        
        //   655: istore          9
        //   657: goto            766
        //   660: aload           19
        //   662: getfield        acw.c:I
        //   665: iconst_m1      
        //   666: if_icmpeq       694
        //   669: aload_0        
        //   670: invokevirtual   act.f:()Z
        //   673: ifeq            694
        //   676: aload           19
        //   678: aload_0        
        //   679: invokevirtual   act.h:()I
        //   682: aload           19
        //   684: getfield        acw.c:I
        //   687: isub           
        //   688: invokevirtual   acw.a:(I)V
        //   691: goto            651
        //   694: aload_0        
        //   695: invokevirtual   act.f:()Z
        //   698: ifeq            651
        //   701: aload           19
        //   703: aload           19
        //   705: getfield        acw.a:F
        //   708: aload_0        
        //   709: invokevirtual   act.h:()I
        //   712: i2f            
        //   713: fmul           
        //   714: ldc_w           0.5
        //   717: fadd           
        //   718: f2i            
        //   719: invokevirtual   acw.a:(I)V
        //   722: goto            651
        //   725: iload           8
        //   727: istore          10
        //   729: iload_1        
        //   730: istore          9
        //   732: aload           19
        //   734: instanceof      Lacq;
        //   737: ifeq            766
        //   740: iload           8
        //   742: istore          10
        //   744: iload_1        
        //   745: istore          9
        //   747: aload           19
        //   749: checkcast       Lacq;
        //   752: invokevirtual   acq.a:()I
        //   755: iconst_1       
        //   756: if_icmpne       766
        //   759: iconst_1       
        //   760: istore          9
        //   762: iload           8
        //   764: istore          10
        //   766: iinc            7, 1
        //   769: iload           10
        //   771: istore          8
        //   773: iload           9
        //   775: istore_1       
        //   776: goto            582
        //   779: iload           8
        //   781: ifeq            843
        //   784: iconst_0       
        //   785: istore          7
        //   787: iload           7
        //   789: iload           11
        //   791: if_icmpge       843
        //   794: aload           18
        //   796: iload           7
        //   798: invokevirtual   java/util/ArrayList.get:(I)Ljava/lang/Object;
        //   801: checkcast       Lact;
        //   804: astore          19
        //   806: aload           19
        //   808: instanceof      Lacw;
        //   811: ifeq            837
        //   814: aload           19
        //   816: checkcast       Lacw;
        //   819: astore          19
        //   821: aload           19
        //   823: getfield        acw.ar:I
        //   826: ifne            837
        //   829: iconst_1       
        //   830: aload           19
        //   832: aload           17
        //   834: invokestatic    adh.b:(ILact;Ladt;)V
        //   837: iinc            7, 1
        //   840: goto            787
        //   843: iconst_0       
        //   844: aload_0        
        //   845: aload           17
        //   847: invokestatic    adh.b:(ILact;Ladt;)V
        //   850: iload_1        
        //   851: ifeq            913
        //   854: iconst_0       
        //   855: istore_1       
        //   856: iload_1        
        //   857: iload           11
        //   859: if_icmpge       913
        //   862: aload           18
        //   864: iload_1        
        //   865: invokevirtual   java/util/ArrayList.get:(I)Ljava/lang/Object;
        //   868: checkcast       Lact;
        //   871: astore          19
        //   873: aload           19
        //   875: instanceof      Lacq;
        //   878: ifeq            907
        //   881: aload           19
        //   883: checkcast       Lacq;
        //   886: astore          19
        //   888: aload           19
        //   890: invokevirtual   acq.a:()I
        //   893: iconst_1       
        //   894: if_icmpne       907
        //   897: aload           19
        //   899: aload           17
        //   901: iconst_1       
        //   902: iload           15
        //   904: invokestatic    adh.d:(Lacq;Ladt;IZ)V
        //   907: iinc            1, 1
        //   910: goto            856
        //   913: iconst_0       
        //   914: istore_1       
        //   915: iload_1        
        //   916: iload           11
        //   918: if_icmpge       1025
        //   921: aload           18
        //   923: iload_1        
        //   924: invokevirtual   java/util/ArrayList.get:(I)Ljava/lang/Object;
        //   927: checkcast       Lact;
        //   930: astore          19
        //   932: aload           19
        //   934: invokevirtual   act.J:()Z
        //   937: ifeq            1019
        //   940: aload           19
        //   942: invokestatic    adh.c:(Lact;)Z
        //   945: ifeq            1019
        //   948: aload           19
        //   950: aload           17
        //   952: getstatic       adh.a:Ladb;
        //   955: invokestatic    acu.X:(Lact;Ladt;Ladb;)V
        //   958: aload           19
        //   960: instanceof      Lacw;
        //   963: ifeq            1001
        //   966: aload           19
        //   968: checkcast       Lacw;
        //   971: getfield        acw.ar:I
        //   974: ifne            988
        //   977: iconst_0       
        //   978: aload           19
        //   980: aload           17
        //   982: invokestatic    adh.b:(ILact;Ladt;)V
        //   985: goto            1019
        //   988: iconst_0       
        //   989: aload           19
        //   991: aload           17
        //   993: iload           15
        //   995: invokestatic    adh.a:(ILact;Ladt;Z)V
        //   998: goto            1019
        //  1001: iconst_0       
        //  1002: aload           19
        //  1004: aload           17
        //  1006: iload           15
        //  1008: invokestatic    adh.a:(ILact;Ladt;Z)V
        //  1011: iconst_0       
        //  1012: aload           19
        //  1014: aload           17
        //  1016: invokestatic    adh.b:(ILact;Ladt;)V
        //  1019: iinc            1, 1
        //  1022: goto            915
        //  1025: iconst_0       
        //  1026: istore_1       
        //  1027: iload_1        
        //  1028: iload_3        
        //  1029: if_icmpge       1156
        //  1032: aload_0        
        //  1033: getfield        acu.aI:Ljava/util/ArrayList;
        //  1036: iload_1        
        //  1037: invokevirtual   java/util/ArrayList.get:(I)Ljava/lang/Object;
        //  1040: checkcast       Lact;
        //  1043: astore          18
        //  1045: aload           18
        //  1047: invokevirtual   act.J:()Z
        //  1050: ifeq            1150
        //  1053: aload           18
        //  1055: instanceof      Lacw;
        //  1058: ifne            1150
        //  1061: aload           18
        //  1063: instanceof      Lacq;
        //  1066: ifne            1150
        //  1069: aload           18
        //  1071: instanceof      Lacz;
        //  1074: ifne            1150
        //  1077: aload           18
        //  1079: getfield        act.G:Z
        //  1082: istore          15
        //  1084: aload           18
        //  1086: iconst_0       
        //  1087: invokevirtual   act.L:(I)I
        //  1090: istore          7
        //  1092: aload           18
        //  1094: iconst_1       
        //  1095: invokevirtual   act.L:(I)I
        //  1098: istore          8
        //  1100: iload           7
        //  1102: iconst_3       
        //  1103: if_icmpne       1130
        //  1106: aload           18
        //  1108: getfield        act.s:I
        //  1111: iconst_1       
        //  1112: if_icmpeq       1130
        //  1115: iload           8
        //  1117: iconst_3       
        //  1118: if_icmpne       1130
        //  1121: aload           18
        //  1123: getfield        act.t:I
        //  1126: iconst_1       
        //  1127: if_icmpne       1150
        //  1130: new             Ladb;
        //  1133: dup            
        //  1134: invokespecial   adb.<init>:()V
        //  1137: astore          17
        //  1139: aload           18
        //  1141: aload_0        
        //  1142: getfield        acu.aG:Ladt;
        //  1145: aload           17
        //  1147: invokestatic    acu.X:(Lact;Ladt;Ladb;)V
        //  1150: iinc            1, 1
        //  1153: goto            1027
        //  1156: iload           6
        //  1158: istore          7
        //  1160: iload_3        
        //  1161: iconst_2       
        //  1162: if_icmple       3197
        //  1165: iload           6
        //  1167: istore_1       
        //  1168: iload           4
        //  1170: iconst_2       
        //  1171: if_icmpeq       1203
        //  1174: iload           6
        //  1176: istore_1       
        //  1177: iload           6
        //  1179: iconst_2       
        //  1180: if_icmpne       1188
        //  1183: iconst_2       
        //  1184: istore_1       
        //  1185: goto            1203
        //  1188: iload_1        
        //  1189: istore          7
        //  1191: iconst_0       
        //  1192: istore_1       
        //  1193: iload           4
        //  1195: istore          6
        //  1197: iload_3        
        //  1198: istore          8
        //  1200: goto            3206
        //  1203: iload_1        
        //  1204: istore          7
        //  1206: aload_0        
        //  1207: getfield        acu.ax:I
        //  1210: sipush          1024
        //  1213: invokestatic    acy.b:(II)Z
        //  1216: ifeq            3197
        //  1219: aload_0        
        //  1220: getfield        acu.aG:Ladt;
        //  1223: astore          29
        //  1225: aload_0        
        //  1226: getfield        ada.aI:Ljava/util/ArrayList;
        //  1229: astore          28
        //  1231: aload           28
        //  1233: invokevirtual   java/util/ArrayList.size:()I
        //  1236: istore          7
        //  1238: iconst_0       
        //  1239: istore          6
        //  1241: iload           6
        //  1243: iload           7
        //  1245: if_icmpge       1304
        //  1248: aload           28
        //  1250: iload           6
        //  1252: invokevirtual   java/util/ArrayList.get:(I)Ljava/lang/Object;
        //  1255: checkcast       Lact;
        //  1258: astore          17
        //  1260: aload_0        
        //  1261: invokevirtual   act.M:()I
        //  1264: aload_0        
        //  1265: invokevirtual   act.N:()I
        //  1268: aload           17
        //  1270: invokevirtual   act.M:()I
        //  1273: aload           17
        //  1275: invokevirtual   act.N:()I
        //  1278: invokestatic    sn.d:(IIII)Z
        //  1281: ifne            1287
        //  1284: goto            1188
        //  1287: aload           17
        //  1289: instanceof      Lacv;
        //  1292: ifeq            1298
        //  1295: goto            1188
        //  1298: iinc            6, 1
        //  1301: goto            1241
        //  1304: aconst_null    
        //  1305: astore          23
        //  1307: iconst_0       
        //  1308: istore          6
        //  1310: aconst_null    
        //  1311: astore          17
        //  1313: aconst_null    
        //  1314: astore          19
        //  1316: aconst_null    
        //  1317: astore          18
        //  1319: aconst_null    
        //  1320: astore          21
        //  1322: aconst_null    
        //  1323: astore          20
        //  1325: iload_3        
        //  1326: istore          8
        //  1328: iload_1        
        //  1329: istore_3       
        //  1330: iload_2        
        //  1331: istore_1       
        //  1332: iload           5
        //  1334: istore_2       
        //  1335: iload           6
        //  1337: iload           7
        //  1339: if_icmpge       1890
        //  1342: aload           28
        //  1344: iload           6
        //  1346: invokevirtual   java/util/ArrayList.get:(I)Ljava/lang/Object;
        //  1349: checkcast       Lact;
        //  1352: astore          30
        //  1354: aload_0        
        //  1355: invokevirtual   act.M:()I
        //  1358: aload_0        
        //  1359: invokevirtual   act.N:()I
        //  1362: aload           30
        //  1364: invokevirtual   act.M:()I
        //  1367: aload           30
        //  1369: invokevirtual   act.N:()I
        //  1372: invokestatic    sn.d:(IIII)Z
        //  1375: ifne            1389
        //  1378: aload           30
        //  1380: aload           29
        //  1382: aload_0        
        //  1383: getfield        acu.aF:Ladb;
        //  1386: invokestatic    acu.X:(Lact;Ladt;Ladb;)V
        //  1389: aload           30
        //  1391: instanceof      Lacw;
        //  1394: istore          15
        //  1396: aload           23
        //  1398: astore          25
        //  1400: aload           19
        //  1402: astore          24
        //  1404: iload           15
        //  1406: ifeq            1505
        //  1409: aload           30
        //  1411: checkcast       Lacw;
        //  1414: astore          26
        //  1416: aload           19
        //  1418: astore          22
        //  1420: aload           26
        //  1422: getfield        acw.ar:I
        //  1425: ifne            1454
        //  1428: aload           19
        //  1430: astore          22
        //  1432: aload           19
        //  1434: ifnonnull       1446
        //  1437: new             Ljava/util/ArrayList;
        //  1440: dup            
        //  1441: invokespecial   java/util/ArrayList.<init>:()V
        //  1444: astore          22
        //  1446: aload           22
        //  1448: aload           26
        //  1450: invokevirtual   java/util/ArrayList.add:(Ljava/lang/Object;)Z
        //  1453: pop            
        //  1454: aload           23
        //  1456: astore          25
        //  1458: aload           22
        //  1460: astore          24
        //  1462: aload           26
        //  1464: getfield        acw.ar:I
        //  1467: iconst_1       
        //  1468: if_icmpne       1505
        //  1471: aload           23
        //  1473: astore          19
        //  1475: aload           23
        //  1477: ifnonnull       1489
        //  1480: new             Ljava/util/ArrayList;
        //  1483: dup            
        //  1484: invokespecial   java/util/ArrayList.<init>:()V
        //  1487: astore          19
        //  1489: aload           19
        //  1491: aload           26
        //  1493: invokevirtual   java/util/ArrayList.add:(Ljava/lang/Object;)Z
        //  1496: pop            
        //  1497: aload           22
        //  1499: astore          24
        //  1501: aload           19
        //  1503: astore          25
        //  1505: aload           17
        //  1507: astore          19
        //  1509: aload           18
        //  1511: astore          22
        //  1513: aload           30
        //  1515: instanceof      Lacx;
        //  1518: ifeq            1683
        //  1521: aload           30
        //  1523: instanceof      Lacq;
        //  1526: ifeq            1624
        //  1529: aload           30
        //  1531: checkcast       Lacq;
        //  1534: astore          26
        //  1536: aload           17
        //  1538: astore          23
        //  1540: aload           26
        //  1542: invokevirtual   acq.a:()I
        //  1545: ifne            1574
        //  1548: aload           17
        //  1550: astore          23
        //  1552: aload           17
        //  1554: ifnonnull       1566
        //  1557: new             Ljava/util/ArrayList;
        //  1560: dup            
        //  1561: invokespecial   java/util/ArrayList.<init>:()V
        //  1564: astore          23
        //  1566: aload           23
        //  1568: aload           26
        //  1570: invokevirtual   java/util/ArrayList.add:(Ljava/lang/Object;)Z
        //  1573: pop            
        //  1574: aload           23
        //  1576: astore          19
        //  1578: aload           18
        //  1580: astore          22
        //  1582: aload           26
        //  1584: invokevirtual   acq.a:()I
        //  1587: iconst_1       
        //  1588: if_icmpne       1683
        //  1591: aload           18
        //  1593: astore          22
        //  1595: aload           18
        //  1597: ifnonnull       1609
        //  1600: new             Ljava/util/ArrayList;
        //  1603: dup            
        //  1604: invokespecial   java/util/ArrayList.<init>:()V
        //  1607: astore          22
        //  1609: aload           22
        //  1611: aload           26
        //  1613: invokevirtual   java/util/ArrayList.add:(Ljava/lang/Object;)Z
        //  1616: pop            
        //  1617: aload           23
        //  1619: astore          19
        //  1621: goto            1683
        //  1624: aload           30
        //  1626: checkcast       Lacx;
        //  1629: astore          23
        //  1631: aload           17
        //  1633: astore          19
        //  1635: aload           17
        //  1637: ifnonnull       1649
        //  1640: new             Ljava/util/ArrayList;
        //  1643: dup            
        //  1644: invokespecial   java/util/ArrayList.<init>:()V
        //  1647: astore          19
        //  1649: aload           19
        //  1651: aload           23
        //  1653: invokevirtual   java/util/ArrayList.add:(Ljava/lang/Object;)Z
        //  1656: pop            
        //  1657: aload           18
        //  1659: astore          22
        //  1661: aload           18
        //  1663: ifnonnull       1675
        //  1666: new             Ljava/util/ArrayList;
        //  1669: dup            
        //  1670: invokespecial   java/util/ArrayList.<init>:()V
        //  1673: astore          22
        //  1675: aload           22
        //  1677: aload           23
        //  1679: invokevirtual   java/util/ArrayList.add:(Ljava/lang/Object;)Z
        //  1682: pop            
        //  1683: aload           21
        //  1685: astore          26
        //  1687: aload           30
        //  1689: getfield        act.J:Lacs;
        //  1692: getfield        acs.e:Lacs;
        //  1695: ifnonnull       1764
        //  1698: aload           21
        //  1700: astore          26
        //  1702: aload           30
        //  1704: getfield        act.L:Lacs;
        //  1707: getfield        acs.e:Lacs;
        //  1710: ifnonnull       1764
        //  1713: aload           21
        //  1715: astore          26
        //  1717: iload           15
        //  1719: ifne            1764
        //  1722: aload           21
        //  1724: astore          26
        //  1726: aload           30
        //  1728: instanceof      Lacq;
        //  1731: ifne            1764
        //  1734: aload           21
        //  1736: astore          17
        //  1738: aload           21
        //  1740: ifnonnull       1752
        //  1743: new             Ljava/util/ArrayList;
        //  1746: dup            
        //  1747: invokespecial   java/util/ArrayList.<init>:()V
        //  1750: astore          17
        //  1752: aload           17
        //  1754: aload           30
        //  1756: invokevirtual   java/util/ArrayList.add:(Ljava/lang/Object;)Z
        //  1759: pop            
        //  1760: aload           17
        //  1762: astore          26
        //  1764: aload           20
        //  1766: astore          27
        //  1768: aload           30
        //  1770: getfield        act.K:Lacs;
        //  1773: getfield        acs.e:Lacs;
        //  1776: ifnonnull       1860
        //  1779: aload           20
        //  1781: astore          27
        //  1783: aload           30
        //  1785: getfield        act.M:Lacs;
        //  1788: getfield        acs.e:Lacs;
        //  1791: ifnonnull       1860
        //  1794: aload           20
        //  1796: astore          27
        //  1798: aload           30
        //  1800: getfield        act.N:Lacs;
        //  1803: getfield        acs.e:Lacs;
        //  1806: ifnonnull       1860
        //  1809: aload           20
        //  1811: astore          27
        //  1813: iload           15
        //  1815: ifne            1860
        //  1818: aload           20
        //  1820: astore          27
        //  1822: aload           30
        //  1824: instanceof      Lacq;
        //  1827: ifne            1860
        //  1830: aload           20
        //  1832: astore          17
        //  1834: aload           20
        //  1836: ifnonnull       1848
        //  1839: new             Ljava/util/ArrayList;
        //  1842: dup            
        //  1843: invokespecial   java/util/ArrayList.<init>:()V
        //  1846: astore          17
        //  1848: aload           17
        //  1850: aload           30
        //  1852: invokevirtual   java/util/ArrayList.add:(Ljava/lang/Object;)Z
        //  1855: pop            
        //  1856: aload           17
        //  1858: astore          27
        //  1860: iinc            6, 1
        //  1863: aload           25
        //  1865: astore          23
        //  1867: aload           19
        //  1869: astore          17
        //  1871: aload           24
        //  1873: astore          19
        //  1875: aload           22
        //  1877: astore          18
        //  1879: aload           26
        //  1881: astore          21
        //  1883: aload           27
        //  1885: astore          20
        //  1887: goto            1335
        //  1890: new             Ljava/util/ArrayList;
        //  1893: dup            
        //  1894: invokespecial   java/util/ArrayList.<init>:()V
        //  1897: astore          22
        //  1899: aload           23
        //  1901: ifnull          1949
        //  1904: aload           23
        //  1906: invokeinterface java/util/List.size:()I
        //  1911: istore          6
        //  1913: iconst_0       
        //  1914: istore          5
        //  1916: iload           5
        //  1918: iload           6
        //  1920: if_icmpge       1949
        //  1923: aload           23
        //  1925: iload           5
        //  1927: invokeinterface java/util/List.get:(I)Ljava/lang/Object;
        //  1932: checkcast       Lacw;
        //  1935: iconst_0       
        //  1936: aload           22
        //  1938: aconst_null    
        //  1939: invokestatic    sn.b:(Lact;ILjava/util/ArrayList;Ladn;)Ladn;
        //  1942: pop            
        //  1943: iinc            5, 1
        //  1946: goto            1916
        //  1949: aload           17
        //  1951: ifnull          2021
        //  1954: aload           17
        //  1956: invokeinterface java/util/List.size:()I
        //  1961: istore          6
        //  1963: iconst_0       
        //  1964: istore          5
        //  1966: iload           5
        //  1968: iload           6
        //  1970: if_icmpge       2021
        //  1973: aload           17
        //  1975: iload           5
        //  1977: invokeinterface java/util/List.get:(I)Ljava/lang/Object;
        //  1982: checkcast       Lacx;
        //  1985: astore          23
        //  1987: aload           23
        //  1989: iconst_0       
        //  1990: aload           22
        //  1992: aconst_null    
        //  1993: invokestatic    sn.b:(Lact;ILjava/util/ArrayList;Ladn;)Ladn;
        //  1996: astore          24
        //  1998: aload           23
        //  2000: aload           22
        //  2002: iconst_0       
        //  2003: aload           24
        //  2005: invokevirtual   acx.T:(Ljava/util/ArrayList;ILadn;)V
        //  2008: aload           24
        //  2010: aload           22
        //  2012: invokevirtual   adn.b:(Ljava/util/ArrayList;)V
        //  2015: iinc            5, 1
        //  2018: goto            1966
        //  2021: aload_0        
        //  2022: iconst_2       
        //  2023: invokevirtual   act.K:(I)Lacs;
        //  2026: getfield        acs.a:Ljava/util/HashSet;
        //  2029: astore          17
        //  2031: aload           17
        //  2033: ifnull          2077
        //  2036: aload           17
        //  2038: invokevirtual   java/util/HashSet.iterator:()Ljava/util/Iterator;
        //  2041: astore          17
        //  2043: aload           17
        //  2045: invokeinterface java/util/Iterator.hasNext:()Z
        //  2050: ifeq            2077
        //  2053: aload           17
        //  2055: invokeinterface java/util/Iterator.next:()Ljava/lang/Object;
        //  2060: checkcast       Lacs;
        //  2063: getfield        acs.d:Lact;
        //  2066: iconst_0       
        //  2067: aload           22
        //  2069: aconst_null    
        //  2070: invokestatic    sn.b:(Lact;ILjava/util/ArrayList;Ladn;)Ladn;
        //  2073: pop            
        //  2074: goto            2043
        //  2077: aload_0        
        //  2078: iconst_4       
        //  2079: invokevirtual   act.K:(I)Lacs;
        //  2082: getfield        acs.a:Ljava/util/HashSet;
        //  2085: astore          17
        //  2087: aload           17
        //  2089: ifnull          2133
        //  2092: aload           17
        //  2094: invokevirtual   java/util/HashSet.iterator:()Ljava/util/Iterator;
        //  2097: astore          17
        //  2099: aload           17
        //  2101: invokeinterface java/util/Iterator.hasNext:()Z
        //  2106: ifeq            2133
        //  2109: aload           17
        //  2111: invokeinterface java/util/Iterator.next:()Ljava/lang/Object;
        //  2116: checkcast       Lacs;
        //  2119: getfield        acs.d:Lact;
        //  2122: iconst_0       
        //  2123: aload           22
        //  2125: aconst_null    
        //  2126: invokestatic    sn.b:(Lact;ILjava/util/ArrayList;Ladn;)Ladn;
        //  2129: pop            
        //  2130: goto            2099
        //  2133: aload_0        
        //  2134: bipush          7
        //  2136: invokevirtual   act.K:(I)Lacs;
        //  2139: getfield        acs.a:Ljava/util/HashSet;
        //  2142: astore          17
        //  2144: aload           17
        //  2146: ifnull          2190
        //  2149: aload           17
        //  2151: invokevirtual   java/util/HashSet.iterator:()Ljava/util/Iterator;
        //  2154: astore          17
        //  2156: aload           17
        //  2158: invokeinterface java/util/Iterator.hasNext:()Z
        //  2163: ifeq            2190
        //  2166: aload           17
        //  2168: invokeinterface java/util/Iterator.next:()Ljava/lang/Object;
        //  2173: checkcast       Lacs;
        //  2176: getfield        acs.d:Lact;
        //  2179: iconst_0       
        //  2180: aload           22
        //  2182: aconst_null    
        //  2183: invokestatic    sn.b:(Lact;ILjava/util/ArrayList;Ladn;)Ladn;
        //  2186: pop            
        //  2187: goto            2156
        //  2190: aload           21
        //  2192: ifnull          2240
        //  2195: aload           21
        //  2197: invokeinterface java/util/List.size:()I
        //  2202: istore          6
        //  2204: iconst_0       
        //  2205: istore          5
        //  2207: iload           5
        //  2209: iload           6
        //  2211: if_icmpge       2240
        //  2214: aload           21
        //  2216: iload           5
        //  2218: invokeinterface java/util/List.get:(I)Ljava/lang/Object;
        //  2223: checkcast       Lact;
        //  2226: iconst_0       
        //  2227: aload           22
        //  2229: aconst_null    
        //  2230: invokestatic    sn.b:(Lact;ILjava/util/ArrayList;Ladn;)Ladn;
        //  2233: pop            
        //  2234: iinc            5, 1
        //  2237: goto            2207
        //  2240: aload           19
        //  2242: ifnull          2290
        //  2245: aload           19
        //  2247: invokeinterface java/util/List.size:()I
        //  2252: istore          6
        //  2254: iconst_0       
        //  2255: istore          5
        //  2257: iload           5
        //  2259: iload           6
        //  2261: if_icmpge       2290
        //  2264: aload           19
        //  2266: iload           5
        //  2268: invokeinterface java/util/List.get:(I)Ljava/lang/Object;
        //  2273: checkcast       Lacw;
        //  2276: iconst_1       
        //  2277: aload           22
        //  2279: aconst_null    
        //  2280: invokestatic    sn.b:(Lact;ILjava/util/ArrayList;Ladn;)Ladn;
        //  2283: pop            
        //  2284: iinc            5, 1
        //  2287: goto            2257
        //  2290: aload           18
        //  2292: ifnull          2362
        //  2295: aload           18
        //  2297: invokeinterface java/util/List.size:()I
        //  2302: istore          6
        //  2304: iconst_0       
        //  2305: istore          5
        //  2307: iload           5
        //  2309: iload           6
        //  2311: if_icmpge       2362
        //  2314: aload           18
        //  2316: iload           5
        //  2318: invokeinterface java/util/List.get:(I)Ljava/lang/Object;
        //  2323: checkcast       Lacx;
        //  2326: astore          19
        //  2328: aload           19
        //  2330: iconst_1       
        //  2331: aload           22
        //  2333: aconst_null    
        //  2334: invokestatic    sn.b:(Lact;ILjava/util/ArrayList;Ladn;)Ladn;
        //  2337: astore          17
        //  2339: aload           19
        //  2341: aload           22
        //  2343: iconst_1       
        //  2344: aload           17
        //  2346: invokevirtual   acx.T:(Ljava/util/ArrayList;ILadn;)V
        //  2349: aload           17
        //  2351: aload           22
        //  2353: invokevirtual   adn.b:(Ljava/util/ArrayList;)V
        //  2356: iinc            5, 1
        //  2359: goto            2307
        //  2362: aload_0        
        //  2363: iconst_3       
        //  2364: invokevirtual   act.K:(I)Lacs;
        //  2367: getfield        acs.a:Ljava/util/HashSet;
        //  2370: astore          17
        //  2372: aload           17
        //  2374: ifnull          2418
        //  2377: aload           17
        //  2379: invokevirtual   java/util/HashSet.iterator:()Ljava/util/Iterator;
        //  2382: astore          17
        //  2384: aload           17
        //  2386: invokeinterface java/util/Iterator.hasNext:()Z
        //  2391: ifeq            2418
        //  2394: aload           17
        //  2396: invokeinterface java/util/Iterator.next:()Ljava/lang/Object;
        //  2401: checkcast       Lacs;
        //  2404: getfield        acs.d:Lact;
        //  2407: iconst_1       
        //  2408: aload           22
        //  2410: aconst_null    
        //  2411: invokestatic    sn.b:(Lact;ILjava/util/ArrayList;Ladn;)Ladn;
        //  2414: pop            
        //  2415: goto            2384
        //  2418: aload_0        
        //  2419: bipush          6
        //  2421: invokevirtual   act.K:(I)Lacs;
        //  2424: getfield        acs.a:Ljava/util/HashSet;
        //  2427: astore          17
        //  2429: aload           17
        //  2431: ifnull          2475
        //  2434: aload           17
        //  2436: invokevirtual   java/util/HashSet.iterator:()Ljava/util/Iterator;
        //  2439: astore          17
        //  2441: aload           17
        //  2443: invokeinterface java/util/Iterator.hasNext:()Z
        //  2448: ifeq            2475
        //  2451: aload           17
        //  2453: invokeinterface java/util/Iterator.next:()Ljava/lang/Object;
        //  2458: checkcast       Lacs;
        //  2461: getfield        acs.d:Lact;
        //  2464: iconst_1       
        //  2465: aload           22
        //  2467: aconst_null    
        //  2468: invokestatic    sn.b:(Lact;ILjava/util/ArrayList;Ladn;)Ladn;
        //  2471: pop            
        //  2472: goto            2441
        //  2475: aload_0        
        //  2476: iconst_5       
        //  2477: invokevirtual   act.K:(I)Lacs;
        //  2480: getfield        acs.a:Ljava/util/HashSet;
        //  2483: astore          17
        //  2485: aload           17
        //  2487: ifnull          2531
        //  2490: aload           17
        //  2492: invokevirtual   java/util/HashSet.iterator:()Ljava/util/Iterator;
        //  2495: astore          17
        //  2497: aload           17
        //  2499: invokeinterface java/util/Iterator.hasNext:()Z
        //  2504: ifeq            2531
        //  2507: aload           17
        //  2509: invokeinterface java/util/Iterator.next:()Ljava/lang/Object;
        //  2514: checkcast       Lacs;
        //  2517: getfield        acs.d:Lact;
        //  2520: iconst_1       
        //  2521: aload           22
        //  2523: aconst_null    
        //  2524: invokestatic    sn.b:(Lact;ILjava/util/ArrayList;Ladn;)Ladn;
        //  2527: pop            
        //  2528: goto            2497
        //  2531: aload_0        
        //  2532: bipush          7
        //  2534: invokevirtual   act.K:(I)Lacs;
        //  2537: getfield        acs.a:Ljava/util/HashSet;
        //  2540: astore          17
        //  2542: aload           17
        //  2544: ifnull          2588
        //  2547: aload           17
        //  2549: invokevirtual   java/util/HashSet.iterator:()Ljava/util/Iterator;
        //  2552: astore          17
        //  2554: aload           17
        //  2556: invokeinterface java/util/Iterator.hasNext:()Z
        //  2561: ifeq            2588
        //  2564: aload           17
        //  2566: invokeinterface java/util/Iterator.next:()Ljava/lang/Object;
        //  2571: checkcast       Lacs;
        //  2574: getfield        acs.d:Lact;
        //  2577: iconst_1       
        //  2578: aload           22
        //  2580: aconst_null    
        //  2581: invokestatic    sn.b:(Lact;ILjava/util/ArrayList;Ladn;)Ladn;
        //  2584: pop            
        //  2585: goto            2554
        //  2588: aload           20
        //  2590: ifnull          2638
        //  2593: aload           20
        //  2595: invokeinterface java/util/List.size:()I
        //  2600: istore          6
        //  2602: iconst_0       
        //  2603: istore          5
        //  2605: iload           5
        //  2607: iload           6
        //  2609: if_icmpge       2638
        //  2612: aload           20
        //  2614: iload           5
        //  2616: invokeinterface java/util/List.get:(I)Ljava/lang/Object;
        //  2621: checkcast       Lact;
        //  2624: iconst_1       
        //  2625: aload           22
        //  2627: aconst_null    
        //  2628: invokestatic    sn.b:(Lact;ILjava/util/ArrayList;Ladn;)Ladn;
        //  2631: pop            
        //  2632: iinc            5, 1
        //  2635: goto            2605
        //  2638: iconst_0       
        //  2639: istore          5
        //  2641: iload           5
        //  2643: iload           7
        //  2645: if_icmpge       2745
        //  2648: aload           28
        //  2650: iload           5
        //  2652: invokevirtual   java/util/ArrayList.get:(I)Ljava/lang/Object;
        //  2655: checkcast       Lact;
        //  2658: astore          18
        //  2660: aload           18
        //  2662: getfield        act.aq:[I
        //  2665: astore          17
        //  2667: aload           17
        //  2669: iconst_0       
        //  2670: iaload         
        //  2671: iconst_3       
        //  2672: if_icmpne       2739
        //  2675: aload           17
        //  2677: iconst_1       
        //  2678: iaload         
        //  2679: iconst_3       
        //  2680: if_icmpne       2739
        //  2683: aload           22
        //  2685: aload           18
        //  2687: getfield        act.ao:I
        //  2690: invokestatic    sn.c:(Ljava/util/ArrayList;I)Ladn;
        //  2693: astore          17
        //  2695: aload           22
        //  2697: aload           18
        //  2699: getfield        act.ap:I
        //  2702: invokestatic    sn.c:(Ljava/util/ArrayList;I)Ladn;
        //  2705: astore          18
        //  2707: aload           17
        //  2709: ifnull          2739
        //  2712: aload           18
        //  2714: ifnull          2739
        //  2717: aload           17
        //  2719: iconst_0       
        //  2720: aload           18
        //  2722: invokevirtual   adn.c:(ILadn;)V
        //  2725: aload           18
        //  2727: iconst_2       
        //  2728: putfield        adn.d:I
        //  2731: aload           22
        //  2733: aload           17
        //  2735: invokevirtual   java/util/ArrayList.remove:(Ljava/lang/Object;)Z
        //  2738: pop            
        //  2739: iinc            5, 1
        //  2742: goto            2641
        //  2745: aload           22
        //  2747: invokevirtual   java/util/ArrayList.size:()I
        //  2750: iconst_1       
        //  2751: if_icmpgt       2769
        //  2754: iload_2        
        //  2755: istore          5
        //  2757: iload_1        
        //  2758: istore_2       
        //  2759: iload           4
        //  2761: istore          6
        //  2763: iload_3        
        //  2764: istore          7
        //  2766: goto            3204
        //  2769: aload_0        
        //  2770: invokevirtual   act.M:()I
        //  2773: iconst_2       
        //  2774: if_icmpne       2916
        //  2777: aload           22
        //  2779: invokeinterface java/util/List.size:()I
        //  2784: istore          10
        //  2786: aconst_null    
        //  2787: astore          17
        //  2789: iconst_0       
        //  2790: istore          7
        //  2792: iconst_0       
        //  2793: istore          5
        //  2795: iload           7
        //  2797: iload           10
        //  2799: if_icmpge       2893
        //  2802: aload           22
        //  2804: iload           7
        //  2806: invokeinterface java/util/List.get:(I)Ljava/lang/Object;
        //  2811: checkcast       Ladn;
        //  2814: astore          19
        //  2816: aload           17
        //  2818: astore          18
        //  2820: iload           5
        //  2822: istore          6
        //  2824: aload           19
        //  2826: getfield        adn.d:I
        //  2829: iconst_1       
        //  2830: if_icmpeq       2879
        //  2833: aload           19
        //  2835: aload_0        
        //  2836: getfield        acu.d:Lacl;
        //  2839: iconst_0       
        //  2840: invokevirtual   adn.a:(Lacl;I)I
        //  2843: istore          9
        //  2845: iload           9
        //  2847: iload           5
        //  2849: if_icmple       2856
        //  2852: aload           19
        //  2854: astore          17
        //  2856: aload           17
        //  2858: astore          18
        //  2860: iload           5
        //  2862: istore          6
        //  2864: iload           9
        //  2866: iload           5
        //  2868: if_icmple       2879
        //  2871: iload           9
        //  2873: istore          6
        //  2875: aload           17
        //  2877: astore          18
        //  2879: iinc            7, 1
        //  2882: aload           18
        //  2884: astore          17
        //  2886: iload           6
        //  2888: istore          5
        //  2890: goto            2795
        //  2893: aload           17
        //  2895: ifnull          2916
        //  2898: aload_0        
        //  2899: iconst_1       
        //  2900: invokevirtual   act.P:(I)V
        //  2903: aload_0        
        //  2904: iload           5
        //  2906: invokevirtual   act.C:(I)V
        //  2909: aload           17
        //  2911: astore          18
        //  2913: goto            2919
        //  2916: aconst_null    
        //  2917: astore          18
        //  2919: aload_0        
        //  2920: invokevirtual   act.N:()I
        //  2923: iconst_2       
        //  2924: if_icmpne       3061
        //  2927: aload           22
        //  2929: invokeinterface java/util/List.size:()I
        //  2934: istore          10
        //  2936: aconst_null    
        //  2937: astore          17
        //  2939: iconst_0       
        //  2940: istore          6
        //  2942: iconst_0       
        //  2943: istore          7
        //  2945: iload           6
        //  2947: iload           10
        //  2949: if_icmpge       3042
        //  2952: aload           22
        //  2954: iload           6
        //  2956: invokeinterface java/util/List.get:(I)Ljava/lang/Object;
        //  2961: checkcast       Ladn;
        //  2964: astore          20
        //  2966: aload           17
        //  2968: astore          19
        //  2970: iload           7
        //  2972: istore          5
        //  2974: aload           20
        //  2976: getfield        adn.d:I
        //  2979: ifeq            3028
        //  2982: aload           20
        //  2984: aload_0        
        //  2985: getfield        acu.d:Lacl;
        //  2988: iconst_1       
        //  2989: invokevirtual   adn.a:(Lacl;I)I
        //  2992: istore          9
        //  2994: iload           9
        //  2996: iload           7
        //  2998: if_icmple       3005
        //  3001: aload           20
        //  3003: astore          17
        //  3005: aload           17
        //  3007: astore          19
        //  3009: iload           7
        //  3011: istore          5
        //  3013: iload           9
        //  3015: iload           7
        //  3017: if_icmple       3028
        //  3020: iload           9
        //  3022: istore          5
        //  3024: aload           17
        //  3026: astore          19
        //  3028: iinc            6, 1
        //  3031: aload           19
        //  3033: astore          17
        //  3035: iload           5
        //  3037: istore          7
        //  3039: goto            2945
        //  3042: aload           17
        //  3044: ifnull          3061
        //  3047: aload_0        
        //  3048: iconst_1       
        //  3049: invokevirtual   act.Q:(I)V
        //  3052: aload_0        
        //  3053: iload           7
        //  3055: invokevirtual   act.x:(I)V
        //  3058: goto            3064
        //  3061: aconst_null    
        //  3062: astore          17
        //  3064: aload           18
        //  3066: ifnonnull       3074
        //  3069: aload           17
        //  3071: ifnull          2754
        //  3074: iload           4
        //  3076: iconst_2       
        //  3077: if_icmpne       3119
        //  3080: iload_2        
        //  3081: aload_0        
        //  3082: invokevirtual   act.j:()I
        //  3085: if_icmpge       3108
        //  3088: iload_2        
        //  3089: ifle            3108
        //  3092: aload_0        
        //  3093: iload_2        
        //  3094: invokevirtual   act.C:(I)V
        //  3097: aload_0        
        //  3098: iconst_1       
        //  3099: putfield        acu.ay:Z
        //  3102: iload_2        
        //  3103: istore          4
        //  3105: goto            3114
        //  3108: aload_0        
        //  3109: invokevirtual   act.j:()I
        //  3112: istore          4
        //  3114: iconst_2       
        //  3115: istore_2       
        //  3116: goto            3129
        //  3119: iload           4
        //  3121: istore          5
        //  3123: iload_2        
        //  3124: istore          4
        //  3126: iload           5
        //  3128: istore_2       
        //  3129: iload_3        
        //  3130: istore          5
        //  3132: iload           5
        //  3134: iconst_2       
        //  3135: if_icmpne       3175
        //  3138: iload_1        
        //  3139: aload_0        
        //  3140: invokevirtual   act.h:()I
        //  3143: if_icmpge       3165
        //  3146: iload_1        
        //  3147: ifle            3165
        //  3150: aload_0        
        //  3151: iload_1        
        //  3152: invokevirtual   act.x:(I)V
        //  3155: aload_0        
        //  3156: iconst_1       
        //  3157: putfield        acu.az:Z
        //  3160: iload_1        
        //  3161: istore_3       
        //  3162: goto            3170
        //  3165: aload_0        
        //  3166: invokevirtual   act.h:()I
        //  3169: istore_3       
        //  3170: iconst_2       
        //  3171: istore_1       
        //  3172: goto            3180
        //  3175: iload_1        
        //  3176: istore_3       
        //  3177: iload           5
        //  3179: istore_1       
        //  3180: iload_2        
        //  3181: istore          6
        //  3183: iload_1        
        //  3184: istore          7
        //  3186: iconst_1       
        //  3187: istore_1       
        //  3188: iload           4
        //  3190: istore          5
        //  3192: iload_3        
        //  3193: istore_2       
        //  3194: goto            3206
        //  3197: iload_3        
        //  3198: istore          8
        //  3200: iload           4
        //  3202: istore          6
        //  3204: iconst_0       
        //  3205: istore_1       
        //  3206: aload_0        
        //  3207: bipush          64
        //  3209: invokevirtual   acu.W:(I)Z
        //  3212: ifne            3233
        //  3215: aload_0        
        //  3216: sipush          128
        //  3219: invokevirtual   acu.W:(I)Z
        //  3222: ifeq            3228
        //  3225: goto            3233
        //  3228: iconst_0       
        //  3229: istore_3       
        //  3230: goto            3235
        //  3233: iconst_1       
        //  3234: istore_3       
        //  3235: aload_0        
        //  3236: getfield        acu.d:Lacl;
        //  3239: astore          17
        //  3241: aload           17
        //  3243: iconst_0       
        //  3244: putfield        acl.f:Z
        //  3247: aload           17
        //  3249: iconst_0       
        //  3250: putfield        acl.g:Z
        //  3253: aload_0        
        //  3254: getfield        acu.ax:I
        //  3257: ifeq            3270
        //  3260: iload_3        
        //  3261: ifeq            3270
        //  3264: aload           17
        //  3266: iconst_1       
        //  3267: putfield        acl.g:Z
        //  3270: aload_0        
        //  3271: getfield        acu.aI:Ljava/util/ArrayList;
        //  3274: astore          17
        //  3276: aload_0        
        //  3277: invokevirtual   act.M:()I
        //  3280: iconst_2       
        //  3281: if_icmpeq       3301
        //  3284: aload_0        
        //  3285: invokevirtual   act.N:()I
        //  3288: iconst_2       
        //  3289: if_icmpne       3295
        //  3292: goto            3301
        //  3295: iconst_0       
        //  3296: istore          13
        //  3298: goto            3304
        //  3301: iconst_1       
        //  3302: istore          13
        //  3304: aload_0        
        //  3305: invokespecial   acu.ab:()V
        //  3308: iconst_0       
        //  3309: istore_3       
        //  3310: iload_3        
        //  3311: iload           8
        //  3313: if_icmpge       3351
        //  3316: aload_0        
        //  3317: getfield        acu.aI:Ljava/util/ArrayList;
        //  3320: iload_3        
        //  3321: invokevirtual   java/util/ArrayList.get:(I)Ljava/lang/Object;
        //  3324: checkcast       Lact;
        //  3327: astore          18
        //  3329: aload           18
        //  3331: instanceof      Lada;
        //  3334: ifeq            3345
        //  3337: aload           18
        //  3339: checkcast       Lada;
        //  3342: invokevirtual   ada.T:()V
        //  3345: iinc            3, 1
        //  3348: goto            3310
        //  3351: iconst_1       
        //  3352: istore          4
        //  3354: iconst_0       
        //  3355: istore          9
        //  3357: iload_1        
        //  3358: istore_3       
        //  3359: iload           9
        //  3361: istore_1       
        //  3362: iload           4
        //  3364: ifeq            5483
        //  3367: iinc            1, 1
        //  3370: iload_1        
        //  3371: istore          4
        //  3373: aload_0        
        //  3374: getfield        acu.d:Lacl;
        //  3377: invokevirtual   acl.k:()V
        //  3380: iload_1        
        //  3381: istore          4
        //  3383: aload_0        
        //  3384: invokespecial   acu.ab:()V
        //  3387: iload_1        
        //  3388: istore          4
        //  3390: aload_0        
        //  3391: aload_0        
        //  3392: getfield        acu.d:Lacl;
        //  3395: invokevirtual   act.q:(Lacl;)V
        //  3398: iconst_0       
        //  3399: istore          9
        //  3401: iload           9
        //  3403: iload           8
        //  3405: if_icmpge       3436
        //  3408: iload_1        
        //  3409: istore          4
        //  3411: aload_0        
        //  3412: getfield        acu.aI:Ljava/util/ArrayList;
        //  3415: iload           9
        //  3417: invokevirtual   java/util/ArrayList.get:(I)Ljava/lang/Object;
        //  3420: checkcast       Lact;
        //  3423: aload_0        
        //  3424: getfield        acu.d:Lacl;
        //  3427: invokevirtual   act.q:(Lacl;)V
        //  3430: iinc            9, 1
        //  3433: goto            3401
        //  3436: iload_1        
        //  3437: istore          4
        //  3439: aload_0        
        //  3440: getfield        acu.d:Lacl;
        //  3443: astore          20
        //  3445: iload_1        
        //  3446: istore          4
        //  3448: aload_0        
        //  3449: bipush          64
        //  3451: invokevirtual   acu.W:(I)Z
        //  3454: istore          15
        //  3456: iload_1        
        //  3457: istore          4
        //  3459: aload_0        
        //  3460: aload           20
        //  3462: iload           15
        //  3464: invokevirtual   act.b:(Lacl;Z)V
        //  3467: iload_1        
        //  3468: istore          4
        //  3470: aload_0        
        //  3471: getfield        acu.aI:Ljava/util/ArrayList;
        //  3474: invokevirtual   java/util/ArrayList.size:()I
        //  3477: istore          12
        //  3479: iconst_0       
        //  3480: istore          11
        //  3482: iconst_0       
        //  3483: istore          10
        //  3485: iload           11
        //  3487: iload           12
        //  3489: if_icmpge       3562
        //  3492: iload_1        
        //  3493: istore          4
        //  3495: aload_0        
        //  3496: getfield        acu.aI:Ljava/util/ArrayList;
        //  3499: iload           11
        //  3501: invokevirtual   java/util/ArrayList.get:(I)Ljava/lang/Object;
        //  3504: checkcast       Lact;
        //  3507: astore          19
        //  3509: iload_1        
        //  3510: istore          4
        //  3512: aload           19
        //  3514: iconst_0       
        //  3515: iconst_0       
        //  3516: invokevirtual   act.y:(IZ)V
        //  3519: iload_2        
        //  3520: istore          9
        //  3522: aload           17
        //  3524: astore          18
        //  3526: iload_1        
        //  3527: istore          4
        //  3529: aload           19
        //  3531: iconst_1       
        //  3532: iconst_0       
        //  3533: invokevirtual   act.y:(IZ)V
        //  3536: iload_2        
        //  3537: istore          9
        //  3539: aload           17
        //  3541: astore          18
        //  3543: iload_1        
        //  3544: istore          4
        //  3546: iload           10
        //  3548: aload           19
        //  3550: instanceof      Lacq;
        //  3553: ior            
        //  3554: istore          10
        //  3556: iinc            11, 1
        //  3559: goto            3485
        //  3562: iload           10
        //  3564: ifeq            3813
        //  3567: iconst_0       
        //  3568: istore          10
        //  3570: iload           10
        //  3572: iload           12
        //  3574: if_icmpge       3813
        //  3577: iload_2        
        //  3578: istore          9
        //  3580: aload           17
        //  3582: astore          18
        //  3584: iload_1        
        //  3585: istore          4
        //  3587: aload_0        
        //  3588: getfield        acu.aI:Ljava/util/ArrayList;
        //  3591: iload           10
        //  3593: invokevirtual   java/util/ArrayList.get:(I)Ljava/lang/Object;
        //  3596: checkcast       Lact;
        //  3599: astore          19
        //  3601: iload_2        
        //  3602: istore          9
        //  3604: aload           17
        //  3606: astore          18
        //  3608: iload_1        
        //  3609: istore          4
        //  3611: aload           19
        //  3613: instanceof      Lacq;
        //  3616: ifeq            3807
        //  3619: iload_2        
        //  3620: istore          9
        //  3622: aload           17
        //  3624: astore          18
        //  3626: iload_1        
        //  3627: istore          4
        //  3629: aload           19
        //  3631: checkcast       Lacq;
        //  3634: astore          19
        //  3636: iconst_0       
        //  3637: istore          11
        //  3639: iload_2        
        //  3640: istore          9
        //  3642: aload           17
        //  3644: astore          18
        //  3646: iload_1        
        //  3647: istore          4
        //  3649: iload           11
        //  3651: aload           19
        //  3653: getfield        acq.as:I
        //  3656: if_icmpge       3807
        //  3659: iload_2        
        //  3660: istore          9
        //  3662: aload           17
        //  3664: astore          18
        //  3666: iload_1        
        //  3667: istore          4
        //  3669: aload           19
        //  3671: getfield        acq.ar:[Lact;
        //  3674: iload           11
        //  3676: aaload         
        //  3677: astore          21
        //  3679: iload_2        
        //  3680: istore          9
        //  3682: aload           17
        //  3684: astore          18
        //  3686: iload_1        
        //  3687: istore          4
        //  3689: aload           19
        //  3691: getfield        acq.b:Z
        //  3694: ifne            3718
        //  3697: iload_2        
        //  3698: istore          9
        //  3700: aload           17
        //  3702: astore          18
        //  3704: iload_1        
        //  3705: istore          4
        //  3707: aload           21
        //  3709: invokevirtual   act.d:()Z
        //  3712: ifne            3718
        //  3715: goto            3801
        //  3718: iload_2        
        //  3719: istore          9
        //  3721: aload           17
        //  3723: astore          18
        //  3725: iload_1        
        //  3726: istore          4
        //  3728: aload           19
        //  3730: getfield        acq.a:I
        //  3733: istore          14
        //  3735: iload           14
        //  3737: ifeq            3784
        //  3740: iload           14
        //  3742: iconst_1       
        //  3743: if_icmpne       3749
        //  3746: goto            3784
        //  3749: iload           14
        //  3751: iconst_2       
        //  3752: if_icmpeq       3764
        //  3755: iload           14
        //  3757: iconst_3       
        //  3758: if_icmpne       3801
        //  3761: goto            3764
        //  3764: iload_2        
        //  3765: istore          9
        //  3767: aload           17
        //  3769: astore          18
        //  3771: iload_1        
        //  3772: istore          4
        //  3774: aload           21
        //  3776: iconst_1       
        //  3777: iconst_1       
        //  3778: invokevirtual   act.y:(IZ)V
        //  3781: goto            3801
        //  3784: iload_2        
        //  3785: istore          9
        //  3787: aload           17
        //  3789: astore          18
        //  3791: iload_1        
        //  3792: istore          4
        //  3794: aload           21
        //  3796: iconst_0       
        //  3797: iconst_1       
        //  3798: invokevirtual   act.y:(IZ)V
        //  3801: iinc            11, 1
        //  3804: goto            3639
        //  3807: iinc            10, 1
        //  3810: goto            3570
        //  3813: iload_2        
        //  3814: istore          9
        //  3816: aload           17
        //  3818: astore          18
        //  3820: iload_1        
        //  3821: istore          4
        //  3823: aload_0        
        //  3824: getfield        acu.aE:Ljava/util/HashSet;
        //  3827: invokevirtual   java/util/HashSet.clear:()V
        //  3830: iconst_0       
        //  3831: istore          4
        //  3833: iload           4
        //  3835: iload           12
        //  3837: if_icmplt       4799
        //  3840: iload_2        
        //  3841: istore          9
        //  3843: aload           17
        //  3845: astore          18
        //  3847: iload_1        
        //  3848: istore          4
        //  3850: aload_0        
        //  3851: getfield        acu.aE:Ljava/util/HashSet;
        //  3854: invokevirtual   java/util/HashSet.size:()I
        //  3857: ifle            4170
        //  3860: iload_2        
        //  3861: istore          9
        //  3863: aload           17
        //  3865: astore          18
        //  3867: iload_1        
        //  3868: istore          4
        //  3870: aload_0        
        //  3871: getfield        acu.aE:Ljava/util/HashSet;
        //  3874: invokevirtual   java/util/HashSet.size:()I
        //  3877: istore          11
        //  3879: iload_2        
        //  3880: istore          9
        //  3882: aload           17
        //  3884: astore          18
        //  3886: iload_1        
        //  3887: istore          4
        //  3889: aload_0        
        //  3890: getfield        acu.aE:Ljava/util/HashSet;
        //  3893: invokevirtual   java/util/HashSet.iterator:()Ljava/util/Iterator;
        //  3896: astore          19
        //  3898: iload_2        
        //  3899: istore          9
        //  3901: aload           17
        //  3903: astore          18
        //  3905: iload_1        
        //  3906: istore          4
        //  3908: aload           19
        //  3910: invokeinterface java/util/Iterator.hasNext:()Z
        //  3915: ifeq            4059
        //  3918: iload_2        
        //  3919: istore          9
        //  3921: aload           17
        //  3923: astore          18
        //  3925: iload_1        
        //  3926: istore          4
        //  3928: aload           19
        //  3930: invokeinterface java/util/Iterator.next:()Ljava/lang/Object;
        //  3935: checkcast       Lact;
        //  3938: checkcast       Lacz;
        //  3941: astore          22
        //  3943: iload_2        
        //  3944: istore          9
        //  3946: aload           17
        //  3948: astore          18
        //  3950: iload_1        
        //  3951: istore          4
        //  3953: aload_0        
        //  3954: getfield        acu.aE:Ljava/util/HashSet;
        //  3957: astore          21
        //  3959: iconst_0       
        //  3960: istore          10
        //  3962: iload_2        
        //  3963: istore          9
        //  3965: aload           17
        //  3967: astore          18
        //  3969: iload_1        
        //  3970: istore          4
        //  3972: iload           10
        //  3974: aload           22
        //  3976: getfield        acz.as:I
        //  3979: if_icmpge       4056
        //  3982: iload_2        
        //  3983: istore          9
        //  3985: aload           17
        //  3987: astore          18
        //  3989: iload_1        
        //  3990: istore          4
        //  3992: aload           21
        //  3994: aload           22
        //  3996: getfield        acz.ar:[Lact;
        //  3999: iload           10
        //  4001: aaload         
        //  4002: invokevirtual   java/util/HashSet.contains:(Ljava/lang/Object;)Z
        //  4005: ifeq            4050
        //  4008: iload_2        
        //  4009: istore          9
        //  4011: aload           17
        //  4013: astore          18
        //  4015: iload_1        
        //  4016: istore          4
        //  4018: aload           22
        //  4020: aload           20
        //  4022: iload           15
        //  4024: invokevirtual   act.b:(Lacl;Z)V
        //  4027: iload_2        
        //  4028: istore          9
        //  4030: aload           17
        //  4032: astore          18
        //  4034: iload_1        
        //  4035: istore          4
        //  4037: aload_0        
        //  4038: getfield        acu.aE:Ljava/util/HashSet;
        //  4041: aload           22
        //  4043: invokevirtual   java/util/HashSet.remove:(Ljava/lang/Object;)Z
        //  4046: pop            
        //  4047: goto            4059
        //  4050: iinc            10, 1
        //  4053: goto            3962
        //  4056: goto            3898
        //  4059: iload_2        
        //  4060: istore          9
        //  4062: aload           17
        //  4064: astore          18
        //  4066: iload_1        
        //  4067: istore          4
        //  4069: iload           11
        //  4071: aload_0        
        //  4072: getfield        acu.aE:Ljava/util/HashSet;
        //  4075: invokevirtual   java/util/HashSet.size:()I
        //  4078: if_icmpne       3840
        //  4081: iload_2        
        //  4082: istore          9
        //  4084: aload           17
        //  4086: astore          18
        //  4088: iload_1        
        //  4089: istore          4
        //  4091: aload_0        
        //  4092: getfield        acu.aE:Ljava/util/HashSet;
        //  4095: invokevirtual   java/util/HashSet.iterator:()Ljava/util/Iterator;
        //  4098: astore          19
        //  4100: iload_2        
        //  4101: istore          9
        //  4103: aload           17
        //  4105: astore          18
        //  4107: iload_1        
        //  4108: istore          4
        //  4110: aload           19
        //  4112: invokeinterface java/util/Iterator.hasNext:()Z
        //  4117: ifeq            4150
        //  4120: iload_2        
        //  4121: istore          9
        //  4123: aload           17
        //  4125: astore          18
        //  4127: iload_1        
        //  4128: istore          4
        //  4130: aload           19
        //  4132: invokeinterface java/util/Iterator.next:()Ljava/lang/Object;
        //  4137: checkcast       Lact;
        //  4140: aload           20
        //  4142: iload           15
        //  4144: invokevirtual   act.b:(Lacl;Z)V
        //  4147: goto            4100
        //  4150: iload_2        
        //  4151: istore          9
        //  4153: aload           17
        //  4155: astore          18
        //  4157: iload_1        
        //  4158: istore          4
        //  4160: aload_0        
        //  4161: getfield        acu.aE:Ljava/util/HashSet;
        //  4164: invokevirtual   java/util/HashSet.clear:()V
        //  4167: goto            3840
        //  4170: iload_2        
        //  4171: istore          9
        //  4173: aload           17
        //  4175: astore          18
        //  4177: iload_1        
        //  4178: istore          4
        //  4180: getstatic       acl.a:Z
        //  4183: istore          16
        //  4185: iload           16
        //  4187: ifeq            4363
        //  4190: new             Ljava/util/HashSet;
        //  4193: astore          19
        //  4195: aload           19
        //  4197: invokespecial   java/util/HashSet.<init>:()V
        //  4200: iconst_0       
        //  4201: istore          10
        //  4203: iload           10
        //  4205: iload           12
        //  4207: if_icmpge       4276
        //  4210: iload_2        
        //  4211: istore          9
        //  4213: aload           17
        //  4215: astore          18
        //  4217: iload_1        
        //  4218: istore          4
        //  4220: aload_0        
        //  4221: getfield        acu.aI:Ljava/util/ArrayList;
        //  4224: iload           10
        //  4226: invokevirtual   java/util/ArrayList.get:(I)Ljava/lang/Object;
        //  4229: checkcast       Lact;
        //  4232: astore          21
        //  4234: iload_2        
        //  4235: istore          9
        //  4237: aload           17
        //  4239: astore          18
        //  4241: iload_1        
        //  4242: istore          4
        //  4244: aload           21
        //  4246: invokevirtual   act.E:()Z
        //  4249: ifne            4270
        //  4252: iload_2        
        //  4253: istore          9
        //  4255: aload           17
        //  4257: astore          18
        //  4259: iload_1        
        //  4260: istore          4
        //  4262: aload           19
        //  4264: aload           21
        //  4266: invokevirtual   java/util/HashSet.add:(Ljava/lang/Object;)Z
        //  4269: pop            
        //  4270: iinc            10, 1
        //  4273: goto            4203
        //  4276: aload_0        
        //  4277: invokevirtual   act.M:()I
        //  4280: istore          4
        //  4282: iload           4
        //  4284: iconst_2       
        //  4285: if_icmpne       4294
        //  4288: iconst_0       
        //  4289: istore          4
        //  4291: goto            4297
        //  4294: iconst_1       
        //  4295: istore          4
        //  4297: aload_0        
        //  4298: aload_0        
        //  4299: aload           20
        //  4301: aload           19
        //  4303: iload           4
        //  4305: iconst_0       
        //  4306: invokevirtual   act.p:(Lacu;Lacl;Ljava/util/HashSet;IZ)V
        //  4309: aload           19
        //  4311: invokevirtual   java/util/HashSet.iterator:()Ljava/util/Iterator;
        //  4314: astore          19
        //  4316: aload           19
        //  4318: invokeinterface java/util/Iterator.hasNext:()Z
        //  4323: ifeq            4519
        //  4326: aload           19
        //  4328: invokeinterface java/util/Iterator.next:()Ljava/lang/Object;
        //  4333: checkcast       Lact;
        //  4336: astore          18
        //  4338: aload_0        
        //  4339: aload           20
        //  4341: aload           18
        //  4343: invokestatic    acy.a:(Lacu;Lacl;Lact;)V
        //  4346: aload           18
        //  4348: aload           20
        //  4350: iload           15
        //  4352: invokevirtual   act.b:(Lacl;Z)V
        //  4355: goto            4316
        //  4358: astore          18
        //  4360: goto            4890
        //  4363: iconst_0       
        //  4364: istore          4
        //  4366: iload           4
        //  4368: iload           12
        //  4370: if_icmpge       4519
        //  4373: aload_0        
        //  4374: getfield        acu.aI:Ljava/util/ArrayList;
        //  4377: iload           4
        //  4379: invokevirtual   java/util/ArrayList.get:(I)Ljava/lang/Object;
        //  4382: checkcast       Lact;
        //  4385: astore          19
        //  4387: aload           19
        //  4389: instanceof      Lacu;
        //  4392: ifeq            4488
        //  4395: aload           19
        //  4397: getfield        act.aq:[I
        //  4400: astore          18
        //  4402: aload           18
        //  4404: iconst_0       
        //  4405: iaload         
        //  4406: istore          10
        //  4408: aload           18
        //  4410: iconst_1       
        //  4411: iaload         
        //  4412: istore          11
        //  4414: iload           10
        //  4416: istore          9
        //  4418: iload           10
        //  4420: iconst_2       
        //  4421: if_icmpne       4433
        //  4424: aload           19
        //  4426: iconst_1       
        //  4427: invokevirtual   act.P:(I)V
        //  4430: iconst_2       
        //  4431: istore          9
        //  4433: iload           11
        //  4435: istore          10
        //  4437: iload           11
        //  4439: iconst_2       
        //  4440: if_icmpne       4452
        //  4443: aload           19
        //  4445: iconst_1       
        //  4446: invokevirtual   act.Q:(I)V
        //  4449: iconst_2       
        //  4450: istore          10
        //  4452: aload           19
        //  4454: aload           20
        //  4456: iload           15
        //  4458: invokevirtual   act.b:(Lacl;Z)V
        //  4461: iload           9
        //  4463: iconst_2       
        //  4464: if_icmpne       4473
        //  4467: aload           19
        //  4469: iconst_2       
        //  4470: invokevirtual   act.P:(I)V
        //  4473: iload           10
        //  4475: iconst_2       
        //  4476: if_icmpne       4513
        //  4479: aload           19
        //  4481: iconst_2       
        //  4482: invokevirtual   act.Q:(I)V
        //  4485: goto            4513
        //  4488: aload_0        
        //  4489: aload           20
        //  4491: aload           19
        //  4493: invokestatic    acy.a:(Lacu;Lacl;Lact;)V
        //  4496: aload           19
        //  4498: invokevirtual   act.E:()Z
        //  4501: ifne            4513
        //  4504: aload           19
        //  4506: aload           20
        //  4508: iload           15
        //  4510: invokevirtual   act.b:(Lacl;Z)V
        //  4513: iinc            4, 1
        //  4516: goto            4366
        //  4519: iload_2        
        //  4520: istore          9
        //  4522: aload           17
        //  4524: astore          19
        //  4526: iload_1        
        //  4527: istore          10
        //  4529: aload_0        
        //  4530: getfield        acu.at:I
        //  4533: istore          4
        //  4535: iload           4
        //  4537: ifle            4551
        //  4540: aload_0        
        //  4541: aload           20
        //  4543: aconst_null    
        //  4544: iconst_0       
        //  4545: invokestatic    sm.c:(Lacu;Lacl;Ljava/util/ArrayList;I)V
        //  4548: goto            4551
        //  4551: aload_0        
        //  4552: getfield        acu.au:I
        //  4555: ifle            4566
        //  4558: aload_0        
        //  4559: aload           20
        //  4561: aconst_null    
        //  4562: iconst_1       
        //  4563: invokestatic    sm.c:(Lacu;Lacl;Ljava/util/ArrayList;I)V
        //  4566: aload_0        
        //  4567: getfield        acu.aA:Ljava/lang/ref/WeakReference;
        //  4570: astore          18
        //  4572: aload           18
        //  4574: ifnull          4615
        //  4577: aload           18
        //  4579: invokevirtual   java/lang/ref/WeakReference.get:()Ljava/lang/Object;
        //  4582: ifnull          4615
        //  4585: aload_0        
        //  4586: aload_0        
        //  4587: getfield        acu.aA:Ljava/lang/ref/WeakReference;
        //  4590: invokevirtual   java/lang/ref/WeakReference.get:()Ljava/lang/Object;
        //  4593: checkcast       Lacs;
        //  4596: aload_0        
        //  4597: getfield        acu.d:Lacl;
        //  4600: aload_0        
        //  4601: getfield        acu.K:Lacs;
        //  4604: invokevirtual   acl.b:(Ljava/lang/Object;)Laco;
        //  4607: invokespecial   acu.aa:(Lacs;Laco;)V
        //  4610: aload_0        
        //  4611: aconst_null    
        //  4612: putfield        acu.aA:Ljava/lang/ref/WeakReference;
        //  4615: aload_0        
        //  4616: getfield        acu.aC:Ljava/lang/ref/WeakReference;
        //  4619: astore          18
        //  4621: aload           18
        //  4623: ifnull          4664
        //  4626: aload           18
        //  4628: invokevirtual   java/lang/ref/WeakReference.get:()Ljava/lang/Object;
        //  4631: ifnull          4664
        //  4634: aload_0        
        //  4635: aload_0        
        //  4636: getfield        acu.aC:Ljava/lang/ref/WeakReference;
        //  4639: invokevirtual   java/lang/ref/WeakReference.get:()Ljava/lang/Object;
        //  4642: checkcast       Lacs;
        //  4645: aload_0        
        //  4646: getfield        acu.d:Lacl;
        //  4649: aload_0        
        //  4650: getfield        acu.M:Lacs;
        //  4653: invokevirtual   acl.b:(Ljava/lang/Object;)Laco;
        //  4656: invokespecial   acu.Z:(Lacs;Laco;)V
        //  4659: aload_0        
        //  4660: aconst_null    
        //  4661: putfield        acu.aC:Ljava/lang/ref/WeakReference;
        //  4664: aload_0        
        //  4665: getfield        acu.aB:Ljava/lang/ref/WeakReference;
        //  4668: astore          18
        //  4670: aload           18
        //  4672: ifnull          4713
        //  4675: aload           18
        //  4677: invokevirtual   java/lang/ref/WeakReference.get:()Ljava/lang/Object;
        //  4680: ifnull          4713
        //  4683: aload_0        
        //  4684: aload_0        
        //  4685: getfield        acu.aB:Ljava/lang/ref/WeakReference;
        //  4688: invokevirtual   java/lang/ref/WeakReference.get:()Ljava/lang/Object;
        //  4691: checkcast       Lacs;
        //  4694: aload_0        
        //  4695: getfield        acu.d:Lacl;
        //  4698: aload_0        
        //  4699: getfield        acu.J:Lacs;
        //  4702: invokevirtual   acl.b:(Ljava/lang/Object;)Laco;
        //  4705: invokespecial   acu.aa:(Lacs;Laco;)V
        //  4708: aload_0        
        //  4709: aconst_null    
        //  4710: putfield        acu.aB:Ljava/lang/ref/WeakReference;
        //  4713: aload_0        
        //  4714: getfield        acu.aD:Ljava/lang/ref/WeakReference;
        //  4717: astore          18
        //  4719: aload           18
        //  4721: ifnull          4765
        //  4724: aload           18
        //  4726: invokevirtual   java/lang/ref/WeakReference.get:()Ljava/lang/Object;
        //  4729: ifnull          4765
        //  4732: aload_0        
        //  4733: aload_0        
        //  4734: getfield        acu.aD:Ljava/lang/ref/WeakReference;
        //  4737: invokevirtual   java/lang/ref/WeakReference.get:()Ljava/lang/Object;
        //  4740: checkcast       Lacs;
        //  4743: aload_0        
        //  4744: getfield        acu.d:Lacl;
        //  4747: aload_0        
        //  4748: getfield        acu.L:Lacs;
        //  4751: invokevirtual   acl.b:(Ljava/lang/Object;)Laco;
        //  4754: invokespecial   acu.Z:(Lacs;Laco;)V
        //  4757: aload_0        
        //  4758: aconst_null    
        //  4759: putfield        acu.aD:Ljava/lang/ref/WeakReference;
        //  4762: goto            4765
        //  4765: aload_0        
        //  4766: getfield        acu.d:Lacl;
        //  4769: invokevirtual   acl.j:()V
        //  4772: aload           19
        //  4774: astore          17
        //  4776: goto            4918
        //  4779: astore          18
        //  4781: iload           10
        //  4783: istore_1       
        //  4784: aload           19
        //  4786: astore          17
        //  4788: iload           9
        //  4790: istore_2       
        //  4791: goto            4890
        //  4794: astore          18
        //  4796: goto            4360
        //  4799: aload_0        
        //  4800: getfield        acu.aI:Ljava/util/ArrayList;
        //  4803: iload           4
        //  4805: invokevirtual   java/util/ArrayList.get:(I)Ljava/lang/Object;
        //  4808: checkcast       Lact;
        //  4811: astore          18
        //  4813: aload           18
        //  4815: invokevirtual   act.E:()Z
        //  4818: ifeq            4851
        //  4821: aload           18
        //  4823: instanceof      Lacz;
        //  4826: ifeq            4842
        //  4829: aload_0        
        //  4830: getfield        acu.aE:Ljava/util/HashSet;
        //  4833: aload           18
        //  4835: invokevirtual   java/util/HashSet.add:(Ljava/lang/Object;)Z
        //  4838: pop            
        //  4839: goto            4851
        //  4842: aload           18
        //  4844: aload           20
        //  4846: iload           15
        //  4848: invokevirtual   act.b:(Lacl;Z)V
        //  4851: iinc            4, 1
        //  4854: goto            3833
        //  4857: astore          18
        //  4859: goto            4890
        //  4862: astore          17
        //  4864: iload           9
        //  4866: istore_2       
        //  4867: aload           18
        //  4869: astore          19
        //  4871: iload           4
        //  4873: istore_1       
        //  4874: aload           17
        //  4876: astore          18
        //  4878: aload           19
        //  4880: astore          17
        //  4882: goto            4890
        //  4885: astore          18
        //  4887: iload           4
        //  4889: istore_1       
        //  4890: aload           18
        //  4892: invokevirtual   java/lang/Exception.printStackTrace:()V
        //  4895: getstatic       java/lang/System.out:Ljava/io/PrintStream;
        //  4898: ldc_w           "EXCEPTION : "
        //  4901: aload           18
        //  4903: invokevirtual   java/lang/Object.toString:()Ljava/lang/String;
        //  4906: invokevirtual   java/lang/String.concat:(Ljava/lang/String;)Ljava/lang/String;
        //  4909: invokevirtual   java/io/PrintStream.println:(Ljava/lang/String;)V
        //  4912: iload_2        
        //  4913: istore          9
        //  4915: iload_1        
        //  4916: istore          10
        //  4918: getstatic       acy.a:[Z
        //  4921: iconst_2       
        //  4922: iconst_0       
        //  4923: bastore        
        //  4924: aload_0        
        //  4925: bipush          64
        //  4927: invokevirtual   acu.W:(I)Z
        //  4930: istore          15
        //  4932: aload_0        
        //  4933: iload           15
        //  4935: invokevirtual   act.R:(Z)V
        //  4938: aload_0        
        //  4939: getfield        acu.aI:Ljava/util/ArrayList;
        //  4942: invokevirtual   java/util/ArrayList.size:()I
        //  4945: istore          11
        //  4947: iconst_0       
        //  4948: istore_2       
        //  4949: iconst_0       
        //  4950: istore_1       
        //  4951: iload_2        
        //  4952: iload           11
        //  4954: if_icmpge       5018
        //  4957: aload_0        
        //  4958: getfield        acu.aI:Ljava/util/ArrayList;
        //  4961: iload_2        
        //  4962: invokevirtual   java/util/ArrayList.get:(I)Ljava/lang/Object;
        //  4965: checkcast       Lact;
        //  4968: astore          18
        //  4970: aload           18
        //  4972: iload           15
        //  4974: invokevirtual   act.R:(Z)V
        //  4977: aload           18
        //  4979: getfield        act.k:I
        //  4982: iconst_m1      
        //  4983: if_icmpne       5004
        //  4986: aload           18
        //  4988: getfield        act.l:I
        //  4991: iconst_m1      
        //  4992: if_icmpeq       4998
        //  4995: goto            5004
        //  4998: iconst_0       
        //  4999: istore          4
        //  5001: goto            5007
        //  5004: iconst_1       
        //  5005: istore          4
        //  5007: iload_1        
        //  5008: iload           4
        //  5010: ior            
        //  5011: istore_1       
        //  5012: iinc            2, 1
        //  5015: goto            4951
        //  5018: iload_1        
        //  5019: istore          4
        //  5021: iload_3        
        //  5022: istore_2       
        //  5023: iload           13
        //  5025: ifeq            5236
        //  5028: iload_1        
        //  5029: istore          4
        //  5031: iload_3        
        //  5032: istore_2       
        //  5033: iload           10
        //  5035: bipush          8
        //  5037: if_icmpge       5236
        //  5040: iload_1        
        //  5041: istore          4
        //  5043: iload_3        
        //  5044: istore_2       
        //  5045: getstatic       acy.a:[Z
        //  5048: iconst_2       
        //  5049: baload         
        //  5050: ifeq            5236
        //  5053: iconst_0       
        //  5054: istore          11
        //  5056: iconst_0       
        //  5057: istore          4
        //  5059: iconst_0       
        //  5060: istore_2       
        //  5061: iload           11
        //  5063: iload           8
        //  5065: if_icmpge       5122
        //  5068: aload_0        
        //  5069: getfield        acu.aI:Ljava/util/ArrayList;
        //  5072: iload           11
        //  5074: invokevirtual   java/util/ArrayList.get:(I)Ljava/lang/Object;
        //  5077: checkcast       Lact;
        //  5080: astore          18
        //  5082: iload           4
        //  5084: aload           18
        //  5086: getfield        act.Z:I
        //  5089: aload           18
        //  5091: invokevirtual   act.j:()I
        //  5094: iadd           
        //  5095: invokestatic    java/lang/Math.max:(II)I
        //  5098: istore          4
        //  5100: iload_2        
        //  5101: aload           18
        //  5103: getfield        act.aa:I
        //  5106: aload           18
        //  5108: invokevirtual   act.h:()I
        //  5111: iadd           
        //  5112: invokestatic    java/lang/Math.max:(II)I
        //  5115: istore_2       
        //  5116: iinc            11, 1
        //  5119: goto            5061
        //  5122: aload_0        
        //  5123: getfield        acu.ac:I
        //  5126: iload           4
        //  5128: invokestatic    java/lang/Math.max:(II)I
        //  5131: istore          4
        //  5133: aload_0        
        //  5134: getfield        acu.ad:I
        //  5137: iload_2        
        //  5138: invokestatic    java/lang/Math.max:(II)I
        //  5141: istore          14
        //  5143: iload_1        
        //  5144: istore          12
        //  5146: iload_3        
        //  5147: istore          11
        //  5149: iload           6
        //  5151: iconst_2       
        //  5152: if_icmpne       5189
        //  5155: iload_1        
        //  5156: istore          12
        //  5158: iload_3        
        //  5159: istore          11
        //  5161: aload_0        
        //  5162: invokevirtual   act.j:()I
        //  5165: iload           4
        //  5167: if_icmpge       5189
        //  5170: aload_0        
        //  5171: iload           4
        //  5173: invokevirtual   act.C:(I)V
        //  5176: aload_0        
        //  5177: getfield        acu.aq:[I
        //  5180: iconst_0       
        //  5181: iconst_2       
        //  5182: iastore        
        //  5183: iconst_1       
        //  5184: istore          12
        //  5186: iconst_1       
        //  5187: istore          11
        //  5189: iload           12
        //  5191: istore          4
        //  5193: iload           11
        //  5195: istore_2       
        //  5196: iload           7
        //  5198: iconst_2       
        //  5199: if_icmpne       5236
        //  5202: iload           12
        //  5204: istore          4
        //  5206: iload           11
        //  5208: istore_2       
        //  5209: aload_0        
        //  5210: invokevirtual   act.h:()I
        //  5213: iload           14
        //  5215: if_icmpge       5236
        //  5218: aload_0        
        //  5219: iload           14
        //  5221: invokevirtual   act.x:(I)V
        //  5224: aload_0        
        //  5225: getfield        acu.aq:[I
        //  5228: iconst_1       
        //  5229: iconst_2       
        //  5230: iastore        
        //  5231: iconst_1       
        //  5232: istore          4
        //  5234: iconst_1       
        //  5235: istore_2       
        //  5236: aload_0        
        //  5237: getfield        acu.ac:I
        //  5240: aload_0        
        //  5241: invokevirtual   act.j:()I
        //  5244: invokestatic    java/lang/Math.max:(II)I
        //  5247: istore_1       
        //  5248: iload_1        
        //  5249: aload_0        
        //  5250: invokevirtual   act.j:()I
        //  5253: if_icmple       5275
        //  5256: aload_0        
        //  5257: iload_1        
        //  5258: invokevirtual   act.C:(I)V
        //  5261: aload_0        
        //  5262: getfield        acu.aq:[I
        //  5265: iconst_0       
        //  5266: iconst_1       
        //  5267: iastore        
        //  5268: iconst_1       
        //  5269: istore_1       
        //  5270: iconst_1       
        //  5271: istore_2       
        //  5272: goto            5278
        //  5275: iload           4
        //  5277: istore_1       
        //  5278: aload_0        
        //  5279: getfield        acu.ad:I
        //  5282: aload_0        
        //  5283: invokevirtual   act.h:()I
        //  5286: invokestatic    java/lang/Math.max:(II)I
        //  5289: istore_3       
        //  5290: iload_3        
        //  5291: aload_0        
        //  5292: invokevirtual   act.h:()I
        //  5295: if_icmple       5317
        //  5298: aload_0        
        //  5299: iload_3        
        //  5300: invokevirtual   act.x:(I)V
        //  5303: aload_0        
        //  5304: getfield        acu.aq:[I
        //  5307: iconst_1       
        //  5308: iconst_1       
        //  5309: iastore        
        //  5310: iconst_1       
        //  5311: istore_1       
        //  5312: iconst_1       
        //  5313: istore_3       
        //  5314: goto            5319
        //  5317: iload_2        
        //  5318: istore_3       
        //  5319: iload_3        
        //  5320: ifne            5455
        //  5323: aload_0        
        //  5324: getfield        acu.aq:[I
        //  5327: astore          18
        //  5329: iload_1        
        //  5330: istore          4
        //  5332: iload_3        
        //  5333: istore_2       
        //  5334: aload           18
        //  5336: iconst_0       
        //  5337: iaload         
        //  5338: iconst_2       
        //  5339: if_icmpne       5387
        //  5342: iload_1        
        //  5343: istore          4
        //  5345: iload_3        
        //  5346: istore_2       
        //  5347: iload           5
        //  5349: ifle            5387
        //  5352: iload_1        
        //  5353: istore          4
        //  5355: iload_3        
        //  5356: istore_2       
        //  5357: aload_0        
        //  5358: invokevirtual   act.j:()I
        //  5361: iload           5
        //  5363: if_icmple       5387
        //  5366: aload_0        
        //  5367: iconst_1       
        //  5368: putfield        acu.ay:Z
        //  5371: aload           18
        //  5373: iconst_0       
        //  5374: iconst_1       
        //  5375: iastore        
        //  5376: aload_0        
        //  5377: iload           5
        //  5379: invokevirtual   act.C:(I)V
        //  5382: iconst_1       
        //  5383: istore          4
        //  5385: iconst_1       
        //  5386: istore_2       
        //  5387: aload_0        
        //  5388: getfield        acu.aq:[I
        //  5391: astore          18
        //  5393: aload           18
        //  5395: iconst_1       
        //  5396: iaload         
        //  5397: iconst_2       
        //  5398: if_icmpne       5447
        //  5401: iload           9
        //  5403: ifle            5447
        //  5406: aload_0        
        //  5407: invokevirtual   act.h:()I
        //  5410: istore          11
        //  5412: iload           4
        //  5414: istore_1       
        //  5415: iload_2        
        //  5416: istore_3       
        //  5417: iload           11
        //  5419: iload           9
        //  5421: if_icmple       5455
        //  5424: aload_0        
        //  5425: iconst_1       
        //  5426: putfield        acu.az:Z
        //  5429: aload           18
        //  5431: iconst_1       
        //  5432: iconst_1       
        //  5433: iastore        
        //  5434: aload_0        
        //  5435: iload           9
        //  5437: invokevirtual   act.x:(I)V
        //  5440: iconst_1       
        //  5441: istore_1       
        //  5442: iconst_1       
        //  5443: istore_3       
        //  5444: goto            5455
        //  5447: iload           4
        //  5449: istore_1       
        //  5450: iload_2        
        //  5451: istore_3       
        //  5452: goto            5455
        //  5455: iload           10
        //  5457: bipush          8
        //  5459: if_icmple       5467
        //  5462: iconst_0       
        //  5463: istore_2       
        //  5464: goto            5469
        //  5467: iconst_1       
        //  5468: istore_2       
        //  5469: iload_2        
        //  5470: iload_1        
        //  5471: iand           
        //  5472: istore          4
        //  5474: iload           10
        //  5476: istore_1       
        //  5477: iload           9
        //  5479: istore_2       
        //  5480: goto            3362
        //  5483: aload_0        
        //  5484: aload           17
        //  5486: putfield        acu.aI:Ljava/util/ArrayList;
        //  5489: iload_3        
        //  5490: ifeq            5511
        //  5493: aload_0        
        //  5494: getfield        acu.aq:[I
        //  5497: astore          17
        //  5499: aload           17
        //  5501: iconst_0       
        //  5502: iload           6
        //  5504: iastore        
        //  5505: aload           17
        //  5507: iconst_1       
        //  5508: iload           7
        //  5510: iastore        
        //  5511: aload_0        
        //  5512: aload_0        
        //  5513: getfield        acu.d:Lacl;
        //  5516: getfield        acl.j:Lcdr;
        //  5519: invokevirtual   act.S:(Lcdr;)V
        //  5522: return         
        //    Exceptions:
        //  Try           Handler
        //  Start  End    Start  End    Type                 
        //  -----  -----  -----  -----  ---------------------
        //  3373   3380   4885   4890   Ljava/lang/Exception;
        //  3383   3387   4885   4890   Ljava/lang/Exception;
        //  3390   3398   4885   4890   Ljava/lang/Exception;
        //  3411   3430   4885   4890   Ljava/lang/Exception;
        //  3439   3445   4885   4890   Ljava/lang/Exception;
        //  3448   3456   4885   4890   Ljava/lang/Exception;
        //  3459   3467   4885   4890   Ljava/lang/Exception;
        //  3470   3479   4885   4890   Ljava/lang/Exception;
        //  3495   3509   4885   4890   Ljava/lang/Exception;
        //  3512   3519   4885   4890   Ljava/lang/Exception;
        //  3529   3536   4862   4885   Ljava/lang/Exception;
        //  3546   3556   4862   4885   Ljava/lang/Exception;
        //  3587   3601   4862   4885   Ljava/lang/Exception;
        //  3611   3619   4862   4885   Ljava/lang/Exception;
        //  3629   3636   4862   4885   Ljava/lang/Exception;
        //  3649   3659   4862   4885   Ljava/lang/Exception;
        //  3669   3679   4862   4885   Ljava/lang/Exception;
        //  3689   3697   4862   4885   Ljava/lang/Exception;
        //  3707   3715   4862   4885   Ljava/lang/Exception;
        //  3728   3735   4862   4885   Ljava/lang/Exception;
        //  3774   3781   4862   4885   Ljava/lang/Exception;
        //  3794   3801   4862   4885   Ljava/lang/Exception;
        //  3823   3830   4862   4885   Ljava/lang/Exception;
        //  3850   3860   4862   4885   Ljava/lang/Exception;
        //  3870   3879   4862   4885   Ljava/lang/Exception;
        //  3889   3898   4862   4885   Ljava/lang/Exception;
        //  3908   3918   4862   4885   Ljava/lang/Exception;
        //  3928   3943   4862   4885   Ljava/lang/Exception;
        //  3953   3959   4862   4885   Ljava/lang/Exception;
        //  3972   3982   4862   4885   Ljava/lang/Exception;
        //  3992   4008   4862   4885   Ljava/lang/Exception;
        //  4018   4027   4862   4885   Ljava/lang/Exception;
        //  4037   4047   4862   4885   Ljava/lang/Exception;
        //  4069   4081   4862   4885   Ljava/lang/Exception;
        //  4091   4100   4862   4885   Ljava/lang/Exception;
        //  4110   4120   4862   4885   Ljava/lang/Exception;
        //  4130   4147   4862   4885   Ljava/lang/Exception;
        //  4160   4167   4862   4885   Ljava/lang/Exception;
        //  4180   4185   4862   4885   Ljava/lang/Exception;
        //  4190   4200   4358   4360   Ljava/lang/Exception;
        //  4220   4234   4862   4885   Ljava/lang/Exception;
        //  4244   4252   4862   4885   Ljava/lang/Exception;
        //  4262   4270   4862   4885   Ljava/lang/Exception;
        //  4276   4282   4358   4360   Ljava/lang/Exception;
        //  4297   4316   4794   4799   Ljava/lang/Exception;
        //  4316   4355   4794   4799   Ljava/lang/Exception;
        //  4373   4402   4794   4799   Ljava/lang/Exception;
        //  4424   4430   4794   4799   Ljava/lang/Exception;
        //  4443   4449   4794   4799   Ljava/lang/Exception;
        //  4452   4461   4794   4799   Ljava/lang/Exception;
        //  4467   4473   4794   4799   Ljava/lang/Exception;
        //  4479   4485   4794   4799   Ljava/lang/Exception;
        //  4488   4513   4794   4799   Ljava/lang/Exception;
        //  4529   4535   4794   4799   Ljava/lang/Exception;
        //  4540   4548   4779   4794   Ljava/lang/Exception;
        //  4551   4566   4779   4794   Ljava/lang/Exception;
        //  4566   4572   4794   4799   Ljava/lang/Exception;
        //  4577   4610   4794   4799   Ljava/lang/Exception;
        //  4610   4615   4779   4794   Ljava/lang/Exception;
        //  4615   4621   4794   4799   Ljava/lang/Exception;
        //  4626   4659   4794   4799   Ljava/lang/Exception;
        //  4659   4664   4779   4794   Ljava/lang/Exception;
        //  4664   4670   4794   4799   Ljava/lang/Exception;
        //  4675   4708   4794   4799   Ljava/lang/Exception;
        //  4708   4713   4779   4794   Ljava/lang/Exception;
        //  4713   4719   4794   4799   Ljava/lang/Exception;
        //  4724   4757   4794   4799   Ljava/lang/Exception;
        //  4757   4762   4857   4862   Ljava/lang/Exception;
        //  4765   4772   4857   4862   Ljava/lang/Exception;
        //  4799   4839   4857   4862   Ljava/lang/Exception;
        //  4842   4851   4857   4862   Ljava/lang/Exception;
        // 
        // The error that occurred was:
        // 
        // java.lang.IllegalStateException: Expression is linked from several locations: Label_4297:
        //     at com.strobel.decompiler.ast.Error.expressionLinkedFromMultipleLocations(Error.java:27)
        //     at com.strobel.decompiler.ast.AstOptimizer.mergeDisparateObjectInitializations(AstOptimizer.java:2604)
        //     at com.strobel.decompiler.ast.AstOptimizer.optimize(AstOptimizer.java:235)
        //     at com.strobel.decompiler.ast.AstOptimizer.optimize(AstOptimizer.java:42)
        //     at com.strobel.decompiler.languages.java.ast.AstMethodBodyBuilder.createMethodBody(AstMethodBodyBuilder.java:206)
        //     at com.strobel.decompiler.languages.java.ast.AstMethodBodyBuilder.createMethodBody(AstMethodBodyBuilder.java:93)
        //     at com.strobel.decompiler.languages.java.ast.AstBuilder.createMethodBody(AstBuilder.java:868)
        //     at com.strobel.decompiler.languages.java.ast.AstBuilder.createMethod(AstBuilder.java:761)
        //     at com.strobel.decompiler.languages.java.ast.AstBuilder.addTypeMembers(AstBuilder.java:638)
        //     at com.strobel.decompiler.languages.java.ast.AstBuilder.createTypeCore(AstBuilder.java:605)
        //     at com.strobel.decompiler.languages.java.ast.AstBuilder.createTypeNoCache(AstBuilder.java:195)
        //     at com.strobel.decompiler.languages.java.ast.AstBuilder.createType(AstBuilder.java:162)
        //     at com.strobel.decompiler.languages.java.ast.AstBuilder.addType(AstBuilder.java:137)
        //     at com.strobel.decompiler.languages.java.JavaLanguage.buildAst(JavaLanguage.java:71)
        //     at com.strobel.decompiler.languages.java.JavaLanguage.decompileType(JavaLanguage.java:59)
        //     at com.strobel.decompiler.DecompilerDriver.decompileType(DecompilerDriver.java:333)
        //     at com.strobel.decompiler.DecompilerDriver.decompileJar(DecompilerDriver.java:254)
        //     at com.strobel.decompiler.DecompilerDriver.main(DecompilerDriver.java:129)
        // 
        throw new IllegalStateException("An error occurred while decompiling this method.");
    }
    
    public final void U(final int ax) {
        this.ax = ax;
        acl.a = this.W(512);
    }
    
    public final boolean V(final boolean b, final int n) {
        final ade a = this.a;
        final acu a2 = a.a;
        final boolean b2 = false;
        final int l = a2.L(0);
        final int i = a.a.L(1);
        final acu a3 = a.a;
        final int k = a3.k();
        final int j = a3.l();
        int n2 = i;
        Label_0307: {
            if (b) {
                int n3 = i;
                if (l != 2) {
                    if ((n2 = i) != 2) {
                        break Label_0307;
                    }
                    n3 = 2;
                }
                final ArrayList e = a.e;
                final int size = e.size();
                int n4 = 0;
                while (true) {
                    while (n4 < size) {
                        final ado ado = (ado)e.get(n4);
                        if (ado.g == n && !ado.e()) {
                            final boolean b3 = false;
                            if (n == 0) {
                                n2 = n3;
                                if (!b3) {
                                    break Label_0307;
                                }
                                n2 = n3;
                                if (l == 2) {
                                    a.a.P(1);
                                    final acu a4 = a.a;
                                    a4.C(a.a(a4, 0));
                                    final acu a5 = a.a;
                                    a5.h.f.c(a5.j());
                                    n2 = n3;
                                }
                                break Label_0307;
                            }
                            else {
                                n2 = n3;
                                if (b3 && (n2 = n3) == 2) {
                                    a.a.Q(1);
                                    final acu a6 = a.a;
                                    a6.x(a.a(a6, 1));
                                    final acu a7 = a.a;
                                    a7.i.f.c(a7.h());
                                    n2 = n3;
                                }
                                break Label_0307;
                            }
                        }
                        else {
                            ++n4;
                        }
                    }
                    final boolean b3 = true;
                    continue;
                }
            }
        }
        boolean b4 = false;
        Label_0452: {
            Label_0450: {
                if (n == 0) {
                    final acu a8 = a.a;
                    final int n5 = a8.aq[0];
                    if (n5 == 1 || n5 == 4) {
                        final int n6 = a8.j() + k;
                        a8.h.j.c(n6);
                        a.a.h.f.c(n6 - k);
                        break Label_0450;
                    }
                }
                else {
                    final acu a9 = a.a;
                    final int n7 = a9.aq[1];
                    if (n7 == 1 || n7 == 4) {
                        final int n8 = a9.h() + j;
                        a9.i.j.c(n8);
                        a.a.i.f.c(n8 - j);
                        break Label_0450;
                    }
                }
                b4 = false;
                break Label_0452;
            }
            b4 = true;
        }
        a.c();
        final ArrayList e2 = a.e;
        for (int size2 = e2.size(), n9 = 0; n9 < size2; ++n9) {
            final ado ado2 = (ado)e2.get(n9);
            if (ado2.g == n) {
                if (ado2.d != a.a || ado2.h) {
                    ado2.c();
                }
            }
        }
        final ArrayList e3 = a.e;
        while (true) {
            for (int size3 = e3.size(), n10 = 0; n10 < size3; ++n10) {
                final ado ado3 = (ado)e3.get(n10);
                if (ado3.g == n) {
                    if (b4 || ado3.d != a.a) {
                        boolean b5;
                        if (!ado3.i.i) {
                            b5 = b2;
                        }
                        else if (!ado3.j.i) {
                            b5 = b2;
                        }
                        else {
                            if (ado3 instanceof adc || ado3.f.i) {
                                continue;
                            }
                            b5 = b2;
                        }
                        a.a.P(l);
                        a.a.Q(n2);
                        return b5;
                    }
                }
            }
            boolean b5 = true;
            continue;
        }
    }
    
    public final boolean W(final int n) {
        return (this.ax & n) == n;
    }
    
    final void a(final act act, int n) {
        if (n == 0) {
            n = this.at;
            final acr[] aw = this.aw;
            final int length = aw.length;
            if (n + 1 >= length) {
                this.aw = Arrays.copyOf(aw, length + length);
            }
            final acr[] aw2 = this.aw;
            n = this.at;
            aw2[n] = new acr(act, 0, this.c);
            this.at = n + 1;
            return;
        }
        n = this.au;
        final acr[] av = this.av;
        final int length2 = av.length;
        if (n + 1 >= length2) {
            this.av = Arrays.copyOf(av, length2 + length2);
        }
        final acr[] av2 = this.av;
        n = this.au;
        av2[n] = new acr(act, 1, this.c);
        this.au = n + 1;
    }
    
    public final void c() {
        this.a.b = true;
    }
    
    @Override
    public final void s() {
        this.d.k();
        this.ar = 0;
        this.as = 0;
        super.s();
    }
}
