import org.webrtc.VideoFrame$I420Buffer;
import org.chromium.net.impl.VersionSafeCallbacks$UrlRequestStatusListener;
import org.chromium.net.impl.CronetUrlRequestContext;
import org.chromium.net.impl.CronetUrlRequest;
import java.util.concurrent.CountDownLatch;
import java.nio.ByteBuffer;

// 
// Decompiled by Procyon v0.6.0
// 

public final class audk implements Runnable
{
    final Object a;
    private final int b;
    
    public audk(final asfa a, final int b, final byte[] array) {
        this.b = b;
        this.a = a;
    }
    
    public audk(final auea a, final int b) {
        this.b = b;
        this.a = a;
    }
    
    public audk(final aueb a, final int b) {
        this.b = b;
        this.a = a;
    }
    
    public audk(final aukx a, final int b) {
        this.b = b;
        this.a = a;
    }
    
    public audk(final aukx a, final int b, final byte[] array) {
        this.b = b;
        this.a = a;
    }
    
    public audk(final aukx a, final int b, final char[] array) {
        this.b = b;
        this.a = a;
    }
    
    public audk(final aulx a, final int b) {
        this.b = b;
        this.a = a;
    }
    
    public audk(final ByteBuffer a, final int b) {
        this.b = b;
        this.a = a;
    }
    
    public audk(final CountDownLatch a, final int b) {
        this.b = b;
        this.a = a;
    }
    
    public audk(final CronetUrlRequest a, final int b) {
        this.b = b;
        this.a = a;
    }
    
    public audk(final CronetUrlRequestContext a, final int b) {
        this.b = b;
        this.a = a;
    }
    
    public audk(final VersionSafeCallbacks$UrlRequestStatusListener a, final int b) {
        this.b = b;
        this.a = a;
    }
    
    public audk(final VideoFrame$I420Buffer a, final int b) {
        this.b = b;
        this.a = a;
    }
    
    @Override
    public final void run() {
        // 
        // This method could not be decompiled.
        // 
        // Original Bytecode:
        // 
        //     1: getfield        audk.b:I
        //     4: tableswitch {
        //                0: 2769
        //                1: 2757
        //                2: 2628
        //                3: 2555
        //                4: 2470
        //                5: 2421
        //                6: 2348
        //                7: 2302
        //                8: 2266
        //                9: 2235
        //               10: 2187
        //               11: 1937
        //               12: 683
        //               13: 250
        //               14: 212
        //               15: 202
        //               16: 191
        //               17: 180
        //               18: 151
        //               19: 129
        //          default: 100
        //        }
        //   100: aload_0        
        //   101: getfield        audk.a:Ljava/lang/Object;
        //   104: checkcast       Laulx;
        //   107: astore          16
        //   109: aload           16
        //   111: iconst_0       
        //   112: putfield        aulx.e:Z
        //   115: aload           16
        //   117: getfield        aulx.f:Z
        //   120: ifeq            2888
        //   123: aload           16
        //   125: invokevirtual   aulx.a:()V
        //   128: return         
        //   129: aload_0        
        //   130: getfield        audk.a:Ljava/lang/Object;
        //   133: checkcast       Laulx;
        //   136: astore          16
        //   138: aload           16
        //   140: aconst_null    
        //   141: putfield        aulx.c:Lorg/webrtc/VideoSink;
        //   144: aload           16
        //   146: aconst_null    
        //   147: putfield        aulx.j:Lorg/webrtc/VideoSink;
        //   150: return         
        //   151: aload_0        
        //   152: getfield        audk.a:Ljava/lang/Object;
        //   155: checkcast       Laulx;
        //   158: astore          16
        //   160: aload           16
        //   162: iconst_1       
        //   163: putfield        aulx.f:Z
        //   166: aload           16
        //   168: getfield        aulx.e:Z
        //   171: ifne            179
        //   174: aload           16
        //   176: invokevirtual   aulx.a:()V
        //   179: return         
        //   180: aload_0        
        //   181: getfield        audk.a:Ljava/lang/Object;
        //   184: checkcast       Ljava/util/concurrent/CountDownLatch;
        //   187: invokevirtual   java/util/concurrent/CountDownLatch.countDown:()V
        //   190: return         
        //   191: aload_0        
        //   192: getfield        audk.a:Ljava/lang/Object;
        //   195: checkcast       Ljava/nio/ByteBuffer;
        //   198: invokestatic    org/webrtc/JniCommon.nativeFreeByteBuffer:(Ljava/nio/ByteBuffer;)V
        //   201: return         
        //   202: aload_0        
        //   203: getfield        audk.a:Ljava/lang/Object;
        //   206: invokeinterface org/webrtc/VideoFrame$Buffer.release:()V
        //   211: return         
        //   212: aload_0        
        //   213: getfield        audk.a:Ljava/lang/Object;
        //   216: checkcast       Laukx;
        //   219: getfield        aukx.b:Ljava/lang/Object;
        //   222: astore          17
        //   224: aload           17
        //   226: monitorenter   
        //   227: aload_0        
        //   228: getfield        audk.a:Ljava/lang/Object;
        //   231: checkcast       Laukx;
        //   234: aconst_null    
        //   235: putfield        aukx.c:Landroid/os/Handler;
        //   238: aload           17
        //   240: monitorexit    
        //   241: return         
        //   242: astore          16
        //   244: aload           17
        //   246: monitorexit    
        //   247: aload           16
        //   249: athrow         
        //   250: aload_0        
        //   251: getfield        audk.a:Ljava/lang/Object;
        //   254: astore          17
        //   256: new             Ljava/text/DecimalFormat;
        //   259: dup            
        //   260: ldc             "#.0"
        //   262: invokespecial   java/text/DecimalFormat.<init>:(Ljava/lang/String;)V
        //   265: astore          18
        //   267: invokestatic    java/lang/System.nanoTime:()J
        //   270: lstore          7
        //   272: aload           17
        //   274: checkcast       Laukx;
        //   277: getfield        aukx.o:Ljava/lang/Object;
        //   280: astore          16
        //   282: aload           16
        //   284: monitorenter   
        //   285: lload           7
        //   287: aload           17
        //   289: checkcast       Laukx;
        //   292: getfield        aukx.s:J
        //   295: lsub           
        //   296: lstore          9
        //   298: lload           9
        //   300: lconst_0       
        //   301: lcmp           
        //   302: ifle            576
        //   305: aload           17
        //   307: checkcast       Laukx;
        //   310: getfield        aukx.r:I
        //   313: i2l            
        //   314: getstatic       java/util/concurrent/TimeUnit.SECONDS:Ljava/util/concurrent/TimeUnit;
        //   317: lconst_1       
        //   318: invokevirtual   java/util/concurrent/TimeUnit.toNanos:(J)J
        //   321: lmul           
        //   322: l2f            
        //   323: lload           9
        //   325: l2f            
        //   326: fdiv           
        //   327: fstore_1       
        //   328: getstatic       java/util/concurrent/TimeUnit.NANOSECONDS:Ljava/util/concurrent/TimeUnit;
        //   331: lload           9
        //   333: invokevirtual   java/util/concurrent/TimeUnit.toMillis:(J)J
        //   336: lstore          9
        //   338: aload           17
        //   340: checkcast       Laukx;
        //   343: getfield        aukx.p:I
        //   346: istore          4
        //   348: aload           17
        //   350: checkcast       Laukx;
        //   353: getfield        aukx.q:I
        //   356: istore          5
        //   358: aload           17
        //   360: checkcast       Laukx;
        //   363: getfield        aukx.r:I
        //   366: istore          6
        //   368: aload           18
        //   370: fload_1        
        //   371: f2d            
        //   372: invokevirtual   java/text/DecimalFormat.format:(D)Ljava/lang/String;
        //   375: astore          19
        //   377: aload           17
        //   379: checkcast       Laukx;
        //   382: getfield        aukx.t:J
        //   385: aload           17
        //   387: checkcast       Laukx;
        //   390: getfield        aukx.r:I
        //   393: invokestatic    aukx.c:(JI)Ljava/lang/String;
        //   396: astore          20
        //   398: aload           17
        //   400: checkcast       Laukx;
        //   403: getfield        aukx.u:J
        //   406: aload           17
        //   408: checkcast       Laukx;
        //   411: getfield        aukx.r:I
        //   414: invokestatic    aukx.c:(JI)Ljava/lang/String;
        //   417: astore          21
        //   419: new             Ljava/lang/StringBuilder;
        //   422: astore          18
        //   424: aload           18
        //   426: ldc             "Duration: "
        //   428: invokespecial   java/lang/StringBuilder.<init>:(Ljava/lang/String;)V
        //   431: aload           18
        //   433: lload           9
        //   435: invokevirtual   java/lang/StringBuilder.append:(J)Ljava/lang/StringBuilder;
        //   438: pop            
        //   439: aload           18
        //   441: ldc             " ms. Frames received: "
        //   443: invokevirtual   java/lang/StringBuilder.append:(Ljava/lang/String;)Ljava/lang/StringBuilder;
        //   446: pop            
        //   447: aload           18
        //   449: iload           4
        //   451: invokevirtual   java/lang/StringBuilder.append:(I)Ljava/lang/StringBuilder;
        //   454: pop            
        //   455: aload           18
        //   457: ldc             ". Dropped: "
        //   459: invokevirtual   java/lang/StringBuilder.append:(Ljava/lang/String;)Ljava/lang/StringBuilder;
        //   462: pop            
        //   463: aload           18
        //   465: iload           5
        //   467: invokevirtual   java/lang/StringBuilder.append:(I)Ljava/lang/StringBuilder;
        //   470: pop            
        //   471: aload           18
        //   473: ldc             ". Rendered: "
        //   475: invokevirtual   java/lang/StringBuilder.append:(Ljava/lang/String;)Ljava/lang/StringBuilder;
        //   478: pop            
        //   479: aload           18
        //   481: iload           6
        //   483: invokevirtual   java/lang/StringBuilder.append:(I)Ljava/lang/StringBuilder;
        //   486: pop            
        //   487: aload           18
        //   489: ldc             ". Render fps: "
        //   491: invokevirtual   java/lang/StringBuilder.append:(Ljava/lang/String;)Ljava/lang/StringBuilder;
        //   494: pop            
        //   495: aload           18
        //   497: aload           19
        //   499: invokevirtual   java/lang/StringBuilder.append:(Ljava/lang/String;)Ljava/lang/StringBuilder;
        //   502: pop            
        //   503: aload           18
        //   505: ldc             ". Average render time: "
        //   507: invokevirtual   java/lang/StringBuilder.append:(Ljava/lang/String;)Ljava/lang/StringBuilder;
        //   510: pop            
        //   511: aload           18
        //   513: aload           20
        //   515: invokevirtual   java/lang/StringBuilder.append:(Ljava/lang/String;)Ljava/lang/StringBuilder;
        //   518: pop            
        //   519: aload           18
        //   521: ldc             ". Average swapBuffer time: "
        //   523: invokevirtual   java/lang/StringBuilder.append:(Ljava/lang/String;)Ljava/lang/StringBuilder;
        //   526: pop            
        //   527: aload           18
        //   529: aload           21
        //   531: invokevirtual   java/lang/StringBuilder.append:(Ljava/lang/String;)Ljava/lang/StringBuilder;
        //   534: pop            
        //   535: aload           18
        //   537: ldc             "."
        //   539: invokevirtual   java/lang/StringBuilder.append:(Ljava/lang/String;)Ljava/lang/StringBuilder;
        //   542: pop            
        //   543: aload           18
        //   545: invokevirtual   java/lang/StringBuilder.toString:()Ljava/lang/String;
        //   548: astore          18
        //   550: aload           17
        //   552: checkcast       Laukx;
        //   555: aload           18
        //   557: invokevirtual   aukx.b:(Ljava/lang/String;)V
        //   560: aload           17
        //   562: checkcast       Laukx;
        //   565: lload           7
        //   567: invokevirtual   aukx.a:(J)V
        //   570: aload           16
        //   572: monitorexit    
        //   573: goto            579
        //   576: aload           16
        //   578: monitorexit    
        //   579: aload_0        
        //   580: getfield        audk.a:Ljava/lang/Object;
        //   583: checkcast       Laukx;
        //   586: getfield        aukx.b:Ljava/lang/Object;
        //   589: astore          16
        //   591: aload           16
        //   593: monitorenter   
        //   594: aload_0        
        //   595: getfield        audk.a:Ljava/lang/Object;
        //   598: astore          17
        //   600: aload           17
        //   602: checkcast       Laukx;
        //   605: getfield        aukx.c:Landroid/os/Handler;
        //   608: astore          18
        //   610: aload           18
        //   612: ifnull          663
        //   615: aload           18
        //   617: aload           17
        //   619: checkcast       Laukx;
        //   622: getfield        aukx.w:Ljava/lang/Runnable;
        //   625: invokevirtual   android/os/Handler.removeCallbacks:(Ljava/lang/Runnable;)V
        //   628: aload_0        
        //   629: getfield        audk.a:Ljava/lang/Object;
        //   632: astore          17
        //   634: aload           17
        //   636: checkcast       Laukx;
        //   639: getfield        aukx.c:Landroid/os/Handler;
        //   642: aload           17
        //   644: checkcast       Laukx;
        //   647: getfield        aukx.w:Ljava/lang/Runnable;
        //   650: getstatic       java/util/concurrent/TimeUnit.SECONDS:Ljava/util/concurrent/TimeUnit;
        //   653: ldc2_w          4
        //   656: invokevirtual   java/util/concurrent/TimeUnit.toMillis:(J)J
        //   659: invokevirtual   android/os/Handler.postDelayed:(Ljava/lang/Runnable;J)Z
        //   662: pop            
        //   663: aload           16
        //   665: monitorexit    
        //   666: return         
        //   667: astore          17
        //   669: aload           16
        //   671: monitorexit    
        //   672: aload           17
        //   674: athrow         
        //   675: astore          17
        //   677: aload           16
        //   679: monitorexit    
        //   680: aload           17
        //   682: athrow         
        //   683: aload_0        
        //   684: getfield        audk.a:Ljava/lang/Object;
        //   687: astore          19
        //   689: aload           19
        //   691: checkcast       Laukx;
        //   694: astore          17
        //   696: aload           17
        //   698: getfield        aukx.k:Ljava/lang/Object;
        //   701: astore          18
        //   703: aload           18
        //   705: monitorenter   
        //   706: aload           19
        //   708: checkcast       Laukx;
        //   711: getfield        aukx.l:Lorg/webrtc/VideoFrame;
        //   714: astore          16
        //   716: aload           16
        //   718: ifnonnull       725
        //   721: aload           18
        //   723: monitorexit    
        //   724: return         
        //   725: aload           19
        //   727: checkcast       Laukx;
        //   730: aconst_null    
        //   731: putfield        aukx.l:Lorg/webrtc/VideoFrame;
        //   734: aload           18
        //   736: monitorexit    
        //   737: aload           17
        //   739: getfield        aukx.g:Lauks;
        //   742: astore          18
        //   744: aload           18
        //   746: ifnull          1915
        //   749: aload           18
        //   751: invokeinterface auks.k:()Z
        //   756: ifne            762
        //   759: goto            1915
        //   762: aload           17
        //   764: getfield        aukx.f:Ljava/lang/Object;
        //   767: astore          18
        //   769: aload           18
        //   771: monitorenter   
        //   772: aload           18
        //   774: monitorexit    
        //   775: invokestatic    java/lang/System.nanoTime:()J
        //   778: lstore          13
        //   780: aload           16
        //   782: invokevirtual   org/webrtc/VideoFrame.b:()I
        //   785: i2f            
        //   786: fstore_2       
        //   787: aload           16
        //   789: invokevirtual   org/webrtc/VideoFrame.a:()I
        //   792: i2f            
        //   793: fstore_3       
        //   794: aload           17
        //   796: getfield        aukx.m:Ljava/lang/Object;
        //   799: astore          18
        //   801: aload           18
        //   803: monitorenter   
        //   804: aload           19
        //   806: checkcast       Laukx;
        //   809: getfield        aukx.n:F
        //   812: fstore_1       
        //   813: fload_2        
        //   814: fload_3        
        //   815: fdiv           
        //   816: fstore_2       
        //   817: fload_1        
        //   818: fconst_0       
        //   819: fcmpl          
        //   820: ifeq            826
        //   823: goto            828
        //   826: fload_2        
        //   827: fstore_1       
        //   828: aload           18
        //   830: monitorexit    
        //   831: fload_2        
        //   832: fload_1        
        //   833: fcmpl          
        //   834: ifle            846
        //   837: fload_1        
        //   838: fload_2        
        //   839: fdiv           
        //   840: fstore_1       
        //   841: fconst_1       
        //   842: fstore_2       
        //   843: goto            852
        //   846: fload_2        
        //   847: fload_1        
        //   848: fdiv           
        //   849: fstore_2       
        //   850: fconst_1       
        //   851: fstore_1       
        //   852: aload           17
        //   854: getfield        aukx.j:Landroid/graphics/Matrix;
        //   857: invokevirtual   android/graphics/Matrix.reset:()V
        //   860: aload           17
        //   862: getfield        aukx.j:Landroid/graphics/Matrix;
        //   865: ldc             0.5
        //   867: ldc             0.5
        //   869: invokevirtual   android/graphics/Matrix.preTranslate:(FF)Z
        //   872: pop            
        //   873: aload           17
        //   875: getfield        aukx.j:Landroid/graphics/Matrix;
        //   878: fconst_1       
        //   879: fconst_1       
        //   880: invokevirtual   android/graphics/Matrix.preScale:(FF)Z
        //   883: pop            
        //   884: aload           17
        //   886: getfield        aukx.j:Landroid/graphics/Matrix;
        //   889: fload_1        
        //   890: fload_2        
        //   891: invokevirtual   android/graphics/Matrix.preScale:(FF)Z
        //   894: pop            
        //   895: aload           17
        //   897: getfield        aukx.j:Landroid/graphics/Matrix;
        //   900: ldc             -0.5
        //   902: ldc             -0.5
        //   904: invokevirtual   android/graphics/Matrix.preTranslate:(FF)Z
        //   907: pop            
        //   908: fconst_0       
        //   909: fconst_0       
        //   910: fconst_0       
        //   911: fconst_0       
        //   912: invokestatic    android/opengl/GLES20.glClearColor:(FFFF)V
        //   915: sipush          16384
        //   918: invokestatic    android/opengl/GLES20.glClear:(I)V
        //   921: aload           19
        //   923: checkcast       Laukx;
        //   926: getfield        aukx.h:Laumi;
        //   929: aload           16
        //   931: aload           19
        //   933: checkcast       Laukx;
        //   936: getfield        aukx.i:Laulr;
        //   939: aload           19
        //   941: checkcast       Laukx;
        //   944: getfield        aukx.j:Landroid/graphics/Matrix;
        //   947: aload           19
        //   949: checkcast       Laukx;
        //   952: getfield        aukx.g:Lauks;
        //   955: invokeinterface auks.b:()I
        //   960: aload           19
        //   962: checkcast       Laukx;
        //   965: getfield        aukx.g:Lauks;
        //   968: invokeinterface auks.a:()I
        //   973: invokevirtual   aumi.b:(Lorg/webrtc/VideoFrame;Laulr;Landroid/graphics/Matrix;II)V
        //   976: invokestatic    java/lang/System.nanoTime:()J
        //   979: lstore          7
        //   981: aload           19
        //   983: checkcast       Laukx;
        //   986: getfield        aukx.g:Lauks;
        //   989: invokeinterface auks.i:()V
        //   994: invokestatic    java/lang/System.nanoTime:()J
        //   997: lstore          9
        //   999: aload           19
        //  1001: checkcast       Laukx;
        //  1004: getfield        aukx.o:Ljava/lang/Object;
        //  1007: astore          20
        //  1009: aload           20
        //  1011: monitorenter   
        //  1012: aload           19
        //  1014: checkcast       Laukx;
        //  1017: getfield        aukx.r:I
        //  1020: istore          4
        //  1022: aload           19
        //  1024: checkcast       Laukx;
        //  1027: iload           4
        //  1029: iconst_1       
        //  1030: iadd           
        //  1031: putfield        aukx.r:I
        //  1034: aload           19
        //  1036: checkcast       Laukx;
        //  1039: astore          21
        //  1041: aload           16
        //  1043: astore          17
        //  1045: aload           17
        //  1047: astore          18
        //  1049: aload           21
        //  1051: getfield        aukx.t:J
        //  1054: lstore          11
        //  1056: aload           17
        //  1058: astore          18
        //  1060: aload           19
        //  1062: checkcast       Laukx;
        //  1065: lload           11
        //  1067: lload           9
        //  1069: lload           13
        //  1071: lsub           
        //  1072: ladd           
        //  1073: putfield        aukx.t:J
        //  1076: aload           17
        //  1078: astore          18
        //  1080: aload           19
        //  1082: checkcast       Laukx;
        //  1085: getfield        aukx.u:J
        //  1088: lstore          11
        //  1090: aload           17
        //  1092: astore          18
        //  1094: aload           19
        //  1096: checkcast       Laukx;
        //  1099: lload           11
        //  1101: lload           9
        //  1103: lload           7
        //  1105: lsub           
        //  1106: ladd           
        //  1107: putfield        aukx.u:J
        //  1110: aload           17
        //  1112: astore          18
        //  1114: aload           20
        //  1116: monitorexit    
        //  1117: aload           17
        //  1119: astore          18
        //  1121: aload           17
        //  1123: astore          16
        //  1125: aload           19
        //  1127: checkcast       Laukx;
        //  1130: getfield        aukx.d:Ljava/util/ArrayList;
        //  1133: invokevirtual   java/util/ArrayList.isEmpty:()Z
        //  1136: ifeq            1142
        //  1139: goto            1746
        //  1142: aload           17
        //  1144: astore          18
        //  1146: aload           17
        //  1148: astore          16
        //  1150: aload           19
        //  1152: checkcast       Laukx;
        //  1155: getfield        aukx.j:Landroid/graphics/Matrix;
        //  1158: invokevirtual   android/graphics/Matrix.reset:()V
        //  1161: aload           17
        //  1163: astore          18
        //  1165: aload           17
        //  1167: astore          16
        //  1169: aload           19
        //  1171: checkcast       Laukx;
        //  1174: getfield        aukx.j:Landroid/graphics/Matrix;
        //  1177: ldc             0.5
        //  1179: ldc             0.5
        //  1181: invokevirtual   android/graphics/Matrix.preTranslate:(FF)Z
        //  1184: pop            
        //  1185: aload           17
        //  1187: astore          18
        //  1189: aload           17
        //  1191: astore          16
        //  1193: aload           19
        //  1195: checkcast       Laukx;
        //  1198: getfield        aukx.j:Landroid/graphics/Matrix;
        //  1201: fconst_1       
        //  1202: fconst_1       
        //  1203: invokevirtual   android/graphics/Matrix.preScale:(FF)Z
        //  1206: pop            
        //  1207: aload           17
        //  1209: astore          18
        //  1211: aload           17
        //  1213: astore          16
        //  1215: aload           19
        //  1217: checkcast       Laukx;
        //  1220: getfield        aukx.j:Landroid/graphics/Matrix;
        //  1223: fconst_1       
        //  1224: ldc_w           -1.0
        //  1227: invokevirtual   android/graphics/Matrix.preScale:(FF)Z
        //  1230: pop            
        //  1231: aload           17
        //  1233: astore          18
        //  1235: aload           17
        //  1237: astore          16
        //  1239: aload           19
        //  1241: checkcast       Laukx;
        //  1244: getfield        aukx.j:Landroid/graphics/Matrix;
        //  1247: ldc             -0.5
        //  1249: ldc             -0.5
        //  1251: invokevirtual   android/graphics/Matrix.preTranslate:(FF)Z
        //  1254: pop            
        //  1255: aload           17
        //  1257: astore          18
        //  1259: aload           17
        //  1261: astore          16
        //  1263: aload           19
        //  1265: checkcast       Laukx;
        //  1268: getfield        aukx.d:Ljava/util/ArrayList;
        //  1271: invokevirtual   java/util/ArrayList.iterator:()Ljava/util/Iterator;
        //  1274: astore          21
        //  1276: aload           17
        //  1278: astore          18
        //  1280: aload           17
        //  1282: astore          16
        //  1284: aload           21
        //  1286: invokeinterface java/util/Iterator.hasNext:()Z
        //  1291: ifeq            1746
        //  1294: aload           17
        //  1296: astore          18
        //  1298: aload           17
        //  1300: astore          16
        //  1302: aload           21
        //  1304: invokeinterface java/util/Iterator.next:()Ljava/lang/Object;
        //  1309: checkcast       Laukv;
        //  1312: astore          20
        //  1314: aload           17
        //  1316: astore          18
        //  1318: aload           17
        //  1320: astore          16
        //  1322: aload           21
        //  1324: invokeinterface java/util/Iterator.remove:()V
        //  1329: aload           17
        //  1331: astore          18
        //  1333: aload           17
        //  1335: astore          16
        //  1337: aload           20
        //  1339: getfield        aukv.a:F
        //  1342: fstore_1       
        //  1343: aload           17
        //  1345: astore          18
        //  1347: aload           17
        //  1349: astore          16
        //  1351: aload           17
        //  1353: invokevirtual   org/webrtc/VideoFrame.b:()I
        //  1356: i2f            
        //  1357: fstore_1       
        //  1358: aload           17
        //  1360: astore          18
        //  1362: aload           17
        //  1364: astore          16
        //  1366: aload           20
        //  1368: getfield        aukv.a:F
        //  1371: fstore_2       
        //  1372: aload           17
        //  1374: astore          18
        //  1376: aload           17
        //  1378: astore          16
        //  1380: aload           17
        //  1382: invokevirtual   org/webrtc/VideoFrame.a:()I
        //  1385: i2f            
        //  1386: fstore_2       
        //  1387: fload_1        
        //  1388: fconst_0       
        //  1389: fmul           
        //  1390: f2i            
        //  1391: istore          4
        //  1393: iload           4
        //  1395: ifeq            1721
        //  1398: fload_2        
        //  1399: fconst_0       
        //  1400: fmul           
        //  1401: f2i            
        //  1402: istore          5
        //  1404: iload           5
        //  1406: ifne            1412
        //  1409: goto            1721
        //  1412: aload           17
        //  1414: astore          18
        //  1416: aload           17
        //  1418: astore          16
        //  1420: aload           19
        //  1422: checkcast       Laukx;
        //  1425: getfield        aukx.v:Lauld;
        //  1428: iload           4
        //  1430: iload           5
        //  1432: invokevirtual   auld.b:(II)V
        //  1435: aload           17
        //  1437: astore          18
        //  1439: aload           17
        //  1441: astore          16
        //  1443: ldc_w           36160
        //  1446: aload           19
        //  1448: checkcast       Laukx;
        //  1451: getfield        aukx.v:Lauld;
        //  1454: getfield        auld.a:I
        //  1457: invokestatic    android/opengl/GLES20.glBindFramebuffer:(II)V
        //  1460: aload           17
        //  1462: astore          18
        //  1464: aload           17
        //  1466: astore          16
        //  1468: ldc_w           36160
        //  1471: ldc_w           36064
        //  1474: sipush          3553
        //  1477: aload           19
        //  1479: checkcast       Laukx;
        //  1482: getfield        aukx.v:Lauld;
        //  1485: getfield        auld.b:I
        //  1488: iconst_0       
        //  1489: invokestatic    android/opengl/GLES20.glFramebufferTexture2D:(IIIII)V
        //  1492: aload           17
        //  1494: astore          18
        //  1496: aload           17
        //  1498: astore          16
        //  1500: fconst_0       
        //  1501: fconst_0       
        //  1502: fconst_0       
        //  1503: fconst_0       
        //  1504: invokestatic    android/opengl/GLES20.glClearColor:(FFFF)V
        //  1507: aload           17
        //  1509: astore          18
        //  1511: aload           17
        //  1513: astore          16
        //  1515: sipush          16384
        //  1518: invokestatic    android/opengl/GLES20.glClear:(I)V
        //  1521: aload           17
        //  1523: astore          18
        //  1525: aload           17
        //  1527: astore          16
        //  1529: aload           19
        //  1531: checkcast       Laukx;
        //  1534: getfield        aukx.h:Laumi;
        //  1537: astore          22
        //  1539: aload           17
        //  1541: astore          18
        //  1543: aload           17
        //  1545: astore          16
        //  1547: aload           20
        //  1549: getfield        aukv.c:Ljava/lang/Object;
        //  1552: astore          21
        //  1554: aload           17
        //  1556: astore          18
        //  1558: aload           17
        //  1560: astore          16
        //  1562: aload           22
        //  1564: aload           17
        //  1566: aconst_null    
        //  1567: aload           19
        //  1569: checkcast       Laukx;
        //  1572: getfield        aukx.j:Landroid/graphics/Matrix;
        //  1575: iload           4
        //  1577: iload           5
        //  1579: invokevirtual   aumi.b:(Lorg/webrtc/VideoFrame;Laulr;Landroid/graphics/Matrix;II)V
        //  1582: aload           17
        //  1584: astore          18
        //  1586: aload           17
        //  1588: astore          16
        //  1590: iload           4
        //  1592: iload           5
        //  1594: imul           
        //  1595: iconst_4       
        //  1596: imul           
        //  1597: invokestatic    java/nio/ByteBuffer.allocateDirect:(I)Ljava/nio/ByteBuffer;
        //  1600: astore          21
        //  1602: aload           17
        //  1604: astore          18
        //  1606: aload           17
        //  1608: astore          16
        //  1610: iconst_0       
        //  1611: iconst_0       
        //  1612: iload           4
        //  1614: iload           5
        //  1616: invokestatic    android/opengl/GLES20.glViewport:(IIII)V
        //  1619: aload           17
        //  1621: astore          18
        //  1623: aload           17
        //  1625: astore          16
        //  1627: iconst_0       
        //  1628: iconst_0       
        //  1629: iload           4
        //  1631: iload           5
        //  1633: sipush          6408
        //  1636: sipush          5121
        //  1639: aload           21
        //  1641: invokestatic    android/opengl/GLES20.glReadPixels:(IIIIIILjava/nio/Buffer;)V
        //  1644: aload           17
        //  1646: astore          18
        //  1648: aload           17
        //  1650: astore          16
        //  1652: ldc_w           36160
        //  1655: iconst_0       
        //  1656: invokestatic    android/opengl/GLES20.glBindFramebuffer:(II)V
        //  1659: aload           17
        //  1661: astore          18
        //  1663: aload           17
        //  1665: astore          16
        //  1667: ldc_w           "EglRenderer.notifyCallbacks"
        //  1670: invokestatic    aucl.d:(Ljava/lang/String;)V
        //  1673: aload           17
        //  1675: astore          18
        //  1677: aload           17
        //  1679: astore          16
        //  1681: iload           4
        //  1683: iload           5
        //  1685: getstatic       android/graphics/Bitmap$Config.ARGB_8888:Landroid/graphics/Bitmap$Config;
        //  1688: invokestatic    android/graphics/Bitmap.createBitmap:(IILandroid/graphics/Bitmap$Config;)Landroid/graphics/Bitmap;
        //  1691: aload           21
        //  1693: invokevirtual   android/graphics/Bitmap.copyPixelsFromBuffer:(Ljava/nio/Buffer;)V
        //  1696: aload           17
        //  1698: astore          18
        //  1700: aload           17
        //  1702: astore          16
        //  1704: aload           20
        //  1706: getfield        aukv.b:Ljava/lang/Object;
        //  1709: astore          20
        //  1711: aload           17
        //  1713: astore          18
        //  1715: aload           17
        //  1717: astore          16
        //  1719: aconst_null    
        //  1720: athrow         
        //  1721: aload           17
        //  1723: astore          18
        //  1725: aload           17
        //  1727: astore          16
        //  1729: aload           20
        //  1731: getfield        aukv.b:Ljava/lang/Object;
        //  1734: astore          20
        //  1736: aload           17
        //  1738: astore          18
        //  1740: aload           17
        //  1742: astore          16
        //  1744: aconst_null    
        //  1745: athrow         
        //  1746: aload           17
        //  1748: invokevirtual   org/webrtc/VideoFrame.release:()V
        //  1751: return         
        //  1752: astore          17
        //  1754: aload           16
        //  1756: astore          18
        //  1758: aload           20
        //  1760: monitorexit    
        //  1761: aload           16
        //  1763: astore          18
        //  1765: aload           17
        //  1767: athrow         
        //  1768: astore          17
        //  1770: goto            1793
        //  1773: astore          17
        //  1775: aload           18
        //  1777: astore          16
        //  1779: goto            1754
        //  1782: astore          17
        //  1784: goto            1891
        //  1787: astore          17
        //  1789: aload           16
        //  1791: astore          18
        //  1793: aload           18
        //  1795: astore          16
        //  1797: ldc_w           "EglRenderer"
        //  1800: aload           19
        //  1802: checkcast       Laukx;
        //  1805: getfield        aukx.a:Ljava/lang/String;
        //  1808: invokestatic    java/lang/String.valueOf:(Ljava/lang/Object;)Ljava/lang/String;
        //  1811: ldc_w           "Error while drawing frame"
        //  1814: invokevirtual   java/lang/String.concat:(Ljava/lang/String;)Ljava/lang/String;
        //  1817: aload           17
        //  1819: invokestatic    org/webrtc/Logging.c:(Ljava/lang/String;Ljava/lang/String;Ljava/lang/Throwable;)V
        //  1822: aload           18
        //  1824: astore          16
        //  1826: aload           19
        //  1828: checkcast       Laukx;
        //  1831: getfield        aukx.e:Lauku;
        //  1834: astore          17
        //  1836: aload           18
        //  1838: astore          16
        //  1840: aload           19
        //  1842: checkcast       Laukx;
        //  1845: getfield        aukx.i:Laulr;
        //  1848: invokeinterface aulr.c:()V
        //  1853: aload           18
        //  1855: astore          16
        //  1857: aload           19
        //  1859: checkcast       Laukx;
        //  1862: getfield        aukx.h:Laumi;
        //  1865: invokevirtual   aumi.a:()V
        //  1868: aload           18
        //  1870: astore          16
        //  1872: aload           19
        //  1874: checkcast       Laukx;
        //  1877: getfield        aukx.v:Lauld;
        //  1880: invokevirtual   auld.a:()V
        //  1883: aload           18
        //  1885: invokevirtual   org/webrtc/VideoFrame.release:()V
        //  1888: return         
        //  1889: astore          17
        //  1891: aload           16
        //  1893: invokevirtual   org/webrtc/VideoFrame.release:()V
        //  1896: aload           17
        //  1898: athrow         
        //  1899: astore          16
        //  1901: aload           18
        //  1903: monitorexit    
        //  1904: aload           16
        //  1906: athrow         
        //  1907: astore          16
        //  1909: aload           18
        //  1911: monitorexit    
        //  1912: aload           16
        //  1914: athrow         
        //  1915: aload           17
        //  1917: ldc_w           "Dropping frame - No surface"
        //  1920: invokevirtual   aukx.b:(Ljava/lang/String;)V
        //  1923: aload           16
        //  1925: invokevirtual   org/webrtc/VideoFrame.release:()V
        //  1928: return         
        //  1929: astore          16
        //  1931: aload           18
        //  1933: monitorexit    
        //  1934: aload           16
        //  1936: athrow         
        //  1937: aload_0        
        //  1938: getfield        audk.a:Ljava/lang/Object;
        //  1941: checkcast       Lauea;
        //  1944: getfield        auea.c:Ljava/util/ArrayDeque;
        //  1947: astore          17
        //  1949: aload           17
        //  1951: monitorenter   
        //  1952: aload_0        
        //  1953: getfield        audk.a:Ljava/lang/Object;
        //  1956: astore          16
        //  1958: aload           16
        //  1960: checkcast       Lauea;
        //  1963: getfield        auea.d:Z
        //  1966: ifeq            1973
        //  1969: aload           17
        //  1971: monitorexit    
        //  1972: return         
        //  1973: aload           16
        //  1975: checkcast       Lauea;
        //  1978: getfield        auea.c:Ljava/util/ArrayDeque;
        //  1981: invokevirtual   java/util/ArrayDeque.pollFirst:()Ljava/lang/Object;
        //  1984: checkcast       Ljava/lang/Runnable;
        //  1987: astore          16
        //  1989: aload_0        
        //  1990: getfield        audk.a:Ljava/lang/Object;
        //  1993: astore          18
        //  1995: aload           16
        //  1997: ifnull          2006
        //  2000: iconst_1       
        //  2001: istore          15
        //  2003: goto            2009
        //  2006: iconst_0       
        //  2007: istore          15
        //  2009: aload           18
        //  2011: checkcast       Lauea;
        //  2014: iload           15
        //  2016: putfield        auea.d:Z
        //  2019: aload           17
        //  2021: monitorexit    
        //  2022: aload           16
        //  2024: ifnull          2178
        //  2027: aload           16
        //  2029: invokeinterface java/lang/Runnable.run:()V
        //  2034: aload_0        
        //  2035: getfield        audk.a:Ljava/lang/Object;
        //  2038: checkcast       Lauea;
        //  2041: getfield        auea.c:Ljava/util/ArrayDeque;
        //  2044: astore          17
        //  2046: aload           17
        //  2048: monitorenter   
        //  2049: aload_0        
        //  2050: getfield        audk.a:Ljava/lang/Object;
        //  2053: checkcast       Lauea;
        //  2056: getfield        auea.c:Ljava/util/ArrayDeque;
        //  2059: invokevirtual   java/util/ArrayDeque.pollFirst:()Ljava/lang/Object;
        //  2062: checkcast       Ljava/lang/Runnable;
        //  2065: astore          16
        //  2067: aload_0        
        //  2068: getfield        audk.a:Ljava/lang/Object;
        //  2071: astore          18
        //  2073: aload           16
        //  2075: ifnull          2084
        //  2078: iconst_1       
        //  2079: istore          15
        //  2081: goto            2087
        //  2084: iconst_0       
        //  2085: istore          15
        //  2087: aload           18
        //  2089: checkcast       Lauea;
        //  2092: iload           15
        //  2094: putfield        auea.d:Z
        //  2097: aload           17
        //  2099: monitorexit    
        //  2100: goto            2022
        //  2103: astore          16
        //  2105: aload           17
        //  2107: monitorexit    
        //  2108: aload           16
        //  2110: athrow         
        //  2111: astore          17
        //  2113: aload_0        
        //  2114: getfield        audk.a:Ljava/lang/Object;
        //  2117: checkcast       Lauea;
        //  2120: getfield        auea.c:Ljava/util/ArrayDeque;
        //  2123: astore          16
        //  2125: aload           16
        //  2127: monitorenter   
        //  2128: aload_0        
        //  2129: getfield        audk.a:Ljava/lang/Object;
        //  2132: astore          18
        //  2134: aload           18
        //  2136: checkcast       Lauea;
        //  2139: iconst_0       
        //  2140: putfield        auea.d:Z
        //  2143: aload           18
        //  2145: checkcast       Lauea;
        //  2148: getfield        auea.a:Ljava/util/concurrent/Executor;
        //  2151: aload           18
        //  2153: checkcast       Lauea;
        //  2156: getfield        auea.b:Ljava/lang/Runnable;
        //  2159: invokeinterface java/util/concurrent/Executor.execute:(Ljava/lang/Runnable;)V
        //  2164: aload           16
        //  2166: monitorexit    
        //  2167: aload           17
        //  2169: athrow         
        //  2170: astore          17
        //  2172: aload           16
        //  2174: monitorexit    
        //  2175: aload           17
        //  2177: athrow         
        //  2178: return         
        //  2179: astore          16
        //  2181: aload           17
        //  2183: monitorexit    
        //  2184: aload           16
        //  2186: athrow         
        //  2187: aload_0        
        //  2188: getfield        audk.a:Ljava/lang/Object;
        //  2191: checkcast       Lasfa;
        //  2194: getfield        asfa.a:Ljava/lang/Object;
        //  2197: checkcast       Laueb;
        //  2200: astore          17
        //  2202: aload           17
        //  2204: getfield        aueb.b:Laudz;
        //  2207: astore          16
        //  2209: aload           16
        //  2211: new             Laudy;
        //  2214: dup            
        //  2215: aload           16
        //  2217: aload           17
        //  2219: getfield        aueb.o:Lauen;
        //  2222: aload           17
        //  2224: getfield        aueb.p:Ljava/lang/String;
        //  2227: iconst_1       
        //  2228: invokespecial   audy.<init>:(Laudz;Lorg/chromium/net/UrlResponseInfo;Ljava/lang/String;I)V
        //  2231: invokevirtual   audz.a:(Lauec;)V
        //  2234: return         
        //  2235: aload_0        
        //  2236: getfield        audk.a:Ljava/lang/Object;
        //  2239: checkcast       Laueb;
        //  2242: astore          16
        //  2244: aload           16
        //  2246: aload           16
        //  2248: getfield        aueb.p:Ljava/lang/String;
        //  2251: putfield        aueb.m:Ljava/lang/String;
        //  2254: aload           16
        //  2256: aconst_null    
        //  2257: putfield        aueb.p:Ljava/lang/String;
        //  2260: aload           16
        //  2262: invokevirtual   aueb.n:()V
        //  2265: return         
        //  2266: aload_0        
        //  2267: getfield        audk.a:Ljava/lang/Object;
        //  2270: checkcast       Laueb;
        //  2273: astore          16
        //  2275: aload           16
        //  2277: getfield        aueb.f:Ljava/util/List;
        //  2280: aload           16
        //  2282: getfield        aueb.m:Ljava/lang/String;
        //  2285: invokeinterface java/util/List.add:(Ljava/lang/Object;)Z
        //  2290: pop            
        //  2291: aload_0        
        //  2292: getfield        audk.a:Ljava/lang/Object;
        //  2295: checkcast       Laueb;
        //  2298: invokevirtual   aueb.n:()V
        //  2301: return         
        //  2302: aload_0        
        //  2303: getfield        audk.a:Ljava/lang/Object;
        //  2306: checkcast       Laueb;
        //  2309: getfield        aueb.n:Ljava/nio/channels/ReadableByteChannel;
        //  2312: astore          16
        //  2314: aload           16
        //  2316: ifnull          2347
        //  2319: aload           16
        //  2321: invokeinterface java/nio/channels/ReadableByteChannel.close:()V
        //  2326: goto            2336
        //  2329: astore          16
        //  2331: aload           16
        //  2333: invokevirtual   java/io/IOException.printStackTrace:()V
        //  2336: aload_0        
        //  2337: getfield        audk.a:Ljava/lang/Object;
        //  2340: checkcast       Laueb;
        //  2343: aconst_null    
        //  2344: putfield        aueb.n:Ljava/nio/channels/ReadableByteChannel;
        //  2347: return         
        //  2348: aload_0        
        //  2349: getfield        audk.a:Ljava/lang/Object;
        //  2352: checkcast       Laueb;
        //  2355: getfield        aueb.t:Laudv;
        //  2358: astore          16
        //  2360: aload           16
        //  2362: ifnull          2387
        //  2365: aload           16
        //  2367: invokevirtual   audv.d:()V
        //  2370: goto            2387
        //  2373: astore          16
        //  2375: getstatic       aueb.a:Ljava/lang/String;
        //  2378: ldc_w           "Exception when closing OutputChannel"
        //  2381: aload           16
        //  2383: invokestatic    android/util/Log.e:(Ljava/lang/String;Ljava/lang/String;Ljava/lang/Throwable;)I
        //  2386: pop            
        //  2387: aload_0        
        //  2388: getfield        audk.a:Ljava/lang/Object;
        //  2391: checkcast       Laueb;
        //  2394: getfield        aueb.q:Ljava/net/HttpURLConnection;
        //  2397: astore          16
        //  2399: aload           16
        //  2401: ifnull          2420
        //  2404: aload           16
        //  2406: invokevirtual   java/net/HttpURLConnection.disconnect:()V
        //  2409: aload_0        
        //  2410: getfield        audk.a:Ljava/lang/Object;
        //  2413: checkcast       Laueb;
        //  2416: aconst_null    
        //  2417: putfield        aueb.q:Ljava/net/HttpURLConnection;
        //  2420: return         
        //  2421: invokestatic    org/chromium/net/impl/CronetLibraryLoader.b:()V
        //  2424: aload_0        
        //  2425: getfield        audk.a:Ljava/lang/Object;
        //  2428: checkcast       Lorg/chromium/net/impl/CronetUrlRequestContext;
        //  2431: getfield        org/chromium/net/impl/CronetUrlRequestContext.c:Ljava/lang/Object;
        //  2434: astore          16
        //  2436: aload           16
        //  2438: monitorenter   
        //  2439: aload_0        
        //  2440: getfield        audk.a:Ljava/lang/Object;
        //  2443: astore          17
        //  2445: aload           17
        //  2447: checkcast       Lorg/chromium/net/impl/CronetUrlRequestContext;
        //  2450: getfield        org/chromium/net/impl/CronetUrlRequestContext.d:J
        //  2453: aload           17
        //  2455: invokestatic    J/N.M6Dz0nZ5:(JLjava/lang/Object;)V
        //  2458: aload           16
        //  2460: monitorexit    
        //  2461: return         
        //  2462: astore          17
        //  2464: aload           16
        //  2466: monitorexit    
        //  2467: aload           17
        //  2469: athrow         
        //  2470: aload_0        
        //  2471: getfield        audk.a:Ljava/lang/Object;
        //  2474: astore          18
        //  2476: aload           18
        //  2478: checkcast       Lorg/chromium/net/impl/CronetUrlRequest;
        //  2481: getfield        org/chromium/net/impl/CronetUrlRequest.d:Lauev;
        //  2484: astore          19
        //  2486: aload           18
        //  2488: checkcast       Lorg/chromium/net/impl/CronetUrlRequest;
        //  2491: getfield        org/chromium/net/impl/CronetUrlRequest.g:Lauen;
        //  2494: astore          17
        //  2496: aload           18
        //  2498: checkcast       Lorg/chromium/net/impl/CronetUrlRequest;
        //  2501: getfield        org/chromium/net/impl/CronetUrlRequest.h:Lorg/chromium/net/CronetException;
        //  2504: astore          16
        //  2506: aload           19
        //  2508: aload           18
        //  2510: checkcast       Lorg/chromium/net/UrlRequest;
        //  2513: aload           17
        //  2515: aload           16
        //  2517: invokevirtual   auev.onFailed:(Lorg/chromium/net/UrlRequest;Lorg/chromium/net/UrlResponseInfo;Lorg/chromium/net/CronetException;)V
        //  2520: aload_0        
        //  2521: getfield        audk.a:Ljava/lang/Object;
        //  2524: checkcast       Lorg/chromium/net/impl/CronetUrlRequest;
        //  2527: invokevirtual   org/chromium/net/impl/CronetUrlRequest.d:()V
        //  2530: return         
        //  2531: astore          16
        //  2533: ldc_w           "cr_"
        //  2536: getstatic       org/chromium/net/impl/CronetUrlRequestContext.b:Ljava/lang/String;
        //  2539: invokestatic    java/lang/String.valueOf:(Ljava/lang/Object;)Ljava/lang/String;
        //  2542: invokevirtual   java/lang/String.concat:(Ljava/lang/String;)Ljava/lang/String;
        //  2545: ldc_w           "Exception in onFailed method"
        //  2548: aload           16
        //  2550: invokestatic    android/util/Log.e:(Ljava/lang/String;Ljava/lang/String;Ljava/lang/Throwable;)I
        //  2553: pop            
        //  2554: return         
        //  2555: aload_0        
        //  2556: getfield        audk.a:Ljava/lang/Object;
        //  2559: astore          18
        //  2561: aload           18
        //  2563: checkcast       Lorg/chromium/net/impl/CronetUrlRequest;
        //  2566: getfield        org/chromium/net/impl/CronetUrlRequest.d:Lauev;
        //  2569: astore          17
        //  2571: aload           18
        //  2573: checkcast       Lorg/chromium/net/impl/CronetUrlRequest;
        //  2576: getfield        org/chromium/net/impl/CronetUrlRequest.g:Lauen;
        //  2579: astore          16
        //  2581: aload           17
        //  2583: aload           18
        //  2585: checkcast       Lorg/chromium/net/UrlRequest;
        //  2588: aload           16
        //  2590: invokevirtual   org/chromium/net/UrlRequest$Callback.onCanceled:(Lorg/chromium/net/UrlRequest;Lorg/chromium/net/UrlResponseInfo;)V
        //  2593: aload_0        
        //  2594: getfield        audk.a:Ljava/lang/Object;
        //  2597: checkcast       Lorg/chromium/net/impl/CronetUrlRequest;
        //  2600: invokevirtual   org/chromium/net/impl/CronetUrlRequest.d:()V
        //  2603: return         
        //  2604: astore          16
        //  2606: ldc_w           "cr_"
        //  2609: getstatic       org/chromium/net/impl/CronetUrlRequestContext.b:Ljava/lang/String;
        //  2612: invokestatic    java/lang/String.valueOf:(Ljava/lang/Object;)Ljava/lang/String;
        //  2615: invokevirtual   java/lang/String.concat:(Ljava/lang/String;)Ljava/lang/String;
        //  2618: ldc_w           "Exception in onCanceled method"
        //  2621: aload           16
        //  2623: invokestatic    android/util/Log.e:(Ljava/lang/String;Ljava/lang/String;Ljava/lang/Throwable;)I
        //  2626: pop            
        //  2627: return         
        //  2628: aload_0        
        //  2629: getfield        audk.a:Ljava/lang/Object;
        //  2632: checkcast       Lorg/chromium/net/impl/CronetUrlRequest;
        //  2635: getfield        org/chromium/net/impl/CronetUrlRequest.c:Ljava/lang/Object;
        //  2638: astore          16
        //  2640: aload           16
        //  2642: monitorenter   
        //  2643: aload_0        
        //  2644: getfield        audk.a:Ljava/lang/Object;
        //  2647: astore          17
        //  2649: aload           17
        //  2651: checkcast       Lorg/chromium/net/impl/CronetUrlRequest;
        //  2654: invokevirtual   org/chromium/net/impl/CronetUrlRequest.j:()Z
        //  2657: ifeq            2664
        //  2660: aload           16
        //  2662: monitorexit    
        //  2663: return         
        //  2664: aload           17
        //  2666: checkcast       Lorg/chromium/net/impl/CronetUrlRequest;
        //  2669: iconst_0       
        //  2670: invokevirtual   org/chromium/net/impl/CronetUrlRequest.c:(I)V
        //  2673: aload           16
        //  2675: monitorexit    
        //  2676: aload_0        
        //  2677: getfield        audk.a:Ljava/lang/Object;
        //  2680: astore          16
        //  2682: aload           16
        //  2684: checkcast       Lorg/chromium/net/impl/CronetUrlRequest;
        //  2687: getfield        org/chromium/net/impl/CronetUrlRequest.d:Lauev;
        //  2690: astore          18
        //  2692: aload           16
        //  2694: checkcast       Lorg/chromium/net/impl/CronetUrlRequest;
        //  2697: getfield        org/chromium/net/impl/CronetUrlRequest.g:Lauen;
        //  2700: astore          17
        //  2702: aload           18
        //  2704: aload           16
        //  2706: checkcast       Lorg/chromium/net/UrlRequest;
        //  2709: aload           17
        //  2711: invokevirtual   auev.onSucceeded:(Lorg/chromium/net/UrlRequest;Lorg/chromium/net/UrlResponseInfo;)V
        //  2714: aload_0        
        //  2715: getfield        audk.a:Ljava/lang/Object;
        //  2718: checkcast       Lorg/chromium/net/impl/CronetUrlRequest;
        //  2721: invokevirtual   org/chromium/net/impl/CronetUrlRequest.d:()V
        //  2724: return         
        //  2725: astore          16
        //  2727: ldc_w           "cr_"
        //  2730: getstatic       org/chromium/net/impl/CronetUrlRequestContext.b:Ljava/lang/String;
        //  2733: invokestatic    java/lang/String.valueOf:(Ljava/lang/Object;)Ljava/lang/String;
        //  2736: invokevirtual   java/lang/String.concat:(Ljava/lang/String;)Ljava/lang/String;
        //  2739: ldc_w           "Exception in onSucceeded method"
        //  2742: aload           16
        //  2744: invokestatic    android/util/Log.e:(Ljava/lang/String;Ljava/lang/String;Ljava/lang/Throwable;)I
        //  2747: pop            
        //  2748: return         
        //  2749: astore          17
        //  2751: aload           16
        //  2753: monitorexit    
        //  2754: aload           17
        //  2756: athrow         
        //  2757: aload_0        
        //  2758: getfield        audk.a:Ljava/lang/Object;
        //  2761: checkcast       Lorg/chromium/net/impl/VersionSafeCallbacks$UrlRequestStatusListener;
        //  2764: iconst_m1      
        //  2765: invokevirtual   org/chromium/net/impl/VersionSafeCallbacks$UrlRequestStatusListener.onStatus:(I)V
        //  2768: return         
        //  2769: aload_0        
        //  2770: getfield        audk.a:Ljava/lang/Object;
        //  2773: checkcast       Lorg/chromium/net/impl/CronetUrlRequest;
        //  2776: invokevirtual   org/chromium/net/impl/CronetUrlRequest.b:()V
        //  2779: aload_0        
        //  2780: getfield        audk.a:Ljava/lang/Object;
        //  2783: checkcast       Lorg/chromium/net/impl/CronetUrlRequest;
        //  2786: getfield        org/chromium/net/impl/CronetUrlRequest.c:Ljava/lang/Object;
        //  2789: astore          16
        //  2791: aload           16
        //  2793: monitorenter   
        //  2794: aload_0        
        //  2795: getfield        audk.a:Ljava/lang/Object;
        //  2798: astore          17
        //  2800: aload           17
        //  2802: checkcast       Lorg/chromium/net/impl/CronetUrlRequest;
        //  2805: invokevirtual   org/chromium/net/impl/CronetUrlRequest.j:()Z
        //  2808: ifeq            2815
        //  2811: aload           16
        //  2813: monitorexit    
        //  2814: return         
        //  2815: aload           17
        //  2817: checkcast       Lorg/chromium/net/impl/CronetUrlRequest;
        //  2820: invokestatic    org/chromium/net/impl/CronetUrlRequest.k:(Lorg/chromium/net/impl/CronetUrlRequest;)V
        //  2823: aload           16
        //  2825: monitorexit    
        //  2826: aload_0        
        //  2827: getfield        audk.a:Ljava/lang/Object;
        //  2830: astore          16
        //  2832: aload           16
        //  2834: checkcast       Lorg/chromium/net/impl/CronetUrlRequest;
        //  2837: getfield        org/chromium/net/impl/CronetUrlRequest.d:Lauev;
        //  2840: astore          18
        //  2842: aload           16
        //  2844: checkcast       Lorg/chromium/net/impl/CronetUrlRequest;
        //  2847: getfield        org/chromium/net/impl/CronetUrlRequest.g:Lauen;
        //  2850: astore          17
        //  2852: aload           18
        //  2854: aload           16
        //  2856: checkcast       Lorg/chromium/net/UrlRequest;
        //  2859: aload           17
        //  2861: invokevirtual   auev.onResponseStarted:(Lorg/chromium/net/UrlRequest;Lorg/chromium/net/UrlResponseInfo;)V
        //  2864: return         
        //  2865: astore          16
        //  2867: aload_0        
        //  2868: getfield        audk.a:Ljava/lang/Object;
        //  2871: checkcast       Lorg/chromium/net/impl/CronetUrlRequest;
        //  2874: aload           16
        //  2876: invokevirtual   org/chromium/net/impl/CronetUrlRequest.e:(Ljava/lang/Exception;)V
        //  2879: return         
        //  2880: astore          17
        //  2882: aload           16
        //  2884: monitorexit    
        //  2885: aload           17
        //  2887: athrow         
        //  2888: aload           16
        //  2890: invokevirtual   aulx.b:()V
        //  2893: return         
        //  2894: astore          18
        //  2896: goto            2164
        //    Exceptions:
        //  Try           Handler
        //  Start  End    Start  End    Type                                             
        //  -----  -----  -----  -----  -------------------------------------------------
        //  227    241    242    250    Any
        //  244    247    242    250    Any
        //  285    298    675    683    Any
        //  305    573    675    683    Any
        //  576    579    675    683    Any
        //  594    610    667    675    Any
        //  615    663    667    675    Any
        //  663    666    667    675    Any
        //  669    672    667    675    Any
        //  677    680    675    683    Any
        //  706    716    1929   1937   Any
        //  721    724    1929   1937   Any
        //  725    737    1929   1937   Any
        //  772    775    1907   1915   Any
        //  804    813    1899   1907   Any
        //  828    831    1899   1907   Any
        //  908    1012   1787   1793   Laule;
        //  908    1012   1782   1787   Any
        //  1012   1041   1752   1754   Any
        //  1049   1056   1773   1782   Any
        //  1060   1076   1773   1782   Any
        //  1080   1090   1773   1782   Any
        //  1094   1110   1773   1782   Any
        //  1114   1117   1773   1782   Any
        //  1125   1139   1768   1773   Laule;
        //  1125   1139   1889   1891   Any
        //  1150   1161   1768   1773   Laule;
        //  1150   1161   1889   1891   Any
        //  1169   1185   1768   1773   Laule;
        //  1169   1185   1889   1891   Any
        //  1193   1207   1768   1773   Laule;
        //  1193   1207   1889   1891   Any
        //  1215   1231   1768   1773   Laule;
        //  1215   1231   1889   1891   Any
        //  1239   1255   1768   1773   Laule;
        //  1239   1255   1889   1891   Any
        //  1263   1276   1768   1773   Laule;
        //  1263   1276   1889   1891   Any
        //  1284   1294   1768   1773   Laule;
        //  1284   1294   1889   1891   Any
        //  1302   1314   1768   1773   Laule;
        //  1302   1314   1889   1891   Any
        //  1322   1329   1768   1773   Laule;
        //  1322   1329   1889   1891   Any
        //  1337   1343   1768   1773   Laule;
        //  1337   1343   1889   1891   Any
        //  1351   1358   1768   1773   Laule;
        //  1351   1358   1889   1891   Any
        //  1366   1372   1768   1773   Laule;
        //  1366   1372   1889   1891   Any
        //  1380   1387   1768   1773   Laule;
        //  1380   1387   1889   1891   Any
        //  1420   1435   1768   1773   Laule;
        //  1420   1435   1889   1891   Any
        //  1443   1460   1768   1773   Laule;
        //  1443   1460   1889   1891   Any
        //  1468   1492   1768   1773   Laule;
        //  1468   1492   1889   1891   Any
        //  1500   1507   1768   1773   Laule;
        //  1500   1507   1889   1891   Any
        //  1515   1521   1768   1773   Laule;
        //  1515   1521   1889   1891   Any
        //  1529   1539   1768   1773   Laule;
        //  1529   1539   1889   1891   Any
        //  1547   1554   1768   1773   Laule;
        //  1547   1554   1889   1891   Any
        //  1562   1582   1768   1773   Laule;
        //  1562   1582   1889   1891   Any
        //  1590   1602   1768   1773   Laule;
        //  1590   1602   1889   1891   Any
        //  1610   1619   1768   1773   Laule;
        //  1610   1619   1889   1891   Any
        //  1627   1644   1768   1773   Laule;
        //  1627   1644   1889   1891   Any
        //  1652   1659   1768   1773   Laule;
        //  1652   1659   1889   1891   Any
        //  1667   1673   1768   1773   Laule;
        //  1667   1673   1889   1891   Any
        //  1681   1696   1768   1773   Laule;
        //  1681   1696   1889   1891   Any
        //  1704   1711   1768   1773   Laule;
        //  1704   1711   1889   1891   Any
        //  1719   1721   1768   1773   Laule;
        //  1719   1721   1889   1891   Any
        //  1729   1736   1768   1773   Laule;
        //  1729   1736   1889   1891   Any
        //  1744   1746   1768   1773   Laule;
        //  1744   1746   1889   1891   Any
        //  1758   1761   1773   1782   Any
        //  1765   1768   1768   1773   Laule;
        //  1765   1768   1889   1891   Any
        //  1797   1822   1889   1891   Any
        //  1826   1836   1889   1891   Any
        //  1840   1853   1889   1891   Any
        //  1857   1868   1889   1891   Any
        //  1872   1883   1889   1891   Any
        //  1901   1904   1899   1907   Any
        //  1909   1912   1907   1915   Any
        //  1931   1934   1929   1937   Any
        //  1952   1972   2179   2187   Any
        //  1973   1995   2179   2187   Any
        //  2009   2022   2179   2187   Any
        //  2027   2034   2111   2178   Any
        //  2049   2073   2103   2111   Any
        //  2087   2100   2103   2111   Any
        //  2105   2108   2103   2111   Any
        //  2128   2143   2170   2178   Any
        //  2143   2164   2894   2899   Ljava/util/concurrent/RejectedExecutionException;
        //  2143   2164   2170   2178   Any
        //  2164   2167   2170   2178   Any
        //  2172   2175   2170   2178   Any
        //  2181   2184   2179   2187   Any
        //  2319   2326   2329   2336   Ljava/io/IOException;
        //  2365   2370   2373   2387   Ljava/io/IOException;
        //  2439   2461   2462   2470   Any
        //  2464   2467   2462   2470   Any
        //  2470   2530   2531   2555   Ljava/lang/Exception;
        //  2555   2603   2604   2628   Ljava/lang/Exception;
        //  2643   2663   2749   2757   Any
        //  2664   2676   2749   2757   Any
        //  2676   2724   2725   2749   Ljava/lang/Exception;
        //  2751   2754   2749   2757   Any
        //  2794   2814   2880   2888   Any
        //  2815   2826   2880   2888   Any
        //  2826   2864   2865   2880   Ljava/lang/Exception;
        //  2882   2885   2880   2888   Any
        // 
        // The error that occurred was:
        // 
        // java.lang.IllegalStateException: Expression is linked from several locations: Label_1142:
        //     at com.strobel.decompiler.ast.Error.expressionLinkedFromMultipleLocations(Error.java:27)
        //     at com.strobel.decompiler.ast.AstOptimizer.mergeDisparateObjectInitializations(AstOptimizer.java:2604)
        //     at com.strobel.decompiler.ast.AstOptimizer.optimize(AstOptimizer.java:235)
        //     at com.strobel.decompiler.ast.AstOptimizer.optimize(AstOptimizer.java:42)
        //     at com.strobel.decompiler.languages.java.ast.AstMethodBodyBuilder.createMethodBody(AstMethodBodyBuilder.java:206)
        //     at com.strobel.decompiler.languages.java.ast.AstMethodBodyBuilder.createMethodBody(AstMethodBodyBuilder.java:93)
        //     at com.strobel.decompiler.languages.java.ast.AstBuilder.createMethodBody(AstBuilder.java:868)
        //     at com.strobel.decompiler.languages.java.ast.AstBuilder.createMethod(AstBuilder.java:761)
        //     at com.strobel.decompiler.languages.java.ast.AstBuilder.addTypeMembers(AstBuilder.java:638)
        //     at com.strobel.decompiler.languages.java.ast.AstBuilder.createTypeCore(AstBuilder.java:605)
        //     at com.strobel.decompiler.languages.java.ast.AstBuilder.createTypeNoCache(AstBuilder.java:195)
        //     at com.strobel.decompiler.languages.java.ast.AstBuilder.createType(AstBuilder.java:162)
        //     at com.strobel.decompiler.languages.java.ast.AstBuilder.addType(AstBuilder.java:137)
        //     at com.strobel.decompiler.languages.java.JavaLanguage.buildAst(JavaLanguage.java:71)
        //     at com.strobel.decompiler.languages.java.JavaLanguage.decompileType(JavaLanguage.java:59)
        //     at com.strobel.decompiler.DecompilerDriver.decompileType(DecompilerDriver.java:333)
        //     at com.strobel.decompiler.DecompilerDriver.decompileJar(DecompilerDriver.java:254)
        //     at com.strobel.decompiler.DecompilerDriver.main(DecompilerDriver.java:129)
        // 
        throw new IllegalStateException("An error occurred while decompiling this method.");
    }
}
