import com.google.android.apps.youtube.app.extensions.reel.creation.shorts.search.MusicSearchResultsController;
import com.google.android.apps.youtube.app.extensions.lens.LensController;
import com.google.android.apps.youtube.app.datasaving.DefaultNetworkDataUsageMonitor;
import android.view.View;

// 
// Decompiled by Procyon v0.6.0
// 

public final class esc implements tet
{
    public final Object a;
    private final int b;
    
    public esc(final View a, final int b) {
        this.b = b;
        this.a = a;
    }
    
    public esc(final ashj a, final int b) {
        this.b = b;
        this.a = a;
    }
    
    public esc(final DefaultNetworkDataUsageMonitor a, final int b) {
        this.b = b;
        this.a = a;
    }
    
    public esc(final LensController a, final int b) {
        this.b = b;
        this.a = a;
    }
    
    public esc(final MusicSearchResultsController a, final int b) {
        this.b = b;
        this.a = a;
    }
    
    public esc(final esm a, final int b) {
        this.b = b;
        this.a = a;
    }
    
    public esc(final etk a, final int b) {
        this.b = b;
        this.a = a;
    }
    
    public esc(final eyn a, final int b) {
        this.b = b;
        this.a = a;
    }
    
    public esc(final fcg a, final int b) {
        this.b = b;
        this.a = a;
    }
    
    public esc(final fff a, final int b) {
        this.b = b;
        this.a = a;
    }
    
    public esc(final flb a, final int b) {
        this.b = b;
        this.a = a;
    }
    
    public esc(final fle a, final int b) {
        this.b = b;
        this.a = a;
    }
    
    public esc(final fyw a, final int b) {
        this.b = b;
        this.a = a;
    }
    
    public esc(final gyf a, final int b) {
        this.b = b;
        this.a = a;
    }
    
    public esc(final hbx a, final int b) {
        this.b = b;
        this.a = a;
    }
    
    public esc(final hcq a, final int b) {
        this.b = b;
        this.a = a;
    }
    
    public esc(final hga a, final int b) {
        this.b = b;
        this.a = a;
    }
    
    public esc(final zpf a, final int b) {
        this.b = b;
        this.a = a;
    }
    
    public final void a(final Object p0) {
        // 
        // This method could not be decompiled.
        // 
        // Original Bytecode:
        // 
        //     1: getfield        esc.b:I
        //     4: istore          4
        //     6: aconst_null    
        //     7: astore          11
        //     9: aconst_null    
        //    10: astore          8
        //    12: aconst_null    
        //    13: astore          9
        //    15: aconst_null    
        //    16: astore          10
        //    18: iconst_0       
        //    19: istore_3       
        //    20: iconst_0       
        //    21: istore_2       
        //    22: iload           4
        //    24: tableswitch {
        //                0: 2997
        //                1: 2961
        //                2: 2940
        //                3: 2505
        //                4: 2379
        //                5: 2208
        //                6: 2169
        //                7: 2124
        //                8: 2055
        //                9: 2001
        //               10: 1807
        //               11: 1750
        //               12: 1714
        //               13: 1700
        //               14: 1413
        //               15: 840
        //               16: 804
        //               17: 545
        //               18: 524
        //               19: 188
        //          default: 120
        //        }
        //   120: aload_0        
        //   121: getfield        esc.a:Ljava/lang/Object;
        //   124: astore          11
        //   126: aload_1        
        //   127: checkcast       [Lcom/google/android/libraries/youtube/innertube/model/player/PlayerResponseModel;
        //   130: astore_1       
        //   131: aload_1        
        //   132: iconst_0       
        //   133: aaload         
        //   134: astore          10
        //   136: aload_1        
        //   137: iconst_1       
        //   138: aaload         
        //   139: astore          13
        //   141: aload           10
        //   143: invokeinterface com/google/android/libraries/youtube/innertube/model/player/PlayerResponseModel.n:()Lcom/google/android/libraries/youtube/innertube/model/media/VideoStreamingData;
        //   148: astore_1       
        //   149: aload           13
        //   151: invokeinterface com/google/android/libraries/youtube/innertube/model/player/PlayerResponseModel.n:()Lcom/google/android/libraries/youtube/innertube/model/media/VideoStreamingData;
        //   156: astore          12
        //   158: aload_1        
        //   159: ifnull          3456
        //   162: aload           12
        //   164: ifnull          3456
        //   167: aload_1        
        //   168: getfield        com/google/android/libraries/youtube/innertube/model/media/VideoStreamingData.q:Ljava/util/List;
        //   171: astore_1       
        //   172: aload_1        
        //   173: ifnull          3258
        //   176: aload_1        
        //   177: invokeinterface java/util/List.isEmpty:()Z
        //   182: ifeq            3059
        //   185: goto            3258
        //   188: aload_0        
        //   189: getfield        esc.a:Ljava/lang/Object;
        //   192: astore          8
        //   194: aload_1        
        //   195: checkcast       Lcom/google/android/libraries/youtube/innertube/model/SearchResponseModel;
        //   198: astore_1       
        //   199: aload           8
        //   201: checkcast       Lcom/google/android/apps/youtube/app/extensions/reel/creation/shorts/search/MusicSearchResultsController;
        //   204: astore          9
        //   206: aload           9
        //   208: getfield        com/google/android/apps/youtube/app/extensions/reel/creation/shorts/search/MusicSearchResultsController.o:Lacqv;
        //   211: ifnull          523
        //   214: aload           9
        //   216: getfield        com/google/android/apps/youtube/app/extensions/reel/creation/shorts/search/MusicSearchResultsController.p:Lcom/google/android/libraries/youtube/rendering/ui/widget/loadingframe/LoadingFrameLayout;
        //   219: ifnonnull       225
        //   222: goto            523
        //   225: aload           9
        //   227: getfield        com/google/android/apps/youtube/app/extensions/reel/creation/shorts/search/MusicSearchResultsController.n:Lcom/google/android/apps/youtube/app/extensions/reel/creation/shorts/search/MusicSearchSuggestionsController;
        //   230: invokevirtual   com/google/android/apps/youtube/app/extensions/reel/creation/shorts/search/MusicSearchSuggestionsController.g:()V
        //   233: aload           9
        //   235: getfield        com/google/android/apps/youtube/app/extensions/reel/creation/shorts/search/MusicSearchResultsController.t:Landroid/support/v7/widget/RecyclerView;
        //   238: astore          8
        //   240: aload           8
        //   242: ifnull          252
        //   245: aload           8
        //   247: bipush          8
        //   249: invokevirtual   android/support/v7/widget/RecyclerView.setVisibility:(I)V
        //   252: aload           9
        //   254: getfield        com/google/android/apps/youtube/app/extensions/reel/creation/shorts/search/MusicSearchResultsController.s:Landroid/support/v7/widget/RecyclerView;
        //   257: astore          8
        //   259: aload           8
        //   261: ifnull          270
        //   264: aload           8
        //   266: iconst_0       
        //   267: invokevirtual   android/support/v7/widget/RecyclerView.setVisibility:(I)V
        //   270: aload           9
        //   272: getfield        com/google/android/apps/youtube/app/extensions/reel/creation/shorts/search/MusicSearchResultsController.e:Lwyv;
        //   275: invokeinterface wyv.pF:()Lwyw;
        //   280: new             Lwyt;
        //   283: dup            
        //   284: aload_1        
        //   285: invokevirtual   com/google/android/libraries/youtube/innertube/model/SearchResponseModel.d:()[B
        //   288: invokespecial   wyt.<init>:([B)V
        //   291: invokeinterface wyw.D:(Lwzz;)V
        //   296: aload           9
        //   298: getfield        com/google/android/apps/youtube/app/extensions/reel/creation/shorts/search/MusicSearchResultsController.p:Lcom/google/android/libraries/youtube/rendering/ui/widget/loadingframe/LoadingFrameLayout;
        //   301: invokevirtual   com/google/android/libraries/youtube/rendering/ui/widget/loadingframe/LoadingFrameLayout.a:()V
        //   304: aload           9
        //   306: getfield        com/google/android/apps/youtube/app/extensions/reel/creation/shorts/search/MusicSearchResultsController.o:Lacqv;
        //   309: aload_1        
        //   310: invokevirtual   com/google/android/libraries/youtube/innertube/model/SearchResponseModel.e:()Lvgu;
        //   313: invokevirtual   acns.N:(Lvgu;)V
        //   316: aload_1        
        //   317: invokevirtual   com/google/android/libraries/youtube/innertube/model/SearchResponseModel.e:()Lvgu;
        //   320: astore          10
        //   322: aload           10
        //   324: ifnull          523
        //   327: aload           10
        //   329: getfield        vgu.a:Lanyv;
        //   332: getfield        anyv.g:Lanyu;
        //   335: astore          8
        //   337: aload           8
        //   339: astore_1       
        //   340: aload           8
        //   342: ifnonnull       349
        //   345: getstatic       anyu.a:Lanyu;
        //   348: astore_1       
        //   349: aload_1        
        //   350: getfield        anyu.b:I
        //   353: ldc             420115721
        //   355: if_icmpne       523
        //   358: aload           10
        //   360: getfield        vgu.a:Lanyv;
        //   363: getfield        anyv.g:Lanyu;
        //   366: astore          8
        //   368: aload           8
        //   370: astore_1       
        //   371: aload           8
        //   373: ifnonnull       380
        //   376: getstatic       anyu.a:Lanyu;
        //   379: astore_1       
        //   380: aload_1        
        //   381: getfield        anyu.b:I
        //   384: ldc             420115721
        //   386: if_icmpne       400
        //   389: aload_1        
        //   390: getfield        anyu.c:Ljava/lang/Object;
        //   393: checkcast       Lcom/google/protos/youtube/api/innertube/FilterChipBarElementRendererOuterClass$FilterChipBarElementRenderer;
        //   396: astore_1       
        //   397: goto            404
        //   400: getstatic       com/google/protos/youtube/api/innertube/FilterChipBarElementRendererOuterClass$FilterChipBarElementRenderer.a:Lcom/google/protos/youtube/api/innertube/FilterChipBarElementRendererOuterClass$FilterChipBarElementRenderer;
        //   403: astore_1       
        //   404: new             Lackm;
        //   407: dup            
        //   408: invokespecial   ackm.<init>:()V
        //   411: astore          8
        //   413: aload           8
        //   415: aload           9
        //   417: getfield        com/google/android/apps/youtube/app/extensions/reel/creation/shorts/search/MusicSearchResultsController.e:Lwyv;
        //   420: invokeinterface wyv.pF:()Lwyw;
        //   425: invokevirtual   wyy.a:(Lwyw;)V
        //   428: aload           9
        //   430: getfield        com/google/android/apps/youtube/app/extensions/reel/creation/shorts/search/MusicSearchResultsController.m:Lactr;
        //   433: aload           8
        //   435: aload_1        
        //   436: invokevirtual   actr.d:(Lackm;Lcom/google/protos/youtube/api/innertube/FilterChipBarElementRendererOuterClass$FilterChipBarElementRenderer;)V
        //   439: aload           9
        //   441: aload           9
        //   443: getfield        com/google/android/apps/youtube/app/extensions/reel/creation/shorts/search/MusicSearchResultsController.m:Lactr;
        //   446: invokevirtual   actr.a:()Landroid/view/View;
        //   449: putfield        com/google/android/apps/youtube/app/extensions/reel/creation/shorts/search/MusicSearchResultsController.v:Landroid/view/View;
        //   452: aload           9
        //   454: getfield        com/google/android/apps/youtube/app/extensions/reel/creation/shorts/search/MusicSearchResultsController.u:Landroid/widget/FrameLayout;
        //   457: astore_1       
        //   458: aload           9
        //   460: getfield        com/google/android/apps/youtube/app/extensions/reel/creation/shorts/search/MusicSearchResultsController.v:Landroid/view/View;
        //   463: astore          10
        //   465: aload_1        
        //   466: ifnull          508
        //   469: aload           10
        //   471: ifnonnull       477
        //   474: goto            508
        //   477: aload           10
        //   479: invokevirtual   android/view/View.getParent:()Landroid/view/ViewParent;
        //   482: astore          8
        //   484: aload           8
        //   486: instanceof      Landroid/view/ViewGroup;
        //   489: ifeq            502
        //   492: aload           8
        //   494: checkcast       Landroid/view/ViewGroup;
        //   497: aload           10
        //   499: invokevirtual   android/view/ViewGroup.removeView:(Landroid/view/View;)V
        //   502: aload_1        
        //   503: aload           10
        //   505: invokevirtual   android/view/ViewGroup.addView:(Landroid/view/View;)V
        //   508: aload           9
        //   510: getfield        com/google/android/apps/youtube/app/extensions/reel/creation/shorts/search/MusicSearchResultsController.u:Landroid/widget/FrameLayout;
        //   513: astore_1       
        //   514: aload_1        
        //   515: ifnull          523
        //   518: aload_1        
        //   519: iconst_0       
        //   520: invokevirtual   android/widget/FrameLayout.setVisibility:(I)V
        //   523: return         
        //   524: aload_0        
        //   525: getfield        esc.a:Ljava/lang/Object;
        //   528: astore          8
        //   530: aload_1        
        //   531: checkcast       Lcom/google/android/libraries/youtube/innertube/model/player/PlayerResponseModel;
        //   534: astore_1       
        //   535: aload           8
        //   537: checkcast       Lhcq;
        //   540: aload_1        
        //   541: invokevirtual   hcq.m:(Lcom/google/android/libraries/youtube/innertube/model/player/PlayerResponseModel;)V
        //   544: return         
        //   545: aload_0        
        //   546: getfield        esc.a:Ljava/lang/Object;
        //   549: astore          9
        //   551: aload_1        
        //   552: checkcast       Ljava/util/List;
        //   555: astore          8
        //   557: aload           9
        //   559: checkcast       Lhbx;
        //   562: astore_1       
        //   563: aload_1        
        //   564: getfield        hbx.aj:Ljava/lang/String;
        //   567: invokestatic    android/text/TextUtils.isEmpty:(Ljava/lang/CharSequence;)Z
        //   570: ifeq            594
        //   573: aload_1        
        //   574: getfield        hbx.e:Lurz;
        //   577: astore          9
        //   579: aload           9
        //   581: ifnull          594
        //   584: aload           9
        //   586: aload           8
        //   588: invokevirtual   urz.z:(Ljava/util/List;)V
        //   591: goto            642
        //   594: aload_1        
        //   595: getfield        hbx.d:Lula;
        //   598: aload_1        
        //   599: getfield        hbx.ak:I
        //   602: invokevirtual   ula.d:(I)Ljava/util/Map;
        //   605: aload_1        
        //   606: getfield        hbx.aj:Ljava/lang/String;
        //   609: invokeinterface java/util/Map.get:(Ljava/lang/Object;)Ljava/lang/Object;
        //   614: checkcast       Ljava/util/List;
        //   617: astore          9
        //   619: aload           9
        //   621: ifnull          642
        //   624: aload_1        
        //   625: getfield        hbx.e:Lurz;
        //   628: astore          10
        //   630: aload           10
        //   632: ifnull          642
        //   635: aload           10
        //   637: aload           9
        //   639: invokevirtual   urz.z:(Ljava/util/List;)V
        //   642: aload_1        
        //   643: getfield        hbx.af:Landroid/view/View;
        //   646: astore          9
        //   648: aload           9
        //   650: ifnull          660
        //   653: aload           9
        //   655: bipush          8
        //   657: invokevirtual   android/view/View.setVisibility:(I)V
        //   660: aload_1        
        //   661: getfield        hbx.ag:Landroid/view/View;
        //   664: astore          9
        //   666: aload           9
        //   668: ifnull          678
        //   671: aload           9
        //   673: bipush          8
        //   675: invokevirtual   android/view/View.setVisibility:(I)V
        //   678: aload_1        
        //   679: invokevirtual   hbx.r:()Z
        //   682: ifne            740
        //   685: aload_1        
        //   686: getfield        hbx.ag:Landroid/view/View;
        //   689: astore          8
        //   691: aload           8
        //   693: ifnull          702
        //   696: aload           8
        //   698: iconst_0       
        //   699: invokevirtual   android/view/View.setVisibility:(I)V
        //   702: aload_1        
        //   703: getfield        hbx.ao:Laeea;
        //   706: astore          8
        //   708: aload           8
        //   710: ifnull          772
        //   713: aload           8
        //   715: ldc_w           99787
        //   718: invokestatic    xaa.c:(I)Lxab;
        //   721: invokevirtual   aeea.cG:(Lxab;)Ltwx;
        //   724: astore          8
        //   726: aload           8
        //   728: iconst_1       
        //   729: invokevirtual   twx.k:(Z)V
        //   732: aload           8
        //   734: invokevirtual   twx.c:()V
        //   737: goto            772
        //   740: aload           8
        //   742: ifnull          755
        //   745: aload           8
        //   747: invokeinterface java/util/List.isEmpty:()Z
        //   752: ifeq            772
        //   755: aload_1        
        //   756: getfield        hbx.af:Landroid/view/View;
        //   759: astore          8
        //   761: aload           8
        //   763: ifnull          772
        //   766: aload           8
        //   768: iconst_0       
        //   769: invokevirtual   android/view/View.setVisibility:(I)V
        //   772: aload_1        
        //   773: getfield        hbx.ai:I
        //   776: iconst_m1      
        //   777: if_icmpne       781
        //   780: return         
        //   781: aload_1        
        //   782: getfield        hbx.b:Ljava/util/concurrent/Executor;
        //   785: new             Lgxo;
        //   788: dup            
        //   789: aload_1        
        //   790: bipush          11
        //   792: invokespecial   gxo.<init>:(Lhbx;I)V
        //   795: invokestatic    aeun.h:(Ljava/lang/Runnable;)Ljava/lang/Runnable;
        //   798: invokeinterface java/util/concurrent/Executor.execute:(Ljava/lang/Runnable;)V
        //   803: return         
        //   804: aload_0        
        //   805: getfield        esc.a:Ljava/lang/Object;
        //   808: astore          8
        //   810: aload_1        
        //   811: checkcast       Laezp;
        //   814: invokevirtual   aezp.f:()Ljava/lang/Object;
        //   817: checkcast       Landroid/graphics/Bitmap;
        //   820: astore_1       
        //   821: aload           8
        //   823: checkcast       Landroid/view/View;
        //   826: ldc_w           2131429152
        //   829: invokevirtual   android/view/View.findViewById:(I)Landroid/view/View;
        //   832: checkcast       Landroid/widget/ImageView;
        //   835: aload_1        
        //   836: invokevirtual   android/widget/ImageView.setImageBitmap:(Landroid/graphics/Bitmap;)V
        //   839: return         
        //   840: aload_0        
        //   841: getfield        esc.a:Ljava/lang/Object;
        //   844: astore          8
        //   846: aload_1        
        //   847: checkcast       Landroid/net/Uri;
        //   850: astore          10
        //   852: aload           8
        //   854: checkcast       Lgyf;
        //   857: astore_1       
        //   858: aload_1        
        //   859: getfield        gyf.j:Lfzw;
        //   862: getstatic       apht.br:Lapht;
        //   865: invokevirtual   fzw.K:(Lapht;)V
        //   868: aload_1        
        //   869: getfield        gyf.h:Lhbo;
        //   872: astore          9
        //   874: aload           9
        //   876: ifnull          1412
        //   879: aload           9
        //   881: getfield        hbo.d:Lhbp;
        //   884: getfield        hbp.g:Luby;
        //   887: astore_1       
        //   888: aload_1        
        //   889: invokevirtual   java/lang/Object.getClass:()Ljava/lang/Class;
        //   892: pop            
        //   893: ldc_w           "REMIX"
        //   896: ldc_w           ".mp4"
        //   899: aload_1        
        //   900: invokevirtual   ucd.g:()Ljava/io/File;
        //   903: invokestatic    java/io/File.createTempFile:(Ljava/lang/String;Ljava/lang/String;Ljava/io/File;)Ljava/io/File;
        //   906: astore          11
        //   908: new             Ljava/io/FileOutputStream;
        //   911: astore          12
        //   913: aload           12
        //   915: aload           11
        //   917: invokespecial   java/io/FileOutputStream.<init>:(Ljava/io/File;)V
        //   920: aload           9
        //   922: getfield        hbo.d:Lhbp;
        //   925: getfield        hbp.g:Luby;
        //   928: invokevirtual   uby.r:()Lafeq;
        //   931: astore          14
        //   933: aload           9
        //   935: getfield        hbo.e:Lpvh;
        //   938: astore          8
        //   940: aload           9
        //   942: getfield        hbo.a:Landroid/net/Uri;
        //   945: astore          13
        //   947: aload           9
        //   949: getfield        hbo.b:Larbk;
        //   952: astore_1       
        //   953: aload           8
        //   955: getfield        pvh.a:Ljava/lang/Object;
        //   958: checkcast       Lhbp;
        //   961: getfield        hbp.b:Landroid/content/Context;
        //   964: astore          15
        //   966: aload_1        
        //   967: getfield        arbk.f:Larbj;
        //   970: astore          8
        //   972: aload           8
        //   974: astore_1       
        //   975: aload           8
        //   977: ifnonnull       984
        //   980: getstatic       arbj.a:Larbj;
        //   983: astore_1       
        //   984: aload_1        
        //   985: getfield        arbj.d:I
        //   988: i2l            
        //   989: invokestatic    j$/time/Duration.ofMillis:(J)Lj$/time/Duration;
        //   992: invokestatic    afsp.a:(Lj$/time/Duration;)J
        //   995: lstore          6
        //   997: aload           10
        //   999: invokevirtual   android/net/Uri.toString:()Ljava/lang/String;
        //  1002: astore_1       
        //  1003: new             Lrdz;
        //  1006: astore          8
        //  1008: aload           8
        //  1010: aload           15
        //  1012: aconst_null    
        //  1013: aload           13
        //  1015: lconst_0       
        //  1016: lload           6
        //  1018: aload           10
        //  1020: fconst_1       
        //  1021: lconst_0       
        //  1022: aconst_null    
        //  1023: iconst_0       
        //  1024: ldc2_w          9223372036854775807
        //  1027: aload_1        
        //  1028: fconst_0       
        //  1029: invokestatic    afeq.q:()Lafeq;
        //  1032: fconst_0       
        //  1033: invokespecial   rdz.<init>:(Landroid/content/Context;Ljava/io/File;Landroid/net/Uri;JJLandroid/net/Uri;FJLrbe;ZJLjava/lang/String;FLafeq;F)V
        //  1036: aload           8
        //  1038: aload           12
        //  1040: invokevirtual   java/io/FileOutputStream.getChannel:()Ljava/nio/channels/FileChannel;
        //  1043: invokevirtual   rdz.d:(Ljava/nio/channels/WritableByteChannel;)V
        //  1046: aload           14
        //  1048: invokevirtual   afeq.size:()I
        //  1051: istore_3       
        //  1052: aload           9
        //  1054: getfield        hbo.c:I
        //  1057: istore_2       
        //  1058: iload_3        
        //  1059: iload_2        
        //  1060: if_icmple       1232
        //  1063: aload           9
        //  1065: getfield        hbo.b:Larbk;
        //  1068: aload           14
        //  1070: iload_2        
        //  1071: invokevirtual   afeq.get:(I)Ljava/lang/Object;
        //  1074: invokevirtual   ahbh.equals:(Ljava/lang/Object;)Z
        //  1077: ifeq            1232
        //  1080: aload           9
        //  1082: getfield        hbo.d:Lhbp;
        //  1085: getfield        hbp.g:Luby;
        //  1088: astore          8
        //  1090: aload           9
        //  1092: getfield        hbo.c:I
        //  1095: istore_2       
        //  1096: aload           11
        //  1098: invokevirtual   java/io/File.getName:()Ljava/lang/String;
        //  1101: astore          10
        //  1103: aload           8
        //  1105: getfield        uby.c:Ljava/lang/Object;
        //  1108: astore_1       
        //  1109: aload_1        
        //  1110: monitorenter   
        //  1111: aload           8
        //  1113: getfield        uby.d:Ljava/util/List;
        //  1116: invokeinterface java/util/List.isEmpty:()Z
        //  1121: ifeq            1129
        //  1124: aload_1        
        //  1125: monitorexit    
        //  1126: goto            1232
        //  1129: aload           8
        //  1131: getfield        uby.d:Ljava/util/List;
        //  1134: iload_2        
        //  1135: invokeinterface java/util/List.get:(I)Ljava/lang/Object;
        //  1140: checkcast       Larbk;
        //  1143: astore          11
        //  1145: getstatic       arbk.a:Larbk;
        //  1148: aload           11
        //  1150: invokevirtual   ahbh.createBuilder:(Lahbh;)Lahaz;
        //  1153: astore          12
        //  1155: aload           12
        //  1157: invokevirtual   ahaz.copyOnWrite:()V
        //  1160: aload           12
        //  1162: getfield        ahaz.instance:Lahbh;
        //  1165: checkcast       Larbk;
        //  1168: astore          11
        //  1170: aload           10
        //  1172: invokevirtual   java/lang/Object.getClass:()Ljava/lang/Class;
        //  1175: pop            
        //  1176: aload           11
        //  1178: iconst_1       
        //  1179: aload           11
        //  1181: getfield        arbk.b:I
        //  1184: ior            
        //  1185: putfield        arbk.b:I
        //  1188: aload           11
        //  1190: aload           10
        //  1192: putfield        arbk.e:Ljava/lang/String;
        //  1195: aload           8
        //  1197: getfield        uby.d:Ljava/util/List;
        //  1200: iload_2        
        //  1201: aload           12
        //  1203: invokevirtual   ahaz.build:()Lahbh;
        //  1206: checkcast       Larbk;
        //  1209: invokeinterface java/util/List.set:(ILjava/lang/Object;)Ljava/lang/Object;
        //  1214: pop            
        //  1215: aload           8
        //  1217: invokevirtual   uby.M:()V
        //  1220: aload_1        
        //  1221: monitorexit    
        //  1222: goto            1232
        //  1225: astore          8
        //  1227: aload_1        
        //  1228: monitorexit    
        //  1229: aload           8
        //  1231: athrow         
        //  1232: aload           9
        //  1234: getfield        hbo.d:Lhbp;
        //  1237: getfield        hbp.h:Ljava/util/Deque;
        //  1240: astore_1       
        //  1241: aload_1        
        //  1242: monitorenter   
        //  1243: aload           9
        //  1245: getfield        hbo.d:Lhbp;
        //  1248: iconst_0       
        //  1249: putfield        hbp.i:Z
        //  1252: aload_1        
        //  1253: monitorexit    
        //  1254: aload           9
        //  1256: getfield        hbo.d:Lhbp;
        //  1259: getfield        hbp.j:Lpvh;
        //  1262: astore_1       
        //  1263: aload_1        
        //  1264: ifnull          1271
        //  1267: aload_1        
        //  1268: invokevirtual   pvh.K:()V
        //  1271: aload           9
        //  1273: getfield        hbo.d:Lhbp;
        //  1276: invokevirtual   hbp.m:()V
        //  1279: return         
        //  1280: astore          8
        //  1282: aload_1        
        //  1283: monitorexit    
        //  1284: aload           8
        //  1286: athrow         
        //  1287: astore_1       
        //  1288: goto            1351
        //  1291: astore_1       
        //  1292: aload_1        
        //  1293: invokestatic    hbo.a:(Ljava/lang/Throwable;)V
        //  1296: aload           9
        //  1298: getfield        hbo.d:Lhbp;
        //  1301: getfield        hbp.h:Ljava/util/Deque;
        //  1304: astore_1       
        //  1305: aload_1        
        //  1306: monitorenter   
        //  1307: aload           9
        //  1309: getfield        hbo.d:Lhbp;
        //  1312: iconst_0       
        //  1313: putfield        hbp.i:Z
        //  1316: aload_1        
        //  1317: monitorexit    
        //  1318: aload           9
        //  1320: getfield        hbo.d:Lhbp;
        //  1323: getfield        hbp.j:Lpvh;
        //  1326: astore_1       
        //  1327: aload_1        
        //  1328: ifnull          1335
        //  1331: aload_1        
        //  1332: invokevirtual   pvh.K:()V
        //  1335: aload           9
        //  1337: getfield        hbo.d:Lhbp;
        //  1340: invokevirtual   hbp.m:()V
        //  1343: return         
        //  1344: astore          8
        //  1346: aload_1        
        //  1347: monitorexit    
        //  1348: aload           8
        //  1350: athrow         
        //  1351: aload           9
        //  1353: getfield        hbo.d:Lhbp;
        //  1356: getfield        hbp.h:Ljava/util/Deque;
        //  1359: astore          8
        //  1361: aload           8
        //  1363: monitorenter   
        //  1364: aload           9
        //  1366: getfield        hbo.d:Lhbp;
        //  1369: iconst_0       
        //  1370: putfield        hbp.i:Z
        //  1373: aload           8
        //  1375: monitorexit    
        //  1376: aload           9
        //  1378: getfield        hbo.d:Lhbp;
        //  1381: getfield        hbp.j:Lpvh;
        //  1384: astore          8
        //  1386: aload           8
        //  1388: ifnull          1396
        //  1391: aload           8
        //  1393: invokevirtual   pvh.K:()V
        //  1396: aload           9
        //  1398: getfield        hbo.d:Lhbp;
        //  1401: invokevirtual   hbp.m:()V
        //  1404: aload_1        
        //  1405: athrow         
        //  1406: astore_1       
        //  1407: aload           8
        //  1409: monitorexit    
        //  1410: aload_1        
        //  1411: athrow         
        //  1412: return         
        //  1413: aload_0        
        //  1414: getfield        esc.a:Ljava/lang/Object;
        //  1417: astore          8
        //  1419: aload_1        
        //  1420: checkcast       Lcom/google/android/libraries/youtube/innertube/model/WatchNextResponseModel;
        //  1423: astore_1       
        //  1424: getstatic       fca.e:I
        //  1427: istore_2       
        //  1428: aload_1        
        //  1429: getfield        com/google/android/libraries/youtube/innertube/model/WatchNextResponseModel.a:Lalem;
        //  1432: astore_1       
        //  1433: aload           8
        //  1435: checkcast       Lcom/google/android/apps/youtube/app/extensions/lens/LensController;
        //  1438: astore          9
        //  1440: aload           9
        //  1442: getfield        com/google/android/apps/youtube/app/extensions/lens/LensController.b:Z
        //  1445: ifeq            1699
        //  1448: aload_1        
        //  1449: getfield        alem.f:Lanuu;
        //  1452: astore          8
        //  1454: aload           8
        //  1456: astore_1       
        //  1457: aload           8
        //  1459: ifnonnull       1466
        //  1462: getstatic       anuu.a:Lanuu;
        //  1465: astore_1       
        //  1466: aload_1        
        //  1467: getstatic       alnq.b:Lahbf;
        //  1470: invokevirtual   ahbc.rx:(Lahaq;)Ljava/lang/Object;
        //  1473: checkcast       Lalnq;
        //  1476: astore          10
        //  1478: aload           10
        //  1480: getfield        alnq.c:I
        //  1483: istore_2       
        //  1484: iload_2        
        //  1485: bipush          8
        //  1487: iand           
        //  1488: ifeq            1527
        //  1491: aload           9
        //  1493: getfield        com/google/android/apps/youtube/app/extensions/lens/LensController.c:Lvcy;
        //  1496: astore          9
        //  1498: aload           10
        //  1500: getfield        alnq.g:Laiqj;
        //  1503: astore          8
        //  1505: aload           8
        //  1507: astore_1       
        //  1508: aload           8
        //  1510: ifnonnull       1517
        //  1513: getstatic       aiqj.a:Laiqj;
        //  1516: astore_1       
        //  1517: aload           9
        //  1519: aload_1        
        //  1520: aconst_null    
        //  1521: invokeinterface vcy.c:(Laiqj;Ljava/util/Map;)V
        //  1526: return         
        //  1527: iload_2        
        //  1528: iconst_1       
        //  1529: iand           
        //  1530: ifeq            1615
        //  1533: aload           9
        //  1535: getfield        com/google/android/apps/youtube/app/extensions/lens/LensController.d:Latke;
        //  1538: invokeinterface atke.a:()Ljava/lang/Object;
        //  1543: checkcast       Lelx;
        //  1546: getfield        elx.a:Ljava/lang/Object;
        //  1549: astore_1       
        //  1550: aload_1        
        //  1551: ifnull          1615
        //  1554: aload_1        
        //  1555: checkcast       Lcom/google/android/apps/youtube/app/watch/panel/ui/DefaultWatchPanelViewController;
        //  1558: getfield        com/google/android/apps/youtube/app/watch/panel/ui/DefaultWatchPanelViewController.d:Luve;
        //  1561: astore          11
        //  1563: aload           10
        //  1565: getfield        alnq.d:Lajpm;
        //  1568: astore          8
        //  1570: aload           8
        //  1572: astore_1       
        //  1573: aload           8
        //  1575: ifnonnull       1582
        //  1578: getstatic       ajpm.a:Lajpm;
        //  1581: astore_1       
        //  1582: aload_1        
        //  1583: getfield        ajpm.b:I
        //  1586: ldc_w           138681066
        //  1589: if_icmpne       1603
        //  1592: aload_1        
        //  1593: getfield        ajpm.c:Ljava/lang/Object;
        //  1596: checkcast       Lajpq;
        //  1599: astore_1       
        //  1600: goto            1607
        //  1603: getstatic       ajpq.b:Lajpq;
        //  1606: astore_1       
        //  1607: aload           11
        //  1609: aload_1        
        //  1610: invokeinterface uve.o:(Lajpq;)V
        //  1615: aload           10
        //  1617: getfield        alnq.c:I
        //  1620: istore_2       
        //  1621: iload_2        
        //  1622: iconst_2       
        //  1623: iand           
        //  1624: ifeq            1699
        //  1627: iload_2        
        //  1628: iconst_4       
        //  1629: iand           
        //  1630: ifeq            1699
        //  1633: aload           9
        //  1635: getfield        com/google/android/apps/youtube/app/extensions/lens/LensController.e:Ljava/util/LinkedHashMap;
        //  1638: astore          12
        //  1640: aload           10
        //  1642: getfield        alnq.f:Ljava/lang/String;
        //  1645: astore          11
        //  1647: aload           10
        //  1649: getfield        alnq.e:Laiqj;
        //  1652: astore          8
        //  1654: aload           8
        //  1656: astore_1       
        //  1657: aload           8
        //  1659: ifnonnull       1666
        //  1662: getstatic       aiqj.a:Laiqj;
        //  1665: astore_1       
        //  1666: aload           12
        //  1668: aload           11
        //  1670: aload_1        
        //  1671: invokevirtual   java/util/LinkedHashMap.put:(Ljava/lang/Object;Ljava/lang/Object;)Ljava/lang/Object;
        //  1674: pop            
        //  1675: aload           9
        //  1677: getfield        com/google/android/apps/youtube/app/extensions/lens/LensController.a:Latke;
        //  1680: invokeinterface atke.a:()Ljava/lang/Object;
        //  1685: checkcast       Labpq;
        //  1688: invokevirtual   abpq.f:()Z
        //  1691: ifeq            1699
        //  1694: aload           9
        //  1696: invokevirtual   com/google/android/apps/youtube/app/extensions/lens/LensController.g:()V
        //  1699: return         
        //  1700: aload_0        
        //  1701: getfield        esc.a:Ljava/lang/Object;
        //  1704: aload_1        
        //  1705: checkcast       Lvvl;
        //  1708: invokeinterface dbf.mX:(Ljava/lang/Object;)V
        //  1713: return         
        //  1714: aload_0        
        //  1715: getfield        esc.a:Ljava/lang/Object;
        //  1718: astore          8
        //  1720: aload_1        
        //  1721: checkcast       Ljqf;
        //  1724: getfield        jqf.v:Z
        //  1727: ifeq            1737
        //  1730: getstatic       gmw.b:Lgmw;
        //  1733: astore_1       
        //  1734: goto            1741
        //  1737: getstatic       gmw.a:Lgmw;
        //  1740: astore_1       
        //  1741: aload           8
        //  1743: aload_1        
        //  1744: invokeinterface ashj.c:(Ljava/lang/Object;)V
        //  1749: return         
        //  1750: aload_0        
        //  1751: getfield        esc.a:Ljava/lang/Object;
        //  1754: astore          8
        //  1756: aload_1        
        //  1757: checkcast       Ljava/lang/Long;
        //  1760: astore_1       
        //  1761: aload           8
        //  1763: checkcast       Lcom/google/android/apps/youtube/app/datasaving/DefaultNetworkDataUsageMonitor;
        //  1766: astore          8
        //  1768: aload           8
        //  1770: new             Lgmu;
        //  1773: dup            
        //  1774: aload           8
        //  1776: invokespecial   gmu.<init>:(Lcom/google/android/apps/youtube/app/datasaving/DefaultNetworkDataUsageMonitor;)V
        //  1779: putfield        com/google/android/apps/youtube/app/datasaving/DefaultNetworkDataUsageMonitor.d:Landroid/app/usage/NetworkStatsManager$UsageCallback;
        //  1782: aload           8
        //  1784: getfield        com/google/android/apps/youtube/app/datasaving/DefaultNetworkDataUsageMonitor.a:Landroid/app/usage/NetworkStatsManager;
        //  1787: iconst_0       
        //  1788: aconst_null    
        //  1789: aload_1        
        //  1790: invokevirtual   java/lang/Long.longValue:()J
        //  1793: aload           8
        //  1795: getfield        com/google/android/apps/youtube/app/datasaving/DefaultNetworkDataUsageMonitor.d:Landroid/app/usage/NetworkStatsManager$UsageCallback;
        //  1798: aload           8
        //  1800: getfield        com/google/android/apps/youtube/app/datasaving/DefaultNetworkDataUsageMonitor.c:Landroid/os/Handler;
        //  1803: invokevirtual   android/app/usage/NetworkStatsManager.registerUsageCallback:(ILjava/lang/String;JLandroid/app/usage/NetworkStatsManager$UsageCallback;Landroid/os/Handler;)V
        //  1806: return         
        //  1807: aload_0        
        //  1808: getfield        esc.a:Ljava/lang/Object;
        //  1811: astore          12
        //  1813: aload_1        
        //  1814: checkcast       Lalcg;
        //  1817: astore          11
        //  1819: aload           12
        //  1821: checkcast       Lfyw;
        //  1824: astore          9
        //  1826: aload           9
        //  1828: getfield        fyw.j:Z
        //  1831: ifeq            1835
        //  1834: return         
        //  1835: aload           9
        //  1837: aload           11
        //  1839: getfield        alcg.e:Lahbx;
        //  1842: aload           9
        //  1844: getfield        fyw.c:Ljava/util/ArrayList;
        //  1847: aload           9
        //  1849: getfield        fyw.d:Ljava/util/ArrayList;
        //  1852: aload           9
        //  1854: getfield        fyw.e:Ljava/util/ArrayList;
        //  1857: aload           9
        //  1859: getfield        fyw.f:Ljava/util/ArrayList;
        //  1862: aload           9
        //  1864: getfield        fyw.b:Ljava/lang/String;
        //  1867: invokevirtual   fyw.d:(Ljava/util/List;Ljava/util/List;Ljava/util/List;Ljava/util/List;Ljava/util/List;Ljava/lang/String;)V
        //  1870: aload           10
        //  1872: astore_1       
        //  1873: aload           11
        //  1875: getfield        alcg.b:I
        //  1878: iconst_2       
        //  1879: iand           
        //  1880: ifeq            1920
        //  1883: aload           11
        //  1885: getfield        alcg.d:Lalch;
        //  1888: astore          8
        //  1890: aload           8
        //  1892: astore_1       
        //  1893: aload           8
        //  1895: ifnonnull       1902
        //  1898: getstatic       alch.a:Lalch;
        //  1901: astore_1       
        //  1902: aload_1        
        //  1903: getfield        alch.b:Laoua;
        //  1906: astore          8
        //  1908: aload           8
        //  1910: astore_1       
        //  1911: aload           8
        //  1913: ifnonnull       1920
        //  1916: getstatic       aoua.a:Laoua;
        //  1919: astore_1       
        //  1920: aload_1        
        //  1921: ifnonnull       1940
        //  1924: aload           9
        //  1926: getstatic       aeyo.a:Laeyo;
        //  1929: putfield        fyw.g:Laezp;
        //  1932: aload           9
        //  1934: invokevirtual   fyw.b:()V
        //  1937: goto            1990
        //  1940: aload           9
        //  1942: aload_1        
        //  1943: getfield        aoua.d:Ljava/lang/String;
        //  1946: invokestatic    aezp.k:(Ljava/lang/Object;)Laezp;
        //  1949: putfield        fyw.g:Laezp;
        //  1952: aload_1        
        //  1953: getfield        aoua.c:I
        //  1956: istore_2       
        //  1957: iload_2        
        //  1958: ifeq            1968
        //  1961: iload_2        
        //  1962: i2l            
        //  1963: lstore          6
        //  1965: goto            1973
        //  1968: ldc2_w          30000
        //  1971: lstore          6
        //  1973: aload           9
        //  1975: getfield        fyw.a:Landroid/os/Handler;
        //  1978: aload           12
        //  1980: lload           6
        //  1982: invokevirtual   android/os/Handler.postDelayed:(Ljava/lang/Runnable;J)Z
        //  1985: pop            
        //  1986: getstatic       fzb.a:Ljava/lang/String;
        //  1989: astore_1       
        //  1990: aload           9
        //  1992: aload           11
        //  1994: getfield        alcg.e:Lahbx;
        //  1997: putfield        fyw.h:Ljava/util/List;
        //  2000: return         
        //  2001: aload_0        
        //  2002: getfield        esc.a:Ljava/lang/Object;
        //  2005: astore          8
        //  2007: aload_1        
        //  2008: checkcast       Ljava/lang/Boolean;
        //  2011: astore_1       
        //  2012: aload           8
        //  2014: checkcast       Lfle;
        //  2017: getfield        fle.b:Ltnu;
        //  2020: iconst_2       
        //  2021: invokeinterface tnu.q:(I)Laels;
        //  2026: astore          8
        //  2028: aload           8
        //  2030: getstatic       tnu.z:I
        //  2033: aload_1        
        //  2034: invokevirtual   java/lang/Boolean.booleanValue:()Z
        //  2037: invokevirtual   aels.e:(IZ)V
        //  2040: aload           8
        //  2042: getstatic       tnu.y:I
        //  2045: iconst_1       
        //  2046: invokevirtual   aels.e:(IZ)V
        //  2049: aload           8
        //  2051: invokevirtual   aels.b:()V
        //  2054: return         
        //  2055: aload_0        
        //  2056: getfield        esc.a:Ljava/lang/Object;
        //  2059: astore          8
        //  2061: aload_1        
        //  2062: checkcast       Lzqd;
        //  2065: astore_1       
        //  2066: aload_1        
        //  2067: ifnull          2123
        //  2070: new             Ljava/util/ArrayList;
        //  2073: dup            
        //  2074: aload           8
        //  2076: checkcast       Lflb;
        //  2079: getfield        flb.a:Ljava/util/Set;
        //  2082: invokespecial   java/util/ArrayList.<init>:(Ljava/util/Collection;)V
        //  2085: astore          8
        //  2087: aload           8
        //  2089: invokeinterface java/util/List.size:()I
        //  2094: istore_3       
        //  2095: iload_2        
        //  2096: iload_3        
        //  2097: if_icmpge       2123
        //  2100: aload           8
        //  2102: iload_2        
        //  2103: invokeinterface java/util/List.get:(I)Ljava/lang/Object;
        //  2108: checkcast       Lfla;
        //  2111: aload_1        
        //  2112: invokeinterface fla.a:(Lzqd;)V
        //  2117: iinc            2, 1
        //  2120: goto            2095
        //  2123: return         
        //  2124: aload_0        
        //  2125: getfield        esc.a:Ljava/lang/Object;
        //  2128: astore          8
        //  2130: aload_1        
        //  2131: checkcast       Ljava/lang/Boolean;
        //  2134: invokevirtual   java/lang/Boolean.booleanValue:()Z
        //  2137: istore          5
        //  2139: aload           8
        //  2141: checkcast       Lfff;
        //  2144: astore_1       
        //  2145: aload_1        
        //  2146: iload           5
        //  2148: aload_1        
        //  2149: getfield        fff.a:Latke;
        //  2152: invokeinterface atke.a:()Ljava/lang/Object;
        //  2157: checkcast       Ljava/lang/Boolean;
        //  2160: invokevirtual   java/lang/Boolean.booleanValue:()Z
        //  2163: iconst_1       
        //  2164: ixor           
        //  2165: invokevirtual   fff.c:(ZZ)V
        //  2168: return         
        //  2169: aload_0        
        //  2170: getfield        esc.a:Ljava/lang/Object;
        //  2173: astore          8
        //  2175: aload_1        
        //  2176: checkcast       Lakzs;
        //  2179: astore_1       
        //  2180: aload           8
        //  2182: checkcast       Lfcg;
        //  2185: getfield        fcg.a:Lvcy;
        //  2188: astore          8
        //  2190: aload           8
        //  2192: ifnull          2207
        //  2195: aload           8
        //  2197: aload_1        
        //  2198: getfield        akzs.c:Lahbx;
        //  2201: aconst_null    
        //  2202: invokeinterface vcy.d:(Ljava/util/List;Ljava/util/Map;)V
        //  2207: return         
        //  2208: aload_0        
        //  2209: getfield        esc.a:Ljava/lang/Object;
        //  2212: astore          8
        //  2214: aload_1        
        //  2215: checkcast       Laldj;
        //  2218: astore_1       
        //  2219: aload           8
        //  2221: checkcast       Leyn;
        //  2224: astore          8
        //  2226: aload           8
        //  2228: invokevirtual   eyn.a:()Z
        //  2231: ifne            2235
        //  2234: return         
        //  2235: aload           8
        //  2237: getfield        eyn.a:Leyo;
        //  2240: astore          9
        //  2242: aload_1        
        //  2243: getfield        aldj.c:Lanuv;
        //  2246: astore          8
        //  2248: aload           8
        //  2250: astore_1       
        //  2251: aload           8
        //  2253: ifnonnull       2260
        //  2256: getstatic       anuv.a:Lanuv;
        //  2259: astore_1       
        //  2260: aload_1        
        //  2261: getstatic       com/google/protos/youtube/api/innertube/ChannelHandleValidationResultRendererOuterClass.channelHandleValidationResultRenderer:Lahbf;
        //  2264: invokevirtual   ahbc.rx:(Lahaq;)Ljava/lang/Object;
        //  2267: checkcast       Laihn;
        //  2270: astore_1       
        //  2271: aload_1        
        //  2272: getfield        aihn.b:I
        //  2275: invokestatic    aefb.T:(I)I
        //  2278: istore_3       
        //  2279: iload_3        
        //  2280: istore_2       
        //  2281: iload_3        
        //  2282: ifne            2287
        //  2285: iconst_1       
        //  2286: istore_2       
        //  2287: iinc            2, -1
        //  2290: iload_2        
        //  2291: iconst_1       
        //  2292: if_icmpeq       2343
        //  2295: iload_2        
        //  2296: iconst_2       
        //  2297: if_icmpeq       2317
        //  2300: iload_2        
        //  2301: iconst_3       
        //  2302: if_icmpeq       2317
        //  2305: iload_2        
        //  2306: iconst_4       
        //  2307: if_icmpeq       2317
        //  2310: invokestatic    ttl.B:()Lttl;
        //  2313: astore_1       
        //  2314: goto            2372
        //  2317: aload_1        
        //  2318: getfield        aihn.c:Lajut;
        //  2321: astore          8
        //  2323: aload           8
        //  2325: astore_1       
        //  2326: aload           8
        //  2328: ifnonnull       2335
        //  2331: getstatic       ajut.a:Lajut;
        //  2334: astore_1       
        //  2335: aload_1        
        //  2336: invokestatic    ttl.A:(Lajut;)Lttl;
        //  2339: astore_1       
        //  2340: goto            2372
        //  2343: aload_1        
        //  2344: getfield        aihn.d:Lajut;
        //  2347: astore          8
        //  2349: aload           8
        //  2351: astore_1       
        //  2352: aload           8
        //  2354: ifnonnull       2361
        //  2357: getstatic       ajut.a:Lajut;
        //  2360: astore_1       
        //  2361: new             Lttl;
        //  2364: dup            
        //  2365: iconst_4       
        //  2366: aconst_null    
        //  2367: aload_1        
        //  2368: invokespecial   ttl.<init>:(ILajut;Lajut;)V
        //  2371: astore_1       
        //  2372: aload           9
        //  2374: aload_1        
        //  2375: invokevirtual   eyo.f:(Lttl;)V
        //  2378: return         
        //  2379: aload_0        
        //  2380: getfield        esc.a:Ljava/lang/Object;
        //  2383: astore          9
        //  2385: aload_1        
        //  2386: checkcast       Lalay;
        //  2389: astore          8
        //  2391: aload           11
        //  2393: astore_1       
        //  2394: aload           8
        //  2396: getfield        alay.b:I
        //  2399: iconst_2       
        //  2400: iand           
        //  2401: ifeq            2423
        //  2404: aload           8
        //  2406: getfield        alay.d:Lanuv;
        //  2409: astore          8
        //  2411: aload           8
        //  2413: astore_1       
        //  2414: aload           8
        //  2416: ifnonnull       2423
        //  2419: getstatic       anuv.a:Lanuv;
        //  2422: astore_1       
        //  2423: aload_1        
        //  2424: getstatic       com/google/protos/youtube/api/innertube/SurveyRenderer.surveyTriggerRenderer:Lahbf;
        //  2427: invokestatic    aakt.v:(Lanuv;Lahaq;)Ljava/lang/Object;
        //  2430: checkcast       Laopp;
        //  2433: astore_1       
        //  2434: aload_1        
        //  2435: ifnull          2504
        //  2438: aload_1        
        //  2439: getfield        aopp.b:I
        //  2442: bipush          16
        //  2444: iand           
        //  2445: ifeq            2504
        //  2448: aload           9
        //  2450: checkcast       Letk;
        //  2453: astore          8
        //  2455: aload           8
        //  2457: getfield        etk.i:Lfjv;
        //  2460: invokeinterface fjv.j:()Lfkr;
        //  2465: getstatic       fkr.d:Lfkr;
        //  2468: if_acmpne       2504
        //  2471: aload           8
        //  2473: getfield        etk.g:Lgbo;
        //  2476: astore          9
        //  2478: aload_1        
        //  2479: getfield        aopp.c:Laopo;
        //  2482: astore          8
        //  2484: aload           8
        //  2486: astore_1       
        //  2487: aload           8
        //  2489: ifnonnull       2496
        //  2492: getstatic       aopo.a:Laopo;
        //  2495: astore_1       
        //  2496: aload           9
        //  2498: aload_1        
        //  2499: invokeinterface gbo.q:(Laopo;)V
        //  2504: return         
        //  2505: aload_0        
        //  2506: getfield        esc.a:Ljava/lang/Object;
        //  2509: astore          9
        //  2511: aload_1        
        //  2512: checkcast       Lakqj;
        //  2515: astore          11
        //  2517: aload           9
        //  2519: checkcast       Letk;
        //  2522: astore          10
        //  2524: aload           10
        //  2526: getfield        etk.k:Lacle;
        //  2529: invokevirtual   java/lang/Object.getClass:()Ljava/lang/Class;
        //  2532: pop            
        //  2533: aload           10
        //  2535: getfield        etk.n:Lwyw;
        //  2538: invokevirtual   java/lang/Object.getClass:()Ljava/lang/Class;
        //  2541: pop            
        //  2542: aload           10
        //  2544: invokevirtual   etk.a:()V
        //  2547: aload           10
        //  2549: aload           11
        //  2551: getfield        akqj.g:Z
        //  2554: putfield        etk.o:Z
        //  2557: aload           10
        //  2559: getfield        etk.n:Lwyw;
        //  2562: new             Lwyt;
        //  2565: dup            
        //  2566: aload           11
        //  2568: getfield        akqj.f:Lahab;
        //  2571: invokevirtual   ahab.I:()[B
        //  2574: invokespecial   wyt.<init>:([B)V
        //  2577: invokeinterface wyw.D:(Lwzz;)V
        //  2582: aload           11
        //  2584: getfield        akqj.c:Lanuv;
        //  2587: astore          9
        //  2589: aload           9
        //  2591: astore_1       
        //  2592: aload           9
        //  2594: ifnonnull       2601
        //  2597: getstatic       anuv.a:Lanuv;
        //  2600: astore_1       
        //  2601: aload_1        
        //  2602: getstatic       com/google/protos/youtube/api/innertube/ElementRendererOuterClass.elementRenderer:Lahbf;
        //  2605: invokevirtual   ahbc.ry:(Lahaq;)Z
        //  2608: ifeq            2644
        //  2611: aload           11
        //  2613: getfield        akqj.c:Lanuv;
        //  2616: astore          9
        //  2618: aload           9
        //  2620: astore_1       
        //  2621: aload           9
        //  2623: ifnonnull       2630
        //  2626: getstatic       anuv.a:Lanuv;
        //  2629: astore_1       
        //  2630: aload_1        
        //  2631: getstatic       com/google/protos/youtube/api/innertube/ElementRendererOuterClass.elementRenderer:Lahbf;
        //  2634: invokevirtual   ahbc.rx:(Lahaq;)Ljava/lang/Object;
        //  2637: checkcast       Lajmo;
        //  2640: astore_1       
        //  2641: goto            2646
        //  2644: aconst_null    
        //  2645: astore_1       
        //  2646: aload_1        
        //  2647: ifnull          2702
        //  2650: aload           10
        //  2652: getfield        etk.c:Laccf;
        //  2655: astore          12
        //  2657: aload           11
        //  2659: getfield        akqj.c:Lanuv;
        //  2662: astore          9
        //  2664: aload           9
        //  2666: astore_1       
        //  2667: aload           9
        //  2669: ifnonnull       2676
        //  2672: getstatic       anuv.a:Lanuv;
        //  2675: astore_1       
        //  2676: aload           12
        //  2678: aload_1        
        //  2679: getstatic       com/google/protos/youtube/api/innertube/ElementRendererOuterClass.elementRenderer:Lahbf;
        //  2682: invokevirtual   ahbc.rx:(Lahaq;)Ljava/lang/Object;
        //  2685: checkcast       Lajmo;
        //  2688: invokevirtual   accf.d:(Lajmo;)Lacbj;
        //  2691: astore_1       
        //  2692: aload           10
        //  2694: getfield        etk.k:Lacle;
        //  2697: aload_1        
        //  2698: invokevirtual   acle.add:(Ljava/lang/Object;)Z
        //  2701: pop            
        //  2702: aload           11
        //  2704: getfield        akqj.e:Lanuv;
        //  2707: astore          9
        //  2709: aload           9
        //  2711: astore_1       
        //  2712: aload           9
        //  2714: ifnonnull       2721
        //  2717: getstatic       anuv.a:Lanuv;
        //  2720: astore_1       
        //  2721: aload_1        
        //  2722: getstatic       com/google/protos/youtube/api/innertube/ElementRendererOuterClass.elementRenderer:Lahbf;
        //  2725: invokevirtual   ahbc.ry:(Lahaq;)Z
        //  2728: ifeq            2764
        //  2731: aload           11
        //  2733: getfield        akqj.e:Lanuv;
        //  2736: astore          9
        //  2738: aload           9
        //  2740: astore_1       
        //  2741: aload           9
        //  2743: ifnonnull       2750
        //  2746: getstatic       anuv.a:Lanuv;
        //  2749: astore_1       
        //  2750: aload_1        
        //  2751: getstatic       com/google/protos/youtube/api/innertube/ElementRendererOuterClass.elementRenderer:Lahbf;
        //  2754: invokevirtual   ahbc.rx:(Lahaq;)Ljava/lang/Object;
        //  2757: checkcast       Lajmo;
        //  2760: astore_1       
        //  2761: goto            2766
        //  2764: aconst_null    
        //  2765: astore_1       
        //  2766: aload_1        
        //  2767: ifnull          2822
        //  2770: aload           10
        //  2772: getfield        etk.c:Laccf;
        //  2775: astore          12
        //  2777: aload           11
        //  2779: getfield        akqj.e:Lanuv;
        //  2782: astore          9
        //  2784: aload           9
        //  2786: astore_1       
        //  2787: aload           9
        //  2789: ifnonnull       2796
        //  2792: getstatic       anuv.a:Lanuv;
        //  2795: astore_1       
        //  2796: aload           12
        //  2798: aload_1        
        //  2799: getstatic       com/google/protos/youtube/api/innertube/ElementRendererOuterClass.elementRenderer:Lahbf;
        //  2802: invokevirtual   ahbc.rx:(Lahaq;)Ljava/lang/Object;
        //  2805: checkcast       Lajmo;
        //  2808: invokevirtual   accf.d:(Lajmo;)Lacbj;
        //  2811: astore_1       
        //  2812: aload           10
        //  2814: getfield        etk.k:Lacle;
        //  2817: aload_1        
        //  2818: invokevirtual   acle.add:(Ljava/lang/Object;)Z
        //  2821: pop            
        //  2822: aload           11
        //  2824: getfield        akqj.d:Lanuv;
        //  2827: astore          9
        //  2829: aload           9
        //  2831: astore_1       
        //  2832: aload           9
        //  2834: ifnonnull       2841
        //  2837: getstatic       anuv.a:Lanuv;
        //  2840: astore_1       
        //  2841: aload_1        
        //  2842: getstatic       com/google/protos/youtube/api/innertube/ElementRendererOuterClass.elementRenderer:Lahbf;
        //  2845: invokevirtual   ahbc.ry:(Lahaq;)Z
        //  2848: ifeq            2882
        //  2851: aload           11
        //  2853: getfield        akqj.d:Lanuv;
        //  2856: astore          8
        //  2858: aload           8
        //  2860: astore_1       
        //  2861: aload           8
        //  2863: ifnonnull       2870
        //  2866: getstatic       anuv.a:Lanuv;
        //  2869: astore_1       
        //  2870: aload_1        
        //  2871: getstatic       com/google/protos/youtube/api/innertube/ElementRendererOuterClass.elementRenderer:Lahbf;
        //  2874: invokevirtual   ahbc.rx:(Lahaq;)Ljava/lang/Object;
        //  2877: checkcast       Lajmo;
        //  2880: astore          8
        //  2882: aload           8
        //  2884: ifnull          2939
        //  2887: aload           10
        //  2889: getfield        etk.c:Laccf;
        //  2892: astore          9
        //  2894: aload           11
        //  2896: getfield        akqj.d:Lanuv;
        //  2899: astore          8
        //  2901: aload           8
        //  2903: astore_1       
        //  2904: aload           8
        //  2906: ifnonnull       2913
        //  2909: getstatic       anuv.a:Lanuv;
        //  2912: astore_1       
        //  2913: aload           9
        //  2915: aload_1        
        //  2916: getstatic       com/google/protos/youtube/api/innertube/ElementRendererOuterClass.elementRenderer:Lahbf;
        //  2919: invokevirtual   ahbc.rx:(Lahaq;)Ljava/lang/Object;
        //  2922: checkcast       Lajmo;
        //  2925: invokevirtual   accf.d:(Lajmo;)Lacbj;
        //  2928: astore_1       
        //  2929: aload           10
        //  2931: getfield        etk.k:Lacle;
        //  2934: aload_1        
        //  2935: invokevirtual   acle.add:(Ljava/lang/Object;)Z
        //  2938: pop            
        //  2939: return         
        //  2940: aload_0        
        //  2941: getfield        esc.a:Ljava/lang/Object;
        //  2944: astore          8
        //  2946: aload_1        
        //  2947: checkcast       Ljava/lang/Boolean;
        //  2950: astore_1       
        //  2951: aload           8
        //  2953: checkcast       Lesm;
        //  2956: aload_1        
        //  2957: invokevirtual   esm.g:(Ljava/lang/Boolean;)V
        //  2960: return         
        //  2961: aload_0        
        //  2962: getfield        esc.a:Ljava/lang/Object;
        //  2965: astore          8
        //  2967: aload_1        
        //  2968: checkcast       Ljava/lang/Boolean;
        //  2971: invokevirtual   java/lang/Boolean.booleanValue:()Z
        //  2974: ifeq            2996
        //  2977: aload           8
        //  2979: checkcast       Lesm;
        //  2982: getfield        esm.ac:Latke;
        //  2985: invokeinterface atke.a:()Ljava/lang/Object;
        //  2990: checkcast       Lzrg;
        //  2993: invokestatic    xmm.z:(Lzrg;)V
        //  2996: return         
        //  2997: aload_0        
        //  2998: getfield        esc.a:Ljava/lang/Object;
        //  3001: astore          8
        //  3003: aload_1        
        //  3004: checkcast       Ljava/lang/Boolean;
        //  3007: invokevirtual   java/lang/Boolean.booleanValue:()Z
        //  3010: ifeq            3058
        //  3013: aload           8
        //  3015: checkcast       Lesm;
        //  3018: getfield        esm.aX:Latke;
        //  3021: invokeinterface atke.a:()Ljava/lang/Object;
        //  3026: checkcast       Ljava/io/File;
        //  3029: invokevirtual   java/io/File.listFiles:()[Ljava/io/File;
        //  3032: astore_1       
        //  3033: aload_1        
        //  3034: ifnull          3058
        //  3037: iload_3        
        //  3038: istore_2       
        //  3039: iload_2        
        //  3040: aload_1        
        //  3041: arraylength    
        //  3042: if_icmpge       3058
        //  3045: aload_1        
        //  3046: iload_2        
        //  3047: aaload         
        //  3048: invokevirtual   java/io/File.delete:()Z
        //  3051: pop            
        //  3052: iinc            2, 1
        //  3055: goto            3039
        //  3058: return         
        //  3059: aload_1        
        //  3060: invokeinterface java/util/List.iterator:()Ljava/util/Iterator;
        //  3065: astore          14
        //  3067: ldc_w           2147483647
        //  3070: istore_2       
        //  3071: aload           9
        //  3073: astore_1       
        //  3074: aload           14
        //  3076: invokeinterface java/util/Iterator.hasNext:()Z
        //  3081: ifeq            3250
        //  3084: aload           14
        //  3086: invokeinterface java/util/Iterator.next:()Ljava/lang/Object;
        //  3091: checkcast       Lcom/google/android/libraries/youtube/innertube/model/media/FormatStreamModel;
        //  3094: astore          9
        //  3096: aload_1        
        //  3097: astore          8
        //  3099: iload_2        
        //  3100: istore_3       
        //  3101: aload           9
        //  3103: ifnull          3242
        //  3106: aload_1        
        //  3107: astore          8
        //  3109: iload_2        
        //  3110: istore_3       
        //  3111: aload           9
        //  3113: getfield        com/google/android/libraries/youtube/innertube/model/media/FormatStreamModel.d:Landroid/net/Uri;
        //  3116: invokevirtual   android/net/Uri.toString:()Ljava/lang/String;
        //  3119: invokevirtual   java/lang/String.isEmpty:()Z
        //  3122: ifne            3242
        //  3125: aload_1        
        //  3126: astore          8
        //  3128: iload_2        
        //  3129: istore_3       
        //  3130: aload           9
        //  3132: invokevirtual   com/google/android/libraries/youtube/innertube/model/media/FormatStreamModel.G:()Z
        //  3135: ifne            3242
        //  3138: aload_1        
        //  3139: astore          8
        //  3141: iload_2        
        //  3142: istore_3       
        //  3143: aload           9
        //  3145: invokevirtual   com/google/android/libraries/youtube/innertube/model/media/FormatStreamModel.P:()Z
        //  3148: ifeq            3242
        //  3151: aload           9
        //  3153: getfield        com/google/android/libraries/youtube/innertube/model/media/FormatStreamModel.a:Lajum;
        //  3156: getfield        ajum.B:I
        //  3159: invokestatic    adyf.ca:(I)I
        //  3162: istore          4
        //  3164: iload           4
        //  3166: ifne            3172
        //  3169: goto            3183
        //  3172: aload_1        
        //  3173: astore          8
        //  3175: iload_2        
        //  3176: istore_3       
        //  3177: iload           4
        //  3179: iconst_4       
        //  3180: if_icmpeq       3242
        //  3183: aload           9
        //  3185: invokevirtual   com/google/android/libraries/youtube/innertube/model/media/FormatStreamModel.f:()I
        //  3188: aload           9
        //  3190: invokevirtual   com/google/android/libraries/youtube/innertube/model/media/FormatStreamModel.c:()I
        //  3193: invokestatic    hga.b:(II)Ljava/lang/String;
        //  3196: astore          8
        //  3198: getstatic       hga.a:Lafev;
        //  3201: aload           8
        //  3203: ldc_w           2147483647
        //  3206: invokestatic    java/lang/Integer.valueOf:(I)Ljava/lang/Integer;
        //  3209: invokevirtual   afev.getOrDefault:(Ljava/lang/Object;Ljava/lang/Object;)Ljava/lang/Object;
        //  3212: checkcast       Ljava/lang/Integer;
        //  3215: invokevirtual   java/lang/Integer.intValue:()I
        //  3218: istore          4
        //  3220: aload_1        
        //  3221: ifnull          3235
        //  3224: aload_1        
        //  3225: astore          8
        //  3227: iload_2        
        //  3228: istore_3       
        //  3229: iload           4
        //  3231: iload_2        
        //  3232: if_icmpge       3242
        //  3235: iload           4
        //  3237: istore_3       
        //  3238: aload           9
        //  3240: astore          8
        //  3242: aload           8
        //  3244: astore_1       
        //  3245: iload_3        
        //  3246: istore_2       
        //  3247: goto            3074
        //  3250: aload_1        
        //  3251: invokestatic    aezp.j:(Ljava/lang/Object;)Laezp;
        //  3254: astore_1       
        //  3255: goto            3268
        //  3258: ldc_w           "VideoIngestionFetchResponseController: No usable video streams found in response"
        //  3261: invokestatic    ttr.b:(Ljava/lang/String;)V
        //  3264: getstatic       aeyo.a:Laeyo;
        //  3267: astore_1       
        //  3268: aload           11
        //  3270: checkcast       Lhga;
        //  3273: astore          8
        //  3275: aload           8
        //  3277: aload_1        
        //  3278: putfield        hga.f:Laezp;
        //  3281: aload           13
        //  3283: invokeinterface com/google/android/libraries/youtube/innertube/model/player/PlayerResponseModel.m:()Lcom/google/android/libraries/youtube/innertube/model/media/PlayerConfigModel;
        //  3288: astore_1       
        //  3289: aload           11
        //  3291: checkcast       Lhga;
        //  3294: getfield        hga.d:Lynp;
        //  3297: aload           12
        //  3299: aload_1        
        //  3300: iconst_1       
        //  3301: invokevirtual   ynp.j:(Lcom/google/android/libraries/youtube/innertube/model/media/VideoStreamingData;Lcom/google/android/libraries/youtube/innertube/model/media/PlayerConfigModel;Z)Lyfu;
        //  3304: astore          9
        //  3306: aload           9
        //  3308: getfield        yfu.c:[Lcom/google/android/libraries/youtube/innertube/model/media/FormatStreamModel;
        //  3311: astore          12
        //  3313: aload           12
        //  3315: ifnull          3422
        //  3318: aload           12
        //  3320: arraylength    
        //  3321: istore_3       
        //  3322: iload_3        
        //  3323: ifne            3329
        //  3326: goto            3422
        //  3329: iconst_0       
        //  3330: istore_2       
        //  3331: iload_2        
        //  3332: iload_3        
        //  3333: if_icmpge       3376
        //  3336: aload           12
        //  3338: iload_2        
        //  3339: aaload         
        //  3340: astore_1       
        //  3341: aload_1        
        //  3342: invokevirtual   com/google/android/libraries/youtube/innertube/model/media/FormatStreamModel.f:()I
        //  3345: iconst_3       
        //  3346: if_icmpne       3370
        //  3349: aload_1        
        //  3350: getfield        com/google/android/libraries/youtube/innertube/model/media/FormatStreamModel.d:Landroid/net/Uri;
        //  3353: invokevirtual   android/net/Uri.toString:()Ljava/lang/String;
        //  3356: invokevirtual   java/lang/String.isEmpty:()Z
        //  3359: ifne            3370
        //  3362: aload_1        
        //  3363: invokestatic    aezp.k:(Ljava/lang/Object;)Laezp;
        //  3366: astore_1       
        //  3367: goto            3447
        //  3370: iinc            2, 1
        //  3373: goto            3331
        //  3376: ldc_w           "VideoIngestionFetchResponseController: Medium quality stream not found, using the first available stream. "
        //  3379: invokestatic    ttr.l:(Ljava/lang/String;)V
        //  3382: aload           9
        //  3384: getfield        yfu.c:[Lcom/google/android/libraries/youtube/innertube/model/media/FormatStreamModel;
        //  3387: iconst_0       
        //  3388: aaload         
        //  3389: getfield        com/google/android/libraries/youtube/innertube/model/media/FormatStreamModel.d:Landroid/net/Uri;
        //  3392: invokevirtual   android/net/Uri.toString:()Ljava/lang/String;
        //  3395: invokevirtual   java/lang/String.isEmpty:()Z
        //  3398: ifne            3415
        //  3401: aload           9
        //  3403: getfield        yfu.c:[Lcom/google/android/libraries/youtube/innertube/model/media/FormatStreamModel;
        //  3406: iconst_0       
        //  3407: aaload         
        //  3408: invokestatic    aezp.k:(Ljava/lang/Object;)Laezp;
        //  3411: astore_1       
        //  3412: goto            3447
        //  3415: getstatic       aeyo.a:Laeyo;
        //  3418: astore_1       
        //  3419: goto            3447
        //  3422: ldc_w           "VideoIngestionFetchResponseController: No usable audio streams found in response"
        //  3425: invokestatic    ttr.b:(Ljava/lang/String;)V
        //  3428: getstatic       aeyo.a:Laeyo;
        //  3431: astore_1       
        //  3432: goto            3447
        //  3435: astore_1       
        //  3436: ldc_w           "VideoIngestionFetchResponseController: Missing audio stream"
        //  3439: aload_1        
        //  3440: invokestatic    ttr.d:(Ljava/lang/String;Ljava/lang/Throwable;)V
        //  3443: getstatic       aeyo.a:Laeyo;
        //  3446: astore_1       
        //  3447: aload           8
        //  3449: aload_1        
        //  3450: putfield        hga.g:Laezp;
        //  3453: goto            3477
        //  3456: aload_1        
        //  3457: ifnull          3466
        //  3460: ldc_w           "Missing visual stream"
        //  3463: invokestatic    hga.c:(Ljava/lang/String;)V
        //  3466: aload           12
        //  3468: ifnull          3477
        //  3471: ldc_w           "Missing audio stream"
        //  3474: invokestatic    hga.c:(Ljava/lang/String;)V
        //  3477: aload           11
        //  3479: checkcast       Lhga;
        //  3482: astore          9
        //  3484: aload           9
        //  3486: getfield        hga.e:Lhfz;
        //  3489: astore          8
        //  3491: aload           8
        //  3493: ifnull          3624
        //  3496: aload           9
        //  3498: getfield        hga.f:Laezp;
        //  3501: astore_1       
        //  3502: aload           9
        //  3504: getfield        hga.g:Laezp;
        //  3507: astore          9
        //  3509: aload_1        
        //  3510: invokevirtual   aezp.h:()Z
        //  3513: ifne            3547
        //  3516: aload           8
        //  3518: checkcast       Lhge;
        //  3521: astore_1       
        //  3522: aload_1        
        //  3523: getfield        hge.b:Lhgg;
        //  3526: getfield        hgg.aC:Ljava/util/concurrent/Executor;
        //  3529: new             Lhdh;
        //  3532: dup            
        //  3533: aload_1        
        //  3534: iconst_2       
        //  3535: invokespecial   hdh.<init>:(Lhge;I)V
        //  3538: invokestatic    aeun.h:(Ljava/lang/Runnable;)Ljava/lang/Runnable;
        //  3541: invokeinterface java/util/concurrent/Executor.execute:(Ljava/lang/Runnable;)V
        //  3546: return         
        //  3547: aload           9
        //  3549: invokevirtual   aezp.h:()Z
        //  3552: ifeq            3577
        //  3555: aload           8
        //  3557: checkcast       Lhge;
        //  3560: getfield        hge.b:Lhgg;
        //  3563: aload           9
        //  3565: invokevirtual   aezp.c:()Ljava/lang/Object;
        //  3568: checkcast       Lcom/google/android/libraries/youtube/innertube/model/media/FormatStreamModel;
        //  3571: getfield        com/google/android/libraries/youtube/innertube/model/media/FormatStreamModel.d:Landroid/net/Uri;
        //  3574: putfield        hgg.ao:Landroid/net/Uri;
        //  3577: aload           8
        //  3579: checkcast       Lhge;
        //  3582: astore          8
        //  3584: aload           8
        //  3586: getfield        hge.b:Lhgg;
        //  3589: aload_1        
        //  3590: invokevirtual   aezp.c:()Ljava/lang/Object;
        //  3593: checkcast       Lcom/google/android/libraries/youtube/innertube/model/media/FormatStreamModel;
        //  3596: invokevirtual   hgg.aP:(Lcom/google/android/libraries/youtube/innertube/model/media/FormatStreamModel;)V
        //  3599: aload           8
        //  3601: getfield        hge.b:Lhgg;
        //  3604: aload_1        
        //  3605: invokevirtual   aezp.c:()Ljava/lang/Object;
        //  3608: checkcast       Lcom/google/android/libraries/youtube/innertube/model/media/FormatStreamModel;
        //  3611: getfield        com/google/android/libraries/youtube/innertube/model/media/FormatStreamModel.d:Landroid/net/Uri;
        //  3614: putfield        hgg.an:Landroid/net/Uri;
        //  3617: aload           8
        //  3619: aload           10
        //  3621: invokevirtual   hge.a:(Lcom/google/android/libraries/youtube/innertube/model/player/PlayerResponseModel;)V
        //  3624: return         
        //    Exceptions:
        //  Try           Handler
        //  Start  End    Start  End    Type                 
        //  -----  -----  -----  -----  ---------------------
        //  879    972    1291   1351   Ljava/io/IOException;
        //  879    972    1287   1412   Any
        //  980    984    1291   1351   Ljava/io/IOException;
        //  980    984    1287   1412   Any
        //  984    1058   1291   1351   Ljava/io/IOException;
        //  984    1058   1287   1412   Any
        //  1063   1111   1291   1351   Ljava/io/IOException;
        //  1063   1111   1287   1412   Any
        //  1111   1126   1225   1232   Any
        //  1129   1222   1225   1232   Any
        //  1227   1229   1225   1232   Any
        //  1229   1232   1291   1351   Ljava/io/IOException;
        //  1229   1232   1287   1412   Any
        //  1243   1254   1280   1287   Any
        //  1282   1284   1280   1287   Any
        //  1292   1296   1287   1412   Any
        //  1307   1318   1344   1351   Any
        //  1346   1348   1344   1351   Any
        //  1364   1376   1406   1412   Any
        //  1407   1410   1406   1412   Any
        //  3289   3306   3435   3447   Lyfw;
        // 
        // The error that occurred was:
        // 
        // java.lang.IndexOutOfBoundsException: Index: 1628, Size: 1628
        //     at java.util.ArrayList.rangeCheck(Unknown Source)
        //     at java.util.ArrayList.get(Unknown Source)
        //     at com.strobel.decompiler.ast.AstBuilder.convertToAst(AstBuilder.java:3362)
        //     at com.strobel.decompiler.ast.AstBuilder.convertToAst(AstBuilder.java:3611)
        //     at com.strobel.decompiler.ast.AstBuilder.build(AstBuilder.java:112)
        //     at com.strobel.decompiler.languages.java.ast.AstMethodBodyBuilder.createMethodBody(AstMethodBodyBuilder.java:203)
        //     at com.strobel.decompiler.languages.java.ast.AstMethodBodyBuilder.createMethodBody(AstMethodBodyBuilder.java:93)
        //     at com.strobel.decompiler.languages.java.ast.AstBuilder.createMethodBody(AstBuilder.java:868)
        //     at com.strobel.decompiler.languages.java.ast.AstBuilder.createMethod(AstBuilder.java:761)
        //     at com.strobel.decompiler.languages.java.ast.AstBuilder.addTypeMembers(AstBuilder.java:638)
        //     at com.strobel.decompiler.languages.java.ast.AstBuilder.createTypeCore(AstBuilder.java:605)
        //     at com.strobel.decompiler.languages.java.ast.AstBuilder.createTypeNoCache(AstBuilder.java:195)
        //     at com.strobel.decompiler.languages.java.ast.AstBuilder.createType(AstBuilder.java:162)
        //     at com.strobel.decompiler.languages.java.ast.AstBuilder.addType(AstBuilder.java:137)
        //     at com.strobel.decompiler.languages.java.JavaLanguage.buildAst(JavaLanguage.java:71)
        //     at com.strobel.decompiler.languages.java.JavaLanguage.decompileType(JavaLanguage.java:59)
        //     at com.strobel.decompiler.DecompilerDriver.decompileType(DecompilerDriver.java:333)
        //     at com.strobel.decompiler.DecompilerDriver.decompileJar(DecompilerDriver.java:254)
        //     at com.strobel.decompiler.DecompilerDriver.main(DecompilerDriver.java:129)
        // 
        throw new IllegalStateException("An error occurred while decompiling this method.");
    }
}
