// 
// Decompiled by Procyon v0.6.0
// 

package com.facebook.litho;

import java.util.ArrayDeque;
import androidx.viewpager.widget.ViewPager;
import android.os.HandlerThread;
import java.util.LinkedList;
import android.graphics.drawable.Drawable;
import android.view.View;
import java.util.Collection;
import java.util.HashSet;
import java.util.Map;
import android.view.ViewGroup;
import android.util.Log;
import android.graphics.Rect;
import java.util.Iterator;
import java.util.concurrent.Executor;
import java.util.ArrayList;
import java.util.List;
import java.util.Deque;
import android.os.Looper;
import java.util.concurrent.atomic.AtomicInteger;

public class ComponentTree
{
    private static final AtomicInteger H;
    private static volatile Looper I;
    public static final String a = "ComponentTree";
    public static final ThreadLocal b;
    public final String A;
    public trw B;
    public trw C;
    public final bhy D;
    public final med E;
    public final ajc F;
    public volatile oqz G;
    private boolean J;
    private String K;
    private Deque L;
    private int M;
    private boolean N;
    private final boolean O;
    private final boolean P;
    private dvn Q;
    private final Runnable R;
    private final Object S;
    private final List T;
    private int U;
    private int V;
    private int W;
    private int X;
    private int Y;
    private int Z;
    private final eae aa;
    private volatile ema ab;
    private bhy ac;
    private final cyd ad;
    private cyd ae;
    private final hho af;
    public final boolean c;
    public List d;
    public final Object e;
    public dtn f;
    public final dta g;
    public boolean h;
    public final boolean i;
    public final boolean j;
    public boolean k;
    public final boolean l;
    public dvx m;
    public dvn n;
    public final Object o;
    public dtk p;
    public volatile boolean q;
    public volatile boolean r;
    public dsw s;
    public dvi t;
    public dvi u;
    public dwv v;
    public final int w;
    public final duo x;
    public final boolean y;
    public final boolean z;
    
    static {
        H = new AtomicInteger(0);
        b = new ThreadLocal();
    }
    
    public ComponentTree(final dtj dtj) {
        this.F = new ajc((byte[])null);
        this.e = new Object();
        this.Q = (dvn)new dvm(Looper.getMainLooper());
        this.R = (Runnable)new dew(this, 3);
        this.o = new Object();
        this.S = new Object();
        this.T = new ArrayList();
        this.U = -1;
        this.W = -1;
        this.X = -1;
        this.Y = -1;
        this.Z = -1;
        this.D = new bhy((char[])null);
        this.af = new hho((byte[])null, (byte[])null);
        this.ad = new cyd((byte[])null, (byte[])null, (char[])null);
        final dta g = new dta(dtj.a, new dwv((dwv)null), (cyd)null, (pb)null, (byte[])null, (byte[])null, (byte[])null, (byte[])null);
        g.h = this;
        g.e = null;
        this.g = g;
        this.s = dtj.c;
        boolean i;
        if (dtj.d) {
            final boolean a = dys.a;
            i = true;
        }
        else {
            i = false;
        }
        this.i = i;
        this.j = dtj.b;
        this.O = dtj.e;
        this.P = dtj.f;
        this.n = dtj.g;
        this.l = true;
        this.q = dtj.i;
        this.r = false;
        this.g(dtj.j);
        this.z = dtj.m;
        final boolean a2 = dys.a;
        this.y = dtj.k;
        this.x = dtj.l;
        dwv v;
        if ((v = dtj.h) == null) {
            v = dwv.a((dwv)null);
        }
        this.v = v;
        this.w = ComponentTree.H.getAndIncrement();
        this.aa = new eae(this);
        final dvn q = this.Q;
        final duw a3 = bih.a;
        this.Q = q;
        Object o;
        if ((o = this.n) == null) {
            if (dys.u == null) {
                o = new dvm(z());
            }
            else {
                if (dwy.a == null) {
                    synchronized (dwy.class) {
                        if (dwy.a == null) {
                            dwy.a = new dwy(dwy.c, (byte[])null);
                        }
                    }
                }
                o = dwy.a;
            }
        }
        Object n;
        if (dys.o) {
            n = o;
            if (o instanceof dwy) {
                n = new dur(afxr.f(((dwy)o).b));
            }
            final duw a4 = bih.a;
        }
        else {
            n = new dws((dvn)o);
            final duw a5 = bih.a;
        }
        this.n = (dvn)n;
        this.E = dtj.o;
        this.A = dtj.n;
        this.c = dsm.a(g.b);
    }
    
    private final void A() {
        this.af.h();
    }
    
    private final void B() {
        monitorenter(this);
        try {
            final dvi u = this.u;
            if (u != null) {
                final cyd ad = this.ad;
                final ema g = u.G;
                if (g != null) {
                    final Object a = g.a;
                    if (a != null) {
                        final Iterator iterator = ((Map)a).keySet().iterator();
                        while (iterator.hasNext()) {
                            final hzf hzf = ((Map<K, hzf>)g.a).get(iterator.next());
                            for (int size = ((List)hzf.c).size(), i = 0; i < size; ++i) {
                                final dsw dsw = ((List<dsw>)hzf.c).get(i);
                                final String s = ((List<String>)hzf.a).get(i);
                                final Object b = hzf.b;
                                if (ad.s(dsw)) {
                                    final dta p = dsw.p;
                                    final Object b2 = hzf.b;
                                    ((dtg)dsw).ao();
                                }
                            }
                        }
                    }
                }
            }
            ((Map)this.ad.a).clear();
            monitorexit(this);
        }
        finally {
            monitorexit(this);
            while (true) {}
        }
    }
    
    private final void C(Rect bounds, boolean b) {
        final dvi t = this.t;
        if (t == null) {
            Log.w(ComponentTree.a, "Main Thread Layout state is not found");
            return;
        }
        this.m.G();
        this.h = true;
        while (true) {
            if (!this.q) {
                dvx m;
                ComponentTree j;
                Rect rect;
                dvw q;
                boolean[] a;
                dvw q2;
                boolean[] a2;
                boolean[] b2;
                ViewGroup viewGroup;
                dwc k;
                ComponentTree i;
                int l;
                int j2;
                ajc x;
                egu egu;
                epi a3;
                ajc y;
                dxp dxp;
                dxp dxp2;
                Iterator iterator;
                dxn e;
                Iterator iterator2;
                dxl dxl;
                hzf j3;
                epi a4;
                int n2 = 0;
                int n3 = 0;
                dxp dxp3;
                Iterator iterator3;
                dwm dwm;
                dxj h;
                dxp dxp4;
                egr i2;
                Map<K, dwm> x2;
                dxn e2;
                Map x3;
                Iterator iterator4;
                int n4;
                boolean b3;
                HashSet<dxk> set;
                int a5;
                dwm dwm2;
                dwm dwm3;
                Rect rect2;
                Iterator<K> iterator7;
                dxk dxk2;
                HashSet set2;
                dxl dxl2;
                Iterator iterator9;
                epi a6;
                Iterator iterator10;
                dxk dxk4;
                dxn e3;
                ArrayList list;
                dxl dxl3;
                ArrayList list2;
                Object c;
                dxp dxp5;
                dwm dwm4;
                epi a7;
                int b5;
                dxp dxp6;
                int n8;
                egr i3;
                dxk h2;
                dxl dxl4;
                int a8;
                long a9;
                egj b6;
                egd g;
                StringBuilder sb;
                ega b7;
                ega b8;
                StringBuilder sb2;
                Object a10;
                StringBuilder sb3;
                ega ega;
                int n10;
                int n11;
                View view;
                int n12;
                int n13;
                int width;
                int n14;
                int n15;
                int width2;
                Rect rect3;
                dvg a11;
                dxk h3;
                dwm dwm5;
                long a12;
                egc k2;
                egd egd;
                epi a13;
                med p;
                int s;
                dwn v;
                dta g2;
                mxt v2;
                int n16;
                long[] d;
                int b9;
                dvg c2;
                int j4;
                egd g3;
                egl s2;
                mxt mxt;
                int n17;
                long i4;
                mxt v3;
                mxt v4;
                int a14;
                long[] d2;
                dwb k3;
                dwn dwn;
                int n19;
                Rect rect4;
                dvi p2;
                egd egd2;
                int a15;
                int n20;
                Rect rect5;
                int n21;
                egh e4;
                dvg c3;
                dsw c4;
                egd g4;
                boolean b10;
                boolean b11 = false;
                Object a16;
                boolean b12 = false;
                egd g5;
                dxq t2;
                ajc y2;
                egh d3;
                egj b13;
                Object a17;
                Object c5;
                wwr w;
                egh d4;
                egj b14;
                Object a18;
                Object c6;
                egm egm;
                dvi p3;
                boolean b15;
                long nanoTime;
                dvg c7;
                dsw c8;
                dvg b16;
                dsw c9;
                Object a19;
                ega b17;
                int l2;
                dsw c10;
                Rect d5;
                Rect d6;
                dta a20;
                dta a21;
                boolean az = false;
                dta a22;
                dta a23;
                glt n23;
                glt n24;
                glt glt;
                duc m2;
                duc m3;
                duc duc;
                boolean b18 = false;
                dsw c11;
                dsw c12;
                Object a24;
                dwb k4;
                List h4;
                double n25;
                dwb k5;
                dwn dwn2;
                dvi dvi;
                ArrayList i5;
                ArrayList j5;
                int a25;
                Rect rect6;
                int m4;
                boolean e5;
                Map c13;
                List m5;
                int size4;
                List m6;
                dww dww;
                long b19;
                long c14;
                egd egd3;
                TestItem testItem;
                ComponentHost c15;
                Object a26;
                Deque deque;
                Object o;
                Label_0127_Outer:Label_5715_Outer:
                while (true) {
                    this.r = true;
                    this.q = true;
                    while (true) {
                        try {
                            try {
                                m = this.m;
                                Label_5690: {
                                    while (true) {
                                        Label_0130: {
                                            if (m.p <= 0) {
                                                break Label_0130;
                                            }
                                            try {
                                                j = m.j;
                                                if (j == null || !j.i) {
                                                    break Label_0130;
                                                }
                                                if (!m.G()) {
                                                    break Label_5690;
                                                }
                                                rect = new Rect(0, 0, m.getWidth(), m.getHeight());
                                                b = false;
                                                break Label_0130;
                                            }
                                            finally {}
                                            break;
                                        }
                                        m.m.set(bounds);
                                        q = m.q;
                                        if (q != null && dvt.b((dvt)null)) {
                                            a = q.a;
                                            if (a != null) {
                                                if (!a[0]) {
                                                    throw null;
                                                }
                                            }
                                        }
                                        q2 = m.q;
                                        Label_0319: {
                                            if (q2 != null && dvt.b((dvt)null)) {
                                                a2 = q2.a;
                                                if (a2 != null && a2[0]) {
                                                    b2 = q2.b;
                                                    if (b2 != null && !b2[0]) {
                                                        viewGroup = (ViewGroup)m.getParent();
                                                        if (viewGroup != null) {
                                                            if (!q2.c) {
                                                                if (q2.d) {
                                                                    if (m.getBottom() < viewGroup.getHeight() - viewGroup.getPaddingBottom()) {
                                                                        break Label_0319;
                                                                    }
                                                                }
                                                                else if (m.getRight() < viewGroup.getWidth() - viewGroup.getPaddingRight()) {
                                                                    break Label_0319;
                                                                }
                                                            }
                                                            throw null;
                                                        }
                                                    }
                                                }
                                            }
                                        }
                                        k = m.k;
                                        i = k.i.j;
                                        l = (i.i ? 1 : 0);
                                        j2 = (i.j ? 1 : 0);
                                        bkx.q();
                                        if (k.e) {
                                            x = k.x;
                                            egg.a();
                                            egu = (egu)x.a;
                                            egu.c = t.h;
                                            egu.d = t.k;
                                            egu.b.setEmpty();
                                            egu.e = bounds;
                                            a3 = egg.a;
                                        }
                                        Label_2877: {
                                            if (k.t == null) {
                                                break Label_2877;
                                            }
                                            try {
                                                Label_2885: {
                                                    try {
                                                        if (k.e) {
                                                            y = k.y;
                                                            dxp = (dxp)y.a;
                                                            dxp.c = (egr)t;
                                                            if (t.s != dxp.d) {
                                                                dxp.i = null;
                                                            }
                                                            egg.a();
                                                            try {
                                                                Label_1984: {
                                                                    if (dxp.d != t.s) {
                                                                        dxp2 = (dxp)y.a;
                                                                        if (dxp2.e != null) {
                                                                            iterator = dxp2.a.values().iterator();
                                                                            while (iterator.hasNext()) {
                                                                                dxq.f(y, (dwm)iterator.next());
                                                                            }
                                                                            y.g();
                                                                            dxp2.a.clear();
                                                                            dxp2.b.clear();
                                                                            dxp2.f.clear();
                                                                            e = dxp2.e;
                                                                            iterator2 = e.j.G().iterator();
                                                                            while (iterator2.hasNext()) {
                                                                                dxl = (dxl)e.j.E((dxk)iterator2.next());
                                                                                e.h(dxl, (dwm)null);
                                                                                dxn.b(dxl);
                                                                            }
                                                                            j3 = e.j;
                                                                            ((Map)j3.b).clear();
                                                                            ((Map)j3.c).clear();
                                                                            ((Map)j3.d).clear();
                                                                            ((Map)j3.a).clear();
                                                                            e.b.f();
                                                                            e.a.clear();
                                                                            for (int n = e.d.size() - 1; n >= 0; --n) {
                                                                                ((dyb)e.d.get(n)).d();
                                                                            }
                                                                            e.d.clear();
                                                                            e.f = null;
                                                                            e.g.clear();
                                                                        }
                                                                        if (!dxp.c.l()) {
                                                                            a4 = egg.a;
                                                                            n2 = l;
                                                                            l = j2;
                                                                            n3 = (b ? 1 : 0);
                                                                            break Label_1984;
                                                                        }
                                                                    }
                                                                    if (!dxp.a.isEmpty()) {
                                                                        dxp3 = (dxp)y.a;
                                                                        iterator3 = t.x.keySet().iterator();
                                                                        while (iterator3.hasNext()) {
                                                                            dwm = dxp3.a.remove(iterator3.next());
                                                                            if (dwm != null) {
                                                                                dxq.f(y, dwm);
                                                                            }
                                                                        }
                                                                    }
                                                                    Label_1665: {
                                                                        if (dxq.d(dxp, (egr)t)) {
                                                                            dxq.e(y, (egr)t);
                                                                            if (dxq.c(dxp)) {
                                                                                h = dxp.h;
                                                                                dxp4 = (dxp)y.a;
                                                                                if (dxp4.e == null) {
                                                                                    dxp4.e = new dxn(new eae(y, (byte[])null, (byte[])null, (byte[])null), (byte[])null);
                                                                                }
                                                                                i2 = dxp4.i;
                                                                                if (i2 == null) {
                                                                                    x2 = null;
                                                                                }
                                                                                else {
                                                                                    x2 = ((dvi)i2).x;
                                                                                }
                                                                                e2 = dxp4.e;
                                                                                x3 = t.x;
                                                                                egg.a();
                                                                                iterator4 = e2.j.F().iterator();
                                                                                while (iterator4.hasNext()) {
                                                                                    ((dxl)iterator4.next()).f = false;
                                                                                }
                                                                                n4 = j2;
                                                                                if (x2 == null) {
                                                                                    for (final Map.Entry<dxk, V> entry : x3.entrySet()) {
                                                                                        e2.c((dxk)entry.getKey(), (dwm)null, (dwm)entry.getValue());
                                                                                    }
                                                                                    b3 = b;
                                                                                    b = (l != 0);
                                                                                }
                                                                                else {
                                                                                    set = new HashSet<dxk>();
                                                                                    for (final dxk dxk : x3.keySet()) {
                                                                                        a5 = dxk.a;
                                                                                        dwm2 = x3.get(dxk);
                                                                                        dwm3 = x2.get(dxk);
                                                                                        if (dwm2 != null) {
                                                                                            set.add(dxk);
                                                                                        }
                                                                                        else if (a5 == 3) {
                                                                                            continue Label_0127_Outer;
                                                                                        }
                                                                                        e2.c(dxk, dwm3, dwm2);
                                                                                    }
                                                                                    rect2 = bounds;
                                                                                    j2 = (b ? 1 : 0);
                                                                                    iterator7 = x2.keySet().iterator();
                                                                                    while (true) {
                                                                                        bounds = rect2;
                                                                                        b = (l != 0);
                                                                                        b3 = (j2 != 0);
                                                                                        if (!iterator7.hasNext()) {
                                                                                            break;
                                                                                        }
                                                                                        dxk2 = iterator7.next();
                                                                                        if (set.contains(dxk2)) {
                                                                                            continue Label_0127_Outer;
                                                                                        }
                                                                                        e2.c(dxk2, (dwm)x2.get(dxk2), (dwm)null);
                                                                                    }
                                                                                }
                                                                                e2.f = e2.a(h);
                                                                                set2 = new HashSet();
                                                                                for (final dxk dxk3 : e2.j.G()) {
                                                                                    dxl2 = (dxl)e2.j.E(dxk3);
                                                                                    if (dxl2.a.isEmpty()) {
                                                                                        e2.h(dxl2, (dwm)null);
                                                                                        dxn.b(dxl2);
                                                                                        set2.add(dxk3);
                                                                                    }
                                                                                }
                                                                                iterator9 = set2.iterator();
                                                                                while (iterator9.hasNext()) {
                                                                                    e2.j.H((dxk)iterator9.next());
                                                                                }
                                                                                a6 = egg.a;
                                                                                iterator10 = t.x.keySet().iterator();
                                                                                while (true) {
                                                                                    j2 = n4;
                                                                                    n2 = (b ? 1 : 0);
                                                                                    l = (b3 ? 1 : 0);
                                                                                    if (!iterator10.hasNext()) {
                                                                                        break Label_1665;
                                                                                    }
                                                                                    dxk4 = (dxk)iterator10.next();
                                                                                    if (!((Map)dxp4.e.j.a).containsKey(dxk4)) {
                                                                                        continue Label_0127_Outer;
                                                                                    }
                                                                                    dxp4.f.add(dxk4);
                                                                                }
                                                                            }
                                                                        }
                                                                        n2 = l;
                                                                        l = (b ? 1 : 0);
                                                                    }
                                                                    e3 = dxp.e;
                                                                    if (e3 != null) {
                                                                        list = new ArrayList(e3.j.F());
                                                                        for (int size = list.size(), n5 = 0; n5 < size; ++n5) {
                                                                            dxl3 = (dxl)list.get(n5);
                                                                            if (dxl3.g) {
                                                                                dxl3.g = false;
                                                                                list2 = new ArrayList(dxl3.a.values());
                                                                                for (int size2 = list2.size(), n6 = 0; n6 < size2; ++n6) {
                                                                                    c = ((glt)list2.get(n6)).c;
                                                                                    if (c != null) {
                                                                                        ((dyb)c).d();
                                                                                        e3.e.a((dyb)c);
                                                                                    }
                                                                                }
                                                                            }
                                                                        }
                                                                    }
                                                                    y.g();
                                                                    if (!dxp.f.isEmpty()) {
                                                                        dxp5 = (dxp)y.a;
                                                                        for (final Map.Entry<Object, V> entry2 : t.x.entrySet()) {
                                                                            if (dxp5.f.contains(entry2.getKey())) {
                                                                                dwm4 = (dwm)entry2.getValue();
                                                                                for (short b4 = dwm4.b, n7 = 0; n7 < b4; ++n7) {
                                                                                    dxq.g(y, (egr)t, ((egr)t).b(((dvg)dwm4.c((int)n7)).k), true);
                                                                                }
                                                                            }
                                                                        }
                                                                    }
                                                                    a7 = egg.a;
                                                                    n3 = l;
                                                                    l = j2;
                                                                }
                                                                b5 = dxq.k(y).b();
                                                                dxp6 = (dxp)y.a;
                                                                n4 = l;
                                                                j2 = n2;
                                                                b = (n3 != 0);
                                                                if (dxp6.i == null) {
                                                                    break Label_2885;
                                                                }
                                                                if (b5 == 0) {
                                                                    n4 = l;
                                                                    j2 = n2;
                                                                    b = (n3 != 0);
                                                                    break Label_2885;
                                                                }
                                                                n8 = 1;
                                                                while (true) {
                                                                    n4 = l;
                                                                    j2 = n2;
                                                                    b = (n3 != 0);
                                                                    if (n8 >= b5) {
                                                                        break Label_2885;
                                                                    }
                                                                    if (dxq.d(dxp6, (egr)t) && dxq.c(dxp6) && dxp6.e != null) {
                                                                        i3 = dxp6.i;
                                                                        if (i3 != null) {
                                                                            h2 = i3.e(n8).b.a.h;
                                                                            if (h2 != null) {
                                                                                dxl4 = (dxl)dxp6.e.j.E(h2);
                                                                                if (dxl4 != null && dxl4.c == 2 && dxl4.h) {
                                                                                    a8 = dxq.a(dxp6.i, n8);
                                                                                    for (int n9 = n8; n9 <= a8; ++n9) {
                                                                                        if (((dwc)dxq.k(y)).g(n9) == null) {
                                                                                            a9 = dxp6.i.e(n9).b.a();
                                                                                            if (y.h(a9)) {
                                                                                                y.i(a9);
                                                                                            }
                                                                                            y.f(a9, true);
                                                                                            y.i(a9);
                                                                                        }
                                                                                        b6 = ((dwc)dxq.k(y)).g(n9).d.b;
                                                                                        dxp6.b.put(b6, b6.a);
                                                                                    }
                                                                                    g = ((dwc)dxq.k(y)).g(n8);
                                                                                    if (g == null) {
                                                                                        sb = new StringBuilder();
                                                                                        sb.append("The root of the disappearing subtree should not be null, acquireMountReference on this index should be called before this. Index: ");
                                                                                        sb.append(n8);
                                                                                        throw new IllegalStateException(sb.toString());
                                                                                    }
                                                                                    b7 = dxq.k(y).h().b;
                                                                                    b8 = g.b;
                                                                                    if (b8 == null) {
                                                                                        sb2 = new StringBuilder();
                                                                                        sb2.append("Disappearing item host should never be null. Index: ");
                                                                                        sb2.append(n8);
                                                                                        throw new IllegalStateException(sb2.toString());
                                                                                    }
                                                                                    if (b7 != b8) {
                                                                                        a10 = g.a;
                                                                                        if (a10 == null) {
                                                                                            sb3 = new StringBuilder();
                                                                                            sb3.append("Disappearing item content should never be null. Index: ");
                                                                                            sb3.append(n8);
                                                                                            throw new IllegalStateException(sb3.toString());
                                                                                        }
                                                                                        ega = b8;
                                                                                        n10 = 0;
                                                                                        n11 = 0;
                                                                                        while (ega != b7) {
                                                                                            n10 += ega.getLeft();
                                                                                            n11 += ega.getTop();
                                                                                            ega = (ega)ega.getParent();
                                                                                        }
                                                                                        if (a10 instanceof View) {
                                                                                            view = (View)a10;
                                                                                            n12 = n10 + view.getLeft();
                                                                                            n13 = n11 + view.getTop();
                                                                                            width = view.getWidth();
                                                                                            n14 = view.getHeight() + n13;
                                                                                            n15 = n12 + width;
                                                                                        }
                                                                                        else {
                                                                                            bounds = ((Drawable)a10).getBounds();
                                                                                            n12 = n10 + bounds.left;
                                                                                            width2 = bounds.width();
                                                                                            n13 = n11 + bounds.top;
                                                                                            n14 = n13 + bounds.height();
                                                                                            n15 = width2 + n12;
                                                                                        }
                                                                                        b8.l(g);
                                                                                        rect3 = new Rect(n12, n13, n15, n14);
                                                                                        epi.S(rect3.left, rect3.top, rect3.right, rect3.bottom, a10, false);
                                                                                        b7.g(n8, g);
                                                                                        g.b = b7;
                                                                                    }
                                                                                    a11 = g.d.b.a;
                                                                                    h3 = a11.h;
                                                                                    if ((dwm5 = dxp6.a.get(h3)) == null) {
                                                                                        dwm5 = new dwm();
                                                                                        dxp6.a.put(h3, dwm5);
                                                                                    }
                                                                                    dwm5.e(a11.a(), (Object)g);
                                                                                    a12 = g.d.b.a();
                                                                                    k2 = dxq.k(y);
                                                                                    egd = (egd)((dwc)k2).b.e(a12);
                                                                                    if (egd != null) {
                                                                                        ((dwc)k2).w(dvg.b(egd).j, ((dwc)k2).h);
                                                                                    }
                                                                                    n8 = a8;
                                                                                }
                                                                            }
                                                                        }
                                                                    }
                                                                    ++n8;
                                                                }
                                                            }
                                                            finally {
                                                                a13 = egg.a;
                                                            }
                                                        }
                                                    }
                                                    finally {
                                                        continue Label_5715_Outer;
                                                    }
                                                    n4 = j2;
                                                    j2 = l;
                                                    try {
                                                        k.o = t;
                                                        if (k.f) {
                                                            cqj.c(3, "MountState:InvalidReentrantMounts", "Trying to mount while already mounting! ".concat(k.i(k.q)));
                                                        }
                                                        k.f = true;
                                                        p = i.g.p();
                                                        s = t.s;
                                                        if (s != k.n) {
                                                            k.p = null;
                                                        }
                                                        if (p == null) {
                                                            v = null;
                                                        }
                                                        else {
                                                            g2 = i.g;
                                                            v = bkx.v(g2, p, p.u(g2, 6));
                                                        }
                                                        if (k.e) {
                                                            if (v != null) {
                                                                v.b("PREPARE_MOUNT_START");
                                                            }
                                                            v2 = k.v;
                                                            v2.b = 0;
                                                            v2.a = 0;
                                                            v2.c = 0;
                                                            if (k.d != null) {
                                                                n16 = 0;
                                                                while (true) {
                                                                    d = k.d;
                                                                    if (n16 >= d.length) {
                                                                        break;
                                                                    }
                                                                    b9 = t.b(d[n16]);
                                                                    if (b9 < 0) {
                                                                        c2 = null;
                                                                    }
                                                                    else {
                                                                        c2 = dvg.c(t.e(b9));
                                                                    }
                                                                    if (c2 == null) {
                                                                        j4 = -1;
                                                                    }
                                                                    else {
                                                                        j4 = c2.j;
                                                                    }
                                                                    g3 = k.g(n16);
                                                                    s2 = k.s;
                                                                    Label_3374: {
                                                                        if (s2 == null || g3 == null || !s2.h((ajc)k.w.d, g3)) {
                                                                            if (j4 == -1) {
                                                                                k.w(n16, k.h);
                                                                                mxt = k.v;
                                                                                n17 = mxt.c;
                                                                            }
                                                                            else {
                                                                                i4 = c2.i;
                                                                                if (g3 == null) {
                                                                                    mxt = k.v;
                                                                                    n17 = mxt.c;
                                                                                }
                                                                                else if (g3.b != k.h.e(i4)) {
                                                                                    k.w(n16, k.h);
                                                                                    mxt = k.v;
                                                                                    n17 = mxt.c;
                                                                                }
                                                                                else {
                                                                                    if (j4 != n16) {
                                                                                        g3.b.i(g3, n16, j4);
                                                                                        v3 = k.v;
                                                                                        ++v3.a;
                                                                                        break Label_3374;
                                                                                    }
                                                                                    v4 = k.v;
                                                                                    ++v4.b;
                                                                                    break Label_3374;
                                                                                }
                                                                            }
                                                                            mxt.c = n17 + 1;
                                                                        }
                                                                    }
                                                                    ++n16;
                                                                }
                                                            }
                                                            if (k.h.e(0L) == null) {
                                                                k.r(0L, (ComponentHost)k.i);
                                                                k.b.i(0L, k.q);
                                                            }
                                                            a14 = t.a();
                                                            d2 = k.d;
                                                            if (d2 == null || a14 != d2.length) {
                                                                k.d = new long[a14];
                                                            }
                                                            for (int n18 = 0; n18 < a14; ++n18) {
                                                                k.d[n18] = dvg.c(t.e(n18)).k;
                                                            }
                                                            if (v != null) {
                                                                v.b("PREPARE_MOUNT_END");
                                                            }
                                                        }
                                                        k3 = k.k;
                                                        k3.j = 0;
                                                        k3.k = 0;
                                                        k3.l = 0;
                                                        k3.m = 0;
                                                        if (k3.o) {
                                                            k3.a.clear();
                                                            k3.b.clear();
                                                            k3.c.clear();
                                                            k3.d.clear();
                                                            k3.e.clear();
                                                            k3.f.clear();
                                                            k3.g.clear();
                                                            k3.h.clear();
                                                            k3.i.clear();
                                                        }
                                                        k3.n = false;
                                                        if (v != null && med.w(v)) {
                                                            k.k.a();
                                                        }
                                                        if (j2 != 0 && k.z(t, bounds, b)) {
                                                            dwn = v;
                                                            n19 = s;
                                                            rect4 = bounds;
                                                            p2 = t;
                                                        }
                                                        else {
                                                            egd2 = (egd)k.b.e(0L);
                                                            a15 = t.a();
                                                            n20 = 0;
                                                            rect5 = bounds;
                                                            n21 = s;
                                                            p2 = t;
                                                            while (n20 < a15) {
                                                                e4 = p2.e(n20);
                                                                c3 = dvg.c(e4);
                                                                c4 = c3.c;
                                                                g4 = k.g(n20);
                                                                b10 = (g4 != null);
                                                                Label_3819: {
                                                                    if (g4 != null) {
                                                                        if (g4 == egd2) {
                                                                            b11 = true;
                                                                            break Label_3819;
                                                                        }
                                                                    }
                                                                    else {
                                                                        g4 = null;
                                                                    }
                                                                    b11 = false;
                                                                }
                                                                Label_3901: {
                                                                    Label_3898: {
                                                                        if (j2 != 0) {
                                                                            if (g4 != null) {
                                                                                a16 = g4.a;
                                                                                if (a16 instanceof ComponentHost && ((ComponentHost)a16).a() > 0) {
                                                                                    break Label_3898;
                                                                                }
                                                                            }
                                                                            if (!Rect.intersects(rect5, c3.d) && !k.x(e4)) {
                                                                                if (!b11) {
                                                                                    b12 = false;
                                                                                    break Label_3901;
                                                                                }
                                                                            }
                                                                        }
                                                                    }
                                                                    b12 = true;
                                                                }
                                                                if (b12 && !b10) {
                                                                    k.q(n20, e4, c3, p2);
                                                                    if (j2 != 0) {
                                                                        g5 = k.g(n20);
                                                                        t2 = k.t;
                                                                        if (t2 != null) {
                                                                            y2 = k.y;
                                                                            d3 = g5.d;
                                                                            b13 = d3.b;
                                                                            a17 = g5.a;
                                                                            c5 = d3.c;
                                                                            ((egm)t2).i(y2, b13, a17);
                                                                        }
                                                                        else {
                                                                            w = k.w;
                                                                            if (w != null) {
                                                                                d4 = g5.d;
                                                                                b14 = d4.b;
                                                                                a18 = g5.a;
                                                                                c6 = d4.c;
                                                                                for (int size3 = ((List)w.b).size(), n22 = 0; n22 < size3; ++n22) {
                                                                                    egm = ((List<egm>)w.b).get(n22);
                                                                                    egm.i(w.p(egm), b14, a18);
                                                                                }
                                                                            }
                                                                        }
                                                                    }
                                                                }
                                                                else if (!b12 && b10) {
                                                                    k.w(n20, k.h);
                                                                }
                                                                else if (b10) {
                                                                    if (k.e || (b11 && k.g)) {
                                                                        p3 = k.p;
                                                                        b15 = (p3 != null && p3.t == p2.u);
                                                                        nanoTime = System.nanoTime();
                                                                        c7 = dvg.c(e4);
                                                                        c8 = c7.c;
                                                                        b16 = dvg.b(g4);
                                                                        c9 = b16.c;
                                                                        a19 = g4.a;
                                                                        b17 = g4.b;
                                                                        l2 = c7.l;
                                                                        c10 = c7.c;
                                                                        Label_4422: {
                                                                            Label_4269: {
                                                                                if (!dys.n || c7.g == b16.g) {
                                                                                    if (((dtg)c10).al()) {
                                                                                        d5 = c7.d;
                                                                                        d6 = b16.d;
                                                                                        if (d5.width() != d6.width() || d5.height() != d6.height()) {
                                                                                            break Label_4269;
                                                                                        }
                                                                                    }
                                                                                    if (b15) {
                                                                                        if (l2 == 1) {
                                                                                            if (c9 instanceof dui && c10 instanceof dui) {
                                                                                                a20 = b16.a;
                                                                                                a21 = c7.a;
                                                                                                if (((dtg)c9).az(c9, c10)) {
                                                                                                    break Label_4269;
                                                                                                }
                                                                                            }
                                                                                            az = false;
                                                                                            break Label_4422;
                                                                                        }
                                                                                        if (l2 == 2) {
                                                                                            break Label_4269;
                                                                                        }
                                                                                    }
                                                                                    a22 = b16.a;
                                                                                    a23 = c7.a;
                                                                                    az = ((dtg)c9).az(c9, c10);
                                                                                    break Label_4422;
                                                                                }
                                                                            }
                                                                            az = true;
                                                                        }
                                                                        Label_4651: {
                                                                            Label_4648: {
                                                                                if (!az) {
                                                                                    n23 = c7.n;
                                                                                    n24 = b16.n;
                                                                                    glt = n23;
                                                                                    if (n24 == null) {
                                                                                        if (n23 != null) {
                                                                                            break Label_4648;
                                                                                        }
                                                                                        glt = null;
                                                                                    }
                                                                                    if (n24 != null) {
                                                                                        if (n24 != glt) {
                                                                                            if (glt == null) {
                                                                                                break Label_4648;
                                                                                            }
                                                                                            if (!bky.f((Drawable)n24.b, (Drawable)glt.b)) {
                                                                                                break Label_4648;
                                                                                            }
                                                                                            if (!bky.f(null, null)) {
                                                                                                break Label_4648;
                                                                                            }
                                                                                            if (!cpb.d(n24.c, glt.c)) {
                                                                                                break Label_4648;
                                                                                            }
                                                                                            if (!cpb.d(n24.d, glt.d)) {
                                                                                                break Label_4648;
                                                                                            }
                                                                                            if (!cpb.d(n24.e, glt.e)) {
                                                                                                break Label_4648;
                                                                                            }
                                                                                            if (!cpb.d((Object)null, (Object)null)) {
                                                                                                break Label_4648;
                                                                                            }
                                                                                        }
                                                                                    }
                                                                                    m2 = c7.m;
                                                                                    m3 = b16.m;
                                                                                    duc = m2;
                                                                                    if (m3 == null) {
                                                                                        if (m2 != null) {
                                                                                            break Label_4648;
                                                                                        }
                                                                                        duc = null;
                                                                                    }
                                                                                    if (m3 == null || m3.a((Object)duc)) {
                                                                                        b18 = false;
                                                                                        break Label_4651;
                                                                                    }
                                                                                }
                                                                            }
                                                                            b18 = true;
                                                                        }
                                                                        if (b18) {
                                                                            dwc.o(g4);
                                                                        }
                                                                        if (g4.c) {
                                                                            k.u(g4, c9, g4.a);
                                                                        }
                                                                        g4.d = e4;
                                                                        if (az) {
                                                                            c11 = c7.c;
                                                                            c12 = b16.c;
                                                                            if (!dsw.v(c11)) {
                                                                                a24 = g4.a;
                                                                                ((dtg)c12).ae(k.A(c12), a24);
                                                                                ((dtg)c11).V(k.A(c11), a24);
                                                                            }
                                                                        }
                                                                        if (b18) {
                                                                            dwc.t(g4);
                                                                        }
                                                                        k.l(g4, c8, a19);
                                                                        if (c7.k != 0L) {
                                                                            c7.f(dwc.a);
                                                                            dwc.k(g4.a, dwc.a.left, dwc.a.top, dwc.a.right, dwc.a.bottom, dsw.z(c7.c) && ((View)g4.a).isLayoutRequested());
                                                                        }
                                                                        if (g4.a instanceof Drawable) {
                                                                            cpc.h((View)b17, (Drawable)a19, b16.e, b16.m);
                                                                        }
                                                                        k4 = k.k;
                                                                        if (k4.n) {
                                                                            if (az) {
                                                                                k4.c.add(c4.q());
                                                                                h4 = k.k.h;
                                                                                n25 = (double)(System.nanoTime() - nanoTime);
                                                                                Double.isNaN(n25);
                                                                                h4.add(n25 / 1000000.0);
                                                                                k5 = k.k;
                                                                                ++k5.l;
                                                                            }
                                                                            else {
                                                                                ++k4.m;
                                                                            }
                                                                        }
                                                                    }
                                                                    if (j2 && ((dtg)c4).ah()) {
                                                                        dwc.p(g4, b);
                                                                    }
                                                                }
                                                                ++n20;
                                                            }
                                                            dwn2 = v;
                                                            if (j2 && !rect5.isEmpty()) {
                                                                dvi = p2;
                                                                i5 = dvi.i;
                                                                j5 = dvi.j;
                                                                a25 = dvi.a();
                                                                k.l = dvi.a();
                                                                for (int l3 = 0; l3 < a25; ++l3) {
                                                                    if (rect5.bottom <= dvi.d((egn)i5.get(l3)).d.top) {
                                                                        k.l = l3;
                                                                        break;
                                                                    }
                                                                }
                                                                rect6 = rect5;
                                                                k.m = dvi.a();
                                                                m4 = 0;
                                                                while (true) {
                                                                    p2 = dvi;
                                                                    rect4 = rect6;
                                                                    n19 = n21;
                                                                    dwn = dwn2;
                                                                    if (m4 >= a25) {
                                                                        break;
                                                                    }
                                                                    if (rect6.top < dvi.d((egn)j5.get(m4)).d.bottom) {
                                                                        k.m = m4;
                                                                        p2 = dvi;
                                                                        rect4 = rect6;
                                                                        n19 = n21;
                                                                        dwn = dwn2;
                                                                        break;
                                                                    }
                                                                    ++m4;
                                                                }
                                                            }
                                                            else {
                                                                rect4 = rect5;
                                                                dwn = dwn2;
                                                                n19 = n21;
                                                            }
                                                        }
                                                        k.j();
                                                        if (n4 != 0) {
                                                            if (dwn != null) {
                                                                dwn.b("EVENT_PROCESS_VISIBILITY_OUTPUTS_START");
                                                            }
                                                            k.B(rect4, k.e);
                                                            if (dwn != null) {
                                                                dwn.b("EVENT_PROCESS_VISIBILITY_OUTPUTS_END");
                                                            }
                                                        }
                                                        e5 = k.e;
                                                        k.e = false;
                                                        k.g = false;
                                                        k.j.set(rect4);
                                                        k.n = n19;
                                                        k.p = p2;
                                                        c13 = k.c;
                                                        if (c13 != null) {
                                                            c13.clear();
                                                            m5 = p2.m;
                                                            if (m5 == null) {
                                                                size4 = 0;
                                                            }
                                                            else {
                                                                size4 = m5.size();
                                                            }
                                                            for (int n26 = 0; n26 < size4; ++n26) {
                                                                m6 = p2.m;
                                                                if (m6 == null) {
                                                                    dww = null;
                                                                }
                                                                else {
                                                                    dww = m6.get(n26);
                                                                }
                                                                b19 = dww.b;
                                                                c14 = dww.c;
                                                                if (c14 == -1L) {
                                                                    egd3 = null;
                                                                }
                                                                else {
                                                                    egd3 = (egd)k.b.e(c14);
                                                                }
                                                                testItem = new TestItem();
                                                                if (b19 == -1L) {
                                                                    c15 = null;
                                                                }
                                                                else {
                                                                    c15 = (ComponentHost)k.h.e(b19);
                                                                }
                                                                testItem.c = c15;
                                                                testItem.b.set(dww.d);
                                                                testItem.a = dww.a;
                                                                if (egd3 == null) {
                                                                    a26 = null;
                                                                }
                                                                else {
                                                                    a26 = egd3.a;
                                                                }
                                                                testItem.d = a26;
                                                                if ((deque = k.c.get(dww.a)) == null) {
                                                                    deque = new LinkedList();
                                                                }
                                                                deque.add(testItem);
                                                                k.c.put(dww.a, deque);
                                                            }
                                                        }
                                                        if (dwn != null) {
                                                            k.C(dwn);
                                                        }
                                                        ebh.f.addAndGet(1L);
                                                        k.f = false;
                                                        this.h = false;
                                                        this.C = null;
                                                        this.B = null;
                                                        return;
                                                    }
                                                    finally {}
                                                }
                                            }
                                            catch (final Exception ex) {}
                                        }
                                        break;
                                    }
                                }
                            }
                            finally {}
                            break;
                        }
                        catch (final Exception ex2) {}
                        try {
                            if (bounds instanceof dvp) {
                                o = bounds;
                            }
                            else {
                                o = new dvp(this, (Throwable)bounds);
                            }
                            throw o;
                        }
                        finally {
                            continue;
                        }
                        break;
                    }
                    break;
                }
                this.h = false;
                this.C = null;
                this.B = null;
                throw bounds;
            }
            continue;
        }
    }
    
    private final void D() {
        final dvi u = this.u;
        if (u == null) {
            throw new RuntimeException("Cannot promote null LayoutState!");
        }
        if (u == this.t) {
            return;
        }
        this.t = u;
        final dvx m = this.m;
        if (m != null) {
            m.D();
        }
    }
    
    private static boolean E(final dvi dvi, final int n, final int n2, final int n3) {
        return dvi != null && dvi.j(n, n2, n3) && dvi.i();
    }
    
    private static boolean F(final dvi dvi, final int n, final int n2) {
        return dvi != null && dvi.k(n, n2) && dvi.i();
    }
    
    private final void G(dsw k, final int x, final int y, final boolean b, final dwt dwt, final int z, final String s, final cyd ae, final boolean b2, final boolean b3) {
        synchronized (this) {
            if (this.J) {
                return;
            }
            boolean b4 = true;
            if (z == 0 || z == 1) {
                if (this.U >= 0) {
                    throw new IllegalStateException("Setting an unversioned root after calling setVersionedRootAndSizeSpec is not supported. If this ComponentTree takes its version from a parent tree make sure to always call setVersionedRootAndSizeSpec");
                }
                this.U = -1;
            }
            if (k != null && this.v.m()) {
                k = k.k();
            }
            final boolean b5 = x != -1;
            if (y == -1) {
                b4 = false;
            }
            dsw s3;
            dsw s2;
            if (k != null) {
                s2 = (s3 = k);
            }
            else {
                s3 = this.s;
                s2 = null;
            }
            int x2;
            if (b5) {
                x2 = x;
            }
            else {
                x2 = this.X;
            }
            int y2;
            if (b4) {
                y2 = y;
            }
            else {
                y2 = this.Y;
            }
            final dvi u = this.u;
            if (!b3 && s3 != null && u != null && u.j(s3.j, x2, y2)) {
                if (dwt != null) {
                    dwt.b = u.r;
                    dwt.a = u.q;
                }
                return;
            }
            if (b5) {
                this.X = x;
            }
            if (b4) {
                this.Y = y;
            }
            if (k != null) {
                this.s = s2;
            }
            if (b3) {
                this.s = this.s.k();
            }
            cyd ae2;
            if (ae != null) {
                this.ae = ae;
                ae2 = ae;
            }
            else {
                ae2 = this.ae;
            }
            this.Z = z;
            monitorexit(this);
            if (b && dwt != null) {
                throw new IllegalArgumentException("The layout can't be calculated asynchronously if we need the Size back");
            }
            if (b) {
                synchronized (this.o) {
                    final dtk p10 = this.p;
                    if (p10 != null) {
                        this.n.a((Runnable)p10);
                    }
                    this.p = new dtk(this, z, ae2, s, b2, (byte[])null, (byte[])null, (byte[])null);
                    this.n.b();
                    this.n.c((Runnable)this.p);
                    return;
                }
            }
            this.x(dwt, z, s, ae2, b2);
        }
    }
    
    public static dtj b(final dta dta, final dsw c) {
        final dtj dtj = new dtj(dta);
        if (c != null) {
            dtj.c = c;
            return dtj;
        }
        throw new NullPointerException("Creating a ComponentTree with a null root is not allowed!");
    }
    
    public static boolean r(final int n) {
        return n == 0 || n == 2 || n == 4 || n == 6;
    }
    
    private static Looper z() {
        synchronized (ComponentTree.class) {
            if (ComponentTree.I == null) {
                final boolean a = dys.a;
                final HandlerThread handlerThread = new HandlerThread("ComponentLayoutThread", 5);
                handlerThread.start();
                ComponentTree.I = handlerThread.getLooper();
            }
            return ComponentTree.I;
        }
    }
    
    public final dsw a() {
        synchronized (this) {
            return this.s;
        }
    }
    
    public final dwv c() {
        synchronized (this) {
            return dwv.a(this.v);
        }
    }
    
    public final String d() {
        synchronized (this) {
            return this.K;
        }
    }
    
    public final String e() {
        synchronized (this) {
            final dsw s = this.s;
            if (s == null) {
                return null;
            }
            return s.q();
        }
    }
    
    public final List f() {
        monitorenter(this);
        try {
            final dwv v = this.v;
            List list = null;
            if (v != null) {
                list = list;
                if (v.d() != null) {
                    final Map d = v.d();
                    final ArrayList list2 = new ArrayList();
                    final Iterator iterator = d.values().iterator();
                    while (true) {
                        list = list2;
                        if (!iterator.hasNext()) {
                            break;
                        }
                        list2.addAll((Collection)iterator.next());
                    }
                }
            }
            monitorexit(this);
            return list;
        }
        finally {
            monitorexit(this);
            while (true) {}
        }
    }
    
    public final void g(final dtm dtm) {
        if (dtm == null) {
            return;
        }
        synchronized (this) {
            if (this.d == null) {
                this.d = new ArrayList();
            }
            this.d.add(dtm);
        }
    }
    
    public dvx getLithoView() {
        return this.m;
    }
    
    public final void h() {
        bkx.q();
        final dvx m = this.m;
        if (m != null) {
            final eae aa = this.aa;
            if (aa != null) {
                aa.c(m);
            }
            synchronized (this) {
                this.k = true;
                final dvi u = this.u;
                if (u != null && this.t != u) {
                    this.D();
                }
                if (this.s != null) {
                    monitorexit(this);
                    final int measuredWidth = this.m.getMeasuredWidth();
                    final int measuredHeight = this.m.getMeasuredHeight();
                    int n;
                    if ((n = measuredWidth) == 0) {
                        if (measuredHeight == 0) {
                            return;
                        }
                        n = 0;
                    }
                    final dvi t = this.t;
                    if (t != null && t.q == n) {
                        if (t.r == measuredHeight) {
                            if (!this.m.G()) {
                                this.m.w();
                                return;
                            }
                        }
                    }
                    ((ComponentHost)this.m).requestLayout();
                    return;
                }
                final boolean j = this.J;
                final String k = this.K;
                final StringBuilder sb = new StringBuilder("Trying to attach a ComponentTree with a null root. Is released: ");
                sb.append(j);
                sb.append(", Released Component name is: ");
                sb.append(k);
                throw new IllegalStateException(sb.toString());
            }
        }
        throw new IllegalStateException("Trying to attach a ComponentTree without a set View");
    }
    
    public final void i() {
        bkx.q();
        synchronized (this) {
            if (this.s == null) {
                return;
            }
            final dvi u = this.u;
            if (u != null) {
                final dvi t = this.t;
                final int n = 0;
                boolean b;
                if (t != u) {
                    this.D();
                    b = true;
                }
                else {
                    b = false;
                }
                monitorexit(this);
                if (b) {
                    final oqz g = this.G;
                    if (g != null) {
                        ((eee)g.a).u();
                        this.G = null;
                    }
                    if (this.k) {
                        if (!this.N) {
                            int measuredWidth = this.m.getMeasuredWidth();
                            final int measuredHeight = this.m.getMeasuredHeight();
                            if (measuredWidth == 0) {
                                if (measuredHeight == 0) {
                                    return;
                                }
                                measuredWidth = n;
                            }
                            final dvi t2 = this.t;
                            if (t2.q == measuredWidth && t2.r == measuredHeight) {
                                this.t();
                                return;
                            }
                            ((ComponentHost)this.m).requestLayout();
                        }
                    }
                }
                return;
            }
            throw new RuntimeException("Unexpected null mCommittedLayoutState");
        }
    }
    
    public final void j() {
        bkx.q();
        final eae aa = this.aa;
        if (aa != null) {
            for (int size = ((List)aa.b).size(), i = 0; i < size; ++i) {
                final dvb dvb = ((List<dvb>)aa.b).get(i);
                dvb.a.clear();
                final ViewPager viewPager = (ViewPager)dvb.b.get();
                if (viewPager != null) {
                    anc.I((View)viewPager, new cok(dvb, viewPager, 14));
                }
            }
            ((List)aa.b).clear();
        }
        monitorenter(this);
        try {
            this.k = false;
            monitorexit(this);
        }
        finally {
            monitorexit(this);
            while (true) {}
        }
    }
    
    public final void k() {
        bkx.q();
        if (!this.i) {
            throw new IllegalStateException("Calling incrementalMountComponent() but incremental mount is not enabled");
        }
        if (this.m == null) {
            return;
        }
        final Rect rect = new Rect();
        Label_0076: {
            if (!this.m.getLocalVisibleRect(rect)) {
                if (!this.q) {
                    if (this.C != null && rect.height() == 0) {
                        break Label_0076;
                    }
                    if (this.B != null && rect.width() == 0) {
                        break Label_0076;
                    }
                }
                return;
            }
        }
        this.m(rect, true);
    }
    
    public final void l(final int p0, final int p1, final int[] p2, final boolean p3) {
        // 
        // This method could not be decompiled.
        // 
        // Original Bytecode:
        // 
        //     3: aload_0        
        //     4: iconst_1       
        //     5: putfield        com/facebook/litho/ComponentTree.N:Z
        //     8: aload_0        
        //     9: monitorenter   
        //    10: aload_0        
        //    11: getfield        com/facebook/litho/ComponentTree.u:Ldvi;
        //    14: astore          7
        //    16: aload           7
        //    18: ifnull          44
        //    21: aload           7
        //    23: aload_0        
        //    24: getfield        com/facebook/litho/ComponentTree.t:Ldvi;
        //    27: if_acmpeq       44
        //    30: aload           7
        //    32: iload_1        
        //    33: iload_2        
        //    34: invokestatic    com/facebook/litho/ComponentTree.F:(Ldvi;II)Z
        //    37: ifeq            44
        //    40: aload_0        
        //    41: invokespecial   com/facebook/litho/ComponentTree.D:()V
        //    44: aload_0        
        //    45: getfield        com/facebook/litho/ComponentTree.t:Ldvi;
        //    48: astore          7
        //    50: aload           7
        //    52: ifnull          79
        //    55: aload           7
        //    57: getfield        dvi.e:I
        //    60: iload_1        
        //    61: if_icmpne       79
        //    64: aload           7
        //    66: getfield        dvi.f:I
        //    69: iload_2        
        //    70: if_icmpne       79
        //    73: iconst_1       
        //    74: istore          5
        //    76: goto            82
        //    79: iconst_0       
        //    80: istore          5
        //    82: aload           7
        //    84: aload_0        
        //    85: getfield        com/facebook/litho/ComponentTree.s:Ldsw;
        //    88: getfield        dsw.j:I
        //    91: iload_1        
        //    92: iload_2        
        //    93: invokestatic    com/facebook/litho/ComponentTree.E:(Ldvi;III)Z
        //    96: istore          6
        //    98: iload           5
        //   100: ifne            117
        //   103: iload           6
        //   105: ifeq            111
        //   108: goto            117
        //   111: iconst_1       
        //   112: istore          5
        //   114: goto            142
        //   117: aload_0        
        //   118: getfield        com/facebook/litho/ComponentTree.t:Ldvi;
        //   121: astore          7
        //   123: aload_3        
        //   124: iconst_0       
        //   125: aload           7
        //   127: getfield        dvi.q:I
        //   130: iastore        
        //   131: aload_3        
        //   132: iconst_1       
        //   133: aload           7
        //   135: getfield        dvi.r:I
        //   138: iastore        
        //   139: iconst_0       
        //   140: istore          5
        //   142: aload_0        
        //   143: monitorexit    
        //   144: iload           5
        //   146: ifne            178
        //   149: iload           4
        //   151: ifeq            160
        //   154: iconst_1       
        //   155: istore          4
        //   157: goto            178
        //   160: aload_0        
        //   161: aconst_null    
        //   162: iload_1        
        //   163: iload_2        
        //   164: iconst_1       
        //   165: aconst_null    
        //   166: bipush          7
        //   168: aconst_null    
        //   169: aconst_null    
        //   170: iconst_0       
        //   171: iconst_0       
        //   172: invokespecial   com/facebook/litho/ComponentTree.G:(Ldsw;IIZLdwt;ILjava/lang/String;Lcyd;ZZ)V
        //   175: goto            459
        //   178: new             Ldwt;
        //   181: astore          9
        //   183: aload           9
        //   185: invokespecial   dwt.<init>:()V
        //   188: aload_0        
        //   189: aconst_null    
        //   190: iload_1        
        //   191: iload_2        
        //   192: iconst_0       
        //   193: aload           9
        //   195: bipush          6
        //   197: aconst_null    
        //   198: aconst_null    
        //   199: iconst_0       
        //   200: iload           4
        //   202: invokespecial   com/facebook/litho/ComponentTree.G:(Ldsw;IIZLdwt;ILjava/lang/String;Lcyd;ZZ)V
        //   205: aload_0        
        //   206: monitorenter   
        //   207: aload_0        
        //   208: getfield        com/facebook/litho/ComponentTree.J:Z
        //   211: ifne            465
        //   214: aload_0        
        //   215: getfield        com/facebook/litho/ComponentTree.u:Ldvi;
        //   218: aload_0        
        //   219: getfield        com/facebook/litho/ComponentTree.t:Ldvi;
        //   222: if_acmpeq       229
        //   225: aload_0        
        //   226: invokespecial   com/facebook/litho/ComponentTree.D:()V
        //   229: aload_0        
        //   230: getfield        com/facebook/litho/ComponentTree.t:Ldvi;
        //   233: astore          7
        //   235: aload           7
        //   237: ifnull          259
        //   240: aload_3        
        //   241: iconst_0       
        //   242: aload           7
        //   244: getfield        dvi.q:I
        //   247: iastore        
        //   248: aload_3        
        //   249: iconst_1       
        //   250: aload           7
        //   252: getfield        dvi.r:I
        //   255: iastore        
        //   256: goto            457
        //   259: aload_3        
        //   260: iconst_0       
        //   261: aload           9
        //   263: getfield        dwt.a:I
        //   266: iastore        
        //   267: aload_3        
        //   268: iconst_1       
        //   269: aload           9
        //   271: getfield        dwt.b:I
        //   274: iastore        
        //   275: iload_1        
        //   276: invokestatic    android/view/View$MeasureSpec.toString:(I)Ljava/lang/String;
        //   279: astore          7
        //   281: iload_2        
        //   282: invokestatic    android/view/View$MeasureSpec.toString:(I)Ljava/lang/String;
        //   285: astore_3       
        //   286: aload_0        
        //   287: getfield        com/facebook/litho/ComponentTree.X:I
        //   290: invokestatic    android/view/View$MeasureSpec.toString:(I)Ljava/lang/String;
        //   293: astore          10
        //   295: aload_0        
        //   296: getfield        com/facebook/litho/ComponentTree.Y:I
        //   299: invokestatic    android/view/View$MeasureSpec.toString:(I)Ljava/lang/String;
        //   302: astore          8
        //   304: aload           9
        //   306: getfield        dwt.a:I
        //   309: istore_2       
        //   310: aload           9
        //   312: getfield        dwt.b:I
        //   315: istore_1       
        //   316: aload_0        
        //   317: getfield        com/facebook/litho/ComponentTree.Z:I
        //   320: invokestatic    dvi.g:(I)Ljava/lang/String;
        //   323: astore          9
        //   325: new             Ljava/lang/StringBuilder;
        //   328: astore          11
        //   330: aload           11
        //   332: ldc_w           "Measure Specs: ["
        //   335: invokespecial   java/lang/StringBuilder.<init>:(Ljava/lang/String;)V
        //   338: aload           11
        //   340: aload           7
        //   342: invokevirtual   java/lang/StringBuilder.append:(Ljava/lang/String;)Ljava/lang/StringBuilder;
        //   345: pop            
        //   346: aload           11
        //   348: ldc_w           ", "
        //   351: invokevirtual   java/lang/StringBuilder.append:(Ljava/lang/String;)Ljava/lang/StringBuilder;
        //   354: pop            
        //   355: aload           11
        //   357: aload_3        
        //   358: invokevirtual   java/lang/StringBuilder.append:(Ljava/lang/String;)Ljava/lang/StringBuilder;
        //   361: pop            
        //   362: aload           11
        //   364: ldc_w           "], Current Specs: ["
        //   367: invokevirtual   java/lang/StringBuilder.append:(Ljava/lang/String;)Ljava/lang/StringBuilder;
        //   370: pop            
        //   371: aload           11
        //   373: aload           10
        //   375: invokevirtual   java/lang/StringBuilder.append:(Ljava/lang/String;)Ljava/lang/StringBuilder;
        //   378: pop            
        //   379: aload           11
        //   381: ldc_w           ", "
        //   384: invokevirtual   java/lang/StringBuilder.append:(Ljava/lang/String;)Ljava/lang/StringBuilder;
        //   387: pop            
        //   388: aload           11
        //   390: aload           8
        //   392: invokevirtual   java/lang/StringBuilder.append:(Ljava/lang/String;)Ljava/lang/StringBuilder;
        //   395: pop            
        //   396: aload           11
        //   398: ldc_w           "], Output [W: "
        //   401: invokevirtual   java/lang/StringBuilder.append:(Ljava/lang/String;)Ljava/lang/StringBuilder;
        //   404: pop            
        //   405: aload           11
        //   407: iload_2        
        //   408: invokevirtual   java/lang/StringBuilder.append:(I)Ljava/lang/StringBuilder;
        //   411: pop            
        //   412: aload           11
        //   414: ldc_w           ", H:"
        //   417: invokevirtual   java/lang/StringBuilder.append:(Ljava/lang/String;)Ljava/lang/StringBuilder;
        //   420: pop            
        //   421: aload           11
        //   423: iload_1        
        //   424: invokevirtual   java/lang/StringBuilder.append:(I)Ljava/lang/StringBuilder;
        //   427: pop            
        //   428: aload           11
        //   430: ldc_w           "], Last Layout Source: "
        //   433: invokevirtual   java/lang/StringBuilder.append:(Ljava/lang/String;)Ljava/lang/StringBuilder;
        //   436: pop            
        //   437: aload           11
        //   439: aload           9
        //   441: invokevirtual   java/lang/StringBuilder.append:(Ljava/lang/String;)Ljava/lang/StringBuilder;
        //   444: pop            
        //   445: iconst_2       
        //   446: ldc_w           "NullLayoutStateInMeasure"
        //   449: aload           11
        //   451: invokevirtual   java/lang/StringBuilder.toString:()Ljava/lang/String;
        //   454: invokestatic    cqj.c:(ILjava/lang/String;Ljava/lang/String;)V
        //   457: aload_0        
        //   458: monitorexit    
        //   459: aload_0        
        //   460: iconst_0       
        //   461: putfield        com/facebook/litho/ComponentTree.N:Z
        //   464: return         
        //   465: new             Ljava/lang/RuntimeException;
        //   468: astore_3       
        //   469: aload_3        
        //   470: ldc_w           "Tree is released during measure!"
        //   473: invokespecial   java/lang/RuntimeException.<init>:(Ljava/lang/String;)V
        //   476: aload_3        
        //   477: athrow         
        //   478: astore_3       
        //   479: aload_0        
        //   480: monitorexit    
        //   481: aload_3        
        //   482: athrow         
        //   483: astore_3       
        //   484: aload_0        
        //   485: monitorexit    
        //   486: aload_3        
        //   487: athrow         
        //   488: astore_3       
        //   489: goto            497
        //   492: astore_3       
        //   493: goto            484
        //   496: astore_3       
        //   497: aload_0        
        //   498: iconst_0       
        //   499: putfield        com/facebook/litho/ComponentTree.N:Z
        //   502: goto            507
        //   505: aload_3        
        //   506: athrow         
        //   507: goto            505
        //    Exceptions:
        //  Try           Handler
        //  Start  End    Start  End    Type
        //  -----  -----  -----  -----  ----
        //  8      10     496    497    Any
        //  10     16     483    488    Any
        //  21     44     483    488    Any
        //  44     50     483    488    Any
        //  55     73     483    488    Any
        //  82     98     483    488    Any
        //  117    139    483    488    Any
        //  142    144    483    488    Any
        //  160    175    496    497    Any
        //  178    188    496    497    Any
        //  188    207    488    492    Any
        //  207    229    478    483    Any
        //  229    235    478    483    Any
        //  240    256    478    483    Any
        //  259    457    478    483    Any
        //  457    459    478    483    Any
        //  465    478    478    483    Any
        //  479    481    478    483    Any
        //  481    483    488    492    Any
        //  484    486    492    496    Any
        //  486    488    488    492    Any
        // 
        // The error that occurred was:
        // 
        // java.lang.IndexOutOfBoundsException: Index: 268, Size: 268
        //     at java.util.ArrayList.rangeCheck(Unknown Source)
        //     at java.util.ArrayList.get(Unknown Source)
        //     at com.strobel.decompiler.ast.AstBuilder.convertToAst(AstBuilder.java:3362)
        //     at com.strobel.decompiler.ast.AstBuilder.convertToAst(AstBuilder.java:3476)
        //     at com.strobel.decompiler.ast.AstBuilder.build(AstBuilder.java:112)
        //     at com.strobel.decompiler.languages.java.ast.AstMethodBodyBuilder.createMethodBody(AstMethodBodyBuilder.java:203)
        //     at com.strobel.decompiler.languages.java.ast.AstMethodBodyBuilder.createMethodBody(AstMethodBodyBuilder.java:93)
        //     at com.strobel.decompiler.languages.java.ast.AstBuilder.createMethodBody(AstBuilder.java:868)
        //     at com.strobel.decompiler.languages.java.ast.AstBuilder.createMethod(AstBuilder.java:761)
        //     at com.strobel.decompiler.languages.java.ast.AstBuilder.addTypeMembers(AstBuilder.java:638)
        //     at com.strobel.decompiler.languages.java.ast.AstBuilder.createTypeCore(AstBuilder.java:605)
        //     at com.strobel.decompiler.languages.java.ast.AstBuilder.createTypeNoCache(AstBuilder.java:195)
        //     at com.strobel.decompiler.languages.java.ast.AstBuilder.createType(AstBuilder.java:162)
        //     at com.strobel.decompiler.languages.java.ast.AstBuilder.addType(AstBuilder.java:137)
        //     at com.strobel.decompiler.languages.java.JavaLanguage.buildAst(JavaLanguage.java:71)
        //     at com.strobel.decompiler.languages.java.JavaLanguage.decompileType(JavaLanguage.java:59)
        //     at com.strobel.decompiler.DecompilerDriver.decompileType(DecompilerDriver.java:333)
        //     at com.strobel.decompiler.DecompilerDriver.decompileJar(DecompilerDriver.java:254)
        //     at com.strobel.decompiler.DecompilerDriver.main(DecompilerDriver.java:129)
        // 
        throw new IllegalStateException("An error occurred while decompiling this method.");
    }
    
    public final void m(final Rect rect, final boolean b) {
        bkx.q();
        if (this.h) {
            final fwz fwz = new fwz(rect, b);
            final Deque l = this.L;
            if (l == null) {
                this.L = new ArrayDeque();
            }
            else if (l.size() > 25) {
                final dvx m = this.m;
                String a;
                if (m != null) {
                    a = LithoViewTestHelper.a(m);
                }
                else {
                    a = null;
                }
                Object o;
                if ((o = this.s) == null) {
                    o = this.e();
                }
                final String value = String.valueOf(o);
                final StringBuilder sb = new StringBuilder("Reentrant mounts exceed max attempts, view=");
                sb.append(a);
                sb.append(", component=");
                sb.append(value);
                cqj.c(3, "ComponentTree:ReentrantMountsExceedMaxAttempts", sb.toString());
                this.L.clear();
                return;
            }
            this.L.add(fwz);
            return;
        }
        this.C(rect, b);
        final Deque i = this.L;
        if (i != null) {
            final ArrayDeque arrayDeque = new ArrayDeque(i);
            this.L.clear();
            while (!arrayDeque.isEmpty()) {
                final fwz fwz2 = (fwz)arrayDeque.pollFirst();
                this.m.D();
                this.C((Rect)fwz2.b, fwz2.a);
            }
        }
    }
    
    public final void n() {
        if (!this.h) {
            synchronized (this) {
                ((dvm)this.Q).removeCallbacks(this.R);
                Object o = this.o;
                synchronized (o) {
                    final dtk p = this.p;
                    if (p != null) {
                        this.n.a((Runnable)p);
                        this.p = null;
                    }
                    monitorexit(o);
                    o = this.e;
                    synchronized (o) {
                        final dtn f = this.f;
                        if (f != null) {
                            this.n.a((Runnable)f);
                            this.f = null;
                        }
                        monitorexit(o);
                        o = this.S;
                        monitorenter(o);
                        final int n = 0;
                        int i = 0;
                        try {
                            while (i < this.T.size()) {
                                ((dtl)this.T.get(i)).a();
                                ++i;
                            }
                            this.T.clear();
                            monitorexit(o);
                            this.J = true;
                            o = this.s;
                            if (o != null) {
                                this.K = ((dsw)o).q();
                            }
                            o = this.m;
                            if (o != null) {
                                ((dvx)o).B((ComponentTree)null);
                            }
                            this.s = null;
                            this.B();
                            this.t = null;
                            this.u = null;
                            this.v = null;
                            this.d = null;
                            monitorexit(this);
                            synchronized (this.af) {
                                this.A();
                                monitorexit(this.af);
                                if (this.ab != null) {
                                    Object ab = this.ab;
                                    monitorenter(ab);
                                    try {
                                        if (((ema)ab).a == null) {
                                            return;
                                        }
                                        final ArrayList list = new ArrayList();
                                        final ArrayList list2 = new ArrayList();
                                        for (final Map.Entry<K, dsw> entry : ((Map<Object, Object>)((ema)ab).a).entrySet()) {
                                            list.add(entry.getValue());
                                            list2.add(entry.getKey());
                                        }
                                        ((Map)((ema)ab).a).clear();
                                        monitorexit(ab);
                                        for (int size = list.size(), j = n; j < size; ++j) {
                                            ab = list.get(j);
                                            final String s = (String)list2.get(j);
                                            final dta p2 = ((dsw)ab).p;
                                            ((dtg)ab).as();
                                        }
                                    }
                                    finally {}
                                }
                                return;
                            }
                        }
                        finally {
                            monitorexit(o);
                        }
                    }
                }
            }
        }
        throw new IllegalStateException("Releasing a ComponentTree that is currently being mounted");
    }
    
    public final void o(final dsw dsw, final int n, final int n2, final dwt dwt) {
        if (dsw != null) {
            this.y(dsw, n, n2, false, dwt, 0, null);
            return;
        }
        throw new IllegalArgumentException("Root component can't be null");
    }
    
    public final void p(final boolean b, final String s, final boolean b2) {
        final boolean a = dys.a;
        synchronized (this) {
            final dsw s2 = this.s;
            if (s2 != null) {
                final dsw j = s2.j();
                final cyd x = cyd.x(this.ae);
                if (b2 && ++this.M == 50) {
                    cqj.c(3, "ComponentTree:StateUpdatesWhenLayoutInProgressExceedsThreshold", "State Updates when create layout in progress exceeds threshold");
                }
                monitorexit(this);
                int n;
                if (!b) {
                    n = 4;
                }
                else {
                    n = 5;
                }
                this.G(j, -1, -1, b, null, n, s, x, b2, false);
            }
        }
    }
    
    public final boolean q(final int n, final int n2) {
        synchronized (this) {
            return F(this.t, n, n2) || F(this.u, n, n2);
        }
    }
    
    public final boolean s() {
        synchronized (this) {
            return this.J;
        }
    }
    
    public final boolean t() {
        if (!this.m.G() && !this.m.H()) {
            if (this.O) {
                final dwc k = this.m.k;
                bkx.q();
                this.m.w();
            }
            return false;
        }
        if (this.i) {
            this.k();
        }
        else {
            final Rect rect = new Rect();
            this.m.getLocalVisibleRect(rect);
            this.m(rect, true);
        }
        return true;
    }
    
    public final void u(final int n, final int n2, final int n3) {
        monitorenter(this);
        try {
            final dvi u = this.u;
            if (u != null) {
                final cyd ad = this.ad;
                final ema g = u.G;
                if (g != null) {
                    final Object a = g.a;
                    if (a != null) {
                        final Iterator iterator = ((Map)a).keySet().iterator();
                        while (iterator.hasNext()) {
                            final hzf hzf = ((Map<K, hzf>)g.a).get(iterator.next());
                            for (int size = ((List)hzf.c).size(), i = 0; i < size; ++i) {
                                final dsw dsw = ((List<dsw>)hzf.c).get(i);
                                final String s = ((List<String>)hzf.a).get(i);
                                final Object b = hzf.b;
                                if (!ad.s(dsw)) {
                                    final int n4 = (int)((n3 - n2 + 1) * ((owr)hzf.d).a);
                                    if (n >= n2 - n4 && n <= n4 + n3) {
                                        final dta p3 = dsw.p;
                                        final Object b2 = hzf.b;
                                        ((dtg)dsw).ap();
                                        final Object b3 = hzf.b;
                                        ad.t(dsw, 1);
                                        continue;
                                    }
                                }
                                final Object b4 = hzf.b;
                                if (ad.s(dsw)) {
                                    final int n5 = (int)((n3 - n2 + 1) * ((owr)hzf.d).a);
                                    if (n < n2 - n5 || n > n5 + n3) {
                                        final dta p4 = dsw.p;
                                        final Object b5 = hzf.b;
                                        ((dtg)dsw).ao();
                                        final Object b6 = hzf.b;
                                        ad.t(dsw, 2);
                                    }
                                }
                            }
                        }
                    }
                }
            }
            monitorexit(this);
        }
        finally {
            monitorexit(this);
            while (true) {}
        }
    }
    
    public final int v(final int n, final boolean b, final trw trw) {
        if (trw == null) {
            return -1;
        }
        if (!this.q) {
            final Object b2 = trw.b;
            if (b2 != null) {
                return (int)dxj.f((dxi)b2, (egr)this.t);
            }
        }
        if (this.q && !b) {
            return n;
        }
        return -1;
    }
    
    public final med w() {
        med med;
        if ((med = this.E) == null) {
            med = this.g.p();
        }
        return med;
    }
    
    public final void x(final dwt p0, final int p1, final String p2, final cyd p3, final boolean p4) {
        // 
        // This method could not be decompiled.
        // 
        // Original Bytecode:
        // 
        //     1: getfield        com/facebook/litho/ComponentTree.o:Ljava/lang/Object;
        //     4: astore          16
        //     6: aload           16
        //     8: monitorenter   
        //     9: aload_0        
        //    10: getfield        com/facebook/litho/ComponentTree.p:Ldtk;
        //    13: astore          17
        //    15: aload           17
        //    17: ifnull          36
        //    20: aload_0        
        //    21: getfield        com/facebook/litho/ComponentTree.n:Ldvn;
        //    24: aload           17
        //    26: invokeinterface dvn.a:(Ljava/lang/Runnable;)V
        //    31: aload_0        
        //    32: aconst_null    
        //    33: putfield        com/facebook/litho/ComponentTree.p:Ldtk;
        //    36: aload           16
        //    38: monitorexit    
        //    39: aload_0        
        //    40: monitorenter   
        //    41: aload_0        
        //    42: getfield        com/facebook/litho/ComponentTree.X:I
        //    45: istore          6
        //    47: iload           6
        //    49: iconst_m1      
        //    50: if_icmpeq       2425
        //    53: aload_0        
        //    54: getfield        com/facebook/litho/ComponentTree.Y:I
        //    57: istore          7
        //    59: iload           7
        //    61: iconst_m1      
        //    62: if_icmpeq       2425
        //    65: aload_0        
        //    66: getfield        com/facebook/litho/ComponentTree.s:Ldsw;
        //    69: astore          16
        //    71: aload           16
        //    73: ifnonnull       79
        //    76: goto            2425
        //    79: aload_0        
        //    80: getfield        com/facebook/litho/ComponentTree.u:Ldvi;
        //    83: aload           16
        //    85: getfield        dsw.j:I
        //    88: iload           6
        //    90: iload           7
        //    92: invokestatic    com/facebook/litho/ComponentTree.E:(Ldvi;III)Z
        //    95: ifeq            126
        //    98: aload_1        
        //    99: ifnull          123
        //   102: aload_0        
        //   103: getfield        com/facebook/litho/ComponentTree.u:Ldvi;
        //   106: astore_3       
        //   107: aload_1        
        //   108: aload_3        
        //   109: getfield        dvi.q:I
        //   112: putfield        dwt.a:I
        //   115: aload_1        
        //   116: aload_3        
        //   117: getfield        dvi.r:I
        //   120: putfield        dwt.b:I
        //   123: aload_0        
        //   124: monitorexit    
        //   125: return         
        //   126: aload_0        
        //   127: getfield        com/facebook/litho/ComponentTree.X:I
        //   130: istore          6
        //   132: aload_0        
        //   133: getfield        com/facebook/litho/ComponentTree.Y:I
        //   136: istore          7
        //   138: aload_0        
        //   139: getfield        com/facebook/litho/ComponentTree.s:Ldsw;
        //   142: invokevirtual   dsw.j:()Ldsw;
        //   145: astore          19
        //   147: aload_0        
        //   148: getfield        com/facebook/litho/ComponentTree.V:I
        //   151: istore          11
        //   153: aload_0        
        //   154: iload           11
        //   156: iconst_1       
        //   157: iadd           
        //   158: putfield        com/facebook/litho/ComponentTree.V:I
        //   161: aload_0        
        //   162: monitorexit    
        //   163: aload_0        
        //   164: getfield        com/facebook/litho/ComponentTree.g:Ldta;
        //   167: astore          20
        //   169: new             Ldtl;
        //   172: dup            
        //   173: aload_0        
        //   174: aload           20
        //   176: aload           19
        //   178: iload           6
        //   180: iload           7
        //   182: aload_0        
        //   183: getfield        com/facebook/litho/ComponentTree.P:Z
        //   186: aload           4
        //   188: iload_2        
        //   189: aload_3        
        //   190: aconst_null    
        //   191: aconst_null    
        //   192: aconst_null    
        //   193: invokespecial   dtl.<init>:(Lcom/facebook/litho/ComponentTree;Ldta;Ldsw;IIZLcyd;ILjava/lang/String;[B[B[B)V
        //   196: astore_3       
        //   197: aload_0        
        //   198: getfield        com/facebook/litho/ComponentTree.S:Ljava/lang/Object;
        //   201: astore          4
        //   203: aload           4
        //   205: monitorenter   
        //   206: iconst_0       
        //   207: istore          9
        //   209: iconst_0       
        //   210: istore          6
        //   212: aload_0        
        //   213: getfield        com/facebook/litho/ComponentTree.T:Ljava/util/List;
        //   216: invokeinterface java/util/List.size:()I
        //   221: istore          7
        //   223: iconst_1       
        //   224: istore          8
        //   226: iload           6
        //   228: iload           7
        //   230: if_icmpge       278
        //   233: aload_0        
        //   234: getfield        com/facebook/litho/ComponentTree.T:Ljava/util/List;
        //   237: iload           6
        //   239: invokeinterface java/util/List.get:(I)Ljava/lang/Object;
        //   244: checkcast       Ldtl;
        //   247: astore          17
        //   249: aload           17
        //   251: getfield        dtl.o:Z
        //   254: ifne            272
        //   257: aload           17
        //   259: aload_3        
        //   260: invokevirtual   dtl.equals:(Ljava/lang/Object;)Z
        //   263: ifeq            272
        //   266: iconst_1       
        //   267: istore          6
        //   269: goto            284
        //   272: iinc            6, 1
        //   275: goto            212
        //   278: aload_3        
        //   279: astore          17
        //   281: iconst_0       
        //   282: istore          6
        //   284: iload           6
        //   286: ifne            301
        //   289: aload_0        
        //   290: getfield        com/facebook/litho/ComponentTree.T:Ljava/util/List;
        //   293: aload           17
        //   295: invokeinterface java/util/List.add:(Ljava/lang/Object;)Z
        //   300: pop            
        //   301: aload           17
        //   303: getfield        dtl.h:Ljava/util/concurrent/atomic/AtomicInteger;
        //   306: invokevirtual   java/util/concurrent/atomic/AtomicInteger.incrementAndGet:()I
        //   309: pop            
        //   310: aload           4
        //   312: monitorexit    
        //   313: aload           17
        //   315: getfield        dtl.a:Ljava/util/concurrent/atomic/AtomicInteger;
        //   318: iconst_m1      
        //   319: invokestatic    android/os/Process.myTid:()I
        //   322: invokevirtual   java/util/concurrent/atomic/AtomicInteger.compareAndSet:(II)Z
        //   325: ifeq            338
        //   328: aload           17
        //   330: getfield        dtl.g:Ljava/util/concurrent/RunnableFuture;
        //   333: invokeinterface java/util/concurrent/RunnableFuture.run:()V
        //   338: aload           17
        //   340: getfield        dtl.a:Ljava/util/concurrent/atomic/AtomicInteger;
        //   343: invokevirtual   java/util/concurrent/atomic/AtomicInteger.get:()I
        //   346: istore          12
        //   348: invokestatic    android/os/Process.myTid:()I
        //   351: istore          6
        //   353: aload           17
        //   355: getfield        dtl.g:Ljava/util/concurrent/RunnableFuture;
        //   358: invokeinterface java/util/concurrent/RunnableFuture.isDone:()Z
        //   363: ifne            379
        //   366: iload           12
        //   368: iload           6
        //   370: if_icmpeq       379
        //   373: iconst_1       
        //   374: istore          6
        //   376: goto            382
        //   379: iconst_0       
        //   380: istore          6
        //   382: aload           17
        //   384: getfield        dtl.i:Z
        //   387: istore          15
        //   389: iload           6
        //   391: ifeq            412
        //   394: invokestatic    bkx.r:()Z
        //   397: ifne            412
        //   400: iload_2        
        //   401: invokestatic    com/facebook/litho/ComponentTree.r:(I)Z
        //   404: ifne            412
        //   407: aconst_null    
        //   408: astore_3       
        //   409: goto            876
        //   412: invokestatic    bkx.r:()Z
        //   415: ifeq            512
        //   418: iload           6
        //   420: ifeq            512
        //   423: aload           17
        //   425: getfield        dtl.p:Lcom/facebook/litho/ComponentTree;
        //   428: getfield        com/facebook/litho/ComponentTree.z:Z
        //   431: ifeq            455
        //   434: iload           15
        //   436: ifne            455
        //   439: aload           17
        //   441: iconst_1       
        //   442: putfield        dtl.j:Z
        //   445: getstatic       bky.a:Ldxu;
        //   448: astore_3       
        //   449: aload           17
        //   451: aconst_null    
        //   452: putfield        dtl.m:Ljava/lang/Object;
        //   455: iload           12
        //   457: invokestatic    android/os/Process.getThreadPriority:(I)I
        //   460: istore          10
        //   462: bipush          -4
        //   464: istore          7
        //   466: iconst_0       
        //   467: istore          6
        //   469: iload           6
        //   471: ifne            501
        //   474: iload           7
        //   476: iload           10
        //   478: if_icmpge       501
        //   481: iload           12
        //   483: iload           7
        //   485: invokestatic    android/os/Process.setThreadPriority:(II)V
        //   488: iconst_1       
        //   489: istore          6
        //   491: goto            469
        //   494: astore_3       
        //   495: iinc            7, 1
        //   498: goto            469
        //   501: iconst_1       
        //   502: istore          6
        //   504: iload           10
        //   506: istore          7
        //   508: goto            518
        //   511: astore_3       
        //   512: iconst_0       
        //   513: istore          7
        //   515: iconst_0       
        //   516: istore          6
        //   518: aload           17
        //   520: getfield        dtl.p:Lcom/facebook/litho/ComponentTree;
        //   523: invokevirtual   com/facebook/litho/ComponentTree.w:()Lmed;
        //   526: astore          4
        //   528: aload           4
        //   530: ifnull          567
        //   533: aload           17
        //   535: getfield        dtl.p:Lcom/facebook/litho/ComponentTree;
        //   538: getfield        com/facebook/litho/ComponentTree.g:Ldta;
        //   541: astore_3       
        //   542: aload_3        
        //   543: aload           4
        //   545: aload           4
        //   547: aload_3        
        //   548: bipush          21
        //   550: invokevirtual   med.u:(Ldta;I)Ldwn;
        //   553: invokestatic    bkx.v:(Ldta;Lmed;Ldwn;)Ldwn;
        //   556: astore_3       
        //   557: goto            569
        //   560: astore          4
        //   562: aconst_null    
        //   563: astore_1       
        //   564: goto            2355
        //   567: aconst_null    
        //   568: astore_3       
        //   569: aload           17
        //   571: getfield        dtl.g:Ljava/util/concurrent/RunnableFuture;
        //   574: invokestatic    aewr.G:(Ljava/util/concurrent/Future;)Ljava/lang/Object;
        //   577: checkcast       Ldvi;
        //   580: astore          18
        //   582: aload_3        
        //   583: ifnull          612
        //   586: aload_3        
        //   587: astore          16
        //   589: aload_3        
        //   590: ldc_w           "FUTURE_TASK_END"
        //   593: invokeinterface dwn.b:(Ljava/lang/String;)V
        //   598: goto            612
        //   601: astore_1       
        //   602: aload           16
        //   604: astore_3       
        //   605: goto            2405
        //   608: astore_1       
        //   609: goto            2375
        //   612: iload           6
        //   614: ifeq            627
        //   617: aload_3        
        //   618: astore          16
        //   620: iload           12
        //   622: iload           7
        //   624: invokestatic    android/os/Process.setThreadPriority:(II)V
        //   627: aload_3        
        //   628: astore          16
        //   630: aload           18
        //   632: astore          4
        //   634: aload           17
        //   636: getfield        dtl.j:Z
        //   639: ifeq            833
        //   642: aload_3        
        //   643: astore          16
        //   645: aload           18
        //   647: astore          4
        //   649: aload           18
        //   651: getfield        dvi.z:Z
        //   654: ifeq            833
        //   657: aload_3        
        //   658: astore          16
        //   660: invokestatic    bkx.r:()Z
        //   663: ifeq            794
        //   666: aload_3        
        //   667: astore          16
        //   669: aload           17
        //   671: getfield        dtl.n:Ljava/lang/Object;
        //   674: astore          4
        //   676: aload_3        
        //   677: astore          16
        //   679: getstatic       bky.a:Ldxu;
        //   682: astore          4
        //   684: aload_3        
        //   685: astore          16
        //   687: aload           17
        //   689: aconst_null    
        //   690: putfield        dtl.n:Ljava/lang/Object;
        //   693: aload           17
        //   695: getfield        dtl.o:Z
        //   698: ifeq            707
        //   701: aconst_null    
        //   702: astore          4
        //   704: goto            753
        //   707: aload           17
        //   709: getfield        dtl.k:I
        //   712: istore          6
        //   714: aload           17
        //   716: getfield        dtl.l:Ljava/lang/String;
        //   719: astore          4
        //   721: iload           6
        //   723: aload           18
        //   725: invokestatic    dvi.n:(ILdvi;)V
        //   728: aload           17
        //   730: monitorenter   
        //   731: iconst_1       
        //   732: aload           17
        //   734: getfield        dtl.o:Z
        //   737: if_icmpeq       747
        //   740: aload           18
        //   742: astore          4
        //   744: goto            750
        //   747: aconst_null    
        //   748: astore          4
        //   750: aload           17
        //   752: monitorexit    
        //   753: aload_3        
        //   754: astore          16
        //   756: getstatic       bky.a:Ldxu;
        //   759: astore          18
        //   761: goto            833
        //   764: astore_1       
        //   765: aload           17
        //   767: monitorexit    
        //   768: aload_1        
        //   769: athrow         
        //   770: astore          4
        //   772: getstatic       bky.a:Ldxu;
        //   775: astore_1       
        //   776: aload           4
        //   778: athrow         
        //   779: astore          4
        //   781: aload_3        
        //   782: astore          16
        //   784: getstatic       bky.a:Ldxu;
        //   787: astore_1       
        //   788: aload_3        
        //   789: astore          16
        //   791: aload           4
        //   793: athrow         
        //   794: aload_3        
        //   795: astore          16
        //   797: aload           17
        //   799: getfield        dtl.m:Ljava/lang/Object;
        //   802: astore          4
        //   804: aload_3        
        //   805: astore          16
        //   807: getstatic       bky.a:Ldxu;
        //   810: astore          4
        //   812: aload_3        
        //   813: astore          16
        //   815: aload           17
        //   817: aconst_null    
        //   818: putfield        dtl.n:Ljava/lang/Object;
        //   821: aload_3        
        //   822: astore          16
        //   824: aload           17
        //   826: aconst_null    
        //   827: putfield        dtl.m:Ljava/lang/Object;
        //   830: aconst_null    
        //   831: astore          4
        //   833: aload_3        
        //   834: ifnull          845
        //   837: invokestatic    bkx.r:()Z
        //   840: pop            
        //   841: aload_3        
        //   842: invokestatic    med.x:(Ldwn;)V
        //   845: aload           4
        //   847: ifnonnull       853
        //   850: goto            407
        //   853: aload           17
        //   855: monitorenter   
        //   856: aload           17
        //   858: getfield        dtl.o:Z
        //   861: ifeq            870
        //   864: aload           17
        //   866: monitorexit    
        //   867: goto            407
        //   870: aload           17
        //   872: monitorexit    
        //   873: aload           4
        //   875: astore_3       
        //   876: aload_0        
        //   877: getfield        com/facebook/litho/ComponentTree.S:Ljava/lang/Object;
        //   880: astore          4
        //   882: aload           4
        //   884: monitorenter   
        //   885: aload           17
        //   887: getfield        dtl.h:Ljava/util/concurrent/atomic/AtomicInteger;
        //   890: invokevirtual   java/util/concurrent/atomic/AtomicInteger.decrementAndGet:()I
        //   893: iflt            2326
        //   896: aload           17
        //   898: getfield        dtl.h:Ljava/util/concurrent/atomic/AtomicInteger;
        //   901: invokevirtual   java/util/concurrent/atomic/AtomicInteger.get:()I
        //   904: ifne            924
        //   907: aload           17
        //   909: invokevirtual   dtl.a:()V
        //   912: aload_0        
        //   913: getfield        com/facebook/litho/ComponentTree.T:Ljava/util/List;
        //   916: aload           17
        //   918: invokeinterface java/util/List.remove:(Ljava/lang/Object;)Z
        //   923: pop            
        //   924: aload           4
        //   926: monitorexit    
        //   927: aload           19
        //   929: getfield        dsw.r:Landroid/content/Context;
        //   932: astore          4
        //   934: aload           4
        //   936: ifnull          1067
        //   939: aload           20
        //   941: getfield        dta.b:Landroid/content/Context;
        //   944: astore          16
        //   946: aload           4
        //   948: aload           16
        //   950: if_acmpeq       1067
        //   953: aload           16
        //   955: invokestatic    java/lang/String.valueOf:(Ljava/lang/Object;)Ljava/lang/String;
        //   958: astore          4
        //   960: aload           19
        //   962: getfield        dsw.r:Landroid/content/Context;
        //   965: invokestatic    java/lang/String.valueOf:(Ljava/lang/Object;)Ljava/lang/String;
        //   968: astore          16
        //   970: aload           19
        //   972: invokevirtual   dsw.q:()Ljava/lang/String;
        //   975: astore          17
        //   977: aload           20
        //   979: invokestatic    cpc.b:(Ldta;)Ljava/lang/String;
        //   982: astore          18
        //   984: new             Ljava/lang/StringBuilder;
        //   987: dup            
        //   988: ldc_w           "ComponentTree context is different from root builder context, ComponentTree context="
        //   991: invokespecial   java/lang/StringBuilder.<init>:(Ljava/lang/String;)V
        //   994: astore          20
        //   996: aload           20
        //   998: aload           4
        //  1000: invokevirtual   java/lang/StringBuilder.append:(Ljava/lang/String;)Ljava/lang/StringBuilder;
        //  1003: pop            
        //  1004: aload           20
        //  1006: ldc_w           ", root builder context="
        //  1009: invokevirtual   java/lang/StringBuilder.append:(Ljava/lang/String;)Ljava/lang/StringBuilder;
        //  1012: pop            
        //  1013: aload           20
        //  1015: aload           16
        //  1017: invokevirtual   java/lang/StringBuilder.append:(Ljava/lang/String;)Ljava/lang/StringBuilder;
        //  1020: pop            
        //  1021: aload           20
        //  1023: ldc_w           ", root="
        //  1026: invokevirtual   java/lang/StringBuilder.append:(Ljava/lang/String;)Ljava/lang/StringBuilder;
        //  1029: pop            
        //  1030: aload           20
        //  1032: aload           17
        //  1034: invokevirtual   java/lang/StringBuilder.append:(Ljava/lang/String;)Ljava/lang/StringBuilder;
        //  1037: pop            
        //  1038: aload           20
        //  1040: ldc_w           ", ContextTree="
        //  1043: invokevirtual   java/lang/StringBuilder.append:(Ljava/lang/String;)Ljava/lang/StringBuilder;
        //  1046: pop            
        //  1047: aload           20
        //  1049: aload           18
        //  1051: invokevirtual   java/lang/StringBuilder.append:(Ljava/lang/String;)Ljava/lang/StringBuilder;
        //  1054: pop            
        //  1055: iconst_2       
        //  1056: ldc_w           "ComponentTree:CTContextIsDifferentFromRootBuilderContext"
        //  1059: aload           20
        //  1061: invokevirtual   java/lang/StringBuilder.toString:()Ljava/lang/String;
        //  1064: invokestatic    cqj.c:(ILjava/lang/String;Ljava/lang/String;)V
        //  1067: aload_3        
        //  1068: ifnonnull       1215
        //  1071: aload_0        
        //  1072: invokevirtual   com/facebook/litho/ComponentTree.s:()Z
        //  1075: ifne            1214
        //  1078: iload_2        
        //  1079: invokestatic    com/facebook/litho/ComponentTree.r:(I)Z
        //  1082: ifeq            1214
        //  1085: iload_2        
        //  1086: invokestatic    dvi.g:(I)Ljava/lang/String;
        //  1089: astore          4
        //  1091: invokestatic    java/lang/Thread.currentThread:()Ljava/lang/Thread;
        //  1094: invokevirtual   java/lang/Thread.getName:()Ljava/lang/String;
        //  1097: astore_3       
        //  1098: aload_0        
        //  1099: getfield        com/facebook/litho/ComponentTree.s:Ldsw;
        //  1102: astore_1       
        //  1103: aload_1        
        //  1104: ifnonnull       1114
        //  1107: ldc_w           "null"
        //  1110: astore_1       
        //  1111: goto            1119
        //  1114: aload_1        
        //  1115: invokevirtual   dsw.q:()Ljava/lang/String;
        //  1118: astore_1       
        //  1119: aload_0        
        //  1120: getfield        com/facebook/litho/ComponentTree.z:Z
        //  1123: istore          5
        //  1125: new             Ljava/lang/StringBuilder;
        //  1128: dup            
        //  1129: ldc_w           "LayoutState is null, but only async operations can return a null LayoutState. Source: "
        //  1132: invokespecial   java/lang/StringBuilder.<init>:(Ljava/lang/String;)V
        //  1135: astore          16
        //  1137: aload           16
        //  1139: aload           4
        //  1141: invokevirtual   java/lang/StringBuilder.append:(Ljava/lang/String;)Ljava/lang/StringBuilder;
        //  1144: pop            
        //  1145: aload           16
        //  1147: ldc_w           ", current thread: "
        //  1150: invokevirtual   java/lang/StringBuilder.append:(Ljava/lang/String;)Ljava/lang/StringBuilder;
        //  1153: pop            
        //  1154: aload           16
        //  1156: aload_3        
        //  1157: invokevirtual   java/lang/StringBuilder.append:(Ljava/lang/String;)Ljava/lang/StringBuilder;
        //  1160: pop            
        //  1161: aload           16
        //  1163: ldc_w           ". Root: "
        //  1166: invokevirtual   java/lang/StringBuilder.append:(Ljava/lang/String;)Ljava/lang/StringBuilder;
        //  1169: pop            
        //  1170: aload           16
        //  1172: aload_1        
        //  1173: invokevirtual   java/lang/StringBuilder.append:(Ljava/lang/String;)Ljava/lang/StringBuilder;
        //  1176: pop            
        //  1177: aload           16
        //  1179: ldc_w           ". Interruptible layouts: "
        //  1182: invokevirtual   java/lang/StringBuilder.append:(Ljava/lang/String;)Ljava/lang/StringBuilder;
        //  1185: pop            
        //  1186: aload           16
        //  1188: iload           5
        //  1190: invokevirtual   java/lang/StringBuilder.append:(Z)Ljava/lang/StringBuilder;
        //  1193: pop            
        //  1194: aload           16
        //  1196: invokevirtual   java/lang/StringBuilder.toString:()Ljava/lang/String;
        //  1199: astore_1       
        //  1200: getstatic       dys.a:Z
        //  1203: istore          5
        //  1205: new             Ljava/lang/IllegalStateException;
        //  1208: dup            
        //  1209: aload_1        
        //  1210: invokespecial   java/lang/IllegalStateException.<init>:(Ljava/lang/String;)V
        //  1213: athrow         
        //  1214: return         
        //  1215: aload_1        
        //  1216: ifnull          1235
        //  1219: aload_1        
        //  1220: aload_3        
        //  1221: getfield        dvi.q:I
        //  1224: putfield        dwt.a:I
        //  1227: aload_1        
        //  1228: aload_3        
        //  1229: getfield        dvi.r:I
        //  1232: putfield        dwt.b:I
        //  1235: aload_0        
        //  1236: monitorenter   
        //  1237: iload           11
        //  1239: aload_0        
        //  1240: getfield        com/facebook/litho/ComponentTree.W:I
        //  1243: if_icmple       1291
        //  1246: aload_3        
        //  1247: getfield        dvi.E:Z
        //  1250: ifne            1291
        //  1253: aload_3        
        //  1254: aload_0        
        //  1255: getfield        com/facebook/litho/ComponentTree.X:I
        //  1258: aload_0        
        //  1259: getfield        com/facebook/litho/ComponentTree.Y:I
        //  1262: invokestatic    com/facebook/litho/ComponentTree.F:(Ldvi;II)Z
        //  1265: ifeq            1291
        //  1268: aload_0        
        //  1269: iload           11
        //  1271: putfield        com/facebook/litho/ComponentTree.W:I
        //  1274: aload_0        
        //  1275: aload_3        
        //  1276: putfield        com/facebook/litho/ComponentTree.u:Ldvi;
        //  1279: aload_3        
        //  1280: iconst_1       
        //  1281: putfield        dvi.E:Z
        //  1284: iload           8
        //  1286: istore          7
        //  1288: goto            1294
        //  1291: iconst_0       
        //  1292: istore          7
        //  1294: aload_3        
        //  1295: getfield        dvi.w:Ldwv;
        //  1298: astore          17
        //  1300: aconst_null    
        //  1301: astore_1       
        //  1302: aload_3        
        //  1303: aconst_null    
        //  1304: putfield        dvi.w:Ldwv;
        //  1307: iload           7
        //  1309: ifne            1325
        //  1312: aconst_null    
        //  1313: astore          4
        //  1315: iconst_0       
        //  1316: istore_2       
        //  1317: iconst_0       
        //  1318: istore          6
        //  1320: aload_1        
        //  1321: astore_3       
        //  1322: goto            1990
        //  1325: aload_3        
        //  1326: getfield        dvi.a:Ljava/util/List;
        //  1329: astore          16
        //  1331: aload_3        
        //  1332: aconst_null    
        //  1333: putfield        dvi.a:Ljava/util/List;
        //  1336: aload_3        
        //  1337: aconst_null    
        //  1338: putfield        dvi.b:Ljava/util/List;
        //  1341: aload           17
        //  1343: ifnull          1950
        //  1346: aload_0        
        //  1347: getfield        com/facebook/litho/ComponentTree.v:Ldwv;
        //  1350: astore          4
        //  1352: aload           4
        //  1354: ifnull          1950
        //  1357: getstatic       dys.t:Z
        //  1360: ifeq            1483
        //  1363: aload           16
        //  1365: aload           19
        //  1367: invokeinterface java/util/List.indexOf:(Ljava/lang/Object;)I
        //  1372: pop            
        //  1373: aload           19
        //  1375: invokestatic    cqj.l:(Ldsw;)Ljava/lang/String;
        //  1378: pop            
        //  1379: getstatic       dtw.a:Ljava/util/HashSet;
        //  1382: aload_0        
        //  1383: getfield        com/facebook/litho/ComponentTree.w:I
        //  1386: invokestatic    java/lang/Integer.valueOf:(I)Ljava/lang/Integer;
        //  1389: invokevirtual   java/util/HashSet.remove:(Ljava/lang/Object;)Z
        //  1392: ifne            1483
        //  1395: new             Ldwv;
        //  1398: aload           4
        //  1400: invokespecial   dwv.<init>:(Ldwv;)V
        //  1403: aload_0        
        //  1404: getfield        com/facebook/litho/ComponentTree.ac:Lbhy;
        //  1407: astore_1       
        //  1408: aload_1        
        //  1409: ifnonnull       1430
        //  1412: new             Lbhy;
        //  1415: astore_1       
        //  1416: aload_1        
        //  1417: aload           19
        //  1419: invokespecial   bhy.<init>:(Ldsw;)V
        //  1422: aload_0        
        //  1423: aload_1        
        //  1424: putfield        com/facebook/litho/ComponentTree.ac:Lbhy;
        //  1427: goto            1483
        //  1430: aload_1        
        //  1431: getfield        bhy.a:Ljava/lang/Object;
        //  1434: astore          18
        //  1436: aload           18
        //  1438: aload           18
        //  1440: invokeinterface java/util/List.size:()I
        //  1445: iconst_1       
        //  1446: isub           
        //  1447: invokeinterface java/util/List.get:(I)Ljava/lang/Object;
        //  1452: checkcast       Ldtv;
        //  1455: getfield        dtv.a:J
        //  1458: lstore          13
        //  1460: new             Ldtv;
        //  1463: astore          18
        //  1465: aload           18
        //  1467: invokestatic    java/lang/System.currentTimeMillis:()J
        //  1470: lload           13
        //  1472: lconst_1       
        //  1473: ladd           
        //  1474: invokespecial   dtv.<init>:(JJ)V
        //  1477: aload_1        
        //  1478: aload           18
        //  1480: invokevirtual   bhy.n:(Ldtv;)V
        //  1483: aload           17
        //  1485: invokevirtual   dwv.b:()Ljava/util/Map;
        //  1488: astore          18
        //  1490: aload           4
        //  1492: monitorenter   
        //  1493: aload           18
        //  1495: ifnull          1734
        //  1498: aload           4
        //  1500: getfield        dwv.a:Ljava/util/Map;
        //  1503: astore_1       
        //  1504: aload_1        
        //  1505: ifnull          1734
        //  1508: aload_1        
        //  1509: invokeinterface java/util/Map.isEmpty:()Z
        //  1514: ifeq            1520
        //  1517: goto            1734
        //  1520: aload           4
        //  1522: monitorexit    
        //  1523: aload           18
        //  1525: invokeinterface java/util/Map.entrySet:()Ljava/util/Set;
        //  1530: invokeinterface java/util/Set.iterator:()Ljava/util/Iterator;
        //  1535: astore          18
        //  1537: aload           18
        //  1539: invokeinterface java/util/Iterator.hasNext:()Z
        //  1544: ifeq            1737
        //  1547: aload           18
        //  1549: invokeinterface java/util/Iterator.next:()Ljava/lang/Object;
        //  1554: checkcast       Ljava/util/Map$Entry;
        //  1557: astore          21
        //  1559: aload           21
        //  1561: invokeinterface java/util/Map$Entry.getKey:()Ljava/lang/Object;
        //  1566: checkcast       Ljava/lang/String;
        //  1569: astore          19
        //  1571: aload           4
        //  1573: monitorenter   
        //  1574: aload           4
        //  1576: getfield        dwv.a:Ljava/util/Map;
        //  1579: aload           19
        //  1581: invokeinterface java/util/Map.get:(Ljava/lang/Object;)Ljava/lang/Object;
        //  1586: checkcast       Ljava/util/List;
        //  1589: astore          20
        //  1591: aload           4
        //  1593: getfield        dwv.b:Ljava/util/Map;
        //  1596: astore_1       
        //  1597: aload_1        
        //  1598: ifnonnull       1606
        //  1601: aconst_null    
        //  1602: astore_1       
        //  1603: goto            1618
        //  1606: aload_1        
        //  1607: aload           19
        //  1609: invokeinterface java/util/Map.get:(Ljava/lang/Object;)Ljava/lang/Object;
        //  1614: checkcast       Ljava/util/List;
        //  1617: astore_1       
        //  1618: aload           4
        //  1620: monitorexit    
        //  1621: aload           20
        //  1623: ifnull          1537
        //  1626: aload           21
        //  1628: invokeinterface java/util/Map$Entry.getValue:()Ljava/lang/Object;
        //  1633: checkcast       Ljava/util/List;
        //  1636: astore          21
        //  1638: aload           20
        //  1640: invokeinterface java/util/List.size:()I
        //  1645: aload           21
        //  1647: invokeinterface java/util/List.size:()I
        //  1652: if_icmpne       1702
        //  1655: aload           4
        //  1657: monitorenter   
        //  1658: aload           4
        //  1660: getfield        dwv.a:Ljava/util/Map;
        //  1663: aload           19
        //  1665: invokeinterface java/util/Map.remove:(Ljava/lang/Object;)Ljava/lang/Object;
        //  1670: pop            
        //  1671: aload           4
        //  1673: getfield        dwv.b:Ljava/util/Map;
        //  1676: astore_1       
        //  1677: aload_1        
        //  1678: ifnull          1690
        //  1681: aload_1        
        //  1682: aload           19
        //  1684: invokeinterface java/util/Map.remove:(Ljava/lang/Object;)Ljava/lang/Object;
        //  1689: pop            
        //  1690: aload           4
        //  1692: monitorexit    
        //  1693: goto            1537
        //  1696: astore_1       
        //  1697: aload           4
        //  1699: monitorexit    
        //  1700: aload_1        
        //  1701: athrow         
        //  1702: aload           20
        //  1704: aload           21
        //  1706: invokeinterface java/util/List.removeAll:(Ljava/util/Collection;)Z
        //  1711: pop            
        //  1712: aload_1        
        //  1713: ifnull          1537
        //  1716: aload_1        
        //  1717: aload           21
        //  1719: invokeinterface java/util/List.removeAll:(Ljava/util/Collection;)Z
        //  1724: pop            
        //  1725: goto            1537
        //  1728: astore_1       
        //  1729: aload           4
        //  1731: monitorexit    
        //  1732: aload_1        
        //  1733: athrow         
        //  1734: aload           4
        //  1736: monitorexit    
        //  1737: aload           17
        //  1739: getfield        dwv.f:Ljava/util/HashSet;
        //  1742: astore          18
        //  1744: new             Ljava/util/ArrayList;
        //  1747: astore_1       
        //  1748: aload_1        
        //  1749: invokespecial   java/util/ArrayList.<init>:()V
        //  1752: aload           18
        //  1754: ifnull          1843
        //  1757: aload           17
        //  1759: getfield        dwv.e:Ljava/util/Map;
        //  1762: astore          19
        //  1764: aload           19
        //  1766: ifnonnull       1772
        //  1769: goto            1843
        //  1772: aload_1        
        //  1773: aload           19
        //  1775: invokeinterface java/util/Map.keySet:()Ljava/util/Set;
        //  1780: invokeinterface java/util/List.addAll:(Ljava/util/Collection;)Z
        //  1785: pop            
        //  1786: aload_1        
        //  1787: invokeinterface java/util/List.size:()I
        //  1792: istore          6
        //  1794: iconst_0       
        //  1795: istore_2       
        //  1796: iload_2        
        //  1797: iload           6
        //  1799: if_icmpge       1843
        //  1802: aload_1        
        //  1803: iload_2        
        //  1804: invokeinterface java/util/List.get:(I)Ljava/lang/Object;
        //  1809: checkcast       Ljava/lang/String;
        //  1812: astore          19
        //  1814: aload           18
        //  1816: aload           19
        //  1818: invokevirtual   java/util/HashSet.contains:(Ljava/lang/Object;)Z
        //  1821: ifne            1837
        //  1824: aload           17
        //  1826: getfield        dwv.e:Ljava/util/Map;
        //  1829: aload           19
        //  1831: invokeinterface java/util/Map.remove:(Ljava/lang/Object;)Ljava/lang/Object;
        //  1836: pop            
        //  1837: iinc            2, 1
        //  1840: goto            1796
        //  1843: aload           4
        //  1845: aload           17
        //  1847: invokevirtual   dwv.f:()Ljava/util/Map;
        //  1850: invokevirtual   dwv.h:(Ljava/util/Map;)V
        //  1853: aload           4
        //  1855: aload           17
        //  1857: invokevirtual   dwv.d:()Ljava/util/Map;
        //  1860: invokevirtual   dwv.i:(Ljava/util/Map;)V
        //  1863: aload           4
        //  1865: getfield        dwv.g:Ljava/util/Map;
        //  1868: astore_1       
        //  1869: aload_1        
        //  1870: ifnull          1879
        //  1873: aload_1        
        //  1874: invokeinterface java/util/Map.clear:()V
        //  1879: aload           17
        //  1881: getfield        dwv.g:Ljava/util/Map;
        //  1884: astore_1       
        //  1885: aload_1        
        //  1886: ifnull          1950
        //  1889: aload_1        
        //  1890: invokeinterface java/util/Map.isEmpty:()Z
        //  1895: ifne            1950
        //  1898: aload           4
        //  1900: getfield        dwv.g:Ljava/util/Map;
        //  1903: astore_1       
        //  1904: aload_1        
        //  1905: ifnonnull       1930
        //  1908: new             Ljava/util/HashMap;
        //  1911: astore_1       
        //  1912: aload_1        
        //  1913: aload           17
        //  1915: getfield        dwv.g:Ljava/util/Map;
        //  1918: invokespecial   java/util/HashMap.<init>:(Ljava/util/Map;)V
        //  1921: aload           4
        //  1923: aload_1        
        //  1924: putfield        dwv.g:Ljava/util/Map;
        //  1927: goto            1950
        //  1930: aload_1        
        //  1931: aload           17
        //  1933: getfield        dwv.g:Ljava/util/Map;
        //  1936: invokeinterface java/util/Map.putAll:(Ljava/util/Map;)V
        //  1941: goto            1950
        //  1944: astore_1       
        //  1945: aload           4
        //  1947: monitorexit    
        //  1948: aload_1        
        //  1949: athrow         
        //  1950: aload_0        
        //  1951: getfield        com/facebook/litho/ComponentTree.d:Ljava/util/List;
        //  1954: ifnull          1971
        //  1957: aload_3        
        //  1958: getfield        dvi.q:I
        //  1961: istore_2       
        //  1962: aload_3        
        //  1963: getfield        dvi.r:I
        //  1966: istore          6
        //  1968: goto            1976
        //  1971: iconst_0       
        //  1972: istore_2       
        //  1973: iconst_0       
        //  1974: istore          6
        //  1976: aload_3        
        //  1977: getfield        dvi.B:Ljava/util/Map;
        //  1980: astore          4
        //  1982: aload_3        
        //  1983: aconst_null    
        //  1984: putfield        dvi.B:Ljava/util/Map;
        //  1987: aload           16
        //  1989: astore_3       
        //  1990: aload           17
        //  1992: ifnull          2004
        //  1995: aload_0        
        //  1996: getfield        com/facebook/litho/ComponentTree.F:Lajc;
        //  1999: aload           17
        //  2001: invokevirtual   ajc.k:(Ldwv;)V
        //  2004: iload           5
        //  2006: ifne            2014
        //  2009: aload_0        
        //  2010: iconst_0       
        //  2011: putfield        com/facebook/litho/ComponentTree.M:I
        //  2014: aload_0        
        //  2015: monitorexit    
        //  2016: iload           7
        //  2018: ifeq            2186
        //  2021: aload_0        
        //  2022: monitorenter   
        //  2023: aload_0        
        //  2024: getfield        com/facebook/litho/ComponentTree.d:Ljava/util/List;
        //  2027: astore_1       
        //  2028: aload_1        
        //  2029: ifnonnull       2037
        //  2032: aconst_null    
        //  2033: astore_1       
        //  2034: goto            2046
        //  2037: new             Ljava/util/ArrayList;
        //  2040: dup            
        //  2041: aload_1        
        //  2042: invokespecial   java/util/ArrayList.<init>:(Ljava/util/Collection;)V
        //  2045: astore_1       
        //  2046: aload_0        
        //  2047: monitorexit    
        //  2048: aload_1        
        //  2049: ifnull          2095
        //  2052: aload_1        
        //  2053: invokeinterface java/util/List.size:()I
        //  2058: istore          10
        //  2060: iconst_0       
        //  2061: istore          8
        //  2063: iload           8
        //  2065: iload           10
        //  2067: if_icmpge       2095
        //  2070: aload_1        
        //  2071: iload           8
        //  2073: invokeinterface java/util/List.get:(I)Ljava/lang/Object;
        //  2078: checkcast       Ldtm;
        //  2081: iload_2        
        //  2082: iload           6
        //  2084: invokeinterface dtm.a:(II)V
        //  2089: iinc            8, 1
        //  2092: goto            2063
        //  2095: aload_0        
        //  2096: getfield        com/facebook/litho/ComponentTree.ab:Lema;
        //  2099: ifnull          2114
        //  2102: aload_0        
        //  2103: getfield        com/facebook/litho/ComponentTree.ab:Lema;
        //  2106: aload           4
        //  2108: invokevirtual   ema.l:(Ljava/util/Map;)V
        //  2111: goto            2186
        //  2114: aload           4
        //  2116: ifnull          2186
        //  2119: aload_0        
        //  2120: getfield        com/facebook/litho/ComponentTree.ab:Lema;
        //  2123: astore          16
        //  2125: aload           16
        //  2127: astore_1       
        //  2128: aload           16
        //  2130: ifnonnull       2172
        //  2133: aload_0        
        //  2134: monitorenter   
        //  2135: aload_0        
        //  2136: getfield        com/facebook/litho/ComponentTree.ab:Lema;
        //  2139: astore          16
        //  2141: aload           16
        //  2143: astore_1       
        //  2144: aload           16
        //  2146: ifnonnull       2162
        //  2149: new             Lema;
        //  2152: astore_1       
        //  2153: aload_1        
        //  2154: invokespecial   ema.<init>:()V
        //  2157: aload_0        
        //  2158: aload_1        
        //  2159: putfield        com/facebook/litho/ComponentTree.ab:Lema;
        //  2162: aload_0        
        //  2163: monitorexit    
        //  2164: goto            2172
        //  2167: astore_1       
        //  2168: aload_0        
        //  2169: monitorexit    
        //  2170: aload_1        
        //  2171: athrow         
        //  2172: aload_1        
        //  2173: aload           4
        //  2175: invokevirtual   ema.l:(Ljava/util/Map;)V
        //  2178: goto            2186
        //  2181: astore_1       
        //  2182: aload_0        
        //  2183: monitorexit    
        //  2184: aload_1        
        //  2185: athrow         
        //  2186: aload_3        
        //  2187: ifnull          2285
        //  2190: aload_0        
        //  2191: invokespecial   com/facebook/litho/ComponentTree.A:()V
        //  2194: aload_3        
        //  2195: invokeinterface java/util/List.size:()I
        //  2200: istore          6
        //  2202: iload           9
        //  2204: istore_2       
        //  2205: iload_2        
        //  2206: iload           6
        //  2208: if_icmpge       2278
        //  2211: aload_3        
        //  2212: iload_2        
        //  2213: invokeinterface java/util/List.get:(I)Ljava/lang/Object;
        //  2218: checkcast       Ldsw;
        //  2221: astore_1       
        //  2222: aload_1        
        //  2223: invokestatic    cqj.l:(Ldsw;)Ljava/lang/String;
        //  2226: astore          16
        //  2228: aload_1        
        //  2229: getfield        dsw.p:Ldta;
        //  2232: astore          4
        //  2234: aload_0        
        //  2235: getfield        com/facebook/litho/ComponentTree.D:Lbhy;
        //  2238: aload           4
        //  2240: aload_1        
        //  2241: aload           16
        //  2243: invokevirtual   bhy.j:(Ldta;Lduy;Ljava/lang/String;)V
        //  2246: aload_0        
        //  2247: getfield        com/facebook/litho/ComponentTree.af:Lhho;
        //  2250: astore          4
        //  2252: aload           4
        //  2254: monitorenter   
        //  2255: aload_1        
        //  2256: aload_0        
        //  2257: getfield        com/facebook/litho/ComponentTree.af:Lhho;
        //  2260: invokevirtual   dsw.J:(Lhho;)V
        //  2263: aload           4
        //  2265: monitorexit    
        //  2266: iinc            2, 1
        //  2269: goto            2205
        //  2272: astore_1       
        //  2273: aload           4
        //  2275: monitorexit    
        //  2276: aload_1        
        //  2277: athrow         
        //  2278: aload_0        
        //  2279: getfield        com/facebook/litho/ComponentTree.D:Lbhy;
        //  2282: invokevirtual   bhy.k:()V
        //  2285: iload           7
        //  2287: ifeq            2320
        //  2290: invokestatic    bkx.r:()Z
        //  2293: ifeq            2301
        //  2296: aload_0        
        //  2297: invokevirtual   com/facebook/litho/ComponentTree.i:()V
        //  2300: return         
        //  2301: aload_0        
        //  2302: getfield        com/facebook/litho/ComponentTree.Q:Ldvn;
        //  2305: astore_3       
        //  2306: aload_0        
        //  2307: getfield        com/facebook/litho/ComponentTree.R:Ljava/lang/Runnable;
        //  2310: astore_1       
        //  2311: aload_3        
        //  2312: checkcast       Ldvm;
        //  2315: aload_1        
        //  2316: invokevirtual   dvm.post:(Ljava/lang/Runnable;)Z
        //  2319: pop            
        //  2320: return         
        //  2321: astore_1       
        //  2322: aload_0        
        //  2323: monitorexit    
        //  2324: aload_1        
        //  2325: athrow         
        //  2326: new             Ljava/lang/IllegalStateException;
        //  2329: astore_1       
        //  2330: aload_1        
        //  2331: ldc_w           "LayoutStateFuture ref count is below 0"
        //  2334: invokespecial   java/lang/IllegalStateException.<init>:(Ljava/lang/String;)V
        //  2337: aload_1        
        //  2338: athrow         
        //  2339: astore_1       
        //  2340: aload           4
        //  2342: monitorexit    
        //  2343: aload_1        
        //  2344: athrow         
        //  2345: astore_1       
        //  2346: aload           17
        //  2348: monitorexit    
        //  2349: aload_1        
        //  2350: athrow         
        //  2351: astore          4
        //  2353: aload_3        
        //  2354: astore_1       
        //  2355: aload           4
        //  2357: athrow         
        //  2358: astore          4
        //  2360: aload_1        
        //  2361: astore_3       
        //  2362: aload           4
        //  2364: astore_1       
        //  2365: goto            2405
        //  2368: astore          4
        //  2370: aload_1        
        //  2371: astore_3       
        //  2372: aload           4
        //  2374: astore_1       
        //  2375: aload_3        
        //  2376: astore          16
        //  2378: new             Ljava/lang/RuntimeException;
        //  2381: astore          4
        //  2383: aload_3        
        //  2384: astore          16
        //  2386: aload           4
        //  2388: aload_1        
        //  2389: invokevirtual   java/util/concurrent/ExecutionException.getMessage:()Ljava/lang/String;
        //  2392: aload_1        
        //  2393: invokevirtual   java/util/concurrent/ExecutionException.getCause:()Ljava/lang/Throwable;
        //  2396: invokespecial   java/lang/RuntimeException.<init>:(Ljava/lang/String;Ljava/lang/Throwable;)V
        //  2399: aload_3        
        //  2400: astore          16
        //  2402: aload           4
        //  2404: athrow         
        //  2405: aload_3        
        //  2406: ifnull          2417
        //  2409: invokestatic    bkx.r:()Z
        //  2412: pop            
        //  2413: aload_3        
        //  2414: invokestatic    med.x:(Ldwn;)V
        //  2417: aload_1        
        //  2418: athrow         
        //  2419: astore_1       
        //  2420: aload           4
        //  2422: monitorexit    
        //  2423: aload_1        
        //  2424: athrow         
        //  2425: aload_0        
        //  2426: monitorexit    
        //  2427: return         
        //  2428: astore_1       
        //  2429: aload_0        
        //  2430: monitorexit    
        //  2431: aload_1        
        //  2432: athrow         
        //  2433: astore_1       
        //  2434: aload           16
        //  2436: monitorexit    
        //  2437: goto            2442
        //  2440: aload_1        
        //  2441: athrow         
        //  2442: goto            2440
        //  2445: astore          4
        //  2447: goto            627
        //    Exceptions:
        //  Try           Handler
        //  Start  End    Start  End    Type                                     
        //  -----  -----  -----  -----  -----------------------------------------
        //  9      15     2433   2445   Any
        //  20     36     2433   2445   Any
        //  36     39     2433   2445   Any
        //  41     47     2428   2433   Any
        //  53     59     2428   2433   Any
        //  65     71     2428   2433   Any
        //  79     98     2428   2433   Any
        //  102    123    2428   2433   Any
        //  123    125    2428   2433   Any
        //  126    163    2428   2433   Any
        //  212    223    2419   2425   Any
        //  233    266    2419   2425   Any
        //  289    301    2419   2425   Any
        //  301    313    2419   2425   Any
        //  455    462    511    512    Ljava/lang/RuntimeException;
        //  481    488    494    501    Ljava/lang/SecurityException;
        //  481    488    511    512    Ljava/lang/RuntimeException;
        //  533    557    560    567    Any
        //  569    582    2351   2355   Any
        //  589    598    608    612    Ljava/util/concurrent/ExecutionException;
        //  589    598    601    608    Any
        //  620    627    2445   2450   Ljava/lang/IllegalArgumentException;
        //  620    627    2445   2450   Ljava/lang/SecurityException;
        //  620    627    608    612    Ljava/util/concurrent/ExecutionException;
        //  620    627    601    608    Any
        //  634    642    608    612    Ljava/util/concurrent/ExecutionException;
        //  634    642    601    608    Any
        //  649    657    608    612    Ljava/util/concurrent/ExecutionException;
        //  649    657    601    608    Any
        //  660    666    608    612    Ljava/util/concurrent/ExecutionException;
        //  660    666    601    608    Any
        //  669    676    608    612    Ljava/util/concurrent/ExecutionException;
        //  669    676    601    608    Any
        //  679    684    608    612    Ljava/util/concurrent/ExecutionException;
        //  679    684    601    608    Any
        //  687    693    608    612    Ljava/util/concurrent/ExecutionException;
        //  687    693    601    608    Any
        //  693    701    770    794    Any
        //  707    731    770    794    Any
        //  731    740    764    770    Any
        //  750    753    764    770    Any
        //  756    761    608    612    Ljava/util/concurrent/ExecutionException;
        //  756    761    601    608    Any
        //  765    768    764    770    Any
        //  768    770    770    794    Any
        //  772    779    779    794    Any
        //  784    788    608    612    Ljava/util/concurrent/ExecutionException;
        //  784    788    601    608    Any
        //  791    794    608    612    Ljava/util/concurrent/ExecutionException;
        //  791    794    601    608    Any
        //  797    804    608    612    Ljava/util/concurrent/ExecutionException;
        //  797    804    601    608    Any
        //  807    812    608    612    Ljava/util/concurrent/ExecutionException;
        //  807    812    601    608    Any
        //  815    821    608    612    Ljava/util/concurrent/ExecutionException;
        //  815    821    601    608    Any
        //  824    830    608    612    Ljava/util/concurrent/ExecutionException;
        //  824    830    601    608    Any
        //  856    867    2345   2351   Any
        //  870    873    2345   2351   Any
        //  885    924    2339   2345   Any
        //  924    927    2339   2345   Any
        //  1237   1284   2321   2326   Any
        //  1294   1300   2321   2326   Any
        //  1302   1307   2321   2326   Any
        //  1325   1341   2321   2326   Any
        //  1346   1352   2321   2326   Any
        //  1357   1408   2321   2326   Any
        //  1412   1427   2321   2326   Any
        //  1430   1483   2321   2326   Any
        //  1483   1493   2321   2326   Any
        //  1498   1504   1944   1950   Any
        //  1508   1517   1944   1950   Any
        //  1520   1523   1944   1950   Any
        //  1523   1537   2321   2326   Any
        //  1537   1574   2321   2326   Any
        //  1574   1597   1728   1734   Any
        //  1606   1618   1728   1734   Any
        //  1618   1621   1728   1734   Any
        //  1626   1658   2321   2326   Any
        //  1658   1677   1696   1702   Any
        //  1681   1690   1696   1702   Any
        //  1690   1693   1696   1702   Any
        //  1697   1700   1696   1702   Any
        //  1700   1702   2321   2326   Any
        //  1702   1712   2321   2326   Any
        //  1716   1725   2321   2326   Any
        //  1729   1732   1728   1734   Any
        //  1732   1734   2321   2326   Any
        //  1734   1737   1944   1950   Any
        //  1737   1752   2321   2326   Any
        //  1757   1764   2321   2326   Any
        //  1772   1794   2321   2326   Any
        //  1802   1837   2321   2326   Any
        //  1843   1869   2321   2326   Any
        //  1873   1879   2321   2326   Any
        //  1879   1885   2321   2326   Any
        //  1889   1904   2321   2326   Any
        //  1908   1927   2321   2326   Any
        //  1930   1941   2321   2326   Any
        //  1945   1948   1944   1950   Any
        //  1948   1950   2321   2326   Any
        //  1950   1968   2321   2326   Any
        //  1976   1987   2321   2326   Any
        //  1995   2004   2321   2326   Any
        //  2009   2014   2321   2326   Any
        //  2014   2016   2321   2326   Any
        //  2023   2028   2181   2186   Any
        //  2037   2046   2181   2186   Any
        //  2046   2048   2181   2186   Any
        //  2135   2141   2167   2172   Any
        //  2149   2162   2167   2172   Any
        //  2162   2164   2167   2172   Any
        //  2168   2170   2167   2172   Any
        //  2182   2184   2181   2186   Any
        //  2255   2266   2272   2278   Any
        //  2273   2276   2272   2278   Any
        //  2322   2324   2321   2326   Any
        //  2326   2339   2339   2345   Any
        //  2340   2343   2339   2345   Any
        //  2346   2349   2345   2351   Any
        //  2355   2358   2368   2375   Ljava/util/concurrent/ExecutionException;
        //  2355   2358   2358   2368   Any
        //  2378   2383   601    608    Any
        //  2386   2399   601    608    Any
        //  2402   2405   601    608    Any
        //  2420   2423   2419   2425   Any
        //  2425   2427   2428   2433   Any
        //  2429   2431   2428   2433   Any
        //  2434   2437   2433   2445   Any
        // 
        // The error that occurred was:
        // 
        // java.lang.IllegalStateException: Expression is linked from several locations: Label_0627:
        //     at com.strobel.decompiler.ast.Error.expressionLinkedFromMultipleLocations(Error.java:27)
        //     at com.strobel.decompiler.ast.AstOptimizer.mergeDisparateObjectInitializations(AstOptimizer.java:2604)
        //     at com.strobel.decompiler.ast.AstOptimizer.optimize(AstOptimizer.java:235)
        //     at com.strobel.decompiler.ast.AstOptimizer.optimize(AstOptimizer.java:42)
        //     at com.strobel.decompiler.languages.java.ast.AstMethodBodyBuilder.createMethodBody(AstMethodBodyBuilder.java:206)
        //     at com.strobel.decompiler.languages.java.ast.AstMethodBodyBuilder.createMethodBody(AstMethodBodyBuilder.java:93)
        //     at com.strobel.decompiler.languages.java.ast.AstBuilder.createMethodBody(AstBuilder.java:868)
        //     at com.strobel.decompiler.languages.java.ast.AstBuilder.createMethod(AstBuilder.java:761)
        //     at com.strobel.decompiler.languages.java.ast.AstBuilder.addTypeMembers(AstBuilder.java:638)
        //     at com.strobel.decompiler.languages.java.ast.AstBuilder.createTypeCore(AstBuilder.java:605)
        //     at com.strobel.decompiler.languages.java.ast.AstBuilder.createTypeNoCache(AstBuilder.java:195)
        //     at com.strobel.decompiler.languages.java.ast.AstBuilder.createType(AstBuilder.java:162)
        //     at com.strobel.decompiler.languages.java.ast.AstBuilder.addType(AstBuilder.java:137)
        //     at com.strobel.decompiler.languages.java.JavaLanguage.buildAst(JavaLanguage.java:71)
        //     at com.strobel.decompiler.languages.java.JavaLanguage.decompileType(JavaLanguage.java:59)
        //     at com.strobel.decompiler.DecompilerDriver.decompileType(DecompilerDriver.java:333)
        //     at com.strobel.decompiler.DecompilerDriver.decompileJar(DecompilerDriver.java:254)
        //     at com.strobel.decompiler.DecompilerDriver.main(DecompilerDriver.java:129)
        // 
        throw new IllegalStateException("An error occurred while decompiling this method.");
    }
    
    public final void y(final dsw dsw, final int n, final int n2, final boolean b, final dwt dwt, final int n3, final cyd cyd) {
        this.G(dsw, n, n2, b, dwt, n3, null, cyd, false, false);
    }
}
