// 
// Decompiled by Procyon v0.6.0
// 

package com.google.android.apps.youtube.embeddedplayer.service.ui.overlays.surveyoverlay.remoteloaded;

import com.google.android.libraries.youtube.innertube.model.media.VideoStreamingData;
import android.net.Uri;
import com.google.android.gms.measurement.internal.UserAttributeParcel;
import com.google.android.gms.measurement.internal.EventParcel;
import com.google.android.gms.measurement.internal.ConditionalUserPropertyParcel;
import com.google.android.gms.measurement.internal.AppMetadata;
import com.google.android.apps.youtube.embeddedplayer.service.ui.subscriptionnotificationbutton.model.SubscriptionNotificationMenuItem;
import com.google.android.apps.youtube.embeddedplayer.service.ui.subscriptionnotificationbutton.remoteloaded.i;
import com.google.android.apps.youtube.embeddedplayer.service.ui.preview.service.e;
import java.util.List;
import com.google.android.apps.youtube.embeddedplayer.service.ui.overlays.surveyoverlay.shared.b;
import com.google.android.libraries.youtube.player.model.PlaybackStartDescriptor;

public final class a implements Runnable
{
    public final boolean a;
    public final Object b;
    public final Object c;
    public final Object d;
    private final int e;
    
    public a(final aadg b, final PlaybackStartDescriptor c, final tcd d, final boolean a, final int e) {
        this.e = e;
        this.b = b;
        this.c = c;
        this.d = d;
        this.a = a;
    }
    
    public a(final abrm b, final zme d, final String c, final boolean a, final int e) {
        this.e = e;
        this.b = b;
        this.d = d;
        this.c = c;
        this.a = a;
    }
    
    public a(final atjz b, final vft d, final boolean a, final atjz c, final int e) {
        this.e = e;
        this.b = b;
        this.d = d;
        this.a = a;
        this.c = c;
    }
    
    public a(final b d, final String b, final List c, final boolean a, final int e) {
        this.e = e;
        this.d = d;
        this.b = b;
        this.c = c;
        this.a = a;
    }
    
    public a(final e d, final String c, final boolean a, final aezp b, final int e, final byte[] array) {
        this.e = e;
        this.d = d;
        this.c = c;
        this.a = a;
        this.b = b;
    }
    
    public a(final i c, final boolean a, final ako d, final SubscriptionNotificationMenuItem b, final int e) {
        this.e = e;
        this.c = c;
        this.a = a;
        this.d = d;
        this.b = b;
    }
    
    public a(final nhy c, final AppMetadata d, final boolean a, final ConditionalUserPropertyParcel b, final int e) {
        this.e = e;
        this.c = c;
        this.d = d;
        this.a = a;
        this.b = b;
    }
    
    public a(final nhy c, final AppMetadata d, final boolean a, final EventParcel b, final int e) {
        this.e = e;
        this.c = c;
        this.d = d;
        this.a = a;
        this.b = b;
    }
    
    public a(final nhy b, final AppMetadata d, final boolean a, final UserAttributeParcel c, final int e) {
        this.e = e;
        this.b = b;
        this.d = d;
        this.a = a;
        this.c = c;
    }
    
    public a(final sis b, final Uri d, final List c, final boolean a, final int e) {
        this.e = e;
        this.b = b;
        this.d = d;
        this.c = c;
        this.a = a;
    }
    
    public a(final yun d, final String c, final boolean a, final ywo b, final int e) {
        this.e = e;
        this.d = d;
        this.c = c;
        this.a = a;
        this.b = b;
    }
    
    public a(final yup d, final zbq c, final ywi b, final boolean a, final int e) {
        this.e = e;
        this.d = d;
        this.c = c;
        this.b = b;
        this.a = a;
    }
    
    public a(final yyq c, final VideoStreamingData d, final boolean a, final ypw b, final int e) {
        this.e = e;
        this.c = c;
        this.d = d;
        this.a = a;
        this.b = b;
    }
    
    public a(final zst b, final boolean a, final ako d, final aomx c, final int e) {
        this.e = e;
        this.b = b;
        this.a = a;
        this.d = d;
        this.c = c;
    }
    
    @Override
    public final void run() {
        // 
        // This method could not be decompiled.
        // 
        // Original Bytecode:
        // 
        //     1: getfield        com/google/android/apps/youtube/embeddedplayer/service/ui/overlays/surveyoverlay/remoteloaded/a.e:I
        //     4: istore_1       
        //     5: aconst_null    
        //     6: astore          8
        //     8: aconst_null    
        //     9: astore          10
        //    11: aconst_null    
        //    12: astore          9
        //    14: iconst_1       
        //    15: istore          5
        //    17: iconst_0       
        //    18: istore          6
        //    20: iload_1        
        //    21: tableswitch {
        //                0: 1734
        //                1: 1574
        //                2: 1527
        //                3: 1430
        //                4: 1337
        //                5: 1240
        //                6: 1082
        //                7: 1013
        //                8: 866
        //                9: 411
        //               10: 248
        //               11: 201
        //               12: 155
        //          default: 88
        //        }
        //    88: aload_0        
        //    89: getfield        com/google/android/apps/youtube/embeddedplayer/service/ui/overlays/surveyoverlay/remoteloaded/a.b:Ljava/lang/Object;
        //    92: astore          10
        //    94: aload_0        
        //    95: getfield        com/google/android/apps/youtube/embeddedplayer/service/ui/overlays/surveyoverlay/remoteloaded/a.d:Ljava/lang/Object;
        //    98: astore          9
        //   100: aload_0        
        //   101: getfield        com/google/android/apps/youtube/embeddedplayer/service/ui/overlays/surveyoverlay/remoteloaded/a.c:Ljava/lang/Object;
        //   104: astore          8
        //   106: aload_0        
        //   107: getfield        com/google/android/apps/youtube/embeddedplayer/service/ui/overlays/surveyoverlay/remoteloaded/a.a:Z
        //   110: istore          4
        //   112: aload           10
        //   114: checkcast       Labrm;
        //   117: astore          10
        //   119: aload           10
        //   121: getfield        abrm.h:Lajdf;
        //   124: astore          11
        //   126: aload           11
        //   128: ifnull          2186
        //   131: aload           11
        //   133: getfield        ajdf.c:Z
        //   136: ifeq            2186
        //   139: aload           10
        //   141: getfield        abrm.f:Ltjm;
        //   144: invokeinterface tjm.o:()Z
        //   149: ifeq            1782
        //   152: goto            2186
        //   155: aload_0        
        //   156: getfield        com/google/android/apps/youtube/embeddedplayer/service/ui/overlays/surveyoverlay/remoteloaded/a.b:Ljava/lang/Object;
        //   159: astore          8
        //   161: aload_0        
        //   162: getfield        com/google/android/apps/youtube/embeddedplayer/service/ui/overlays/surveyoverlay/remoteloaded/a.c:Ljava/lang/Object;
        //   165: astore          10
        //   167: aload_0        
        //   168: getfield        com/google/android/apps/youtube/embeddedplayer/service/ui/overlays/surveyoverlay/remoteloaded/a.d:Ljava/lang/Object;
        //   171: astore          9
        //   173: aload_0        
        //   174: getfield        com/google/android/apps/youtube/embeddedplayer/service/ui/overlays/surveyoverlay/remoteloaded/a.a:Z
        //   177: istore          4
        //   179: aload           10
        //   181: checkcast       Lcom/google/android/libraries/youtube/player/model/PlaybackStartDescriptor;
        //   184: astore          10
        //   186: aload           8
        //   188: checkcast       Laadg;
        //   191: aload           10
        //   193: aload           9
        //   195: iload           4
        //   197: invokevirtual   aadg.a:(Lcom/google/android/libraries/youtube/player/model/PlaybackStartDescriptor;Ltcc;Z)V
        //   200: return         
        //   201: aload_0        
        //   202: getfield        com/google/android/apps/youtube/embeddedplayer/service/ui/overlays/surveyoverlay/remoteloaded/a.b:Ljava/lang/Object;
        //   205: astore          9
        //   207: aload_0        
        //   208: getfield        com/google/android/apps/youtube/embeddedplayer/service/ui/overlays/surveyoverlay/remoteloaded/a.a:Z
        //   211: istore          4
        //   213: aload_0        
        //   214: getfield        com/google/android/apps/youtube/embeddedplayer/service/ui/overlays/surveyoverlay/remoteloaded/a.d:Ljava/lang/Object;
        //   217: astore          8
        //   219: aload_0        
        //   220: getfield        com/google/android/apps/youtube/embeddedplayer/service/ui/overlays/surveyoverlay/remoteloaded/a.c:Ljava/lang/Object;
        //   223: astore          10
        //   225: aload           9
        //   227: checkcast       Lzst;
        //   230: invokevirtual   zst.a:()V
        //   233: iload           4
        //   235: ifne            247
        //   238: aload           8
        //   240: aload           10
        //   242: invokeinterface ako.accept:(Ljava/lang/Object;)V
        //   247: return         
        //   248: aload_0        
        //   249: getfield        com/google/android/apps/youtube/embeddedplayer/service/ui/overlays/surveyoverlay/remoteloaded/a.c:Ljava/lang/Object;
        //   252: astore          9
        //   254: aload_0        
        //   255: getfield        com/google/android/apps/youtube/embeddedplayer/service/ui/overlays/surveyoverlay/remoteloaded/a.d:Ljava/lang/Object;
        //   258: astore          10
        //   260: aload_0        
        //   261: getfield        com/google/android/apps/youtube/embeddedplayer/service/ui/overlays/surveyoverlay/remoteloaded/a.a:Z
        //   264: istore          7
        //   266: aload_0        
        //   267: getfield        com/google/android/apps/youtube/embeddedplayer/service/ui/overlays/surveyoverlay/remoteloaded/a.b:Ljava/lang/Object;
        //   270: astore          8
        //   272: aload           9
        //   274: checkcast       Lyyq;
        //   277: getfield        yyq.c:Lxwk;
        //   280: astore          9
        //   282: iload           7
        //   284: ifeq            391
        //   287: aload           10
        //   289: checkcast       Lcom/google/android/libraries/youtube/innertube/model/media/VideoStreamingData;
        //   292: astore          10
        //   294: aload           10
        //   296: getfield        com/google/android/libraries/youtube/innertube/model/media/VideoStreamingData.q:Ljava/util/List;
        //   299: invokeinterface java/util/List.iterator:()Ljava/util/Iterator;
        //   304: astore          11
        //   306: iload           6
        //   308: istore          4
        //   310: aload           11
        //   312: invokeinterface java/util/Iterator.hasNext:()Z
        //   317: ifeq            341
        //   320: aload           11
        //   322: invokeinterface java/util/Iterator.next:()Ljava/lang/Object;
        //   327: checkcast       Lcom/google/android/libraries/youtube/innertube/model/media/FormatStreamModel;
        //   330: aload           9
        //   332: invokestatic    yyq.d:(Lcom/google/android/libraries/youtube/innertube/model/media/FormatStreamModel;Lxwk;)Z
        //   335: ifeq            306
        //   338: iconst_1       
        //   339: istore          4
        //   341: aload           10
        //   343: getfield        com/google/android/libraries/youtube/innertube/model/media/VideoStreamingData.p:Ljava/util/List;
        //   346: invokeinterface java/util/List.iterator:()Ljava/util/Iterator;
        //   351: astore          10
        //   353: aload           10
        //   355: invokeinterface java/util/Iterator.hasNext:()Z
        //   360: ifeq            388
        //   363: aload           10
        //   365: invokeinterface java/util/Iterator.next:()Ljava/lang/Object;
        //   370: checkcast       Lcom/google/android/libraries/youtube/innertube/model/media/FormatStreamModel;
        //   373: aload           9
        //   375: invokestatic    yyq.d:(Lcom/google/android/libraries/youtube/innertube/model/media/FormatStreamModel;Lxwk;)Z
        //   378: ifeq            353
        //   381: iload           5
        //   383: istore          4
        //   385: goto            394
        //   388: goto            394
        //   391: iconst_0       
        //   392: istore          4
        //   394: getstatic       zbk.a:Lzbk;
        //   397: astore          9
        //   399: aload           8
        //   401: iload           7
        //   403: iload           4
        //   405: invokeinterface ypw.l:(ZZ)V
        //   410: return         
        //   411: aload_0        
        //   412: getfield        com/google/android/apps/youtube/embeddedplayer/service/ui/overlays/surveyoverlay/remoteloaded/a.d:Ljava/lang/Object;
        //   415: astore          12
        //   417: aload_0        
        //   418: getfield        com/google/android/apps/youtube/embeddedplayer/service/ui/overlays/surveyoverlay/remoteloaded/a.c:Ljava/lang/Object;
        //   421: astore          9
        //   423: aload_0        
        //   424: getfield        com/google/android/apps/youtube/embeddedplayer/service/ui/overlays/surveyoverlay/remoteloaded/a.b:Ljava/lang/Object;
        //   427: astore          11
        //   429: aload_0        
        //   430: getfield        com/google/android/apps/youtube/embeddedplayer/service/ui/overlays/surveyoverlay/remoteloaded/a.a:Z
        //   433: istore          5
        //   435: aload           11
        //   437: ifnonnull       448
        //   440: getstatic       ypw.a:Lypw;
        //   443: astore          10
        //   445: goto            458
        //   448: aload           11
        //   450: checkcast       Lywi;
        //   453: getfield        ywi.O:Lypw;
        //   456: astore          10
        //   458: aload           9
        //   460: checkcast       Lzbq;
        //   463: invokevirtual   zbq.w:()Z
        //   466: istore          4
        //   468: iload           4
        //   470: ifeq            492
        //   473: iload           5
        //   475: ifne            504
        //   478: aload           12
        //   480: checkcast       Lyup;
        //   483: getfield        yup.a:Lyux;
        //   486: invokevirtual   yux.h:()V
        //   489: goto            497
        //   492: iload           5
        //   494: ifne            504
        //   497: aload           9
        //   499: astore          8
        //   501: goto            620
        //   504: aload           12
        //   506: checkcast       Lyup;
        //   509: getfield        yup.c:Lqv;
        //   512: iconst_0       
        //   513: invokevirtual   qv.e:(Z)V
        //   516: aload           11
        //   518: ifnull          589
        //   521: new             Lzbo;
        //   524: astore          13
        //   526: aload           13
        //   528: aload           9
        //   530: checkcast       Lzbq;
        //   533: invokespecial   zbo.<init>:(Lzbq;)V
        //   536: aload           13
        //   538: ldc             "smfc.d"
        //   540: invokevirtual   zbo.c:(Ljava/lang/String;)V
        //   543: new             Lyuv;
        //   546: astore          8
        //   548: aload           8
        //   550: invokespecial   yuv.<init>:()V
        //   553: aload           13
        //   555: aload           8
        //   557: invokevirtual   zbo.b:(Ljava/lang/Object;)V
        //   560: aload           13
        //   562: invokevirtual   zbo.a:()Lzbq;
        //   565: astore          8
        //   567: aload           12
        //   569: checkcast       Lyup;
        //   572: getfield        yup.a:Lyux;
        //   575: aload           11
        //   577: checkcast       Lywi;
        //   580: getfield        ywi.O:Lypw;
        //   583: invokevirtual   yux.f:(Lypw;)V
        //   586: goto            609
        //   589: aload           12
        //   591: checkcast       Lyup;
        //   594: getfield        yup.b:Lzct;
        //   597: aload           9
        //   599: checkcast       Lzbq;
        //   602: invokevirtual   zct.bh:(Lzbq;)V
        //   605: aload           9
        //   607: astore          8
        //   609: aload           10
        //   611: ldc             "smfc"
        //   613: ldc             "d"
        //   615: invokeinterface ypw.k:(Ljava/lang/String;Ljava/lang/String;)V
        //   620: aload           11
        //   622: ifnonnull       689
        //   625: ldc             "Scripted MediaFetch error with no playback: %s:%s"
        //   627: iconst_2       
        //   628: anewarray       Ljava/lang/Object;
        //   631: dup            
        //   632: iconst_0       
        //   633: aload           9
        //   635: checkcast       Lzbq;
        //   638: invokevirtual   zbq.m:()Ljava/lang/String;
        //   641: aastore        
        //   642: dup            
        //   643: iconst_1       
        //   644: aload           9
        //   646: checkcast       Lzbq;
        //   649: invokevirtual   zbq.o:()Ljava/lang/String;
        //   652: invokestatic    tvb.i:(Ljava/lang/String;)Ljava/lang/String;
        //   655: aastore        
        //   656: invokestatic    java/lang/String.format:(Ljava/lang/String;[Ljava/lang/Object;)Ljava/lang/String;
        //   659: astore          9
        //   661: getstatic       zll.b:Lzll;
        //   664: getstatic       zlk.f:Lzlk;
        //   667: aload           9
        //   669: invokestatic    zlm.b:(Lzll;Lzlk;Ljava/lang/String;)V
        //   672: getstatic       zbk.i:Lzbk;
        //   675: ldc             "%s"
        //   677: iconst_1       
        //   678: anewarray       Ljava/lang/Object;
        //   681: dup            
        //   682: iconst_0       
        //   683: aload           9
        //   685: aastore        
        //   686: invokestatic    zbl.b:(Lzbk;Ljava/lang/String;[Ljava/lang/Object;)V
        //   689: aload           12
        //   691: checkcast       Lyup;
        //   694: getfield        yup.d:Lxra;
        //   697: astore          10
        //   699: aload           11
        //   701: ifnonnull       712
        //   704: getstatic       yps.d:Lyps;
        //   707: astore          9
        //   709: goto            722
        //   712: aload           11
        //   714: checkcast       Lywi;
        //   717: getfield        ywi.b:Lyps;
        //   720: astore          9
        //   722: aload           10
        //   724: getfield        xra.a:Ljava/lang/Object;
        //   727: checkcast       Lyri;
        //   730: aload           9
        //   732: aload           8
        //   734: checkcast       Lzbq;
        //   737: invokevirtual   yri.q:(Lyps;Lzbq;)V
        //   740: return         
        //   741: astore          9
        //   743: aload           11
        //   745: ifnonnull       756
        //   748: getstatic       ypw.a:Lypw;
        //   751: astore          8
        //   753: goto            766
        //   756: aload           11
        //   758: checkcast       Lywi;
        //   761: getfield        ywi.O:Lypw;
        //   764: astore          8
        //   766: getstatic       zll.b:Lzll;
        //   769: getstatic       zlk.f:Lzlk;
        //   772: ldc_w           "ScriptedMediaFetchControllerBridge error"
        //   775: aload           9
        //   777: invokestatic    zlm.c:(Lzll;Lzlk;Ljava/lang/String;Ljava/lang/Throwable;)V
        //   780: aload           11
        //   782: ifnonnull       790
        //   785: lconst_0       
        //   786: lstore_2       
        //   787: goto            804
        //   790: aload           11
        //   792: checkcast       Lywi;
        //   795: getfield        ywi.e:Lywh;
        //   798: invokeinterface ywh.e:()J
        //   803: lstore_2       
        //   804: new             Lzbo;
        //   807: astore          10
        //   809: aload           10
        //   811: ldc_w           "player.exception"
        //   814: lload_2        
        //   815: invokespecial   zbo.<init>:(Ljava/lang/String;J)V
        //   818: aload           10
        //   820: getstatic       zbp.i:Lzbp;
        //   823: putfield        zbo.a:Lzbp;
        //   826: aload           10
        //   828: aload           9
        //   830: putfield        zbo.c:Ljava/lang/Throwable;
        //   833: aload           10
        //   835: ldc_w           "c.main_thread_post"
        //   838: putfield        zbo.b:Ljava/lang/String;
        //   841: aload           8
        //   843: aload           10
        //   845: invokevirtual   zbo.a:()Lzbq;
        //   848: invokeinterface ypw.j:(Lzbq;)V
        //   853: return         
        //   854: astore          8
        //   856: getstatic       zbk.i:Lzbk;
        //   859: ldc_w           "Error when reporting error"
        //   862: invokestatic    zbl.a:(Lzbk;Ljava/lang/Object;)V
        //   865: return         
        //   866: aload_0        
        //   867: getfield        com/google/android/apps/youtube/embeddedplayer/service/ui/overlays/surveyoverlay/remoteloaded/a.d:Ljava/lang/Object;
        //   870: astore          8
        //   872: aload_0        
        //   873: getfield        com/google/android/apps/youtube/embeddedplayer/service/ui/overlays/surveyoverlay/remoteloaded/a.c:Ljava/lang/Object;
        //   876: astore          10
        //   878: aload_0        
        //   879: getfield        com/google/android/apps/youtube/embeddedplayer/service/ui/overlays/surveyoverlay/remoteloaded/a.a:Z
        //   882: istore          4
        //   884: aload_0        
        //   885: getfield        com/google/android/apps/youtube/embeddedplayer/service/ui/overlays/surveyoverlay/remoteloaded/a.b:Ljava/lang/Object;
        //   888: astore          11
        //   890: aload           8
        //   892: checkcast       Lyun;
        //   895: getfield        yun.d:Lywi;
        //   898: astore          9
        //   900: aload           11
        //   902: checkcast       Lywo;
        //   905: astore          11
        //   907: aload           9
        //   909: aload           10
        //   911: checkcast       Ljava/lang/String;
        //   914: iload           4
        //   916: aload           11
        //   918: iconst_3       
        //   919: invokevirtual   ywi.g:(Ljava/lang/String;ZLywo;I)V
        //   922: return         
        //   923: astore          9
        //   925: aload           8
        //   927: checkcast       Lyun;
        //   930: getfield        yun.d:Lywi;
        //   933: astore          10
        //   935: aload           10
        //   937: getfield        ywi.O:Lypw;
        //   940: astore          11
        //   942: new             Lzbo;
        //   945: astore          8
        //   947: aload           8
        //   949: ldc_w           "player.exception"
        //   952: aload           10
        //   954: getfield        ywi.e:Lywh;
        //   957: invokeinterface ywh.e:()J
        //   962: invokespecial   zbo.<init>:(Ljava/lang/String;J)V
        //   965: aload           8
        //   967: getstatic       zbp.i:Lzbp;
        //   970: putfield        zbo.a:Lzbp;
        //   973: aload           8
        //   975: aload           9
        //   977: putfield        zbo.c:Ljava/lang/Throwable;
        //   980: aload           8
        //   982: ldc_w           "c.main_thread_post"
        //   985: putfield        zbo.b:Ljava/lang/String;
        //   988: aload           11
        //   990: aload           8
        //   992: invokevirtual   zbo.a:()Lzbq;
        //   995: invokeinterface ypw.j:(Lzbq;)V
        //  1000: return         
        //  1001: astore          8
        //  1003: getstatic       zbk.i:Lzbk;
        //  1006: ldc_w           "Error when reporting error"
        //  1009: invokestatic    zbl.a:(Lzbk;Ljava/lang/Object;)V
        //  1012: return         
        //  1013: aload_0        
        //  1014: getfield        com/google/android/apps/youtube/embeddedplayer/service/ui/overlays/surveyoverlay/remoteloaded/a.b:Ljava/lang/Object;
        //  1017: astore          10
        //  1019: aload_0        
        //  1020: getfield        com/google/android/apps/youtube/embeddedplayer/service/ui/overlays/surveyoverlay/remoteloaded/a.d:Ljava/lang/Object;
        //  1023: astore          8
        //  1025: aload_0        
        //  1026: getfield        com/google/android/apps/youtube/embeddedplayer/service/ui/overlays/surveyoverlay/remoteloaded/a.a:Z
        //  1029: istore          4
        //  1031: aload_0        
        //  1032: getfield        com/google/android/apps/youtube/embeddedplayer/service/ui/overlays/surveyoverlay/remoteloaded/a.c:Ljava/lang/Object;
        //  1035: astore          9
        //  1037: aload           10
        //  1039: ifnull          1066
        //  1042: aload           10
        //  1044: checkcast       Latjz;
        //  1047: astore          10
        //  1049: aload           10
        //  1051: aload           8
        //  1053: invokevirtual   atjz.tu:(Ljava/lang/Object;)V
        //  1056: iload           4
        //  1058: ifeq            1066
        //  1061: aload           10
        //  1063: invokevirtual   atjz.tx:()V
        //  1066: aload           9
        //  1068: ifnull          1081
        //  1071: aload           9
        //  1073: checkcast       Latjz;
        //  1076: aload           8
        //  1078: invokevirtual   atjz.tu:(Ljava/lang/Object;)V
        //  1081: return         
        //  1082: aload_0        
        //  1083: getfield        com/google/android/apps/youtube/embeddedplayer/service/ui/overlays/surveyoverlay/remoteloaded/a.d:Ljava/lang/Object;
        //  1086: invokestatic    java/lang/String.valueOf:(Ljava/lang/Object;)Ljava/lang/String;
        //  1089: pop            
        //  1090: aload_0        
        //  1091: getfield        com/google/android/apps/youtube/embeddedplayer/service/ui/overlays/surveyoverlay/remoteloaded/a.b:Ljava/lang/Object;
        //  1094: astore          8
        //  1096: aload_0        
        //  1097: getfield        com/google/android/apps/youtube/embeddedplayer/service/ui/overlays/surveyoverlay/remoteloaded/a.d:Ljava/lang/Object;
        //  1100: astore          10
        //  1102: aload_0        
        //  1103: getfield        com/google/android/apps/youtube/embeddedplayer/service/ui/overlays/surveyoverlay/remoteloaded/a.c:Ljava/lang/Object;
        //  1106: astore          9
        //  1108: aload_0        
        //  1109: getfield        com/google/android/apps/youtube/embeddedplayer/service/ui/overlays/surveyoverlay/remoteloaded/a.a:Z
        //  1112: istore          4
        //  1114: aload           10
        //  1116: checkcast       Landroid/net/Uri;
        //  1119: astore          10
        //  1121: aload           8
        //  1123: checkcast       Lsis;
        //  1126: aload           10
        //  1128: aload           9
        //  1130: iload           4
        //  1132: invokevirtual   sis.h:(Landroid/net/Uri;Ljava/util/List;Z)Lznf;
        //  1135: astore          8
        //  1137: aload_0        
        //  1138: getfield        com/google/android/apps/youtube/embeddedplayer/service/ui/overlays/surveyoverlay/remoteloaded/a.b:Ljava/lang/Object;
        //  1141: checkcast       Lsis;
        //  1144: getfield        sis.e:Lvhe;
        //  1147: astore          9
        //  1149: aload           9
        //  1151: ifnull          1178
        //  1154: aload           8
        //  1156: aload           9
        //  1158: invokeinterface vhe.b:()Z
        //  1163: putfield        znf.d:Z
        //  1166: aload           8
        //  1168: aload           9
        //  1170: invokeinterface vhe.a:()J
        //  1175: putfield        znf.e:J
        //  1178: aload_0        
        //  1179: getfield        com/google/android/apps/youtube/embeddedplayer/service/ui/overlays/surveyoverlay/remoteloaded/a.b:Ljava/lang/Object;
        //  1182: checkcast       Lsis;
        //  1185: getfield        sis.d:Lsiq;
        //  1188: astore          9
        //  1190: getstatic       zpl.a:Ldbe;
        //  1193: astore          10
        //  1195: aload           9
        //  1197: getfield        siq.a:Ljava/util/regex/Pattern;
        //  1200: aload           8
        //  1202: getfield        znf.b:Landroid/net/Uri;
        //  1205: invokevirtual   android/net/Uri.toString:()Ljava/lang/String;
        //  1208: invokevirtual   java/util/regex/Pattern.matcher:(Ljava/lang/CharSequence;)Ljava/util/regex/Matcher;
        //  1211: invokevirtual   java/util/regex/Matcher.find:()Z
        //  1214: ifne            1227
        //  1217: aload           9
        //  1219: aload           8
        //  1221: aload           10
        //  1223: invokevirtual   siq.b:(Lznf;Ldbe;)V
        //  1226: return         
        //  1227: aload           9
        //  1229: getfield        siq.b:Laahc;
        //  1232: aload           8
        //  1234: aload           10
        //  1236: invokevirtual   aahc.j:(Lznf;Ldbe;)V
        //  1239: return         
        //  1240: aload_0        
        //  1241: getfield        com/google/android/apps/youtube/embeddedplayer/service/ui/overlays/surveyoverlay/remoteloaded/a.c:Ljava/lang/Object;
        //  1244: astore          8
        //  1246: aload           8
        //  1248: checkcast       Lnhy;
        //  1251: astore          10
        //  1253: aload           10
        //  1255: getfield        nhy.c:Lnfp;
        //  1258: astore          11
        //  1260: aload           11
        //  1262: ifnonnull       1283
        //  1265: aload           8
        //  1267: checkcast       Lngy;
        //  1270: invokevirtual   ngy.aA:()Lnfx;
        //  1273: getfield        nfx.c:Lnfv;
        //  1276: ldc_w           "Discarding data. Failed to send conditional user property to service"
        //  1279: invokevirtual   nfv.a:(Ljava/lang/String;)V
        //  1282: return         
        //  1283: aload_0        
        //  1284: getfield        com/google/android/apps/youtube/embeddedplayer/service/ui/overlays/surveyoverlay/remoteloaded/a.a:Z
        //  1287: ifeq            1297
        //  1290: aload           9
        //  1292: astore          8
        //  1294: goto            1303
        //  1297: aload_0        
        //  1298: getfield        com/google/android/apps/youtube/embeddedplayer/service/ui/overlays/surveyoverlay/remoteloaded/a.b:Ljava/lang/Object;
        //  1301: astore          8
        //  1303: aload_0        
        //  1304: getfield        com/google/android/apps/youtube/embeddedplayer/service/ui/overlays/surveyoverlay/remoteloaded/a.d:Ljava/lang/Object;
        //  1307: checkcast       Lcom/google/android/gms/measurement/internal/AppMetadata;
        //  1310: astore          9
        //  1312: aload           10
        //  1314: aload           11
        //  1316: aload           8
        //  1318: checkcast       Lcom/google/android/gms/common/internal/safeparcel/AbstractSafeParcelable;
        //  1321: aload           9
        //  1323: invokevirtual   nhy.v:(Lnfp;Lcom/google/android/gms/common/internal/safeparcel/AbstractSafeParcelable;Lcom/google/android/gms/measurement/internal/AppMetadata;)V
        //  1326: aload_0        
        //  1327: getfield        com/google/android/apps/youtube/embeddedplayer/service/ui/overlays/surveyoverlay/remoteloaded/a.c:Ljava/lang/Object;
        //  1330: checkcast       Lnhy;
        //  1333: invokevirtual   nhy.t:()V
        //  1336: return         
        //  1337: aload_0        
        //  1338: getfield        com/google/android/apps/youtube/embeddedplayer/service/ui/overlays/surveyoverlay/remoteloaded/a.c:Ljava/lang/Object;
        //  1341: astore          11
        //  1343: aload           11
        //  1345: checkcast       Lnhy;
        //  1348: astore          10
        //  1350: aload           10
        //  1352: getfield        nhy.c:Lnfp;
        //  1355: astore          9
        //  1357: aload           9
        //  1359: ifnonnull       1380
        //  1362: aload           11
        //  1364: checkcast       Lngy;
        //  1367: invokevirtual   ngy.aA:()Lnfx;
        //  1370: getfield        nfx.c:Lnfv;
        //  1373: ldc_w           "Discarding data. Failed to send event to service"
        //  1376: invokevirtual   nfv.a:(Ljava/lang/String;)V
        //  1379: return         
        //  1380: aload_0        
        //  1381: getfield        com/google/android/apps/youtube/embeddedplayer/service/ui/overlays/surveyoverlay/remoteloaded/a.a:Z
        //  1384: ifeq            1390
        //  1387: goto            1396
        //  1390: aload_0        
        //  1391: getfield        com/google/android/apps/youtube/embeddedplayer/service/ui/overlays/surveyoverlay/remoteloaded/a.b:Ljava/lang/Object;
        //  1394: astore          8
        //  1396: aload_0        
        //  1397: getfield        com/google/android/apps/youtube/embeddedplayer/service/ui/overlays/surveyoverlay/remoteloaded/a.d:Ljava/lang/Object;
        //  1400: checkcast       Lcom/google/android/gms/measurement/internal/AppMetadata;
        //  1403: astore          11
        //  1405: aload           10
        //  1407: aload           9
        //  1409: aload           8
        //  1411: checkcast       Lcom/google/android/gms/common/internal/safeparcel/AbstractSafeParcelable;
        //  1414: aload           11
        //  1416: invokevirtual   nhy.v:(Lnfp;Lcom/google/android/gms/common/internal/safeparcel/AbstractSafeParcelable;Lcom/google/android/gms/measurement/internal/AppMetadata;)V
        //  1419: aload_0        
        //  1420: getfield        com/google/android/apps/youtube/embeddedplayer/service/ui/overlays/surveyoverlay/remoteloaded/a.c:Ljava/lang/Object;
        //  1423: checkcast       Lnhy;
        //  1426: invokevirtual   nhy.t:()V
        //  1429: return         
        //  1430: aload_0        
        //  1431: getfield        com/google/android/apps/youtube/embeddedplayer/service/ui/overlays/surveyoverlay/remoteloaded/a.b:Ljava/lang/Object;
        //  1434: astore          8
        //  1436: aload           8
        //  1438: checkcast       Lnhy;
        //  1441: astore          11
        //  1443: aload           11
        //  1445: getfield        nhy.c:Lnfp;
        //  1448: astore          9
        //  1450: aload           9
        //  1452: ifnonnull       1473
        //  1455: aload           8
        //  1457: checkcast       Lngy;
        //  1460: invokevirtual   ngy.aA:()Lnfx;
        //  1463: getfield        nfx.c:Lnfv;
        //  1466: ldc_w           "Discarding data. Failed to set user property"
        //  1469: invokevirtual   nfv.a:(Ljava/lang/String;)V
        //  1472: return         
        //  1473: aload_0        
        //  1474: getfield        com/google/android/apps/youtube/embeddedplayer/service/ui/overlays/surveyoverlay/remoteloaded/a.a:Z
        //  1477: ifeq            1487
        //  1480: aload           10
        //  1482: astore          8
        //  1484: goto            1493
        //  1487: aload_0        
        //  1488: getfield        com/google/android/apps/youtube/embeddedplayer/service/ui/overlays/surveyoverlay/remoteloaded/a.c:Ljava/lang/Object;
        //  1491: astore          8
        //  1493: aload_0        
        //  1494: getfield        com/google/android/apps/youtube/embeddedplayer/service/ui/overlays/surveyoverlay/remoteloaded/a.d:Ljava/lang/Object;
        //  1497: checkcast       Lcom/google/android/gms/measurement/internal/AppMetadata;
        //  1500: astore          10
        //  1502: aload           11
        //  1504: aload           9
        //  1506: aload           8
        //  1508: checkcast       Lcom/google/android/gms/common/internal/safeparcel/AbstractSafeParcelable;
        //  1511: aload           10
        //  1513: invokevirtual   nhy.v:(Lnfp;Lcom/google/android/gms/common/internal/safeparcel/AbstractSafeParcelable;Lcom/google/android/gms/measurement/internal/AppMetadata;)V
        //  1516: aload_0        
        //  1517: getfield        com/google/android/apps/youtube/embeddedplayer/service/ui/overlays/surveyoverlay/remoteloaded/a.b:Ljava/lang/Object;
        //  1520: checkcast       Lnhy;
        //  1523: invokevirtual   nhy.t:()V
        //  1526: return         
        //  1527: aload_0        
        //  1528: getfield        com/google/android/apps/youtube/embeddedplayer/service/ui/overlays/surveyoverlay/remoteloaded/a.c:Ljava/lang/Object;
        //  1531: astore          9
        //  1533: aload_0        
        //  1534: getfield        com/google/android/apps/youtube/embeddedplayer/service/ui/overlays/surveyoverlay/remoteloaded/a.a:Z
        //  1537: istore          4
        //  1539: aload_0        
        //  1540: getfield        com/google/android/apps/youtube/embeddedplayer/service/ui/overlays/surveyoverlay/remoteloaded/a.d:Ljava/lang/Object;
        //  1543: astore          8
        //  1545: aload_0        
        //  1546: getfield        com/google/android/apps/youtube/embeddedplayer/service/ui/overlays/surveyoverlay/remoteloaded/a.b:Ljava/lang/Object;
        //  1549: astore          10
        //  1551: aload           9
        //  1553: checkcast       Lcom/google/android/apps/youtube/embeddedplayer/service/ui/subscriptionnotificationbutton/remoteloaded/i;
        //  1556: invokevirtual   com/google/android/apps/youtube/embeddedplayer/service/ui/subscriptionnotificationbutton/remoteloaded/i.b:()V
        //  1559: iload           4
        //  1561: ifne            1573
        //  1564: aload           8
        //  1566: aload           10
        //  1568: invokeinterface ako.accept:(Ljava/lang/Object;)V
        //  1573: return         
        //  1574: aload_0        
        //  1575: getfield        com/google/android/apps/youtube/embeddedplayer/service/ui/overlays/surveyoverlay/remoteloaded/a.d:Ljava/lang/Object;
        //  1578: astore          8
        //  1580: aload_0        
        //  1581: getfield        com/google/android/apps/youtube/embeddedplayer/service/ui/overlays/surveyoverlay/remoteloaded/a.c:Ljava/lang/Object;
        //  1584: astore          9
        //  1586: aload_0        
        //  1587: getfield        com/google/android/apps/youtube/embeddedplayer/service/ui/overlays/surveyoverlay/remoteloaded/a.a:Z
        //  1590: istore          4
        //  1592: aload_0        
        //  1593: getfield        com/google/android/apps/youtube/embeddedplayer/service/ui/overlays/surveyoverlay/remoteloaded/a.b:Ljava/lang/Object;
        //  1596: astore          10
        //  1598: aload           8
        //  1600: checkcast       Lcom/google/android/apps/youtube/embeddedplayer/service/ui/preview/service/e;
        //  1603: astore          11
        //  1605: aload           11
        //  1607: getfield        com/google/android/apps/youtube/embeddedplayer/service/ui/preview/service/e.d:Ljava/lang/Object;
        //  1610: astore          8
        //  1612: aload           8
        //  1614: ifnull          1652
        //  1617: aload           8
        //  1619: invokeinterface com/google/common/util/concurrent/ListenableFuture.isCancelled:()Z
        //  1624: ifne            1652
        //  1627: aload           11
        //  1629: getfield        com/google/android/apps/youtube/embeddedplayer/service/ui/preview/service/e.d:Ljava/lang/Object;
        //  1632: invokeinterface com/google/common/util/concurrent/ListenableFuture.isDone:()Z
        //  1637: ifne            1652
        //  1640: aload           11
        //  1642: getfield        com/google/android/apps/youtube/embeddedplayer/service/ui/preview/service/e.d:Ljava/lang/Object;
        //  1645: iconst_0       
        //  1646: invokeinterface com/google/common/util/concurrent/ListenableFuture.cancel:(Z)Z
        //  1651: pop            
        //  1652: iload           4
        //  1654: ifeq            1667
        //  1657: aload           11
        //  1659: getfield        com/google/android/apps/youtube/embeddedplayer/service/ui/preview/service/e.f:Ljava/lang/Object;
        //  1662: astore          8
        //  1664: goto            1674
        //  1667: aload           11
        //  1669: getfield        com/google/android/apps/youtube/embeddedplayer/service/ui/preview/service/e.a:Ljava/lang/Object;
        //  1672: astore          8
        //  1674: aload           10
        //  1676: checkcast       Laezp;
        //  1679: astore          10
        //  1681: aload           11
        //  1683: aload           8
        //  1685: aload           9
        //  1687: checkcast       Ljava/lang/String;
        //  1690: aload           10
        //  1692: invokeinterface adgg.a:(Ljava/lang/String;Laezp;)Lcom/google/common/util/concurrent/ListenableFuture;
        //  1697: putfield        com/google/android/apps/youtube/embeddedplayer/service/ui/preview/service/e.d:Ljava/lang/Object;
        //  1700: aload           11
        //  1702: getfield        com/google/android/apps/youtube/embeddedplayer/service/ui/preview/service/e.d:Ljava/lang/Object;
        //  1705: aload           11
        //  1707: getfield        com/google/android/apps/youtube/embeddedplayer/service/ui/preview/service/e.e:Ljava/lang/Object;
        //  1710: new             Ljdb;
        //  1713: dup            
        //  1714: iconst_4       
        //  1715: invokespecial   jdb.<init>:(I)V
        //  1718: new             Lhgd;
        //  1721: dup            
        //  1722: aload           11
        //  1724: bipush          18
        //  1726: aconst_null    
        //  1727: invokespecial   hgd.<init>:(Lcom/google/android/apps/youtube/embeddedplayer/service/ui/preview/service/e;I[B)V
        //  1730: invokestatic    teu.k:(Lcom/google/common/util/concurrent/ListenableFuture;Ljava/util/concurrent/Executor;Ltes;Ltet;)V
        //  1733: return         
        //  1734: aload_0        
        //  1735: getfield        com/google/android/apps/youtube/embeddedplayer/service/ui/overlays/surveyoverlay/remoteloaded/a.d:Ljava/lang/Object;
        //  1738: astore          9
        //  1740: aload_0        
        //  1741: getfield        com/google/android/apps/youtube/embeddedplayer/service/ui/overlays/surveyoverlay/remoteloaded/a.b:Ljava/lang/Object;
        //  1744: astore          10
        //  1746: aload_0        
        //  1747: getfield        com/google/android/apps/youtube/embeddedplayer/service/ui/overlays/surveyoverlay/remoteloaded/a.c:Ljava/lang/Object;
        //  1750: astore          8
        //  1752: aload_0        
        //  1753: getfield        com/google/android/apps/youtube/embeddedplayer/service/ui/overlays/surveyoverlay/remoteloaded/a.a:Z
        //  1756: istore          4
        //  1758: aload           9
        //  1760: checkcast       Lcom/google/android/apps/youtube/embeddedplayer/service/ui/overlays/surveyoverlay/shared/b;
        //  1763: getfield        com/google/android/apps/youtube/embeddedplayer/service/ui/overlays/surveyoverlay/shared/b.a:Lsjs;
        //  1766: aload           10
        //  1768: checkcast       Ljava/lang/String;
        //  1771: aload           8
        //  1773: iload           4
        //  1775: aconst_null    
        //  1776: invokeinterface sjs.o:(Ljava/lang/String;Ljava/util/List;ZLaool;)V
        //  1781: return         
        //  1782: aload           10
        //  1784: ldc_w           "e"
        //  1787: invokevirtual   abrm.a:(Ljava/lang/String;)Ljava/lang/String;
        //  1790: astore          13
        //  1792: aload           13
        //  1794: ifnonnull       1798
        //  1797: return         
        //  1798: getstatic       ahwa.a:Lahwa;
        //  1801: invokevirtual   ahbh.createBuilder:()Lahaz;
        //  1804: astore          11
        //  1806: getstatic       ahvz.a:Lahvz;
        //  1809: invokevirtual   ahbh.createBuilder:()Lahaz;
        //  1812: astore          12
        //  1814: aload           10
        //  1816: getfield        abrm.d:Ljava/lang/String;
        //  1819: astore          15
        //  1821: aload           12
        //  1823: invokevirtual   ahaz.copyOnWrite:()V
        //  1826: aload           12
        //  1828: getfield        ahaz.instance:Lahbh;
        //  1831: checkcast       Lahvz;
        //  1834: astore          14
        //  1836: aload           14
        //  1838: aload           14
        //  1840: getfield        ahvz.b:I
        //  1843: iconst_2       
        //  1844: ior            
        //  1845: putfield        ahvz.b:I
        //  1848: aload           14
        //  1850: aload           15
        //  1852: putfield        ahvz.d:Ljava/lang/String;
        //  1855: aload           12
        //  1857: invokevirtual   ahaz.copyOnWrite:()V
        //  1860: aload           12
        //  1862: getfield        ahaz.instance:Lahbh;
        //  1865: checkcast       Lahvz;
        //  1868: astore          14
        //  1870: aload           14
        //  1872: aload           14
        //  1874: getfield        ahvz.b:I
        //  1877: iconst_1       
        //  1878: ior            
        //  1879: putfield        ahvz.b:I
        //  1882: aload           14
        //  1884: aload           13
        //  1886: putfield        ahvz.c:Ljava/lang/String;
        //  1889: aload           11
        //  1891: invokevirtual   ahaz.copyOnWrite:()V
        //  1894: aload           11
        //  1896: getfield        ahaz.instance:Lahbh;
        //  1899: checkcast       Lahwa;
        //  1902: astore          13
        //  1904: aload           12
        //  1906: invokevirtual   ahaz.build:()Lahbh;
        //  1909: checkcast       Lahvz;
        //  1912: astore          12
        //  1914: aload           12
        //  1916: invokevirtual   java/lang/Object.getClass:()Ljava/lang/Class;
        //  1919: pop            
        //  1920: aload           13
        //  1922: aload           12
        //  1924: putfield        ahwa.c:Ljava/lang/Object;
        //  1927: aload           13
        //  1929: iconst_1       
        //  1930: putfield        ahwa.b:I
        //  1933: aload           11
        //  1935: invokevirtual   ahaz.build:()Lahbh;
        //  1938: checkcast       Lahwa;
        //  1941: astore          12
        //  1943: aload           10
        //  1945: getfield        abrm.g:Lzki;
        //  1948: astore          10
        //  1950: getstatic       lqw.a:Llqw;
        //  1953: invokevirtual   ahbh.createBuilder:()Lahaz;
        //  1956: astore          11
        //  1958: aload           12
        //  1960: invokevirtual   agzk.toByteString:()Lahab;
        //  1963: astore          12
        //  1965: aload           11
        //  1967: invokevirtual   ahaz.copyOnWrite:()V
        //  1970: aload           11
        //  1972: getfield        ahaz.instance:Lahbh;
        //  1975: checkcast       Llqw;
        //  1978: astore          13
        //  1980: aload           13
        //  1982: iconst_4       
        //  1983: aload           13
        //  1985: getfield        lqw.b:I
        //  1988: ior            
        //  1989: putfield        lqw.b:I
        //  1992: aload           13
        //  1994: aload           12
        //  1996: putfield        lqw.e:Lahab;
        //  1999: aload           11
        //  2001: invokevirtual   ahaz.copyOnWrite:()V
        //  2004: aload           11
        //  2006: getfield        ahaz.instance:Lahbh;
        //  2009: checkcast       Llqw;
        //  2012: astore          12
        //  2014: aload           12
        //  2016: iconst_2       
        //  2017: aload           12
        //  2019: getfield        lqw.b:I
        //  2022: ior            
        //  2023: putfield        lqw.b:I
        //  2026: aload           12
        //  2028: ldc_w           "attestation"
        //  2031: putfield        lqw.d:Ljava/lang/String;
        //  2034: aload           9
        //  2036: invokeinterface zme.d:()Ljava/lang/String;
        //  2041: astore          12
        //  2043: aload           11
        //  2045: invokevirtual   ahaz.copyOnWrite:()V
        //  2048: aload           11
        //  2050: getfield        ahaz.instance:Lahbh;
        //  2053: checkcast       Llqw;
        //  2056: astore          9
        //  2058: aload           9
        //  2060: aload           9
        //  2062: getfield        lqw.b:I
        //  2065: bipush          16
        //  2067: ior            
        //  2068: putfield        lqw.b:I
        //  2071: aload           9
        //  2073: aload           12
        //  2075: putfield        lqw.g:Ljava/lang/String;
        //  2078: aload           8
        //  2080: invokestatic    android/text/TextUtils.isEmpty:(Ljava/lang/CharSequence;)Z
        //  2083: ifne            2131
        //  2086: aload           11
        //  2088: invokevirtual   ahaz.copyOnWrite:()V
        //  2091: aload           11
        //  2093: getfield        ahaz.instance:Lahbh;
        //  2096: checkcast       Llqw;
        //  2099: astore          9
        //  2101: aload           8
        //  2103: invokevirtual   java/lang/Object.getClass:()Ljava/lang/Class;
        //  2106: pop            
        //  2107: aload           9
        //  2109: aload           9
        //  2111: getfield        lqw.b:I
        //  2114: sipush          128
        //  2117: ior            
        //  2118: putfield        lqw.b:I
        //  2121: aload           9
        //  2123: aload           8
        //  2125: checkcast       Ljava/lang/String;
        //  2128: putfield        lqw.j:Ljava/lang/String;
        //  2131: aload           11
        //  2133: invokevirtual   ahaz.copyOnWrite:()V
        //  2136: aload           11
        //  2138: getfield        ahaz.instance:Lahbh;
        //  2141: checkcast       Llqw;
        //  2144: astore          8
        //  2146: aload           8
        //  2148: aload           8
        //  2150: getfield        lqw.b:I
        //  2153: sipush          256
        //  2156: ior            
        //  2157: putfield        lqw.b:I
        //  2160: aload           8
        //  2162: iload           4
        //  2164: putfield        lqw.k:Z
        //  2167: aload           10
        //  2169: aload           11
        //  2171: invokevirtual   ahaz.build:()Lahbh;
        //  2174: checkcast       Llqw;
        //  2177: invokevirtual   ahbh.toBuilder:()Lahaz;
        //  2180: invokeinterface zki.l:(Lahaz;)V
        //  2185: return         
        //  2186: aload           10
        //  2188: aload           9
        //  2190: invokevirtual   abrm.c:(Lzme;)V
        //  2193: return         
        //  2194: astore          8
        //  2196: goto            504
        //    Exceptions:
        //  Try           Handler
        //  Start  End    Start  End    Type 
        //  -----  -----  -----  -----  -----
        //  440    445    741    866    Any
        //  448    458    741    866    Any
        //  458    468    741    866    Any
        //  478    489    2194   2199   Lyyx;
        //  478    489    741    866    Any
        //  504    516    741    866    Any
        //  521    586    741    866    Any
        //  589    605    741    866    Any
        //  609    620    741    866    Any
        //  625    689    741    866    Any
        //  689    699    741    866    Any
        //  704    709    741    866    Any
        //  712    722    741    866    Any
        //  722    740    741    866    Any
        //  748    753    854    866    Any
        //  756    766    854    866    Any
        //  766    780    854    866    Any
        //  790    804    854    866    Any
        //  804    853    854    866    Any
        //  890    922    923    1013   Any
        //  925    1000   1001   1013   Any
        // 
        // The error that occurred was:
        // 
        // java.lang.StackOverflowError
        //     at com.strobel.assembler.metadata.MetadataResolver.resolve(MetadataResolver.java:76)
        //     at com.strobel.assembler.metadata.CoreMetadataFactory$UnresolvedType.resolve(CoreMetadataFactory.java:616)
        //     at com.strobel.assembler.metadata.MetadataHelper$9.visitClassType(MetadataHelper.java:2292)
        //     at com.strobel.assembler.metadata.MetadataHelper$9.visitClassType(MetadataHelper.java:2240)
        //     at com.strobel.assembler.metadata.CoreMetadataFactory$UnresolvedType.accept(CoreMetadataFactory.java:577)
        //     at com.strobel.assembler.metadata.DefaultTypeVisitor.visit(DefaultTypeVisitor.java:25)
        //     at com.strobel.assembler.metadata.DefaultTypeVisitor.visit(DefaultTypeVisitor.java:21)
        //     at com.strobel.assembler.metadata.MetadataHelper.getSuperType(MetadataHelper.java:1369)
        //     at com.strobel.assembler.metadata.MetadataHelper$8.visitClassType(MetadataHelper.java:2163)
        //     at com.strobel.assembler.metadata.MetadataHelper$8.visitClassType(MetadataHelper.java:2146)
        //     at com.strobel.assembler.metadata.CoreMetadataFactory$UnresolvedType.accept(CoreMetadataFactory.java:577)
        //     at com.strobel.assembler.metadata.DefaultTypeVisitor.visit(DefaultTypeVisitor.java:25)
        //     at com.strobel.assembler.metadata.MetadataHelper.asSuper(MetadataHelper.java:833)
        //     at com.strobel.assembler.metadata.MetadataHelper$6.visitClassType(MetadataHelper.java:1973)
        //     at com.strobel.assembler.metadata.MetadataHelper$6.visitClassType(MetadataHelper.java:1935)
        //     at com.strobel.assembler.metadata.CoreMetadataFactory$UnresolvedType.accept(CoreMetadataFactory.java:577)
        //     at com.strobel.assembler.metadata.DefaultTypeVisitor.visit(DefaultTypeVisitor.java:25)
        //     at com.strobel.assembler.metadata.MetadataHelper.isSubType(MetadataHelper.java:1408)
        //     at com.strobel.assembler.metadata.MetadataHelper.isSubType(MetadataHelper.java:648)
        //     at com.strobel.decompiler.ast.TypeAnalysis.doInferTypeForExpression(TypeAnalysis.java:933)
        //     at com.strobel.decompiler.ast.TypeAnalysis.inferTypeForExpression(TypeAnalysis.java:815)
        //     at com.strobel.decompiler.ast.TypeAnalysis.inferTypeForExpression(TypeAnalysis.java:782)
        //     at com.strobel.decompiler.ast.TypeAnalysis.inferTypeForExpression(TypeAnalysis.java:778)
        //     at com.strobel.decompiler.ast.TypeAnalysis.doInferTypeForExpression(TypeAnalysis.java:1049)
        //     at com.strobel.decompiler.ast.TypeAnalysis.inferTypeForExpression(TypeAnalysis.java:815)
        //     at com.strobel.decompiler.ast.TypeAnalysis.inferTypeForExpression(TypeAnalysis.java:782)
        //     at com.strobel.decompiler.ast.TypeAnalysis.inferTypeForExpression(TypeAnalysis.java:778)
        //     at com.strobel.decompiler.ast.TypeAnalysis.doInferTypeForExpression(TypeAnalysis.java:1510)
        //     at com.strobel.decompiler.ast.TypeAnalysis.inferTypeForExpression(TypeAnalysis.java:815)
        //     at com.strobel.decompiler.ast.TypeAnalysis.inferTypeForExpression(TypeAnalysis.java:782)
        //     at com.strobel.decompiler.ast.TypeAnalysis.doInferTypeForExpression(TypeAnalysis.java:892)
        //     at com.strobel.decompiler.ast.TypeAnalysis.inferTypeForExpression(TypeAnalysis.java:815)
        //     at com.strobel.decompiler.ast.TypeAnalysis.runInference(TypeAnalysis.java:684)
        //     at com.strobel.decompiler.ast.TypeAnalysis.invalidateDependentExpressions(TypeAnalysis.java:771)
        //     at com.strobel.decompiler.ast.TypeAnalysis.doInferTypeForExpression(TypeAnalysis.java:1022)
        //     at com.strobel.decompiler.ast.TypeAnalysis.inferTypeForExpression(TypeAnalysis.java:815)
        //     at com.strobel.decompiler.ast.TypeAnalysis.inferTypeForExpression(TypeAnalysis.java:782)
        //     at com.strobel.decompiler.ast.TypeAnalysis.inferTypeForExpression(TypeAnalysis.java:778)
        //     at com.strobel.decompiler.ast.TypeAnalysis.inferCall(TypeAnalysis.java:2483)
        //     at com.strobel.decompiler.ast.TypeAnalysis.doInferTypeForExpression(TypeAnalysis.java:1040)
        //     at com.strobel.decompiler.ast.TypeAnalysis.inferTypeForExpression(TypeAnalysis.java:815)
        //     at com.strobel.decompiler.ast.TypeAnalysis.inferTypeForExpression(TypeAnalysis.java:782)
        //     at com.strobel.decompiler.ast.TypeAnalysis.doInferTypeForExpression(TypeAnalysis.java:892)
        //     at com.strobel.decompiler.ast.TypeAnalysis.inferTypeForExpression(TypeAnalysis.java:815)
        //     at com.strobel.decompiler.ast.TypeAnalysis.runInference(TypeAnalysis.java:684)
        //     at com.strobel.decompiler.ast.TypeAnalysis.invalidateDependentExpressions(TypeAnalysis.java:771)
        //     at com.strobel.decompiler.ast.TypeAnalysis.doInferTypeForExpression(TypeAnalysis.java:1022)
        //     at com.strobel.decompiler.ast.TypeAnalysis.inferTypeForExpression(TypeAnalysis.java:815)
        //     at com.strobel.decompiler.ast.TypeAnalysis.inferTypeForExpression(TypeAnalysis.java:782)
        //     at com.strobel.decompiler.ast.TypeAnalysis.inferTypeForExpression(TypeAnalysis.java:778)
        //     at com.strobel.decompiler.ast.TypeAnalysis.doInferTypeForExpression(TypeAnalysis.java:1049)
        //     at com.strobel.decompiler.ast.TypeAnalysis.inferTypeForExpression(TypeAnalysis.java:815)
        //     at com.strobel.decompiler.ast.TypeAnalysis.inferTypeForExpression(TypeAnalysis.java:782)
        //     at com.strobel.decompiler.ast.TypeAnalysis.inferTypeForExpression(TypeAnalysis.java:778)
        //     at com.strobel.decompiler.ast.TypeAnalysis.doInferTypeForExpression(TypeAnalysis.java:1510)
        //     at com.strobel.decompiler.ast.TypeAnalysis.inferTypeForExpression(TypeAnalysis.java:815)
        //     at com.strobel.decompiler.ast.TypeAnalysis.inferTypeForExpression(TypeAnalysis.java:782)
        //     at com.strobel.decompiler.ast.TypeAnalysis.doInferTypeForExpression(TypeAnalysis.java:892)
        //     at com.strobel.decompiler.ast.TypeAnalysis.inferTypeForExpression(TypeAnalysis.java:815)
        //     at com.strobel.decompiler.ast.TypeAnalysis.runInference(TypeAnalysis.java:684)
        //     at com.strobel.decompiler.ast.TypeAnalysis.invalidateDependentExpressions(TypeAnalysis.java:771)
        //     at com.strobel.decompiler.ast.TypeAnalysis.doInferTypeForExpression(TypeAnalysis.java:1022)
        //     at com.strobel.decompiler.ast.TypeAnalysis.inferTypeForExpression(TypeAnalysis.java:815)
        //     at com.strobel.decompiler.ast.TypeAnalysis.inferTypeForExpression(TypeAnalysis.java:782)
        //     at com.strobel.decompiler.ast.TypeAnalysis.inferTypeForExpression(TypeAnalysis.java:778)
        //     at com.strobel.decompiler.ast.TypeAnalysis.doInferTypeForExpression(TypeAnalysis.java:1072)
        //     at com.strobel.decompiler.ast.TypeAnalysis.inferTypeForExpression(TypeAnalysis.java:815)
        //     at com.strobel.decompiler.ast.TypeAnalysis.runInference(TypeAnalysis.java:684)
        //     at com.strobel.decompiler.ast.TypeAnalysis.invalidateDependentExpressions(TypeAnalysis.java:771)
        //     at com.strobel.decompiler.ast.TypeAnalysis.doInferTypeForExpression(TypeAnalysis.java:1022)
        //     at com.strobel.decompiler.ast.TypeAnalysis.inferTypeForExpression(TypeAnalysis.java:815)
        //     at com.strobel.decompiler.ast.TypeAnalysis.inferTypeForExpression(TypeAnalysis.java:782)
        //     at com.strobel.decompiler.ast.TypeAnalysis.inferTypeForExpression(TypeAnalysis.java:778)
        //     at com.strobel.decompiler.ast.TypeAnalysis.doInferTypeForExpression(TypeAnalysis.java:1067)
        //     at com.strobel.decompiler.ast.TypeAnalysis.inferTypeForExpression(TypeAnalysis.java:815)
        //     at com.strobel.decompiler.ast.TypeAnalysis.runInference(TypeAnalysis.java:684)
        //     at com.strobel.decompiler.ast.TypeAnalysis.invalidateDependentExpressions(TypeAnalysis.java:771)
        //     at com.strobel.decompiler.ast.TypeAnalysis.doInferTypeForExpression(TypeAnalysis.java:1022)
        //     at com.strobel.decompiler.ast.TypeAnalysis.inferTypeForExpression(TypeAnalysis.java:815)
        //     at com.strobel.decompiler.ast.TypeAnalysis.inferTypeForExpression(TypeAnalysis.java:782)
        //     at com.strobel.decompiler.ast.TypeAnalysis.inferTypeForExpression(TypeAnalysis.java:778)
        //     at com.strobel.decompiler.ast.TypeAnalysis.inferCall(TypeAnalysis.java:2483)
        //     at com.strobel.decompiler.ast.TypeAnalysis.doInferTypeForExpression(TypeAnalysis.java:1040)
        //     at com.strobel.decompiler.ast.TypeAnalysis.inferTypeForExpression(TypeAnalysis.java:815)
        //     at com.strobel.decompiler.ast.TypeAnalysis.inferTypeForExpression(TypeAnalysis.java:782)
        //     at com.strobel.decompiler.ast.TypeAnalysis.doInferTypeForExpression(TypeAnalysis.java:892)
        //     at com.strobel.decompiler.ast.TypeAnalysis.inferTypeForExpression(TypeAnalysis.java:815)
        //     at com.strobel.decompiler.ast.TypeAnalysis.runInference(TypeAnalysis.java:684)
        //     at com.strobel.decompiler.ast.TypeAnalysis.invalidateDependentExpressions(TypeAnalysis.java:771)
        //     at com.strobel.decompiler.ast.TypeAnalysis.doInferTypeForExpression(TypeAnalysis.java:1022)
        //     at com.strobel.decompiler.ast.TypeAnalysis.inferTypeForExpression(TypeAnalysis.java:815)
        //     at com.strobel.decompiler.ast.TypeAnalysis.inferTypeForExpression(TypeAnalysis.java:782)
        //     at com.strobel.decompiler.ast.TypeAnalysis.inferTypeForExpression(TypeAnalysis.java:778)
        //     at com.strobel.decompiler.ast.TypeAnalysis.doInferTypeForExpression(TypeAnalysis.java:1510)
        //     at com.strobel.decompiler.ast.TypeAnalysis.inferTypeForExpression(TypeAnalysis.java:815)
        //     at com.strobel.decompiler.ast.TypeAnalysis.inferTypeForExpression(TypeAnalysis.java:782)
        //     at com.strobel.decompiler.ast.TypeAnalysis.inferTypeForExpression(TypeAnalysis.java:778)
        //     at com.strobel.decompiler.ast.TypeAnalysis.doInferTypeForExpression(TypeAnalysis.java:1049)
        //     at com.strobel.decompiler.ast.TypeAnalysis.inferTypeForExpression(TypeAnalysis.java:815)
        //     at com.strobel.decompiler.ast.TypeAnalysis.inferTypeForExpression(TypeAnalysis.java:782)
        //     at com.strobel.decompiler.ast.TypeAnalysis.inferTypeForExpression(TypeAnalysis.java:778)
        //     at com.strobel.decompiler.ast.TypeAnalysis.inferCall(TypeAnalysis.java:2483)
        //     at com.strobel.decompiler.ast.TypeAnalysis.doInferTypeForExpression(TypeAnalysis.java:1040)
        //     at com.strobel.decompiler.ast.TypeAnalysis.inferTypeForExpression(TypeAnalysis.java:815)
        //     at com.strobel.decompiler.ast.TypeAnalysis.runInference(TypeAnalysis.java:684)
        //     at com.strobel.decompiler.ast.TypeAnalysis.invalidateDependentExpressions(TypeAnalysis.java:771)
        //     at com.strobel.decompiler.ast.TypeAnalysis.doInferTypeForExpression(TypeAnalysis.java:1022)
        //     at com.strobel.decompiler.ast.TypeAnalysis.inferTypeForExpression(TypeAnalysis.java:815)
        //     at com.strobel.decompiler.ast.TypeAnalysis.inferTypeForExpression(TypeAnalysis.java:782)
        //     at com.strobel.decompiler.ast.TypeAnalysis.inferTypeForExpression(TypeAnalysis.java:778)
        //     at com.strobel.decompiler.ast.TypeAnalysis.doInferTypeForExpression(TypeAnalysis.java:1510)
        //     at com.strobel.decompiler.ast.TypeAnalysis.inferTypeForExpression(TypeAnalysis.java:815)
        //     at com.strobel.decompiler.ast.TypeAnalysis.inferTypeForExpression(TypeAnalysis.java:782)
        //     at com.strobel.decompiler.ast.TypeAnalysis.inferTypeForExpression(TypeAnalysis.java:778)
        //     at com.strobel.decompiler.ast.TypeAnalysis.inferCall(TypeAnalysis.java:2483)
        //     at com.strobel.decompiler.ast.TypeAnalysis.doInferTypeForExpression(TypeAnalysis.java:1040)
        //     at com.strobel.decompiler.ast.TypeAnalysis.inferTypeForExpression(TypeAnalysis.java:815)
        //     at com.strobel.decompiler.ast.TypeAnalysis.runInference(TypeAnalysis.java:684)
        //     at com.strobel.decompiler.ast.TypeAnalysis.invalidateDependentExpressions(TypeAnalysis.java:771)
        //     at com.strobel.decompiler.ast.TypeAnalysis.doInferTypeForExpression(TypeAnalysis.java:1022)
        //     at com.strobel.decompiler.ast.TypeAnalysis.inferTypeForExpression(TypeAnalysis.java:815)
        //     at com.strobel.decompiler.ast.TypeAnalysis.inferTypeForExpression(TypeAnalysis.java:782)
        //     at com.strobel.decompiler.ast.TypeAnalysis.inferTypeForExpression(TypeAnalysis.java:778)
        //     at com.strobel.decompiler.ast.TypeAnalysis.doInferTypeForExpression(TypeAnalysis.java:1510)
        //     at com.strobel.decompiler.ast.TypeAnalysis.inferTypeForExpression(TypeAnalysis.java:815)
        //     at com.strobel.decompiler.ast.TypeAnalysis.inferCall(TypeAnalysis.java:2715)
        //     at com.strobel.decompiler.ast.TypeAnalysis.doInferTypeForExpression(TypeAnalysis.java:1040)
        //     at com.strobel.decompiler.ast.TypeAnalysis.inferTypeForExpression(TypeAnalysis.java:815)
        //     at com.strobel.decompiler.ast.TypeAnalysis.runInference(TypeAnalysis.java:684)
        //     at com.strobel.decompiler.ast.TypeAnalysis.invalidateDependentExpressions(TypeAnalysis.java:771)
        //     at com.strobel.decompiler.ast.TypeAnalysis.doInferTypeForExpression(TypeAnalysis.java:1022)
        //     at com.strobel.decompiler.ast.TypeAnalysis.inferTypeForExpression(TypeAnalysis.java:815)
        //     at com.strobel.decompiler.ast.TypeAnalysis.inferTypeForExpression(TypeAnalysis.java:782)
        //     at com.strobel.decompiler.ast.TypeAnalysis.inferTypeForExpression(TypeAnalysis.java:778)
        //     at com.strobel.decompiler.ast.TypeAnalysis.inferCall(TypeAnalysis.java:2483)
        //     at com.strobel.decompiler.ast.TypeAnalysis.doInferTypeForExpression(TypeAnalysis.java:1040)
        //     at com.strobel.decompiler.ast.TypeAnalysis.inferTypeForExpression(TypeAnalysis.java:815)
        //     at com.strobel.decompiler.ast.TypeAnalysis.runInference(TypeAnalysis.java:684)
        //     at com.strobel.decompiler.ast.TypeAnalysis.invalidateDependentExpressions(TypeAnalysis.java:771)
        //     at com.strobel.decompiler.ast.TypeAnalysis.doInferTypeForExpression(TypeAnalysis.java:1022)
        //     at com.strobel.decompiler.ast.TypeAnalysis.inferTypeForExpression(TypeAnalysis.java:815)
        //     at com.strobel.decompiler.ast.TypeAnalysis.inferTypeForExpression(TypeAnalysis.java:782)
        //     at com.strobel.decompiler.ast.TypeAnalysis.inferTypeForExpression(TypeAnalysis.java:778)
        //     at com.strobel.decompiler.ast.TypeAnalysis.doInferTypeForExpression(TypeAnalysis.java:1049)
        //     at com.strobel.decompiler.ast.TypeAnalysis.inferTypeForExpression(TypeAnalysis.java:815)
        //     at com.strobel.decompiler.ast.TypeAnalysis.inferTypeForExpression(TypeAnalysis.java:782)
        //     at com.strobel.decompiler.ast.TypeAnalysis.inferTypeForExpression(TypeAnalysis.java:778)
        //     at com.strobel.decompiler.ast.TypeAnalysis.doInferTypeForExpression(TypeAnalysis.java:1510)
        //     at com.strobel.decompiler.ast.TypeAnalysis.inferTypeForExpression(TypeAnalysis.java:815)
        //     at com.strobel.decompiler.ast.TypeAnalysis.inferTypeForExpression(TypeAnalysis.java:782)
        //     at com.strobel.decompiler.ast.TypeAnalysis.doInferTypeForExpression(TypeAnalysis.java:892)
        //     at com.strobel.decompiler.ast.TypeAnalysis.inferTypeForExpression(TypeAnalysis.java:815)
        //     at com.strobel.decompiler.ast.TypeAnalysis.runInference(TypeAnalysis.java:684)
        //     at com.strobel.decompiler.ast.TypeAnalysis.invalidateDependentExpressions(TypeAnalysis.java:771)
        //     at com.strobel.decompiler.ast.TypeAnalysis.doInferTypeForExpression(TypeAnalysis.java:1022)
        //     at com.strobel.decompiler.ast.TypeAnalysis.inferTypeForExpression(TypeAnalysis.java:815)
        //     at com.strobel.decompiler.ast.TypeAnalysis.inferTypeForExpression(TypeAnalysis.java:782)
        //     at com.strobel.decompiler.ast.TypeAnalysis.inferTypeForExpression(TypeAnalysis.java:778)
        //     at com.strobel.decompiler.ast.TypeAnalysis.doInferTypeForExpression(TypeAnalysis.java:1067)
        //     at com.strobel.decompiler.ast.TypeAnalysis.inferTypeForExpression(TypeAnalysis.java:815)
        //     at com.strobel.decompiler.ast.TypeAnalysis.runInference(TypeAnalysis.java:684)
        //     at com.strobel.decompiler.ast.TypeAnalysis.invalidateDependentExpressions(TypeAnalysis.java:771)
        //     at com.strobel.decompiler.ast.TypeAnalysis.doInferTypeForExpression(TypeAnalysis.java:1022)
        //     at com.strobel.decompiler.ast.TypeAnalysis.inferTypeForExpression(TypeAnalysis.java:815)
        //     at com.strobel.decompiler.ast.TypeAnalysis.inferTypeForExpression(TypeAnalysis.java:782)
        //     at com.strobel.decompiler.ast.TypeAnalysis.inferTypeForExpression(TypeAnalysis.java:778)
        //     at com.strobel.decompiler.ast.TypeAnalysis.doInferTypeForExpression(TypeAnalysis.java:1510)
        //     at com.strobel.decompiler.ast.TypeAnalysis.inferTypeForExpression(TypeAnalysis.java:815)
        //     at com.strobel.decompiler.ast.TypeAnalysis.inferTypeForExpression(TypeAnalysis.java:782)
        //     at com.strobel.decompiler.ast.TypeAnalysis.doInferTypeForExpression(TypeAnalysis.java:892)
        //     at com.strobel.decompiler.ast.TypeAnalysis.inferTypeForExpression(TypeAnalysis.java:815)
        //     at com.strobel.decompiler.ast.TypeAnalysis.runInference(TypeAnalysis.java:684)
        //     at com.strobel.decompiler.ast.TypeAnalysis.invalidateDependentExpressions(TypeAnalysis.java:771)
        //     at com.strobel.decompiler.ast.TypeAnalysis.doInferTypeForExpression(TypeAnalysis.java:1022)
        //     at com.strobel.decompiler.ast.TypeAnalysis.inferTypeForExpression(TypeAnalysis.java:815)
        //     at com.strobel.decompiler.ast.TypeAnalysis.inferTypeForExpression(TypeAnalysis.java:782)
        //     at com.strobel.decompiler.ast.TypeAnalysis.doInferTypeForExpression(TypeAnalysis.java:892)
        //     at com.strobel.decompiler.ast.TypeAnalysis.inferTypeForExpression(TypeAnalysis.java:815)
        //     at com.strobel.decompiler.ast.TypeAnalysis.runInference(TypeAnalysis.java:684)
        //     at com.strobel.decompiler.ast.TypeAnalysis.invalidateDependentExpressions(TypeAnalysis.java:771)
        //     at com.strobel.decompiler.ast.TypeAnalysis.doInferTypeForExpression(TypeAnalysis.java:1022)
        //     at com.strobel.decompiler.ast.TypeAnalysis.inferTypeForExpression(TypeAnalysis.java:815)
        //     at com.strobel.decompiler.ast.TypeAnalysis.inferTypeForExpression(TypeAnalysis.java:782)
        //     at com.strobel.decompiler.ast.TypeAnalysis.inferTypeForExpression(TypeAnalysis.java:778)
        //     at com.strobel.decompiler.ast.TypeAnalysis.doInferTypeForExpression(TypeAnalysis.java:1510)
        //     at com.strobel.decompiler.ast.TypeAnalysis.inferTypeForExpression(TypeAnalysis.java:815)
        //     at com.strobel.decompiler.ast.TypeAnalysis.inferCall(TypeAnalysis.java:2715)
        //     at com.strobel.decompiler.ast.TypeAnalysis.doInferTypeForExpression(TypeAnalysis.java:1040)
        //     at com.strobel.decompiler.ast.TypeAnalysis.inferTypeForExpression(TypeAnalysis.java:815)
        //     at com.strobel.decompiler.ast.TypeAnalysis.runInference(TypeAnalysis.java:684)
        //     at com.strobel.decompiler.ast.TypeAnalysis.invalidateDependentExpressions(TypeAnalysis.java:771)
        //     at com.strobel.decompiler.ast.TypeAnalysis.doInferTypeForExpression(TypeAnalysis.java:1022)
        //     at com.strobel.decompiler.ast.TypeAnalysis.inferTypeForExpression(TypeAnalysis.java:815)
        //     at com.strobel.decompiler.ast.TypeAnalysis.inferCall(TypeAnalysis.java:2715)
        //     at com.strobel.decompiler.ast.TypeAnalysis.doInferTypeForExpression(TypeAnalysis.java:1040)
        //     at com.strobel.decompiler.ast.TypeAnalysis.inferTypeForExpression(TypeAnalysis.java:815)
        //     at com.strobel.decompiler.ast.TypeAnalysis.runInference(TypeAnalysis.java:684)
        //     at com.strobel.decompiler.ast.TypeAnalysis.invalidateDependentExpressions(TypeAnalysis.java:771)
        //     at com.strobel.decompiler.ast.TypeAnalysis.doInferTypeForExpression(TypeAnalysis.java:1022)
        //     at com.strobel.decompiler.ast.TypeAnalysis.inferTypeForExpression(TypeAnalysis.java:815)
        //     at com.strobel.decompiler.ast.TypeAnalysis.inferTypeForExpression(TypeAnalysis.java:782)
        //     at com.strobel.decompiler.ast.TypeAnalysis.inferTypeForExpression(TypeAnalysis.java:778)
        //     at com.strobel.decompiler.ast.TypeAnalysis.doInferTypeForExpression(TypeAnalysis.java:1510)
        //     at com.strobel.decompiler.ast.TypeAnalysis.inferTypeForExpression(TypeAnalysis.java:815)
        //     at com.strobel.decompiler.ast.TypeAnalysis.inferTypeForExpression(TypeAnalysis.java:782)
        //     at com.strobel.decompiler.ast.TypeAnalysis.inferTypeForExpression(TypeAnalysis.java:778)
        //     at com.strobel.decompiler.ast.TypeAnalysis.inferCall(TypeAnalysis.java:2483)
        //     at com.strobel.decompiler.ast.TypeAnalysis.doInferTypeForExpression(TypeAnalysis.java:1040)
        //     at com.strobel.decompiler.ast.TypeAnalysis.inferTypeForExpression(TypeAnalysis.java:815)
        //     at com.strobel.decompiler.ast.TypeAnalysis.inferTypeForExpression(TypeAnalysis.java:782)
        //     at com.strobel.decompiler.ast.TypeAnalysis.inferTypeForExpression(TypeAnalysis.java:778)
        //     at com.strobel.decompiler.ast.TypeAnalysis.doInferTypeForExpression(TypeAnalysis.java:1049)
        //     at com.strobel.decompiler.ast.TypeAnalysis.inferTypeForExpression(TypeAnalysis.java:815)
        //     at com.strobel.decompiler.ast.TypeAnalysis.inferTypeForExpression(TypeAnalysis.java:782)
        //     at com.strobel.decompiler.ast.TypeAnalysis.inferTypeForExpression(TypeAnalysis.java:778)
        //     at com.strobel.decompiler.ast.TypeAnalysis.inferCall(TypeAnalysis.java:2483)
        //     at com.strobel.decompiler.ast.TypeAnalysis.doInferTypeForExpression(TypeAnalysis.java:1040)
        //     at com.strobel.decompiler.ast.TypeAnalysis.inferTypeForExpression(TypeAnalysis.java:815)
        //     at com.strobel.decompiler.ast.TypeAnalysis.runInference(TypeAnalysis.java:684)
        //     at com.strobel.decompiler.ast.TypeAnalysis.invalidateDependentExpressions(TypeAnalysis.java:771)
        //     at com.strobel.decompiler.ast.TypeAnalysis.doInferTypeForExpression(TypeAnalysis.java:1022)
        //     at com.strobel.decompiler.ast.TypeAnalysis.inferTypeForExpression(TypeAnalysis.java:815)
        //     at com.strobel.decompiler.ast.TypeAnalysis.inferTypeForExpression(TypeAnalysis.java:782)
        //     at com.strobel.decompiler.ast.TypeAnalysis.inferTypeForExpression(TypeAnalysis.java:778)
        //     at com.strobel.decompiler.ast.TypeAnalysis.doInferTypeForExpression(TypeAnalysis.java:1510)
        //     at com.strobel.decompiler.ast.TypeAnalysis.inferTypeForExpression(TypeAnalysis.java:815)
        //     at com.strobel.decompiler.ast.TypeAnalysis.inferTypeForExpression(TypeAnalysis.java:782)
        //     at com.strobel.decompiler.ast.TypeAnalysis.doInferTypeForExpression(TypeAnalysis.java:892)
        //     at com.strobel.decompiler.ast.TypeAnalysis.inferTypeForExpression(TypeAnalysis.java:815)
        //     at com.strobel.decompiler.ast.TypeAnalysis.runInference(TypeAnalysis.java:684)
        //     at com.strobel.decompiler.ast.TypeAnalysis.invalidateDependentExpressions(TypeAnalysis.java:771)
        //     at com.strobel.decompiler.ast.TypeAnalysis.doInferTypeForExpression(TypeAnalysis.java:1022)
        //     at com.strobel.decompiler.ast.TypeAnalysis.inferTypeForExpression(TypeAnalysis.java:815)
        //     at com.strobel.decompiler.ast.TypeAnalysis.inferCall(TypeAnalysis.java:2715)
        //     at com.strobel.decompiler.ast.TypeAnalysis.doInferTypeForExpression(TypeAnalysis.java:1040)
        //     at com.strobel.decompiler.ast.TypeAnalysis.inferTypeForExpression(TypeAnalysis.java:815)
        //     at com.strobel.decompiler.ast.TypeAnalysis.runInference(TypeAnalysis.java:684)
        //     at com.strobel.decompiler.ast.TypeAnalysis.invalidateDependentExpressions(TypeAnalysis.java:771)
        //     at com.strobel.decompiler.ast.TypeAnalysis.doInferTypeForExpression(TypeAnalysis.java:1022)
        //     at com.strobel.decompiler.ast.TypeAnalysis.inferTypeForExpression(TypeAnalysis.java:815)
        //     at com.strobel.decompiler.ast.TypeAnalysis.inferCall(TypeAnalysis.java:2715)
        //     at com.strobel.decompiler.ast.TypeAnalysis.doInferTypeForExpression(TypeAnalysis.java:1040)
        //     at com.strobel.decompiler.ast.TypeAnalysis.inferTypeForExpression(TypeAnalysis.java:815)
        //     at com.strobel.decompiler.ast.TypeAnalysis.runInference(TypeAnalysis.java:684)
        //     at com.strobel.decompiler.ast.TypeAnalysis.invalidateDependentExpressions(TypeAnalysis.java:771)
        //     at com.strobel.decompiler.ast.TypeAnalysis.doInferTypeForExpression(TypeAnalysis.java:1022)
        //     at com.strobel.decompiler.ast.TypeAnalysis.inferTypeForExpression(TypeAnalysis.java:815)
        //     at com.strobel.decompiler.ast.TypeAnalysis.inferTypeForExpression(TypeAnalysis.java:782)
        //     at com.strobel.decompiler.ast.TypeAnalysis.inferTypeForExpression(TypeAnalysis.java:778)
        //     at com.strobel.decompiler.ast.TypeAnalysis.inferCall(TypeAnalysis.java:2483)
        //     at com.strobel.decompiler.ast.TypeAnalysis.doInferTypeForExpression(TypeAnalysis.java:1040)
        //     at com.strobel.decompiler.ast.TypeAnalysis.inferTypeForExpression(TypeAnalysis.java:815)
        //     at com.strobel.decompiler.ast.TypeAnalysis.inferTypeForExpression(TypeAnalysis.java:782)
        //     at com.strobel.decompiler.ast.TypeAnalysis.inferTypeForExpression(TypeAnalysis.java:778)
        //     at com.strobel.decompiler.ast.TypeAnalysis.doInferTypeForExpression(TypeAnalysis.java:1072)
        //     at com.strobel.decompiler.ast.TypeAnalysis.inferTypeForExpression(TypeAnalysis.java:815)
        //     at com.strobel.decompiler.ast.TypeAnalysis.runInference(TypeAnalysis.java:684)
        //     at com.strobel.decompiler.ast.TypeAnalysis.invalidateDependentExpressions(TypeAnalysis.java:771)
        //     at com.strobel.decompiler.ast.TypeAnalysis.doInferTypeForExpression(TypeAnalysis.java:1022)
        //     at com.strobel.decompiler.ast.TypeAnalysis.inferTypeForExpression(TypeAnalysis.java:815)
        //     at com.strobel.decompiler.ast.TypeAnalysis.inferTypeForExpression(TypeAnalysis.java:782)
        //     at com.strobel.decompiler.ast.TypeAnalysis.inferTypeForExpression(TypeAnalysis.java:778)
        //     at com.strobel.decompiler.ast.TypeAnalysis.doInferTypeForExpression(TypeAnalysis.java:1510)
        //     at com.strobel.decompiler.ast.TypeAnalysis.inferTypeForExpression(TypeAnalysis.java:815)
        //     at com.strobel.decompiler.ast.TypeAnalysis.inferTypeForExpression(TypeAnalysis.java:782)
        //     at com.strobel.decompiler.ast.TypeAnalysis.inferTypeForExpression(TypeAnalysis.java:778)
        //     at com.strobel.decompiler.ast.TypeAnalysis.inferCall(TypeAnalysis.java:2483)
        //     at com.strobel.decompiler.ast.TypeAnalysis.doInferTypeForExpression(TypeAnalysis.java:1040)
        //     at com.strobel.decompiler.ast.TypeAnalysis.inferTypeForExpression(TypeAnalysis.java:815)
        //     at com.strobel.decompiler.ast.TypeAnalysis.runInference(TypeAnalysis.java:684)
        //     at com.strobel.decompiler.ast.TypeAnalysis.invalidateDependentExpressions(TypeAnalysis.java:771)
        //     at com.strobel.decompiler.ast.TypeAnalysis.doInferTypeForExpression(TypeAnalysis.java:1022)
        //     at com.strobel.decompiler.ast.TypeAnalysis.inferTypeForExpression(TypeAnalysis.java:815)
        //     at com.strobel.decompiler.ast.TypeAnalysis.inferTypeForExpression(TypeAnalysis.java:782)
        //     at com.strobel.decompiler.ast.TypeAnalysis.inferTypeForExpression(TypeAnalysis.java:778)
        //     at com.strobel.decompiler.ast.TypeAnalysis.inferCall(TypeAnalysis.java:2483)
        //     at com.strobel.decompiler.ast.TypeAnalysis.doInferTypeForExpression(TypeAnalysis.java:1040)
        //     at com.strobel.decompiler.ast.TypeAnalysis.inferTypeForExpression(TypeAnalysis.java:815)
        //     at com.strobel.decompiler.ast.TypeAnalysis.runInference(TypeAnalysis.java:684)
        //     at com.strobel.decompiler.ast.TypeAnalysis.invalidateDependentExpressions(TypeAnalysis.java:771)
        //     at com.strobel.decompiler.ast.TypeAnalysis.doInferTypeForExpression(TypeAnalysis.java:1022)
        //     at com.strobel.decompiler.ast.TypeAnalysis.inferTypeForExpression(TypeAnalysis.java:815)
        //     at com.strobel.decompiler.ast.TypeAnalysis.inferTypeForExpression(TypeAnalysis.java:782)
        //     at com.strobel.decompiler.ast.TypeAnalysis.inferTypeForExpression(TypeAnalysis.java:778)
        //     at com.strobel.decompiler.ast.TypeAnalysis.doInferTypeForExpression(TypeAnalysis.java:1049)
        //     at com.strobel.decompiler.ast.TypeAnalysis.inferTypeForExpression(TypeAnalysis.java:815)
        //     at com.strobel.decompiler.ast.TypeAnalysis.inferTypeForExpression(TypeAnalysis.java:782)
        //     at com.strobel.decompiler.ast.TypeAnalysis.doInferTypeForExpression(TypeAnalysis.java:892)
        //     at com.strobel.decompiler.ast.TypeAnalysis.inferTypeForExpression(TypeAnalysis.java:815)
        //     at com.strobel.decompiler.ast.TypeAnalysis.runInference(TypeAnalysis.java:684)
        //     at com.strobel.decompiler.ast.TypeAnalysis.invalidateDependentExpressions(TypeAnalysis.java:771)
        //     at com.strobel.decompiler.ast.TypeAnalysis.doInferTypeForExpression(TypeAnalysis.java:1022)
        //     at com.strobel.decompiler.ast.TypeAnalysis.inferTypeForExpression(TypeAnalysis.java:815)
        //     at com.strobel.decompiler.ast.TypeAnalysis.inferTypeForExpression(TypeAnalysis.java:782)
        //     at com.strobel.decompiler.ast.TypeAnalysis.inferTypeForExpression(TypeAnalysis.java:778)
        //     at com.strobel.decompiler.ast.TypeAnalysis.inferCall(TypeAnalysis.java:2483)
        //     at com.strobel.decompiler.ast.TypeAnalysis.doInferTypeForExpression(TypeAnalysis.java:1040)
        //     at com.strobel.decompiler.ast.TypeAnalysis.inferTypeForExpression(TypeAnalysis.java:815)
        //     at com.strobel.decompiler.ast.TypeAnalysis.runInference(TypeAnalysis.java:684)
        //     at com.strobel.decompiler.ast.TypeAnalysis.invalidateDependentExpressions(TypeAnalysis.java:771)
        //     at com.strobel.decompiler.ast.TypeAnalysis.doInferTypeForExpression(TypeAnalysis.java:1022)
        //     at com.strobel.decompiler.ast.TypeAnalysis.inferTypeForExpression(TypeAnalysis.java:815)
        //     at com.strobel.decompiler.ast.TypeAnalysis.inferTypeForExpression(TypeAnalysis.java:782)
        //     at com.strobel.decompiler.ast.TypeAnalysis.inferTypeForExpression(TypeAnalysis.java:778)
        //     at com.strobel.decompiler.ast.TypeAnalysis.doInferTypeForExpression(TypeAnalysis.java:1067)
        //     at com.strobel.decompiler.ast.TypeAnalysis.inferTypeForExpression(TypeAnalysis.java:815)
        //     at com.strobel.decompiler.ast.TypeAnalysis.runInference(TypeAnalysis.java:684)
        //     at com.strobel.decompiler.ast.TypeAnalysis.invalidateDependentExpressions(TypeAnalysis.java:771)
        //     at com.strobel.decompiler.ast.TypeAnalysis.doInferTypeForExpression(TypeAnalysis.java:1022)
        //     at com.strobel.decompiler.ast.TypeAnalysis.inferTypeForExpression(TypeAnalysis.java:815)
        //     at com.strobel.decompiler.ast.TypeAnalysis.inferTypeForExpression(TypeAnalysis.java:782)
        //     at com.strobel.decompiler.ast.TypeAnalysis.inferTypeForExpression(TypeAnalysis.java:778)
        //     at com.strobel.decompiler.ast.TypeAnalysis.doInferTypeForExpression(TypeAnalysis.java:1510)
        //     at com.strobel.decompiler.ast.TypeAnalysis.inferTypeForExpression(TypeAnalysis.java:815)
        //     at com.strobel.decompiler.ast.TypeAnalysis.inferTypeForExpression(TypeAnalysis.java:782)
        //     at com.strobel.decompiler.ast.TypeAnalysis.inferTypeForExpression(TypeAnalysis.java:778)
        //     at com.strobel.decompiler.ast.TypeAnalysis.inferCall(TypeAnalysis.java:2483)
        //     at com.strobel.decompiler.ast.TypeAnalysis.doInferTypeForExpression(TypeAnalysis.java:1040)
        //     at com.strobel.decompiler.ast.TypeAnalysis.inferTypeForExpression(TypeAnalysis.java:815)
        //     at com.strobel.decompiler.ast.TypeAnalysis.inferTypeForExpression(TypeAnalysis.java:782)
        //     at com.strobel.decompiler.ast.TypeAnalysis.doInferTypeForExpression(TypeAnalysis.java:892)
        //     at com.strobel.decompiler.ast.TypeAnalysis.inferTypeForExpression(TypeAnalysis.java:815)
        //     at com.strobel.decompiler.ast.TypeAnalysis.runInference(TypeAnalysis.java:684)
        //     at com.strobel.decompiler.ast.TypeAnalysis.invalidateDependentExpressions(TypeAnalysis.java:771)
        //     at com.strobel.decompiler.ast.TypeAnalysis.doInferTypeForExpression(TypeAnalysis.java:1022)
        //     at com.strobel.decompiler.ast.TypeAnalysis.inferTypeForExpression(TypeAnalysis.java:815)
        //     at com.strobel.decompiler.ast.TypeAnalysis.inferCall(TypeAnalysis.java:2715)
        //     at com.strobel.decompiler.ast.TypeAnalysis.doInferTypeForExpression(TypeAnalysis.java:1040)
        //     at com.strobel.decompiler.ast.TypeAnalysis.inferTypeForExpression(TypeAnalysis.java:815)
        //     at com.strobel.decompiler.ast.TypeAnalysis.inferTypeForExpression(TypeAnalysis.java:782)
        //     at com.strobel.decompiler.ast.TypeAnalysis.doInferTypeForExpression(TypeAnalysis.java:892)
        //     at com.strobel.decompiler.ast.TypeAnalysis.inferTypeForExpression(TypeAnalysis.java:815)
        //     at com.strobel.decompiler.ast.TypeAnalysis.runInference(TypeAnalysis.java:684)
        //     at com.strobel.decompiler.ast.TypeAnalysis.invalidateDependentExpressions(TypeAnalysis.java:771)
        //     at com.strobel.decompiler.ast.TypeAnalysis.doInferTypeForExpression(TypeAnalysis.java:1022)
        //     at com.strobel.decompiler.ast.TypeAnalysis.inferTypeForExpression(TypeAnalysis.java:815)
        //     at com.strobel.decompiler.ast.TypeAnalysis.inferTypeForExpression(TypeAnalysis.java:782)
        //     at com.strobel.decompiler.ast.TypeAnalysis.inferTypeForExpression(TypeAnalysis.java:778)
        //     at com.strobel.decompiler.ast.TypeAnalysis.doInferTypeForExpression(TypeAnalysis.java:1510)
        //     at com.strobel.decompiler.ast.TypeAnalysis.inferTypeForExpression(TypeAnalysis.java:815)
        //     at com.strobel.decompiler.ast.TypeAnalysis.inferTypeForExpression(TypeAnalysis.java:782)
        //     at com.strobel.decompiler.ast.TypeAnalysis.doInferTypeForExpression(TypeAnalysis.java:892)
        //     at com.strobel.decompiler.ast.TypeAnalysis.inferTypeForExpression(TypeAnalysis.java:815)
        //     at com.strobel.decompiler.ast.TypeAnalysis.runInference(TypeAnalysis.java:684)
        //     at com.strobel.decompiler.ast.TypeAnalysis.invalidateDependentExpressions(TypeAnalysis.java:771)
        //     at com.strobel.decompiler.ast.TypeAnalysis.doInferTypeForExpression(TypeAnalysis.java:1022)
        //     at com.strobel.decompiler.ast.TypeAnalysis.inferTypeForExpression(TypeAnalysis.java:815)
        //     at com.strobel.decompiler.ast.TypeAnalysis.inferTypeForExpression(TypeAnalysis.java:782)
        //     at com.strobel.decompiler.ast.TypeAnalysis.inferTypeForExpression(TypeAnalysis.java:778)
        //     at com.strobel.decompiler.ast.TypeAnalysis.doInferTypeForExpression(TypeAnalysis.java:1510)
        //     at com.strobel.decompiler.ast.TypeAnalysis.inferTypeForExpression(TypeAnalysis.java:815)
        //     at com.strobel.decompiler.ast.TypeAnalysis.inferTypeForExpression(TypeAnalysis.java:782)
        //     at com.strobel.decompiler.ast.TypeAnalysis.doInferTypeForExpression(TypeAnalysis.java:892)
        //     at com.strobel.decompiler.ast.TypeAnalysis.inferTypeForExpression(TypeAnalysis.java:815)
        //     at com.strobel.decompiler.ast.TypeAnalysis.runInference(TypeAnalysis.java:684)
        //     at com.strobel.decompiler.ast.TypeAnalysis.invalidateDependentExpressions(TypeAnalysis.java:771)
        //     at com.strobel.decompiler.ast.TypeAnalysis.doInferTypeForExpression(TypeAnalysis.java:1022)
        //     at com.strobel.decompiler.ast.TypeAnalysis.inferTypeForExpression(TypeAnalysis.java:815)
        //     at com.strobel.decompiler.ast.TypeAnalysis.inferTypeForExpression(TypeAnalysis.java:782)
        //     at com.strobel.decompiler.ast.TypeAnalysis.inferTypeForExpression(TypeAnalysis.java:778)
        //     at com.strobel.decompiler.ast.TypeAnalysis.doInferTypeForExpression(TypeAnalysis.java:1049)
        //     at com.strobel.decompiler.ast.TypeAnalysis.inferTypeForExpression(TypeAnalysis.java:815)
        //     at com.strobel.decompiler.ast.TypeAnalysis.inferTypeForExpression(TypeAnalysis.java:782)
        //     at com.strobel.decompiler.ast.TypeAnalysis.doInferTypeForExpression(TypeAnalysis.java:892)
        //     at com.strobel.decompiler.ast.TypeAnalysis.inferTypeForExpression(TypeAnalysis.java:815)
        //     at com.strobel.decompiler.ast.TypeAnalysis.runInference(TypeAnalysis.java:684)
        //     at com.strobel.decompiler.ast.TypeAnalysis.invalidateDependentExpressions(TypeAnalysis.java:771)
        //     at com.strobel.decompiler.ast.TypeAnalysis.doInferTypeForExpression(TypeAnalysis.java:1022)
        //     at com.strobel.decompiler.ast.TypeAnalysis.inferTypeForExpression(TypeAnalysis.java:815)
        //     at com.strobel.decompiler.ast.TypeAnalysis.inferTypeForExpression(TypeAnalysis.java:782)
        //     at com.strobel.decompiler.ast.TypeAnalysis.inferTypeForExpression(TypeAnalysis.java:778)
        //     at com.strobel.decompiler.ast.TypeAnalysis.doInferTypeForExpression(TypeAnalysis.java:1510)
        //     at com.strobel.decompiler.ast.TypeAnalysis.inferTypeForExpression(TypeAnalysis.java:815)
        //     at com.strobel.decompiler.ast.TypeAnalysis.inferCall(TypeAnalysis.java:2715)
        //     at com.strobel.decompiler.ast.TypeAnalysis.doInferTypeForExpression(TypeAnalysis.java:1040)
        //     at com.strobel.decompiler.ast.TypeAnalysis.inferTypeForExpression(TypeAnalysis.java:815)
        //     at com.strobel.decompiler.ast.TypeAnalysis.runInference(TypeAnalysis.java:684)
        //     at com.strobel.decompiler.ast.TypeAnalysis.invalidateDependentExpressions(TypeAnalysis.java:771)
        //     at com.strobel.decompiler.ast.TypeAnalysis.doInferTypeForExpression(TypeAnalysis.java:1022)
        //     at com.strobel.decompiler.ast.TypeAnalysis.inferTypeForExpression(TypeAnalysis.java:815)
        //     at com.strobel.decompiler.ast.TypeAnalysis.inferTypeForExpression(TypeAnalysis.java:782)
        //     at com.strobel.decompiler.ast.TypeAnalysis.inferTypeForExpression(TypeAnalysis.java:778)
        //     at com.strobel.decompiler.ast.TypeAnalysis.doInferTypeForExpression(TypeAnalysis.java:1510)
        //     at com.strobel.decompiler.ast.TypeAnalysis.inferTypeForExpression(TypeAnalysis.java:815)
        //     at com.strobel.decompiler.ast.TypeAnalysis.inferTypeForExpression(TypeAnalysis.java:782)
        //     at com.strobel.decompiler.ast.TypeAnalysis.doInferTypeForExpression(TypeAnalysis.java:892)
        //     at com.strobel.decompiler.ast.TypeAnalysis.inferTypeForExpression(TypeAnalysis.java:815)
        //     at com.strobel.decompiler.ast.TypeAnalysis.runInference(TypeAnalysis.java:684)
        //     at com.strobel.decompiler.ast.TypeAnalysis.invalidateDependentExpressions(TypeAnalysis.java:771)
        //     at com.strobel.decompiler.ast.TypeAnalysis.doInferTypeForExpression(TypeAnalysis.java:1022)
        //     at com.strobel.decompiler.ast.TypeAnalysis.inferTypeForExpression(TypeAnalysis.java:815)
        //     at com.strobel.decompiler.ast.TypeAnalysis.inferTypeForExpression(TypeAnalysis.java:782)
        //     at com.strobel.decompiler.ast.TypeAnalysis.inferTypeForExpression(TypeAnalysis.java:778)
        //     at com.strobel.decompiler.ast.TypeAnalysis.doInferTypeForExpression(TypeAnalysis.java:1049)
        //     at com.strobel.decompiler.ast.TypeAnalysis.inferTypeForExpression(TypeAnalysis.java:815)
        //     at com.strobel.decompiler.ast.TypeAnalysis.runInference(TypeAnalysis.java:684)
        //     at com.strobel.decompiler.ast.TypeAnalysis.runInference(TypeAnalysis.java:667)
        //     at com.strobel.decompiler.ast.TypeAnalysis.inferBinaryExpression(TypeAnalysis.java:2124)
        //     at com.strobel.decompiler.ast.TypeAnalysis.doInferTypeForExpression(TypeAnalysis.java:1545)
        //     at com.strobel.decompiler.ast.TypeAnalysis.inferTypeForExpression(TypeAnalysis.java:815)
        //     at com.strobel.decompiler.ast.TypeAnalysis.runInference(TypeAnalysis.java:684)
        //     at com.strobel.decompiler.ast.TypeAnalysis.invalidateDependentExpressions(TypeAnalysis.java:771)
        //     at com.strobel.decompiler.ast.TypeAnalysis.doInferTypeForExpression(TypeAnalysis.java:1022)
        //     at com.strobel.decompiler.ast.TypeAnalysis.inferTypeForExpression(TypeAnalysis.java:815)
        //     at com.strobel.decompiler.ast.TypeAnalysis.inferTypeForExpression(TypeAnalysis.java:782)
        //     at com.strobel.decompiler.ast.TypeAnalysis.inferTypeForExpression(TypeAnalysis.java:778)
        //     at com.strobel.decompiler.ast.TypeAnalysis.doInferTypeForExpression(TypeAnalysis.java:1510)
        //     at com.strobel.decompiler.ast.TypeAnalysis.inferTypeForExpression(TypeAnalysis.java:815)
        //     at com.strobel.decompiler.ast.TypeAnalysis.inferTypeForExpression(TypeAnalysis.java:782)
        //     at com.strobel.decompiler.ast.TypeAnalysis.inferTypeForExpression(TypeAnalysis.java:778)
        //     at com.strobel.decompiler.ast.TypeAnalysis.doInferTypeForExpression(TypeAnalysis.java:1049)
        //     at com.strobel.decompiler.ast.TypeAnalysis.inferTypeForExpression(TypeAnalysis.java:815)
        //     at com.strobel.decompiler.ast.TypeAnalysis.inferTypeForExpression(TypeAnalysis.java:782)
        //     at com.strobel.decompiler.ast.TypeAnalysis.doInferTypeForExpression(TypeAnalysis.java:892)
        //     at com.strobel.decompiler.ast.TypeAnalysis.inferTypeForExpression(TypeAnalysis.java:815)
        //     at com.strobel.decompiler.ast.TypeAnalysis.runInference(TypeAnalysis.java:684)
        //     at com.strobel.decompiler.ast.TypeAnalysis.invalidateDependentExpressions(TypeAnalysis.java:771)
        //     at com.strobel.decompiler.ast.TypeAnalysis.doInferTypeForExpression(TypeAnalysis.java:1022)
        //     at com.strobel.decompiler.ast.TypeAnalysis.inferTypeForExpression(TypeAnalysis.java:815)
        //     at com.strobel.decompiler.ast.TypeAnalysis.inferTypeForExpression(TypeAnalysis.java:782)
        //     at com.strobel.decompiler.ast.TypeAnalysis.inferTypeForExpression(TypeAnalysis.java:778)
        //     at com.strobel.decompiler.ast.TypeAnalysis.doInferTypeForExpression(TypeAnalysis.java:1049)
        //     at com.strobel.decompiler.ast.TypeAnalysis.inferTypeForExpression(TypeAnalysis.java:815)
        //     at com.strobel.decompiler.ast.TypeAnalysis.inferTypeForExpression(TypeAnalysis.java:782)
        //     at com.strobel.decompiler.ast.TypeAnalysis.doInferTypeForExpression(TypeAnalysis.java:892)
        //     at com.strobel.decompiler.ast.TypeAnalysis.inferTypeForExpression(TypeAnalysis.java:815)
        //     at com.strobel.decompiler.ast.TypeAnalysis.runInference(TypeAnalysis.java:684)
        //     at com.strobel.decompiler.ast.TypeAnalysis.runInference(TypeAnalysis.java:667)
        //     at com.strobel.decompiler.ast.TypeAnalysis.runInference(TypeAnalysis.java:373)
        //     at com.strobel.decompiler.ast.TypeAnalysis.run(TypeAnalysis.java:95)
        //     at com.strobel.decompiler.ast.AstOptimizer.optimize(AstOptimizer.java:109)
        //     at com.strobel.decompiler.ast.AstOptimizer.optimize(AstOptimizer.java:42)
        //     at com.strobel.decompiler.languages.java.ast.AstMethodBodyBuilder.createMethodBody(AstMethodBodyBuilder.java:206)
        //     at com.strobel.decompiler.languages.java.ast.AstMethodBodyBuilder.createMethodBody(AstMethodBodyBuilder.java:93)
        //     at com.strobel.decompiler.languages.java.ast.AstBuilder.createMethodBody(AstBuilder.java:868)
        //     at com.strobel.decompiler.languages.java.ast.AstBuilder.createMethod(AstBuilder.java:761)
        //     at com.strobel.decompiler.languages.java.ast.AstBuilder.addTypeMembers(AstBuilder.java:638)
        //     at com.strobel.decompiler.languages.java.ast.AstBuilder.createTypeCore(AstBuilder.java:605)
        //     at com.strobel.decompiler.languages.java.ast.AstBuilder.createTypeNoCache(AstBuilder.java:195)
        //     at com.strobel.decompiler.languages.java.ast.AstBuilder.createType(AstBuilder.java:162)
        //     at com.strobel.decompiler.languages.java.ast.AstBuilder.addType(AstBuilder.java:137)
        //     at com.strobel.decompiler.languages.java.JavaLanguage.buildAst(JavaLanguage.java:71)
        //     at com.strobel.decompiler.languages.java.JavaLanguage.decompileType(JavaLanguage.java:59)
        //     at com.strobel.decompiler.DecompilerDriver.decompileType(DecompilerDriver.java:333)
        //     at com.strobel.decompiler.DecompilerDriver.decompileJar(DecompilerDriver.java:254)
        //     at com.strobel.decompiler.DecompilerDriver.main(DecompilerDriver.java:129)
        // 
        throw new IllegalStateException("An error occurred while decompiling this method.");
    }
}
