// 
// Decompiled by Procyon v0.6.0
// 

package com.google.android.apps.youtube.embeddedplayer.service.ui.overlays.surveyoverlay.remoteloaded;

import com.google.android.libraries.youtube.innertube.model.media.VideoStreamingData;
import android.net.Uri;
import com.google.android.gms.measurement.internal.UserAttributeParcel;
import com.google.android.gms.measurement.internal.EventParcel;
import com.google.android.gms.measurement.internal.ConditionalUserPropertyParcel;
import com.google.android.gms.measurement.internal.AppMetadata;
import com.google.android.apps.youtube.embeddedplayer.service.ui.subscriptionnotificationbutton.model.SubscriptionNotificationMenuItem;
import com.google.android.apps.youtube.embeddedplayer.service.ui.subscriptionnotificationbutton.remoteloaded.i;
import com.google.android.apps.youtube.embeddedplayer.service.ui.preview.service.e;
import java.util.List;
import com.google.android.apps.youtube.embeddedplayer.service.ui.overlays.surveyoverlay.shared.b;
import com.google.android.libraries.youtube.player.model.PlaybackStartDescriptor;

public final class a implements Runnable
{
    public final boolean a;
    public final Object b;
    public final Object c;
    public final Object d;
    private final int e;
    
    public a(final aafd b, final PlaybackStartDescriptor c, final tdh d, final boolean a, final int e) {
        this.e = e;
        this.b = b;
        this.c = c;
        this.d = d;
        this.a = a;
    }
    
    public a(final absy b, final znz d, final String c, final boolean a, final int e) {
        this.e = e;
        this.b = b;
        this.d = d;
        this.c = c;
        this.a = a;
    }
    
    public a(final atmw b, final vhb d, final boolean a, final atmw c, final int e) {
        this.e = e;
        this.b = b;
        this.d = d;
        this.a = a;
        this.c = c;
    }
    
    public a(final b d, final String b, final List c, final boolean a, final int e) {
        this.e = e;
        this.d = d;
        this.b = b;
        this.c = c;
        this.a = a;
    }
    
    public a(final e d, final String c, final boolean a, final afbh b, final int e, final byte[] array) {
        this.e = e;
        this.d = d;
        this.c = c;
        this.a = a;
        this.b = b;
    }
    
    public a(final i c, final boolean a, final akp d, final SubscriptionNotificationMenuItem b, final int e) {
        this.e = e;
        this.c = c;
        this.a = a;
        this.d = d;
        this.b = b;
    }
    
    public a(final nip c, final AppMetadata d, final boolean a, final ConditionalUserPropertyParcel b, final int e) {
        this.e = e;
        this.c = c;
        this.d = d;
        this.a = a;
        this.b = b;
    }
    
    public a(final nip c, final AppMetadata d, final boolean a, final EventParcel b, final int e) {
        this.e = e;
        this.c = c;
        this.d = d;
        this.a = a;
        this.b = b;
    }
    
    public a(final nip b, final AppMetadata d, final boolean a, final UserAttributeParcel c, final int e) {
        this.e = e;
        this.b = b;
        this.d = d;
        this.a = a;
        this.c = c;
    }
    
    public a(final sjr b, final Uri d, final List c, final boolean a, final int e) {
        this.e = e;
        this.b = b;
        this.d = d;
        this.c = c;
        this.a = a;
    }
    
    public a(final ywj d, final String c, final boolean a, final yyk b, final int e) {
        this.e = e;
        this.d = d;
        this.c = c;
        this.a = a;
        this.b = b;
    }
    
    public a(final ywl d, final zdk c, final yye b, final boolean a, final int e) {
        this.e = e;
        this.d = d;
        this.c = c;
        this.b = b;
        this.a = a;
    }
    
    public a(final zap c, final VideoStreamingData d, final boolean a, final yrr b, final int e) {
        this.e = e;
        this.c = c;
        this.d = d;
        this.a = a;
        this.b = b;
    }
    
    public a(final zuq b, final boolean a, final akp d, final aoph c, final int e) {
        this.e = e;
        this.b = b;
        this.a = a;
        this.d = d;
        this.c = c;
    }
    
    @Override
    public final void run() {
        // 
        // This method could not be decompiled.
        // 
        // Original Bytecode:
        // 
        //     1: getfield        com/google/android/apps/youtube/embeddedplayer/service/ui/overlays/surveyoverlay/remoteloaded/a.e:I
        //     4: istore_1       
        //     5: aconst_null    
        //     6: astore          10
        //     8: aconst_null    
        //     9: astore          8
        //    11: aconst_null    
        //    12: astore          9
        //    14: iconst_1       
        //    15: istore          5
        //    17: iconst_0       
        //    18: istore          6
        //    20: iload_1        
        //    21: tableswitch {
        //                0: 1734
        //                1: 1574
        //                2: 1527
        //                3: 1434
        //                4: 1337
        //                5: 1240
        //                6: 1082
        //                7: 1013
        //                8: 866
        //                9: 411
        //               10: 248
        //               11: 201
        //               12: 155
        //          default: 88
        //        }
        //    88: aload_0        
        //    89: getfield        com/google/android/apps/youtube/embeddedplayer/service/ui/overlays/surveyoverlay/remoteloaded/a.b:Ljava/lang/Object;
        //    92: astore          10
        //    94: aload_0        
        //    95: getfield        com/google/android/apps/youtube/embeddedplayer/service/ui/overlays/surveyoverlay/remoteloaded/a.d:Ljava/lang/Object;
        //    98: astore          9
        //   100: aload_0        
        //   101: getfield        com/google/android/apps/youtube/embeddedplayer/service/ui/overlays/surveyoverlay/remoteloaded/a.c:Ljava/lang/Object;
        //   104: astore          8
        //   106: aload_0        
        //   107: getfield        com/google/android/apps/youtube/embeddedplayer/service/ui/overlays/surveyoverlay/remoteloaded/a.a:Z
        //   110: istore          4
        //   112: aload           10
        //   114: checkcast       Labsy;
        //   117: astore          10
        //   119: aload           10
        //   121: getfield        absy.h:Lajfd;
        //   124: astore          11
        //   126: aload           11
        //   128: ifnull          2186
        //   131: aload           11
        //   133: getfield        ajfd.c:Z
        //   136: ifeq            2186
        //   139: aload           10
        //   141: getfield        absy.f:Ltkq;
        //   144: invokeinterface tkq.o:()Z
        //   149: ifeq            1782
        //   152: goto            2186
        //   155: aload_0        
        //   156: getfield        com/google/android/apps/youtube/embeddedplayer/service/ui/overlays/surveyoverlay/remoteloaded/a.b:Ljava/lang/Object;
        //   159: astore          9
        //   161: aload_0        
        //   162: getfield        com/google/android/apps/youtube/embeddedplayer/service/ui/overlays/surveyoverlay/remoteloaded/a.c:Ljava/lang/Object;
        //   165: astore          10
        //   167: aload_0        
        //   168: getfield        com/google/android/apps/youtube/embeddedplayer/service/ui/overlays/surveyoverlay/remoteloaded/a.d:Ljava/lang/Object;
        //   171: astore          8
        //   173: aload_0        
        //   174: getfield        com/google/android/apps/youtube/embeddedplayer/service/ui/overlays/surveyoverlay/remoteloaded/a.a:Z
        //   177: istore          4
        //   179: aload           10
        //   181: checkcast       Lcom/google/android/libraries/youtube/player/model/PlaybackStartDescriptor;
        //   184: astore          10
        //   186: aload           9
        //   188: checkcast       Laafd;
        //   191: aload           10
        //   193: aload           8
        //   195: iload           4
        //   197: invokevirtual   aafd.a:(Lcom/google/android/libraries/youtube/player/model/PlaybackStartDescriptor;Ltdg;Z)V
        //   200: return         
        //   201: aload_0        
        //   202: getfield        com/google/android/apps/youtube/embeddedplayer/service/ui/overlays/surveyoverlay/remoteloaded/a.b:Ljava/lang/Object;
        //   205: astore          9
        //   207: aload_0        
        //   208: getfield        com/google/android/apps/youtube/embeddedplayer/service/ui/overlays/surveyoverlay/remoteloaded/a.a:Z
        //   211: istore          4
        //   213: aload_0        
        //   214: getfield        com/google/android/apps/youtube/embeddedplayer/service/ui/overlays/surveyoverlay/remoteloaded/a.d:Ljava/lang/Object;
        //   217: astore          10
        //   219: aload_0        
        //   220: getfield        com/google/android/apps/youtube/embeddedplayer/service/ui/overlays/surveyoverlay/remoteloaded/a.c:Ljava/lang/Object;
        //   223: astore          8
        //   225: aload           9
        //   227: checkcast       Lzuq;
        //   230: invokevirtual   zuq.a:()V
        //   233: iload           4
        //   235: ifne            247
        //   238: aload           10
        //   240: aload           8
        //   242: invokeinterface akp.accept:(Ljava/lang/Object;)V
        //   247: return         
        //   248: aload_0        
        //   249: getfield        com/google/android/apps/youtube/embeddedplayer/service/ui/overlays/surveyoverlay/remoteloaded/a.c:Ljava/lang/Object;
        //   252: astore          9
        //   254: aload_0        
        //   255: getfield        com/google/android/apps/youtube/embeddedplayer/service/ui/overlays/surveyoverlay/remoteloaded/a.d:Ljava/lang/Object;
        //   258: astore          10
        //   260: aload_0        
        //   261: getfield        com/google/android/apps/youtube/embeddedplayer/service/ui/overlays/surveyoverlay/remoteloaded/a.a:Z
        //   264: istore          7
        //   266: aload_0        
        //   267: getfield        com/google/android/apps/youtube/embeddedplayer/service/ui/overlays/surveyoverlay/remoteloaded/a.b:Ljava/lang/Object;
        //   270: astore          8
        //   272: aload           9
        //   274: checkcast       Lzap;
        //   277: getfield        zap.c:Lxyj;
        //   280: astore          9
        //   282: iload           7
        //   284: ifeq            391
        //   287: aload           10
        //   289: checkcast       Lcom/google/android/libraries/youtube/innertube/model/media/VideoStreamingData;
        //   292: astore          10
        //   294: aload           10
        //   296: getfield        com/google/android/libraries/youtube/innertube/model/media/VideoStreamingData.q:Ljava/util/List;
        //   299: invokeinterface java/util/List.iterator:()Ljava/util/Iterator;
        //   304: astore          11
        //   306: iload           6
        //   308: istore          4
        //   310: aload           11
        //   312: invokeinterface java/util/Iterator.hasNext:()Z
        //   317: ifeq            341
        //   320: aload           11
        //   322: invokeinterface java/util/Iterator.next:()Ljava/lang/Object;
        //   327: checkcast       Lcom/google/android/libraries/youtube/innertube/model/media/FormatStreamModel;
        //   330: aload           9
        //   332: invokestatic    zap.d:(Lcom/google/android/libraries/youtube/innertube/model/media/FormatStreamModel;Lxyj;)Z
        //   335: ifeq            306
        //   338: iconst_1       
        //   339: istore          4
        //   341: aload           10
        //   343: getfield        com/google/android/libraries/youtube/innertube/model/media/VideoStreamingData.p:Ljava/util/List;
        //   346: invokeinterface java/util/List.iterator:()Ljava/util/Iterator;
        //   351: astore          10
        //   353: aload           10
        //   355: invokeinterface java/util/Iterator.hasNext:()Z
        //   360: ifeq            388
        //   363: aload           10
        //   365: invokeinterface java/util/Iterator.next:()Ljava/lang/Object;
        //   370: checkcast       Lcom/google/android/libraries/youtube/innertube/model/media/FormatStreamModel;
        //   373: aload           9
        //   375: invokestatic    zap.d:(Lcom/google/android/libraries/youtube/innertube/model/media/FormatStreamModel;Lxyj;)Z
        //   378: ifeq            353
        //   381: iload           5
        //   383: istore          4
        //   385: goto            394
        //   388: goto            394
        //   391: iconst_0       
        //   392: istore          4
        //   394: getstatic       zde.a:Lzde;
        //   397: astore          9
        //   399: aload           8
        //   401: iload           7
        //   403: iload           4
        //   405: invokeinterface yrr.l:(ZZ)V
        //   410: return         
        //   411: aload_0        
        //   412: getfield        com/google/android/apps/youtube/embeddedplayer/service/ui/overlays/surveyoverlay/remoteloaded/a.d:Ljava/lang/Object;
        //   415: astore          12
        //   417: aload_0        
        //   418: getfield        com/google/android/apps/youtube/embeddedplayer/service/ui/overlays/surveyoverlay/remoteloaded/a.c:Ljava/lang/Object;
        //   421: astore          9
        //   423: aload_0        
        //   424: getfield        com/google/android/apps/youtube/embeddedplayer/service/ui/overlays/surveyoverlay/remoteloaded/a.b:Ljava/lang/Object;
        //   427: astore          11
        //   429: aload_0        
        //   430: getfield        com/google/android/apps/youtube/embeddedplayer/service/ui/overlays/surveyoverlay/remoteloaded/a.a:Z
        //   433: istore          4
        //   435: aload           11
        //   437: ifnonnull       448
        //   440: getstatic       yrr.a:Lyrr;
        //   443: astore          10
        //   445: goto            458
        //   448: aload           11
        //   450: checkcast       Lyye;
        //   453: getfield        yye.P:Lyrr;
        //   456: astore          10
        //   458: aload           9
        //   460: checkcast       Lzdk;
        //   463: invokevirtual   zdk.w:()Z
        //   466: istore          5
        //   468: iload           5
        //   470: ifeq            492
        //   473: iload           4
        //   475: ifne            504
        //   478: aload           12
        //   480: checkcast       Lywl;
        //   483: getfield        ywl.a:Lywt;
        //   486: invokevirtual   ywt.h:()V
        //   489: goto            497
        //   492: iload           4
        //   494: ifne            504
        //   497: aload           9
        //   499: astore          8
        //   501: goto            620
        //   504: aload           12
        //   506: checkcast       Lywl;
        //   509: getfield        ywl.c:Lqw;
        //   512: iconst_0       
        //   513: invokevirtual   qw.e:(Z)V
        //   516: aload           11
        //   518: ifnull          589
        //   521: new             Lzdi;
        //   524: astore          13
        //   526: aload           13
        //   528: aload           9
        //   530: checkcast       Lzdk;
        //   533: invokespecial   zdi.<init>:(Lzdk;)V
        //   536: aload           13
        //   538: ldc             "smfc.d"
        //   540: invokevirtual   zdi.c:(Ljava/lang/String;)V
        //   543: new             Lywr;
        //   546: astore          8
        //   548: aload           8
        //   550: invokespecial   ywr.<init>:()V
        //   553: aload           13
        //   555: aload           8
        //   557: invokevirtual   zdi.b:(Ljava/lang/Object;)V
        //   560: aload           13
        //   562: invokevirtual   zdi.a:()Lzdk;
        //   565: astore          8
        //   567: aload           12
        //   569: checkcast       Lywl;
        //   572: getfield        ywl.a:Lywt;
        //   575: aload           11
        //   577: checkcast       Lyye;
        //   580: getfield        yye.P:Lyrr;
        //   583: invokevirtual   ywt.f:(Lyrr;)V
        //   586: goto            609
        //   589: aload           12
        //   591: checkcast       Lywl;
        //   594: getfield        ywl.b:Lzeo;
        //   597: aload           9
        //   599: checkcast       Lzdk;
        //   602: invokevirtual   zeo.bi:(Lzdk;)V
        //   605: aload           9
        //   607: astore          8
        //   609: aload           10
        //   611: ldc             "smfc"
        //   613: ldc             "d"
        //   615: invokeinterface yrr.k:(Ljava/lang/String;Ljava/lang/String;)V
        //   620: aload           11
        //   622: ifnonnull       689
        //   625: ldc             "Scripted MediaFetch error with no playback: %s:%s"
        //   627: iconst_2       
        //   628: anewarray       Ljava/lang/Object;
        //   631: dup            
        //   632: iconst_0       
        //   633: aload           9
        //   635: checkcast       Lzdk;
        //   638: invokevirtual   zdk.m:()Ljava/lang/String;
        //   641: aastore        
        //   642: dup            
        //   643: iconst_1       
        //   644: aload           9
        //   646: checkcast       Lzdk;
        //   649: invokevirtual   zdk.o:()Ljava/lang/String;
        //   652: invokestatic    twd.i:(Ljava/lang/String;)Ljava/lang/String;
        //   655: aastore        
        //   656: invokestatic    java/lang/String.format:(Ljava/lang/String;[Ljava/lang/Object;)Ljava/lang/String;
        //   659: astore          9
        //   661: getstatic       zng.b:Lzng;
        //   664: getstatic       znf.f:Lznf;
        //   667: aload           9
        //   669: invokestatic    znh.b:(Lzng;Lznf;Ljava/lang/String;)V
        //   672: getstatic       zde.i:Lzde;
        //   675: ldc             "%s"
        //   677: iconst_1       
        //   678: anewarray       Ljava/lang/Object;
        //   681: dup            
        //   682: iconst_0       
        //   683: aload           9
        //   685: aastore        
        //   686: invokestatic    zdf.b:(Lzde;Ljava/lang/String;[Ljava/lang/Object;)V
        //   689: aload           12
        //   691: checkcast       Lywl;
        //   694: getfield        ywl.d:Lxsj;
        //   697: astore          10
        //   699: aload           11
        //   701: ifnonnull       712
        //   704: getstatic       yrn.d:Lyrn;
        //   707: astore          9
        //   709: goto            722
        //   712: aload           11
        //   714: checkcast       Lyye;
        //   717: getfield        yye.b:Lyrn;
        //   720: astore          9
        //   722: aload           10
        //   724: getfield        xsj.a:Ljava/lang/Object;
        //   727: checkcast       Lytd;
        //   730: aload           9
        //   732: aload           8
        //   734: checkcast       Lzdk;
        //   737: invokevirtual   ytd.q:(Lyrn;Lzdk;)V
        //   740: return         
        //   741: astore          9
        //   743: aload           11
        //   745: ifnonnull       756
        //   748: getstatic       yrr.a:Lyrr;
        //   751: astore          8
        //   753: goto            766
        //   756: aload           11
        //   758: checkcast       Lyye;
        //   761: getfield        yye.P:Lyrr;
        //   764: astore          8
        //   766: getstatic       zng.b:Lzng;
        //   769: getstatic       znf.f:Lznf;
        //   772: ldc_w           "ScriptedMediaFetchControllerBridge error"
        //   775: aload           9
        //   777: invokestatic    znh.c:(Lzng;Lznf;Ljava/lang/String;Ljava/lang/Throwable;)V
        //   780: aload           11
        //   782: ifnonnull       790
        //   785: lconst_0       
        //   786: lstore_2       
        //   787: goto            804
        //   790: aload           11
        //   792: checkcast       Lyye;
        //   795: getfield        yye.e:Lyyd;
        //   798: invokeinterface yyd.e:()J
        //   803: lstore_2       
        //   804: new             Lzdi;
        //   807: astore          10
        //   809: aload           10
        //   811: ldc_w           "player.exception"
        //   814: lload_2        
        //   815: invokespecial   zdi.<init>:(Ljava/lang/String;J)V
        //   818: aload           10
        //   820: getstatic       zdj.i:Lzdj;
        //   823: putfield        zdi.a:Lzdj;
        //   826: aload           10
        //   828: aload           9
        //   830: putfield        zdi.c:Ljava/lang/Throwable;
        //   833: aload           10
        //   835: ldc_w           "c.main_thread_post"
        //   838: putfield        zdi.b:Ljava/lang/String;
        //   841: aload           8
        //   843: aload           10
        //   845: invokevirtual   zdi.a:()Lzdk;
        //   848: invokeinterface yrr.j:(Lzdk;)V
        //   853: return         
        //   854: astore          8
        //   856: getstatic       zde.i:Lzde;
        //   859: ldc_w           "Error when reporting error"
        //   862: invokestatic    zdf.a:(Lzde;Ljava/lang/Object;)V
        //   865: return         
        //   866: aload_0        
        //   867: getfield        com/google/android/apps/youtube/embeddedplayer/service/ui/overlays/surveyoverlay/remoteloaded/a.d:Ljava/lang/Object;
        //   870: astore          8
        //   872: aload_0        
        //   873: getfield        com/google/android/apps/youtube/embeddedplayer/service/ui/overlays/surveyoverlay/remoteloaded/a.c:Ljava/lang/Object;
        //   876: astore          9
        //   878: aload_0        
        //   879: getfield        com/google/android/apps/youtube/embeddedplayer/service/ui/overlays/surveyoverlay/remoteloaded/a.a:Z
        //   882: istore          4
        //   884: aload_0        
        //   885: getfield        com/google/android/apps/youtube/embeddedplayer/service/ui/overlays/surveyoverlay/remoteloaded/a.b:Ljava/lang/Object;
        //   888: astore          11
        //   890: aload           8
        //   892: checkcast       Lywj;
        //   895: getfield        ywj.d:Lyye;
        //   898: astore          10
        //   900: aload           11
        //   902: checkcast       Lyyk;
        //   905: astore          11
        //   907: aload           10
        //   909: aload           9
        //   911: checkcast       Ljava/lang/String;
        //   914: iload           4
        //   916: aload           11
        //   918: iconst_3       
        //   919: invokevirtual   yye.g:(Ljava/lang/String;ZLyyk;I)V
        //   922: return         
        //   923: astore          9
        //   925: aload           8
        //   927: checkcast       Lywj;
        //   930: getfield        ywj.d:Lyye;
        //   933: astore          11
        //   935: aload           11
        //   937: getfield        yye.P:Lyrr;
        //   940: astore          8
        //   942: new             Lzdi;
        //   945: astore          10
        //   947: aload           10
        //   949: ldc_w           "player.exception"
        //   952: aload           11
        //   954: getfield        yye.e:Lyyd;
        //   957: invokeinterface yyd.e:()J
        //   962: invokespecial   zdi.<init>:(Ljava/lang/String;J)V
        //   965: aload           10
        //   967: getstatic       zdj.i:Lzdj;
        //   970: putfield        zdi.a:Lzdj;
        //   973: aload           10
        //   975: aload           9
        //   977: putfield        zdi.c:Ljava/lang/Throwable;
        //   980: aload           10
        //   982: ldc_w           "c.main_thread_post"
        //   985: putfield        zdi.b:Ljava/lang/String;
        //   988: aload           8
        //   990: aload           10
        //   992: invokevirtual   zdi.a:()Lzdk;
        //   995: invokeinterface yrr.j:(Lzdk;)V
        //  1000: return         
        //  1001: astore          8
        //  1003: getstatic       zde.i:Lzde;
        //  1006: ldc_w           "Error when reporting error"
        //  1009: invokestatic    zdf.a:(Lzde;Ljava/lang/Object;)V
        //  1012: return         
        //  1013: aload_0        
        //  1014: getfield        com/google/android/apps/youtube/embeddedplayer/service/ui/overlays/surveyoverlay/remoteloaded/a.b:Ljava/lang/Object;
        //  1017: astore          10
        //  1019: aload_0        
        //  1020: getfield        com/google/android/apps/youtube/embeddedplayer/service/ui/overlays/surveyoverlay/remoteloaded/a.d:Ljava/lang/Object;
        //  1023: astore          8
        //  1025: aload_0        
        //  1026: getfield        com/google/android/apps/youtube/embeddedplayer/service/ui/overlays/surveyoverlay/remoteloaded/a.a:Z
        //  1029: istore          4
        //  1031: aload_0        
        //  1032: getfield        com/google/android/apps/youtube/embeddedplayer/service/ui/overlays/surveyoverlay/remoteloaded/a.c:Ljava/lang/Object;
        //  1035: astore          9
        //  1037: aload           10
        //  1039: ifnull          1066
        //  1042: aload           10
        //  1044: checkcast       Latmw;
        //  1047: astore          10
        //  1049: aload           10
        //  1051: aload           8
        //  1053: invokevirtual   atmw.tt:(Ljava/lang/Object;)V
        //  1056: iload           4
        //  1058: ifeq            1066
        //  1061: aload           10
        //  1063: invokevirtual   atmw.tw:()V
        //  1066: aload           9
        //  1068: ifnull          1081
        //  1071: aload           9
        //  1073: checkcast       Latmw;
        //  1076: aload           8
        //  1078: invokevirtual   atmw.tt:(Ljava/lang/Object;)V
        //  1081: return         
        //  1082: aload_0        
        //  1083: getfield        com/google/android/apps/youtube/embeddedplayer/service/ui/overlays/surveyoverlay/remoteloaded/a.d:Ljava/lang/Object;
        //  1086: invokestatic    java/lang/String.valueOf:(Ljava/lang/Object;)Ljava/lang/String;
        //  1089: pop            
        //  1090: aload_0        
        //  1091: getfield        com/google/android/apps/youtube/embeddedplayer/service/ui/overlays/surveyoverlay/remoteloaded/a.b:Ljava/lang/Object;
        //  1094: astore          9
        //  1096: aload_0        
        //  1097: getfield        com/google/android/apps/youtube/embeddedplayer/service/ui/overlays/surveyoverlay/remoteloaded/a.d:Ljava/lang/Object;
        //  1100: astore          10
        //  1102: aload_0        
        //  1103: getfield        com/google/android/apps/youtube/embeddedplayer/service/ui/overlays/surveyoverlay/remoteloaded/a.c:Ljava/lang/Object;
        //  1106: astore          8
        //  1108: aload_0        
        //  1109: getfield        com/google/android/apps/youtube/embeddedplayer/service/ui/overlays/surveyoverlay/remoteloaded/a.a:Z
        //  1112: istore          4
        //  1114: aload           10
        //  1116: checkcast       Landroid/net/Uri;
        //  1119: astore          10
        //  1121: aload           9
        //  1123: checkcast       Lsjr;
        //  1126: aload           10
        //  1128: aload           8
        //  1130: iload           4
        //  1132: invokevirtual   sjr.h:(Landroid/net/Uri;Ljava/util/List;Z)Lzpb;
        //  1135: astore          8
        //  1137: aload_0        
        //  1138: getfield        com/google/android/apps/youtube/embeddedplayer/service/ui/overlays/surveyoverlay/remoteloaded/a.b:Ljava/lang/Object;
        //  1141: checkcast       Lsjr;
        //  1144: getfield        sjr.e:Lvim;
        //  1147: astore          9
        //  1149: aload           9
        //  1151: ifnull          1178
        //  1154: aload           8
        //  1156: aload           9
        //  1158: invokeinterface vim.b:()Z
        //  1163: putfield        zpb.d:Z
        //  1166: aload           8
        //  1168: aload           9
        //  1170: invokeinterface vim.a:()J
        //  1175: putfield        zpb.e:J
        //  1178: aload_0        
        //  1179: getfield        com/google/android/apps/youtube/embeddedplayer/service/ui/overlays/surveyoverlay/remoteloaded/a.b:Ljava/lang/Object;
        //  1182: checkcast       Lsjr;
        //  1185: getfield        sjr.d:Lsjp;
        //  1188: astore          10
        //  1190: getstatic       zrh.a:Ldbh;
        //  1193: astore          9
        //  1195: aload           10
        //  1197: getfield        sjp.a:Ljava/util/regex/Pattern;
        //  1200: aload           8
        //  1202: getfield        zpb.b:Landroid/net/Uri;
        //  1205: invokevirtual   android/net/Uri.toString:()Ljava/lang/String;
        //  1208: invokevirtual   java/util/regex/Pattern.matcher:(Ljava/lang/CharSequence;)Ljava/util/regex/Matcher;
        //  1211: invokevirtual   java/util/regex/Matcher.find:()Z
        //  1214: ifne            1227
        //  1217: aload           10
        //  1219: aload           8
        //  1221: aload           9
        //  1223: invokevirtual   sjp.b:(Lzpb;Ldbh;)V
        //  1226: return         
        //  1227: aload           10
        //  1229: getfield        sjp.b:Laajb;
        //  1232: aload           8
        //  1234: aload           9
        //  1236: invokevirtual   aajb.j:(Lzpb;Ldbh;)V
        //  1239: return         
        //  1240: aload_0        
        //  1241: getfield        com/google/android/apps/youtube/embeddedplayer/service/ui/overlays/surveyoverlay/remoteloaded/a.c:Ljava/lang/Object;
        //  1244: astore          8
        //  1246: aload           8
        //  1248: checkcast       Lnip;
        //  1251: astore          11
        //  1253: aload           11
        //  1255: getfield        nip.c:Lngf;
        //  1258: astore          10
        //  1260: aload           10
        //  1262: ifnonnull       1283
        //  1265: aload           8
        //  1267: checkcast       Lnho;
        //  1270: invokevirtual   nho.aA:()Lngn;
        //  1273: getfield        ngn.c:Lngl;
        //  1276: ldc_w           "Discarding data. Failed to send conditional user property to service"
        //  1279: invokevirtual   ngl.a:(Ljava/lang/String;)V
        //  1282: return         
        //  1283: aload_0        
        //  1284: getfield        com/google/android/apps/youtube/embeddedplayer/service/ui/overlays/surveyoverlay/remoteloaded/a.a:Z
        //  1287: ifeq            1297
        //  1290: aload           9
        //  1292: astore          8
        //  1294: goto            1303
        //  1297: aload_0        
        //  1298: getfield        com/google/android/apps/youtube/embeddedplayer/service/ui/overlays/surveyoverlay/remoteloaded/a.b:Ljava/lang/Object;
        //  1301: astore          8
        //  1303: aload_0        
        //  1304: getfield        com/google/android/apps/youtube/embeddedplayer/service/ui/overlays/surveyoverlay/remoteloaded/a.d:Ljava/lang/Object;
        //  1307: checkcast       Lcom/google/android/gms/measurement/internal/AppMetadata;
        //  1310: astore          9
        //  1312: aload           11
        //  1314: aload           10
        //  1316: aload           8
        //  1318: checkcast       Lcom/google/android/gms/common/internal/safeparcel/AbstractSafeParcelable;
        //  1321: aload           9
        //  1323: invokevirtual   nip.v:(Lngf;Lcom/google/android/gms/common/internal/safeparcel/AbstractSafeParcelable;Lcom/google/android/gms/measurement/internal/AppMetadata;)V
        //  1326: aload_0        
        //  1327: getfield        com/google/android/apps/youtube/embeddedplayer/service/ui/overlays/surveyoverlay/remoteloaded/a.c:Ljava/lang/Object;
        //  1330: checkcast       Lnip;
        //  1333: invokevirtual   nip.t:()V
        //  1336: return         
        //  1337: aload_0        
        //  1338: getfield        com/google/android/apps/youtube/embeddedplayer/service/ui/overlays/surveyoverlay/remoteloaded/a.c:Ljava/lang/Object;
        //  1341: astore          8
        //  1343: aload           8
        //  1345: checkcast       Lnip;
        //  1348: astore          11
        //  1350: aload           11
        //  1352: getfield        nip.c:Lngf;
        //  1355: astore          9
        //  1357: aload           9
        //  1359: ifnonnull       1380
        //  1362: aload           8
        //  1364: checkcast       Lnho;
        //  1367: invokevirtual   nho.aA:()Lngn;
        //  1370: getfield        ngn.c:Lngl;
        //  1373: ldc_w           "Discarding data. Failed to send event to service"
        //  1376: invokevirtual   ngl.a:(Ljava/lang/String;)V
        //  1379: return         
        //  1380: aload_0        
        //  1381: getfield        com/google/android/apps/youtube/embeddedplayer/service/ui/overlays/surveyoverlay/remoteloaded/a.a:Z
        //  1384: ifeq            1394
        //  1387: aload           10
        //  1389: astore          8
        //  1391: goto            1400
        //  1394: aload_0        
        //  1395: getfield        com/google/android/apps/youtube/embeddedplayer/service/ui/overlays/surveyoverlay/remoteloaded/a.b:Ljava/lang/Object;
        //  1398: astore          8
        //  1400: aload_0        
        //  1401: getfield        com/google/android/apps/youtube/embeddedplayer/service/ui/overlays/surveyoverlay/remoteloaded/a.d:Ljava/lang/Object;
        //  1404: checkcast       Lcom/google/android/gms/measurement/internal/AppMetadata;
        //  1407: astore          10
        //  1409: aload           11
        //  1411: aload           9
        //  1413: aload           8
        //  1415: checkcast       Lcom/google/android/gms/common/internal/safeparcel/AbstractSafeParcelable;
        //  1418: aload           10
        //  1420: invokevirtual   nip.v:(Lngf;Lcom/google/android/gms/common/internal/safeparcel/AbstractSafeParcelable;Lcom/google/android/gms/measurement/internal/AppMetadata;)V
        //  1423: aload_0        
        //  1424: getfield        com/google/android/apps/youtube/embeddedplayer/service/ui/overlays/surveyoverlay/remoteloaded/a.c:Ljava/lang/Object;
        //  1427: checkcast       Lnip;
        //  1430: invokevirtual   nip.t:()V
        //  1433: return         
        //  1434: aload_0        
        //  1435: getfield        com/google/android/apps/youtube/embeddedplayer/service/ui/overlays/surveyoverlay/remoteloaded/a.b:Ljava/lang/Object;
        //  1438: astore          11
        //  1440: aload           11
        //  1442: checkcast       Lnip;
        //  1445: astore          9
        //  1447: aload           9
        //  1449: getfield        nip.c:Lngf;
        //  1452: astore          10
        //  1454: aload           10
        //  1456: ifnonnull       1477
        //  1459: aload           11
        //  1461: checkcast       Lnho;
        //  1464: invokevirtual   nho.aA:()Lngn;
        //  1467: getfield        ngn.c:Lngl;
        //  1470: ldc_w           "Discarding data. Failed to set user property"
        //  1473: invokevirtual   ngl.a:(Ljava/lang/String;)V
        //  1476: return         
        //  1477: aload_0        
        //  1478: getfield        com/google/android/apps/youtube/embeddedplayer/service/ui/overlays/surveyoverlay/remoteloaded/a.a:Z
        //  1481: ifeq            1487
        //  1484: goto            1493
        //  1487: aload_0        
        //  1488: getfield        com/google/android/apps/youtube/embeddedplayer/service/ui/overlays/surveyoverlay/remoteloaded/a.c:Ljava/lang/Object;
        //  1491: astore          8
        //  1493: aload_0        
        //  1494: getfield        com/google/android/apps/youtube/embeddedplayer/service/ui/overlays/surveyoverlay/remoteloaded/a.d:Ljava/lang/Object;
        //  1497: checkcast       Lcom/google/android/gms/measurement/internal/AppMetadata;
        //  1500: astore          11
        //  1502: aload           9
        //  1504: aload           10
        //  1506: aload           8
        //  1508: checkcast       Lcom/google/android/gms/common/internal/safeparcel/AbstractSafeParcelable;
        //  1511: aload           11
        //  1513: invokevirtual   nip.v:(Lngf;Lcom/google/android/gms/common/internal/safeparcel/AbstractSafeParcelable;Lcom/google/android/gms/measurement/internal/AppMetadata;)V
        //  1516: aload_0        
        //  1517: getfield        com/google/android/apps/youtube/embeddedplayer/service/ui/overlays/surveyoverlay/remoteloaded/a.b:Ljava/lang/Object;
        //  1520: checkcast       Lnip;
        //  1523: invokevirtual   nip.t:()V
        //  1526: return         
        //  1527: aload_0        
        //  1528: getfield        com/google/android/apps/youtube/embeddedplayer/service/ui/overlays/surveyoverlay/remoteloaded/a.c:Ljava/lang/Object;
        //  1531: astore          9
        //  1533: aload_0        
        //  1534: getfield        com/google/android/apps/youtube/embeddedplayer/service/ui/overlays/surveyoverlay/remoteloaded/a.a:Z
        //  1537: istore          4
        //  1539: aload_0        
        //  1540: getfield        com/google/android/apps/youtube/embeddedplayer/service/ui/overlays/surveyoverlay/remoteloaded/a.d:Ljava/lang/Object;
        //  1543: astore          8
        //  1545: aload_0        
        //  1546: getfield        com/google/android/apps/youtube/embeddedplayer/service/ui/overlays/surveyoverlay/remoteloaded/a.b:Ljava/lang/Object;
        //  1549: astore          10
        //  1551: aload           9
        //  1553: checkcast       Lcom/google/android/apps/youtube/embeddedplayer/service/ui/subscriptionnotificationbutton/remoteloaded/i;
        //  1556: invokevirtual   com/google/android/apps/youtube/embeddedplayer/service/ui/subscriptionnotificationbutton/remoteloaded/i.b:()V
        //  1559: iload           4
        //  1561: ifne            1573
        //  1564: aload           8
        //  1566: aload           10
        //  1568: invokeinterface akp.accept:(Ljava/lang/Object;)V
        //  1573: return         
        //  1574: aload_0        
        //  1575: getfield        com/google/android/apps/youtube/embeddedplayer/service/ui/overlays/surveyoverlay/remoteloaded/a.d:Ljava/lang/Object;
        //  1578: astore          8
        //  1580: aload_0        
        //  1581: getfield        com/google/android/apps/youtube/embeddedplayer/service/ui/overlays/surveyoverlay/remoteloaded/a.c:Ljava/lang/Object;
        //  1584: astore          9
        //  1586: aload_0        
        //  1587: getfield        com/google/android/apps/youtube/embeddedplayer/service/ui/overlays/surveyoverlay/remoteloaded/a.a:Z
        //  1590: istore          4
        //  1592: aload_0        
        //  1593: getfield        com/google/android/apps/youtube/embeddedplayer/service/ui/overlays/surveyoverlay/remoteloaded/a.b:Ljava/lang/Object;
        //  1596: astore          11
        //  1598: aload           8
        //  1600: checkcast       Lcom/google/android/apps/youtube/embeddedplayer/service/ui/preview/service/e;
        //  1603: astore          10
        //  1605: aload           10
        //  1607: getfield        com/google/android/apps/youtube/embeddedplayer/service/ui/preview/service/e.d:Ljava/lang/Object;
        //  1610: astore          8
        //  1612: aload           8
        //  1614: ifnull          1652
        //  1617: aload           8
        //  1619: invokeinterface com/google/common/util/concurrent/ListenableFuture.isCancelled:()Z
        //  1624: ifne            1652
        //  1627: aload           10
        //  1629: getfield        com/google/android/apps/youtube/embeddedplayer/service/ui/preview/service/e.d:Ljava/lang/Object;
        //  1632: invokeinterface com/google/common/util/concurrent/ListenableFuture.isDone:()Z
        //  1637: ifne            1652
        //  1640: aload           10
        //  1642: getfield        com/google/android/apps/youtube/embeddedplayer/service/ui/preview/service/e.d:Ljava/lang/Object;
        //  1645: iconst_0       
        //  1646: invokeinterface com/google/common/util/concurrent/ListenableFuture.cancel:(Z)Z
        //  1651: pop            
        //  1652: iload           4
        //  1654: ifeq            1667
        //  1657: aload           10
        //  1659: getfield        com/google/android/apps/youtube/embeddedplayer/service/ui/preview/service/e.f:Ljava/lang/Object;
        //  1662: astore          8
        //  1664: goto            1674
        //  1667: aload           10
        //  1669: getfield        com/google/android/apps/youtube/embeddedplayer/service/ui/preview/service/e.a:Ljava/lang/Object;
        //  1672: astore          8
        //  1674: aload           11
        //  1676: checkcast       Lafbh;
        //  1679: astore          11
        //  1681: aload           10
        //  1683: aload           8
        //  1685: aload           9
        //  1687: checkcast       Ljava/lang/String;
        //  1690: aload           11
        //  1692: invokeinterface adht.a:(Ljava/lang/String;Lafbh;)Lcom/google/common/util/concurrent/ListenableFuture;
        //  1697: putfield        com/google/android/apps/youtube/embeddedplayer/service/ui/preview/service/e.d:Ljava/lang/Object;
        //  1700: aload           10
        //  1702: getfield        com/google/android/apps/youtube/embeddedplayer/service/ui/preview/service/e.d:Ljava/lang/Object;
        //  1705: aload           10
        //  1707: getfield        com/google/android/apps/youtube/embeddedplayer/service/ui/preview/service/e.e:Ljava/lang/Object;
        //  1710: new             Ljea;
        //  1713: dup            
        //  1714: iconst_3       
        //  1715: invokespecial   jea.<init>:(I)V
        //  1718: new             Lhzj;
        //  1721: dup            
        //  1722: aload           10
        //  1724: bipush          14
        //  1726: aconst_null    
        //  1727: invokespecial   hzj.<init>:(Lcom/google/android/apps/youtube/embeddedplayer/service/ui/preview/service/e;I[B)V
        //  1730: invokestatic    tfx.k:(Lcom/google/common/util/concurrent/ListenableFuture;Ljava/util/concurrent/Executor;Ltfv;Ltfw;)V
        //  1733: return         
        //  1734: aload_0        
        //  1735: getfield        com/google/android/apps/youtube/embeddedplayer/service/ui/overlays/surveyoverlay/remoteloaded/a.d:Ljava/lang/Object;
        //  1738: astore          10
        //  1740: aload_0        
        //  1741: getfield        com/google/android/apps/youtube/embeddedplayer/service/ui/overlays/surveyoverlay/remoteloaded/a.b:Ljava/lang/Object;
        //  1744: astore          9
        //  1746: aload_0        
        //  1747: getfield        com/google/android/apps/youtube/embeddedplayer/service/ui/overlays/surveyoverlay/remoteloaded/a.c:Ljava/lang/Object;
        //  1750: astore          8
        //  1752: aload_0        
        //  1753: getfield        com/google/android/apps/youtube/embeddedplayer/service/ui/overlays/surveyoverlay/remoteloaded/a.a:Z
        //  1756: istore          4
        //  1758: aload           10
        //  1760: checkcast       Lcom/google/android/apps/youtube/embeddedplayer/service/ui/overlays/surveyoverlay/shared/b;
        //  1763: getfield        com/google/android/apps/youtube/embeddedplayer/service/ui/overlays/surveyoverlay/shared/b.a:Lsks;
        //  1766: aload           9
        //  1768: checkcast       Ljava/lang/String;
        //  1771: aload           8
        //  1773: iload           4
        //  1775: aconst_null    
        //  1776: invokeinterface sks.o:(Ljava/lang/String;Ljava/util/List;ZLaoqv;)V
        //  1781: return         
        //  1782: aload           10
        //  1784: ldc_w           "e"
        //  1787: invokevirtual   absy.a:(Ljava/lang/String;)Ljava/lang/String;
        //  1790: astore          13
        //  1792: aload           13
        //  1794: ifnonnull       1798
        //  1797: return         
        //  1798: getstatic       ahxt.a:Lahxt;
        //  1801: invokevirtual   ahcz.createBuilder:()Lahcr;
        //  1804: astore          11
        //  1806: getstatic       ahxs.a:Lahxs;
        //  1809: invokevirtual   ahcz.createBuilder:()Lahcr;
        //  1812: astore          12
        //  1814: aload           10
        //  1816: getfield        absy.d:Ljava/lang/String;
        //  1819: astore          14
        //  1821: aload           12
        //  1823: invokevirtual   ahcr.copyOnWrite:()V
        //  1826: aload           12
        //  1828: getfield        ahcr.instance:Lahcz;
        //  1831: checkcast       Lahxs;
        //  1834: astore          15
        //  1836: aload           15
        //  1838: aload           15
        //  1840: getfield        ahxs.b:I
        //  1843: iconst_2       
        //  1844: ior            
        //  1845: putfield        ahxs.b:I
        //  1848: aload           15
        //  1850: aload           14
        //  1852: putfield        ahxs.d:Ljava/lang/String;
        //  1855: aload           12
        //  1857: invokevirtual   ahcr.copyOnWrite:()V
        //  1860: aload           12
        //  1862: getfield        ahcr.instance:Lahcz;
        //  1865: checkcast       Lahxs;
        //  1868: astore          14
        //  1870: aload           14
        //  1872: aload           14
        //  1874: getfield        ahxs.b:I
        //  1877: iconst_1       
        //  1878: ior            
        //  1879: putfield        ahxs.b:I
        //  1882: aload           14
        //  1884: aload           13
        //  1886: putfield        ahxs.c:Ljava/lang/String;
        //  1889: aload           11
        //  1891: invokevirtual   ahcr.copyOnWrite:()V
        //  1894: aload           11
        //  1896: getfield        ahcr.instance:Lahcz;
        //  1899: checkcast       Lahxt;
        //  1902: astore          13
        //  1904: aload           12
        //  1906: invokevirtual   ahcr.build:()Lahcz;
        //  1909: checkcast       Lahxs;
        //  1912: astore          12
        //  1914: aload           12
        //  1916: invokevirtual   java/lang/Object.getClass:()Ljava/lang/Class;
        //  1919: pop            
        //  1920: aload           13
        //  1922: aload           12
        //  1924: putfield        ahxt.c:Ljava/lang/Object;
        //  1927: aload           13
        //  1929: iconst_1       
        //  1930: putfield        ahxt.b:I
        //  1933: aload           11
        //  1935: invokevirtual   ahcr.build:()Lahcz;
        //  1938: checkcast       Lahxt;
        //  1941: astore          12
        //  1943: aload           10
        //  1945: getfield        absy.g:Lzmd;
        //  1948: astore          10
        //  1950: getstatic       lrk.a:Llrk;
        //  1953: invokevirtual   ahcz.createBuilder:()Lahcr;
        //  1956: astore          11
        //  1958: aload           12
        //  1960: invokevirtual   ahbc.toByteString:()Lahbt;
        //  1963: astore          13
        //  1965: aload           11
        //  1967: invokevirtual   ahcr.copyOnWrite:()V
        //  1970: aload           11
        //  1972: getfield        ahcr.instance:Lahcz;
        //  1975: checkcast       Llrk;
        //  1978: astore          12
        //  1980: aload           12
        //  1982: aload           12
        //  1984: getfield        lrk.b:I
        //  1987: iconst_4       
        //  1988: ior            
        //  1989: putfield        lrk.b:I
        //  1992: aload           12
        //  1994: aload           13
        //  1996: putfield        lrk.e:Lahbt;
        //  1999: aload           11
        //  2001: invokevirtual   ahcr.copyOnWrite:()V
        //  2004: aload           11
        //  2006: getfield        ahcr.instance:Lahcz;
        //  2009: checkcast       Llrk;
        //  2012: astore          12
        //  2014: aload           12
        //  2016: iconst_2       
        //  2017: aload           12
        //  2019: getfield        lrk.b:I
        //  2022: ior            
        //  2023: putfield        lrk.b:I
        //  2026: aload           12
        //  2028: ldc_w           "attestation"
        //  2031: putfield        lrk.d:Ljava/lang/String;
        //  2034: aload           9
        //  2036: invokeinterface znz.d:()Ljava/lang/String;
        //  2041: astore          12
        //  2043: aload           11
        //  2045: invokevirtual   ahcr.copyOnWrite:()V
        //  2048: aload           11
        //  2050: getfield        ahcr.instance:Lahcz;
        //  2053: checkcast       Llrk;
        //  2056: astore          9
        //  2058: aload           9
        //  2060: aload           9
        //  2062: getfield        lrk.b:I
        //  2065: bipush          16
        //  2067: ior            
        //  2068: putfield        lrk.b:I
        //  2071: aload           9
        //  2073: aload           12
        //  2075: putfield        lrk.g:Ljava/lang/String;
        //  2078: aload           8
        //  2080: invokestatic    android/text/TextUtils.isEmpty:(Ljava/lang/CharSequence;)Z
        //  2083: ifne            2131
        //  2086: aload           11
        //  2088: invokevirtual   ahcr.copyOnWrite:()V
        //  2091: aload           11
        //  2093: getfield        ahcr.instance:Lahcz;
        //  2096: checkcast       Llrk;
        //  2099: astore          9
        //  2101: aload           8
        //  2103: invokevirtual   java/lang/Object.getClass:()Ljava/lang/Class;
        //  2106: pop            
        //  2107: aload           9
        //  2109: aload           9
        //  2111: getfield        lrk.b:I
        //  2114: sipush          128
        //  2117: ior            
        //  2118: putfield        lrk.b:I
        //  2121: aload           9
        //  2123: aload           8
        //  2125: checkcast       Ljava/lang/String;
        //  2128: putfield        lrk.j:Ljava/lang/String;
        //  2131: aload           11
        //  2133: invokevirtual   ahcr.copyOnWrite:()V
        //  2136: aload           11
        //  2138: getfield        ahcr.instance:Lahcz;
        //  2141: checkcast       Llrk;
        //  2144: astore          8
        //  2146: aload           8
        //  2148: aload           8
        //  2150: getfield        lrk.b:I
        //  2153: sipush          256
        //  2156: ior            
        //  2157: putfield        lrk.b:I
        //  2160: aload           8
        //  2162: iload           4
        //  2164: putfield        lrk.k:Z
        //  2167: aload           10
        //  2169: aload           11
        //  2171: invokevirtual   ahcr.build:()Lahcz;
        //  2174: checkcast       Llrk;
        //  2177: invokevirtual   ahcz.toBuilder:()Lahcr;
        //  2180: invokeinterface zmd.l:(Lahcr;)V
        //  2185: return         
        //  2186: aload           10
        //  2188: aload           9
        //  2190: invokevirtual   absy.c:(Lznz;)V
        //  2193: return         
        //  2194: astore          8
        //  2196: goto            504
        //    Exceptions:
        //  Try           Handler
        //  Start  End    Start  End    Type 
        //  -----  -----  -----  -----  -----
        //  440    445    741    866    Any
        //  448    458    741    866    Any
        //  458    468    741    866    Any
        //  478    489    2194   2199   Lzaw;
        //  478    489    741    866    Any
        //  504    516    741    866    Any
        //  521    586    741    866    Any
        //  589    605    741    866    Any
        //  609    620    741    866    Any
        //  625    689    741    866    Any
        //  689    699    741    866    Any
        //  704    709    741    866    Any
        //  712    722    741    866    Any
        //  722    740    741    866    Any
        //  748    753    854    866    Any
        //  756    766    854    866    Any
        //  766    780    854    866    Any
        //  790    804    854    866    Any
        //  804    853    854    866    Any
        //  890    922    923    1013   Any
        //  925    1000   1001   1013   Any
        // 
        // The error that occurred was:
        // 
        // java.lang.IllegalStateException: Expression is linked from several locations: Label_0492:
        //     at com.strobel.decompiler.ast.Error.expressionLinkedFromMultipleLocations(Error.java:27)
        //     at com.strobel.decompiler.ast.AstOptimizer.mergeDisparateObjectInitializations(AstOptimizer.java:2604)
        //     at com.strobel.decompiler.ast.AstOptimizer.optimize(AstOptimizer.java:235)
        //     at com.strobel.decompiler.ast.AstOptimizer.optimize(AstOptimizer.java:42)
        //     at com.strobel.decompiler.languages.java.ast.AstMethodBodyBuilder.createMethodBody(AstMethodBodyBuilder.java:206)
        //     at com.strobel.decompiler.languages.java.ast.AstMethodBodyBuilder.createMethodBody(AstMethodBodyBuilder.java:93)
        //     at com.strobel.decompiler.languages.java.ast.AstBuilder.createMethodBody(AstBuilder.java:868)
        //     at com.strobel.decompiler.languages.java.ast.AstBuilder.createMethod(AstBuilder.java:761)
        //     at com.strobel.decompiler.languages.java.ast.AstBuilder.addTypeMembers(AstBuilder.java:638)
        //     at com.strobel.decompiler.languages.java.ast.AstBuilder.createTypeCore(AstBuilder.java:605)
        //     at com.strobel.decompiler.languages.java.ast.AstBuilder.createTypeNoCache(AstBuilder.java:195)
        //     at com.strobel.decompiler.languages.java.ast.AstBuilder.createType(AstBuilder.java:162)
        //     at com.strobel.decompiler.languages.java.ast.AstBuilder.addType(AstBuilder.java:137)
        //     at com.strobel.decompiler.languages.java.JavaLanguage.buildAst(JavaLanguage.java:71)
        //     at com.strobel.decompiler.languages.java.JavaLanguage.decompileType(JavaLanguage.java:59)
        //     at com.strobel.decompiler.DecompilerDriver.decompileType(DecompilerDriver.java:333)
        //     at com.strobel.decompiler.DecompilerDriver.decompileJar(DecompilerDriver.java:254)
        //     at com.strobel.decompiler.DecompilerDriver.main(DecompilerDriver.java:129)
        // 
        throw new IllegalStateException("An error occurred while decompiling this method.");
    }
}
