// 
// Decompiled by Procyon v0.6.0
// 

public final class aafd implements aads
{
    private volatile boolean A;
    private final int B;
    private final int C;
    private final aamd D;
    private final acga E;
    private final avt F;
    yyg a;
    final aeby b;
    final aeby c;
    private final aaha d;
    private final aadr e;
    private final aack f;
    private final vhm g;
    private final zzo h;
    private final String i;
    private final String j;
    private final String k;
    private final byte[] l;
    private final String m;
    private ydr n;
    private ydr o;
    private final aafg p;
    private final aafk q;
    private final aafk r;
    private final zym s;
    private final oas t;
    private final int u;
    private final int v;
    private final String w;
    private final aafi x;
    private final yha y;
    private final yyh z;
    
    public aafd(final aadr e, final aack f, final vhm g, final oas t, final avt f2, final zzo h, final aeby b, final aeby c, final aafi x, final acga e2, final zym s, final yyh z, final aaha d, final yha y, final aamd d2, final byte[] array, final byte[] array2, final byte[] array3, final byte[] array4, final byte[] array5, final byte[] array6) {
        this.e = e;
        this.f = f;
        this.g = g;
        this.t = t;
        this.F = f2;
        this.h = h;
        this.b = b;
        this.c = c;
        this.x = x;
        this.E = e2;
        this.s = s;
        this.z = z;
        this.d = d;
        this.y = y;
        this.D = d2;
        final int d3 = aadj.d(h.f);
        this.u = d3;
        this.v = d3;
        final int aj = aadj.aj(h.f);
        this.B = aj;
        this.C = aj;
        this.w = aadj.q(h.f);
        this.i = h.a;
        this.j = f2.Z();
        this.k = aadj.u(h.f);
        this.l = aadj.af(h.f);
        this.q = new aafk();
        this.r = new aafk();
        this.p = new aafg(t, f.d(), (aaff)new aafb(this, 0));
        this.m = aadj.t(h.f);
    }
    
    private final zyq c() {
        final zyq g = this.h.g;
        aadj.z(g, this.q.a() + this.r.a());
        aadj.N(g, this.q.b() + this.r.b());
        return g;
    }
    
    private final void d(final aadt aadt) {
        if (aadt.a) {
            final Throwable cause = aadt.getCause();
            if (cause != null) {
                final String m = this.m;
                final String message = aadt.getMessage();
                final StringBuilder sb = new StringBuilder("[Offline] pudl task cotn [");
                sb.append(m);
                sb.append("] failed: ");
                sb.append(message);
                trn.d(sb.toString(), cause);
            }
            else {
                final String i = this.m;
                final String message2 = aadt.getMessage();
                final StringBuilder sb2 = new StringBuilder("[Offline] pudl task cotn [");
                sb2.append(i);
                sb2.append("] failed, unknown cause: ");
                sb2.append(message2);
                trn.d(sb2.toString(), (Throwable)new IllegalArgumentException());
            }
        }
        else {
            final String j = this.m;
            final String message3 = aadt.getMessage();
            final StringBuilder sb3 = new StringBuilder("[Offline] pudl task cotn [");
            sb3.append(j);
            sb3.append("]: ");
            sb3.append(message3);
            trn.l(sb3.toString());
        }
        final yyg a = this.a;
        if (a != null) {
            a.g();
        }
        this.e.d(this.i, aadt, this.c());
    }
    
    private static final boolean e(final zzd zzd, final boolean b) {
        boolean b2 = true;
        if (!b) {
            if (zzd != null) {
                if (zzd.i()) {
                    return false;
                }
                b2 = b2;
            }
            else {
                b2 = false;
            }
        }
        return b2;
    }
    
    public final void a(final int n) {
        boolean b = true;
        this.A = true;
        if ((n & 0x180) != 0x0) {
            b = false;
        }
        final ydr n2 = this.n;
        if (n2 != null) {
            n2.a(b);
        }
        final ydr o = this.o;
        if (o != null) {
            o.a(b);
        }
    }
    
    public final void b(final long n, final double n2, final boolean b) {
        this.e.b(this.i, n, n2, b);
    }
    
    public final void run() {
        // 
        // This method could not be decompiled.
        // 
        // Original Bytecode:
        // 
        //     2: invokestatic    android/os/Process.setThreadPriority:(I)V
        //     5: aload_0        
        //     6: getfield        aafd.f:Laack;
        //     9: invokeinterface aack.B:()Lztu;
        //    14: astore_1       
        //    15: aload_0        
        //    16: getfield        aafd.h:Lzzo;
        //    19: getfield        zzo.i:Z
        //    22: ifne            39
        //    25: aload_1        
        //    26: ifnull          32
        //    29: goto            39
        //    32: ldc_w           "[Offline] Couldn't get db helper due to initialization or non-active store."
        //    35: invokestatic    trn.b:(Ljava/lang/String;)V
        //    38: return         
        //    39: aload_0        
        //    40: getfield        aafd.A:Z
        //    43: ifeq            49
        //    46: goto            4677
        //    49: aload_0        
        //    50: getfield        aafd.k:Ljava/lang/String;
        //    53: invokestatic    android/text/TextUtils.isEmpty:(Ljava/lang/CharSequence;)Z
        //    56: ifeq            85
        //    59: new             Ljava/lang/IllegalArgumentException;
        //    62: astore_2       
        //    63: aload_2        
        //    64: invokespecial   java/lang/IllegalArgumentException.<init>:()V
        //    67: aload_0        
        //    68: ldc_w           "No videoid specified on video transfer."
        //    71: aload_2        
        //    72: getstatic       zyw.d:Lzyw;
        //    75: getstatic       amtj.a:Lamtj;
        //    78: invokestatic    aadt.a:(Ljava/lang/String;Ljava/lang/Exception;Lzyw;Lamtj;)Laadt;
        //    81: invokespecial   aafd.d:(Laadt;)V
        //    84: return         
        //    85: aload_0        
        //    86: getfield        aafd.f:Laack;
        //    89: invokeinterface aack.f:()Lzxz;
        //    94: astore_2       
        //    95: aload_0        
        //    96: getfield        aafd.h:Lzzo;
        //    99: astore_3       
        //   100: aload_3        
        //   101: getfield        zzo.i:Z
        //   104: ifeq            110
        //   107: goto            184
        //   110: aload_3        
        //   111: getfield        zzo.f:Lzyq;
        //   114: invokestatic    aadj.s:(Lzyq;)Ljava/lang/String;
        //   117: astore_3       
        //   118: aload_0        
        //   119: getfield        aafd.d:Laaha;
        //   122: getfield        aaha.c:Luyi;
        //   125: ldc2_w          45367078
        //   128: invokevirtual   uyi.f:(J)Z
        //   131: ifeq            138
        //   134: aload_3        
        //   135: ifnull          184
        //   138: aload_0        
        //   139: getfield        aafd.d:Laaha;
        //   142: invokevirtual   aaha.n:()Z
        //   145: ifeq            152
        //   148: aload_3        
        //   149: ifnonnull       184
        //   152: aload_1        
        //   153: ifnull          184
        //   156: aload_2        
        //   157: ifnull          184
        //   160: aload_1        
        //   161: aload_2        
        //   162: aload_0        
        //   163: getfield        aafd.h:Lzzo;
        //   166: invokestatic    aafi.f:(Lztu;Lzya;Lzzo;)V
        //   169: goto            184
        //   172: astore_3       
        //   173: goto            3871
        //   176: astore_2       
        //   177: goto            3933
        //   180: astore_2       
        //   181: goto            3947
        //   184: aload_0        
        //   185: getfield        aafd.f:Laack;
        //   188: invokeinterface aack.d:()Lzul;
        //   193: astore          4
        //   195: aload_0        
        //   196: getfield        aafd.d:Laaha;
        //   199: invokevirtual   aaha.l:()Z
        //   202: istore          5
        //   204: iload           5
        //   206: ifeq            340
        //   209: aload_0        
        //   210: getfield        aafd.x:Laafi;
        //   213: astore_3       
        //   214: aload_0        
        //   215: getfield        aafd.h:Lzzo;
        //   218: getfield        zzo.j:Lzkh;
        //   221: astore          6
        //   223: aload_0        
        //   224: getfield        aafd.k:Ljava/lang/String;
        //   227: astore_2       
        //   228: aload           6
        //   230: invokeinterface zkh.z:()Z
        //   235: ifeq            243
        //   238: aconst_null    
        //   239: astore_2       
        //   240: goto            302
        //   243: aload_3        
        //   244: getfield        aafi.h:Ljava/lang/Object;
        //   247: aload           6
        //   249: invokeinterface vcf.a:(Lzkh;)Lvce;
        //   254: aload_2        
        //   255: invokestatic    aafi.b:(Ljava/lang/String;)Ljava/lang/String;
        //   258: invokeinterface vce.f:(Ljava/lang/String;)Lasgy;
        //   263: ldc_w           Lanau;.class
        //   266: invokevirtual   asgy.j:(Ljava/lang/Class;)Lasgy;
        //   269: invokevirtual   asgy.af:()Ljava/lang/Object;
        //   272: checkcast       Lanau;
        //   275: astore_2       
        //   276: aload_2        
        //   277: ifnull          238
        //   280: aload_2        
        //   281: invokevirtual   anau.i:()Z
        //   284: ifne            290
        //   287: goto            238
        //   290: aload_2        
        //   291: invokevirtual   anau.getPlayerResponseBytes:()Lagyc;
        //   294: invokevirtual   agyc.I:()[B
        //   297: lconst_0       
        //   298: invokestatic    com/google/android/libraries/youtube/innertube/model/player/PlayerResponseModelImpl.af:([BJ)Lcom/google/android/libraries/youtube/innertube/model/player/PlayerResponseModel;
        //   301: astore_2       
        //   302: aload_2        
        //   303: ifnonnull       337
        //   306: aload_0        
        //   307: getfield        aafd.e:Laadr;
        //   310: aload_0        
        //   311: getfield        aafd.i:Ljava/lang/String;
        //   314: ldc_w           "PlayerResponse doesn't exist"
        //   317: aconst_null    
        //   318: getstatic       zyw.h:Lzyw;
        //   321: getstatic       amtj.e:Lamtj;
        //   324: invokestatic    aadt.a:(Ljava/lang/String;Ljava/lang/Exception;Lzyw;Lamtj;)Laadt;
        //   327: aload_0        
        //   328: invokespecial   aafd.c:()Lzyq;
        //   331: invokeinterface aadr.d:(Ljava/lang/String;Laadt;Lzyq;)V
        //   336: return         
        //   337: goto            419
        //   340: aload_0        
        //   341: getfield        aafd.x:Laafi;
        //   344: aload_0        
        //   345: getfield        aafd.k:Ljava/lang/String;
        //   348: aload_0        
        //   349: getfield        aafd.l:[B
        //   352: aload_0        
        //   353: getfield        aafd.h:Lzzo;
        //   356: iconst_2       
        //   357: invokevirtual   aafi.h:(Ljava/lang/String;[BLzzo;I)Lcom/google/android/libraries/youtube/innertube/model/player/PlayerResponseModel;
        //   360: astore_2       
        //   361: aload_0        
        //   362: getfield        aafd.h:Lzzo;
        //   365: getfield        zzo.i:Z
        //   368: istore          5
        //   370: iload           5
        //   372: ifne            419
        //   375: aload_1        
        //   376: ifnull          419
        //   379: aload_1        
        //   380: aload_0        
        //   381: getfield        aafd.k:Ljava/lang/String;
        //   384: invokevirtual   ztu.q:(Ljava/lang/String;)Lcom/google/android/libraries/youtube/innertube/model/player/PlayerResponseModel;
        //   387: ifnonnull       419
        //   390: aload_0        
        //   391: getfield        aafd.i:Ljava/lang/String;
        //   394: aload_0        
        //   395: getfield        aafd.k:Ljava/lang/String;
        //   398: aload_2        
        //   399: aload_1        
        //   400: aload_0        
        //   401: getfield        aafd.t:Loas;
        //   404: invokeinterface oas.c:()J
        //   409: aload_0        
        //   410: getfield        aafd.g:Lvhm;
        //   413: invokestatic    aafi.e:(Ljava/lang/String;Ljava/lang/String;Lcom/google/android/libraries/youtube/innertube/model/player/PlayerResponseModel;Lztu;JLvhm;)V
        //   416: goto            419
        //   419: aload_0        
        //   420: getfield        aafd.i:Ljava/lang/String;
        //   423: aload_2        
        //   424: invokestatic    aafi.i:(Ljava/lang/String;Lcom/google/android/libraries/youtube/innertube/model/player/PlayerResponseModel;)V
        //   427: aload_0        
        //   428: getfield        aafd.f:Laack;
        //   431: invokeinterface aack.g:()Laacg;
        //   436: astore          6
        //   438: aload_0        
        //   439: getfield        aafd.k:Ljava/lang/String;
        //   442: astore_3       
        //   443: aload_0        
        //   444: getfield        aafd.v:I
        //   447: invokestatic    aahf.c:(I)Lamuv;
        //   450: pop            
        //   451: getstatic       uyp.a:[B
        //   454: astore          7
        //   456: aload           6
        //   458: aload_3        
        //   459: aload_2        
        //   460: invokeinterface aacg.j:(Ljava/lang/String;Lcom/google/android/libraries/youtube/innertube/model/player/PlayerResponseModel;)Ljava/lang/String;
        //   465: astore          8
        //   467: aload           8
        //   469: invokestatic    android/text/TextUtils.isEmpty:(Ljava/lang/CharSequence;)Z
        //   472: istore          5
        //   474: iload           5
        //   476: ifne            511
        //   479: aload_0        
        //   480: getfield        aafd.x:Laafi;
        //   483: aload           8
        //   485: aload_0        
        //   486: getfield        aafd.l:[B
        //   489: aload_0        
        //   490: getfield        aafd.h:Lzzo;
        //   493: iconst_1       
        //   494: invokevirtual   aafi.h:(Ljava/lang/String;[BLzzo;I)Lcom/google/android/libraries/youtube/innertube/model/player/PlayerResponseModel;
        //   497: astore          9
        //   499: aload_0        
        //   500: getfield        aafd.i:Ljava/lang/String;
        //   503: aload           9
        //   505: invokestatic    aafi.i:(Ljava/lang/String;Lcom/google/android/libraries/youtube/innertube/model/player/PlayerResponseModel;)V
        //   508: goto            514
        //   511: aconst_null    
        //   512: astore          9
        //   514: aload_0        
        //   515: getfield        aafd.h:Lzzo;
        //   518: getfield        zzo.i:Z
        //   521: istore          5
        //   523: iload           5
        //   525: ifne            552
        //   528: aload_1        
        //   529: ifnull          552
        //   532: aload_0        
        //   533: getfield        aafd.x:Laafi;
        //   536: aload_0        
        //   537: getfield        aafd.i:Ljava/lang/String;
        //   540: aload_0        
        //   541: getfield        aafd.k:Ljava/lang/String;
        //   544: aload_1        
        //   545: aload_0        
        //   546: getfield        aafd.e:Laadr;
        //   549: invokevirtual   aafi.d:(Ljava/lang/String;Ljava/lang/String;Lztu;Laadr;)V
        //   552: aload_2        
        //   553: invokeinterface com/google/android/libraries/youtube/innertube/model/player/PlayerResponseModel.n:()Lcom/google/android/libraries/youtube/innertube/model/media/VideoStreamingData;
        //   558: astore          7
        //   560: aload_0        
        //   561: getfield        aafd.x:Laafi;
        //   564: astore          10
        //   566: aload_0        
        //   567: getfield        aafd.u:I
        //   570: istore          11
        //   572: iload           11
        //   574: istore          12
        //   576: iload           11
        //   578: ifne            664
        //   581: aload_2        
        //   582: ifnull          661
        //   585: aload_2        
        //   586: invokeinterface com/google/android/libraries/youtube/innertube/model/player/PlayerResponseModel.y:()Lakuv;
        //   591: getfield        akuv.k:Lakul;
        //   594: astore          6
        //   596: aload           6
        //   598: astore_3       
        //   599: aload           6
        //   601: ifnonnull       608
        //   604: getstatic       akul.a:Lakul;
        //   607: astore_3       
        //   608: aload_3        
        //   609: getfield        akul.b:Lahul;
        //   612: astore          6
        //   614: aload           6
        //   616: astore_3       
        //   617: aload           6
        //   619: ifnonnull       626
        //   622: getstatic       ahul.a:Lahul;
        //   625: astore_3       
        //   626: aload_3        
        //   627: getfield        ahul.b:I
        //   630: invokestatic    afld.X:(I)I
        //   633: istore          12
        //   635: iload           12
        //   637: ifne            643
        //   640: goto            661
        //   643: iload           12
        //   645: iconst_3       
        //   646: if_icmpne       661
        //   649: getstatic       amuv.c:Lamuv;
        //   652: iconst_0       
        //   653: invokestatic    aahf.a:(Lamuv;I)I
        //   656: istore          12
        //   658: goto            664
        //   661: iconst_0       
        //   662: istore          12
        //   664: aload           10
        //   666: iload           12
        //   668: aload_0        
        //   669: getfield        aafd.B:I
        //   672: aload_0        
        //   673: getfield        aafd.w:Ljava/lang/String;
        //   676: aload_0        
        //   677: getfield        aafd.k:Ljava/lang/String;
        //   680: aload           7
        //   682: aload_2        
        //   683: invokeinterface com/google/android/libraries/youtube/innertube/model/player/PlayerResponseModel.m:()Lcom/google/android/libraries/youtube/innertube/model/media/PlayerConfigModel;
        //   688: aload           4
        //   690: invokevirtual   aafi.g:(IILjava/lang/String;Ljava/lang/String;Lcom/google/android/libraries/youtube/innertube/model/media/VideoStreamingData;Lcom/google/android/libraries/youtube/innertube/model/media/PlayerConfigModel;Lzul;)Lzze;
        //   693: astore_3       
        //   694: aload           4
        //   696: aload_0        
        //   697: getfield        aafd.k:Ljava/lang/String;
        //   700: aload_3        
        //   701: invokeinterface zul.c:(Ljava/lang/String;Lzze;)V
        //   706: aload_0        
        //   707: getfield        aafd.z:Lyyh;
        //   710: astore          13
        //   712: aload_2        
        //   713: invokeinterface com/google/android/libraries/youtube/innertube/model/player/PlayerResponseModel.o:()Lcom/google/android/libraries/youtube/innertube/model/player/PlaybackTrackingModel;
        //   718: getfield        com/google/android/libraries/youtube/innertube/model/player/PlaybackTrackingModel.f:Lcom/google/android/libraries/youtube/innertube/model/player/TrackingUrlModel;
        //   721: astore          6
        //   723: aload_0        
        //   724: getfield        aafd.j:Ljava/lang/String;
        //   727: astore          14
        //   729: aload_0        
        //   730: getfield        aafd.m:Ljava/lang/String;
        //   733: astore          10
        //   735: aload_0        
        //   736: getfield        aafd.h:Lzzo;
        //   739: getfield        zzo.f:Lzyq;
        //   742: invokestatic    aadj.ak:(Lzyq;)I
        //   745: bipush          6
        //   747: if_icmpne       756
        //   750: iconst_2       
        //   751: istore          12
        //   753: goto            759
        //   756: iconst_1       
        //   757: istore          12
        //   759: aload           13
        //   761: aload           6
        //   763: aload           14
        //   765: aconst_null    
        //   766: aload           10
        //   768: iload           12
        //   770: invokestatic    java/lang/Integer.valueOf:(I)Ljava/lang/Integer;
        //   773: aload_0        
        //   774: getfield        aafd.k:Ljava/lang/String;
        //   777: aload           7
        //   779: iconst_0       
        //   780: aload_2        
        //   781: invokeinterface com/google/android/libraries/youtube/innertube/model/player/PlayerResponseModel.m:()Lcom/google/android/libraries/youtube/innertube/model/media/PlayerConfigModel;
        //   786: invokevirtual   yyh.b:(Lcom/google/android/libraries/youtube/innertube/model/player/TrackingUrlModel;Ljava/lang/String;Lappy;Ljava/lang/String;Ljava/lang/Integer;Ljava/lang/String;Lcom/google/android/libraries/youtube/innertube/model/media/VideoStreamingData;ZLcom/google/android/libraries/youtube/innertube/model/media/PlayerConfigModel;)Lyyg;
        //   789: astore          14
        //   791: aload_0        
        //   792: aload           14
        //   794: putfield        aafd.a:Lyyg;
        //   797: aload           14
        //   799: ifnull          862
        //   802: aload_0        
        //   803: getfield        aafd.y:Lyha;
        //   806: astore          6
        //   808: aload           6
        //   810: getfield        yha.d:Lthh;
        //   813: invokeinterface thh.r:()Z
        //   818: ifne            862
        //   821: aload           6
        //   823: getfield        yha.c:Landroid/os/Handler;
        //   826: astore          10
        //   828: new             Lxcu;
        //   831: astore          7
        //   833: aload           7
        //   835: aload           6
        //   837: aload           14
        //   839: bipush          19
        //   841: invokespecial   xcu.<init>:(Lyha;Lyyg;I)V
        //   844: aload           10
        //   846: aload           7
        //   848: invokevirtual   android/os/Handler.post:(Ljava/lang/Runnable;)Z
        //   851: pop            
        //   852: goto            862
        //   855: astore          6
        //   857: getstatic       yzr.a:Lyzr;
        //   860: astore          6
        //   862: aload_0        
        //   863: getfield        aafd.h:Lzzo;
        //   866: getfield        zzo.f:Lzyq;
        //   869: invokestatic    aadj.ab:(Lzyq;)Z
        //   872: istore          5
        //   874: iload           5
        //   876: ifeq            901
        //   879: aload_0        
        //   880: getfield        aafd.a:Lyyg;
        //   883: astore          6
        //   885: aload           6
        //   887: ifnull          901
        //   890: aload           6
        //   892: ldc_w           "cat"
        //   895: ldc_w           "unmetered_5g"
        //   898: invokevirtual   yyg.B:(Ljava/lang/String;Ljava/lang/String;)V
        //   901: aload           9
        //   903: ifnull          950
        //   906: aload           8
        //   908: ifnull          950
        //   911: aload_0        
        //   912: getfield        aafd.x:Laafi;
        //   915: aload_0        
        //   916: getfield        aafd.v:I
        //   919: aload_0        
        //   920: getfield        aafd.C:I
        //   923: aconst_null    
        //   924: aload           8
        //   926: aload           9
        //   928: invokeinterface com/google/android/libraries/youtube/innertube/model/player/PlayerResponseModel.n:()Lcom/google/android/libraries/youtube/innertube/model/media/VideoStreamingData;
        //   933: aload           9
        //   935: invokeinterface com/google/android/libraries/youtube/innertube/model/player/PlayerResponseModel.m:()Lcom/google/android/libraries/youtube/innertube/model/media/PlayerConfigModel;
        //   940: aload           4
        //   942: invokevirtual   aafi.g:(IILjava/lang/String;Ljava/lang/String;Lcom/google/android/libraries/youtube/innertube/model/media/VideoStreamingData;Lcom/google/android/libraries/youtube/innertube/model/media/PlayerConfigModel;Lzul;)Lzze;
        //   945: astore          10
        //   947: goto            953
        //   950: aconst_null    
        //   951: astore          10
        //   953: new             Ljava/util/HashSet;
        //   956: astore          6
        //   958: aload           6
        //   960: invokespecial   java/util/HashSet.<init>:()V
        //   963: new             Ljava/util/ArrayList;
        //   966: astore          7
        //   968: aload           7
        //   970: invokespecial   java/util/ArrayList.<init>:()V
        //   973: aload_0        
        //   974: getfield        aafd.D:Laamd;
        //   977: astore          14
        //   979: aload           14
        //   981: aload_2        
        //   982: invokevirtual   aamd.f:(Lcom/google/android/libraries/youtube/innertube/model/player/PlayerResponseModel;)Ljava/util/List;
        //   985: astore          13
        //   987: aload           13
        //   989: invokeinterface java/util/List.iterator:()Ljava/util/Iterator;
        //   994: astore          14
        //   996: aload           14
        //   998: invokeinterface java/util/Iterator.hasNext:()Z
        //  1003: istore          5
        //  1005: iload           5
        //  1007: ifeq            1036
        //  1010: aload           6
        //  1012: aload           14
        //  1014: invokeinterface java/util/Iterator.next:()Ljava/lang/Object;
        //  1019: checkcast       Lcom/google/android/libraries/youtube/innertube/model/player/PlayerResponseModel;
        //  1022: invokeinterface com/google/android/libraries/youtube/innertube/model/player/PlayerResponseModel.K:()Ljava/lang/String;
        //  1027: invokeinterface java/util/Set.add:(Ljava/lang/Object;)Z
        //  1032: pop            
        //  1033: goto            996
        //  1036: aload           4
        //  1038: aload           6
        //  1040: aload_0        
        //  1041: getfield        aafd.k:Ljava/lang/String;
        //  1044: invokeinterface zul.d:(Ljava/util/Set;Ljava/lang/String;)V
        //  1049: aload           13
        //  1051: invokeinterface java/util/List.iterator:()Ljava/util/Iterator;
        //  1056: astore          14
        //  1058: aload_2        
        //  1059: astore          6
        //  1061: aload           14
        //  1063: invokeinterface java/util/Iterator.hasNext:()Z
        //  1068: istore          5
        //  1070: iload           5
        //  1072: ifeq            1137
        //  1075: aload           14
        //  1077: invokeinterface java/util/Iterator.next:()Ljava/lang/Object;
        //  1082: checkcast       Lcom/google/android/libraries/youtube/innertube/model/player/PlayerResponseModel;
        //  1085: astore_2       
        //  1086: aload           7
        //  1088: aload_2        
        //  1089: aload_0        
        //  1090: getfield        aafd.x:Laafi;
        //  1093: aload_0        
        //  1094: getfield        aafd.u:I
        //  1097: aload_0        
        //  1098: getfield        aafd.B:I
        //  1101: aconst_null    
        //  1102: aload_2        
        //  1103: invokeinterface com/google/android/libraries/youtube/innertube/model/player/PlayerResponseModel.K:()Ljava/lang/String;
        //  1108: aload_2        
        //  1109: invokeinterface com/google/android/libraries/youtube/innertube/model/player/PlayerResponseModel.n:()Lcom/google/android/libraries/youtube/innertube/model/media/VideoStreamingData;
        //  1114: aload_2        
        //  1115: invokeinterface com/google/android/libraries/youtube/innertube/model/player/PlayerResponseModel.m:()Lcom/google/android/libraries/youtube/innertube/model/media/PlayerConfigModel;
        //  1120: aload           4
        //  1122: invokevirtual   aafi.g:(IILjava/lang/String;Ljava/lang/String;Lcom/google/android/libraries/youtube/innertube/model/media/VideoStreamingData;Lcom/google/android/libraries/youtube/innertube/model/media/PlayerConfigModel;Lzul;)Lzze;
        //  1125: invokestatic    aexr.a:(Ljava/lang/Object;Ljava/lang/Object;)Laexr;
        //  1128: invokeinterface java/util/List.add:(Ljava/lang/Object;)Z
        //  1133: pop            
        //  1134: goto            1061
        //  1137: aload_3        
        //  1138: getfield        zze.c:J
        //  1141: lstore          15
        //  1143: aload_3        
        //  1144: getfield        zze.d:J
        //  1147: lstore          17
        //  1149: lload           15
        //  1151: lstore          19
        //  1153: lload           17
        //  1155: lstore          21
        //  1157: aload           10
        //  1159: ifnull          1186
        //  1162: lload           15
        //  1164: aload           10
        //  1166: getfield        zze.c:J
        //  1169: ladd           
        //  1170: lstore          19
        //  1172: aload           10
        //  1174: getfield        zze.d:J
        //  1177: lstore          21
        //  1179: lload           17
        //  1181: lload           21
        //  1183: ladd           
        //  1184: lstore          21
        //  1186: aload           7
        //  1188: invokeinterface java/util/List.iterator:()Ljava/util/Iterator;
        //  1193: astore_2       
        //  1194: aload_2        
        //  1195: invokeinterface java/util/Iterator.hasNext:()Z
        //  1200: istore          5
        //  1202: iload           5
        //  1204: ifeq            1251
        //  1207: aload_2        
        //  1208: invokeinterface java/util/Iterator.next:()Ljava/lang/Object;
        //  1213: checkcast       Laexr;
        //  1216: getfield        aexr.b:Ljava/lang/Object;
        //  1219: checkcast       Lzze;
        //  1222: astore          4
        //  1224: lload           19
        //  1226: aload           4
        //  1228: getfield        zze.c:J
        //  1231: ladd           
        //  1232: lstore          19
        //  1234: aload           4
        //  1236: getfield        zze.d:J
        //  1239: lstore          17
        //  1241: lload           21
        //  1243: lload           17
        //  1245: ladd           
        //  1246: lstore          21
        //  1248: goto            1194
        //  1251: lload           21
        //  1253: lload           19
        //  1255: lcmp           
        //  1256: ifle            1265
        //  1259: iconst_1       
        //  1260: istore          5
        //  1262: goto            1268
        //  1265: iconst_0       
        //  1266: istore          5
        //  1268: aload_0        
        //  1269: getfield        aafd.p:Laafg;
        //  1272: astore_2       
        //  1273: aload_2        
        //  1274: lload           21
        //  1276: putfield        aafg.c:J
        //  1279: aload_2        
        //  1280: lconst_0       
        //  1281: putfield        aafg.b:J
        //  1284: aload_0        
        //  1285: getfield        aafd.e:Laadr;
        //  1288: aload_0        
        //  1289: getfield        aafd.i:Ljava/lang/String;
        //  1292: lload           21
        //  1294: invokeinterface aadr.c:(Ljava/lang/String;J)V
        //  1299: aload_3        
        //  1300: astore_2       
        //  1301: aload_0        
        //  1302: lload           19
        //  1304: dconst_0       
        //  1305: iload           5
        //  1307: invokevirtual   aafd.b:(JDZ)V
        //  1310: aload_2        
        //  1311: astore          14
        //  1313: iload           5
        //  1315: istore          23
        //  1317: aload           7
        //  1319: invokeinterface java/util/List.isEmpty:()Z
        //  1324: ifne            1696
        //  1327: aload           7
        //  1329: invokeinterface java/util/List.iterator:()Ljava/util/Iterator;
        //  1334: astore_3       
        //  1335: aload_2        
        //  1336: astore          14
        //  1338: iload           5
        //  1340: istore          23
        //  1342: aload_3        
        //  1343: invokeinterface java/util/Iterator.hasNext:()Z
        //  1348: ifeq            1696
        //  1351: aload_3        
        //  1352: invokeinterface java/util/Iterator.next:()Ljava/lang/Object;
        //  1357: checkcast       Laexr;
        //  1360: astore          7
        //  1362: aload           7
        //  1364: getfield        aexr.a:Ljava/lang/Object;
        //  1367: checkcast       Lcom/google/android/libraries/youtube/innertube/model/player/PlayerResponseModel;
        //  1370: astore          13
        //  1372: aload           7
        //  1374: getfield        aexr.b:Ljava/lang/Object;
        //  1377: checkcast       Lzze;
        //  1380: astore          14
        //  1382: aload_0        
        //  1383: getfield        aafd.b:Laeby;
        //  1386: invokevirtual   aeby.bm:()Laeby;
        //  1389: astore          24
        //  1391: aload           24
        //  1393: invokevirtual   aeby.aH:()Laexq;
        //  1396: invokevirtual   aexq.f:()Ljava/lang/Object;
        //  1399: checkcast       Ljava/lang/String;
        //  1402: astore          4
        //  1404: aload_0        
        //  1405: getfield        aafd.n:Lydr;
        //  1408: astore          7
        //  1410: aload           7
        //  1412: ifnonnull       1446
        //  1415: aload           24
        //  1417: getfield        aeby.a:Ljava/lang/Object;
        //  1420: checkcast       Laaex;
        //  1423: invokevirtual   aaex.a:()Lydr;
        //  1426: astore          7
        //  1428: aload           7
        //  1430: aload_0        
        //  1431: getfield        aafd.p:Laafg;
        //  1434: putfield        ydr.b:Lydq;
        //  1437: aload_0        
        //  1438: aload           7
        //  1440: putfield        aafd.n:Lydr;
        //  1443: goto            1446
        //  1446: aload           13
        //  1448: invokeinterface com/google/android/libraries/youtube/innertube/model/player/PlayerResponseModel.K:()Ljava/lang/String;
        //  1453: astore          13
        //  1455: aload_0        
        //  1456: getfield        aafd.p:Laafg;
        //  1459: aload           13
        //  1461: putfield        aafg.a:Ljava/lang/String;
        //  1464: aload           14
        //  1466: getfield        zze.a:Lzzd;
        //  1469: astore          24
        //  1471: aload           24
        //  1473: ifnull          1570
        //  1476: aload_0        
        //  1477: getfield        aafd.i:Ljava/lang/String;
        //  1480: astore          25
        //  1482: aload_0        
        //  1483: getfield        aafd.j:Ljava/lang/String;
        //  1486: astore          26
        //  1488: aload           24
        //  1490: invokevirtual   zzd.b:()J
        //  1493: lstore          19
        //  1495: aload_0        
        //  1496: getfield        aafd.f:Laack;
        //  1499: invokeinterface aack.d:()Lzul;
        //  1504: astore          27
        //  1506: aload_0        
        //  1507: getfield        aafd.q:Laafk;
        //  1510: astore          28
        //  1512: aload           13
        //  1514: aload           25
        //  1516: aload           26
        //  1518: aload           7
        //  1520: aload           24
        //  1522: lload           19
        //  1524: aload           27
        //  1526: aload           4
        //  1528: aload           28
        //  1530: getfield        aafk.c:Lyyt;
        //  1533: aload           28
        //  1535: getfield        aafk.a:Lyyt;
        //  1538: aload_0        
        //  1539: getfield        aafd.E:Lacga;
        //  1542: invokestatic    aafi.o:(Ljava/lang/String;Ljava/lang/String;Ljava/lang/String;Lydr;Lzzd;JLzul;Ljava/lang/String;Lyyt;Lyyt;Lacga;)V
        //  1545: aload_0        
        //  1546: getfield        aafd.p:Laafg;
        //  1549: astore          27
        //  1551: aload           27
        //  1553: aload           27
        //  1555: getfield        aafg.b:J
        //  1558: aload           24
        //  1560: invokevirtual   zzd.b:()J
        //  1563: ladd           
        //  1564: putfield        aafg.b:J
        //  1567: goto            1570
        //  1570: aload_0        
        //  1571: getfield        aafd.A:Z
        //  1574: ifeq            1580
        //  1577: goto            1683
        //  1580: aload           14
        //  1582: getfield        zze.b:Lzzd;
        //  1585: astore          14
        //  1587: aload           14
        //  1589: ifnull          1683
        //  1592: aload_0        
        //  1593: getfield        aafd.i:Ljava/lang/String;
        //  1596: astore          28
        //  1598: aload_0        
        //  1599: getfield        aafd.j:Ljava/lang/String;
        //  1602: astore          25
        //  1604: aload           14
        //  1606: invokevirtual   zzd.b:()J
        //  1609: lstore          19
        //  1611: aload_0        
        //  1612: getfield        aafd.f:Laack;
        //  1615: invokeinterface aack.d:()Lzul;
        //  1620: astore          24
        //  1622: aload_0        
        //  1623: getfield        aafd.q:Laafk;
        //  1626: astore          27
        //  1628: aload           13
        //  1630: aload           28
        //  1632: aload           25
        //  1634: aload           7
        //  1636: aload           14
        //  1638: lload           19
        //  1640: aload           24
        //  1642: aload           4
        //  1644: aload           27
        //  1646: getfield        aafk.d:Lyyt;
        //  1649: aload           27
        //  1651: getfield        aafk.b:Lyyt;
        //  1654: aload_0        
        //  1655: getfield        aafd.E:Lacga;
        //  1658: invokestatic    aafi.o:(Ljava/lang/String;Ljava/lang/String;Ljava/lang/String;Lydr;Lzzd;JLzul;Ljava/lang/String;Lyyt;Lyyt;Lacga;)V
        //  1661: aload_0        
        //  1662: getfield        aafd.p:Laafg;
        //  1665: astore          7
        //  1667: aload           7
        //  1669: aload           7
        //  1671: getfield        aafg.b:J
        //  1674: aload           14
        //  1676: invokevirtual   zzd.b:()J
        //  1679: ladd           
        //  1680: putfield        aafg.b:J
        //  1683: aload_0        
        //  1684: getfield        aafd.A:Z
        //  1687: ifeq            1693
        //  1690: goto            4677
        //  1693: goto            1335
        //  1696: aload_0        
        //  1697: getfield        aafd.k:Ljava/lang/String;
        //  1700: astore_2       
        //  1701: aload_0        
        //  1702: getfield        aafd.f:Laack;
        //  1705: invokeinterface aack.f:()Lzxz;
        //  1710: astore          28
        //  1712: aload           28
        //  1714: ifnull          2762
        //  1717: aload_0        
        //  1718: getfield        aafd.h:Lzzo;
        //  1721: getfield        zzo.i:Z
        //  1724: ifne            1746
        //  1727: aload_0        
        //  1728: getfield        aafd.d:Laaha;
        //  1731: invokevirtual   aaha.c:()Lztk;
        //  1734: invokevirtual   ztk.c:()Z
        //  1737: ifeq            1743
        //  1740: goto            1746
        //  1743: goto            2408
        //  1746: aload_0        
        //  1747: getfield        aafd.x:Laafi;
        //  1750: astore_3       
        //  1751: aload_0        
        //  1752: getfield        aafd.h:Lzzo;
        //  1755: getfield        zzo.j:Lzkh;
        //  1758: astore          7
        //  1760: aload           6
        //  1762: invokeinterface com/google/android/libraries/youtube/innertube/model/player/PlayerResponseModel.K:()Ljava/lang/String;
        //  1767: astore          25
        //  1769: aload           7
        //  1771: invokeinterface zkh.z:()Z
        //  1776: ifeq            1782
        //  1779: goto            1743
        //  1782: aload_3        
        //  1783: getfield        aafi.h:Ljava/lang/Object;
        //  1786: aload           7
        //  1788: invokeinterface vcf.a:(Lzkh;)Lvce;
        //  1793: astore          26
        //  1795: aload_3        
        //  1796: getfield        aafi.f:Ljava/lang/Object;
        //  1799: astore          7
        //  1801: aload_3        
        //  1802: getfield        aafi.k:Ljava/lang/Object;
        //  1805: checkcast       Labpj;
        //  1808: astore          4
        //  1810: aload           7
        //  1812: checkcast       Landroid/content/Context;
        //  1815: astore          13
        //  1817: aload_2        
        //  1818: astore_3       
        //  1819: aload_2        
        //  1820: astore          7
        //  1822: aload           6
        //  1824: aload           13
        //  1826: aload           4
        //  1828: invokestatic    abri.g:(Lcom/google/android/libraries/youtube/innertube/model/player/PlayerResponseModel;Landroid/content/Context;Labpj;)Labri;
        //  1831: astore          24
        //  1833: aload_2        
        //  1834: astore          4
        //  1836: aload           24
        //  1838: ifnull          2362
        //  1841: aload_2        
        //  1842: astore_3       
        //  1843: aload_2        
        //  1844: astore          7
        //  1846: aload           26
        //  1848: aload_2        
        //  1849: invokestatic    aafi.c:(Ljava/lang/String;)Ljava/lang/String;
        //  1852: invokeinterface vce.f:(Ljava/lang/String;)Lasgy;
        //  1857: ldc_w           Laouz;.class
        //  1860: invokevirtual   asgy.j:(Ljava/lang/Class;)Lasgy;
        //  1863: invokevirtual   asgy.af:()Ljava/lang/Object;
        //  1866: checkcast       Laouz;
        //  1869: astore          27
        //  1871: aload_2        
        //  1872: astore          4
        //  1874: aload           27
        //  1876: ifnull          2362
        //  1879: aload_2        
        //  1880: astore_3       
        //  1881: aload_2        
        //  1882: astore          7
        //  1884: aload           27
        //  1886: getfield        aouz.b:Laova;
        //  1889: getfield        aova.n:Lagzy;
        //  1892: astore          13
        //  1894: aload_2        
        //  1895: astore_3       
        //  1896: aload_2        
        //  1897: astore          7
        //  1899: aload           24
        //  1901: invokevirtual   abri.f:()Ljava/util/List;
        //  1904: astore          24
        //  1906: aload_2        
        //  1907: astore          4
        //  1909: aload_2        
        //  1910: astore_3       
        //  1911: aload_2        
        //  1912: astore          7
        //  1914: aload           24
        //  1916: invokeinterface java/util/List.isEmpty:()Z
        //  1921: ifne            2362
        //  1924: aload_2        
        //  1925: astore_3       
        //  1926: aload_2        
        //  1927: astore          7
        //  1929: aload           24
        //  1931: invokeinterface java/util/List.iterator:()Ljava/util/Iterator;
        //  1936: astore          24
        //  1938: aload_2        
        //  1939: astore          4
        //  1941: aload_2        
        //  1942: astore_3       
        //  1943: aload_2        
        //  1944: astore          7
        //  1946: aload           24
        //  1948: invokeinterface java/util/Iterator.hasNext:()Z
        //  1953: ifeq            2362
        //  1956: aload_2        
        //  1957: astore_3       
        //  1958: aload_2        
        //  1959: astore          7
        //  1961: aload           24
        //  1963: invokeinterface java/util/Iterator.next:()Ljava/lang/Object;
        //  1968: checkcast       Lcom/google/android/libraries/youtube/player/subtitles/model/SubtitleTrack;
        //  1971: astore          4
        //  1973: aload_2        
        //  1974: astore_3       
        //  1975: aload_2        
        //  1976: astore          7
        //  1978: sipush          225
        //  1981: aload           4
        //  1983: invokevirtual   com/google/android/libraries/youtube/player/subtitles/model/SubtitleTrack.k:()Ljava/lang/String;
        //  1986: aload           4
        //  1988: invokevirtual   com/google/android/libraries/youtube/player/subtitles/model/SubtitleTrack.l:()Ljava/lang/String;
        //  1991: invokevirtual   java/lang/String.concat:(Ljava/lang/String;)Ljava/lang/String;
        //  1994: invokestatic    vek.h:(ILjava/lang/String;)Ljava/lang/String;
        //  1997: astore          29
        //  1999: aload_2        
        //  2000: astore_3       
        //  2001: aload_2        
        //  2002: astore          7
        //  2004: aload           13
        //  2006: aload           29
        //  2008: invokeinterface java/util/List.contains:(Ljava/lang/Object;)Z
        //  2013: ifne            2359
        //  2016: aload_2        
        //  2017: astore_3       
        //  2018: aload_2        
        //  2019: astore          7
        //  2021: aload           4
        //  2023: invokevirtual   com/google/android/libraries/youtube/player/subtitles/model/SubtitleTrack.t:()Z
        //  2026: ifne            2359
        //  2029: aload_2        
        //  2030: astore_3       
        //  2031: aload_2        
        //  2032: astore          7
        //  2034: aload           28
        //  2036: aload           25
        //  2038: aload           4
        //  2040: invokeinterface zya.n:(Ljava/lang/String;Lcom/google/android/libraries/youtube/player/subtitles/model/SubtitleTrack;)Ljava/lang/String;
        //  2045: astore          30
        //  2047: aload_2        
        //  2048: astore_3       
        //  2049: aload_2        
        //  2050: astore          7
        //  2052: aload           29
        //  2054: invokevirtual   java/lang/Object.getClass:()Ljava/lang/Class;
        //  2057: pop            
        //  2058: aload_2        
        //  2059: astore_3       
        //  2060: aload_2        
        //  2061: astore          7
        //  2063: aload           29
        //  2065: invokevirtual   java/lang/String.isEmpty:()Z
        //  2068: iconst_1       
        //  2069: ixor           
        //  2070: ldc_w           "key cannot be empty"
        //  2073: invokestatic    agot.E:(ZLjava/lang/Object;)V
        //  2076: aload_2        
        //  2077: astore_3       
        //  2078: aload_2        
        //  2079: astore          7
        //  2081: getstatic       aicn.a:Laicn;
        //  2084: invokevirtual   agzi.createBuilder:()Lagza;
        //  2087: astore          31
        //  2089: aload_2        
        //  2090: astore_3       
        //  2091: aload_2        
        //  2092: astore          7
        //  2094: aload           31
        //  2096: invokevirtual   agza.copyOnWrite:()V
        //  2099: aload_2        
        //  2100: astore_3       
        //  2101: aload_2        
        //  2102: astore          7
        //  2104: aload           31
        //  2106: getfield        agza.instance:Lagzi;
        //  2109: checkcast       Laicn;
        //  2112: astore          4
        //  2114: aload_2        
        //  2115: astore_3       
        //  2116: aload           4
        //  2118: aload           4
        //  2120: getfield        aicn.b:I
        //  2123: iconst_1       
        //  2124: ior            
        //  2125: putfield        aicn.b:I
        //  2128: aload           4
        //  2130: aload           29
        //  2132: putfield        aicn.c:Ljava/lang/String;
        //  2135: new             Laick;
        //  2138: astore          4
        //  2140: aload           4
        //  2142: aload           31
        //  2144: invokespecial   aick.<init>:(Lagza;)V
        //  2147: aload           4
        //  2149: getfield        aick.a:Lagza;
        //  2152: astore          7
        //  2154: aload           7
        //  2156: invokevirtual   agza.copyOnWrite:()V
        //  2159: aload           7
        //  2161: getfield        agza.instance:Lagzi;
        //  2164: checkcast       Laicn;
        //  2167: astore          7
        //  2169: aload           30
        //  2171: invokevirtual   java/lang/Object.getClass:()Ljava/lang/Class;
        //  2174: pop            
        //  2175: aload           7
        //  2177: aload           7
        //  2179: getfield        aicn.b:I
        //  2182: iconst_2       
        //  2183: ior            
        //  2184: putfield        aicn.b:I
        //  2187: aload           7
        //  2189: aload           30
        //  2191: putfield        aicn.d:Ljava/lang/String;
        //  2194: aload           27
        //  2196: invokevirtual   aouz.f:()Laoux;
        //  2199: astore          27
        //  2201: iconst_1       
        //  2202: anewarray       Ljava/lang/String;
        //  2205: astore          7
        //  2207: aload           7
        //  2209: iconst_0       
        //  2210: aload           29
        //  2212: aastore        
        //  2213: iconst_0       
        //  2214: istore          12
        //  2216: iload           12
        //  2218: ifgt            2302
        //  2221: aload           7
        //  2223: iload           12
        //  2225: aaload         
        //  2226: astore          29
        //  2228: aload           27
        //  2230: getfield        aoux.a:Lagzc;
        //  2233: astore          30
        //  2235: aload           30
        //  2237: invokevirtual   agza.copyOnWrite:()V
        //  2240: aload           30
        //  2242: getfield        agzc.instance:Lagzi;
        //  2245: checkcast       Laova;
        //  2248: astore          31
        //  2250: aload           29
        //  2252: invokevirtual   java/lang/Object.getClass:()Ljava/lang/Class;
        //  2255: pop            
        //  2256: aload           31
        //  2258: getfield        aova.n:Lagzy;
        //  2261: astore          30
        //  2263: aload           30
        //  2265: invokeinterface agzy.c:()Z
        //  2270: ifne            2283
        //  2273: aload           31
        //  2275: aload           30
        //  2277: invokestatic    agzi.mutableCopy:(Lagzy;)Lagzy;
        //  2280: putfield        aova.n:Lagzy;
        //  2283: aload           31
        //  2285: getfield        aova.n:Lagzy;
        //  2288: aload           29
        //  2290: invokeinterface agzy.add:(Ljava/lang/Object;)Z
        //  2295: pop            
        //  2296: iinc            12, 1
        //  2299: goto            2216
        //  2302: aload           27
        //  2304: aload           26
        //  2306: invokevirtual   aoux.b:(Lvdo;)Laouz;
        //  2309: astore          27
        //  2311: aload           26
        //  2313: invokeinterface vce.c:()Lvdv;
        //  2318: astore          7
        //  2320: aload           7
        //  2322: aload           4
        //  2324: invokeinterface vdv.j:(Lvdj;)V
        //  2329: aload           7
        //  2331: aload           27
        //  2333: invokeinterface vdv.d:(Lvdm;)V
        //  2338: aload           7
        //  2340: invokeinterface vdv.b:()Lasgn;
        //  2345: invokevirtual   asgn.X:()V
        //  2348: goto            2359
        //  2351: astore_2       
        //  2352: goto            2391
        //  2355: astore_2       
        //  2356: goto            2391
        //  2359: goto            1938
        //  2362: aload           4
        //  2364: astore_2       
        //  2365: goto            2408
        //  2368: astore_2       
        //  2369: goto            2376
        //  2372: astore_2       
        //  2373: aload           7
        //  2375: astore_3       
        //  2376: goto            2391
        //  2379: astore          7
        //  2381: goto            2386
        //  2384: astore          7
        //  2386: aload_2        
        //  2387: astore_3       
        //  2388: aload           7
        //  2390: astore_2       
        //  2391: ldc_w           "[Offline] Failed saving video subtitles entities "
        //  2394: aload           25
        //  2396: invokestatic    java/lang/String.valueOf:(Ljava/lang/Object;)Ljava/lang/String;
        //  2399: invokevirtual   java/lang/String.concat:(Ljava/lang/String;)Ljava/lang/String;
        //  2402: aload_2        
        //  2403: invokestatic    trn.n:(Ljava/lang/String;Ljava/lang/Throwable;)V
        //  2406: aload_3        
        //  2407: astore_2       
        //  2408: aload_2        
        //  2409: astore_3       
        //  2410: aload_1        
        //  2411: ifnull          2807
        //  2414: aload_2        
        //  2415: astore_3       
        //  2416: aload_0        
        //  2417: getfield        aafd.d:Laaha;
        //  2420: invokevirtual   aaha.c:()Lztk;
        //  2423: invokevirtual   ztk.d:()Z
        //  2426: ifeq            2807
        //  2429: aload_0        
        //  2430: getfield        aafd.x:Laafi;
        //  2433: astore          4
        //  2435: aload           6
        //  2437: invokeinterface com/google/android/libraries/youtube/innertube/model/player/PlayerResponseModel.K:()Ljava/lang/String;
        //  2442: astore          7
        //  2444: aload           4
        //  2446: getfield        aafi.f:Ljava/lang/Object;
        //  2449: astore_3       
        //  2450: aload           4
        //  2452: getfield        aafi.k:Ljava/lang/Object;
        //  2455: checkcast       Labpj;
        //  2458: astore          4
        //  2460: aload           6
        //  2462: aload_3        
        //  2463: checkcast       Landroid/content/Context;
        //  2466: aload           4
        //  2468: invokestatic    abri.g:(Lcom/google/android/libraries/youtube/innertube/model/player/PlayerResponseModel;Landroid/content/Context;Labpj;)Labri;
        //  2471: astore_3       
        //  2472: aload_3        
        //  2473: ifnonnull       2481
        //  2476: aload_2        
        //  2477: astore_3       
        //  2478: goto            2807
        //  2481: aload_3        
        //  2482: invokevirtual   abri.f:()Ljava/util/List;
        //  2485: astore          4
        //  2487: aload_1        
        //  2488: aload           7
        //  2490: invokevirtual   ztu.i:(Ljava/lang/String;)Ljava/util/List;
        //  2493: astore          6
        //  2495: aload_2        
        //  2496: astore_3       
        //  2497: aload           4
        //  2499: invokeinterface java/util/List.isEmpty:()Z
        //  2504: ifne            2807
        //  2507: aload           4
        //  2509: invokeinterface java/util/List.iterator:()Ljava/util/Iterator;
        //  2514: astore          4
        //  2516: aload_2        
        //  2517: astore_3       
        //  2518: aload           4
        //  2520: invokeinterface java/util/Iterator.hasNext:()Z
        //  2525: ifeq            2807
        //  2528: aload           4
        //  2530: invokeinterface java/util/Iterator.next:()Ljava/lang/Object;
        //  2535: checkcast       Lcom/google/android/libraries/youtube/player/subtitles/model/SubtitleTrack;
        //  2538: astore          27
        //  2540: aload           6
        //  2542: aload           27
        //  2544: invokeinterface java/util/List.contains:(Ljava/lang/Object;)Z
        //  2549: ifne            2516
        //  2552: aload           27
        //  2554: invokevirtual   com/google/android/libraries/youtube/player/subtitles/model/SubtitleTrack.t:()Z
        //  2557: ifne            2516
        //  2560: aload           27
        //  2562: invokevirtual   com/google/android/libraries/youtube/player/subtitles/model/SubtitleTrack.r:()Z
        //  2565: ifne            2516
        //  2568: aload           28
        //  2570: aload           7
        //  2572: aload           27
        //  2574: invokeinterface zya.n:(Ljava/lang/String;Lcom/google/android/libraries/youtube/player/subtitles/model/SubtitleTrack;)Ljava/lang/String;
        //  2579: astore          24
        //  2581: invokestatic    com/google/android/libraries/youtube/player/subtitles/model/SubtitleTrack.o:()Labrg;
        //  2584: astore          13
        //  2586: aload           27
        //  2588: invokevirtual   com/google/android/libraries/youtube/player/subtitles/model/SubtitleTrack.d:()Ljava/lang/CharSequence;
        //  2591: astore_3       
        //  2592: aload_3        
        //  2593: ifnull          2605
        //  2596: aload           13
        //  2598: aload_3        
        //  2599: invokevirtual   java/lang/Object.toString:()Ljava/lang/String;
        //  2602: putfield        abrg.b:Ljava/lang/CharSequence;
        //  2605: aload           13
        //  2607: aload           27
        //  2609: invokevirtual   com/google/android/libraries/youtube/player/subtitles/model/SubtitleTrack.e:()Ljava/lang/String;
        //  2612: invokevirtual   abrg.f:(Ljava/lang/String;)V
        //  2615: aload           13
        //  2617: aload           27
        //  2619: invokevirtual   com/google/android/libraries/youtube/player/subtitles/model/SubtitleTrack.k:()Ljava/lang/String;
        //  2622: invokevirtual   abrg.k:(Ljava/lang/String;)V
        //  2625: aload           13
        //  2627: aload           27
        //  2629: invokevirtual   com/google/android/libraries/youtube/player/subtitles/model/SubtitleTrack.l:()Ljava/lang/String;
        //  2632: invokevirtual   abrg.l:(Ljava/lang/String;)V
        //  2635: aload           13
        //  2637: aload           27
        //  2639: invokevirtual   com/google/android/libraries/youtube/player/subtitles/model/SubtitleTrack.j:()Ljava/lang/String;
        //  2642: invokevirtual   abrg.j:(Ljava/lang/String;)V
        //  2645: aload           13
        //  2647: aload           27
        //  2649: invokevirtual   com/google/android/libraries/youtube/player/subtitles/model/SubtitleTrack.f:()Ljava/lang/String;
        //  2652: invokevirtual   abrg.g:(Ljava/lang/String;)V
        //  2655: aload           13
        //  2657: aload           27
        //  2659: invokevirtual   com/google/android/libraries/youtube/player/subtitles/model/SubtitleTrack.i:()Ljava/lang/String;
        //  2662: invokevirtual   abrg.i:(Ljava/lang/String;)V
        //  2665: aload           13
        //  2667: aload           27
        //  2669: invokevirtual   com/google/android/libraries/youtube/player/subtitles/model/SubtitleTrack.b:()I
        //  2672: invokevirtual   abrg.c:(I)V
        //  2675: aload           13
        //  2677: aload           27
        //  2679: invokevirtual   com/google/android/libraries/youtube/player/subtitles/model/SubtitleTrack.h:()Ljava/lang/String;
        //  2682: invokevirtual   abrg.h:(Ljava/lang/String;)V
        //  2685: aload           13
        //  2687: iconst_1       
        //  2688: invokevirtual   abrg.d:(Z)V
        //  2691: aload           13
        //  2693: aload           24
        //  2695: putfield        abrg.a:Ljava/lang/String;
        //  2698: aload_1        
        //  2699: aload           13
        //  2701: invokevirtual   abrg.a:()Lcom/google/android/libraries/youtube/player/subtitles/model/SubtitleTrack;
        //  2704: invokevirtual   ztu.Y:(Lcom/google/android/libraries/youtube/player/subtitles/model/SubtitleTrack;)V
        //  2707: goto            2516
        //  2710: astore_3       
        //  2711: goto            2719
        //  2714: astore_3       
        //  2715: goto            2719
        //  2718: astore_3       
        //  2719: getstatic       zjo.b:Lzjo;
        //  2722: getstatic       zjn.B:Lzjn;
        //  2725: ldc_w           "Offline caption download exception: "
        //  2728: aload_3        
        //  2729: invokevirtual   java/lang/Exception.getMessage:()Ljava/lang/String;
        //  2732: invokestatic    java/lang/String.valueOf:(Ljava/lang/Object;)Ljava/lang/String;
        //  2735: invokevirtual   java/lang/String.concat:(Ljava/lang/String;)Ljava/lang/String;
        //  2738: aload_3        
        //  2739: invokestatic    zjp.c:(Lzjo;Lzjn;Ljava/lang/String;Ljava/lang/Throwable;)V
        //  2742: ldc_w           "[Offline] Failed saving video subtitles "
        //  2745: aload           7
        //  2747: invokestatic    java/lang/String.valueOf:(Ljava/lang/Object;)Ljava/lang/String;
        //  2750: invokevirtual   java/lang/String.concat:(Ljava/lang/String;)Ljava/lang/String;
        //  2753: aload_3        
        //  2754: invokestatic    trn.n:(Ljava/lang/String;Ljava/lang/Throwable;)V
        //  2757: aload_2        
        //  2758: astore_3       
        //  2759: goto            2807
        //  2762: aload_0        
        //  2763: getfield        aafd.m:Ljava/lang/String;
        //  2766: astore          6
        //  2768: new             Ljava/lang/StringBuilder;
        //  2771: astore_3       
        //  2772: aload_3        
        //  2773: invokespecial   java/lang/StringBuilder.<init>:()V
        //  2776: aload_3        
        //  2777: ldc             "[Offline] pudl task cotn ["
        //  2779: invokevirtual   java/lang/StringBuilder.append:(Ljava/lang/String;)Ljava/lang/StringBuilder;
        //  2782: pop            
        //  2783: aload_3        
        //  2784: aload           6
        //  2786: invokevirtual   java/lang/StringBuilder.append:(Ljava/lang/String;)Ljava/lang/StringBuilder;
        //  2789: pop            
        //  2790: aload_3        
        //  2791: ldc_w           "] subtitle failed, no filestore"
        //  2794: invokevirtual   java/lang/StringBuilder.append:(Ljava/lang/String;)Ljava/lang/StringBuilder;
        //  2797: pop            
        //  2798: aload_3        
        //  2799: invokevirtual   java/lang/StringBuilder.toString:()Ljava/lang/String;
        //  2802: invokestatic    trn.b:(Ljava/lang/String;)V
        //  2805: aload_2        
        //  2806: astore_3       
        //  2807: aload_0        
        //  2808: getfield        aafd.F:Lavt;
        //  2811: invokevirtual   avt.Z:()Ljava/lang/String;
        //  2814: astore          6
        //  2816: aload_0        
        //  2817: getfield        aafd.e:Laadr;
        //  2820: astore_2       
        //  2821: aload_0        
        //  2822: getfield        aafd.i:Ljava/lang/String;
        //  2825: astore          7
        //  2827: bipush          18
        //  2829: invokestatic    aaea.a:(I)Laadz;
        //  2832: astore          4
        //  2834: aload           4
        //  2836: aload           7
        //  2838: invokevirtual   aadz.f:(Ljava/lang/String;)V
        //  2841: aload           4
        //  2843: invokevirtual   aadz.a:()Laaea;
        //  2846: astore          7
        //  2848: aload_2        
        //  2849: checkcast       Laaeb;
        //  2852: aload           7
        //  2854: invokevirtual   aaeb.k:(Laaea;)V
        //  2857: aload           10
        //  2859: ifnull          3351
        //  2862: aload           8
        //  2864: ifnull          3351
        //  2867: aload           9
        //  2869: ifnull          3351
        //  2872: aload_0        
        //  2873: getfield        aafd.c:Laeby;
        //  2876: invokevirtual   aeby.bm:()Laeby;
        //  2879: astore          4
        //  2881: aload           4
        //  2883: invokevirtual   aeby.aH:()Laexq;
        //  2886: invokevirtual   aexq.f:()Ljava/lang/Object;
        //  2889: checkcast       Ljava/lang/String;
        //  2892: astore          7
        //  2894: aload_0        
        //  2895: getfield        aafd.o:Lydr;
        //  2898: astore_2       
        //  2899: aload_2        
        //  2900: ifnonnull       2931
        //  2903: aload           4
        //  2905: getfield        aeby.a:Ljava/lang/Object;
        //  2908: checkcast       Laaex;
        //  2911: invokevirtual   aaex.a:()Lydr;
        //  2914: astore_2       
        //  2915: aload_2        
        //  2916: aload_0        
        //  2917: getfield        aafd.p:Laafg;
        //  2920: putfield        ydr.b:Lydq;
        //  2923: aload_0        
        //  2924: aload_2        
        //  2925: putfield        aafd.o:Lydr;
        //  2928: goto            2931
        //  2931: getstatic       amtm.a:Lamtm;
        //  2934: invokevirtual   agzi.createBuilder:()Lagza;
        //  2937: astore          4
        //  2939: aload           4
        //  2941: invokevirtual   agza.copyOnWrite:()V
        //  2944: aload           4
        //  2946: getfield        agza.instance:Lagzi;
        //  2949: checkcast       Lamtm;
        //  2952: astore          9
        //  2954: aload           9
        //  2956: aload           9
        //  2958: getfield        amtm.b:I
        //  2961: iconst_1       
        //  2962: ior            
        //  2963: putfield        amtm.b:I
        //  2966: aload           9
        //  2968: aload           8
        //  2970: putfield        amtm.d:Ljava/lang/String;
        //  2973: aload           4
        //  2975: invokevirtual   agza.copyOnWrite:()V
        //  2978: aload           4
        //  2980: getfield        agza.instance:Lagzi;
        //  2983: checkcast       Lamtm;
        //  2986: astore          9
        //  2988: aload           9
        //  2990: iconst_1       
        //  2991: putfield        amtm.h:I
        //  2994: aload           9
        //  2996: aload           9
        //  2998: getfield        amtm.b:I
        //  3001: bipush          16
        //  3003: ior            
        //  3004: putfield        amtm.b:I
        //  3007: aload           4
        //  3009: invokevirtual   agza.copyOnWrite:()V
        //  3012: aload           4
        //  3014: getfield        agza.instance:Lagzi;
        //  3017: checkcast       Lamtm;
        //  3020: astore          9
        //  3022: aload           6
        //  3024: invokevirtual   java/lang/Object.getClass:()Ljava/lang/Class;
        //  3027: pop            
        //  3028: aload           9
        //  3030: aload           9
        //  3032: getfield        amtm.b:I
        //  3035: iconst_2       
        //  3036: ior            
        //  3037: putfield        amtm.b:I
        //  3040: aload           9
        //  3042: aload           6
        //  3044: putfield        amtm.e:Ljava/lang/String;
        //  3047: aload           4
        //  3049: invokevirtual   agza.copyOnWrite:()V
        //  3052: aload           4
        //  3054: getfield        agza.instance:Lagzi;
        //  3057: checkcast       Lamtm;
        //  3060: astore          9
        //  3062: aload           9
        //  3064: aload           9
        //  3066: getfield        amtm.b:I
        //  3069: ldc_w           32768
        //  3072: ior            
        //  3073: putfield        amtm.b:I
        //  3076: aload           9
        //  3078: iconst_1       
        //  3079: putfield        amtm.q:Z
        //  3082: aload           4
        //  3084: invokevirtual   agza.build:()Lagzi;
        //  3087: checkcast       Lamtm;
        //  3090: astore          4
        //  3092: aload_0        
        //  3093: getfield        aafd.s:Lzym;
        //  3096: aload           4
        //  3098: invokeinterface zym.b:(Lamtm;)V
        //  3103: aload_0        
        //  3104: getfield        aafd.p:Laafg;
        //  3107: aload           8
        //  3109: putfield        aafg.a:Ljava/lang/String;
        //  3112: aload           10
        //  3114: getfield        zze.a:Lzzd;
        //  3117: astore          4
        //  3119: aload           4
        //  3121: iload           23
        //  3123: invokestatic    aafd.e:(Lzzd;Z)Z
        //  3126: istore          5
        //  3128: aload           4
        //  3130: ifnull          3223
        //  3133: aload_0        
        //  3134: getfield        aafd.i:Ljava/lang/String;
        //  3137: astore          13
        //  3139: aload_0        
        //  3140: getfield        aafd.j:Ljava/lang/String;
        //  3143: astore          24
        //  3145: aload           4
        //  3147: invokevirtual   zzd.b:()J
        //  3150: lstore          19
        //  3152: aload_0        
        //  3153: getfield        aafd.f:Laack;
        //  3156: invokeinterface aack.d:()Lzul;
        //  3161: astore          9
        //  3163: aload_0        
        //  3164: getfield        aafd.r:Laafk;
        //  3167: astore          27
        //  3169: aload           8
        //  3171: aload           13
        //  3173: aload           24
        //  3175: aload_2        
        //  3176: aload           4
        //  3178: lload           19
        //  3180: aload           9
        //  3182: aload           7
        //  3184: aload           27
        //  3186: getfield        aafk.c:Lyyt;
        //  3189: aload           27
        //  3191: getfield        aafk.a:Lyyt;
        //  3194: aload_0        
        //  3195: getfield        aafd.E:Lacga;
        //  3198: invokestatic    aafi.o:(Ljava/lang/String;Ljava/lang/String;Ljava/lang/String;Lydr;Lzzd;JLzul;Ljava/lang/String;Lyyt;Lyyt;Lacga;)V
        //  3201: aload_0        
        //  3202: getfield        aafd.p:Laafg;
        //  3205: astore          9
        //  3207: aload           9
        //  3209: aload           9
        //  3211: getfield        aafg.b:J
        //  3214: aload           4
        //  3216: invokevirtual   zzd.b:()J
        //  3219: ladd           
        //  3220: putfield        aafg.b:J
        //  3223: aload_0        
        //  3224: getfield        aafd.A:Z
        //  3227: ifeq            3233
        //  3230: goto            3853
        //  3233: aload           10
        //  3235: getfield        zze.b:Lzzd;
        //  3238: astore          4
        //  3240: aload           4
        //  3242: iload           5
        //  3244: invokestatic    aafd.e:(Lzzd;Z)Z
        //  3247: istore          23
        //  3249: aload           4
        //  3251: ifnull          3341
        //  3254: aload_0        
        //  3255: getfield        aafd.i:Ljava/lang/String;
        //  3258: astore          13
        //  3260: aload_0        
        //  3261: getfield        aafd.j:Ljava/lang/String;
        //  3264: astore          9
        //  3266: aload           4
        //  3268: invokevirtual   zzd.b:()J
        //  3271: lstore          19
        //  3273: aload_0        
        //  3274: getfield        aafd.f:Laack;
        //  3277: invokeinterface aack.d:()Lzul;
        //  3282: astore          24
        //  3284: aload_0        
        //  3285: getfield        aafd.r:Laafk;
        //  3288: astore          10
        //  3290: aload           8
        //  3292: aload           13
        //  3294: aload           9
        //  3296: aload_2        
        //  3297: aload           4
        //  3299: lload           19
        //  3301: aload           24
        //  3303: aload           7
        //  3305: aload           10
        //  3307: getfield        aafk.d:Lyyt;
        //  3310: aload           10
        //  3312: getfield        aafk.b:Lyyt;
        //  3315: aload_0        
        //  3316: getfield        aafd.E:Lacga;
        //  3319: invokestatic    aafi.o:(Ljava/lang/String;Ljava/lang/String;Ljava/lang/String;Lydr;Lzzd;JLzul;Ljava/lang/String;Lyyt;Lyyt;Lacga;)V
        //  3322: aload_0        
        //  3323: getfield        aafd.p:Laafg;
        //  3326: astore_2       
        //  3327: aload_2        
        //  3328: aload_2        
        //  3329: getfield        aafg.b:J
        //  3332: aload           4
        //  3334: invokevirtual   zzd.b:()J
        //  3337: ladd           
        //  3338: putfield        aafg.b:J
        //  3341: aload_0        
        //  3342: getfield        aafd.A:Z
        //  3345: ifne            3853
        //  3348: goto            3351
        //  3351: aload           8
        //  3353: ifnull          3529
        //  3356: aload_1        
        //  3357: ifnull          3529
        //  3360: aload_1        
        //  3361: aload           8
        //  3363: getstatic       zyw.b:Lzyw;
        //  3366: invokevirtual   ztu.F:(Ljava/lang/String;Lzyw;)V
        //  3369: getstatic       amtm.a:Lamtm;
        //  3372: invokevirtual   agzi.createBuilder:()Lagza;
        //  3375: astore_2       
        //  3376: aload_2        
        //  3377: invokevirtual   agza.copyOnWrite:()V
        //  3380: aload_2        
        //  3381: getfield        agza.instance:Lagzi;
        //  3384: checkcast       Lamtm;
        //  3387: astore          7
        //  3389: aload           7
        //  3391: aload           7
        //  3393: getfield        amtm.b:I
        //  3396: iconst_1       
        //  3397: ior            
        //  3398: putfield        amtm.b:I
        //  3401: aload           7
        //  3403: aload           8
        //  3405: putfield        amtm.d:Ljava/lang/String;
        //  3408: aload_2        
        //  3409: invokevirtual   agza.copyOnWrite:()V
        //  3412: aload_2        
        //  3413: getfield        agza.instance:Lagzi;
        //  3416: checkcast       Lamtm;
        //  3419: astore          7
        //  3421: aload           7
        //  3423: aload           7
        //  3425: getfield        amtm.b:I
        //  3428: ldc_w           32768
        //  3431: ior            
        //  3432: putfield        amtm.b:I
        //  3435: aload           7
        //  3437: iconst_1       
        //  3438: putfield        amtm.q:Z
        //  3441: aload_2        
        //  3442: invokevirtual   agza.copyOnWrite:()V
        //  3445: aload_2        
        //  3446: getfield        agza.instance:Lagzi;
        //  3449: checkcast       Lamtm;
        //  3452: astore          7
        //  3454: aload           7
        //  3456: iconst_4       
        //  3457: putfield        amtm.h:I
        //  3460: aload           7
        //  3462: aload           7
        //  3464: getfield        amtm.b:I
        //  3467: bipush          16
        //  3469: ior            
        //  3470: putfield        amtm.b:I
        //  3473: aload_2        
        //  3474: invokevirtual   agza.copyOnWrite:()V
        //  3477: aload_2        
        //  3478: getfield        agza.instance:Lagzi;
        //  3481: checkcast       Lamtm;
        //  3484: astore          7
        //  3486: aload           6
        //  3488: invokevirtual   java/lang/Object.getClass:()Ljava/lang/Class;
        //  3491: pop            
        //  3492: aload           7
        //  3494: aload           7
        //  3496: getfield        amtm.b:I
        //  3499: iconst_2       
        //  3500: ior            
        //  3501: putfield        amtm.b:I
        //  3504: aload           7
        //  3506: aload           6
        //  3508: putfield        amtm.e:Ljava/lang/String;
        //  3511: aload_2        
        //  3512: invokevirtual   agza.build:()Lagzi;
        //  3515: checkcast       Lamtm;
        //  3518: astore_2       
        //  3519: aload_0        
        //  3520: getfield        aafd.s:Lzym;
        //  3523: aload_2        
        //  3524: invokeinterface zym.b:(Lamtm;)V
        //  3529: aload_0        
        //  3530: getfield        aafd.b:Laeby;
        //  3533: invokevirtual   aeby.bm:()Laeby;
        //  3536: astore          7
        //  3538: aload           7
        //  3540: invokevirtual   aeby.aH:()Laexq;
        //  3543: invokevirtual   aexq.f:()Ljava/lang/Object;
        //  3546: checkcast       Ljava/lang/String;
        //  3549: astore          6
        //  3551: aload_0        
        //  3552: getfield        aafd.n:Lydr;
        //  3555: astore_2       
        //  3556: aload_2        
        //  3557: ifnonnull       3588
        //  3560: aload           7
        //  3562: getfield        aeby.a:Ljava/lang/Object;
        //  3565: checkcast       Laaex;
        //  3568: invokevirtual   aaex.a:()Lydr;
        //  3571: astore_2       
        //  3572: aload_2        
        //  3573: aload_0        
        //  3574: getfield        aafd.p:Laafg;
        //  3577: putfield        ydr.b:Lydq;
        //  3580: aload_0        
        //  3581: aload_2        
        //  3582: putfield        aafd.n:Lydr;
        //  3585: goto            3588
        //  3588: aload_0        
        //  3589: getfield        aafd.p:Laafg;
        //  3592: aload_3        
        //  3593: putfield        aafg.a:Ljava/lang/String;
        //  3596: aload           14
        //  3598: getfield        zze.b:Lzzd;
        //  3601: astore          7
        //  3603: aload           7
        //  3605: iload           23
        //  3607: invokestatic    aafd.e:(Lzzd;Z)Z
        //  3610: istore          5
        //  3612: aload           7
        //  3614: ifnull          3706
        //  3617: aload_0        
        //  3618: getfield        aafd.i:Ljava/lang/String;
        //  3621: astore          4
        //  3623: aload_0        
        //  3624: getfield        aafd.j:Ljava/lang/String;
        //  3627: astore          9
        //  3629: aload           7
        //  3631: invokevirtual   zzd.b:()J
        //  3634: lstore          19
        //  3636: aload_0        
        //  3637: getfield        aafd.f:Laack;
        //  3640: invokeinterface aack.d:()Lzul;
        //  3645: astore          10
        //  3647: aload_0        
        //  3648: getfield        aafd.q:Laafk;
        //  3651: astore          13
        //  3653: aload_3        
        //  3654: aload           4
        //  3656: aload           9
        //  3658: aload_2        
        //  3659: aload           7
        //  3661: lload           19
        //  3663: aload           10
        //  3665: aload           6
        //  3667: aload           13
        //  3669: getfield        aafk.d:Lyyt;
        //  3672: aload           13
        //  3674: getfield        aafk.b:Lyyt;
        //  3677: aload_0        
        //  3678: getfield        aafd.E:Lacga;
        //  3681: invokestatic    aafi.o:(Ljava/lang/String;Ljava/lang/String;Ljava/lang/String;Lydr;Lzzd;JLzul;Ljava/lang/String;Lyyt;Lyyt;Lacga;)V
        //  3684: aload_0        
        //  3685: getfield        aafd.p:Laafg;
        //  3688: astore          4
        //  3690: aload           4
        //  3692: aload           4
        //  3694: getfield        aafg.b:J
        //  3697: aload           7
        //  3699: invokevirtual   zzd.b:()J
        //  3702: ladd           
        //  3703: putfield        aafg.b:J
        //  3706: aload_0        
        //  3707: getfield        aafd.A:Z
        //  3710: ifne            3853
        //  3713: aload           14
        //  3715: getfield        zze.a:Lzzd;
        //  3718: astore          7
        //  3720: aload           7
        //  3722: iload           5
        //  3724: invokestatic    aafd.e:(Lzzd;Z)Z
        //  3727: istore          5
        //  3729: aload           7
        //  3731: ifnull          3820
        //  3734: aload_0        
        //  3735: getfield        aafd.i:Ljava/lang/String;
        //  3738: astore          4
        //  3740: aload_0        
        //  3741: getfield        aafd.j:Ljava/lang/String;
        //  3744: astore          14
        //  3746: aload           7
        //  3748: invokevirtual   zzd.b:()J
        //  3751: lstore          19
        //  3753: aload_0        
        //  3754: getfield        aafd.f:Laack;
        //  3757: invokeinterface aack.d:()Lzul;
        //  3762: astore          10
        //  3764: aload_0        
        //  3765: getfield        aafd.q:Laafk;
        //  3768: astore          9
        //  3770: aload_3        
        //  3771: aload           4
        //  3773: aload           14
        //  3775: aload_2        
        //  3776: aload           7
        //  3778: lload           19
        //  3780: aload           10
        //  3782: aload           6
        //  3784: aload           9
        //  3786: getfield        aafk.c:Lyyt;
        //  3789: aload           9
        //  3791: getfield        aafk.a:Lyyt;
        //  3794: aload_0        
        //  3795: getfield        aafd.E:Lacga;
        //  3798: invokestatic    aafi.o:(Ljava/lang/String;Ljava/lang/String;Ljava/lang/String;Lydr;Lzzd;JLzul;Ljava/lang/String;Lyyt;Lyyt;Lacga;)V
        //  3801: aload_0        
        //  3802: getfield        aafd.p:Laafg;
        //  3805: astore_2       
        //  3806: aload_2        
        //  3807: aload_2        
        //  3808: getfield        aafg.b:J
        //  3811: aload           7
        //  3813: invokevirtual   zzd.b:()J
        //  3816: ladd           
        //  3817: putfield        aafg.b:J
        //  3820: aload_0        
        //  3821: getfield        aafd.A:Z
        //  3824: ifne            3853
        //  3827: aload_0        
        //  3828: lload           21
        //  3830: dconst_0       
        //  3831: iload           5
        //  3833: invokevirtual   aafd.b:(JDZ)V
        //  3836: aload_0        
        //  3837: getfield        aafd.e:Laadr;
        //  3840: aload_0        
        //  3841: getfield        aafd.i:Ljava/lang/String;
        //  3844: aload_0        
        //  3845: invokespecial   aafd.c:()Lzyq;
        //  3848: invokeinterface aadr.a:(Ljava/lang/String;Lzyq;)V
        //  3853: aload_0        
        //  3854: getfield        aafd.a:Lyyg;
        //  3857: astore_2       
        //  3858: aload_2        
        //  3859: ifnull          4677
        //  3862: aload_2        
        //  3863: invokevirtual   yyg.g:()V
        //  3866: return         
        //  3867: astore_2       
        //  3868: goto            3947
        //  3871: aload_0        
        //  3872: getfield        aafd.m:Ljava/lang/String;
        //  3875: astore          6
        //  3877: new             Ljava/lang/StringBuilder;
        //  3880: astore_2       
        //  3881: aload_2        
        //  3882: invokespecial   java/lang/StringBuilder.<init>:()V
        //  3885: aload_2        
        //  3886: ldc             "[Offline] pudl task cotn ["
        //  3888: invokevirtual   java/lang/StringBuilder.append:(Ljava/lang/String;)Ljava/lang/StringBuilder;
        //  3891: pop            
        //  3892: aload_2        
        //  3893: aload           6
        //  3895: invokevirtual   java/lang/StringBuilder.append:(Ljava/lang/String;)Ljava/lang/StringBuilder;
        //  3898: pop            
        //  3899: aload_2        
        //  3900: ldc_w           "] error while downloading video"
        //  3903: invokevirtual   java/lang/StringBuilder.append:(Ljava/lang/String;)Ljava/lang/StringBuilder;
        //  3906: pop            
        //  3907: aload_2        
        //  3908: invokevirtual   java/lang/StringBuilder.toString:()Ljava/lang/String;
        //  3911: aload_3        
        //  3912: invokestatic    trn.d:(Ljava/lang/String;Ljava/lang/Throwable;)V
        //  3915: aload_0        
        //  3916: ldc_w           "Error encountered while downloading the video"
        //  3919: aload_3        
        //  3920: getstatic       zyw.d:Lzyw;
        //  3923: getstatic       amtj.w:Lamtj;
        //  3926: invokestatic    aadt.b:(Ljava/lang/String;Ljava/lang/Exception;Lzyw;Lamtj;)Laadt;
        //  3929: invokespecial   aafd.d:(Laadt;)V
        //  3932: return         
        //  3933: aload_0        
        //  3934: aload_0        
        //  3935: getfield        aafd.x:Laafi;
        //  3938: aload_2        
        //  3939: invokevirtual   aafi.a:(Ljava/io/IOException;)Laadt;
        //  3942: invokespecial   aafd.d:(Laadt;)V
        //  3945: return         
        //  3946: astore_2       
        //  3947: aload_0        
        //  3948: getfield        aafd.d:Laaha;
        //  3951: invokevirtual   aaha.l:()Z
        //  3954: ifeq            4709
        //  3957: aload_0        
        //  3958: getfield        aafd.x:Laafi;
        //  3961: astore_2       
        //  3962: aload_0        
        //  3963: getfield        aafd.h:Lzzo;
        //  3966: getfield        zzo.j:Lzkh;
        //  3969: astore_3       
        //  3970: aload_0        
        //  3971: getfield        aafd.k:Ljava/lang/String;
        //  3974: astore          6
        //  3976: aload_2        
        //  3977: getfield        aafi.h:Ljava/lang/Object;
        //  3980: aload_3        
        //  3981: invokeinterface vcf.a:(Lzkh;)Lvce;
        //  3986: astore          7
        //  3988: aload           7
        //  3990: aload           6
        //  3992: invokestatic    aafi.c:(Ljava/lang/String;)Ljava/lang/String;
        //  3995: invokeinterface vce.f:(Ljava/lang/String;)Lasgy;
        //  4000: ldc_w           Laouz;.class
        //  4003: invokevirtual   asgy.j:(Ljava/lang/Class;)Lasgy;
        //  4006: invokevirtual   asgy.af:()Ljava/lang/Object;
        //  4009: checkcast       Laouz;
        //  4012: astore_3       
        //  4013: aload_3        
        //  4014: ifnonnull       4020
        //  4017: goto            4678
        //  4020: aload           7
        //  4022: invokeinterface vce.c:()Lvdv;
        //  4027: astore          7
        //  4029: aload_3        
        //  4030: invokevirtual   aouz.f:()Laoux;
        //  4033: astore_3       
        //  4034: aload_3        
        //  4035: getstatic       aouv.h:Laouv;
        //  4038: invokevirtual   aoux.g:(Laouv;)V
        //  4041: aload           7
        //  4043: aload_3        
        //  4044: invokeinterface vdv.j:(Lvdj;)V
        //  4049: aload           7
        //  4051: invokeinterface vdv.b:()Lasgn;
        //  4056: invokevirtual   asgn.X:()V
        //  4059: aload_2        
        //  4060: getfield        aafi.i:Ljava/lang/Object;
        //  4063: invokeinterface atjj.a:()Ljava/lang/Object;
        //  4068: checkcast       Laaam;
        //  4071: astore_2       
        //  4072: getstatic       amsh.a:Lamsh;
        //  4075: invokevirtual   agzi.createBuilder:()Lagza;
        //  4078: astore_3       
        //  4079: aload_3        
        //  4080: invokevirtual   agza.copyOnWrite:()V
        //  4083: aload_3        
        //  4084: getfield        agza.instance:Lagzi;
        //  4087: checkcast       Lamsh;
        //  4090: astore          7
        //  4092: aload           7
        //  4094: iconst_1       
        //  4095: putfield        amsh.c:I
        //  4098: aload           7
        //  4100: aload           7
        //  4102: getfield        amsh.b:I
        //  4105: iconst_1       
        //  4106: ior            
        //  4107: putfield        amsh.b:I
        //  4110: aload           6
        //  4112: invokestatic    aafi.b:(Ljava/lang/String;)Ljava/lang/String;
        //  4115: astore          7
        //  4117: aload_3        
        //  4118: invokevirtual   agza.copyOnWrite:()V
        //  4121: aload_3        
        //  4122: getfield        agza.instance:Lagzi;
        //  4125: checkcast       Lamsh;
        //  4128: astore          4
        //  4130: aload           7
        //  4132: invokevirtual   java/lang/Object.getClass:()Ljava/lang/Class;
        //  4135: pop            
        //  4136: aload           4
        //  4138: aload           4
        //  4140: getfield        amsh.b:I
        //  4143: iconst_2       
        //  4144: ior            
        //  4145: putfield        amsh.b:I
        //  4148: aload           4
        //  4150: aload           7
        //  4152: putfield        amsh.d:Ljava/lang/String;
        //  4155: getstatic       amsf.b:Lamsf;
        //  4158: invokevirtual   agzi.createBuilder:()Lagza;
        //  4161: checkcast       Lagzc;
        //  4164: astore          7
        //  4166: aload           7
        //  4168: getstatic       amse.c:Lamse;
        //  4171: invokevirtual   agzc.p:(Lamse;)V
        //  4174: aload           7
        //  4176: invokevirtual   agza.copyOnWrite:()V
        //  4179: aload           7
        //  4181: getfield        agzc.instance:Lagzi;
        //  4184: checkcast       Lamsf;
        //  4187: astore          4
        //  4189: aload           4
        //  4191: invokevirtual   amsf.d:()V
        //  4194: aload           4
        //  4196: getfield        amsf.f:Lagzq;
        //  4199: bipush          15
        //  4201: invokeinterface agzq.g:(I)V
        //  4206: getstatic       anar.b:Lagzg;
        //  4209: astore          9
        //  4211: getstatic       anar.a:Lanar;
        //  4214: invokevirtual   agzi.createBuilder:()Lagza;
        //  4217: astore          10
        //  4219: aload           10
        //  4221: invokevirtual   agza.copyOnWrite:()V
        //  4224: aload           10
        //  4226: getfield        agza.instance:Lagzi;
        //  4229: checkcast       Lanar;
        //  4232: astore          4
        //  4234: aload           4
        //  4236: aload           4
        //  4238: getfield        anar.c:I
        //  4241: bipush          16
        //  4243: ior            
        //  4244: putfield        anar.c:I
        //  4247: aload           4
        //  4249: iconst_1       
        //  4250: putfield        anar.g:Z
        //  4253: aload           7
        //  4255: aload           9
        //  4257: aload           10
        //  4259: invokevirtual   agza.build:()Lagzi;
        //  4262: checkcast       Lanar;
        //  4265: invokevirtual   agzc.e:(Lagyr;Ljava/lang/Object;)V
        //  4268: aload           7
        //  4270: invokevirtual   agza.build:()Lagzi;
        //  4273: checkcast       Lamsf;
        //  4276: astore          4
        //  4278: aload_3        
        //  4279: invokevirtual   agza.copyOnWrite:()V
        //  4282: aload_3        
        //  4283: getfield        agza.instance:Lagzi;
        //  4286: checkcast       Lamsh;
        //  4289: astore          7
        //  4291: aload           4
        //  4293: invokevirtual   java/lang/Object.getClass:()Ljava/lang/Class;
        //  4296: pop            
        //  4297: aload           7
        //  4299: aload           4
        //  4301: putfield        amsh.e:Lamsf;
        //  4304: aload           7
        //  4306: aload           7
        //  4308: getfield        amsh.b:I
        //  4311: iconst_4       
        //  4312: ior            
        //  4313: putfield        amsh.b:I
        //  4316: getstatic       amsh.a:Lamsh;
        //  4319: invokevirtual   agzi.createBuilder:()Lagza;
        //  4322: astore          7
        //  4324: aload           7
        //  4326: invokevirtual   agza.copyOnWrite:()V
        //  4329: aload           7
        //  4331: getfield        agza.instance:Lagzi;
        //  4334: checkcast       Lamsh;
        //  4337: astore          4
        //  4339: aload           4
        //  4341: iconst_4       
        //  4342: putfield        amsh.c:I
        //  4345: aload           4
        //  4347: aload           4
        //  4349: getfield        amsh.b:I
        //  4352: iconst_1       
        //  4353: ior            
        //  4354: putfield        amsh.b:I
        //  4357: aload           6
        //  4359: invokestatic    aafi.c:(Ljava/lang/String;)Ljava/lang/String;
        //  4362: astore          4
        //  4364: aload           7
        //  4366: invokevirtual   agza.copyOnWrite:()V
        //  4369: aload           7
        //  4371: getfield        agza.instance:Lagzi;
        //  4374: checkcast       Lamsh;
        //  4377: astore          6
        //  4379: aload           4
        //  4381: invokevirtual   java/lang/Object.getClass:()Ljava/lang/Class;
        //  4384: pop            
        //  4385: aload           6
        //  4387: aload           6
        //  4389: getfield        amsh.b:I
        //  4392: iconst_2       
        //  4393: ior            
        //  4394: putfield        amsh.b:I
        //  4397: aload           6
        //  4399: aload           4
        //  4401: putfield        amsh.d:Ljava/lang/String;
        //  4404: getstatic       amsf.b:Lamsf;
        //  4407: invokevirtual   agzi.createBuilder:()Lagza;
        //  4410: checkcast       Lagzc;
        //  4413: astore          9
        //  4415: getstatic       aouu.b:Lagzg;
        //  4418: astore          6
        //  4420: getstatic       aouu.a:Laouu;
        //  4423: invokevirtual   agzi.createBuilder:()Lagza;
        //  4426: astore          10
        //  4428: aload           10
        //  4430: invokevirtual   agza.copyOnWrite:()V
        //  4433: aload           10
        //  4435: getfield        agza.instance:Lagzi;
        //  4438: checkcast       Laouu;
        //  4441: astore          4
        //  4443: aload           4
        //  4445: aload           4
        //  4447: getfield        aouu.c:I
        //  4450: iconst_4       
        //  4451: ior            
        //  4452: putfield        aouu.c:I
        //  4455: aload           4
        //  4457: iconst_1       
        //  4458: putfield        aouu.f:Z
        //  4461: aload           9
        //  4463: aload           6
        //  4465: aload           10
        //  4467: invokevirtual   agza.build:()Lagzi;
        //  4470: checkcast       Laouu;
        //  4473: invokevirtual   agzc.e:(Lagyr;Ljava/lang/Object;)V
        //  4476: aload           9
        //  4478: invokevirtual   agza.build:()Lagzi;
        //  4481: checkcast       Lamsf;
        //  4484: astore          6
        //  4486: aload           7
        //  4488: invokevirtual   agza.copyOnWrite:()V
        //  4491: aload           7
        //  4493: getfield        agza.instance:Lagzi;
        //  4496: checkcast       Lamsh;
        //  4499: astore          4
        //  4501: aload           6
        //  4503: invokevirtual   java/lang/Object.getClass:()Ljava/lang/Class;
        //  4506: pop            
        //  4507: aload           4
        //  4509: aload           6
        //  4511: putfield        amsh.e:Lamsf;
        //  4514: aload           4
        //  4516: aload           4
        //  4518: getfield        amsh.b:I
        //  4521: iconst_4       
        //  4522: ior            
        //  4523: putfield        amsh.b:I
        //  4526: aload           7
        //  4528: invokevirtual   agza.build:()Lagzi;
        //  4531: checkcast       Lamsh;
        //  4534: astore          6
        //  4536: aload_3        
        //  4537: invokevirtual   agza.copyOnWrite:()V
        //  4540: aload_3        
        //  4541: getfield        agza.instance:Lagzi;
        //  4544: checkcast       Lamsh;
        //  4547: astore          7
        //  4549: aload           6
        //  4551: invokevirtual   java/lang/Object.getClass:()Ljava/lang/Class;
        //  4554: pop            
        //  4555: aload           7
        //  4557: getfield        amsh.g:Lagzy;
        //  4560: astore          4
        //  4562: aload           4
        //  4564: invokeinterface agzy.c:()Z
        //  4569: ifne            4582
        //  4572: aload           7
        //  4574: aload           4
        //  4576: invokestatic    agzi.mutableCopy:(Lagzy;)Lagzy;
        //  4579: putfield        amsh.g:Lagzy;
        //  4582: aload           7
        //  4584: getfield        amsh.g:Lagzy;
        //  4587: aload           6
        //  4589: invokeinterface agzy.add:(Ljava/lang/Object;)Z
        //  4594: pop            
        //  4595: aload_2        
        //  4596: aload_3        
        //  4597: invokevirtual   agza.build:()Lagzi;
        //  4600: checkcast       Lamsh;
        //  4603: invokevirtual   aaam.a:(Lamsh;)Lashe;
        //  4606: pop            
        //  4607: aload_0        
        //  4608: getfield        aafd.e:Laadr;
        //  4611: astore_3       
        //  4612: aload_0        
        //  4613: getfield        aafd.i:Ljava/lang/String;
        //  4616: astore          6
        //  4618: aload_3        
        //  4619: checkcast       Laaeb;
        //  4622: getfield        aaeb.l:Laamd;
        //  4625: aload           6
        //  4627: invokevirtual   aamd.h:(Ljava/lang/String;)Laadh;
        //  4630: astore_2       
        //  4631: aload_2        
        //  4632: ifnull          4677
        //  4635: aload_2        
        //  4636: getstatic       aouv.h:Laouv;
        //  4639: putfield        aadh.j:Laouv;
        //  4642: aload_3        
        //  4643: checkcast       Laaeb;
        //  4646: getfield        aaeb.c:Laaem;
        //  4649: aload           6
        //  4651: invokevirtual   aaem.b:(Ljava/lang/String;)Laads;
        //  4654: pop            
        //  4655: aload_3        
        //  4656: checkcast       Laaeb;
        //  4659: getfield        aaeb.f:Ljava/util/Set;
        //  4662: aload           6
        //  4664: invokeinterface java/util/Set.remove:(Ljava/lang/Object;)Z
        //  4669: pop            
        //  4670: aload_3        
        //  4671: checkcast       Laaeb;
        //  4674: invokevirtual   aaeb.m:()V
        //  4677: return         
        //  4678: aload_0        
        //  4679: getfield        aafd.e:Laadr;
        //  4682: aload_0        
        //  4683: getfield        aafd.i:Ljava/lang/String;
        //  4686: ldc_w           "Internal error. Couldn't enqueue a player response refetch"
        //  4689: aconst_null    
        //  4690: getstatic       zyw.h:Lzyw;
        //  4693: getstatic       amtj.t:Lamtj;
        //  4696: invokestatic    aadt.a:(Ljava/lang/String;Ljava/lang/Exception;Lzyw;Lamtj;)Laadt;
        //  4699: aload_0        
        //  4700: invokespecial   aafd.c:()Lzyq;
        //  4703: invokeinterface aadr.d:(Ljava/lang/String;Laadt;Lzyq;)V
        //  4708: return         
        //  4709: aload_0        
        //  4710: aload_0        
        //  4711: getfield        aafd.x:Laafi;
        //  4714: aload_2        
        //  4715: invokevirtual   aafi.a:(Ljava/io/IOException;)Laadt;
        //  4718: invokespecial   aafd.d:(Laadt;)V
        //  4721: return         
        //  4722: astore_2       
        //  4723: aload_0        
        //  4724: aload_2        
        //  4725: invokespecial   aafd.d:(Laadt;)V
        //  4728: return         
        //  4729: astore          6
        //  4731: aload_0        
        //  4732: getfield        aafd.m:Ljava/lang/String;
        //  4735: astore_2       
        //  4736: new             Ljava/lang/StringBuilder;
        //  4739: dup            
        //  4740: ldc             "[Offline] pudl task cotn ["
        //  4742: invokespecial   java/lang/StringBuilder.<init>:(Ljava/lang/String;)V
        //  4745: astore_3       
        //  4746: aload_3        
        //  4747: aload_2        
        //  4748: invokevirtual   java/lang/StringBuilder.append:(Ljava/lang/String;)Ljava/lang/StringBuilder;
        //  4751: pop            
        //  4752: aload_3        
        //  4753: ldc_w           "] error while pinning video"
        //  4756: invokevirtual   java/lang/StringBuilder.append:(Ljava/lang/String;)Ljava/lang/StringBuilder;
        //  4759: pop            
        //  4760: aload_3        
        //  4761: invokevirtual   java/lang/StringBuilder.toString:()Ljava/lang/String;
        //  4764: aload           6
        //  4766: invokestatic    trn.d:(Ljava/lang/String;Ljava/lang/Throwable;)V
        //  4769: getstatic       zjo.b:Lzjo;
        //  4772: getstatic       zjn.B:Lzjn;
        //  4775: ldc_w           "VideoAd pin exception: "
        //  4778: aload           6
        //  4780: invokevirtual   java/lang/Exception.getMessage:()Ljava/lang/String;
        //  4783: invokestatic    java/lang/String.valueOf:(Ljava/lang/Object;)Ljava/lang/String;
        //  4786: invokevirtual   java/lang/String.concat:(Ljava/lang/String;)Ljava/lang/String;
        //  4789: aload           6
        //  4791: invokestatic    zjp.c:(Lzjo;Lzjn;Ljava/lang/String;Ljava/lang/Throwable;)V
        //  4794: aload_0        
        //  4795: ldc_w           "Error encountered while pinning the video"
        //  4798: aload           6
        //  4800: getstatic       zyw.d:Lzyw;
        //  4803: getstatic       amtj.a:Lamtj;
        //  4806: invokestatic    aadt.b:(Ljava/lang/String;Ljava/lang/Exception;Lzyw;Lamtj;)Laadt;
        //  4809: invokespecial   aafd.d:(Laadt;)V
        //  4812: return         
        //  4813: astore_2       
        //  4814: goto            184
        //  4817: astore_2       
        //  4818: goto            4678
        //    Exceptions:
        //  Try           Handler
        //  Start  End    Start  End    Type                                     
        //  -----  -----  -----  -----  -----------------------------------------
        //  5      25     4729   4813   Ljava/lang/Exception;
        //  32     38     4729   4813   Ljava/lang/Exception;
        //  39     46     4729   4813   Ljava/lang/Exception;
        //  49     84     4729   4813   Ljava/lang/Exception;
        //  85     107    4813   4817   Laadt;
        //  85     107    180    184    Laafe;
        //  85     107    176    3946   Ljava/io/IOException;
        //  85     107    172    3933   Ljava/lang/InterruptedException;
        //  85     107    4729   4813   Ljava/lang/Exception;
        //  110    134    4813   4817   Laadt;
        //  110    134    180    184    Laafe;
        //  110    134    176    3946   Ljava/io/IOException;
        //  110    134    172    3933   Ljava/lang/InterruptedException;
        //  110    134    4729   4813   Ljava/lang/Exception;
        //  138    148    4813   4817   Laadt;
        //  138    148    180    184    Laafe;
        //  138    148    176    3946   Ljava/io/IOException;
        //  138    148    172    3933   Ljava/lang/InterruptedException;
        //  138    148    4729   4813   Ljava/lang/Exception;
        //  160    169    4813   4817   Laadt;
        //  160    169    180    184    Laafe;
        //  160    169    176    3946   Ljava/io/IOException;
        //  160    169    172    3933   Ljava/lang/InterruptedException;
        //  160    169    4729   4813   Ljava/lang/Exception;
        //  184    204    4722   4729   Laadt;
        //  184    204    3946   3947   Laafe;
        //  184    204    176    3946   Ljava/io/IOException;
        //  184    204    172    3933   Ljava/lang/InterruptedException;
        //  184    204    4729   4813   Ljava/lang/Exception;
        //  209    238    4722   4729   Laadt;
        //  209    238    180    184    Laafe;
        //  209    238    176    3946   Ljava/io/IOException;
        //  209    238    172    3933   Ljava/lang/InterruptedException;
        //  209    238    4729   4813   Ljava/lang/Exception;
        //  243    276    4722   4729   Laadt;
        //  243    276    180    184    Laafe;
        //  243    276    176    3946   Ljava/io/IOException;
        //  243    276    172    3933   Ljava/lang/InterruptedException;
        //  243    276    4729   4813   Ljava/lang/Exception;
        //  280    287    4722   4729   Laadt;
        //  280    287    180    184    Laafe;
        //  280    287    176    3946   Ljava/io/IOException;
        //  280    287    172    3933   Ljava/lang/InterruptedException;
        //  280    287    4729   4813   Ljava/lang/Exception;
        //  290    302    4722   4729   Laadt;
        //  290    302    180    184    Laafe;
        //  290    302    176    3946   Ljava/io/IOException;
        //  290    302    172    3933   Ljava/lang/InterruptedException;
        //  290    302    4729   4813   Ljava/lang/Exception;
        //  306    336    4722   4729   Laadt;
        //  306    336    180    184    Laafe;
        //  306    336    176    3946   Ljava/io/IOException;
        //  306    336    172    3933   Ljava/lang/InterruptedException;
        //  306    336    4729   4813   Ljava/lang/Exception;
        //  340    370    4722   4729   Laadt;
        //  340    370    3946   3947   Laafe;
        //  340    370    176    3946   Ljava/io/IOException;
        //  340    370    172    3933   Ljava/lang/InterruptedException;
        //  340    370    4729   4813   Ljava/lang/Exception;
        //  379    416    4722   4729   Laadt;
        //  379    416    180    184    Laafe;
        //  379    416    176    3946   Ljava/io/IOException;
        //  379    416    172    3933   Ljava/lang/InterruptedException;
        //  379    416    4729   4813   Ljava/lang/Exception;
        //  419    474    4722   4729   Laadt;
        //  419    474    3946   3947   Laafe;
        //  419    474    176    3946   Ljava/io/IOException;
        //  419    474    172    3933   Ljava/lang/InterruptedException;
        //  419    474    4729   4813   Ljava/lang/Exception;
        //  479    508    4722   4729   Laadt;
        //  479    508    180    184    Laafe;
        //  479    508    176    3946   Ljava/io/IOException;
        //  479    508    172    3933   Ljava/lang/InterruptedException;
        //  479    508    4729   4813   Ljava/lang/Exception;
        //  514    523    4722   4729   Laadt;
        //  514    523    3946   3947   Laafe;
        //  514    523    176    3946   Ljava/io/IOException;
        //  514    523    172    3933   Ljava/lang/InterruptedException;
        //  514    523    4729   4813   Ljava/lang/Exception;
        //  532    552    4722   4729   Laadt;
        //  532    552    180    184    Laafe;
        //  532    552    176    3946   Ljava/io/IOException;
        //  532    552    172    3933   Ljava/lang/InterruptedException;
        //  532    552    4729   4813   Ljava/lang/Exception;
        //  552    572    4722   4729   Laadt;
        //  552    572    3946   3947   Laafe;
        //  552    572    176    3946   Ljava/io/IOException;
        //  552    572    172    3933   Ljava/lang/InterruptedException;
        //  552    572    4729   4813   Ljava/lang/Exception;
        //  585    596    4722   4729   Laadt;
        //  585    596    180    184    Laafe;
        //  585    596    176    3946   Ljava/io/IOException;
        //  585    596    172    3933   Ljava/lang/InterruptedException;
        //  585    596    4729   4813   Ljava/lang/Exception;
        //  604    608    4722   4729   Laadt;
        //  604    608    180    184    Laafe;
        //  604    608    176    3946   Ljava/io/IOException;
        //  604    608    172    3933   Ljava/lang/InterruptedException;
        //  604    608    4729   4813   Ljava/lang/Exception;
        //  608    614    4722   4729   Laadt;
        //  608    614    180    184    Laafe;
        //  608    614    176    3946   Ljava/io/IOException;
        //  608    614    172    3933   Ljava/lang/InterruptedException;
        //  608    614    4729   4813   Ljava/lang/Exception;
        //  622    626    4722   4729   Laadt;
        //  622    626    180    184    Laafe;
        //  622    626    176    3946   Ljava/io/IOException;
        //  622    626    172    3933   Ljava/lang/InterruptedException;
        //  622    626    4729   4813   Ljava/lang/Exception;
        //  626    635    4722   4729   Laadt;
        //  626    635    180    184    Laafe;
        //  626    635    176    3946   Ljava/io/IOException;
        //  626    635    172    3933   Ljava/lang/InterruptedException;
        //  626    635    4729   4813   Ljava/lang/Exception;
        //  649    658    4722   4729   Laadt;
        //  649    658    180    184    Laafe;
        //  649    658    176    3946   Ljava/io/IOException;
        //  649    658    172    3933   Ljava/lang/InterruptedException;
        //  649    658    4729   4813   Ljava/lang/Exception;
        //  664    750    4722   4729   Laadt;
        //  664    750    3946   3947   Laafe;
        //  664    750    176    3946   Ljava/io/IOException;
        //  664    750    172    3933   Ljava/lang/InterruptedException;
        //  664    750    4729   4813   Ljava/lang/Exception;
        //  759    797    4722   4729   Laadt;
        //  759    797    3946   3947   Laafe;
        //  759    797    176    3946   Ljava/io/IOException;
        //  759    797    172    3933   Ljava/lang/InterruptedException;
        //  759    797    4729   4813   Ljava/lang/Exception;
        //  802    808    4722   4729   Laadt;
        //  802    808    180    184    Laafe;
        //  802    808    176    3946   Ljava/io/IOException;
        //  802    808    172    3933   Ljava/lang/InterruptedException;
        //  802    808    4729   4813   Ljava/lang/Exception;
        //  808    852    855    862    Ljava/lang/RuntimeException;
        //  808    852    180    184    Laafe;
        //  808    852    176    3946   Ljava/io/IOException;
        //  808    852    172    3933   Ljava/lang/InterruptedException;
        //  808    852    4729   4813   Ljava/lang/Exception;
        //  857    862    4722   4729   Laadt;
        //  857    862    180    184    Laafe;
        //  857    862    176    3946   Ljava/io/IOException;
        //  857    862    172    3933   Ljava/lang/InterruptedException;
        //  857    862    4729   4813   Ljava/lang/Exception;
        //  862    874    4722   4729   Laadt;
        //  862    874    3946   3947   Laafe;
        //  862    874    176    3946   Ljava/io/IOException;
        //  862    874    172    3933   Ljava/lang/InterruptedException;
        //  862    874    4729   4813   Ljava/lang/Exception;
        //  879    885    4722   4729   Laadt;
        //  879    885    180    184    Laafe;
        //  879    885    176    3946   Ljava/io/IOException;
        //  879    885    172    3933   Ljava/lang/InterruptedException;
        //  879    885    4729   4813   Ljava/lang/Exception;
        //  890    901    4722   4729   Laadt;
        //  890    901    180    184    Laafe;
        //  890    901    176    3946   Ljava/io/IOException;
        //  890    901    172    3933   Ljava/lang/InterruptedException;
        //  890    901    4729   4813   Ljava/lang/Exception;
        //  911    947    4722   4729   Laadt;
        //  911    947    180    184    Laafe;
        //  911    947    176    3946   Ljava/io/IOException;
        //  911    947    172    3933   Ljava/lang/InterruptedException;
        //  911    947    4729   4813   Ljava/lang/Exception;
        //  953    979    4722   4729   Laadt;
        //  953    979    3946   3947   Laafe;
        //  953    979    176    3946   Ljava/io/IOException;
        //  953    979    172    3933   Ljava/lang/InterruptedException;
        //  953    979    4729   4813   Ljava/lang/Exception;
        //  979    996    4722   4729   Laadt;
        //  979    996    3946   3947   Laafe;
        //  979    996    176    3946   Ljava/io/IOException;
        //  979    996    172    3933   Ljava/lang/InterruptedException;
        //  979    996    4729   4813   Ljava/lang/Exception;
        //  996    1005   4722   4729   Laadt;
        //  996    1005   3946   3947   Laafe;
        //  996    1005   176    3946   Ljava/io/IOException;
        //  996    1005   172    3933   Ljava/lang/InterruptedException;
        //  996    1005   4729   4813   Ljava/lang/Exception;
        //  1010   1033   4722   4729   Laadt;
        //  1010   1033   180    184    Laafe;
        //  1010   1033   176    3946   Ljava/io/IOException;
        //  1010   1033   172    3933   Ljava/lang/InterruptedException;
        //  1010   1033   4729   4813   Ljava/lang/Exception;
        //  1036   1058   4722   4729   Laadt;
        //  1036   1058   3946   3947   Laafe;
        //  1036   1058   176    3946   Ljava/io/IOException;
        //  1036   1058   172    3933   Ljava/lang/InterruptedException;
        //  1036   1058   4729   4813   Ljava/lang/Exception;
        //  1061   1070   4722   4729   Laadt;
        //  1061   1070   3946   3947   Laafe;
        //  1061   1070   176    3946   Ljava/io/IOException;
        //  1061   1070   172    3933   Ljava/lang/InterruptedException;
        //  1061   1070   4729   4813   Ljava/lang/Exception;
        //  1075   1134   4722   4729   Laadt;
        //  1075   1134   180    184    Laafe;
        //  1075   1134   176    3946   Ljava/io/IOException;
        //  1075   1134   172    3933   Ljava/lang/InterruptedException;
        //  1075   1134   4729   4813   Ljava/lang/Exception;
        //  1137   1149   4722   4729   Laadt;
        //  1137   1149   3946   3947   Laafe;
        //  1137   1149   176    3946   Ljava/io/IOException;
        //  1137   1149   172    3933   Ljava/lang/InterruptedException;
        //  1137   1149   4729   4813   Ljava/lang/Exception;
        //  1162   1179   4722   4729   Laadt;
        //  1162   1179   180    184    Laafe;
        //  1162   1179   176    3946   Ljava/io/IOException;
        //  1162   1179   172    3933   Ljava/lang/InterruptedException;
        //  1162   1179   4729   4813   Ljava/lang/Exception;
        //  1186   1194   4722   4729   Laadt;
        //  1186   1194   3946   3947   Laafe;
        //  1186   1194   176    3946   Ljava/io/IOException;
        //  1186   1194   172    3933   Ljava/lang/InterruptedException;
        //  1186   1194   4729   4813   Ljava/lang/Exception;
        //  1194   1202   4722   4729   Laadt;
        //  1194   1202   3946   3947   Laafe;
        //  1194   1202   176    3946   Ljava/io/IOException;
        //  1194   1202   172    3933   Ljava/lang/InterruptedException;
        //  1194   1202   4729   4813   Ljava/lang/Exception;
        //  1207   1241   4722   4729   Laadt;
        //  1207   1241   180    184    Laafe;
        //  1207   1241   176    3946   Ljava/io/IOException;
        //  1207   1241   172    3933   Ljava/lang/InterruptedException;
        //  1207   1241   4729   4813   Ljava/lang/Exception;
        //  1268   1299   4722   4729   Laadt;
        //  1268   1299   3946   3947   Laafe;
        //  1268   1299   176    3946   Ljava/io/IOException;
        //  1268   1299   172    3933   Ljava/lang/InterruptedException;
        //  1268   1299   4729   4813   Ljava/lang/Exception;
        //  1301   1310   4722   4729   Laadt;
        //  1301   1310   3867   3871   Laafe;
        //  1301   1310   176    3946   Ljava/io/IOException;
        //  1301   1310   172    3933   Ljava/lang/InterruptedException;
        //  1301   1310   4729   4813   Ljava/lang/Exception;
        //  1317   1335   4722   4729   Laadt;
        //  1317   1335   3867   3871   Laafe;
        //  1317   1335   176    3946   Ljava/io/IOException;
        //  1317   1335   172    3933   Ljava/lang/InterruptedException;
        //  1317   1335   4729   4813   Ljava/lang/Exception;
        //  1342   1410   4722   4729   Laadt;
        //  1342   1410   3867   3871   Laafe;
        //  1342   1410   176    3946   Ljava/io/IOException;
        //  1342   1410   172    3933   Ljava/lang/InterruptedException;
        //  1342   1410   4729   4813   Ljava/lang/Exception;
        //  1415   1443   4722   4729   Laadt;
        //  1415   1443   3867   3871   Laafe;
        //  1415   1443   176    3946   Ljava/io/IOException;
        //  1415   1443   172    3933   Ljava/lang/InterruptedException;
        //  1415   1443   4729   4813   Ljava/lang/Exception;
        //  1446   1471   4722   4729   Laadt;
        //  1446   1471   3867   3871   Laafe;
        //  1446   1471   176    3946   Ljava/io/IOException;
        //  1446   1471   172    3933   Ljava/lang/InterruptedException;
        //  1446   1471   4729   4813   Ljava/lang/Exception;
        //  1476   1567   4722   4729   Laadt;
        //  1476   1567   3867   3871   Laafe;
        //  1476   1567   176    3946   Ljava/io/IOException;
        //  1476   1567   172    3933   Ljava/lang/InterruptedException;
        //  1476   1567   4729   4813   Ljava/lang/Exception;
        //  1570   1577   4722   4729   Laadt;
        //  1570   1577   3867   3871   Laafe;
        //  1570   1577   176    3946   Ljava/io/IOException;
        //  1570   1577   172    3933   Ljava/lang/InterruptedException;
        //  1570   1577   4729   4813   Ljava/lang/Exception;
        //  1580   1587   4722   4729   Laadt;
        //  1580   1587   3867   3871   Laafe;
        //  1580   1587   176    3946   Ljava/io/IOException;
        //  1580   1587   172    3933   Ljava/lang/InterruptedException;
        //  1580   1587   4729   4813   Ljava/lang/Exception;
        //  1592   1683   4722   4729   Laadt;
        //  1592   1683   3867   3871   Laafe;
        //  1592   1683   176    3946   Ljava/io/IOException;
        //  1592   1683   172    3933   Ljava/lang/InterruptedException;
        //  1592   1683   4729   4813   Ljava/lang/Exception;
        //  1683   1690   4722   4729   Laadt;
        //  1683   1690   3867   3871   Laafe;
        //  1683   1690   176    3946   Ljava/io/IOException;
        //  1683   1690   172    3933   Ljava/lang/InterruptedException;
        //  1683   1690   4729   4813   Ljava/lang/Exception;
        //  1696   1712   4722   4729   Laadt;
        //  1696   1712   3867   3871   Laafe;
        //  1696   1712   176    3946   Ljava/io/IOException;
        //  1696   1712   172    3933   Ljava/lang/InterruptedException;
        //  1696   1712   4729   4813   Ljava/lang/Exception;
        //  1717   1740   4722   4729   Laadt;
        //  1717   1740   3867   3871   Laafe;
        //  1717   1740   176    3946   Ljava/io/IOException;
        //  1717   1740   172    3933   Ljava/lang/InterruptedException;
        //  1717   1740   4729   4813   Ljava/lang/Exception;
        //  1746   1779   4722   4729   Laadt;
        //  1746   1779   3867   3871   Laafe;
        //  1746   1779   176    3946   Ljava/io/IOException;
        //  1746   1779   172    3933   Ljava/lang/InterruptedException;
        //  1746   1779   4729   4813   Ljava/lang/Exception;
        //  1782   1795   4722   4729   Laadt;
        //  1782   1795   3867   3871   Laafe;
        //  1782   1795   176    3946   Ljava/io/IOException;
        //  1782   1795   172    3933   Ljava/lang/InterruptedException;
        //  1782   1795   4729   4813   Ljava/lang/Exception;
        //  1795   1817   2384   2386   Ljava/io/IOException;
        //  1795   1817   2379   2384   Ljava/util/concurrent/ExecutionException;
        //  1795   1817   4722   4729   Laadt;
        //  1795   1817   172    3933   Ljava/lang/InterruptedException;
        //  1795   1817   4729   4813   Ljava/lang/Exception;
        //  1822   1833   2372   2376   Ljava/io/IOException;
        //  1822   1833   2368   2372   Ljava/util/concurrent/ExecutionException;
        //  1822   1833   4722   4729   Laadt;
        //  1822   1833   172    3933   Ljava/lang/InterruptedException;
        //  1822   1833   4729   4813   Ljava/lang/Exception;
        //  1846   1871   2372   2376   Ljava/io/IOException;
        //  1846   1871   2368   2372   Ljava/util/concurrent/ExecutionException;
        //  1846   1871   4722   4729   Laadt;
        //  1846   1871   172    3933   Ljava/lang/InterruptedException;
        //  1846   1871   4729   4813   Ljava/lang/Exception;
        //  1884   1894   2372   2376   Ljava/io/IOException;
        //  1884   1894   2368   2372   Ljava/util/concurrent/ExecutionException;
        //  1884   1894   4722   4729   Laadt;
        //  1884   1894   172    3933   Ljava/lang/InterruptedException;
        //  1884   1894   4729   4813   Ljava/lang/Exception;
        //  1899   1906   2372   2376   Ljava/io/IOException;
        //  1899   1906   2368   2372   Ljava/util/concurrent/ExecutionException;
        //  1899   1906   4722   4729   Laadt;
        //  1899   1906   172    3933   Ljava/lang/InterruptedException;
        //  1899   1906   4729   4813   Ljava/lang/Exception;
        //  1914   1924   2372   2376   Ljava/io/IOException;
        //  1914   1924   2368   2372   Ljava/util/concurrent/ExecutionException;
        //  1914   1924   4722   4729   Laadt;
        //  1914   1924   172    3933   Ljava/lang/InterruptedException;
        //  1914   1924   4729   4813   Ljava/lang/Exception;
        //  1929   1938   2372   2376   Ljava/io/IOException;
        //  1929   1938   2368   2372   Ljava/util/concurrent/ExecutionException;
        //  1929   1938   4722   4729   Laadt;
        //  1929   1938   172    3933   Ljava/lang/InterruptedException;
        //  1929   1938   4729   4813   Ljava/lang/Exception;
        //  1946   1956   2372   2376   Ljava/io/IOException;
        //  1946   1956   2368   2372   Ljava/util/concurrent/ExecutionException;
        //  1946   1956   4722   4729   Laadt;
        //  1946   1956   172    3933   Ljava/lang/InterruptedException;
        //  1946   1956   4729   4813   Ljava/lang/Exception;
        //  1961   1973   2372   2376   Ljava/io/IOException;
        //  1961   1973   2368   2372   Ljava/util/concurrent/ExecutionException;
        //  1961   1973   4722   4729   Laadt;
        //  1961   1973   172    3933   Ljava/lang/InterruptedException;
        //  1961   1973   4729   4813   Ljava/lang/Exception;
        //  1978   1999   2372   2376   Ljava/io/IOException;
        //  1978   1999   2368   2372   Ljava/util/concurrent/ExecutionException;
        //  1978   1999   4722   4729   Laadt;
        //  1978   1999   172    3933   Ljava/lang/InterruptedException;
        //  1978   1999   4729   4813   Ljava/lang/Exception;
        //  2004   2016   2372   2376   Ljava/io/IOException;
        //  2004   2016   2368   2372   Ljava/util/concurrent/ExecutionException;
        //  2004   2016   4722   4729   Laadt;
        //  2004   2016   172    3933   Ljava/lang/InterruptedException;
        //  2004   2016   4729   4813   Ljava/lang/Exception;
        //  2021   2029   2372   2376   Ljava/io/IOException;
        //  2021   2029   2368   2372   Ljava/util/concurrent/ExecutionException;
        //  2021   2029   4722   4729   Laadt;
        //  2021   2029   172    3933   Ljava/lang/InterruptedException;
        //  2021   2029   4729   4813   Ljava/lang/Exception;
        //  2034   2047   2372   2376   Ljava/io/IOException;
        //  2034   2047   2368   2372   Ljava/util/concurrent/ExecutionException;
        //  2034   2047   4722   4729   Laadt;
        //  2034   2047   172    3933   Ljava/lang/InterruptedException;
        //  2034   2047   4729   4813   Ljava/lang/Exception;
        //  2052   2058   2372   2376   Ljava/io/IOException;
        //  2052   2058   2368   2372   Ljava/util/concurrent/ExecutionException;
        //  2052   2058   4722   4729   Laadt;
        //  2052   2058   172    3933   Ljava/lang/InterruptedException;
        //  2052   2058   4729   4813   Ljava/lang/Exception;
        //  2063   2076   2372   2376   Ljava/io/IOException;
        //  2063   2076   2368   2372   Ljava/util/concurrent/ExecutionException;
        //  2063   2076   4722   4729   Laadt;
        //  2063   2076   172    3933   Ljava/lang/InterruptedException;
        //  2063   2076   4729   4813   Ljava/lang/Exception;
        //  2081   2089   2372   2376   Ljava/io/IOException;
        //  2081   2089   2368   2372   Ljava/util/concurrent/ExecutionException;
        //  2081   2089   4722   4729   Laadt;
        //  2081   2089   172    3933   Ljava/lang/InterruptedException;
        //  2081   2089   4729   4813   Ljava/lang/Exception;
        //  2094   2099   2372   2376   Ljava/io/IOException;
        //  2094   2099   2368   2372   Ljava/util/concurrent/ExecutionException;
        //  2094   2099   4722   4729   Laadt;
        //  2094   2099   172    3933   Ljava/lang/InterruptedException;
        //  2094   2099   4729   4813   Ljava/lang/Exception;
        //  2104   2114   2372   2376   Ljava/io/IOException;
        //  2104   2114   2368   2372   Ljava/util/concurrent/ExecutionException;
        //  2104   2114   4722   4729   Laadt;
        //  2104   2114   172    3933   Ljava/lang/InterruptedException;
        //  2104   2114   4729   4813   Ljava/lang/Exception;
        //  2116   2207   2355   2359   Ljava/io/IOException;
        //  2116   2207   2351   2355   Ljava/util/concurrent/ExecutionException;
        //  2116   2207   4722   4729   Laadt;
        //  2116   2207   172    3933   Ljava/lang/InterruptedException;
        //  2116   2207   4729   4813   Ljava/lang/Exception;
        //  2228   2283   2355   2359   Ljava/io/IOException;
        //  2228   2283   2351   2355   Ljava/util/concurrent/ExecutionException;
        //  2228   2283   4722   4729   Laadt;
        //  2228   2283   172    3933   Ljava/lang/InterruptedException;
        //  2228   2283   4729   4813   Ljava/lang/Exception;
        //  2283   2296   2355   2359   Ljava/io/IOException;
        //  2283   2296   2351   2355   Ljava/util/concurrent/ExecutionException;
        //  2283   2296   4722   4729   Laadt;
        //  2283   2296   172    3933   Ljava/lang/InterruptedException;
        //  2283   2296   4729   4813   Ljava/lang/Exception;
        //  2302   2348   2355   2359   Ljava/io/IOException;
        //  2302   2348   2351   2355   Ljava/util/concurrent/ExecutionException;
        //  2302   2348   4722   4729   Laadt;
        //  2302   2348   172    3933   Ljava/lang/InterruptedException;
        //  2302   2348   4729   4813   Ljava/lang/Exception;
        //  2391   2406   4722   4729   Laadt;
        //  2391   2406   3867   3871   Laafe;
        //  2391   2406   176    3946   Ljava/io/IOException;
        //  2391   2406   172    3933   Ljava/lang/InterruptedException;
        //  2391   2406   4729   4813   Ljava/lang/Exception;
        //  2416   2444   4722   4729   Laadt;
        //  2416   2444   3867   3871   Laafe;
        //  2416   2444   176    3946   Ljava/io/IOException;
        //  2416   2444   172    3933   Ljava/lang/InterruptedException;
        //  2416   2444   4729   4813   Ljava/lang/Exception;
        //  2444   2472   2718   2719   Ljava/io/IOException;
        //  2444   2472   2714   2718   Ljava/util/concurrent/ExecutionException;
        //  2444   2472   2710   2714   Ljava/lang/RuntimeException;
        //  2444   2472   172    3933   Ljava/lang/InterruptedException;
        //  2444   2472   4729   4813   Ljava/lang/Exception;
        //  2481   2495   2718   2719   Ljava/io/IOException;
        //  2481   2495   2714   2718   Ljava/util/concurrent/ExecutionException;
        //  2481   2495   2710   2714   Ljava/lang/RuntimeException;
        //  2481   2495   172    3933   Ljava/lang/InterruptedException;
        //  2481   2495   4729   4813   Ljava/lang/Exception;
        //  2497   2516   2718   2719   Ljava/io/IOException;
        //  2497   2516   2714   2718   Ljava/util/concurrent/ExecutionException;
        //  2497   2516   2710   2714   Ljava/lang/RuntimeException;
        //  2497   2516   172    3933   Ljava/lang/InterruptedException;
        //  2497   2516   4729   4813   Ljava/lang/Exception;
        //  2518   2592   2718   2719   Ljava/io/IOException;
        //  2518   2592   2714   2718   Ljava/util/concurrent/ExecutionException;
        //  2518   2592   2710   2714   Ljava/lang/RuntimeException;
        //  2518   2592   172    3933   Ljava/lang/InterruptedException;
        //  2518   2592   4729   4813   Ljava/lang/Exception;
        //  2596   2605   2718   2719   Ljava/io/IOException;
        //  2596   2605   2714   2718   Ljava/util/concurrent/ExecutionException;
        //  2596   2605   2710   2714   Ljava/lang/RuntimeException;
        //  2596   2605   172    3933   Ljava/lang/InterruptedException;
        //  2596   2605   4729   4813   Ljava/lang/Exception;
        //  2605   2707   2718   2719   Ljava/io/IOException;
        //  2605   2707   2714   2718   Ljava/util/concurrent/ExecutionException;
        //  2605   2707   2710   2714   Ljava/lang/RuntimeException;
        //  2605   2707   172    3933   Ljava/lang/InterruptedException;
        //  2605   2707   4729   4813   Ljava/lang/Exception;
        //  2719   2757   4722   4729   Laadt;
        //  2719   2757   3867   3871   Laafe;
        //  2719   2757   176    3946   Ljava/io/IOException;
        //  2719   2757   172    3933   Ljava/lang/InterruptedException;
        //  2719   2757   4729   4813   Ljava/lang/Exception;
        //  2762   2805   4722   4729   Laadt;
        //  2762   2805   3867   3871   Laafe;
        //  2762   2805   176    3946   Ljava/io/IOException;
        //  2762   2805   172    3933   Ljava/lang/InterruptedException;
        //  2762   2805   4729   4813   Ljava/lang/Exception;
        //  2807   2857   4722   4729   Laadt;
        //  2807   2857   3867   3871   Laafe;
        //  2807   2857   176    3946   Ljava/io/IOException;
        //  2807   2857   172    3933   Ljava/lang/InterruptedException;
        //  2807   2857   4729   4813   Ljava/lang/Exception;
        //  2872   2899   4722   4729   Laadt;
        //  2872   2899   3867   3871   Laafe;
        //  2872   2899   176    3946   Ljava/io/IOException;
        //  2872   2899   172    3933   Ljava/lang/InterruptedException;
        //  2872   2899   4729   4813   Ljava/lang/Exception;
        //  2903   2928   4722   4729   Laadt;
        //  2903   2928   3867   3871   Laafe;
        //  2903   2928   176    3946   Ljava/io/IOException;
        //  2903   2928   172    3933   Ljava/lang/InterruptedException;
        //  2903   2928   4729   4813   Ljava/lang/Exception;
        //  2931   3128   4722   4729   Laadt;
        //  2931   3128   3867   3871   Laafe;
        //  2931   3128   176    3946   Ljava/io/IOException;
        //  2931   3128   172    3933   Ljava/lang/InterruptedException;
        //  2931   3128   4729   4813   Ljava/lang/Exception;
        //  3133   3223   4722   4729   Laadt;
        //  3133   3223   3867   3871   Laafe;
        //  3133   3223   176    3946   Ljava/io/IOException;
        //  3133   3223   172    3933   Ljava/lang/InterruptedException;
        //  3133   3223   4729   4813   Ljava/lang/Exception;
        //  3223   3230   4722   4729   Laadt;
        //  3223   3230   3867   3871   Laafe;
        //  3223   3230   176    3946   Ljava/io/IOException;
        //  3223   3230   172    3933   Ljava/lang/InterruptedException;
        //  3223   3230   4729   4813   Ljava/lang/Exception;
        //  3233   3249   4722   4729   Laadt;
        //  3233   3249   3867   3871   Laafe;
        //  3233   3249   176    3946   Ljava/io/IOException;
        //  3233   3249   172    3933   Ljava/lang/InterruptedException;
        //  3233   3249   4729   4813   Ljava/lang/Exception;
        //  3254   3341   4722   4729   Laadt;
        //  3254   3341   3867   3871   Laafe;
        //  3254   3341   176    3946   Ljava/io/IOException;
        //  3254   3341   172    3933   Ljava/lang/InterruptedException;
        //  3254   3341   4729   4813   Ljava/lang/Exception;
        //  3341   3348   4722   4729   Laadt;
        //  3341   3348   3867   3871   Laafe;
        //  3341   3348   176    3946   Ljava/io/IOException;
        //  3341   3348   172    3933   Ljava/lang/InterruptedException;
        //  3341   3348   4729   4813   Ljava/lang/Exception;
        //  3360   3529   4722   4729   Laadt;
        //  3360   3529   3867   3871   Laafe;
        //  3360   3529   176    3946   Ljava/io/IOException;
        //  3360   3529   172    3933   Ljava/lang/InterruptedException;
        //  3360   3529   4729   4813   Ljava/lang/Exception;
        //  3529   3556   4722   4729   Laadt;
        //  3529   3556   3867   3871   Laafe;
        //  3529   3556   176    3946   Ljava/io/IOException;
        //  3529   3556   172    3933   Ljava/lang/InterruptedException;
        //  3529   3556   4729   4813   Ljava/lang/Exception;
        //  3560   3585   4722   4729   Laadt;
        //  3560   3585   3867   3871   Laafe;
        //  3560   3585   176    3946   Ljava/io/IOException;
        //  3560   3585   172    3933   Ljava/lang/InterruptedException;
        //  3560   3585   4729   4813   Ljava/lang/Exception;
        //  3588   3612   4722   4729   Laadt;
        //  3588   3612   3867   3871   Laafe;
        //  3588   3612   176    3946   Ljava/io/IOException;
        //  3588   3612   172    3933   Ljava/lang/InterruptedException;
        //  3588   3612   4729   4813   Ljava/lang/Exception;
        //  3617   3706   4722   4729   Laadt;
        //  3617   3706   3867   3871   Laafe;
        //  3617   3706   176    3946   Ljava/io/IOException;
        //  3617   3706   172    3933   Ljava/lang/InterruptedException;
        //  3617   3706   4729   4813   Ljava/lang/Exception;
        //  3706   3729   4722   4729   Laadt;
        //  3706   3729   3867   3871   Laafe;
        //  3706   3729   176    3946   Ljava/io/IOException;
        //  3706   3729   172    3933   Ljava/lang/InterruptedException;
        //  3706   3729   4729   4813   Ljava/lang/Exception;
        //  3734   3820   4722   4729   Laadt;
        //  3734   3820   3867   3871   Laafe;
        //  3734   3820   176    3946   Ljava/io/IOException;
        //  3734   3820   172    3933   Ljava/lang/InterruptedException;
        //  3734   3820   4729   4813   Ljava/lang/Exception;
        //  3820   3853   4722   4729   Laadt;
        //  3820   3853   3867   3871   Laafe;
        //  3820   3853   176    3946   Ljava/io/IOException;
        //  3820   3853   172    3933   Ljava/lang/InterruptedException;
        //  3820   3853   4729   4813   Ljava/lang/Exception;
        //  3853   3858   4722   4729   Laadt;
        //  3853   3858   3867   3871   Laafe;
        //  3853   3858   176    3946   Ljava/io/IOException;
        //  3853   3858   172    3933   Ljava/lang/InterruptedException;
        //  3853   3858   4729   4813   Ljava/lang/Exception;
        //  3862   3866   4722   4729   Laadt;
        //  3862   3866   3867   3871   Laafe;
        //  3862   3866   176    3946   Ljava/io/IOException;
        //  3862   3866   172    3933   Ljava/lang/InterruptedException;
        //  3862   3866   4729   4813   Ljava/lang/Exception;
        //  3871   3932   4729   4813   Ljava/lang/Exception;
        //  3933   3945   4729   4813   Ljava/lang/Exception;
        //  3947   4013   4729   4813   Ljava/lang/Exception;
        //  4020   4059   4729   4813   Ljava/lang/Exception;
        //  4059   4582   4817   4821   Laaan;
        //  4059   4582   4729   4813   Ljava/lang/Exception;
        //  4582   4607   4817   4821   Laaan;
        //  4582   4607   4729   4813   Ljava/lang/Exception;
        //  4607   4631   4729   4813   Ljava/lang/Exception;
        //  4635   4677   4729   4813   Ljava/lang/Exception;
        //  4678   4708   4729   4813   Ljava/lang/Exception;
        //  4709   4721   4729   4813   Ljava/lang/Exception;
        //  4723   4728   4729   4813   Ljava/lang/Exception;
        // 
        // The error that occurred was:
        // 
        // java.lang.IndexOutOfBoundsException: Index: 2151, Size: 2151
        //     at java.util.ArrayList.rangeCheck(Unknown Source)
        //     at java.util.ArrayList.get(Unknown Source)
        //     at com.strobel.decompiler.ast.AstBuilder.convertToAst(AstBuilder.java:3362)
        //     at com.strobel.decompiler.ast.AstBuilder.build(AstBuilder.java:112)
        //     at com.strobel.decompiler.languages.java.ast.AstMethodBodyBuilder.createMethodBody(AstMethodBodyBuilder.java:203)
        //     at com.strobel.decompiler.languages.java.ast.AstMethodBodyBuilder.createMethodBody(AstMethodBodyBuilder.java:93)
        //     at com.strobel.decompiler.languages.java.ast.AstBuilder.createMethodBody(AstBuilder.java:868)
        //     at com.strobel.decompiler.languages.java.ast.AstBuilder.createMethod(AstBuilder.java:761)
        //     at com.strobel.decompiler.languages.java.ast.AstBuilder.addTypeMembers(AstBuilder.java:638)
        //     at com.strobel.decompiler.languages.java.ast.AstBuilder.createTypeCore(AstBuilder.java:605)
        //     at com.strobel.decompiler.languages.java.ast.AstBuilder.createTypeNoCache(AstBuilder.java:195)
        //     at com.strobel.decompiler.languages.java.ast.AstBuilder.createType(AstBuilder.java:162)
        //     at com.strobel.decompiler.languages.java.ast.AstBuilder.addType(AstBuilder.java:137)
        //     at com.strobel.decompiler.languages.java.JavaLanguage.buildAst(JavaLanguage.java:71)
        //     at com.strobel.decompiler.languages.java.JavaLanguage.decompileType(JavaLanguage.java:59)
        //     at com.strobel.decompiler.DecompilerDriver.decompileType(DecompilerDriver.java:333)
        //     at com.strobel.decompiler.DecompilerDriver.decompileJar(DecompilerDriver.java:254)
        //     at com.strobel.decompiler.DecompilerDriver.main(DecompilerDriver.java:129)
        // 
        throw new IllegalStateException("An error occurred while decompiling this method.");
    }
}
