import java.util.Arrays;
import java.util.ArrayList;
import java.util.HashSet;
import java.lang.ref.WeakReference;

// 
// Decompiled by Procyon v0.6.0
// 

public final class acs extends acy
{
    public final adc a;
    public WeakReference aA;
    public WeakReference aB;
    public WeakReference aC;
    public WeakReference aD;
    final HashSet aE;
    public final acz aF;
    public adr aG;
    public final aja aH;
    public int ar;
    public int as;
    public int at;
    public int au;
    public acp[] av;
    public acp[] aw;
    public int ax;
    public boolean ay;
    public boolean az;
    public int b;
    public boolean c;
    public final acj d;
    
    public acs() {
        this.aH = new aja(this);
        this.a = new adc(this);
        this.aG = null;
        this.c = false;
        this.d = new acj();
        this.at = 0;
        this.au = 0;
        this.av = new acp[4];
        this.aw = new acp[4];
        this.ax = 257;
        this.ay = false;
        this.az = false;
        this.aA = null;
        this.aB = null;
        this.aC = null;
        this.aD = null;
        this.aE = new HashSet();
        this.aF = new acz();
    }
    
    public static void X(final acr acr, final adr adr, final acz acz) {
        if (adr == null) {
            return;
        }
        if (acr.ah != 8 && !(acr instanceof acu) && !(acr instanceof aco)) {
            acz.i = acr.M();
            acz.j = acr.N();
            acz.a = acr.j();
            acz.b = acr.h();
            acz.g = false;
            acz.h = 0;
            final boolean b = acz.i == 3;
            final boolean b2 = acz.j == 3;
            final boolean b3 = b && acr.X > 0.0f;
            final boolean b4 = b2 && acr.X > 0.0f;
            int n;
            if ((n = (b ? 1 : 0)) != 0) {
                n = (b ? 1 : 0);
                if (acr.F(0)) {
                    n = (b ? 1 : 0);
                    if (acr.s == 0) {
                        n = (b ? 1 : 0);
                        if (!b3) {
                            acz.i = 2;
                            if (b2 && acr.t == 0) {
                                acz.i = 1;
                            }
                            n = 0;
                        }
                    }
                }
            }
            boolean b5;
            if (b5 = b2) {
                b5 = b2;
                if (acr.F(1)) {
                    b5 = b2;
                    if (acr.t == 0) {
                        b5 = b2;
                        if (!b4) {
                            acz.j = 2;
                            if (n != 0 && acr.s == 0) {
                                acz.j = 1;
                            }
                            b5 = false;
                        }
                    }
                }
            }
            if (acr.e()) {
                acz.i = 1;
                n = 0;
            }
            if (acr.f()) {
                acz.j = 1;
                b5 = false;
            }
            if (b3) {
                if (acr.u[0] == 4) {
                    acz.i = 1;
                }
                else if (!b5) {
                    int n2;
                    if (acz.j == 1) {
                        n2 = acz.b;
                    }
                    else {
                        acz.i = 2;
                        adr.a(acr, acz);
                        n2 = acz.d;
                    }
                    acz.i = 1;
                    acz.a = (int)(acr.X * n2);
                }
            }
            if (b4) {
                if (acr.u[1] == 4) {
                    acz.j = 1;
                }
                else if (n == 0) {
                    int n3;
                    if (acz.i == 1) {
                        n3 = acz.a;
                    }
                    else {
                        acz.j = 2;
                        adr.a(acr, acz);
                        n3 = acz.c;
                    }
                    acz.j = 1;
                    if (acr.Y == -1) {
                        acz.b = (int)(n3 / acr.X);
                    }
                    else {
                        acz.b = (int)(acr.X * n3);
                    }
                }
            }
            adr.a(acr, acz);
            acr.C(acz.c);
            acr.x(acz.d);
            acr.F = acz.f;
            acr.u(acz.e);
            acz.h = 0;
            final boolean g = acz.g;
            return;
        }
        acz.c = 0;
        acz.d = 0;
    }
    
    private final void Z(final acq acq, final acm acm) {
        this.d.g(acm, this.d.b((Object)acq), 0, 5);
    }
    
    private final void aa(final acq acq, final acm acm) {
        this.d.g(this.d.b((Object)acq), acm, 0, 5);
    }
    
    private final void ab() {
        this.at = 0;
        this.au = 0;
    }
    
    @Override
    public final void D(final boolean b, final boolean b2) {
        super.D(b, b2);
        for (int size = this.aI.size(), i = 0; i < size; ++i) {
            ((acr)this.aI.get(i)).D(b, b2);
        }
    }
    
    @Override
    public final void T() {
        // 
        // This method could not be decompiled.
        // 
        // Original Bytecode:
        // 
        //     1: iconst_0       
        //     2: putfield        acs.Z:I
        //     5: aload_0        
        //     6: iconst_0       
        //     7: putfield        acs.aa:I
        //    10: aload_0        
        //    11: iconst_0       
        //    12: putfield        acs.ay:Z
        //    15: aload_0        
        //    16: iconst_0       
        //    17: putfield        acs.az:Z
        //    20: aload_0        
        //    21: getfield        acs.aI:Ljava/util/ArrayList;
        //    24: invokevirtual   java/util/ArrayList.size:()I
        //    27: istore_1       
        //    28: iconst_0       
        //    29: aload_0        
        //    30: invokevirtual   acr.j:()I
        //    33: invokestatic    java/lang/Math.max:(II)I
        //    36: istore_2       
        //    37: iconst_0       
        //    38: aload_0        
        //    39: invokevirtual   acr.h:()I
        //    42: invokestatic    java/lang/Math.max:(II)I
        //    45: istore_3       
        //    46: aload_0        
        //    47: getfield        acs.aq:[I
        //    50: astore          4
        //    52: aload           4
        //    54: iconst_1       
        //    55: iaload         
        //    56: istore          5
        //    58: aload           4
        //    60: iconst_0       
        //    61: iaload         
        //    62: istore          6
        //    64: aload_0        
        //    65: getfield        acs.b:I
        //    68: ifne            1185
        //    71: aload_0        
        //    72: getfield        acs.ax:I
        //    75: iconst_1       
        //    76: invokestatic    acw.b:(II)Z
        //    79: ifeq            1185
        //    82: aload_0        
        //    83: getfield        acs.aG:Ladr;
        //    86: astore          7
        //    88: aload_0        
        //    89: invokevirtual   acr.M:()I
        //    92: istore          8
        //    94: aload_0        
        //    95: invokevirtual   acr.N:()I
        //    98: istore          9
        //   100: iconst_0       
        //   101: putstatic       adf.b:I
        //   104: iconst_0       
        //   105: putstatic       adf.c:I
        //   108: aload_0        
        //   109: invokevirtual   acr.t:()V
        //   112: aload_0        
        //   113: getfield        acy.aI:Ljava/util/ArrayList;
        //   116: astore          4
        //   118: aload           4
        //   120: invokevirtual   java/util/ArrayList.size:()I
        //   123: istore          10
        //   125: iconst_0       
        //   126: istore          11
        //   128: iload           11
        //   130: iload           10
        //   132: if_icmpge       154
        //   135: aload           4
        //   137: iload           11
        //   139: invokevirtual   java/util/ArrayList.get:(I)Ljava/lang/Object;
        //   142: checkcast       Lacr;
        //   145: invokevirtual   acr.t:()V
        //   148: iinc            11, 1
        //   151: goto            128
        //   154: aload_0        
        //   155: getfield        acs.c:Z
        //   158: istore          12
        //   160: iload           8
        //   162: iconst_1       
        //   163: if_icmpne       178
        //   166: aload_0        
        //   167: iconst_0       
        //   168: aload_0        
        //   169: invokevirtual   acr.j:()I
        //   172: invokevirtual   acr.v:(II)V
        //   175: goto            191
        //   178: aload_0        
        //   179: getfield        acr.J:Lacq;
        //   182: iconst_0       
        //   183: invokevirtual   acq.e:(I)V
        //   186: aload_0        
        //   187: iconst_0       
        //   188: putfield        acr.Z:I
        //   191: iconst_0       
        //   192: istore          8
        //   194: iconst_0       
        //   195: istore          13
        //   197: iconst_0       
        //   198: istore          11
        //   200: iload           8
        //   202: iload           10
        //   204: if_icmpge       402
        //   207: aload           4
        //   209: iload           8
        //   211: invokevirtual   java/util/ArrayList.get:(I)Ljava/lang/Object;
        //   214: checkcast       Lacr;
        //   217: astore          14
        //   219: aload           14
        //   221: instanceof      Lacu;
        //   224: ifeq            346
        //   227: aload           14
        //   229: checkcast       Lacu;
        //   232: astore          14
        //   234: iload           13
        //   236: istore          15
        //   238: iload           11
        //   240: istore          16
        //   242: aload           14
        //   244: getfield        acu.ar:I
        //   247: iconst_1       
        //   248: if_icmpne       388
        //   251: aload           14
        //   253: getfield        acu.b:I
        //   256: istore          13
        //   258: iload           13
        //   260: iconst_m1      
        //   261: if_icmpeq       281
        //   264: aload           14
        //   266: iload           13
        //   268: invokevirtual   acu.a:(I)V
        //   271: iconst_1       
        //   272: istore          15
        //   274: iload           11
        //   276: istore          16
        //   278: goto            388
        //   281: aload           14
        //   283: getfield        acu.c:I
        //   286: iconst_m1      
        //   287: if_icmpeq       315
        //   290: aload_0        
        //   291: invokevirtual   acr.e:()Z
        //   294: ifeq            315
        //   297: aload           14
        //   299: aload_0        
        //   300: invokevirtual   acr.j:()I
        //   303: aload           14
        //   305: getfield        acu.c:I
        //   308: isub           
        //   309: invokevirtual   acu.a:(I)V
        //   312: goto            271
        //   315: aload_0        
        //   316: invokevirtual   acr.e:()Z
        //   319: ifeq            271
        //   322: aload           14
        //   324: aload           14
        //   326: getfield        acu.a:F
        //   329: aload_0        
        //   330: invokevirtual   acr.j:()I
        //   333: i2f            
        //   334: fmul           
        //   335: ldc_w           0.5
        //   338: fadd           
        //   339: f2i            
        //   340: invokevirtual   acu.a:(I)V
        //   343: goto            271
        //   346: iload           13
        //   348: istore          15
        //   350: iload           11
        //   352: istore          16
        //   354: aload           14
        //   356: instanceof      Laco;
        //   359: ifeq            388
        //   362: iload           13
        //   364: istore          15
        //   366: iload           11
        //   368: istore          16
        //   370: aload           14
        //   372: checkcast       Laco;
        //   375: invokevirtual   aco.a:()I
        //   378: ifne            388
        //   381: iconst_1       
        //   382: istore          16
        //   384: iload           13
        //   386: istore          15
        //   388: iinc            8, 1
        //   391: iload           15
        //   393: istore          13
        //   395: iload           16
        //   397: istore          11
        //   399: goto            200
        //   402: iload           13
        //   404: ifeq            472
        //   407: iconst_0       
        //   408: istore          8
        //   410: iload           8
        //   412: iload           10
        //   414: if_icmpge       472
        //   417: aload           4
        //   419: iload           8
        //   421: invokevirtual   java/util/ArrayList.get:(I)Ljava/lang/Object;
        //   424: checkcast       Lacr;
        //   427: astore          14
        //   429: aload           14
        //   431: instanceof      Lacu;
        //   434: ifeq            466
        //   437: aload           14
        //   439: checkcast       Lacu;
        //   442: astore          14
        //   444: aload           14
        //   446: getfield        acu.ar:I
        //   449: iconst_1       
        //   450: if_icmpne       466
        //   453: iconst_0       
        //   454: aload           14
        //   456: aload           7
        //   458: iload           12
        //   460: invokestatic    adf.a:(ILacr;Ladr;Z)V
        //   463: goto            466
        //   466: iinc            8, 1
        //   469: goto            410
        //   472: iconst_0       
        //   473: istore          8
        //   475: iconst_0       
        //   476: aload_0        
        //   477: aload           7
        //   479: iload           12
        //   481: invokestatic    adf.a:(ILacr;Ladr;Z)V
        //   484: iload           11
        //   486: ifeq            550
        //   489: iconst_0       
        //   490: istore          11
        //   492: iload           11
        //   494: iload           10
        //   496: if_icmpge       550
        //   499: aload           4
        //   501: iload           11
        //   503: invokevirtual   java/util/ArrayList.get:(I)Ljava/lang/Object;
        //   506: checkcast       Lacr;
        //   509: astore          14
        //   511: aload           14
        //   513: instanceof      Laco;
        //   516: ifeq            544
        //   519: aload           14
        //   521: checkcast       Laco;
        //   524: astore          14
        //   526: aload           14
        //   528: invokevirtual   aco.a:()I
        //   531: ifne            544
        //   534: aload           14
        //   536: aload           7
        //   538: iconst_0       
        //   539: iload           12
        //   541: invokestatic    adf.d:(Laco;Ladr;IZ)V
        //   544: iinc            11, 1
        //   547: goto            492
        //   550: iload           9
        //   552: iconst_1       
        //   553: if_icmpne       574
        //   556: aload_0        
        //   557: iconst_0       
        //   558: aload_0        
        //   559: invokevirtual   acr.h:()I
        //   562: invokevirtual   acr.w:(II)V
        //   565: iconst_0       
        //   566: istore          13
        //   568: iconst_0       
        //   569: istore          11
        //   571: goto            596
        //   574: aload_0        
        //   575: getfield        acr.K:Lacq;
        //   578: iconst_0       
        //   579: invokevirtual   acq.e:(I)V
        //   582: aload_0        
        //   583: iconst_0       
        //   584: putfield        acr.aa:I
        //   587: iconst_0       
        //   588: istore          13
        //   590: iconst_0       
        //   591: istore          11
        //   593: iconst_0       
        //   594: istore          8
        //   596: iload           8
        //   598: iload           10
        //   600: if_icmpge       798
        //   603: aload           4
        //   605: iload           8
        //   607: invokevirtual   java/util/ArrayList.get:(I)Ljava/lang/Object;
        //   610: checkcast       Lacr;
        //   613: astore          14
        //   615: aload           14
        //   617: instanceof      Lacu;
        //   620: ifeq            741
        //   623: aload           14
        //   625: checkcast       Lacu;
        //   628: astore          14
        //   630: iload           13
        //   632: istore          15
        //   634: iload           11
        //   636: istore          16
        //   638: aload           14
        //   640: getfield        acu.ar:I
        //   643: ifne            784
        //   646: aload           14
        //   648: getfield        acu.b:I
        //   651: istore          13
        //   653: iload           13
        //   655: iconst_m1      
        //   656: if_icmpeq       676
        //   659: aload           14
        //   661: iload           13
        //   663: invokevirtual   acu.a:(I)V
        //   666: iconst_1       
        //   667: istore          15
        //   669: iload           11
        //   671: istore          16
        //   673: goto            784
        //   676: aload           14
        //   678: getfield        acu.c:I
        //   681: iconst_m1      
        //   682: if_icmpeq       710
        //   685: aload_0        
        //   686: invokevirtual   acr.f:()Z
        //   689: ifeq            710
        //   692: aload           14
        //   694: aload_0        
        //   695: invokevirtual   acr.h:()I
        //   698: aload           14
        //   700: getfield        acu.c:I
        //   703: isub           
        //   704: invokevirtual   acu.a:(I)V
        //   707: goto            666
        //   710: aload_0        
        //   711: invokevirtual   acr.f:()Z
        //   714: ifeq            666
        //   717: aload           14
        //   719: aload           14
        //   721: getfield        acu.a:F
        //   724: aload_0        
        //   725: invokevirtual   acr.h:()I
        //   728: i2f            
        //   729: fmul           
        //   730: ldc_w           0.5
        //   733: fadd           
        //   734: f2i            
        //   735: invokevirtual   acu.a:(I)V
        //   738: goto            666
        //   741: iload           13
        //   743: istore          15
        //   745: iload           11
        //   747: istore          16
        //   749: aload           14
        //   751: instanceof      Laco;
        //   754: ifeq            784
        //   757: iload           13
        //   759: istore          15
        //   761: iload           11
        //   763: istore          16
        //   765: aload           14
        //   767: checkcast       Laco;
        //   770: invokevirtual   aco.a:()I
        //   773: iconst_1       
        //   774: if_icmpne       784
        //   777: iconst_1       
        //   778: istore          16
        //   780: iload           13
        //   782: istore          15
        //   784: iinc            8, 1
        //   787: iload           15
        //   789: istore          13
        //   791: iload           16
        //   793: istore          11
        //   795: goto            596
        //   798: iload           13
        //   800: ifeq            862
        //   803: iconst_0       
        //   804: istore          8
        //   806: iload           8
        //   808: iload           10
        //   810: if_icmpge       862
        //   813: aload           4
        //   815: iload           8
        //   817: invokevirtual   java/util/ArrayList.get:(I)Ljava/lang/Object;
        //   820: checkcast       Lacr;
        //   823: astore          14
        //   825: aload           14
        //   827: instanceof      Lacu;
        //   830: ifeq            856
        //   833: aload           14
        //   835: checkcast       Lacu;
        //   838: astore          14
        //   840: aload           14
        //   842: getfield        acu.ar:I
        //   845: ifne            856
        //   848: iconst_1       
        //   849: aload           14
        //   851: aload           7
        //   853: invokestatic    adf.b:(ILacr;Ladr;)V
        //   856: iinc            8, 1
        //   859: goto            806
        //   862: iconst_0       
        //   863: aload_0        
        //   864: aload           7
        //   866: invokestatic    adf.b:(ILacr;Ladr;)V
        //   869: iload           11
        //   871: ifeq            936
        //   874: iconst_0       
        //   875: istore          11
        //   877: iload           11
        //   879: iload           10
        //   881: if_icmpge       936
        //   884: aload           4
        //   886: iload           11
        //   888: invokevirtual   java/util/ArrayList.get:(I)Ljava/lang/Object;
        //   891: checkcast       Lacr;
        //   894: astore          14
        //   896: aload           14
        //   898: instanceof      Laco;
        //   901: ifeq            930
        //   904: aload           14
        //   906: checkcast       Laco;
        //   909: astore          14
        //   911: aload           14
        //   913: invokevirtual   aco.a:()I
        //   916: iconst_1       
        //   917: if_icmpne       930
        //   920: aload           14
        //   922: aload           7
        //   924: iconst_1       
        //   925: iload           12
        //   927: invokestatic    adf.d:(Laco;Ladr;IZ)V
        //   930: iinc            11, 1
        //   933: goto            877
        //   936: iconst_0       
        //   937: istore          11
        //   939: iload           11
        //   941: iload           10
        //   943: if_icmpge       1051
        //   946: aload           4
        //   948: iload           11
        //   950: invokevirtual   java/util/ArrayList.get:(I)Ljava/lang/Object;
        //   953: checkcast       Lacr;
        //   956: astore          14
        //   958: aload           14
        //   960: invokevirtual   acr.J:()Z
        //   963: ifeq            1045
        //   966: aload           14
        //   968: invokestatic    adf.c:(Lacr;)Z
        //   971: ifeq            1045
        //   974: aload           14
        //   976: aload           7
        //   978: getstatic       adf.a:Lacz;
        //   981: invokestatic    acs.X:(Lacr;Ladr;Lacz;)V
        //   984: aload           14
        //   986: instanceof      Lacu;
        //   989: ifeq            1027
        //   992: aload           14
        //   994: checkcast       Lacu;
        //   997: getfield        acu.ar:I
        //  1000: ifne            1014
        //  1003: iconst_0       
        //  1004: aload           14
        //  1006: aload           7
        //  1008: invokestatic    adf.b:(ILacr;Ladr;)V
        //  1011: goto            1045
        //  1014: iconst_0       
        //  1015: aload           14
        //  1017: aload           7
        //  1019: iload           12
        //  1021: invokestatic    adf.a:(ILacr;Ladr;Z)V
        //  1024: goto            1045
        //  1027: iconst_0       
        //  1028: aload           14
        //  1030: aload           7
        //  1032: iload           12
        //  1034: invokestatic    adf.a:(ILacr;Ladr;Z)V
        //  1037: iconst_0       
        //  1038: aload           14
        //  1040: aload           7
        //  1042: invokestatic    adf.b:(ILacr;Ladr;)V
        //  1045: iinc            11, 1
        //  1048: goto            939
        //  1051: iconst_0       
        //  1052: istore          11
        //  1054: iload           11
        //  1056: iload_1        
        //  1057: if_icmpge       1185
        //  1060: aload_0        
        //  1061: getfield        acs.aI:Ljava/util/ArrayList;
        //  1064: iload           11
        //  1066: invokevirtual   java/util/ArrayList.get:(I)Ljava/lang/Object;
        //  1069: checkcast       Lacr;
        //  1072: astore          7
        //  1074: aload           7
        //  1076: invokevirtual   acr.J:()Z
        //  1079: ifeq            1179
        //  1082: aload           7
        //  1084: instanceof      Lacu;
        //  1087: ifne            1179
        //  1090: aload           7
        //  1092: instanceof      Laco;
        //  1095: ifne            1179
        //  1098: aload           7
        //  1100: instanceof      Lacx;
        //  1103: ifne            1179
        //  1106: aload           7
        //  1108: getfield        acr.G:Z
        //  1111: istore          12
        //  1113: aload           7
        //  1115: iconst_0       
        //  1116: invokevirtual   acr.L:(I)I
        //  1119: istore          13
        //  1121: aload           7
        //  1123: iconst_1       
        //  1124: invokevirtual   acr.L:(I)I
        //  1127: istore          8
        //  1129: iload           13
        //  1131: iconst_3       
        //  1132: if_icmpne       1159
        //  1135: aload           7
        //  1137: getfield        acr.s:I
        //  1140: iconst_1       
        //  1141: if_icmpeq       1159
        //  1144: iload           8
        //  1146: iconst_3       
        //  1147: if_icmpne       1159
        //  1150: aload           7
        //  1152: getfield        acr.t:I
        //  1155: iconst_1       
        //  1156: if_icmpne       1179
        //  1159: new             Lacz;
        //  1162: dup            
        //  1163: invokespecial   acz.<init>:()V
        //  1166: astore          4
        //  1168: aload           7
        //  1170: aload_0        
        //  1171: getfield        acs.aG:Ladr;
        //  1174: aload           4
        //  1176: invokestatic    acs.X:(Lacr;Ladr;Lacz;)V
        //  1179: iinc            11, 1
        //  1182: goto            1054
        //  1185: iload           5
        //  1187: istore          8
        //  1189: iload_1        
        //  1190: iconst_2       
        //  1191: if_icmple       3225
        //  1194: iload           5
        //  1196: istore          11
        //  1198: iload           6
        //  1200: iconst_2       
        //  1201: if_icmpeq       1240
        //  1204: iload           5
        //  1206: istore          11
        //  1208: iload           5
        //  1210: iconst_2       
        //  1211: if_icmpne       1220
        //  1214: iconst_2       
        //  1215: istore          11
        //  1217: goto            1240
        //  1220: iload           11
        //  1222: istore          13
        //  1224: iconst_0       
        //  1225: istore          11
        //  1227: iload_2        
        //  1228: istore          5
        //  1230: iload           6
        //  1232: istore          8
        //  1234: iload_1        
        //  1235: istore          15
        //  1237: goto            3242
        //  1240: iload           11
        //  1242: istore          8
        //  1244: aload_0        
        //  1245: getfield        acs.ax:I
        //  1248: sipush          1024
        //  1251: invokestatic    acw.b:(II)Z
        //  1254: ifeq            3225
        //  1257: aload_0        
        //  1258: getfield        acs.aG:Ladr;
        //  1261: astore          17
        //  1263: aload_0        
        //  1264: getfield        acy.aI:Ljava/util/ArrayList;
        //  1267: astore          18
        //  1269: aload           18
        //  1271: invokevirtual   java/util/ArrayList.size:()I
        //  1274: istore          8
        //  1276: iconst_0       
        //  1277: istore          5
        //  1279: iload           5
        //  1281: iload           8
        //  1283: if_icmpge       1342
        //  1286: aload           18
        //  1288: iload           5
        //  1290: invokevirtual   java/util/ArrayList.get:(I)Ljava/lang/Object;
        //  1293: checkcast       Lacr;
        //  1296: astore          4
        //  1298: aload_0        
        //  1299: invokevirtual   acr.M:()I
        //  1302: aload_0        
        //  1303: invokevirtual   acr.N:()I
        //  1306: aload           4
        //  1308: invokevirtual   acr.M:()I
        //  1311: aload           4
        //  1313: invokevirtual   acr.N:()I
        //  1316: invokestatic    sq.f:(IIII)Z
        //  1319: ifne            1325
        //  1322: goto            1220
        //  1325: aload           4
        //  1327: instanceof      Lact;
        //  1330: ifeq            1336
        //  1333: goto            1220
        //  1336: iinc            5, 1
        //  1339: goto            1279
        //  1342: aconst_null    
        //  1343: astore          19
        //  1345: iconst_0       
        //  1346: istore          5
        //  1348: aconst_null    
        //  1349: astore          4
        //  1351: aconst_null    
        //  1352: astore          14
        //  1354: aconst_null    
        //  1355: astore          7
        //  1357: aconst_null    
        //  1358: astore          20
        //  1360: aconst_null    
        //  1361: astore          21
        //  1363: iload_1        
        //  1364: istore          15
        //  1366: iload           11
        //  1368: istore_1       
        //  1369: iload_3        
        //  1370: istore          11
        //  1372: iload_2        
        //  1373: istore_3       
        //  1374: iload           5
        //  1376: iload           8
        //  1378: if_icmpge       1929
        //  1381: aload           18
        //  1383: iload           5
        //  1385: invokevirtual   java/util/ArrayList.get:(I)Ljava/lang/Object;
        //  1388: checkcast       Lacr;
        //  1391: astore          22
        //  1393: aload_0        
        //  1394: invokevirtual   acr.M:()I
        //  1397: aload_0        
        //  1398: invokevirtual   acr.N:()I
        //  1401: aload           22
        //  1403: invokevirtual   acr.M:()I
        //  1406: aload           22
        //  1408: invokevirtual   acr.N:()I
        //  1411: invokestatic    sq.f:(IIII)Z
        //  1414: ifne            1428
        //  1417: aload           22
        //  1419: aload           17
        //  1421: aload_0        
        //  1422: getfield        acs.aF:Lacz;
        //  1425: invokestatic    acs.X:(Lacr;Ladr;Lacz;)V
        //  1428: aload           22
        //  1430: instanceof      Lacu;
        //  1433: istore          12
        //  1435: aload           19
        //  1437: astore          23
        //  1439: aload           14
        //  1441: astore          24
        //  1443: iload           12
        //  1445: ifeq            1544
        //  1448: aload           22
        //  1450: checkcast       Lacu;
        //  1453: astore          25
        //  1455: aload           14
        //  1457: astore          26
        //  1459: aload           25
        //  1461: getfield        acu.ar:I
        //  1464: ifne            1493
        //  1467: aload           14
        //  1469: astore          26
        //  1471: aload           14
        //  1473: ifnonnull       1485
        //  1476: new             Ljava/util/ArrayList;
        //  1479: dup            
        //  1480: invokespecial   java/util/ArrayList.<init>:()V
        //  1483: astore          26
        //  1485: aload           26
        //  1487: aload           25
        //  1489: invokevirtual   java/util/ArrayList.add:(Ljava/lang/Object;)Z
        //  1492: pop            
        //  1493: aload           19
        //  1495: astore          23
        //  1497: aload           26
        //  1499: astore          24
        //  1501: aload           25
        //  1503: getfield        acu.ar:I
        //  1506: iconst_1       
        //  1507: if_icmpne       1544
        //  1510: aload           19
        //  1512: astore          14
        //  1514: aload           19
        //  1516: ifnonnull       1528
        //  1519: new             Ljava/util/ArrayList;
        //  1522: dup            
        //  1523: invokespecial   java/util/ArrayList.<init>:()V
        //  1526: astore          14
        //  1528: aload           14
        //  1530: aload           25
        //  1532: invokevirtual   java/util/ArrayList.add:(Ljava/lang/Object;)Z
        //  1535: pop            
        //  1536: aload           26
        //  1538: astore          24
        //  1540: aload           14
        //  1542: astore          23
        //  1544: aload           4
        //  1546: astore          14
        //  1548: aload           7
        //  1550: astore          26
        //  1552: aload           22
        //  1554: instanceof      Lacv;
        //  1557: ifeq            1722
        //  1560: aload           22
        //  1562: instanceof      Laco;
        //  1565: ifeq            1663
        //  1568: aload           22
        //  1570: checkcast       Laco;
        //  1573: astore          25
        //  1575: aload           4
        //  1577: astore          19
        //  1579: aload           25
        //  1581: invokevirtual   aco.a:()I
        //  1584: ifne            1613
        //  1587: aload           4
        //  1589: astore          19
        //  1591: aload           4
        //  1593: ifnonnull       1605
        //  1596: new             Ljava/util/ArrayList;
        //  1599: dup            
        //  1600: invokespecial   java/util/ArrayList.<init>:()V
        //  1603: astore          19
        //  1605: aload           19
        //  1607: aload           25
        //  1609: invokevirtual   java/util/ArrayList.add:(Ljava/lang/Object;)Z
        //  1612: pop            
        //  1613: aload           19
        //  1615: astore          14
        //  1617: aload           7
        //  1619: astore          26
        //  1621: aload           25
        //  1623: invokevirtual   aco.a:()I
        //  1626: iconst_1       
        //  1627: if_icmpne       1722
        //  1630: aload           7
        //  1632: astore          26
        //  1634: aload           7
        //  1636: ifnonnull       1648
        //  1639: new             Ljava/util/ArrayList;
        //  1642: dup            
        //  1643: invokespecial   java/util/ArrayList.<init>:()V
        //  1646: astore          26
        //  1648: aload           26
        //  1650: aload           25
        //  1652: invokevirtual   java/util/ArrayList.add:(Ljava/lang/Object;)Z
        //  1655: pop            
        //  1656: aload           19
        //  1658: astore          14
        //  1660: goto            1722
        //  1663: aload           22
        //  1665: checkcast       Lacv;
        //  1668: astore          19
        //  1670: aload           4
        //  1672: astore          14
        //  1674: aload           4
        //  1676: ifnonnull       1688
        //  1679: new             Ljava/util/ArrayList;
        //  1682: dup            
        //  1683: invokespecial   java/util/ArrayList.<init>:()V
        //  1686: astore          14
        //  1688: aload           14
        //  1690: aload           19
        //  1692: invokevirtual   java/util/ArrayList.add:(Ljava/lang/Object;)Z
        //  1695: pop            
        //  1696: aload           7
        //  1698: astore          26
        //  1700: aload           7
        //  1702: ifnonnull       1714
        //  1705: new             Ljava/util/ArrayList;
        //  1708: dup            
        //  1709: invokespecial   java/util/ArrayList.<init>:()V
        //  1712: astore          26
        //  1714: aload           26
        //  1716: aload           19
        //  1718: invokevirtual   java/util/ArrayList.add:(Ljava/lang/Object;)Z
        //  1721: pop            
        //  1722: aload           20
        //  1724: astore          25
        //  1726: aload           22
        //  1728: getfield        acr.J:Lacq;
        //  1731: getfield        acq.e:Lacq;
        //  1734: ifnonnull       1803
        //  1737: aload           20
        //  1739: astore          25
        //  1741: aload           22
        //  1743: getfield        acr.L:Lacq;
        //  1746: getfield        acq.e:Lacq;
        //  1749: ifnonnull       1803
        //  1752: aload           20
        //  1754: astore          25
        //  1756: iload           12
        //  1758: ifne            1803
        //  1761: aload           20
        //  1763: astore          25
        //  1765: aload           22
        //  1767: instanceof      Laco;
        //  1770: ifne            1803
        //  1773: aload           20
        //  1775: astore          4
        //  1777: aload           20
        //  1779: ifnonnull       1791
        //  1782: new             Ljava/util/ArrayList;
        //  1785: dup            
        //  1786: invokespecial   java/util/ArrayList.<init>:()V
        //  1789: astore          4
        //  1791: aload           4
        //  1793: aload           22
        //  1795: invokevirtual   java/util/ArrayList.add:(Ljava/lang/Object;)Z
        //  1798: pop            
        //  1799: aload           4
        //  1801: astore          25
        //  1803: aload           21
        //  1805: astore          27
        //  1807: aload           22
        //  1809: getfield        acr.K:Lacq;
        //  1812: getfield        acq.e:Lacq;
        //  1815: ifnonnull       1899
        //  1818: aload           21
        //  1820: astore          27
        //  1822: aload           22
        //  1824: getfield        acr.M:Lacq;
        //  1827: getfield        acq.e:Lacq;
        //  1830: ifnonnull       1899
        //  1833: aload           21
        //  1835: astore          27
        //  1837: aload           22
        //  1839: getfield        acr.N:Lacq;
        //  1842: getfield        acq.e:Lacq;
        //  1845: ifnonnull       1899
        //  1848: aload           21
        //  1850: astore          27
        //  1852: iload           12
        //  1854: ifne            1899
        //  1857: aload           21
        //  1859: astore          27
        //  1861: aload           22
        //  1863: instanceof      Laco;
        //  1866: ifne            1899
        //  1869: aload           21
        //  1871: astore          4
        //  1873: aload           21
        //  1875: ifnonnull       1887
        //  1878: new             Ljava/util/ArrayList;
        //  1881: dup            
        //  1882: invokespecial   java/util/ArrayList.<init>:()V
        //  1885: astore          4
        //  1887: aload           4
        //  1889: aload           22
        //  1891: invokevirtual   java/util/ArrayList.add:(Ljava/lang/Object;)Z
        //  1894: pop            
        //  1895: aload           4
        //  1897: astore          27
        //  1899: iinc            5, 1
        //  1902: aload           23
        //  1904: astore          19
        //  1906: aload           14
        //  1908: astore          4
        //  1910: aload           24
        //  1912: astore          14
        //  1914: aload           26
        //  1916: astore          7
        //  1918: aload           25
        //  1920: astore          20
        //  1922: aload           27
        //  1924: astore          21
        //  1926: goto            1374
        //  1929: new             Ljava/util/ArrayList;
        //  1932: dup            
        //  1933: invokespecial   java/util/ArrayList.<init>:()V
        //  1936: astore          26
        //  1938: aload           19
        //  1940: ifnull          1985
        //  1943: aload           19
        //  1945: invokeinterface java/util/List.size:()I
        //  1950: istore          5
        //  1952: iconst_0       
        //  1953: istore_2       
        //  1954: iload_2        
        //  1955: iload           5
        //  1957: if_icmpge       1985
        //  1960: aload           19
        //  1962: iload_2        
        //  1963: invokeinterface java/util/List.get:(I)Ljava/lang/Object;
        //  1968: checkcast       Lacu;
        //  1971: iconst_0       
        //  1972: aload           26
        //  1974: aconst_null    
        //  1975: invokestatic    sq.d:(Lacr;ILjava/util/ArrayList;Ladl;)Ladl;
        //  1978: pop            
        //  1979: iinc            2, 1
        //  1982: goto            1954
        //  1985: aload           4
        //  1987: ifnull          2054
        //  1990: aload           4
        //  1992: invokeinterface java/util/List.size:()I
        //  1997: istore          5
        //  1999: iconst_0       
        //  2000: istore_2       
        //  2001: iload_2        
        //  2002: iload           5
        //  2004: if_icmpge       2054
        //  2007: aload           4
        //  2009: iload_2        
        //  2010: invokeinterface java/util/List.get:(I)Ljava/lang/Object;
        //  2015: checkcast       Lacv;
        //  2018: astore          24
        //  2020: aload           24
        //  2022: iconst_0       
        //  2023: aload           26
        //  2025: aconst_null    
        //  2026: invokestatic    sq.d:(Lacr;ILjava/util/ArrayList;Ladl;)Ladl;
        //  2029: astore          19
        //  2031: aload           24
        //  2033: aload           26
        //  2035: iconst_0       
        //  2036: aload           19
        //  2038: invokevirtual   acv.T:(Ljava/util/ArrayList;ILadl;)V
        //  2041: aload           19
        //  2043: aload           26
        //  2045: invokevirtual   adl.b:(Ljava/util/ArrayList;)V
        //  2048: iinc            2, 1
        //  2051: goto            2001
        //  2054: aload_0        
        //  2055: iconst_2       
        //  2056: invokevirtual   acr.K:(I)Lacq;
        //  2059: getfield        acq.a:Ljava/util/HashSet;
        //  2062: astore          4
        //  2064: aload           4
        //  2066: ifnull          2110
        //  2069: aload           4
        //  2071: invokevirtual   java/util/HashSet.iterator:()Ljava/util/Iterator;
        //  2074: astore          4
        //  2076: aload           4
        //  2078: invokeinterface java/util/Iterator.hasNext:()Z
        //  2083: ifeq            2110
        //  2086: aload           4
        //  2088: invokeinterface java/util/Iterator.next:()Ljava/lang/Object;
        //  2093: checkcast       Lacq;
        //  2096: getfield        acq.d:Lacr;
        //  2099: iconst_0       
        //  2100: aload           26
        //  2102: aconst_null    
        //  2103: invokestatic    sq.d:(Lacr;ILjava/util/ArrayList;Ladl;)Ladl;
        //  2106: pop            
        //  2107: goto            2076
        //  2110: aload_0        
        //  2111: iconst_4       
        //  2112: invokevirtual   acr.K:(I)Lacq;
        //  2115: getfield        acq.a:Ljava/util/HashSet;
        //  2118: astore          4
        //  2120: aload           4
        //  2122: ifnull          2166
        //  2125: aload           4
        //  2127: invokevirtual   java/util/HashSet.iterator:()Ljava/util/Iterator;
        //  2130: astore          4
        //  2132: aload           4
        //  2134: invokeinterface java/util/Iterator.hasNext:()Z
        //  2139: ifeq            2166
        //  2142: aload           4
        //  2144: invokeinterface java/util/Iterator.next:()Ljava/lang/Object;
        //  2149: checkcast       Lacq;
        //  2152: getfield        acq.d:Lacr;
        //  2155: iconst_0       
        //  2156: aload           26
        //  2158: aconst_null    
        //  2159: invokestatic    sq.d:(Lacr;ILjava/util/ArrayList;Ladl;)Ladl;
        //  2162: pop            
        //  2163: goto            2132
        //  2166: aload_0        
        //  2167: bipush          7
        //  2169: invokevirtual   acr.K:(I)Lacq;
        //  2172: getfield        acq.a:Ljava/util/HashSet;
        //  2175: astore          4
        //  2177: aload           4
        //  2179: ifnull          2223
        //  2182: aload           4
        //  2184: invokevirtual   java/util/HashSet.iterator:()Ljava/util/Iterator;
        //  2187: astore          4
        //  2189: aload           4
        //  2191: invokeinterface java/util/Iterator.hasNext:()Z
        //  2196: ifeq            2223
        //  2199: aload           4
        //  2201: invokeinterface java/util/Iterator.next:()Ljava/lang/Object;
        //  2206: checkcast       Lacq;
        //  2209: getfield        acq.d:Lacr;
        //  2212: iconst_0       
        //  2213: aload           26
        //  2215: aconst_null    
        //  2216: invokestatic    sq.d:(Lacr;ILjava/util/ArrayList;Ladl;)Ladl;
        //  2219: pop            
        //  2220: goto            2189
        //  2223: aload           20
        //  2225: ifnull          2270
        //  2228: aload           20
        //  2230: invokeinterface java/util/List.size:()I
        //  2235: istore          5
        //  2237: iconst_0       
        //  2238: istore_2       
        //  2239: iload_2        
        //  2240: iload           5
        //  2242: if_icmpge       2270
        //  2245: aload           20
        //  2247: iload_2        
        //  2248: invokeinterface java/util/List.get:(I)Ljava/lang/Object;
        //  2253: checkcast       Lacr;
        //  2256: iconst_0       
        //  2257: aload           26
        //  2259: aconst_null    
        //  2260: invokestatic    sq.d:(Lacr;ILjava/util/ArrayList;Ladl;)Ladl;
        //  2263: pop            
        //  2264: iinc            2, 1
        //  2267: goto            2239
        //  2270: aload           14
        //  2272: ifnull          2317
        //  2275: aload           14
        //  2277: invokeinterface java/util/List.size:()I
        //  2282: istore          5
        //  2284: iconst_0       
        //  2285: istore_2       
        //  2286: iload_2        
        //  2287: iload           5
        //  2289: if_icmpge       2317
        //  2292: aload           14
        //  2294: iload_2        
        //  2295: invokeinterface java/util/List.get:(I)Ljava/lang/Object;
        //  2300: checkcast       Lacu;
        //  2303: iconst_1       
        //  2304: aload           26
        //  2306: aconst_null    
        //  2307: invokestatic    sq.d:(Lacr;ILjava/util/ArrayList;Ladl;)Ladl;
        //  2310: pop            
        //  2311: iinc            2, 1
        //  2314: goto            2286
        //  2317: aload           7
        //  2319: ifnull          2386
        //  2322: aload           7
        //  2324: invokeinterface java/util/List.size:()I
        //  2329: istore          5
        //  2331: iconst_0       
        //  2332: istore_2       
        //  2333: iload_2        
        //  2334: iload           5
        //  2336: if_icmpge       2386
        //  2339: aload           7
        //  2341: iload_2        
        //  2342: invokeinterface java/util/List.get:(I)Ljava/lang/Object;
        //  2347: checkcast       Lacv;
        //  2350: astore          4
        //  2352: aload           4
        //  2354: iconst_1       
        //  2355: aload           26
        //  2357: aconst_null    
        //  2358: invokestatic    sq.d:(Lacr;ILjava/util/ArrayList;Ladl;)Ladl;
        //  2361: astore          14
        //  2363: aload           4
        //  2365: aload           26
        //  2367: iconst_1       
        //  2368: aload           14
        //  2370: invokevirtual   acv.T:(Ljava/util/ArrayList;ILadl;)V
        //  2373: aload           14
        //  2375: aload           26
        //  2377: invokevirtual   adl.b:(Ljava/util/ArrayList;)V
        //  2380: iinc            2, 1
        //  2383: goto            2333
        //  2386: aload_0        
        //  2387: iconst_3       
        //  2388: invokevirtual   acr.K:(I)Lacq;
        //  2391: getfield        acq.a:Ljava/util/HashSet;
        //  2394: astore          4
        //  2396: aload           4
        //  2398: ifnull          2442
        //  2401: aload           4
        //  2403: invokevirtual   java/util/HashSet.iterator:()Ljava/util/Iterator;
        //  2406: astore          4
        //  2408: aload           4
        //  2410: invokeinterface java/util/Iterator.hasNext:()Z
        //  2415: ifeq            2442
        //  2418: aload           4
        //  2420: invokeinterface java/util/Iterator.next:()Ljava/lang/Object;
        //  2425: checkcast       Lacq;
        //  2428: getfield        acq.d:Lacr;
        //  2431: iconst_1       
        //  2432: aload           26
        //  2434: aconst_null    
        //  2435: invokestatic    sq.d:(Lacr;ILjava/util/ArrayList;Ladl;)Ladl;
        //  2438: pop            
        //  2439: goto            2408
        //  2442: aload_0        
        //  2443: bipush          6
        //  2445: invokevirtual   acr.K:(I)Lacq;
        //  2448: getfield        acq.a:Ljava/util/HashSet;
        //  2451: astore          4
        //  2453: aload           4
        //  2455: ifnull          2499
        //  2458: aload           4
        //  2460: invokevirtual   java/util/HashSet.iterator:()Ljava/util/Iterator;
        //  2463: astore          4
        //  2465: aload           4
        //  2467: invokeinterface java/util/Iterator.hasNext:()Z
        //  2472: ifeq            2499
        //  2475: aload           4
        //  2477: invokeinterface java/util/Iterator.next:()Ljava/lang/Object;
        //  2482: checkcast       Lacq;
        //  2485: getfield        acq.d:Lacr;
        //  2488: iconst_1       
        //  2489: aload           26
        //  2491: aconst_null    
        //  2492: invokestatic    sq.d:(Lacr;ILjava/util/ArrayList;Ladl;)Ladl;
        //  2495: pop            
        //  2496: goto            2465
        //  2499: aload_0        
        //  2500: iconst_5       
        //  2501: invokevirtual   acr.K:(I)Lacq;
        //  2504: getfield        acq.a:Ljava/util/HashSet;
        //  2507: astore          4
        //  2509: aload           4
        //  2511: ifnull          2555
        //  2514: aload           4
        //  2516: invokevirtual   java/util/HashSet.iterator:()Ljava/util/Iterator;
        //  2519: astore          4
        //  2521: aload           4
        //  2523: invokeinterface java/util/Iterator.hasNext:()Z
        //  2528: ifeq            2555
        //  2531: aload           4
        //  2533: invokeinterface java/util/Iterator.next:()Ljava/lang/Object;
        //  2538: checkcast       Lacq;
        //  2541: getfield        acq.d:Lacr;
        //  2544: iconst_1       
        //  2545: aload           26
        //  2547: aconst_null    
        //  2548: invokestatic    sq.d:(Lacr;ILjava/util/ArrayList;Ladl;)Ladl;
        //  2551: pop            
        //  2552: goto            2521
        //  2555: aload_0        
        //  2556: bipush          7
        //  2558: invokevirtual   acr.K:(I)Lacq;
        //  2561: getfield        acq.a:Ljava/util/HashSet;
        //  2564: astore          4
        //  2566: aload           4
        //  2568: ifnull          2612
        //  2571: aload           4
        //  2573: invokevirtual   java/util/HashSet.iterator:()Ljava/util/Iterator;
        //  2576: astore          4
        //  2578: aload           4
        //  2580: invokeinterface java/util/Iterator.hasNext:()Z
        //  2585: ifeq            2612
        //  2588: aload           4
        //  2590: invokeinterface java/util/Iterator.next:()Ljava/lang/Object;
        //  2595: checkcast       Lacq;
        //  2598: getfield        acq.d:Lacr;
        //  2601: iconst_1       
        //  2602: aload           26
        //  2604: aconst_null    
        //  2605: invokestatic    sq.d:(Lacr;ILjava/util/ArrayList;Ladl;)Ladl;
        //  2608: pop            
        //  2609: goto            2578
        //  2612: aload           21
        //  2614: ifnull          2659
        //  2617: aload           21
        //  2619: invokeinterface java/util/List.size:()I
        //  2624: istore          5
        //  2626: iconst_0       
        //  2627: istore_2       
        //  2628: iload_2        
        //  2629: iload           5
        //  2631: if_icmpge       2659
        //  2634: aload           21
        //  2636: iload_2        
        //  2637: invokeinterface java/util/List.get:(I)Ljava/lang/Object;
        //  2642: checkcast       Lacr;
        //  2645: iconst_1       
        //  2646: aload           26
        //  2648: aconst_null    
        //  2649: invokestatic    sq.d:(Lacr;ILjava/util/ArrayList;Ladl;)Ladl;
        //  2652: pop            
        //  2653: iinc            2, 1
        //  2656: goto            2628
        //  2659: iconst_0       
        //  2660: istore_2       
        //  2661: iload_2        
        //  2662: iload           8
        //  2664: if_icmpge       2763
        //  2667: aload           18
        //  2669: iload_2        
        //  2670: invokevirtual   java/util/ArrayList.get:(I)Ljava/lang/Object;
        //  2673: checkcast       Lacr;
        //  2676: astore          7
        //  2678: aload           7
        //  2680: getfield        acr.aq:[I
        //  2683: astore          4
        //  2685: aload           4
        //  2687: iconst_0       
        //  2688: iaload         
        //  2689: iconst_3       
        //  2690: if_icmpne       2757
        //  2693: aload           4
        //  2695: iconst_1       
        //  2696: iaload         
        //  2697: iconst_3       
        //  2698: if_icmpne       2757
        //  2701: aload           26
        //  2703: aload           7
        //  2705: getfield        acr.ao:I
        //  2708: invokestatic    sq.e:(Ljava/util/ArrayList;I)Ladl;
        //  2711: astore          4
        //  2713: aload           26
        //  2715: aload           7
        //  2717: getfield        acr.ap:I
        //  2720: invokestatic    sq.e:(Ljava/util/ArrayList;I)Ladl;
        //  2723: astore          7
        //  2725: aload           4
        //  2727: ifnull          2757
        //  2730: aload           7
        //  2732: ifnull          2757
        //  2735: aload           4
        //  2737: iconst_0       
        //  2738: aload           7
        //  2740: invokevirtual   adl.c:(ILadl;)V
        //  2743: aload           7
        //  2745: iconst_2       
        //  2746: putfield        adl.d:I
        //  2749: aload           26
        //  2751: aload           4
        //  2753: invokevirtual   java/util/ArrayList.remove:(Ljava/lang/Object;)Z
        //  2756: pop            
        //  2757: iinc            2, 1
        //  2760: goto            2661
        //  2763: aload           26
        //  2765: invokevirtual   java/util/ArrayList.size:()I
        //  2768: iconst_1       
        //  2769: if_icmpgt       2788
        //  2772: iload_3        
        //  2773: istore          5
        //  2775: iload           11
        //  2777: istore_3       
        //  2778: iload           6
        //  2780: istore          8
        //  2782: iload_1        
        //  2783: istore          13
        //  2785: goto            3239
        //  2788: aload_0        
        //  2789: invokevirtual   acr.M:()I
        //  2792: iconst_2       
        //  2793: if_icmpne       2937
        //  2796: aload           26
        //  2798: invokeinterface java/util/List.size:()I
        //  2803: istore          16
        //  2805: aconst_null    
        //  2806: astore          4
        //  2808: iconst_0       
        //  2809: istore          8
        //  2811: iconst_0       
        //  2812: istore          5
        //  2814: iload           8
        //  2816: iload           16
        //  2818: if_icmpge       2914
        //  2821: aload           26
        //  2823: iload           8
        //  2825: invokeinterface java/util/List.get:(I)Ljava/lang/Object;
        //  2830: checkcast       Ladl;
        //  2833: astore          7
        //  2835: aload           7
        //  2837: getfield        adl.d:I
        //  2840: iconst_1       
        //  2841: if_icmpne       2854
        //  2844: aload           4
        //  2846: astore          7
        //  2848: iload           5
        //  2850: istore_2       
        //  2851: goto            2901
        //  2854: aload           7
        //  2856: aload_0        
        //  2857: getfield        acs.d:Lacj;
        //  2860: iconst_0       
        //  2861: invokevirtual   adl.a:(Lacj;I)I
        //  2864: istore          13
        //  2866: iload           13
        //  2868: iload           5
        //  2870: if_icmpgt       2876
        //  2873: goto            2880
        //  2876: aload           7
        //  2878: astore          4
        //  2880: aload           4
        //  2882: astore          7
        //  2884: iload           5
        //  2886: istore_2       
        //  2887: iload           13
        //  2889: iload           5
        //  2891: if_icmple       2901
        //  2894: iload           13
        //  2896: istore_2       
        //  2897: aload           4
        //  2899: astore          7
        //  2901: iinc            8, 1
        //  2904: aload           7
        //  2906: astore          4
        //  2908: iload_2        
        //  2909: istore          5
        //  2911: goto            2814
        //  2914: aload           4
        //  2916: ifnull          2937
        //  2919: aload_0        
        //  2920: iconst_1       
        //  2921: invokevirtual   acr.P:(I)V
        //  2924: aload_0        
        //  2925: iload           5
        //  2927: invokevirtual   acr.C:(I)V
        //  2930: aload           4
        //  2932: astore          7
        //  2934: goto            2940
        //  2937: aconst_null    
        //  2938: astore          7
        //  2940: aload_0        
        //  2941: invokevirtual   acr.N:()I
        //  2944: iconst_2       
        //  2945: if_icmpne       3085
        //  2948: aload           26
        //  2950: invokeinterface java/util/List.size:()I
        //  2955: istore          16
        //  2957: aconst_null    
        //  2958: astore          4
        //  2960: iconst_0       
        //  2961: istore_2       
        //  2962: iconst_0       
        //  2963: istore          8
        //  2965: iload_2        
        //  2966: iload           16
        //  2968: if_icmpge       3066
        //  2971: aload           26
        //  2973: iload_2        
        //  2974: invokeinterface java/util/List.get:(I)Ljava/lang/Object;
        //  2979: checkcast       Ladl;
        //  2982: astore          14
        //  2984: aload           14
        //  2986: getfield        adl.d:I
        //  2989: ifne            3003
        //  2992: aload           4
        //  2994: astore          14
        //  2996: iload           8
        //  2998: istore          5
        //  3000: goto            3052
        //  3003: aload           14
        //  3005: aload_0        
        //  3006: getfield        acs.d:Lacj;
        //  3009: iconst_1       
        //  3010: invokevirtual   adl.a:(Lacj;I)I
        //  3013: istore          13
        //  3015: iload           13
        //  3017: iload           8
        //  3019: if_icmpgt       3025
        //  3022: goto            3029
        //  3025: aload           14
        //  3027: astore          4
        //  3029: aload           4
        //  3031: astore          14
        //  3033: iload           8
        //  3035: istore          5
        //  3037: iload           13
        //  3039: iload           8
        //  3041: if_icmple       3052
        //  3044: iload           13
        //  3046: istore          5
        //  3048: aload           4
        //  3050: astore          14
        //  3052: iinc            2, 1
        //  3055: aload           14
        //  3057: astore          4
        //  3059: iload           5
        //  3061: istore          8
        //  3063: goto            2965
        //  3066: aload           4
        //  3068: ifnull          3085
        //  3071: aload_0        
        //  3072: iconst_1       
        //  3073: invokevirtual   acr.Q:(I)V
        //  3076: aload_0        
        //  3077: iload           8
        //  3079: invokevirtual   acr.x:(I)V
        //  3082: goto            3088
        //  3085: aconst_null    
        //  3086: astore          4
        //  3088: aload           7
        //  3090: ifnonnull       3098
        //  3093: aload           4
        //  3095: ifnull          2772
        //  3098: iload           6
        //  3100: iconst_2       
        //  3101: if_icmpne       3143
        //  3104: iload_3        
        //  3105: aload_0        
        //  3106: invokevirtual   acr.j:()I
        //  3109: if_icmpge       3132
        //  3112: iload_3        
        //  3113: ifle            3132
        //  3116: aload_0        
        //  3117: iload_3        
        //  3118: invokevirtual   acr.C:(I)V
        //  3121: aload_0        
        //  3122: iconst_1       
        //  3123: putfield        acs.ay:Z
        //  3126: iload_3        
        //  3127: istore          6
        //  3129: goto            3138
        //  3132: aload_0        
        //  3133: invokevirtual   acr.j:()I
        //  3136: istore          6
        //  3138: iconst_2       
        //  3139: istore_3       
        //  3140: goto            3151
        //  3143: iload           6
        //  3145: istore_2       
        //  3146: iload_3        
        //  3147: istore          6
        //  3149: iload_2        
        //  3150: istore_3       
        //  3151: iload_1        
        //  3152: istore_2       
        //  3153: iload_2        
        //  3154: iconst_2       
        //  3155: if_icmpne       3200
        //  3158: iload           11
        //  3160: aload_0        
        //  3161: invokevirtual   acr.h:()I
        //  3164: if_icmpge       3189
        //  3167: iload           11
        //  3169: ifle            3189
        //  3172: aload_0        
        //  3173: iload           11
        //  3175: invokevirtual   acr.x:(I)V
        //  3178: aload_0        
        //  3179: iconst_1       
        //  3180: putfield        acs.az:Z
        //  3183: iload           11
        //  3185: istore_1       
        //  3186: goto            3194
        //  3189: aload_0        
        //  3190: invokevirtual   acr.h:()I
        //  3193: istore_1       
        //  3194: iconst_2       
        //  3195: istore          11
        //  3197: goto            3206
        //  3200: iload           11
        //  3202: istore_1       
        //  3203: iload_2        
        //  3204: istore          11
        //  3206: iload_3        
        //  3207: istore          8
        //  3209: iload           11
        //  3211: istore          13
        //  3213: iconst_1       
        //  3214: istore          11
        //  3216: iload           6
        //  3218: istore          5
        //  3220: iload_1        
        //  3221: istore_3       
        //  3222: goto            3242
        //  3225: iload_1        
        //  3226: istore          15
        //  3228: iload           8
        //  3230: istore          13
        //  3232: iload           6
        //  3234: istore          8
        //  3236: iload_2        
        //  3237: istore          5
        //  3239: iconst_0       
        //  3240: istore          11
        //  3242: aload_0        
        //  3243: bipush          64
        //  3245: invokevirtual   acs.W:(I)Z
        //  3248: ifne            3269
        //  3251: aload_0        
        //  3252: sipush          128
        //  3255: invokevirtual   acs.W:(I)Z
        //  3258: ifeq            3264
        //  3261: goto            3269
        //  3264: iconst_0       
        //  3265: istore_1       
        //  3266: goto            3271
        //  3269: iconst_1       
        //  3270: istore_1       
        //  3271: aload_0        
        //  3272: getfield        acs.d:Lacj;
        //  3275: astore          4
        //  3277: aload           4
        //  3279: iconst_0       
        //  3280: putfield        acj.f:Z
        //  3283: aload           4
        //  3285: iconst_0       
        //  3286: putfield        acj.g:Z
        //  3289: aload_0        
        //  3290: getfield        acs.ax:I
        //  3293: ifeq            3306
        //  3296: iload_1        
        //  3297: ifeq            3306
        //  3300: aload           4
        //  3302: iconst_1       
        //  3303: putfield        acj.g:Z
        //  3306: aload_0        
        //  3307: getfield        acs.aI:Ljava/util/ArrayList;
        //  3310: astore          4
        //  3312: aload_0        
        //  3313: invokevirtual   acr.M:()I
        //  3316: iconst_2       
        //  3317: if_icmpeq       3337
        //  3320: aload_0        
        //  3321: invokevirtual   acr.N:()I
        //  3324: iconst_2       
        //  3325: if_icmpne       3331
        //  3328: goto            3337
        //  3331: iconst_0       
        //  3332: istore          28
        //  3334: goto            3340
        //  3337: iconst_1       
        //  3338: istore          28
        //  3340: aload_0        
        //  3341: invokespecial   acs.ab:()V
        //  3344: iconst_0       
        //  3345: istore_1       
        //  3346: iload_1        
        //  3347: iload           15
        //  3349: if_icmpge       3387
        //  3352: aload_0        
        //  3353: getfield        acs.aI:Ljava/util/ArrayList;
        //  3356: iload_1        
        //  3357: invokevirtual   java/util/ArrayList.get:(I)Ljava/lang/Object;
        //  3360: checkcast       Lacr;
        //  3363: astore          7
        //  3365: aload           7
        //  3367: instanceof      Lacy;
        //  3370: ifeq            3381
        //  3373: aload           7
        //  3375: checkcast       Lacy;
        //  3378: invokevirtual   acy.T:()V
        //  3381: iinc            1, 1
        //  3384: goto            3346
        //  3387: iconst_1       
        //  3388: istore_2       
        //  3389: iconst_0       
        //  3390: istore          6
        //  3392: iload           11
        //  3394: istore_1       
        //  3395: iload_2        
        //  3396: istore          11
        //  3398: iload           11
        //  3400: ifeq            5552
        //  3403: iload           6
        //  3405: iconst_1       
        //  3406: iadd           
        //  3407: istore          11
        //  3409: iload           11
        //  3411: istore          6
        //  3413: aload_0        
        //  3414: getfield        acs.d:Lacj;
        //  3417: invokevirtual   acj.k:()V
        //  3420: iload           11
        //  3422: istore          6
        //  3424: aload_0        
        //  3425: invokespecial   acs.ab:()V
        //  3428: iload           11
        //  3430: istore          6
        //  3432: aload_0        
        //  3433: aload_0        
        //  3434: getfield        acs.d:Lacj;
        //  3437: invokevirtual   acr.q:(Lacj;)V
        //  3440: iconst_0       
        //  3441: istore_2       
        //  3442: iload_2        
        //  3443: iload           15
        //  3445: if_icmpge       3476
        //  3448: iload           11
        //  3450: istore          6
        //  3452: aload_0        
        //  3453: getfield        acs.aI:Ljava/util/ArrayList;
        //  3456: iload_2        
        //  3457: invokevirtual   java/util/ArrayList.get:(I)Ljava/lang/Object;
        //  3460: checkcast       Lacr;
        //  3463: aload_0        
        //  3464: getfield        acs.d:Lacj;
        //  3467: invokevirtual   acr.q:(Lacj;)V
        //  3470: iinc            2, 1
        //  3473: goto            3442
        //  3476: iload           11
        //  3478: istore          6
        //  3480: aload_0        
        //  3481: getfield        acs.d:Lacj;
        //  3484: astore          21
        //  3486: iload           11
        //  3488: istore          6
        //  3490: aload_0        
        //  3491: bipush          64
        //  3493: invokevirtual   acs.W:(I)Z
        //  3496: istore          12
        //  3498: iload           11
        //  3500: istore          6
        //  3502: aload_0        
        //  3503: aload           21
        //  3505: iload           12
        //  3507: invokevirtual   acr.b:(Lacj;Z)V
        //  3510: iload           11
        //  3512: istore          6
        //  3514: aload_0        
        //  3515: getfield        acs.aI:Ljava/util/ArrayList;
        //  3518: invokevirtual   java/util/ArrayList.size:()I
        //  3521: istore          9
        //  3523: iconst_0       
        //  3524: istore          10
        //  3526: iconst_0       
        //  3527: istore          16
        //  3529: iload           10
        //  3531: iload           9
        //  3533: if_icmpge       3608
        //  3536: iload           11
        //  3538: istore          6
        //  3540: aload_0        
        //  3541: getfield        acs.aI:Ljava/util/ArrayList;
        //  3544: iload           10
        //  3546: invokevirtual   java/util/ArrayList.get:(I)Ljava/lang/Object;
        //  3549: checkcast       Lacr;
        //  3552: astore          14
        //  3554: iload           11
        //  3556: istore          6
        //  3558: aload           14
        //  3560: iconst_0       
        //  3561: iconst_0       
        //  3562: invokevirtual   acr.y:(IZ)V
        //  3565: iload_3        
        //  3566: istore_2       
        //  3567: aload           4
        //  3569: astore          7
        //  3571: iload           11
        //  3573: istore          6
        //  3575: aload           14
        //  3577: iconst_1       
        //  3578: iconst_0       
        //  3579: invokevirtual   acr.y:(IZ)V
        //  3582: iload_3        
        //  3583: istore_2       
        //  3584: aload           4
        //  3586: astore          7
        //  3588: iload           11
        //  3590: istore          6
        //  3592: iload           16
        //  3594: aload           14
        //  3596: instanceof      Laco;
        //  3599: ior            
        //  3600: istore          16
        //  3602: iinc            10, 1
        //  3605: goto            3529
        //  3608: iload           16
        //  3610: ifeq            3859
        //  3613: iconst_0       
        //  3614: istore          16
        //  3616: iload           16
        //  3618: iload           9
        //  3620: if_icmpge       3859
        //  3623: iload_3        
        //  3624: istore_2       
        //  3625: aload           4
        //  3627: astore          7
        //  3629: iload           11
        //  3631: istore          6
        //  3633: aload_0        
        //  3634: getfield        acs.aI:Ljava/util/ArrayList;
        //  3637: iload           16
        //  3639: invokevirtual   java/util/ArrayList.get:(I)Ljava/lang/Object;
        //  3642: checkcast       Lacr;
        //  3645: astore          14
        //  3647: iload_3        
        //  3648: istore_2       
        //  3649: aload           4
        //  3651: astore          7
        //  3653: iload           11
        //  3655: istore          6
        //  3657: aload           14
        //  3659: instanceof      Laco;
        //  3662: ifeq            3853
        //  3665: iload_3        
        //  3666: istore_2       
        //  3667: aload           4
        //  3669: astore          7
        //  3671: iload           11
        //  3673: istore          6
        //  3675: aload           14
        //  3677: checkcast       Laco;
        //  3680: astore          14
        //  3682: iconst_0       
        //  3683: istore          10
        //  3685: iload_3        
        //  3686: istore_2       
        //  3687: aload           4
        //  3689: astore          7
        //  3691: iload           11
        //  3693: istore          6
        //  3695: iload           10
        //  3697: aload           14
        //  3699: getfield        aco.as:I
        //  3702: if_icmpge       3853
        //  3705: iload_3        
        //  3706: istore_2       
        //  3707: aload           4
        //  3709: astore          7
        //  3711: iload           11
        //  3713: istore          6
        //  3715: aload           14
        //  3717: getfield        aco.ar:[Lacr;
        //  3720: iload           10
        //  3722: aaload         
        //  3723: astore          20
        //  3725: iload_3        
        //  3726: istore_2       
        //  3727: aload           4
        //  3729: astore          7
        //  3731: iload           11
        //  3733: istore          6
        //  3735: aload           14
        //  3737: getfield        aco.b:Z
        //  3740: ifne            3764
        //  3743: iload_3        
        //  3744: istore_2       
        //  3745: aload           4
        //  3747: astore          7
        //  3749: iload           11
        //  3751: istore          6
        //  3753: aload           20
        //  3755: invokevirtual   acr.d:()Z
        //  3758: ifne            3764
        //  3761: goto            3847
        //  3764: iload_3        
        //  3765: istore_2       
        //  3766: aload           4
        //  3768: astore          7
        //  3770: iload           11
        //  3772: istore          6
        //  3774: aload           14
        //  3776: getfield        aco.a:I
        //  3779: istore          29
        //  3781: iload           29
        //  3783: ifeq            3830
        //  3786: iload           29
        //  3788: iconst_1       
        //  3789: if_icmpne       3795
        //  3792: goto            3830
        //  3795: iload           29
        //  3797: iconst_2       
        //  3798: if_icmpeq       3810
        //  3801: iload           29
        //  3803: iconst_3       
        //  3804: if_icmpne       3847
        //  3807: goto            3810
        //  3810: iload_3        
        //  3811: istore_2       
        //  3812: aload           4
        //  3814: astore          7
        //  3816: iload           11
        //  3818: istore          6
        //  3820: aload           20
        //  3822: iconst_1       
        //  3823: iconst_1       
        //  3824: invokevirtual   acr.y:(IZ)V
        //  3827: goto            3847
        //  3830: iload_3        
        //  3831: istore_2       
        //  3832: aload           4
        //  3834: astore          7
        //  3836: iload           11
        //  3838: istore          6
        //  3840: aload           20
        //  3842: iconst_0       
        //  3843: iconst_1       
        //  3844: invokevirtual   acr.y:(IZ)V
        //  3847: iinc            10, 1
        //  3850: goto            3685
        //  3853: iinc            16, 1
        //  3856: goto            3616
        //  3859: iload_3        
        //  3860: istore_2       
        //  3861: aload           4
        //  3863: astore          7
        //  3865: iload           11
        //  3867: istore          6
        //  3869: aload_0        
        //  3870: getfield        acs.aE:Ljava/util/HashSet;
        //  3873: invokevirtual   java/util/HashSet.clear:()V
        //  3876: iconst_0       
        //  3877: istore          6
        //  3879: iload           6
        //  3881: iload           9
        //  3883: if_icmplt       4845
        //  3886: iload_3        
        //  3887: istore_2       
        //  3888: aload           4
        //  3890: astore          7
        //  3892: iload           11
        //  3894: istore          6
        //  3896: aload_0        
        //  3897: getfield        acs.aE:Ljava/util/HashSet;
        //  3900: invokevirtual   java/util/HashSet.size:()I
        //  3903: ifle            4216
        //  3906: iload_3        
        //  3907: istore_2       
        //  3908: aload           4
        //  3910: astore          7
        //  3912: iload           11
        //  3914: istore          6
        //  3916: aload_0        
        //  3917: getfield        acs.aE:Ljava/util/HashSet;
        //  3920: invokevirtual   java/util/HashSet.size:()I
        //  3923: istore          10
        //  3925: iload_3        
        //  3926: istore_2       
        //  3927: aload           4
        //  3929: astore          7
        //  3931: iload           11
        //  3933: istore          6
        //  3935: aload_0        
        //  3936: getfield        acs.aE:Ljava/util/HashSet;
        //  3939: invokevirtual   java/util/HashSet.iterator:()Ljava/util/Iterator;
        //  3942: astore          14
        //  3944: iload_3        
        //  3945: istore_2       
        //  3946: aload           4
        //  3948: astore          7
        //  3950: iload           11
        //  3952: istore          6
        //  3954: aload           14
        //  3956: invokeinterface java/util/Iterator.hasNext:()Z
        //  3961: ifeq            4105
        //  3964: iload_3        
        //  3965: istore_2       
        //  3966: aload           4
        //  3968: astore          7
        //  3970: iload           11
        //  3972: istore          6
        //  3974: aload           14
        //  3976: invokeinterface java/util/Iterator.next:()Ljava/lang/Object;
        //  3981: checkcast       Lacr;
        //  3984: checkcast       Lacx;
        //  3987: astore          20
        //  3989: iload_3        
        //  3990: istore_2       
        //  3991: aload           4
        //  3993: astore          7
        //  3995: iload           11
        //  3997: istore          6
        //  3999: aload_0        
        //  4000: getfield        acs.aE:Ljava/util/HashSet;
        //  4003: astore          26
        //  4005: iconst_0       
        //  4006: istore          16
        //  4008: iload_3        
        //  4009: istore_2       
        //  4010: aload           4
        //  4012: astore          7
        //  4014: iload           11
        //  4016: istore          6
        //  4018: iload           16
        //  4020: aload           20
        //  4022: getfield        acx.as:I
        //  4025: if_icmpge       4102
        //  4028: iload_3        
        //  4029: istore_2       
        //  4030: aload           4
        //  4032: astore          7
        //  4034: iload           11
        //  4036: istore          6
        //  4038: aload           26
        //  4040: aload           20
        //  4042: getfield        acx.ar:[Lacr;
        //  4045: iload           16
        //  4047: aaload         
        //  4048: invokevirtual   java/util/HashSet.contains:(Ljava/lang/Object;)Z
        //  4051: ifeq            4096
        //  4054: iload_3        
        //  4055: istore_2       
        //  4056: aload           4
        //  4058: astore          7
        //  4060: iload           11
        //  4062: istore          6
        //  4064: aload           20
        //  4066: aload           21
        //  4068: iload           12
        //  4070: invokevirtual   acr.b:(Lacj;Z)V
        //  4073: iload_3        
        //  4074: istore_2       
        //  4075: aload           4
        //  4077: astore          7
        //  4079: iload           11
        //  4081: istore          6
        //  4083: aload_0        
        //  4084: getfield        acs.aE:Ljava/util/HashSet;
        //  4087: aload           20
        //  4089: invokevirtual   java/util/HashSet.remove:(Ljava/lang/Object;)Z
        //  4092: pop            
        //  4093: goto            4105
        //  4096: iinc            16, 1
        //  4099: goto            4008
        //  4102: goto            3944
        //  4105: iload_3        
        //  4106: istore_2       
        //  4107: aload           4
        //  4109: astore          7
        //  4111: iload           11
        //  4113: istore          6
        //  4115: iload           10
        //  4117: aload_0        
        //  4118: getfield        acs.aE:Ljava/util/HashSet;
        //  4121: invokevirtual   java/util/HashSet.size:()I
        //  4124: if_icmpne       3886
        //  4127: iload_3        
        //  4128: istore_2       
        //  4129: aload           4
        //  4131: astore          7
        //  4133: iload           11
        //  4135: istore          6
        //  4137: aload_0        
        //  4138: getfield        acs.aE:Ljava/util/HashSet;
        //  4141: invokevirtual   java/util/HashSet.iterator:()Ljava/util/Iterator;
        //  4144: astore          14
        //  4146: iload_3        
        //  4147: istore_2       
        //  4148: aload           4
        //  4150: astore          7
        //  4152: iload           11
        //  4154: istore          6
        //  4156: aload           14
        //  4158: invokeinterface java/util/Iterator.hasNext:()Z
        //  4163: ifeq            4196
        //  4166: iload_3        
        //  4167: istore_2       
        //  4168: aload           4
        //  4170: astore          7
        //  4172: iload           11
        //  4174: istore          6
        //  4176: aload           14
        //  4178: invokeinterface java/util/Iterator.next:()Ljava/lang/Object;
        //  4183: checkcast       Lacr;
        //  4186: aload           21
        //  4188: iload           12
        //  4190: invokevirtual   acr.b:(Lacj;Z)V
        //  4193: goto            4146
        //  4196: iload_3        
        //  4197: istore_2       
        //  4198: aload           4
        //  4200: astore          7
        //  4202: iload           11
        //  4204: istore          6
        //  4206: aload_0        
        //  4207: getfield        acs.aE:Ljava/util/HashSet;
        //  4210: invokevirtual   java/util/HashSet.clear:()V
        //  4213: goto            3886
        //  4216: iload_3        
        //  4217: istore_2       
        //  4218: aload           4
        //  4220: astore          7
        //  4222: iload           11
        //  4224: istore          6
        //  4226: getstatic       acj.a:Z
        //  4229: istore          30
        //  4231: iload           30
        //  4233: ifeq            4409
        //  4236: new             Ljava/util/HashSet;
        //  4239: astore          20
        //  4241: aload           20
        //  4243: invokespecial   java/util/HashSet.<init>:()V
        //  4246: iconst_0       
        //  4247: istore          16
        //  4249: iload           16
        //  4251: iload           9
        //  4253: if_icmpge       4322
        //  4256: iload_3        
        //  4257: istore_2       
        //  4258: aload           4
        //  4260: astore          7
        //  4262: iload           11
        //  4264: istore          6
        //  4266: aload_0        
        //  4267: getfield        acs.aI:Ljava/util/ArrayList;
        //  4270: iload           16
        //  4272: invokevirtual   java/util/ArrayList.get:(I)Ljava/lang/Object;
        //  4275: checkcast       Lacr;
        //  4278: astore          14
        //  4280: iload_3        
        //  4281: istore_2       
        //  4282: aload           4
        //  4284: astore          7
        //  4286: iload           11
        //  4288: istore          6
        //  4290: aload           14
        //  4292: invokevirtual   acr.E:()Z
        //  4295: ifne            4316
        //  4298: iload_3        
        //  4299: istore_2       
        //  4300: aload           4
        //  4302: astore          7
        //  4304: iload           11
        //  4306: istore          6
        //  4308: aload           20
        //  4310: aload           14
        //  4312: invokevirtual   java/util/HashSet.add:(Ljava/lang/Object;)Z
        //  4315: pop            
        //  4316: iinc            16, 1
        //  4319: goto            4249
        //  4322: aload_0        
        //  4323: invokevirtual   acr.M:()I
        //  4326: istore          6
        //  4328: iload           6
        //  4330: iconst_2       
        //  4331: if_icmpne       4340
        //  4334: iconst_0       
        //  4335: istore          6
        //  4337: goto            4343
        //  4340: iconst_1       
        //  4341: istore          6
        //  4343: aload_0        
        //  4344: aload_0        
        //  4345: aload           21
        //  4347: aload           20
        //  4349: iload           6
        //  4351: iconst_0       
        //  4352: invokevirtual   acr.p:(Lacs;Lacj;Ljava/util/HashSet;IZ)V
        //  4355: aload           20
        //  4357: invokevirtual   java/util/HashSet.iterator:()Ljava/util/Iterator;
        //  4360: astore          14
        //  4362: aload           14
        //  4364: invokeinterface java/util/Iterator.hasNext:()Z
        //  4369: ifeq            4562
        //  4372: aload           14
        //  4374: invokeinterface java/util/Iterator.next:()Ljava/lang/Object;
        //  4379: checkcast       Lacr;
        //  4382: astore          7
        //  4384: aload_0        
        //  4385: aload           21
        //  4387: aload           7
        //  4389: invokestatic    acw.a:(Lacs;Lacj;Lacr;)V
        //  4392: aload           7
        //  4394: aload           21
        //  4396: iload           12
        //  4398: invokevirtual   acr.b:(Lacj;Z)V
        //  4401: goto            4362
        //  4404: astore          7
        //  4406: goto            4937
        //  4409: iconst_0       
        //  4410: istore          6
        //  4412: iload           6
        //  4414: iload           9
        //  4416: if_icmpge       4562
        //  4419: aload_0        
        //  4420: getfield        acs.aI:Ljava/util/ArrayList;
        //  4423: iload           6
        //  4425: invokevirtual   java/util/ArrayList.get:(I)Ljava/lang/Object;
        //  4428: checkcast       Lacr;
        //  4431: astore          7
        //  4433: aload           7
        //  4435: instanceof      Lacs;
        //  4438: ifeq            4531
        //  4441: aload           7
        //  4443: getfield        acr.aq:[I
        //  4446: astore          14
        //  4448: aload           14
        //  4450: iconst_0       
        //  4451: iaload         
        //  4452: istore          16
        //  4454: aload           14
        //  4456: iconst_1       
        //  4457: iaload         
        //  4458: istore          10
        //  4460: iload           16
        //  4462: istore_2       
        //  4463: iload           16
        //  4465: iconst_2       
        //  4466: if_icmpne       4477
        //  4469: aload           7
        //  4471: iconst_1       
        //  4472: invokevirtual   acr.P:(I)V
        //  4475: iconst_2       
        //  4476: istore_2       
        //  4477: iload           10
        //  4479: istore          16
        //  4481: iload           10
        //  4483: iconst_2       
        //  4484: if_icmpne       4496
        //  4487: aload           7
        //  4489: iconst_1       
        //  4490: invokevirtual   acr.Q:(I)V
        //  4493: iconst_2       
        //  4494: istore          16
        //  4496: aload           7
        //  4498: aload           21
        //  4500: iload           12
        //  4502: invokevirtual   acr.b:(Lacj;Z)V
        //  4505: iload_2        
        //  4506: iconst_2       
        //  4507: if_icmpne       4516
        //  4510: aload           7
        //  4512: iconst_2       
        //  4513: invokevirtual   acr.P:(I)V
        //  4516: iload           16
        //  4518: iconst_2       
        //  4519: if_icmpne       4556
        //  4522: aload           7
        //  4524: iconst_2       
        //  4525: invokevirtual   acr.Q:(I)V
        //  4528: goto            4556
        //  4531: aload_0        
        //  4532: aload           21
        //  4534: aload           7
        //  4536: invokestatic    acw.a:(Lacs;Lacj;Lacr;)V
        //  4539: aload           7
        //  4541: invokevirtual   acr.E:()Z
        //  4544: ifne            4556
        //  4547: aload           7
        //  4549: aload           21
        //  4551: iload           12
        //  4553: invokevirtual   acr.b:(Lacj;Z)V
        //  4556: iinc            6, 1
        //  4559: goto            4412
        //  4562: iload_3        
        //  4563: istore          6
        //  4565: aload           4
        //  4567: astore          14
        //  4569: iload           11
        //  4571: istore          16
        //  4573: aload_0        
        //  4574: getfield        acs.at:I
        //  4577: istore_2       
        //  4578: iload_2        
        //  4579: ifle            4593
        //  4582: aload_0        
        //  4583: aload           21
        //  4585: aconst_null    
        //  4586: iconst_0       
        //  4587: invokestatic    sm.b:(Lacs;Lacj;Ljava/util/ArrayList;I)V
        //  4590: goto            4593
        //  4593: aload_0        
        //  4594: getfield        acs.au:I
        //  4597: ifle            4608
        //  4600: aload_0        
        //  4601: aload           21
        //  4603: aconst_null    
        //  4604: iconst_1       
        //  4605: invokestatic    sm.b:(Lacs;Lacj;Ljava/util/ArrayList;I)V
        //  4608: aload_0        
        //  4609: getfield        acs.aA:Ljava/lang/ref/WeakReference;
        //  4612: astore          7
        //  4614: aload           7
        //  4616: ifnull          4657
        //  4619: aload           7
        //  4621: invokevirtual   java/lang/ref/WeakReference.get:()Ljava/lang/Object;
        //  4624: ifnull          4657
        //  4627: aload_0        
        //  4628: aload_0        
        //  4629: getfield        acs.aA:Ljava/lang/ref/WeakReference;
        //  4632: invokevirtual   java/lang/ref/WeakReference.get:()Ljava/lang/Object;
        //  4635: checkcast       Lacq;
        //  4638: aload_0        
        //  4639: getfield        acs.d:Lacj;
        //  4642: aload_0        
        //  4643: getfield        acs.K:Lacq;
        //  4646: invokevirtual   acj.b:(Ljava/lang/Object;)Lacm;
        //  4649: invokespecial   acs.aa:(Lacq;Lacm;)V
        //  4652: aload_0        
        //  4653: aconst_null    
        //  4654: putfield        acs.aA:Ljava/lang/ref/WeakReference;
        //  4657: aload_0        
        //  4658: getfield        acs.aC:Ljava/lang/ref/WeakReference;
        //  4661: astore          7
        //  4663: aload           7
        //  4665: ifnull          4706
        //  4668: aload           7
        //  4670: invokevirtual   java/lang/ref/WeakReference.get:()Ljava/lang/Object;
        //  4673: ifnull          4706
        //  4676: aload_0        
        //  4677: aload_0        
        //  4678: getfield        acs.aC:Ljava/lang/ref/WeakReference;
        //  4681: invokevirtual   java/lang/ref/WeakReference.get:()Ljava/lang/Object;
        //  4684: checkcast       Lacq;
        //  4687: aload_0        
        //  4688: getfield        acs.d:Lacj;
        //  4691: aload_0        
        //  4692: getfield        acs.M:Lacq;
        //  4695: invokevirtual   acj.b:(Ljava/lang/Object;)Lacm;
        //  4698: invokespecial   acs.Z:(Lacq;Lacm;)V
        //  4701: aload_0        
        //  4702: aconst_null    
        //  4703: putfield        acs.aC:Ljava/lang/ref/WeakReference;
        //  4706: aload_0        
        //  4707: getfield        acs.aB:Ljava/lang/ref/WeakReference;
        //  4710: astore          7
        //  4712: aload           7
        //  4714: ifnull          4755
        //  4717: aload           7
        //  4719: invokevirtual   java/lang/ref/WeakReference.get:()Ljava/lang/Object;
        //  4722: ifnull          4755
        //  4725: aload_0        
        //  4726: aload_0        
        //  4727: getfield        acs.aB:Ljava/lang/ref/WeakReference;
        //  4730: invokevirtual   java/lang/ref/WeakReference.get:()Ljava/lang/Object;
        //  4733: checkcast       Lacq;
        //  4736: aload_0        
        //  4737: getfield        acs.d:Lacj;
        //  4740: aload_0        
        //  4741: getfield        acs.J:Lacq;
        //  4744: invokevirtual   acj.b:(Ljava/lang/Object;)Lacm;
        //  4747: invokespecial   acs.aa:(Lacq;Lacm;)V
        //  4750: aload_0        
        //  4751: aconst_null    
        //  4752: putfield        acs.aB:Ljava/lang/ref/WeakReference;
        //  4755: aload_0        
        //  4756: getfield        acs.aD:Ljava/lang/ref/WeakReference;
        //  4759: astore          7
        //  4761: aload           7
        //  4763: ifnull          4807
        //  4766: aload           7
        //  4768: invokevirtual   java/lang/ref/WeakReference.get:()Ljava/lang/Object;
        //  4771: ifnull          4807
        //  4774: aload_0        
        //  4775: aload_0        
        //  4776: getfield        acs.aD:Ljava/lang/ref/WeakReference;
        //  4779: invokevirtual   java/lang/ref/WeakReference.get:()Ljava/lang/Object;
        //  4782: checkcast       Lacq;
        //  4785: aload_0        
        //  4786: getfield        acs.d:Lacj;
        //  4789: aload_0        
        //  4790: getfield        acs.L:Lacq;
        //  4793: invokevirtual   acj.b:(Ljava/lang/Object;)Lacm;
        //  4796: invokespecial   acs.Z:(Lacq;Lacm;)V
        //  4799: aload_0        
        //  4800: aconst_null    
        //  4801: putfield        acs.aD:Ljava/lang/ref/WeakReference;
        //  4804: goto            4807
        //  4807: aload_0        
        //  4808: getfield        acs.d:Lacj;
        //  4811: invokevirtual   acj.j:()V
        //  4814: aload           14
        //  4816: astore          4
        //  4818: iload           6
        //  4820: istore_3       
        //  4821: goto            4963
        //  4824: astore          7
        //  4826: iload           16
        //  4828: istore          11
        //  4830: aload           14
        //  4832: astore          4
        //  4834: iload           6
        //  4836: istore_3       
        //  4837: goto            4937
        //  4840: astore          7
        //  4842: goto            4406
        //  4845: aload_0        
        //  4846: getfield        acs.aI:Ljava/util/ArrayList;
        //  4849: iload           6
        //  4851: invokevirtual   java/util/ArrayList.get:(I)Ljava/lang/Object;
        //  4854: checkcast       Lacr;
        //  4857: astore          7
        //  4859: aload           7
        //  4861: invokevirtual   acr.E:()Z
        //  4864: ifeq            4897
        //  4867: aload           7
        //  4869: instanceof      Lacx;
        //  4872: ifeq            4888
        //  4875: aload_0        
        //  4876: getfield        acs.aE:Ljava/util/HashSet;
        //  4879: aload           7
        //  4881: invokevirtual   java/util/HashSet.add:(Ljava/lang/Object;)Z
        //  4884: pop            
        //  4885: goto            4897
        //  4888: aload           7
        //  4890: aload           21
        //  4892: iload           12
        //  4894: invokevirtual   acr.b:(Lacj;Z)V
        //  4897: iinc            6, 1
        //  4900: goto            3879
        //  4903: astore          7
        //  4905: goto            4937
        //  4908: astore          4
        //  4910: iload_2        
        //  4911: istore_3       
        //  4912: aload           7
        //  4914: astore          14
        //  4916: iload           6
        //  4918: istore          11
        //  4920: aload           4
        //  4922: astore          7
        //  4924: aload           14
        //  4926: astore          4
        //  4928: goto            4937
        //  4931: astore          7
        //  4933: iload           6
        //  4935: istore          11
        //  4937: aload           7
        //  4939: invokevirtual   java/lang/Exception.printStackTrace:()V
        //  4942: getstatic       java/lang/System.out:Ljava/io/PrintStream;
        //  4945: ldc_w           "EXCEPTION : "
        //  4948: aload           7
        //  4950: invokevirtual   java/lang/Object.toString:()Ljava/lang/String;
        //  4953: invokevirtual   java/lang/String.concat:(Ljava/lang/String;)Ljava/lang/String;
        //  4956: invokevirtual   java/io/PrintStream.println:(Ljava/lang/String;)V
        //  4959: iload           11
        //  4961: istore          16
        //  4963: getstatic       acw.a:[Z
        //  4966: iconst_2       
        //  4967: iconst_0       
        //  4968: bastore        
        //  4969: aload_0        
        //  4970: bipush          64
        //  4972: invokevirtual   acs.W:(I)Z
        //  4975: istore          12
        //  4977: aload_0        
        //  4978: iload           12
        //  4980: invokevirtual   acr.R:(Z)V
        //  4983: aload_0        
        //  4984: getfield        acs.aI:Ljava/util/ArrayList;
        //  4987: invokevirtual   java/util/ArrayList.size:()I
        //  4990: istore          10
        //  4992: iconst_0       
        //  4993: istore          6
        //  4995: iconst_0       
        //  4996: istore          11
        //  4998: iload           6
        //  5000: iload           10
        //  5002: if_icmpge       5066
        //  5005: aload_0        
        //  5006: getfield        acs.aI:Ljava/util/ArrayList;
        //  5009: iload           6
        //  5011: invokevirtual   java/util/ArrayList.get:(I)Ljava/lang/Object;
        //  5014: checkcast       Lacr;
        //  5017: astore          7
        //  5019: aload           7
        //  5021: iload           12
        //  5023: invokevirtual   acr.R:(Z)V
        //  5026: aload           7
        //  5028: getfield        acr.k:I
        //  5031: iconst_m1      
        //  5032: if_icmpne       5052
        //  5035: aload           7
        //  5037: getfield        acr.l:I
        //  5040: iconst_m1      
        //  5041: if_icmpeq       5047
        //  5044: goto            5052
        //  5047: iconst_0       
        //  5048: istore_2       
        //  5049: goto            5054
        //  5052: iconst_1       
        //  5053: istore_2       
        //  5054: iload           11
        //  5056: iload_2        
        //  5057: ior            
        //  5058: istore          11
        //  5060: iinc            6, 1
        //  5063: goto            4998
        //  5066: iload           11
        //  5068: istore_2       
        //  5069: iload_1        
        //  5070: istore          6
        //  5072: iload           28
        //  5074: ifeq            5286
        //  5077: iload           11
        //  5079: istore_2       
        //  5080: iload_1        
        //  5081: istore          6
        //  5083: iload           16
        //  5085: bipush          8
        //  5087: if_icmpge       5286
        //  5090: iload           11
        //  5092: istore_2       
        //  5093: iload_1        
        //  5094: istore          6
        //  5096: getstatic       acw.a:[Z
        //  5099: iconst_2       
        //  5100: baload         
        //  5101: ifeq            5286
        //  5104: iconst_0       
        //  5105: istore          10
        //  5107: iconst_0       
        //  5108: istore_2       
        //  5109: iconst_0       
        //  5110: istore          6
        //  5112: iload           10
        //  5114: iload           15
        //  5116: if_icmpge       5173
        //  5119: aload_0        
        //  5120: getfield        acs.aI:Ljava/util/ArrayList;
        //  5123: iload           10
        //  5125: invokevirtual   java/util/ArrayList.get:(I)Ljava/lang/Object;
        //  5128: checkcast       Lacr;
        //  5131: astore          7
        //  5133: iload_2        
        //  5134: aload           7
        //  5136: getfield        acr.Z:I
        //  5139: aload           7
        //  5141: invokevirtual   acr.j:()I
        //  5144: iadd           
        //  5145: invokestatic    java/lang/Math.max:(II)I
        //  5148: istore_2       
        //  5149: iload           6
        //  5151: aload           7
        //  5153: getfield        acr.aa:I
        //  5156: aload           7
        //  5158: invokevirtual   acr.h:()I
        //  5161: iadd           
        //  5162: invokestatic    java/lang/Math.max:(II)I
        //  5165: istore          6
        //  5167: iinc            10, 1
        //  5170: goto            5112
        //  5173: aload_0        
        //  5174: getfield        acs.ac:I
        //  5177: iload_2        
        //  5178: invokestatic    java/lang/Math.max:(II)I
        //  5181: istore_2       
        //  5182: aload_0        
        //  5183: getfield        acs.ad:I
        //  5186: iload           6
        //  5188: invokestatic    java/lang/Math.max:(II)I
        //  5191: istore          29
        //  5193: iload           11
        //  5195: istore          9
        //  5197: iload_1        
        //  5198: istore          10
        //  5200: iload           8
        //  5202: iconst_2       
        //  5203: if_icmpne       5239
        //  5206: iload           11
        //  5208: istore          9
        //  5210: iload_1        
        //  5211: istore          10
        //  5213: aload_0        
        //  5214: invokevirtual   acr.j:()I
        //  5217: iload_2        
        //  5218: if_icmpge       5239
        //  5221: aload_0        
        //  5222: iload_2        
        //  5223: invokevirtual   acr.C:(I)V
        //  5226: aload_0        
        //  5227: getfield        acs.aq:[I
        //  5230: iconst_0       
        //  5231: iconst_2       
        //  5232: iastore        
        //  5233: iconst_1       
        //  5234: istore          9
        //  5236: iconst_1       
        //  5237: istore          10
        //  5239: iload           9
        //  5241: istore_2       
        //  5242: iload           10
        //  5244: istore          6
        //  5246: iload           13
        //  5248: iconst_2       
        //  5249: if_icmpne       5286
        //  5252: iload           9
        //  5254: istore_2       
        //  5255: iload           10
        //  5257: istore          6
        //  5259: aload_0        
        //  5260: invokevirtual   acr.h:()I
        //  5263: iload           29
        //  5265: if_icmpge       5286
        //  5268: aload_0        
        //  5269: iload           29
        //  5271: invokevirtual   acr.x:(I)V
        //  5274: aload_0        
        //  5275: getfield        acs.aq:[I
        //  5278: iconst_1       
        //  5279: iconst_2       
        //  5280: iastore        
        //  5281: iconst_1       
        //  5282: istore_2       
        //  5283: iconst_1       
        //  5284: istore          6
        //  5286: aload_0        
        //  5287: getfield        acs.ac:I
        //  5290: aload_0        
        //  5291: invokevirtual   acr.j:()I
        //  5294: invokestatic    java/lang/Math.max:(II)I
        //  5297: istore          11
        //  5299: iload           11
        //  5301: aload_0        
        //  5302: invokevirtual   acr.j:()I
        //  5305: if_icmple       5329
        //  5308: aload_0        
        //  5309: iload           11
        //  5311: invokevirtual   acr.C:(I)V
        //  5314: aload_0        
        //  5315: getfield        acs.aq:[I
        //  5318: iconst_0       
        //  5319: iconst_1       
        //  5320: iastore        
        //  5321: iconst_1       
        //  5322: istore          11
        //  5324: iconst_1       
        //  5325: istore_1       
        //  5326: goto            5335
        //  5329: iload_2        
        //  5330: istore          11
        //  5332: iload           6
        //  5334: istore_1       
        //  5335: aload_0        
        //  5336: getfield        acs.ad:I
        //  5339: aload_0        
        //  5340: invokevirtual   acr.h:()I
        //  5343: invokestatic    java/lang/Math.max:(II)I
        //  5346: istore          6
        //  5348: iload           6
        //  5350: aload_0        
        //  5351: invokevirtual   acr.h:()I
        //  5354: if_icmple       5378
        //  5357: aload_0        
        //  5358: iload           6
        //  5360: invokevirtual   acr.x:(I)V
        //  5363: aload_0        
        //  5364: getfield        acs.aq:[I
        //  5367: iconst_1       
        //  5368: iconst_1       
        //  5369: iastore        
        //  5370: iconst_1       
        //  5371: istore          11
        //  5373: iconst_1       
        //  5374: istore_1       
        //  5375: goto            5378
        //  5378: iload_1        
        //  5379: ifne            5522
        //  5382: aload_0        
        //  5383: getfield        acs.aq:[I
        //  5386: astore          7
        //  5388: iload           11
        //  5390: istore_2       
        //  5391: iload_1        
        //  5392: istore          6
        //  5394: aload           7
        //  5396: iconst_0       
        //  5397: iaload         
        //  5398: iconst_2       
        //  5399: if_icmpne       5449
        //  5402: iload           11
        //  5404: istore_2       
        //  5405: iload_1        
        //  5406: istore          6
        //  5408: iload           5
        //  5410: ifle            5449
        //  5413: iload           11
        //  5415: istore_2       
        //  5416: iload_1        
        //  5417: istore          6
        //  5419: aload_0        
        //  5420: invokevirtual   acr.j:()I
        //  5423: iload           5
        //  5425: if_icmple       5449
        //  5428: aload_0        
        //  5429: iconst_1       
        //  5430: putfield        acs.ay:Z
        //  5433: aload           7
        //  5435: iconst_0       
        //  5436: iconst_1       
        //  5437: iastore        
        //  5438: aload_0        
        //  5439: iload           5
        //  5441: invokevirtual   acr.C:(I)V
        //  5444: iconst_1       
        //  5445: istore_2       
        //  5446: iconst_1       
        //  5447: istore          6
        //  5449: aload_0        
        //  5450: getfield        acs.aq:[I
        //  5453: astore          7
        //  5455: aload           7
        //  5457: iconst_1       
        //  5458: iaload         
        //  5459: iconst_2       
        //  5460: if_icmpne       5513
        //  5463: iload_3        
        //  5464: ifle            5513
        //  5467: aload_0        
        //  5468: invokevirtual   acr.h:()I
        //  5471: istore          9
        //  5473: iload_3        
        //  5474: istore          10
        //  5476: iload_2        
        //  5477: istore          11
        //  5479: iload           6
        //  5481: istore_1       
        //  5482: iload           9
        //  5484: iload           10
        //  5486: if_icmple       5522
        //  5489: aload_0        
        //  5490: iconst_1       
        //  5491: putfield        acs.az:Z
        //  5494: aload           7
        //  5496: iconst_1       
        //  5497: iconst_1       
        //  5498: iastore        
        //  5499: aload_0        
        //  5500: iload           10
        //  5502: invokevirtual   acr.x:(I)V
        //  5505: iconst_1       
        //  5506: istore          11
        //  5508: iconst_1       
        //  5509: istore_1       
        //  5510: goto            5522
        //  5513: iload_2        
        //  5514: istore          11
        //  5516: iload           6
        //  5518: istore_1       
        //  5519: goto            5522
        //  5522: iload           16
        //  5524: bipush          8
        //  5526: if_icmple       5535
        //  5529: iconst_0       
        //  5530: istore          6
        //  5532: goto            5538
        //  5535: iconst_1       
        //  5536: istore          6
        //  5538: iload           6
        //  5540: iload           11
        //  5542: iand           
        //  5543: istore          11
        //  5545: iload           16
        //  5547: istore          6
        //  5549: goto            3398
        //  5552: aload_0        
        //  5553: aload           4
        //  5555: putfield        acs.aI:Ljava/util/ArrayList;
        //  5558: iload_1        
        //  5559: ifeq            5580
        //  5562: aload_0        
        //  5563: getfield        acs.aq:[I
        //  5566: astore          4
        //  5568: aload           4
        //  5570: iconst_0       
        //  5571: iload           8
        //  5573: iastore        
        //  5574: aload           4
        //  5576: iconst_1       
        //  5577: iload           13
        //  5579: iastore        
        //  5580: aload_0        
        //  5581: aload_0        
        //  5582: getfield        acs.d:Lacj;
        //  5585: getfield        acj.j:Lcdn;
        //  5588: invokevirtual   acr.S:(Lcdn;)V
        //  5591: return         
        //    Exceptions:
        //  Try           Handler
        //  Start  End    Start  End    Type                 
        //  -----  -----  -----  -----  ---------------------
        //  3413   3420   4931   4937   Ljava/lang/Exception;
        //  3424   3428   4931   4937   Ljava/lang/Exception;
        //  3432   3440   4931   4937   Ljava/lang/Exception;
        //  3452   3470   4931   4937   Ljava/lang/Exception;
        //  3480   3486   4931   4937   Ljava/lang/Exception;
        //  3490   3498   4931   4937   Ljava/lang/Exception;
        //  3502   3510   4931   4937   Ljava/lang/Exception;
        //  3514   3523   4931   4937   Ljava/lang/Exception;
        //  3540   3554   4931   4937   Ljava/lang/Exception;
        //  3558   3565   4931   4937   Ljava/lang/Exception;
        //  3575   3582   4908   4931   Ljava/lang/Exception;
        //  3592   3602   4908   4931   Ljava/lang/Exception;
        //  3633   3647   4908   4931   Ljava/lang/Exception;
        //  3657   3665   4908   4931   Ljava/lang/Exception;
        //  3675   3682   4908   4931   Ljava/lang/Exception;
        //  3695   3705   4908   4931   Ljava/lang/Exception;
        //  3715   3725   4908   4931   Ljava/lang/Exception;
        //  3735   3743   4908   4931   Ljava/lang/Exception;
        //  3753   3761   4908   4931   Ljava/lang/Exception;
        //  3774   3781   4908   4931   Ljava/lang/Exception;
        //  3820   3827   4908   4931   Ljava/lang/Exception;
        //  3840   3847   4908   4931   Ljava/lang/Exception;
        //  3869   3876   4908   4931   Ljava/lang/Exception;
        //  3896   3906   4908   4931   Ljava/lang/Exception;
        //  3916   3925   4908   4931   Ljava/lang/Exception;
        //  3935   3944   4908   4931   Ljava/lang/Exception;
        //  3954   3964   4908   4931   Ljava/lang/Exception;
        //  3974   3989   4908   4931   Ljava/lang/Exception;
        //  3999   4005   4908   4931   Ljava/lang/Exception;
        //  4018   4028   4908   4931   Ljava/lang/Exception;
        //  4038   4054   4908   4931   Ljava/lang/Exception;
        //  4064   4073   4908   4931   Ljava/lang/Exception;
        //  4083   4093   4908   4931   Ljava/lang/Exception;
        //  4115   4127   4908   4931   Ljava/lang/Exception;
        //  4137   4146   4908   4931   Ljava/lang/Exception;
        //  4156   4166   4908   4931   Ljava/lang/Exception;
        //  4176   4193   4908   4931   Ljava/lang/Exception;
        //  4206   4213   4908   4931   Ljava/lang/Exception;
        //  4226   4231   4908   4931   Ljava/lang/Exception;
        //  4236   4246   4404   4406   Ljava/lang/Exception;
        //  4266   4280   4908   4931   Ljava/lang/Exception;
        //  4290   4298   4908   4931   Ljava/lang/Exception;
        //  4308   4316   4908   4931   Ljava/lang/Exception;
        //  4322   4328   4404   4406   Ljava/lang/Exception;
        //  4343   4362   4840   4845   Ljava/lang/Exception;
        //  4362   4401   4840   4845   Ljava/lang/Exception;
        //  4419   4448   4840   4845   Ljava/lang/Exception;
        //  4469   4475   4840   4845   Ljava/lang/Exception;
        //  4487   4493   4840   4845   Ljava/lang/Exception;
        //  4496   4505   4840   4845   Ljava/lang/Exception;
        //  4510   4516   4840   4845   Ljava/lang/Exception;
        //  4522   4528   4840   4845   Ljava/lang/Exception;
        //  4531   4556   4840   4845   Ljava/lang/Exception;
        //  4573   4578   4840   4845   Ljava/lang/Exception;
        //  4582   4590   4824   4840   Ljava/lang/Exception;
        //  4593   4608   4824   4840   Ljava/lang/Exception;
        //  4608   4614   4840   4845   Ljava/lang/Exception;
        //  4619   4652   4840   4845   Ljava/lang/Exception;
        //  4652   4657   4824   4840   Ljava/lang/Exception;
        //  4657   4663   4840   4845   Ljava/lang/Exception;
        //  4668   4701   4840   4845   Ljava/lang/Exception;
        //  4701   4706   4824   4840   Ljava/lang/Exception;
        //  4706   4712   4840   4845   Ljava/lang/Exception;
        //  4717   4750   4840   4845   Ljava/lang/Exception;
        //  4750   4755   4824   4840   Ljava/lang/Exception;
        //  4755   4761   4840   4845   Ljava/lang/Exception;
        //  4766   4799   4840   4845   Ljava/lang/Exception;
        //  4799   4804   4903   4908   Ljava/lang/Exception;
        //  4807   4814   4903   4908   Ljava/lang/Exception;
        //  4845   4885   4903   4908   Ljava/lang/Exception;
        //  4888   4897   4903   4908   Ljava/lang/Exception;
        // 
        // The error that occurred was:
        // 
        // java.lang.IllegalStateException: Expression is linked from several locations: Label_4343:
        //     at com.strobel.decompiler.ast.Error.expressionLinkedFromMultipleLocations(Error.java:27)
        //     at com.strobel.decompiler.ast.AstOptimizer.mergeDisparateObjectInitializations(AstOptimizer.java:2604)
        //     at com.strobel.decompiler.ast.AstOptimizer.optimize(AstOptimizer.java:235)
        //     at com.strobel.decompiler.ast.AstOptimizer.optimize(AstOptimizer.java:42)
        //     at com.strobel.decompiler.languages.java.ast.AstMethodBodyBuilder.createMethodBody(AstMethodBodyBuilder.java:206)
        //     at com.strobel.decompiler.languages.java.ast.AstMethodBodyBuilder.createMethodBody(AstMethodBodyBuilder.java:93)
        //     at com.strobel.decompiler.languages.java.ast.AstBuilder.createMethodBody(AstBuilder.java:868)
        //     at com.strobel.decompiler.languages.java.ast.AstBuilder.createMethod(AstBuilder.java:761)
        //     at com.strobel.decompiler.languages.java.ast.AstBuilder.addTypeMembers(AstBuilder.java:638)
        //     at com.strobel.decompiler.languages.java.ast.AstBuilder.createTypeCore(AstBuilder.java:605)
        //     at com.strobel.decompiler.languages.java.ast.AstBuilder.createTypeNoCache(AstBuilder.java:195)
        //     at com.strobel.decompiler.languages.java.ast.AstBuilder.createType(AstBuilder.java:162)
        //     at com.strobel.decompiler.languages.java.ast.AstBuilder.addType(AstBuilder.java:137)
        //     at com.strobel.decompiler.languages.java.JavaLanguage.buildAst(JavaLanguage.java:71)
        //     at com.strobel.decompiler.languages.java.JavaLanguage.decompileType(JavaLanguage.java:59)
        //     at com.strobel.decompiler.DecompilerDriver.decompileType(DecompilerDriver.java:333)
        //     at com.strobel.decompiler.DecompilerDriver.decompileJar(DecompilerDriver.java:254)
        //     at com.strobel.decompiler.DecompilerDriver.main(DecompilerDriver.java:129)
        // 
        throw new IllegalStateException("An error occurred while decompiling this method.");
    }
    
    public final void U(final int ax) {
        this.ax = ax;
        acj.a = this.W(512);
    }
    
    public final boolean V(final boolean b, final int n) {
        final adc a = this.a;
        final acs a2 = a.a;
        final boolean b2 = false;
        final int l = a2.L(0);
        final int i = a.a.L(1);
        final acs a3 = a.a;
        final int k = a3.k();
        final int j = a3.l();
        int n2 = i;
        Label_0303: {
            if (b) {
                int n3 = i;
                if (l != 2) {
                    if ((n2 = i) != 2) {
                        break Label_0303;
                    }
                    n3 = 2;
                }
                final ArrayList e = a.e;
                final int size = e.size();
                int n4 = 0;
                while (true) {
                    while (n4 < size) {
                        final adm adm = (adm)e.get(n4);
                        if (adm.g == n && !adm.e()) {
                            final boolean b3 = false;
                            if (n == 0) {
                                n2 = n3;
                                if (!b3) {
                                    break Label_0303;
                                }
                                n2 = n3;
                                if (l == 2) {
                                    a.a.P(1);
                                    final acs a4 = a.a;
                                    a4.C(a.a(a4, 0));
                                    final acs a5 = a.a;
                                    a5.h.f.c(a5.j());
                                    n2 = n3;
                                }
                                break Label_0303;
                            }
                            else {
                                n2 = n3;
                                if (b3 && (n2 = n3) == 2) {
                                    a.a.Q(1);
                                    final acs a6 = a.a;
                                    a6.x(a.a(a6, 1));
                                    final acs a7 = a.a;
                                    a7.i.f.c(a7.h());
                                    n2 = n3;
                                }
                                break Label_0303;
                            }
                        }
                        else {
                            ++n4;
                        }
                    }
                    final boolean b3 = true;
                    continue;
                }
            }
        }
        boolean b4 = false;
        Label_0458: {
            Label_0455: {
                if (n == 0) {
                    final acs a8 = a.a;
                    final int n5 = a8.aq[0];
                    if (n5 == 1 || n5 == 4) {
                        final int n6 = a8.j() + k;
                        a8.h.j.c(n6);
                        a.a.h.f.c(n6 - k);
                        break Label_0455;
                    }
                }
                else {
                    final acs a9 = a.a;
                    final int n7 = a9.aq[1];
                    if (n7 == 1 || n7 == 4) {
                        final int n8 = a9.h() + j;
                        a9.i.j.c(n8);
                        a.a.i.f.c(n8 - j);
                        break Label_0455;
                    }
                }
                b4 = false;
                break Label_0458;
            }
            b4 = true;
        }
        a.c();
        final ArrayList e2 = a.e;
        for (int size2 = e2.size(), n9 = 0; n9 < size2; ++n9) {
            final adm adm2 = (adm)e2.get(n9);
            if (adm2.g == n) {
                if (adm2.d != a.a || adm2.h) {
                    adm2.c();
                }
            }
        }
        final ArrayList e3 = a.e;
        while (true) {
            for (int size3 = e3.size(), n10 = 0; n10 < size3; ++n10) {
                final adm adm3 = (adm)e3.get(n10);
                if (adm3.g == n) {
                    if (b4 || adm3.d != a.a) {
                        boolean b5;
                        if (!adm3.i.i) {
                            b5 = b2;
                        }
                        else if (!adm3.j.i) {
                            b5 = b2;
                        }
                        else {
                            if (adm3 instanceof ada || adm3.f.i) {
                                continue;
                            }
                            b5 = b2;
                        }
                        a.a.P(l);
                        a.a.Q(n2);
                        return b5;
                    }
                }
            }
            boolean b5 = true;
            continue;
        }
    }
    
    public final boolean W(final int n) {
        return (this.ax & n) == n;
    }
    
    final void a(final acr acr, int n) {
        if (n == 0) {
            n = this.at;
            final acp[] aw = this.aw;
            final int length = aw.length;
            if (n + 1 >= length) {
                this.aw = Arrays.copyOf(aw, length + length);
            }
            final acp[] aw2 = this.aw;
            n = this.at;
            aw2[n] = new acp(acr, 0, this.c);
            this.at = n + 1;
            return;
        }
        final int au = this.au;
        final acp[] av = this.av;
        n = av.length;
        if (au + 1 >= n) {
            this.av = Arrays.copyOf(av, n + n);
        }
        final acp[] av2 = this.av;
        n = this.au;
        av2[n] = new acp(acr, 1, this.c);
        this.au = n + 1;
    }
    
    public final void c() {
        this.a.b = true;
    }
    
    @Override
    public final void s() {
        this.d.k();
        this.ar = 0;
        this.as = 0;
        super.s();
    }
}
