// 
// Decompiled by Procyon v0.6.0
// 

public final class arzy implements Runnable
{
    public final /* synthetic */ asab a;
    private final atdo b;
    
    public arzy(final asab a, final atdo b, final byte[] array) {
        this.a = a;
        b.getClass();
        this.b = b;
    }
    
    @Override
    public final void run() {
        // 
        // This method could not be decompiled.
        // 
        // Original Bytecode:
        // 
        //     3: getstatic       java/util/logging/Level.FINER:Ljava/util/logging/Level;
        //     6: invokevirtual   java/util/logging/Logger.isLoggable:(Ljava/util/logging/Level;)Z
        //     9: ifeq            40
        //    12: getstatic       asab.a:Ljava/util/logging/Logger;
        //    15: getstatic       java/util/logging/Level.FINER:Ljava/util/logging/Level;
        //    18: ldc             "io.grpc.internal.DnsNameResolver$Resolve"
        //    20: ldc             "run"
        //    22: ldc             "Attempting DNS resolution of "
        //    24: aload_0        
        //    25: getfield        arzy.a:Lasab;
        //    28: getfield        asab.k:Ljava/lang/String;
        //    31: invokestatic    java/lang/String.valueOf:(Ljava/lang/Object;)Ljava/lang/String;
        //    34: invokevirtual   java/lang/String.concat:(Ljava/lang/String;)Ljava/lang/String;
        //    37: invokevirtual   java/util/logging/Logger.logp:(Ljava/util/logging/Level;Ljava/lang/String;Ljava/lang/String;Ljava/lang/String;)V
        //    40: aload_0        
        //    41: getfield        arzy.a:Lasab;
        //    44: astore_1       
        //    45: aload_1        
        //    46: getfield        asab.k:Ljava/lang/String;
        //    49: aload_1        
        //    50: getfield        asab.l:I
        //    53: invokestatic    java/net/InetSocketAddress.createUnresolved:(Ljava/lang/String;I)Ljava/net/InetSocketAddress;
        //    56: astore_2       
        //    57: aload_1        
        //    58: getfield        asab.g:Larvb;
        //    61: astore_1       
        //    62: aload_2        
        //    63: instanceof      Ljava/net/InetSocketAddress;
        //    66: ifne            74
        //    69: aconst_null    
        //    70: astore_2       
        //    71: goto            113
        //    74: aload_1        
        //    75: checkcast       Lasdb;
        //    78: getfield        asdb.b:Ljava/net/InetSocketAddress;
        //    81: astore_3       
        //    82: aload_3        
        //    83: ifnull          108
        //    86: invokestatic    arsr.a:()Larss;
        //    89: astore_1       
        //    90: aload_1        
        //    91: aload_3        
        //    92: invokevirtual   arss.d:(Ljava/net/SocketAddress;)V
        //    95: aload_1        
        //    96: aload_2        
        //    97: invokevirtual   arss.e:(Ljava/net/InetSocketAddress;)V
        //   100: aload_1        
        //   101: invokevirtual   arss.c:()Larsr;
        //   104: astore_2       
        //   105: goto            113
        //   108: aload_2        
        //   109: invokestatic    asdb.a:(Ljava/net/InetSocketAddress;)Larva;
        //   112: astore_2       
        //   113: aload_2        
        //   114: ifnull          139
        //   117: new             Larsk;
        //   120: astore_1       
        //   121: aload_1        
        //   122: aload_2        
        //   123: invokespecial   arsk.<init>:(Ljava/net/SocketAddress;)V
        //   126: aload_1        
        //   127: astore_2       
        //   128: goto            141
        //   131: astore_2       
        //   132: goto            2681
        //   135: astore_1       
        //   136: goto            2689
        //   139: aconst_null    
        //   140: astore_2       
        //   141: invokestatic    java/util/Collections.emptyList:()Ljava/util/List;
        //   144: astore          4
        //   146: getstatic       arrg.a:Larrg;
        //   149: astore          5
        //   151: aload_2        
        //   152: ifnull          234
        //   155: getstatic       asab.a:Ljava/util/logging/Logger;
        //   158: getstatic       java/util/logging/Level.FINER:Ljava/util/logging/Level;
        //   161: invokevirtual   java/util/logging/Logger.isLoggable:(Ljava/util/logging/Level;)Z
        //   164: ifeq            215
        //   167: getstatic       asab.a:Ljava/util/logging/Logger;
        //   170: astore          6
        //   172: getstatic       java/util/logging/Level.FINER:Ljava/util/logging/Level;
        //   175: astore_3       
        //   176: aload_2        
        //   177: invokevirtual   java/lang/Object.toString:()Ljava/lang/String;
        //   180: astore_1       
        //   181: new             Ljava/lang/StringBuilder;
        //   184: astore          7
        //   186: aload           7
        //   188: ldc             "Using proxy address "
        //   190: invokespecial   java/lang/StringBuilder.<init>:(Ljava/lang/String;)V
        //   193: aload           7
        //   195: aload_1        
        //   196: invokevirtual   java/lang/StringBuilder.append:(Ljava/lang/String;)Ljava/lang/StringBuilder;
        //   199: pop            
        //   200: aload           6
        //   202: aload_3        
        //   203: ldc             "io.grpc.internal.DnsNameResolver$Resolve"
        //   205: ldc             "run"
        //   207: aload           7
        //   209: invokevirtual   java/lang/StringBuilder.toString:()Ljava/lang/String;
        //   212: invokevirtual   java/util/logging/Logger.logp:(Ljava/util/logging/Level;Ljava/lang/String;Ljava/lang/String;Ljava/lang/String;)V
        //   215: aload_2        
        //   216: invokestatic    java/util/Collections.singletonList:(Ljava/lang/Object;)Ljava/util/List;
        //   219: astore_3       
        //   220: aconst_null    
        //   221: astore          6
        //   223: aconst_null    
        //   224: astore_2       
        //   225: aload           6
        //   227: astore_1       
        //   228: aload_3        
        //   229: astore          7
        //   231: goto            2596
        //   234: aload_0        
        //   235: getfield        arzy.a:Lasab;
        //   238: astore          7
        //   240: new             Larzw;
        //   243: astore_1       
        //   244: aload_1        
        //   245: invokespecial   arzw.<init>:()V
        //   248: aload           7
        //   250: getfield        asab.i:Larzv;
        //   253: astore_2       
        //   254: aload           7
        //   256: getfield        asab.k:Ljava/lang/String;
        //   259: invokestatic    java/net/InetAddress.getAllByName:(Ljava/lang/String;)[Ljava/net/InetAddress;
        //   262: invokestatic    java/util/Arrays.asList:([Ljava/lang/Object;)Ljava/util/List;
        //   265: invokestatic    java/util/Collections.unmodifiableList:(Ljava/util/List;)Ljava/util/List;
        //   268: astore_3       
        //   269: new             Ljava/util/ArrayList;
        //   272: astore_2       
        //   273: aload_2        
        //   274: aload_3        
        //   275: invokeinterface java/util/List.size:()I
        //   280: invokespecial   java/util/ArrayList.<init>:(I)V
        //   283: aload_3        
        //   284: invokeinterface java/util/List.iterator:()Ljava/util/Iterator;
        //   289: astore_3       
        //   290: aload_3        
        //   291: invokeinterface java/util/Iterator.hasNext:()Z
        //   296: istore          8
        //   298: iload           8
        //   300: ifeq            359
        //   303: aload_3        
        //   304: invokeinterface java/util/Iterator.next:()Ljava/lang/Object;
        //   309: checkcast       Ljava/net/InetAddress;
        //   312: astore          9
        //   314: new             Larsk;
        //   317: astore          6
        //   319: new             Ljava/net/InetSocketAddress;
        //   322: astore          10
        //   324: aload           10
        //   326: aload           9
        //   328: aload           7
        //   330: getfield        asab.l:I
        //   333: invokespecial   java/net/InetSocketAddress.<init>:(Ljava/net/InetAddress;I)V
        //   336: aload           6
        //   338: aload           10
        //   340: invokespecial   arsk.<init>:(Ljava/net/SocketAddress;)V
        //   343: aload_2        
        //   344: aload           6
        //   346: invokeinterface java/util/List.add:(Ljava/lang/Object;)Z
        //   351: pop            
        //   352: goto            290
        //   355: astore_2       
        //   356: goto            2446
        //   359: aload_1        
        //   360: aload_2        
        //   361: invokestatic    java/util/Collections.unmodifiableList:(Ljava/util/List;)Ljava/util/List;
        //   364: putfield        arzw.b:Ljava/lang/Object;
        //   367: getstatic       asab.e:Z
        //   370: ifeq            2386
        //   373: invokestatic    java/util/Collections.emptyList:()Ljava/util/List;
        //   376: astore          6
        //   378: getstatic       asab.c:Z
        //   381: istore          8
        //   383: getstatic       asab.d:Z
        //   386: istore          11
        //   388: aload           7
        //   390: getfield        asab.k:Ljava/lang/String;
        //   393: astore_2       
        //   394: iload           8
        //   396: ifne            404
        //   399: aconst_null    
        //   400: astore_2       
        //   401: goto            557
        //   404: ldc             "localhost"
        //   406: aload_2        
        //   407: invokevirtual   java/lang/String.equalsIgnoreCase:(Ljava/lang/String;)Z
        //   410: ifeq            421
        //   413: iload           11
        //   415: ifne            519
        //   418: goto            399
        //   421: aload_2        
        //   422: ldc             ":"
        //   424: invokevirtual   java/lang/String.contains:(Ljava/lang/CharSequence;)Z
        //   427: ifeq            433
        //   430: goto            399
        //   433: iconst_0       
        //   434: istore          12
        //   436: iconst_1       
        //   437: istore          13
        //   439: aload_2        
        //   440: invokevirtual   java/lang/String.length:()I
        //   443: istore          14
        //   445: iload           12
        //   447: iload           14
        //   449: if_icmpge       511
        //   452: aload_2        
        //   453: iload           12
        //   455: invokevirtual   java/lang/String.charAt:(I)C
        //   458: istore          15
        //   460: iload           13
        //   462: istore          14
        //   464: iload           15
        //   466: bipush          46
        //   468: if_icmpeq       501
        //   471: iload           15
        //   473: bipush          48
        //   475: if_icmplt       491
        //   478: iload           15
        //   480: bipush          57
        //   482: if_icmpgt       491
        //   485: iconst_1       
        //   486: istore          14
        //   488: goto            494
        //   491: iconst_0       
        //   492: istore          14
        //   494: iload           13
        //   496: iload           14
        //   498: iand           
        //   499: istore          14
        //   501: iinc            12, 1
        //   504: iload           14
        //   506: istore          13
        //   508: goto            439
        //   511: iload           13
        //   513: ifeq            519
        //   516: goto            399
        //   519: aload           7
        //   521: getfield        asab.j:Ljava/util/concurrent/atomic/AtomicReference;
        //   524: invokevirtual   java/util/concurrent/atomic/AtomicReference.get:()Ljava/lang/Object;
        //   527: checkcast       Larzz;
        //   530: astore_3       
        //   531: aload_3        
        //   532: astore_2       
        //   533: aload_3        
        //   534: ifnonnull       557
        //   537: getstatic       asab.f:Lasaa;
        //   540: astore          9
        //   542: aload_3        
        //   543: astore_2       
        //   544: aload           9
        //   546: ifnull          557
        //   549: aload           9
        //   551: invokeinterface asaa.a:()Larzz;
        //   556: astore_2       
        //   557: aload           6
        //   559: astore_3       
        //   560: aload_2        
        //   561: ifnull          597
        //   564: aload_2        
        //   565: invokeinterface arzz.a:()Ljava/util/List;
        //   570: astore_3       
        //   571: goto            597
        //   574: astore_2       
        //   575: getstatic       asab.a:Ljava/util/logging/Logger;
        //   578: getstatic       java/util/logging/Level.FINE:Ljava/util/logging/Level;
        //   581: ldc_w           "io.grpc.internal.DnsNameResolver"
        //   584: ldc_w           "resolveServiceConfig"
        //   587: ldc_w           "ServiceConfig resolution failure"
        //   590: aload_2        
        //   591: invokevirtual   java/util/logging/Logger.logp:(Ljava/util/logging/Level;Ljava/lang/String;Ljava/lang/String;Ljava/lang/String;Ljava/lang/Throwable;)V
        //   594: aload           6
        //   596: astore_3       
        //   597: aload_3        
        //   598: invokeinterface java/util/List.isEmpty:()Z
        //   603: istore          8
        //   605: iload           8
        //   607: ifne            2330
        //   610: aload           7
        //   612: getfield        asab.h:Ljava/util/Random;
        //   615: astore          9
        //   617: invokestatic    asab.e:()Ljava/lang/String;
        //   620: astore          6
        //   622: new             Ljava/util/ArrayList;
        //   625: astore_2       
        //   626: aload_2        
        //   627: invokespecial   java/util/ArrayList.<init>:()V
        //   630: aload_3        
        //   631: invokeinterface java/util/List.iterator:()Ljava/util/Iterator;
        //   636: astore_3       
        //   637: aload_3        
        //   638: invokeinterface java/util/Iterator.hasNext:()Z
        //   643: ifeq            766
        //   646: aload_3        
        //   647: invokeinterface java/util/Iterator.next:()Ljava/lang/Object;
        //   652: checkcast       Ljava/lang/String;
        //   655: astore          10
        //   657: aload           10
        //   659: ldc_w           "grpc_config="
        //   662: invokevirtual   java/lang/String.startsWith:(Ljava/lang/String;)Z
        //   665: ifne            698
        //   668: getstatic       asab.a:Ljava/util/logging/Logger;
        //   671: getstatic       java/util/logging/Level.FINE:Ljava/util/logging/Level;
        //   674: ldc_w           "io.grpc.internal.DnsNameResolver"
        //   677: ldc_w           "parseTxtResults"
        //   680: ldc_w           "Ignoring non service config {0}"
        //   683: iconst_1       
        //   684: anewarray       Ljava/lang/Object;
        //   687: dup            
        //   688: iconst_0       
        //   689: aload           10
        //   691: aastore        
        //   692: invokevirtual   java/util/logging/Logger.logp:(Ljava/util/logging/Level;Ljava/lang/String;Ljava/lang/String;Ljava/lang/String;[Ljava/lang/Object;)V
        //   695: goto            637
        //   698: aload           10
        //   700: bipush          12
        //   702: invokevirtual   java/lang/String.substring:(I)Ljava/lang/String;
        //   705: invokestatic    asbe.a:(Ljava/lang/String;)Ljava/lang/Object;
        //   708: astore          10
        //   710: aload           10
        //   712: instanceof      Ljava/util/List;
        //   715: ifeq            742
        //   718: aload           10
        //   720: checkcast       Ljava/util/List;
        //   723: astore          10
        //   725: aload           10
        //   727: invokestatic    asbf.i:(Ljava/util/List;)V
        //   730: aload_2        
        //   731: aload           10
        //   733: invokeinterface java/util/List.addAll:(Ljava/util/Collection;)Z
        //   738: pop            
        //   739: goto            637
        //   742: new             Ljava/lang/ClassCastException;
        //   745: astore_2       
        //   746: aload_2        
        //   747: ldc_w           "wrong type "
        //   750: aload           10
        //   752: invokestatic    java/lang/String.valueOf:(Ljava/lang/Object;)Ljava/lang/String;
        //   755: invokestatic    java/lang/String.valueOf:(Ljava/lang/Object;)Ljava/lang/String;
        //   758: invokevirtual   java/lang/String.concat:(Ljava/lang/String;)Ljava/lang/String;
        //   761: invokespecial   java/lang/ClassCastException.<init>:(Ljava/lang/String;)V
        //   764: aload_2        
        //   765: athrow         
        //   766: aload_2        
        //   767: invokeinterface java/util/List.iterator:()Ljava/util/Iterator;
        //   772: astore_3       
        //   773: aconst_null    
        //   774: astore_2       
        //   775: aload_3        
        //   776: invokeinterface java/util/Iterator.hasNext:()Z
        //   781: ifeq            1112
        //   784: aload_3        
        //   785: invokeinterface java/util/Iterator.next:()Ljava/lang/Object;
        //   790: checkcast       Ljava/util/Map;
        //   793: astore          10
        //   795: aload           10
        //   797: invokeinterface java/util/Map.entrySet:()Ljava/util/Set;
        //   802: invokeinterface java/util/Set.iterator:()Ljava/util/Iterator;
        //   807: astore          16
        //   809: aload           16
        //   811: invokeinterface java/util/Iterator.hasNext:()Z
        //   816: ifeq            854
        //   819: aload           16
        //   821: invokeinterface java/util/Iterator.next:()Ljava/lang/Object;
        //   826: checkcast       Ljava/util/Map$Entry;
        //   829: astore_2       
        //   830: getstatic       asab.b:Ljava/util/Set;
        //   833: aload_2        
        //   834: invokeinterface java/util/Map$Entry.getKey:()Ljava/lang/Object;
        //   839: invokeinterface java/util/Set.contains:(Ljava/lang/Object;)Z
        //   844: ldc_w           "Bad key: %s"
        //   847: aload_2        
        //   848: invokestatic    agnj.C:(ZLjava/lang/String;Ljava/lang/Object;)V
        //   851: goto            809
        //   854: aload           10
        //   856: ldc_w           "clientLanguage"
        //   859: invokestatic    asbf.g:(Ljava/util/Map;Ljava/lang/String;)Ljava/util/List;
        //   862: astore_2       
        //   863: aload_2        
        //   864: ifnull          918
        //   867: aload_2        
        //   868: invokeinterface java/util/List.isEmpty:()Z
        //   873: ifne            918
        //   876: aload_2        
        //   877: invokeinterface java/util/List.iterator:()Ljava/util/Iterator;
        //   882: astore_2       
        //   883: aload_2        
        //   884: invokeinterface java/util/Iterator.hasNext:()Z
        //   889: ifeq            913
        //   892: ldc_w           "java"
        //   895: aload_2        
        //   896: invokeinterface java/util/Iterator.next:()Ljava/lang/Object;
        //   901: checkcast       Ljava/lang/String;
        //   904: invokevirtual   java/lang/String.equalsIgnoreCase:(Ljava/lang/String;)Z
        //   907: ifeq            883
        //   910: goto            918
        //   913: aconst_null    
        //   914: astore_2       
        //   915: goto            1050
        //   918: aload           10
        //   920: ldc_w           "percentage"
        //   923: invokestatic    asbf.a:(Ljava/util/Map;Ljava/lang/String;)Ljava/lang/Double;
        //   926: astore_2       
        //   927: aload_2        
        //   928: ifnull          982
        //   931: aload_2        
        //   932: invokevirtual   java/lang/Double.intValue:()I
        //   935: istore          13
        //   937: iload           13
        //   939: iflt            955
        //   942: iload           13
        //   944: bipush          100
        //   946: if_icmpgt       955
        //   949: iconst_1       
        //   950: istore          8
        //   952: goto            958
        //   955: iconst_0       
        //   956: istore          8
        //   958: iload           8
        //   960: ldc_w           "Bad percentage: %s"
        //   963: aload_2        
        //   964: invokestatic    agnj.C:(ZLjava/lang/String;Ljava/lang/Object;)V
        //   967: aload           9
        //   969: bipush          100
        //   971: invokevirtual   java/util/Random.nextInt:(I)I
        //   974: iload           13
        //   976: if_icmplt       982
        //   979: goto            913
        //   982: aload           10
        //   984: ldc_w           "clientHostname"
        //   987: invokestatic    asbf.g:(Ljava/util/Map;Ljava/lang/String;)Ljava/util/List;
        //   990: astore_2       
        //   991: aload_2        
        //   992: ifnull          1037
        //   995: aload_2        
        //   996: invokeinterface java/util/List.isEmpty:()Z
        //  1001: ifne            1037
        //  1004: aload_2        
        //  1005: invokeinterface java/util/List.iterator:()Ljava/util/Iterator;
        //  1010: astore_2       
        //  1011: aload_2        
        //  1012: invokeinterface java/util/Iterator.hasNext:()Z
        //  1017: ifeq            913
        //  1020: aload_2        
        //  1021: invokeinterface java/util/Iterator.next:()Ljava/lang/Object;
        //  1026: checkcast       Ljava/lang/String;
        //  1029: aload           6
        //  1031: invokevirtual   java/lang/String.equals:(Ljava/lang/Object;)Z
        //  1034: ifeq            1011
        //  1037: aload           10
        //  1039: ldc_w           "serviceConfig"
        //  1042: invokestatic    asbf.h:(Ljava/util/Map;Ljava/lang/String;)Ljava/util/Map;
        //  1045: astore_2       
        //  1046: aload_2        
        //  1047: ifnull          1060
        //  1050: aload_2        
        //  1051: ifnull          1057
        //  1054: goto            1112
        //  1057: goto            775
        //  1060: new             Laeyz;
        //  1063: astore_2       
        //  1064: aload_2        
        //  1065: ldc_w           "key '%s' missing in '%s'"
        //  1068: iconst_2       
        //  1069: anewarray       Ljava/lang/Object;
        //  1072: dup            
        //  1073: iconst_0       
        //  1074: aload           10
        //  1076: aastore        
        //  1077: dup            
        //  1078: iconst_1       
        //  1079: ldc_w           "serviceConfig"
        //  1082: aastore        
        //  1083: invokestatic    java/lang/String.format:(Ljava/lang/String;[Ljava/lang/Object;)Ljava/lang/String;
        //  1086: invokespecial   aeyz.<init>:(Ljava/lang/String;)V
        //  1089: aload_2        
        //  1090: athrow         
        //  1091: astore_2       
        //  1092: getstatic       io/grpc/Status.c:Lio/grpc/Status;
        //  1095: ldc_w           "failed to pick service config choice"
        //  1098: invokevirtual   io/grpc/Status.withDescription:(Ljava/lang/String;)Lio/grpc/Status;
        //  1101: aload_2        
        //  1102: invokevirtual   io/grpc/Status.c:(Ljava/lang/Throwable;)Lio/grpc/Status;
        //  1105: invokestatic    arum.b:(Lio/grpc/Status;)Larum;
        //  1108: astore_2       
        //  1109: goto            1151
        //  1112: aload_2        
        //  1113: ifnonnull       1121
        //  1116: aconst_null    
        //  1117: astore_2       
        //  1118: goto            1151
        //  1121: aload_2        
        //  1122: invokestatic    arum.a:(Ljava/lang/Object;)Larum;
        //  1125: astore_2       
        //  1126: goto            1151
        //  1129: astore_2       
        //  1130: goto            1134
        //  1133: astore_2       
        //  1134: getstatic       io/grpc/Status.c:Lio/grpc/Status;
        //  1137: ldc_w           "failed to parse TXT records"
        //  1140: invokevirtual   io/grpc/Status.withDescription:(Ljava/lang/String;)Lio/grpc/Status;
        //  1143: aload_2        
        //  1144: invokevirtual   io/grpc/Status.c:(Ljava/lang/Throwable;)Lio/grpc/Status;
        //  1147: invokestatic    arum.b:(Lio/grpc/Status;)Larum;
        //  1150: astore_2       
        //  1151: aload_2        
        //  1152: ifnull          2325
        //  1155: aload_2        
        //  1156: getfield        arum.a:Lio/grpc/Status;
        //  1159: astore_3       
        //  1160: aload_3        
        //  1161: ifnull          1172
        //  1164: aload_3        
        //  1165: invokestatic    arum.b:(Lio/grpc/Status;)Larum;
        //  1168: astore_2       
        //  1169: goto            2327
        //  1172: aload_2        
        //  1173: getfield        arum.b:Ljava/lang/Object;
        //  1176: checkcast       Ljava/util/Map;
        //  1179: astore          16
        //  1181: aload           7
        //  1183: getfield        asab.q:Larup;
        //  1186: astore          6
        //  1188: aload           6
        //  1190: getfield        arup.d:Ljava/lang/Object;
        //  1193: astore_3       
        //  1194: aload           16
        //  1196: ifnull          1481
        //  1199: new             Ljava/util/ArrayList;
        //  1202: astore          7
        //  1204: aload           7
        //  1206: invokespecial   java/util/ArrayList.<init>:()V
        //  1209: aload           16
        //  1211: ldc_w           "loadBalancingConfig"
        //  1214: invokeinterface java/util/Map.containsKey:(Ljava/lang/Object;)Z
        //  1219: ifeq            1238
        //  1222: aload           7
        //  1224: aload           16
        //  1226: ldc_w           "loadBalancingConfig"
        //  1229: invokestatic    asbf.f:(Ljava/util/Map;Ljava/lang/String;)Ljava/util/List;
        //  1232: invokeinterface java/util/List.addAll:(Ljava/util/Collection;)Z
        //  1237: pop            
        //  1238: aload           7
        //  1240: invokeinterface java/util/List.isEmpty:()Z
        //  1245: ifeq            1282
        //  1248: aload           16
        //  1250: ldc_w           "loadBalancingPolicy"
        //  1253: invokestatic    asbf.d:(Ljava/util/Map;Ljava/lang/String;)Ljava/lang/String;
        //  1256: astore_2       
        //  1257: aload_2        
        //  1258: ifnull          1282
        //  1261: aload           7
        //  1263: aload_2        
        //  1264: getstatic       java/util/Locale.ROOT:Ljava/util/Locale;
        //  1267: invokevirtual   java/lang/String.toLowerCase:(Ljava/util/Locale;)Ljava/lang/String;
        //  1270: invokestatic    java/util/Collections.emptyMap:()Ljava/util/Map;
        //  1273: invokestatic    java/util/Collections.singletonMap:(Ljava/lang/Object;Ljava/lang/Object;)Ljava/util/Map;
        //  1276: invokeinterface java/util/List.add:(Ljava/lang/Object;)Z
        //  1281: pop            
        //  1282: aload           7
        //  1284: invokestatic    java/util/Collections.unmodifiableList:(Ljava/util/List;)Ljava/util/List;
        //  1287: astore_2       
        //  1288: aload_2        
        //  1289: ifnonnull       1295
        //  1292: goto            1481
        //  1295: new             Ljava/util/ArrayList;
        //  1298: astore          7
        //  1300: aload           7
        //  1302: invokespecial   java/util/ArrayList.<init>:()V
        //  1305: aload_2        
        //  1306: invokeinterface java/util/List.iterator:()Ljava/util/Iterator;
        //  1311: astore          10
        //  1313: aload           10
        //  1315: invokeinterface java/util/Iterator.hasNext:()Z
        //  1320: ifeq            1468
        //  1323: aload           10
        //  1325: invokeinterface java/util/Iterator.next:()Ljava/lang/Object;
        //  1330: checkcast       Ljava/util/Map;
        //  1333: astore_2       
        //  1334: aload_2        
        //  1335: invokeinterface java/util/Map.size:()I
        //  1340: iconst_1       
        //  1341: if_icmpne       1402
        //  1344: aload_2        
        //  1345: invokeinterface java/util/Map.entrySet:()Ljava/util/Set;
        //  1350: invokeinterface java/util/Set.iterator:()Ljava/util/Iterator;
        //  1355: invokeinterface java/util/Iterator.next:()Ljava/lang/Object;
        //  1360: checkcast       Ljava/util/Map$Entry;
        //  1363: invokeinterface java/util/Map$Entry.getKey:()Ljava/lang/Object;
        //  1368: checkcast       Ljava/lang/String;
        //  1371: astore          9
        //  1373: new             Lasew;
        //  1376: astore          17
        //  1378: aload           17
        //  1380: aload           9
        //  1382: aload_2        
        //  1383: aload           9
        //  1385: invokestatic    asbf.h:(Ljava/util/Map;Ljava/lang/String;)Ljava/util/Map;
        //  1388: invokespecial   asew.<init>:(Ljava/lang/String;Ljava/util/Map;)V
        //  1391: aload           7
        //  1393: aload           17
        //  1395: invokevirtual   java/util/ArrayList.add:(Ljava/lang/Object;)Z
        //  1398: pop            
        //  1399: goto            1313
        //  1402: new             Ljava/lang/RuntimeException;
        //  1405: astore_3       
        //  1406: aload_2        
        //  1407: invokeinterface java/util/Map.size:()I
        //  1412: istore          13
        //  1414: aload_2        
        //  1415: invokestatic    java/lang/String.valueOf:(Ljava/lang/Object;)Ljava/lang/String;
        //  1418: astore          7
        //  1420: new             Ljava/lang/StringBuilder;
        //  1423: astore_2       
        //  1424: aload_2        
        //  1425: invokespecial   java/lang/StringBuilder.<init>:()V
        //  1428: aload_2        
        //  1429: ldc_w           "There are "
        //  1432: invokevirtual   java/lang/StringBuilder.append:(Ljava/lang/String;)Ljava/lang/StringBuilder;
        //  1435: pop            
        //  1436: aload_2        
        //  1437: iload           13
        //  1439: invokevirtual   java/lang/StringBuilder.append:(I)Ljava/lang/StringBuilder;
        //  1442: pop            
        //  1443: aload_2        
        //  1444: ldc_w           " fields in a LoadBalancingConfig object. Exactly one is expected. Config="
        //  1447: invokevirtual   java/lang/StringBuilder.append:(Ljava/lang/String;)Ljava/lang/StringBuilder;
        //  1450: pop            
        //  1451: aload_2        
        //  1452: aload           7
        //  1454: invokevirtual   java/lang/StringBuilder.append:(Ljava/lang/String;)Ljava/lang/StringBuilder;
        //  1457: pop            
        //  1458: aload_3        
        //  1459: aload_2        
        //  1460: invokevirtual   java/lang/StringBuilder.toString:()Ljava/lang/String;
        //  1463: invokespecial   java/lang/RuntimeException.<init>:(Ljava/lang/String;)V
        //  1466: aload_3        
        //  1467: athrow         
        //  1468: aload           7
        //  1470: invokestatic    java/util/Collections.unmodifiableList:(Ljava/util/List;)Ljava/util/List;
        //  1473: astore_2       
        //  1474: goto            1483
        //  1477: astore_2       
        //  1478: goto            1709
        //  1481: aconst_null    
        //  1482: astore_2       
        //  1483: aload_2        
        //  1484: ifnull          1729
        //  1487: aload_2        
        //  1488: invokeinterface java/util/List.isEmpty:()Z
        //  1493: ifne            1729
        //  1496: aload_3        
        //  1497: checkcast       Laseo;
        //  1500: getfield        aseo.b:Ljava/lang/Object;
        //  1503: astore          9
        //  1505: new             Ljava/util/ArrayList;
        //  1508: astore_3       
        //  1509: aload_3        
        //  1510: invokespecial   java/util/ArrayList.<init>:()V
        //  1513: aload_2        
        //  1514: invokeinterface java/util/List.iterator:()Ljava/util/Iterator;
        //  1519: astore          17
        //  1521: aload           17
        //  1523: invokeinterface java/util/Iterator.hasNext:()Z
        //  1528: ifeq            1653
        //  1531: aload           17
        //  1533: invokeinterface java/util/Iterator.next:()Ljava/lang/Object;
        //  1538: checkcast       Lasew;
        //  1541: astore          10
        //  1543: aload           10
        //  1545: getfield        asew.a:Ljava/lang/String;
        //  1548: astore_2       
        //  1549: aload           9
        //  1551: checkcast       Larts;
        //  1554: aload_2        
        //  1555: invokevirtual   arts.a:(Ljava/lang/String;)Lartr;
        //  1558: astore          7
        //  1560: aload           7
        //  1562: ifnonnull       1576
        //  1565: aload_3        
        //  1566: aload_2        
        //  1567: invokeinterface java/util/List.add:(Ljava/lang/Object;)Z
        //  1572: pop            
        //  1573: goto            1521
        //  1576: aload_3        
        //  1577: invokeinterface java/util/List.isEmpty:()Z
        //  1582: ifne            1610
        //  1585: ldc_w           Lasey;.class
        //  1588: invokevirtual   java/lang/Class.getName:()Ljava/lang/String;
        //  1591: invokestatic    java/util/logging/Logger.getLogger:(Ljava/lang/String;)Ljava/util/logging/Logger;
        //  1594: getstatic       java/util/logging/Level.FINEST:Ljava/util/logging/Level;
        //  1597: ldc_w           "io.grpc.internal.ServiceConfigUtil"
        //  1600: ldc_w           "selectLbPolicyFromList"
        //  1603: ldc_w           "{0} specified by Service Config are not available"
        //  1606: aload_3        
        //  1607: invokevirtual   java/util/logging/Logger.logp:(Ljava/util/logging/Level;Ljava/lang/String;Ljava/lang/String;Ljava/lang/String;Ljava/lang/Object;)V
        //  1610: aload           10
        //  1612: getfield        asew.b:Ljava/util/Map;
        //  1615: astore_2       
        //  1616: aload           7
        //  1618: invokevirtual   artr.c:()Larum;
        //  1621: astore_3       
        //  1622: aload_3        
        //  1623: astore_2       
        //  1624: aload_3        
        //  1625: getfield        arum.a:Lio/grpc/Status;
        //  1628: ifnonnull       1731
        //  1631: new             Lasex;
        //  1634: astore_2       
        //  1635: aload_2        
        //  1636: aload           7
        //  1638: aload_3        
        //  1639: getfield        arum.b:Ljava/lang/Object;
        //  1642: invokespecial   asex.<init>:(Lartr;Ljava/lang/Object;)V
        //  1645: aload_2        
        //  1646: invokestatic    arum.a:(Ljava/lang/Object;)Larum;
        //  1649: astore_2       
        //  1650: goto            1731
        //  1653: getstatic       io/grpc/Status.c:Lio/grpc/Status;
        //  1656: astore_2       
        //  1657: aload_3        
        //  1658: invokevirtual   java/lang/Object.toString:()Ljava/lang/String;
        //  1661: astore          7
        //  1663: new             Ljava/lang/StringBuilder;
        //  1666: astore_3       
        //  1667: aload_3        
        //  1668: invokespecial   java/lang/StringBuilder.<init>:()V
        //  1671: aload_3        
        //  1672: ldc_w           "None of "
        //  1675: invokevirtual   java/lang/StringBuilder.append:(Ljava/lang/String;)Ljava/lang/StringBuilder;
        //  1678: pop            
        //  1679: aload_3        
        //  1680: aload           7
        //  1682: invokevirtual   java/lang/StringBuilder.append:(Ljava/lang/String;)Ljava/lang/StringBuilder;
        //  1685: pop            
        //  1686: aload_3        
        //  1687: ldc_w           " specified by Service Config are available."
        //  1690: invokevirtual   java/lang/StringBuilder.append:(Ljava/lang/String;)Ljava/lang/StringBuilder;
        //  1693: pop            
        //  1694: aload_2        
        //  1695: aload_3        
        //  1696: invokevirtual   java/lang/StringBuilder.toString:()Ljava/lang/String;
        //  1699: invokevirtual   io/grpc/Status.withDescription:(Ljava/lang/String;)Lio/grpc/Status;
        //  1702: invokestatic    arum.b:(Lio/grpc/Status;)Larum;
        //  1705: astore_2       
        //  1706: goto            1731
        //  1709: getstatic       io/grpc/Status.c:Lio/grpc/Status;
        //  1712: ldc_w           "can't parse load balancer configuration"
        //  1715: invokevirtual   io/grpc/Status.withDescription:(Ljava/lang/String;)Lio/grpc/Status;
        //  1718: aload_2        
        //  1719: invokevirtual   io/grpc/Status.c:(Ljava/lang/Throwable;)Lio/grpc/Status;
        //  1722: invokestatic    arum.b:(Lio/grpc/Status;)Larum;
        //  1725: astore_2       
        //  1726: goto            1731
        //  1729: aconst_null    
        //  1730: astore_2       
        //  1731: aload_2        
        //  1732: ifnonnull       1740
        //  1735: aconst_null    
        //  1736: astore_2       
        //  1737: goto            1762
        //  1740: aload_2        
        //  1741: getfield        arum.a:Lio/grpc/Status;
        //  1744: astore_3       
        //  1745: aload_3        
        //  1746: ifnull          1757
        //  1749: aload_3        
        //  1750: invokestatic    arum.b:(Lio/grpc/Status;)Larum;
        //  1753: astore_2       
        //  1754: goto            1169
        //  1757: aload_2        
        //  1758: getfield        arum.b:Ljava/lang/Object;
        //  1761: astore_2       
        //  1762: aload           6
        //  1764: getfield        arup.a:Z
        //  1767: istore          11
        //  1769: aload           6
        //  1771: getfield        arup.b:I
        //  1774: istore          14
        //  1776: aload           6
        //  1778: getfield        arup.c:I
        //  1781: istore          13
        //  1783: iload           11
        //  1785: ifeq            1899
        //  1788: aload           16
        //  1790: ifnonnull       1796
        //  1793: goto            1899
        //  1796: aload           16
        //  1798: ldc_w           "retryThrottling"
        //  1801: invokestatic    asbf.h:(Ljava/util/Map;Ljava/lang/String;)Ljava/util/Map;
        //  1804: astore_3       
        //  1805: aload_3        
        //  1806: ifnonnull       1812
        //  1809: goto            1899
        //  1812: aload_3        
        //  1813: ldc_w           "maxTokens"
        //  1816: invokestatic    asbf.a:(Ljava/util/Map;Ljava/lang/String;)Ljava/lang/Double;
        //  1819: invokevirtual   java/lang/Double.floatValue:()F
        //  1822: fstore          18
        //  1824: aload_3        
        //  1825: ldc_w           "tokenRatio"
        //  1828: invokestatic    asbf.a:(Ljava/util/Map;Ljava/lang/String;)Ljava/lang/Double;
        //  1831: invokevirtual   java/lang/Double.floatValue:()F
        //  1834: fstore          19
        //  1836: fload           18
        //  1838: fconst_0       
        //  1839: fcmpl          
        //  1840: ifle            1849
        //  1843: iconst_1       
        //  1844: istore          8
        //  1846: goto            1852
        //  1849: iconst_0       
        //  1850: istore          8
        //  1852: iload           8
        //  1854: ldc_w           "maxToken should be greater than zero"
        //  1857: invokestatic    agot.E:(ZLjava/lang/Object;)V
        //  1860: fload           19
        //  1862: fconst_0       
        //  1863: fcmpl          
        //  1864: ifle            1873
        //  1867: iconst_1       
        //  1868: istore          8
        //  1870: goto            1876
        //  1873: iconst_0       
        //  1874: istore          8
        //  1876: iload           8
        //  1878: ldc_w           "tokenRatio should be greater than zero"
        //  1881: invokestatic    agot.E:(ZLjava/lang/Object;)V
        //  1884: new             Lasdw;
        //  1887: dup            
        //  1888: fload           18
        //  1890: fload           19
        //  1892: invokespecial   asdw.<init>:(FF)V
        //  1895: astore_3       
        //  1896: goto            1901
        //  1899: aconst_null    
        //  1900: astore_3       
        //  1901: new             Ljava/util/HashMap;
        //  1904: astore          20
        //  1906: aload           20
        //  1908: invokespecial   java/util/HashMap.<init>:()V
        //  1911: new             Ljava/util/HashMap;
        //  1914: astore          17
        //  1916: aload           17
        //  1918: invokespecial   java/util/HashMap.<init>:()V
        //  1921: aload           16
        //  1923: ifnonnull       1932
        //  1926: aconst_null    
        //  1927: astore          6
        //  1929: goto            1942
        //  1932: aload           16
        //  1934: ldc_w           "healthCheckConfig"
        //  1937: invokestatic    asbf.h:(Ljava/util/Map;Ljava/lang/String;)Ljava/util/Map;
        //  1940: astore          6
        //  1942: aload           16
        //  1944: ldc_w           "methodConfig"
        //  1947: invokestatic    asbf.f:(Ljava/util/Map;Ljava/lang/String;)Ljava/util/List;
        //  1950: astore          7
        //  1952: aload           7
        //  1954: ifnonnull       1982
        //  1957: new             Lasci;
        //  1960: astore          7
        //  1962: aload           7
        //  1964: aconst_null    
        //  1965: aload           20
        //  1967: aload           17
        //  1969: aload_3        
        //  1970: aload_2        
        //  1971: aload           6
        //  1973: invokespecial   asci.<init>:(Lascg;Ljava/util/Map;Ljava/util/Map;Lasdw;Ljava/lang/Object;Ljava/util/Map;)V
        //  1976: aload           7
        //  1978: astore_2       
        //  1979: goto            2296
        //  1982: aload           7
        //  1984: invokeinterface java/util/List.iterator:()Ljava/util/Iterator;
        //  1989: astore          21
        //  1991: aconst_null    
        //  1992: astore          9
        //  1994: iload           11
        //  1996: istore          8
        //  1998: aload           21
        //  2000: invokeinterface java/util/Iterator.hasNext:()Z
        //  2005: ifeq            2278
        //  2008: aload           21
        //  2010: invokeinterface java/util/Iterator.next:()Ljava/lang/Object;
        //  2015: checkcast       Ljava/util/Map;
        //  2018: astore          7
        //  2020: new             Lascg;
        //  2023: astore          10
        //  2025: aload           10
        //  2027: aload           7
        //  2029: iload           8
        //  2031: iload           14
        //  2033: iload           13
        //  2035: invokespecial   ascg.<init>:(Ljava/util/Map;ZII)V
        //  2038: aload           7
        //  2040: ldc_w           "name"
        //  2043: invokestatic    asbf.f:(Ljava/util/Map;Ljava/lang/String;)Ljava/util/List;
        //  2046: astore          7
        //  2048: aload           7
        //  2050: ifnull          2275
        //  2053: aload           7
        //  2055: invokeinterface java/util/List.isEmpty:()Z
        //  2060: ifne            2275
        //  2063: aload           7
        //  2065: invokeinterface java/util/List.iterator:()Ljava/util/Iterator;
        //  2070: astore          22
        //  2072: aload           9
        //  2074: astore          7
        //  2076: iload           8
        //  2078: istore          11
        //  2080: iload           13
        //  2082: istore          12
        //  2084: iload           12
        //  2086: istore          13
        //  2088: iload           11
        //  2090: istore          8
        //  2092: aload           7
        //  2094: astore          9
        //  2096: aload           22
        //  2098: invokeinterface java/util/Iterator.hasNext:()Z
        //  2103: ifeq            1998
        //  2106: aload           22
        //  2108: invokeinterface java/util/Iterator.next:()Ljava/lang/Object;
        //  2113: checkcast       Ljava/util/Map;
        //  2116: astore          23
        //  2118: aload           23
        //  2120: ldc_w           "service"
        //  2123: invokestatic    asbf.d:(Ljava/util/Map;Ljava/lang/String;)Ljava/lang/String;
        //  2126: astore          9
        //  2128: aload           23
        //  2130: ldc_w           "method"
        //  2133: invokestatic    asbf.d:(Ljava/util/Map;Ljava/lang/String;)Ljava/lang/String;
        //  2136: astore          23
        //  2138: aload           9
        //  2140: invokestatic    aexs.f:(Ljava/lang/String;)Z
        //  2143: ifeq            2190
        //  2146: aload           23
        //  2148: invokestatic    aexs.f:(Ljava/lang/String;)Z
        //  2151: ldc_w           "missing service name for method %s"
        //  2154: aload           23
        //  2156: invokestatic    agot.z:(ZLjava/lang/String;Ljava/lang/Object;)V
        //  2159: aload           7
        //  2161: ifnonnull       2170
        //  2164: iconst_1       
        //  2165: istore          8
        //  2167: goto            2173
        //  2170: iconst_0       
        //  2171: istore          8
        //  2173: iload           8
        //  2175: ldc_w           "Duplicate default method config in service config %s"
        //  2178: aload           16
        //  2180: invokestatic    agot.z:(ZLjava/lang/String;Ljava/lang/Object;)V
        //  2183: aload           10
        //  2185: astore          7
        //  2187: goto            2272
        //  2190: aload           23
        //  2192: invokestatic    aexs.f:(Ljava/lang/String;)Z
        //  2195: ifeq            2232
        //  2198: aload           17
        //  2200: aload           9
        //  2202: invokeinterface java/util/Map.containsKey:(Ljava/lang/Object;)Z
        //  2207: iconst_1       
        //  2208: ixor           
        //  2209: ldc_w           "Duplicate service %s"
        //  2212: aload           9
        //  2214: invokestatic    agot.z:(ZLjava/lang/String;Ljava/lang/Object;)V
        //  2217: aload           17
        //  2219: aload           9
        //  2221: aload           10
        //  2223: invokeinterface java/util/Map.put:(Ljava/lang/Object;Ljava/lang/Object;)Ljava/lang/Object;
        //  2228: pop            
        //  2229: goto            2272
        //  2232: aload           9
        //  2234: aload           23
        //  2236: invokestatic    aruk.c:(Ljava/lang/String;Ljava/lang/String;)Ljava/lang/String;
        //  2239: astore          9
        //  2241: aload           20
        //  2243: aload           9
        //  2245: invokeinterface java/util/Map.containsKey:(Ljava/lang/Object;)Z
        //  2250: iconst_1       
        //  2251: ixor           
        //  2252: ldc_w           "Duplicate method name %s"
        //  2255: aload           9
        //  2257: invokestatic    agot.z:(ZLjava/lang/String;Ljava/lang/Object;)V
        //  2260: aload           20
        //  2262: aload           9
        //  2264: aload           10
        //  2266: invokeinterface java/util/Map.put:(Ljava/lang/Object;Ljava/lang/Object;)Ljava/lang/Object;
        //  2271: pop            
        //  2272: goto            2084
        //  2275: goto            1998
        //  2278: new             Lasci;
        //  2281: dup            
        //  2282: aload           9
        //  2284: aload           20
        //  2286: aload           17
        //  2288: aload_3        
        //  2289: aload_2        
        //  2290: aload           6
        //  2292: invokespecial   asci.<init>:(Lascg;Ljava/util/Map;Ljava/util/Map;Lasdw;Ljava/lang/Object;Ljava/util/Map;)V
        //  2295: astore_2       
        //  2296: aload_2        
        //  2297: invokestatic    arum.a:(Ljava/lang/Object;)Larum;
        //  2300: astore_2       
        //  2301: goto            1169
        //  2304: astore_2       
        //  2305: getstatic       io/grpc/Status.c:Lio/grpc/Status;
        //  2308: ldc_w           "failed to parse service config"
        //  2311: invokevirtual   io/grpc/Status.withDescription:(Ljava/lang/String;)Lio/grpc/Status;
        //  2314: aload_2        
        //  2315: invokevirtual   io/grpc/Status.c:(Ljava/lang/Throwable;)Lio/grpc/Status;
        //  2318: invokestatic    arum.b:(Lio/grpc/Status;)Larum;
        //  2321: astore_2       
        //  2322: goto            1169
        //  2325: aconst_null    
        //  2326: astore_2       
        //  2327: goto            2370
        //  2330: getstatic       asab.a:Ljava/util/logging/Logger;
        //  2333: astore_3       
        //  2334: getstatic       java/util/logging/Level.FINE:Ljava/util/logging/Level;
        //  2337: astore_2       
        //  2338: aload           7
        //  2340: getfield        asab.k:Ljava/lang/String;
        //  2343: astore          6
        //  2345: aload_3        
        //  2346: aload_2        
        //  2347: ldc_w           "io.grpc.internal.DnsNameResolver"
        //  2350: ldc_w           "resolveServiceConfig"
        //  2353: ldc_w           "No TXT records found for {0}"
        //  2356: iconst_1       
        //  2357: anewarray       Ljava/lang/Object;
        //  2360: dup            
        //  2361: iconst_0       
        //  2362: aload           6
        //  2364: aastore        
        //  2365: invokevirtual   java/util/logging/Logger.logp:(Ljava/util/logging/Level;Ljava/lang/String;Ljava/lang/String;Ljava/lang/String;[Ljava/lang/Object;)V
        //  2368: aconst_null    
        //  2369: astore_2       
        //  2370: aload_1        
        //  2371: aload_2        
        //  2372: putfield        arzw.c:Ljava/lang/Object;
        //  2375: goto            2474
        //  2378: astore_2       
        //  2379: goto            2681
        //  2382: astore_2       
        //  2383: goto            2687
        //  2386: goto            2474
        //  2389: astore_2       
        //  2390: goto            2446
        //  2393: astore_3       
        //  2394: aconst_null    
        //  2395: astore_2       
        //  2396: goto            2416
        //  2399: astore_2       
        //  2400: aload_2        
        //  2401: invokestatic    aeyv.e:(Ljava/lang/Throwable;)V
        //  2404: new             Ljava/lang/RuntimeException;
        //  2407: astore_3       
        //  2408: aload_3        
        //  2409: aload_2        
        //  2410: invokespecial   java/lang/RuntimeException.<init>:(Ljava/lang/Throwable;)V
        //  2413: aload_3        
        //  2414: athrow         
        //  2415: astore_3       
        //  2416: aload_2        
        //  2417: ifnull          2439
        //  2420: getstatic       asab.a:Ljava/util/logging/Logger;
        //  2423: getstatic       java/util/logging/Level.FINE:Ljava/util/logging/Level;
        //  2426: ldc_w           "io.grpc.internal.DnsNameResolver"
        //  2429: ldc_w           "resolveAddresses"
        //  2432: ldc_w           "Address resolution failure"
        //  2435: aload_2        
        //  2436: invokevirtual   java/util/logging/Logger.logp:(Ljava/util/logging/Level;Ljava/lang/String;Ljava/lang/String;Ljava/lang/String;Ljava/lang/Throwable;)V
        //  2439: aload_3        
        //  2440: athrow         
        //  2441: astore_2       
        //  2442: goto            2681
        //  2445: astore_2       
        //  2446: aload_1        
        //  2447: getstatic       io/grpc/Status.l:Lio/grpc/Status;
        //  2450: ldc_w           "Unable to resolve host "
        //  2453: aload           7
        //  2455: getfield        asab.k:Ljava/lang/String;
        //  2458: invokestatic    java/lang/String.valueOf:(Ljava/lang/Object;)Ljava/lang/String;
        //  2461: invokevirtual   java/lang/String.concat:(Ljava/lang/String;)Ljava/lang/String;
        //  2464: invokevirtual   io/grpc/Status.withDescription:(Ljava/lang/String;)Lio/grpc/Status;
        //  2467: aload_2        
        //  2468: invokevirtual   io/grpc/Status.c:(Ljava/lang/Throwable;)Lio/grpc/Status;
        //  2471: putfield        arzw.a:Ljava/lang/Object;
        //  2474: aload_1        
        //  2475: astore          6
        //  2477: aload_1        
        //  2478: astore_3       
        //  2479: aload_1        
        //  2480: getfield        arzw.a:Ljava/lang/Object;
        //  2483: astore_2       
        //  2484: aload_2        
        //  2485: ifnull          2547
        //  2488: aload_1        
        //  2489: astore          6
        //  2491: aload_1        
        //  2492: astore_3       
        //  2493: aload_0        
        //  2494: getfield        arzy.b:Latdo;
        //  2497: aload_2        
        //  2498: checkcast       Lio/grpc/Status;
        //  2501: invokevirtual   atdo.c:(Lio/grpc/Status;)V
        //  2504: aload_1        
        //  2505: getfield        arzw.a:Ljava/lang/Object;
        //  2508: ifnonnull       2517
        //  2511: iconst_1       
        //  2512: istore          8
        //  2514: goto            2520
        //  2517: iconst_0       
        //  2518: istore          8
        //  2520: aload_0        
        //  2521: getfield        arzy.a:Lasab;
        //  2524: getfield        asab.n:Larvo;
        //  2527: astore_2       
        //  2528: new             Lcom/google/android/apps/youtube/embeddedplayer/service/ui/player/remoteloaded/a;
        //  2531: dup            
        //  2532: aload_0        
        //  2533: iload           8
        //  2535: bipush          20
        //  2537: invokespecial   com/google/android/apps/youtube/embeddedplayer/service/ui/player/remoteloaded/a.<init>:(Larzy;ZI)V
        //  2540: astore_1       
        //  2541: aload_2        
        //  2542: aload_1        
        //  2543: invokevirtual   arvo.execute:(Ljava/lang/Runnable;)V
        //  2546: return         
        //  2547: aload_1        
        //  2548: astore          6
        //  2550: aload_1        
        //  2551: astore_3       
        //  2552: aload_1        
        //  2553: getfield        arzw.b:Ljava/lang/Object;
        //  2556: astore_2       
        //  2557: aload_2        
        //  2558: ifnonnull       2567
        //  2561: aload           4
        //  2563: astore_2       
        //  2564: goto            2567
        //  2567: aload_1        
        //  2568: astore          6
        //  2570: aload_1        
        //  2571: astore_3       
        //  2572: aload_1        
        //  2573: getfield        arzw.c:Ljava/lang/Object;
        //  2576: astore          7
        //  2578: aload_1        
        //  2579: astore          6
        //  2581: aload_2        
        //  2582: astore_3       
        //  2583: aload           7
        //  2585: ifnull          223
        //  2588: aload           7
        //  2590: astore_3       
        //  2591: aload_2        
        //  2592: astore          7
        //  2594: aload_3        
        //  2595: astore_2       
        //  2596: aload_1        
        //  2597: astore          6
        //  2599: aload_1        
        //  2600: astore_3       
        //  2601: aload_0        
        //  2602: getfield        arzy.b:Latdo;
        //  2605: aload           7
        //  2607: aload           5
        //  2609: aload_2        
        //  2610: checkcast       Larum;
        //  2613: invokestatic    arsu.c:(Ljava/util/List;Larrg;Larum;)Laruo;
        //  2616: invokevirtual   atdo.d:(Laruo;)V
        //  2619: aload_1        
        //  2620: ifnull          2636
        //  2623: aload_1        
        //  2624: getfield        arzw.a:Ljava/lang/Object;
        //  2627: ifnonnull       2636
        //  2630: iconst_1       
        //  2631: istore          8
        //  2633: goto            2639
        //  2636: iconst_0       
        //  2637: istore          8
        //  2639: aload_0        
        //  2640: getfield        arzy.a:Lasab;
        //  2643: getfield        asab.n:Larvo;
        //  2646: astore_2       
        //  2647: new             Lcom/google/android/apps/youtube/embeddedplayer/service/ui/player/remoteloaded/a;
        //  2650: dup            
        //  2651: aload_0        
        //  2652: iload           8
        //  2654: bipush          20
        //  2656: invokespecial   com/google/android/apps/youtube/embeddedplayer/service/ui/player/remoteloaded/a.<init>:(Larzy;ZI)V
        //  2659: astore_1       
        //  2660: goto            2541
        //  2663: astore_2       
        //  2664: aload           6
        //  2666: astore_1       
        //  2667: goto            2804
        //  2670: astore_1       
        //  2671: aload_3        
        //  2672: astore_2       
        //  2673: goto            2691
        //  2676: astore_2       
        //  2677: goto            2687
        //  2680: astore_2       
        //  2681: aconst_null    
        //  2682: astore_1       
        //  2683: goto            2804
        //  2686: astore_2       
        //  2687: aload_2        
        //  2688: astore_1       
        //  2689: aconst_null    
        //  2690: astore_2       
        //  2691: aload_0        
        //  2692: getfield        arzy.b:Latdo;
        //  2695: astore_3       
        //  2696: getstatic       io/grpc/Status.l:Lio/grpc/Status;
        //  2699: astore          9
        //  2701: aload_0        
        //  2702: getfield        arzy.a:Lasab;
        //  2705: getfield        asab.k:Ljava/lang/String;
        //  2708: astore          6
        //  2710: new             Ljava/lang/StringBuilder;
        //  2713: astore          7
        //  2715: aload           7
        //  2717: invokespecial   java/lang/StringBuilder.<init>:()V
        //  2720: aload           7
        //  2722: ldc_w           "Unable to resolve host "
        //  2725: invokevirtual   java/lang/StringBuilder.append:(Ljava/lang/String;)Ljava/lang/StringBuilder;
        //  2728: pop            
        //  2729: aload           7
        //  2731: aload           6
        //  2733: invokevirtual   java/lang/StringBuilder.append:(Ljava/lang/String;)Ljava/lang/StringBuilder;
        //  2736: pop            
        //  2737: aload_3        
        //  2738: aload           9
        //  2740: aload           7
        //  2742: invokevirtual   java/lang/StringBuilder.toString:()Ljava/lang/String;
        //  2745: invokevirtual   io/grpc/Status.withDescription:(Ljava/lang/String;)Lio/grpc/Status;
        //  2748: aload_1        
        //  2749: invokevirtual   io/grpc/Status.c:(Ljava/lang/Throwable;)Lio/grpc/Status;
        //  2752: invokevirtual   atdo.c:(Lio/grpc/Status;)V
        //  2755: aload_2        
        //  2756: ifnull          2772
        //  2759: aload_2        
        //  2760: getfield        arzw.a:Ljava/lang/Object;
        //  2763: ifnonnull       2772
        //  2766: iconst_1       
        //  2767: istore          8
        //  2769: goto            2775
        //  2772: iconst_0       
        //  2773: istore          8
        //  2775: aload_0        
        //  2776: getfield        arzy.a:Lasab;
        //  2779: getfield        asab.n:Larvo;
        //  2782: astore_2       
        //  2783: new             Lcom/google/android/apps/youtube/embeddedplayer/service/ui/player/remoteloaded/a;
        //  2786: dup            
        //  2787: aload_0        
        //  2788: iload           8
        //  2790: bipush          20
        //  2792: invokespecial   com/google/android/apps/youtube/embeddedplayer/service/ui/player/remoteloaded/a.<init>:(Larzy;ZI)V
        //  2795: astore_1       
        //  2796: goto            2541
        //  2799: astore_3       
        //  2800: aload_2        
        //  2801: astore_1       
        //  2802: aload_3        
        //  2803: astore_2       
        //  2804: aload_1        
        //  2805: ifnull          2821
        //  2808: aload_1        
        //  2809: getfield        arzw.a:Ljava/lang/Object;
        //  2812: ifnonnull       2821
        //  2815: iconst_1       
        //  2816: istore          8
        //  2818: goto            2824
        //  2821: iconst_0       
        //  2822: istore          8
        //  2824: aload_0        
        //  2825: getfield        arzy.a:Lasab;
        //  2828: getfield        asab.n:Larvo;
        //  2831: new             Lcom/google/android/apps/youtube/embeddedplayer/service/ui/player/remoteloaded/a;
        //  2834: dup            
        //  2835: aload_0        
        //  2836: iload           8
        //  2838: bipush          20
        //  2840: invokespecial   com/google/android/apps/youtube/embeddedplayer/service/ui/player/remoteloaded/a.<init>:(Larzy;ZI)V
        //  2843: invokevirtual   arvo.execute:(Ljava/lang/Runnable;)V
        //  2846: goto            2851
        //  2849: aload_2        
        //  2850: athrow         
        //  2851: goto            2849
        //    Exceptions:
        //  Try           Handler
        //  Start  End    Start  End    Type                        
        //  -----  -----  -----  -----  ----------------------------
        //  40     69     2686   2687   Ljava/io/IOException;
        //  40     69     2680   2681   Any
        //  74     82     2686   2687   Ljava/io/IOException;
        //  74     82     2680   2681   Any
        //  86     105    135    139    Ljava/io/IOException;
        //  86     105    131    135    Any
        //  108    113    2686   2687   Ljava/io/IOException;
        //  108    113    2680   2681   Any
        //  117    126    135    139    Ljava/io/IOException;
        //  117    126    131    135    Any
        //  141    151    2686   2687   Ljava/io/IOException;
        //  141    151    2680   2681   Any
        //  155    215    135    139    Ljava/io/IOException;
        //  155    215    131    135    Any
        //  215    220    135    139    Ljava/io/IOException;
        //  215    220    131    135    Any
        //  234    248    2686   2687   Ljava/io/IOException;
        //  234    248    2680   2681   Any
        //  248    269    2399   2416   Ljava/lang/Exception;
        //  248    269    2393   2399   Any
        //  269    290    2389   2393   Ljava/lang/Exception;
        //  269    290    2680   2681   Any
        //  290    298    2389   2393   Ljava/lang/Exception;
        //  290    298    2680   2681   Any
        //  303    352    355    359    Ljava/lang/Exception;
        //  303    352    131    135    Any
        //  359    367    2389   2393   Ljava/lang/Exception;
        //  359    367    2680   2681   Any
        //  367    394    2686   2687   Ljava/io/IOException;
        //  367    394    2680   2681   Any
        //  404    413    2686   2687   Ljava/io/IOException;
        //  404    413    2680   2681   Any
        //  421    430    2686   2687   Ljava/io/IOException;
        //  421    430    2680   2681   Any
        //  439    445    2686   2687   Ljava/io/IOException;
        //  439    445    2680   2681   Any
        //  452    460    135    139    Ljava/io/IOException;
        //  452    460    131    135    Any
        //  519    531    2686   2687   Ljava/io/IOException;
        //  519    531    2680   2681   Any
        //  537    542    135    139    Ljava/io/IOException;
        //  537    542    131    135    Any
        //  549    557    135    139    Ljava/io/IOException;
        //  549    557    131    135    Any
        //  564    571    574    597    Ljava/lang/Exception;
        //  564    571    131    135    Any
        //  575    594    135    139    Ljava/io/IOException;
        //  575    594    131    135    Any
        //  597    605    2686   2687   Ljava/io/IOException;
        //  597    605    2680   2681   Any
        //  610    622    135    139    Ljava/io/IOException;
        //  610    622    131    135    Any
        //  622    637    1133   1134   Ljava/io/IOException;
        //  622    637    1129   1133   Ljava/lang/RuntimeException;
        //  622    637    131    135    Any
        //  637    695    1133   1134   Ljava/io/IOException;
        //  637    695    1129   1133   Ljava/lang/RuntimeException;
        //  637    695    131    135    Any
        //  698    739    1133   1134   Ljava/io/IOException;
        //  698    739    1129   1133   Ljava/lang/RuntimeException;
        //  698    739    131    135    Any
        //  742    766    1133   1134   Ljava/io/IOException;
        //  742    766    1129   1133   Ljava/lang/RuntimeException;
        //  742    766    131    135    Any
        //  766    773    135    139    Ljava/io/IOException;
        //  766    773    131    135    Any
        //  775    795    135    139    Ljava/io/IOException;
        //  775    795    131    135    Any
        //  795    809    1091   1112   Ljava/lang/RuntimeException;
        //  795    809    135    139    Ljava/io/IOException;
        //  795    809    131    135    Any
        //  809    851    1091   1112   Ljava/lang/RuntimeException;
        //  809    851    135    139    Ljava/io/IOException;
        //  809    851    131    135    Any
        //  854    863    1091   1112   Ljava/lang/RuntimeException;
        //  854    863    135    139    Ljava/io/IOException;
        //  854    863    131    135    Any
        //  867    883    1091   1112   Ljava/lang/RuntimeException;
        //  867    883    135    139    Ljava/io/IOException;
        //  867    883    131    135    Any
        //  883    910    1091   1112   Ljava/lang/RuntimeException;
        //  883    910    135    139    Ljava/io/IOException;
        //  883    910    131    135    Any
        //  918    927    1091   1112   Ljava/lang/RuntimeException;
        //  918    927    135    139    Ljava/io/IOException;
        //  918    927    131    135    Any
        //  931    937    1091   1112   Ljava/lang/RuntimeException;
        //  931    937    135    139    Ljava/io/IOException;
        //  931    937    131    135    Any
        //  958    979    1091   1112   Ljava/lang/RuntimeException;
        //  958    979    135    139    Ljava/io/IOException;
        //  958    979    131    135    Any
        //  982    991    1091   1112   Ljava/lang/RuntimeException;
        //  982    991    135    139    Ljava/io/IOException;
        //  982    991    131    135    Any
        //  995    1011   1091   1112   Ljava/lang/RuntimeException;
        //  995    1011   135    139    Ljava/io/IOException;
        //  995    1011   131    135    Any
        //  1011   1037   1091   1112   Ljava/lang/RuntimeException;
        //  1011   1037   135    139    Ljava/io/IOException;
        //  1011   1037   131    135    Any
        //  1037   1046   1091   1112   Ljava/lang/RuntimeException;
        //  1037   1046   135    139    Ljava/io/IOException;
        //  1037   1046   131    135    Any
        //  1060   1091   1091   1112   Ljava/lang/RuntimeException;
        //  1060   1091   135    139    Ljava/io/IOException;
        //  1060   1091   131    135    Any
        //  1092   1109   135    139    Ljava/io/IOException;
        //  1092   1109   131    135    Any
        //  1121   1126   135    139    Ljava/io/IOException;
        //  1121   1126   131    135    Any
        //  1134   1151   135    139    Ljava/io/IOException;
        //  1134   1151   131    135    Any
        //  1155   1160   135    139    Ljava/io/IOException;
        //  1155   1160   131    135    Any
        //  1164   1169   135    139    Ljava/io/IOException;
        //  1164   1169   131    135    Any
        //  1172   1188   135    139    Ljava/io/IOException;
        //  1172   1188   131    135    Any
        //  1188   1194   2304   2325   Ljava/lang/RuntimeException;
        //  1188   1194   135    139    Ljava/io/IOException;
        //  1188   1194   131    135    Any
        //  1199   1238   1477   1729   Ljava/lang/RuntimeException;
        //  1199   1238   135    139    Ljava/io/IOException;
        //  1199   1238   131    135    Any
        //  1238   1257   1477   1729   Ljava/lang/RuntimeException;
        //  1238   1257   135    139    Ljava/io/IOException;
        //  1238   1257   131    135    Any
        //  1261   1282   1477   1729   Ljava/lang/RuntimeException;
        //  1261   1282   135    139    Ljava/io/IOException;
        //  1261   1282   131    135    Any
        //  1282   1288   1477   1729   Ljava/lang/RuntimeException;
        //  1282   1288   135    139    Ljava/io/IOException;
        //  1282   1288   131    135    Any
        //  1295   1313   1477   1729   Ljava/lang/RuntimeException;
        //  1295   1313   135    139    Ljava/io/IOException;
        //  1295   1313   131    135    Any
        //  1313   1399   1477   1729   Ljava/lang/RuntimeException;
        //  1313   1399   135    139    Ljava/io/IOException;
        //  1313   1399   131    135    Any
        //  1402   1468   1477   1729   Ljava/lang/RuntimeException;
        //  1402   1468   135    139    Ljava/io/IOException;
        //  1402   1468   131    135    Any
        //  1468   1474   1477   1729   Ljava/lang/RuntimeException;
        //  1468   1474   135    139    Ljava/io/IOException;
        //  1468   1474   131    135    Any
        //  1487   1521   1477   1729   Ljava/lang/RuntimeException;
        //  1487   1521   135    139    Ljava/io/IOException;
        //  1487   1521   131    135    Any
        //  1521   1560   1477   1729   Ljava/lang/RuntimeException;
        //  1521   1560   135    139    Ljava/io/IOException;
        //  1521   1560   131    135    Any
        //  1565   1573   1477   1729   Ljava/lang/RuntimeException;
        //  1565   1573   135    139    Ljava/io/IOException;
        //  1565   1573   131    135    Any
        //  1576   1610   1477   1729   Ljava/lang/RuntimeException;
        //  1576   1610   135    139    Ljava/io/IOException;
        //  1576   1610   131    135    Any
        //  1610   1622   1477   1729   Ljava/lang/RuntimeException;
        //  1610   1622   135    139    Ljava/io/IOException;
        //  1610   1622   131    135    Any
        //  1624   1650   1477   1729   Ljava/lang/RuntimeException;
        //  1624   1650   135    139    Ljava/io/IOException;
        //  1624   1650   131    135    Any
        //  1653   1706   1477   1729   Ljava/lang/RuntimeException;
        //  1653   1706   135    139    Ljava/io/IOException;
        //  1653   1706   131    135    Any
        //  1709   1726   2304   2325   Ljava/lang/RuntimeException;
        //  1709   1726   135    139    Ljava/io/IOException;
        //  1709   1726   131    135    Any
        //  1740   1745   2304   2325   Ljava/lang/RuntimeException;
        //  1740   1745   135    139    Ljava/io/IOException;
        //  1740   1745   131    135    Any
        //  1749   1754   2304   2325   Ljava/lang/RuntimeException;
        //  1749   1754   135    139    Ljava/io/IOException;
        //  1749   1754   131    135    Any
        //  1757   1762   2304   2325   Ljava/lang/RuntimeException;
        //  1757   1762   135    139    Ljava/io/IOException;
        //  1757   1762   131    135    Any
        //  1762   1783   2304   2325   Ljava/lang/RuntimeException;
        //  1762   1783   135    139    Ljava/io/IOException;
        //  1762   1783   131    135    Any
        //  1796   1805   2304   2325   Ljava/lang/RuntimeException;
        //  1796   1805   135    139    Ljava/io/IOException;
        //  1796   1805   131    135    Any
        //  1812   1836   2304   2325   Ljava/lang/RuntimeException;
        //  1812   1836   135    139    Ljava/io/IOException;
        //  1812   1836   131    135    Any
        //  1852   1860   2304   2325   Ljava/lang/RuntimeException;
        //  1852   1860   135    139    Ljava/io/IOException;
        //  1852   1860   131    135    Any
        //  1876   1896   2304   2325   Ljava/lang/RuntimeException;
        //  1876   1896   135    139    Ljava/io/IOException;
        //  1876   1896   131    135    Any
        //  1901   1921   2304   2325   Ljava/lang/RuntimeException;
        //  1901   1921   135    139    Ljava/io/IOException;
        //  1901   1921   131    135    Any
        //  1932   1942   2304   2325   Ljava/lang/RuntimeException;
        //  1932   1942   135    139    Ljava/io/IOException;
        //  1932   1942   131    135    Any
        //  1942   1952   2304   2325   Ljava/lang/RuntimeException;
        //  1942   1952   135    139    Ljava/io/IOException;
        //  1942   1952   131    135    Any
        //  1957   1976   2304   2325   Ljava/lang/RuntimeException;
        //  1957   1976   135    139    Ljava/io/IOException;
        //  1957   1976   131    135    Any
        //  1982   1991   2304   2325   Ljava/lang/RuntimeException;
        //  1982   1991   135    139    Ljava/io/IOException;
        //  1982   1991   131    135    Any
        //  1998   2048   2304   2325   Ljava/lang/RuntimeException;
        //  1998   2048   135    139    Ljava/io/IOException;
        //  1998   2048   131    135    Any
        //  2053   2072   2304   2325   Ljava/lang/RuntimeException;
        //  2053   2072   135    139    Ljava/io/IOException;
        //  2053   2072   131    135    Any
        //  2096   2159   2304   2325   Ljava/lang/RuntimeException;
        //  2096   2159   135    139    Ljava/io/IOException;
        //  2096   2159   131    135    Any
        //  2173   2183   2304   2325   Ljava/lang/RuntimeException;
        //  2173   2183   135    139    Ljava/io/IOException;
        //  2173   2183   131    135    Any
        //  2190   2229   2304   2325   Ljava/lang/RuntimeException;
        //  2190   2229   135    139    Ljava/io/IOException;
        //  2190   2229   131    135    Any
        //  2232   2272   2304   2325   Ljava/lang/RuntimeException;
        //  2232   2272   135    139    Ljava/io/IOException;
        //  2232   2272   131    135    Any
        //  2278   2296   2304   2325   Ljava/lang/RuntimeException;
        //  2278   2296   135    139    Ljava/io/IOException;
        //  2278   2296   131    135    Any
        //  2296   2301   2304   2325   Ljava/lang/RuntimeException;
        //  2296   2301   135    139    Ljava/io/IOException;
        //  2296   2301   131    135    Any
        //  2305   2322   135    139    Ljava/io/IOException;
        //  2305   2322   131    135    Any
        //  2330   2338   2686   2687   Ljava/io/IOException;
        //  2330   2338   2680   2681   Any
        //  2338   2345   2382   2386   Ljava/io/IOException;
        //  2338   2345   2378   2382   Any
        //  2345   2368   2676   2680   Ljava/io/IOException;
        //  2345   2368   2441   2445   Any
        //  2370   2375   2676   2680   Ljava/io/IOException;
        //  2370   2375   2441   2445   Any
        //  2400   2415   2415   2416   Any
        //  2420   2439   2445   2446   Ljava/lang/Exception;
        //  2420   2439   2441   2445   Any
        //  2439   2441   2445   2446   Ljava/lang/Exception;
        //  2439   2441   2441   2445   Any
        //  2446   2474   2676   2680   Ljava/io/IOException;
        //  2446   2474   2441   2445   Any
        //  2479   2484   2670   2676   Ljava/io/IOException;
        //  2479   2484   2663   2670   Any
        //  2493   2504   2670   2676   Ljava/io/IOException;
        //  2493   2504   2663   2670   Any
        //  2552   2557   2670   2676   Ljava/io/IOException;
        //  2552   2557   2663   2670   Any
        //  2572   2578   2670   2676   Ljava/io/IOException;
        //  2572   2578   2663   2670   Any
        //  2601   2619   2670   2676   Ljava/io/IOException;
        //  2601   2619   2663   2670   Any
        //  2691   2755   2799   2804   Any
        // 
        // The error that occurred was:
        // 
        // java.lang.IndexOutOfBoundsException: Index: 1299, Size: 1299
        //     at java.util.ArrayList.rangeCheck(Unknown Source)
        //     at java.util.ArrayList.get(Unknown Source)
        //     at com.strobel.decompiler.ast.AstBuilder.convertToAst(AstBuilder.java:3362)
        //     at com.strobel.decompiler.ast.AstBuilder.convertToAst(AstBuilder.java:3476)
        //     at com.strobel.decompiler.ast.AstBuilder.build(AstBuilder.java:112)
        //     at com.strobel.decompiler.languages.java.ast.AstMethodBodyBuilder.createMethodBody(AstMethodBodyBuilder.java:203)
        //     at com.strobel.decompiler.languages.java.ast.AstMethodBodyBuilder.createMethodBody(AstMethodBodyBuilder.java:93)
        //     at com.strobel.decompiler.languages.java.ast.AstBuilder.createMethodBody(AstBuilder.java:868)
        //     at com.strobel.decompiler.languages.java.ast.AstBuilder.createMethod(AstBuilder.java:761)
        //     at com.strobel.decompiler.languages.java.ast.AstBuilder.addTypeMembers(AstBuilder.java:638)
        //     at com.strobel.decompiler.languages.java.ast.AstBuilder.createTypeCore(AstBuilder.java:605)
        //     at com.strobel.decompiler.languages.java.ast.AstBuilder.createTypeNoCache(AstBuilder.java:195)
        //     at com.strobel.decompiler.languages.java.ast.AstBuilder.createType(AstBuilder.java:162)
        //     at com.strobel.decompiler.languages.java.ast.AstBuilder.addType(AstBuilder.java:137)
        //     at com.strobel.decompiler.languages.java.JavaLanguage.buildAst(JavaLanguage.java:71)
        //     at com.strobel.decompiler.languages.java.JavaLanguage.decompileType(JavaLanguage.java:59)
        //     at com.strobel.decompiler.DecompilerDriver.decompileType(DecompilerDriver.java:333)
        //     at com.strobel.decompiler.DecompilerDriver.decompileJar(DecompilerDriver.java:254)
        //     at com.strobel.decompiler.DecompilerDriver.main(DecompilerDriver.java:129)
        // 
        throw new IllegalStateException("An error occurred while decompiling this method.");
    }
}
