import org.chromium.net.impl.CronetUploadDataStream;
import org.chromium.net.impl.CronetBidirectionalStream;
import org.chromium.net.NetworkChangeNotifierAutoDetect;

// 
// Decompiled by Procyon v0.6.0
// 

public final class ascx implements Runnable
{
    final /* synthetic */ Object a = a;
    private final /* synthetic */ int b;
    
    public ascx(final arxw a, final int b) {
        this.b = b;
        this.a = a;
    }
    
    public ascx(final ascx a, final int b, final byte[] array) {
        this.b = b;
        this.a = a;
    }
    
    public ascx(final ascy a, final int b) {
        this.b = b;
        this.a = a;
    }
    
    public ascx(final asdi a, final int b) {
        this.b = b;
        this.a = a;
    }
    
    public ascx(final asdu a, final int b) {
        this.b = b;
        this.a = a;
    }
    
    public ascx(final asdx a, final int b) {
        this.b = b;
        this.a = a;
    }
    
    public ascx(final asep a, final int b) {
        this.b = b;
        this.a = a;
    }
    
    public ascx(final ashu a, final int b) {
        this.b = b;
        this.a = a;
    }
    
    public ascx(final asnw a, final int b) {
        this.b = b;
        this.a = a;
    }
    
    public ascx(final asye a, final int b) {
        this.b = b;
        this.a = a;
    }
    
    public ascx(final NetworkChangeNotifierAutoDetect a, final int b) {
        this.b = b;
        this.a = a;
    }
    
    public ascx(final CronetBidirectionalStream a, final int b) {
        this.b = b;
        this.a = a;
    }
    
    public ascx(final CronetUploadDataStream a, final int b) {
        this.b = b;
        this.a = a;
    }
    
    public ascx(final yku a, final int b, final byte[] array) {
        this.b = b;
        this.a = a;
    }
    
    @Override
    public final void run() {
        // 
        // This method could not be decompiled.
        // 
        // Original Bytecode:
        // 
        //     1: getfield        ascx.b:I
        //     4: istore_1       
        //     5: iconst_1       
        //     6: istore_2       
        //     7: iload_1        
        //     8: tableswitch {
        //                0: 1312
        //                1: 1295
        //                2: 1196
        //                3: 1169
        //                4: 1144
        //                5: 776
        //                6: 723
        //                7: 693
        //                8: 665
        //                9: 641
        //               10: 630
        //               11: 585
        //               12: 540
        //               13: 529
        //               14: 514
        //               15: 497
        //               16: 314
        //               17: 278
        //               18: 177
        //               19: 120
        //          default: 104
        //        }
        //   104: aload_0        
        //   105: getfield        ascx.a:Ljava/lang/Object;
        //   108: checkcast       Lorg/chromium/net/impl/CronetUploadDataStream;
        //   111: getfield        org/chromium/net/impl/CronetUploadDataStream.g:Ljava/lang/Object;
        //   114: astore_3       
        //   115: aload_3        
        //   116: monitorenter   
        //   117: goto            1326
        //   120: aload_0        
        //   121: getfield        ascx.a:Ljava/lang/Object;
        //   124: astore          4
        //   126: aload           4
        //   128: checkcast       Lorg/chromium/net/impl/CronetBidirectionalStream;
        //   131: getfield        org/chromium/net/impl/CronetBidirectionalStream.a:Laudy;
        //   134: astore          5
        //   136: aload           4
        //   138: checkcast       Lorg/chromium/net/impl/CronetBidirectionalStream;
        //   141: getfield        org/chromium/net/impl/CronetBidirectionalStream.g:Laudw;
        //   144: astore_3       
        //   145: aload           5
        //   147: aload           4
        //   149: checkcast       Lorg/chromium/net/BidirectionalStream;
        //   152: aload_3        
        //   153: invokevirtual   org/chromium/net/BidirectionalStream$Callback.onCanceled:(Lorg/chromium/net/BidirectionalStream;Lorg/chromium/net/UrlResponseInfo;)V
        //   156: return         
        //   157: astore_3       
        //   158: ldc             "cr_"
        //   160: getstatic       org/chromium/net/impl/CronetUrlRequestContext.b:Ljava/lang/String;
        //   163: invokestatic    java/lang/String.valueOf:(Ljava/lang/Object;)Ljava/lang/String;
        //   166: invokevirtual   java/lang/String.concat:(Ljava/lang/String;)Ljava/lang/String;
        //   169: ldc             "Exception in onCanceled method"
        //   171: aload_3        
        //   172: invokestatic    android/util/Log.e:(Ljava/lang/String;Ljava/lang/String;Ljava/lang/Throwable;)I
        //   175: pop            
        //   176: return         
        //   177: aload_0        
        //   178: getfield        ascx.a:Ljava/lang/Object;
        //   181: checkcast       Lorg/chromium/net/impl/CronetBidirectionalStream;
        //   184: getfield        org/chromium/net/impl/CronetBidirectionalStream.c:Ljava/lang/Object;
        //   187: astore_3       
        //   188: aload_3        
        //   189: monitorenter   
        //   190: aload_0        
        //   191: getfield        ascx.a:Ljava/lang/Object;
        //   194: astore          5
        //   196: aload           5
        //   198: checkcast       Lorg/chromium/net/impl/CronetBidirectionalStream;
        //   201: invokevirtual   org/chromium/net/impl/CronetBidirectionalStream.e:()Z
        //   204: ifeq            210
        //   207: aload_3        
        //   208: monitorexit    
        //   209: return         
        //   210: aload           5
        //   212: checkcast       Lorg/chromium/net/impl/CronetBidirectionalStream;
        //   215: iconst_2       
        //   216: putfield        org/chromium/net/impl/CronetBidirectionalStream.e:I
        //   219: aload_3        
        //   220: monitorexit    
        //   221: aload_0        
        //   222: getfield        ascx.a:Ljava/lang/Object;
        //   225: astore          4
        //   227: aload           4
        //   229: checkcast       Lorg/chromium/net/impl/CronetBidirectionalStream;
        //   232: getfield        org/chromium/net/impl/CronetBidirectionalStream.a:Laudy;
        //   235: astore_3       
        //   236: aload           4
        //   238: checkcast       Lorg/chromium/net/impl/CronetBidirectionalStream;
        //   241: getfield        org/chromium/net/impl/CronetBidirectionalStream.g:Laudw;
        //   244: astore          5
        //   246: aload_3        
        //   247: aload           4
        //   249: checkcast       Lorg/chromium/net/BidirectionalStream;
        //   252: aload           5
        //   254: invokevirtual   audy.onResponseHeadersReceived:(Lorg/chromium/net/BidirectionalStream;Lorg/chromium/net/UrlResponseInfo;)V
        //   257: return         
        //   258: astore_3       
        //   259: aload_0        
        //   260: getfield        ascx.a:Ljava/lang/Object;
        //   263: checkcast       Lorg/chromium/net/impl/CronetBidirectionalStream;
        //   266: aload_3        
        //   267: invokevirtual   org/chromium/net/impl/CronetBidirectionalStream.c:(Ljava/lang/Exception;)V
        //   270: return         
        //   271: astore          5
        //   273: aload_3        
        //   274: monitorexit    
        //   275: aload           5
        //   277: athrow         
        //   278: aload_0        
        //   279: getfield        ascx.a:Ljava/lang/Object;
        //   282: checkcast       Lorg/chromium/net/NetworkChangeNotifierAutoDetect;
        //   285: invokestatic    org/chromium/net/NetworkChangeNotifierAutoDetect.-$$Nest$fgetmIgnoreNextBroadcast:(Lorg/chromium/net/NetworkChangeNotifierAutoDetect;)Z
        //   288: ifeq            303
        //   291: aload_0        
        //   292: getfield        ascx.a:Ljava/lang/Object;
        //   295: checkcast       Lorg/chromium/net/NetworkChangeNotifierAutoDetect;
        //   298: iconst_0       
        //   299: invokestatic    org/chromium/net/NetworkChangeNotifierAutoDetect.-$$Nest$fputmIgnoreNextBroadcast:(Lorg/chromium/net/NetworkChangeNotifierAutoDetect;Z)V
        //   302: return         
        //   303: aload_0        
        //   304: getfield        ascx.a:Ljava/lang/Object;
        //   307: checkcast       Lorg/chromium/net/NetworkChangeNotifierAutoDetect;
        //   310: invokestatic    org/chromium/net/NetworkChangeNotifierAutoDetect.-$$Nest$mconnectionTypeChanged:(Lorg/chromium/net/NetworkChangeNotifierAutoDetect;)V
        //   313: return         
        //   314: aload_0        
        //   315: getfield        ascx.a:Ljava/lang/Object;
        //   318: astore          4
        //   320: aload           4
        //   322: checkcast       Laubf;
        //   325: getfield        aubf.c:Ljava/lang/String;
        //   328: invokestatic    org/chromium/base/TraceEvent.b:(Ljava/lang/String;)Lorg/chromium/base/TraceEvent;
        //   331: astore_3       
        //   332: aload           4
        //   334: checkcast       Laubf;
        //   337: getfield        aubf.f:Ljava/lang/Object;
        //   340: astore          5
        //   342: aload           5
        //   344: monitorenter   
        //   345: aload           4
        //   347: checkcast       Laubf;
        //   350: getfield        aubf.g:Ljava/util/LinkedList;
        //   353: astore          6
        //   355: aload           6
        //   357: ifnonnull       372
        //   360: aload           5
        //   362: monitorexit    
        //   363: aload_3        
        //   364: ifnull          441
        //   367: aload_3        
        //   368: invokevirtual   org/chromium/base/TraceEvent.close:()V
        //   371: return         
        //   372: aload           6
        //   374: invokevirtual   java/util/LinkedList.poll:()Ljava/lang/Object;
        //   377: checkcast       Ljava/lang/Runnable;
        //   380: astore          6
        //   382: aload           5
        //   384: monitorexit    
        //   385: aload           4
        //   387: checkcast       Laubf;
        //   390: getfield        aubf.b:Laubg;
        //   393: getfield        aubg.f:I
        //   396: istore_2       
        //   397: iload_2        
        //   398: iconst_1       
        //   399: if_icmpeq       422
        //   402: iload_2        
        //   403: iconst_2       
        //   404: if_icmpeq       415
        //   407: bipush          10
        //   409: invokestatic    android/os/Process.setThreadPriority:(I)V
        //   412: goto            426
        //   415: iconst_m1      
        //   416: invokestatic    android/os/Process.setThreadPriority:(I)V
        //   419: goto            426
        //   422: iconst_0       
        //   423: invokestatic    android/os/Process.setThreadPriority:(I)V
        //   426: aload           6
        //   428: invokeinterface java/lang/Runnable.run:()V
        //   433: aload_3        
        //   434: ifnull          441
        //   437: aload_3        
        //   438: invokevirtual   org/chromium/base/TraceEvent.close:()V
        //   441: return         
        //   442: astore          4
        //   444: aload           5
        //   446: monitorexit    
        //   447: aload           4
        //   449: athrow         
        //   450: astore          5
        //   452: aload_3        
        //   453: ifnull          494
        //   456: aload_3        
        //   457: invokevirtual   org/chromium/base/TraceEvent.close:()V
        //   460: goto            494
        //   463: astore_3       
        //   464: ldc             Ljava/lang/Throwable;.class
        //   466: ldc             "addSuppressed"
        //   468: iconst_1       
        //   469: anewarray       Ljava/lang/Class;
        //   472: dup            
        //   473: iconst_0       
        //   474: ldc             Ljava/lang/Throwable;.class
        //   476: aastore        
        //   477: invokevirtual   java/lang/Class.getDeclaredMethod:(Ljava/lang/String;[Ljava/lang/Class;)Ljava/lang/reflect/Method;
        //   480: aload           5
        //   482: iconst_1       
        //   483: anewarray       Ljava/lang/Object;
        //   486: dup            
        //   487: iconst_0       
        //   488: aload_3        
        //   489: aastore        
        //   490: invokevirtual   java/lang/reflect/Method.invoke:(Ljava/lang/Object;[Ljava/lang/Object;)Ljava/lang/Object;
        //   493: pop            
        //   494: aload           5
        //   496: athrow         
        //   497: aload_0        
        //   498: getfield        ascx.a:Ljava/lang/Object;
        //   501: astore_3       
        //   502: bipush          10
        //   504: invokestatic    android/os/Process.setThreadPriority:(I)V
        //   507: aload_3        
        //   508: invokeinterface java/lang/Runnable.run:()V
        //   513: return         
        //   514: aload_0        
        //   515: getfield        ascx.a:Ljava/lang/Object;
        //   518: checkcast       Laqph;
        //   521: invokevirtual   aqph.e:()Laqpo;
        //   524: invokevirtual   aqpo.c:()Z
        //   527: pop            
        //   528: return         
        //   529: aload_0        
        //   530: getfield        ascx.a:Ljava/lang/Object;
        //   533: checkcast       Latyq;
        //   536: invokevirtual   atyq.h:()V
        //   539: return         
        //   540: aload_0        
        //   541: getfield        ascx.a:Ljava/lang/Object;
        //   544: checkcast       Lasye;
        //   547: getfield        asye.a:Lashj;
        //   550: invokeinterface ashj.tu:()V
        //   555: aload_0        
        //   556: getfield        ascx.a:Ljava/lang/Object;
        //   559: checkcast       Lasye;
        //   562: getfield        asye.d:Lashn;
        //   565: invokevirtual   ashn.dispose:()V
        //   568: return         
        //   569: astore_3       
        //   570: aload_0        
        //   571: getfield        ascx.a:Ljava/lang/Object;
        //   574: checkcast       Lasye;
        //   577: getfield        asye.d:Lashn;
        //   580: invokevirtual   ashn.dispose:()V
        //   583: aload_3        
        //   584: athrow         
        //   585: aload_0        
        //   586: getfield        ascx.a:Ljava/lang/Object;
        //   589: checkcast       Lasnw;
        //   592: getfield        asnw.a:Laujp;
        //   595: invokeinterface aujp.tu:()V
        //   600: aload_0        
        //   601: getfield        ascx.a:Ljava/lang/Object;
        //   604: checkcast       Lasnw;
        //   607: getfield        asnw.d:Lashn;
        //   610: invokevirtual   ashn.dispose:()V
        //   613: return         
        //   614: astore_3       
        //   615: aload_0        
        //   616: getfield        ascx.a:Ljava/lang/Object;
        //   619: checkcast       Lasnw;
        //   622: getfield        asnw.d:Lashn;
        //   625: invokevirtual   ashn.dispose:()V
        //   628: aload_3        
        //   629: athrow         
        //   630: aload_0        
        //   631: getfield        ascx.a:Ljava/lang/Object;
        //   634: checkcast       Lashu;
        //   637: invokevirtual   ashu.a:()V
        //   640: return         
        //   641: aload_0        
        //   642: getfield        ascx.a:Ljava/lang/Object;
        //   645: checkcast       Lasep;
        //   648: getfield        asep.a:Lasev;
        //   651: getstatic       io/grpc/Status.b:Lio/grpc/Status;
        //   654: ldc             "Handshake timeout exceeded"
        //   656: invokevirtual   io/grpc/Status.withDescription:(Ljava/lang/String;)Lio/grpc/Status;
        //   659: invokeinterface asev.k:(Lio/grpc/Status;)V
        //   664: return         
        //   665: aload_0        
        //   666: getfield        ascx.a:Ljava/lang/Object;
        //   669: checkcast       Lasdu;
        //   672: getfield        asdu.b:Lasdx;
        //   675: astore_3       
        //   676: aload_3        
        //   677: getfield        asdx.w:Z
        //   680: ifne            692
        //   683: aload_3        
        //   684: getfield        asdx.u:Laryv;
        //   687: invokeinterface aryv.e:()V
        //   692: return         
        //   693: aload_0        
        //   694: getfield        ascx.a:Ljava/lang/Object;
        //   697: checkcast       Lasdu;
        //   700: getfield        asdu.b:Lasdx;
        //   703: getfield        asdx.f:Ljava/util/concurrent/Executor;
        //   706: new             Lascx;
        //   709: dup            
        //   710: aload_0        
        //   711: bipush          6
        //   713: aconst_null    
        //   714: invokespecial   ascx.<init>:(Lascx;I[B)V
        //   717: invokeinterface java/util/concurrent/Executor.execute:(Ljava/lang/Runnable;)V
        //   722: return         
        //   723: aload_0        
        //   724: getfield        ascx.a:Ljava/lang/Object;
        //   727: checkcast       Lascx;
        //   730: getfield        ascx.a:Ljava/lang/Object;
        //   733: checkcast       Lasdu;
        //   736: astore_3       
        //   737: aload_3        
        //   738: getfield        asdu.b:Lasdx;
        //   741: aload_3        
        //   742: getfield        asdu.a:Lasdv;
        //   745: getfield        asdv.d:I
        //   748: iconst_1       
        //   749: iadd           
        //   750: iconst_0       
        //   751: invokevirtual   asdx.p:(IZ)Lasdv;
        //   754: astore_3       
        //   755: aload_0        
        //   756: getfield        ascx.a:Ljava/lang/Object;
        //   759: checkcast       Lascx;
        //   762: getfield        ascx.a:Ljava/lang/Object;
        //   765: checkcast       Lasdu;
        //   768: getfield        asdu.b:Lasdx;
        //   771: aload_3        
        //   772: invokevirtual   asdx.t:(Lasdv;)V
        //   775: return         
        //   776: aload_0        
        //   777: getfield        ascx.a:Ljava/lang/Object;
        //   780: checkcast       Lyku;
        //   783: getfield        yku.b:Ljava/lang/Object;
        //   786: checkcast       Lasdx;
        //   789: astore_3       
        //   790: aload_3        
        //   791: aload_3        
        //   792: getfield        asdx.q:Lasdt;
        //   795: getfield        asdt.e:I
        //   798: iconst_0       
        //   799: invokevirtual   asdx.p:(IZ)Lasdv;
        //   802: astore          4
        //   804: aload_0        
        //   805: getfield        ascx.a:Ljava/lang/Object;
        //   808: checkcast       Lyku;
        //   811: getfield        yku.b:Ljava/lang/Object;
        //   814: checkcast       Lasdx;
        //   817: getfield        asdx.l:Ljava/lang/Object;
        //   820: astore          5
        //   822: aload           5
        //   824: monitorenter   
        //   825: aload_0        
        //   826: getfield        ascx.a:Ljava/lang/Object;
        //   829: astore_3       
        //   830: aload_3        
        //   831: checkcast       Lyku;
        //   834: getfield        yku.a:Ljava/lang/Object;
        //   837: checkcast       Labbu;
        //   840: getfield        abbu.a:Z
        //   843: ifeq            851
        //   846: aconst_null    
        //   847: astore_3       
        //   848: goto            1036
        //   851: aload_3        
        //   852: checkcast       Lyku;
        //   855: getfield        yku.b:Ljava/lang/Object;
        //   858: astore_3       
        //   859: aload_3        
        //   860: checkcast       Lasdx;
        //   863: getfield        asdx.q:Lasdt;
        //   866: aload           4
        //   868: invokevirtual   asdt.a:(Lasdv;)Lasdt;
        //   871: astore          6
        //   873: aload_3        
        //   874: checkcast       Lasdx;
        //   877: aload           6
        //   879: putfield        asdx.q:Lasdt;
        //   882: aload_0        
        //   883: getfield        ascx.a:Ljava/lang/Object;
        //   886: checkcast       Lyku;
        //   889: getfield        yku.b:Ljava/lang/Object;
        //   892: astore          6
        //   894: aload           6
        //   896: checkcast       Lasdx;
        //   899: getfield        asdx.q:Lasdt;
        //   902: astore_3       
        //   903: aload           6
        //   905: checkcast       Lasdx;
        //   908: aload_3        
        //   909: invokevirtual   asdx.v:(Lasdt;)Z
        //   912: ifeq            983
        //   915: aload_0        
        //   916: getfield        ascx.a:Ljava/lang/Object;
        //   919: checkcast       Lyku;
        //   922: getfield        yku.b:Ljava/lang/Object;
        //   925: checkcast       Lasdx;
        //   928: getfield        asdx.o:Lasdw;
        //   931: astore_3       
        //   932: aload_3        
        //   933: ifnull          943
        //   936: aload_3        
        //   937: invokevirtual   asdw.a:()Z
        //   940: ifeq            983
        //   943: aload_0        
        //   944: getfield        ascx.a:Ljava/lang/Object;
        //   947: checkcast       Lyku;
        //   950: getfield        yku.b:Ljava/lang/Object;
        //   953: astore          6
        //   955: new             Labbu;
        //   958: astore_3       
        //   959: aload_3        
        //   960: aload           6
        //   962: checkcast       Lasdx;
        //   965: getfield        asdx.l:Ljava/lang/Object;
        //   968: invokespecial   abbu.<init>:(Ljava/lang/Object;)V
        //   971: aload           6
        //   973: checkcast       Lasdx;
        //   976: aload_3        
        //   977: putfield        asdx.B:Labbu;
        //   980: goto            1034
        //   983: aload_0        
        //   984: getfield        ascx.a:Ljava/lang/Object;
        //   987: checkcast       Lyku;
        //   990: getfield        yku.b:Ljava/lang/Object;
        //   993: astore_3       
        //   994: aload_3        
        //   995: checkcast       Lasdx;
        //   998: getfield        asdx.q:Lasdt;
        //  1001: invokevirtual   asdt.b:()Lasdt;
        //  1004: astore          6
        //  1006: aload_3        
        //  1007: checkcast       Lasdx;
        //  1010: aload           6
        //  1012: putfield        asdx.q:Lasdt;
        //  1015: aload_0        
        //  1016: getfield        ascx.a:Ljava/lang/Object;
        //  1019: checkcast       Lyku;
        //  1022: getfield        yku.b:Ljava/lang/Object;
        //  1025: checkcast       Lasdx;
        //  1028: aconst_null    
        //  1029: putfield        asdx.B:Labbu;
        //  1032: aconst_null    
        //  1033: astore_3       
        //  1034: iconst_0       
        //  1035: istore_2       
        //  1036: aload           5
        //  1038: monitorexit    
        //  1039: iload_2        
        //  1040: ifeq            1063
        //  1043: aload           4
        //  1045: getfield        asdv.a:Laryt;
        //  1048: getstatic       io/grpc/Status.b:Lio/grpc/Status;
        //  1051: ldc_w           "Unneeded hedging"
        //  1054: invokevirtual   io/grpc/Status.withDescription:(Ljava/lang/String;)Lio/grpc/Status;
        //  1057: invokeinterface aryt.c:(Lio/grpc/Status;)V
        //  1062: return         
        //  1063: aload_3        
        //  1064: ifnull          1119
        //  1067: aload_0        
        //  1068: getfield        ascx.a:Ljava/lang/Object;
        //  1071: checkcast       Lyku;
        //  1074: getfield        yku.b:Ljava/lang/Object;
        //  1077: checkcast       Lasdx;
        //  1080: astore          5
        //  1082: aload_3        
        //  1083: aload           5
        //  1085: getfield        asdx.h:Ljava/util/concurrent/ScheduledExecutorService;
        //  1088: new             Lyku;
        //  1091: dup            
        //  1092: aload           5
        //  1094: aload_3        
        //  1095: iconst_2       
        //  1096: aconst_null    
        //  1097: invokespecial   yku.<init>:(Lasdx;Labbu;I[B)V
        //  1100: aload           5
        //  1102: getfield        asdx.j:Lasaq;
        //  1105: getfield        asaq.b:J
        //  1108: getstatic       java/util/concurrent/TimeUnit.NANOSECONDS:Ljava/util/concurrent/TimeUnit;
        //  1111: invokeinterface java/util/concurrent/ScheduledExecutorService.schedule:(Ljava/lang/Runnable;JLjava/util/concurrent/TimeUnit;)Ljava/util/concurrent/ScheduledFuture;
        //  1116: invokevirtual   abbu.j:(Ljava/util/concurrent/Future;)V
        //  1119: aload_0        
        //  1120: getfield        ascx.a:Ljava/lang/Object;
        //  1123: checkcast       Lyku;
        //  1126: getfield        yku.b:Ljava/lang/Object;
        //  1129: checkcast       Lasdx;
        //  1132: aload           4
        //  1134: invokevirtual   asdx.t:(Lasdv;)V
        //  1137: return         
        //  1138: astore_3       
        //  1139: aload           5
        //  1141: monitorexit    
        //  1142: aload_3        
        //  1143: athrow         
        //  1144: aload_0        
        //  1145: getfield        ascx.a:Ljava/lang/Object;
        //  1148: checkcast       Lasdx;
        //  1151: astore_3       
        //  1152: aload_3        
        //  1153: getfield        asdx.w:Z
        //  1156: ifne            1168
        //  1159: aload_3        
        //  1160: getfield        asdx.u:Laryv;
        //  1163: invokeinterface aryv.e:()V
        //  1168: return         
        //  1169: aload_0        
        //  1170: getfield        ascx.a:Ljava/lang/Object;
        //  1173: checkcast       Lasdi;
        //  1176: astore_3       
        //  1177: aload_3        
        //  1178: getfield        asdi.b:Ljava/util/concurrent/Executor;
        //  1181: new             Lascx;
        //  1184: dup            
        //  1185: aload_3        
        //  1186: iconst_2       
        //  1187: invokespecial   ascx.<init>:(Lasdi;I)V
        //  1190: invokeinterface java/util/concurrent/Executor.execute:(Ljava/lang/Runnable;)V
        //  1195: return         
        //  1196: aload_0        
        //  1197: getfield        ascx.a:Ljava/lang/Object;
        //  1200: checkcast       Lasdi;
        //  1203: astore_3       
        //  1204: aload_3        
        //  1205: getfield        asdi.e:Z
        //  1208: ifne            1217
        //  1211: aload_3        
        //  1212: aconst_null    
        //  1213: putfield        asdi.f:Ljava/util/concurrent/ScheduledFuture;
        //  1216: return         
        //  1217: aload_3        
        //  1218: invokevirtual   asdi.a:()J
        //  1221: lstore          7
        //  1223: aload_0        
        //  1224: getfield        ascx.a:Ljava/lang/Object;
        //  1227: checkcast       Lasdi;
        //  1230: astore_3       
        //  1231: aload_3        
        //  1232: getfield        asdi.d:J
        //  1235: lload           7
        //  1237: lsub           
        //  1238: lstore          7
        //  1240: lload           7
        //  1242: lconst_0       
        //  1243: lcmp           
        //  1244: ifle            1275
        //  1247: aload_3        
        //  1248: aload_3        
        //  1249: getfield        asdi.a:Ljava/util/concurrent/ScheduledExecutorService;
        //  1252: new             Lascx;
        //  1255: dup            
        //  1256: aload_3        
        //  1257: iconst_3       
        //  1258: invokespecial   ascx.<init>:(Lasdi;I)V
        //  1261: lload           7
        //  1263: getstatic       java/util/concurrent/TimeUnit.NANOSECONDS:Ljava/util/concurrent/TimeUnit;
        //  1266: invokeinterface java/util/concurrent/ScheduledExecutorService.schedule:(Ljava/lang/Runnable;JLjava/util/concurrent/TimeUnit;)Ljava/util/concurrent/ScheduledFuture;
        //  1271: putfield        asdi.f:Ljava/util/concurrent/ScheduledFuture;
        //  1274: return         
        //  1275: aload_3        
        //  1276: iconst_0       
        //  1277: putfield        asdi.e:Z
        //  1280: aload_3        
        //  1281: aconst_null    
        //  1282: putfield        asdi.f:Ljava/util/concurrent/ScheduledFuture;
        //  1285: aload_3        
        //  1286: getfield        asdi.c:Ljava/lang/Runnable;
        //  1289: invokeinterface java/lang/Runnable.run:()V
        //  1294: return         
        //  1295: aload_0        
        //  1296: getfield        ascx.a:Ljava/lang/Object;
        //  1299: checkcast       Larxw;
        //  1302: getfield        arxw.f:Lasbd;
        //  1305: getstatic       asbz.e:Lio/grpc/Status;
        //  1308: invokevirtual   asbd.g:(Lio/grpc/Status;)V
        //  1311: return         
        //  1312: aload_0        
        //  1313: getfield        ascx.a:Ljava/lang/Object;
        //  1316: checkcast       Lascy;
        //  1319: getfield        ascy.a:Lartn;
        //  1322: invokevirtual   artn.c:()V
        //  1325: return         
        //  1326: aload_0        
        //  1327: getfield        ascx.a:Ljava/lang/Object;
        //  1330: astore          5
        //  1332: aload           5
        //  1334: checkcast       Lorg/chromium/net/impl/CronetUploadDataStream;
        //  1337: getfield        org/chromium/net/impl/CronetUploadDataStream.h:J
        //  1340: lconst_0       
        //  1341: lcmp           
        //  1342: ifne            1348
        //  1345: aload_3        
        //  1346: monitorexit    
        //  1347: return         
        //  1348: aload           5
        //  1350: checkcast       Lorg/chromium/net/impl/CronetUploadDataStream;
        //  1353: invokestatic    org/chromium/net/impl/CronetUploadDataStream.d:(Lorg/chromium/net/impl/CronetUploadDataStream;)V
        //  1356: aload_0        
        //  1357: getfield        ascx.a:Ljava/lang/Object;
        //  1360: astore          5
        //  1362: aload           5
        //  1364: checkcast       Lorg/chromium/net/impl/CronetUploadDataStream;
        //  1367: getfield        org/chromium/net/impl/CronetUploadDataStream.f:Ljava/nio/ByteBuffer;
        //  1370: ifnull          1444
        //  1373: aload           5
        //  1375: checkcast       Lorg/chromium/net/impl/CronetUploadDataStream;
        //  1378: iconst_0       
        //  1379: putfield        org/chromium/net/impl/CronetUploadDataStream.i:I
        //  1382: aload_3        
        //  1383: monitorexit    
        //  1384: aload_0        
        //  1385: getfield        ascx.a:Ljava/lang/Object;
        //  1388: checkcast       Lorg/chromium/net/impl/CronetUploadDataStream;
        //  1391: invokevirtual   org/chromium/net/impl/CronetUploadDataStream.a:()V
        //  1394: aload_0        
        //  1395: getfield        ascx.a:Ljava/lang/Object;
        //  1398: astore          5
        //  1400: aload           5
        //  1402: checkcast       Lorg/chromium/net/impl/CronetUploadDataStream;
        //  1405: getfield        org/chromium/net/impl/CronetUploadDataStream.b:Laued;
        //  1408: astore          4
        //  1410: aload           5
        //  1412: checkcast       Lorg/chromium/net/impl/CronetUploadDataStream;
        //  1415: getfield        org/chromium/net/impl/CronetUploadDataStream.f:Ljava/nio/ByteBuffer;
        //  1418: astore_3       
        //  1419: aload           4
        //  1421: aload           5
        //  1423: checkcast       Lorg/chromium/net/UploadDataSink;
        //  1426: aload_3        
        //  1427: invokevirtual   aued.read:(Lorg/chromium/net/UploadDataSink;Ljava/nio/ByteBuffer;)V
        //  1430: return         
        //  1431: astore_3       
        //  1432: aload_0        
        //  1433: getfield        ascx.a:Ljava/lang/Object;
        //  1436: checkcast       Lorg/chromium/net/impl/CronetUploadDataStream;
        //  1439: aload_3        
        //  1440: invokevirtual   org/chromium/net/impl/CronetUploadDataStream.b:(Ljava/lang/Throwable;)V
        //  1443: return         
        //  1444: new             Ljava/lang/IllegalStateException;
        //  1447: astore          5
        //  1449: aload           5
        //  1451: ldc_w           "Unexpected readData call. Buffer is null"
        //  1454: invokespecial   java/lang/IllegalStateException.<init>:(Ljava/lang/String;)V
        //  1457: aload           5
        //  1459: athrow         
        //  1460: astore          5
        //  1462: aload_3        
        //  1463: monitorexit    
        //  1464: aload           5
        //  1466: athrow         
        //  1467: astore_3       
        //  1468: goto            494
        //    Exceptions:
        //  Try           Handler
        //  Start  End    Start  End    Type                 
        //  -----  -----  -----  -----  ---------------------
        //  120    156    157    177    Ljava/lang/Exception;
        //  190    209    271    278    Any
        //  210    221    271    278    Any
        //  221    257    258    271    Ljava/lang/Exception;
        //  273    275    271    278    Any
        //  332    345    450    497    Any
        //  345    355    442    450    Any
        //  360    363    442    450    Any
        //  372    385    442    450    Any
        //  385    397    450    497    Any
        //  407    412    450    497    Any
        //  415    419    450    497    Any
        //  422    426    450    497    Any
        //  426    433    450    497    Any
        //  444    447    442    450    Any
        //  447    450    450    497    Any
        //  456    460    463    494    Any
        //  464    494    1467   1471   Ljava/lang/Exception;
        //  540    555    569    585    Any
        //  585    600    614    630    Any
        //  825    846    1138   1144   Any
        //  851    932    1138   1144   Any
        //  936    943    1138   1144   Any
        //  943    980    1138   1144   Any
        //  983    1032   1138   1144   Any
        //  1036   1039   1138   1144   Any
        //  1139   1142   1138   1144   Any
        //  1326   1347   1460   1467   Any
        //  1348   1384   1460   1467   Any
        //  1384   1430   1431   1444   Ljava/lang/Exception;
        //  1444   1460   1460   1467   Any
        //  1462   1464   1460   1467   Any
        // 
        // The error that occurred was:
        // 
        // java.lang.IllegalStateException: Expression is linked from several locations: Label_0494:
        //     at com.strobel.decompiler.ast.Error.expressionLinkedFromMultipleLocations(Error.java:27)
        //     at com.strobel.decompiler.ast.AstOptimizer.mergeDisparateObjectInitializations(AstOptimizer.java:2604)
        //     at com.strobel.decompiler.ast.AstOptimizer.optimize(AstOptimizer.java:235)
        //     at com.strobel.decompiler.ast.AstOptimizer.optimize(AstOptimizer.java:42)
        //     at com.strobel.decompiler.languages.java.ast.AstMethodBodyBuilder.createMethodBody(AstMethodBodyBuilder.java:206)
        //     at com.strobel.decompiler.languages.java.ast.AstMethodBodyBuilder.createMethodBody(AstMethodBodyBuilder.java:93)
        //     at com.strobel.decompiler.languages.java.ast.AstBuilder.createMethodBody(AstBuilder.java:868)
        //     at com.strobel.decompiler.languages.java.ast.AstBuilder.createMethod(AstBuilder.java:761)
        //     at com.strobel.decompiler.languages.java.ast.AstBuilder.addTypeMembers(AstBuilder.java:638)
        //     at com.strobel.decompiler.languages.java.ast.AstBuilder.createTypeCore(AstBuilder.java:605)
        //     at com.strobel.decompiler.languages.java.ast.AstBuilder.createTypeNoCache(AstBuilder.java:195)
        //     at com.strobel.decompiler.languages.java.ast.AstBuilder.createType(AstBuilder.java:162)
        //     at com.strobel.decompiler.languages.java.ast.AstBuilder.addType(AstBuilder.java:137)
        //     at com.strobel.decompiler.languages.java.JavaLanguage.buildAst(JavaLanguage.java:71)
        //     at com.strobel.decompiler.languages.java.JavaLanguage.decompileType(JavaLanguage.java:59)
        //     at com.strobel.decompiler.DecompilerDriver.decompileType(DecompilerDriver.java:333)
        //     at com.strobel.decompiler.DecompilerDriver.decompileJar(DecompilerDriver.java:254)
        //     at com.strobel.decompiler.DecompilerDriver.main(DecompilerDriver.java:129)
        // 
        throw new IllegalStateException("An error occurred while decompiling this method.");
    }
}
