import org.webrtc.VideoFrame$I420Buffer;
import org.chromium.net.impl.VersionSafeCallbacks$UrlRequestStatusListener;
import org.chromium.net.impl.CronetUrlRequestContext;
import org.chromium.net.impl.CronetUrlRequest;
import org.chromium.net.impl.CronetUploadDataStream;
import java.util.concurrent.CountDownLatch;
import java.nio.ByteBuffer;

// 
// Decompiled by Procyon v0.6.0
// 

public final class auct implements Runnable
{
    final /* synthetic */ Object a = a;
    private final /* synthetic */ int b;
    
    public auct(final atyo a, final int b, final byte[] array) {
        this.b = b;
        this.a = a;
    }
    
    public auct(final audj a, final int b) {
        this.b = b;
        this.a = a;
    }
    
    public auct(final audk a, final int b) {
        this.b = b;
        this.a = a;
    }
    
    public auct(final aukh a, final int b, final byte[] array) {
        this.b = b;
        this.a = a;
    }
    
    public auct(final aukh a, final int b, final char[] array) {
        this.b = b;
        this.a = a;
    }
    
    public auct(final CronetUploadDataStream a, final int b) {
        this.b = b;
        this.a = a;
    }
    
    public auct(final CronetUrlRequest a, final int b) {
        this.b = b;
        this.a = a;
    }
    
    public auct(final CronetUrlRequestContext a, final int b) {
        this.b = b;
        this.a = a;
    }
    
    public auct(final VersionSafeCallbacks$UrlRequestStatusListener a, final int b) {
        this.b = b;
        this.a = a;
    }
    
    @Override
    public final void run() {
        // 
        // This method could not be decompiled.
        // 
        // Original Bytecode:
        // 
        //     1: getfield        auct.b:I
        //     4: tableswitch {
        //                0: 2704
        //                1: 2603
        //                2: 2423
        //                3: 2411
        //                4: 2312
        //                5: 2203
        //                6: 2140
        //                7: 2066
        //                8: 2026
        //                9: 1961
        //               10: 1920
        //               11: 1887
        //               12: 1861
        //               13: 1820
        //               14: 1608
        //               15: 555
        //               16: 164
        //               17: 132
        //               18: 122
        //               19: 111
        //          default: 100
        //        }
        //   100: aload_0        
        //   101: getfield        auct.a:Ljava/lang/Object;
        //   104: checkcast       Ljava/util/concurrent/CountDownLatch;
        //   107: invokevirtual   java/util/concurrent/CountDownLatch.countDown:()V
        //   110: return         
        //   111: aload_0        
        //   112: getfield        auct.a:Ljava/lang/Object;
        //   115: checkcast       Ljava/nio/ByteBuffer;
        //   118: invokestatic    org/webrtc/JniCommon.nativeFreeByteBuffer:(Ljava/nio/ByteBuffer;)V
        //   121: return         
        //   122: aload_0        
        //   123: getfield        auct.a:Ljava/lang/Object;
        //   126: invokeinterface org/webrtc/VideoFrame$Buffer.release:()V
        //   131: return         
        //   132: aload_0        
        //   133: getfield        auct.a:Ljava/lang/Object;
        //   136: checkcast       Laukh;
        //   139: getfield        aukh.b:Ljava/lang/Object;
        //   142: astore_1       
        //   143: aload_1        
        //   144: monitorenter   
        //   145: aload_0        
        //   146: getfield        auct.a:Ljava/lang/Object;
        //   149: checkcast       Laukh;
        //   152: aconst_null    
        //   153: putfield        aukh.c:Landroid/os/Handler;
        //   156: aload_1        
        //   157: monitorexit    
        //   158: return         
        //   159: astore_2       
        //   160: aload_1        
        //   161: monitorexit    
        //   162: aload_2        
        //   163: athrow         
        //   164: aload_0        
        //   165: getfield        auct.a:Ljava/lang/Object;
        //   168: astore_1       
        //   169: new             Ljava/text/DecimalFormat;
        //   172: dup            
        //   173: ldc             "#.0"
        //   175: invokespecial   java/text/DecimalFormat.<init>:(Ljava/lang/String;)V
        //   178: astore_3       
        //   179: invokestatic    java/lang/System.nanoTime:()J
        //   182: lstore          4
        //   184: aload_1        
        //   185: checkcast       Laukh;
        //   188: getfield        aukh.o:Ljava/lang/Object;
        //   191: astore_2       
        //   192: aload_2        
        //   193: monitorenter   
        //   194: aload_1        
        //   195: checkcast       Laukh;
        //   198: getfield        aukh.s:J
        //   201: lstore          6
        //   203: lload           4
        //   205: lload           6
        //   207: lsub           
        //   208: lstore          8
        //   210: lload           8
        //   212: lconst_0       
        //   213: lcmp           
        //   214: ifle            463
        //   217: aload_1        
        //   218: checkcast       Laukh;
        //   221: getfield        aukh.r:I
        //   224: i2l            
        //   225: lstore          6
        //   227: getstatic       java/util/concurrent/TimeUnit.SECONDS:Ljava/util/concurrent/TimeUnit;
        //   230: lconst_1       
        //   231: invokevirtual   java/util/concurrent/TimeUnit.toNanos:(J)J
        //   234: lstore          10
        //   236: getstatic       java/util/concurrent/TimeUnit.NANOSECONDS:Ljava/util/concurrent/TimeUnit;
        //   239: lload           8
        //   241: invokevirtual   java/util/concurrent/TimeUnit.toMillis:(J)J
        //   244: lstore          12
        //   246: aload_1        
        //   247: checkcast       Laukh;
        //   250: getfield        aukh.p:I
        //   253: istore          14
        //   255: aload_1        
        //   256: checkcast       Laukh;
        //   259: getfield        aukh.q:I
        //   262: istore          15
        //   264: aload_1        
        //   265: checkcast       Laukh;
        //   268: getfield        aukh.r:I
        //   271: istore          16
        //   273: aload_3        
        //   274: lload           6
        //   276: lload           10
        //   278: lmul           
        //   279: l2f            
        //   280: lload           8
        //   282: l2f            
        //   283: fdiv           
        //   284: f2d            
        //   285: invokevirtual   java/text/DecimalFormat.format:(D)Ljava/lang/String;
        //   288: astore          17
        //   290: aload_1        
        //   291: checkcast       Laukh;
        //   294: getfield        aukh.t:J
        //   297: aload_1        
        //   298: checkcast       Laukh;
        //   301: getfield        aukh.r:I
        //   304: invokestatic    aukh.c:(JI)Ljava/lang/String;
        //   307: astore          18
        //   309: aload_1        
        //   310: checkcast       Laukh;
        //   313: getfield        aukh.u:J
        //   316: aload_1        
        //   317: checkcast       Laukh;
        //   320: getfield        aukh.r:I
        //   323: invokestatic    aukh.c:(JI)Ljava/lang/String;
        //   326: astore          19
        //   328: new             Ljava/lang/StringBuilder;
        //   331: astore_3       
        //   332: aload_3        
        //   333: ldc             "Duration: "
        //   335: invokespecial   java/lang/StringBuilder.<init>:(Ljava/lang/String;)V
        //   338: aload_3        
        //   339: lload           12
        //   341: invokevirtual   java/lang/StringBuilder.append:(J)Ljava/lang/StringBuilder;
        //   344: pop            
        //   345: aload_3        
        //   346: ldc             " ms. Frames received: "
        //   348: invokevirtual   java/lang/StringBuilder.append:(Ljava/lang/String;)Ljava/lang/StringBuilder;
        //   351: pop            
        //   352: aload_3        
        //   353: iload           14
        //   355: invokevirtual   java/lang/StringBuilder.append:(I)Ljava/lang/StringBuilder;
        //   358: pop            
        //   359: aload_3        
        //   360: ldc             ". Dropped: "
        //   362: invokevirtual   java/lang/StringBuilder.append:(Ljava/lang/String;)Ljava/lang/StringBuilder;
        //   365: pop            
        //   366: aload_3        
        //   367: iload           15
        //   369: invokevirtual   java/lang/StringBuilder.append:(I)Ljava/lang/StringBuilder;
        //   372: pop            
        //   373: aload_3        
        //   374: ldc             ". Rendered: "
        //   376: invokevirtual   java/lang/StringBuilder.append:(Ljava/lang/String;)Ljava/lang/StringBuilder;
        //   379: pop            
        //   380: aload_3        
        //   381: iload           16
        //   383: invokevirtual   java/lang/StringBuilder.append:(I)Ljava/lang/StringBuilder;
        //   386: pop            
        //   387: aload_3        
        //   388: ldc             ". Render fps: "
        //   390: invokevirtual   java/lang/StringBuilder.append:(Ljava/lang/String;)Ljava/lang/StringBuilder;
        //   393: pop            
        //   394: aload_3        
        //   395: aload           17
        //   397: invokevirtual   java/lang/StringBuilder.append:(Ljava/lang/String;)Ljava/lang/StringBuilder;
        //   400: pop            
        //   401: aload_3        
        //   402: ldc             ". Average render time: "
        //   404: invokevirtual   java/lang/StringBuilder.append:(Ljava/lang/String;)Ljava/lang/StringBuilder;
        //   407: pop            
        //   408: aload_3        
        //   409: aload           18
        //   411: invokevirtual   java/lang/StringBuilder.append:(Ljava/lang/String;)Ljava/lang/StringBuilder;
        //   414: pop            
        //   415: aload_3        
        //   416: ldc             ". Average swapBuffer time: "
        //   418: invokevirtual   java/lang/StringBuilder.append:(Ljava/lang/String;)Ljava/lang/StringBuilder;
        //   421: pop            
        //   422: aload_3        
        //   423: aload           19
        //   425: invokevirtual   java/lang/StringBuilder.append:(Ljava/lang/String;)Ljava/lang/StringBuilder;
        //   428: pop            
        //   429: aload_3        
        //   430: ldc             "."
        //   432: invokevirtual   java/lang/StringBuilder.append:(Ljava/lang/String;)Ljava/lang/StringBuilder;
        //   435: pop            
        //   436: aload_3        
        //   437: invokevirtual   java/lang/StringBuilder.toString:()Ljava/lang/String;
        //   440: astore_3       
        //   441: aload_1        
        //   442: checkcast       Laukh;
        //   445: aload_3        
        //   446: invokevirtual   aukh.b:(Ljava/lang/String;)V
        //   449: aload_1        
        //   450: checkcast       Laukh;
        //   453: lload           4
        //   455: invokevirtual   aukh.a:(J)V
        //   458: aload_2        
        //   459: monitorexit    
        //   460: goto            465
        //   463: aload_2        
        //   464: monitorexit    
        //   465: aload_0        
        //   466: getfield        auct.a:Ljava/lang/Object;
        //   469: checkcast       Laukh;
        //   472: getfield        aukh.b:Ljava/lang/Object;
        //   475: astore_1       
        //   476: aload_1        
        //   477: monitorenter   
        //   478: aload_0        
        //   479: getfield        auct.a:Ljava/lang/Object;
        //   482: astore_3       
        //   483: aload_3        
        //   484: checkcast       Laukh;
        //   487: getfield        aukh.c:Landroid/os/Handler;
        //   490: astore_2       
        //   491: aload_2        
        //   492: ifnull          538
        //   495: aload_2        
        //   496: aload_3        
        //   497: checkcast       Laukh;
        //   500: getfield        aukh.w:Ljava/lang/Runnable;
        //   503: invokevirtual   android/os/Handler.removeCallbacks:(Ljava/lang/Runnable;)V
        //   506: aload_0        
        //   507: getfield        auct.a:Ljava/lang/Object;
        //   510: astore_2       
        //   511: aload_2        
        //   512: checkcast       Laukh;
        //   515: getfield        aukh.c:Landroid/os/Handler;
        //   518: aload_2        
        //   519: checkcast       Laukh;
        //   522: getfield        aukh.w:Ljava/lang/Runnable;
        //   525: getstatic       java/util/concurrent/TimeUnit.SECONDS:Ljava/util/concurrent/TimeUnit;
        //   528: ldc2_w          4
        //   531: invokevirtual   java/util/concurrent/TimeUnit.toMillis:(J)J
        //   534: invokevirtual   android/os/Handler.postDelayed:(Ljava/lang/Runnable;J)Z
        //   537: pop            
        //   538: aload_1        
        //   539: monitorexit    
        //   540: return         
        //   541: astore_2       
        //   542: aload_1        
        //   543: monitorexit    
        //   544: aload_2        
        //   545: athrow         
        //   546: astore_1       
        //   547: goto            551
        //   550: astore_1       
        //   551: aload_2        
        //   552: monitorexit    
        //   553: aload_1        
        //   554: athrow         
        //   555: aload_0        
        //   556: getfield        auct.a:Ljava/lang/Object;
        //   559: astore          19
        //   561: aload           19
        //   563: checkcast       Laukh;
        //   566: astore_2       
        //   567: aload_2        
        //   568: getfield        aukh.k:Ljava/lang/Object;
        //   571: astore_3       
        //   572: aload_3        
        //   573: monitorenter   
        //   574: aload           19
        //   576: checkcast       Laukh;
        //   579: getfield        aukh.l:Lorg/webrtc/VideoFrame;
        //   582: astore_1       
        //   583: aload_1        
        //   584: ifnonnull       590
        //   587: aload_3        
        //   588: monitorexit    
        //   589: return         
        //   590: aload           19
        //   592: checkcast       Laukh;
        //   595: aconst_null    
        //   596: putfield        aukh.l:Lorg/webrtc/VideoFrame;
        //   599: aload_3        
        //   600: monitorexit    
        //   601: aload_2        
        //   602: getfield        aukh.g:Laukc;
        //   605: astore_3       
        //   606: aload_3        
        //   607: ifnull          1591
        //   610: aload_3        
        //   611: invokeinterface aukc.k:()Z
        //   616: ifne            622
        //   619: goto            1591
        //   622: aload_2        
        //   623: getfield        aukh.f:Ljava/lang/Object;
        //   626: astore_3       
        //   627: aload_3        
        //   628: monitorenter   
        //   629: aload_3        
        //   630: monitorexit    
        //   631: invokestatic    java/lang/System.nanoTime:()J
        //   634: lstore          8
        //   636: aload_1        
        //   637: invokevirtual   org/webrtc/VideoFrame.b:()I
        //   640: i2f            
        //   641: aload_1        
        //   642: invokevirtual   org/webrtc/VideoFrame.a:()I
        //   645: i2f            
        //   646: fdiv           
        //   647: fstore          20
        //   649: aload_2        
        //   650: getfield        aukh.m:Ljava/lang/Object;
        //   653: astore_3       
        //   654: aload_3        
        //   655: monitorenter   
        //   656: aload           19
        //   658: checkcast       Laukh;
        //   661: getfield        aukh.n:F
        //   664: fstore          21
        //   666: fload           21
        //   668: fstore          22
        //   670: fload           21
        //   672: fconst_0       
        //   673: fcmpl          
        //   674: ifne            681
        //   677: fload           20
        //   679: fstore          22
        //   681: aload_3        
        //   682: monitorexit    
        //   683: fload           20
        //   685: fload           22
        //   687: fcmpl          
        //   688: ifle            704
        //   691: fload           22
        //   693: fload           20
        //   695: fdiv           
        //   696: fstore          20
        //   698: fconst_1       
        //   699: fstore          22
        //   701: goto            714
        //   704: fload           20
        //   706: fload           22
        //   708: fdiv           
        //   709: fstore          22
        //   711: fconst_1       
        //   712: fstore          20
        //   714: aload_2        
        //   715: getfield        aukh.j:Landroid/graphics/Matrix;
        //   718: invokevirtual   android/graphics/Matrix.reset:()V
        //   721: aload_2        
        //   722: getfield        aukh.j:Landroid/graphics/Matrix;
        //   725: ldc             0.5
        //   727: ldc             0.5
        //   729: invokevirtual   android/graphics/Matrix.preTranslate:(FF)Z
        //   732: pop            
        //   733: aload_2        
        //   734: getfield        aukh.j:Landroid/graphics/Matrix;
        //   737: fconst_1       
        //   738: fconst_1       
        //   739: invokevirtual   android/graphics/Matrix.preScale:(FF)Z
        //   742: pop            
        //   743: aload_2        
        //   744: getfield        aukh.j:Landroid/graphics/Matrix;
        //   747: fload           20
        //   749: fload           22
        //   751: invokevirtual   android/graphics/Matrix.preScale:(FF)Z
        //   754: pop            
        //   755: aload_2        
        //   756: getfield        aukh.j:Landroid/graphics/Matrix;
        //   759: ldc             -0.5
        //   761: ldc             -0.5
        //   763: invokevirtual   android/graphics/Matrix.preTranslate:(FF)Z
        //   766: pop            
        //   767: fconst_0       
        //   768: fconst_0       
        //   769: fconst_0       
        //   770: fconst_0       
        //   771: invokestatic    android/opengl/GLES20.glClearColor:(FFFF)V
        //   774: sipush          16384
        //   777: invokestatic    android/opengl/GLES20.glClear:(I)V
        //   780: aload           19
        //   782: checkcast       Laukh;
        //   785: getfield        aukh.h:Lault;
        //   788: aload_1        
        //   789: aload           19
        //   791: checkcast       Laukh;
        //   794: getfield        aukh.i:Laulb;
        //   797: aload           19
        //   799: checkcast       Laukh;
        //   802: getfield        aukh.j:Landroid/graphics/Matrix;
        //   805: aload           19
        //   807: checkcast       Laukh;
        //   810: getfield        aukh.g:Laukc;
        //   813: invokeinterface aukc.b:()I
        //   818: aload           19
        //   820: checkcast       Laukh;
        //   823: getfield        aukh.g:Laukc;
        //   826: invokeinterface aukc.a:()I
        //   831: invokevirtual   ault.b:(Lorg/webrtc/VideoFrame;Laulb;Landroid/graphics/Matrix;II)V
        //   834: invokestatic    java/lang/System.nanoTime:()J
        //   837: lstore          4
        //   839: aload           19
        //   841: checkcast       Laukh;
        //   844: getfield        aukh.g:Laukc;
        //   847: invokeinterface aukc.i:()V
        //   852: invokestatic    java/lang/System.nanoTime:()J
        //   855: lstore          6
        //   857: aload           19
        //   859: checkcast       Laukh;
        //   862: getfield        aukh.o:Ljava/lang/Object;
        //   865: astore          17
        //   867: aload           17
        //   869: monitorenter   
        //   870: aload           19
        //   872: checkcast       Laukh;
        //   875: getfield        aukh.r:I
        //   878: istore          14
        //   880: aload           19
        //   882: checkcast       Laukh;
        //   885: iload           14
        //   887: iconst_1       
        //   888: iadd           
        //   889: putfield        aukh.r:I
        //   892: aload           19
        //   894: checkcast       Laukh;
        //   897: astore          18
        //   899: aload_1        
        //   900: astore_2       
        //   901: aload_2        
        //   902: astore_3       
        //   903: aload           18
        //   905: getfield        aukh.t:J
        //   908: lstore          10
        //   910: aload_2        
        //   911: astore_3       
        //   912: aload           19
        //   914: checkcast       Laukh;
        //   917: lload           10
        //   919: lload           6
        //   921: lload           8
        //   923: lsub           
        //   924: ladd           
        //   925: putfield        aukh.t:J
        //   928: aload_2        
        //   929: astore_3       
        //   930: aload           19
        //   932: checkcast       Laukh;
        //   935: getfield        aukh.u:J
        //   938: lstore          8
        //   940: aload_2        
        //   941: astore_3       
        //   942: aload           19
        //   944: checkcast       Laukh;
        //   947: lload           8
        //   949: lload           6
        //   951: lload           4
        //   953: lsub           
        //   954: ladd           
        //   955: putfield        aukh.u:J
        //   958: aload_2        
        //   959: astore_3       
        //   960: aload           17
        //   962: monitorexit    
        //   963: aload_2        
        //   964: astore_3       
        //   965: aload_2        
        //   966: astore_1       
        //   967: aload           19
        //   969: checkcast       Laukh;
        //   972: getfield        aukh.d:Ljava/util/ArrayList;
        //   975: invokevirtual   java/util/ArrayList.isEmpty:()Z
        //   978: ifeq            984
        //   981: goto            1459
        //   984: aload_2        
        //   985: astore_3       
        //   986: aload_2        
        //   987: astore_1       
        //   988: aload           19
        //   990: checkcast       Laukh;
        //   993: getfield        aukh.j:Landroid/graphics/Matrix;
        //   996: invokevirtual   android/graphics/Matrix.reset:()V
        //   999: aload_2        
        //  1000: astore_3       
        //  1001: aload_2        
        //  1002: astore_1       
        //  1003: aload           19
        //  1005: checkcast       Laukh;
        //  1008: getfield        aukh.j:Landroid/graphics/Matrix;
        //  1011: ldc             0.5
        //  1013: ldc             0.5
        //  1015: invokevirtual   android/graphics/Matrix.preTranslate:(FF)Z
        //  1018: pop            
        //  1019: aload_2        
        //  1020: astore_3       
        //  1021: aload_2        
        //  1022: astore_1       
        //  1023: aload           19
        //  1025: checkcast       Laukh;
        //  1028: getfield        aukh.j:Landroid/graphics/Matrix;
        //  1031: fconst_1       
        //  1032: fconst_1       
        //  1033: invokevirtual   android/graphics/Matrix.preScale:(FF)Z
        //  1036: pop            
        //  1037: aload_2        
        //  1038: astore_3       
        //  1039: aload_2        
        //  1040: astore_1       
        //  1041: aload           19
        //  1043: checkcast       Laukh;
        //  1046: getfield        aukh.j:Landroid/graphics/Matrix;
        //  1049: fconst_1       
        //  1050: ldc_w           -1.0
        //  1053: invokevirtual   android/graphics/Matrix.preScale:(FF)Z
        //  1056: pop            
        //  1057: aload_2        
        //  1058: astore_3       
        //  1059: aload_2        
        //  1060: astore_1       
        //  1061: aload           19
        //  1063: checkcast       Laukh;
        //  1066: getfield        aukh.j:Landroid/graphics/Matrix;
        //  1069: ldc             -0.5
        //  1071: ldc             -0.5
        //  1073: invokevirtual   android/graphics/Matrix.preTranslate:(FF)Z
        //  1076: pop            
        //  1077: aload_2        
        //  1078: astore_3       
        //  1079: aload_2        
        //  1080: astore_1       
        //  1081: aload           19
        //  1083: checkcast       Laukh;
        //  1086: getfield        aukh.d:Ljava/util/ArrayList;
        //  1089: invokevirtual   java/util/ArrayList.iterator:()Ljava/util/Iterator;
        //  1092: astore          18
        //  1094: aload_2        
        //  1095: astore_3       
        //  1096: aload_2        
        //  1097: astore_1       
        //  1098: aload           18
        //  1100: invokeinterface java/util/Iterator.hasNext:()Z
        //  1105: ifeq            1459
        //  1108: aload_2        
        //  1109: astore_3       
        //  1110: aload_2        
        //  1111: astore_1       
        //  1112: aload           18
        //  1114: invokeinterface java/util/Iterator.next:()Ljava/lang/Object;
        //  1119: checkcast       Laukf;
        //  1122: astore          17
        //  1124: aload_2        
        //  1125: astore_3       
        //  1126: aload_2        
        //  1127: astore_1       
        //  1128: aload           18
        //  1130: invokeinterface java/util/Iterator.remove:()V
        //  1135: aload_2        
        //  1136: astore_3       
        //  1137: aload_2        
        //  1138: astore_1       
        //  1139: aload           17
        //  1141: getfield        aukf.a:F
        //  1144: fstore          22
        //  1146: aload_2        
        //  1147: astore_3       
        //  1148: aload_2        
        //  1149: astore_1       
        //  1150: aload_2        
        //  1151: invokevirtual   org/webrtc/VideoFrame.b:()I
        //  1154: i2f            
        //  1155: fconst_0       
        //  1156: fmul           
        //  1157: f2i            
        //  1158: istore          15
        //  1160: aload_2        
        //  1161: astore_3       
        //  1162: aload_2        
        //  1163: astore_1       
        //  1164: aload           17
        //  1166: getfield        aukf.a:F
        //  1169: fstore          22
        //  1171: aload_2        
        //  1172: astore_3       
        //  1173: aload_2        
        //  1174: astore_1       
        //  1175: aload_2        
        //  1176: invokevirtual   org/webrtc/VideoFrame.a:()I
        //  1179: i2f            
        //  1180: fconst_0       
        //  1181: fmul           
        //  1182: f2i            
        //  1183: istore          14
        //  1185: iload           15
        //  1187: ifeq            1442
        //  1190: iload           14
        //  1192: ifne            1198
        //  1195: goto            1442
        //  1198: aload_2        
        //  1199: astore_3       
        //  1200: aload_2        
        //  1201: astore_1       
        //  1202: aload           19
        //  1204: checkcast       Laukh;
        //  1207: getfield        aukh.v:Laukn;
        //  1210: iload           15
        //  1212: iload           14
        //  1214: invokevirtual   aukn.b:(II)V
        //  1217: aload_2        
        //  1218: astore_3       
        //  1219: aload_2        
        //  1220: astore_1       
        //  1221: ldc_w           36160
        //  1224: aload           19
        //  1226: checkcast       Laukh;
        //  1229: getfield        aukh.v:Laukn;
        //  1232: getfield        aukn.a:I
        //  1235: invokestatic    android/opengl/GLES20.glBindFramebuffer:(II)V
        //  1238: aload_2        
        //  1239: astore_3       
        //  1240: aload_2        
        //  1241: astore_1       
        //  1242: ldc_w           36160
        //  1245: ldc_w           36064
        //  1248: sipush          3553
        //  1251: aload           19
        //  1253: checkcast       Laukh;
        //  1256: getfield        aukh.v:Laukn;
        //  1259: getfield        aukn.b:I
        //  1262: iconst_0       
        //  1263: invokestatic    android/opengl/GLES20.glFramebufferTexture2D:(IIIII)V
        //  1266: aload_2        
        //  1267: astore_3       
        //  1268: aload_2        
        //  1269: astore_1       
        //  1270: fconst_0       
        //  1271: fconst_0       
        //  1272: fconst_0       
        //  1273: fconst_0       
        //  1274: invokestatic    android/opengl/GLES20.glClearColor:(FFFF)V
        //  1277: aload_2        
        //  1278: astore_3       
        //  1279: aload_2        
        //  1280: astore_1       
        //  1281: sipush          16384
        //  1284: invokestatic    android/opengl/GLES20.glClear:(I)V
        //  1287: aload_2        
        //  1288: astore_3       
        //  1289: aload_2        
        //  1290: astore_1       
        //  1291: aload           19
        //  1293: checkcast       Laukh;
        //  1296: getfield        aukh.h:Lault;
        //  1299: astore          23
        //  1301: aload_2        
        //  1302: astore_3       
        //  1303: aload_2        
        //  1304: astore_1       
        //  1305: aload           17
        //  1307: getfield        aukf.c:Ljava/lang/Object;
        //  1310: astore          18
        //  1312: aload_2        
        //  1313: astore_3       
        //  1314: aload_2        
        //  1315: astore_1       
        //  1316: aload           23
        //  1318: aload_2        
        //  1319: aconst_null    
        //  1320: aload           19
        //  1322: checkcast       Laukh;
        //  1325: getfield        aukh.j:Landroid/graphics/Matrix;
        //  1328: iload           15
        //  1330: iload           14
        //  1332: invokevirtual   ault.b:(Lorg/webrtc/VideoFrame;Laulb;Landroid/graphics/Matrix;II)V
        //  1335: aload_2        
        //  1336: astore_3       
        //  1337: aload_2        
        //  1338: astore_1       
        //  1339: iload           15
        //  1341: iload           14
        //  1343: imul           
        //  1344: iconst_4       
        //  1345: imul           
        //  1346: invokestatic    java/nio/ByteBuffer.allocateDirect:(I)Ljava/nio/ByteBuffer;
        //  1349: astore          18
        //  1351: aload_2        
        //  1352: astore_3       
        //  1353: aload_2        
        //  1354: astore_1       
        //  1355: iconst_0       
        //  1356: iconst_0       
        //  1357: iload           15
        //  1359: iload           14
        //  1361: invokestatic    android/opengl/GLES20.glViewport:(IIII)V
        //  1364: aload_2        
        //  1365: astore_3       
        //  1366: aload_2        
        //  1367: astore_1       
        //  1368: iconst_0       
        //  1369: iconst_0       
        //  1370: iload           15
        //  1372: iload           14
        //  1374: sipush          6408
        //  1377: sipush          5121
        //  1380: aload           18
        //  1382: invokestatic    android/opengl/GLES20.glReadPixels:(IIIIIILjava/nio/Buffer;)V
        //  1385: aload_2        
        //  1386: astore_3       
        //  1387: aload_2        
        //  1388: astore_1       
        //  1389: ldc_w           36160
        //  1392: iconst_0       
        //  1393: invokestatic    android/opengl/GLES20.glBindFramebuffer:(II)V
        //  1396: aload_2        
        //  1397: astore_3       
        //  1398: aload_2        
        //  1399: astore_1       
        //  1400: ldc_w           "EglRenderer.notifyCallbacks"
        //  1403: invokestatic    aulo.i:(Ljava/lang/String;)V
        //  1406: aload_2        
        //  1407: astore_3       
        //  1408: aload_2        
        //  1409: astore_1       
        //  1410: iload           15
        //  1412: iload           14
        //  1414: getstatic       android/graphics/Bitmap$Config.ARGB_8888:Landroid/graphics/Bitmap$Config;
        //  1417: invokestatic    android/graphics/Bitmap.createBitmap:(IILandroid/graphics/Bitmap$Config;)Landroid/graphics/Bitmap;
        //  1420: aload           18
        //  1422: invokevirtual   android/graphics/Bitmap.copyPixelsFromBuffer:(Ljava/nio/Buffer;)V
        //  1425: aload_2        
        //  1426: astore_3       
        //  1427: aload_2        
        //  1428: astore_1       
        //  1429: aload           17
        //  1431: getfield        aukf.b:Ljava/lang/Object;
        //  1434: astore          17
        //  1436: aload_2        
        //  1437: astore_3       
        //  1438: aload_2        
        //  1439: astore_1       
        //  1440: aconst_null    
        //  1441: athrow         
        //  1442: aload_2        
        //  1443: astore_3       
        //  1444: aload_2        
        //  1445: astore_1       
        //  1446: aload           17
        //  1448: getfield        aukf.b:Ljava/lang/Object;
        //  1451: astore          17
        //  1453: aload_2        
        //  1454: astore_3       
        //  1455: aload_2        
        //  1456: astore_1       
        //  1457: aconst_null    
        //  1458: athrow         
        //  1459: aload_2        
        //  1460: invokevirtual   org/webrtc/VideoFrame.release:()V
        //  1463: return         
        //  1464: astore_2       
        //  1465: aload_1        
        //  1466: astore_3       
        //  1467: aload           17
        //  1469: monitorexit    
        //  1470: aload_1        
        //  1471: astore_3       
        //  1472: aload_2        
        //  1473: athrow         
        //  1474: astore_2       
        //  1475: goto            1491
        //  1478: astore_2       
        //  1479: aload_3        
        //  1480: astore_1       
        //  1481: goto            1465
        //  1484: astore_2       
        //  1485: goto            1575
        //  1488: astore_2       
        //  1489: aload_1        
        //  1490: astore_3       
        //  1491: aload_3        
        //  1492: astore_1       
        //  1493: ldc_w           "EglRenderer"
        //  1496: aload           19
        //  1498: checkcast       Laukh;
        //  1501: getfield        aukh.a:Ljava/lang/String;
        //  1504: invokestatic    java/lang/String.valueOf:(Ljava/lang/Object;)Ljava/lang/String;
        //  1507: ldc_w           "Error while drawing frame"
        //  1510: invokevirtual   java/lang/String.concat:(Ljava/lang/String;)Ljava/lang/String;
        //  1513: aload_2        
        //  1514: invokestatic    org/webrtc/Logging.c:(Ljava/lang/String;Ljava/lang/String;Ljava/lang/Throwable;)V
        //  1517: aload_3        
        //  1518: astore_1       
        //  1519: aload           19
        //  1521: checkcast       Laukh;
        //  1524: getfield        aukh.e:Lauke;
        //  1527: astore_2       
        //  1528: aload_3        
        //  1529: astore_1       
        //  1530: aload           19
        //  1532: checkcast       Laukh;
        //  1535: getfield        aukh.i:Laulb;
        //  1538: invokeinterface aulb.c:()V
        //  1543: aload_3        
        //  1544: astore_1       
        //  1545: aload           19
        //  1547: checkcast       Laukh;
        //  1550: getfield        aukh.h:Lault;
        //  1553: invokevirtual   ault.a:()V
        //  1556: aload_3        
        //  1557: astore_1       
        //  1558: aload           19
        //  1560: checkcast       Laukh;
        //  1563: getfield        aukh.v:Laukn;
        //  1566: invokevirtual   aukn.a:()V
        //  1569: aload_3        
        //  1570: invokevirtual   org/webrtc/VideoFrame.release:()V
        //  1573: return         
        //  1574: astore_2       
        //  1575: aload_1        
        //  1576: invokevirtual   org/webrtc/VideoFrame.release:()V
        //  1579: aload_2        
        //  1580: athrow         
        //  1581: astore_1       
        //  1582: aload_3        
        //  1583: monitorexit    
        //  1584: aload_1        
        //  1585: athrow         
        //  1586: astore_1       
        //  1587: aload_3        
        //  1588: monitorexit    
        //  1589: aload_1        
        //  1590: athrow         
        //  1591: aload_2        
        //  1592: ldc_w           "Dropping frame - No surface"
        //  1595: invokevirtual   aukh.b:(Ljava/lang/String;)V
        //  1598: aload_1        
        //  1599: invokevirtual   org/webrtc/VideoFrame.release:()V
        //  1602: return         
        //  1603: astore_1       
        //  1604: aload_3        
        //  1605: monitorexit    
        //  1606: aload_1        
        //  1607: athrow         
        //  1608: aload_0        
        //  1609: getfield        auct.a:Ljava/lang/Object;
        //  1612: checkcast       Laudj;
        //  1615: getfield        audj.c:Ljava/util/ArrayDeque;
        //  1618: astore_2       
        //  1619: aload_2        
        //  1620: monitorenter   
        //  1621: aload_0        
        //  1622: getfield        auct.a:Ljava/lang/Object;
        //  1625: astore_1       
        //  1626: aload_1        
        //  1627: checkcast       Laudj;
        //  1630: getfield        audj.d:Z
        //  1633: ifeq            1639
        //  1636: aload_2        
        //  1637: monitorexit    
        //  1638: return         
        //  1639: aload_1        
        //  1640: checkcast       Laudj;
        //  1643: getfield        audj.c:Ljava/util/ArrayDeque;
        //  1646: invokevirtual   java/util/ArrayDeque.pollFirst:()Ljava/lang/Object;
        //  1649: checkcast       Ljava/lang/Runnable;
        //  1652: astore_1       
        //  1653: aload_0        
        //  1654: getfield        auct.a:Ljava/lang/Object;
        //  1657: astore_3       
        //  1658: aload_1        
        //  1659: ifnull          1668
        //  1662: iconst_1       
        //  1663: istore          24
        //  1665: goto            1671
        //  1668: iconst_0       
        //  1669: istore          24
        //  1671: aload_3        
        //  1672: checkcast       Laudj;
        //  1675: iload           24
        //  1677: putfield        audj.d:Z
        //  1680: aload_2        
        //  1681: monitorexit    
        //  1682: aload_1        
        //  1683: ifnull          1814
        //  1686: aload_1        
        //  1687: invokeinterface java/lang/Runnable.run:()V
        //  1692: aload_0        
        //  1693: getfield        auct.a:Ljava/lang/Object;
        //  1696: checkcast       Laudj;
        //  1699: getfield        audj.c:Ljava/util/ArrayDeque;
        //  1702: astore_2       
        //  1703: aload_2        
        //  1704: monitorenter   
        //  1705: aload_0        
        //  1706: getfield        auct.a:Ljava/lang/Object;
        //  1709: checkcast       Laudj;
        //  1712: getfield        audj.c:Ljava/util/ArrayDeque;
        //  1715: invokevirtual   java/util/ArrayDeque.pollFirst:()Ljava/lang/Object;
        //  1718: checkcast       Ljava/lang/Runnable;
        //  1721: astore_1       
        //  1722: aload_0        
        //  1723: getfield        auct.a:Ljava/lang/Object;
        //  1726: astore_3       
        //  1727: aload_1        
        //  1728: ifnull          1737
        //  1731: iconst_1       
        //  1732: istore          24
        //  1734: goto            1740
        //  1737: iconst_0       
        //  1738: istore          24
        //  1740: aload_3        
        //  1741: checkcast       Laudj;
        //  1744: iload           24
        //  1746: putfield        audj.d:Z
        //  1749: aload_2        
        //  1750: monitorexit    
        //  1751: goto            1682
        //  1754: astore_1       
        //  1755: aload_2        
        //  1756: monitorexit    
        //  1757: aload_1        
        //  1758: athrow         
        //  1759: astore_2       
        //  1760: aload_0        
        //  1761: getfield        auct.a:Ljava/lang/Object;
        //  1764: checkcast       Laudj;
        //  1767: getfield        audj.c:Ljava/util/ArrayDeque;
        //  1770: astore_1       
        //  1771: aload_1        
        //  1772: monitorenter   
        //  1773: aload_0        
        //  1774: getfield        auct.a:Ljava/lang/Object;
        //  1777: astore_3       
        //  1778: aload_3        
        //  1779: checkcast       Laudj;
        //  1782: iconst_0       
        //  1783: putfield        audj.d:Z
        //  1786: aload_3        
        //  1787: checkcast       Laudj;
        //  1790: getfield        audj.a:Ljava/util/concurrent/Executor;
        //  1793: aload_3        
        //  1794: checkcast       Laudj;
        //  1797: getfield        audj.b:Ljava/lang/Runnable;
        //  1800: invokeinterface java/util/concurrent/Executor.execute:(Ljava/lang/Runnable;)V
        //  1805: aload_1        
        //  1806: monitorexit    
        //  1807: aload_2        
        //  1808: athrow         
        //  1809: astore_2       
        //  1810: aload_1        
        //  1811: monitorexit    
        //  1812: aload_2        
        //  1813: athrow         
        //  1814: return         
        //  1815: astore_1       
        //  1816: aload_2        
        //  1817: monitorexit    
        //  1818: aload_1        
        //  1819: athrow         
        //  1820: aload_0        
        //  1821: getfield        auct.a:Ljava/lang/Object;
        //  1824: checkcast       Latyo;
        //  1827: getfield        atyo.a:Ljava/lang/Object;
        //  1830: checkcast       Laudk;
        //  1833: astore_2       
        //  1834: aload_2        
        //  1835: getfield        audk.b:Laudi;
        //  1838: astore_1       
        //  1839: aload_1        
        //  1840: new             Laudh;
        //  1843: dup            
        //  1844: aload_1        
        //  1845: aload_2        
        //  1846: getfield        audk.o:Laudw;
        //  1849: aload_2        
        //  1850: getfield        audk.p:Ljava/lang/String;
        //  1853: iconst_1       
        //  1854: invokespecial   audh.<init>:(Laudi;Lorg/chromium/net/UrlResponseInfo;Ljava/lang/String;I)V
        //  1857: invokevirtual   audi.a:(Laudl;)V
        //  1860: return         
        //  1861: aload_0        
        //  1862: getfield        auct.a:Ljava/lang/Object;
        //  1865: checkcast       Laudk;
        //  1868: astore_1       
        //  1869: aload_1        
        //  1870: aload_1        
        //  1871: getfield        audk.p:Ljava/lang/String;
        //  1874: putfield        audk.m:Ljava/lang/String;
        //  1877: aload_1        
        //  1878: aconst_null    
        //  1879: putfield        audk.p:Ljava/lang/String;
        //  1882: aload_1        
        //  1883: invokevirtual   audk.n:()V
        //  1886: return         
        //  1887: aload_0        
        //  1888: getfield        auct.a:Ljava/lang/Object;
        //  1891: checkcast       Laudk;
        //  1894: astore_1       
        //  1895: aload_1        
        //  1896: getfield        audk.f:Ljava/util/List;
        //  1899: aload_1        
        //  1900: getfield        audk.m:Ljava/lang/String;
        //  1903: invokeinterface java/util/List.add:(Ljava/lang/Object;)Z
        //  1908: pop            
        //  1909: aload_0        
        //  1910: getfield        auct.a:Ljava/lang/Object;
        //  1913: checkcast       Laudk;
        //  1916: invokevirtual   audk.n:()V
        //  1919: return         
        //  1920: aload_0        
        //  1921: getfield        auct.a:Ljava/lang/Object;
        //  1924: checkcast       Laudk;
        //  1927: getfield        audk.n:Ljava/nio/channels/ReadableByteChannel;
        //  1930: astore_1       
        //  1931: aload_1        
        //  1932: ifnull          1960
        //  1935: aload_1        
        //  1936: invokeinterface java/nio/channels/ReadableByteChannel.close:()V
        //  1941: goto            1949
        //  1944: astore_1       
        //  1945: aload_1        
        //  1946: invokevirtual   java/io/IOException.printStackTrace:()V
        //  1949: aload_0        
        //  1950: getfield        auct.a:Ljava/lang/Object;
        //  1953: checkcast       Laudk;
        //  1956: aconst_null    
        //  1957: putfield        audk.n:Ljava/nio/channels/ReadableByteChannel;
        //  1960: return         
        //  1961: aload_0        
        //  1962: getfield        auct.a:Ljava/lang/Object;
        //  1965: checkcast       Laudk;
        //  1968: getfield        audk.t:Laude;
        //  1971: astore_1       
        //  1972: aload_1        
        //  1973: ifnull          1995
        //  1976: aload_1        
        //  1977: invokevirtual   aude.d:()V
        //  1980: goto            1995
        //  1983: astore_1       
        //  1984: getstatic       audk.a:Ljava/lang/String;
        //  1987: ldc_w           "Exception when closing OutputChannel"
        //  1990: aload_1        
        //  1991: invokestatic    android/util/Log.e:(Ljava/lang/String;Ljava/lang/String;Ljava/lang/Throwable;)I
        //  1994: pop            
        //  1995: aload_0        
        //  1996: getfield        auct.a:Ljava/lang/Object;
        //  1999: checkcast       Laudk;
        //  2002: getfield        audk.q:Ljava/net/HttpURLConnection;
        //  2005: astore_1       
        //  2006: aload_1        
        //  2007: ifnull          2025
        //  2010: aload_1        
        //  2011: invokevirtual   java/net/HttpURLConnection.disconnect:()V
        //  2014: aload_0        
        //  2015: getfield        auct.a:Ljava/lang/Object;
        //  2018: checkcast       Laudk;
        //  2021: aconst_null    
        //  2022: putfield        audk.q:Ljava/net/HttpURLConnection;
        //  2025: return         
        //  2026: invokestatic    org/chromium/net/impl/CronetLibraryLoader.b:()V
        //  2029: aload_0        
        //  2030: getfield        auct.a:Ljava/lang/Object;
        //  2033: checkcast       Lorg/chromium/net/impl/CronetUrlRequestContext;
        //  2036: getfield        org/chromium/net/impl/CronetUrlRequestContext.c:Ljava/lang/Object;
        //  2039: astore_1       
        //  2040: aload_1        
        //  2041: monitorenter   
        //  2042: aload_0        
        //  2043: getfield        auct.a:Ljava/lang/Object;
        //  2046: astore_2       
        //  2047: aload_2        
        //  2048: checkcast       Lorg/chromium/net/impl/CronetUrlRequestContext;
        //  2051: getfield        org/chromium/net/impl/CronetUrlRequestContext.d:J
        //  2054: aload_2        
        //  2055: invokestatic    J/N.M6Dz0nZ5:(JLjava/lang/Object;)V
        //  2058: aload_1        
        //  2059: monitorexit    
        //  2060: return         
        //  2061: astore_2       
        //  2062: aload_1        
        //  2063: monitorexit    
        //  2064: aload_2        
        //  2065: athrow         
        //  2066: aload_0        
        //  2067: getfield        auct.a:Ljava/lang/Object;
        //  2070: astore_2       
        //  2071: aload_2        
        //  2072: checkcast       Lorg/chromium/net/impl/CronetUrlRequest;
        //  2075: getfield        org/chromium/net/impl/CronetUrlRequest.d:Lauee;
        //  2078: astore_3       
        //  2079: aload_2        
        //  2080: checkcast       Lorg/chromium/net/impl/CronetUrlRequest;
        //  2083: getfield        org/chromium/net/impl/CronetUrlRequest.g:Laudw;
        //  2086: astore_1       
        //  2087: aload_2        
        //  2088: checkcast       Lorg/chromium/net/impl/CronetUrlRequest;
        //  2091: getfield        org/chromium/net/impl/CronetUrlRequest.h:Lorg/chromium/net/CronetException;
        //  2094: astore          19
        //  2096: aload_3        
        //  2097: aload_2        
        //  2098: checkcast       Lorg/chromium/net/UrlRequest;
        //  2101: aload_1        
        //  2102: aload           19
        //  2104: invokevirtual   auee.onFailed:(Lorg/chromium/net/UrlRequest;Lorg/chromium/net/UrlResponseInfo;Lorg/chromium/net/CronetException;)V
        //  2107: aload_0        
        //  2108: getfield        auct.a:Ljava/lang/Object;
        //  2111: checkcast       Lorg/chromium/net/impl/CronetUrlRequest;
        //  2114: invokevirtual   org/chromium/net/impl/CronetUrlRequest.d:()V
        //  2117: return         
        //  2118: astore_1       
        //  2119: ldc_w           "cr_"
        //  2122: getstatic       org/chromium/net/impl/CronetUrlRequestContext.b:Ljava/lang/String;
        //  2125: invokestatic    java/lang/String.valueOf:(Ljava/lang/Object;)Ljava/lang/String;
        //  2128: invokevirtual   java/lang/String.concat:(Ljava/lang/String;)Ljava/lang/String;
        //  2131: ldc_w           "Exception in onFailed method"
        //  2134: aload_1        
        //  2135: invokestatic    android/util/Log.e:(Ljava/lang/String;Ljava/lang/String;Ljava/lang/Throwable;)I
        //  2138: pop            
        //  2139: return         
        //  2140: aload_0        
        //  2141: getfield        auct.a:Ljava/lang/Object;
        //  2144: astore_3       
        //  2145: aload_3        
        //  2146: checkcast       Lorg/chromium/net/impl/CronetUrlRequest;
        //  2149: getfield        org/chromium/net/impl/CronetUrlRequest.d:Lauee;
        //  2152: astore_1       
        //  2153: aload_3        
        //  2154: checkcast       Lorg/chromium/net/impl/CronetUrlRequest;
        //  2157: getfield        org/chromium/net/impl/CronetUrlRequest.g:Laudw;
        //  2160: astore_2       
        //  2161: aload_1        
        //  2162: aload_3        
        //  2163: checkcast       Lorg/chromium/net/UrlRequest;
        //  2166: aload_2        
        //  2167: invokevirtual   org/chromium/net/UrlRequest$Callback.onCanceled:(Lorg/chromium/net/UrlRequest;Lorg/chromium/net/UrlResponseInfo;)V
        //  2170: aload_0        
        //  2171: getfield        auct.a:Ljava/lang/Object;
        //  2174: checkcast       Lorg/chromium/net/impl/CronetUrlRequest;
        //  2177: invokevirtual   org/chromium/net/impl/CronetUrlRequest.d:()V
        //  2180: return         
        //  2181: astore_1       
        //  2182: ldc_w           "cr_"
        //  2185: getstatic       org/chromium/net/impl/CronetUrlRequestContext.b:Ljava/lang/String;
        //  2188: invokestatic    java/lang/String.valueOf:(Ljava/lang/Object;)Ljava/lang/String;
        //  2191: invokevirtual   java/lang/String.concat:(Ljava/lang/String;)Ljava/lang/String;
        //  2194: ldc_w           "Exception in onCanceled method"
        //  2197: aload_1        
        //  2198: invokestatic    android/util/Log.e:(Ljava/lang/String;Ljava/lang/String;Ljava/lang/Throwable;)I
        //  2201: pop            
        //  2202: return         
        //  2203: aload_0        
        //  2204: getfield        auct.a:Ljava/lang/Object;
        //  2207: checkcast       Lorg/chromium/net/impl/CronetUrlRequest;
        //  2210: getfield        org/chromium/net/impl/CronetUrlRequest.c:Ljava/lang/Object;
        //  2213: astore_1       
        //  2214: aload_1        
        //  2215: monitorenter   
        //  2216: aload_0        
        //  2217: getfield        auct.a:Ljava/lang/Object;
        //  2220: astore_2       
        //  2221: aload_2        
        //  2222: checkcast       Lorg/chromium/net/impl/CronetUrlRequest;
        //  2225: invokevirtual   org/chromium/net/impl/CronetUrlRequest.j:()Z
        //  2228: ifeq            2234
        //  2231: aload_1        
        //  2232: monitorexit    
        //  2233: return         
        //  2234: aload_2        
        //  2235: checkcast       Lorg/chromium/net/impl/CronetUrlRequest;
        //  2238: iconst_0       
        //  2239: invokevirtual   org/chromium/net/impl/CronetUrlRequest.c:(I)V
        //  2242: aload_1        
        //  2243: monitorexit    
        //  2244: aload_0        
        //  2245: getfield        auct.a:Ljava/lang/Object;
        //  2248: astore_2       
        //  2249: aload_2        
        //  2250: checkcast       Lorg/chromium/net/impl/CronetUrlRequest;
        //  2253: getfield        org/chromium/net/impl/CronetUrlRequest.d:Lauee;
        //  2256: astore_1       
        //  2257: aload_2        
        //  2258: checkcast       Lorg/chromium/net/impl/CronetUrlRequest;
        //  2261: getfield        org/chromium/net/impl/CronetUrlRequest.g:Laudw;
        //  2264: astore_3       
        //  2265: aload_1        
        //  2266: aload_2        
        //  2267: checkcast       Lorg/chromium/net/UrlRequest;
        //  2270: aload_3        
        //  2271: invokevirtual   auee.onSucceeded:(Lorg/chromium/net/UrlRequest;Lorg/chromium/net/UrlResponseInfo;)V
        //  2274: aload_0        
        //  2275: getfield        auct.a:Ljava/lang/Object;
        //  2278: checkcast       Lorg/chromium/net/impl/CronetUrlRequest;
        //  2281: invokevirtual   org/chromium/net/impl/CronetUrlRequest.d:()V
        //  2284: return         
        //  2285: astore_1       
        //  2286: ldc_w           "cr_"
        //  2289: getstatic       org/chromium/net/impl/CronetUrlRequestContext.b:Ljava/lang/String;
        //  2292: invokestatic    java/lang/String.valueOf:(Ljava/lang/Object;)Ljava/lang/String;
        //  2295: invokevirtual   java/lang/String.concat:(Ljava/lang/String;)Ljava/lang/String;
        //  2298: ldc_w           "Exception in onSucceeded method"
        //  2301: aload_1        
        //  2302: invokestatic    android/util/Log.e:(Ljava/lang/String;Ljava/lang/String;Ljava/lang/Throwable;)I
        //  2305: pop            
        //  2306: return         
        //  2307: astore_2       
        //  2308: aload_1        
        //  2309: monitorexit    
        //  2310: aload_2        
        //  2311: athrow         
        //  2312: aload_0        
        //  2313: getfield        auct.a:Ljava/lang/Object;
        //  2316: checkcast       Lorg/chromium/net/impl/CronetUrlRequest;
        //  2319: invokevirtual   org/chromium/net/impl/CronetUrlRequest.b:()V
        //  2322: aload_0        
        //  2323: getfield        auct.a:Ljava/lang/Object;
        //  2326: checkcast       Lorg/chromium/net/impl/CronetUrlRequest;
        //  2329: getfield        org/chromium/net/impl/CronetUrlRequest.c:Ljava/lang/Object;
        //  2332: astore_1       
        //  2333: aload_1        
        //  2334: monitorenter   
        //  2335: aload_0        
        //  2336: getfield        auct.a:Ljava/lang/Object;
        //  2339: astore_2       
        //  2340: aload_2        
        //  2341: checkcast       Lorg/chromium/net/impl/CronetUrlRequest;
        //  2344: invokevirtual   org/chromium/net/impl/CronetUrlRequest.j:()Z
        //  2347: ifeq            2353
        //  2350: aload_1        
        //  2351: monitorexit    
        //  2352: return         
        //  2353: aload_2        
        //  2354: checkcast       Lorg/chromium/net/impl/CronetUrlRequest;
        //  2357: invokestatic    org/chromium/net/impl/CronetUrlRequest.k:(Lorg/chromium/net/impl/CronetUrlRequest;)V
        //  2360: aload_1        
        //  2361: monitorexit    
        //  2362: aload_0        
        //  2363: getfield        auct.a:Ljava/lang/Object;
        //  2366: astore_3       
        //  2367: aload_3        
        //  2368: checkcast       Lorg/chromium/net/impl/CronetUrlRequest;
        //  2371: getfield        org/chromium/net/impl/CronetUrlRequest.d:Lauee;
        //  2374: astore_2       
        //  2375: aload_3        
        //  2376: checkcast       Lorg/chromium/net/impl/CronetUrlRequest;
        //  2379: getfield        org/chromium/net/impl/CronetUrlRequest.g:Laudw;
        //  2382: astore_1       
        //  2383: aload_2        
        //  2384: aload_3        
        //  2385: checkcast       Lorg/chromium/net/UrlRequest;
        //  2388: aload_1        
        //  2389: invokevirtual   auee.onResponseStarted:(Lorg/chromium/net/UrlRequest;Lorg/chromium/net/UrlResponseInfo;)V
        //  2392: return         
        //  2393: astore_1       
        //  2394: aload_0        
        //  2395: getfield        auct.a:Ljava/lang/Object;
        //  2398: checkcast       Lorg/chromium/net/impl/CronetUrlRequest;
        //  2401: aload_1        
        //  2402: invokevirtual   org/chromium/net/impl/CronetUrlRequest.e:(Ljava/lang/Exception;)V
        //  2405: return         
        //  2406: astore_2       
        //  2407: aload_1        
        //  2408: monitorexit    
        //  2409: aload_2        
        //  2410: athrow         
        //  2411: aload_0        
        //  2412: getfield        auct.a:Ljava/lang/Object;
        //  2415: checkcast       Lorg/chromium/net/impl/VersionSafeCallbacks$UrlRequestStatusListener;
        //  2418: iconst_m1      
        //  2419: invokevirtual   org/chromium/net/impl/VersionSafeCallbacks$UrlRequestStatusListener.onStatus:(I)V
        //  2422: return         
        //  2423: aload_0        
        //  2424: getfield        auct.a:Ljava/lang/Object;
        //  2427: checkcast       Lorg/chromium/net/impl/CronetUrlRequest;
        //  2430: getfield        org/chromium/net/impl/CronetUrlRequest.f:Lorg/chromium/net/impl/CronetUploadDataStream;
        //  2433: astore_1       
        //  2434: aload_1        
        //  2435: getfield        org/chromium/net/impl/CronetUploadDataStream.g:Ljava/lang/Object;
        //  2438: astore_2       
        //  2439: aload_2        
        //  2440: monitorenter   
        //  2441: aload_1        
        //  2442: iconst_2       
        //  2443: putfield        org/chromium/net/impl/CronetUploadDataStream.i:I
        //  2446: aload_2        
        //  2447: monitorexit    
        //  2448: aload_1        
        //  2449: getfield        org/chromium/net/impl/CronetUploadDataStream.c:Lorg/chromium/net/impl/CronetUrlRequest;
        //  2452: invokevirtual   org/chromium/net/impl/CronetUrlRequest.b:()V
        //  2455: aload_1        
        //  2456: getfield        org/chromium/net/impl/CronetUploadDataStream.b:Laued;
        //  2459: invokevirtual   aued.getLength:()J
        //  2462: lstore          4
        //  2464: aload_1        
        //  2465: lload           4
        //  2467: putfield        org/chromium/net/impl/CronetUploadDataStream.d:J
        //  2470: aload_1        
        //  2471: lload           4
        //  2473: putfield        org/chromium/net/impl/CronetUploadDataStream.e:J
        //  2476: goto            2485
        //  2479: astore_2       
        //  2480: aload_1        
        //  2481: aload_2        
        //  2482: invokevirtual   org/chromium/net/impl/CronetUploadDataStream.b:(Ljava/lang/Throwable;)V
        //  2485: aload_1        
        //  2486: getfield        org/chromium/net/impl/CronetUploadDataStream.g:Ljava/lang/Object;
        //  2489: astore_2       
        //  2490: aload_2        
        //  2491: monitorenter   
        //  2492: aload_1        
        //  2493: iconst_3       
        //  2494: putfield        org/chromium/net/impl/CronetUploadDataStream.i:I
        //  2497: aload_2        
        //  2498: monitorexit    
        //  2499: aload_0        
        //  2500: getfield        auct.a:Ljava/lang/Object;
        //  2503: checkcast       Lorg/chromium/net/impl/CronetUrlRequest;
        //  2506: getfield        org/chromium/net/impl/CronetUrlRequest.c:Ljava/lang/Object;
        //  2509: astore_1       
        //  2510: aload_1        
        //  2511: monitorenter   
        //  2512: aload_0        
        //  2513: getfield        auct.a:Ljava/lang/Object;
        //  2516: astore_2       
        //  2517: aload_2        
        //  2518: checkcast       Lorg/chromium/net/impl/CronetUrlRequest;
        //  2521: invokevirtual   org/chromium/net/impl/CronetUrlRequest.j:()Z
        //  2524: ifeq            2530
        //  2527: aload_1        
        //  2528: monitorexit    
        //  2529: return         
        //  2530: aload_2        
        //  2531: checkcast       Lorg/chromium/net/impl/CronetUrlRequest;
        //  2534: getfield        org/chromium/net/impl/CronetUrlRequest.f:Lorg/chromium/net/impl/CronetUploadDataStream;
        //  2537: astore_3       
        //  2538: aload_2        
        //  2539: checkcast       Lorg/chromium/net/impl/CronetUrlRequest;
        //  2542: getfield        org/chromium/net/impl/CronetUrlRequest.a:J
        //  2545: lstore          4
        //  2547: aload_3        
        //  2548: getfield        org/chromium/net/impl/CronetUploadDataStream.g:Ljava/lang/Object;
        //  2551: astore_2       
        //  2552: aload_2        
        //  2553: monitorenter   
        //  2554: aload_3        
        //  2555: aload_3        
        //  2556: lload           4
        //  2558: aload_3        
        //  2559: getfield        org/chromium/net/impl/CronetUploadDataStream.d:J
        //  2562: invokestatic    J/N.MA4X1aZa:(Ljava/lang/Object;JJ)J
        //  2565: putfield        org/chromium/net/impl/CronetUploadDataStream.h:J
        //  2568: aload_2        
        //  2569: monitorexit    
        //  2570: aload_0        
        //  2571: getfield        auct.a:Ljava/lang/Object;
        //  2574: checkcast       Lorg/chromium/net/impl/CronetUrlRequest;
        //  2577: invokevirtual   org/chromium/net/impl/CronetUrlRequest.i:()V
        //  2580: aload_1        
        //  2581: monitorexit    
        //  2582: return         
        //  2583: astore_3       
        //  2584: aload_2        
        //  2585: monitorexit    
        //  2586: aload_3        
        //  2587: athrow         
        //  2588: astore_2       
        //  2589: aload_1        
        //  2590: monitorexit    
        //  2591: aload_2        
        //  2592: athrow         
        //  2593: astore_1       
        //  2594: aload_2        
        //  2595: monitorexit    
        //  2596: aload_1        
        //  2597: athrow         
        //  2598: astore_1       
        //  2599: aload_2        
        //  2600: monitorexit    
        //  2601: aload_1        
        //  2602: athrow         
        //  2603: aload_0        
        //  2604: getfield        auct.a:Ljava/lang/Object;
        //  2607: checkcast       Lorg/chromium/net/impl/CronetUploadDataStream;
        //  2610: getfield        org/chromium/net/impl/CronetUploadDataStream.g:Ljava/lang/Object;
        //  2613: astore_1       
        //  2614: aload_1        
        //  2615: monitorenter   
        //  2616: aload_0        
        //  2617: getfield        auct.a:Ljava/lang/Object;
        //  2620: astore_2       
        //  2621: aload_2        
        //  2622: checkcast       Lorg/chromium/net/impl/CronetUploadDataStream;
        //  2625: getfield        org/chromium/net/impl/CronetUploadDataStream.h:J
        //  2628: lconst_0       
        //  2629: lcmp           
        //  2630: ifne            2636
        //  2633: aload_1        
        //  2634: monitorexit    
        //  2635: return         
        //  2636: aload_2        
        //  2637: checkcast       Lorg/chromium/net/impl/CronetUploadDataStream;
        //  2640: invokestatic    org/chromium/net/impl/CronetUploadDataStream.d:(Lorg/chromium/net/impl/CronetUploadDataStream;)V
        //  2643: aload_0        
        //  2644: getfield        auct.a:Ljava/lang/Object;
        //  2647: checkcast       Lorg/chromium/net/impl/CronetUploadDataStream;
        //  2650: iconst_1       
        //  2651: putfield        org/chromium/net/impl/CronetUploadDataStream.i:I
        //  2654: aload_1        
        //  2655: monitorexit    
        //  2656: aload_0        
        //  2657: getfield        auct.a:Ljava/lang/Object;
        //  2660: checkcast       Lorg/chromium/net/impl/CronetUploadDataStream;
        //  2663: invokevirtual   org/chromium/net/impl/CronetUploadDataStream.a:()V
        //  2666: aload_0        
        //  2667: getfield        auct.a:Ljava/lang/Object;
        //  2670: astore_1       
        //  2671: aload_1        
        //  2672: checkcast       Lorg/chromium/net/impl/CronetUploadDataStream;
        //  2675: getfield        org/chromium/net/impl/CronetUploadDataStream.b:Laued;
        //  2678: aload_1        
        //  2679: checkcast       Lorg/chromium/net/UploadDataSink;
        //  2682: invokevirtual   aued.rewind:(Lorg/chromium/net/UploadDataSink;)V
        //  2685: return         
        //  2686: astore_1       
        //  2687: aload_0        
        //  2688: getfield        auct.a:Ljava/lang/Object;
        //  2691: checkcast       Lorg/chromium/net/impl/CronetUploadDataStream;
        //  2694: aload_1        
        //  2695: invokevirtual   org/chromium/net/impl/CronetUploadDataStream.b:(Ljava/lang/Throwable;)V
        //  2698: return         
        //  2699: astore_2       
        //  2700: aload_1        
        //  2701: monitorexit    
        //  2702: aload_2        
        //  2703: athrow         
        //  2704: aload_0        
        //  2705: getfield        auct.a:Ljava/lang/Object;
        //  2708: checkcast       Lorg/chromium/net/impl/CronetUploadDataStream;
        //  2711: invokevirtual   org/chromium/net/impl/CronetUploadDataStream.a:()V
        //  2714: aload_0        
        //  2715: getfield        auct.a:Ljava/lang/Object;
        //  2718: checkcast       Lorg/chromium/net/impl/CronetUploadDataStream;
        //  2721: getfield        org/chromium/net/impl/CronetUploadDataStream.b:Laued;
        //  2724: invokevirtual   org/chromium/net/UploadDataProvider.close:()V
        //  2727: return         
        //  2728: astore_1       
        //  2729: ldc_w           "cr_"
        //  2732: getstatic       org/chromium/net/impl/CronetUploadDataStream.a:Ljava/lang/String;
        //  2735: invokestatic    java/lang/String.valueOf:(Ljava/lang/Object;)Ljava/lang/String;
        //  2738: invokevirtual   java/lang/String.concat:(Ljava/lang/String;)Ljava/lang/String;
        //  2741: ldc_w           "Exception thrown when closing"
        //  2744: aload_1        
        //  2745: invokestatic    android/util/Log.e:(Ljava/lang/String;Ljava/lang/String;Ljava/lang/Throwable;)I
        //  2748: pop            
        //  2749: return         
        //  2750: astore_3       
        //  2751: goto            1805
        //    Exceptions:
        //  Try           Handler
        //  Start  End    Start  End    Type                                             
        //  -----  -----  -----  -----  -------------------------------------------------
        //  145    158    159    164    Any
        //  160    162    159    164    Any
        //  194    203    550    551    Any
        //  217    460    546    550    Any
        //  463    465    546    550    Any
        //  478    491    541    546    Any
        //  495    538    541    546    Any
        //  538    540    541    546    Any
        //  542    544    541    546    Any
        //  551    553    550    551    Any
        //  574    583    1603   1608   Any
        //  587    589    1603   1608   Any
        //  590    601    1603   1608   Any
        //  629    631    1586   1591   Any
        //  656    666    1581   1586   Any
        //  681    683    1581   1586   Any
        //  767    870    1488   1491   Lauko;
        //  767    870    1484   1488   Any
        //  870    899    1464   1465   Any
        //  903    910    1478   1484   Any
        //  912    928    1478   1484   Any
        //  930    940    1478   1484   Any
        //  942    958    1478   1484   Any
        //  960    963    1478   1484   Any
        //  967    981    1474   1478   Lauko;
        //  967    981    1574   1575   Any
        //  988    999    1474   1478   Lauko;
        //  988    999    1574   1575   Any
        //  1003   1019   1474   1478   Lauko;
        //  1003   1019   1574   1575   Any
        //  1023   1037   1474   1478   Lauko;
        //  1023   1037   1574   1575   Any
        //  1041   1057   1474   1478   Lauko;
        //  1041   1057   1574   1575   Any
        //  1061   1077   1474   1478   Lauko;
        //  1061   1077   1574   1575   Any
        //  1081   1094   1474   1478   Lauko;
        //  1081   1094   1574   1575   Any
        //  1098   1108   1474   1478   Lauko;
        //  1098   1108   1574   1575   Any
        //  1112   1124   1474   1478   Lauko;
        //  1112   1124   1574   1575   Any
        //  1128   1135   1474   1478   Lauko;
        //  1128   1135   1574   1575   Any
        //  1139   1146   1474   1478   Lauko;
        //  1139   1146   1574   1575   Any
        //  1150   1160   1474   1478   Lauko;
        //  1150   1160   1574   1575   Any
        //  1164   1171   1474   1478   Lauko;
        //  1164   1171   1574   1575   Any
        //  1175   1185   1474   1478   Lauko;
        //  1175   1185   1574   1575   Any
        //  1202   1217   1474   1478   Lauko;
        //  1202   1217   1574   1575   Any
        //  1221   1238   1474   1478   Lauko;
        //  1221   1238   1574   1575   Any
        //  1242   1266   1474   1478   Lauko;
        //  1242   1266   1574   1575   Any
        //  1270   1277   1474   1478   Lauko;
        //  1270   1277   1574   1575   Any
        //  1281   1287   1474   1478   Lauko;
        //  1281   1287   1574   1575   Any
        //  1291   1301   1474   1478   Lauko;
        //  1291   1301   1574   1575   Any
        //  1305   1312   1474   1478   Lauko;
        //  1305   1312   1574   1575   Any
        //  1316   1335   1474   1478   Lauko;
        //  1316   1335   1574   1575   Any
        //  1339   1351   1474   1478   Lauko;
        //  1339   1351   1574   1575   Any
        //  1355   1364   1474   1478   Lauko;
        //  1355   1364   1574   1575   Any
        //  1368   1385   1474   1478   Lauko;
        //  1368   1385   1574   1575   Any
        //  1389   1396   1474   1478   Lauko;
        //  1389   1396   1574   1575   Any
        //  1400   1406   1474   1478   Lauko;
        //  1400   1406   1574   1575   Any
        //  1410   1425   1474   1478   Lauko;
        //  1410   1425   1574   1575   Any
        //  1429   1436   1474   1478   Lauko;
        //  1429   1436   1574   1575   Any
        //  1440   1442   1474   1478   Lauko;
        //  1440   1442   1574   1575   Any
        //  1446   1453   1474   1478   Lauko;
        //  1446   1453   1574   1575   Any
        //  1457   1459   1474   1478   Lauko;
        //  1457   1459   1574   1575   Any
        //  1467   1470   1478   1484   Any
        //  1472   1474   1474   1478   Lauko;
        //  1472   1474   1574   1575   Any
        //  1493   1517   1574   1575   Any
        //  1519   1528   1574   1575   Any
        //  1530   1543   1574   1575   Any
        //  1545   1556   1574   1575   Any
        //  1558   1569   1574   1575   Any
        //  1582   1584   1581   1586   Any
        //  1587   1589   1586   1591   Any
        //  1604   1606   1603   1608   Any
        //  1621   1638   1815   1820   Any
        //  1639   1658   1815   1820   Any
        //  1671   1682   1815   1820   Any
        //  1686   1692   1759   1814   Any
        //  1705   1727   1754   1759   Any
        //  1740   1751   1754   1759   Any
        //  1755   1757   1754   1759   Any
        //  1773   1786   1809   1814   Any
        //  1786   1805   2750   2754   Ljava/util/concurrent/RejectedExecutionException;
        //  1786   1805   1809   1814   Any
        //  1805   1807   1809   1814   Any
        //  1810   1812   1809   1814   Any
        //  1816   1818   1815   1820   Any
        //  1935   1941   1944   1949   Ljava/io/IOException;
        //  1976   1980   1983   1995   Ljava/io/IOException;
        //  2042   2060   2061   2066   Any
        //  2062   2064   2061   2066   Any
        //  2066   2117   2118   2140   Ljava/lang/Exception;
        //  2140   2180   2181   2203   Ljava/lang/Exception;
        //  2216   2233   2307   2312   Any
        //  2234   2244   2307   2312   Any
        //  2244   2284   2285   2307   Ljava/lang/Exception;
        //  2308   2310   2307   2312   Any
        //  2335   2352   2406   2411   Any
        //  2353   2362   2406   2411   Any
        //  2362   2392   2393   2406   Ljava/lang/Exception;
        //  2407   2409   2406   2411   Any
        //  2441   2448   2598   2603   Any
        //  2448   2476   2479   2485   Any
        //  2492   2499   2593   2598   Any
        //  2512   2529   2588   2593   Any
        //  2530   2554   2588   2593   Any
        //  2554   2570   2583   2588   Any
        //  2570   2582   2588   2593   Any
        //  2584   2586   2583   2588   Any
        //  2586   2588   2588   2593   Any
        //  2589   2591   2588   2593   Any
        //  2594   2596   2593   2598   Any
        //  2599   2601   2598   2603   Any
        //  2616   2635   2699   2704   Any
        //  2636   2656   2699   2704   Any
        //  2656   2685   2686   2699   Ljava/lang/Exception;
        //  2700   2702   2699   2704   Any
        //  2704   2727   2728   2750   Ljava/lang/Exception;
        // 
        // The error that occurred was:
        // 
        // java.lang.IllegalStateException: Expression is linked from several locations: Label_0984:
        //     at com.strobel.decompiler.ast.Error.expressionLinkedFromMultipleLocations(Error.java:27)
        //     at com.strobel.decompiler.ast.AstOptimizer.mergeDisparateObjectInitializations(AstOptimizer.java:2604)
        //     at com.strobel.decompiler.ast.AstOptimizer.optimize(AstOptimizer.java:235)
        //     at com.strobel.decompiler.ast.AstOptimizer.optimize(AstOptimizer.java:42)
        //     at com.strobel.decompiler.languages.java.ast.AstMethodBodyBuilder.createMethodBody(AstMethodBodyBuilder.java:206)
        //     at com.strobel.decompiler.languages.java.ast.AstMethodBodyBuilder.createMethodBody(AstMethodBodyBuilder.java:93)
        //     at com.strobel.decompiler.languages.java.ast.AstBuilder.createMethodBody(AstBuilder.java:868)
        //     at com.strobel.decompiler.languages.java.ast.AstBuilder.createMethod(AstBuilder.java:761)
        //     at com.strobel.decompiler.languages.java.ast.AstBuilder.addTypeMembers(AstBuilder.java:638)
        //     at com.strobel.decompiler.languages.java.ast.AstBuilder.createTypeCore(AstBuilder.java:605)
        //     at com.strobel.decompiler.languages.java.ast.AstBuilder.createTypeNoCache(AstBuilder.java:195)
        //     at com.strobel.decompiler.languages.java.ast.AstBuilder.createType(AstBuilder.java:162)
        //     at com.strobel.decompiler.languages.java.ast.AstBuilder.addType(AstBuilder.java:137)
        //     at com.strobel.decompiler.languages.java.JavaLanguage.buildAst(JavaLanguage.java:71)
        //     at com.strobel.decompiler.languages.java.JavaLanguage.decompileType(JavaLanguage.java:59)
        //     at com.strobel.decompiler.DecompilerDriver.decompileType(DecompilerDriver.java:333)
        //     at com.strobel.decompiler.DecompilerDriver.decompileJar(DecompilerDriver.java:254)
        //     at com.strobel.decompiler.DecompilerDriver.main(DecompilerDriver.java:129)
        // 
        throw new IllegalStateException("An error occurred while decompiling this method.");
    }
}
