import android.os.Message;
import java.util.Collections;
import java.util.Iterator;
import java.io.IOException;
import java.util.List;
import androidx.media3.common.Metadata;
import androidx.media3.common.Metadata$Entry;
import android.util.Pair;
import android.os.SystemClock;
import android.os.Handler;
import java.util.ArrayList;
import android.os.HandlerThread;
import java.util.Set;
import android.os.Looper;
import android.os.Handler$Callback;

// 
// Decompiled by Procyon v0.6.0
// 

public final class bez implements Handler$Callback, bnt, bqz, bfk, beb, bfn
{
    private boolean A;
    private int B;
    private boolean C;
    private boolean D;
    private boolean E;
    private int F;
    private bey G;
    private long H;
    private int I;
    private boolean J;
    private bee K;
    private long L;
    private final bdz M;
    private lzz N;
    private final aetc O;
    private final qpt P;
    public final baj a;
    public final Looper b;
    public boolean c;
    public boolean d;
    private final bfq[] e;
    private final Set f;
    private final bfr[] g;
    private final bra h;
    private final bfb i;
    private final brd j;
    private final HandlerThread k;
    private final azk l;
    private final azj m;
    private final long n;
    private final boolean o;
    private final bec p;
    private final ArrayList q;
    private final bac r;
    private final bff s;
    private final bfl t;
    private final long u;
    private bfu v;
    private bfm w;
    private boolean x;
    private boolean y;
    private boolean z;
    
    public bez(final bfq[] e, final bra h, final aetc o, final bfb i, final brd brd, int j, final bfz bfz, final bfu v, final bdz m, final long u, final boolean x, final Looper looper, final bac r, final qpt p22, final bgz bgz, final byte[] array, final byte[] array2, final byte[] array3, final byte[] array4, final byte[] array5, final byte[] array6, final byte[] array7) {
        this.P = p22;
        this.e = e;
        this.h = h;
        this.O = o;
        this.i = i;
        this.j = brd;
        this.B = j;
        j = 0;
        this.C = false;
        this.v = v;
        this.M = m;
        this.u = u;
        this.x = x;
        this.r = r;
        this.L = -9223372036854775807L;
        this.n = i.a();
        this.o = i.g();
        this.w = bfm.g(o);
        this.N = new lzz(this.w);
        this.g = new bfr[e.length];
        while (j < e.length) {
            e[j].u(j, bgz);
            this.g[j] = e[j].o();
            ++j;
        }
        this.p = new bec((beb)this);
        this.q = new ArrayList();
        this.f = aesy.r();
        this.l = new azk();
        this.m = new azj();
        h.j = this;
        h.k = brd;
        this.J = true;
        final Handler handler = new Handler(looper);
        this.s = new bff(bfz, handler);
        this.t = new bfl((bfk)this, bfz, handler, bgz);
        final HandlerThread k = new HandlerThread("ExoPlayer:Playback", -16);
        (this.k = k).start();
        final Looper looper2 = k.getLooper();
        this.b = looper2;
        this.a = r.b(looper2, (Handler$Callback)this);
    }
    
    private final void A(final long n, final long n2) {
        ((bat)this.a).b.sendEmptyMessageAtTime(2, n + n2);
    }
    
    private final void B(final boolean b) {
        final ayx i = this.s.d.f.i;
        final long t = this.T(i, this.w.o, true, false);
        if (t != this.w.o) {
            final bfm w = this.w;
            this.w = this.U(i, t, w.b, w.c, b, 5);
        }
    }
    
    private final void C(final bfp bfp) {
        if (bfp.e != this.b) {
            this.a.f(15, (Object)bfp).r();
            return;
        }
        f(bfp);
        final int d = this.w.d;
        if (d != 3 && d != 2) {
            return;
        }
        this.a.d(2);
    }
    
    private final void D(final boolean b, int i, final boolean b2, final int c) {
        this.N.b((int)(b2 ? 1 : 0));
        final lzz n = this.N;
        n.d = true;
        n.a = true;
        n.c = c;
        this.w = this.w.a(b, i);
        this.z = false;
        for (bfd bfd = this.s.d; bfd != null; bfd = bfd.h) {
            final bqv[] array = (bqv[])bfd.k.c;
            int length;
            bqv bqv;
            for (length = array.length, i = 0; i < length; ++i) {
                bqv = array[i];
            }
        }
        if (!this.Q()) {
            this.H();
            this.J();
            return;
        }
        i = this.w.d;
        if (i == 3) {
            this.F();
            this.a.d(2);
            return;
        }
        if (i == 2) {
            this.a.d(2);
        }
    }
    
    private final void E(final int n) {
        final bfm w = this.w;
        if (w.d != n) {
            if (n != 2) {
                this.L = -9223372036854775807L;
            }
            this.w = w.d(n);
        }
    }
    
    private final void F() {
        int i = 0;
        this.z = false;
        final bec p = this.p;
        p.f = true;
        p.a.e();
        for (bfq[] e = this.e; i < e.length; ++i) {
            final bfq bfq = e[i];
            if (M(bfq)) {
                bfq.I();
            }
        }
    }
    
    private final void G(final boolean b, final boolean b2) {
        this.w(b || !this.D, false, true, false);
        this.N.b((int)(b2 ? 1 : 0));
        this.i.e();
        this.E(1);
    }
    
    private final void H() {
        this.p.d();
        for (final bfq bfq : this.e) {
            if (M(bfq)) {
                X(bfq);
            }
        }
    }
    
    private final void I() {
        final bfd f = this.s.f;
        final boolean b = this.A || (f != null && f.a.o());
        final bfm w = this.w;
        if (b != w.f) {
            this.w = new bfm(w.a, w.q, w.b, w.c, w.d, w.e, b, w.g, w.s, w.h, w.r, w.i, w.j, w.k, w.m, w.n, w.o, w.l, (byte[])null, (byte[])null, (byte[])null);
        }
    }
    
    private final void J() {
        final bfd d = this.s.d;
        if (d == null) {
            return;
        }
        long e;
        if (d.d) {
            e = d.a.e();
        }
        else {
            e = -9223372036854775807L;
        }
        if (e != -9223372036854775807L) {
            this.y(e);
            if (e != this.w.o) {
                final bfm w = this.w;
                this.w = this.U(w.q, e, w.b, e, true, 5);
            }
        }
        else {
            final bec p = this.p;
            final bfd e2 = this.s.e;
            final bfq c = p.c;
            Label_0332: {
                Label_0310: {
                    if (c != null && !c.S()) {
                        if (!p.c.T()) {
                            if (d != e2) {
                                break Label_0310;
                            }
                            if (p.c.K()) {
                                break Label_0310;
                            }
                        }
                        final bfc d2 = p.d;
                        dk.d((Object)d2);
                        final long kh = d2.kH();
                        if (p.e) {
                            if (kh < p.a.kH()) {
                                p.a.f();
                                break Label_0332;
                            }
                            p.e = false;
                            if (p.f) {
                                p.a.e();
                            }
                        }
                        p.a.d(kh);
                        final azb ki = d2.kI();
                        if (!ki.equals((Object)p.a.a)) {
                            p.a.kJ(ki);
                            ((bez)p.b).a.f(16, (Object)ki).r();
                        }
                        break Label_0332;
                    }
                }
                p.e = true;
                if (p.f) {
                    p.a.e();
                }
            }
            final long kh2 = p.kH();
            this.H = kh2;
            final long d3 = d.d(kh2);
            final long o = this.w.o;
            Label_0886: {
                if (!this.q.isEmpty()) {
                    if (!this.w.q.a()) {
                        long n = o;
                        if (this.J) {
                            n = o - 1L;
                            this.J = false;
                        }
                        final bfm w2 = this.w;
                        final int a = w2.a.a(w2.q.a);
                        final int min = Math.min(this.I, this.q.size());
                        long n2 = n;
                    Label_0609_Outer:
                        while (true) {
                            Label_0480: {
                                int n3;
                                if ((n3 = min) <= 0) {
                                    break Label_0480;
                                }
                                bex bex = this.q.get(min - 1);
                                n3 = min;
                                while (bex != null) {
                                    final int b = bex.b;
                                    if (b <= a && (b != a || bex.c <= n)) {
                                        break;
                                    }
                                    final int n4 = n3 - 1;
                                    n2 = n;
                                    if ((n3 = n4) <= 0) {
                                        break Label_0480;
                                    }
                                    bex = (bex)this.q.get(n4 - 1);
                                    n3 = n4;
                                }
                                long n5 = n;
                                while (true) {
                                    int n6 = 0;
                                    Label_0599: {
                                        if ((n6 = n3) >= this.q.size()) {
                                            break Label_0599;
                                        }
                                        bex bex2 = this.q.get(n3);
                                        int i;
                                        Object a2;
                                        while (true) {
                                            i = n3;
                                            a2 = bex2;
                                            if (bex2 == null) {
                                                break;
                                            }
                                            i = n3;
                                            a2 = bex2;
                                            if (bex2.d == null) {
                                                break;
                                            }
                                            final int b2 = bex2.b;
                                            if (b2 >= a) {
                                                i = n3;
                                                a2 = bex2;
                                                if (b2 != a) {
                                                    break;
                                                }
                                                i = n3;
                                                a2 = bex2;
                                                if (bex2.c > n) {
                                                    break;
                                                }
                                            }
                                            ++n3;
                                            n5 = n;
                                            if ((n6 = n3) >= this.q.size()) {
                                                break Label_0599;
                                            }
                                            bex2 = this.q.get(n3);
                                        }
                                        while (a2 != null && ((bex)a2).d != null && ((bex)a2).b == a) {
                                            final long c2 = ((bex)a2).c;
                                            if (c2 > n && c2 <= d3) {
                                                try {
                                                    this.C(((bex)a2).a);
                                                    final bfp a3 = ((bex)a2).a;
                                                    if (!a3.h && !a3.b()) {
                                                        ++i;
                                                    }
                                                    else {
                                                        this.q.remove(i);
                                                    }
                                                    if (i < this.q.size()) {
                                                        a2 = this.q.get(i);
                                                        continue Label_0609_Outer;
                                                    }
                                                    a2 = null;
                                                    continue Label_0609_Outer;
                                                }
                                                finally {
                                                    a2 = ((bex)a2).a;
                                                    if (((bfp)a2).h || ((bfp)a2).b()) {
                                                        this.q.remove(i);
                                                    }
                                                }
                                                break;
                                            }
                                            break;
                                        }
                                        this.I = i;
                                        break Label_0886;
                                    }
                                    bex bex2 = null;
                                    n3 = n6;
                                    n = n5;
                                    continue;
                                }
                            }
                            bex bex = null;
                            n = n2;
                            continue;
                        }
                    }
                }
            }
            this.w.o = d3;
        }
        this.w.m = this.s.f.a();
        this.w.n = this.h();
        final bfm w3 = this.w;
        if (w3.i && w3.d == 3 && this.W(w3.a, w3.q)) {
            final bfm w4 = this.w;
            final float b3 = w4.k.b;
            float o2 = 1.0f;
            if (b3 == 1.0f) {
                final bdz m = this.M;
                final long g = this.g(w4.a, w4.q.a, w4.o);
                final long h = this.h();
                Label_1473: {
                    if (m.h != -9223372036854775807L) {
                        final long q = g - h;
                        final long q2 = m.q;
                        if (q2 == -9223372036854775807L) {
                            m.q = q;
                            m.r = 0L;
                        }
                        else {
                            final float g2 = m.g;
                            final long max = Math.max(q, bdz.c(q2, q));
                            m.q = max;
                            final long abs = Math.abs(q - max);
                            final long r = m.r;
                            final float g3 = m.g;
                            m.r = bdz.c(r, abs);
                        }
                        if (m.p != -9223372036854775807L) {
                            final long elapsedRealtime = SystemClock.elapsedRealtime();
                            final long p2 = m.p;
                            final long c3 = m.c;
                            if (elapsedRealtime - p2 < 1000L) {
                                o2 = m.o;
                                break Label_1473;
                            }
                        }
                        final long n7 = g;
                        m.p = SystemClock.elapsedRealtime();
                        final long n8 = m.q + m.r * 3L;
                        long c5;
                        if (m.l > n8) {
                            final long c4 = m.c;
                            final long w5 = baw.w(1000L);
                            final float o3 = m.o;
                            final float n9 = (float)w5;
                            c5 = afva.C(n8, m.i, m.l - ((long)((o3 - 1.0f) * n9) + (long)((m.m - 1.0f) * n9)));
                            m.l = c5;
                        }
                        else {
                            final float max2 = Math.max(0.0f, m.o - 1.0f);
                            final float d4 = m.d;
                            final long r2 = baw.r(n7 - (long)(max2 / 1.0E-7f), m.l, n8);
                            m.l = r2;
                            final long k = m.k;
                            c5 = r2;
                            if (k != -9223372036854775807L) {
                                c5 = r2;
                                if (r2 > k) {
                                    m.l = k;
                                    c5 = k;
                                }
                            }
                        }
                        final long n10 = n7 - c5;
                        if (Math.abs(n10) < m.e) {
                            m.o = 1.0f;
                            o2 = 1.0f;
                        }
                        else {
                            final float d5 = m.d;
                            o2 = baw.a(n10 * 1.0E-7f + 1.0f, m.n, m.m);
                            m.o = o2;
                        }
                    }
                }
                if (this.p.kI().b != o2) {
                    this.p.kJ(new azb(o2, this.w.k.c));
                    this.t(this.w.k, this.p.kI().b, false, false);
                }
            }
        }
    }
    
    private final void K(final aeyr aeyr, final long n) {
        monitorenter(this);
        try {
            final long elapsedRealtime = SystemClock.elapsedRealtime();
            boolean b = false;
            for (long n2 = n; !(boolean)aeyr.a() && n2 > 0L; n2 = elapsedRealtime + n - SystemClock.elapsedRealtime()) {
                try {
                    this.wait(n2);
                }
                catch (final InterruptedException ex) {
                    b = true;
                }
            }
            if (b) {
                Thread.currentThread().interrupt();
                monitorexit(this);
                return;
            }
            monitorexit(this);
        }
        finally {
            monitorexit(this);
            while (true) {}
        }
    }
    
    private final boolean L() {
        final bfd f = this.s.f;
        return f != null && f.b() != Long.MIN_VALUE;
    }
    
    private static boolean M(final bfq bfq) {
        return bfq.g() != 0;
    }
    
    private final boolean N() {
        final bfd d = this.s.d;
        final long d2 = d.f.d;
        final boolean d3 = d.d;
        boolean b = false;
        if (d3) {
            if (d2 != -9223372036854775807L && this.w.o >= d2) {
                if (!this.Q()) {
                    return true;
                }
                b = b;
            }
            else {
                b = true;
            }
        }
        return b;
    }
    
    private static boolean O(final bfm bfm, final azj azj) {
        final ayx q = bfm.q;
        final azl a = bfm.a;
        return a.p() || a.n(q.a, azj).f;
    }
    
    private static boolean P(final bex bex, final azl azl, final azl azl2, int a, final boolean b, final azk azk, final azj azj) {
        final Object d = bex.d;
        if (d == null) {
            final long w = baw.w(bex.a.g);
            final bfp a2 = bex.a;
            final Pair k = k(azl, new bey(a2.b, a2.f, w), false, a, b, azk, azj);
            if (k == null) {
                return false;
            }
            bex.a(azl.a(k.first), (long)k.second, k.first);
            final long g = bex.a.g;
            return true;
        }
        else {
            a = azl.a(d);
            if (a == -1) {
                return false;
            }
            final long g2 = bex.a.g;
            bex.b = a;
            azl2.n(bex.d, azj);
            if (azj.f && azl2.o(azj.c, azk).o == azl2.a(bex.d)) {
                final Pair i = azl.k(azk, azj, azl.n(bex.d, azj).c, bex.c + azj.e);
                bex.a(azl.a(i.first), (long)i.second, i.first);
            }
            return true;
        }
    }
    
    private final boolean Q() {
        final bfm w = this.w;
        return w.i && w.j == 0;
    }
    
    private static ayf[] R(final bqv bqv) {
        int i = 0;
        int g;
        if (bqv != null) {
            g = bqv.g();
        }
        else {
            g = 0;
        }
        final ayf[] array = new ayf[g];
        while (i < g) {
            array[i] = bqv.h(i);
            ++i;
        }
        return array;
    }
    
    private final long S(final ayx ayx, final long n, final boolean b) {
        final bff s = this.s;
        return this.T(ayx, n, s.d != s.e, b);
    }
    
    private final long T(final ayx ayx, long n, final boolean b, final boolean b2) {
        this.H();
        this.z = false;
        if (b2 || this.w.d == 3) {
            this.E(2);
        }
        bfd bfd2;
        bfd bfd;
        for (bfd = (bfd2 = this.s.d); bfd2 != null && !ayx.equals((Object)bfd2.f.i); bfd2 = bfd2.h) {}
        if (b || bfd != bfd2 || (bfd2 != null && bfd2.e(n) < 0L)) {
            final bfq[] e = this.e;
            for (int length = e.length, i = 0; i < length; ++i) {
                this.l(e[i]);
            }
            if (bfd2 != null) {
                bff s;
                while (true) {
                    s = this.s;
                    if (s.d == bfd2) {
                        break;
                    }
                    s.a();
                }
                s.h(bfd2);
                bfd2.j = 1000000000000L;
                this.n();
            }
        }
        if (bfd2 != null) {
            this.s.h(bfd2);
            long f;
            if (!bfd2.d) {
                bfd2.f = bfd2.f.b(n);
                f = n;
            }
            else {
                f = n;
                if (bfd2.e) {
                    f = bfd2.a.f(n);
                    bfd2.a.i(f - this.n, this.o);
                }
            }
            this.y(f);
            this.u();
            n = f;
        }
        else {
            this.s.d();
            this.y(n);
        }
        this.q(false);
        this.a.d(2);
        return n;
    }
    
    private final bfm U(final ayx ayx, final long n, final long n2, final long n3, final boolean b, final int e) {
        final boolean j = this.J;
        final boolean b2 = false;
        this.J = (j || n != this.w.o || !ayx.equals((Object)this.w.q));
        this.x();
        final bfm w = this.w;
        bpd bpd = w.g;
        aetc aetc = w.s;
        Object o = w.h;
        if (this.t.h) {
            final bfd d = this.s.d;
            if (d == null) {
                bpd = bpd.a;
            }
            else {
                bpd = d.i;
            }
            if (d == null) {
                aetc = this.O;
            }
            else {
                aetc = d.k;
            }
            final Object c = aetc.c;
            final afcm afcm = new afcm();
            final bqv[] array = (bqv[])c;
            final int length = array.length;
            int i = 0;
            int n4 = 0;
            while (i < length) {
                final bqv bqv = array[i];
                int n5 = n4;
                if (bqv != null) {
                    final Metadata l = bqv.h(0).l;
                    if (l == null) {
                        afcm.h(new Metadata(new Metadata$Entry[0]));
                        n5 = n4;
                    }
                    else {
                        afcm.h(l);
                        n5 = 1;
                    }
                }
                ++i;
                n4 = n5;
            }
            if (n4 != 0) {
                o = afcm.g();
            }
            else {
                o = afcr.q();
            }
            if (d != null) {
                final bfe f = d.f;
                if (f.b != n2) {
                    d.f = f.a(n2);
                }
            }
        }
        else if (!ayx.equals((Object)w.q)) {
            bpd = bpd.a;
            aetc = this.O;
            o = afcr.q();
        }
        if (b) {
            final lzz n6 = this.N;
            if (n6.f && n6.e != 5) {
                boolean b3 = b2;
                if (e == 5) {
                    b3 = true;
                }
                dk.f(b3);
            }
            else {
                n6.d = true;
                n6.f = true;
                n6.e = e;
            }
        }
        return this.w.h(ayx, n, n2, n3, this.h(), bpd, aetc, (List)o);
    }
    
    private final void V(final azl azl, final ayx ayx, final azl azl2, final ayx ayx2, final long n) {
        if (!this.W(azl, ayx)) {
            azb azb;
            if (ayx.a()) {
                azb = azb.a;
            }
            else {
                azb = this.w.k;
            }
            if (!this.p.kI().equals((Object)azb)) {
                this.p.kJ(azb);
            }
            return;
        }
        azl.o(azl.n(ayx.a, this.m).c, this.l);
        final bdz m = this.M;
        final ayo k = this.l.k;
        final int a = baw.a;
        m.h = baw.w(k.a);
        m.j = baw.w(k.b);
        m.k = baw.w(k.c);
        float d;
        if ((d = k.d) == -3.4028235E38f) {
            final float a2 = m.a;
            d = 0.97f;
        }
        m.n = d;
        float e;
        if ((e = k.e) == -3.4028235E38f) {
            final float b = m.b;
            e = 1.03f;
        }
        m.m = e;
        if (d == 1.0f && e == 1.0f) {
            m.h = -9223372036854775807L;
        }
        m.a();
        if (n != -9223372036854775807L) {
            this.M.b(this.g(azl, ayx.a, n));
            return;
        }
        final Object b2 = this.l.b;
        Object b3;
        if (!azl2.p()) {
            b3 = azl2.o(azl2.n(ayx2.a, this.m).c, this.l).b;
        }
        else {
            b3 = null;
        }
        if (!baw.aa(b3, b2)) {
            this.M.b(-9223372036854775807L);
        }
    }
    
    private final boolean W(final azl azl, final ayx ayx) {
        if (!ayx.a()) {
            if (!azl.p()) {
                azl.o(azl.n(ayx.a, this.m).c, this.l);
                if (this.l.d()) {
                    final azk l = this.l;
                    if (l.i && l.f != -9223372036854775807L) {
                        return true;
                    }
                }
            }
        }
        return false;
    }
    
    private static final void X(final bfq bfq) {
        if (bfq.g() == 2) {
            bfq.J();
        }
    }
    
    private static final void Y(final bfq bfq, final long d) {
        bfq.G();
        if (bfq instanceof bqb) {
            final bqb bqb = (bqb)bfq;
            dk.h(((bdw)bqb).c);
            bqb.d = d;
        }
    }
    
    private final void Z(final bpd bpd, final aetc aetc) {
        this.i.f(this.e, bpd, (bqv[])aetc.c);
    }
    
    static Object a(final azk azk, final azj azj, final int n, final boolean b, final Object o, final azl azl, final azl azl2) {
        int n2 = azl.a(o);
        final int b2 = azl.b();
        int n3 = 0;
        int a = -1;
        int n4;
        while (true) {
            n4 = a;
            if (n3 >= b2 || (n4 = a) != -1) {
                break;
            }
            n2 = azl.i(n2, azj, azk, n, b);
            if (n2 == -1) {
                n4 = -1;
                break;
            }
            a = azl2.a(azl.f(n2));
            ++n3;
        }
        if (n4 == -1) {
            return null;
        }
        return azl2.f(n4);
    }
    
    public static final void f(final bfp bfp) {
        if (!bfp.b()) {
            try {
                bfp.a.t(bfp.c, bfp.d);
            }
            finally {
                bfp.a(true);
            }
        }
    }
    
    private final long g(final azl azl, final Object o, final long n) {
        azl.o(azl.n(o, this.m).c, this.l);
        final azk l = this.l;
        if (l.f != -9223372036854775807L && l.d()) {
            final azk i = this.l;
            if (i.i) {
                return baw.w(baw.t(i.g) - this.l.f) - (n + this.m.e);
            }
        }
        return -9223372036854775807L;
    }
    
    private final long h() {
        return this.i(this.w.m);
    }
    
    private final long i(final long n) {
        final bfd f = this.s.f;
        if (f == null) {
            return 0L;
        }
        return Math.max(0L, n - f.d(this.H));
    }
    
    private final Pair j(final azl azl) {
        final boolean p = azl.p();
        final long n = 0L;
        if (p) {
            return Pair.create((Object)bfm.p, (Object)0L);
        }
        final Pair k = azl.k(this.l, this.m, azl.g(this.C), -9223372036854775807L);
        final ayx i = this.s.k(azl, k.first, 0L);
        long longValue = (long)k.second;
        if (i.a()) {
            azl.n(i.a, this.m);
            longValue = n;
            if (i.c == this.m.d(i.b)) {
                this.m.j();
                longValue = n;
            }
        }
        return Pair.create((Object)i, (Object)longValue);
    }
    
    private static Pair k(final azl azl, final bey bey, final boolean b, final int n, final boolean b2, final azk azk, final azj azj) {
        azl a = bey.a;
        if (azl.p()) {
            return null;
        }
        if (a.p()) {
            a = azl;
        }
        try {
            final Pair k = a.k(azk, azj, bey.b, bey.c);
            if (azl.equals((Object)a)) {
                return k;
            }
            if (azl.a(k.first) == -1) {
                if (b) {
                    final Object a2 = a(azk, azj, n, b2, k.first, a, azl);
                    if (a2 != null) {
                        return azl.k(azk, azj, azl.n(a2, azj).c, -9223372036854775807L);
                    }
                }
                return null;
            }
            if (a.n(k.first, azj).f && a.o(azj.c, azk).o == a.a(k.first)) {
                return azl.k(azk, azj, azl.n(k.first, azj).c, bey.c);
            }
            return k;
        }
        catch (final IndexOutOfBoundsException ex) {
            return null;
        }
    }
    
    private final void l(final bfq bfq) {
        if (!M(bfq)) {
            return;
        }
        final bec p = this.p;
        if (bfq == p.c) {
            p.d = null;
            p.c = null;
            p.e = true;
        }
        X(bfq);
        bfq.r();
        --this.F;
    }
    
    private final void m() {
        final long uptimeMillis = SystemClock.uptimeMillis();
        this.a.c();
        if (!this.w.a.p()) {
            if (this.t.h) {
                this.s.f(this.H);
                final bff s = this.s;
                final bfd f = s.f;
                if (f == null || (!f.f.h && f.i() && s.f.f.d != -9223372036854775807L && s.g < 100)) {
                    final bff s2 = this.s;
                    final long h = this.H;
                    final bfm w = this.w;
                    final bfd f2 = s2.f;
                    bfe bfe;
                    if (f2 == null) {
                        bfe = s2.j(w.a, w.q, w.b, w.o);
                    }
                    else {
                        bfe = s2.b(w.a, f2, h);
                    }
                    if (bfe != null) {
                        final bff s3 = this.s;
                        final bfr[] g = this.g;
                        final bra h2 = this.h;
                        final bre j = this.i.j();
                        final bfl t = this.t;
                        final aetc o = this.O;
                        final bfd f3 = s3.f;
                        long n;
                        if (f3 == null) {
                            n = 1000000000000L;
                        }
                        else {
                            n = f3.j + f3.f.d - bfe.a;
                        }
                        final bfd f4 = new bfd(g, n, h2, j, t, bfe, o, (byte[])null, (byte[])null, (byte[])null);
                        final bfd f5 = s3.f;
                        if (f5 != null) {
                            f5.g(f4);
                        }
                        else {
                            s3.d = f4;
                            s3.e = f4;
                        }
                        s3.h = null;
                        s3.f = f4;
                        ++s3.g;
                        s3.e();
                        f4.a.l((bnt)this, bfe.a);
                        if (this.s.d == f4) {
                            this.y(bfe.a);
                        }
                        this.q(false);
                    }
                }
                if (this.A) {
                    this.A = this.L();
                    this.I();
                }
                else {
                    this.u();
                }
                final bfd e = this.s.e;
                if (e != null) {
                    if (e.h != null && !this.y) {
                        if (e.d) {
                            int n2 = 0;
                            while (true) {
                                final bfq[] e2 = this.e;
                                if (n2 < e2.length) {
                                    final bfq bfq = e2[n2];
                                    final bov bov = e.c[n2];
                                    if (bfq.q() != bov) {
                                        break;
                                    }
                                    if (bov != null && !bfq.K()) {
                                        final boolean e3 = e.f.e;
                                        break;
                                    }
                                    ++n2;
                                }
                                else {
                                    final bfd h3 = e.h;
                                    if (!h3.d && this.H < h3.c()) {
                                        break;
                                    }
                                    final aetc k = e.k;
                                    final bff s4 = this.s;
                                    final bfd e4 = s4.e;
                                    dk.h(e4 != null && e4.h != null);
                                    s4.e = s4.e.h;
                                    s4.e();
                                    final bfd e5 = s4.e;
                                    final aetc i = e5.k;
                                    final azl a = this.w.a;
                                    this.V(a, e5.f.i, a, e.f.i, -9223372036854775807L);
                                    if (e5.d && e5.a.e() != -9223372036854775807L) {
                                        final long c = e5.c();
                                        for (final bfq bfq2 : this.e) {
                                            if (bfq2.q() != null) {
                                                Y(bfq2, c);
                                            }
                                        }
                                        break;
                                    }
                                    for (int n3 = 0; n3 < this.e.length; ++n3) {
                                        final boolean m = k.i(n3);
                                        final boolean i2 = i.i(n3);
                                        if (m && !this.e[n3].L()) {
                                            this.g[n3].h();
                                            final bfs bfs = ((bfs[])k.b)[n3];
                                            final bfs bfs2 = ((bfs[])i.b)[n3];
                                            if (!i2 || !bfs2.equals((Object)bfs)) {
                                                Y(this.e[n3], e5.c());
                                            }
                                        }
                                    }
                                    break;
                                }
                            }
                        }
                    }
                    else if (e.f.h || this.y) {
                        int n4 = 0;
                        while (true) {
                            final bfq[] e7 = this.e;
                            if (n4 >= e7.length) {
                                break;
                            }
                            final bfq bfq3 = e7[n4];
                            final bov bov2 = e.c[n4];
                            if (bov2 != null && bfq3.q() == bov2 && bfq3.K()) {
                                final long d = e.f.d;
                                long n5;
                                if (d != -9223372036854775807L && d != Long.MIN_VALUE) {
                                    n5 = d + e.j;
                                }
                                else {
                                    n5 = -9223372036854775807L;
                                }
                                Y(bfq3, n5);
                            }
                            ++n4;
                        }
                    }
                }
                final bff s5 = this.s;
                final bfd e8 = s5.e;
                if (e8 != null && s5.d != e8) {
                    if (!e8.g) {
                        final aetc k2 = e8.k;
                        int n6 = 0;
                        int n7 = 0;
                        while (true) {
                            final bfq[] e9 = this.e;
                            if (n6 >= e9.length) {
                                break;
                            }
                            final bfq bfq4 = e9[n6];
                            int n8 = n7;
                            if (M(bfq4)) {
                                final bov q = bfq4.q();
                                final bov bov3 = e8.c[n6];
                                if (k2.i(n6) && q == bov3) {
                                    n8 = n7;
                                }
                                else if (!bfq4.L()) {
                                    bfq4.D(R(((bqv[])k2.c)[n6]), e8.c[n6], e8.c(), e8.j);
                                    n8 = n7;
                                }
                                else if (bfq4.S()) {
                                    this.l(bfq4);
                                    n8 = n7;
                                }
                                else {
                                    n8 = 1;
                                }
                            }
                            ++n6;
                            n7 = n8;
                        }
                        if (n7 == 0) {
                            this.n();
                        }
                    }
                }
                int n9 = 0;
                while (this.Q() && !this.y) {
                    final bfd d2 = this.s.d;
                    if (d2 == null) {
                        break;
                    }
                    final bfd h4 = d2.h;
                    if (h4 == null || this.H < h4.c() || !h4.g) {
                        break;
                    }
                    if (n9 != 0) {
                        this.v();
                    }
                    final bfd a2 = this.s.a();
                    dk.d((Object)a2);
                    boolean b = false;
                    Label_1402: {
                        if (this.w.q.a.equals(a2.f.i.a)) {
                            final ayx q2 = this.w.q;
                            if (q2.b == -1) {
                                final ayx i3 = a2.f.i;
                                if (i3.b == -1 && q2.e != i3.e) {
                                    b = true;
                                    break Label_1402;
                                }
                            }
                        }
                        b = false;
                    }
                    final bfe f6 = a2.f;
                    final ayx i4 = f6.i;
                    final long a3 = f6.a;
                    this.w = this.U(i4, a3, f6.b, a3, b ^ true, 0);
                    this.x();
                    this.J();
                    n9 = 1;
                }
            }
        }
        final int d3 = this.w.d;
        if (d3 != 1) {
            if (d3 != 4) {
                final bfd d4 = this.s.d;
                if (d4 == null) {
                    this.A(uptimeMillis, 10L);
                    return;
                }
                final int a4 = baw.a;
                this.J();
                int n11;
                int n12;
                if (d4.d) {
                    final long elapsedRealtime = SystemClock.elapsedRealtime();
                    d4.a.i(this.w.o - this.n, this.o);
                    int n10 = 0;
                    n11 = 1;
                    n12 = 1;
                    while (true) {
                        final bfq[] e10 = this.e;
                        if (n10 >= e10.length) {
                            break;
                        }
                        final bfq bfq5 = e10[n10];
                        int n13;
                        int n14;
                        if (!M(bfq5)) {
                            n13 = n11;
                            n14 = n12;
                        }
                        else {
                            bfq5.R(this.H, elapsedRealtime * 1000L);
                            int n15;
                            if (n11 != 0 && bfq5.S()) {
                                n15 = 1;
                            }
                            else {
                                n15 = 0;
                            }
                            final boolean b2 = d4.c[n10] != bfq5.q();
                            final boolean b3 = !b2 && bfq5.K();
                            final boolean b4 = b2 || b3 || bfq5.T() || bfq5.S();
                            int n16;
                            if (n12 != 0 && b4) {
                                n16 = 1;
                            }
                            else {
                                n16 = 0;
                            }
                            n13 = n15;
                            n14 = n16;
                            if (!b4) {
                                bfq5.v();
                                n14 = n16;
                                n13 = n15;
                            }
                        }
                        ++n10;
                        n11 = n13;
                        n12 = n14;
                    }
                }
                else {
                    d4.a.j();
                    n12 = 1;
                    n11 = 1;
                }
                final long d5 = d4.f.d;
                Label_2304: {
                    if (n11 != 0 && d4.d && (d5 == -9223372036854775807L || d5 <= this.w.o)) {
                        if (this.y) {
                            this.D(this.y = false, this.w.j, false, 5);
                        }
                        if (d4.f.h) {
                            this.E(4);
                            this.H();
                            break Label_2304;
                        }
                    }
                    final bfm w2 = this.w;
                    Label_2113: {
                        if (w2.d == 2) {
                            if (this.F == 0) {
                                if (!this.N()) {
                                    break Label_2113;
                                }
                            }
                            else {
                                if (n12 == 0) {
                                    break Label_2113;
                                }
                                if (w2.f) {
                                    long l2;
                                    if (this.W(w2.a, this.s.d.f.i)) {
                                        l2 = this.M.l;
                                    }
                                    else {
                                        l2 = -9223372036854775807L;
                                    }
                                    final bfd f7 = this.s.f;
                                    final boolean b5 = f7.i() && f7.f.h;
                                    final boolean b6 = f7.f.i.a() && !f7.d;
                                    if (!b5 && !b6 && !this.i.i(this.h(), this.p.kI().b, this.z, l2)) {
                                        break Label_2113;
                                    }
                                }
                            }
                            this.E(3);
                            this.K = null;
                            if (this.Q()) {
                                this.F();
                            }
                            break Label_2304;
                        }
                    }
                    if (this.w.d == 3) {
                        if (this.F == 0) {
                            if (this.N()) {
                                break Label_2304;
                            }
                        }
                        else if (n12 != 0) {
                            break Label_2304;
                        }
                        this.z = this.Q();
                        this.E(2);
                        if (this.z) {
                            for (bfd bfd = this.s.d; bfd != null; bfd = bfd.h) {
                                for (final bqv bqv : (bqv[])bfd.k.c) {}
                            }
                            final bdz m2 = this.M;
                            final long l3 = m2.l;
                            if (l3 != -9223372036854775807L) {
                                final long l4 = l3 + m2.f;
                                m2.l = l4;
                                final long k3 = m2.k;
                                if (k3 != -9223372036854775807L && l4 > k3) {
                                    m2.l = k3;
                                }
                                m2.p = -9223372036854775807L;
                            }
                        }
                        this.H();
                    }
                }
                Label_2468: {
                    if (this.w.d == 2) {
                        int n18 = 0;
                        while (true) {
                            final bfq[] e11 = this.e;
                            if (n18 >= e11.length) {
                                break;
                            }
                            if (M(e11[n18]) && this.e[n18].q() == d4.c[n18]) {
                                this.e[n18].v();
                            }
                            ++n18;
                        }
                        final bfm w3 = this.w;
                        if (!w3.f && w3.n < 500000L && this.L()) {
                            if (this.L == -9223372036854775807L) {
                                this.L = SystemClock.elapsedRealtime();
                                break Label_2468;
                            }
                            if (SystemClock.elapsedRealtime() - this.L < 4000L) {
                                break Label_2468;
                            }
                            throw new IllegalStateException("Playback stuck buffering and not loading");
                        }
                    }
                    this.L = -9223372036854775807L;
                }
                final boolean b7 = this.Q() && this.w.d == 3;
                final boolean b8 = this.E && this.d && b7;
                final bfm w4 = this.w;
                if (w4.l != b8) {
                    this.w = new bfm(w4.a, w4.q, w4.b, w4.c, w4.d, w4.e, w4.f, w4.g, w4.s, w4.h, w4.r, w4.i, w4.j, w4.k, w4.m, w4.n, w4.o, b8, (byte[])null, (byte[])null, (byte[])null);
                }
                this.d = false;
                if (!b8) {
                    final int d6 = this.w.d;
                    if (d6 != 4) {
                        if (!b7 && d6 != 2) {
                            if (d6 == 3 && this.F != 0) {
                                this.A(uptimeMillis, 1000L);
                            }
                        }
                        else {
                            this.A(uptimeMillis, 10L);
                        }
                    }
                }
            }
        }
    }
    
    private final void n() {
        this.o(new boolean[this.e.length]);
    }
    
    private final void o(final boolean[] array) {
        final bfd e = this.s.e;
        final aetc k = e.k;
        for (int i = 0; i < this.e.length; ++i) {
            if (!k.i(i) && this.f.remove(this.e[i])) {
                this.e[i].E();
            }
        }
        for (int j = 0; j < this.e.length; ++j) {
            if (k.i(j)) {
                final boolean b = array[j];
                final bfq c = this.e[j];
                if (!M(c)) {
                    final bff s = this.s;
                    final bfd e2 = s.e;
                    final boolean b2 = e2 == s.d;
                    final aetc l = e2.k;
                    final bfs bfs = ((bfs[])l.b)[j];
                    final ayf[] r = R(((bqv[])l.c)[j]);
                    final boolean b3 = this.Q() && this.w.d == 3;
                    final boolean b4 = !b && b3;
                    ++this.F;
                    this.f.add(c);
                    c.s(bfs, r, e2.c[j], this.H, b4, b2, e2.c(), e2.j);
                    c.t(11, (Object)new qpt(this));
                    final bec p = this.p;
                    final bfc n = c.n();
                    if (n != null) {
                        final bfc d = p.d;
                        if (n != d) {
                            if (d != null) {
                                throw bee.b(new IllegalStateException("Multiple renderer media clocks enabled."), 1000);
                            }
                            p.d = n;
                            p.c = c;
                            p.d.kJ(p.a.a);
                        }
                    }
                    if (b3) {
                        c.I();
                    }
                }
            }
        }
        e.g = true;
    }
    
    private final void p(final IOException ex, final int n) {
        final bee bee = new bee(0, ex, n);
        final bfd d = this.s.d;
        bee a = bee;
        if (d != null) {
            a = bee.a(d.f.i);
        }
        bao.b("ExoPlayerImplInternal", "Playback error", (Throwable)a);
        this.G(false, false);
        this.w = this.w.b(a);
    }
    
    private final void q(final boolean b) {
        final bfd f = this.s.f;
        ayx ayx;
        if (f == null) {
            ayx = this.w.q;
        }
        else {
            ayx = f.f.i;
        }
        final boolean b2 = this.w.r.equals((Object)ayx) ^ true;
        if (b2) {
            this.w = this.w.f(ayx);
        }
        final bfm w = this.w;
        long m;
        if (f == null) {
            m = w.o;
        }
        else {
            m = f.a();
        }
        w.m = m;
        this.w.n = this.h();
        if ((b2 || b) && f != null && f.d) {
            this.Z(f.i, f.k);
        }
    }
    
    private final void r(final azl p0, final boolean p1) {
        // 
        // This method could not be decompiled.
        // 
        // Original Bytecode:
        // 
        //     1: getfield        bez.w:Lbfm;
        //     4: astore_3       
        //     5: aload_0        
        //     6: getfield        bez.G:Lbey;
        //     9: astore          4
        //    11: aload_0        
        //    12: getfield        bez.s:Lbff;
        //    15: astore          5
        //    17: aload_0        
        //    18: getfield        bez.B:I
        //    21: istore          6
        //    23: aload_0        
        //    24: getfield        bez.C:Z
        //    27: istore          7
        //    29: aload_0        
        //    30: getfield        bez.l:Lazk;
        //    33: astore          8
        //    35: aload_0        
        //    36: getfield        bez.m:Lazj;
        //    39: astore          9
        //    41: aload_1        
        //    42: invokevirtual   azl.p:()Z
        //    45: istore          10
        //    47: ldc2_w          -9223372036854775807
        //    50: lstore          11
        //    52: iload           10
        //    54: ifeq            82
        //    57: getstatic       bfm.p:Layx;
        //    60: astore          13
        //    62: lconst_0       
        //    63: lstore          14
        //    65: ldc2_w          -9223372036854775807
        //    68: lstore          16
        //    70: iconst_0       
        //    71: istore          6
        //    73: iconst_0       
        //    74: istore          7
        //    76: iconst_1       
        //    77: istore          18
        //    79: goto            927
        //    82: aload_3        
        //    83: getfield        bfm.q:Layx;
        //    86: astore          13
        //    88: aload           13
        //    90: getfield        ayx.a:Ljava/lang/Object;
        //    93: astore          19
        //    95: aload_3        
        //    96: aload           9
        //    98: invokestatic    bez.O:(Lbfm;Lazj;)Z
        //   101: istore          10
        //   103: aload_3        
        //   104: getfield        bfm.q:Layx;
        //   107: invokevirtual   ayx.a:()Z
        //   110: ifne            130
        //   113: iload           10
        //   115: ifeq            121
        //   118: goto            130
        //   121: aload_3        
        //   122: getfield        bfm.o:J
        //   125: lstore          16
        //   127: goto            136
        //   130: aload_3        
        //   131: getfield        bfm.b:J
        //   134: lstore          16
        //   136: aload           4
        //   138: ifnull          298
        //   141: aload_1        
        //   142: aload           4
        //   144: iconst_1       
        //   145: iload           6
        //   147: iload           7
        //   149: aload           8
        //   151: aload           9
        //   153: invokestatic    bez.k:(Lazl;Lbey;ZIZLazk;Lazj;)Landroid/util/Pair;
        //   156: astore          20
        //   158: aload           20
        //   160: ifnonnull       187
        //   163: aload_1        
        //   164: iload           7
        //   166: invokevirtual   azl.g:(Z)I
        //   169: istore          6
        //   171: lload           16
        //   173: lstore          14
        //   175: iconst_0       
        //   176: istore          7
        //   178: iconst_1       
        //   179: istore          18
        //   181: iconst_0       
        //   182: istore          21
        //   184: goto            283
        //   187: aload           4
        //   189: getfield        bey.c:J
        //   192: ldc2_w          -9223372036854775807
        //   195: lcmp           
        //   196: ifne            225
        //   199: aload_1        
        //   200: aload           20
        //   202: getfield        android/util/Pair.first:Ljava/lang/Object;
        //   205: aload           9
        //   207: invokevirtual   azl.n:(Ljava/lang/Object;Lazj;)Lazj;
        //   210: getfield        azj.c:I
        //   213: istore          21
        //   215: lload           16
        //   217: lstore          14
        //   219: iconst_0       
        //   220: istore          6
        //   222: goto            251
        //   225: aload           20
        //   227: getfield        android/util/Pair.first:Ljava/lang/Object;
        //   230: astore          19
        //   232: aload           20
        //   234: getfield        android/util/Pair.second:Ljava/lang/Object;
        //   237: checkcast       Ljava/lang/Long;
        //   240: invokevirtual   java/lang/Long.longValue:()J
        //   243: lstore          14
        //   245: iconst_1       
        //   246: istore          6
        //   248: iconst_m1      
        //   249: istore          21
        //   251: aload_3        
        //   252: getfield        bfm.d:I
        //   255: iconst_4       
        //   256: if_icmpne       265
        //   259: iconst_1       
        //   260: istore          7
        //   262: goto            268
        //   265: iconst_0       
        //   266: istore          7
        //   268: iload           21
        //   270: istore          22
        //   272: iconst_0       
        //   273: istore          18
        //   275: iload           6
        //   277: istore          21
        //   279: iload           22
        //   281: istore          6
        //   283: iload           18
        //   285: istore          22
        //   287: iload           6
        //   289: istore          18
        //   291: iload           22
        //   293: istore          6
        //   295: goto            593
        //   298: aload_3        
        //   299: getfield        bfm.a:Lazl;
        //   302: invokevirtual   azl.p:()Z
        //   305: ifeq            344
        //   308: aload_1        
        //   309: iload           7
        //   311: invokevirtual   azl.g:(Z)I
        //   314: istore          6
        //   316: iconst_0       
        //   317: istore          21
        //   319: lload           16
        //   321: lstore          14
        //   323: iconst_0       
        //   324: istore          7
        //   326: iconst_0       
        //   327: istore          22
        //   329: iload           6
        //   331: istore          18
        //   333: iload           21
        //   335: istore          6
        //   337: iload           22
        //   339: istore          21
        //   341: goto            593
        //   344: aload_1        
        //   345: aload           19
        //   347: invokevirtual   azl.a:(Ljava/lang/Object;)I
        //   350: iconst_m1      
        //   351: if_icmpne       424
        //   354: aload           8
        //   356: aload           9
        //   358: iload           6
        //   360: iload           7
        //   362: aload           19
        //   364: aload_3        
        //   365: getfield        bfm.a:Lazl;
        //   368: aload_1        
        //   369: invokestatic    bez.a:(Lazk;Lazj;IZLjava/lang/Object;Lazl;Lazl;)Ljava/lang/Object;
        //   372: astore          20
        //   374: aload           20
        //   376: ifnonnull       393
        //   379: aload_1        
        //   380: iload           7
        //   382: invokevirtual   azl.g:(Z)I
        //   385: istore          21
        //   387: iconst_1       
        //   388: istore          6
        //   390: goto            409
        //   393: aload_1        
        //   394: aload           20
        //   396: aload           9
        //   398: invokevirtual   azl.n:(Ljava/lang/Object;Lazj;)Lazj;
        //   401: getfield        azj.c:I
        //   404: istore          21
        //   406: iconst_0       
        //   407: istore          6
        //   409: iload           6
        //   411: istore          18
        //   413: iload           21
        //   415: istore          6
        //   417: iload           18
        //   419: istore          21
        //   421: goto            319
        //   424: lload           16
        //   426: ldc2_w          -9223372036854775807
        //   429: lcmp           
        //   430: ifne            452
        //   433: aload_1        
        //   434: aload           19
        //   436: aload           9
        //   438: invokevirtual   azl.n:(Ljava/lang/Object;Lazj;)Lazj;
        //   441: getfield        azj.c:I
        //   444: istore          6
        //   446: iconst_0       
        //   447: istore          21
        //   449: goto            319
        //   452: iload           10
        //   454: ifeq            587
        //   457: aload_3        
        //   458: getfield        bfm.a:Lazl;
        //   461: astore          4
        //   463: aload           13
        //   465: astore          20
        //   467: aload           4
        //   469: aload           20
        //   471: getfield        ayx.a:Ljava/lang/Object;
        //   474: aload           9
        //   476: invokevirtual   azl.n:(Ljava/lang/Object;Lazj;)Lazj;
        //   479: pop            
        //   480: aload_3        
        //   481: getfield        bfm.a:Lazl;
        //   484: aload           9
        //   486: getfield        azj.c:I
        //   489: aload           8
        //   491: invokevirtual   azl.o:(ILazk;)Lazk;
        //   494: getfield        azk.o:I
        //   497: aload_3        
        //   498: getfield        bfm.a:Lazl;
        //   501: aload           20
        //   503: getfield        ayx.a:Ljava/lang/Object;
        //   506: invokevirtual   azl.a:(Ljava/lang/Object;)I
        //   509: if_icmpne       568
        //   512: aload           9
        //   514: getfield        azj.e:J
        //   517: lstore          14
        //   519: aload_1        
        //   520: aload           8
        //   522: aload           9
        //   524: aload_1        
        //   525: aload           19
        //   527: aload           9
        //   529: invokevirtual   azl.n:(Ljava/lang/Object;Lazj;)Lazj;
        //   532: getfield        azj.c:I
        //   535: lload           16
        //   537: lload           14
        //   539: ladd           
        //   540: invokevirtual   azl.k:(Lazk;Lazj;IJ)Landroid/util/Pair;
        //   543: astore          20
        //   545: aload           20
        //   547: getfield        android/util/Pair.first:Ljava/lang/Object;
        //   550: astore          19
        //   552: aload           20
        //   554: getfield        android/util/Pair.second:Ljava/lang/Object;
        //   557: checkcast       Ljava/lang/Long;
        //   560: invokevirtual   java/lang/Long.longValue:()J
        //   563: lstore          14
        //   565: goto            572
        //   568: lload           16
        //   570: lstore          14
        //   572: iconst_m1      
        //   573: istore          18
        //   575: iconst_0       
        //   576: istore          7
        //   578: iconst_0       
        //   579: istore          6
        //   581: iconst_1       
        //   582: istore          21
        //   584: goto            593
        //   587: iconst_m1      
        //   588: istore          6
        //   590: goto            446
        //   593: iload           18
        //   595: iconst_m1      
        //   596: if_icmpeq       642
        //   599: aload_1        
        //   600: aload           8
        //   602: aload           9
        //   604: iload           18
        //   606: ldc2_w          -9223372036854775807
        //   609: invokevirtual   azl.k:(Lazk;Lazj;IJ)Landroid/util/Pair;
        //   612: astore          20
        //   614: aload           20
        //   616: getfield        android/util/Pair.first:Ljava/lang/Object;
        //   619: astore          19
        //   621: aload           20
        //   623: getfield        android/util/Pair.second:Ljava/lang/Object;
        //   626: checkcast       Ljava/lang/Long;
        //   629: invokevirtual   java/lang/Long.longValue:()J
        //   632: lstore          14
        //   634: ldc2_w          -9223372036854775807
        //   637: lstore          23
        //   639: goto            646
        //   642: lload           14
        //   644: lstore          23
        //   646: aload           5
        //   648: aload_1        
        //   649: aload           19
        //   651: lload           14
        //   653: invokevirtual   bff.k:(Lazl;Ljava/lang/Object;J)Layx;
        //   656: astore          20
        //   658: aload           20
        //   660: getfield        ayx.e:I
        //   663: istore          22
        //   665: iload           22
        //   667: iconst_m1      
        //   668: if_icmpeq       700
        //   671: aload           13
        //   673: getfield        ayx.e:I
        //   676: istore          18
        //   678: iload           18
        //   680: iconst_m1      
        //   681: if_icmpeq       694
        //   684: iload           22
        //   686: iload           18
        //   688: if_icmplt       694
        //   691: goto            700
        //   694: iconst_0       
        //   695: istore          18
        //   697: goto            703
        //   700: iconst_1       
        //   701: istore          18
        //   703: aload           13
        //   705: getfield        ayx.a:Ljava/lang/Object;
        //   708: aload           19
        //   710: invokevirtual   java/lang/Object.equals:(Ljava/lang/Object;)Z
        //   713: ifeq            743
        //   716: aload           13
        //   718: invokevirtual   ayx.a:()Z
        //   721: ifne            743
        //   724: aload           20
        //   726: invokevirtual   ayx.a:()Z
        //   729: ifne            743
        //   732: iload           18
        //   734: ifeq            743
        //   737: iconst_1       
        //   738: istore          18
        //   740: goto            746
        //   743: iconst_0       
        //   744: istore          18
        //   746: aload_1        
        //   747: aload           19
        //   749: aload           9
        //   751: invokevirtual   azl.n:(Ljava/lang/Object;Lazj;)Lazj;
        //   754: astore          19
        //   756: iload           10
        //   758: ifne            824
        //   761: lload           16
        //   763: lload           23
        //   765: lcmp           
        //   766: ifne            824
        //   769: aload           13
        //   771: getfield        ayx.a:Ljava/lang/Object;
        //   774: aload           20
        //   776: getfield        ayx.a:Ljava/lang/Object;
        //   779: invokevirtual   java/lang/Object.equals:(Ljava/lang/Object;)Z
        //   782: ifne            788
        //   785: goto            824
        //   788: aload           13
        //   790: invokevirtual   ayx.a:()Z
        //   793: ifeq            806
        //   796: aload           19
        //   798: aload           13
        //   800: getfield        ayx.b:I
        //   803: invokevirtual   azj.k:(I)V
        //   806: aload           20
        //   808: invokevirtual   ayx.a:()Z
        //   811: ifeq            824
        //   814: aload           19
        //   816: aload           20
        //   818: getfield        ayx.b:I
        //   821: invokevirtual   azj.k:(I)V
        //   824: aload           20
        //   826: astore          19
        //   828: iconst_1       
        //   829: iload           18
        //   831: if_icmpne       838
        //   834: aload           13
        //   836: astore          19
        //   838: lload           14
        //   840: lstore          16
        //   842: aload           19
        //   844: invokevirtual   ayx.a:()Z
        //   847: ifeq            907
        //   850: aload           19
        //   852: aload           13
        //   854: invokevirtual   ayx.equals:(Ljava/lang/Object;)Z
        //   857: ifeq            869
        //   860: aload_3        
        //   861: getfield        bfm.o:J
        //   864: lstore          16
        //   866: goto            907
        //   869: aload_1        
        //   870: aload           19
        //   872: getfield        ayx.a:Ljava/lang/Object;
        //   875: aload           9
        //   877: invokevirtual   azl.n:(Ljava/lang/Object;Lazj;)Lazj;
        //   880: pop            
        //   881: aload           19
        //   883: getfield        ayx.c:I
        //   886: aload           9
        //   888: aload           19
        //   890: getfield        ayx.b:I
        //   893: invokevirtual   azj.d:(I)I
        //   896: if_icmpne       904
        //   899: aload           9
        //   901: invokevirtual   azj.j:()V
        //   904: lconst_0       
        //   905: lstore          16
        //   907: iload           6
        //   909: istore          18
        //   911: lload           16
        //   913: lstore          14
        //   915: iload           21
        //   917: istore          6
        //   919: lload           23
        //   921: lstore          16
        //   923: aload           19
        //   925: astore          13
        //   927: aload_0        
        //   928: getfield        bez.w:Lbfm;
        //   931: getfield        bfm.q:Layx;
        //   934: aload           13
        //   936: invokevirtual   ayx.equals:(Ljava/lang/Object;)Z
        //   939: ifeq            964
        //   942: lload           14
        //   944: aload_0        
        //   945: getfield        bez.w:Lbfm;
        //   948: getfield        bfm.o:J
        //   951: lcmp           
        //   952: ifeq            958
        //   955: goto            964
        //   958: iconst_0       
        //   959: istore          21
        //   961: goto            967
        //   964: iconst_1       
        //   965: istore          21
        //   967: iload           18
        //   969: ifeq            1022
        //   972: lload           16
        //   974: lstore          23
        //   976: aload_0        
        //   977: getfield        bez.w:Lbfm;
        //   980: getfield        bfm.d:I
        //   983: iconst_1       
        //   984: if_icmpeq       999
        //   987: lload           16
        //   989: lstore          23
        //   991: aload_0        
        //   992: iconst_4       
        //   993: invokespecial   bez.E:(I)V
        //   996: goto            999
        //   999: lload           16
        //  1001: lstore          23
        //  1003: aload_0        
        //  1004: iconst_0       
        //  1005: iconst_0       
        //  1006: iconst_0       
        //  1007: iconst_1       
        //  1008: invokespecial   bez.w:(ZZZZ)V
        //  1011: goto            1022
        //  1014: astore          19
        //  1016: iconst_4       
        //  1017: istore          18
        //  1019: goto            2134
        //  1022: iload           21
        //  1024: ifne            1738
        //  1027: lload           16
        //  1029: lstore          23
        //  1031: aload_0        
        //  1032: getfield        bez.s:Lbff;
        //  1035: astore_3       
        //  1036: lload           16
        //  1038: lstore          23
        //  1040: aload_0        
        //  1041: getfield        bez.H:J
        //  1044: lstore          25
        //  1046: lload           16
        //  1048: lstore          23
        //  1050: aload_3        
        //  1051: getfield        bff.e:Lbfd;
        //  1054: astore          19
        //  1056: aload           19
        //  1058: ifnonnull       1067
        //  1061: lconst_0       
        //  1062: lstore          27
        //  1064: goto            1236
        //  1067: lload           16
        //  1069: lstore          23
        //  1071: aload           19
        //  1073: getfield        bfd.j:J
        //  1076: lstore          27
        //  1078: lload           16
        //  1080: lstore          23
        //  1082: aload           19
        //  1084: getfield        bfd.d:Z
        //  1087: ifne            1093
        //  1090: goto            1236
        //  1093: iconst_0       
        //  1094: istore          18
        //  1096: lload           16
        //  1098: lstore          23
        //  1100: aload_0        
        //  1101: getfield        bez.e:[Lbfq;
        //  1104: astore          20
        //  1106: lload           16
        //  1108: lstore          23
        //  1110: iload           18
        //  1112: aload           20
        //  1114: arraylength    
        //  1115: if_icmpge       1236
        //  1118: lload           16
        //  1120: lstore          23
        //  1122: aload           20
        //  1124: iload           18
        //  1126: aaload         
        //  1127: invokestatic    bez.M:(Lbfq;)Z
        //  1130: ifeq            1222
        //  1133: lload           16
        //  1135: lstore          23
        //  1137: aload_0        
        //  1138: getfield        bez.e:[Lbfq;
        //  1141: iload           18
        //  1143: aaload         
        //  1144: invokeinterface bfq.q:()Lbov;
        //  1149: aload           19
        //  1151: getfield        bfd.c:[Lbov;
        //  1154: iload           18
        //  1156: aaload         
        //  1157: if_acmpeq       1163
        //  1160: goto            1222
        //  1163: lload           16
        //  1165: lstore          23
        //  1167: aload_0        
        //  1168: getfield        bez.e:[Lbfq;
        //  1171: iload           18
        //  1173: aaload         
        //  1174: invokeinterface bfq.k:()J
        //  1179: lstore          29
        //  1181: lload           29
        //  1183: ldc2_w          -9223372036854775808
        //  1186: lcmp           
        //  1187: ifne            1198
        //  1190: ldc2_w          -9223372036854775808
        //  1193: lstore          27
        //  1195: goto            1236
        //  1198: lload           16
        //  1200: lstore          23
        //  1202: lload           14
        //  1204: lstore          31
        //  1206: lload           29
        //  1208: lload           27
        //  1210: invokestatic    java/lang/Math.max:(JJ)J
        //  1213: lstore          27
        //  1215: lload           27
        //  1217: lstore          23
        //  1219: goto            1226
        //  1222: lload           27
        //  1224: lstore          23
        //  1226: iinc            18, 1
        //  1229: lload           23
        //  1231: lstore          27
        //  1233: goto            1096
        //  1236: lload           14
        //  1238: lstore          31
        //  1240: lload           16
        //  1242: lstore          23
        //  1244: aload_3        
        //  1245: getfield        bff.d:Lbfd;
        //  1248: astore          19
        //  1250: aconst_null    
        //  1251: astore          20
        //  1253: lload           14
        //  1255: lstore          23
        //  1257: aload           19
        //  1259: ifnull          1722
        //  1262: lload           14
        //  1264: lstore          31
        //  1266: lload           16
        //  1268: lstore          23
        //  1270: aload           19
        //  1272: getfield        bfd.f:Lbfe;
        //  1275: astore          5
        //  1277: aload           20
        //  1279: ifnonnull       1302
        //  1282: lload           14
        //  1284: lstore          31
        //  1286: lload           16
        //  1288: lstore          23
        //  1290: aload_3        
        //  1291: aload_1        
        //  1292: aload           5
        //  1294: invokevirtual   bff.c:(Lazl;Lbfe;)Lbfe;
        //  1297: astore          20
        //  1299: goto            1419
        //  1302: lload           14
        //  1304: lstore          31
        //  1306: lload           16
        //  1308: lstore          23
        //  1310: aload_3        
        //  1311: aload_1        
        //  1312: aload           20
        //  1314: lload           25
        //  1316: invokevirtual   bff.b:(Lazl;Lbfd;J)Lbfe;
        //  1319: astore          9
        //  1321: aload           9
        //  1323: ifnonnull       1353
        //  1326: lload           14
        //  1328: lstore          31
        //  1330: lload           16
        //  1332: lstore          23
        //  1334: aload_3        
        //  1335: aload           20
        //  1337: invokevirtual   bff.h:(Lbfd;)Z
        //  1340: ifne            1350
        //  1343: lload           14
        //  1345: lstore          23
        //  1347: goto            1722
        //  1350: goto            1698
        //  1353: lload           14
        //  1355: lstore          31
        //  1357: lload           16
        //  1359: lstore          23
        //  1361: aload           5
        //  1363: getfield        bfe.a:J
        //  1366: lstore          33
        //  1368: lload           14
        //  1370: lstore          29
        //  1372: lload           16
        //  1374: lstore          31
        //  1376: lload           29
        //  1378: lstore          23
        //  1380: lload           33
        //  1382: aload           9
        //  1384: getfield        bfe.a:J
        //  1387: lcmp           
        //  1388: ifne            1674
        //  1391: lload           16
        //  1393: lstore          31
        //  1395: lload           29
        //  1397: lstore          23
        //  1399: aload           5
        //  1401: getfield        bfe.i:Layx;
        //  1404: aload           9
        //  1406: getfield        bfe.i:Layx;
        //  1409: invokevirtual   ayx.equals:(Ljava/lang/Object;)Z
        //  1412: ifeq            1674
        //  1415: aload           9
        //  1417: astore          20
        //  1419: lload           14
        //  1421: lstore          29
        //  1423: lload           16
        //  1425: lstore          31
        //  1427: lload           29
        //  1429: lstore          23
        //  1431: aload           19
        //  1433: aload           20
        //  1435: aload           5
        //  1437: getfield        bfe.b:J
        //  1440: invokevirtual   bfe.a:(J)Lbfe;
        //  1443: putfield        bfd.f:Lbfe;
        //  1446: lload           16
        //  1448: lstore          31
        //  1450: lload           29
        //  1452: lstore          23
        //  1454: aload           5
        //  1456: getfield        bfe.d:J
        //  1459: lstore          33
        //  1461: lload           16
        //  1463: lstore          31
        //  1465: lload           29
        //  1467: lstore          23
        //  1469: aload           20
        //  1471: getfield        bfe.d:J
        //  1474: lstore          35
        //  1476: lload           33
        //  1478: ldc2_w          -9223372036854775807
        //  1481: lcmp           
        //  1482: ifeq            1644
        //  1485: lload           33
        //  1487: lload           35
        //  1489: lcmp           
        //  1490: ifne            1496
        //  1493: goto            1644
        //  1496: lload           16
        //  1498: lstore          31
        //  1500: lload           29
        //  1502: lstore          23
        //  1504: aload           19
        //  1506: invokevirtual   bfd.h:()V
        //  1509: lload           16
        //  1511: lstore          31
        //  1513: lload           29
        //  1515: lstore          23
        //  1517: aload           20
        //  1519: getfield        bfe.d:J
        //  1522: lstore          25
        //  1524: lload           25
        //  1526: ldc2_w          -9223372036854775807
        //  1529: lcmp           
        //  1530: ifne            1541
        //  1533: ldc2_w          9223372036854775807
        //  1536: lstore          25
        //  1538: goto            1558
        //  1541: lload           16
        //  1543: lstore          31
        //  1545: lload           29
        //  1547: lstore          23
        //  1549: aload           19
        //  1551: lload           25
        //  1553: invokevirtual   bfd.e:(J)J
        //  1556: lstore          25
        //  1558: lload           16
        //  1560: lstore          31
        //  1562: lload           29
        //  1564: lstore          23
        //  1566: aload           19
        //  1568: aload_3        
        //  1569: getfield        bff.e:Lbfd;
        //  1572: if_acmpne       1616
        //  1575: lload           16
        //  1577: lstore          31
        //  1579: lload           29
        //  1581: lstore          23
        //  1583: aload           19
        //  1585: getfield        bfd.f:Lbfe;
        //  1588: getfield        bfe.e:Z
        //  1591: istore          7
        //  1593: lload           27
        //  1595: ldc2_w          -9223372036854775808
        //  1598: lcmp           
        //  1599: ifeq            1610
        //  1602: lload           27
        //  1604: lload           25
        //  1606: lcmp           
        //  1607: iflt            1616
        //  1610: iconst_1       
        //  1611: istore          18
        //  1613: goto            1619
        //  1616: iconst_0       
        //  1617: istore          18
        //  1619: lload           16
        //  1621: lstore          31
        //  1623: lload           29
        //  1625: lstore          23
        //  1627: aload_3        
        //  1628: aload           19
        //  1630: invokevirtual   bff.h:(Lbfd;)Z
        //  1633: ifne            1350
        //  1636: iload           18
        //  1638: ifne            1350
        //  1641: goto            1691
        //  1644: lload           16
        //  1646: lstore          31
        //  1648: lload           29
        //  1650: lstore          23
        //  1652: aload           19
        //  1654: getfield        bfd.h:Lbfd;
        //  1657: astore          9
        //  1659: aload           19
        //  1661: astore          20
        //  1663: lload           29
        //  1665: lstore          14
        //  1667: aload           9
        //  1669: astore          19
        //  1671: goto            1253
        //  1674: lload           16
        //  1676: lstore          31
        //  1678: lload           29
        //  1680: lstore          23
        //  1682: aload_3        
        //  1683: aload           20
        //  1685: invokevirtual   bff.h:(Lbfd;)Z
        //  1688: ifne            1350
        //  1691: lload           14
        //  1693: lstore          23
        //  1695: goto            1722
        //  1698: lload           16
        //  1700: lstore          31
        //  1702: lload           14
        //  1704: lstore          23
        //  1706: aload_0        
        //  1707: iconst_0       
        //  1708: invokespecial   bez.B:(Z)V
        //  1711: lload           16
        //  1713: lstore          27
        //  1715: lload           14
        //  1717: lstore          29
        //  1719: goto            1887
        //  1722: lload           23
        //  1724: lstore          14
        //  1726: goto            1895
        //  1729: astore          19
        //  1731: lload           31
        //  1733: lstore          14
        //  1735: goto            1016
        //  1738: lload           16
        //  1740: lstore          27
        //  1742: lload           14
        //  1744: lstore          29
        //  1746: lload           16
        //  1748: lstore          31
        //  1750: lload           14
        //  1752: lstore          23
        //  1754: aload_1        
        //  1755: invokevirtual   azl.p:()Z
        //  1758: ifne            1887
        //  1761: lload           16
        //  1763: lstore          31
        //  1765: lload           14
        //  1767: lstore          23
        //  1769: aload_0        
        //  1770: getfield        bez.s:Lbff;
        //  1773: getfield        bff.d:Lbfd;
        //  1776: astore          19
        //  1778: aload           19
        //  1780: ifnull          1864
        //  1783: lload           16
        //  1785: lstore          31
        //  1787: lload           14
        //  1789: lstore          23
        //  1791: aload           19
        //  1793: getfield        bfd.f:Lbfe;
        //  1796: getfield        bfe.i:Layx;
        //  1799: aload           13
        //  1801: invokevirtual   ayx.equals:(Ljava/lang/Object;)Z
        //  1804: ifeq            1846
        //  1807: lload           16
        //  1809: lstore          31
        //  1811: lload           14
        //  1813: lstore          23
        //  1815: aload           19
        //  1817: aload_0        
        //  1818: getfield        bez.s:Lbff;
        //  1821: aload_1        
        //  1822: aload           19
        //  1824: getfield        bfd.f:Lbfe;
        //  1827: invokevirtual   bff.c:(Lazl;Lbfe;)Lbfe;
        //  1830: putfield        bfd.f:Lbfe;
        //  1833: lload           16
        //  1835: lstore          31
        //  1837: lload           14
        //  1839: lstore          23
        //  1841: aload           19
        //  1843: invokevirtual   bfd.h:()V
        //  1846: lload           16
        //  1848: lstore          31
        //  1850: lload           14
        //  1852: lstore          23
        //  1854: aload           19
        //  1856: getfield        bfd.h:Lbfd;
        //  1859: astore          19
        //  1861: goto            1778
        //  1864: lload           14
        //  1866: lstore          31
        //  1868: lload           16
        //  1870: lstore          23
        //  1872: aload_0        
        //  1873: aload           13
        //  1875: lload           14
        //  1877: iload           7
        //  1879: invokespecial   bez.S:(Layx;JZ)J
        //  1882: lstore          14
        //  1884: goto            1895
        //  1887: lload           29
        //  1889: lstore          14
        //  1891: lload           27
        //  1893: lstore          16
        //  1895: aload_0        
        //  1896: getfield        bez.w:Lbfm;
        //  1899: astore          20
        //  1901: aload           20
        //  1903: getfield        bfm.a:Lazl;
        //  1906: astore          19
        //  1908: aload           20
        //  1910: getfield        bfm.q:Layx;
        //  1913: astore          20
        //  1915: iconst_1       
        //  1916: iload           6
        //  1918: if_icmpeq       1929
        //  1921: ldc2_w          -9223372036854775807
        //  1924: lstore          23
        //  1926: goto            1933
        //  1929: lload           14
        //  1931: lstore          23
        //  1933: iconst_4       
        //  1934: istore          6
        //  1936: aload_0        
        //  1937: aload_1        
        //  1938: aload           13
        //  1940: aload           19
        //  1942: aload           20
        //  1944: lload           23
        //  1946: invokespecial   bez.V:(Lazl;Layx;Lazl;Layx;J)V
        //  1949: iload           21
        //  1951: ifne            1967
        //  1954: lload           16
        //  1956: aload_0        
        //  1957: getfield        bez.w:Lbfm;
        //  1960: getfield        bfm.b:J
        //  1963: lcmp           
        //  1964: ifeq            2075
        //  1967: aload_0        
        //  1968: getfield        bez.w:Lbfm;
        //  1971: astore          20
        //  1973: aload           20
        //  1975: getfield        bfm.q:Layx;
        //  1978: getfield        ayx.a:Ljava/lang/Object;
        //  1981: astore          19
        //  1983: aload           20
        //  1985: getfield        bfm.a:Lazl;
        //  1988: astore          20
        //  1990: iload           21
        //  1992: ifeq            2029
        //  1995: iload_2        
        //  1996: ifeq            2029
        //  1999: aload           20
        //  2001: invokevirtual   azl.p:()Z
        //  2004: ifne            2029
        //  2007: aload           20
        //  2009: aload           19
        //  2011: aload_0        
        //  2012: getfield        bez.m:Lazj;
        //  2015: invokevirtual   azl.n:(Ljava/lang/Object;Lazj;)Lazj;
        //  2018: getfield        azj.f:Z
        //  2021: ifne            2029
        //  2024: iconst_1       
        //  2025: istore_2       
        //  2026: goto            2031
        //  2029: iconst_0       
        //  2030: istore_2       
        //  2031: aload_0        
        //  2032: getfield        bez.w:Lbfm;
        //  2035: getfield        bfm.c:J
        //  2038: lstore          23
        //  2040: aload_1        
        //  2041: aload           19
        //  2043: invokevirtual   azl.a:(Ljava/lang/Object;)I
        //  2046: iconst_m1      
        //  2047: if_icmpne       2053
        //  2050: goto            2056
        //  2053: iconst_3       
        //  2054: istore          6
        //  2056: aload_0        
        //  2057: aload_0        
        //  2058: aload           13
        //  2060: lload           14
        //  2062: lload           16
        //  2064: lload           23
        //  2066: iload_2        
        //  2067: iload           6
        //  2069: invokespecial   bez.U:(Layx;JJJZI)Lbfm;
        //  2072: putfield        bez.w:Lbfm;
        //  2075: aload_0        
        //  2076: invokespecial   bez.x:()V
        //  2079: aload_0        
        //  2080: aload_1        
        //  2081: aload_0        
        //  2082: getfield        bez.w:Lbfm;
        //  2085: getfield        bfm.a:Lazl;
        //  2088: invokespecial   bez.z:(Lazl;Lazl;)V
        //  2091: aload_0        
        //  2092: aload_0        
        //  2093: getfield        bez.w:Lbfm;
        //  2096: aload_1        
        //  2097: invokevirtual   bfm.e:(Lazl;)Lbfm;
        //  2100: putfield        bez.w:Lbfm;
        //  2103: aload_1        
        //  2104: invokevirtual   azl.p:()Z
        //  2107: ifne            2115
        //  2110: aload_0        
        //  2111: aconst_null    
        //  2112: putfield        bez.G:Lbey;
        //  2115: aload_0        
        //  2116: iconst_0       
        //  2117: invokespecial   bez.q:(Z)V
        //  2120: return         
        //  2121: astore          19
        //  2123: lload           23
        //  2125: lstore          14
        //  2127: lload           31
        //  2129: lstore          23
        //  2131: goto            1016
        //  2134: aload_0        
        //  2135: getfield        bez.w:Lbfm;
        //  2138: astore          9
        //  2140: aload           9
        //  2142: getfield        bfm.a:Lazl;
        //  2145: astore          20
        //  2147: aload           9
        //  2149: getfield        bfm.q:Layx;
        //  2152: astore          9
        //  2154: iconst_1       
        //  2155: iload           6
        //  2157: if_icmpeq       2167
        //  2160: lload           11
        //  2162: lstore          16
        //  2164: goto            2171
        //  2167: lload           14
        //  2169: lstore          16
        //  2171: iconst_1       
        //  2172: istore          7
        //  2174: aload_0        
        //  2175: aload_1        
        //  2176: aload           13
        //  2178: aload           20
        //  2180: aload           9
        //  2182: lload           16
        //  2184: invokespecial   bez.V:(Lazl;Layx;Lazl;Layx;J)V
        //  2187: iload           21
        //  2189: ifne            2205
        //  2192: lload           23
        //  2194: aload_0        
        //  2195: getfield        bez.w:Lbfm;
        //  2198: getfield        bfm.b:J
        //  2201: lcmp           
        //  2202: ifeq            2318
        //  2205: aload_0        
        //  2206: getfield        bez.w:Lbfm;
        //  2209: astore          9
        //  2211: aload           9
        //  2213: getfield        bfm.q:Layx;
        //  2216: getfield        ayx.a:Ljava/lang/Object;
        //  2219: astore          20
        //  2221: aload           9
        //  2223: getfield        bfm.a:Lazl;
        //  2226: astore          9
        //  2228: iload           21
        //  2230: ifeq            2268
        //  2233: iload_2        
        //  2234: ifeq            2268
        //  2237: aload           9
        //  2239: invokevirtual   azl.p:()Z
        //  2242: ifne            2268
        //  2245: aload           9
        //  2247: aload           20
        //  2249: aload_0        
        //  2250: getfield        bez.m:Lazj;
        //  2253: invokevirtual   azl.n:(Ljava/lang/Object;Lazj;)Lazj;
        //  2256: getfield        azj.f:Z
        //  2259: ifne            2268
        //  2262: iload           7
        //  2264: istore_2       
        //  2265: goto            2270
        //  2268: iconst_0       
        //  2269: istore_2       
        //  2270: aload_0        
        //  2271: getfield        bez.w:Lbfm;
        //  2274: getfield        bfm.c:J
        //  2277: lstore          16
        //  2279: aload_1        
        //  2280: aload           20
        //  2282: invokevirtual   azl.a:(Ljava/lang/Object;)I
        //  2285: iconst_m1      
        //  2286: if_icmpne       2296
        //  2289: iload           18
        //  2291: istore          6
        //  2293: goto            2299
        //  2296: iconst_3       
        //  2297: istore          6
        //  2299: aload_0        
        //  2300: aload_0        
        //  2301: aload           13
        //  2303: lload           14
        //  2305: lload           23
        //  2307: lload           16
        //  2309: iload_2        
        //  2310: iload           6
        //  2312: invokespecial   bez.U:(Layx;JJJZI)Lbfm;
        //  2315: putfield        bez.w:Lbfm;
        //  2318: aload_0        
        //  2319: invokespecial   bez.x:()V
        //  2322: aload_0        
        //  2323: aload_1        
        //  2324: aload_0        
        //  2325: getfield        bez.w:Lbfm;
        //  2328: getfield        bfm.a:Lazl;
        //  2331: invokespecial   bez.z:(Lazl;Lazl;)V
        //  2334: aload_0        
        //  2335: aload_0        
        //  2336: getfield        bez.w:Lbfm;
        //  2339: aload_1        
        //  2340: invokevirtual   bfm.e:(Lazl;)Lbfm;
        //  2343: putfield        bez.w:Lbfm;
        //  2346: aload_1        
        //  2347: invokevirtual   azl.p:()Z
        //  2350: ifne            2358
        //  2353: aload_0        
        //  2354: aconst_null    
        //  2355: putfield        bez.G:Lbey;
        //  2358: aload_0        
        //  2359: iconst_0       
        //  2360: invokespecial   bez.q:(Z)V
        //  2363: goto            2369
        //  2366: aload           19
        //  2368: athrow         
        //  2369: goto            2366
        //    Exceptions:
        //  Try           Handler
        //  Start  End    Start  End    Type
        //  -----  -----  -----  -----  ----
        //  976    987    1014   1016   Any
        //  991    996    1014   1016   Any
        //  1003   1011   1014   1016   Any
        //  1031   1036   1014   1016   Any
        //  1040   1046   1014   1016   Any
        //  1050   1056   1014   1016   Any
        //  1071   1078   1014   1016   Any
        //  1082   1090   1014   1016   Any
        //  1100   1106   1014   1016   Any
        //  1110   1118   1014   1016   Any
        //  1122   1133   1014   1016   Any
        //  1137   1160   1014   1016   Any
        //  1167   1181   1014   1016   Any
        //  1206   1215   1729   1738   Any
        //  1244   1250   1729   1738   Any
        //  1270   1277   1729   1738   Any
        //  1290   1299   1729   1738   Any
        //  1310   1321   1729   1738   Any
        //  1334   1343   1729   1738   Any
        //  1361   1368   1729   1738   Any
        //  1380   1391   2121   2134   Any
        //  1399   1415   2121   2134   Any
        //  1431   1446   2121   2134   Any
        //  1454   1461   2121   2134   Any
        //  1469   1476   2121   2134   Any
        //  1504   1509   2121   2134   Any
        //  1517   1524   2121   2134   Any
        //  1549   1558   2121   2134   Any
        //  1566   1575   2121   2134   Any
        //  1583   1593   2121   2134   Any
        //  1627   1636   2121   2134   Any
        //  1652   1659   2121   2134   Any
        //  1682   1691   2121   2134   Any
        //  1706   1711   2121   2134   Any
        //  1754   1761   2121   2134   Any
        //  1769   1778   2121   2134   Any
        //  1791   1807   2121   2134   Any
        //  1815   1833   2121   2134   Any
        //  1841   1846   2121   2134   Any
        //  1854   1861   2121   2134   Any
        //  1872   1884   1729   1738   Any
        // 
        // The error that occurred was:
        // 
        // java.lang.IllegalStateException: Expression is linked from several locations: Label_1419:
        //     at com.strobel.decompiler.ast.Error.expressionLinkedFromMultipleLocations(Error.java:27)
        //     at com.strobel.decompiler.ast.AstOptimizer.mergeDisparateObjectInitializations(AstOptimizer.java:2604)
        //     at com.strobel.decompiler.ast.AstOptimizer.optimize(AstOptimizer.java:235)
        //     at com.strobel.decompiler.ast.AstOptimizer.optimize(AstOptimizer.java:42)
        //     at com.strobel.decompiler.languages.java.ast.AstMethodBodyBuilder.createMethodBody(AstMethodBodyBuilder.java:206)
        //     at com.strobel.decompiler.languages.java.ast.AstMethodBodyBuilder.createMethodBody(AstMethodBodyBuilder.java:93)
        //     at com.strobel.decompiler.languages.java.ast.AstBuilder.createMethodBody(AstBuilder.java:868)
        //     at com.strobel.decompiler.languages.java.ast.AstBuilder.createMethod(AstBuilder.java:761)
        //     at com.strobel.decompiler.languages.java.ast.AstBuilder.addTypeMembers(AstBuilder.java:638)
        //     at com.strobel.decompiler.languages.java.ast.AstBuilder.createTypeCore(AstBuilder.java:605)
        //     at com.strobel.decompiler.languages.java.ast.AstBuilder.createTypeNoCache(AstBuilder.java:195)
        //     at com.strobel.decompiler.languages.java.ast.AstBuilder.createType(AstBuilder.java:162)
        //     at com.strobel.decompiler.languages.java.ast.AstBuilder.addType(AstBuilder.java:137)
        //     at com.strobel.decompiler.languages.java.JavaLanguage.buildAst(JavaLanguage.java:71)
        //     at com.strobel.decompiler.languages.java.JavaLanguage.decompileType(JavaLanguage.java:59)
        //     at com.strobel.decompiler.DecompilerDriver.decompileType(DecompilerDriver.java:333)
        //     at com.strobel.decompiler.DecompilerDriver.decompileJar(DecompilerDriver.java:254)
        //     at com.strobel.decompiler.DecompilerDriver.main(DecompilerDriver.java:129)
        // 
        throw new IllegalStateException("An error occurred while decompiling this method.");
    }
    
    private final void s(final azb azb, final boolean b) {
        this.t(azb, azb.b, true, b);
    }
    
    private final void t(final azb azb, final float n, final boolean b, final boolean b2) {
        if (b) {
            if (b2) {
                this.N.b(1);
            }
            this.w = this.w.c(azb);
        }
        final float b3 = azb.b;
        bfd bfd = this.s.d;
        int n2;
        while (true) {
            n2 = 0;
            int i = 0;
            if (bfd == null) {
                break;
            }
            for (bqv[] array = (bqv[])bfd.k.c; i < array.length; ++i) {
                final bqv bqv = array[i];
                if (bqv != null) {
                    bqv.n(b3);
                }
            }
            bfd = bfd.h;
        }
        final bfq[] e = this.e;
        for (int length = e.length, j = n2; j < length; ++j) {
            final bfq bfq = e[j];
            if (bfq != null) {
                bfq.H(n, azb.b);
            }
        }
    }
    
    private final void u() {
        final boolean l = this.L();
        boolean a = false;
        if (l) {
            final bfd f = this.s.f;
            final long i = this.i(f.b());
            long d;
            if (f == this.s.d) {
                d = f.d(this.H);
            }
            else {
                d = f.d(this.H) - f.f.a;
            }
            a = this.i.h(d, i, this.p.kI().b);
            if (!a && i < 500000L && (this.n > 0L || this.o)) {
                this.s.d.a.i(this.w.o, false);
                a = this.i.h(d, i, this.p.kI().b);
            }
        }
        if (this.A = a) {
            final bfd f2 = this.s.f;
            final long h = this.H;
            dk.h(f2.j());
            f2.a.n(f2.d(h));
        }
        this.I();
    }
    
    private final void v() {
        final lzz n = this.N;
        final bfm w = this.w;
        final boolean d = n.d | n.g != w;
        n.d = d;
        n.g = w;
        if (d) {
            this.P.aa(n);
            this.N = new lzz(this.w);
        }
    }
    
    private final void w(final boolean b, final boolean b2, final boolean b3, final boolean b4) {
        this.a.c();
        final bee bee = null;
        this.K = null;
        this.z = false;
        this.p.d();
        this.H = 1000000000000L;
        for (final bfq bfq : this.e) {
            Label_0091: {
                try {
                    this.l(bfq);
                    break Label_0091;
                }
                catch (final RuntimeException bfq) {}
                catch (final bee bee2) {}
                bao.b("ExoPlayerImplInternal", "Disable failed.", (Throwable)bfq);
            }
        }
        if (b) {
            for (final bfq bfq2 : this.e) {
                if (this.f.remove(bfq2)) {
                    try {
                        bfq2.E();
                    }
                    catch (final RuntimeException ex) {
                        bao.b("ExoPlayerImplInternal", "Reset failed.", (Throwable)ex);
                    }
                }
            }
        }
        this.F = 0;
        final bfm w = this.w;
        ayx q = w.q;
        long o = w.o;
        long n;
        if (!this.w.q.a() && !O(this.w, this.m)) {
            n = this.w.o;
        }
        else {
            n = this.w.b;
        }
        boolean b5 = false;
        Label_0348: {
            if (b2) {
                this.G = null;
                final Pair k = this.j(this.w.a);
                final ayx ayx = (ayx)k.first;
                final long longValue = (long)k.second;
                final boolean equals = ayx.equals((Object)this.w.q);
                final long n2 = -9223372036854775807L;
                q = ayx;
                o = longValue;
                n = n2;
                if (!equals) {
                    b5 = true;
                    q = ayx;
                    o = longValue;
                    n = n2;
                    break Label_0348;
                }
            }
            b5 = false;
        }
        this.s.d();
        this.A = false;
        final bfm w2 = this.w;
        final azl a = w2.a;
        final int d = w2.d;
        bee e3;
        if (b4) {
            e3 = bee;
        }
        else {
            e3 = w2.e;
        }
        bpd bpd;
        if (b5) {
            bpd = bpd.a;
        }
        else {
            bpd = w2.g;
        }
        aetc aetc;
        if (b5) {
            aetc = this.O;
        }
        else {
            aetc = this.w.s;
        }
        Object o2;
        if (b5) {
            o2 = afcr.q();
        }
        else {
            o2 = this.w.h;
        }
        final bfm w3 = this.w;
        this.w = new bfm(a, q, n, o, d, e3, false, bpd, aetc, (List)o2, q, w3.i, w3.j, w3.k, o, 0L, o, false, (byte[])null, (byte[])null, (byte[])null);
        if (b3) {
            final bfl t = this.t;
            for (final alm alm : t.f.values()) {
                try {
                    ((bnx)alm.c).z((bnw)alm.b);
                }
                catch (final RuntimeException ex2) {
                    bao.b("MediaSourceList", "Failed to release child source.", (Throwable)ex2);
                }
                ((bnx)alm.c).B((bnz)alm.a);
                ((bnx)alm.c).A((bkm)alm.a);
            }
            t.f.clear();
            t.g.clear();
            t.h = false;
        }
    }
    
    private final void x() {
        final bfd d = this.s.d;
        boolean y;
        final boolean b = y = false;
        if (d != null) {
            y = b;
            if (d.f.g) {
                y = b;
                if (this.x) {
                    y = true;
                }
            }
        }
        this.y = y;
    }
    
    private final void y(long e) {
        final bfd d = this.s.d;
        if (d == null) {
            e += 1000000000000L;
        }
        else {
            e = d.e(e);
        }
        this.H = e;
        this.p.a.d(e);
        for (final bfq bfq : this.e) {
            if (M(bfq)) {
                bfq.F(this.H);
            }
        }
        for (bfd bfd = this.s.d; bfd != null; bfd = bfd.h) {
            for (final bqv bqv : (bqv[])bfd.k.c) {}
        }
    }
    
    private final void z(final azl azl, final azl azl2) {
        if (azl.p() && azl2.p()) {
            return;
        }
        int size = this.q.size();
        while (true) {
            final int n = size - 1;
            if (n < 0) {
                break;
            }
            size = n;
            if (P((bex)this.q.get(n), azl, azl2, this.B, this.C, this.l, this.m)) {
                continue;
            }
            ((bex)this.q.get(n)).a.a(false);
            this.q.remove(n);
            size = n;
        }
        Collections.sort((List<Comparable>)this.q);
    }
    
    public final void d(final bfp bfp) {
        synchronized (this) {
            if (!this.c && this.k.isAlive()) {
                this.a.f(14, (Object)bfp).r();
                return;
            }
            bao.c("ExoPlayerImplInternal", "Ignoring messages sent after release.");
            bfp.a(false);
        }
    }
    
    public final boolean e() {
        synchronized (this) {
            if (!this.c && this.k.isAlive()) {
                this.a.d(7);
                this.K((aeyr)new beg(this, 15), this.u);
                return this.c;
            }
            return true;
        }
    }
    
    public final boolean handleMessage(final Message p0) {
        // 
        // This method could not be decompiled.
        // 
        // Original Bytecode:
        // 
        //     1: getfield        android/os/Message.what:I
        //     4: tableswitch {
        //                0: 2664
        //                1: 2636
        //                2: 2629
        //                3: 2054
        //                4: 2023
        //                5: 2009
        //                6: 2000
        //                7: 1950
        //                8: 1693
        //                9: 1656
        //               10: 1186
        //               11: 1134
        //               12: 1076
        //               13: 953
        //               14: 815
        //               15: 741
        //               16: 726
        //               17: 596
        //               18: 528
        //               19: 449
        //               20: 359
        //               21: 263
        //               22: 248
        //               23: 189
        //               24: 134
        //               25: 126
        //          default: 124
        //        }
        //   124: iconst_0       
        //   125: ireturn        
        //   126: aload_0        
        //   127: iconst_1       
        //   128: invokespecial   bez.B:(Z)V
        //   131: goto            3017
        //   134: aload_1        
        //   135: getfield        android/os/Message.arg1:I
        //   138: iconst_1       
        //   139: if_icmpne       147
        //   142: iconst_1       
        //   143: istore_2       
        //   144: goto            149
        //   147: iconst_0       
        //   148: istore_2       
        //   149: iload_2        
        //   150: aload_0        
        //   151: getfield        bez.E:Z
        //   154: if_icmpeq       3017
        //   157: aload_0        
        //   158: iload_2        
        //   159: putfield        bez.E:Z
        //   162: iload_2        
        //   163: ifne            3017
        //   166: aload_0        
        //   167: getfield        bez.w:Lbfm;
        //   170: getfield        bfm.l:Z
        //   173: ifeq            3017
        //   176: aload_0        
        //   177: getfield        bez.a:Lbaj;
        //   180: iconst_2       
        //   181: invokeinterface baj.d:(I)V
        //   186: goto            3017
        //   189: aload_1        
        //   190: getfield        android/os/Message.arg1:I
        //   193: ifeq            201
        //   196: iconst_1       
        //   197: istore_2       
        //   198: goto            203
        //   201: iconst_0       
        //   202: istore_2       
        //   203: aload_0        
        //   204: iload_2        
        //   205: putfield        bez.x:Z
        //   208: aload_0        
        //   209: invokespecial   bez.x:()V
        //   212: aload_0        
        //   213: getfield        bez.y:Z
        //   216: ifeq            3017
        //   219: aload_0        
        //   220: getfield        bez.s:Lbff;
        //   223: astore_1       
        //   224: aload_1        
        //   225: getfield        bff.e:Lbfd;
        //   228: aload_1        
        //   229: getfield        bff.d:Lbfd;
        //   232: if_acmpeq       3017
        //   235: aload_0        
        //   236: iconst_1       
        //   237: invokespecial   bez.B:(Z)V
        //   240: aload_0        
        //   241: iconst_0       
        //   242: invokespecial   bez.q:(Z)V
        //   245: goto            3017
        //   248: aload_0        
        //   249: aload_0        
        //   250: getfield        bez.t:Lbfl;
        //   253: invokevirtual   bfl.b:()Lazl;
        //   256: iconst_1       
        //   257: invokespecial   bez.r:(Lazl;Z)V
        //   260: goto            3017
        //   263: aload_1        
        //   264: getfield        android/os/Message.obj:Ljava/lang/Object;
        //   267: checkcast       Leg;
        //   270: astore_3       
        //   271: aload_0        
        //   272: getfield        bez.N:Llzz;
        //   275: iconst_1       
        //   276: invokevirtual   lzz.b:(I)V
        //   279: aload_0        
        //   280: getfield        bez.t:Lbfl;
        //   283: astore          4
        //   285: aload           4
        //   287: invokevirtual   bfl.a:()I
        //   290: istore          5
        //   292: aload_3        
        //   293: astore_1       
        //   294: aload_3        
        //   295: invokevirtual   eg.v:()I
        //   298: iload           5
        //   300: if_icmpeq       340
        //   303: new             Leg;
        //   306: astore_1       
        //   307: new             Ljava/util/Random;
        //   310: astore          6
        //   312: aload           6
        //   314: aload_3        
        //   315: getfield        eg.b:Ljava/lang/Object;
        //   318: checkcast       Ljava/util/Random;
        //   321: invokevirtual   java/util/Random.nextLong:()J
        //   324: invokespecial   java/util/Random.<init>:(J)V
        //   327: aload_1        
        //   328: aload           6
        //   330: invokespecial   eg.<init>:(Ljava/util/Random;)V
        //   333: aload_1        
        //   334: iload           5
        //   336: invokevirtual   eg.w:(I)Leg;
        //   339: astore_1       
        //   340: aload           4
        //   342: aload_1        
        //   343: putfield        bfl.j:Leg;
        //   346: aload_0        
        //   347: aload           4
        //   349: invokevirtual   bfl.b:()Lazl;
        //   352: iconst_0       
        //   353: invokespecial   bez.r:(Lazl;Z)V
        //   356: goto            3017
        //   359: aload_1        
        //   360: getfield        android/os/Message.arg1:I
        //   363: istore          7
        //   365: aload_1        
        //   366: getfield        android/os/Message.arg2:I
        //   369: istore          5
        //   371: aload_1        
        //   372: getfield        android/os/Message.obj:Ljava/lang/Object;
        //   375: checkcast       Leg;
        //   378: astore_3       
        //   379: aload_0        
        //   380: getfield        bez.N:Llzz;
        //   383: iconst_1       
        //   384: invokevirtual   lzz.b:(I)V
        //   387: aload_0        
        //   388: getfield        bez.t:Lbfl;
        //   391: astore_1       
        //   392: iload           7
        //   394: iflt            418
        //   397: iload           7
        //   399: iload           5
        //   401: if_icmpgt       418
        //   404: iload           5
        //   406: aload_1        
        //   407: invokevirtual   bfl.a:()I
        //   410: if_icmpgt       418
        //   413: iconst_1       
        //   414: istore_2       
        //   415: goto            420
        //   418: iconst_0       
        //   419: istore_2       
        //   420: iload_2        
        //   421: invokestatic    dk.f:(Z)V
        //   424: aload_1        
        //   425: aload_3        
        //   426: putfield        bfl.j:Leg;
        //   429: aload_1        
        //   430: iload           7
        //   432: iload           5
        //   434: invokevirtual   bfl.f:(II)V
        //   437: aload_0        
        //   438: aload_1        
        //   439: invokevirtual   bfl.b:()Lazl;
        //   442: iconst_0       
        //   443: invokespecial   bez.r:(Lazl;Z)V
        //   446: goto            3017
        //   449: aload_1        
        //   450: getfield        android/os/Message.obj:Ljava/lang/Object;
        //   453: checkcast       Laerj;
        //   456: astore_3       
        //   457: aload_0        
        //   458: getfield        bez.N:Llzz;
        //   461: iconst_1       
        //   462: invokevirtual   lzz.b:(I)V
        //   465: aload_0        
        //   466: getfield        bez.t:Lbfl;
        //   469: astore_1       
        //   470: aload_3        
        //   471: getfield        aerj.b:I
        //   474: istore          5
        //   476: aload_3        
        //   477: getfield        aerj.a:I
        //   480: istore          5
        //   482: aload_3        
        //   483: getfield        aerj.c:I
        //   486: istore          5
        //   488: aload_3        
        //   489: getfield        aerj.d:Ljava/lang/Object;
        //   492: astore_3       
        //   493: aload_1        
        //   494: invokevirtual   bfl.a:()I
        //   497: iflt            505
        //   500: iconst_1       
        //   501: istore_2       
        //   502: goto            507
        //   505: iconst_0       
        //   506: istore_2       
        //   507: iload_2        
        //   508: invokestatic    dk.f:(Z)V
        //   511: aload_1        
        //   512: aconst_null    
        //   513: putfield        bfl.j:Leg;
        //   516: aload_0        
        //   517: aload_1        
        //   518: invokevirtual   bfl.b:()Lazl;
        //   521: iconst_0       
        //   522: invokespecial   bez.r:(Lazl;Z)V
        //   525: goto            3017
        //   528: aload_1        
        //   529: getfield        android/os/Message.obj:Ljava/lang/Object;
        //   532: checkcast       Lbny;
        //   535: astore_3       
        //   536: aload_1        
        //   537: getfield        android/os/Message.arg1:I
        //   540: istore          7
        //   542: aload_0        
        //   543: getfield        bez.N:Llzz;
        //   546: iconst_1       
        //   547: invokevirtual   lzz.b:(I)V
        //   550: aload_0        
        //   551: getfield        bez.t:Lbfl;
        //   554: astore_1       
        //   555: iload           7
        //   557: istore          5
        //   559: iload           7
        //   561: iconst_m1      
        //   562: if_icmpne       571
        //   565: aload_1        
        //   566: invokevirtual   bfl.a:()I
        //   569: istore          5
        //   571: aload_0        
        //   572: aload_1        
        //   573: iload           5
        //   575: aload_3        
        //   576: getfield        bny.c:Ljava/util/List;
        //   579: aload_3        
        //   580: getfield        bny.d:Ljava/lang/Object;
        //   583: checkcast       Leg;
        //   586: invokevirtual   bfl.g:(ILjava/util/List;Leg;)Lazl;
        //   589: iconst_0       
        //   590: invokespecial   bez.r:(Lazl;Z)V
        //   593: goto            3017
        //   596: aload_1        
        //   597: getfield        android/os/Message.obj:Ljava/lang/Object;
        //   600: checkcast       Lbny;
        //   603: astore_1       
        //   604: aload_0        
        //   605: getfield        bez.N:Llzz;
        //   608: iconst_1       
        //   609: invokevirtual   lzz.b:(I)V
        //   612: aload_1        
        //   613: getfield        bny.a:I
        //   616: iconst_m1      
        //   617: if_icmpeq       666
        //   620: new             Lbey;
        //   623: astore_3       
        //   624: new             Lbdr;
        //   627: astore          4
        //   629: aload           4
        //   631: aload_1        
        //   632: getfield        bny.c:Ljava/util/List;
        //   635: aload_1        
        //   636: getfield        bny.d:Ljava/lang/Object;
        //   639: checkcast       Leg;
        //   642: aconst_null    
        //   643: aconst_null    
        //   644: invokespecial   bdr.<init>:(Ljava/util/Collection;Leg;[B[B)V
        //   647: aload_3        
        //   648: aload           4
        //   650: aload_1        
        //   651: getfield        bny.a:I
        //   654: aload_1        
        //   655: getfield        bny.b:J
        //   658: invokespecial   bey.<init>:(Lazl;IJ)V
        //   661: aload_0        
        //   662: aload_3        
        //   663: putfield        bez.G:Lbey;
        //   666: aload_0        
        //   667: getfield        bez.t:Lbfl;
        //   670: astore          4
        //   672: aload_1        
        //   673: getfield        bny.c:Ljava/util/List;
        //   676: astore_3       
        //   677: aload_1        
        //   678: getfield        bny.d:Ljava/lang/Object;
        //   681: astore_1       
        //   682: aload           4
        //   684: iconst_0       
        //   685: aload           4
        //   687: getfield        bfl.a:Ljava/util/List;
        //   690: invokeinterface java/util/List.size:()I
        //   695: invokevirtual   bfl.f:(II)V
        //   698: aload_0        
        //   699: aload           4
        //   701: aload           4
        //   703: getfield        bfl.a:Ljava/util/List;
        //   706: invokeinterface java/util/List.size:()I
        //   711: aload_3        
        //   712: aload_1        
        //   713: checkcast       Leg;
        //   716: invokevirtual   bfl.g:(ILjava/util/List;Leg;)Lazl;
        //   719: iconst_0       
        //   720: invokespecial   bez.r:(Lazl;Z)V
        //   723: goto            3017
        //   726: aload_0        
        //   727: aload_1        
        //   728: getfield        android/os/Message.obj:Ljava/lang/Object;
        //   731: checkcast       Lazb;
        //   734: iconst_0       
        //   735: invokespecial   bez.s:(Lazb;Z)V
        //   738: goto            3017
        //   741: aload_1        
        //   742: getfield        android/os/Message.obj:Ljava/lang/Object;
        //   745: checkcast       Lbfp;
        //   748: astore_1       
        //   749: aload_1        
        //   750: getfield        bfp.e:Landroid/os/Looper;
        //   753: astore_3       
        //   754: aload_3        
        //   755: invokevirtual   android/os/Looper.getThread:()Ljava/lang/Thread;
        //   758: invokevirtual   java/lang/Thread.isAlive:()Z
        //   761: ifne            781
        //   764: ldc_w           "TAG"
        //   767: ldc_w           "Trying to send message on a dead thread."
        //   770: invokestatic    bao.c:(Ljava/lang/String;Ljava/lang/String;)V
        //   773: aload_1        
        //   774: iconst_0       
        //   775: invokevirtual   bfp.a:(Z)V
        //   778: goto            3017
        //   781: aload_0        
        //   782: getfield        bez.r:Lbac;
        //   785: aload_3        
        //   786: aconst_null    
        //   787: invokeinterface bac.b:(Landroid/os/Looper;Landroid/os/Handler$Callback;)Lbaj;
        //   792: astore          4
        //   794: new             Laur;
        //   797: astore_3       
        //   798: aload_3        
        //   799: aload_1        
        //   800: iconst_4       
        //   801: invokespecial   aur.<init>:(Lbfp;I)V
        //   804: aload           4
        //   806: aload_3        
        //   807: invokeinterface baj.b:(Ljava/lang/Runnable;)V
        //   812: goto            3017
        //   815: aload_1        
        //   816: getfield        android/os/Message.obj:Ljava/lang/Object;
        //   819: checkcast       Lbfp;
        //   822: astore_1       
        //   823: aload_1        
        //   824: getfield        bfp.g:J
        //   827: ldc2_w          -9223372036854775807
        //   830: lcmp           
        //   831: ifne            842
        //   834: aload_0        
        //   835: aload_1        
        //   836: invokespecial   bez.C:(Lbfp;)V
        //   839: goto            3017
        //   842: aload_0        
        //   843: getfield        bez.w:Lbfm;
        //   846: getfield        bfm.a:Lazl;
        //   849: invokevirtual   azl.p:()Z
        //   852: ifeq            881
        //   855: aload_0        
        //   856: getfield        bez.q:Ljava/util/ArrayList;
        //   859: astore_3       
        //   860: new             Lbex;
        //   863: astore          4
        //   865: aload           4
        //   867: aload_1        
        //   868: invokespecial   bex.<init>:(Lbfp;)V
        //   871: aload_3        
        //   872: aload           4
        //   874: invokevirtual   java/util/ArrayList.add:(Ljava/lang/Object;)Z
        //   877: pop            
        //   878: goto            3017
        //   881: new             Lbex;
        //   884: astore_3       
        //   885: aload_3        
        //   886: aload_1        
        //   887: invokespecial   bex.<init>:(Lbfp;)V
        //   890: aload_0        
        //   891: getfield        bez.w:Lbfm;
        //   894: getfield        bfm.a:Lazl;
        //   897: astore          4
        //   899: aload_3        
        //   900: aload           4
        //   902: aload           4
        //   904: aload_0        
        //   905: getfield        bez.B:I
        //   908: aload_0        
        //   909: getfield        bez.C:Z
        //   912: aload_0        
        //   913: getfield        bez.l:Lazk;
        //   916: aload_0        
        //   917: getfield        bez.m:Lazj;
        //   920: invokestatic    bez.P:(Lbex;Lazl;Lazl;IZLazk;Lazj;)Z
        //   923: ifeq            945
        //   926: aload_0        
        //   927: getfield        bez.q:Ljava/util/ArrayList;
        //   930: aload_3        
        //   931: invokevirtual   java/util/ArrayList.add:(Ljava/lang/Object;)Z
        //   934: pop            
        //   935: aload_0        
        //   936: getfield        bez.q:Ljava/util/ArrayList;
        //   939: invokestatic    java/util/Collections.sort:(Ljava/util/List;)V
        //   942: goto            3017
        //   945: aload_1        
        //   946: iconst_0       
        //   947: invokevirtual   bfp.a:(Z)V
        //   950: goto            3017
        //   953: aload_1        
        //   954: getfield        android/os/Message.arg1:I
        //   957: ifeq            965
        //   960: iconst_1       
        //   961: istore_2       
        //   962: goto            967
        //   965: iconst_0       
        //   966: istore_2       
        //   967: aload_1        
        //   968: getfield        android/os/Message.obj:Ljava/lang/Object;
        //   971: checkcast       Ljava/util/concurrent/atomic/AtomicBoolean;
        //   974: astore          4
        //   976: aload_0        
        //   977: getfield        bez.D:Z
        //   980: iload_2        
        //   981: if_icmpeq       1049
        //   984: aload_0        
        //   985: iload_2        
        //   986: putfield        bez.D:Z
        //   989: iload_2        
        //   990: ifne            1049
        //   993: aload_0        
        //   994: getfield        bez.e:[Lbfq;
        //   997: astore_3       
        //   998: aload_3        
        //   999: arraylength    
        //  1000: istore          7
        //  1002: iconst_0       
        //  1003: istore          5
        //  1005: iload           5
        //  1007: iload           7
        //  1009: if_icmpge       1049
        //  1012: aload_3        
        //  1013: iload           5
        //  1015: aaload         
        //  1016: astore_1       
        //  1017: aload_1        
        //  1018: invokestatic    bez.M:(Lbfq;)Z
        //  1021: ifne            1043
        //  1024: aload_0        
        //  1025: getfield        bez.f:Ljava/util/Set;
        //  1028: aload_1        
        //  1029: invokeinterface java/util/Set.remove:(Ljava/lang/Object;)Z
        //  1034: ifeq            1043
        //  1037: aload_1        
        //  1038: invokeinterface bfq.E:()V
        //  1043: iinc            5, 1
        //  1046: goto            1005
        //  1049: aload           4
        //  1051: ifnull          3017
        //  1054: aload_0        
        //  1055: monitorenter   
        //  1056: aload           4
        //  1058: iconst_1       
        //  1059: invokevirtual   java/util/concurrent/atomic/AtomicBoolean.set:(Z)V
        //  1062: aload_0        
        //  1063: invokevirtual   java/lang/Object.notifyAll:()V
        //  1066: aload_0        
        //  1067: monitorexit    
        //  1068: goto            3017
        //  1071: astore_1       
        //  1072: aload_0        
        //  1073: monitorexit    
        //  1074: aload_1        
        //  1075: athrow         
        //  1076: aload_1        
        //  1077: getfield        android/os/Message.arg1:I
        //  1080: ifeq            1088
        //  1083: iconst_1       
        //  1084: istore_2       
        //  1085: goto            1090
        //  1088: iconst_0       
        //  1089: istore_2       
        //  1090: aload_0        
        //  1091: iload_2        
        //  1092: putfield        bez.C:Z
        //  1095: aload_0        
        //  1096: getfield        bez.s:Lbff;
        //  1099: astore_1       
        //  1100: aload_0        
        //  1101: getfield        bez.w:Lbfm;
        //  1104: getfield        bfm.a:Lazl;
        //  1107: astore_3       
        //  1108: aload_1        
        //  1109: iload_2        
        //  1110: putfield        bff.c:Z
        //  1113: aload_1        
        //  1114: aload_3        
        //  1115: invokevirtual   bff.i:(Lazl;)Z
        //  1118: ifne            1126
        //  1121: aload_0        
        //  1122: iconst_1       
        //  1123: invokespecial   bez.B:(Z)V
        //  1126: aload_0        
        //  1127: iconst_0       
        //  1128: invokespecial   bez.q:(Z)V
        //  1131: goto            3017
        //  1134: aload_1        
        //  1135: getfield        android/os/Message.arg1:I
        //  1138: istore          5
        //  1140: aload_0        
        //  1141: iload           5
        //  1143: putfield        bez.B:I
        //  1146: aload_0        
        //  1147: getfield        bez.s:Lbff;
        //  1150: astore_1       
        //  1151: aload_0        
        //  1152: getfield        bez.w:Lbfm;
        //  1155: getfield        bfm.a:Lazl;
        //  1158: astore_3       
        //  1159: aload_1        
        //  1160: iload           5
        //  1162: putfield        bff.b:I
        //  1165: aload_1        
        //  1166: aload_3        
        //  1167: invokevirtual   bff.i:(Lazl;)Z
        //  1170: ifne            1178
        //  1173: aload_0        
        //  1174: iconst_1       
        //  1175: invokespecial   bez.B:(Z)V
        //  1178: aload_0        
        //  1179: iconst_0       
        //  1180: invokespecial   bez.q:(Z)V
        //  1183: goto            3017
        //  1186: aload_0        
        //  1187: getfield        bez.p:Lbec;
        //  1190: invokevirtual   bec.kI:()Lazb;
        //  1193: getfield        azb.b:F
        //  1196: fstore          8
        //  1198: aload_0        
        //  1199: getfield        bez.s:Lbff;
        //  1202: astore_3       
        //  1203: aload_3        
        //  1204: getfield        bff.d:Lbfd;
        //  1207: astore_1       
        //  1208: aload_3        
        //  1209: getfield        bff.e:Lbfd;
        //  1212: astore_3       
        //  1213: iconst_1       
        //  1214: istore          5
        //  1216: aload_1        
        //  1217: ifnull          3017
        //  1220: aload_1        
        //  1221: getfield        bfd.d:Z
        //  1224: ifne            1230
        //  1227: goto            3017
        //  1230: aload_1        
        //  1231: fload           8
        //  1233: aload_0        
        //  1234: getfield        bez.w:Lbfm;
        //  1237: getfield        bfm.a:Lazl;
        //  1240: invokevirtual   bfd.l:(FLazl;)Laetc;
        //  1243: astore          4
        //  1245: aload_1        
        //  1246: getfield        bfd.k:Laetc;
        //  1249: astore          6
        //  1251: aload           6
        //  1253: ifnull          1344
        //  1256: aload           6
        //  1258: getfield        aetc.c:Ljava/lang/Object;
        //  1261: checkcast       [Lbqv;
        //  1264: arraylength    
        //  1265: aload           4
        //  1267: getfield        aetc.c:Ljava/lang/Object;
        //  1270: checkcast       [Lbqv;
        //  1273: arraylength    
        //  1274: if_icmpeq       1280
        //  1277: goto            1344
        //  1280: iconst_0       
        //  1281: istore          7
        //  1283: iload           7
        //  1285: aload           4
        //  1287: getfield        aetc.c:Ljava/lang/Object;
        //  1290: checkcast       [Lbqv;
        //  1293: arraylength    
        //  1294: if_icmpge       1315
        //  1297: aload           4
        //  1299: aload           6
        //  1301: iload           7
        //  1303: invokevirtual   aetc.j:(Laetc;I)Z
        //  1306: ifeq            1344
        //  1309: iinc            7, 1
        //  1312: goto            1283
        //  1315: aload_1        
        //  1316: aload_3        
        //  1317: if_acmpne       1326
        //  1320: iconst_0       
        //  1321: istore          7
        //  1323: goto            1329
        //  1326: iconst_1       
        //  1327: istore          7
        //  1329: iload           5
        //  1331: iload           7
        //  1333: iand           
        //  1334: istore          5
        //  1336: aload_1        
        //  1337: getfield        bfd.h:Lbfd;
        //  1340: astore_1       
        //  1341: goto            1216
        //  1344: iload           5
        //  1346: ifeq            1578
        //  1349: aload_0        
        //  1350: getfield        bez.s:Lbff;
        //  1353: astore_3       
        //  1354: aload_3        
        //  1355: getfield        bff.d:Lbfd;
        //  1358: astore_1       
        //  1359: aload_3        
        //  1360: aload_1        
        //  1361: invokevirtual   bff.h:(Lbfd;)Z
        //  1364: istore_2       
        //  1365: aload_0        
        //  1366: getfield        bez.e:[Lbfq;
        //  1369: arraylength    
        //  1370: newarray        Z
        //  1372: astore_3       
        //  1373: aload_1        
        //  1374: aload           4
        //  1376: aload_0        
        //  1377: getfield        bez.w:Lbfm;
        //  1380: getfield        bfm.o:J
        //  1383: iload_2        
        //  1384: aload_3        
        //  1385: invokevirtual   bfd.k:(Laetc;JZ[Z)J
        //  1388: lstore          9
        //  1390: aload_0        
        //  1391: getfield        bez.w:Lbfm;
        //  1394: astore          4
        //  1396: aload           4
        //  1398: getfield        bfm.d:I
        //  1401: iconst_4       
        //  1402: if_icmpeq       1421
        //  1405: lload           9
        //  1407: aload           4
        //  1409: getfield        bfm.o:J
        //  1412: lcmp           
        //  1413: ifeq            1421
        //  1416: iconst_1       
        //  1417: istore_2       
        //  1418: goto            1423
        //  1421: iconst_0       
        //  1422: istore_2       
        //  1423: aload_0        
        //  1424: getfield        bez.w:Lbfm;
        //  1427: astore          4
        //  1429: aload_0        
        //  1430: aload_0        
        //  1431: aload           4
        //  1433: getfield        bfm.q:Layx;
        //  1436: lload           9
        //  1438: aload           4
        //  1440: getfield        bfm.b:J
        //  1443: aload           4
        //  1445: getfield        bfm.c:J
        //  1448: iload_2        
        //  1449: iconst_5       
        //  1450: invokespecial   bez.U:(Layx;JJJZI)Lbfm;
        //  1453: putfield        bez.w:Lbfm;
        //  1456: iload_2        
        //  1457: ifeq            1466
        //  1460: aload_0        
        //  1461: lload           9
        //  1463: invokespecial   bez.y:(J)V
        //  1466: aload_0        
        //  1467: getfield        bez.e:[Lbfq;
        //  1470: arraylength    
        //  1471: newarray        Z
        //  1473: astore          4
        //  1475: iconst_0       
        //  1476: istore          5
        //  1478: aload_0        
        //  1479: getfield        bez.e:[Lbfq;
        //  1482: astore          6
        //  1484: iload           5
        //  1486: aload           6
        //  1488: arraylength    
        //  1489: if_icmpge       1569
        //  1492: aload           6
        //  1494: iload           5
        //  1496: aaload         
        //  1497: astore          11
        //  1499: aload           11
        //  1501: invokestatic    bez.M:(Lbfq;)Z
        //  1504: istore_2       
        //  1505: aload           4
        //  1507: iload           5
        //  1509: iload_2        
        //  1510: bastore        
        //  1511: aload_1        
        //  1512: getfield        bfd.c:[Lbov;
        //  1515: iload           5
        //  1517: aaload         
        //  1518: astore          6
        //  1520: iload_2        
        //  1521: ifeq            1563
        //  1524: aload           6
        //  1526: aload           11
        //  1528: invokeinterface bfq.q:()Lbov;
        //  1533: if_acmpeq       1545
        //  1536: aload_0        
        //  1537: aload           11
        //  1539: invokespecial   bez.l:(Lbfq;)V
        //  1542: goto            1563
        //  1545: aload_3        
        //  1546: iload           5
        //  1548: baload         
        //  1549: ifeq            1563
        //  1552: aload           11
        //  1554: aload_0        
        //  1555: getfield        bez.H:J
        //  1558: invokeinterface bfq.F:(J)V
        //  1563: iinc            5, 1
        //  1566: goto            1478
        //  1569: aload_0        
        //  1570: aload           4
        //  1572: invokespecial   bez.o:([Z)V
        //  1575: goto            1619
        //  1578: aload_0        
        //  1579: getfield        bez.s:Lbff;
        //  1582: aload_1        
        //  1583: invokevirtual   bff.h:(Lbfd;)Z
        //  1586: pop            
        //  1587: aload_1        
        //  1588: getfield        bfd.d:Z
        //  1591: ifeq            1619
        //  1594: aload_1        
        //  1595: aload           4
        //  1597: aload_1        
        //  1598: getfield        bfd.f:Lbfe;
        //  1601: getfield        bfe.a:J
        //  1604: aload_1        
        //  1605: aload_0        
        //  1606: getfield        bez.H:J
        //  1609: invokevirtual   bfd.d:(J)J
        //  1612: invokestatic    java/lang/Math.max:(JJ)J
        //  1615: invokevirtual   bfd.m:(Laetc;J)J
        //  1618: pop2           
        //  1619: aload_0        
        //  1620: iconst_1       
        //  1621: invokespecial   bez.q:(Z)V
        //  1624: aload_0        
        //  1625: getfield        bez.w:Lbfm;
        //  1628: getfield        bfm.d:I
        //  1631: iconst_4       
        //  1632: if_icmpeq       3017
        //  1635: aload_0        
        //  1636: invokespecial   bez.u:()V
        //  1639: aload_0        
        //  1640: invokespecial   bez.J:()V
        //  1643: aload_0        
        //  1644: getfield        bez.a:Lbaj;
        //  1647: iconst_2       
        //  1648: invokeinterface baj.d:(I)V
        //  1653: goto            3017
        //  1656: aload_1        
        //  1657: getfield        android/os/Message.obj:Ljava/lang/Object;
        //  1660: checkcast       Lbnu;
        //  1663: astore_1       
        //  1664: aload_0        
        //  1665: getfield        bez.s:Lbff;
        //  1668: aload_1        
        //  1669: invokevirtual   bff.g:(Lbnu;)Z
        //  1672: ifeq            3017
        //  1675: aload_0        
        //  1676: getfield        bez.s:Lbff;
        //  1679: aload_0        
        //  1680: getfield        bez.H:J
        //  1683: invokevirtual   bff.f:(J)V
        //  1686: aload_0        
        //  1687: invokespecial   bez.u:()V
        //  1690: goto            3017
        //  1693: aload_1        
        //  1694: getfield        android/os/Message.obj:Ljava/lang/Object;
        //  1697: checkcast       Lbnu;
        //  1700: astore_1       
        //  1701: aload_0        
        //  1702: getfield        bez.s:Lbff;
        //  1705: aload_1        
        //  1706: invokevirtual   bff.g:(Lbnu;)Z
        //  1709: ifeq            3017
        //  1712: aload_0        
        //  1713: getfield        bez.s:Lbff;
        //  1716: getfield        bff.f:Lbfd;
        //  1719: astore_1       
        //  1720: aload_0        
        //  1721: getfield        bez.p:Lbec;
        //  1724: invokevirtual   bec.kI:()Lazb;
        //  1727: getfield        azb.b:F
        //  1730: fstore          8
        //  1732: aload_0        
        //  1733: getfield        bez.w:Lbfm;
        //  1736: getfield        bfm.a:Lazl;
        //  1739: astore_3       
        //  1740: aload_1        
        //  1741: iconst_1       
        //  1742: putfield        bfd.d:Z
        //  1745: aload_1        
        //  1746: aload_1        
        //  1747: getfield        bfd.a:Lbnu;
        //  1750: invokeinterface bnu.h:()Lbpd;
        //  1755: putfield        bfd.i:Lbpd;
        //  1758: aload_1        
        //  1759: fload           8
        //  1761: aload_3        
        //  1762: invokevirtual   bfd.l:(FLazl;)Laetc;
        //  1765: astore          4
        //  1767: aload_1        
        //  1768: getfield        bfd.f:Lbfe;
        //  1771: astore_3       
        //  1772: aload_3        
        //  1773: getfield        bfe.a:J
        //  1776: lstore          12
        //  1778: aload_3        
        //  1779: getfield        bfe.d:J
        //  1782: lstore          14
        //  1784: lload           12
        //  1786: lstore          9
        //  1788: lload           14
        //  1790: ldc2_w          -9223372036854775807
        //  1793: lcmp           
        //  1794: ifeq            1819
        //  1797: lload           12
        //  1799: lstore          9
        //  1801: lload           12
        //  1803: lload           14
        //  1805: lcmp           
        //  1806: iflt            1819
        //  1809: lconst_0       
        //  1810: lload           14
        //  1812: lconst_1       
        //  1813: lsub           
        //  1814: invokestatic    java/lang/Math.max:(JJ)J
        //  1817: lstore          9
        //  1819: aload_1        
        //  1820: aload           4
        //  1822: lload           9
        //  1824: invokevirtual   bfd.m:(Laetc;J)J
        //  1827: lstore          9
        //  1829: aload_1        
        //  1830: getfield        bfd.j:J
        //  1833: lstore          12
        //  1835: aload_1        
        //  1836: getfield        bfd.f:Lbfe;
        //  1839: astore_3       
        //  1840: aload_1        
        //  1841: lload           12
        //  1843: aload_3        
        //  1844: getfield        bfe.a:J
        //  1847: lload           9
        //  1849: lsub           
        //  1850: ladd           
        //  1851: putfield        bfd.j:J
        //  1854: aload_1        
        //  1855: aload_3        
        //  1856: lload           9
        //  1858: invokevirtual   bfe.b:(J)Lbfe;
        //  1861: putfield        bfd.f:Lbfe;
        //  1864: aload_0        
        //  1865: aload_1        
        //  1866: getfield        bfd.i:Lbpd;
        //  1869: aload_1        
        //  1870: getfield        bfd.k:Laetc;
        //  1873: invokespecial   bez.Z:(Lbpd;Laetc;)V
        //  1876: aload_1        
        //  1877: aload_0        
        //  1878: getfield        bez.s:Lbff;
        //  1881: getfield        bff.d:Lbfd;
        //  1884: if_acmpne       1943
        //  1887: aload_0        
        //  1888: aload_1        
        //  1889: getfield        bfd.f:Lbfe;
        //  1892: getfield        bfe.a:J
        //  1895: invokespecial   bez.y:(J)V
        //  1898: aload_0        
        //  1899: invokespecial   bez.n:()V
        //  1902: aload_0        
        //  1903: getfield        bez.w:Lbfm;
        //  1906: astore          4
        //  1908: aload           4
        //  1910: getfield        bfm.q:Layx;
        //  1913: astore_3       
        //  1914: aload_1        
        //  1915: getfield        bfd.f:Lbfe;
        //  1918: getfield        bfe.a:J
        //  1921: lstore          9
        //  1923: aload_0        
        //  1924: aload_0        
        //  1925: aload_3        
        //  1926: lload           9
        //  1928: aload           4
        //  1930: getfield        bfm.b:J
        //  1933: lload           9
        //  1935: iconst_0       
        //  1936: iconst_5       
        //  1937: invokespecial   bez.U:(Layx;JJJZI)Lbfm;
        //  1940: putfield        bez.w:Lbfm;
        //  1943: aload_0        
        //  1944: invokespecial   bez.u:()V
        //  1947: goto            3017
        //  1950: aload_0        
        //  1951: iconst_1       
        //  1952: iconst_0       
        //  1953: iconst_1       
        //  1954: iconst_0       
        //  1955: invokespecial   bez.w:(ZZZZ)V
        //  1958: aload_0        
        //  1959: getfield        bez.i:Lbfb;
        //  1962: invokeinterface bfb.d:()V
        //  1967: aload_0        
        //  1968: iconst_1       
        //  1969: invokespecial   bez.E:(I)V
        //  1972: aload_0        
        //  1973: getfield        bez.k:Landroid/os/HandlerThread;
        //  1976: invokevirtual   android/os/HandlerThread.quit:()Z
        //  1979: pop            
        //  1980: aload_0        
        //  1981: monitorenter   
        //  1982: aload_0        
        //  1983: iconst_1       
        //  1984: putfield        bez.c:Z
        //  1987: aload_0        
        //  1988: invokevirtual   java/lang/Object.notifyAll:()V
        //  1991: aload_0        
        //  1992: monitorexit    
        //  1993: iconst_1       
        //  1994: ireturn        
        //  1995: astore_1       
        //  1996: aload_0        
        //  1997: monitorexit    
        //  1998: aload_1        
        //  1999: athrow         
        //  2000: aload_0        
        //  2001: iconst_0       
        //  2002: iconst_1       
        //  2003: invokespecial   bez.G:(ZZ)V
        //  2006: goto            3017
        //  2009: aload_0        
        //  2010: aload_1        
        //  2011: getfield        android/os/Message.obj:Ljava/lang/Object;
        //  2014: checkcast       Lbfu;
        //  2017: putfield        bez.v:Lbfu;
        //  2020: goto            3017
        //  2023: aload_1        
        //  2024: getfield        android/os/Message.obj:Ljava/lang/Object;
        //  2027: checkcast       Lazb;
        //  2030: astore_1       
        //  2031: aload_0        
        //  2032: getfield        bez.p:Lbec;
        //  2035: aload_1        
        //  2036: invokevirtual   bec.kJ:(Lazb;)V
        //  2039: aload_0        
        //  2040: aload_0        
        //  2041: getfield        bez.p:Lbec;
        //  2044: invokevirtual   bec.kI:()Lazb;
        //  2047: iconst_1       
        //  2048: invokespecial   bez.s:(Lazb;Z)V
        //  2051: goto            3017
        //  2054: aload_1        
        //  2055: getfield        android/os/Message.obj:Ljava/lang/Object;
        //  2058: checkcast       Lbey;
        //  2061: astore          4
        //  2063: aload_0        
        //  2064: getfield        bez.N:Llzz;
        //  2067: iconst_1       
        //  2068: invokevirtual   lzz.b:(I)V
        //  2071: aload_0        
        //  2072: getfield        bez.w:Lbfm;
        //  2075: getfield        bfm.a:Lazl;
        //  2078: aload           4
        //  2080: iconst_1       
        //  2081: aload_0        
        //  2082: getfield        bez.B:I
        //  2085: aload_0        
        //  2086: getfield        bez.C:Z
        //  2089: aload_0        
        //  2090: getfield        bez.l:Lazk;
        //  2093: aload_0        
        //  2094: getfield        bez.m:Lazj;
        //  2097: invokestatic    bez.k:(Lazl;Lbey;ZIZLazk;Lazj;)Landroid/util/Pair;
        //  2100: astore_3       
        //  2101: aload_3        
        //  2102: ifnonnull       2161
        //  2105: aload_0        
        //  2106: aload_0        
        //  2107: getfield        bez.w:Lbfm;
        //  2110: getfield        bfm.a:Lazl;
        //  2113: invokespecial   bez.j:(Lazl;)Landroid/util/Pair;
        //  2116: astore          6
        //  2118: aload           6
        //  2120: getfield        android/util/Pair.first:Ljava/lang/Object;
        //  2123: checkcast       Layx;
        //  2126: astore_1       
        //  2127: aload           6
        //  2129: getfield        android/util/Pair.second:Ljava/lang/Object;
        //  2132: checkcast       Ljava/lang/Long;
        //  2135: invokevirtual   java/lang/Long.longValue:()J
        //  2138: lstore          9
        //  2140: aload_0        
        //  2141: getfield        bez.w:Lbfm;
        //  2144: getfield        bfm.a:Lazl;
        //  2147: invokevirtual   azl.p:()Z
        //  2150: iconst_1       
        //  2151: ixor           
        //  2152: istore_2       
        //  2153: ldc2_w          -9223372036854775807
        //  2156: lstore          12
        //  2158: goto            2302
        //  2161: aload_3        
        //  2162: getfield        android/util/Pair.first:Ljava/lang/Object;
        //  2165: astore_1       
        //  2166: aload_3        
        //  2167: getfield        android/util/Pair.second:Ljava/lang/Object;
        //  2170: checkcast       Ljava/lang/Long;
        //  2173: invokevirtual   java/lang/Long.longValue:()J
        //  2176: lstore          9
        //  2178: aload           4
        //  2180: getfield        bey.c:J
        //  2183: ldc2_w          -9223372036854775807
        //  2186: lcmp           
        //  2187: ifne            2198
        //  2190: ldc2_w          -9223372036854775807
        //  2193: lstore          12
        //  2195: goto            2202
        //  2198: lload           9
        //  2200: lstore          12
        //  2202: aload_0        
        //  2203: getfield        bez.s:Lbff;
        //  2206: aload_0        
        //  2207: getfield        bez.w:Lbfm;
        //  2210: getfield        bfm.a:Lazl;
        //  2213: aload_1        
        //  2214: lload           9
        //  2216: invokevirtual   bff.k:(Lazl;Ljava/lang/Object;J)Layx;
        //  2219: astore_1       
        //  2220: aload_1        
        //  2221: invokevirtual   ayx.a:()Z
        //  2224: ifeq            2279
        //  2227: aload_0        
        //  2228: getfield        bez.w:Lbfm;
        //  2231: getfield        bfm.a:Lazl;
        //  2234: aload_1        
        //  2235: getfield        ayx.a:Ljava/lang/Object;
        //  2238: aload_0        
        //  2239: getfield        bez.m:Lazj;
        //  2242: invokevirtual   azl.n:(Ljava/lang/Object;Lazj;)Lazj;
        //  2245: pop            
        //  2246: aload_0        
        //  2247: getfield        bez.m:Lazj;
        //  2250: aload_1        
        //  2251: getfield        ayx.b:I
        //  2254: invokevirtual   azj.d:(I)I
        //  2257: aload_1        
        //  2258: getfield        ayx.c:I
        //  2261: if_icmpne       2271
        //  2264: aload_0        
        //  2265: getfield        bez.m:Lazj;
        //  2268: invokevirtual   azj.j:()V
        //  2271: lconst_0       
        //  2272: lstore          9
        //  2274: iconst_1       
        //  2275: istore_2       
        //  2276: goto            2302
        //  2279: aload           4
        //  2281: getfield        bey.c:J
        //  2284: lstore          14
        //  2286: lload           14
        //  2288: ldc2_w          -9223372036854775807
        //  2291: lcmp           
        //  2292: ifne            2300
        //  2295: iconst_1       
        //  2296: istore_2       
        //  2297: goto            2302
        //  2300: iconst_0       
        //  2301: istore_2       
        //  2302: aload_0        
        //  2303: getfield        bez.w:Lbfm;
        //  2306: getfield        bfm.a:Lazl;
        //  2309: invokevirtual   azl.p:()Z
        //  2312: ifeq            2324
        //  2315: aload_0        
        //  2316: aload           4
        //  2318: putfield        bez.G:Lbey;
        //  2321: goto            2352
        //  2324: aload_3        
        //  2325: ifnonnull       2359
        //  2328: aload_0        
        //  2329: getfield        bez.w:Lbfm;
        //  2332: getfield        bfm.d:I
        //  2335: iconst_1       
        //  2336: if_icmpeq       2344
        //  2339: aload_0        
        //  2340: iconst_4       
        //  2341: invokespecial   bez.E:(I)V
        //  2344: aload_0        
        //  2345: iconst_0       
        //  2346: iconst_1       
        //  2347: iconst_0       
        //  2348: iconst_1       
        //  2349: invokespecial   bez.w:(ZZZZ)V
        //  2352: lload           9
        //  2354: lstore          14
        //  2356: goto            2584
        //  2359: aload_1        
        //  2360: aload_0        
        //  2361: getfield        bez.w:Lbfm;
        //  2364: getfield        bfm.q:Layx;
        //  2367: invokevirtual   ayx.equals:(Ljava/lang/Object;)Z
        //  2370: ifeq            2501
        //  2373: aload_0        
        //  2374: getfield        bez.s:Lbff;
        //  2377: getfield        bff.d:Lbfd;
        //  2380: astore_3       
        //  2381: aload_3        
        //  2382: ifnull          2419
        //  2385: aload_3        
        //  2386: getfield        bfd.d:Z
        //  2389: ifeq            2419
        //  2392: lload           9
        //  2394: lconst_0       
        //  2395: lcmp           
        //  2396: ifeq            2419
        //  2399: aload_3        
        //  2400: getfield        bfd.a:Lbnu;
        //  2403: lload           9
        //  2405: aload_0        
        //  2406: getfield        bez.v:Lbfu;
        //  2409: invokeinterface bnu.a:(JLbfu;)J
        //  2414: lstore          14
        //  2416: goto            2423
        //  2419: lload           9
        //  2421: lstore          14
        //  2423: lload           14
        //  2425: lstore          16
        //  2427: lload           14
        //  2429: invokestatic    baw.A:(J)J
        //  2432: aload_0        
        //  2433: getfield        bez.w:Lbfm;
        //  2436: getfield        bfm.o:J
        //  2439: invokestatic    baw.A:(J)J
        //  2442: lcmp           
        //  2443: ifne            2505
        //  2446: aload_0        
        //  2447: getfield        bez.w:Lbfm;
        //  2450: astore_3       
        //  2451: aload_3        
        //  2452: getfield        bfm.d:I
        //  2455: istore          5
        //  2457: iload           5
        //  2459: iconst_2       
        //  2460: if_icmpeq       2473
        //  2463: lload           14
        //  2465: lstore          16
        //  2467: iload           5
        //  2469: iconst_3       
        //  2470: if_icmpne       2505
        //  2473: aload_3        
        //  2474: getfield        bfm.o:J
        //  2477: lstore          14
        //  2479: aload_0        
        //  2480: aload_1        
        //  2481: lload           14
        //  2483: lload           12
        //  2485: lload           14
        //  2487: iload_2        
        //  2488: iconst_2       
        //  2489: invokespecial   bez.U:(Layx;JJJZI)Lbfm;
        //  2492: astore_1       
        //  2493: aload_0        
        //  2494: aload_1        
        //  2495: putfield        bez.w:Lbfm;
        //  2498: goto            3017
        //  2501: lload           9
        //  2503: lstore          16
        //  2505: aload_0        
        //  2506: getfield        bez.w:Lbfm;
        //  2509: getfield        bfm.d:I
        //  2512: iconst_4       
        //  2513: if_icmpne       2522
        //  2516: iconst_1       
        //  2517: istore          18
        //  2519: goto            2525
        //  2522: iconst_0       
        //  2523: istore          18
        //  2525: aload_0        
        //  2526: aload_1        
        //  2527: lload           16
        //  2529: iload           18
        //  2531: invokespecial   bez.S:(Layx;JZ)J
        //  2534: lstore          14
        //  2536: lload           9
        //  2538: lload           14
        //  2540: lcmp           
        //  2541: ifeq            2550
        //  2544: iconst_1       
        //  2545: istore          5
        //  2547: goto            2553
        //  2550: iconst_0       
        //  2551: istore          5
        //  2553: iload_2        
        //  2554: iload           5
        //  2556: ior            
        //  2557: istore_2       
        //  2558: aload_0        
        //  2559: getfield        bez.w:Lbfm;
        //  2562: astore          4
        //  2564: aload           4
        //  2566: getfield        bfm.a:Lazl;
        //  2569: astore_3       
        //  2570: aload_0        
        //  2571: aload_3        
        //  2572: aload_1        
        //  2573: aload_3        
        //  2574: aload           4
        //  2576: getfield        bfm.q:Layx;
        //  2579: lload           12
        //  2581: invokespecial   bez.V:(Lazl;Layx;Lazl;Layx;J)V
        //  2584: aload_0        
        //  2585: aload_1        
        //  2586: lload           14
        //  2588: lload           12
        //  2590: lload           14
        //  2592: iload_2        
        //  2593: iconst_2       
        //  2594: invokespecial   bez.U:(Layx;JJJZI)Lbfm;
        //  2597: astore_1       
        //  2598: goto            2493
        //  2601: astore_3       
        //  2602: lload           14
        //  2604: lstore          9
        //  2606: goto            2610
        //  2609: astore_3       
        //  2610: aload_0        
        //  2611: aload_0        
        //  2612: aload_1        
        //  2613: lload           9
        //  2615: lload           12
        //  2617: lload           9
        //  2619: iload_2        
        //  2620: iconst_2       
        //  2621: invokespecial   bez.U:(Layx;JJJZI)Lbfm;
        //  2624: putfield        bez.w:Lbfm;
        //  2627: aload_3        
        //  2628: athrow         
        //  2629: aload_0        
        //  2630: invokespecial   bez.m:()V
        //  2633: goto            3017
        //  2636: aload_1        
        //  2637: getfield        android/os/Message.arg1:I
        //  2640: ifeq            2648
        //  2643: iconst_1       
        //  2644: istore_2       
        //  2645: goto            2650
        //  2648: iconst_0       
        //  2649: istore_2       
        //  2650: aload_0        
        //  2651: iload_2        
        //  2652: aload_1        
        //  2653: getfield        android/os/Message.arg2:I
        //  2656: iconst_1       
        //  2657: iconst_1       
        //  2658: invokespecial   bez.D:(ZIZI)V
        //  2661: goto            3017
        //  2664: aload_0        
        //  2665: getfield        bez.N:Llzz;
        //  2668: iconst_1       
        //  2669: invokevirtual   lzz.b:(I)V
        //  2672: aload_0        
        //  2673: iconst_0       
        //  2674: iconst_0       
        //  2675: iconst_0       
        //  2676: iconst_1       
        //  2677: invokespecial   bez.w:(ZZZZ)V
        //  2680: aload_0        
        //  2681: getfield        bez.i:Lbfb;
        //  2684: invokeinterface bfb.c:()V
        //  2689: iconst_1       
        //  2690: aload_0        
        //  2691: getfield        bez.w:Lbfm;
        //  2694: getfield        bfm.a:Lazl;
        //  2697: invokevirtual   azl.p:()Z
        //  2700: if_icmpeq       2709
        //  2703: iconst_2       
        //  2704: istore          5
        //  2706: goto            2712
        //  2709: iconst_4       
        //  2710: istore          5
        //  2712: aload_0        
        //  2713: iload           5
        //  2715: invokespecial   bez.E:(I)V
        //  2718: aload_0        
        //  2719: getfield        bez.t:Lbfl;
        //  2722: astore_1       
        //  2723: aload_0        
        //  2724: getfield        bez.j:Lbrd;
        //  2727: invokeinterface brd.f:()Lbcn;
        //  2732: astore_3       
        //  2733: aload_1        
        //  2734: getfield        bfl.h:Z
        //  2737: iconst_1       
        //  2738: ixor           
        //  2739: invokestatic    dk.h:(Z)V
        //  2742: aload_1        
        //  2743: aload_3        
        //  2744: putfield        bfl.i:Lbcn;
        //  2747: iconst_0       
        //  2748: istore          5
        //  2750: iload           5
        //  2752: aload_1        
        //  2753: getfield        bfl.a:Ljava/util/List;
        //  2756: invokeinterface java/util/List.size:()I
        //  2761: if_icmpge       2801
        //  2764: aload_1        
        //  2765: getfield        bfl.a:Ljava/util/List;
        //  2768: iload           5
        //  2770: invokeinterface java/util/List.get:(I)Ljava/lang/Object;
        //  2775: checkcast       Lbfj;
        //  2778: astore_3       
        //  2779: aload_1        
        //  2780: aload_3        
        //  2781: invokevirtual   bfl.d:(Lbfj;)V
        //  2784: aload_1        
        //  2785: getfield        bfl.g:Ljava/util/Set;
        //  2788: aload_3        
        //  2789: invokeinterface java/util/Set.add:(Ljava/lang/Object;)Z
        //  2794: pop            
        //  2795: iinc            5, 1
        //  2798: goto            2750
        //  2801: aload_1        
        //  2802: iconst_1       
        //  2803: putfield        bfl.h:Z
        //  2806: aload_0        
        //  2807: getfield        bez.a:Lbaj;
        //  2810: iconst_2       
        //  2811: invokeinterface baj.d:(I)V
        //  2816: goto            3017
        //  2819: astore_1       
        //  2820: aload_1        
        //  2821: instanceof      Ljava/lang/IllegalStateException;
        //  2824: ifne            2845
        //  2827: aload_1        
        //  2828: instanceof      Ljava/lang/IllegalArgumentException;
        //  2831: ifeq            2837
        //  2834: goto            2845
        //  2837: sipush          1000
        //  2840: istore          5
        //  2842: goto            2850
        //  2845: sipush          1004
        //  2848: istore          5
        //  2850: aload_1        
        //  2851: iload           5
        //  2853: invokestatic    bee.b:(Ljava/lang/RuntimeException;I)Lbee;
        //  2856: astore_1       
        //  2857: ldc_w           "ExoPlayerImplInternal"
        //  2860: ldc_w           "Playback error"
        //  2863: aload_1        
        //  2864: invokestatic    bao.b:(Ljava/lang/String;Ljava/lang/String;Ljava/lang/Throwable;)V
        //  2867: aload_0        
        //  2868: iconst_1       
        //  2869: iconst_0       
        //  2870: invokespecial   bez.G:(ZZ)V
        //  2873: aload_0        
        //  2874: aload_0        
        //  2875: getfield        bez.w:Lbfm;
        //  2878: aload_1        
        //  2879: invokevirtual   bfm.b:(Lbee;)Lbfm;
        //  2882: putfield        bez.w:Lbfm;
        //  2885: goto            3017
        //  2888: astore_1       
        //  2889: aload_0        
        //  2890: aload_1        
        //  2891: sipush          2000
        //  2894: invokespecial   bez.p:(Ljava/io/IOException;I)V
        //  2897: goto            3017
        //  2900: astore_1       
        //  2901: aload_0        
        //  2902: aload_1        
        //  2903: sipush          1002
        //  2906: invokespecial   bez.p:(Ljava/io/IOException;I)V
        //  2909: goto            3017
        //  2912: astore_1       
        //  2913: aload_0        
        //  2914: aload_1        
        //  2915: aload_1        
        //  2916: getfield        bbl.a:I
        //  2919: invokespecial   bez.p:(Ljava/io/IOException;I)V
        //  2922: goto            3017
        //  2925: astore_1       
        //  2926: aload_1        
        //  2927: getfield        ayz.b:I
        //  2930: istore          5
        //  2932: iload           5
        //  2934: iconst_1       
        //  2935: if_icmpne       2962
        //  2938: iconst_1       
        //  2939: aload_1        
        //  2940: getfield        ayz.a:Z
        //  2943: if_icmpeq       2954
        //  2946: sipush          3003
        //  2949: istore          5
        //  2951: goto            2997
        //  2954: sipush          3001
        //  2957: istore          5
        //  2959: goto            2997
        //  2962: iload           5
        //  2964: iconst_4       
        //  2965: if_icmpne       2992
        //  2968: iconst_1       
        //  2969: aload_1        
        //  2970: getfield        ayz.a:Z
        //  2973: if_icmpeq       2984
        //  2976: sipush          3004
        //  2979: istore          5
        //  2981: goto            2997
        //  2984: sipush          3002
        //  2987: istore          5
        //  2989: goto            2997
        //  2992: sipush          1000
        //  2995: istore          5
        //  2997: aload_0        
        //  2998: aload_1        
        //  2999: iload           5
        //  3001: invokespecial   bez.p:(Ljava/io/IOException;I)V
        //  3004: goto            3017
        //  3007: astore_1       
        //  3008: aload_0        
        //  3009: aload_1        
        //  3010: aload_1        
        //  3011: getfield        bkk.a:I
        //  3014: invokespecial   bez.p:(Ljava/io/IOException;I)V
        //  3017: goto            3191
        //  3020: astore_3       
        //  3021: aload_3        
        //  3022: astore_1       
        //  3023: aload_3        
        //  3024: getfield        bee.c:I
        //  3027: iconst_1       
        //  3028: if_icmpne       3060
        //  3031: aload_0        
        //  3032: getfield        bez.s:Lbff;
        //  3035: getfield        bff.e:Lbfd;
        //  3038: astore          4
        //  3040: aload_3        
        //  3041: astore_1       
        //  3042: aload           4
        //  3044: ifnull          3060
        //  3047: aload_3        
        //  3048: aload           4
        //  3050: getfield        bfd.f:Lbfe;
        //  3053: getfield        bfe.i:Layx;
        //  3056: invokevirtual   bee.a:(Layx;)Lbee;
        //  3059: astore_1       
        //  3060: aload_1        
        //  3061: getfield        bee.i:Z
        //  3064: ifeq            3112
        //  3067: aload_0        
        //  3068: getfield        bez.K:Lbee;
        //  3071: ifnonnull       3112
        //  3074: ldc_w           "ExoPlayerImplInternal"
        //  3077: ldc_w           "Recoverable renderer error"
        //  3080: aload_1        
        //  3081: invokestatic    bao.d:(Ljava/lang/String;Ljava/lang/String;Ljava/lang/Throwable;)V
        //  3084: aload_0        
        //  3085: aload_1        
        //  3086: putfield        bez.K:Lbee;
        //  3089: aload_0        
        //  3090: getfield        bez.a:Lbaj;
        //  3093: astore_3       
        //  3094: aload_3        
        //  3095: aload_3        
        //  3096: bipush          25
        //  3098: aload_1        
        //  3099: invokeinterface baj.f:(ILjava/lang/Object;)Lelw;
        //  3104: invokeinterface baj.h:(Lelw;)V
        //  3109: goto            3017
        //  3112: aload_0        
        //  3113: getfield        bez.K:Lbee;
        //  3116: astore          4
        //  3118: aload_1        
        //  3119: astore_3       
        //  3120: aload           4
        //  3122: ifnull          3163
        //  3125: ldc_w           Ljava/lang/Throwable;.class
        //  3128: ldc_w           "addSuppressed"
        //  3131: iconst_1       
        //  3132: anewarray       Ljava/lang/Class;
        //  3135: dup            
        //  3136: iconst_0       
        //  3137: ldc_w           Ljava/lang/Throwable;.class
        //  3140: aastore        
        //  3141: invokevirtual   java/lang/Class.getDeclaredMethod:(Ljava/lang/String;[Ljava/lang/Class;)Ljava/lang/reflect/Method;
        //  3144: aload           4
        //  3146: iconst_1       
        //  3147: anewarray       Ljava/lang/Object;
        //  3150: dup            
        //  3151: iconst_0       
        //  3152: aload_1        
        //  3153: aastore        
        //  3154: invokevirtual   java/lang/reflect/Method.invoke:(Ljava/lang/Object;[Ljava/lang/Object;)Ljava/lang/Object;
        //  3157: pop            
        //  3158: aload_0        
        //  3159: getfield        bez.K:Lbee;
        //  3162: astore_3       
        //  3163: ldc_w           "ExoPlayerImplInternal"
        //  3166: ldc_w           "Playback error"
        //  3169: aload_3        
        //  3170: invokestatic    bao.b:(Ljava/lang/String;Ljava/lang/String;Ljava/lang/Throwable;)V
        //  3173: aload_0        
        //  3174: iconst_1       
        //  3175: iconst_0       
        //  3176: invokespecial   bez.G:(ZZ)V
        //  3179: aload_0        
        //  3180: aload_0        
        //  3181: getfield        bez.w:Lbfm;
        //  3184: aload_3        
        //  3185: invokevirtual   bfm.b:(Lbee;)Lbfm;
        //  3188: putfield        bez.w:Lbfm;
        //  3191: aload_0        
        //  3192: invokespecial   bez.v:()V
        //  3195: iconst_1       
        //  3196: ireturn        
        //  3197: astore_1       
        //  3198: goto            3158
        //    Exceptions:
        //  Try           Handler
        //  Start  End    Start  End    Type                        
        //  -----  -----  -----  -----  ----------------------------
        //  0      124    3020   3191   Lbee;
        //  0      124    3007   3017   Lbkk;
        //  0      124    2925   3007   Layz;
        //  0      124    2912   2925   Lbbl;
        //  0      124    2900   2912   Lbms;
        //  0      124    2888   2900   Ljava/io/IOException;
        //  0      124    2819   2888   Ljava/lang/RuntimeException;
        //  126    131    3020   3191   Lbee;
        //  126    131    3007   3017   Lbkk;
        //  126    131    2925   3007   Layz;
        //  126    131    2912   2925   Lbbl;
        //  126    131    2900   2912   Lbms;
        //  126    131    2888   2900   Ljava/io/IOException;
        //  126    131    2819   2888   Ljava/lang/RuntimeException;
        //  134    142    3020   3191   Lbee;
        //  134    142    3007   3017   Lbkk;
        //  134    142    2925   3007   Layz;
        //  134    142    2912   2925   Lbbl;
        //  134    142    2900   2912   Lbms;
        //  134    142    2888   2900   Ljava/io/IOException;
        //  134    142    2819   2888   Ljava/lang/RuntimeException;
        //  149    162    3020   3191   Lbee;
        //  149    162    3007   3017   Lbkk;
        //  149    162    2925   3007   Layz;
        //  149    162    2912   2925   Lbbl;
        //  149    162    2900   2912   Lbms;
        //  149    162    2888   2900   Ljava/io/IOException;
        //  149    162    2819   2888   Ljava/lang/RuntimeException;
        //  166    186    3020   3191   Lbee;
        //  166    186    3007   3017   Lbkk;
        //  166    186    2925   3007   Layz;
        //  166    186    2912   2925   Lbbl;
        //  166    186    2900   2912   Lbms;
        //  166    186    2888   2900   Ljava/io/IOException;
        //  166    186    2819   2888   Ljava/lang/RuntimeException;
        //  189    196    3020   3191   Lbee;
        //  189    196    3007   3017   Lbkk;
        //  189    196    2925   3007   Layz;
        //  189    196    2912   2925   Lbbl;
        //  189    196    2900   2912   Lbms;
        //  189    196    2888   2900   Ljava/io/IOException;
        //  189    196    2819   2888   Ljava/lang/RuntimeException;
        //  203    245    3020   3191   Lbee;
        //  203    245    3007   3017   Lbkk;
        //  203    245    2925   3007   Layz;
        //  203    245    2912   2925   Lbbl;
        //  203    245    2900   2912   Lbms;
        //  203    245    2888   2900   Ljava/io/IOException;
        //  203    245    2819   2888   Ljava/lang/RuntimeException;
        //  248    260    3020   3191   Lbee;
        //  248    260    3007   3017   Lbkk;
        //  248    260    2925   3007   Layz;
        //  248    260    2912   2925   Lbbl;
        //  248    260    2900   2912   Lbms;
        //  248    260    2888   2900   Ljava/io/IOException;
        //  248    260    2819   2888   Ljava/lang/RuntimeException;
        //  263    292    3020   3191   Lbee;
        //  263    292    3007   3017   Lbkk;
        //  263    292    2925   3007   Layz;
        //  263    292    2912   2925   Lbbl;
        //  263    292    2900   2912   Lbms;
        //  263    292    2888   2900   Ljava/io/IOException;
        //  263    292    2819   2888   Ljava/lang/RuntimeException;
        //  294    340    3020   3191   Lbee;
        //  294    340    3007   3017   Lbkk;
        //  294    340    2925   3007   Layz;
        //  294    340    2912   2925   Lbbl;
        //  294    340    2900   2912   Lbms;
        //  294    340    2888   2900   Ljava/io/IOException;
        //  294    340    2819   2888   Ljava/lang/RuntimeException;
        //  340    356    3020   3191   Lbee;
        //  340    356    3007   3017   Lbkk;
        //  340    356    2925   3007   Layz;
        //  340    356    2912   2925   Lbbl;
        //  340    356    2900   2912   Lbms;
        //  340    356    2888   2900   Ljava/io/IOException;
        //  340    356    2819   2888   Ljava/lang/RuntimeException;
        //  359    392    3020   3191   Lbee;
        //  359    392    3007   3017   Lbkk;
        //  359    392    2925   3007   Layz;
        //  359    392    2912   2925   Lbbl;
        //  359    392    2900   2912   Lbms;
        //  359    392    2888   2900   Ljava/io/IOException;
        //  359    392    2819   2888   Ljava/lang/RuntimeException;
        //  404    413    3020   3191   Lbee;
        //  404    413    3007   3017   Lbkk;
        //  404    413    2925   3007   Layz;
        //  404    413    2912   2925   Lbbl;
        //  404    413    2900   2912   Lbms;
        //  404    413    2888   2900   Ljava/io/IOException;
        //  404    413    2819   2888   Ljava/lang/RuntimeException;
        //  420    446    3020   3191   Lbee;
        //  420    446    3007   3017   Lbkk;
        //  420    446    2925   3007   Layz;
        //  420    446    2912   2925   Lbbl;
        //  420    446    2900   2912   Lbms;
        //  420    446    2888   2900   Ljava/io/IOException;
        //  420    446    2819   2888   Ljava/lang/RuntimeException;
        //  449    500    3020   3191   Lbee;
        //  449    500    3007   3017   Lbkk;
        //  449    500    2925   3007   Layz;
        //  449    500    2912   2925   Lbbl;
        //  449    500    2900   2912   Lbms;
        //  449    500    2888   2900   Ljava/io/IOException;
        //  449    500    2819   2888   Ljava/lang/RuntimeException;
        //  507    525    3020   3191   Lbee;
        //  507    525    3007   3017   Lbkk;
        //  507    525    2925   3007   Layz;
        //  507    525    2912   2925   Lbbl;
        //  507    525    2900   2912   Lbms;
        //  507    525    2888   2900   Ljava/io/IOException;
        //  507    525    2819   2888   Ljava/lang/RuntimeException;
        //  528    555    3020   3191   Lbee;
        //  528    555    3007   3017   Lbkk;
        //  528    555    2925   3007   Layz;
        //  528    555    2912   2925   Lbbl;
        //  528    555    2900   2912   Lbms;
        //  528    555    2888   2900   Ljava/io/IOException;
        //  528    555    2819   2888   Ljava/lang/RuntimeException;
        //  565    571    3020   3191   Lbee;
        //  565    571    3007   3017   Lbkk;
        //  565    571    2925   3007   Layz;
        //  565    571    2912   2925   Lbbl;
        //  565    571    2900   2912   Lbms;
        //  565    571    2888   2900   Ljava/io/IOException;
        //  565    571    2819   2888   Ljava/lang/RuntimeException;
        //  571    593    3020   3191   Lbee;
        //  571    593    3007   3017   Lbkk;
        //  571    593    2925   3007   Layz;
        //  571    593    2912   2925   Lbbl;
        //  571    593    2900   2912   Lbms;
        //  571    593    2888   2900   Ljava/io/IOException;
        //  571    593    2819   2888   Ljava/lang/RuntimeException;
        //  596    666    3020   3191   Lbee;
        //  596    666    3007   3017   Lbkk;
        //  596    666    2925   3007   Layz;
        //  596    666    2912   2925   Lbbl;
        //  596    666    2900   2912   Lbms;
        //  596    666    2888   2900   Ljava/io/IOException;
        //  596    666    2819   2888   Ljava/lang/RuntimeException;
        //  666    723    3020   3191   Lbee;
        //  666    723    3007   3017   Lbkk;
        //  666    723    2925   3007   Layz;
        //  666    723    2912   2925   Lbbl;
        //  666    723    2900   2912   Lbms;
        //  666    723    2888   2900   Ljava/io/IOException;
        //  666    723    2819   2888   Ljava/lang/RuntimeException;
        //  726    738    3020   3191   Lbee;
        //  726    738    3007   3017   Lbkk;
        //  726    738    2925   3007   Layz;
        //  726    738    2912   2925   Lbbl;
        //  726    738    2900   2912   Lbms;
        //  726    738    2888   2900   Ljava/io/IOException;
        //  726    738    2819   2888   Ljava/lang/RuntimeException;
        //  741    778    3020   3191   Lbee;
        //  741    778    3007   3017   Lbkk;
        //  741    778    2925   3007   Layz;
        //  741    778    2912   2925   Lbbl;
        //  741    778    2900   2912   Lbms;
        //  741    778    2888   2900   Ljava/io/IOException;
        //  741    778    2819   2888   Ljava/lang/RuntimeException;
        //  781    812    3020   3191   Lbee;
        //  781    812    3007   3017   Lbkk;
        //  781    812    2925   3007   Layz;
        //  781    812    2912   2925   Lbbl;
        //  781    812    2900   2912   Lbms;
        //  781    812    2888   2900   Ljava/io/IOException;
        //  781    812    2819   2888   Ljava/lang/RuntimeException;
        //  815    839    3020   3191   Lbee;
        //  815    839    3007   3017   Lbkk;
        //  815    839    2925   3007   Layz;
        //  815    839    2912   2925   Lbbl;
        //  815    839    2900   2912   Lbms;
        //  815    839    2888   2900   Ljava/io/IOException;
        //  815    839    2819   2888   Ljava/lang/RuntimeException;
        //  842    878    3020   3191   Lbee;
        //  842    878    3007   3017   Lbkk;
        //  842    878    2925   3007   Layz;
        //  842    878    2912   2925   Lbbl;
        //  842    878    2900   2912   Lbms;
        //  842    878    2888   2900   Ljava/io/IOException;
        //  842    878    2819   2888   Ljava/lang/RuntimeException;
        //  881    942    3020   3191   Lbee;
        //  881    942    3007   3017   Lbkk;
        //  881    942    2925   3007   Layz;
        //  881    942    2912   2925   Lbbl;
        //  881    942    2900   2912   Lbms;
        //  881    942    2888   2900   Ljava/io/IOException;
        //  881    942    2819   2888   Ljava/lang/RuntimeException;
        //  945    950    3020   3191   Lbee;
        //  945    950    3007   3017   Lbkk;
        //  945    950    2925   3007   Layz;
        //  945    950    2912   2925   Lbbl;
        //  945    950    2900   2912   Lbms;
        //  945    950    2888   2900   Ljava/io/IOException;
        //  945    950    2819   2888   Ljava/lang/RuntimeException;
        //  953    960    3020   3191   Lbee;
        //  953    960    3007   3017   Lbkk;
        //  953    960    2925   3007   Layz;
        //  953    960    2912   2925   Lbbl;
        //  953    960    2900   2912   Lbms;
        //  953    960    2888   2900   Ljava/io/IOException;
        //  953    960    2819   2888   Ljava/lang/RuntimeException;
        //  967    989    3020   3191   Lbee;
        //  967    989    3007   3017   Lbkk;
        //  967    989    2925   3007   Layz;
        //  967    989    2912   2925   Lbbl;
        //  967    989    2900   2912   Lbms;
        //  967    989    2888   2900   Ljava/io/IOException;
        //  967    989    2819   2888   Ljava/lang/RuntimeException;
        //  993    1002   3020   3191   Lbee;
        //  993    1002   3007   3017   Lbkk;
        //  993    1002   2925   3007   Layz;
        //  993    1002   2912   2925   Lbbl;
        //  993    1002   2900   2912   Lbms;
        //  993    1002   2888   2900   Ljava/io/IOException;
        //  993    1002   2819   2888   Ljava/lang/RuntimeException;
        //  1017   1043   3020   3191   Lbee;
        //  1017   1043   3007   3017   Lbkk;
        //  1017   1043   2925   3007   Layz;
        //  1017   1043   2912   2925   Lbbl;
        //  1017   1043   2900   2912   Lbms;
        //  1017   1043   2888   2900   Ljava/io/IOException;
        //  1017   1043   2819   2888   Ljava/lang/RuntimeException;
        //  1054   1056   3020   3191   Lbee;
        //  1054   1056   3007   3017   Lbkk;
        //  1054   1056   2925   3007   Layz;
        //  1054   1056   2912   2925   Lbbl;
        //  1054   1056   2900   2912   Lbms;
        //  1054   1056   2888   2900   Ljava/io/IOException;
        //  1054   1056   2819   2888   Ljava/lang/RuntimeException;
        //  1056   1068   1071   1076   Any
        //  1072   1074   1071   1076   Any
        //  1074   1076   3020   3191   Lbee;
        //  1074   1076   3007   3017   Lbkk;
        //  1074   1076   2925   3007   Layz;
        //  1074   1076   2912   2925   Lbbl;
        //  1074   1076   2900   2912   Lbms;
        //  1074   1076   2888   2900   Ljava/io/IOException;
        //  1074   1076   2819   2888   Ljava/lang/RuntimeException;
        //  1076   1083   3020   3191   Lbee;
        //  1076   1083   3007   3017   Lbkk;
        //  1076   1083   2925   3007   Layz;
        //  1076   1083   2912   2925   Lbbl;
        //  1076   1083   2900   2912   Lbms;
        //  1076   1083   2888   2900   Ljava/io/IOException;
        //  1076   1083   2819   2888   Ljava/lang/RuntimeException;
        //  1090   1126   3020   3191   Lbee;
        //  1090   1126   3007   3017   Lbkk;
        //  1090   1126   2925   3007   Layz;
        //  1090   1126   2912   2925   Lbbl;
        //  1090   1126   2900   2912   Lbms;
        //  1090   1126   2888   2900   Ljava/io/IOException;
        //  1090   1126   2819   2888   Ljava/lang/RuntimeException;
        //  1126   1131   3020   3191   Lbee;
        //  1126   1131   3007   3017   Lbkk;
        //  1126   1131   2925   3007   Layz;
        //  1126   1131   2912   2925   Lbbl;
        //  1126   1131   2900   2912   Lbms;
        //  1126   1131   2888   2900   Ljava/io/IOException;
        //  1126   1131   2819   2888   Ljava/lang/RuntimeException;
        //  1134   1178   3020   3191   Lbee;
        //  1134   1178   3007   3017   Lbkk;
        //  1134   1178   2925   3007   Layz;
        //  1134   1178   2912   2925   Lbbl;
        //  1134   1178   2900   2912   Lbms;
        //  1134   1178   2888   2900   Ljava/io/IOException;
        //  1134   1178   2819   2888   Ljava/lang/RuntimeException;
        //  1178   1183   3020   3191   Lbee;
        //  1178   1183   3007   3017   Lbkk;
        //  1178   1183   2925   3007   Layz;
        //  1178   1183   2912   2925   Lbbl;
        //  1178   1183   2900   2912   Lbms;
        //  1178   1183   2888   2900   Ljava/io/IOException;
        //  1178   1183   2819   2888   Ljava/lang/RuntimeException;
        //  1186   1213   3020   3191   Lbee;
        //  1186   1213   3007   3017   Lbkk;
        //  1186   1213   2925   3007   Layz;
        //  1186   1213   2912   2925   Lbbl;
        //  1186   1213   2900   2912   Lbms;
        //  1186   1213   2888   2900   Ljava/io/IOException;
        //  1186   1213   2819   2888   Ljava/lang/RuntimeException;
        //  1220   1227   3020   3191   Lbee;
        //  1220   1227   3007   3017   Lbkk;
        //  1220   1227   2925   3007   Layz;
        //  1220   1227   2912   2925   Lbbl;
        //  1220   1227   2900   2912   Lbms;
        //  1220   1227   2888   2900   Ljava/io/IOException;
        //  1220   1227   2819   2888   Ljava/lang/RuntimeException;
        //  1230   1251   3020   3191   Lbee;
        //  1230   1251   3007   3017   Lbkk;
        //  1230   1251   2925   3007   Layz;
        //  1230   1251   2912   2925   Lbbl;
        //  1230   1251   2900   2912   Lbms;
        //  1230   1251   2888   2900   Ljava/io/IOException;
        //  1230   1251   2819   2888   Ljava/lang/RuntimeException;
        //  1256   1277   3020   3191   Lbee;
        //  1256   1277   3007   3017   Lbkk;
        //  1256   1277   2925   3007   Layz;
        //  1256   1277   2912   2925   Lbbl;
        //  1256   1277   2900   2912   Lbms;
        //  1256   1277   2888   2900   Ljava/io/IOException;
        //  1256   1277   2819   2888   Ljava/lang/RuntimeException;
        //  1283   1309   3020   3191   Lbee;
        //  1283   1309   3007   3017   Lbkk;
        //  1283   1309   2925   3007   Layz;
        //  1283   1309   2912   2925   Lbbl;
        //  1283   1309   2900   2912   Lbms;
        //  1283   1309   2888   2900   Ljava/io/IOException;
        //  1283   1309   2819   2888   Ljava/lang/RuntimeException;
        //  1336   1341   3020   3191   Lbee;
        //  1336   1341   3007   3017   Lbkk;
        //  1336   1341   2925   3007   Layz;
        //  1336   1341   2912   2925   Lbbl;
        //  1336   1341   2900   2912   Lbms;
        //  1336   1341   2888   2900   Ljava/io/IOException;
        //  1336   1341   2819   2888   Ljava/lang/RuntimeException;
        //  1349   1416   3020   3191   Lbee;
        //  1349   1416   3007   3017   Lbkk;
        //  1349   1416   2925   3007   Layz;
        //  1349   1416   2912   2925   Lbbl;
        //  1349   1416   2900   2912   Lbms;
        //  1349   1416   2888   2900   Ljava/io/IOException;
        //  1349   1416   2819   2888   Ljava/lang/RuntimeException;
        //  1423   1456   3020   3191   Lbee;
        //  1423   1456   3007   3017   Lbkk;
        //  1423   1456   2925   3007   Layz;
        //  1423   1456   2912   2925   Lbbl;
        //  1423   1456   2900   2912   Lbms;
        //  1423   1456   2888   2900   Ljava/io/IOException;
        //  1423   1456   2819   2888   Ljava/lang/RuntimeException;
        //  1460   1466   3020   3191   Lbee;
        //  1460   1466   3007   3017   Lbkk;
        //  1460   1466   2925   3007   Layz;
        //  1460   1466   2912   2925   Lbbl;
        //  1460   1466   2900   2912   Lbms;
        //  1460   1466   2888   2900   Ljava/io/IOException;
        //  1460   1466   2819   2888   Ljava/lang/RuntimeException;
        //  1466   1475   3020   3191   Lbee;
        //  1466   1475   3007   3017   Lbkk;
        //  1466   1475   2925   3007   Layz;
        //  1466   1475   2912   2925   Lbbl;
        //  1466   1475   2900   2912   Lbms;
        //  1466   1475   2888   2900   Ljava/io/IOException;
        //  1466   1475   2819   2888   Ljava/lang/RuntimeException;
        //  1478   1492   3020   3191   Lbee;
        //  1478   1492   3007   3017   Lbkk;
        //  1478   1492   2925   3007   Layz;
        //  1478   1492   2912   2925   Lbbl;
        //  1478   1492   2900   2912   Lbms;
        //  1478   1492   2888   2900   Ljava/io/IOException;
        //  1478   1492   2819   2888   Ljava/lang/RuntimeException;
        //  1499   1505   3020   3191   Lbee;
        //  1499   1505   3007   3017   Lbkk;
        //  1499   1505   2925   3007   Layz;
        //  1499   1505   2912   2925   Lbbl;
        //  1499   1505   2900   2912   Lbms;
        //  1499   1505   2888   2900   Ljava/io/IOException;
        //  1499   1505   2819   2888   Ljava/lang/RuntimeException;
        //  1511   1520   3020   3191   Lbee;
        //  1511   1520   3007   3017   Lbkk;
        //  1511   1520   2925   3007   Layz;
        //  1511   1520   2912   2925   Lbbl;
        //  1511   1520   2900   2912   Lbms;
        //  1511   1520   2888   2900   Ljava/io/IOException;
        //  1511   1520   2819   2888   Ljava/lang/RuntimeException;
        //  1524   1542   3020   3191   Lbee;
        //  1524   1542   3007   3017   Lbkk;
        //  1524   1542   2925   3007   Layz;
        //  1524   1542   2912   2925   Lbbl;
        //  1524   1542   2900   2912   Lbms;
        //  1524   1542   2888   2900   Ljava/io/IOException;
        //  1524   1542   2819   2888   Ljava/lang/RuntimeException;
        //  1552   1563   3020   3191   Lbee;
        //  1552   1563   3007   3017   Lbkk;
        //  1552   1563   2925   3007   Layz;
        //  1552   1563   2912   2925   Lbbl;
        //  1552   1563   2900   2912   Lbms;
        //  1552   1563   2888   2900   Ljava/io/IOException;
        //  1552   1563   2819   2888   Ljava/lang/RuntimeException;
        //  1569   1575   3020   3191   Lbee;
        //  1569   1575   3007   3017   Lbkk;
        //  1569   1575   2925   3007   Layz;
        //  1569   1575   2912   2925   Lbbl;
        //  1569   1575   2900   2912   Lbms;
        //  1569   1575   2888   2900   Ljava/io/IOException;
        //  1569   1575   2819   2888   Ljava/lang/RuntimeException;
        //  1578   1619   3020   3191   Lbee;
        //  1578   1619   3007   3017   Lbkk;
        //  1578   1619   2925   3007   Layz;
        //  1578   1619   2912   2925   Lbbl;
        //  1578   1619   2900   2912   Lbms;
        //  1578   1619   2888   2900   Ljava/io/IOException;
        //  1578   1619   2819   2888   Ljava/lang/RuntimeException;
        //  1619   1653   3020   3191   Lbee;
        //  1619   1653   3007   3017   Lbkk;
        //  1619   1653   2925   3007   Layz;
        //  1619   1653   2912   2925   Lbbl;
        //  1619   1653   2900   2912   Lbms;
        //  1619   1653   2888   2900   Ljava/io/IOException;
        //  1619   1653   2819   2888   Ljava/lang/RuntimeException;
        //  1656   1690   3020   3191   Lbee;
        //  1656   1690   3007   3017   Lbkk;
        //  1656   1690   2925   3007   Layz;
        //  1656   1690   2912   2925   Lbbl;
        //  1656   1690   2900   2912   Lbms;
        //  1656   1690   2888   2900   Ljava/io/IOException;
        //  1656   1690   2819   2888   Ljava/lang/RuntimeException;
        //  1693   1784   3020   3191   Lbee;
        //  1693   1784   3007   3017   Lbkk;
        //  1693   1784   2925   3007   Layz;
        //  1693   1784   2912   2925   Lbbl;
        //  1693   1784   2900   2912   Lbms;
        //  1693   1784   2888   2900   Ljava/io/IOException;
        //  1693   1784   2819   2888   Ljava/lang/RuntimeException;
        //  1809   1819   3020   3191   Lbee;
        //  1809   1819   3007   3017   Lbkk;
        //  1809   1819   2925   3007   Layz;
        //  1809   1819   2912   2925   Lbbl;
        //  1809   1819   2900   2912   Lbms;
        //  1809   1819   2888   2900   Ljava/io/IOException;
        //  1809   1819   2819   2888   Ljava/lang/RuntimeException;
        //  1819   1943   3020   3191   Lbee;
        //  1819   1943   3007   3017   Lbkk;
        //  1819   1943   2925   3007   Layz;
        //  1819   1943   2912   2925   Lbbl;
        //  1819   1943   2900   2912   Lbms;
        //  1819   1943   2888   2900   Ljava/io/IOException;
        //  1819   1943   2819   2888   Ljava/lang/RuntimeException;
        //  1943   1947   3020   3191   Lbee;
        //  1943   1947   3007   3017   Lbkk;
        //  1943   1947   2925   3007   Layz;
        //  1943   1947   2912   2925   Lbbl;
        //  1943   1947   2900   2912   Lbms;
        //  1943   1947   2888   2900   Ljava/io/IOException;
        //  1943   1947   2819   2888   Ljava/lang/RuntimeException;
        //  1950   1982   3020   3191   Lbee;
        //  1950   1982   3007   3017   Lbkk;
        //  1950   1982   2925   3007   Layz;
        //  1950   1982   2912   2925   Lbbl;
        //  1950   1982   2900   2912   Lbms;
        //  1950   1982   2888   2900   Ljava/io/IOException;
        //  1950   1982   2819   2888   Ljava/lang/RuntimeException;
        //  1982   1993   1995   2000   Any
        //  1996   1998   1995   2000   Any
        //  1998   2000   3020   3191   Lbee;
        //  1998   2000   3007   3017   Lbkk;
        //  1998   2000   2925   3007   Layz;
        //  1998   2000   2912   2925   Lbbl;
        //  1998   2000   2900   2912   Lbms;
        //  1998   2000   2888   2900   Ljava/io/IOException;
        //  1998   2000   2819   2888   Ljava/lang/RuntimeException;
        //  2000   2006   3020   3191   Lbee;
        //  2000   2006   3007   3017   Lbkk;
        //  2000   2006   2925   3007   Layz;
        //  2000   2006   2912   2925   Lbbl;
        //  2000   2006   2900   2912   Lbms;
        //  2000   2006   2888   2900   Ljava/io/IOException;
        //  2000   2006   2819   2888   Ljava/lang/RuntimeException;
        //  2009   2020   3020   3191   Lbee;
        //  2009   2020   3007   3017   Lbkk;
        //  2009   2020   2925   3007   Layz;
        //  2009   2020   2912   2925   Lbbl;
        //  2009   2020   2900   2912   Lbms;
        //  2009   2020   2888   2900   Ljava/io/IOException;
        //  2009   2020   2819   2888   Ljava/lang/RuntimeException;
        //  2023   2051   3020   3191   Lbee;
        //  2023   2051   3007   3017   Lbkk;
        //  2023   2051   2925   3007   Layz;
        //  2023   2051   2912   2925   Lbbl;
        //  2023   2051   2900   2912   Lbms;
        //  2023   2051   2888   2900   Ljava/io/IOException;
        //  2023   2051   2819   2888   Ljava/lang/RuntimeException;
        //  2054   2101   3020   3191   Lbee;
        //  2054   2101   3007   3017   Lbkk;
        //  2054   2101   2925   3007   Layz;
        //  2054   2101   2912   2925   Lbbl;
        //  2054   2101   2900   2912   Lbms;
        //  2054   2101   2888   2900   Ljava/io/IOException;
        //  2054   2101   2819   2888   Ljava/lang/RuntimeException;
        //  2105   2153   3020   3191   Lbee;
        //  2105   2153   3007   3017   Lbkk;
        //  2105   2153   2925   3007   Layz;
        //  2105   2153   2912   2925   Lbbl;
        //  2105   2153   2900   2912   Lbms;
        //  2105   2153   2888   2900   Ljava/io/IOException;
        //  2105   2153   2819   2888   Ljava/lang/RuntimeException;
        //  2161   2190   3020   3191   Lbee;
        //  2161   2190   3007   3017   Lbkk;
        //  2161   2190   2925   3007   Layz;
        //  2161   2190   2912   2925   Lbbl;
        //  2161   2190   2900   2912   Lbms;
        //  2161   2190   2888   2900   Ljava/io/IOException;
        //  2161   2190   2819   2888   Ljava/lang/RuntimeException;
        //  2202   2271   3020   3191   Lbee;
        //  2202   2271   3007   3017   Lbkk;
        //  2202   2271   2925   3007   Layz;
        //  2202   2271   2912   2925   Lbbl;
        //  2202   2271   2900   2912   Lbms;
        //  2202   2271   2888   2900   Ljava/io/IOException;
        //  2202   2271   2819   2888   Ljava/lang/RuntimeException;
        //  2279   2286   3020   3191   Lbee;
        //  2279   2286   3007   3017   Lbkk;
        //  2279   2286   2925   3007   Layz;
        //  2279   2286   2912   2925   Lbbl;
        //  2279   2286   2900   2912   Lbms;
        //  2279   2286   2888   2900   Ljava/io/IOException;
        //  2279   2286   2819   2888   Ljava/lang/RuntimeException;
        //  2302   2321   2609   2610   Any
        //  2328   2344   2609   2610   Any
        //  2344   2352   2609   2610   Any
        //  2359   2381   2609   2610   Any
        //  2385   2392   2609   2610   Any
        //  2399   2416   2609   2610   Any
        //  2427   2457   2609   2610   Any
        //  2473   2479   2609   2610   Any
        //  2479   2493   3020   3191   Lbee;
        //  2479   2493   3007   3017   Lbkk;
        //  2479   2493   2925   3007   Layz;
        //  2479   2493   2912   2925   Lbbl;
        //  2479   2493   2900   2912   Lbms;
        //  2479   2493   2888   2900   Ljava/io/IOException;
        //  2479   2493   2819   2888   Ljava/lang/RuntimeException;
        //  2493   2498   3020   3191   Lbee;
        //  2493   2498   3007   3017   Lbkk;
        //  2493   2498   2925   3007   Layz;
        //  2493   2498   2912   2925   Lbbl;
        //  2493   2498   2900   2912   Lbms;
        //  2493   2498   2888   2900   Ljava/io/IOException;
        //  2493   2498   2819   2888   Ljava/lang/RuntimeException;
        //  2505   2516   2609   2610   Any
        //  2525   2536   2609   2610   Any
        //  2558   2584   2601   2609   Any
        //  2584   2598   3020   3191   Lbee;
        //  2584   2598   3007   3017   Lbkk;
        //  2584   2598   2925   3007   Layz;
        //  2584   2598   2912   2925   Lbbl;
        //  2584   2598   2900   2912   Lbms;
        //  2584   2598   2888   2900   Ljava/io/IOException;
        //  2584   2598   2819   2888   Ljava/lang/RuntimeException;
        //  2610   2629   3020   3191   Lbee;
        //  2610   2629   3007   3017   Lbkk;
        //  2610   2629   2925   3007   Layz;
        //  2610   2629   2912   2925   Lbbl;
        //  2610   2629   2900   2912   Lbms;
        //  2610   2629   2888   2900   Ljava/io/IOException;
        //  2610   2629   2819   2888   Ljava/lang/RuntimeException;
        //  2629   2633   3020   3191   Lbee;
        //  2629   2633   3007   3017   Lbkk;
        //  2629   2633   2925   3007   Layz;
        //  2629   2633   2912   2925   Lbbl;
        //  2629   2633   2900   2912   Lbms;
        //  2629   2633   2888   2900   Ljava/io/IOException;
        //  2629   2633   2819   2888   Ljava/lang/RuntimeException;
        //  2636   2643   3020   3191   Lbee;
        //  2636   2643   3007   3017   Lbkk;
        //  2636   2643   2925   3007   Layz;
        //  2636   2643   2912   2925   Lbbl;
        //  2636   2643   2900   2912   Lbms;
        //  2636   2643   2888   2900   Ljava/io/IOException;
        //  2636   2643   2819   2888   Ljava/lang/RuntimeException;
        //  2650   2661   3020   3191   Lbee;
        //  2650   2661   3007   3017   Lbkk;
        //  2650   2661   2925   3007   Layz;
        //  2650   2661   2912   2925   Lbbl;
        //  2650   2661   2900   2912   Lbms;
        //  2650   2661   2888   2900   Ljava/io/IOException;
        //  2650   2661   2819   2888   Ljava/lang/RuntimeException;
        //  2664   2703   3020   3191   Lbee;
        //  2664   2703   3007   3017   Lbkk;
        //  2664   2703   2925   3007   Layz;
        //  2664   2703   2912   2925   Lbbl;
        //  2664   2703   2900   2912   Lbms;
        //  2664   2703   2888   2900   Ljava/io/IOException;
        //  2664   2703   2819   2888   Ljava/lang/RuntimeException;
        //  2712   2747   3020   3191   Lbee;
        //  2712   2747   3007   3017   Lbkk;
        //  2712   2747   2925   3007   Layz;
        //  2712   2747   2912   2925   Lbbl;
        //  2712   2747   2900   2912   Lbms;
        //  2712   2747   2888   2900   Ljava/io/IOException;
        //  2712   2747   2819   2888   Ljava/lang/RuntimeException;
        //  2750   2795   3020   3191   Lbee;
        //  2750   2795   3007   3017   Lbkk;
        //  2750   2795   2925   3007   Layz;
        //  2750   2795   2912   2925   Lbbl;
        //  2750   2795   2900   2912   Lbms;
        //  2750   2795   2888   2900   Ljava/io/IOException;
        //  2750   2795   2819   2888   Ljava/lang/RuntimeException;
        //  2801   2816   3020   3191   Lbee;
        //  2801   2816   3007   3017   Lbkk;
        //  2801   2816   2925   3007   Layz;
        //  2801   2816   2912   2925   Lbbl;
        //  2801   2816   2900   2912   Lbms;
        //  2801   2816   2888   2900   Ljava/io/IOException;
        //  2801   2816   2819   2888   Ljava/lang/RuntimeException;
        //  3125   3158   3197   3201   Ljava/lang/Exception;
        // 
        // The error that occurred was:
        // 
        // java.lang.IllegalStateException: Expression is linked from several locations: Label_3158:
        //     at com.strobel.decompiler.ast.Error.expressionLinkedFromMultipleLocations(Error.java:27)
        //     at com.strobel.decompiler.ast.AstOptimizer.mergeDisparateObjectInitializations(AstOptimizer.java:2604)
        //     at com.strobel.decompiler.ast.AstOptimizer.optimize(AstOptimizer.java:235)
        //     at com.strobel.decompiler.ast.AstOptimizer.optimize(AstOptimizer.java:42)
        //     at com.strobel.decompiler.languages.java.ast.AstMethodBodyBuilder.createMethodBody(AstMethodBodyBuilder.java:206)
        //     at com.strobel.decompiler.languages.java.ast.AstMethodBodyBuilder.createMethodBody(AstMethodBodyBuilder.java:93)
        //     at com.strobel.decompiler.languages.java.ast.AstBuilder.createMethodBody(AstBuilder.java:868)
        //     at com.strobel.decompiler.languages.java.ast.AstBuilder.createMethod(AstBuilder.java:761)
        //     at com.strobel.decompiler.languages.java.ast.AstBuilder.addTypeMembers(AstBuilder.java:638)
        //     at com.strobel.decompiler.languages.java.ast.AstBuilder.createTypeCore(AstBuilder.java:605)
        //     at com.strobel.decompiler.languages.java.ast.AstBuilder.createTypeNoCache(AstBuilder.java:195)
        //     at com.strobel.decompiler.languages.java.ast.AstBuilder.createType(AstBuilder.java:162)
        //     at com.strobel.decompiler.languages.java.ast.AstBuilder.addType(AstBuilder.java:137)
        //     at com.strobel.decompiler.languages.java.JavaLanguage.buildAst(JavaLanguage.java:71)
        //     at com.strobel.decompiler.languages.java.JavaLanguage.decompileType(JavaLanguage.java:59)
        //     at com.strobel.decompiler.DecompilerDriver.decompileType(DecompilerDriver.java:333)
        //     at com.strobel.decompiler.DecompilerDriver.decompileJar(DecompilerDriver.java:254)
        //     at com.strobel.decompiler.DecompilerDriver.main(DecompilerDriver.java:129)
        // 
        throw new IllegalStateException("An error occurred while decompiling this method.");
    }
    
    public final void kX(final bnu bnu) {
        this.a.f(8, (Object)bnu).r();
    }
}
