import java.util.List;
import com.facebook.litho.ComponentTree;
import android.animation.Animator;

// 
// Decompiled by Procyon v0.6.0
// 

public final class dmb implements Runnable
{
    final /* synthetic */ Object a = a;
    private final /* synthetic */ int b;
    
    public dmb(final athj a, final int b, final byte[] array, final byte[] array2, final byte[] array3) {
        this.b = b;
        this.a = a;
    }
    
    public dmb(final ComponentTree a, final int b) {
        this.b = b;
        this.a = a;
    }
    
    public dmb(final deu a, final int b) {
        this.b = b;
        this.a = a;
    }
    
    public dmb(final dmd a, final int b, final byte[] array) {
        this.b = b;
        this.a = a;
    }
    
    public dmb(final dvt a, final int b) {
        this.b = b;
        this.a = a;
    }
    
    public dmb(final dyl a, final int b) {
        this.b = b;
        this.a = a;
    }
    
    public dmb(final dyn a, final int b) {
        this.b = b;
        this.a = a;
    }
    
    public dmb(final ebs a, final int b) {
        this.b = b;
        this.a = a;
    }
    
    public dmb(final eea a, final int b) {
        this.b = b;
        this.a = a;
    }
    
    public dmb(final elk a, final int b) {
        this.b = b;
        this.a = a;
    }
    
    public dmb(final emj a, final int b) {
        this.b = b;
        this.a = a;
    }
    
    public dmb(final emp a, final int b) {
        this.b = b;
        this.a = a;
    }
    
    public dmb(final ent a, final int b) {
        this.b = b;
        this.a = a;
    }
    
    public dmb(final gvr a, final int b, final byte[] array) {
        this.b = b;
        this.a = a;
    }
    
    public dmb(final List a, final int b) {
        this.b = b;
        this.a = a;
    }
    
    @Override
    public final void run() {
        // 
        // This method could not be decompiled.
        // 
        // Original Bytecode:
        // 
        //     1: getfield        dmb.b:I
        //     4: istore_1       
        //     5: iconst_0       
        //     6: istore_2       
        //     7: iload_1        
        //     8: tableswitch {
        //                0: 1687
        //                1: 1626
        //                2: 1615
        //                3: 1595
        //                4: 1575
        //                5: 1564
        //                6: 1556
        //                7: 1545
        //                8: 1518
        //                9: 1504
        //               10: 1328
        //               11: 1173
        //               12: 1140
        //               13: 763
        //               14: 647
        //               15: 565
        //               16: 492
        //               17: 478
        //               18: 467
        //               19: 253
        //          default: 104
        //        }
        //   104: aload_0        
        //   105: getfield        dmb.a:Ljava/lang/Object;
        //   108: astore_3       
        //   109: getstatic       aint.a:Laint;
        //   112: invokevirtual   agzi.createBuilder:()Lagza;
        //   115: astore          4
        //   117: aload           4
        //   119: invokevirtual   agza.copyOnWrite:()V
        //   122: aload           4
        //   124: getfield        agza.instance:Lagzi;
        //   127: checkcast       Laint;
        //   130: astore          5
        //   132: aload           5
        //   134: bipush          6
        //   136: putfield        aint.d:I
        //   139: aload           5
        //   141: aload           5
        //   143: getfield        aint.b:I
        //   146: iconst_2       
        //   147: ior            
        //   148: putfield        aint.b:I
        //   151: aload           4
        //   153: invokevirtual   agza.copyOnWrite:()V
        //   156: aload           4
        //   158: getfield        agza.instance:Lagzi;
        //   161: checkcast       Laint;
        //   164: astore          5
        //   166: aload           5
        //   168: iconst_1       
        //   169: putfield        aint.c:I
        //   172: aload           5
        //   174: iconst_1       
        //   175: aload           5
        //   177: getfield        aint.b:I
        //   180: ior            
        //   181: putfield        aint.b:I
        //   184: aload           4
        //   186: invokevirtual   agza.build:()Lagzi;
        //   189: checkcast       Laint;
        //   192: astore          4
        //   194: invokestatic    aklq.d:()Laklo;
        //   197: astore          5
        //   199: aload           5
        //   201: invokevirtual   agza.copyOnWrite:()V
        //   204: aload           5
        //   206: getfield        aklo.instance:Lagzi;
        //   209: checkcast       Laklq;
        //   212: aload           4
        //   214: invokestatic    aklq.au:(Laklq;Laint;)V
        //   217: aload           5
        //   219: invokevirtual   agza.build:()Lagzi;
        //   222: checkcast       Laklq;
        //   225: astore          4
        //   227: aload_3        
        //   228: checkcast       Landroid/content/Context;
        //   231: ldc             Lerr;.class
        //   233: invokestatic    ahbz.az:(Landroid/content/Context;Ljava/lang/Class;)Ljava/lang/Object;
        //   236: checkcast       Lerr;
        //   239: invokeinterface err.au:()Lwvu;
        //   244: aload           4
        //   246: invokeinterface wvu.d:(Laklq;)Z
        //   251: pop            
        //   252: return         
        //   253: aload_0        
        //   254: getfield        dmb.a:Ljava/lang/Object;
        //   257: astore_3       
        //   258: aload_3        
        //   259: checkcast       Lent;
        //   262: getfield        ent.a:Lemj;
        //   265: astore          4
        //   267: aload           4
        //   269: getfield        emj.c:Ldalvik/system/DexClassLoader;
        //   272: aload           4
        //   274: getfield        emj.d:[B
        //   277: aload_3        
        //   278: checkcast       Lent;
        //   281: getfield        ent.b:Ljava/lang/String;
        //   284: invokestatic    ent.a:([BLjava/lang/String;)Ljava/lang/String;
        //   287: invokevirtual   dalvik/system/DexClassLoader.loadClass:(Ljava/lang/String;)Ljava/lang/Class;
        //   290: astore          4
        //   292: aload           4
        //   294: ifnonnull       308
        //   297: aload_3        
        //   298: checkcast       Lent;
        //   301: getfield        ent.f:Ljava/util/concurrent/CountDownLatch;
        //   304: invokevirtual   java/util/concurrent/CountDownLatch.countDown:()V
        //   307: return         
        //   308: aload           4
        //   310: aload_3        
        //   311: checkcast       Lent;
        //   314: getfield        ent.a:Lemj;
        //   317: getfield        emj.d:[B
        //   320: aload_3        
        //   321: checkcast       Lent;
        //   324: getfield        ent.c:Ljava/lang/String;
        //   327: invokestatic    ent.a:([BLjava/lang/String;)Ljava/lang/String;
        //   330: aload_3        
        //   331: checkcast       Lent;
        //   334: getfield        ent.e:[Ljava/lang/Class;
        //   337: invokevirtual   java/lang/Class.getMethod:(Ljava/lang/String;[Ljava/lang/Class;)Ljava/lang/reflect/Method;
        //   340: astore          4
        //   342: aload_3        
        //   343: checkcast       Lent;
        //   346: aload           4
        //   348: putfield        ent.d:Ljava/lang/reflect/Method;
        //   351: aload_3        
        //   352: checkcast       Lent;
        //   355: getfield        ent.d:Ljava/lang/reflect/Method;
        //   358: astore          4
        //   360: aload           4
        //   362: ifnonnull       376
        //   365: aload_3        
        //   366: checkcast       Lent;
        //   369: getfield        ent.f:Ljava/util/concurrent/CountDownLatch;
        //   372: invokevirtual   java/util/concurrent/CountDownLatch.countDown:()V
        //   375: return         
        //   376: aload_3        
        //   377: checkcast       Lent;
        //   380: getfield        ent.f:Ljava/util/concurrent/CountDownLatch;
        //   383: invokevirtual   java/util/concurrent/CountDownLatch.countDown:()V
        //   386: return         
        //   387: astore          4
        //   389: aload_3        
        //   390: checkcast       Lent;
        //   393: getfield        ent.f:Ljava/util/concurrent/CountDownLatch;
        //   396: invokevirtual   java/util/concurrent/CountDownLatch.countDown:()V
        //   399: aload           4
        //   401: athrow         
        //   402: astore          4
        //   404: aload_3        
        //   405: checkcast       Lent;
        //   408: getfield        ent.f:Ljava/util/concurrent/CountDownLatch;
        //   411: invokevirtual   java/util/concurrent/CountDownLatch.countDown:()V
        //   414: return         
        //   415: astore          4
        //   417: aload_3        
        //   418: checkcast       Lent;
        //   421: getfield        ent.f:Ljava/util/concurrent/CountDownLatch;
        //   424: invokevirtual   java/util/concurrent/CountDownLatch.countDown:()V
        //   427: return         
        //   428: astore          4
        //   430: aload_3        
        //   431: checkcast       Lent;
        //   434: getfield        ent.f:Ljava/util/concurrent/CountDownLatch;
        //   437: invokevirtual   java/util/concurrent/CountDownLatch.countDown:()V
        //   440: return         
        //   441: astore          4
        //   443: aload_3        
        //   444: checkcast       Lent;
        //   447: getfield        ent.f:Ljava/util/concurrent/CountDownLatch;
        //   450: invokevirtual   java/util/concurrent/CountDownLatch.countDown:()V
        //   453: return         
        //   454: astore          4
        //   456: aload_3        
        //   457: checkcast       Lent;
        //   460: getfield        ent.f:Ljava/util/concurrent/CountDownLatch;
        //   463: invokevirtual   java/util/concurrent/CountDownLatch.countDown:()V
        //   466: return         
        //   467: aload_0        
        //   468: getfield        dmb.a:Ljava/lang/Object;
        //   471: checkcast       Lemp;
        //   474: invokevirtual   emp.c:()V
        //   477: return         
        //   478: aload_0        
        //   479: getfield        dmb.a:Ljava/lang/Object;
        //   482: checkcast       Lemj;
        //   485: getfield        emj.a:Landroid/content/Context;
        //   488: invokestatic    mcs.b:(Landroid/content/Context;)V
        //   491: return         
        //   492: aload_0        
        //   493: getfield        dmb.a:Ljava/lang/Object;
        //   496: astore_3       
        //   497: aload_3        
        //   498: checkcast       Lemj;
        //   501: getfield        emj.e:Lmah;
        //   504: ifnonnull       553
        //   507: aload_3        
        //   508: checkcast       Lemj;
        //   511: getfield        emj.h:Z
        //   514: ifeq            553
        //   517: new             Lmah;
        //   520: astore          4
        //   522: aload           4
        //   524: aload_3        
        //   525: checkcast       Lemj;
        //   528: getfield        emj.a:Landroid/content/Context;
        //   531: ldc2_w          30000
        //   534: iconst_0       
        //   535: invokespecial   mah.<init>:(Landroid/content/Context;JZ)V
        //   538: aload           4
        //   540: iconst_1       
        //   541: invokevirtual   mah.c:(Z)V
        //   544: aload_3        
        //   545: checkcast       Lemj;
        //   548: aload           4
        //   550: putfield        emj.e:Lmah;
        //   553: return         
        //   554: astore          4
        //   556: aload_3        
        //   557: checkcast       Lemj;
        //   560: aconst_null    
        //   561: putfield        emj.e:Lmah;
        //   564: return         
        //   565: aload_0        
        //   566: getfield        dmb.a:Ljava/lang/Object;
        //   569: astore          4
        //   571: invokestatic    java/lang/System.currentTimeMillis:()J
        //   574: lstore          6
        //   576: aload           4
        //   578: checkcast       Lelp;
        //   581: getfield        elp.d:Lehi;
        //   584: getfield        ehi.e:Ljava/lang/String;
        //   587: aload           4
        //   589: checkcast       Lelp;
        //   592: getfield        elp.b:Landroid/content/Context;
        //   595: invokestatic    elp.a:(Landroid/content/Context;)Landroid/content/Context;
        //   598: aload           4
        //   600: checkcast       Lelp;
        //   603: getfield        elp.d:Lehi;
        //   606: getfield        ehi.f:Z
        //   609: aload           4
        //   611: checkcast       Lelp;
        //   614: getfield        elp.e:Z
        //   617: invokestatic    elj.a:(Ljava/lang/String;Landroid/content/Context;ZZ)Lelj;
        //   620: invokevirtual   elj.l:()V
        //   623: return         
        //   624: astore_3       
        //   625: aload           4
        //   627: checkcast       Lelp;
        //   630: getfield        elp.c:Lmxe;
        //   633: sipush          2027
        //   636: invokestatic    java/lang/System.currentTimeMillis:()J
        //   639: lload           6
        //   641: lsub           
        //   642: aload_3        
        //   643: invokevirtual   mxe.c:(IJLjava/lang/Exception;)V
        //   646: return         
        //   647: aload_0        
        //   648: getfield        dmb.a:Ljava/lang/Object;
        //   651: checkcast       Lelk;
        //   654: getfield        elk.d:Ljava/lang/Boolean;
        //   657: ifnull          661
        //   660: return         
        //   661: getstatic       elk.a:Landroid/os/ConditionVariable;
        //   664: astore_3       
        //   665: aload_3        
        //   666: monitorenter   
        //   667: aload_0        
        //   668: getfield        dmb.a:Ljava/lang/Object;
        //   671: checkcast       Lelk;
        //   674: getfield        elk.d:Ljava/lang/Boolean;
        //   677: ifnull          683
        //   680: aload_3        
        //   681: monitorexit    
        //   682: return         
        //   683: getstatic       mcs.J:Ltrg;
        //   686: invokevirtual   trg.l:()Ljava/lang/Object;
        //   689: checkcast       Ljava/lang/Boolean;
        //   692: invokevirtual   java/lang/Boolean.booleanValue:()Z
        //   695: istore          8
        //   697: goto            705
        //   700: astore          4
        //   702: iconst_0       
        //   703: istore          8
        //   705: iload           8
        //   707: ifeq            732
        //   710: aload_0        
        //   711: getfield        dmb.a:Ljava/lang/Object;
        //   714: checkcast       Lelk;
        //   717: getfield        elk.c:Lemj;
        //   720: getfield        emj.a:Landroid/content/Context;
        //   723: ldc_w           "ADSHIELD"
        //   726: invokestatic    ggc.i:(Landroid/content/Context;Ljava/lang/String;)Lggc;
        //   729: putstatic       elk.e:Lggc;
        //   732: aload_0        
        //   733: getfield        dmb.a:Ljava/lang/Object;
        //   736: checkcast       Lelk;
        //   739: iload           8
        //   741: invokestatic    java/lang/Boolean.valueOf:(Z)Ljava/lang/Boolean;
        //   744: putfield        elk.d:Ljava/lang/Boolean;
        //   747: getstatic       elk.a:Landroid/os/ConditionVariable;
        //   750: invokevirtual   android/os/ConditionVariable.open:()V
        //   753: aload_3        
        //   754: monitorexit    
        //   755: return         
        //   756: astore          4
        //   758: aload_3        
        //   759: monitorexit    
        //   760: aload           4
        //   762: athrow         
        //   763: aload_0        
        //   764: getfield        dmb.a:Ljava/lang/Object;
        //   767: checkcast       Lgvr;
        //   770: getfield        gvr.d:Ljava/lang/Object;
        //   773: astore          9
        //   775: aload           9
        //   777: monitorenter   
        //   778: aload_0        
        //   779: getfield        dmb.a:Ljava/lang/Object;
        //   782: astore_3       
        //   783: aload_3        
        //   784: checkcast       Lgvr;
        //   787: getfield        gvr.a:Z
        //   790: ifeq            1130
        //   793: aload_3        
        //   794: checkcast       Lgvr;
        //   797: getfield        gvr.f:Ljava/lang/Object;
        //   800: checkcast       Landroid/content/Context;
        //   803: invokestatic    eii.h:(Landroid/content/Context;)Z
        //   806: ifeq            1130
        //   809: aload_0        
        //   810: getfield        dmb.a:Ljava/lang/Object;
        //   813: astore_3       
        //   814: aload_3        
        //   815: checkcast       Lgvr;
        //   818: getfield        gvr.b:Z
        //   821: ifeq            827
        //   824: goto            1130
        //   827: aload_3        
        //   828: checkcast       Lgvr;
        //   831: getfield        gvr.c:Ljava/lang/Object;
        //   834: astore          5
        //   836: aload_3        
        //   837: checkcast       Lgvr;
        //   840: getfield        gvr.e:Ljava/lang/Object;
        //   843: astore_3       
        //   844: aload_3        
        //   845: checkcast       Leig;
        //   848: getfield        eig.b:Ljava/lang/Object;
        //   851: astore          10
        //   853: aload           10
        //   855: monitorenter   
        //   856: new             Ljava/util/LinkedList;
        //   859: astore          11
        //   861: aload           11
        //   863: invokespecial   java/util/LinkedList.<init>:()V
        //   866: aload_3        
        //   867: checkcast       Leig;
        //   870: invokevirtual   eig.a:()Landroid/database/sqlite/SQLiteDatabase;
        //   873: astore_3       
        //   874: aload_3        
        //   875: ifnonnull       884
        //   878: aload           10
        //   880: monitorexit    
        //   881: goto            1049
        //   884: aload_3        
        //   885: ldc_w           "conversiontracking"
        //   888: aconst_null    
        //   889: aconst_null    
        //   890: aconst_null    
        //   891: aconst_null    
        //   892: aconst_null    
        //   893: ldc_w           "last_retry_time ASC"
        //   896: ldc_w           "100"
        //   899: invokevirtual   android/database/sqlite/SQLiteDatabase.query:(Ljava/lang/String;[Ljava/lang/String;Ljava/lang/String;[Ljava/lang/String;Ljava/lang/String;Ljava/lang/String;Ljava/lang/String;Ljava/lang/String;)Landroid/database/Cursor;
        //   902: astore_3       
        //   903: aload_3        
        //   904: invokeinterface android/database/Cursor.moveToFirst:()Z
        //   909: ifeq            937
        //   912: aload           11
        //   914: aload_3        
        //   915: invokestatic    eig.e:(Landroid/database/Cursor;)Leid;
        //   918: invokeinterface java/util/List.add:(Ljava/lang/Object;)Z
        //   923: pop            
        //   924: aload_3        
        //   925: invokeinterface android/database/Cursor.moveToNext:()Z
        //   930: istore          8
        //   932: iload           8
        //   934: ifne            912
        //   937: aload_3        
        //   938: ifnull          1046
        //   941: aload_3        
        //   942: invokeinterface android/database/Cursor.close:()V
        //   947: goto            1046
        //   950: astore          4
        //   952: aload_3        
        //   953: astore          5
        //   955: aload           4
        //   957: astore_3       
        //   958: aload           5
        //   960: astore          4
        //   962: goto            1110
        //   965: astore          4
        //   967: goto            984
        //   970: astore          4
        //   972: goto            982
        //   975: astore_3       
        //   976: aconst_null    
        //   977: astore          4
        //   979: goto            1110
        //   982: aconst_null    
        //   983: astore_3       
        //   984: aload           4
        //   986: invokevirtual   android/database/sqlite/SQLiteException.getMessage:()Ljava/lang/String;
        //   989: invokestatic    java/lang/String.valueOf:(Ljava/lang/Object;)Ljava/lang/String;
        //   992: astore          4
        //   994: aload           4
        //   996: invokevirtual   java/lang/String.length:()I
        //   999: ifeq            1015
        //  1002: ldc_w           "Error extracing ping Info: "
        //  1005: aload           4
        //  1007: invokevirtual   java/lang/String.concat:(Ljava/lang/String;)Ljava/lang/String;
        //  1010: astore          4
        //  1012: goto            1027
        //  1015: new             Ljava/lang/String;
        //  1018: dup            
        //  1019: ldc_w           "Error extracing ping Info: "
        //  1022: invokespecial   java/lang/String.<init>:(Ljava/lang/String;)V
        //  1025: astore          4
        //  1027: ldc_w           "GoogleConversionReporter"
        //  1030: aload           4
        //  1032: invokestatic    android/util/Log.w:(Ljava/lang/String;Ljava/lang/String;)I
        //  1035: pop            
        //  1036: aload_3        
        //  1037: ifnull          1046
        //  1040: aload_3        
        //  1041: invokeinterface android/database/Cursor.close:()V
        //  1046: aload           10
        //  1048: monitorexit    
        //  1049: aload           5
        //  1051: aload           11
        //  1053: invokeinterface java/util/List.addAll:(Ljava/util/Collection;)Z
        //  1058: pop            
        //  1059: aload_0        
        //  1060: getfield        dmb.a:Ljava/lang/Object;
        //  1063: checkcast       Lgvr;
        //  1066: getfield        gvr.f:Ljava/lang/Object;
        //  1069: checkcast       Landroid/content/Context;
        //  1072: invokestatic    eii.f:(Landroid/content/Context;)V
        //  1075: aload_0        
        //  1076: getfield        dmb.a:Ljava/lang/Object;
        //  1079: astore_3       
        //  1080: aload_3        
        //  1081: checkcast       Lgvr;
        //  1084: iconst_1       
        //  1085: putfield        gvr.b:Z
        //  1088: aload_3        
        //  1089: checkcast       Lgvr;
        //  1092: getfield        gvr.d:Ljava/lang/Object;
        //  1095: invokevirtual   java/lang/Object.notify:()V
        //  1098: aload           9
        //  1100: monitorexit    
        //  1101: return         
        //  1102: astore          5
        //  1104: aload_3        
        //  1105: astore          4
        //  1107: aload           5
        //  1109: astore_3       
        //  1110: aload           4
        //  1112: ifnull          1122
        //  1115: aload           4
        //  1117: invokeinterface android/database/Cursor.close:()V
        //  1122: aload_3        
        //  1123: athrow         
        //  1124: astore_3       
        //  1125: aload           10
        //  1127: monitorexit    
        //  1128: aload_3        
        //  1129: athrow         
        //  1130: aload           9
        //  1132: monitorexit    
        //  1133: return         
        //  1134: astore_3       
        //  1135: aload           9
        //  1137: monitorexit    
        //  1138: aload_3        
        //  1139: athrow         
        //  1140: aload_0        
        //  1141: getfield        dmb.a:Ljava/lang/Object;
        //  1144: checkcast       Lathj;
        //  1147: getfield        athj.c:Ljava/lang/Object;
        //  1150: astore_3       
        //  1151: aload_3        
        //  1152: ifnull          1172
        //  1155: aload_3        
        //  1156: checkcast       Landroidx/swiperefreshlayout/widget/SwipeRefreshLayout;
        //  1159: astore_3       
        //  1160: aload_3        
        //  1161: getfield        androidx/swiperefreshlayout/widget/SwipeRefreshLayout.b:Z
        //  1164: ifeq            1172
        //  1167: aload_3        
        //  1168: iconst_0       
        //  1169: invokevirtual   androidx/swiperefreshlayout/widget/SwipeRefreshLayout.k:(Z)V
        //  1172: return         
        //  1173: aload_0        
        //  1174: getfield        dmb.a:Ljava/lang/Object;
        //  1177: astore_3       
        //  1178: aload_3        
        //  1179: checkcast       Ldvt;
        //  1182: getfield        dvt.j:Lcom/facebook/litho/ComponentTree;
        //  1185: astore          4
        //  1187: aload           4
        //  1189: ifnonnull       1195
        //  1192: goto            1327
        //  1195: aload           4
        //  1197: getfield        com/facebook/litho/ComponentTree.t:Ldve;
        //  1200: astore          4
        //  1202: aload           4
        //  1204: ifnull          1327
        //  1207: aload           4
        //  1209: getfield        dve.h:Ljava/util/List;
        //  1212: invokeinterface java/util/List.size:()I
        //  1217: istore          12
        //  1219: iconst_0       
        //  1220: istore_1       
        //  1221: iload_1        
        //  1222: iload           12
        //  1224: if_icmpge       1327
        //  1227: aload           4
        //  1229: getfield        dve.h:Ljava/util/List;
        //  1232: iload_1        
        //  1233: invokeinterface java/util/List.get:(I)Ljava/lang/Object;
        //  1238: checkcast       Legs;
        //  1241: getfield        egs.i:Ldum;
        //  1244: astore          9
        //  1246: aload           9
        //  1248: ifnonnull       1254
        //  1251: goto            1321
        //  1254: getstatic       epc.f:Ldvh;
        //  1257: ifnonnull       1270
        //  1260: new             Ldvh;
        //  1263: dup            
        //  1264: invokespecial   dvh.<init>:()V
        //  1267: putstatic       epc.f:Ldvh;
        //  1270: getstatic       epc.f:Ldvh;
        //  1273: astore          5
        //  1275: aload           5
        //  1277: aload_3        
        //  1278: checkcast       Landroid/view/View;
        //  1281: putfield        dvh.a:Landroid/view/View;
        //  1284: aload           5
        //  1286: aconst_null    
        //  1287: putfield        dvh.b:Landroid/view/View;
        //  1290: aload           9
        //  1292: iconst_1       
        //  1293: anewarray       Ljava/lang/Object;
        //  1296: dup            
        //  1297: iconst_0       
        //  1298: aload           5
        //  1300: aastore        
        //  1301: invokevirtual   dum.d:([Ljava/lang/Object;)V
        //  1304: getstatic       epc.f:Ldvh;
        //  1307: astore          5
        //  1309: aload           5
        //  1311: aconst_null    
        //  1312: putfield        dvh.a:Landroid/view/View;
        //  1315: aload           5
        //  1317: aconst_null    
        //  1318: putfield        dvh.b:Landroid/view/View;
        //  1321: iinc            1, 1
        //  1324: goto            1221
        //  1327: return         
        //  1328: aload_0        
        //  1329: getfield        dmb.a:Ljava/lang/Object;
        //  1332: checkcast       Leea;
        //  1335: getfield        eea.v:Landroid/support/v7/widget/RecyclerView;
        //  1338: astore_3       
        //  1339: aload_3        
        //  1340: ifnull          1462
        //  1343: aload_3        
        //  1344: invokevirtual   android/support/v7/widget/RecyclerView.ar:()Z
        //  1347: ifne            1353
        //  1350: goto            1462
        //  1353: aload_0        
        //  1354: getfield        dmb.a:Ljava/lang/Object;
        //  1357: checkcast       Leea;
        //  1360: getfield        eea.v:Landroid/support/v7/widget/RecyclerView;
        //  1363: astore_3       
        //  1364: aload_3        
        //  1365: getfield        android/support/v7/widget/RecyclerView.r:Z
        //  1368: ifeq            1450
        //  1371: aload_3        
        //  1372: invokevirtual   android/support/v7/widget/RecyclerView.getVisibility:()I
        //  1375: bipush          8
        //  1377: if_icmpne       1383
        //  1380: goto            1450
        //  1383: aload_0        
        //  1384: getfield        dmb.a:Ljava/lang/Object;
        //  1387: checkcast       Leea;
        //  1390: astore_3       
        //  1391: aload_3        
        //  1392: getfield        eea.G:I
        //  1395: istore_1       
        //  1396: iload_1        
        //  1397: iconst_3       
        //  1398: if_icmplt       1431
        //  1401: aload_3        
        //  1402: iconst_0       
        //  1403: putfield        eea.G:I
        //  1406: aload_3        
        //  1407: getfield        eea.F:Lefr;
        //  1410: invokevirtual   efr.d:()Z
        //  1413: ifeq            1430
        //  1416: aload_0        
        //  1417: getfield        dmb.a:Ljava/lang/Object;
        //  1420: checkcast       Leea;
        //  1423: getfield        eea.F:Lefr;
        //  1426: iconst_1       
        //  1427: invokevirtual   efr.b:(I)V
        //  1430: return         
        //  1431: aload_3        
        //  1432: iload_1        
        //  1433: iconst_1       
        //  1434: iadd           
        //  1435: putfield        eea.G:I
        //  1438: aload_3        
        //  1439: getfield        eea.v:Landroid/support/v7/widget/RecyclerView;
        //  1442: aload_3        
        //  1443: getfield        eea.I:Ljava/lang/Runnable;
        //  1446: invokestatic    ana.I:(Landroid/view/View;Ljava/lang/Runnable;)V
        //  1449: return         
        //  1450: aload_0        
        //  1451: getfield        dmb.a:Ljava/lang/Object;
        //  1454: checkcast       Leea;
        //  1457: iconst_0       
        //  1458: putfield        eea.G:I
        //  1461: return         
        //  1462: aload_0        
        //  1463: getfield        dmb.a:Ljava/lang/Object;
        //  1466: checkcast       Leea;
        //  1469: getfield        eea.F:Lefr;
        //  1472: invokevirtual   efr.d:()Z
        //  1475: ifeq            1492
        //  1478: aload_0        
        //  1479: getfield        dmb.a:Ljava/lang/Object;
        //  1482: checkcast       Leea;
        //  1485: getfield        eea.F:Lefr;
        //  1488: iconst_1       
        //  1489: invokevirtual   efr.b:(I)V
        //  1492: aload_0        
        //  1493: getfield        dmb.a:Ljava/lang/Object;
        //  1496: checkcast       Leea;
        //  1499: iconst_0       
        //  1500: putfield        eea.G:I
        //  1503: return         
        //  1504: aload_0        
        //  1505: getfield        dmb.a:Ljava/lang/Object;
        //  1508: checkcast       Leea;
        //  1511: getfield        eea.f:Lnq;
        //  1514: invokevirtual   nq.rT:()V
        //  1517: return         
        //  1518: aload_0        
        //  1519: getfield        dmb.a:Ljava/lang/Object;
        //  1522: checkcast       Leea;
        //  1525: getfield        eea.A:Ldum;
        //  1528: astore_3       
        //  1529: aload_3        
        //  1530: ifnull          1544
        //  1533: aload_3        
        //  1534: new             Ledb;
        //  1537: dup            
        //  1538: invokespecial   edb.<init>:()V
        //  1541: invokevirtual   dum.ls:(Ljava/lang/Object;)V
        //  1544: return         
        //  1545: aload_0        
        //  1546: getfield        dmb.a:Ljava/lang/Object;
        //  1549: checkcast       Lebs;
        //  1552: invokevirtual   ebs.k:()V
        //  1555: return         
        //  1556: aload_0        
        //  1557: getfield        dmb.a:Ljava/lang/Object;
        //  1560: invokestatic    eea.J:(Ljava/util/List;)V
        //  1563: return         
        //  1564: aload_0        
        //  1565: getfield        dmb.a:Ljava/lang/Object;
        //  1568: checkcast       Landroid/animation/Animator;
        //  1571: invokevirtual   android/animation/Animator.resume:()V
        //  1574: return         
        //  1575: aload_0        
        //  1576: getfield        dmb.a:Ljava/lang/Object;
        //  1579: astore          4
        //  1581: invokestatic    android/view/Choreographer.getInstance:()Landroid/view/Choreographer;
        //  1584: astore_3       
        //  1585: aload           4
        //  1587: checkcast       Ldyn;
        //  1590: aload_3        
        //  1591: putfield        dyn.b:Landroid/view/Choreographer;
        //  1594: return         
        //  1595: aload_0        
        //  1596: getfield        dmb.a:Ljava/lang/Object;
        //  1599: astore_3       
        //  1600: invokestatic    java/lang/System.nanoTime:()J
        //  1603: lstore          6
        //  1605: aload_3        
        //  1606: checkcast       Ldyl;
        //  1609: lload           6
        //  1611: invokevirtual   dyl.d:(J)V
        //  1614: return         
        //  1615: aload_0        
        //  1616: getfield        dmb.a:Ljava/lang/Object;
        //  1619: checkcast       Lcom/facebook/litho/ComponentTree;
        //  1622: invokevirtual   com/facebook/litho/ComponentTree.i:()V
        //  1625: return         
        //  1626: aload_0        
        //  1627: getfield        dmb.a:Ljava/lang/Object;
        //  1630: astore_3       
        //  1631: aload_3        
        //  1632: checkcast       Ldeu;
        //  1635: getfield        deu.c:Z
        //  1638: istore          8
        //  1640: aload_3        
        //  1641: checkcast       Ldeu;
        //  1644: getfield        deu.b:Ljava/lang/ref/ReferenceQueue;
        //  1647: invokevirtual   java/lang/ref/ReferenceQueue.remove:()Ljava/lang/ref/Reference;
        //  1650: checkcast       Ldet;
        //  1653: astore          4
        //  1655: aload_3        
        //  1656: checkcast       Ldeu;
        //  1659: aload           4
        //  1661: invokevirtual   deu.c:(Ldet;)V
        //  1664: aload_3        
        //  1665: checkcast       Ldeu;
        //  1668: getfield        deu.d:Ldes;
        //  1671: astore          4
        //  1673: goto            1631
        //  1676: astore          4
        //  1678: invokestatic    java/lang/Thread.currentThread:()Ljava/lang/Thread;
        //  1681: invokevirtual   java/lang/Thread.interrupt:()V
        //  1684: goto            1631
        //  1687: aload_0        
        //  1688: getfield        dmb.a:Ljava/lang/Object;
        //  1691: checkcast       Ldmd;
        //  1694: astore_3       
        //  1695: aload_3        
        //  1696: getfield        dmd.b:Ljava/lang/Object;
        //  1699: checkcast       Ldmc;
        //  1702: getfield        dmc.a:Z
        //  1705: ifeq            1718
        //  1708: aload_3        
        //  1709: getfield        dmd.a:Ljava/lang/Object;
        //  1712: checkcast       Ldkg;
        //  1715: invokevirtual   dkg.b:()V
        //  1718: return         
        //  1719: astore          4
        //  1721: iload_2        
        //  1722: istore          8
        //  1724: goto            732
        //    Exceptions:
        //  Try           Handler
        //  Start  End    Start  End    Type                                     
        //  -----  -----  -----  -----  -----------------------------------------
        //  258    292    454    467    Lelx;
        //  258    292    441    454    Ljava/io/UnsupportedEncodingException;
        //  258    292    428    441    Ljava/lang/ClassNotFoundException;
        //  258    292    415    428    Ljava/lang/NoSuchMethodException;
        //  258    292    402    415    Ljava/lang/NullPointerException;
        //  258    292    387    402    Any
        //  308    360    454    467    Lelx;
        //  308    360    441    454    Ljava/io/UnsupportedEncodingException;
        //  308    360    428    441    Ljava/lang/ClassNotFoundException;
        //  308    360    415    428    Ljava/lang/NoSuchMethodException;
        //  308    360    402    415    Ljava/lang/NullPointerException;
        //  308    360    387    402    Any
        //  497    553    554    565    Lmpb;
        //  497    553    554    565    Ljava/io/IOException;
        //  497    553    554    565    Lmpc;
        //  576    623    624    647    Ljava/lang/NullPointerException;
        //  667    682    756    763    Any
        //  683    697    700    705    Ljava/lang/IllegalStateException;
        //  683    697    756    763    Any
        //  710    732    1719   1727   Any
        //  732    755    756    763    Any
        //  758    760    756    763    Any
        //  778    824    1134   1140   Any
        //  827    856    1134   1140   Any
        //  856    874    1124   1130   Any
        //  878    881    1124   1130   Any
        //  884    903    970    975    Landroid/database/sqlite/SQLiteException;
        //  884    903    975    982    Any
        //  903    912    965    970    Landroid/database/sqlite/SQLiteException;
        //  903    912    950    965    Any
        //  912    932    965    970    Landroid/database/sqlite/SQLiteException;
        //  912    932    950    965    Any
        //  941    947    1124   1130   Any
        //  984    1012   1102   1110   Any
        //  1015   1027   1102   1110   Any
        //  1027   1036   1102   1110   Any
        //  1040   1046   1124   1130   Any
        //  1046   1049   1124   1130   Any
        //  1049   1101   1134   1140   Any
        //  1115   1122   1124   1130   Any
        //  1122   1124   1124   1130   Any
        //  1125   1128   1124   1130   Any
        //  1128   1130   1134   1140   Any
        //  1130   1133   1134   1140   Any
        //  1135   1138   1134   1140   Any
        //  1640   1673   1676   1687   Ljava/lang/InterruptedException;
        // 
        // The error that occurred was:
        // 
        // java.lang.IllegalStateException: Expression is linked from several locations: Label_0732:
        //     at com.strobel.decompiler.ast.Error.expressionLinkedFromMultipleLocations(Error.java:27)
        //     at com.strobel.decompiler.ast.AstOptimizer.mergeDisparateObjectInitializations(AstOptimizer.java:2604)
        //     at com.strobel.decompiler.ast.AstOptimizer.optimize(AstOptimizer.java:235)
        //     at com.strobel.decompiler.ast.AstOptimizer.optimize(AstOptimizer.java:42)
        //     at com.strobel.decompiler.languages.java.ast.AstMethodBodyBuilder.createMethodBody(AstMethodBodyBuilder.java:206)
        //     at com.strobel.decompiler.languages.java.ast.AstMethodBodyBuilder.createMethodBody(AstMethodBodyBuilder.java:93)
        //     at com.strobel.decompiler.languages.java.ast.AstBuilder.createMethodBody(AstBuilder.java:868)
        //     at com.strobel.decompiler.languages.java.ast.AstBuilder.createMethod(AstBuilder.java:761)
        //     at com.strobel.decompiler.languages.java.ast.AstBuilder.addTypeMembers(AstBuilder.java:638)
        //     at com.strobel.decompiler.languages.java.ast.AstBuilder.createTypeCore(AstBuilder.java:605)
        //     at com.strobel.decompiler.languages.java.ast.AstBuilder.createTypeNoCache(AstBuilder.java:195)
        //     at com.strobel.decompiler.languages.java.ast.AstBuilder.createType(AstBuilder.java:162)
        //     at com.strobel.decompiler.languages.java.ast.AstBuilder.addType(AstBuilder.java:137)
        //     at com.strobel.decompiler.languages.java.JavaLanguage.buildAst(JavaLanguage.java:71)
        //     at com.strobel.decompiler.languages.java.JavaLanguage.decompileType(JavaLanguage.java:59)
        //     at com.strobel.decompiler.DecompilerDriver.decompileType(DecompilerDriver.java:333)
        //     at com.strobel.decompiler.DecompilerDriver.decompileJar(DecompilerDriver.java:254)
        //     at com.strobel.decompiler.DecompilerDriver.main(DecompilerDriver.java:129)
        // 
        throw new IllegalStateException("An error occurred while decompiling this method.");
    }
}
