import android.net.Uri;
import java.util.Iterator;
import com.google.protobuf.MessageLite;
import java.util.List;
import java.util.Arrays;
import com.google.android.libraries.youtube.offline.transfer.service.OfflineTransferService;
import com.google.common.util.concurrent.ListenableFuture;
import com.google.android.libraries.youtube.mdx.smartremote.MdxSmartRemoteDialListener;
import android.content.res.Resources;
import java.util.Map;
import java.security.SecureRandom;
import android.os.Handler;
import com.google.android.apps.youtube.embeddedplayer.service.permissions.b;
import java.util.Random;
import java.util.concurrent.locks.Lock;
import youtube.media.engine.api.MediaEngineAudioContainerRegistrar;
import java.util.Set;
import j$.util.Optional;
import java.io.File;
import com.google.android.apps.youtube.app.extensions.appindexing.WatchVideoIndexer;
import java.util.concurrent.Executor;
import java.util.concurrent.ExecutorService;
import java.util.concurrent.ScheduledExecutorService;
import android.content.Context;
import android.content.SharedPreferences;

// 
// Decompiled by Procyon v0.6.0
// 

final class eqw implements atjj
{
    private final eqv a;
    private final int b;
    
    public eqw(final eqv a, final int b) {
        this.a = a;
        this.b = b;
    }
    
    private final Object b() {
        final int b = this.b;
        switch (b) {
            default: {
                throw new AssertionError(b);
            }
            case 99: {
                final arud arud = (arud)eqv.qo(this.a).a();
                final uyf uyf = (uyf)eqv.po(this.a).a();
                return ewp.s(arud, (SharedPreferences)eqv.sr(this.a).a(), (acws)eqx.ed(eqv.q(this.a)).a(), (Context)eqv.pt(this.a).a(), (zki)eqv.pL(this.a).a(), (rfv)eqv.oF(this.a).a(), (ScheduledExecutorService)eqv.oO(this.a).a(), (oas)eqv.gK(this.a).a(), (jkp)eqx.al(eqv.q(this.a)).a(), (acwg)eqv.om(this.a).a(), (acwj)eqv.tM(this.a).a(), (aeim)eqx.bC(eqv.q(this.a)).a(), eqx.B(eqv.q(this.a)), (auip)eqx.dS(eqv.q(this.a)).a(), (jkq)eqx.am(eqv.q(this.a)).a(), acve.o(), (uyi)eqx.fe(eqv.q(this.a)).a());
            }
            case 98: {
                final eqv a = this.a;
                return new blt(eqx.dR(eqv.q(a)), eqx.dT(eqv.q(a)), eqx.dU(eqv.q(a)), (zki)eqv.pL(a).a(), (uyi)eqx.eM(eqv.q(this.a)).a());
            }
            case 97: {
                return acey.b((Context)eqv.pt(this.a).a());
            }
            case 96: {
                final tgy tgy = (tgy)eqv.qr(this.a).a();
                final daw daw = (daw)eqx.dp(eqv.q(this.a)).a();
                final tgl b2 = thk.b();
                final ExecutorService executorService = (ExecutorService)eqv.oO(this.a).a();
                final ExecutorService executorService2 = (ExecutorService)eqv.pA(this.a).a();
                final ExecutorService executorService3 = (ExecutorService)eqv.lg(this.a).a();
                final eqv a2 = this.a;
                return acey.d(tgy, daw, b2, executorService, executorService2, executorService3, eqv.oK(a2), eqv.pJ(a2), (tlq)eqv.fL(a2).a());
            }
            case 95: {
                final eqv a3 = this.a;
                return acey.e(eqv.qs(a3), aexq.k(eqv.rw(a3)), aexq.i(), eqx.dq(eqv.q(this.a)));
            }
            case 94: {
                return new aant((Context)eqv.pt(this.a).a());
            }
            case 93: {
                final Context context = (Context)eqv.pt(this.a).a();
                final tdz tdz = (tdz)eqv.jp(this.a).a();
                final abhq abhq = (abhq)eqv.kg(this.a).a();
                final yyf yyf = (yyf)eqv.jW(this.a).a();
                final yyf yyf2 = (yyf)eqv.vT(this.a).a();
                final eqv a4 = this.a;
                return new aapf(context, tdz, abhq, yyf, yyf2, eqx.ax(eqv.q(a4)), (aeby)eqv.su(a4).a(), (abpj)eqv.jv(this.a).a(), (byte[])null, (byte[])null, (byte[])null);
            }
            case 92: {
                return wvp.M(eqx.hh(eqv.q(this.a)), (zba)eqv.mt(this.a).a());
            }
            case 91: {
                return lme.m((Context)eqv.pt(this.a).a());
            }
            case 90: {
                return lme.l((Context)eqv.pt(this.a).a());
            }
            case 89: {
                return lme.o((lzh)eqx.es(eqv.q(this.a)).a(), (lzh)eqx.et(eqv.q(this.a)).a(), eqx.gF(eqv.q(this.a)));
            }
            case 88: {
                return adfv.l(eqv.uZ(this.a));
            }
            case 87: {
                return new oqq(eqv.pH(this.a));
            }
            case 86: {
                return ops.m(aexq.i(), aexq.k(eqv.pI(this.a).a()), arjc.b(eqx.aM(eqv.q(this.a))));
            }
            case 85: {
                final eqv a5 = this.a;
                return okq.m(eqv.zf(a5), (otd)eqx.dk(eqv.q(a5)).a(), aexq.k(eqx.gf(eqv.q(this.a))), (Context)eqv.pt(this.a).a());
            }
            case 84: {
                return suh.t((lzi)eqv.et(this.a).a(), (arud)eqv.qo(this.a).a(), (Context)eqv.pt(this.a).a(), (zki)eqv.pL(this.a).a(), (vvt)eqv.on(this.a).a(), (thh)eqv.id(this.a).a());
            }
            case 83: {
                final vbq vbq = (vbq)eqv.kF(this.a).a();
                final zki zki = (zki)eqv.pL(this.a).a();
                final arhr b3 = arjc.b(eqv.ks(this.a));
                final Executor executor = (Executor)eqv.oO(this.a).a();
                final eqv a6 = this.a;
                return gtq.j(vbq, zki, b3, executor, eqv.jp(a6), eqv.po(a6));
            }
            case 82: {
                return gtq.p((vbq)eqv.kF(this.a).a(), (vcf)eqv.nK(this.a).a(), (Executor)eqv.oO(this.a).a());
            }
            case 81: {
                final Context context2 = (Context)eqv.pt(this.a).a();
                final eqv a7 = this.a;
                final atjj vb = eqv.vb(a7);
                final oas oas = (oas)eqv.gK(a7).a();
                final tdz tdz2 = (tdz)eqv.jp(this.a).a();
                final eqv a8 = this.a;
                return addl.d(context2, vb, oas, tdz2, eqv.id(a8), eqv.fG(a8), eqv.iu(a8));
            }
            case 80: {
                return new WatchVideoIndexer(eqx.gX(eqv.q(this.a)), (adcr)eqv.jP(this.a).a(), (Context)eqv.pt(this.a).a(), (abns)eqv.kh(this.a).a(), null, null, null, null, null);
            }
            case 79: {
                return ewp.o((File)eqv.pa(this.a).a(), acve.o());
            }
            case 78: {
                return acve.h((File)eqv.pa(this.a).a(), (Executor)eqv.oO(this.a).a());
            }
            case 77: {
                return ewq.b((vjl)eqv.kM(this.a).a(), (adcg)eqx.dJ(eqv.q(this.a)).a());
            }
            case 76: {
                return ewq.r((File)eqv.pa(this.a).a(), acve.o());
            }
            case 75: {
                return new wvo((Context)eqv.pt(this.a).a(), (oas)eqv.gK(this.a).a(), eqv.gY(this.a));
            }
            case 74: {
                return flp.g((asho)eqv.fN(this.a).a(), (ExecutorService)eqv.oO(this.a).a(), (tdz)eqv.jp(this.a).a(), (vbq)eqv.kF(this.a).a(), (vcf)eqv.nK(this.a).a(), (fml)eqv.lE(this.a).a(), (zki)eqv.pL(this.a).a(), (uyi)eqv.lz(this.a).a());
            }
            case 73: {
                final wvu wvu = (wvu)eqv.th(this.a).a();
                final arud arud2 = (arud)eqv.qo(this.a).a();
                final uyf uyf2 = (uyf)eqv.po(this.a).a();
                final eqv a9 = this.a;
                return jko.m(wvu, arud2, uyf2, eqv.fH(a9), eqv.pS(a9), eqv.nq(a9), (zki)eqv.pL(a9).a(), (Executor)eqv.fX(this.a).a(), (Executor)eqv.oO(this.a).a(), (tdz)eqv.jp(this.a).a(), eqv.xJ(this.a), (uyi)eqv.lh(this.a).a());
            }
            case 72: {
                return frh.n((Context)eqv.pt(this.a).a(), eqv.yv(), (aftr)eqv.oO(this.a).a(), (qbo)eqv.to(this.a).a());
            }
            case 71: {
                final eqv a10 = this.a;
                return frh.m(eqx.dQ(eqv.q(a10)), (oas)eqv.gK(a10).a());
            }
            case 70: {
                return ewp.j((tlq)eqv.fL(this.a).a(), eqx.eL(eqv.q(this.a)));
            }
            case 69: {
                return new fvt((tlq)eqv.fL(this.a).a(), (fvp)eqx.dP(eqv.q(this.a)).a(), eqv.fX(this.a));
            }
            case 68: {
                final eqv a11 = this.a;
                return idf.v(eqv.jp(a11), (vup)eqv.jl(a11).a(), (vbq)eqv.kF(this.a).a(), (vcf)eqv.nK(this.a).a(), (zki)eqv.pL(this.a).a(), (ExecutorService)eqv.oO(this.a).a());
            }
            case 67: {
                return iep.c((Executor)eqv.oO(this.a).a());
            }
            case 66: {
                return idf.p();
            }
            case 65: {
                return idf.f((Executor)eqv.oO(this.a).a());
            }
            case 64: {
                return idf.e((Executor)eqv.oO(this.a).a());
            }
            case 63: {
                final icx icx = (icx)eqx.ca(eqv.q(this.a)).a();
                final idi e = eqx.e(eqv.q(this.a));
                final icx icx2 = (icx)eqx.cb(eqv.q(this.a)).a();
                final icx icx3 = (icx)eqx.fV(eqv.q(this.a)).a();
                final ieh r = idf.r();
                final eqv a12 = this.a;
                return afdu.x((Object)icx, (Object)e, (Object)icx2, (Object)icx3, (Object)r, (Object)eqx.f(eqv.q(a12)), (Object[])new icx[] { (icx)eqx.ga(eqv.q(a12)).a() });
            }
            case 62: {
                return idf.q();
            }
            case 61: {
                return idf.o();
            }
            case 60: {
                final eqv a13 = this.a;
                final atjj ii = eqv.ii(a13);
                final Executor executor2 = (Executor)eqv.oO(a13).a();
                final eqv a14 = this.a;
                return zrt.p(ii, executor2, eqv.nK(a14), (aaha)eqv.jw(a14).a());
            }
            case 59: {
                final eqv a15 = this.a;
                return idf.n(eqv.ii(a15), (zvp)eqx.fm(eqv.q(a15)).a(), (zki)eqv.pL(this.a).a(), (Executor)eqv.oO(this.a).a());
            }
            case 58: {
                final eqv a16 = this.a;
                final atjj ii2 = eqv.ii(a16);
                final Executor executor3 = (Executor)eqv.oO(a16).a();
                final eqv a17 = this.a;
                return zrt.o(ii2, executor3, eqv.nK(a17), (aaha)eqv.jw(a17).a());
            }
            case 57: {
                final eqv a18 = this.a;
                return idf.m(eqv.ii(a18), (zvp)eqx.cI(eqv.q(a18)).a(), (zki)eqv.pL(this.a).a(), (Executor)eqv.oO(this.a).a());
            }
            case 56: {
                final eqv a19 = this.a;
                final atjj ii3 = eqv.ii(a19);
                final Executor executor4 = (Executor)eqv.oO(a19).a();
                final eqv a20 = this.a;
                return zrt.c(ii3, executor4, eqv.nK(a20), (aaha)eqv.jw(a20).a());
            }
            case 55: {
                return idf.l((zvp)eqx.cz(eqv.q(this.a)).a(), (zki)eqv.pL(this.a).a(), (Executor)eqv.oO(this.a).a());
            }
            case 54: {
                return idf.k((uyf)eqv.po(this.a).a());
            }
            case 53: {
                final eqv a21 = this.a;
                final atjj ii4 = eqv.ii(a21);
                final Executor executor5 = (Executor)eqv.oO(a21).a();
                final eqv a22 = this.a;
                return zrt.n(ii4, executor5, eqv.nK(a22), (aaha)eqv.jw(a22).a());
            }
            case 52: {
                return idf.j((zvp)eqx.cw(eqv.q(this.a)).a(), (zki)eqv.pL(this.a).a(), (Executor)eqv.oO(this.a).a());
            }
            case 51: {
                return idf.g((uyi)eqv.lz(this.a).a());
            }
            case 50: {
                return icd.h(eqv.ii(this.a));
            }
            case 49: {
                return afdu.x((Object)eqx.ae(eqv.q(this.a)).a(), (Object)eqx.cc(eqv.q(this.a)).a(), (Object)eqx.cv(eqv.q(this.a)).a(), (Object)eqx.cx(eqv.q(this.a)).a(), (Object)eqx.cy(eqv.q(this.a)).a(), (Object)eqx.cH(eqv.q(this.a)).a(), (Object[])new icy[] { (icy)eqx.fl(eqv.q(this.a)).a(), (icy)eqx.fz(eqv.q(this.a)).a(), (icy)eqx.fW(eqv.q(this.a)).a() });
            }
            case 48: {
                return iep.b(eqv.ii(this.a));
            }
            case 47: {
                return idf.u((vbq)eqv.kF(this.a).a(), (uyi)eqv.lz(this.a).a());
            }
            case 46: {
                return idf.t();
            }
            case 45: {
                return idf.s(eqv.ii(this.a));
            }
            case 44: {
                return idf.h(eqv.ii(this.a));
            }
            case 43: {
                return idf.d();
            }
            case 42: {
                return afdu.x((Object)eqx.bZ(eqv.q(this.a)).a(), (Object)eqx.cd(eqv.q(this.a)).a(), (Object)eqx.fX(eqv.q(this.a)).a(), (Object)eqx.fY(eqv.q(this.a)).a(), (Object)eqx.fZ(eqv.q(this.a)).a(), (Object)eqx.gb(eqv.q(this.a)).a(), (Object[])new ict[0]);
            }
            case 41: {
                return zrt.d((Executor)eqv.oO(this.a).a());
            }
            case 40: {
                final eqv a23 = this.a;
                final atjj db = eqx.db(eqv.q(a23));
                final atjj jp = eqv.jp(a23);
                final atjj ii5 = eqv.ii(a23);
                final atjj kf = eqv.kF(a23);
                final ScheduledExecutorService scheduledExecutorService = (ScheduledExecutorService)eqv.oO(a23).a();
                final eqv a24 = this.a;
                return idf.i(db, jp, ii5, kf, scheduledExecutorService, eqv.hU(a24), eqx.eQ(eqv.q(a24)), eqx.eT(eqv.q(a24)), eqx.eS(eqv.q(a24)), eqv.pL(a24), (uyi)eqv.lz(a24).a());
            }
            case 39: {
                final eqv a25 = this.a;
                return fms.g(eqv.sr(a25), (tlq)eqv.fL(a25).a());
            }
            case 38: {
                return ffg.b((wyo)eqv.hU(this.a).a(), (fes)eqv.fp(this.a).a());
            }
            case 37: {
                return acbj.m((nmo)eqv.fZ(this.a).a());
            }
            case 36: {
                return new phq((osb)eqv.ji(this.a).a());
            }
            case 35: {
                return new adbl((Context)eqv.pt(this.a).a(), (phq)eqx.bi(eqv.q(this.a)).a(), (byte[])null, (byte[])null, (byte[])null);
            }
            case 34: {
                final eqv a26 = this.a;
                return abzu.b(eqv.oZ(a26), eqx.bl(eqv.q(a26)), Optional.of((Object)eqv.hn(a26)), (uyi)eqv.jc(this.a).a(), Optional.of((Object)eqx.fQ(eqv.q(this.a))), (vcf)eqv.nK(this.a).a(), (zki)eqv.pL(this.a).a(), eqv.bS(this.a));
            }
            case 33: {
                return new uyi((uyf)eqv.po(this.a).a(), (arud)eqv.qo(this.a).a(), (float[])null, (byte[])null, (byte[])null);
            }
            case 32: {
                return szp.k((aum)eqv.fn(this.a).a(), arjc.b((atjj)arji.b()));
            }
            case 31: {
                return szp.g(aele.q(eqv.zz(this.a)), (Set)afdu.r());
            }
            case 30: {
                return afdu.u((Object)eqx.gA(), (Object)eqx.cS(eqv.q(this.a)).a(), (Object)eqx.cT(eqv.q(this.a)).a());
            }
            case 29: {
                return thk.g(arjc.b(eqx.an(eqv.q(this.a))));
            }
            case 28: {
                return aaef.u((zax)eqv.lc(this.a).a(), (aeby)eqv.nQ(this.a).a());
            }
            case 27: {
                return adfv.u((adgw)eqv.vj(this.a).a(), (tme)eqv.uJ(this.a).a(), eqv.mF(this.a));
            }
            case 26: {
                return ewp.r(eqv.nx(this.a));
            }
            case 25: {
                final eqv a27 = this.a;
                final eqx q = eqv.q(a27);
                final uye s = jko.s(eqx.dG(eqv.q(a27)), (acvy)eqv.rD(a27).a());
                eqx.gZ(q, s);
                return s;
            }
            case 24: {
                return ljl.n((Context)eqv.pt(this.a).a(), (qbo)eqv.to(this.a).a());
            }
            case 23: {
                return eur.f((uyf)eqv.po(this.a).a());
            }
            case 22: {
                return uto.n(eqv.gk(this.a).a(), eqv.vV(this.a).a());
            }
            case 21: {
                return addl.j((uyf)eqv.po(this.a).a());
            }
            case 20: {
                return new mrm(eqv.ib(this.a));
            }
            case 19: {
                return acey.c((Context)eqv.pt(this.a).a());
            }
            case 18: {
                return new adio();
            }
            case 17: {
                aexq.k(eqv.sH(this.a));
                return pzz.r(eqv.vq(this.a));
            }
            case 16: {
                return qex.l();
            }
            case 15: {
                aexq.k(eqv.sH(this.a));
                return pzz.q(eqv.vq(this.a));
            }
            case 14: {
                aexq.k(eqv.sx(this.a));
                return pzz.v(eqv.uM(this.a));
            }
            case 13: {
                return psw.g();
            }
            case 12: {
                final Executor executor6 = (Executor)eqv.pN(this.a).a();
                final qdi qdi = (qdi)eqv.mv(this.a).a();
                final oas oas2 = (oas)eqv.pn(this.a).a();
                return pzz.t();
            }
            case 11: {
                aexq.k(eqv.qx(this.a));
                return pzz.j(eqv.jX(this.a));
            }
            case 10: {
                aexq.k(eqv.oT(this.a));
                return pzz.h(eqv.fF(this.a));
            }
            case 9: {
                final Context context3 = (Context)eqv.pt(this.a).a();
                final pzx pzx = (pzx)eqv.ut(this.a).a();
                final eqv a28 = this.a;
                return psw.t(pzx, eqv.uj(a28), eqv.gW(a28), eqv.mv(a28), eqv.mv(a28), eqv.mH(a28), (mrm)eqv.gX(a28).a());
            }
            case 8: {
                final pzp p = eqx.p(eqv.q(this.a));
                psw.p(p);
                return p;
            }
            case 7: {
                return new adev(arjc.b(eqx.dw(eqv.q(this.a))));
            }
            case 6: {
                return pnh.f((plu)eqv.ph(this.a).a(), (plx)eqv.gD(this.a).a(), (phy)eqv.pj(this.a).a(), (pps)eqv.vg(this.a).a(), (qbo)eqv.gw(this.a).a(), (Set)arji.b().a());
            }
            case 5: {
                return new rxr((pow)eqv.gB(this.a).a(), (plu)eqv.ph(this.a).a(), (mrm)eqv.gv(this.a).a(), aexq.k(eqv.sc(this.a).a()), (byte[])null, (byte[])null, (byte[])null, (byte[])null);
            }
            case 4: {
                final eqx q2 = eqv.q(this.a);
                final elw r2 = pqv.r();
                eqx.ha(q2, r2);
                return r2;
            }
            case 3: {
                final oas oas3 = (oas)eqv.gK(this.a).a();
                final mrm mrm = (mrm)eqv.gv(this.a).a();
                final pqj pqj = (pqj)eqv.qk(this.a).a();
                final pow pow = (pow)eqv.gB(this.a).a();
                final plu plu = (plu)eqv.ph(this.a).a();
                final elw elw = (elw)eqx.be(eqv.q(this.a)).a();
                final blt blt = (blt)eqv.uP(this.a).a();
                final aexq k = aexq.k(eqv.sc(this.a).a());
                final Context context4 = (Context)eqv.pt(this.a).a();
                final psb psb = (psb)eqv.kv(this.a).a();
                return pqv.s(oas3, mrm, pqj, pow, plu, elw, blt, k, context4);
            }
            case 2: {
                final plu plu2 = (plu)eqv.ph(this.a).a();
                final pro pro = (pro)eqv.jQ(this.a).a();
                final rhv rhv = (rhv)eqx.eF(eqv.q(this.a)).a();
                final rxr rxr = (rxr)eqx.fo(eqv.q(this.a)).a();
                final sxv sxv = (sxv)eqx.ab(eqv.q(this.a)).a();
                return new pso(plu2, rhv, rxr, (byte[])null, (byte[])null, (byte[])null, (byte[])null);
            }
            case 1: {
                return eqx.H(eqv.q(this.a));
            }
            case 0: {
                final eqx q3 = eqv.q(this.a);
                final esj f = eov.f();
                eqx.gN(q3, f);
                return f;
            }
        }
    }
    
    private final Object c() {
        final int b = this.b;
        final Boolean value = false;
        switch (b) {
            default: {
                throw new AssertionError(b);
            }
            case 199: {
                return ops.q(eqx.l(eqv.q(this.a)), (aftr)eqv.oO(this.a).a(), eqx.eR(eqv.q(this.a)), eqx.gB(), (oas)eqv.gK(this.a).a());
            }
            case 198: {
                final ozd ozd = (ozd)eqx.dl(eqv.q(this.a)).a();
                eqx.l(eqv.q(this.a));
                return ops.r(ozd, (oas)eqv.gK(this.a).a());
            }
            case 197: {
                final afdu r = afdu.r();
                final pag pag = (pag)eqx.cW(eqv.q(this.a)).a();
                pal.f();
                return pal.l((Set)r, pag);
            }
            case 196: {
                return pal.o((php)eqx.fw(eqv.q(this.a)).a());
            }
            case 195: {
                return ugi.u((uka)eqx.ex(eqv.q(this.a)).a(), (ujx)eqv.kq(this.a).a(), (auip)eqx.eY(eqv.q(this.a)).a(), (oas)eqv.gK(this.a).a(), (Executor)eqv.oO(this.a).a());
            }
            case 194: {
                return ugi.v((nmo)eqv.fZ(this.a).a(), eqv.zE(this.a), eqx.hb(eqv.q(this.a)), eqx.gV(), eqv.AC(this.a));
            }
            case 193: {
                final eqv a = this.a;
                final atjj ew = eqx.ew(eqv.q(a));
                final Context context = (Context)eqv.pt(a).a();
                return ugi.i(ew);
            }
            case 192: {
                return ugi.j();
            }
            case 191: {
                return aele.n((nmo)eqv.fZ(this.a).a());
            }
            case 190: {
                return trl.f((Context)eqv.pt(this.a).a(), (MediaEngineAudioContainerRegistrar)eqx.cj(eqv.q(this.a)).a());
            }
            case 189: {
                final Context context2 = (Context)eqv.pt(this.a).a();
                final aftr aftr = (aftr)eqv.oO(this.a).a();
                final String yv = eqv.yv();
                final eqv a2 = this.a;
                return tzb.s(context2, aftr, yv, eqv.sr(a2), (qbo)eqv.to(a2).a());
            }
            case 188: {
                return trl.t((arud)eqv.qo(this.a).a(), eqv.xq(this.a), new uyi((uyf)eqv.q(this.a).a.w.a(), (arud)eqv.q(this.a).a.v.a(), (byte[])null, (byte[])null));
            }
            case 187: {
                return new aeim((int[])null);
            }
            case 186: {
                return new vmh((vjh)eqv.rU(this.a).a(), (adcr)eqv.pu(this.a).a(), (zki)eqv.pL(this.a).a(), (tgw)eqv.pd(this.a).a(), (byte[])null, (byte[])null, (byte[])null, (byte[])null, (byte[])null, (byte[])null);
            }
            case 185: {
                return new addp((vjh)eqv.rU(this.a).a(), (adcr)eqv.pu(this.a).a(), (zki)eqv.pL(this.a).a(), (tgw)eqv.oR(this.a).a(), null, null, (byte[])null, (byte[])null, (byte[])null, (byte[])null, (byte[])null, null, null);
            }
            case 184: {
                return abzu.k((arud)eqv.qo(this.a).a());
            }
            case 183: {
                final acbo acbo = (acbo)eqv.jd(this.a).a();
                final Context context3 = (Context)eqv.pt(this.a).a();
                return abzu.f(acbo);
            }
            case 182: {
                return abzu.l();
            }
            case 181: {
                return abzu.e((boolean)eqv.qe(this.a).a(), arjc.b(eqv.q(this.a).aj), arjc.b(eqv.sG(this.a)), arjc.b(eqv.q(this.a).ak), arjc.b(eqv.lg(this.a)));
            }
            case 180: {
                return abzu.c((uyf)eqv.po(this.a).a());
            }
            case 179: {
                final Context context4 = (Context)eqv.pt(this.a).a();
                final int a3 = acbg.a;
                return value;
            }
            case 178: {
                return thk.p((Context)eqv.pt(this.a).a(), new agkw((wvu)eqv.q(this.a).a.aw.a(), (wwv)eqv.q(this.a).a.iG.a()));
            }
            case 177: {
                return abzu.r((tmp)eqv.q(this.a).af.a());
            }
            case 176: {
                return abzu.o(arjc.b(eqv.qw(this.a)), eqv.q(this.a).fq);
            }
            case 175: {
                final acdn acdn = (acdn)eqv.ha(this.a).a();
                final Context context5 = (Context)eqv.pt(this.a).a();
                final int a4 = acbg.a;
                return value;
            }
            case 174: {
                final osb osb = (osb)eqv.ji(this.a).a();
                final Context context6 = (Context)eqv.pt(this.a).a();
                final acdn acdn2 = (acdn)eqv.ha(this.a).a();
                return abzu.d(osb, context6, eqv.cT(this.a));
            }
            case 173: {
                return new bx((xlv)eqv.mi(this.a).a());
            }
            case 172: {
                return iep.l((yzf)eqv.iR(this.a).a(), (Executor)eqv.oO(this.a).a());
            }
            case 171: {
                return iep.n((ifs)eqv.q(this.a).gW.a(), (ifs)new ifz((ifw)eqv.q(this.a).hj(), (Executor)eqv.q(this.a).a.r.a(), 0), (ifs)new ify((ifw)eqv.q(this.a).hj(), (Executor)eqv.q(this.a).a.r.a(), (uyi)eqv.q(this.a).a.jf.a()));
            }
            case 170: {
                final Context context7 = (Context)eqv.pt(this.a).a();
                final eqv a5 = this.a;
                return new jvy(context7, eqv.ii(a5), (fml)eqv.lE(a5).a(), (flo)eqv.fQ(this.a).a());
            }
            case 169: {
                return jtv.f((Executor)eqv.oO(this.a).a(), (Context)eqv.pt(this.a).a(), (flg)eqv.eV(this.a).a(), (jvy)eqv.q(this.a).gV.a(), (eg)eqv.q(this.a).Z.a());
            }
            case 168: {
                eqv.xL(this.a);
                final jsp jsp = (jsp)eqv.q(this.a).gX.a();
                ihg.h(jsp);
                return jsp;
            }
            case 167: {
                return new fzo((byte[])null, (byte[])null);
            }
            case 166: {
                return new addp((vjh)eqv.rU(this.a).a(), (adcr)eqv.pu(this.a).a(), (zki)eqv.pL(this.a).a(), (tgw)eqv.pd(this.a).a(), null, (char[])null, null, null, (char[])null, null, null, null);
            }
            case 165: {
                return eov.b();
            }
            case 164: {
                return eov.c((Context)eqv.pt(this.a).a(), Optional.of((Object)eqv.lg(this.a).a()), Optional.of((Object)eqv.fx(this.a).a()), eov.e(), agnj.d((Context)eqv.q(this.a).a.c.a()));
            }
            case 163: {
                final oas oas = (oas)eqv.gK(this.a).a();
                final lzi lzi = (lzi)eqv.ie(this.a).a();
                final vjl vjl = (vjl)eqv.kM(this.a).a();
                final eqv a6 = this.a;
                return new rpq(oas, lzi, vjl, eqv.sU(a6), (arud)eqv.qo(a6).a(), (byte[])null, (byte[])null, (byte[])null, (byte[])null);
            }
            case 162: {
                final rmy rmy = (rmy)eqv.ox(this.a).a();
                return ihg.f((rpq)eqv.q(this.a).gT.a());
            }
            case 161: {
                return aais.b();
            }
            case 160: {
                return szp.e();
            }
            case 159: {
                return new abqp((Executor)eqv.oO(this.a).a(), (tgj)eqv.pK(this.a).a(), (tud)eqv.q(this.a).gQ.a(), (oas)eqv.gK(this.a).a(), (tbi)eqv.q(this.a).gR.a());
            }
            case 158: {
                return new aaas((abqd)eqv.q(this.a).gS.a(), (Executor)eqv.oO(this.a).a(), (thh)eqv.id(this.a).a(), (zzu)eqv.ii(this.a).a(), zmo.a((tbi)eqv.q(this.a).gR.a(), (zmj)zlv.a((Executor)eqv.q(this.a).a.r.a(), (zmj)new aceu((tud)eqv.q(this.a).gQ.a(), 1)), (oas)eqv.q(this.a).a.e.a(), 7200000L));
            }
            case 157: {
                return new auip((SharedPreferences)eqv.sr(this.a).a(), (avt)eqv.hi(this.a).a(), (byte[])null, (byte[])null, (byte[])null, (byte[])null, (byte[])null, (byte[])null);
            }
            case 156: {
                return new phy(eqx.Q(eqv.q(this.a)), (pqw)eqv.q(this.a).v.a(), eqv.wp(this.a), (byte[])null, (byte[])null);
            }
            case 155: {
                final vjh vjh = (vjh)eqv.rU(this.a).a();
                final adcr adcr = (adcr)eqv.pu(this.a).a();
                final zki zki = (zki)eqv.pL(this.a).a();
                return new aaca(vjh, adcr, (tgw)eqv.oR(this.a).a(), (uyf)eqv.po(this.a).a(), (byte[])null, (byte[])null, (byte[])null, (byte[])null, (byte[])null, (byte[])null);
            }
            case 154: {
                return new addr((vjh)eqv.rU(this.a).a(), (adcr)eqv.pu(this.a).a(), (zki)eqv.pL(this.a).a(), (tgw)eqv.pd(this.a).a(), null, null, null, null, null, null);
            }
            case 153: {
                return addl.u((vjh)eqv.rU(this.a).a(), (adcr)eqv.pu(this.a).a(), (tgw)eqv.oR(this.a).a());
            }
            case 152: {
                final eqv a7 = this.a;
                return adhg.d(eqv.fq(a7), (oas)eqv.gK(a7).a(), (ScheduledExecutorService)eqv.oO(this.a).a(), eqv.q(this.a).O);
            }
            case 151: {
                return adhg.n((Context)eqv.pt(this.a).a());
            }
            case 150: {
                return vny.q((vjh)eqv.rU(this.a).a(), (adcr)eqv.pu(this.a).a(), (zki)eqv.pL(this.a).a(), (tgw)eqv.pd(this.a).a());
            }
            case 149: {
                return new adjl((vjh)eqv.rU(this.a).a(), (adcr)eqv.pu(this.a).a(), (zki)eqv.pL(this.a).a(), (tgw)eqv.oR(this.a).a(), (uyf)eqv.po(this.a).a(), (byte[])null, (byte[])null, (byte[])null, (byte[])null, (byte[])null, (byte[])null);
            }
            case 148: {
                return new auip((Context)eqv.pt(this.a).a(), (byte[])null);
            }
            case 147: {
                return adhg.s((auip)eqv.q(this.a).J.a(), (adcr)eqv.vC(this.a).a());
            }
            case 146: {
                final Context context8 = (Context)eqv.pt(this.a).a();
                final SharedPreferences sharedPreferences = (SharedPreferences)eqv.sr(this.a).a();
                return new adio();
            }
            case 145: {
                return adhg.k((oas)eqv.gK(this.a).a(), (ScheduledExecutorService)eqv.oO(this.a).a(), (arud)eqv.qo(this.a).a(), (adit)eqv.kW(this.a).a(), (adcr)eqv.vC(this.a).a(), (adjo)eqv.vF(this.a).a(), (admn)eqv.mP(this.a).a());
            }
            case 144: {
                return new hyq(this.a);
            }
            case 143: {
                return aele.s(eqv.q(this.a).gP);
            }
            case 142: {
                return ppa.o(new cya(this.a));
            }
            case 141: {
                return pnh.c(afdu.x((Object)eqv.q(this.a).a.oZ.a(), (Object)eqv.q(this.a).a.oY.a(), (Object)eqv.q(this.a).a.oW.a(), (Object)eqv.q(this.a).a.oX.a(), (Object)eqv.q(this.a).a.pa.a(), (Object)eqv.q(this.a).a.pb.a(), (Object[])new psy[] { (psy)eqv.q(this.a).a.pc.a(), (psy)eqv.q(this.a).a.pd.a(), (psy)eqv.q(this.a).a.oQ.a(), (psy)eqv.q(this.a).gM.a(), (psy)eqv.q(this.a).gJ.a() }), (qbo)eqv.gw(this.a).a());
            }
            case 140: {
                return pal.j(afdu.x((Object)eqv.q(this.a).a.oZ.a(), (Object)eqv.q(this.a).a.oY.a(), (Object)eqv.q(this.a).a.oW.a(), (Object)eqv.q(this.a).a.oX.a(), (Object)eqv.q(this.a).a.pa.a(), (Object)eqv.q(this.a).a.pb.a(), (Object[])new psy[] { (psy)eqv.q(this.a).a.pc.a(), (psy)eqv.q(this.a).a.pd.a(), (psy)eqv.q(this.a).a.oQ.a(), (psy)eqv.q(this.a).gM.a(), (psy)eqv.q(this.a).gJ.a() }), (pnr)eqv.gx(this.a).a(), (qbo)eqv.gw(this.a).a());
            }
            case 139: {
                return pnh.g((elw)eqv.q(this.a).gF.a(), (qbo)eqv.gw(this.a).a());
            }
            case 138: {
                return pnh.d((poj)eqv.gy(this.a).a(), (plu)eqv.ph(this.a).a(), (phr)eqv.pk(this.a).a(), (Set)arji.b().a());
            }
            case 137: {
                return new pnb((pte)eqv.gF(this.a).a());
            }
            case 136: {
                return pnh.h(eqv.Af(this.a), (poc)eqv.q(this.a).gJ.a());
            }
            case 135: {
                return poi.j((plu)eqv.ph(this.a).a(), (phy)eqv.pj(this.a).a(), (phy)eqv.pi(this.a).a(), (qbo)eqv.gw(this.a).a(), (Set)arji.b().a());
            }
            case 134: {
                return new rxr((psz)eqv.gE(this.a).a(), arjc.b(eqv.ku(this.a)), (psy)eqv.q(this.a).gJ.a(), (ptb)eqv.q(this.a).gK.a());
            }
            case 133: {
                return pal.u((pqj)eqv.qk(this.a).a(), (elw)eqv.q(this.a).gF.a(), (pte)eqv.gF(this.a).a(), (psz)eqv.gE(this.a).a(), arjc.b(eqv.qy(this.a)), (Set)arji.b().a(), (qbo)eqv.gw(this.a).a(), (rxr)eqv.q(this.a).gL.a(), (pnb)eqv.q(this.a).gM.a(), eqv.q(this.a).ho());
            }
            case 132: {
                return pal.r((elw)eqv.q(this.a).gF.a(), (qbo)eqv.gw(this.a).a());
            }
            case 131: {
                return new phq((plu)eqv.ph(this.a).a(), (prb)eqv.fT(this.a).a());
            }
            case 130: {
                return new pmy((phq)eqv.q(this.a).gI.a(), (poj)eqv.gy(this.a).a(), (mrm)eqv.gC(this.a).a(), (qbo)eqv.gw(this.a).a(), (elw)eqv.q(this.a).gF.a(), (plu)eqv.ph(this.a).a(), (sxv)eqv.q(this.a).eV.a(), (pps)eqv.vg(this.a).a(), arjc.b((atjj)arji.b()), (phy)eqv.pi(this.a).a(), (oas)eqv.gK(this.a).a(), (Lock)eqv.sE(this.a).a(), (byte[])null, (byte[])null, (byte[])null, (byte[])null, (byte[])null, (byte[])null);
            }
            case 129: {
                return new pna((qbo)eqv.gw(this.a).a(), (elw)eqv.q(this.a).gF.a(), 1, (byte[])null, (byte[])null, (byte[])null);
            }
            case 128: {
                return pal.t((plu)eqv.ph(this.a).a(), (sxv)eqv.q(this.a).eV.a(), (elw)eqv.q(this.a).eS.a(), (elw)eqv.q(this.a).gF.a(), (qbo)eqv.gw(this.a).a());
            }
            case 127: {
                return ppa.m();
            }
            case 126: {
                final psb psb = (psb)eqv.kv(this.a).a();
                return new agkh((pni)eqv.q(this.a).hi(), 1);
            }
            case 125: {
                return pal.h((oas)eqv.gK(this.a).a());
            }
            case 124: {
                arjc.b(eqv.gy(this.a));
                final mrm mrm = (mrm)eqv.gv(this.a).a();
                final phr phr = (phr)eqv.pk(this.a).a();
                final elw elw = (elw)eqv.q(this.a).eS.a();
                final qbo qbo = (qbo)eqv.gw(this.a).a();
                final oas oas2 = (oas)eqv.gK(this.a).a();
                final Random random = (Random)eqv.q(this.a).gG.a();
                return pal.k();
            }
            case 123: {
                final mrm mrm2 = (mrm)eqv.gC(this.a).a();
                final plu plu = (plu)eqv.ph(this.a).a();
                return new pmt();
            }
            case 122: {
                final eqx q = eqv.q(this.a);
                final elw q2 = pqv.q();
                eqx.gY(q, q2);
                return q2;
            }
            case 121: {
                return pqv.e();
            }
            case 120: {
                return pqv.d();
            }
            case 119: {
                return pqv.l();
            }
            case 118: {
                return pqv.c();
            }
            case 117: {
                return ops.t();
            }
            case 116: {
                return ops.v();
            }
            case 115: {
                return ops.u();
            }
            case 114: {
                return xab.t((adcr)eqv.oN(this.a).a(), eqv.fO(this.a));
            }
            case 113: {
                return vbj.d((oas)eqv.gK(this.a).a());
            }
            case 112: {
                return com.google.android.apps.youtube.embeddedplayer.service.permissions.b.b();
            }
            case 111: {
                return new uyi((uyf)eqv.po(this.a).a(), (arud)eqv.qo(this.a).a(), (int[])null, (byte[])null, (byte[])null);
            }
            case 110: {
                final eqv a8 = this.a;
                return ewp.l(eqv.q(a8).gs, eqv.oR(a8), eqv.q(a8).gd, (oas)eqv.gK(a8).a(), (uyi)eqv.q(this.a).m.a());
            }
            case 109: {
                final arud arud = (arud)eqv.qo(this.a).a();
                final uyf uyf = (uyf)eqv.po(this.a).a();
                return ewp.u(arud, (SharedPreferences)eqv.sr(this.a).a(), (acws)eqv.q(this.a).gy.a(), (Context)eqv.pt(this.a).a(), (zki)eqv.pL(this.a).a(), (rfv)eqv.oF(this.a).a(), (ScheduledExecutorService)eqv.oO(this.a).a(), (oas)eqv.gK(this.a).a(), (jkp)eqv.q(this.a).n.a(), (acwg)eqv.om(this.a).a(), (acwj)eqv.tM(this.a).a(), ewo.v((acws)eqv.q(this.a).gy.a(), (tlq)eqv.q(this.a).a.m.a()), (auip)eqv.q(this.a).p.a(), (jkq)eqv.q(this.a).gv.a(), acve.o(), (uyi)eqv.q(this.a).m.a());
            }
            case 108: {
                final arud arud2 = (arud)eqv.qo(this.a).a();
                final uyf uyf2 = (uyf)eqv.po(this.a).a();
                return ewp.t(arud2, (SharedPreferences)eqv.sr(this.a).a(), (acws)eqv.q(this.a).gt.a(), (Context)eqv.pt(this.a).a(), (zki)eqv.pL(this.a).a(), (rfv)eqv.oF(this.a).a(), (ScheduledExecutorService)eqv.oO(this.a).a(), (oas)eqv.gK(this.a).a(), (jkp)eqv.q(this.a).n.a(), (acwg)eqv.om(this.a).a(), (acwj)eqv.tM(this.a).a(), eqx.B(eqv.q(this.a)), (auip)eqv.q(this.a).p.a(), (jkq)eqv.q(this.a).gv.a(), acve.o(), (uyi)eqv.q(this.a).m.a());
            }
            case 107: {
                final arud arud3 = (arud)eqv.qo(this.a).a();
                final Context context9 = (Context)eqv.pt(this.a).a();
                final eqv a9 = this.a;
                return jko.v(arud3, context9, eqv.ic(a9), (adcr)eqv.tU(a9).a(), (uyi)eqv.q(this.a).m.a());
            }
            case 106: {
                return ewp.q();
            }
            case 105: {
                return new acwd((acvy)eqv.rD(this.a).a(), ewo.u((acws)eqv.q(this.a).gt.a(), (tlq)eqv.q(this.a).a.m.a()), new acwb((acvy)eqv.q(this.a).a.jz.a(), (agkw)eqv.q(this.a).a.jA.a(), (byte[])null), (ScheduledExecutorService)eqv.oO(this.a).a(), (ScheduledExecutorService)eqv.lg(this.a).a(), (tlq)eqv.fL(this.a).a());
            }
            case 104: {
                return new aeim((Context)eqv.pt(this.a).a(), (byte[])null);
            }
            case 103: {
                return new jkp((SharedPreferences)eqv.sr(this.a).a());
            }
            case 102: {
                return new uyi((uyf)eqv.po(this.a).a(), (arud)eqv.qo(this.a).a(), (short[][])null, (byte[])null, (byte[])null);
            }
            case 101: {
                return acve.c((tgy)eqv.fU(this.a).a(), thk.b(), (ExecutorService)eqv.oO(this.a).a(), (ExecutorService)eqv.pA(this.a).a(), (ExecutorService)eqv.lg(this.a).a(), (tlq)eqv.fL(this.a).a());
            }
            case 100: {
                final eqv a10 = this.a;
                return ewq.c(eqv.q(a10).gs, eqv.oR(a10), eqv.q(a10).gb, (oas)eqv.gK(a10).a(), (uyi)eqv.q(this.a).m.a());
            }
        }
    }
    
    private final Object d() {
        // 
        // This method could not be decompiled.
        // 
        // Original Bytecode:
        // 
        //     1: getfield        eqw.b:I
        //     4: istore_1       
        //     5: iload_1        
        //     6: tableswitch {
        //              400: 4654
        //              401: 4637
        //              402: 4603
        //              403: 4589
        //              404: 4585
        //              405: 4581
        //              406: 4577
        //              407: 4566
        //              408: 4562
        //              409: 4551
        //              410: 4540
        //              411: 4526
        //              412: 4515
        //              413: 4508
        //              414: 4486
        //              415: 4449
        //              416: 4379
        //              417: 4345
        //              418: 4323
        //              419: 4316
        //              420: 4242
        //              421: 4098
        //              422: 4018
        //              423: 3913
        //              424: 3903
        //              425: 3892
        //              426: 3881
        //              427: 3871
        //              428: 3848
        //              429: 3840
        //              430: 3770
        //              431: 3618
        //              432: 3610
        //              433: 3588
        //              434: 3554
        //              435: 3449
        //              436: 3344
        //              437: 3280
        //              438: 3197
        //              439: 3114
        //              440: 3047
        //              441: 3028
        //              442: 2969
        //              443: 2873
        //              444: 2764
        //              445: 2659
        //              446: 2645
        //              447: 2596
        //              448: 2576
        //              449: 2550
        //              450: 2476
        //              451: 2438
        //              452: 2419
        //              453: 2411
        //              454: 2385
        //              455: 2301
        //              456: 2282
        //              457: 2278
        //              458: 2208
        //              459: 2087
        //              460: 2030
        //              461: 1966
        //              462: 1899
        //              463: 1880
        //              464: 1843
        //              465: 1798
        //              466: 1779
        //              467: 1756
        //              468: 1752
        //              469: 1621
        //              470: 1583
        //              471: 1557
        //              472: 1538
        //              473: 1485
        //              474: 1432
        //              475: 1352
        //              476: 1348
        //              477: 1319
        //              478: 1249
        //              479: 1187
        //              480: 1011
        //              481: 1003
        //              482: 984
        //              483: 968
        //              484: 944
        //              485: 925
        //              486: 906
        //              487: 853
        //              488: 834
        //              489: 800
        //              490: 757
        //              491: 735
        //              492: 668
        //              493: 625
        //              494: 581
        //              495: 562
        //              496: 554
        //              497: 544
        //              498: 470
        //              499: 429
        //          default: 420
        //        }
        //   420: new             Ljava/lang/AssertionError;
        //   423: dup            
        //   424: iload_1        
        //   425: invokespecial   java/lang/AssertionError.<init>:(I)V
        //   428: athrow         
        //   429: new             Ltdg;
        //   432: dup            
        //   433: aload_0        
        //   434: getfield        eqw.a:Leqv;
        //   437: getfield        eqv.c:Latjj;
        //   440: invokeinterface atjj.a:()Ljava/lang/Object;
        //   445: checkcast       Landroid/content/Context;
        //   448: aload_0        
        //   449: getfield        eqw.a:Leqv;
        //   452: getfield        eqv.a:Leqx;
        //   455: getfield        eqx.ca:Latjj;
        //   458: invokeinterface atjj.a:()Ljava/lang/Object;
        //   463: checkcast       Lzhs;
        //   466: invokespecial   tdg.<init>:(Landroid/content/Context;Lzhs;)V
        //   469: areturn        
        //   470: new             Labhr;
        //   473: dup            
        //   474: aload_0        
        //   475: getfield        eqw.a:Leqv;
        //   478: getfield        eqv.c:Latjj;
        //   481: invokeinterface atjj.a:()Ljava/lang/Object;
        //   486: checkcast       Landroid/content/Context;
        //   489: aload_0        
        //   490: getfield        eqw.a:Leqv;
        //   493: getfield        eqv.a:Leqx;
        //   496: getfield        eqx.cb:Latjj;
        //   499: invokeinterface atjj.a:()Ljava/lang/Object;
        //   504: checkcast       Ltdg;
        //   507: aload_0        
        //   508: getfield        eqw.a:Leqv;
        //   511: getfield        eqv.g:Latjj;
        //   514: invokeinterface atjj.a:()Ljava/lang/Object;
        //   519: checkcast       Ljava/util/concurrent/Executor;
        //   522: aload_0        
        //   523: getfield        eqw.a:Leqv;
        //   526: getfield        eqv.r:Latjj;
        //   529: invokeinterface atjj.a:()Ljava/lang/Object;
        //   534: checkcast       Ljava/util/concurrent/Executor;
        //   537: aconst_null    
        //   538: aconst_null    
        //   539: aconst_null    
        //   540: invokespecial   abhr.<init>:(Landroid/content/Context;Ltdg;Ljava/util/concurrent/Executor;Ljava/util/concurrent/Executor;[B[B[B)V
        //   543: areturn        
        //   544: new             Lmck;
        //   547: dup            
        //   548: aconst_null    
        //   549: aconst_null    
        //   550: invokespecial   mck.<init>:([B[C)V
        //   553: areturn        
        //   554: new             Lriv;
        //   557: dup            
        //   558: invokespecial   riv.<init>:()V
        //   561: areturn        
        //   562: aload_0        
        //   563: getfield        eqw.a:Leqv;
        //   566: getfield        eqv.w:Latjj;
        //   569: invokeinterface atjj.a:()Ljava/lang/Object;
        //   574: checkcast       Luyf;
        //   577: invokestatic    flp.q:(Luyf;)Lbhu;
        //   580: areturn        
        //   581: aload_0        
        //   582: getfield        eqw.a:Leqv;
        //   585: getfield        eqv.c:Latjj;
        //   588: invokeinterface atjj.a:()Ljava/lang/Object;
        //   593: checkcast       Landroid/content/Context;
        //   596: aload_0        
        //   597: getfield        eqw.a:Leqv;
        //   600: getfield        eqv.d:Latjj;
        //   603: invokeinterface atjj.a:()Ljava/lang/Object;
        //   608: checkcast       Landroid/content/SharedPreferences;
        //   611: aload_0        
        //   612: getfield        eqw.a:Leqv;
        //   615: getfield        eqv.a:Leqx;
        //   618: invokevirtual   eqx.O:()Ljava/lang/String;
        //   621: invokestatic    ewo.C:(Landroid/content/Context;Landroid/content/SharedPreferences;Ljava/lang/String;)Ljava/lang/String;
        //   624: areturn        
        //   625: aload_0        
        //   626: getfield        eqw.a:Leqv;
        //   629: getfield        eqv.c:Latjj;
        //   632: invokeinterface atjj.a:()Ljava/lang/Object;
        //   637: checkcast       Landroid/content/Context;
        //   640: ldc_w           "premium_filter"
        //   643: ldc_w           "premium_filter_schema.pb"
        //   646: aload_0        
        //   647: getfield        eqw.a:Leqv;
        //   650: getfield        eqv.ai:Latjj;
        //   653: invokeinterface atjj.a:()Ljava/lang/Object;
        //   658: checkcast       Lqbo;
        //   661: getstatic       jge.a:Ljge;
        //   664: invokestatic    tdb.p:(Landroid/content/Context;Ljava/lang/String;Ljava/lang/String;Lqbo;Lcom/google/protobuf/MessageLite;)Ltku;
        //   667: areturn        
        //   668: aload_0        
        //   669: getfield        eqw.a:Leqv;
        //   672: getfield        eqv.c:Latjj;
        //   675: invokeinterface atjj.a:()Ljava/lang/Object;
        //   680: checkcast       Landroid/content/Context;
        //   683: invokestatic    eqv.xk:()Ljava/lang/String;
        //   686: aload_0        
        //   687: getfield        eqw.a:Leqv;
        //   690: getfield        eqv.r:Latjj;
        //   693: invokeinterface atjj.a:()Ljava/lang/Object;
        //   698: checkcast       Laftr;
        //   701: aload_0        
        //   702: getfield        eqw.a:Leqv;
        //   705: getfield        eqv.ai:Latjj;
        //   708: invokeinterface atjj.a:()Ljava/lang/Object;
        //   713: checkcast       Lqbo;
        //   716: aload_0        
        //   717: getfield        eqw.a:Leqv;
        //   720: getfield        eqv.am:Latjj;
        //   723: invokeinterface atjj.a:()Ljava/lang/Object;
        //   728: checkcast       Lauip;
        //   731: invokestatic    jqy.b:(Landroid/content/Context;Ljava/lang/String;Laftr;Lqbo;Lauip;)Ltku;
        //   734: areturn        
        //   735: aload_0        
        //   736: getfield        eqw.a:Leqv;
        //   739: getfield        eqv.a:Leqx;
        //   742: getfield        eqx.bT:Latjj;
        //   745: invokeinterface atjj.a:()Ljava/lang/Object;
        //   750: checkcast       Ltku;
        //   753: invokestatic    frh.s:(Ltku;)Lcxz;
        //   756: areturn        
        //   757: aload_0        
        //   758: getfield        eqw.a:Leqv;
        //   761: getfield        eqv.c:Latjj;
        //   764: invokeinterface atjj.a:()Ljava/lang/Object;
        //   769: checkcast       Landroid/content/Context;
        //   772: ldc_w           "renderingui"
        //   775: ldc_w           "frequency_cap_proto.pb"
        //   778: aload_0        
        //   779: getfield        eqw.a:Leqv;
        //   782: getfield        eqv.ai:Latjj;
        //   785: invokeinterface atjj.a:()Ljava/lang/Object;
        //   790: checkcast       Lqbo;
        //   793: getstatic       aqoz.a:Laqoz;
        //   796: invokestatic    tdb.p:(Landroid/content/Context;Ljava/lang/String;Ljava/lang/String;Lqbo;Lcom/google/protobuf/MessageLite;)Ltku;
        //   799: areturn        
        //   800: aload_0        
        //   801: getfield        eqw.a:Leqv;
        //   804: getfield        eqv.c:Latjj;
        //   807: invokeinterface atjj.a:()Ljava/lang/Object;
        //   812: checkcast       Landroid/content/Context;
        //   815: aload_0        
        //   816: getfield        eqw.a:Leqv;
        //   819: getfield        eqv.ai:Latjj;
        //   822: invokeinterface atjj.a:()Ljava/lang/Object;
        //   827: checkcast       Lqbo;
        //   830: invokestatic    jfi.M:(Landroid/content/Context;Lqbo;)Laagm;
        //   833: areturn        
        //   834: aload_0        
        //   835: getfield        eqw.a:Leqv;
        //   838: getfield        eqv.c:Latjj;
        //   841: invokeinterface atjj.a:()Ljava/lang/Object;
        //   846: checkcast       Landroid/content/Context;
        //   849: invokestatic    nan.q:(Landroid/content/Context;)Lmwr;
        //   852: areturn        
        //   853: new             Ladki;
        //   856: dup            
        //   857: aload_0        
        //   858: getfield        eqw.a:Leqv;
        //   861: getfield        eqv.lb:Latjj;
        //   864: invokeinterface atjj.a:()Ljava/lang/Object;
        //   869: checkcast       Ladit;
        //   872: aload_0        
        //   873: getfield        eqw.a:Leqv;
        //   876: getfield        eqv.w:Latjj;
        //   879: invokeinterface atjj.a:()Ljava/lang/Object;
        //   884: checkcast       Luyf;
        //   887: aload_0        
        //   888: getfield        eqw.a:Leqv;
        //   891: getfield        eqv.aC:Latjj;
        //   894: invokeinterface atjj.a:()Ljava/lang/Object;
        //   899: checkcast       Lzki;
        //   902: invokespecial   adki.<init>:(Ladit;Luyf;Lzki;)V
        //   905: areturn        
        //   906: aload_0        
        //   907: getfield        eqw.a:Leqv;
        //   910: getfield        eqv.mv:Latjj;
        //   913: invokeinterface atjj.a:()Ljava/lang/Object;
        //   918: checkcast       Labns;
        //   921: invokestatic    hjq.c:(Labns;)Lhjs;
        //   924: areturn        
        //   925: aload_0        
        //   926: getfield        eqw.a:Leqv;
        //   929: getfield        eqv.es:Latjj;
        //   932: invokeinterface atjj.a:()Ljava/lang/Object;
        //   937: checkcast       Limh;
        //   940: invokestatic    ihg.i:(Limh;)Lvag;
        //   943: areturn        
        //   944: new             Lvag;
        //   947: dup            
        //   948: aload_0        
        //   949: getfield        eqw.a:Leqv;
        //   952: getfield        eqv.km:Latjj;
        //   955: invokeinterface atjj.a:()Ljava/lang/Object;
        //   960: checkcast       Lzyj;
        //   963: iconst_2       
        //   964: invokespecial   vag.<init>:(Lzyj;I)V
        //   967: areturn        
        //   968: new             Lvag;
        //   971: dup            
        //   972: aload_0        
        //   973: getfield        eqw.a:Leqv;
        //   976: getfield        eqv.cm:Latjj;
        //   979: iconst_0       
        //   980: invokespecial   vag.<init>:(Latjj;I)V
        //   983: areturn        
        //   984: aload_0        
        //   985: getfield        eqw.a:Leqv;
        //   988: getfield        eqv.bt:Latjj;
        //   991: invokeinterface atjj.a:()Ljava/lang/Object;
        //   996: checkcast       Labns;
        //   999: invokestatic    fjd.a:(Labns;)Lfjd;
        //  1002: areturn        
        //  1003: new             Lsto;
        //  1006: dup            
        //  1007: invokespecial   sto.<init>:()V
        //  1010: areturn        
        //  1011: aload_0        
        //  1012: getfield        eqw.a:Leqv;
        //  1015: getfield        eqv.a:Leqx;
        //  1018: getfield        eqx.bF:Latjj;
        //  1021: invokeinterface atjj.a:()Ljava/lang/Object;
        //  1026: checkcast       Lven;
        //  1029: aload_0        
        //  1030: getfield        eqw.a:Leqv;
        //  1033: getfield        eqv.a:Leqx;
        //  1036: getfield        eqx.bG:Latjj;
        //  1039: invokeinterface atjj.a:()Ljava/lang/Object;
        //  1044: checkcast       Lven;
        //  1047: aload_0        
        //  1048: getfield        eqw.a:Leqv;
        //  1051: getfield        eqv.nx:Latjj;
        //  1054: invokeinterface atjj.a:()Ljava/lang/Object;
        //  1059: checkcast       Lven;
        //  1062: aload_0        
        //  1063: getfield        eqw.a:Leqv;
        //  1066: getfield        eqv.a:Leqx;
        //  1069: getfield        eqx.bH:Latjj;
        //  1072: invokeinterface atjj.a:()Ljava/lang/Object;
        //  1077: checkcast       Lven;
        //  1080: aload_0        
        //  1081: getfield        eqw.a:Leqv;
        //  1084: getfield        eqv.a:Leqx;
        //  1087: getfield        eqx.bI:Latjj;
        //  1090: invokeinterface atjj.a:()Ljava/lang/Object;
        //  1095: checkcast       Lven;
        //  1098: aload_0        
        //  1099: getfield        eqw.a:Leqv;
        //  1102: getfield        eqv.a:Leqx;
        //  1105: getfield        eqx.bJ:Latjj;
        //  1108: invokeinterface atjj.a:()Ljava/lang/Object;
        //  1113: checkcast       Lven;
        //  1116: iconst_3       
        //  1117: anewarray       Lven;
        //  1120: dup            
        //  1121: iconst_0       
        //  1122: aload_0        
        //  1123: getfield        eqw.a:Leqv;
        //  1126: getfield        eqv.a:Leqx;
        //  1129: getfield        eqx.bK:Latjj;
        //  1132: invokeinterface atjj.a:()Ljava/lang/Object;
        //  1137: checkcast       Lven;
        //  1140: aastore        
        //  1141: dup            
        //  1142: iconst_1       
        //  1143: aload_0        
        //  1144: getfield        eqw.a:Leqv;
        //  1147: getfield        eqv.a:Leqx;
        //  1150: getfield        eqx.bL:Latjj;
        //  1153: invokeinterface atjj.a:()Ljava/lang/Object;
        //  1158: checkcast       Lven;
        //  1161: aastore        
        //  1162: dup            
        //  1163: iconst_2       
        //  1164: aload_0        
        //  1165: getfield        eqw.a:Leqv;
        //  1168: getfield        eqv.a:Leqx;
        //  1171: getfield        eqx.bM:Latjj;
        //  1174: invokeinterface atjj.a:()Ljava/lang/Object;
        //  1179: checkcast       Lven;
        //  1182: aastore        
        //  1183: invokestatic    afdu.x:(Ljava/lang/Object;Ljava/lang/Object;Ljava/lang/Object;Ljava/lang/Object;Ljava/lang/Object;Ljava/lang/Object;[Ljava/lang/Object;)Lafdu;
        //  1186: areturn        
        //  1187: aload_0        
        //  1188: getfield        eqw.a:Leqv;
        //  1191: astore_2       
        //  1192: new             Lacga;
        //  1195: dup            
        //  1196: aload_2        
        //  1197: getfield        eqv.a:Leqx;
        //  1200: getfield        eqx.bN:Latjj;
        //  1203: aload_2        
        //  1204: getfield        eqv.g:Latjj;
        //  1207: invokeinterface atjj.a:()Ljava/lang/Object;
        //  1212: checkcast       Ljava/util/concurrent/Executor;
        //  1215: aload_0        
        //  1216: getfield        eqw.a:Leqv;
        //  1219: getfield        eqv.ay:Latjj;
        //  1222: invokeinterface atjj.a:()Ljava/lang/Object;
        //  1227: checkcast       Laftr;
        //  1230: aload_0        
        //  1231: getfield        eqw.a:Leqv;
        //  1234: getfield        eqv.ew:Latjj;
        //  1237: invokeinterface atjj.a:()Ljava/lang/Object;
        //  1242: checkcast       Ladfy;
        //  1245: invokespecial   acga.<init>:(Latjj;Ljava/util/concurrent/Executor;Laftr;Ladfy;)V
        //  1248: areturn        
        //  1249: new             Lhyc;
        //  1252: dup            
        //  1253: aload_0        
        //  1254: getfield        eqw.a:Leqv;
        //  1257: getfield        eqv.fL:Latjj;
        //  1260: invokeinterface atjj.a:()Ljava/lang/Object;
        //  1265: checkcast       Llzi;
        //  1268: aload_0        
        //  1269: getfield        eqw.a:Leqv;
        //  1272: getfield        eqv.aC:Latjj;
        //  1275: invokeinterface atjj.a:()Ljava/lang/Object;
        //  1280: checkcast       Lzki;
        //  1283: aload_0        
        //  1284: getfield        eqw.a:Leqv;
        //  1287: getfield        eqv.a:Leqx;
        //  1290: getfield        eqx.bO:Latjj;
        //  1293: invokeinterface atjj.a:()Ljava/lang/Object;
        //  1298: checkcast       Lacga;
        //  1301: aload_0        
        //  1302: getfield        eqw.a:Leqv;
        //  1305: getfield        eqv.a:Leqx;
        //  1308: getfield        eqx.bP:Latjj;
        //  1311: aconst_null    
        //  1312: aconst_null    
        //  1313: aconst_null    
        //  1314: aconst_null    
        //  1315: invokespecial   hyc.<init>:(Llzi;Lzki;Lacga;Latjj;[B[B[B[B)V
        //  1318: areturn        
        //  1319: aload_0        
        //  1320: getfield        eqw.a:Leqv;
        //  1323: astore_2       
        //  1324: new             Lggc;
        //  1327: dup            
        //  1328: aload_2        
        //  1329: getfield        eqv.ev:Latjj;
        //  1332: aload_2        
        //  1333: getfield        eqv.im:Latjj;
        //  1336: invokeinterface atjj.a:()Ljava/lang/Object;
        //  1341: checkcast       Lxbz;
        //  1344: invokespecial   ggc.<init>:(Latjj;Lxbz;)V
        //  1347: areturn        
        //  1348: invokestatic    jxe.m:()Larcq;
        //  1351: areturn        
        //  1352: aload_0        
        //  1353: getfield        eqw.a:Leqv;
        //  1356: getfield        eqv.cz:Latjj;
        //  1359: invokeinterface atjj.a:()Ljava/lang/Object;
        //  1364: checkcast       Ljava/lang/Boolean;
        //  1367: invokevirtual   java/lang/Boolean.booleanValue:()Z
        //  1370: istore_3       
        //  1371: aload_0        
        //  1372: getfield        eqw.a:Leqv;
        //  1375: getfield        eqv.a:Leqx;
        //  1378: getfield        eqx.aj:Latjj;
        //  1381: invokestatic    arjc.b:(Latjj;)Larhr;
        //  1384: astore          4
        //  1386: aload_0        
        //  1387: getfield        eqw.a:Leqv;
        //  1390: getfield        eqv.cE:Latjj;
        //  1393: invokestatic    arjc.b:(Latjj;)Larhr;
        //  1396: astore          5
        //  1398: aload_0        
        //  1399: getfield        eqw.a:Leqv;
        //  1402: getfield        eqv.a:Leqx;
        //  1405: getfield        eqx.ak:Latjj;
        //  1408: invokestatic    arjc.b:(Latjj;)Larhr;
        //  1411: astore_2       
        //  1412: iload_3        
        //  1413: aload           4
        //  1415: aload           5
        //  1417: aload_0        
        //  1418: getfield        eqw.a:Leqv;
        //  1421: getfield        eqv.E:Latjj;
        //  1424: invokestatic    arjc.b:(Latjj;)Larhr;
        //  1427: aload_2        
        //  1428: invokestatic    aaja.z:(ZLarhr;Larhr;Larhr;Larhr;)Losx;
        //  1431: areturn        
        //  1432: new             Ljkl;
        //  1435: dup            
        //  1436: aload_0        
        //  1437: getfield        eqw.a:Leqv;
        //  1440: getfield        eqv.gk:Latjj;
        //  1443: invokeinterface atjj.a:()Ljava/lang/Object;
        //  1448: checkcast       Lvjl;
        //  1451: aload_0        
        //  1452: getfield        eqw.a:Leqv;
        //  1455: getfield        eqv.r:Latjj;
        //  1458: invokeinterface atjj.a:()Ljava/lang/Object;
        //  1463: checkcast       Ljava/util/concurrent/Executor;
        //  1466: aload_0        
        //  1467: getfield        eqw.a:Leqv;
        //  1470: getfield        eqv.G:Latjj;
        //  1473: invokeinterface atjj.a:()Ljava/lang/Object;
        //  1478: checkcast       Landroid/os/Handler;
        //  1481: invokespecial   jkl.<init>:(Lvjl;Ljava/util/concurrent/Executor;Landroid/os/Handler;)V
        //  1484: areturn        
        //  1485: new             Lauip;
        //  1488: dup            
        //  1489: aload_0        
        //  1490: getfield        eqw.a:Leqv;
        //  1493: getfield        eqv.jC:Latjj;
        //  1496: invokeinterface atjj.a:()Ljava/lang/Object;
        //  1501: checkcast       Ldaw;
        //  1504: aload_0        
        //  1505: getfield        eqw.a:Leqv;
        //  1508: getfield        eqv.r:Latjj;
        //  1511: invokeinterface atjj.a:()Ljava/lang/Object;
        //  1516: checkcast       Ljava/util/concurrent/Executor;
        //  1519: aload_0        
        //  1520: getfield        eqw.a:Leqv;
        //  1523: getfield        eqv.gk:Latjj;
        //  1526: invokeinterface atjj.a:()Ljava/lang/Object;
        //  1531: checkcast       Lvjl;
        //  1534: invokespecial   auip.<init>:(Ldaw;Ljava/util/concurrent/Executor;Lvjl;)V
        //  1537: areturn        
        //  1538: aload_0        
        //  1539: getfield        eqw.a:Leqv;
        //  1542: getfield        eqv.ik:Latjj;
        //  1545: invokeinterface atjj.a:()Ljava/lang/Object;
        //  1550: checkcast       Lvup;
        //  1553: invokestatic    hxw.l:(Lvup;)Lhxv;
        //  1556: areturn        
        //  1557: aload_0        
        //  1558: getfield        eqw.a:Leqv;
        //  1561: getfield        eqv.d:Latjj;
        //  1564: invokeinterface atjj.a:()Ljava/lang/Object;
        //  1569: checkcast       Landroid/content/SharedPreferences;
        //  1572: aload_0        
        //  1573: getfield        eqw.a:Leqv;
        //  1576: getfield        eqv.P:Latjj;
        //  1579: invokestatic    jcs.f:(Landroid/content/SharedPreferences;Latjj;)Ljgi;
        //  1582: areturn        
        //  1583: aload_0        
        //  1584: getfield        eqw.a:Leqv;
        //  1587: astore_2       
        //  1588: new             Ljgh;
        //  1591: dup            
        //  1592: aload_2        
        //  1593: getfield        eqv.a:Leqx;
        //  1596: getfield        eqx.by:Latjj;
        //  1599: aload_2        
        //  1600: getfield        eqv.ii:Latjj;
        //  1603: aload_2        
        //  1604: getfield        eqv.v:Latjj;
        //  1607: invokeinterface atjj.a:()Ljava/lang/Object;
        //  1612: checkcast       Larud;
        //  1615: aconst_null    
        //  1616: aconst_null    
        //  1617: invokespecial   jgh.<init>:(Latjj;Latjj;Larud;[B[B)V
        //  1620: areturn        
        //  1621: new             Lvte;
        //  1624: dup            
        //  1625: aload_0        
        //  1626: getfield        eqw.a:Leqv;
        //  1629: getfield        eqv.eQ:Latjj;
        //  1632: invokeinterface atjj.a:()Ljava/lang/Object;
        //  1637: checkcast       Ladcr;
        //  1640: aload_0        
        //  1641: getfield        eqw.a:Leqv;
        //  1644: getfield        eqv.aC:Latjj;
        //  1647: invokeinterface atjj.a:()Ljava/lang/Object;
        //  1652: checkcast       Lzki;
        //  1655: aload_0        
        //  1656: getfield        eqw.a:Leqv;
        //  1659: invokevirtual   eqv.ad:()Ltgw;
        //  1662: aload_0        
        //  1663: getfield        eqw.a:Leqv;
        //  1666: getfield        eqv.w:Latjj;
        //  1669: invokeinterface atjj.a:()Ljava/lang/Object;
        //  1674: checkcast       Luyf;
        //  1677: aload_0        
        //  1678: getfield        eqw.a:Leqv;
        //  1681: getfield        eqv.a:Leqx;
        //  1684: invokevirtual   eqx.Y:()Ljava/util/Set;
        //  1687: aload_0        
        //  1688: getfield        eqw.a:Leqv;
        //  1691: getfield        eqv.a:Leqx;
        //  1694: invokevirtual   eqx.s:()Lvtb;
        //  1697: aload_0        
        //  1698: getfield        eqw.a:Leqv;
        //  1701: getfield        eqv.h:Latjj;
        //  1704: invokeinterface atjj.a:()Ljava/lang/Object;
        //  1709: checkcast       Ltdz;
        //  1712: aload_0        
        //  1713: getfield        eqw.a:Leqv;
        //  1716: getfield        eqv.v:Latjj;
        //  1719: invokeinterface atjj.a:()Ljava/lang/Object;
        //  1724: checkcast       Larud;
        //  1727: aload_0        
        //  1728: getfield        eqw.a:Leqv;
        //  1731: getfield        eqv.cW:Latjj;
        //  1734: invokeinterface atjj.a:()Ljava/lang/Object;
        //  1739: checkcast       Lafqr;
        //  1742: aconst_null    
        //  1743: aconst_null    
        //  1744: aconst_null    
        //  1745: aconst_null    
        //  1746: aconst_null    
        //  1747: aconst_null    
        //  1748: invokespecial   vte.<init>:(Ladcr;Lzki;Ltgw;Luyf;Ljava/util/Set;Lvtb;Ltdz;Larud;Lafqr;[B[B[B[B[B[B)V
        //  1751: areturn        
        //  1752: invokestatic    fcv.s:()Lavt;
        //  1755: areturn        
        //  1756: new             Ladcr;
        //  1759: dup            
        //  1760: aload_0        
        //  1761: getfield        eqw.a:Leqv;
        //  1764: getfield        eqv.r:Latjj;
        //  1767: invokeinterface atjj.a:()Ljava/lang/Object;
        //  1772: checkcast       Ljava/util/concurrent/Executor;
        //  1775: invokespecial   adcr.<init>:(Ljava/util/concurrent/Executor;)V
        //  1778: areturn        
        //  1779: aload_0        
        //  1780: getfield        eqw.a:Leqv;
        //  1783: getfield        eqv.c:Latjj;
        //  1786: invokeinterface atjj.a:()Ljava/lang/Object;
        //  1791: checkcast       Landroid/content/Context;
        //  1794: invokestatic    ewo.f:(Landroid/content/Context;)Landroid/provider/SearchRecentSuggestions;
        //  1797: areturn        
        //  1798: aload_0        
        //  1799: getfield        eqw.a:Leqv;
        //  1802: getfield        eqv.a:Leqx;
        //  1805: invokevirtual   eqx.hc:()Lauip;
        //  1808: aload_0        
        //  1809: getfield        eqw.a:Leqv;
        //  1812: getfield        eqv.a:Leqx;
        //  1815: getfield        eqx.g:Latjj;
        //  1818: invokeinterface atjj.a:()Ljava/lang/Object;
        //  1823: checkcast       Ladea;
        //  1826: invokestatic    jko.l:()Ljld;
        //  1829: aload_0        
        //  1830: getfield        eqw.a:Leqv;
        //  1833: getfield        eqv.a:Leqx;
        //  1836: invokevirtual   eqx.j:()Ljld;
        //  1839: invokestatic    ewo.W:(Lauip;Ladea;Ljld;Ljld;)Laded;
        //  1842: areturn        
        //  1843: aload_0        
        //  1844: getfield        eqw.a:Leqv;
        //  1847: getfield        eqv.a:Leqx;
        //  1850: getfield        eqx.o:Latjj;
        //  1853: invokeinterface atjj.a:()Ljava/lang/Object;
        //  1858: checkcast       Laeim;
        //  1861: aload_0        
        //  1862: getfield        eqw.a:Leqv;
        //  1865: getfield        eqv.aC:Latjj;
        //  1868: invokeinterface atjj.a:()Ljava/lang/Object;
        //  1873: checkcast       Lzki;
        //  1876: invokestatic    ewo.T:(Laeim;Lzki;)Ljla;
        //  1879: areturn        
        //  1880: aload_0        
        //  1881: getfield        eqw.a:Leqv;
        //  1884: getfield        eqv.nw:Latjj;
        //  1887: invokeinterface atjj.a:()Ljava/lang/Object;
        //  1892: checkcast       Lacwj;
        //  1895: invokestatic    ewo.i:(Lacwj;)Ljkz;
        //  1898: areturn        
        //  1899: aload_0        
        //  1900: getfield        eqw.a:Leqv;
        //  1903: getfield        eqv.r:Latjj;
        //  1906: invokeinterface atjj.a:()Ljava/lang/Object;
        //  1911: checkcast       Ljava/util/concurrent/Executor;
        //  1914: aload_0        
        //  1915: getfield        eqw.a:Leqv;
        //  1918: getfield        eqv.jz:Latjj;
        //  1921: invokeinterface atjj.a:()Ljava/lang/Object;
        //  1926: checkcast       Lacvy;
        //  1929: aload_0        
        //  1930: getfield        eqw.a:Leqv;
        //  1933: getfield        eqv.jA:Latjj;
        //  1936: invokeinterface atjj.a:()Ljava/lang/Object;
        //  1941: checkcast       Lagkw;
        //  1944: aload_0        
        //  1945: getfield        eqw.a:Leqv;
        //  1948: getfield        eqv.a:Leqx;
        //  1951: getfield        eqx.n:Latjj;
        //  1954: invokeinterface atjj.a:()Ljava/lang/Object;
        //  1959: checkcast       Ljkp;
        //  1962: invokestatic    ewo.P:(Ljava/util/concurrent/Executor;Lacvy;Lagkw;Ljkp;)Ljkx;
        //  1965: areturn        
        //  1966: aload_0        
        //  1967: getfield        eqw.a:Leqv;
        //  1970: getfield        eqv.fH:Latjj;
        //  1973: invokeinterface atjj.a:()Ljava/lang/Object;
        //  1978: checkcast       Lvjh;
        //  1981: aload_0        
        //  1982: getfield        eqw.a:Leqv;
        //  1985: getfield        eqv.eQ:Latjj;
        //  1988: invokeinterface atjj.a:()Ljava/lang/Object;
        //  1993: checkcast       Ladcr;
        //  1996: aload_0        
        //  1997: getfield        eqw.a:Leqv;
        //  2000: getfield        eqv.aC:Latjj;
        //  2003: invokeinterface atjj.a:()Ljava/lang/Object;
        //  2008: checkcast       Lzki;
        //  2011: aload_0        
        //  2012: getfield        eqw.a:Leqv;
        //  2015: getfield        eqv.fI:Latjj;
        //  2018: invokeinterface atjj.a:()Ljava/lang/Object;
        //  2023: checkcast       Ltgw;
        //  2026: invokestatic    vny.u:(Lvjh;Ladcr;Lzki;Ltgw;)Laddp;
        //  2029: areturn        
        //  2030: aload_0        
        //  2031: getfield        eqw.a:Leqv;
        //  2034: getfield        eqv.a:Leqx;
        //  2037: invokevirtual   eqx.hc:()Lauip;
        //  2040: astore_2       
        //  2041: aload_0        
        //  2042: getfield        eqw.a:Leqv;
        //  2045: getfield        eqv.a:Leqx;
        //  2048: getfield        eqx.g:Latjj;
        //  2051: invokeinterface atjj.a:()Ljava/lang/Object;
        //  2056: checkcast       Ladea;
        //  2059: astore          4
        //  2061: aload_0        
        //  2062: getfield        eqw.a:Leqv;
        //  2065: getfield        eqv.a:Leqx;
        //  2068: astore          5
        //  2070: aload_2        
        //  2071: aload           4
        //  2073: aload           5
        //  2075: invokevirtual   eqx.i:()Ljkr;
        //  2078: aload           5
        //  2080: invokevirtual   eqx.j:()Ljld;
        //  2083: invokestatic    ewo.V:(Lauip;Ladea;Ljkr;Ljld;)Laded;
        //  2086: areturn        
        //  2087: aload_0        
        //  2088: getfield        eqw.a:Leqv;
        //  2091: getfield        eqv.r:Latjj;
        //  2094: invokeinterface atjj.a:()Ljava/lang/Object;
        //  2099: checkcast       Ljava/util/concurrent/ScheduledExecutorService;
        //  2102: aload_0        
        //  2103: getfield        eqw.a:Leqv;
        //  2106: getfield        eqv.a:Leqx;
        //  2109: getfield        eqx.bo:Latjj;
        //  2112: invokeinterface atjj.a:()Ljava/lang/Object;
        //  2117: checkcast       Laded;
        //  2120: aload_0        
        //  2121: getfield        eqw.a:Leqv;
        //  2124: getfield        eqv.a:Leqx;
        //  2127: getfield        eqx.bp:Latjj;
        //  2130: invokeinterface atjj.a:()Ljava/lang/Object;
        //  2135: checkcast       Ljkx;
        //  2138: aload_0        
        //  2139: getfield        eqw.a:Leqv;
        //  2142: getfield        eqv.a:Leqx;
        //  2145: getfield        eqx.bq:Latjj;
        //  2148: invokeinterface atjj.a:()Ljava/lang/Object;
        //  2153: checkcast       Ljkz;
        //  2156: aload_0        
        //  2157: getfield        eqw.a:Leqv;
        //  2160: getfield        eqv.a:Leqx;
        //  2163: getfield        eqx.br:Latjj;
        //  2166: invokeinterface atjj.a:()Ljava/lang/Object;
        //  2171: checkcast       Ljla;
        //  2174: aload_0        
        //  2175: getfield        eqw.a:Leqv;
        //  2178: getfield        eqv.jz:Latjj;
        //  2181: invokeinterface atjj.a:()Ljava/lang/Object;
        //  2186: checkcast       Lacvy;
        //  2189: aload_0        
        //  2190: getfield        eqw.a:Leqv;
        //  2193: getfield        eqv.aC:Latjj;
        //  2196: invokeinterface atjj.a:()Ljava/lang/Object;
        //  2201: checkcast       Lzki;
        //  2204: invokestatic    ewo.h:(Ljava/util/concurrent/ScheduledExecutorService;Laded;Ljkx;Ljkz;Ljla;Lacvy;Lzki;)Ljkw;
        //  2207: areturn        
        //  2208: aload_0        
        //  2209: getfield        eqw.a:Leqv;
        //  2212: getfield        eqv.a:Leqx;
        //  2215: getfield        eqx.bs:Latjj;
        //  2218: invokeinterface atjj.a:()Ljava/lang/Object;
        //  2223: checkcast       Ljkw;
        //  2226: aload_0        
        //  2227: getfield        eqw.a:Leqv;
        //  2230: getfield        eqv.a:Leqx;
        //  2233: getfield        eqx.bt:Latjj;
        //  2236: invokeinterface atjj.a:()Ljava/lang/Object;
        //  2241: checkcast       Laded;
        //  2244: aload_0        
        //  2245: getfield        eqw.a:Leqv;
        //  2248: getfield        eqv.g:Latjj;
        //  2251: invokeinterface atjj.a:()Ljava/lang/Object;
        //  2256: checkcast       Ljava/util/concurrent/Executor;
        //  2259: aload_0        
        //  2260: getfield        eqw.a:Leqv;
        //  2263: getfield        eqv.r:Latjj;
        //  2266: invokeinterface atjj.a:()Ljava/lang/Object;
        //  2271: checkcast       Ljava/util/concurrent/Executor;
        //  2274: invokestatic    ewo.U:(Ljkw;Laded;Ljava/util/concurrent/Executor;Ljava/util/concurrent/Executor;)Lcom/google/android/apps/youtube/embeddedplayer/service/ui/preview/service/e;
        //  2277: areturn        
        //  2278: invokestatic    jko.p:()Lkgk;
        //  2281: areturn        
        //  2282: aload_0        
        //  2283: getfield        eqw.a:Leqv;
        //  2286: getfield        eqv.w:Latjj;
        //  2289: invokeinterface atjj.a:()Ljava/lang/Object;
        //  2294: checkcast       Luyf;
        //  2297: invokestatic    kgk.bn:(Luyf;)Lbx;
        //  2300: areturn        
        //  2301: aload_0        
        //  2302: getfield        eqw.a:Leqv;
        //  2305: getfield        eqv.c:Latjj;
        //  2308: invokeinterface atjj.a:()Ljava/lang/Object;
        //  2313: checkcast       Landroid/content/Context;
        //  2316: astore          6
        //  2318: aload_0        
        //  2319: getfield        eqw.a:Leqv;
        //  2322: getfield        eqv.r:Latjj;
        //  2325: invokeinterface atjj.a:()Ljava/lang/Object;
        //  2330: checkcast       Laftr;
        //  2333: astore          5
        //  2335: invokestatic    eqv.xk:()Ljava/lang/String;
        //  2338: astore          4
        //  2340: aload_0        
        //  2341: getfield        eqw.a:Leqv;
        //  2344: getfield        eqv.ai:Latjj;
        //  2347: invokeinterface atjj.a:()Ljava/lang/Object;
        //  2352: checkcast       Lqbo;
        //  2355: astore          7
        //  2357: aload_0        
        //  2358: getfield        eqw.a:Leqv;
        //  2361: getfield        eqv.y:Latjj;
        //  2364: invokeinterface atjj.a:()Ljava/lang/Object;
        //  2369: checkcast       Ltda;
        //  2372: astore_2       
        //  2373: aload           6
        //  2375: aload           5
        //  2377: aload           4
        //  2379: aload           7
        //  2381: invokestatic    actc.S:(Landroid/content/Context;Laftr;Ljava/lang/String;Lqbo;)Ltku;
        //  2384: areturn        
        //  2385: new             Lacsm;
        //  2388: dup            
        //  2389: aload_0        
        //  2390: getfield        eqw.a:Leqv;
        //  2393: getfield        eqv.a:Leqx;
        //  2396: getfield        eqx.bk:Latjj;
        //  2399: invokeinterface atjj.a:()Ljava/lang/Object;
        //  2404: checkcast       Ltku;
        //  2407: invokespecial   acsm.<init>:(Ltku;)V
        //  2410: areturn        
        //  2411: new             Lacxp;
        //  2414: dup            
        //  2415: invokespecial   acxp.<init>:()V
        //  2418: areturn        
        //  2419: aload_0        
        //  2420: getfield        eqw.a:Leqv;
        //  2423: getfield        eqv.e:Latjj;
        //  2426: invokeinterface atjj.a:()Ljava/lang/Object;
        //  2431: checkcast       Loas;
        //  2434: invokestatic    ewo.w:(Loas;)Lacwn;
        //  2437: areturn        
        //  2438: new             Lcom/google/android/apps/youtube/app/search/suggest/SuggestVideoStateSubscriber;
        //  2441: dup            
        //  2442: aload_0        
        //  2443: getfield        eqw.a:Leqv;
        //  2446: getfield        eqv.e:Latjj;
        //  2449: invokeinterface atjj.a:()Ljava/lang/Object;
        //  2454: checkcast       Loas;
        //  2457: aload_0        
        //  2458: getfield        eqw.a:Leqv;
        //  2461: getfield        eqv.bt:Latjj;
        //  2464: invokeinterface atjj.a:()Ljava/lang/Object;
        //  2469: checkcast       Labns;
        //  2472: invokespecial   com/google/android/apps/youtube/app/search/suggest/SuggestVideoStateSubscriber.<init>:(Loas;Labns;)V
        //  2475: areturn        
        //  2476: new             Labjm;
        //  2479: dup            
        //  2480: aload_0        
        //  2481: getfield        eqw.a:Leqv;
        //  2484: getfield        eqv.fH:Latjj;
        //  2487: invokeinterface atjj.a:()Ljava/lang/Object;
        //  2492: checkcast       Lvjh;
        //  2495: aload_0        
        //  2496: getfield        eqw.a:Leqv;
        //  2499: getfield        eqv.eQ:Latjj;
        //  2502: invokeinterface atjj.a:()Ljava/lang/Object;
        //  2507: checkcast       Ladcr;
        //  2510: aload_0        
        //  2511: getfield        eqw.a:Leqv;
        //  2514: getfield        eqv.aC:Latjj;
        //  2517: invokeinterface atjj.a:()Ljava/lang/Object;
        //  2522: checkcast       Lzki;
        //  2525: aload_0        
        //  2526: getfield        eqw.a:Leqv;
        //  2529: getfield        eqv.fI:Latjj;
        //  2532: invokeinterface atjj.a:()Ljava/lang/Object;
        //  2537: checkcast       Ltgw;
        //  2540: aconst_null    
        //  2541: aconst_null    
        //  2542: aconst_null    
        //  2543: aconst_null    
        //  2544: aconst_null    
        //  2545: aconst_null    
        //  2546: invokespecial   abjm.<init>:(Lvjh;Ladcr;Lzki;Ltgw;[B[B[B[B[B[B)V
        //  2549: areturn        
        //  2550: aload_0        
        //  2551: getfield        eqw.a:Leqv;
        //  2554: astore_2       
        //  2555: new             Lauip;
        //  2558: dup            
        //  2559: aload_2        
        //  2560: getfield        eqv.jh:Latjj;
        //  2563: aload_2        
        //  2564: getfield        eqv.ic:Latjj;
        //  2567: aload_2        
        //  2568: getfield        eqv.ew:Latjj;
        //  2571: aconst_null    
        //  2572: invokespecial   auip.<init>:(Latjj;Latjj;Latjj;[S)V
        //  2575: areturn        
        //  2576: aload_0        
        //  2577: getfield        eqw.a:Leqv;
        //  2580: astore_2       
        //  2581: aload_2        
        //  2582: getfield        eqv.cB:Latjj;
        //  2585: aload_2        
        //  2586: getfield        eqv.a:Leqx;
        //  2589: getfield        eqx.be:Latjj;
        //  2592: invokestatic    imu.d:(Latjj;Latjj;)Lioa;
        //  2595: areturn        
        //  2596: aload_0        
        //  2597: getfield        eqw.a:Leqv;
        //  2600: getfield        eqv.bp:Latjj;
        //  2603: invokeinterface atjj.a:()Ljava/lang/Object;
        //  2608: checkcast       Lvbq;
        //  2611: aload_0        
        //  2612: getfield        eqw.a:Leqv;
        //  2615: getfield        eqv.r:Latjj;
        //  2618: invokeinterface atjj.a:()Ljava/lang/Object;
        //  2623: checkcast       Ljava/util/concurrent/Executor;
        //  2626: aload_0        
        //  2627: getfield        eqw.a:Leqv;
        //  2630: getfield        eqv.jf:Latjj;
        //  2633: invokeinterface atjj.a:()Ljava/lang/Object;
        //  2638: checkcast       Luyi;
        //  2641: invokestatic    idf.c:(Lvbq;Ljava/util/concurrent/Executor;Luyi;)Licw;
        //  2644: areturn        
        //  2645: aload_0        
        //  2646: getfield        eqw.a:Leqv;
        //  2649: getfield        eqv.a:Leqx;
        //  2652: getfield        eqx.bc:Latjj;
        //  2655: invokestatic    idf.b:(Latjj;)Lida;
        //  2658: areturn        
        //  2659: aload_0        
        //  2660: getfield        eqw.a:Leqv;
        //  2663: getfield        eqv.fH:Latjj;
        //  2666: invokeinterface atjj.a:()Ljava/lang/Object;
        //  2671: checkcast       Lvjh;
        //  2674: astore          6
        //  2676: aload_0        
        //  2677: getfield        eqw.a:Leqv;
        //  2680: getfield        eqv.eQ:Latjj;
        //  2683: invokeinterface atjj.a:()Ljava/lang/Object;
        //  2688: checkcast       Ladcr;
        //  2691: astore          7
        //  2693: aload_0        
        //  2694: getfield        eqw.a:Leqv;
        //  2697: getfield        eqv.aC:Latjj;
        //  2700: invokeinterface atjj.a:()Ljava/lang/Object;
        //  2705: checkcast       Lzki;
        //  2708: astore_2       
        //  2709: aload_0        
        //  2710: getfield        eqw.a:Leqv;
        //  2713: getfield        eqv.fI:Latjj;
        //  2716: invokeinterface atjj.a:()Ljava/lang/Object;
        //  2721: checkcast       Ltgw;
        //  2724: astore          5
        //  2726: aload_0        
        //  2727: getfield        eqw.a:Leqv;
        //  2730: getfield        eqv.r:Latjj;
        //  2733: invokeinterface atjj.a:()Ljava/lang/Object;
        //  2738: checkcast       Ljava/util/concurrent/ScheduledExecutorService;
        //  2741: astore          4
        //  2743: new             Laddp;
        //  2746: dup            
        //  2747: aload           6
        //  2749: aload           7
        //  2751: aload_2        
        //  2752: aload           5
        //  2754: aconst_null    
        //  2755: aconst_null    
        //  2756: aconst_null    
        //  2757: aconst_null    
        //  2758: aconst_null    
        //  2759: aconst_null    
        //  2760: invokespecial   addp.<init>:(Lvjh;Ladcr;Lzki;Ltgw;[B[B[B[B[B[B)V
        //  2763: areturn        
        //  2764: aload_0        
        //  2765: getfield        eqw.a:Leqv;
        //  2768: getfield        eqv.r:Latjj;
        //  2771: invokeinterface atjj.a:()Ljava/lang/Object;
        //  2776: checkcast       Ljava/util/concurrent/ScheduledExecutorService;
        //  2779: astore          5
        //  2781: aload_0        
        //  2782: getfield        eqw.a:Leqv;
        //  2785: getfield        eqv.bp:Latjj;
        //  2788: invokeinterface atjj.a:()Ljava/lang/Object;
        //  2793: checkcast       Lvbq;
        //  2796: astore          4
        //  2798: aload_0        
        //  2799: getfield        eqw.a:Leqv;
        //  2802: astore_2       
        //  2803: new             Laadb;
        //  2806: dup            
        //  2807: aload           5
        //  2809: aload           4
        //  2811: aload_2        
        //  2812: getfield        eqv.es:Latjj;
        //  2815: aload_2        
        //  2816: getfield        eqv.a:Leqx;
        //  2819: getfield        eqx.aZ:Latjj;
        //  2822: aload_2        
        //  2823: getfield        eqv.el:Latjj;
        //  2826: invokespecial   aadb.<init>:(Ljava/util/concurrent/ScheduledExecutorService;Lvbq;Latjj;Latjj;Latjj;)V
        //  2829: astore_2       
        //  2830: aload_2        
        //  2831: getfield        aadb.b:Lvbq;
        //  2834: invokeinterface vbq.b:()Lvbp;
        //  2839: ldc_w           Lapll;.class
        //  2842: invokeinterface vbp.g:(Ljava/lang/Class;)Lashe;
        //  2847: aload_2        
        //  2848: getfield        aadb.a:Ljava/util/concurrent/ScheduledExecutorService;
        //  2851: invokestatic    atio.b:(Ljava/util/concurrent/Executor;)Lasho;
        //  2854: invokevirtual   ashe.aa:(Lasho;)Lashe;
        //  2857: new             Lzsv;
        //  2860: dup            
        //  2861: aload_2        
        //  2862: bipush          12
        //  2864: invokespecial   zsv.<init>:(Laadb;I)V
        //  2867: invokevirtual   ashe.aB:(Lasix;)Lasic;
        //  2870: pop            
        //  2871: aload_2        
        //  2872: areturn        
        //  2873: aload_0        
        //  2874: getfield        eqw.a:Leqv;
        //  2877: getfield        eqv.P:Latjj;
        //  2880: invokeinterface atjj.a:()Ljava/lang/Object;
        //  2885: checkcast       Lthh;
        //  2888: astore          4
        //  2890: aload_0        
        //  2891: getfield        eqw.a:Leqv;
        //  2894: getfield        eqv.e:Latjj;
        //  2897: invokeinterface atjj.a:()Ljava/lang/Object;
        //  2902: checkcast       Loas;
        //  2905: astore          6
        //  2907: aload_0        
        //  2908: getfield        eqw.a:Leqv;
        //  2911: getfield        eqv.jn:Latjj;
        //  2914: invokeinterface atjj.a:()Ljava/lang/Object;
        //  2919: checkcast       Lfml;
        //  2922: astore          7
        //  2924: aload_0        
        //  2925: getfield        eqw.a:Leqv;
        //  2928: getfield        eqv.ep:Latjj;
        //  2931: invokeinterface atjj.a:()Ljava/lang/Object;
        //  2936: checkcast       Lalm;
        //  2939: astore          5
        //  2941: aload_0        
        //  2942: getfield        eqw.a:Leqv;
        //  2945: astore_2       
        //  2946: aload           4
        //  2948: aload           6
        //  2950: aload           7
        //  2952: aload           5
        //  2954: aload_2        
        //  2955: getfield        eqv.el:Latjj;
        //  2958: aload_2        
        //  2959: getfield        eqv.a:Leqx;
        //  2962: getfield        eqx.ba:Latjj;
        //  2965: invokestatic    ilv.j:(Lthh;Loas;Lfml;Lalm;Latjj;Latjj;)Limo;
        //  2968: areturn        
        //  2969: aload_0        
        //  2970: getfield        eqw.a:Leqv;
        //  2973: getfield        eqv.jn:Latjj;
        //  2976: invokeinterface atjj.a:()Ljava/lang/Object;
        //  2981: checkcast       Lfml;
        //  2984: astore          5
        //  2986: aload_0        
        //  2987: getfield        eqw.a:Leqv;
        //  2990: astore_2       
        //  2991: aload           5
        //  2993: aload_2        
        //  2994: getfield        eqv.el:Latjj;
        //  2997: aload_2        
        //  2998: getfield        eqv.g:Latjj;
        //  3001: invokeinterface atjj.a:()Ljava/lang/Object;
        //  3006: checkcast       Ljava/util/concurrent/Executor;
        //  3009: aload_0        
        //  3010: getfield        eqw.a:Leqv;
        //  3013: getfield        eqv.r:Latjj;
        //  3016: invokeinterface atjj.a:()Ljava/lang/Object;
        //  3021: checkcast       Ljava/util/concurrent/ExecutorService;
        //  3024: invokestatic    ilv.m:(Lfml;Latjj;Ljava/util/concurrent/Executor;Ljava/util/concurrent/ExecutorService;)Lcom/google/android/apps/youtube/embeddedplayer/service/hostappverification/e;
        //  3027: areturn        
        //  3028: aload_0        
        //  3029: getfield        eqw.a:Leqv;
        //  3032: getfield        eqv.kv:Latjj;
        //  3035: invokeinterface atjj.a:()Ljava/lang/Object;
        //  3040: checkcast       Laaam;
        //  3043: invokestatic    ihg.n:(Laaam;)Lhyr;
        //  3046: areturn        
        //  3047: aload_0        
        //  3048: getfield        eqw.a:Leqv;
        //  3051: getfield        eqv.P:Latjj;
        //  3054: invokeinterface atjj.a:()Ljava/lang/Object;
        //  3059: checkcast       Lthh;
        //  3062: aload_0        
        //  3063: getfield        eqw.a:Leqv;
        //  3066: getfield        eqv.e:Latjj;
        //  3069: invokeinterface atjj.a:()Ljava/lang/Object;
        //  3074: checkcast       Loas;
        //  3077: aload_0        
        //  3078: getfield        eqw.a:Leqv;
        //  3081: getfield        eqv.ep:Latjj;
        //  3084: invokeinterface atjj.a:()Ljava/lang/Object;
        //  3089: checkcast       Lalm;
        //  3092: aload_0        
        //  3093: getfield        eqw.a:Leqv;
        //  3096: getfield        eqv.a:Leqx;
        //  3099: getfield        eqx.aW:Latjj;
        //  3102: invokeinterface atjj.a:()Ljava/lang/Object;
        //  3107: checkcast       Lhyr;
        //  3110: invokestatic    ikp.u:(Lthh;Loas;Lalm;Lhyr;)Liko;
        //  3113: areturn        
        //  3114: aload_0        
        //  3115: getfield        eqw.a:Leqv;
        //  3118: getfield        eqv.P:Latjj;
        //  3121: invokeinterface atjj.a:()Ljava/lang/Object;
        //  3126: checkcast       Lthh;
        //  3129: astore          4
        //  3131: aload_0        
        //  3132: getfield        eqw.a:Leqv;
        //  3135: getfield        eqv.lz:Latjj;
        //  3138: invokeinterface atjj.a:()Ljava/lang/Object;
        //  3143: checkcast       Lfmd;
        //  3146: astore_2       
        //  3147: aload_0        
        //  3148: getfield        eqw.a:Leqv;
        //  3151: getfield        eqv.ky:Latjj;
        //  3154: invokeinterface atjj.a:()Ljava/lang/Object;
        //  3159: checkcast       Lyzf;
        //  3162: astore          5
        //  3164: aload_0        
        //  3165: getfield        eqw.a:Leqv;
        //  3168: astore          6
        //  3170: aload           4
        //  3172: aload_2        
        //  3173: aload           5
        //  3175: aload           6
        //  3177: getfield        eqv.es:Latjj;
        //  3180: aload           6
        //  3182: getfield        eqv.eq:Latjj;
        //  3185: invokeinterface atjj.a:()Ljava/lang/Object;
        //  3190: checkcast       Laaha;
        //  3193: invokestatic    ilv.k:(Lthh;Lfmd;Lyzf;Latjj;Laaha;)Line;
        //  3196: areturn        
        //  3197: aload_0        
        //  3198: getfield        eqw.a:Leqv;
        //  3201: getfield        eqv.P:Latjj;
        //  3204: invokeinterface atjj.a:()Ljava/lang/Object;
        //  3209: checkcast       Lthh;
        //  3212: astore          6
        //  3214: aload_0        
        //  3215: getfield        eqw.a:Leqv;
        //  3218: getfield        eqv.lz:Latjj;
        //  3221: invokeinterface atjj.a:()Ljava/lang/Object;
        //  3226: checkcast       Lfmd;
        //  3229: astore_2       
        //  3230: aload_0        
        //  3231: getfield        eqw.a:Leqv;
        //  3234: getfield        eqv.ky:Latjj;
        //  3237: invokeinterface atjj.a:()Ljava/lang/Object;
        //  3242: checkcast       Lyzf;
        //  3245: astore          4
        //  3247: aload_0        
        //  3248: getfield        eqw.a:Leqv;
        //  3251: astore          5
        //  3253: aload           6
        //  3255: aload_2        
        //  3256: aload           4
        //  3258: aload           5
        //  3260: getfield        eqv.es:Latjj;
        //  3263: aload           5
        //  3265: getfield        eqv.eq:Latjj;
        //  3268: invokeinterface atjj.a:()Ljava/lang/Object;
        //  3273: checkcast       Laaha;
        //  3276: invokestatic    imu.n:(Lthh;Lfmd;Lyzf;Latjj;Laaha;)Line;
        //  3279: areturn        
        //  3280: aload_0        
        //  3281: getfield        eqw.a:Leqv;
        //  3284: getfield        eqv.c:Latjj;
        //  3287: invokeinterface atjj.a:()Ljava/lang/Object;
        //  3292: checkcast       Landroid/content/Context;
        //  3295: aload_0        
        //  3296: getfield        eqw.a:Leqv;
        //  3299: getfield        eqv.a:Leqx;
        //  3302: getfield        eqx.aS:Latjj;
        //  3305: invokeinterface atjj.a:()Ljava/lang/Object;
        //  3310: aload_0        
        //  3311: getfield        eqw.a:Leqv;
        //  3314: getfield        eqv.a:Leqx;
        //  3317: getfield        eqx.aT:Latjj;
        //  3320: invokeinterface atjj.a:()Ljava/lang/Object;
        //  3325: aload_0        
        //  3326: getfield        eqw.a:Leqv;
        //  3329: getfield        eqv.e:Latjj;
        //  3332: invokeinterface atjj.a:()Ljava/lang/Object;
        //  3337: checkcast       Loas;
        //  3340: invokestatic    ilv.n:(Landroid/content/Context;Ljava/lang/Object;Ljava/lang/Object;Loas;)Laja;
        //  3343: areturn        
        //  3344: aload_0        
        //  3345: getfield        eqw.a:Leqv;
        //  3348: getfield        eqv.c:Latjj;
        //  3351: invokeinterface atjj.a:()Ljava/lang/Object;
        //  3356: checkcast       Landroid/content/Context;
        //  3359: astore_2       
        //  3360: aload_0        
        //  3361: getfield        eqw.a:Leqv;
        //  3364: astore          5
        //  3366: aload_2        
        //  3367: aload           5
        //  3369: getfield        eqv.el:Latjj;
        //  3372: aload           5
        //  3374: getfield        eqv.jn:Latjj;
        //  3377: aload           5
        //  3379: getfield        eqv.a:Leqx;
        //  3382: getfield        eqx.aU:Latjj;
        //  3385: invokeinterface atjj.a:()Ljava/lang/Object;
        //  3390: checkcast       Laja;
        //  3393: aload_0        
        //  3394: getfield        eqw.a:Leqv;
        //  3397: getfield        eqv.jl:Latjj;
        //  3400: invokeinterface atjj.a:()Ljava/lang/Object;
        //  3405: checkcast       Lflo;
        //  3408: aload_0        
        //  3409: getfield        eqw.a:Leqv;
        //  3412: invokevirtual   eqv.Ar:()Lfzo;
        //  3415: aload_0        
        //  3416: getfield        eqw.a:Leqv;
        //  3419: getfield        eqv.lA:Latjj;
        //  3422: invokeinterface atjj.a:()Ljava/lang/Object;
        //  3427: checkcast       Lflg;
        //  3430: aload_0        
        //  3431: getfield        eqw.a:Leqv;
        //  3434: getfield        eqv.jf:Latjj;
        //  3437: invokeinterface atjj.a:()Ljava/lang/Object;
        //  3442: checkcast       Luyi;
        //  3445: invokestatic    ikp.v:(Landroid/content/Context;Latjj;Latjj;Laja;Lflo;Lfzo;Lflg;Luyi;)Lijz;
        //  3448: areturn        
        //  3449: aload_0        
        //  3450: getfield        eqw.a:Leqv;
        //  3453: getfield        eqv.ej:Latjj;
        //  3456: invokeinterface atjj.a:()Ljava/lang/Object;
        //  3461: checkcast       Laamd;
        //  3464: astore_2       
        //  3465: aload_0        
        //  3466: getfield        eqw.a:Leqv;
        //  3469: astore          5
        //  3471: aload_2        
        //  3472: aload           5
        //  3474: getfield        eqv.el:Latjj;
        //  3477: aload           5
        //  3479: getfield        eqv.kr:Latjj;
        //  3482: aload           5
        //  3484: getfield        eqv.em:Latjj;
        //  3487: aload           5
        //  3489: getfield        eqv.dJ:Latjj;
        //  3492: aload           5
        //  3494: getfield        eqv.e:Latjj;
        //  3497: invokeinterface atjj.a:()Ljava/lang/Object;
        //  3502: checkcast       Loas;
        //  3505: aload_0        
        //  3506: getfield        eqw.a:Leqv;
        //  3509: getfield        eqv.r:Latjj;
        //  3512: invokeinterface atjj.a:()Ljava/lang/Object;
        //  3517: checkcast       Ljava/util/concurrent/ExecutorService;
        //  3520: aload_0        
        //  3521: getfield        eqw.a:Leqv;
        //  3524: getfield        eqv.kv:Latjj;
        //  3527: invokeinterface atjj.a:()Ljava/lang/Object;
        //  3532: checkcast       Laaam;
        //  3535: aload_0        
        //  3536: getfield        eqw.a:Leqv;
        //  3539: getfield        eqv.h:Latjj;
        //  3542: invokeinterface atjj.a:()Ljava/lang/Object;
        //  3547: checkcast       Ltdz;
        //  3550: invokestatic    ilv.i:(Laamd;Latjj;Latjj;Latjj;Latjj;Loas;Ljava/util/concurrent/ExecutorService;Laaam;Ltdz;)Llfy;
        //  3553: areturn        
        //  3554: aload_0        
        //  3555: getfield        eqw.a:Leqv;
        //  3558: getfield        eqv.c:Latjj;
        //  3561: invokeinterface atjj.a:()Ljava/lang/Object;
        //  3566: checkcast       Landroid/content/Context;
        //  3569: aload_0        
        //  3570: getfield        eqw.a:Leqv;
        //  3573: getfield        eqv.ai:Latjj;
        //  3576: invokeinterface atjj.a:()Ljava/lang/Object;
        //  3581: checkcast       Lqbo;
        //  3584: invokestatic    jyg.n:(Landroid/content/Context;Lqbo;)Laagm;
        //  3587: areturn        
        //  3588: aload_0        
        //  3589: getfield        eqw.a:Leqv;
        //  3592: getfield        eqv.a:Leqx;
        //  3595: getfield        eqx.aO:Latjj;
        //  3598: invokeinterface atjj.a:()Ljava/lang/Object;
        //  3603: checkcast       Laagm;
        //  3606: invokestatic    frh.q:(Laagm;)Lcxz;
        //  3609: areturn        
        //  3610: new             Ladcf;
        //  3613: dup            
        //  3614: invokespecial   adcf.<init>:()V
        //  3617: areturn        
        //  3618: aload_0        
        //  3619: getfield        eqw.a:Leqv;
        //  3622: getfield        eqv.c:Latjj;
        //  3625: invokeinterface atjj.a:()Ljava/lang/Object;
        //  3630: checkcast       Landroid/content/Context;
        //  3633: astore          4
        //  3635: aload_0        
        //  3636: getfield        eqw.a:Leqv;
        //  3639: getfield        eqv.r:Latjj;
        //  3642: invokeinterface atjj.a:()Ljava/lang/Object;
        //  3647: checkcast       Ljava/util/concurrent/Executor;
        //  3650: astore_2       
        //  3651: aload_0        
        //  3652: getfield        eqw.a:Leqv;
        //  3655: getfield        eqv.a:Leqx;
        //  3658: getfield        eqx.aM:Latjj;
        //  3661: astore          5
        //  3663: aload           4
        //  3665: invokevirtual   android/content/Context.getFilesDir:()Ljava/io/File;
        //  3668: astore          4
        //  3670: aload           4
        //  3672: ifnonnull       3689
        //  3675: aload           5
        //  3677: invokeinterface atjj.a:()Ljava/lang/Object;
        //  3682: checkcast       Ladcg;
        //  3685: astore_2       
        //  3686: goto            3763
        //  3689: aload           4
        //  3691: invokevirtual   java/io/File.getAbsolutePath:()Ljava/lang/String;
        //  3694: astore          4
        //  3696: getstatic       java/io/File.separator:Ljava/lang/String;
        //  3699: astore          5
        //  3701: new             Ljava/lang/StringBuilder;
        //  3704: dup            
        //  3705: invokespecial   java/lang/StringBuilder.<init>:()V
        //  3708: astore          6
        //  3710: aload           6
        //  3712: aload           4
        //  3714: invokevirtual   java/lang/StringBuilder.append:(Ljava/lang/String;)Ljava/lang/StringBuilder;
        //  3717: pop            
        //  3718: aload           6
        //  3720: aload           5
        //  3722: invokevirtual   java/lang/StringBuilder.append:(Ljava/lang/String;)Ljava/lang/StringBuilder;
        //  3725: pop            
        //  3726: aload           6
        //  3728: ldc_w           "storage"
        //  3731: invokevirtual   java/lang/StringBuilder.append:(Ljava/lang/String;)Ljava/lang/StringBuilder;
        //  3734: pop            
        //  3735: new             Ladce;
        //  3738: dup            
        //  3739: aload           6
        //  3741: invokevirtual   java/lang/StringBuilder.toString:()Ljava/lang/String;
        //  3744: aload_2        
        //  3745: invokespecial   adce.<init>:(Ljava/lang/String;Ljava/util/concurrent/Executor;)V
        //  3748: astore_2       
        //  3749: aload_2        
        //  3750: new             Lysm;
        //  3753: dup            
        //  3754: aload_2        
        //  3755: bipush          19
        //  3757: invokespecial   ysm.<init>:(Ladce;I)V
        //  3760: invokevirtual   adce.e:(Laeyr;)V
        //  3763: aload_2        
        //  3764: invokevirtual   java/lang/Object.getClass:()Ljava/lang/Class;
        //  3767: pop            
        //  3768: aload_2        
        //  3769: areturn        
        //  3770: aload_0        
        //  3771: getfield        eqw.a:Leqv;
        //  3774: getfield        eqv.a:Leqx;
        //  3777: getfield        eqx.aN:Latjj;
        //  3780: invokeinterface atjj.a:()Ljava/lang/Object;
        //  3785: checkcast       Ladcg;
        //  3788: aload_0        
        //  3789: getfield        eqw.a:Leqv;
        //  3792: getfield        eqv.aC:Latjj;
        //  3795: invokeinterface atjj.a:()Ljava/lang/Object;
        //  3800: checkcast       Lzki;
        //  3803: aload_0        
        //  3804: getfield        eqw.a:Leqv;
        //  3807: getfield        eqv.jq:Latjj;
        //  3810: invokeinterface atjj.a:()Ljava/lang/Object;
        //  3815: checkcast       Lvup;
        //  3818: aload_0        
        //  3819: getfield        eqw.a:Leqv;
        //  3822: getfield        eqv.a:Leqx;
        //  3825: getfield        eqx.aP:Latjj;
        //  3828: invokeinterface atjj.a:()Ljava/lang/Object;
        //  3833: checkcast       Lcxz;
        //  3836: invokestatic    frh.t:(Ladcg;Lzki;Lvup;Lcxz;)Lhyc;
        //  3839: areturn        
        //  3840: new             Lrhz;
        //  3843: dup            
        //  3844: invokespecial   rhz.<init>:()V
        //  3847: areturn        
        //  3848: new             Lrif;
        //  3851: dup            
        //  3852: aload_0        
        //  3853: getfield        eqw.a:Leqv;
        //  3856: getfield        eqv.c:Latjj;
        //  3859: invokeinterface atjj.a:()Ljava/lang/Object;
        //  3864: checkcast       Landroid/content/Context;
        //  3867: invokespecial   rif.<init>:(Landroid/content/Context;)V
        //  3870: areturn        
        //  3871: new             Lbx;
        //  3874: dup            
        //  3875: aconst_null    
        //  3876: aconst_null    
        //  3877: invokespecial   bx.<init>:([C[C)V
        //  3880: areturn        
        //  3881: new             Lbx;
        //  3884: dup            
        //  3885: aconst_null    
        //  3886: aconst_null    
        //  3887: aconst_null    
        //  3888: invokespecial   bx.<init>:([B[C[C)V
        //  3891: areturn        
        //  3892: new             Lmck;
        //  3895: dup            
        //  3896: aconst_null    
        //  3897: aconst_null    
        //  3898: aconst_null    
        //  3899: invokespecial   mck.<init>:([B[B[C)V
        //  3902: areturn        
        //  3903: new             Lmck;
        //  3906: dup            
        //  3907: aconst_null    
        //  3908: aconst_null    
        //  3909: invokespecial   mck.<init>:([C[B)V
        //  3912: areturn        
        //  3913: aload_0        
        //  3914: getfield        eqw.a:Leqv;
        //  3917: getfield        eqv.fH:Latjj;
        //  3920: invokeinterface atjj.a:()Ljava/lang/Object;
        //  3925: checkcast       Lvjh;
        //  3928: astore_2       
        //  3929: aload_0        
        //  3930: getfield        eqw.a:Leqv;
        //  3933: getfield        eqv.eQ:Latjj;
        //  3936: invokeinterface atjj.a:()Ljava/lang/Object;
        //  3941: checkcast       Ladcr;
        //  3944: astore          7
        //  3946: aload_0        
        //  3947: getfield        eqw.a:Leqv;
        //  3950: getfield        eqv.aC:Latjj;
        //  3953: invokeinterface atjj.a:()Ljava/lang/Object;
        //  3958: checkcast       Lzki;
        //  3961: astore          4
        //  3963: aload_0        
        //  3964: getfield        eqw.a:Leqv;
        //  3967: getfield        eqv.fI:Latjj;
        //  3970: invokeinterface atjj.a:()Ljava/lang/Object;
        //  3975: checkcast       Ltgw;
        //  3978: astore          6
        //  3980: aload_0        
        //  3981: getfield        eqw.a:Leqv;
        //  3984: getfield        eqv.r:Latjj;
        //  3987: invokeinterface atjj.a:()Ljava/lang/Object;
        //  3992: checkcast       Ljava/util/concurrent/Executor;
        //  3995: astore          5
        //  3997: new             Lvsc;
        //  4000: dup            
        //  4001: aload_2        
        //  4002: aload           7
        //  4004: aload           4
        //  4006: aload           6
        //  4008: aconst_null    
        //  4009: aconst_null    
        //  4010: aconst_null    
        //  4011: aconst_null    
        //  4012: aconst_null    
        //  4013: aconst_null    
        //  4014: invokespecial   vsc.<init>:(Lvjh;Ladcr;Lzki;Ltgw;[B[B[B[B[B[B)V
        //  4017: areturn        
        //  4018: aload_0        
        //  4019: getfield        eqw.a:Leqv;
        //  4022: getfield        eqv.cz:Latjj;
        //  4025: invokeinterface atjj.a:()Ljava/lang/Object;
        //  4030: checkcast       Ljava/lang/Boolean;
        //  4033: invokevirtual   java/lang/Boolean.booleanValue:()Z
        //  4036: istore_3       
        //  4037: aload_0        
        //  4038: getfield        eqw.a:Leqv;
        //  4041: getfield        eqv.a:Leqx;
        //  4044: getfield        eqx.aj:Latjj;
        //  4047: invokestatic    arjc.b:(Latjj;)Larhr;
        //  4050: astore          4
        //  4052: aload_0        
        //  4053: getfield        eqw.a:Leqv;
        //  4056: getfield        eqv.cE:Latjj;
        //  4059: invokestatic    arjc.b:(Latjj;)Larhr;
        //  4062: astore_2       
        //  4063: aload_0        
        //  4064: getfield        eqw.a:Leqv;
        //  4067: getfield        eqv.a:Leqx;
        //  4070: getfield        eqx.ak:Latjj;
        //  4073: invokestatic    arjc.b:(Latjj;)Larhr;
        //  4076: astore          5
        //  4078: iload_3        
        //  4079: aload           4
        //  4081: aload_2        
        //  4082: aload_0        
        //  4083: getfield        eqw.a:Leqv;
        //  4086: getfield        eqv.E:Latjj;
        //  4089: invokestatic    arjc.b:(Latjj;)Larhr;
        //  4092: aload           5
        //  4094: invokestatic    aaja.z:(ZLarhr;Larhr;Larhr;Larhr;)Losx;
        //  4097: areturn        
        //  4098: new             Lrng;
        //  4101: dup            
        //  4102: aload_0        
        //  4103: getfield        eqw.a:Leqv;
        //  4106: getfield        eqv.mb:Latjj;
        //  4109: invokeinterface atjj.a:()Ljava/lang/Object;
        //  4114: checkcast       Lzal;
        //  4117: aload_0        
        //  4118: getfield        eqw.a:Leqv;
        //  4121: getfield        eqv.lE:Latjj;
        //  4124: invokeinterface atjj.a:()Ljava/lang/Object;
        //  4129: checkcast       Lqcv;
        //  4132: aload_0        
        //  4133: getfield        eqw.a:Leqv;
        //  4136: getfield        eqv.c:Latjj;
        //  4139: invokeinterface atjj.a:()Ljava/lang/Object;
        //  4144: checkcast       Landroid/content/Context;
        //  4147: aload_0        
        //  4148: getfield        eqw.a:Leqv;
        //  4151: invokevirtual   eqv.eh:()Ljava/util/Set;
        //  4154: aload_0        
        //  4155: getfield        eqw.a:Leqv;
        //  4158: invokevirtual   eqv.ei:()Ljava/util/Set;
        //  4161: aload_0        
        //  4162: getfield        eqw.a:Leqv;
        //  4165: invokevirtual   eqv.ef:()Ljava/util/Set;
        //  4168: aload_0        
        //  4169: getfield        eqw.a:Leqv;
        //  4172: invokevirtual   eqv.eg:()Ljava/util/Set;
        //  4175: aload_0        
        //  4176: getfield        eqw.a:Leqv;
        //  4179: invokevirtual   eqv.ed:()Ljava/util/Set;
        //  4182: aload_0        
        //  4183: getfield        eqw.a:Leqv;
        //  4186: invokevirtual   eqv.ee:()Ljava/util/Set;
        //  4189: aload_0        
        //  4190: getfield        eqw.a:Leqv;
        //  4193: getfield        eqv.nq:Latjj;
        //  4196: invokeinterface atjj.a:()Ljava/lang/Object;
        //  4201: checkcast       Lafcr;
        //  4204: aload_0        
        //  4205: getfield        eqw.a:Leqv;
        //  4208: getfield        eqv.nr:Latjj;
        //  4211: invokeinterface atjj.a:()Ljava/lang/Object;
        //  4216: checkcast       Lafcr;
        //  4219: aload_0        
        //  4220: getfield        eqw.a:Leqv;
        //  4223: getfield        eqv.v:Latjj;
        //  4226: invokeinterface atjj.a:()Ljava/lang/Object;
        //  4231: checkcast       Larud;
        //  4234: aconst_null    
        //  4235: aconst_null    
        //  4236: aconst_null    
        //  4237: aconst_null    
        //  4238: invokespecial   rng.<init>:(Lzal;Lqcv;Landroid/content/Context;Ljava/util/Set;Ljava/util/Set;Ljava/util/Set;Ljava/util/Set;Ljava/util/Set;Ljava/util/Set;Lafcr;Lafcr;Larud;[B[B[B[B)V
        //  4241: areturn        
        //  4242: new             Lvtr;
        //  4245: dup            
        //  4246: aload_0        
        //  4247: getfield        eqw.a:Leqv;
        //  4250: getfield        eqv.fH:Latjj;
        //  4253: invokeinterface atjj.a:()Ljava/lang/Object;
        //  4258: checkcast       Lvjh;
        //  4261: aload_0        
        //  4262: getfield        eqw.a:Leqv;
        //  4265: getfield        eqv.eQ:Latjj;
        //  4268: invokeinterface atjj.a:()Ljava/lang/Object;
        //  4273: checkcast       Ladcr;
        //  4276: aload_0        
        //  4277: getfield        eqw.a:Leqv;
        //  4280: getfield        eqv.aC:Latjj;
        //  4283: invokeinterface atjj.a:()Ljava/lang/Object;
        //  4288: checkcast       Lzki;
        //  4291: aload_0        
        //  4292: getfield        eqw.a:Leqv;
        //  4295: getfield        eqv.dC:Latjj;
        //  4298: invokeinterface atjj.a:()Ljava/lang/Object;
        //  4303: checkcast       Ltgw;
        //  4306: aconst_null    
        //  4307: aconst_null    
        //  4308: aconst_null    
        //  4309: aconst_null    
        //  4310: aconst_null    
        //  4311: aconst_null    
        //  4312: invokespecial   vtr.<init>:(Lvjh;Ladcr;Lzki;Ltgw;[B[B[B[B[B[B)V
        //  4315: areturn        
        //  4316: invokestatic    atig.aD:()Latig;
        //  4319: invokevirtual   atie.aK:()Latie;
        //  4322: areturn        
        //  4323: aload_0        
        //  4324: getfield        eqw.a:Leqv;
        //  4327: getfield        eqv.a:Leqx;
        //  4330: getfield        eqx.aB:Latjj;
        //  4333: invokeinterface atjj.a:()Ljava/lang/Object;
        //  4338: checkcast       Latie;
        //  4341: invokevirtual   asgt.J:()Lasgt;
        //  4344: areturn        
        //  4345: aload_0        
        //  4346: getfield        eqw.a:Leqv;
        //  4349: getfield        eqv.c:Latjj;
        //  4352: invokeinterface atjj.a:()Ljava/lang/Object;
        //  4357: checkcast       Landroid/content/Context;
        //  4360: aload_0        
        //  4361: getfield        eqw.a:Leqv;
        //  4364: getfield        eqv.ai:Latjj;
        //  4367: invokeinterface atjj.a:()Ljava/lang/Object;
        //  4372: checkcast       Lqbo;
        //  4375: invokestatic    hxd.i:(Landroid/content/Context;Lqbo;)Laagm;
        //  4378: areturn        
        //  4379: ldc_w           "provideExtensionRegistry"
        //  4382: invokestatic    aesw.o:(Ljava/lang/String;)Laere;
        //  4385: astore          5
        //  4387: invokestatic    com/google/protobuf/ExtensionRegistryLite.getGeneratedRegistry:()Lcom/google/protobuf/ExtensionRegistryLite;
        //  4390: astore_2       
        //  4391: aload           5
        //  4393: invokevirtual   aere.close:()V
        //  4396: aload_2        
        //  4397: invokevirtual   java/lang/Object.getClass:()Ljava/lang/Class;
        //  4400: pop            
        //  4401: aload_2        
        //  4402: areturn        
        //  4403: astore_2       
        //  4404: aload           5
        //  4406: invokevirtual   aere.close:()V
        //  4409: goto            4447
        //  4412: astore          5
        //  4414: ldc_w           Ljava/lang/Throwable;.class
        //  4417: ldc_w           "addSuppressed"
        //  4420: iconst_1       
        //  4421: anewarray       Ljava/lang/Class;
        //  4424: dup            
        //  4425: iconst_0       
        //  4426: ldc_w           Ljava/lang/Throwable;.class
        //  4429: aastore        
        //  4430: invokevirtual   java/lang/Class.getDeclaredMethod:(Ljava/lang/String;[Ljava/lang/Class;)Ljava/lang/reflect/Method;
        //  4433: aload_2        
        //  4434: iconst_1       
        //  4435: anewarray       Ljava/lang/Object;
        //  4438: dup            
        //  4439: iconst_0       
        //  4440: aload           5
        //  4442: aastore        
        //  4443: invokevirtual   java/lang/reflect/Method.invoke:(Ljava/lang/Object;[Ljava/lang/Object;)Ljava/lang/Object;
        //  4446: pop            
        //  4447: aload_2        
        //  4448: athrow         
        //  4449: aload_0        
        //  4450: getfield        eqw.a:Leqv;
        //  4453: getfield        eqv.a:Leqx;
        //  4456: getfield        eqx.av:Latjj;
        //  4459: invokeinterface atjj.a:()Ljava/lang/Object;
        //  4464: checkcast       Lozd;
        //  4467: aload_0        
        //  4468: getfield        eqw.a:Leqv;
        //  4471: getfield        eqv.e:Latjj;
        //  4474: invokeinterface atjj.a:()Ljava/lang/Object;
        //  4479: checkcast       Loas;
        //  4482: invokestatic    nzj.Q:(Lozd;Loas;)Lphq;
        //  4485: areturn        
        //  4486: aload_0        
        //  4487: getfield        eqw.a:Leqv;
        //  4490: getfield        eqv.a:Leqx;
        //  4493: getfield        eqx.aw:Latjj;
        //  4496: invokeinterface atjj.a:()Ljava/lang/Object;
        //  4501: checkcast       Lphq;
        //  4504: getfield        phq.b:Ljava/lang/Object;
        //  4507: areturn        
        //  4508: getstatic       afgm.b:Lafcw;
        //  4511: invokestatic    pnl.B:(Ljava/util/Map;)Lphq;
        //  4514: areturn        
        //  4515: getstatic       pbi.g:Lpbi;
        //  4518: astore_2       
        //  4519: aload_2        
        //  4520: invokevirtual   java/lang/Object.getClass:()Ljava/lang/Class;
        //  4523: pop            
        //  4524: aload_2        
        //  4525: areturn        
        //  4526: aload_0        
        //  4527: getfield        eqw.a:Leqv;
        //  4530: getfield        eqv.a:Leqx;
        //  4533: invokevirtual   eqx.R:()Ljava/util/Map;
        //  4536: invokestatic    pnl.z:(Ljava/util/Map;)Lphq;
        //  4539: areturn        
        //  4540: getstatic       pbi.i:Lpbi;
        //  4543: astore_2       
        //  4544: aload_2        
        //  4545: invokevirtual   java/lang/Object.getClass:()Ljava/lang/Class;
        //  4548: pop            
        //  4549: aload_2        
        //  4550: areturn        
        //  4551: getstatic       pbi.h:Lpbi;
        //  4554: astore_2       
        //  4555: aload_2        
        //  4556: invokevirtual   java/lang/Object.getClass:()Ljava/lang/Class;
        //  4559: pop            
        //  4560: aload_2        
        //  4561: areturn        
        //  4562: invokestatic    pal.b:()Lpax;
        //  4565: areturn        
        //  4566: getstatic       pbi.c:Lpbi;
        //  4569: astore_2       
        //  4570: aload_2        
        //  4571: invokevirtual   java/lang/Object.getClass:()Ljava/lang/Class;
        //  4574: pop            
        //  4575: aload_2        
        //  4576: areturn        
        //  4577: invokestatic    pal.c:()Lpax;
        //  4580: areturn        
        //  4581: invokestatic    pal.d:()Lpax;
        //  4584: areturn        
        //  4585: invokestatic    pal.e:()Lpax;
        //  4588: areturn        
        //  4589: aload_0        
        //  4590: getfield        eqw.a:Leqv;
        //  4593: getfield        eqv.a:Leqx;
        //  4596: invokevirtual   eqx.S:()Ljava/util/Map;
        //  4599: invokestatic    pnl.A:(Ljava/util/Map;)Lphq;
        //  4602: areturn        
        //  4603: aload_0        
        //  4604: getfield        eqw.a:Leqv;
        //  4607: getfield        eqv.c:Latjj;
        //  4610: invokeinterface atjj.a:()Ljava/lang/Object;
        //  4615: checkcast       Landroid/content/Context;
        //  4618: aload_0        
        //  4619: getfield        eqw.a:Leqv;
        //  4622: getfield        eqv.r:Latjj;
        //  4625: invokeinterface atjj.a:()Ljava/lang/Object;
        //  4630: checkcast       Laftr;
        //  4633: invokestatic    nrw.N:(Landroid/content/Context;Laftr;)Lozj;
        //  4636: areturn        
        //  4637: getstatic       wwe.a:Lwwe;
        //  4640: aload_0        
        //  4641: getfield        eqw.a:Leqv;
        //  4644: getfield        eqv.a:Leqx;
        //  4647: invokevirtual   eqx.T:()Ljava/util/Map;
        //  4650: invokestatic    pnl.u:(Lpat;Ljava/util/Map;)Lpbs;
        //  4653: areturn        
        //  4654: aload_0        
        //  4655: getfield        eqw.a:Leqv;
        //  4658: getfield        eqv.a:Leqx;
        //  4661: invokevirtual   eqx.m:()Loze;
        //  4664: aload_0        
        //  4665: getfield        eqw.a:Leqv;
        //  4668: getfield        eqv.a:Leqx;
        //  4671: invokevirtual   eqx.n:()Loze;
        //  4674: invokestatic    afdu.t:(Ljava/lang/Object;Ljava/lang/Object;)Lafdu;
        //  4677: areturn        
        //  4678: astore          5
        //  4680: goto            4447
        //    Exceptions:
        //  Try           Handler
        //  Start  End    Start  End    Type                 
        //  -----  -----  -----  -----  ---------------------
        //  4387   4391   4403   4449   Any
        //  4404   4409   4412   4447   Any
        //  4414   4447   4678   4683   Ljava/lang/Exception;
        // 
        // The error that occurred was:
        // 
        // java.lang.IllegalStateException: Expression is linked from several locations: Label_4447:
        //     at com.strobel.decompiler.ast.Error.expressionLinkedFromMultipleLocations(Error.java:27)
        //     at com.strobel.decompiler.ast.AstOptimizer.mergeDisparateObjectInitializations(AstOptimizer.java:2604)
        //     at com.strobel.decompiler.ast.AstOptimizer.optimize(AstOptimizer.java:235)
        //     at com.strobel.decompiler.ast.AstOptimizer.optimize(AstOptimizer.java:42)
        //     at com.strobel.decompiler.languages.java.ast.AstMethodBodyBuilder.createMethodBody(AstMethodBodyBuilder.java:206)
        //     at com.strobel.decompiler.languages.java.ast.AstMethodBodyBuilder.createMethodBody(AstMethodBodyBuilder.java:93)
        //     at com.strobel.decompiler.languages.java.ast.AstBuilder.createMethodBody(AstBuilder.java:868)
        //     at com.strobel.decompiler.languages.java.ast.AstBuilder.createMethod(AstBuilder.java:761)
        //     at com.strobel.decompiler.languages.java.ast.AstBuilder.addTypeMembers(AstBuilder.java:638)
        //     at com.strobel.decompiler.languages.java.ast.AstBuilder.createTypeCore(AstBuilder.java:605)
        //     at com.strobel.decompiler.languages.java.ast.AstBuilder.createTypeNoCache(AstBuilder.java:195)
        //     at com.strobel.decompiler.languages.java.ast.AstBuilder.createType(AstBuilder.java:162)
        //     at com.strobel.decompiler.languages.java.ast.AstBuilder.addType(AstBuilder.java:137)
        //     at com.strobel.decompiler.languages.java.JavaLanguage.buildAst(JavaLanguage.java:71)
        //     at com.strobel.decompiler.languages.java.JavaLanguage.decompileType(JavaLanguage.java:59)
        //     at com.strobel.decompiler.DecompilerDriver.decompileType(DecompilerDriver.java:333)
        //     at com.strobel.decompiler.DecompilerDriver.decompileJar(DecompilerDriver.java:254)
        //     at com.strobel.decompiler.DecompilerDriver.main(DecompilerDriver.java:129)
        // 
        throw new IllegalStateException("An error occurred while decompiling this method.");
    }
    
    private final Object e() {
        final int b = this.b;
        switch (b) {
            default: {
                throw new AssertionError(b);
            }
            case 399: {
                return ewp.p((uyf)eqv.po(this.a).a(), (aaca)eqv.oj(this.a).a());
            }
            case 398: {
                return ilv.g((lfy)eqv.q(this.a).aR.a(), (Handler)eqv.sL(this.a).a());
            }
            case 397: {
                final eqv a = this.a;
                return ilv.e(eqv.nu(a), eqv.ii(a), eqv.q(a).is, (Handler)eqv.sL(a).a());
            }
            case 396: {
                return vny.r((vjh)eqv.rU(this.a).a(), (adcr)eqv.pu(this.a).a(), (zki)eqv.pL(this.a).a(), (tgw)eqv.oR(this.a).a());
            }
            case 395: {
                return ilv.f();
            }
            case 394: {
                return fng.b((Context)eqv.pt(this.a).a(), eqv.to(this.a));
            }
            case 393: {
                return flp.o((tku)eqv.q(this.a).in.a());
            }
            case 392: {
                final bhu bhu = (bhu)eqv.q(this.a).io.a();
                final eqv a2 = this.a;
                return ilv.q(bhu, eqv.ii(a2), (tdz)eqv.jp(a2).a(), (aaam)eqv.nC(this.a).a(), (aaha)eqv.jw(this.a).a());
            }
            case 391: {
                return new zhb((aacf)eqv.lD(this.a).a(), (abpj)eqv.nj(this.a).a(), (Executor)eqv.fX(this.a).a(), (aftr)eqv.oO(this.a).a(), (arud)eqv.qo(this.a).a(), (byte[])null, (byte[])null);
            }
            case 390: {
                return iad.s();
            }
            case 389: {
                return new addp((vjh)eqv.rU(this.a).a(), (adcr)eqv.pu(this.a).a(), (zki)eqv.pL(this.a).a(), (tgw)eqv.pd(this.a).a(), null, null, null, (char[])null, (byte[])null, (byte[])null, null, null);
            }
            case 388: {
                return new acnx((byte[])null, (byte[])null);
            }
            case 387: {
                return new addp((vjh)eqv.rU(this.a).a(), (adcr)eqv.pu(this.a).a(), (zki)eqv.pL(this.a).a(), (tgw)eqv.oR(this.a).a(), null, null, null, null, null, (short[])null, null, null, null);
            }
            case 386: {
                return addl.m((Context)eqv.pt(this.a).a());
            }
            case 385: {
                return new stq((wvu)eqv.th(this.a).a());
            }
            case 384: {
                return vbj.l((vjh)eqv.rU(this.a).a(), (adcr)eqv.pu(this.a).a(), (zki)eqv.pL(this.a).a(), (tgw)eqv.pd(this.a).a());
            }
            case 383: {
                return new eg((gfs)eqv.q(this.a).ih.a(), (asho)eqv.fY(this.a).a(), (vbq)eqv.kF(this.a).a(), (uyf)eqv.po(this.a).a());
            }
            case 382: {
                return gfr.b((uyf)eqv.po(this.a).a());
            }
            case 381: {
                return new hyc((gfs)eqv.q(this.a).ih.a(), (asho)eqv.fY(this.a).a(), (vbq)eqv.kF(this.a).a(), (uyf)eqv.po(this.a).a());
            }
            case 380: {
                return new vmt((vjh)eqv.rU(this.a).a(), (adcr)eqv.pu(this.a).a(), (zki)eqv.pL(this.a).a(), (tgw)eqv.pd(this.a).a(), (byte[])null, (byte[])null, (byte[])null, (byte[])null, (byte[])null, (byte[])null);
            }
            case 379: {
                final zal zal = (zal)eqv.eD(this.a).a();
                final qcv qcv = (qcv)eqv.ja(this.a).a();
                final zhb zhb = (zhb)eqv.uy(this.a).a();
                final qbo qbo = (qbo)eqv.kZ(this.a).a();
                final Context context = (Context)eqv.pt(this.a).a();
                return eur.v(zal, qcv, zhb, qbo, eqv.dP(this.a), eqv.dQ(this.a), eqv.dL(this.a), eqv.dM(this.a), eqv.dF(this.a), eqv.dG(this.a), (afcr)eqv.qz(this.a).a(), (afcr)eqv.qA(this.a).a());
            }
            case 378: {
                final Context context2 = (Context)eqv.pt(this.a).a();
                final eqv a3 = this.a;
                return new hyc(eqv.pm(a3), (rmw)eqv.hw(a3).a());
            }
            case 377: {
                return gqm.m((Context)eqv.pt(this.a).a(), (qbo)eqv.to(this.a).a());
            }
            case 376: {
                return gqm.j((SecureRandom)eqv.rX(this.a).a(), (aagm)eqv.q(this.a).ie.a());
            }
            case 375: {
                return gpg.o((zki)eqv.pL(this.a).a(), (lzi)eqv.et(this.a).a(), (Executor)eqv.oO(this.a).a());
            }
            case 374: {
                return woh.e((Context)eqv.pt(this.a).a(), eqv.to(this.a));
            }
            case 373: {
                return new syb((aabt)eqv.ih(this.a).a(), eqv.ii(this.a), 15);
            }
            case 372: {
                return hty.f(eqv.xn(this.a), arjc.b(eqv.pL(this.a)), arjc.b(eqv.hq(this.a)));
            }
            case 371: {
                return kyn.v((Context)eqv.pt(this.a).a(), eqv.yv(), (aftr)eqv.oO(this.a).a(), (qbo)eqv.to(this.a).a(), (auip)eqv.fB(this.a).a());
            }
            case 370: {
                return xhw.r((asho)eqv.fY(this.a).a());
            }
            case 369: {
                final eqv a4 = this.a;
                final eqx q = eqv.q(a4);
                final Context context3 = (Context)eqv.pt(a4).a();
                final abno abno = (abno)eqv.ki(this.a).a();
                final xew xew = (xew)eqv.ia(this.a).a();
                final eqv a5 = this.a;
                final xks f = xhw.f(context3, abno, xew, eqv.qW(a5), (ccj)eqv.qV(a5).a(), (xfw)eqv.mq(this.a).a(), (xpv)eqv.mk(this.a).a(), (oas)eqv.gK(this.a).a(), (asho)eqv.fY(this.a).a(), (asho)eqv.fN(this.a).a());
                eqx.gM(q, f);
                return f;
            }
            case 368: {
                final Context context4 = (Context)eqv.pt(this.a).a();
                return new xjx((SharedPreferences)eqv.sr(this.a).a(), (xks)eqv.q(this.a).ia.a(), (wzw)eqv.qL(this.a).a(), eqx.W(eqv.q(this.a)), eqx.X(eqv.q(this.a)), (xew)eqv.ia(this.a).a(), (xlv)eqv.mi(this.a).a(), (oas)eqv.gK(this.a).a(), (adcr)eqv.q(this.a).ib.a(), (wzt)eqv.jE(this.a).a(), (byte[])null, (byte[])null, (byte[])null);
            }
            case 367: {
                final Context context5 = (Context)eqv.pt(this.a).a();
                final eqv a6 = this.a;
                final atjj to = eqv.to(a6);
                final aftr aftr = (aftr)eqv.oO(a6).a();
                final String yv = eqv.yv();
                final eg eg = (eg)eqv.uW(this.a).a();
                return jxe.v(context5, to, aftr, yv, (auip)eqv.fB(this.a).a(), Optional.of((Object)eqv.rj(this.a).a()));
            }
            case 366: {
                return hxw.c();
            }
            case 365: {
                final vjh vjh = (vjh)eqv.rU(this.a).a();
                final adcr adcr = (adcr)eqv.pu(this.a).a();
                final zki zki = (zki)eqv.pL(this.a).a();
                final tgw tgw = (tgw)eqv.pd(this.a).a();
                final Context context6 = (Context)eqv.pt(this.a).a();
                return ewp.v(vjh, adcr, zki, tgw);
            }
            case 364: {
                final vou vou = (vou)eqv.q(this.a).hW.a();
                final tdz tdz = (tdz)eqv.jp(this.a).a();
                final asho asho = (asho)eqv.fN(this.a).a();
                final fem fem = (fem)eqv.nd(this.a).a();
                final Resources d = eqx.d(eqv.q(this.a));
                final zki zki2 = (zki)eqv.pL(this.a).a();
                final eg gs = new eg(arjc.b(eqv.q(this.a).a.ih), (uyf)eqv.q(this.a).a.w.a(), (asho)eqv.q(this.a).a.bf.a());
                final uyf uyf = (uyf)eqv.po(this.a).a();
                final mck mck = (mck)eqv.q(this.a).aG.a();
                final eqv a7 = this.a;
                final atjj gk = eqv.gk(a7);
                final Object a8 = eqv.q(a7).hX.a();
                final ewl ewl = (ewl)eqv.uF(this.a).a();
                final Context context7 = (Context)eqv.pt(this.a).a();
                final hyo n = hxw.n(vou, tdz, asho, fem, d, zki2, gs, uyf, mck, gk, a8, ewl, (Executor)eqv.fX(this.a).a());
                eqx.gK(n);
                return n;
            }
            case 363: {
                final Context context8 = (Context)eqv.pt(this.a).a();
                final eqv a9 = this.a;
                final atjj to2 = eqv.to(a9);
                final aftr aftr2 = (aftr)eqv.oO(a9).a();
                final String yv2 = eqv.yv();
                final eg eg2 = (eg)eqv.uW(this.a).a();
                return ljl.t(context8, to2, aftr2, yv2, (auip)eqv.fB(this.a).a(), Optional.of((Object)eqv.rj(this.a).a()));
            }
            case 362: {
                return xhw.q((xgq)eqv.lx(this.a).a());
            }
            case 361: {
                return xfb.v((aepj)eqv.q(this.a).hT.a());
            }
            case 360: {
                final eqv a10 = this.a;
                return ewq.p(eqv.th(a10), (arud)eqv.qo(a10).a(), (uyf)eqv.po(this.a).a(), arjc.b(eqv.fH(this.a)), arjc.b(eqv.uX(this.a)), (Handler)eqv.sL(this.a).a(), (asho)eqv.fY(this.a).a(), (Executor)eqv.oO(this.a).a(), (oas)eqv.gK(this.a).a());
            }
            case 359: {
                return new hdv((Context)eqv.pt(this.a).a(), (arud)eqv.qo(this.a).a(), eqv.q(this.a).bU, (byte[])null, (byte[])null);
            }
            case 358: {
                final Context context9 = (Context)eqv.pt(this.a).a();
                final eqv a11 = this.a;
                final gia h = gfr.h(context9, eqv.q(a11).hQ, (Handler)eqv.sL(a11).a());
                eqx.gL(h);
                return h;
            }
            case 357: {
                return fqj.q((tku)eqv.sZ(this.a).a());
            }
            case 356: {
                return new addp((vjh)eqv.rU(this.a).a(), (adcr)eqv.pu(this.a).a(), (zki)eqv.pL(this.a).a(), (tgw)eqv.pd(this.a).a(), null, null, null, (char[])null, null, null, null);
            }
            case 355: {
                final zal zal2 = (zal)eqv.eD(this.a).a();
                final qcv qcv2 = (qcv)eqv.ja(this.a).a();
                final Context context10 = (Context)eqv.pt(this.a).a();
                final zhb zhb2 = (zhb)eqv.uy(this.a).a();
                final qbo qbo2 = (qbo)eqv.kZ(this.a).a();
                final eqv a12 = this.a;
                return rmc.u(zal2, qcv2, zhb2, qbo2, eqv.hR(a12), eqv.nL(a12), eqv.dP(a12), eqv.dQ(this.a), eqv.dL(this.a), eqv.dM(this.a), eqv.dF(this.a), eqv.dG(this.a), (afcr)eqv.qz(this.a).a(), (afcr)eqv.qA(this.a).a());
            }
            case 354: {
                return isw.c((wyo)eqv.hU(this.a).a(), (afqr)eqv.vp(this.a).a());
            }
            case 353: {
                return acey.s();
            }
            case 352: {
                return vyw.o();
            }
            case 351: {
                return new adcr((wvu)eqv.th(this.a).a());
            }
            case 350: {
                final avt avt = (avt)eqv.ty(this.a).a();
                final tdz tdz2 = (tdz)eqv.jp(this.a).a();
                final wxc wxc = (wxc)eqv.kP(this.a).a();
                final wxg wxg = (wxg)eqv.kQ(this.a).a();
                final adcr adcr2 = (adcr)eqv.nG(this.a).a();
                final Context context11 = (Context)eqv.pt(this.a).a();
                final arud arud = (arud)eqv.qo(this.a).a();
                final eqv a13 = this.a;
                return woh.s(avt, tdz2, wxc, wxg, adcr2, eqv.gY(a13), (uyi)eqv.gI(a13).a(), (uyi)eqv.lq(this.a).a());
            }
            case 349: {
                return new vzt();
            }
            case 348: {
                return new auip((aceo)eqv.ks(this.a).a(), (Executor)eqv.fX(this.a).a());
            }
            case 347: {
                return vyw.n();
            }
            case 346: {
                return new zvt((byte[])null, (byte[])null);
            }
            case 345: {
                return new agkw();
            }
            case 344: {
                return new vqn((vjh)eqv.rU(this.a).a(), (adcr)eqv.pu(this.a).a(), (zki)eqv.pL(this.a).a(), (tgw)eqv.oR(this.a).a(), (byte[])null, (byte[])null, (byte[])null, (byte[])null, (byte[])null, (byte[])null);
            }
            case 343: {
                return new vqq((vjh)eqv.rU(this.a).a(), (adcr)eqv.pu(this.a).a(), (zki)eqv.pL(this.a).a(), (tgw)eqv.pd(this.a).a(), (Set)afdu.r(), (byte[])null, (byte[])null, (byte[])null, (byte[])null, (byte[])null, (byte[])null);
            }
            case 342: {
                return abgv.r((aceo)eqv.ks(this.a).a(), (Executor)eqv.fX(this.a).a(), (ScheduledExecutorService)eqv.oO(this.a).a(), (abhq)eqv.kg(this.a).a(), (abns)eqv.kh(this.a).a(), (arud)eqv.qo(this.a).a(), (wyo)eqv.hU(this.a).a());
            }
            case 341: {
                return ffg.n((wyo)eqv.hU(this.a).a(), (fes)eqv.fp(this.a).a(), (abpj)eqv.jv(this.a).a(), (fjz)eqv.gJ(this.a).a());
            }
            case 340: {
                return new aank((Executor)eqv.oO(this.a).a(), (aafi)eqv.tc(this.a).a(), (zgz)eqv.sW(this.a).a(), (zno)eqv.sM(this.a).a(), (zki)eqv.pL(this.a).a(), (byte[])null);
            }
            case 339: {
                return aboa.n();
            }
            case 338: {
                final Context context12 = (Context)eqv.pt(this.a).a();
                final aajj aajj = (aajj)eqv.q(this.a).hM.a();
                return zja.g(context12);
            }
            case 337: {
                final bx he = eqv.q(this.a).hf();
                final eqv a14 = this.a;
                return new ize(he, eqv.q(a14).bR, (Executor)eqv.fX(a14).a(), (aazh)eqv.q(this.a).cx.a(), (byte[])null, (byte[])null, (byte[])null, (byte[])null, (byte[])null);
            }
            case 336: {
                return ewq.o();
            }
            case 335: {
                return abzu.g((boolean)eqv.qe(this.a).a(), arjc.b(eqv.q(this.a).aj), arjc.b(eqv.sG(this.a)), arjc.b(eqv.q(this.a).ak), arjc.b(eqv.lg(this.a)));
            }
            case 334: {
                return vny.o((adcr)eqv.pu(this.a).a(), eqv.ac(this.a), (zki)eqv.pL(this.a).a(), (uyf)eqv.po(this.a).a(), (vjh)eqv.rU(this.a).a());
            }
            case 333: {
                final vjh vjh2 = (vjh)eqv.rU(this.a).a();
                final adcr adcr3 = (adcr)eqv.pu(this.a).a();
                final zki zki3 = (zki)eqv.pL(this.a).a();
                return vlj.b(vjh2, adcr3, (tgw)eqv.pd(this.a).a());
            }
            case 332: {
                return phz.x((ScheduledExecutorService)eqv.oO(this.a).a(), (adcr)eqv.gc(this.a).a(), (zki)eqv.pL(this.a).a(), (zkb)eqv.pL(this.a).a(), (addt)eqv.fs(this.a).a(), (addt)eqv.q(this.a).hJ.a(), (mrm)eqv.qd(this.a).a());
            }
            case 331: {
                return new fku((Context)eqv.pt(this.a).a(), (Executor)eqv.fX(this.a).a(), (zpm)eqv.ge(this.a).a(), (zoj)eqv.wl(this.a).a());
            }
            case 330: {
                return ohw.q();
            }
            case 329: {
                return vbj.j((vjh)eqv.rU(this.a).a(), (adcr)eqv.pu(this.a).a(), (zki)eqv.pL(this.a).a(), (tgw)eqv.pd(this.a).a());
            }
            case 328: {
                return aais.q((Context)eqv.pt(this.a).a(), eqv.yv(), (aftr)eqv.oO(this.a).a(), (qbo)eqv.to(this.a).a());
            }
            case 327: {
                return aais.k(eqv.q(this.a).hG);
            }
            case 326: {
                return aais.e((Context)eqv.pt(this.a).a());
            }
            case 325: {
                final aapf aapf = (aapf)eqv.q(this.a).j.a();
                final aeby aeby = (aeby)eqv.nR(this.a).a();
                final eqv a15 = this.a;
                return new aauw(aapf, aeby, eqv.ki(a15), eqv.q(a15).hF, (aava)new aavb((tku)eqv.q(a15).cs.a()), (abpj)eqv.jv(this.a).a(), (byte[])null, (byte[])null, (byte[])null, (byte[])null, (byte[])null, (byte[])null, (byte[])null);
            }
            case 324: {
                return eyp.n((arud)eqv.qo(this.a).a(), (adbq)eqv.hJ(this.a).a());
            }
            case 323: {
                return eyp.m((arud)eqv.qo(this.a).a(), (fzo)eqv.q(this.a).hE.a());
            }
            case 322: {
                return gfr.v((auip)eqv.q(this.a).bA.a());
            }
            case 321: {
                return lme.j();
            }
            case 320: {
                return wvl.k((yhy)eqv.oQ(this.a).a(), (abns)eqv.kh(this.a).a(), (uyf)eqv.po(this.a).a());
            }
            case 319: {
                final fes fes = (fes)eqv.fp(this.a).a();
                final eqv a16 = this.a;
                return fdu.f(fes, eqv.kT(a16), eqv.q(a16).fs, (wyo)eqv.hU(a16).a());
            }
            case 318: {
                final eqv a17 = this.a;
                return fdu.e(eqv.q(a17).hC, new uyi((uyf)eqv.q(a17).a.w.a(), (arud)eqv.q(a17).a.v.a(), (byte[])null, (byte[])null));
            }
            case 317: {
                return riz.t((adcr)eqv.gc(this.a).a(), (zki)eqv.pL(this.a).a(), (rkh)eqv.pL(this.a).a(), (Executor)eqv.oO(this.a).a());
            }
            case 316: {
                return riz.p(eqv.zL(this.a), (aeim)eqv.cj(this.a), eqv.zy(this.a), (zki)eqv.pL(this.a).a(), (aeig)eqv.ev(this.a).a(), (rxr)eqv.q(this.a).cn.a());
            }
            case 315: {
                return adhg.o(eqv.zL(this.a));
            }
            case 314: {
                return adhg.u(eqv.zL(this.a), afcw.n((Object)aeji.class, (Object)eqv.q(this.a).hz, (Object)rkr.class, (Object)eqv.q(this.a).hA), (Map)afcw.l(), (Set)afdu.r(), (aehe)eqv.ew(this.a).a());
            }
            case 313: {
                return eur.t();
            }
            case 312: {
                return new avt((vjl)eqv.kx(this.a).a(), (byte[])null);
            }
            case 311: {
                return ewq.u((Context)eqv.pt(this.a).a(), (ttg)eqv.sS(this.a).a(), (avt)eqv.q(this.a).hy.a(), (uyf)eqv.po(this.a).a());
            }
            case 310: {
                return new addp((vjh)eqv.rU(this.a).a(), (adcr)eqv.pu(this.a).a(), (zki)eqv.pL(this.a).a(), (tgw)eqv.oR(this.a).a(), null, null, (char[])null, null, (char[])null, null, null, null);
            }
            case 309: {
                return new avt((arud)eqv.qo(this.a).a(), (byte[])null, (byte[])null);
            }
            case 308: {
                return uto.t((aftr)eqv.oO(this.a).a(), (eg)eqv.uW(this.a).a());
            }
            case 307: {
                final Context context13 = (Context)eqv.pt(this.a).a();
                final eqv a18 = this.a;
                return ugi.q(context13, eqv.sr(a18), (qbo)eqv.to(a18).a(), (aftr)eqv.oO(this.a).a());
            }
            case 306: {
                return sni.i((Context)eqv.pt(this.a).a(), (aftr)eqv.oO(this.a).a(), eqv.yv(), (qbo)eqv.to(this.a).a());
            }
            case 305: {
                return sni.l((Executor)eqv.fX(this.a).a());
            }
            case 304: {
                return new spt((rfv)eqv.oF(this.a).a(), (zki)eqv.pL(this.a).a(), sni.n(), (byte[])null, (byte[])null);
            }
            case 303: {
                return new sxv((Context)eqv.pt(this.a).a(), (Executor)eqv.oO(this.a).a(), (Executor)eqv.fX(this.a).a(), (spt)eqv.q(this.a).hw.a(), (zhs)eqv.q(this.a).ca.a());
            }
            case 302: {
                return new tix((Context)eqv.pt(this.a).a(), (tdg)eqv.q(this.a).cb.a(), (Executor)eqv.oO(this.a).a(), (Executor)eqv.fX(this.a).a(), (byte[])null, (byte[])null, (byte[])null);
            }
            case 301: {
                return trl.j((Context)eqv.pt(this.a).a(), (afts)eqv.oO(this.a).a());
            }
            case 300: {
                return ewq.h((Context)eqv.pt(this.a).a(), (uyf)eqv.po(this.a).a());
            }
        }
    }
    
    private final Object f() {
        final int b = this.b;
        switch (b) {
            default: {
                throw new AssertionError(b);
            }
            case 499: {
                return suh.k();
            }
            case 498: {
                return eyp.p((vbq)eqv.kF(this.a).a(), eqv.zO(this.a));
            }
            case 497: {
                return lme.k();
            }
            case 496: {
                return qex.c();
            }
            case 495: {
                return new xdg((xlv)eqv.mi(this.a).a(), (osb)eqv.ji(this.a).a());
            }
            case 494: {
                return zpn.m((zoj)eqv.wl(this.a).a(), (arud)eqv.qo(this.a).a(), (Context)eqv.pt(this.a).a(), (ScheduledExecutorService)eqv.lg(this.a).a(), (zqm)eqv.rq(this.a).a(), (zpm)eqv.ge(this.a).a(), (wwv)eqv.hR(this.a).a());
            }
            case 493: {
                final Context context = (Context)eqv.pt(this.a).a();
                final eqv a = this.a;
                return jtv.i(context, eqv.to(a), (aftr)eqv.oO(a).a(), eqv.yv(), (auip)eqv.fB(this.a).a(), Optional.of((Object)eqv.rj(this.a).a()));
            }
            case 492: {
                return new lmh((lmt)eqv.q(this.a).jd.a(), (tdz)eqv.jp(this.a).a(), (thh)eqv.id(this.a).a(), (abno)eqv.ki(this.a).a());
            }
            case 491: {
                return new lmt((tdz)eqv.jp(this.a).a(), (Handler)eqv.sL(this.a).a());
            }
            case 490: {
                return xfb.j();
            }
            case 489: {
                return xfb.g();
            }
            case 488: {
                return lia.c((uyi)eqv.lh(this.a).a(), (afqr)eqv.vp(this.a).a());
            }
            case 487: {
                return acve.g((adbq)eqv.hJ(this.a).a(), (wvu)eqv.th(this.a).a(), eqv.xC(this.a), new zhb(eqv.q(this.a).a.xD(), (asgt)eqv.q(this.a).a.nS.a(), (oas)eqv.q(this.a).a.e.a(), (asho)eqv.q(this.a).a.bf.a()), (adfc)eqv.vb(this.a).a(), (asho)eqv.fN(this.a).a(), (ScheduledExecutorService)eqv.oO(this.a).a());
            }
            case 486: {
                return eur.h((Context)eqv.pt(this.a).a(), (Executor)eqv.oO(this.a).a());
            }
            case 485: {
                final eqv a2 = this.a;
                final atjj dr = eqv.q(a2).ja;
                final uyf uyf = (uyf)eqv.po(a2).a();
                final eqv a3 = this.a;
                return eur.i(dr, uyf, eqv.th(a3), (Executor)eqv.oO(a3).a(), (asho)eqv.fN(this.a).a(), eqv.kx(this.a));
            }
            case 484: {
                return jko.n((Context)eqv.pt(this.a).a(), (qbo)eqv.to(this.a).a());
            }
            case 483: {
                return jko.o((Context)eqv.pt(this.a).a(), (qbo)eqv.to(this.a).a());
            }
            case 482: {
                return acve.i();
            }
            case 481: {
                return adhg.m((Context)eqv.pt(this.a).a(), (qbo)eqv.to(this.a).a());
            }
            case 480: {
                return adhg.l((Context)eqv.pt(this.a).a(), (qbo)eqv.to(this.a).a());
            }
            case 479: {
                return new MdxSmartRemoteDialListener((xcw)eqv.pZ(this.a).a(), (xlv)eqv.mi(this.a).a(), (tdz)eqv.jp(this.a).a(), (wzw)eqv.qL(this.a).a());
            }
            case 478: {
                return vny.t((vjh)eqv.rU(this.a).a(), (adcr)eqv.pu(this.a).a(), (zki)eqv.pL(this.a).a(), (tgw)eqv.oR(this.a).a(), (Executor)eqv.oO(this.a).a());
            }
            case 477: {
                final eqv a4 = this.a;
                return gij.k(aele.r(eqv.zz(a4)), (tku)eqv.pS(a4).a(), (uyi)eqv.lh(this.a).a(), (aeke)eqv.qD(this.a).a());
            }
            case 476: {
                return lme.h((ScheduledExecutorService)eqv.oO(this.a).a());
            }
            case 475: {
                return ixb.u(eqv.q(this.a).bR);
            }
            case 474: {
                return uto.c((aceo)eqv.ks(this.a).a());
            }
            case 473: {
                return xab.h();
            }
            case 472: {
                return xhw.i((Context)eqv.pt(this.a).a(), (qbo)eqv.to(this.a).a());
            }
            case 471: {
                final eqv a5 = this.a;
                return xab.g(eqv.q(a5).iV, (xdp)eqv.q(a5).dR.a(), (Executor)eqv.oO(this.a).a());
            }
            case 470: {
                return iad.p((Context)eqv.pt(this.a).a(), (qbo)eqv.to(this.a).a());
            }
            case 469: {
                final eqv a6 = this.a;
                return xlb.o(aele.r(eqv.zz(a6)), (ExecutorService)eqv.oO(a6).a(), (pvk)eqv.q(this.a).iQ.a(), (pbw)eqv.q(this.a).iR.a());
            }
            case 468: {
                final ozd ozd = (ozd)eqv.q(this.a).av.a();
                final oas oas = (oas)eqv.gK(this.a).a();
                return ops.s();
            }
            case 467: {
                final eqv a7 = this.a;
                return pal.g(eqv.q(a7).aw, eqv.q(a7).ax, eqv.q(a7).ay);
            }
            case 466: {
                final eqv a8 = this.a;
                return xlb.n(aele.r(eqv.zz(a8)), (ExecutorService)eqv.oO(a8).a());
            }
            case 465: {
                final eqv a9 = this.a;
                return xlb.l(aele.r(eqv.zz(a9)), (pxx)eqv.q(a9).iP.a());
            }
            case 464: {
                final eqv a10 = this.a;
                return xlb.m(aele.r(eqv.zz(a10)), (ExecutorService)eqv.oO(a10).a(), (pvk)eqv.q(this.a).iQ.a(), (pbw)eqv.q(this.a).iR.a());
            }
            case 463: {
                return xlb.j((tgj)eqv.qq(this.a).a(), (ListenableFuture)eqv.se(this.a).a(), (aftr)eqv.gi(this.a).a());
            }
            case 462: {
                return xhw.m((Context)eqv.pt(this.a).a(), (qbo)eqv.to(this.a).a());
            }
            case 461: {
                return ffg.g(eqv.aA(this.a));
            }
            case 460: {
                return hkl.b();
            }
            case 459: {
                return wgv.n((Context)eqv.pt(this.a).a(), (aftr)eqv.oO(this.a).a(), (qbo)eqv.to(this.a).a(), eqv.yv());
            }
            case 458: {
                final eqv a11 = this.a;
                return wgv.v(eqv.q(a11).dN, (adcr)eqv.q(a11).dK.a());
            }
            case 457: {
                return new xkm();
            }
            case 456: {
                return new adcr((Context)eqv.pt(this.a).a(), (arud)eqv.qo(this.a).a(), null, null);
            }
            case 455: {
                final adcr adcr = (adcr)eqv.q(this.a).dK.a();
                final xkm xkm = (xkm)eqv.q(this.a).dL.a();
                return new zgv(adcr, (byte[])null, (byte[])null, (byte[])null, (byte[])null, (byte[])null);
            }
            case 454: {
                return new yzf((arud)eqv.q(this.a).a.v.a(), (pni)eqv.q(this.a).hi(), (byte[])null, (byte[])null);
            }
            case 453: {
                final rgh rgh = (rgh)eqv.pL(this.a).a();
                final rgm rgm = (rgm)eqv.pL(this.a).a();
                final vkv vkv = (vkv)eqv.ex(this.a).a();
                eqx.gO(eqv.q(this.a));
                return new rhv(rgh, rgm, vkv, (tdz)eqv.jp(this.a).a(), (Executor)eqv.oO(this.a).a(), (rkw)eqv.wi(this.a).a(), (rjq)eqv.ix(this.a).a(), eqv.xt(this.a));
            }
            case 452: {
                return qwl.l();
            }
            case 451: {
                final rjq rjq = (rjq)eqv.ix(this.a).a();
                final rgh rgh2 = (rgh)eqv.pL(this.a).a();
                final rkw rkw = (rkw)eqv.wi(this.a).a();
                final vkv vkv2 = (vkv)eqv.ex(this.a).a();
                final rgc rgc = (rgc)eqv.q(this.a).iJ.a();
                return new rka(rjq, rgh2, rkw, vkv2, (tdz)eqv.jp(this.a).a());
            }
            case 450: {
                return rmc.n((rsl)eqv.fJ(this.a).a());
            }
            case 449: {
                ewq.d();
                return true;
            }
            case 448: {
                return eur.o((Context)eqv.pt(this.a).a(), (ahqj)eqv.qs(this.a).a());
            }
            case 447: {
                final Context context2 = (Context)eqv.pt(this.a).a();
                final SharedPreferences sharedPreferences = (SharedPreferences)eqv.sr(this.a).a();
                final atvw atvw = (atvw)eqv.q(this.a).iG.a();
                ewp.m(atvw);
                return atvw;
            }
            case 446: {
                return xre.r((vjh)eqv.rU(this.a).a(), (adcr)eqv.pu(this.a).a(), (zki)eqv.pL(this.a).a(), (tgw)eqv.pd(this.a).a(), (Executor)eqv.fX(this.a).a());
            }
            case 445: {
                return addl.s((vjh)eqv.rU(this.a).a(), (adcr)eqv.pu(this.a).a(), (tgw)eqv.pd(this.a).a());
            }
            case 444: {
                return addl.r((vjh)eqv.rU(this.a).a(), (adcr)eqv.pu(this.a).a(), (tgw)eqv.pd(this.a).a());
            }
            case 443: {
                return addl.t((vjh)eqv.rU(this.a).a(), (adcr)eqv.pu(this.a).a(), (zki)eqv.pL(this.a).a(), (tgw)eqv.pd(this.a).a(), (Executor)eqv.fX(this.a).a());
            }
            case 442: {
                return vny.k((vjh)eqv.rU(this.a).a(), (adcr)eqv.pu(this.a).a(), (tgw)eqv.oR(this.a).a());
            }
            case 441: {
                return acve.m();
            }
            case 440: {
                return new uyi((uyf)eqv.po(this.a).a(), (arud)eqv.qo(this.a).a(), (byte[][][])null, (byte[])null, (byte[])null);
            }
            case 439: {
                return new aaca((vjh)eqv.rU(this.a).a(), (adcr)eqv.pu(this.a).a(), (zki)eqv.pL(this.a).a(), (uyi)eqv.q(this.a).iC.a(), (zkz)eqv.hU(this.a).a(), (tgw)eqv.pd(this.a).a(), (byte[])null, (byte[])null, (byte[])null, (byte[])null, (byte[])null, (byte[])null, (byte[])null, (byte[])null);
            }
            case 438: {
                return suh.j();
            }
            case 437: {
                return new avt((byte[])null, (char[])null);
            }
            case 436: {
                return suh.m();
            }
            case 435: {
                return suh.l();
            }
            case 434: {
                return riz.o();
            }
            case 433: {
                return riz.u((vjh)eqv.rU(this.a).a(), (adcr)eqv.pu(this.a).a(), (zki)eqv.pL(this.a).a(), (tgw)eqv.oR(this.a).a());
            }
            case 432: {
                return new addr((vjh)eqv.rU(this.a).a(), (adcr)eqv.pu(this.a).a(), (zki)eqv.pL(this.a).a(), (tgw)eqv.pd(this.a).a(), (Executor)eqv.fX(this.a).a(), null, null, null, null, null, null, null, null, null);
            }
            case 431: {
                return new addr((vjh)eqv.rU(this.a).a(), (adcr)eqv.pu(this.a).a(), (zki)eqv.pL(this.a).a(), (tgw)eqv.pd(this.a).a(), (Executor)eqv.fX(this.a).a(), null, null, null, null, null, null, null, null, null, null);
            }
            case 430: {
                return new addr((vjh)eqv.rU(this.a).a(), (adcr)eqv.pu(this.a).a(), (zki)eqv.pL(this.a).a(), (tgw)eqv.pd(this.a).a(), (Executor)eqv.oO(this.a).a(), null, null, null, null, null, null, null, null);
            }
            case 429: {
                return new addr((vjh)eqv.rU(this.a).a(), (adcr)eqv.pu(this.a).a(), (zki)eqv.pL(this.a).a(), (tgw)eqv.pd(this.a).a(), (byte[])null, null, null, null, null, null, null);
            }
            case 428: {
                return new addp((vjh)eqv.rU(this.a).a(), (adcr)eqv.pu(this.a).a(), (zki)eqv.pL(this.a).a(), (tgw)eqv.pd(this.a).a(), null, null, null, null, null, null, (char[])null, null, null);
            }
            case 427: {
                return new addp((vjh)eqv.rU(this.a).a(), (adcr)eqv.pu(this.a).a(), (zki)eqv.pL(this.a).a(), (tgw)eqv.pd(this.a).a(), null, null, (char[])null, null, (byte[])null, null, null, null);
            }
            case 426: {
                return new addp((vjh)eqv.rU(this.a).a(), (adcr)eqv.pu(this.a).a(), (zki)eqv.pL(this.a).a(), (tgw)eqv.pd(this.a).a(), null, null, null, null, (char[])null, null, null, null, null);
            }
            case 425: {
                return new addp((vjh)eqv.rU(this.a).a(), (adcr)eqv.pu(this.a).a(), (zki)eqv.pL(this.a).a(), (tgw)eqv.pd(this.a).a(), null, null, null, null, null, (char[])null, null, null, null);
            }
            case 424: {
                return vny.s((vjh)eqv.rU(this.a).a(), (adcr)eqv.pu(this.a).a(), (zki)eqv.pL(this.a).a(), (tgw)eqv.pd(this.a).a());
            }
            case 423: {
                return vny.m((vjh)eqv.rU(this.a).a(), (adcr)eqv.pu(this.a).a(), (zki)eqv.pL(this.a).a(), (tgw)eqv.pd(this.a).a());
            }
            case 422: {
                return vny.l((vjh)eqv.rU(this.a).a(), (adcr)eqv.pu(this.a).a(), (zki)eqv.pL(this.a).a(), (tgw)eqv.pd(this.a).a());
            }
            case 421: {
                return new addp((vjh)eqv.rU(this.a).a(), (adcr)eqv.pu(this.a).a(), (zki)eqv.pL(this.a).a(), (tgw)eqv.pd(this.a).a(), null, (char[])null, null, null, (byte[])null, null, null, null);
            }
            case 420: {
                return new addp((vjh)eqv.rU(this.a).a(), (adcr)eqv.pu(this.a).a(), (zki)eqv.pL(this.a).a(), (tgw)eqv.pd(this.a).a(), null, null, null, (char[])null, null, null, null, null, null);
            }
            case 419: {
                return new addp((vjh)eqv.rU(this.a).a(), (adcr)eqv.pu(this.a).a(), (zki)eqv.pL(this.a).a(), (tgw)eqv.pd(this.a).a(), null, (char[])null, null, null, null, null, null);
            }
            case 418: {
                return eov.d(eqv.q(this.a).E());
            }
            case 417: {
                return eov.p((eoo)eqv.q(this.a).W.a(), new cya(eqv.q(this.a).iz));
            }
            case 416: {
                return com.google.android.apps.youtube.embeddedplayer.service.permissions.b.c((Context)eqv.pt(this.a).a());
            }
            case 415: {
                return new xkm();
            }
            case 414: {
                return fcv.m((abyn)eqv.hm(this.a).a());
            }
            case 413: {
                return sni.o(eqv.zO(this.a), (vbq)eqv.kF(this.a).a(), (zki)eqv.pL(this.a).a());
            }
            case 412: {
                return new mck((short[])null, (byte[])null);
            }
            case 411: {
                return eyp.o();
            }
            case 410: {
                final eqv a12 = this.a;
                return acve.l(eqv.q(a12).de, (vbq)eqv.kF(a12).a(), (acko)eqv.hM(this.a).a(), (wyo)eqv.hU(this.a).a(), (tny)eqv.qf(this.a).a(), new uyi((uyf)eqv.q(this.a).a.w.a(), (arud)eqv.q(this.a).a.v.a(), (byte[])null, (byte[])null), (oas)eqv.gK(this.a).a());
            }
            case 409: {
                final eqv a13 = this.a;
                return acve.b(aele.r(eqv.zz(a13)), (zjy)eqv.hq(a13).a());
            }
            case 408: {
                return rmc.o((zal)eqv.eD(this.a).a(), afdu.s((Object)eqv.q(this.a).aD.a()), (arud)eqv.qo(this.a).a());
            }
            case 407: {
                return vny.i((vjh)eqv.rU(this.a).a(), (adcr)eqv.pu(this.a).a(), (zki)eqv.pL(this.a).a(), (tgw)eqv.oR(this.a).a());
            }
            case 406: {
                return vny.j((vjh)eqv.rU(this.a).a(), (adcr)eqv.pu(this.a).a(), (zki)eqv.pL(this.a).a(), (tgw)eqv.oR(this.a).a());
            }
            case 405: {
                return new auip((char[])null);
            }
            case 404: {
                return new tdg((byte[])null);
            }
            case 403: {
                return gqm.n();
            }
            case 402: {
                return vny.h((vjh)eqv.rU(this.a).a(), (adcr)eqv.pu(this.a).a(), (zki)eqv.pL(this.a).a(), (tgw)eqv.pd(this.a).a());
            }
            case 401: {
                return acve.n();
            }
            case 400: {
                return fdu.n(eqv.qC(this.a));
            }
        }
    }
    
    @Override
    public final Object a() {
        final int b = this.b;
        final int n = b / 100;
        if (n == 0) {
            return this.b();
        }
        if (n == 1) {
            return this.c();
        }
        if (n == 2) {
            return this.d();
        }
        if (n == 3) {
            return this.e();
        }
        if (n != 4) {
            Object o = null;
            switch (b) {
                default: {
                    throw new AssertionError(b);
                }
                case 541: {
                    final Context context = (Context)this.a.c.a();
                    o = new aade((aaen)this.a.kt.a(), 2);
                    break;
                }
                case 540: {
                    o = new aaeu((Class)OfflineTransferService.class, (aade)this.a.kA.a());
                    break;
                }
                case 539: {
                    o = new arvw(true);
                    break;
                }
                case 538: {
                    final afcw b2 = afgm.b;
                    final aeru aeru = (aeru)this.a.gU.a();
                    final afct h = afcw.h();
                    for (final Map.Entry<String, V> entry : b2.r()) {
                        h.g((Object)entry.getKey(), (Object)new glz(aeru, (Map.Entry)entry, 4));
                    }
                    o = new agmh((Map)h.c());
                    break;
                }
                case 537: {
                    o = new xgt((abky)this.a.ps.a(), this.a.iC, 0);
                    break;
                }
                case 536: {
                    o = new xgt((abky)this.a.ps.a(), this.a.mB, 1);
                    break;
                }
                case 535: {
                    o = new sgh(this.a.mB);
                    break;
                }
                case 534: {
                    final sgg sgg = (sgg)this.a.mB.a();
                    o = new sgj(sgg);
                    sgg.b.add(o);
                    break;
                }
                case 533: {
                    o = Arrays.asList((abkq)this.a.a.eI.a(), (abkq)this.a.ps.a(), (abkq)(abkr)this.a.pu.a());
                    ((aade)o).getClass();
                    break;
                }
                case 532: {
                    final Context context2 = (Context)this.a.c.a();
                    final absk absk = (absk)this.a.mz.a();
                    final absi absi = (absi)this.a.iJ.a();
                    final abns abns = (abns)this.a.bt.a();
                    final List list = (List)this.a.a.eJ.a();
                    final eqx a = this.a.a;
                    final Context context3 = (Context)a.a.c.a();
                    final eqv a2 = a.a;
                    o = new abkw(context2, absk, absi, abns.bO(), (abks)this.a.po.a(), new abkz(context3, a2.iR, (absk)a2.mz.a(), ((xbz)a.a.im.a()).d, a.a.iN, (abkv)a.eK.a()), (oas)this.a.e.a(), list);
                    break;
                }
                case 531: {
                    final Context context4 = (Context)this.a.c.a();
                    final absk absk2 = (absk)this.a.iQ.a();
                    final absi absi2 = (absi)this.a.iJ.a();
                    final abns abns2 = (abns)this.a.bt.a();
                    final eqx a3 = this.a.a;
                    final Context context5 = (Context)a3.a.c.a();
                    final eqv a4 = a3.a;
                    final abkz abkz = new abkz(context5, a4.iR, (absk)a4.iQ.a(), ((xbz)a3.a.im.a()).d, a3.a.iN);
                    final eqx a5 = this.a.a;
                    final afcr u = afcr.u((Object)a5.a.pr.a(), (Object)a5.a.ps.a(), (Object)a5.a.pt.a(), (Object)a5.a.pu.a());
                    u.getClass();
                    o = new abkw(context4, absk2, absi2, abns2.bO(), (abks)this.a.po.a(), abkz, (oas)this.a.e.a(), (List)u);
                    break;
                }
                case 530: {
                    final SharedPreferences sharedPreferences = (SharedPreferences)this.a.d.a();
                    final rgh rgh = (rgh)this.a.aC.a();
                    final rgm rgm = (rgm)this.a.aC.a();
                    final rfv rfv = (rfv)this.a.af.a();
                    final rkw rkw = (rkw)this.a.ad.a();
                    final tzs tzs = (tzs)this.a.av.a();
                    final rjq rjq = (rjq)this.a.kk.a();
                    final eqv a6 = this.a;
                    o = new abpj(sharedPreferences, rgh, rgm, rfv, rkw, tzs, rjq, a6.kl, (tdz)a6.h.a(), (byte[])null, (byte[])null);
                    break;
                }
                case 529: {
                    final Context context6 = (Context)this.a.c.a();
                    final aftr aftr = (aftr)this.a.r.a();
                    final qbo qbo = (qbo)this.a.ai.a();
                    final String xk = eqv.xk();
                    final qmr a7 = qms.a(context6);
                    a7.e("edit");
                    a7.f("camera.pb");
                    final Uri a8 = a7.a();
                    final qos d = qou.d(context6, (Executor)aftr);
                    d.d(new String[] { "camera_facing" });
                    d.b();
                    d.c = xk;
                    d.e((qot)fnd.n);
                    final qou a9 = d.a();
                    final qoq a10 = qor.a();
                    a10.e((MessageLite)ujc.a);
                    a10.f(a8);
                    a10.b((qon)a9);
                    o = qbo.D(a10.a());
                    break;
                }
                case 528: {
                    o = ((atje)atix.e()).aX();
                    break;
                }
                case 527: {
                    final Context context7 = (Context)this.a.c.a();
                    final String xk2 = eqv.xk();
                    final aftr aftr2 = (aftr)this.a.r.a();
                    final qbo qbo2 = (qbo)this.a.ai.a();
                    final qmr a11 = qms.a(context7);
                    a11.e("mdx");
                    a11.f("smart_remote.pb");
                    final Uri a12 = a11.a();
                    final qos d2 = qou.d(context7, (Executor)aftr2);
                    d2.c = xk2;
                    d2.b();
                    d2.d(new String[] { "MDx.SmartRemote.isDisconnectTipAlreadyShown", "MDx.SmartRemote.isPrivacyDialogShown" });
                    d2.e((qot)fnd.s);
                    final qou a13 = d2.a();
                    final qoq a14 = qor.a();
                    a14.f(a12);
                    a14.e((MessageLite)aqnr.a);
                    a14.b((qon)a13);
                    o = qbo2.D(a14.a());
                    break;
                }
                case 526: {
                    o = mih.a((Context)this.a.c.a());
                    break;
                }
                case 525: {
                    o = new aaca((vjh)this.a.fH.a(), (adcr)this.a.eQ.a(), (zki)this.a.aC.a(), (tgw)this.a.fI.a(), (Executor)this.a.r.a(), (byte[])null, (byte[])null, (byte[])null, (byte[])null, (byte[])null, (byte[])null);
                    break;
                }
                case 524: {
                    o = new xkm();
                    break;
                }
                case 523: {
                    o = new wok();
                    break;
                }
                case 522: {
                    o = new qcj((char[])null);
                    break;
                }
                case 521: {
                    o = new eg((tzs)this.a.av.a(), (rgh)this.a.aC.a(), (Executor)this.a.r.a(), (byte[])null, (byte[])null);
                    break;
                }
                case 520: {
                    o = new adbl();
                    break;
                }
                case 519: {
                    o = new adbj();
                    break;
                }
                case 518: {
                    o = new elw();
                    break;
                }
                case 517: {
                    o = ewo.d((Context)this.a.c.a());
                    ((aade)o).getClass();
                    break;
                }
                case 516: {
                    o = aaja.z((boolean)this.a.cz.a(), arjc.b(this.a.a.aj), arjc.b(this.a.cE), arjc.b(this.a.E), arjc.b(this.a.a.ak));
                    break;
                }
                case 515: {
                    final Context context8 = (Context)this.a.c.a();
                    final qbo qbo3 = (qbo)this.a.ai.a();
                    final qmr a15 = qms.a(context8);
                    a15.e("reelwatch");
                    a15.f("reelwatch.pb");
                    final Uri a16 = a15.a();
                    final qoq a17 = qor.a();
                    a17.e((MessageLite)hsd.a);
                    a17.f(a16);
                    o = qbo3.D(a17.a());
                    break;
                }
                case 514: {
                    o = hjq.b();
                    break;
                }
                case 513: {
                    final hrm hrm = (hrm)this.a.pY.a();
                    final hyr hyr = (hyr)this.a.pK.a();
                    final lht lht = (lht)this.a.pW.a();
                    final hqv hqv = (hqv)this.a.jM.a();
                    final hku hku = (hku)this.a.a.dP.a();
                    final oas oas = (oas)this.a.e.a();
                    final Executor executor = (Executor)this.a.g.a();
                    final Executor executor2 = (Executor)this.a.r.a();
                    final wym wym = (wym)this.a.cB.a();
                    final auip auip = (auip)this.a.gc.a();
                    final aeyr aeyr = (aeyr)this.a.pV.a();
                    final abns abns3 = (abns)this.a.mv.a();
                    final vja vja = (vja)this.a.fG.a();
                    final zki zki = (zki)this.a.aC.a();
                    final hjp hjp = (hjp)this.a.a.eq.a();
                    o = new hrf(hrm, hyr, lht, hqv, hku, oas, executor, executor2, wym, auip, aeyr, abns3, vja, zki, (abdh)this.a.fc.a(), (cya)this.a.jP.a(), (byte[])null, (byte[])null, (byte[])null, (byte[])null, (byte[])null, (byte[])null);
                    break;
                }
                case 512: {
                    final Context context9 = (Context)this.a.c.a();
                    final qbo qbo4 = (qbo)this.a.ai.a();
                    final qmr a18 = qms.a(context9);
                    a18.e("reeledu");
                    a18.f("reeledu.pb");
                    final Uri a19 = a18.a();
                    final qoq a20 = qor.a();
                    a20.e((MessageLite)hsc.a);
                    a20.f(a19);
                    o = qbo4.D(a20.a());
                    break;
                }
                case 511: {
                    o = new bhu((adcr)this.a.a.ej.a(), null, null, null);
                    break;
                }
                case 510: {
                    o = new kvp(this.a.cB);
                    break;
                }
                case 509: {
                    final bhu bhu = (bhu)this.a.nB.a();
                    o = new feq();
                    break;
                }
                case 508: {
                    final Context context10 = (Context)this.a.c.a();
                    final uyf uyf = (uyf)this.a.w.a();
                    final eqx a21 = this.a.a;
                    final Context context11 = (Context)a21.a.c.a();
                    final adcr adcr = (adcr)a21.a.ld.a();
                    final aeim aeim = new aeim((byte[])null, (char[])null);
                    final adcr adcr2 = (adcr)this.a.ld.a();
                    final wyo wyo = (wyo)this.a.cB.a();
                    final zhb zhb = (zhb)this.a.lj.a();
                    o = ewo.S(context10, uyf, aeim, adcr2, wyo);
                    break;
                }
                case 507: {
                    o = new bx((int[])null);
                    break;
                }
                case 506: {
                    o = new fly((oas)this.a.e.a(), (tdz)this.a.h.a(), (ScheduledExecutorService)this.a.r.a(), (Executor)this.a.g.a());
                    break;
                }
                case 505: {
                    o = new hyr((Context)this.a.c.a());
                    break;
                }
                case 504: {
                    o = new tdg();
                    break;
                }
                case 503: {
                    o = new stz();
                    break;
                }
                case 502: {
                    o = ewo.e();
                    ((aade)o).getClass();
                    break;
                }
                case 501: {
                    o = new avt((byte[])null, (byte[])null, (char[])null);
                    break;
                }
                case 500: {
                    o = new adcr((byte[])null, null, (char[])null);
                    break;
                }
            }
            return o;
        }
        return this.f();
    }
}
