import java.util.Arrays;
import java.util.ArrayList;
import java.util.HashSet;
import java.lang.ref.WeakReference;

// 
// Decompiled by Procyon v0.6.0
// 

public final class act extends acz
{
    public final add a;
    public WeakReference aA;
    public WeakReference aB;
    public WeakReference aC;
    public WeakReference aD;
    final HashSet aE;
    public final ada aF;
    public ads aG;
    public final ajb aH;
    public int ar;
    public int as;
    public int at;
    public int au;
    public acq[] av;
    public acq[] aw;
    public int ax;
    public boolean ay;
    public boolean az;
    public int b;
    public boolean c;
    public final ack d;
    
    public act() {
        this.aH = new ajb(this);
        this.a = new add(this);
        this.aG = null;
        this.c = false;
        this.d = new ack();
        this.at = 0;
        this.au = 0;
        this.av = new acq[4];
        this.aw = new acq[4];
        this.ax = 257;
        this.ay = false;
        this.az = false;
        this.aA = null;
        this.aB = null;
        this.aC = null;
        this.aD = null;
        this.aE = new HashSet();
        this.aF = new ada();
    }
    
    public static void X(final acs acs, final ads ads, final ada ada) {
        if (ads == null) {
            return;
        }
        if (acs.ah != 8 && !(acs instanceof acv) && !(acs instanceof acp)) {
            ada.i = acs.M();
            ada.j = acs.N();
            ada.a = acs.j();
            ada.b = acs.h();
            ada.g = false;
            ada.h = 0;
            final boolean b = ada.i == 3;
            final boolean b2 = ada.j == 3;
            final boolean b3 = b && acs.X > 0.0f;
            final boolean b4 = b2 && acs.X > 0.0f;
            int n;
            if ((n = (b ? 1 : 0)) != 0) {
                n = (b ? 1 : 0);
                if (acs.F(0)) {
                    n = (b ? 1 : 0);
                    if (acs.s == 0) {
                        n = (b ? 1 : 0);
                        if (!b3) {
                            ada.i = 2;
                            if (b2 && acs.t == 0) {
                                ada.i = 1;
                            }
                            n = 0;
                        }
                    }
                }
            }
            boolean b5;
            if (b5 = b2) {
                b5 = b2;
                if (acs.F(1)) {
                    b5 = b2;
                    if (acs.t == 0) {
                        b5 = b2;
                        if (!b4) {
                            ada.j = 2;
                            if (n != 0 && acs.s == 0) {
                                ada.j = 1;
                            }
                            b5 = false;
                        }
                    }
                }
            }
            if (acs.e()) {
                ada.i = 1;
                n = 0;
            }
            if (acs.f()) {
                ada.j = 1;
                b5 = false;
            }
            if (b3) {
                if (acs.u[0] == 4) {
                    ada.i = 1;
                }
                else if (!b5) {
                    int n2;
                    if (ada.j == 1) {
                        n2 = ada.b;
                    }
                    else {
                        ada.i = 2;
                        ads.a(acs, ada);
                        n2 = ada.d;
                    }
                    ada.i = 1;
                    ada.a = (int)(acs.X * n2);
                }
            }
            if (b4) {
                if (acs.u[1] == 4) {
                    ada.j = 1;
                }
                else if (n == 0) {
                    int n3;
                    if (ada.i == 1) {
                        n3 = ada.a;
                    }
                    else {
                        ada.j = 2;
                        ads.a(acs, ada);
                        n3 = ada.c;
                    }
                    ada.j = 1;
                    if (acs.Y == -1) {
                        ada.b = (int)(n3 / acs.X);
                    }
                    else {
                        ada.b = (int)(acs.X * n3);
                    }
                }
            }
            ads.a(acs, ada);
            acs.C(ada.c);
            acs.x(ada.d);
            acs.F = ada.f;
            acs.u(ada.e);
            ada.h = 0;
            final boolean g = ada.g;
            return;
        }
        ada.c = 0;
        ada.d = 0;
    }
    
    private final void Z(final acr acr, final acn acn) {
        this.d.g(acn, this.d.b(acr), 0, 5);
    }
    
    private final void aa(final acr acr, final acn acn) {
        this.d.g(this.d.b(acr), acn, 0, 5);
    }
    
    private final void ab() {
        this.at = 0;
        this.au = 0;
    }
    
    public final void D(final boolean b, final boolean b2) {
        super.D(b, b2);
        for (int size = this.aI.size(), i = 0; i < size; ++i) {
            ((acs)this.aI.get(i)).D(b, b2);
        }
    }
    
    public final void T() {
        // 
        // This method could not be decompiled.
        // 
        // Original Bytecode:
        // 
        //     1: iconst_0       
        //     2: putfield        act.Z:I
        //     5: aload_0        
        //     6: iconst_0       
        //     7: putfield        act.aa:I
        //    10: aload_0        
        //    11: iconst_0       
        //    12: putfield        act.ay:Z
        //    15: aload_0        
        //    16: iconst_0       
        //    17: putfield        act.az:Z
        //    20: aload_0        
        //    21: getfield        act.aI:Ljava/util/ArrayList;
        //    24: invokevirtual   java/util/ArrayList.size:()I
        //    27: istore_3       
        //    28: iconst_0       
        //    29: aload_0        
        //    30: invokevirtual   acs.j:()I
        //    33: invokestatic    java/lang/Math.max:(II)I
        //    36: istore          5
        //    38: iconst_0       
        //    39: aload_0        
        //    40: invokevirtual   acs.h:()I
        //    43: invokestatic    java/lang/Math.max:(II)I
        //    46: istore_2       
        //    47: aload_0        
        //    48: getfield        act.aq:[I
        //    51: astore          17
        //    53: aload           17
        //    55: iconst_1       
        //    56: iaload         
        //    57: istore          6
        //    59: aload           17
        //    61: iconst_0       
        //    62: iaload         
        //    63: istore          4
        //    65: aload_0        
        //    66: getfield        act.b:I
        //    69: ifne            1156
        //    72: aload_0        
        //    73: getfield        act.ax:I
        //    76: iconst_1       
        //    77: invokestatic    acx.b:(II)Z
        //    80: ifeq            1156
        //    83: aload_0        
        //    84: getfield        act.aG:Lads;
        //    87: astore          18
        //    89: aload_0        
        //    90: invokevirtual   acs.M:()I
        //    93: istore          7
        //    95: aload_0        
        //    96: invokevirtual   acs.N:()I
        //    99: istore          12
        //   101: iconst_0       
        //   102: putstatic       adg.b:I
        //   105: iconst_0       
        //   106: putstatic       adg.c:I
        //   109: aload_0        
        //   110: invokevirtual   acs.t:()V
        //   113: aload_0        
        //   114: getfield        acz.aI:Ljava/util/ArrayList;
        //   117: astore          17
        //   119: aload           17
        //   121: invokevirtual   java/util/ArrayList.size:()I
        //   124: istore          11
        //   126: iconst_0       
        //   127: istore_1       
        //   128: iload_1        
        //   129: iload           11
        //   131: if_icmpge       152
        //   134: aload           17
        //   136: iload_1        
        //   137: invokevirtual   java/util/ArrayList.get:(I)Ljava/lang/Object;
        //   140: checkcast       Lacs;
        //   143: invokevirtual   acs.t:()V
        //   146: iinc            1, 1
        //   149: goto            128
        //   152: aload_0        
        //   153: getfield        act.c:Z
        //   156: istore          15
        //   158: iload           7
        //   160: iconst_1       
        //   161: if_icmpne       176
        //   164: aload_0        
        //   165: iconst_0       
        //   166: aload_0        
        //   167: invokevirtual   acs.j:()I
        //   170: invokevirtual   acs.v:(II)V
        //   173: goto            189
        //   176: aload_0        
        //   177: getfield        acs.J:Lacr;
        //   180: iconst_0       
        //   181: invokevirtual   acr.e:(I)V
        //   184: aload_0        
        //   185: iconst_0       
        //   186: putfield        acs.Z:I
        //   189: iconst_0       
        //   190: istore          7
        //   192: iconst_0       
        //   193: istore          8
        //   195: iconst_0       
        //   196: istore_1       
        //   197: iload           7
        //   199: iload           11
        //   201: if_icmpge       394
        //   204: aload           17
        //   206: iload           7
        //   208: invokevirtual   java/util/ArrayList.get:(I)Ljava/lang/Object;
        //   211: checkcast       Lacs;
        //   214: astore          19
        //   216: aload           19
        //   218: instanceof      Lacv;
        //   221: ifeq            341
        //   224: aload           19
        //   226: checkcast       Lacv;
        //   229: astore          19
        //   231: iload           8
        //   233: istore          10
        //   235: iload_1        
        //   236: istore          9
        //   238: aload           19
        //   240: getfield        acv.ar:I
        //   243: iconst_1       
        //   244: if_icmpne       381
        //   247: aload           19
        //   249: getfield        acv.b:I
        //   252: istore          8
        //   254: iload           8
        //   256: iconst_m1      
        //   257: if_icmpeq       276
        //   260: aload           19
        //   262: iload           8
        //   264: invokevirtual   acv.a:(I)V
        //   267: iconst_1       
        //   268: istore          10
        //   270: iload_1        
        //   271: istore          9
        //   273: goto            381
        //   276: aload           19
        //   278: getfield        acv.c:I
        //   281: iconst_m1      
        //   282: if_icmpeq       310
        //   285: aload_0        
        //   286: invokevirtual   acs.e:()Z
        //   289: ifeq            310
        //   292: aload           19
        //   294: aload_0        
        //   295: invokevirtual   acs.j:()I
        //   298: aload           19
        //   300: getfield        acv.c:I
        //   303: isub           
        //   304: invokevirtual   acv.a:(I)V
        //   307: goto            267
        //   310: aload_0        
        //   311: invokevirtual   acs.e:()Z
        //   314: ifeq            267
        //   317: aload           19
        //   319: aload           19
        //   321: getfield        acv.a:F
        //   324: aload_0        
        //   325: invokevirtual   acs.j:()I
        //   328: i2f            
        //   329: fmul           
        //   330: ldc_w           0.5
        //   333: fadd           
        //   334: f2i            
        //   335: invokevirtual   acv.a:(I)V
        //   338: goto            267
        //   341: iload           8
        //   343: istore          10
        //   345: iload_1        
        //   346: istore          9
        //   348: aload           19
        //   350: instanceof      Lacp;
        //   353: ifeq            381
        //   356: iload           8
        //   358: istore          10
        //   360: iload_1        
        //   361: istore          9
        //   363: aload           19
        //   365: checkcast       Lacp;
        //   368: invokevirtual   acp.a:()I
        //   371: ifne            381
        //   374: iconst_1       
        //   375: istore          9
        //   377: iload           8
        //   379: istore          10
        //   381: iinc            7, 1
        //   384: iload           10
        //   386: istore          8
        //   388: iload           9
        //   390: istore_1       
        //   391: goto            197
        //   394: iload           8
        //   396: ifeq            464
        //   399: iconst_0       
        //   400: istore          7
        //   402: iload           7
        //   404: iload           11
        //   406: if_icmpge       464
        //   409: aload           17
        //   411: iload           7
        //   413: invokevirtual   java/util/ArrayList.get:(I)Ljava/lang/Object;
        //   416: checkcast       Lacs;
        //   419: astore          19
        //   421: aload           19
        //   423: instanceof      Lacv;
        //   426: ifeq            458
        //   429: aload           19
        //   431: checkcast       Lacv;
        //   434: astore          19
        //   436: aload           19
        //   438: getfield        acv.ar:I
        //   441: iconst_1       
        //   442: if_icmpne       458
        //   445: iconst_0       
        //   446: aload           19
        //   448: aload           18
        //   450: iload           15
        //   452: invokestatic    adg.a:(ILacs;Lads;Z)V
        //   455: goto            458
        //   458: iinc            7, 1
        //   461: goto            402
        //   464: iconst_0       
        //   465: istore          7
        //   467: iconst_0       
        //   468: aload_0        
        //   469: aload           18
        //   471: iload           15
        //   473: invokestatic    adg.a:(ILacs;Lads;Z)V
        //   476: iload_1        
        //   477: ifeq            538
        //   480: iconst_0       
        //   481: istore_1       
        //   482: iload_1        
        //   483: iload           11
        //   485: if_icmpge       538
        //   488: aload           17
        //   490: iload_1        
        //   491: invokevirtual   java/util/ArrayList.get:(I)Ljava/lang/Object;
        //   494: checkcast       Lacs;
        //   497: astore          19
        //   499: aload           19
        //   501: instanceof      Lacp;
        //   504: ifeq            532
        //   507: aload           19
        //   509: checkcast       Lacp;
        //   512: astore          19
        //   514: aload           19
        //   516: invokevirtual   acp.a:()I
        //   519: ifne            532
        //   522: aload           19
        //   524: aload           18
        //   526: iconst_0       
        //   527: iload           15
        //   529: invokestatic    adg.d:(Lacp;Lads;IZ)V
        //   532: iinc            1, 1
        //   535: goto            482
        //   538: iload           12
        //   540: iconst_1       
        //   541: if_icmpne       561
        //   544: aload_0        
        //   545: iconst_0       
        //   546: aload_0        
        //   547: invokevirtual   acs.h:()I
        //   550: invokevirtual   acs.w:(II)V
        //   553: iconst_0       
        //   554: istore          8
        //   556: iconst_0       
        //   557: istore_1       
        //   558: goto            582
        //   561: aload_0        
        //   562: getfield        acs.K:Lacr;
        //   565: iconst_0       
        //   566: invokevirtual   acr.e:(I)V
        //   569: aload_0        
        //   570: iconst_0       
        //   571: putfield        acs.aa:I
        //   574: iconst_0       
        //   575: istore          8
        //   577: iconst_0       
        //   578: istore_1       
        //   579: iconst_0       
        //   580: istore          7
        //   582: iload           7
        //   584: iload           11
        //   586: if_icmpge       779
        //   589: aload           17
        //   591: iload           7
        //   593: invokevirtual   java/util/ArrayList.get:(I)Ljava/lang/Object;
        //   596: checkcast       Lacs;
        //   599: astore          19
        //   601: aload           19
        //   603: instanceof      Lacv;
        //   606: ifeq            725
        //   609: aload           19
        //   611: checkcast       Lacv;
        //   614: astore          19
        //   616: iload           8
        //   618: istore          9
        //   620: iload_1        
        //   621: istore          10
        //   623: aload           19
        //   625: getfield        acv.ar:I
        //   628: ifne            766
        //   631: aload           19
        //   633: getfield        acv.b:I
        //   636: istore          8
        //   638: iload           8
        //   640: iconst_m1      
        //   641: if_icmpeq       660
        //   644: aload           19
        //   646: iload           8
        //   648: invokevirtual   acv.a:(I)V
        //   651: iconst_1       
        //   652: istore          9
        //   654: iload_1        
        //   655: istore          10
        //   657: goto            766
        //   660: aload           19
        //   662: getfield        acv.c:I
        //   665: iconst_m1      
        //   666: if_icmpeq       694
        //   669: aload_0        
        //   670: invokevirtual   acs.f:()Z
        //   673: ifeq            694
        //   676: aload           19
        //   678: aload_0        
        //   679: invokevirtual   acs.h:()I
        //   682: aload           19
        //   684: getfield        acv.c:I
        //   687: isub           
        //   688: invokevirtual   acv.a:(I)V
        //   691: goto            651
        //   694: aload_0        
        //   695: invokevirtual   acs.f:()Z
        //   698: ifeq            651
        //   701: aload           19
        //   703: aload           19
        //   705: getfield        acv.a:F
        //   708: aload_0        
        //   709: invokevirtual   acs.h:()I
        //   712: i2f            
        //   713: fmul           
        //   714: ldc_w           0.5
        //   717: fadd           
        //   718: f2i            
        //   719: invokevirtual   acv.a:(I)V
        //   722: goto            651
        //   725: iload           8
        //   727: istore          9
        //   729: iload_1        
        //   730: istore          10
        //   732: aload           19
        //   734: instanceof      Lacp;
        //   737: ifeq            766
        //   740: iload           8
        //   742: istore          9
        //   744: iload_1        
        //   745: istore          10
        //   747: aload           19
        //   749: checkcast       Lacp;
        //   752: invokevirtual   acp.a:()I
        //   755: iconst_1       
        //   756: if_icmpne       766
        //   759: iconst_1       
        //   760: istore          10
        //   762: iload           8
        //   764: istore          9
        //   766: iinc            7, 1
        //   769: iload           9
        //   771: istore          8
        //   773: iload           10
        //   775: istore_1       
        //   776: goto            582
        //   779: iload           8
        //   781: ifeq            843
        //   784: iconst_0       
        //   785: istore          7
        //   787: iload           7
        //   789: iload           11
        //   791: if_icmpge       843
        //   794: aload           17
        //   796: iload           7
        //   798: invokevirtual   java/util/ArrayList.get:(I)Ljava/lang/Object;
        //   801: checkcast       Lacs;
        //   804: astore          19
        //   806: aload           19
        //   808: instanceof      Lacv;
        //   811: ifeq            837
        //   814: aload           19
        //   816: checkcast       Lacv;
        //   819: astore          19
        //   821: aload           19
        //   823: getfield        acv.ar:I
        //   826: ifne            837
        //   829: iconst_1       
        //   830: aload           19
        //   832: aload           18
        //   834: invokestatic    adg.b:(ILacs;Lads;)V
        //   837: iinc            7, 1
        //   840: goto            787
        //   843: iconst_0       
        //   844: aload_0        
        //   845: aload           18
        //   847: invokestatic    adg.b:(ILacs;Lads;)V
        //   850: iload_1        
        //   851: ifeq            913
        //   854: iconst_0       
        //   855: istore_1       
        //   856: iload_1        
        //   857: iload           11
        //   859: if_icmpge       913
        //   862: aload           17
        //   864: iload_1        
        //   865: invokevirtual   java/util/ArrayList.get:(I)Ljava/lang/Object;
        //   868: checkcast       Lacs;
        //   871: astore          19
        //   873: aload           19
        //   875: instanceof      Lacp;
        //   878: ifeq            907
        //   881: aload           19
        //   883: checkcast       Lacp;
        //   886: astore          19
        //   888: aload           19
        //   890: invokevirtual   acp.a:()I
        //   893: iconst_1       
        //   894: if_icmpne       907
        //   897: aload           19
        //   899: aload           18
        //   901: iconst_1       
        //   902: iload           15
        //   904: invokestatic    adg.d:(Lacp;Lads;IZ)V
        //   907: iinc            1, 1
        //   910: goto            856
        //   913: iconst_0       
        //   914: istore_1       
        //   915: iload_1        
        //   916: iload           11
        //   918: if_icmpge       1025
        //   921: aload           17
        //   923: iload_1        
        //   924: invokevirtual   java/util/ArrayList.get:(I)Ljava/lang/Object;
        //   927: checkcast       Lacs;
        //   930: astore          19
        //   932: aload           19
        //   934: invokevirtual   acs.J:()Z
        //   937: ifeq            1019
        //   940: aload           19
        //   942: invokestatic    adg.c:(Lacs;)Z
        //   945: ifeq            1019
        //   948: aload           19
        //   950: aload           18
        //   952: getstatic       adg.a:Lada;
        //   955: invokestatic    act.X:(Lacs;Lads;Lada;)V
        //   958: aload           19
        //   960: instanceof      Lacv;
        //   963: ifeq            1001
        //   966: aload           19
        //   968: checkcast       Lacv;
        //   971: getfield        acv.ar:I
        //   974: ifne            988
        //   977: iconst_0       
        //   978: aload           19
        //   980: aload           18
        //   982: invokestatic    adg.b:(ILacs;Lads;)V
        //   985: goto            1019
        //   988: iconst_0       
        //   989: aload           19
        //   991: aload           18
        //   993: iload           15
        //   995: invokestatic    adg.a:(ILacs;Lads;Z)V
        //   998: goto            1019
        //  1001: iconst_0       
        //  1002: aload           19
        //  1004: aload           18
        //  1006: iload           15
        //  1008: invokestatic    adg.a:(ILacs;Lads;Z)V
        //  1011: iconst_0       
        //  1012: aload           19
        //  1014: aload           18
        //  1016: invokestatic    adg.b:(ILacs;Lads;)V
        //  1019: iinc            1, 1
        //  1022: goto            915
        //  1025: iconst_0       
        //  1026: istore_1       
        //  1027: iload_1        
        //  1028: iload_3        
        //  1029: if_icmpge       1156
        //  1032: aload_0        
        //  1033: getfield        act.aI:Ljava/util/ArrayList;
        //  1036: iload_1        
        //  1037: invokevirtual   java/util/ArrayList.get:(I)Ljava/lang/Object;
        //  1040: checkcast       Lacs;
        //  1043: astore          17
        //  1045: aload           17
        //  1047: invokevirtual   acs.J:()Z
        //  1050: ifeq            1150
        //  1053: aload           17
        //  1055: instanceof      Lacv;
        //  1058: ifne            1150
        //  1061: aload           17
        //  1063: instanceof      Lacp;
        //  1066: ifne            1150
        //  1069: aload           17
        //  1071: instanceof      Lacy;
        //  1074: ifne            1150
        //  1077: aload           17
        //  1079: getfield        acs.G:Z
        //  1082: istore          15
        //  1084: aload           17
        //  1086: iconst_0       
        //  1087: invokevirtual   acs.L:(I)I
        //  1090: istore          8
        //  1092: aload           17
        //  1094: iconst_1       
        //  1095: invokevirtual   acs.L:(I)I
        //  1098: istore          7
        //  1100: iload           8
        //  1102: iconst_3       
        //  1103: if_icmpne       1130
        //  1106: aload           17
        //  1108: getfield        acs.s:I
        //  1111: iconst_1       
        //  1112: if_icmpeq       1130
        //  1115: iload           7
        //  1117: iconst_3       
        //  1118: if_icmpne       1130
        //  1121: aload           17
        //  1123: getfield        acs.t:I
        //  1126: iconst_1       
        //  1127: if_icmpne       1150
        //  1130: new             Lada;
        //  1133: dup            
        //  1134: invokespecial   ada.<init>:()V
        //  1137: astore          18
        //  1139: aload           17
        //  1141: aload_0        
        //  1142: getfield        act.aG:Lads;
        //  1145: aload           18
        //  1147: invokestatic    act.X:(Lacs;Lads;Lada;)V
        //  1150: iinc            1, 1
        //  1153: goto            1027
        //  1156: iload           6
        //  1158: istore          7
        //  1160: iload_3        
        //  1161: iconst_2       
        //  1162: if_icmple       3197
        //  1165: iload           6
        //  1167: istore_1       
        //  1168: iload           4
        //  1170: iconst_2       
        //  1171: if_icmpeq       1203
        //  1174: iload           6
        //  1176: istore_1       
        //  1177: iload           6
        //  1179: iconst_2       
        //  1180: if_icmpne       1188
        //  1183: iconst_2       
        //  1184: istore_1       
        //  1185: goto            1203
        //  1188: iload_1        
        //  1189: istore          7
        //  1191: iconst_0       
        //  1192: istore_1       
        //  1193: iload           4
        //  1195: istore          6
        //  1197: iload_3        
        //  1198: istore          8
        //  1200: goto            3206
        //  1203: iload_1        
        //  1204: istore          7
        //  1206: aload_0        
        //  1207: getfield        act.ax:I
        //  1210: sipush          1024
        //  1213: invokestatic    acx.b:(II)Z
        //  1216: ifeq            3197
        //  1219: aload_0        
        //  1220: getfield        act.aG:Lads;
        //  1223: astore          29
        //  1225: aload_0        
        //  1226: getfield        acz.aI:Ljava/util/ArrayList;
        //  1229: astore          28
        //  1231: aload           28
        //  1233: invokevirtual   java/util/ArrayList.size:()I
        //  1236: istore          7
        //  1238: iconst_0       
        //  1239: istore          6
        //  1241: iload           6
        //  1243: iload           7
        //  1245: if_icmpge       1304
        //  1248: aload           28
        //  1250: iload           6
        //  1252: invokevirtual   java/util/ArrayList.get:(I)Ljava/lang/Object;
        //  1255: checkcast       Lacs;
        //  1258: astore          17
        //  1260: aload_0        
        //  1261: invokevirtual   acs.M:()I
        //  1264: aload_0        
        //  1265: invokevirtual   acs.N:()I
        //  1268: aload           17
        //  1270: invokevirtual   acs.M:()I
        //  1273: aload           17
        //  1275: invokevirtual   acs.N:()I
        //  1278: invokestatic    sq.f:(IIII)Z
        //  1281: ifne            1287
        //  1284: goto            1188
        //  1287: aload           17
        //  1289: instanceof      Lacu;
        //  1292: ifeq            1298
        //  1295: goto            1188
        //  1298: iinc            6, 1
        //  1301: goto            1241
        //  1304: aconst_null    
        //  1305: astore          23
        //  1307: iconst_0       
        //  1308: istore          6
        //  1310: aconst_null    
        //  1311: astore          17
        //  1313: aconst_null    
        //  1314: astore          19
        //  1316: aconst_null    
        //  1317: astore          18
        //  1319: aconst_null    
        //  1320: astore          21
        //  1322: aconst_null    
        //  1323: astore          20
        //  1325: iload_3        
        //  1326: istore          8
        //  1328: iload_1        
        //  1329: istore_3       
        //  1330: iload_2        
        //  1331: istore_1       
        //  1332: iload           5
        //  1334: istore_2       
        //  1335: iload           6
        //  1337: iload           7
        //  1339: if_icmpge       1890
        //  1342: aload           28
        //  1344: iload           6
        //  1346: invokevirtual   java/util/ArrayList.get:(I)Ljava/lang/Object;
        //  1349: checkcast       Lacs;
        //  1352: astore          30
        //  1354: aload_0        
        //  1355: invokevirtual   acs.M:()I
        //  1358: aload_0        
        //  1359: invokevirtual   acs.N:()I
        //  1362: aload           30
        //  1364: invokevirtual   acs.M:()I
        //  1367: aload           30
        //  1369: invokevirtual   acs.N:()I
        //  1372: invokestatic    sq.f:(IIII)Z
        //  1375: ifne            1389
        //  1378: aload           30
        //  1380: aload           29
        //  1382: aload_0        
        //  1383: getfield        act.aF:Lada;
        //  1386: invokestatic    act.X:(Lacs;Lads;Lada;)V
        //  1389: aload           30
        //  1391: instanceof      Lacv;
        //  1394: istore          15
        //  1396: aload           23
        //  1398: astore          25
        //  1400: aload           19
        //  1402: astore          24
        //  1404: iload           15
        //  1406: ifeq            1505
        //  1409: aload           30
        //  1411: checkcast       Lacv;
        //  1414: astore          26
        //  1416: aload           19
        //  1418: astore          22
        //  1420: aload           26
        //  1422: getfield        acv.ar:I
        //  1425: ifne            1454
        //  1428: aload           19
        //  1430: astore          22
        //  1432: aload           19
        //  1434: ifnonnull       1446
        //  1437: new             Ljava/util/ArrayList;
        //  1440: dup            
        //  1441: invokespecial   java/util/ArrayList.<init>:()V
        //  1444: astore          22
        //  1446: aload           22
        //  1448: aload           26
        //  1450: invokevirtual   java/util/ArrayList.add:(Ljava/lang/Object;)Z
        //  1453: pop            
        //  1454: aload           23
        //  1456: astore          25
        //  1458: aload           22
        //  1460: astore          24
        //  1462: aload           26
        //  1464: getfield        acv.ar:I
        //  1467: iconst_1       
        //  1468: if_icmpne       1505
        //  1471: aload           23
        //  1473: astore          19
        //  1475: aload           23
        //  1477: ifnonnull       1489
        //  1480: new             Ljava/util/ArrayList;
        //  1483: dup            
        //  1484: invokespecial   java/util/ArrayList.<init>:()V
        //  1487: astore          19
        //  1489: aload           19
        //  1491: aload           26
        //  1493: invokevirtual   java/util/ArrayList.add:(Ljava/lang/Object;)Z
        //  1496: pop            
        //  1497: aload           22
        //  1499: astore          24
        //  1501: aload           19
        //  1503: astore          25
        //  1505: aload           17
        //  1507: astore          19
        //  1509: aload           18
        //  1511: astore          22
        //  1513: aload           30
        //  1515: instanceof      Lacw;
        //  1518: ifeq            1683
        //  1521: aload           30
        //  1523: instanceof      Lacp;
        //  1526: ifeq            1624
        //  1529: aload           30
        //  1531: checkcast       Lacp;
        //  1534: astore          26
        //  1536: aload           17
        //  1538: astore          23
        //  1540: aload           26
        //  1542: invokevirtual   acp.a:()I
        //  1545: ifne            1574
        //  1548: aload           17
        //  1550: astore          23
        //  1552: aload           17
        //  1554: ifnonnull       1566
        //  1557: new             Ljava/util/ArrayList;
        //  1560: dup            
        //  1561: invokespecial   java/util/ArrayList.<init>:()V
        //  1564: astore          23
        //  1566: aload           23
        //  1568: aload           26
        //  1570: invokevirtual   java/util/ArrayList.add:(Ljava/lang/Object;)Z
        //  1573: pop            
        //  1574: aload           23
        //  1576: astore          19
        //  1578: aload           18
        //  1580: astore          22
        //  1582: aload           26
        //  1584: invokevirtual   acp.a:()I
        //  1587: iconst_1       
        //  1588: if_icmpne       1683
        //  1591: aload           18
        //  1593: astore          22
        //  1595: aload           18
        //  1597: ifnonnull       1609
        //  1600: new             Ljava/util/ArrayList;
        //  1603: dup            
        //  1604: invokespecial   java/util/ArrayList.<init>:()V
        //  1607: astore          22
        //  1609: aload           22
        //  1611: aload           26
        //  1613: invokevirtual   java/util/ArrayList.add:(Ljava/lang/Object;)Z
        //  1616: pop            
        //  1617: aload           23
        //  1619: astore          19
        //  1621: goto            1683
        //  1624: aload           30
        //  1626: checkcast       Lacw;
        //  1629: astore          23
        //  1631: aload           17
        //  1633: astore          19
        //  1635: aload           17
        //  1637: ifnonnull       1649
        //  1640: new             Ljava/util/ArrayList;
        //  1643: dup            
        //  1644: invokespecial   java/util/ArrayList.<init>:()V
        //  1647: astore          19
        //  1649: aload           19
        //  1651: aload           23
        //  1653: invokevirtual   java/util/ArrayList.add:(Ljava/lang/Object;)Z
        //  1656: pop            
        //  1657: aload           18
        //  1659: astore          22
        //  1661: aload           18
        //  1663: ifnonnull       1675
        //  1666: new             Ljava/util/ArrayList;
        //  1669: dup            
        //  1670: invokespecial   java/util/ArrayList.<init>:()V
        //  1673: astore          22
        //  1675: aload           22
        //  1677: aload           23
        //  1679: invokevirtual   java/util/ArrayList.add:(Ljava/lang/Object;)Z
        //  1682: pop            
        //  1683: aload           21
        //  1685: astore          26
        //  1687: aload           30
        //  1689: getfield        acs.J:Lacr;
        //  1692: getfield        acr.e:Lacr;
        //  1695: ifnonnull       1764
        //  1698: aload           21
        //  1700: astore          26
        //  1702: aload           30
        //  1704: getfield        acs.L:Lacr;
        //  1707: getfield        acr.e:Lacr;
        //  1710: ifnonnull       1764
        //  1713: aload           21
        //  1715: astore          26
        //  1717: iload           15
        //  1719: ifne            1764
        //  1722: aload           21
        //  1724: astore          26
        //  1726: aload           30
        //  1728: instanceof      Lacp;
        //  1731: ifne            1764
        //  1734: aload           21
        //  1736: astore          17
        //  1738: aload           21
        //  1740: ifnonnull       1752
        //  1743: new             Ljava/util/ArrayList;
        //  1746: dup            
        //  1747: invokespecial   java/util/ArrayList.<init>:()V
        //  1750: astore          17
        //  1752: aload           17
        //  1754: aload           30
        //  1756: invokevirtual   java/util/ArrayList.add:(Ljava/lang/Object;)Z
        //  1759: pop            
        //  1760: aload           17
        //  1762: astore          26
        //  1764: aload           20
        //  1766: astore          27
        //  1768: aload           30
        //  1770: getfield        acs.K:Lacr;
        //  1773: getfield        acr.e:Lacr;
        //  1776: ifnonnull       1860
        //  1779: aload           20
        //  1781: astore          27
        //  1783: aload           30
        //  1785: getfield        acs.M:Lacr;
        //  1788: getfield        acr.e:Lacr;
        //  1791: ifnonnull       1860
        //  1794: aload           20
        //  1796: astore          27
        //  1798: aload           30
        //  1800: getfield        acs.N:Lacr;
        //  1803: getfield        acr.e:Lacr;
        //  1806: ifnonnull       1860
        //  1809: aload           20
        //  1811: astore          27
        //  1813: iload           15
        //  1815: ifne            1860
        //  1818: aload           20
        //  1820: astore          27
        //  1822: aload           30
        //  1824: instanceof      Lacp;
        //  1827: ifne            1860
        //  1830: aload           20
        //  1832: astore          17
        //  1834: aload           20
        //  1836: ifnonnull       1848
        //  1839: new             Ljava/util/ArrayList;
        //  1842: dup            
        //  1843: invokespecial   java/util/ArrayList.<init>:()V
        //  1846: astore          17
        //  1848: aload           17
        //  1850: aload           30
        //  1852: invokevirtual   java/util/ArrayList.add:(Ljava/lang/Object;)Z
        //  1855: pop            
        //  1856: aload           17
        //  1858: astore          27
        //  1860: iinc            6, 1
        //  1863: aload           25
        //  1865: astore          23
        //  1867: aload           19
        //  1869: astore          17
        //  1871: aload           24
        //  1873: astore          19
        //  1875: aload           22
        //  1877: astore          18
        //  1879: aload           26
        //  1881: astore          21
        //  1883: aload           27
        //  1885: astore          20
        //  1887: goto            1335
        //  1890: new             Ljava/util/ArrayList;
        //  1893: dup            
        //  1894: invokespecial   java/util/ArrayList.<init>:()V
        //  1897: astore          22
        //  1899: aload           23
        //  1901: ifnull          1949
        //  1904: aload           23
        //  1906: invokeinterface java/util/List.size:()I
        //  1911: istore          6
        //  1913: iconst_0       
        //  1914: istore          5
        //  1916: iload           5
        //  1918: iload           6
        //  1920: if_icmpge       1949
        //  1923: aload           23
        //  1925: iload           5
        //  1927: invokeinterface java/util/List.get:(I)Ljava/lang/Object;
        //  1932: checkcast       Lacv;
        //  1935: iconst_0       
        //  1936: aload           22
        //  1938: aconst_null    
        //  1939: invokestatic    sq.d:(Lacs;ILjava/util/ArrayList;Ladm;)Ladm;
        //  1942: pop            
        //  1943: iinc            5, 1
        //  1946: goto            1916
        //  1949: aload           17
        //  1951: ifnull          2021
        //  1954: aload           17
        //  1956: invokeinterface java/util/List.size:()I
        //  1961: istore          6
        //  1963: iconst_0       
        //  1964: istore          5
        //  1966: iload           5
        //  1968: iload           6
        //  1970: if_icmpge       2021
        //  1973: aload           17
        //  1975: iload           5
        //  1977: invokeinterface java/util/List.get:(I)Ljava/lang/Object;
        //  1982: checkcast       Lacw;
        //  1985: astore          24
        //  1987: aload           24
        //  1989: iconst_0       
        //  1990: aload           22
        //  1992: aconst_null    
        //  1993: invokestatic    sq.d:(Lacs;ILjava/util/ArrayList;Ladm;)Ladm;
        //  1996: astore          23
        //  1998: aload           24
        //  2000: aload           22
        //  2002: iconst_0       
        //  2003: aload           23
        //  2005: invokevirtual   acw.T:(Ljava/util/ArrayList;ILadm;)V
        //  2008: aload           23
        //  2010: aload           22
        //  2012: invokevirtual   adm.b:(Ljava/util/ArrayList;)V
        //  2015: iinc            5, 1
        //  2018: goto            1966
        //  2021: aload_0        
        //  2022: iconst_2       
        //  2023: invokevirtual   acs.K:(I)Lacr;
        //  2026: getfield        acr.a:Ljava/util/HashSet;
        //  2029: astore          17
        //  2031: aload           17
        //  2033: ifnull          2077
        //  2036: aload           17
        //  2038: invokevirtual   java/util/HashSet.iterator:()Ljava/util/Iterator;
        //  2041: astore          17
        //  2043: aload           17
        //  2045: invokeinterface java/util/Iterator.hasNext:()Z
        //  2050: ifeq            2077
        //  2053: aload           17
        //  2055: invokeinterface java/util/Iterator.next:()Ljava/lang/Object;
        //  2060: checkcast       Lacr;
        //  2063: getfield        acr.d:Lacs;
        //  2066: iconst_0       
        //  2067: aload           22
        //  2069: aconst_null    
        //  2070: invokestatic    sq.d:(Lacs;ILjava/util/ArrayList;Ladm;)Ladm;
        //  2073: pop            
        //  2074: goto            2043
        //  2077: aload_0        
        //  2078: iconst_4       
        //  2079: invokevirtual   acs.K:(I)Lacr;
        //  2082: getfield        acr.a:Ljava/util/HashSet;
        //  2085: astore          17
        //  2087: aload           17
        //  2089: ifnull          2133
        //  2092: aload           17
        //  2094: invokevirtual   java/util/HashSet.iterator:()Ljava/util/Iterator;
        //  2097: astore          17
        //  2099: aload           17
        //  2101: invokeinterface java/util/Iterator.hasNext:()Z
        //  2106: ifeq            2133
        //  2109: aload           17
        //  2111: invokeinterface java/util/Iterator.next:()Ljava/lang/Object;
        //  2116: checkcast       Lacr;
        //  2119: getfield        acr.d:Lacs;
        //  2122: iconst_0       
        //  2123: aload           22
        //  2125: aconst_null    
        //  2126: invokestatic    sq.d:(Lacs;ILjava/util/ArrayList;Ladm;)Ladm;
        //  2129: pop            
        //  2130: goto            2099
        //  2133: aload_0        
        //  2134: bipush          7
        //  2136: invokevirtual   acs.K:(I)Lacr;
        //  2139: getfield        acr.a:Ljava/util/HashSet;
        //  2142: astore          17
        //  2144: aload           17
        //  2146: ifnull          2190
        //  2149: aload           17
        //  2151: invokevirtual   java/util/HashSet.iterator:()Ljava/util/Iterator;
        //  2154: astore          17
        //  2156: aload           17
        //  2158: invokeinterface java/util/Iterator.hasNext:()Z
        //  2163: ifeq            2190
        //  2166: aload           17
        //  2168: invokeinterface java/util/Iterator.next:()Ljava/lang/Object;
        //  2173: checkcast       Lacr;
        //  2176: getfield        acr.d:Lacs;
        //  2179: iconst_0       
        //  2180: aload           22
        //  2182: aconst_null    
        //  2183: invokestatic    sq.d:(Lacs;ILjava/util/ArrayList;Ladm;)Ladm;
        //  2186: pop            
        //  2187: goto            2156
        //  2190: aload           21
        //  2192: ifnull          2240
        //  2195: aload           21
        //  2197: invokeinterface java/util/List.size:()I
        //  2202: istore          6
        //  2204: iconst_0       
        //  2205: istore          5
        //  2207: iload           5
        //  2209: iload           6
        //  2211: if_icmpge       2240
        //  2214: aload           21
        //  2216: iload           5
        //  2218: invokeinterface java/util/List.get:(I)Ljava/lang/Object;
        //  2223: checkcast       Lacs;
        //  2226: iconst_0       
        //  2227: aload           22
        //  2229: aconst_null    
        //  2230: invokestatic    sq.d:(Lacs;ILjava/util/ArrayList;Ladm;)Ladm;
        //  2233: pop            
        //  2234: iinc            5, 1
        //  2237: goto            2207
        //  2240: aload           19
        //  2242: ifnull          2290
        //  2245: aload           19
        //  2247: invokeinterface java/util/List.size:()I
        //  2252: istore          6
        //  2254: iconst_0       
        //  2255: istore          5
        //  2257: iload           5
        //  2259: iload           6
        //  2261: if_icmpge       2290
        //  2264: aload           19
        //  2266: iload           5
        //  2268: invokeinterface java/util/List.get:(I)Ljava/lang/Object;
        //  2273: checkcast       Lacv;
        //  2276: iconst_1       
        //  2277: aload           22
        //  2279: aconst_null    
        //  2280: invokestatic    sq.d:(Lacs;ILjava/util/ArrayList;Ladm;)Ladm;
        //  2283: pop            
        //  2284: iinc            5, 1
        //  2287: goto            2257
        //  2290: aload           18
        //  2292: ifnull          2362
        //  2295: aload           18
        //  2297: invokeinterface java/util/List.size:()I
        //  2302: istore          6
        //  2304: iconst_0       
        //  2305: istore          5
        //  2307: iload           5
        //  2309: iload           6
        //  2311: if_icmpge       2362
        //  2314: aload           18
        //  2316: iload           5
        //  2318: invokeinterface java/util/List.get:(I)Ljava/lang/Object;
        //  2323: checkcast       Lacw;
        //  2326: astore          19
        //  2328: aload           19
        //  2330: iconst_1       
        //  2331: aload           22
        //  2333: aconst_null    
        //  2334: invokestatic    sq.d:(Lacs;ILjava/util/ArrayList;Ladm;)Ladm;
        //  2337: astore          17
        //  2339: aload           19
        //  2341: aload           22
        //  2343: iconst_1       
        //  2344: aload           17
        //  2346: invokevirtual   acw.T:(Ljava/util/ArrayList;ILadm;)V
        //  2349: aload           17
        //  2351: aload           22
        //  2353: invokevirtual   adm.b:(Ljava/util/ArrayList;)V
        //  2356: iinc            5, 1
        //  2359: goto            2307
        //  2362: aload_0        
        //  2363: iconst_3       
        //  2364: invokevirtual   acs.K:(I)Lacr;
        //  2367: getfield        acr.a:Ljava/util/HashSet;
        //  2370: astore          17
        //  2372: aload           17
        //  2374: ifnull          2418
        //  2377: aload           17
        //  2379: invokevirtual   java/util/HashSet.iterator:()Ljava/util/Iterator;
        //  2382: astore          17
        //  2384: aload           17
        //  2386: invokeinterface java/util/Iterator.hasNext:()Z
        //  2391: ifeq            2418
        //  2394: aload           17
        //  2396: invokeinterface java/util/Iterator.next:()Ljava/lang/Object;
        //  2401: checkcast       Lacr;
        //  2404: getfield        acr.d:Lacs;
        //  2407: iconst_1       
        //  2408: aload           22
        //  2410: aconst_null    
        //  2411: invokestatic    sq.d:(Lacs;ILjava/util/ArrayList;Ladm;)Ladm;
        //  2414: pop            
        //  2415: goto            2384
        //  2418: aload_0        
        //  2419: bipush          6
        //  2421: invokevirtual   acs.K:(I)Lacr;
        //  2424: getfield        acr.a:Ljava/util/HashSet;
        //  2427: astore          17
        //  2429: aload           17
        //  2431: ifnull          2475
        //  2434: aload           17
        //  2436: invokevirtual   java/util/HashSet.iterator:()Ljava/util/Iterator;
        //  2439: astore          17
        //  2441: aload           17
        //  2443: invokeinterface java/util/Iterator.hasNext:()Z
        //  2448: ifeq            2475
        //  2451: aload           17
        //  2453: invokeinterface java/util/Iterator.next:()Ljava/lang/Object;
        //  2458: checkcast       Lacr;
        //  2461: getfield        acr.d:Lacs;
        //  2464: iconst_1       
        //  2465: aload           22
        //  2467: aconst_null    
        //  2468: invokestatic    sq.d:(Lacs;ILjava/util/ArrayList;Ladm;)Ladm;
        //  2471: pop            
        //  2472: goto            2441
        //  2475: aload_0        
        //  2476: iconst_5       
        //  2477: invokevirtual   acs.K:(I)Lacr;
        //  2480: getfield        acr.a:Ljava/util/HashSet;
        //  2483: astore          17
        //  2485: aload           17
        //  2487: ifnull          2531
        //  2490: aload           17
        //  2492: invokevirtual   java/util/HashSet.iterator:()Ljava/util/Iterator;
        //  2495: astore          17
        //  2497: aload           17
        //  2499: invokeinterface java/util/Iterator.hasNext:()Z
        //  2504: ifeq            2531
        //  2507: aload           17
        //  2509: invokeinterface java/util/Iterator.next:()Ljava/lang/Object;
        //  2514: checkcast       Lacr;
        //  2517: getfield        acr.d:Lacs;
        //  2520: iconst_1       
        //  2521: aload           22
        //  2523: aconst_null    
        //  2524: invokestatic    sq.d:(Lacs;ILjava/util/ArrayList;Ladm;)Ladm;
        //  2527: pop            
        //  2528: goto            2497
        //  2531: aload_0        
        //  2532: bipush          7
        //  2534: invokevirtual   acs.K:(I)Lacr;
        //  2537: getfield        acr.a:Ljava/util/HashSet;
        //  2540: astore          17
        //  2542: aload           17
        //  2544: ifnull          2588
        //  2547: aload           17
        //  2549: invokevirtual   java/util/HashSet.iterator:()Ljava/util/Iterator;
        //  2552: astore          17
        //  2554: aload           17
        //  2556: invokeinterface java/util/Iterator.hasNext:()Z
        //  2561: ifeq            2588
        //  2564: aload           17
        //  2566: invokeinterface java/util/Iterator.next:()Ljava/lang/Object;
        //  2571: checkcast       Lacr;
        //  2574: getfield        acr.d:Lacs;
        //  2577: iconst_1       
        //  2578: aload           22
        //  2580: aconst_null    
        //  2581: invokestatic    sq.d:(Lacs;ILjava/util/ArrayList;Ladm;)Ladm;
        //  2584: pop            
        //  2585: goto            2554
        //  2588: aload           20
        //  2590: ifnull          2638
        //  2593: aload           20
        //  2595: invokeinterface java/util/List.size:()I
        //  2600: istore          6
        //  2602: iconst_0       
        //  2603: istore          5
        //  2605: iload           5
        //  2607: iload           6
        //  2609: if_icmpge       2638
        //  2612: aload           20
        //  2614: iload           5
        //  2616: invokeinterface java/util/List.get:(I)Ljava/lang/Object;
        //  2621: checkcast       Lacs;
        //  2624: iconst_1       
        //  2625: aload           22
        //  2627: aconst_null    
        //  2628: invokestatic    sq.d:(Lacs;ILjava/util/ArrayList;Ladm;)Ladm;
        //  2631: pop            
        //  2632: iinc            5, 1
        //  2635: goto            2605
        //  2638: iconst_0       
        //  2639: istore          5
        //  2641: iload           5
        //  2643: iload           7
        //  2645: if_icmpge       2745
        //  2648: aload           28
        //  2650: iload           5
        //  2652: invokevirtual   java/util/ArrayList.get:(I)Ljava/lang/Object;
        //  2655: checkcast       Lacs;
        //  2658: astore          17
        //  2660: aload           17
        //  2662: getfield        acs.aq:[I
        //  2665: astore          18
        //  2667: aload           18
        //  2669: iconst_0       
        //  2670: iaload         
        //  2671: iconst_3       
        //  2672: if_icmpne       2739
        //  2675: aload           18
        //  2677: iconst_1       
        //  2678: iaload         
        //  2679: iconst_3       
        //  2680: if_icmpne       2739
        //  2683: aload           22
        //  2685: aload           17
        //  2687: getfield        acs.ao:I
        //  2690: invokestatic    sq.e:(Ljava/util/ArrayList;I)Ladm;
        //  2693: astore          18
        //  2695: aload           22
        //  2697: aload           17
        //  2699: getfield        acs.ap:I
        //  2702: invokestatic    sq.e:(Ljava/util/ArrayList;I)Ladm;
        //  2705: astore          17
        //  2707: aload           18
        //  2709: ifnull          2739
        //  2712: aload           17
        //  2714: ifnull          2739
        //  2717: aload           18
        //  2719: iconst_0       
        //  2720: aload           17
        //  2722: invokevirtual   adm.c:(ILadm;)V
        //  2725: aload           17
        //  2727: iconst_2       
        //  2728: putfield        adm.d:I
        //  2731: aload           22
        //  2733: aload           18
        //  2735: invokevirtual   java/util/ArrayList.remove:(Ljava/lang/Object;)Z
        //  2738: pop            
        //  2739: iinc            5, 1
        //  2742: goto            2641
        //  2745: aload           22
        //  2747: invokevirtual   java/util/ArrayList.size:()I
        //  2750: iconst_1       
        //  2751: if_icmpgt       2769
        //  2754: iload_2        
        //  2755: istore          5
        //  2757: iload_1        
        //  2758: istore_2       
        //  2759: iload           4
        //  2761: istore          6
        //  2763: iload_3        
        //  2764: istore          7
        //  2766: goto            3204
        //  2769: aload_0        
        //  2770: invokevirtual   acs.M:()I
        //  2773: iconst_2       
        //  2774: if_icmpne       2916
        //  2777: aload           22
        //  2779: invokeinterface java/util/List.size:()I
        //  2784: istore          10
        //  2786: aconst_null    
        //  2787: astore          17
        //  2789: iconst_0       
        //  2790: istore          5
        //  2792: iconst_0       
        //  2793: istore          6
        //  2795: iload           5
        //  2797: iload           10
        //  2799: if_icmpge       2893
        //  2802: aload           22
        //  2804: iload           5
        //  2806: invokeinterface java/util/List.get:(I)Ljava/lang/Object;
        //  2811: checkcast       Ladm;
        //  2814: astore          19
        //  2816: aload           17
        //  2818: astore          18
        //  2820: iload           6
        //  2822: istore          7
        //  2824: aload           19
        //  2826: getfield        adm.d:I
        //  2829: iconst_1       
        //  2830: if_icmpeq       2879
        //  2833: aload           19
        //  2835: aload_0        
        //  2836: getfield        act.d:Lack;
        //  2839: iconst_0       
        //  2840: invokevirtual   adm.a:(Lack;I)I
        //  2843: istore          9
        //  2845: iload           9
        //  2847: iload           6
        //  2849: if_icmple       2856
        //  2852: aload           19
        //  2854: astore          17
        //  2856: aload           17
        //  2858: astore          18
        //  2860: iload           6
        //  2862: istore          7
        //  2864: iload           9
        //  2866: iload           6
        //  2868: if_icmple       2879
        //  2871: iload           9
        //  2873: istore          7
        //  2875: aload           17
        //  2877: astore          18
        //  2879: iinc            5, 1
        //  2882: aload           18
        //  2884: astore          17
        //  2886: iload           7
        //  2888: istore          6
        //  2890: goto            2795
        //  2893: aload           17
        //  2895: ifnull          2916
        //  2898: aload_0        
        //  2899: iconst_1       
        //  2900: invokevirtual   acs.P:(I)V
        //  2903: aload_0        
        //  2904: iload           6
        //  2906: invokevirtual   acs.C:(I)V
        //  2909: aload           17
        //  2911: astore          18
        //  2913: goto            2919
        //  2916: aconst_null    
        //  2917: astore          18
        //  2919: aload_0        
        //  2920: invokevirtual   acs.N:()I
        //  2923: iconst_2       
        //  2924: if_icmpne       3061
        //  2927: aload           22
        //  2929: invokeinterface java/util/List.size:()I
        //  2934: istore          10
        //  2936: aconst_null    
        //  2937: astore          17
        //  2939: iconst_0       
        //  2940: istore          7
        //  2942: iconst_0       
        //  2943: istore          6
        //  2945: iload           7
        //  2947: iload           10
        //  2949: if_icmpge       3042
        //  2952: aload           22
        //  2954: iload           7
        //  2956: invokeinterface java/util/List.get:(I)Ljava/lang/Object;
        //  2961: checkcast       Ladm;
        //  2964: astore          20
        //  2966: aload           17
        //  2968: astore          19
        //  2970: iload           6
        //  2972: istore          5
        //  2974: aload           20
        //  2976: getfield        adm.d:I
        //  2979: ifeq            3028
        //  2982: aload           20
        //  2984: aload_0        
        //  2985: getfield        act.d:Lack;
        //  2988: iconst_1       
        //  2989: invokevirtual   adm.a:(Lack;I)I
        //  2992: istore          9
        //  2994: iload           9
        //  2996: iload           6
        //  2998: if_icmple       3005
        //  3001: aload           20
        //  3003: astore          17
        //  3005: aload           17
        //  3007: astore          19
        //  3009: iload           6
        //  3011: istore          5
        //  3013: iload           9
        //  3015: iload           6
        //  3017: if_icmple       3028
        //  3020: iload           9
        //  3022: istore          5
        //  3024: aload           17
        //  3026: astore          19
        //  3028: iinc            7, 1
        //  3031: aload           19
        //  3033: astore          17
        //  3035: iload           5
        //  3037: istore          6
        //  3039: goto            2945
        //  3042: aload           17
        //  3044: ifnull          3061
        //  3047: aload_0        
        //  3048: iconst_1       
        //  3049: invokevirtual   acs.Q:(I)V
        //  3052: aload_0        
        //  3053: iload           6
        //  3055: invokevirtual   acs.x:(I)V
        //  3058: goto            3064
        //  3061: aconst_null    
        //  3062: astore          17
        //  3064: aload           18
        //  3066: ifnonnull       3074
        //  3069: aload           17
        //  3071: ifnull          2754
        //  3074: iload           4
        //  3076: iconst_2       
        //  3077: if_icmpne       3119
        //  3080: iload_2        
        //  3081: aload_0        
        //  3082: invokevirtual   acs.j:()I
        //  3085: if_icmpge       3108
        //  3088: iload_2        
        //  3089: ifle            3108
        //  3092: aload_0        
        //  3093: iload_2        
        //  3094: invokevirtual   acs.C:(I)V
        //  3097: aload_0        
        //  3098: iconst_1       
        //  3099: putfield        act.ay:Z
        //  3102: iload_2        
        //  3103: istore          4
        //  3105: goto            3114
        //  3108: aload_0        
        //  3109: invokevirtual   acs.j:()I
        //  3112: istore          4
        //  3114: iconst_2       
        //  3115: istore_2       
        //  3116: goto            3129
        //  3119: iload           4
        //  3121: istore          5
        //  3123: iload_2        
        //  3124: istore          4
        //  3126: iload           5
        //  3128: istore_2       
        //  3129: iload_3        
        //  3130: istore          5
        //  3132: iload           5
        //  3134: iconst_2       
        //  3135: if_icmpne       3175
        //  3138: iload_1        
        //  3139: aload_0        
        //  3140: invokevirtual   acs.h:()I
        //  3143: if_icmpge       3165
        //  3146: iload_1        
        //  3147: ifle            3165
        //  3150: aload_0        
        //  3151: iload_1        
        //  3152: invokevirtual   acs.x:(I)V
        //  3155: aload_0        
        //  3156: iconst_1       
        //  3157: putfield        act.az:Z
        //  3160: iload_1        
        //  3161: istore_3       
        //  3162: goto            3170
        //  3165: aload_0        
        //  3166: invokevirtual   acs.h:()I
        //  3169: istore_3       
        //  3170: iconst_2       
        //  3171: istore_1       
        //  3172: goto            3180
        //  3175: iload_1        
        //  3176: istore_3       
        //  3177: iload           5
        //  3179: istore_1       
        //  3180: iload_2        
        //  3181: istore          6
        //  3183: iload_1        
        //  3184: istore          7
        //  3186: iconst_1       
        //  3187: istore_1       
        //  3188: iload           4
        //  3190: istore          5
        //  3192: iload_3        
        //  3193: istore_2       
        //  3194: goto            3206
        //  3197: iload_3        
        //  3198: istore          8
        //  3200: iload           4
        //  3202: istore          6
        //  3204: iconst_0       
        //  3205: istore_1       
        //  3206: aload_0        
        //  3207: bipush          64
        //  3209: invokevirtual   act.W:(I)Z
        //  3212: ifne            3233
        //  3215: aload_0        
        //  3216: sipush          128
        //  3219: invokevirtual   act.W:(I)Z
        //  3222: ifeq            3228
        //  3225: goto            3233
        //  3228: iconst_0       
        //  3229: istore_3       
        //  3230: goto            3235
        //  3233: iconst_1       
        //  3234: istore_3       
        //  3235: aload_0        
        //  3236: getfield        act.d:Lack;
        //  3239: astore          17
        //  3241: aload           17
        //  3243: iconst_0       
        //  3244: putfield        ack.f:Z
        //  3247: aload           17
        //  3249: iconst_0       
        //  3250: putfield        ack.g:Z
        //  3253: aload_0        
        //  3254: getfield        act.ax:I
        //  3257: ifeq            3270
        //  3260: iload_3        
        //  3261: ifeq            3270
        //  3264: aload           17
        //  3266: iconst_1       
        //  3267: putfield        ack.g:Z
        //  3270: aload_0        
        //  3271: getfield        act.aI:Ljava/util/ArrayList;
        //  3274: astore          17
        //  3276: aload_0        
        //  3277: invokevirtual   acs.M:()I
        //  3280: iconst_2       
        //  3281: if_icmpeq       3301
        //  3284: aload_0        
        //  3285: invokevirtual   acs.N:()I
        //  3288: iconst_2       
        //  3289: if_icmpne       3295
        //  3292: goto            3301
        //  3295: iconst_0       
        //  3296: istore          13
        //  3298: goto            3304
        //  3301: iconst_1       
        //  3302: istore          13
        //  3304: aload_0        
        //  3305: invokespecial   act.ab:()V
        //  3308: iconst_0       
        //  3309: istore_3       
        //  3310: iload_3        
        //  3311: iload           8
        //  3313: if_icmpge       3351
        //  3316: aload_0        
        //  3317: getfield        act.aI:Ljava/util/ArrayList;
        //  3320: iload_3        
        //  3321: invokevirtual   java/util/ArrayList.get:(I)Ljava/lang/Object;
        //  3324: checkcast       Lacs;
        //  3327: astore          18
        //  3329: aload           18
        //  3331: instanceof      Lacz;
        //  3334: ifeq            3345
        //  3337: aload           18
        //  3339: checkcast       Lacz;
        //  3342: invokevirtual   acz.T:()V
        //  3345: iinc            3, 1
        //  3348: goto            3310
        //  3351: iconst_1       
        //  3352: istore          9
        //  3354: iconst_0       
        //  3355: istore          4
        //  3357: iload_1        
        //  3358: istore_3       
        //  3359: iload           9
        //  3361: istore_1       
        //  3362: iload_1        
        //  3363: ifeq            5484
        //  3366: iload           4
        //  3368: iconst_1       
        //  3369: iadd           
        //  3370: istore_1       
        //  3371: iload_1        
        //  3372: istore          4
        //  3374: aload_0        
        //  3375: getfield        act.d:Lack;
        //  3378: invokevirtual   ack.k:()V
        //  3381: iload_1        
        //  3382: istore          4
        //  3384: aload_0        
        //  3385: invokespecial   act.ab:()V
        //  3388: iload_1        
        //  3389: istore          4
        //  3391: aload_0        
        //  3392: aload_0        
        //  3393: getfield        act.d:Lack;
        //  3396: invokevirtual   acs.q:(Lack;)V
        //  3399: iconst_0       
        //  3400: istore          9
        //  3402: iload           9
        //  3404: iload           8
        //  3406: if_icmpge       3437
        //  3409: iload_1        
        //  3410: istore          4
        //  3412: aload_0        
        //  3413: getfield        act.aI:Ljava/util/ArrayList;
        //  3416: iload           9
        //  3418: invokevirtual   java/util/ArrayList.get:(I)Ljava/lang/Object;
        //  3421: checkcast       Lacs;
        //  3424: aload_0        
        //  3425: getfield        act.d:Lack;
        //  3428: invokevirtual   acs.q:(Lack;)V
        //  3431: iinc            9, 1
        //  3434: goto            3402
        //  3437: iload_1        
        //  3438: istore          4
        //  3440: aload_0        
        //  3441: getfield        act.d:Lack;
        //  3444: astore          20
        //  3446: iload_1        
        //  3447: istore          4
        //  3449: aload_0        
        //  3450: bipush          64
        //  3452: invokevirtual   act.W:(I)Z
        //  3455: istore          15
        //  3457: iload_1        
        //  3458: istore          4
        //  3460: aload_0        
        //  3461: aload           20
        //  3463: iload           15
        //  3465: invokevirtual   acs.b:(Lack;Z)V
        //  3468: iload_1        
        //  3469: istore          4
        //  3471: aload_0        
        //  3472: getfield        act.aI:Ljava/util/ArrayList;
        //  3475: invokevirtual   java/util/ArrayList.size:()I
        //  3478: istore          12
        //  3480: iconst_0       
        //  3481: istore          11
        //  3483: iconst_0       
        //  3484: istore          10
        //  3486: iload           11
        //  3488: iload           12
        //  3490: if_icmpge       3563
        //  3493: iload_1        
        //  3494: istore          4
        //  3496: aload_0        
        //  3497: getfield        act.aI:Ljava/util/ArrayList;
        //  3500: iload           11
        //  3502: invokevirtual   java/util/ArrayList.get:(I)Ljava/lang/Object;
        //  3505: checkcast       Lacs;
        //  3508: astore          19
        //  3510: iload_1        
        //  3511: istore          4
        //  3513: aload           19
        //  3515: iconst_0       
        //  3516: iconst_0       
        //  3517: invokevirtual   acs.y:(IZ)V
        //  3520: iload_2        
        //  3521: istore          9
        //  3523: aload           17
        //  3525: astore          18
        //  3527: iload_1        
        //  3528: istore          4
        //  3530: aload           19
        //  3532: iconst_1       
        //  3533: iconst_0       
        //  3534: invokevirtual   acs.y:(IZ)V
        //  3537: iload_2        
        //  3538: istore          9
        //  3540: aload           17
        //  3542: astore          18
        //  3544: iload_1        
        //  3545: istore          4
        //  3547: iload           10
        //  3549: aload           19
        //  3551: instanceof      Lacp;
        //  3554: ior            
        //  3555: istore          10
        //  3557: iinc            11, 1
        //  3560: goto            3486
        //  3563: iload           10
        //  3565: ifeq            3814
        //  3568: iconst_0       
        //  3569: istore          10
        //  3571: iload           10
        //  3573: iload           12
        //  3575: if_icmpge       3814
        //  3578: iload_2        
        //  3579: istore          9
        //  3581: aload           17
        //  3583: astore          18
        //  3585: iload_1        
        //  3586: istore          4
        //  3588: aload_0        
        //  3589: getfield        act.aI:Ljava/util/ArrayList;
        //  3592: iload           10
        //  3594: invokevirtual   java/util/ArrayList.get:(I)Ljava/lang/Object;
        //  3597: checkcast       Lacs;
        //  3600: astore          19
        //  3602: iload_2        
        //  3603: istore          9
        //  3605: aload           17
        //  3607: astore          18
        //  3609: iload_1        
        //  3610: istore          4
        //  3612: aload           19
        //  3614: instanceof      Lacp;
        //  3617: ifeq            3808
        //  3620: iload_2        
        //  3621: istore          9
        //  3623: aload           17
        //  3625: astore          18
        //  3627: iload_1        
        //  3628: istore          4
        //  3630: aload           19
        //  3632: checkcast       Lacp;
        //  3635: astore          19
        //  3637: iconst_0       
        //  3638: istore          11
        //  3640: iload_2        
        //  3641: istore          9
        //  3643: aload           17
        //  3645: astore          18
        //  3647: iload_1        
        //  3648: istore          4
        //  3650: iload           11
        //  3652: aload           19
        //  3654: getfield        acp.as:I
        //  3657: if_icmpge       3808
        //  3660: iload_2        
        //  3661: istore          9
        //  3663: aload           17
        //  3665: astore          18
        //  3667: iload_1        
        //  3668: istore          4
        //  3670: aload           19
        //  3672: getfield        acp.ar:[Lacs;
        //  3675: iload           11
        //  3677: aaload         
        //  3678: astore          21
        //  3680: iload_2        
        //  3681: istore          9
        //  3683: aload           17
        //  3685: astore          18
        //  3687: iload_1        
        //  3688: istore          4
        //  3690: aload           19
        //  3692: getfield        acp.b:Z
        //  3695: ifne            3719
        //  3698: iload_2        
        //  3699: istore          9
        //  3701: aload           17
        //  3703: astore          18
        //  3705: iload_1        
        //  3706: istore          4
        //  3708: aload           21
        //  3710: invokevirtual   acs.d:()Z
        //  3713: ifne            3719
        //  3716: goto            3802
        //  3719: iload_2        
        //  3720: istore          9
        //  3722: aload           17
        //  3724: astore          18
        //  3726: iload_1        
        //  3727: istore          4
        //  3729: aload           19
        //  3731: getfield        acp.a:I
        //  3734: istore          14
        //  3736: iload           14
        //  3738: ifeq            3785
        //  3741: iload           14
        //  3743: iconst_1       
        //  3744: if_icmpne       3750
        //  3747: goto            3785
        //  3750: iload           14
        //  3752: iconst_2       
        //  3753: if_icmpeq       3765
        //  3756: iload           14
        //  3758: iconst_3       
        //  3759: if_icmpne       3802
        //  3762: goto            3765
        //  3765: iload_2        
        //  3766: istore          9
        //  3768: aload           17
        //  3770: astore          18
        //  3772: iload_1        
        //  3773: istore          4
        //  3775: aload           21
        //  3777: iconst_1       
        //  3778: iconst_1       
        //  3779: invokevirtual   acs.y:(IZ)V
        //  3782: goto            3802
        //  3785: iload_2        
        //  3786: istore          9
        //  3788: aload           17
        //  3790: astore          18
        //  3792: iload_1        
        //  3793: istore          4
        //  3795: aload           21
        //  3797: iconst_0       
        //  3798: iconst_1       
        //  3799: invokevirtual   acs.y:(IZ)V
        //  3802: iinc            11, 1
        //  3805: goto            3640
        //  3808: iinc            10, 1
        //  3811: goto            3571
        //  3814: iload_2        
        //  3815: istore          9
        //  3817: aload           17
        //  3819: astore          18
        //  3821: iload_1        
        //  3822: istore          4
        //  3824: aload_0        
        //  3825: getfield        act.aE:Ljava/util/HashSet;
        //  3828: invokevirtual   java/util/HashSet.clear:()V
        //  3831: iconst_0       
        //  3832: istore          4
        //  3834: iload           4
        //  3836: iload           12
        //  3838: if_icmplt       4800
        //  3841: iload_2        
        //  3842: istore          9
        //  3844: aload           17
        //  3846: astore          18
        //  3848: iload_1        
        //  3849: istore          4
        //  3851: aload_0        
        //  3852: getfield        act.aE:Ljava/util/HashSet;
        //  3855: invokevirtual   java/util/HashSet.size:()I
        //  3858: ifle            4171
        //  3861: iload_2        
        //  3862: istore          9
        //  3864: aload           17
        //  3866: astore          18
        //  3868: iload_1        
        //  3869: istore          4
        //  3871: aload_0        
        //  3872: getfield        act.aE:Ljava/util/HashSet;
        //  3875: invokevirtual   java/util/HashSet.size:()I
        //  3878: istore          11
        //  3880: iload_2        
        //  3881: istore          9
        //  3883: aload           17
        //  3885: astore          18
        //  3887: iload_1        
        //  3888: istore          4
        //  3890: aload_0        
        //  3891: getfield        act.aE:Ljava/util/HashSet;
        //  3894: invokevirtual   java/util/HashSet.iterator:()Ljava/util/Iterator;
        //  3897: astore          19
        //  3899: iload_2        
        //  3900: istore          9
        //  3902: aload           17
        //  3904: astore          18
        //  3906: iload_1        
        //  3907: istore          4
        //  3909: aload           19
        //  3911: invokeinterface java/util/Iterator.hasNext:()Z
        //  3916: ifeq            4060
        //  3919: iload_2        
        //  3920: istore          9
        //  3922: aload           17
        //  3924: astore          18
        //  3926: iload_1        
        //  3927: istore          4
        //  3929: aload           19
        //  3931: invokeinterface java/util/Iterator.next:()Ljava/lang/Object;
        //  3936: checkcast       Lacs;
        //  3939: checkcast       Lacy;
        //  3942: astore          22
        //  3944: iload_2        
        //  3945: istore          9
        //  3947: aload           17
        //  3949: astore          18
        //  3951: iload_1        
        //  3952: istore          4
        //  3954: aload_0        
        //  3955: getfield        act.aE:Ljava/util/HashSet;
        //  3958: astore          21
        //  3960: iconst_0       
        //  3961: istore          10
        //  3963: iload_2        
        //  3964: istore          9
        //  3966: aload           17
        //  3968: astore          18
        //  3970: iload_1        
        //  3971: istore          4
        //  3973: iload           10
        //  3975: aload           22
        //  3977: getfield        acy.as:I
        //  3980: if_icmpge       4057
        //  3983: iload_2        
        //  3984: istore          9
        //  3986: aload           17
        //  3988: astore          18
        //  3990: iload_1        
        //  3991: istore          4
        //  3993: aload           21
        //  3995: aload           22
        //  3997: getfield        acy.ar:[Lacs;
        //  4000: iload           10
        //  4002: aaload         
        //  4003: invokevirtual   java/util/HashSet.contains:(Ljava/lang/Object;)Z
        //  4006: ifeq            4051
        //  4009: iload_2        
        //  4010: istore          9
        //  4012: aload           17
        //  4014: astore          18
        //  4016: iload_1        
        //  4017: istore          4
        //  4019: aload           22
        //  4021: aload           20
        //  4023: iload           15
        //  4025: invokevirtual   acs.b:(Lack;Z)V
        //  4028: iload_2        
        //  4029: istore          9
        //  4031: aload           17
        //  4033: astore          18
        //  4035: iload_1        
        //  4036: istore          4
        //  4038: aload_0        
        //  4039: getfield        act.aE:Ljava/util/HashSet;
        //  4042: aload           22
        //  4044: invokevirtual   java/util/HashSet.remove:(Ljava/lang/Object;)Z
        //  4047: pop            
        //  4048: goto            4060
        //  4051: iinc            10, 1
        //  4054: goto            3963
        //  4057: goto            3899
        //  4060: iload_2        
        //  4061: istore          9
        //  4063: aload           17
        //  4065: astore          18
        //  4067: iload_1        
        //  4068: istore          4
        //  4070: iload           11
        //  4072: aload_0        
        //  4073: getfield        act.aE:Ljava/util/HashSet;
        //  4076: invokevirtual   java/util/HashSet.size:()I
        //  4079: if_icmpne       3841
        //  4082: iload_2        
        //  4083: istore          9
        //  4085: aload           17
        //  4087: astore          18
        //  4089: iload_1        
        //  4090: istore          4
        //  4092: aload_0        
        //  4093: getfield        act.aE:Ljava/util/HashSet;
        //  4096: invokevirtual   java/util/HashSet.iterator:()Ljava/util/Iterator;
        //  4099: astore          19
        //  4101: iload_2        
        //  4102: istore          9
        //  4104: aload           17
        //  4106: astore          18
        //  4108: iload_1        
        //  4109: istore          4
        //  4111: aload           19
        //  4113: invokeinterface java/util/Iterator.hasNext:()Z
        //  4118: ifeq            4151
        //  4121: iload_2        
        //  4122: istore          9
        //  4124: aload           17
        //  4126: astore          18
        //  4128: iload_1        
        //  4129: istore          4
        //  4131: aload           19
        //  4133: invokeinterface java/util/Iterator.next:()Ljava/lang/Object;
        //  4138: checkcast       Lacs;
        //  4141: aload           20
        //  4143: iload           15
        //  4145: invokevirtual   acs.b:(Lack;Z)V
        //  4148: goto            4101
        //  4151: iload_2        
        //  4152: istore          9
        //  4154: aload           17
        //  4156: astore          18
        //  4158: iload_1        
        //  4159: istore          4
        //  4161: aload_0        
        //  4162: getfield        act.aE:Ljava/util/HashSet;
        //  4165: invokevirtual   java/util/HashSet.clear:()V
        //  4168: goto            3841
        //  4171: iload_2        
        //  4172: istore          9
        //  4174: aload           17
        //  4176: astore          18
        //  4178: iload_1        
        //  4179: istore          4
        //  4181: getstatic       ack.a:Z
        //  4184: istore          16
        //  4186: iload           16
        //  4188: ifeq            4364
        //  4191: new             Ljava/util/HashSet;
        //  4194: astore          21
        //  4196: aload           21
        //  4198: invokespecial   java/util/HashSet.<init>:()V
        //  4201: iconst_0       
        //  4202: istore          10
        //  4204: iload           10
        //  4206: iload           12
        //  4208: if_icmpge       4277
        //  4211: iload_2        
        //  4212: istore          9
        //  4214: aload           17
        //  4216: astore          18
        //  4218: iload_1        
        //  4219: istore          4
        //  4221: aload_0        
        //  4222: getfield        act.aI:Ljava/util/ArrayList;
        //  4225: iload           10
        //  4227: invokevirtual   java/util/ArrayList.get:(I)Ljava/lang/Object;
        //  4230: checkcast       Lacs;
        //  4233: astore          19
        //  4235: iload_2        
        //  4236: istore          9
        //  4238: aload           17
        //  4240: astore          18
        //  4242: iload_1        
        //  4243: istore          4
        //  4245: aload           19
        //  4247: invokevirtual   acs.E:()Z
        //  4250: ifne            4271
        //  4253: iload_2        
        //  4254: istore          9
        //  4256: aload           17
        //  4258: astore          18
        //  4260: iload_1        
        //  4261: istore          4
        //  4263: aload           21
        //  4265: aload           19
        //  4267: invokevirtual   java/util/HashSet.add:(Ljava/lang/Object;)Z
        //  4270: pop            
        //  4271: iinc            10, 1
        //  4274: goto            4204
        //  4277: aload_0        
        //  4278: invokevirtual   acs.M:()I
        //  4281: istore          4
        //  4283: iload           4
        //  4285: iconst_2       
        //  4286: if_icmpne       4295
        //  4289: iconst_0       
        //  4290: istore          4
        //  4292: goto            4298
        //  4295: iconst_1       
        //  4296: istore          4
        //  4298: aload_0        
        //  4299: aload_0        
        //  4300: aload           20
        //  4302: aload           21
        //  4304: iload           4
        //  4306: iconst_0       
        //  4307: invokevirtual   acs.p:(Lact;Lack;Ljava/util/HashSet;IZ)V
        //  4310: aload           21
        //  4312: invokevirtual   java/util/HashSet.iterator:()Ljava/util/Iterator;
        //  4315: astore          19
        //  4317: aload           19
        //  4319: invokeinterface java/util/Iterator.hasNext:()Z
        //  4324: ifeq            4520
        //  4327: aload           19
        //  4329: invokeinterface java/util/Iterator.next:()Ljava/lang/Object;
        //  4334: checkcast       Lacs;
        //  4337: astore          18
        //  4339: aload_0        
        //  4340: aload           20
        //  4342: aload           18
        //  4344: invokestatic    acx.a:(Lact;Lack;Lacs;)V
        //  4347: aload           18
        //  4349: aload           20
        //  4351: iload           15
        //  4353: invokevirtual   acs.b:(Lack;Z)V
        //  4356: goto            4317
        //  4359: astore          18
        //  4361: goto            4891
        //  4364: iconst_0       
        //  4365: istore          4
        //  4367: iload           4
        //  4369: iload           12
        //  4371: if_icmpge       4520
        //  4374: aload_0        
        //  4375: getfield        act.aI:Ljava/util/ArrayList;
        //  4378: iload           4
        //  4380: invokevirtual   java/util/ArrayList.get:(I)Ljava/lang/Object;
        //  4383: checkcast       Lacs;
        //  4386: astore          18
        //  4388: aload           18
        //  4390: instanceof      Lact;
        //  4393: ifeq            4489
        //  4396: aload           18
        //  4398: getfield        acs.aq:[I
        //  4401: astore          19
        //  4403: aload           19
        //  4405: iconst_0       
        //  4406: iaload         
        //  4407: istore          10
        //  4409: aload           19
        //  4411: iconst_1       
        //  4412: iaload         
        //  4413: istore          11
        //  4415: iload           10
        //  4417: istore          9
        //  4419: iload           10
        //  4421: iconst_2       
        //  4422: if_icmpne       4434
        //  4425: aload           18
        //  4427: iconst_1       
        //  4428: invokevirtual   acs.P:(I)V
        //  4431: iconst_2       
        //  4432: istore          9
        //  4434: iload           11
        //  4436: istore          10
        //  4438: iload           11
        //  4440: iconst_2       
        //  4441: if_icmpne       4453
        //  4444: aload           18
        //  4446: iconst_1       
        //  4447: invokevirtual   acs.Q:(I)V
        //  4450: iconst_2       
        //  4451: istore          10
        //  4453: aload           18
        //  4455: aload           20
        //  4457: iload           15
        //  4459: invokevirtual   acs.b:(Lack;Z)V
        //  4462: iload           9
        //  4464: iconst_2       
        //  4465: if_icmpne       4474
        //  4468: aload           18
        //  4470: iconst_2       
        //  4471: invokevirtual   acs.P:(I)V
        //  4474: iload           10
        //  4476: iconst_2       
        //  4477: if_icmpne       4514
        //  4480: aload           18
        //  4482: iconst_2       
        //  4483: invokevirtual   acs.Q:(I)V
        //  4486: goto            4514
        //  4489: aload_0        
        //  4490: aload           20
        //  4492: aload           18
        //  4494: invokestatic    acx.a:(Lact;Lack;Lacs;)V
        //  4497: aload           18
        //  4499: invokevirtual   acs.E:()Z
        //  4502: ifne            4514
        //  4505: aload           18
        //  4507: aload           20
        //  4509: iload           15
        //  4511: invokevirtual   acs.b:(Lack;Z)V
        //  4514: iinc            4, 1
        //  4517: goto            4367
        //  4520: iload_2        
        //  4521: istore          9
        //  4523: aload           17
        //  4525: astore          19
        //  4527: iload_1        
        //  4528: istore          10
        //  4530: aload_0        
        //  4531: getfield        act.at:I
        //  4534: istore          4
        //  4536: iload           4
        //  4538: ifle            4552
        //  4541: aload_0        
        //  4542: aload           20
        //  4544: aconst_null    
        //  4545: iconst_0       
        //  4546: invokestatic    sm.b:(Lact;Lack;Ljava/util/ArrayList;I)V
        //  4549: goto            4552
        //  4552: aload_0        
        //  4553: getfield        act.au:I
        //  4556: ifle            4567
        //  4559: aload_0        
        //  4560: aload           20
        //  4562: aconst_null    
        //  4563: iconst_1       
        //  4564: invokestatic    sm.b:(Lact;Lack;Ljava/util/ArrayList;I)V
        //  4567: aload_0        
        //  4568: getfield        act.aA:Ljava/lang/ref/WeakReference;
        //  4571: astore          18
        //  4573: aload           18
        //  4575: ifnull          4616
        //  4578: aload           18
        //  4580: invokevirtual   java/lang/ref/WeakReference.get:()Ljava/lang/Object;
        //  4583: ifnull          4616
        //  4586: aload_0        
        //  4587: aload_0        
        //  4588: getfield        act.aA:Ljava/lang/ref/WeakReference;
        //  4591: invokevirtual   java/lang/ref/WeakReference.get:()Ljava/lang/Object;
        //  4594: checkcast       Lacr;
        //  4597: aload_0        
        //  4598: getfield        act.d:Lack;
        //  4601: aload_0        
        //  4602: getfield        act.K:Lacr;
        //  4605: invokevirtual   ack.b:(Ljava/lang/Object;)Lacn;
        //  4608: invokespecial   act.aa:(Lacr;Lacn;)V
        //  4611: aload_0        
        //  4612: aconst_null    
        //  4613: putfield        act.aA:Ljava/lang/ref/WeakReference;
        //  4616: aload_0        
        //  4617: getfield        act.aC:Ljava/lang/ref/WeakReference;
        //  4620: astore          18
        //  4622: aload           18
        //  4624: ifnull          4665
        //  4627: aload           18
        //  4629: invokevirtual   java/lang/ref/WeakReference.get:()Ljava/lang/Object;
        //  4632: ifnull          4665
        //  4635: aload_0        
        //  4636: aload_0        
        //  4637: getfield        act.aC:Ljava/lang/ref/WeakReference;
        //  4640: invokevirtual   java/lang/ref/WeakReference.get:()Ljava/lang/Object;
        //  4643: checkcast       Lacr;
        //  4646: aload_0        
        //  4647: getfield        act.d:Lack;
        //  4650: aload_0        
        //  4651: getfield        act.M:Lacr;
        //  4654: invokevirtual   ack.b:(Ljava/lang/Object;)Lacn;
        //  4657: invokespecial   act.Z:(Lacr;Lacn;)V
        //  4660: aload_0        
        //  4661: aconst_null    
        //  4662: putfield        act.aC:Ljava/lang/ref/WeakReference;
        //  4665: aload_0        
        //  4666: getfield        act.aB:Ljava/lang/ref/WeakReference;
        //  4669: astore          18
        //  4671: aload           18
        //  4673: ifnull          4714
        //  4676: aload           18
        //  4678: invokevirtual   java/lang/ref/WeakReference.get:()Ljava/lang/Object;
        //  4681: ifnull          4714
        //  4684: aload_0        
        //  4685: aload_0        
        //  4686: getfield        act.aB:Ljava/lang/ref/WeakReference;
        //  4689: invokevirtual   java/lang/ref/WeakReference.get:()Ljava/lang/Object;
        //  4692: checkcast       Lacr;
        //  4695: aload_0        
        //  4696: getfield        act.d:Lack;
        //  4699: aload_0        
        //  4700: getfield        act.J:Lacr;
        //  4703: invokevirtual   ack.b:(Ljava/lang/Object;)Lacn;
        //  4706: invokespecial   act.aa:(Lacr;Lacn;)V
        //  4709: aload_0        
        //  4710: aconst_null    
        //  4711: putfield        act.aB:Ljava/lang/ref/WeakReference;
        //  4714: aload_0        
        //  4715: getfield        act.aD:Ljava/lang/ref/WeakReference;
        //  4718: astore          18
        //  4720: aload           18
        //  4722: ifnull          4766
        //  4725: aload           18
        //  4727: invokevirtual   java/lang/ref/WeakReference.get:()Ljava/lang/Object;
        //  4730: ifnull          4766
        //  4733: aload_0        
        //  4734: aload_0        
        //  4735: getfield        act.aD:Ljava/lang/ref/WeakReference;
        //  4738: invokevirtual   java/lang/ref/WeakReference.get:()Ljava/lang/Object;
        //  4741: checkcast       Lacr;
        //  4744: aload_0        
        //  4745: getfield        act.d:Lack;
        //  4748: aload_0        
        //  4749: getfield        act.L:Lacr;
        //  4752: invokevirtual   ack.b:(Ljava/lang/Object;)Lacn;
        //  4755: invokespecial   act.Z:(Lacr;Lacn;)V
        //  4758: aload_0        
        //  4759: aconst_null    
        //  4760: putfield        act.aD:Ljava/lang/ref/WeakReference;
        //  4763: goto            4766
        //  4766: aload_0        
        //  4767: getfield        act.d:Lack;
        //  4770: invokevirtual   ack.j:()V
        //  4773: aload           19
        //  4775: astore          17
        //  4777: goto            4919
        //  4780: astore          18
        //  4782: iload           10
        //  4784: istore_1       
        //  4785: aload           19
        //  4787: astore          17
        //  4789: iload           9
        //  4791: istore_2       
        //  4792: goto            4891
        //  4795: astore          18
        //  4797: goto            4361
        //  4800: aload_0        
        //  4801: getfield        act.aI:Ljava/util/ArrayList;
        //  4804: iload           4
        //  4806: invokevirtual   java/util/ArrayList.get:(I)Ljava/lang/Object;
        //  4809: checkcast       Lacs;
        //  4812: astore          18
        //  4814: aload           18
        //  4816: invokevirtual   acs.E:()Z
        //  4819: ifeq            4852
        //  4822: aload           18
        //  4824: instanceof      Lacy;
        //  4827: ifeq            4843
        //  4830: aload_0        
        //  4831: getfield        act.aE:Ljava/util/HashSet;
        //  4834: aload           18
        //  4836: invokevirtual   java/util/HashSet.add:(Ljava/lang/Object;)Z
        //  4839: pop            
        //  4840: goto            4852
        //  4843: aload           18
        //  4845: aload           20
        //  4847: iload           15
        //  4849: invokevirtual   acs.b:(Lack;Z)V
        //  4852: iinc            4, 1
        //  4855: goto            3834
        //  4858: astore          18
        //  4860: goto            4891
        //  4863: astore          17
        //  4865: iload           9
        //  4867: istore_2       
        //  4868: aload           18
        //  4870: astore          19
        //  4872: iload           4
        //  4874: istore_1       
        //  4875: aload           17
        //  4877: astore          18
        //  4879: aload           19
        //  4881: astore          17
        //  4883: goto            4891
        //  4886: astore          18
        //  4888: iload           4
        //  4890: istore_1       
        //  4891: aload           18
        //  4893: invokevirtual   java/lang/Exception.printStackTrace:()V
        //  4896: getstatic       java/lang/System.out:Ljava/io/PrintStream;
        //  4899: ldc_w           "EXCEPTION : "
        //  4902: aload           18
        //  4904: invokevirtual   java/lang/Object.toString:()Ljava/lang/String;
        //  4907: invokevirtual   java/lang/String.concat:(Ljava/lang/String;)Ljava/lang/String;
        //  4910: invokevirtual   java/io/PrintStream.println:(Ljava/lang/String;)V
        //  4913: iload_2        
        //  4914: istore          9
        //  4916: iload_1        
        //  4917: istore          10
        //  4919: getstatic       acx.a:[Z
        //  4922: iconst_2       
        //  4923: iconst_0       
        //  4924: bastore        
        //  4925: aload_0        
        //  4926: bipush          64
        //  4928: invokevirtual   act.W:(I)Z
        //  4931: istore          15
        //  4933: aload_0        
        //  4934: iload           15
        //  4936: invokevirtual   acs.R:(Z)V
        //  4939: aload_0        
        //  4940: getfield        act.aI:Ljava/util/ArrayList;
        //  4943: invokevirtual   java/util/ArrayList.size:()I
        //  4946: istore          11
        //  4948: iconst_0       
        //  4949: istore_2       
        //  4950: iconst_0       
        //  4951: istore_1       
        //  4952: iload_2        
        //  4953: iload           11
        //  4955: if_icmpge       5019
        //  4958: aload_0        
        //  4959: getfield        act.aI:Ljava/util/ArrayList;
        //  4962: iload_2        
        //  4963: invokevirtual   java/util/ArrayList.get:(I)Ljava/lang/Object;
        //  4966: checkcast       Lacs;
        //  4969: astore          18
        //  4971: aload           18
        //  4973: iload           15
        //  4975: invokevirtual   acs.R:(Z)V
        //  4978: aload           18
        //  4980: getfield        acs.k:I
        //  4983: iconst_m1      
        //  4984: if_icmpne       5005
        //  4987: aload           18
        //  4989: getfield        acs.l:I
        //  4992: iconst_m1      
        //  4993: if_icmpeq       4999
        //  4996: goto            5005
        //  4999: iconst_0       
        //  5000: istore          4
        //  5002: goto            5008
        //  5005: iconst_1       
        //  5006: istore          4
        //  5008: iload_1        
        //  5009: iload           4
        //  5011: ior            
        //  5012: istore_1       
        //  5013: iinc            2, 1
        //  5016: goto            4952
        //  5019: iload_1        
        //  5020: istore          4
        //  5022: iload_3        
        //  5023: istore_2       
        //  5024: iload           13
        //  5026: ifeq            5237
        //  5029: iload_1        
        //  5030: istore          4
        //  5032: iload_3        
        //  5033: istore_2       
        //  5034: iload           10
        //  5036: bipush          8
        //  5038: if_icmpge       5237
        //  5041: iload_1        
        //  5042: istore          4
        //  5044: iload_3        
        //  5045: istore_2       
        //  5046: getstatic       acx.a:[Z
        //  5049: iconst_2       
        //  5050: baload         
        //  5051: ifeq            5237
        //  5054: iconst_0       
        //  5055: istore          4
        //  5057: iconst_0       
        //  5058: istore          11
        //  5060: iconst_0       
        //  5061: istore_2       
        //  5062: iload           4
        //  5064: iload           8
        //  5066: if_icmpge       5123
        //  5069: aload_0        
        //  5070: getfield        act.aI:Ljava/util/ArrayList;
        //  5073: iload           4
        //  5075: invokevirtual   java/util/ArrayList.get:(I)Ljava/lang/Object;
        //  5078: checkcast       Lacs;
        //  5081: astore          18
        //  5083: iload           11
        //  5085: aload           18
        //  5087: getfield        acs.Z:I
        //  5090: aload           18
        //  5092: invokevirtual   acs.j:()I
        //  5095: iadd           
        //  5096: invokestatic    java/lang/Math.max:(II)I
        //  5099: istore          11
        //  5101: iload_2        
        //  5102: aload           18
        //  5104: getfield        acs.aa:I
        //  5107: aload           18
        //  5109: invokevirtual   acs.h:()I
        //  5112: iadd           
        //  5113: invokestatic    java/lang/Math.max:(II)I
        //  5116: istore_2       
        //  5117: iinc            4, 1
        //  5120: goto            5062
        //  5123: aload_0        
        //  5124: getfield        act.ac:I
        //  5127: iload           11
        //  5129: invokestatic    java/lang/Math.max:(II)I
        //  5132: istore          4
        //  5134: aload_0        
        //  5135: getfield        act.ad:I
        //  5138: iload_2        
        //  5139: invokestatic    java/lang/Math.max:(II)I
        //  5142: istore          14
        //  5144: iload_1        
        //  5145: istore          12
        //  5147: iload_3        
        //  5148: istore          11
        //  5150: iload           6
        //  5152: iconst_2       
        //  5153: if_icmpne       5190
        //  5156: iload_1        
        //  5157: istore          12
        //  5159: iload_3        
        //  5160: istore          11
        //  5162: aload_0        
        //  5163: invokevirtual   acs.j:()I
        //  5166: iload           4
        //  5168: if_icmpge       5190
        //  5171: aload_0        
        //  5172: iload           4
        //  5174: invokevirtual   acs.C:(I)V
        //  5177: aload_0        
        //  5178: getfield        act.aq:[I
        //  5181: iconst_0       
        //  5182: iconst_2       
        //  5183: iastore        
        //  5184: iconst_1       
        //  5185: istore          12
        //  5187: iconst_1       
        //  5188: istore          11
        //  5190: iload           12
        //  5192: istore          4
        //  5194: iload           11
        //  5196: istore_2       
        //  5197: iload           7
        //  5199: iconst_2       
        //  5200: if_icmpne       5237
        //  5203: iload           12
        //  5205: istore          4
        //  5207: iload           11
        //  5209: istore_2       
        //  5210: aload_0        
        //  5211: invokevirtual   acs.h:()I
        //  5214: iload           14
        //  5216: if_icmpge       5237
        //  5219: aload_0        
        //  5220: iload           14
        //  5222: invokevirtual   acs.x:(I)V
        //  5225: aload_0        
        //  5226: getfield        act.aq:[I
        //  5229: iconst_1       
        //  5230: iconst_2       
        //  5231: iastore        
        //  5232: iconst_1       
        //  5233: istore          4
        //  5235: iconst_1       
        //  5236: istore_2       
        //  5237: aload_0        
        //  5238: getfield        act.ac:I
        //  5241: aload_0        
        //  5242: invokevirtual   acs.j:()I
        //  5245: invokestatic    java/lang/Math.max:(II)I
        //  5248: istore_1       
        //  5249: iload_1        
        //  5250: aload_0        
        //  5251: invokevirtual   acs.j:()I
        //  5254: if_icmple       5276
        //  5257: aload_0        
        //  5258: iload_1        
        //  5259: invokevirtual   acs.C:(I)V
        //  5262: aload_0        
        //  5263: getfield        act.aq:[I
        //  5266: iconst_0       
        //  5267: iconst_1       
        //  5268: iastore        
        //  5269: iconst_1       
        //  5270: istore_1       
        //  5271: iconst_1       
        //  5272: istore_2       
        //  5273: goto            5279
        //  5276: iload           4
        //  5278: istore_1       
        //  5279: aload_0        
        //  5280: getfield        act.ad:I
        //  5283: aload_0        
        //  5284: invokevirtual   acs.h:()I
        //  5287: invokestatic    java/lang/Math.max:(II)I
        //  5290: istore_3       
        //  5291: iload_3        
        //  5292: aload_0        
        //  5293: invokevirtual   acs.h:()I
        //  5296: if_icmple       5318
        //  5299: aload_0        
        //  5300: iload_3        
        //  5301: invokevirtual   acs.x:(I)V
        //  5304: aload_0        
        //  5305: getfield        act.aq:[I
        //  5308: iconst_1       
        //  5309: iconst_1       
        //  5310: iastore        
        //  5311: iconst_1       
        //  5312: istore_1       
        //  5313: iconst_1       
        //  5314: istore_3       
        //  5315: goto            5320
        //  5318: iload_2        
        //  5319: istore_3       
        //  5320: iload_3        
        //  5321: ifne            5456
        //  5324: aload_0        
        //  5325: getfield        act.aq:[I
        //  5328: astore          18
        //  5330: iload_1        
        //  5331: istore          4
        //  5333: iload_3        
        //  5334: istore_2       
        //  5335: aload           18
        //  5337: iconst_0       
        //  5338: iaload         
        //  5339: iconst_2       
        //  5340: if_icmpne       5388
        //  5343: iload_1        
        //  5344: istore          4
        //  5346: iload_3        
        //  5347: istore_2       
        //  5348: iload           5
        //  5350: ifle            5388
        //  5353: iload_1        
        //  5354: istore          4
        //  5356: iload_3        
        //  5357: istore_2       
        //  5358: aload_0        
        //  5359: invokevirtual   acs.j:()I
        //  5362: iload           5
        //  5364: if_icmple       5388
        //  5367: aload_0        
        //  5368: iconst_1       
        //  5369: putfield        act.ay:Z
        //  5372: aload           18
        //  5374: iconst_0       
        //  5375: iconst_1       
        //  5376: iastore        
        //  5377: aload_0        
        //  5378: iload           5
        //  5380: invokevirtual   acs.C:(I)V
        //  5383: iconst_1       
        //  5384: istore          4
        //  5386: iconst_1       
        //  5387: istore_2       
        //  5388: aload_0        
        //  5389: getfield        act.aq:[I
        //  5392: astore          18
        //  5394: aload           18
        //  5396: iconst_1       
        //  5397: iaload         
        //  5398: iconst_2       
        //  5399: if_icmpne       5448
        //  5402: iload           9
        //  5404: ifle            5448
        //  5407: aload_0        
        //  5408: invokevirtual   acs.h:()I
        //  5411: istore          11
        //  5413: iload           4
        //  5415: istore_1       
        //  5416: iload_2        
        //  5417: istore_3       
        //  5418: iload           11
        //  5420: iload           9
        //  5422: if_icmple       5456
        //  5425: aload_0        
        //  5426: iconst_1       
        //  5427: putfield        act.az:Z
        //  5430: aload           18
        //  5432: iconst_1       
        //  5433: iconst_1       
        //  5434: iastore        
        //  5435: aload_0        
        //  5436: iload           9
        //  5438: invokevirtual   acs.x:(I)V
        //  5441: iconst_1       
        //  5442: istore_1       
        //  5443: iconst_1       
        //  5444: istore_3       
        //  5445: goto            5456
        //  5448: iload           4
        //  5450: istore_1       
        //  5451: iload_2        
        //  5452: istore_3       
        //  5453: goto            5456
        //  5456: iload           10
        //  5458: bipush          8
        //  5460: if_icmple       5468
        //  5463: iconst_0       
        //  5464: istore_2       
        //  5465: goto            5470
        //  5468: iconst_1       
        //  5469: istore_2       
        //  5470: iload_2        
        //  5471: iload_1        
        //  5472: iand           
        //  5473: istore_1       
        //  5474: iload           10
        //  5476: istore          4
        //  5478: iload           9
        //  5480: istore_2       
        //  5481: goto            3362
        //  5484: aload_0        
        //  5485: aload           17
        //  5487: putfield        act.aI:Ljava/util/ArrayList;
        //  5490: iload_3        
        //  5491: ifeq            5512
        //  5494: aload_0        
        //  5495: getfield        act.aq:[I
        //  5498: astore          17
        //  5500: aload           17
        //  5502: iconst_0       
        //  5503: iload           6
        //  5505: iastore        
        //  5506: aload           17
        //  5508: iconst_1       
        //  5509: iload           7
        //  5511: iastore        
        //  5512: aload_0        
        //  5513: aload_0        
        //  5514: getfield        act.d:Lack;
        //  5517: getfield        ack.j:Lcdo;
        //  5520: invokevirtual   acs.S:(Lcdo;)V
        //  5523: return         
        //    Exceptions:
        //  Try           Handler
        //  Start  End    Start  End    Type                 
        //  -----  -----  -----  -----  ---------------------
        //  3374   3381   4886   4891   Ljava/lang/Exception;
        //  3384   3388   4886   4891   Ljava/lang/Exception;
        //  3391   3399   4886   4891   Ljava/lang/Exception;
        //  3412   3431   4886   4891   Ljava/lang/Exception;
        //  3440   3446   4886   4891   Ljava/lang/Exception;
        //  3449   3457   4886   4891   Ljava/lang/Exception;
        //  3460   3468   4886   4891   Ljava/lang/Exception;
        //  3471   3480   4886   4891   Ljava/lang/Exception;
        //  3496   3510   4886   4891   Ljava/lang/Exception;
        //  3513   3520   4886   4891   Ljava/lang/Exception;
        //  3530   3537   4863   4886   Ljava/lang/Exception;
        //  3547   3557   4863   4886   Ljava/lang/Exception;
        //  3588   3602   4863   4886   Ljava/lang/Exception;
        //  3612   3620   4863   4886   Ljava/lang/Exception;
        //  3630   3637   4863   4886   Ljava/lang/Exception;
        //  3650   3660   4863   4886   Ljava/lang/Exception;
        //  3670   3680   4863   4886   Ljava/lang/Exception;
        //  3690   3698   4863   4886   Ljava/lang/Exception;
        //  3708   3716   4863   4886   Ljava/lang/Exception;
        //  3729   3736   4863   4886   Ljava/lang/Exception;
        //  3775   3782   4863   4886   Ljava/lang/Exception;
        //  3795   3802   4863   4886   Ljava/lang/Exception;
        //  3824   3831   4863   4886   Ljava/lang/Exception;
        //  3851   3861   4863   4886   Ljava/lang/Exception;
        //  3871   3880   4863   4886   Ljava/lang/Exception;
        //  3890   3899   4863   4886   Ljava/lang/Exception;
        //  3909   3919   4863   4886   Ljava/lang/Exception;
        //  3929   3944   4863   4886   Ljava/lang/Exception;
        //  3954   3960   4863   4886   Ljava/lang/Exception;
        //  3973   3983   4863   4886   Ljava/lang/Exception;
        //  3993   4009   4863   4886   Ljava/lang/Exception;
        //  4019   4028   4863   4886   Ljava/lang/Exception;
        //  4038   4048   4863   4886   Ljava/lang/Exception;
        //  4070   4082   4863   4886   Ljava/lang/Exception;
        //  4092   4101   4863   4886   Ljava/lang/Exception;
        //  4111   4121   4863   4886   Ljava/lang/Exception;
        //  4131   4148   4863   4886   Ljava/lang/Exception;
        //  4161   4168   4863   4886   Ljava/lang/Exception;
        //  4181   4186   4863   4886   Ljava/lang/Exception;
        //  4191   4201   4359   4361   Ljava/lang/Exception;
        //  4221   4235   4863   4886   Ljava/lang/Exception;
        //  4245   4253   4863   4886   Ljava/lang/Exception;
        //  4263   4271   4863   4886   Ljava/lang/Exception;
        //  4277   4283   4359   4361   Ljava/lang/Exception;
        //  4298   4317   4795   4800   Ljava/lang/Exception;
        //  4317   4356   4795   4800   Ljava/lang/Exception;
        //  4374   4403   4795   4800   Ljava/lang/Exception;
        //  4425   4431   4795   4800   Ljava/lang/Exception;
        //  4444   4450   4795   4800   Ljava/lang/Exception;
        //  4453   4462   4795   4800   Ljava/lang/Exception;
        //  4468   4474   4795   4800   Ljava/lang/Exception;
        //  4480   4486   4795   4800   Ljava/lang/Exception;
        //  4489   4514   4795   4800   Ljava/lang/Exception;
        //  4530   4536   4795   4800   Ljava/lang/Exception;
        //  4541   4549   4780   4795   Ljava/lang/Exception;
        //  4552   4567   4780   4795   Ljava/lang/Exception;
        //  4567   4573   4795   4800   Ljava/lang/Exception;
        //  4578   4611   4795   4800   Ljava/lang/Exception;
        //  4611   4616   4780   4795   Ljava/lang/Exception;
        //  4616   4622   4795   4800   Ljava/lang/Exception;
        //  4627   4660   4795   4800   Ljava/lang/Exception;
        //  4660   4665   4780   4795   Ljava/lang/Exception;
        //  4665   4671   4795   4800   Ljava/lang/Exception;
        //  4676   4709   4795   4800   Ljava/lang/Exception;
        //  4709   4714   4780   4795   Ljava/lang/Exception;
        //  4714   4720   4795   4800   Ljava/lang/Exception;
        //  4725   4758   4795   4800   Ljava/lang/Exception;
        //  4758   4763   4858   4863   Ljava/lang/Exception;
        //  4766   4773   4858   4863   Ljava/lang/Exception;
        //  4800   4840   4858   4863   Ljava/lang/Exception;
        //  4843   4852   4858   4863   Ljava/lang/Exception;
        // 
        // The error that occurred was:
        // 
        // java.lang.IllegalStateException: Expression is linked from several locations: Label_4298:
        //     at com.strobel.decompiler.ast.Error.expressionLinkedFromMultipleLocations(Error.java:27)
        //     at com.strobel.decompiler.ast.AstOptimizer.mergeDisparateObjectInitializations(AstOptimizer.java:2604)
        //     at com.strobel.decompiler.ast.AstOptimizer.optimize(AstOptimizer.java:235)
        //     at com.strobel.decompiler.ast.AstOptimizer.optimize(AstOptimizer.java:42)
        //     at com.strobel.decompiler.languages.java.ast.AstMethodBodyBuilder.createMethodBody(AstMethodBodyBuilder.java:206)
        //     at com.strobel.decompiler.languages.java.ast.AstMethodBodyBuilder.createMethodBody(AstMethodBodyBuilder.java:93)
        //     at com.strobel.decompiler.languages.java.ast.AstBuilder.createMethodBody(AstBuilder.java:868)
        //     at com.strobel.decompiler.languages.java.ast.AstBuilder.createMethod(AstBuilder.java:761)
        //     at com.strobel.decompiler.languages.java.ast.AstBuilder.addTypeMembers(AstBuilder.java:638)
        //     at com.strobel.decompiler.languages.java.ast.AstBuilder.createTypeCore(AstBuilder.java:605)
        //     at com.strobel.decompiler.languages.java.ast.AstBuilder.createTypeNoCache(AstBuilder.java:195)
        //     at com.strobel.decompiler.languages.java.ast.AstBuilder.createType(AstBuilder.java:162)
        //     at com.strobel.decompiler.languages.java.ast.AstBuilder.addType(AstBuilder.java:137)
        //     at com.strobel.decompiler.languages.java.JavaLanguage.buildAst(JavaLanguage.java:71)
        //     at com.strobel.decompiler.languages.java.JavaLanguage.decompileType(JavaLanguage.java:59)
        //     at com.strobel.decompiler.DecompilerDriver.decompileType(DecompilerDriver.java:333)
        //     at com.strobel.decompiler.DecompilerDriver.decompileJar(DecompilerDriver.java:254)
        //     at com.strobel.decompiler.DecompilerDriver.main(DecompilerDriver.java:129)
        // 
        throw new IllegalStateException("An error occurred while decompiling this method.");
    }
    
    public final void U(final int ax) {
        this.ax = ax;
        ack.a = this.W(512);
    }
    
    public final boolean V(final boolean b, final int n) {
        final add a = this.a;
        final act a2 = a.a;
        final boolean b2 = false;
        final int l = ((acs)a2).L(0);
        final int i = ((acs)a.a).L(1);
        final act a3 = a.a;
        final int k = ((acs)a3).k();
        final int j = ((acs)a3).l();
        int n2 = i;
        Label_0307: {
            if (b) {
                int n3 = i;
                if (l != 2) {
                    if ((n2 = i) != 2) {
                        break Label_0307;
                    }
                    n3 = 2;
                }
                final ArrayList e = a.e;
                final int size = e.size();
                int n4 = 0;
                while (true) {
                    while (n4 < size) {
                        final adn adn = (adn)e.get(n4);
                        if (adn.g == n && !adn.e()) {
                            final boolean b3 = false;
                            if (n == 0) {
                                n2 = n3;
                                if (!b3) {
                                    break Label_0307;
                                }
                                n2 = n3;
                                if (l == 2) {
                                    ((acs)a.a).P(1);
                                    final act a4 = a.a;
                                    ((acs)a4).C(a.a(a4, 0));
                                    final act a5 = a.a;
                                    a5.h.f.c(((acs)a5).j());
                                    n2 = n3;
                                }
                                break Label_0307;
                            }
                            else {
                                n2 = n3;
                                if (b3 && (n2 = n3) == 2) {
                                    ((acs)a.a).Q(1);
                                    final act a6 = a.a;
                                    ((acs)a6).x(a.a(a6, 1));
                                    final act a7 = a.a;
                                    a7.i.f.c(((acs)a7).h());
                                    n2 = n3;
                                }
                                break Label_0307;
                            }
                        }
                        else {
                            ++n4;
                        }
                    }
                    final boolean b3 = true;
                    continue;
                }
            }
        }
        boolean b4 = false;
        Label_0452: {
            Label_0450: {
                if (n == 0) {
                    final act a8 = a.a;
                    final int n5 = a8.aq[0];
                    if (n5 == 1 || n5 == 4) {
                        final int n6 = ((acs)a8).j() + k;
                        a8.h.j.c(n6);
                        a.a.h.f.c(n6 - k);
                        break Label_0450;
                    }
                }
                else {
                    final act a9 = a.a;
                    final int n7 = a9.aq[1];
                    if (n7 == 1 || n7 == 4) {
                        final int n8 = ((acs)a9).h() + j;
                        a9.i.j.c(n8);
                        a.a.i.f.c(n8 - j);
                        break Label_0450;
                    }
                }
                b4 = false;
                break Label_0452;
            }
            b4 = true;
        }
        a.c();
        final ArrayList e2 = a.e;
        for (int size2 = e2.size(), n9 = 0; n9 < size2; ++n9) {
            final adn adn2 = (adn)e2.get(n9);
            if (adn2.g == n) {
                if (adn2.d != a.a || adn2.h) {
                    adn2.c();
                }
            }
        }
        final ArrayList e3 = a.e;
        while (true) {
            for (int size3 = e3.size(), n10 = 0; n10 < size3; ++n10) {
                final adn adn3 = (adn)e3.get(n10);
                if (adn3.g == n) {
                    if (b4 || adn3.d != a.a) {
                        boolean b5;
                        if (!adn3.i.i) {
                            b5 = b2;
                        }
                        else if (!adn3.j.i) {
                            b5 = b2;
                        }
                        else {
                            if (adn3 instanceof adb || adn3.f.i) {
                                continue;
                            }
                            b5 = b2;
                        }
                        ((acs)a.a).P(l);
                        ((acs)a.a).Q(n2);
                        return b5;
                    }
                }
            }
            boolean b5 = true;
            continue;
        }
    }
    
    public final boolean W(final int n) {
        return (this.ax & n) == n;
    }
    
    final void a(final acs acs, int n) {
        if (n == 0) {
            n = this.at;
            final acq[] aw = this.aw;
            final int length = aw.length;
            if (n + 1 >= length) {
                this.aw = Arrays.copyOf(aw, length + length);
            }
            final acq[] aw2 = this.aw;
            n = this.at;
            aw2[n] = new acq(acs, 0, this.c);
            this.at = n + 1;
            return;
        }
        final int au = this.au;
        final acq[] av = this.av;
        n = av.length;
        if (au + 1 >= n) {
            this.av = Arrays.copyOf(av, n + n);
        }
        final acq[] av2 = this.av;
        n = this.au;
        av2[n] = new acq(acs, 1, this.c);
        this.au = n + 1;
    }
    
    public final void c() {
        this.a.b = true;
    }
    
    public final void s() {
        this.d.k();
        this.ar = 0;
        this.as = 0;
        super.s();
    }
}
