import org.chromium.net.impl.CronetUrlRequest;
import org.chromium.net.impl.CronetUploadDataStream;
import org.chromium.net.impl.CronetBidirectionalStream;
import org.chromium.net.NetworkChangeNotifierAutoDetect;

// 
// Decompiled by Procyon v0.6.0
// 

public final class ased implements Runnable
{
    final Object a;
    private final int b;
    
    public ased(final arzi a, final int b) {
        this.b = b;
        this.a = a;
    }
    
    public ased(final ased a, final int b, final byte[] array) {
        this.b = b;
        this.a = a;
    }
    
    public ased(final asee a, final int b) {
        this.b = b;
        this.a = a;
    }
    
    public ased(final aseo a, final int b) {
        this.b = b;
        this.a = a;
    }
    
    public ased(final asfb a, final int b) {
        this.b = b;
        this.a = a;
    }
    
    public ased(final asfe a, final int b) {
        this.b = b;
        this.a = a;
    }
    
    public ased(final asij a, final int b) {
        this.b = b;
        this.a = a;
    }
    
    public ased(final asol a, final int b) {
        this.b = b;
        this.a = a;
    }
    
    public ased(final asyw a, final int b) {
        this.b = b;
        this.a = a;
    }
    
    public ased(final aubw a, final int b) {
        this.b = b;
        this.a = a;
    }
    
    public ased(final Runnable a, final int b) {
        this.b = b;
        this.a = a;
    }
    
    public ased(final NetworkChangeNotifierAutoDetect a, final int b) {
        this.b = b;
        this.a = a;
    }
    
    public ased(final CronetBidirectionalStream a, final int b) {
        this.b = b;
        this.a = a;
    }
    
    public ased(final CronetUploadDataStream a, final int b) {
        this.b = b;
        this.a = a;
    }
    
    public ased(final CronetUrlRequest a, final int b) {
        this.b = b;
        this.a = a;
    }
    
    public ased(final ymr a, final int b, final byte[] array) {
        this.b = b;
        this.a = a;
    }
    
    @Override
    public final void run() {
        // 
        // This method could not be decompiled.
        // 
        // Original Bytecode:
        // 
        //     1: getfield        ased.b:I
        //     4: istore_2       
        //     5: iconst_1       
        //     6: istore_1       
        //     7: iload_2        
        //     8: tableswitch {
        //                0: 1671
        //                1: 1654
        //                2: 1548
        //                3: 1518
        //                4: 1490
        //                5: 1095
        //                6: 1037
        //                7: 1007
        //                8: 976
        //                9: 965
        //               10: 918
        //               11: 871
        //               12: 852
        //               13: 660
        //               14: 624
        //               15: 514
        //               16: 453
        //               17: 291
        //               18: 175
        //               19: 129
        //          default: 104
        //        }
        //   104: aload_0        
        //   105: getfield        ased.a:Ljava/lang/Object;
        //   108: checkcast       Lorg/chromium/net/impl/CronetUrlRequest;
        //   111: getfield        org/chromium/net/impl/CronetUrlRequest.f:Lorg/chromium/net/impl/CronetUploadDataStream;
        //   114: astore          5
        //   116: aload           5
        //   118: getfield        org/chromium/net/impl/CronetUploadDataStream.g:Ljava/lang/Object;
        //   121: astore          6
        //   123: aload           6
        //   125: monitorenter   
        //   126: goto            1685
        //   129: aload_0        
        //   130: getfield        ased.a:Ljava/lang/Object;
        //   133: checkcast       Lorg/chromium/net/impl/CronetUploadDataStream;
        //   136: invokevirtual   org/chromium/net/impl/CronetUploadDataStream.a:()V
        //   139: aload_0        
        //   140: getfield        ased.a:Ljava/lang/Object;
        //   143: checkcast       Lorg/chromium/net/impl/CronetUploadDataStream;
        //   146: getfield        org/chromium/net/impl/CronetUploadDataStream.b:Laueu;
        //   149: invokevirtual   org/chromium/net/UploadDataProvider.close:()V
        //   152: return         
        //   153: astore          5
        //   155: ldc             "cr_"
        //   157: getstatic       org/chromium/net/impl/CronetUploadDataStream.a:Ljava/lang/String;
        //   160: invokestatic    java/lang/String.valueOf:(Ljava/lang/Object;)Ljava/lang/String;
        //   163: invokevirtual   java/lang/String.concat:(Ljava/lang/String;)Ljava/lang/String;
        //   166: ldc             "Exception thrown when closing"
        //   168: aload           5
        //   170: invokestatic    android/util/Log.e:(Ljava/lang/String;Ljava/lang/String;Ljava/lang/Throwable;)I
        //   173: pop            
        //   174: return         
        //   175: aload_0        
        //   176: getfield        ased.a:Ljava/lang/Object;
        //   179: checkcast       Lorg/chromium/net/impl/CronetUploadDataStream;
        //   182: getfield        org/chromium/net/impl/CronetUploadDataStream.g:Ljava/lang/Object;
        //   185: astore          5
        //   187: aload           5
        //   189: monitorenter   
        //   190: aload_0        
        //   191: getfield        ased.a:Ljava/lang/Object;
        //   194: astore          6
        //   196: aload           6
        //   198: checkcast       Lorg/chromium/net/impl/CronetUploadDataStream;
        //   201: getfield        org/chromium/net/impl/CronetUploadDataStream.h:J
        //   204: lconst_0       
        //   205: lcmp           
        //   206: ifne            213
        //   209: aload           5
        //   211: monitorexit    
        //   212: return         
        //   213: aload           6
        //   215: checkcast       Lorg/chromium/net/impl/CronetUploadDataStream;
        //   218: invokestatic    org/chromium/net/impl/CronetUploadDataStream.d:(Lorg/chromium/net/impl/CronetUploadDataStream;)V
        //   221: aload_0        
        //   222: getfield        ased.a:Ljava/lang/Object;
        //   225: checkcast       Lorg/chromium/net/impl/CronetUploadDataStream;
        //   228: iconst_1       
        //   229: putfield        org/chromium/net/impl/CronetUploadDataStream.i:I
        //   232: aload           5
        //   234: monitorexit    
        //   235: aload_0        
        //   236: getfield        ased.a:Ljava/lang/Object;
        //   239: checkcast       Lorg/chromium/net/impl/CronetUploadDataStream;
        //   242: invokevirtual   org/chromium/net/impl/CronetUploadDataStream.a:()V
        //   245: aload_0        
        //   246: getfield        ased.a:Ljava/lang/Object;
        //   249: astore          5
        //   251: aload           5
        //   253: checkcast       Lorg/chromium/net/impl/CronetUploadDataStream;
        //   256: getfield        org/chromium/net/impl/CronetUploadDataStream.b:Laueu;
        //   259: aload           5
        //   261: checkcast       Lorg/chromium/net/UploadDataSink;
        //   264: invokevirtual   aueu.rewind:(Lorg/chromium/net/UploadDataSink;)V
        //   267: return         
        //   268: astore          5
        //   270: aload_0        
        //   271: getfield        ased.a:Ljava/lang/Object;
        //   274: checkcast       Lorg/chromium/net/impl/CronetUploadDataStream;
        //   277: aload           5
        //   279: invokevirtual   org/chromium/net/impl/CronetUploadDataStream.b:(Ljava/lang/Throwable;)V
        //   282: return         
        //   283: astore          6
        //   285: aload           5
        //   287: monitorexit    
        //   288: aload           6
        //   290: athrow         
        //   291: aload_0        
        //   292: getfield        ased.a:Ljava/lang/Object;
        //   295: checkcast       Lorg/chromium/net/impl/CronetUploadDataStream;
        //   298: getfield        org/chromium/net/impl/CronetUploadDataStream.g:Ljava/lang/Object;
        //   301: astore          5
        //   303: aload           5
        //   305: monitorenter   
        //   306: aload_0        
        //   307: getfield        ased.a:Ljava/lang/Object;
        //   310: astore          6
        //   312: aload           6
        //   314: checkcast       Lorg/chromium/net/impl/CronetUploadDataStream;
        //   317: getfield        org/chromium/net/impl/CronetUploadDataStream.h:J
        //   320: lconst_0       
        //   321: lcmp           
        //   322: ifne            329
        //   325: aload           5
        //   327: monitorexit    
        //   328: return         
        //   329: aload           6
        //   331: checkcast       Lorg/chromium/net/impl/CronetUploadDataStream;
        //   334: invokestatic    org/chromium/net/impl/CronetUploadDataStream.d:(Lorg/chromium/net/impl/CronetUploadDataStream;)V
        //   337: aload_0        
        //   338: getfield        ased.a:Ljava/lang/Object;
        //   341: astore          6
        //   343: aload           6
        //   345: checkcast       Lorg/chromium/net/impl/CronetUploadDataStream;
        //   348: getfield        org/chromium/net/impl/CronetUploadDataStream.f:Ljava/nio/ByteBuffer;
        //   351: ifnull          430
        //   354: aload           6
        //   356: checkcast       Lorg/chromium/net/impl/CronetUploadDataStream;
        //   359: iconst_0       
        //   360: putfield        org/chromium/net/impl/CronetUploadDataStream.i:I
        //   363: aload           5
        //   365: monitorexit    
        //   366: aload_0        
        //   367: getfield        ased.a:Ljava/lang/Object;
        //   370: checkcast       Lorg/chromium/net/impl/CronetUploadDataStream;
        //   373: invokevirtual   org/chromium/net/impl/CronetUploadDataStream.a:()V
        //   376: aload_0        
        //   377: getfield        ased.a:Ljava/lang/Object;
        //   380: astore          6
        //   382: aload           6
        //   384: checkcast       Lorg/chromium/net/impl/CronetUploadDataStream;
        //   387: getfield        org/chromium/net/impl/CronetUploadDataStream.b:Laueu;
        //   390: astore          5
        //   392: aload           6
        //   394: checkcast       Lorg/chromium/net/impl/CronetUploadDataStream;
        //   397: getfield        org/chromium/net/impl/CronetUploadDataStream.f:Ljava/nio/ByteBuffer;
        //   400: astore          7
        //   402: aload           5
        //   404: aload           6
        //   406: checkcast       Lorg/chromium/net/UploadDataSink;
        //   409: aload           7
        //   411: invokevirtual   aueu.read:(Lorg/chromium/net/UploadDataSink;Ljava/nio/ByteBuffer;)V
        //   414: return         
        //   415: astore          5
        //   417: aload_0        
        //   418: getfield        ased.a:Ljava/lang/Object;
        //   421: checkcast       Lorg/chromium/net/impl/CronetUploadDataStream;
        //   424: aload           5
        //   426: invokevirtual   org/chromium/net/impl/CronetUploadDataStream.b:(Ljava/lang/Throwable;)V
        //   429: return         
        //   430: new             Ljava/lang/IllegalStateException;
        //   433: astore          6
        //   435: aload           6
        //   437: ldc             "Unexpected readData call. Buffer is null"
        //   439: invokespecial   java/lang/IllegalStateException.<init>:(Ljava/lang/String;)V
        //   442: aload           6
        //   444: athrow         
        //   445: astore          6
        //   447: aload           5
        //   449: monitorexit    
        //   450: aload           6
        //   452: athrow         
        //   453: aload_0        
        //   454: getfield        ased.a:Ljava/lang/Object;
        //   457: astore          7
        //   459: aload           7
        //   461: checkcast       Lorg/chromium/net/impl/CronetBidirectionalStream;
        //   464: getfield        org/chromium/net/impl/CronetBidirectionalStream.a:Lauep;
        //   467: astore          5
        //   469: aload           7
        //   471: checkcast       Lorg/chromium/net/impl/CronetBidirectionalStream;
        //   474: getfield        org/chromium/net/impl/CronetBidirectionalStream.g:Lauen;
        //   477: astore          6
        //   479: aload           5
        //   481: aload           7
        //   483: checkcast       Lorg/chromium/net/BidirectionalStream;
        //   486: aload           6
        //   488: invokevirtual   org/chromium/net/BidirectionalStream$Callback.onCanceled:(Lorg/chromium/net/BidirectionalStream;Lorg/chromium/net/UrlResponseInfo;)V
        //   491: return         
        //   492: astore          5
        //   494: ldc             "cr_"
        //   496: getstatic       org/chromium/net/impl/CronetUrlRequestContext.b:Ljava/lang/String;
        //   499: invokestatic    java/lang/String.valueOf:(Ljava/lang/Object;)Ljava/lang/String;
        //   502: invokevirtual   java/lang/String.concat:(Ljava/lang/String;)Ljava/lang/String;
        //   505: ldc             "Exception in onCanceled method"
        //   507: aload           5
        //   509: invokestatic    android/util/Log.e:(Ljava/lang/String;Ljava/lang/String;Ljava/lang/Throwable;)I
        //   512: pop            
        //   513: return         
        //   514: aload_0        
        //   515: getfield        ased.a:Ljava/lang/Object;
        //   518: checkcast       Lorg/chromium/net/impl/CronetBidirectionalStream;
        //   521: getfield        org/chromium/net/impl/CronetBidirectionalStream.c:Ljava/lang/Object;
        //   524: astore          5
        //   526: aload           5
        //   528: monitorenter   
        //   529: aload_0        
        //   530: getfield        ased.a:Ljava/lang/Object;
        //   533: astore          6
        //   535: aload           6
        //   537: checkcast       Lorg/chromium/net/impl/CronetBidirectionalStream;
        //   540: invokevirtual   org/chromium/net/impl/CronetBidirectionalStream.e:()Z
        //   543: ifeq            550
        //   546: aload           5
        //   548: monitorexit    
        //   549: return         
        //   550: aload           6
        //   552: checkcast       Lorg/chromium/net/impl/CronetBidirectionalStream;
        //   555: iconst_2       
        //   556: putfield        org/chromium/net/impl/CronetBidirectionalStream.e:I
        //   559: aload           5
        //   561: monitorexit    
        //   562: aload_0        
        //   563: getfield        ased.a:Ljava/lang/Object;
        //   566: astore          6
        //   568: aload           6
        //   570: checkcast       Lorg/chromium/net/impl/CronetBidirectionalStream;
        //   573: getfield        org/chromium/net/impl/CronetBidirectionalStream.a:Lauep;
        //   576: astore          7
        //   578: aload           6
        //   580: checkcast       Lorg/chromium/net/impl/CronetBidirectionalStream;
        //   583: getfield        org/chromium/net/impl/CronetBidirectionalStream.g:Lauen;
        //   586: astore          5
        //   588: aload           7
        //   590: aload           6
        //   592: checkcast       Lorg/chromium/net/BidirectionalStream;
        //   595: aload           5
        //   597: invokevirtual   auep.onResponseHeadersReceived:(Lorg/chromium/net/BidirectionalStream;Lorg/chromium/net/UrlResponseInfo;)V
        //   600: return         
        //   601: astore          5
        //   603: aload_0        
        //   604: getfield        ased.a:Ljava/lang/Object;
        //   607: checkcast       Lorg/chromium/net/impl/CronetBidirectionalStream;
        //   610: aload           5
        //   612: invokevirtual   org/chromium/net/impl/CronetBidirectionalStream.c:(Ljava/lang/Exception;)V
        //   615: return         
        //   616: astore          6
        //   618: aload           5
        //   620: monitorexit    
        //   621: aload           6
        //   623: athrow         
        //   624: aload_0        
        //   625: getfield        ased.a:Ljava/lang/Object;
        //   628: checkcast       Lorg/chromium/net/NetworkChangeNotifierAutoDetect;
        //   631: invokestatic    org/chromium/net/NetworkChangeNotifierAutoDetect.-$$Nest$fgetmIgnoreNextBroadcast:(Lorg/chromium/net/NetworkChangeNotifierAutoDetect;)Z
        //   634: ifeq            649
        //   637: aload_0        
        //   638: getfield        ased.a:Ljava/lang/Object;
        //   641: checkcast       Lorg/chromium/net/NetworkChangeNotifierAutoDetect;
        //   644: iconst_0       
        //   645: invokestatic    org/chromium/net/NetworkChangeNotifierAutoDetect.-$$Nest$fputmIgnoreNextBroadcast:(Lorg/chromium/net/NetworkChangeNotifierAutoDetect;Z)V
        //   648: return         
        //   649: aload_0        
        //   650: getfield        ased.a:Ljava/lang/Object;
        //   653: checkcast       Lorg/chromium/net/NetworkChangeNotifierAutoDetect;
        //   656: invokestatic    org/chromium/net/NetworkChangeNotifierAutoDetect.-$$Nest$mconnectionTypeChanged:(Lorg/chromium/net/NetworkChangeNotifierAutoDetect;)V
        //   659: return         
        //   660: aload_0        
        //   661: getfield        ased.a:Ljava/lang/Object;
        //   664: astore          7
        //   666: aload           7
        //   668: checkcast       Laubw;
        //   671: getfield        aubw.c:Ljava/lang/String;
        //   674: invokestatic    org/chromium/base/TraceEvent.b:(Ljava/lang/String;)Lorg/chromium/base/TraceEvent;
        //   677: astore          5
        //   679: aload           7
        //   681: checkcast       Laubw;
        //   684: getfield        aubw.f:Ljava/lang/Object;
        //   687: astore          6
        //   689: aload           6
        //   691: monitorenter   
        //   692: aload           7
        //   694: checkcast       Laubw;
        //   697: getfield        aubw.g:Ljava/util/LinkedList;
        //   700: astore          8
        //   702: aload           8
        //   704: ifnonnull       721
        //   707: aload           6
        //   709: monitorexit    
        //   710: aload           5
        //   712: ifnull          792
        //   715: aload           5
        //   717: invokevirtual   org/chromium/base/TraceEvent.close:()V
        //   720: return         
        //   721: aload           8
        //   723: invokevirtual   java/util/LinkedList.poll:()Ljava/lang/Object;
        //   726: checkcast       Ljava/lang/Runnable;
        //   729: astore          8
        //   731: aload           6
        //   733: monitorexit    
        //   734: aload           7
        //   736: checkcast       Laubw;
        //   739: getfield        aubw.b:Laubx;
        //   742: getfield        aubx.f:I
        //   745: istore_1       
        //   746: iload_1        
        //   747: iconst_1       
        //   748: if_icmpeq       771
        //   751: iload_1        
        //   752: iconst_2       
        //   753: if_icmpeq       764
        //   756: bipush          10
        //   758: invokestatic    android/os/Process.setThreadPriority:(I)V
        //   761: goto            775
        //   764: iconst_m1      
        //   765: invokestatic    android/os/Process.setThreadPriority:(I)V
        //   768: goto            775
        //   771: iconst_0       
        //   772: invokestatic    android/os/Process.setThreadPriority:(I)V
        //   775: aload           8
        //   777: invokeinterface java/lang/Runnable.run:()V
        //   782: aload           5
        //   784: ifnull          792
        //   787: aload           5
        //   789: invokevirtual   org/chromium/base/TraceEvent.close:()V
        //   792: return         
        //   793: astore          7
        //   795: aload           6
        //   797: monitorexit    
        //   798: aload           7
        //   800: athrow         
        //   801: astore          6
        //   803: aload           5
        //   805: ifnull          849
        //   808: aload           5
        //   810: invokevirtual   org/chromium/base/TraceEvent.close:()V
        //   813: goto            849
        //   816: astore          5
        //   818: ldc             Ljava/lang/Throwable;.class
        //   820: ldc             "addSuppressed"
        //   822: iconst_1       
        //   823: anewarray       Ljava/lang/Class;
        //   826: dup            
        //   827: iconst_0       
        //   828: ldc             Ljava/lang/Throwable;.class
        //   830: aastore        
        //   831: invokevirtual   java/lang/Class.getDeclaredMethod:(Ljava/lang/String;[Ljava/lang/Class;)Ljava/lang/reflect/Method;
        //   834: aload           6
        //   836: iconst_1       
        //   837: anewarray       Ljava/lang/Object;
        //   840: dup            
        //   841: iconst_0       
        //   842: aload           5
        //   844: aastore        
        //   845: invokevirtual   java/lang/reflect/Method.invoke:(Ljava/lang/Object;[Ljava/lang/Object;)Ljava/lang/Object;
        //   848: pop            
        //   849: aload           6
        //   851: athrow         
        //   852: aload_0        
        //   853: getfield        ased.a:Ljava/lang/Object;
        //   856: astore          5
        //   858: bipush          10
        //   860: invokestatic    android/os/Process.setThreadPriority:(I)V
        //   863: aload           5
        //   865: invokeinterface java/lang/Runnable.run:()V
        //   870: return         
        //   871: aload_0        
        //   872: getfield        ased.a:Ljava/lang/Object;
        //   875: checkcast       Lasyw;
        //   878: getfield        asyw.a:Lashy;
        //   881: invokeinterface ashy.tx:()V
        //   886: aload_0        
        //   887: getfield        ased.a:Ljava/lang/Object;
        //   890: checkcast       Lasyw;
        //   893: getfield        asyw.d:Lasic;
        //   896: invokevirtual   asic.dispose:()V
        //   899: return         
        //   900: astore          5
        //   902: aload_0        
        //   903: getfield        ased.a:Ljava/lang/Object;
        //   906: checkcast       Lasyw;
        //   909: getfield        asyw.d:Lasic;
        //   912: invokevirtual   asic.dispose:()V
        //   915: aload           5
        //   917: athrow         
        //   918: aload_0        
        //   919: getfield        ased.a:Ljava/lang/Object;
        //   922: checkcast       Lasol;
        //   925: getfield        asol.a:Laukf;
        //   928: invokeinterface aukf.tx:()V
        //   933: aload_0        
        //   934: getfield        ased.a:Ljava/lang/Object;
        //   937: checkcast       Lasol;
        //   940: getfield        asol.d:Lasic;
        //   943: invokevirtual   asic.dispose:()V
        //   946: return         
        //   947: astore          5
        //   949: aload_0        
        //   950: getfield        ased.a:Ljava/lang/Object;
        //   953: checkcast       Lasol;
        //   956: getfield        asol.d:Lasic;
        //   959: invokevirtual   asic.dispose:()V
        //   962: aload           5
        //   964: athrow         
        //   965: aload_0        
        //   966: getfield        ased.a:Ljava/lang/Object;
        //   969: checkcast       Lasij;
        //   972: invokevirtual   asij.a:()V
        //   975: return         
        //   976: aload_0        
        //   977: getfield        ased.a:Ljava/lang/Object;
        //   980: checkcast       Lasfb;
        //   983: getfield        asfb.b:Lasfe;
        //   986: astore          5
        //   988: aload           5
        //   990: getfield        asfe.w:Z
        //   993: ifne            1006
        //   996: aload           5
        //   998: getfield        asfe.u:Lasae;
        //  1001: invokeinterface asae.e:()V
        //  1006: return         
        //  1007: aload_0        
        //  1008: getfield        ased.a:Ljava/lang/Object;
        //  1011: checkcast       Lasfb;
        //  1014: getfield        asfb.b:Lasfe;
        //  1017: getfield        asfe.f:Ljava/util/concurrent/Executor;
        //  1020: new             Lased;
        //  1023: dup            
        //  1024: aload_0        
        //  1025: bipush          6
        //  1027: aconst_null    
        //  1028: invokespecial   ased.<init>:(Lased;I[B)V
        //  1031: invokeinterface java/util/concurrent/Executor.execute:(Ljava/lang/Runnable;)V
        //  1036: return         
        //  1037: aload_0        
        //  1038: getfield        ased.a:Ljava/lang/Object;
        //  1041: checkcast       Lased;
        //  1044: getfield        ased.a:Ljava/lang/Object;
        //  1047: checkcast       Lasfb;
        //  1050: astore          5
        //  1052: aload           5
        //  1054: getfield        asfb.b:Lasfe;
        //  1057: aload           5
        //  1059: getfield        asfb.a:Lasfc;
        //  1062: getfield        asfc.d:I
        //  1065: iconst_1       
        //  1066: iadd           
        //  1067: iconst_0       
        //  1068: invokevirtual   asfe.p:(IZ)Lasfc;
        //  1071: astore          5
        //  1073: aload_0        
        //  1074: getfield        ased.a:Ljava/lang/Object;
        //  1077: checkcast       Lased;
        //  1080: getfield        ased.a:Ljava/lang/Object;
        //  1083: checkcast       Lasfb;
        //  1086: getfield        asfb.b:Lasfe;
        //  1089: aload           5
        //  1091: invokevirtual   asfe.t:(Lasfc;)V
        //  1094: return         
        //  1095: aload_0        
        //  1096: getfield        ased.a:Ljava/lang/Object;
        //  1099: checkcast       Lymr;
        //  1102: getfield        ymr.b:Ljava/lang/Object;
        //  1105: checkcast       Lasfe;
        //  1108: astore          5
        //  1110: aload           5
        //  1112: aload           5
        //  1114: getfield        asfe.q:Lasez;
        //  1117: getfield        asez.e:I
        //  1120: iconst_0       
        //  1121: invokevirtual   asfe.p:(IZ)Lasfc;
        //  1124: astore          6
        //  1126: aload_0        
        //  1127: getfield        ased.a:Ljava/lang/Object;
        //  1130: checkcast       Lymr;
        //  1133: getfield        ymr.b:Ljava/lang/Object;
        //  1136: checkcast       Lasfe;
        //  1139: getfield        asfe.l:Ljava/lang/Object;
        //  1142: astore          7
        //  1144: aload           7
        //  1146: monitorenter   
        //  1147: aload_0        
        //  1148: getfield        ased.a:Ljava/lang/Object;
        //  1151: astore          5
        //  1153: aload           5
        //  1155: checkcast       Lymr;
        //  1158: getfield        ymr.a:Ljava/lang/Object;
        //  1161: checkcast       Labdo;
        //  1164: getfield        abdo.a:Z
        //  1167: ifeq            1176
        //  1170: aconst_null    
        //  1171: astore          5
        //  1173: goto            1377
        //  1176: aload           5
        //  1178: checkcast       Lymr;
        //  1181: getfield        ymr.b:Ljava/lang/Object;
        //  1184: astore          5
        //  1186: aload           5
        //  1188: checkcast       Lasfe;
        //  1191: getfield        asfe.q:Lasez;
        //  1194: aload           6
        //  1196: invokevirtual   asez.a:(Lasfc;)Lasez;
        //  1199: astore          8
        //  1201: aload           5
        //  1203: checkcast       Lasfe;
        //  1206: aload           8
        //  1208: putfield        asfe.q:Lasez;
        //  1211: aload_0        
        //  1212: getfield        ased.a:Ljava/lang/Object;
        //  1215: checkcast       Lymr;
        //  1218: getfield        ymr.b:Ljava/lang/Object;
        //  1221: astore          5
        //  1223: aload           5
        //  1225: checkcast       Lasfe;
        //  1228: getfield        asfe.q:Lasez;
        //  1231: astore          8
        //  1233: aload           5
        //  1235: checkcast       Lasfe;
        //  1238: aload           8
        //  1240: invokevirtual   asfe.v:(Lasez;)Z
        //  1243: ifeq            1320
        //  1246: aload_0        
        //  1247: getfield        ased.a:Ljava/lang/Object;
        //  1250: checkcast       Lymr;
        //  1253: getfield        ymr.b:Ljava/lang/Object;
        //  1256: checkcast       Lasfe;
        //  1259: getfield        asfe.o:Lasfd;
        //  1262: astore          5
        //  1264: aload           5
        //  1266: ifnull          1277
        //  1269: aload           5
        //  1271: invokevirtual   asfd.a:()Z
        //  1274: ifeq            1320
        //  1277: aload_0        
        //  1278: getfield        ased.a:Ljava/lang/Object;
        //  1281: checkcast       Lymr;
        //  1284: getfield        ymr.b:Ljava/lang/Object;
        //  1287: astore          8
        //  1289: new             Labdo;
        //  1292: astore          5
        //  1294: aload           5
        //  1296: aload           8
        //  1298: checkcast       Lasfe;
        //  1301: getfield        asfe.l:Ljava/lang/Object;
        //  1304: invokespecial   abdo.<init>:(Ljava/lang/Object;)V
        //  1307: aload           8
        //  1309: checkcast       Lasfe;
        //  1312: aload           5
        //  1314: putfield        asfe.B:Labdo;
        //  1317: goto            1375
        //  1320: aload_0        
        //  1321: getfield        ased.a:Ljava/lang/Object;
        //  1324: checkcast       Lymr;
        //  1327: getfield        ymr.b:Ljava/lang/Object;
        //  1330: astore          8
        //  1332: aload           8
        //  1334: checkcast       Lasfe;
        //  1337: getfield        asfe.q:Lasez;
        //  1340: invokevirtual   asez.b:()Lasez;
        //  1343: astore          5
        //  1345: aload           8
        //  1347: checkcast       Lasfe;
        //  1350: aload           5
        //  1352: putfield        asfe.q:Lasez;
        //  1355: aload_0        
        //  1356: getfield        ased.a:Ljava/lang/Object;
        //  1359: checkcast       Lymr;
        //  1362: getfield        ymr.b:Ljava/lang/Object;
        //  1365: checkcast       Lasfe;
        //  1368: aconst_null    
        //  1369: putfield        asfe.B:Labdo;
        //  1372: aconst_null    
        //  1373: astore          5
        //  1375: iconst_0       
        //  1376: istore_1       
        //  1377: aload           7
        //  1379: monitorexit    
        //  1380: iload_1        
        //  1381: ifeq            1404
        //  1384: aload           6
        //  1386: getfield        asfc.a:Lasac;
        //  1389: getstatic       io/grpc/Status.b:Lio/grpc/Status;
        //  1392: ldc_w           "Unneeded hedging"
        //  1395: invokevirtual   io/grpc/Status.withDescription:(Ljava/lang/String;)Lio/grpc/Status;
        //  1398: invokeinterface asac.c:(Lio/grpc/Status;)V
        //  1403: return         
        //  1404: aload           5
        //  1406: ifnull          1463
        //  1409: aload_0        
        //  1410: getfield        ased.a:Ljava/lang/Object;
        //  1413: checkcast       Lymr;
        //  1416: getfield        ymr.b:Ljava/lang/Object;
        //  1419: checkcast       Lasfe;
        //  1422: astore          7
        //  1424: aload           5
        //  1426: aload           7
        //  1428: getfield        asfe.h:Ljava/util/concurrent/ScheduledExecutorService;
        //  1431: new             Lymr;
        //  1434: dup            
        //  1435: aload           7
        //  1437: aload           5
        //  1439: iconst_2       
        //  1440: aconst_null    
        //  1441: invokespecial   ymr.<init>:(Lasfe;Labdo;I[B)V
        //  1444: aload           7
        //  1446: getfield        asfe.j:Lasbz;
        //  1449: getfield        asbz.b:J
        //  1452: getstatic       java/util/concurrent/TimeUnit.NANOSECONDS:Ljava/util/concurrent/TimeUnit;
        //  1455: invokeinterface java/util/concurrent/ScheduledExecutorService.schedule:(Ljava/lang/Runnable;JLjava/util/concurrent/TimeUnit;)Ljava/util/concurrent/ScheduledFuture;
        //  1460: invokevirtual   abdo.j:(Ljava/util/concurrent/Future;)V
        //  1463: aload_0        
        //  1464: getfield        ased.a:Ljava/lang/Object;
        //  1467: checkcast       Lymr;
        //  1470: getfield        ymr.b:Ljava/lang/Object;
        //  1473: checkcast       Lasfe;
        //  1476: aload           6
        //  1478: invokevirtual   asfe.t:(Lasfc;)V
        //  1481: return         
        //  1482: astore          5
        //  1484: aload           7
        //  1486: monitorexit    
        //  1487: aload           5
        //  1489: athrow         
        //  1490: aload_0        
        //  1491: getfield        ased.a:Ljava/lang/Object;
        //  1494: checkcast       Lasfe;
        //  1497: astore          5
        //  1499: aload           5
        //  1501: getfield        asfe.w:Z
        //  1504: ifne            1517
        //  1507: aload           5
        //  1509: getfield        asfe.u:Lasae;
        //  1512: invokeinterface asae.e:()V
        //  1517: return         
        //  1518: aload_0        
        //  1519: getfield        ased.a:Ljava/lang/Object;
        //  1522: checkcast       Laseo;
        //  1525: astore          5
        //  1527: aload           5
        //  1529: getfield        aseo.b:Ljava/util/concurrent/Executor;
        //  1532: new             Lased;
        //  1535: dup            
        //  1536: aload           5
        //  1538: iconst_2       
        //  1539: invokespecial   ased.<init>:(Laseo;I)V
        //  1542: invokeinterface java/util/concurrent/Executor.execute:(Ljava/lang/Runnable;)V
        //  1547: return         
        //  1548: aload_0        
        //  1549: getfield        ased.a:Ljava/lang/Object;
        //  1552: checkcast       Laseo;
        //  1555: astore          5
        //  1557: aload           5
        //  1559: getfield        aseo.e:Z
        //  1562: ifne            1572
        //  1565: aload           5
        //  1567: aconst_null    
        //  1568: putfield        aseo.f:Ljava/util/concurrent/ScheduledFuture;
        //  1571: return         
        //  1572: aload           5
        //  1574: invokevirtual   aseo.a:()J
        //  1577: lstore_3       
        //  1578: aload_0        
        //  1579: getfield        ased.a:Ljava/lang/Object;
        //  1582: checkcast       Laseo;
        //  1585: astore          5
        //  1587: aload           5
        //  1589: getfield        aseo.d:J
        //  1592: lload_3        
        //  1593: lsub           
        //  1594: lstore_3       
        //  1595: lload_3        
        //  1596: lconst_0       
        //  1597: lcmp           
        //  1598: ifle            1631
        //  1601: aload           5
        //  1603: aload           5
        //  1605: getfield        aseo.a:Ljava/util/concurrent/ScheduledExecutorService;
        //  1608: new             Lased;
        //  1611: dup            
        //  1612: aload           5
        //  1614: iconst_3       
        //  1615: invokespecial   ased.<init>:(Laseo;I)V
        //  1618: lload_3        
        //  1619: getstatic       java/util/concurrent/TimeUnit.NANOSECONDS:Ljava/util/concurrent/TimeUnit;
        //  1622: invokeinterface java/util/concurrent/ScheduledExecutorService.schedule:(Ljava/lang/Runnable;JLjava/util/concurrent/TimeUnit;)Ljava/util/concurrent/ScheduledFuture;
        //  1627: putfield        aseo.f:Ljava/util/concurrent/ScheduledFuture;
        //  1630: return         
        //  1631: aload           5
        //  1633: iconst_0       
        //  1634: putfield        aseo.e:Z
        //  1637: aload           5
        //  1639: aconst_null    
        //  1640: putfield        aseo.f:Ljava/util/concurrent/ScheduledFuture;
        //  1643: aload           5
        //  1645: getfield        aseo.c:Ljava/lang/Runnable;
        //  1648: invokeinterface java/lang/Runnable.run:()V
        //  1653: return         
        //  1654: aload_0        
        //  1655: getfield        ased.a:Ljava/lang/Object;
        //  1658: checkcast       Larzi;
        //  1661: getfield        arzi.f:Lasck;
        //  1664: getstatic       asdf.e:Lio/grpc/Status;
        //  1667: invokevirtual   asck.g:(Lio/grpc/Status;)V
        //  1670: return         
        //  1671: aload_0        
        //  1672: getfield        ased.a:Ljava/lang/Object;
        //  1675: checkcast       Lasee;
        //  1678: getfield        asee.a:Larvr;
        //  1681: invokevirtual   arvr.c:()V
        //  1684: return         
        //  1685: aload           5
        //  1687: iconst_2       
        //  1688: putfield        org/chromium/net/impl/CronetUploadDataStream.i:I
        //  1691: aload           6
        //  1693: monitorexit    
        //  1694: aload           5
        //  1696: getfield        org/chromium/net/impl/CronetUploadDataStream.c:Lorg/chromium/net/impl/CronetUrlRequest;
        //  1699: invokevirtual   org/chromium/net/impl/CronetUrlRequest.b:()V
        //  1702: aload           5
        //  1704: getfield        org/chromium/net/impl/CronetUploadDataStream.b:Laueu;
        //  1707: invokevirtual   aueu.getLength:()J
        //  1710: lstore_3       
        //  1711: aload           5
        //  1713: lload_3        
        //  1714: putfield        org/chromium/net/impl/CronetUploadDataStream.d:J
        //  1717: aload           5
        //  1719: lload_3        
        //  1720: putfield        org/chromium/net/impl/CronetUploadDataStream.e:J
        //  1723: goto            1735
        //  1726: astore          6
        //  1728: aload           5
        //  1730: aload           6
        //  1732: invokevirtual   org/chromium/net/impl/CronetUploadDataStream.b:(Ljava/lang/Throwable;)V
        //  1735: aload           5
        //  1737: getfield        org/chromium/net/impl/CronetUploadDataStream.g:Ljava/lang/Object;
        //  1740: astore          6
        //  1742: aload           6
        //  1744: monitorenter   
        //  1745: aload           5
        //  1747: iconst_3       
        //  1748: putfield        org/chromium/net/impl/CronetUploadDataStream.i:I
        //  1751: aload           6
        //  1753: monitorexit    
        //  1754: aload_0        
        //  1755: getfield        ased.a:Ljava/lang/Object;
        //  1758: checkcast       Lorg/chromium/net/impl/CronetUrlRequest;
        //  1761: getfield        org/chromium/net/impl/CronetUrlRequest.c:Ljava/lang/Object;
        //  1764: astore          5
        //  1766: aload           5
        //  1768: monitorenter   
        //  1769: aload_0        
        //  1770: getfield        ased.a:Ljava/lang/Object;
        //  1773: astore          7
        //  1775: aload           7
        //  1777: checkcast       Lorg/chromium/net/impl/CronetUrlRequest;
        //  1780: invokevirtual   org/chromium/net/impl/CronetUrlRequest.j:()Z
        //  1783: ifeq            1790
        //  1786: aload           5
        //  1788: monitorexit    
        //  1789: return         
        //  1790: aload           7
        //  1792: checkcast       Lorg/chromium/net/impl/CronetUrlRequest;
        //  1795: getfield        org/chromium/net/impl/CronetUrlRequest.f:Lorg/chromium/net/impl/CronetUploadDataStream;
        //  1798: astore          6
        //  1800: aload           7
        //  1802: checkcast       Lorg/chromium/net/impl/CronetUrlRequest;
        //  1805: getfield        org/chromium/net/impl/CronetUrlRequest.a:J
        //  1808: lstore_3       
        //  1809: aload           6
        //  1811: getfield        org/chromium/net/impl/CronetUploadDataStream.g:Ljava/lang/Object;
        //  1814: astore          7
        //  1816: aload           7
        //  1818: monitorenter   
        //  1819: aload           6
        //  1821: aload           6
        //  1823: lload_3        
        //  1824: aload           6
        //  1826: getfield        org/chromium/net/impl/CronetUploadDataStream.d:J
        //  1829: invokestatic    J/N.MA4X1aZa:(Ljava/lang/Object;JJ)J
        //  1832: putfield        org/chromium/net/impl/CronetUploadDataStream.h:J
        //  1835: aload           7
        //  1837: monitorexit    
        //  1838: aload_0        
        //  1839: getfield        ased.a:Ljava/lang/Object;
        //  1842: checkcast       Lorg/chromium/net/impl/CronetUrlRequest;
        //  1845: invokevirtual   org/chromium/net/impl/CronetUrlRequest.i:()V
        //  1848: aload           5
        //  1850: monitorexit    
        //  1851: return         
        //  1852: astore          6
        //  1854: aload           7
        //  1856: monitorexit    
        //  1857: aload           6
        //  1859: athrow         
        //  1860: astore          6
        //  1862: aload           5
        //  1864: monitorexit    
        //  1865: aload           6
        //  1867: athrow         
        //  1868: astore          5
        //  1870: aload           6
        //  1872: monitorexit    
        //  1873: aload           5
        //  1875: athrow         
        //  1876: astore          5
        //  1878: aload           6
        //  1880: monitorexit    
        //  1881: aload           5
        //  1883: athrow         
        //  1884: astore          5
        //  1886: goto            849
        //    Exceptions:
        //  Try           Handler
        //  Start  End    Start  End    Type                 
        //  -----  -----  -----  -----  ---------------------
        //  129    152    153    175    Ljava/lang/Exception;
        //  190    212    283    291    Any
        //  213    235    283    291    Any
        //  235    267    268    283    Ljava/lang/Exception;
        //  285    288    283    291    Any
        //  306    328    445    453    Any
        //  329    366    445    453    Any
        //  366    414    415    430    Ljava/lang/Exception;
        //  430    445    445    453    Any
        //  447    450    445    453    Any
        //  453    491    492    514    Ljava/lang/Exception;
        //  529    549    616    624    Any
        //  550    562    616    624    Any
        //  562    600    601    616    Ljava/lang/Exception;
        //  618    621    616    624    Any
        //  679    692    801    852    Any
        //  692    702    793    801    Any
        //  707    710    793    801    Any
        //  721    734    793    801    Any
        //  734    746    801    852    Any
        //  756    761    801    852    Any
        //  764    768    801    852    Any
        //  771    775    801    852    Any
        //  775    782    801    852    Any
        //  795    798    793    801    Any
        //  798    801    801    852    Any
        //  808    813    816    849    Any
        //  818    849    1884   1889   Ljava/lang/Exception;
        //  871    886    900    918    Any
        //  918    933    947    965    Any
        //  1147   1170   1482   1490   Any
        //  1176   1264   1482   1490   Any
        //  1269   1277   1482   1490   Any
        //  1277   1317   1482   1490   Any
        //  1320   1372   1482   1490   Any
        //  1377   1380   1482   1490   Any
        //  1484   1487   1482   1490   Any
        //  1685   1694   1876   1884   Any
        //  1694   1723   1726   1735   Any
        //  1745   1754   1868   1876   Any
        //  1769   1789   1860   1868   Any
        //  1790   1819   1860   1868   Any
        //  1819   1838   1852   1860   Any
        //  1838   1851   1860   1868   Any
        //  1854   1857   1852   1860   Any
        //  1857   1860   1860   1868   Any
        //  1862   1865   1860   1868   Any
        //  1870   1873   1868   1876   Any
        //  1878   1881   1876   1884   Any
        // 
        // The error that occurred was:
        // 
        // java.lang.IllegalStateException: Expression is linked from several locations: Label_0849:
        //     at com.strobel.decompiler.ast.Error.expressionLinkedFromMultipleLocations(Error.java:27)
        //     at com.strobel.decompiler.ast.AstOptimizer.mergeDisparateObjectInitializations(AstOptimizer.java:2604)
        //     at com.strobel.decompiler.ast.AstOptimizer.optimize(AstOptimizer.java:235)
        //     at com.strobel.decompiler.ast.AstOptimizer.optimize(AstOptimizer.java:42)
        //     at com.strobel.decompiler.languages.java.ast.AstMethodBodyBuilder.createMethodBody(AstMethodBodyBuilder.java:206)
        //     at com.strobel.decompiler.languages.java.ast.AstMethodBodyBuilder.createMethodBody(AstMethodBodyBuilder.java:93)
        //     at com.strobel.decompiler.languages.java.ast.AstBuilder.createMethodBody(AstBuilder.java:868)
        //     at com.strobel.decompiler.languages.java.ast.AstBuilder.createMethod(AstBuilder.java:761)
        //     at com.strobel.decompiler.languages.java.ast.AstBuilder.addTypeMembers(AstBuilder.java:638)
        //     at com.strobel.decompiler.languages.java.ast.AstBuilder.createTypeCore(AstBuilder.java:605)
        //     at com.strobel.decompiler.languages.java.ast.AstBuilder.createTypeNoCache(AstBuilder.java:195)
        //     at com.strobel.decompiler.languages.java.ast.AstBuilder.createType(AstBuilder.java:162)
        //     at com.strobel.decompiler.languages.java.ast.AstBuilder.addType(AstBuilder.java:137)
        //     at com.strobel.decompiler.languages.java.JavaLanguage.buildAst(JavaLanguage.java:71)
        //     at com.strobel.decompiler.languages.java.JavaLanguage.decompileType(JavaLanguage.java:59)
        //     at com.strobel.decompiler.DecompilerDriver.decompileType(DecompilerDriver.java:333)
        //     at com.strobel.decompiler.DecompilerDriver.decompileJar(DecompilerDriver.java:254)
        //     at com.strobel.decompiler.DecompilerDriver.main(DecompilerDriver.java:129)
        // 
        throw new IllegalStateException("An error occurred while decompiling this method.");
    }
}
