import android.os.Message;
import java.util.Collections;
import java.util.Iterator;
import java.io.IOException;
import java.util.List;
import androidx.media3.common.Metadata;
import androidx.media3.common.Metadata$Entry;
import android.util.Pair;
import android.os.SystemClock;
import android.os.Handler;
import java.util.ArrayList;
import android.os.HandlerThread;
import java.util.Set;
import android.os.Looper;
import android.os.Handler$Callback;

// 
// Decompiled by Procyon v0.6.0
// 

public final class bfa implements Handler$Callback, bnu, bra, bfl, bec, bfo
{
    private boolean A;
    private int B;
    private boolean C;
    private boolean D;
    private boolean E;
    private int F;
    private bez G;
    private long H;
    private int I;
    private boolean J;
    private bef K;
    private long L;
    private final bea M;
    private mbe N;
    private final aevd O;
    private final pvh P;
    public final bak a;
    public final Looper b;
    public boolean c;
    public boolean d;
    private final bfr[] e;
    private final Set f;
    private final bfs[] g;
    private final brb h;
    private final bfc i;
    private final bre j;
    private final HandlerThread k;
    private final azl l;
    private final azk m;
    private final long n;
    private final boolean o;
    private final bed p;
    private final ArrayList q;
    private final bad r;
    private final bfg s;
    private final bfm t;
    private final long u;
    private bfv v;
    private bfn w;
    private boolean x;
    private boolean y;
    private boolean z;
    
    public bfa(final bfr[] e, final brb h, final aevd o, final bfc i, final bre bre, int j, final bga bga, final bfv v, final bea m, final long u, final boolean x, final Looper looper, final bad r, final pvh p22, final bha bha, final byte[] array, final byte[] array2, final byte[] array3, final byte[] array4, final byte[] array5, final byte[] array6, final byte[] array7) {
        this.P = p22;
        this.e = e;
        this.h = h;
        this.O = o;
        this.i = i;
        this.j = bre;
        this.B = j;
        j = 0;
        this.C = false;
        this.v = v;
        this.M = m;
        this.u = u;
        this.x = x;
        this.r = r;
        this.L = -9223372036854775807L;
        this.n = i.a();
        this.o = i.g();
        this.w = bfn.g(o);
        this.N = new mbe(this.w);
        this.g = new bfs[e.length];
        while (j < e.length) {
            e[j].u(j, bha);
            this.g[j] = e[j].o();
            ++j;
        }
        this.p = new bed((bec)this);
        this.q = new ArrayList();
        this.f = agqs.aj();
        this.l = new azl();
        this.m = new azk();
        h.j = (bra)this;
        h.k = bre;
        this.J = true;
        final Handler handler = new Handler(looper);
        this.s = new bfg(bga, handler);
        this.t = new bfm((bfl)this, bga, handler, bha);
        final HandlerThread k = new HandlerThread("ExoPlayer:Playback", -16);
        (this.k = k).start();
        final Looper looper2 = k.getLooper();
        this.b = looper2;
        this.a = r.b(looper2, (Handler$Callback)this);
    }
    
    private final void A(final long n, final long n2) {
        ((bau)this.a).b.sendEmptyMessageAtTime(2, n + n2);
    }
    
    private final void B(final boolean b) {
        final ayy i = this.s.d.f.i;
        final long t = this.T(i, this.w.o, true, false);
        if (t != this.w.o) {
            final bfn w = this.w;
            this.w = this.U(i, t, w.b, w.c, b, 5);
        }
    }
    
    private final void C(final bfq bfq) {
        if (bfq.e != this.b) {
            this.a.f(15, (Object)bfq).r();
            return;
        }
        f(bfq);
        final int d = this.w.d;
        if (d != 3 && d != 2) {
            return;
        }
        this.a.d(2);
    }
    
    private final void D(final boolean b, int i, final boolean b2, final int c) {
        this.N.b((int)(b2 ? 1 : 0));
        final mbe n = this.N;
        n.d = true;
        n.a = true;
        n.c = c;
        this.w = this.w.a(b, i);
        this.z = false;
        for (bfe bfe = this.s.d; bfe != null; bfe = bfe.h) {
            final bqw[] array = (bqw[])bfe.k.c;
            int length;
            bqw bqw;
            for (length = array.length, i = 0; i < length; ++i) {
                bqw = array[i];
            }
        }
        if (!this.Q()) {
            this.H();
            this.J();
            return;
        }
        i = this.w.d;
        if (i == 3) {
            this.F();
            this.a.d(2);
            return;
        }
        if (i == 2) {
            this.a.d(2);
        }
    }
    
    private final void E(final int n) {
        final bfn w = this.w;
        if (w.d != n) {
            if (n != 2) {
                this.L = -9223372036854775807L;
            }
            this.w = w.d(n);
        }
    }
    
    private final void F() {
        int i = 0;
        this.z = false;
        final bed p = this.p;
        p.f = true;
        p.a.e();
        for (bfr[] e = this.e; i < e.length; ++i) {
            final bfr bfr = e[i];
            if (M(bfr)) {
                bfr.I();
            }
        }
    }
    
    private final void G(final boolean b, final boolean b2) {
        this.w(b || !this.D, false, true, false);
        this.N.b((int)(b2 ? 1 : 0));
        this.i.e();
        this.E(1);
    }
    
    private final void H() {
        this.p.d();
        for (final bfr bfr : this.e) {
            if (M(bfr)) {
                X(bfr);
            }
        }
    }
    
    private final void I() {
        final bfe f = this.s.f;
        final boolean b = this.A || (f != null && f.a.o());
        final bfn w = this.w;
        if (b != w.f) {
            this.w = new bfn(w.a, w.q, w.b, w.c, w.d, w.e, b, w.g, w.s, w.h, w.r, w.i, w.j, w.k, w.m, w.n, w.o, w.l, (byte[])null, (byte[])null, (byte[])null);
        }
    }
    
    private final void J() {
        final bfe d = this.s.d;
        if (d == null) {
            return;
        }
        long e;
        if (d.d) {
            e = d.a.e();
        }
        else {
            e = -9223372036854775807L;
        }
        final int n = 1;
        if (e != -9223372036854775807L) {
            this.y(e);
            if (e != this.w.o) {
                final bfn w = this.w;
                this.w = this.U(w.q, e, w.b, e, true, 5);
            }
        }
        else {
            final bed p = this.p;
            final bfe e2 = this.s.e;
            final bfr c = p.c;
            Label_0350: {
                Label_0328: {
                    if (c != null && !c.S()) {
                        if (!p.c.T()) {
                            if (d != e2) {
                                break Label_0328;
                            }
                            if (p.c.K()) {
                                break Label_0328;
                            }
                        }
                        final bfd d2 = p.d;
                        dk.d((Object)d2);
                        final long kh = d2.kH();
                        if (p.e) {
                            if (kh < p.a.kH()) {
                                p.a.f();
                                break Label_0350;
                            }
                            p.e = false;
                            if (p.f) {
                                p.a.e();
                            }
                        }
                        p.a.d(kh);
                        final azc ki = d2.kI();
                        if (!ki.equals((Object)p.a.a)) {
                            p.a.kJ(ki);
                            ((bfa)p.b).a.f(16, (Object)ki).r();
                        }
                        break Label_0350;
                    }
                }
                p.e = true;
                if (p.f) {
                    p.a.e();
                }
            }
            final long kh2 = p.kH();
            this.H = kh2;
            final long d3 = d.d(kh2);
            final long o = this.w.o;
            Label_0935: {
                if (!this.q.isEmpty()) {
                    if (!this.w.q.a()) {
                        long n2 = o;
                        if (this.J) {
                            n2 = o - 1L;
                            this.J = false;
                        }
                        final bfn w2 = this.w;
                        final int a = w2.a.a(w2.q.a);
                        final int min = Math.min(this.I, this.q.size());
                        long n3 = n2;
                    Label_0639_Outer:
                        while (true) {
                            Label_0581: {
                                int n4;
                                if ((n4 = min) <= 0) {
                                    break Label_0581;
                                }
                                bey bey = this.q.get(min - 1);
                                n4 = min;
                                while (bey != null) {
                                    final int b = bey.b;
                                    if (b <= a && (b != a || bey.c <= n2)) {
                                        break;
                                    }
                                    final int n5 = n4 - 1;
                                    n3 = n2;
                                    if ((n4 = n5) <= 0) {
                                        break Label_0581;
                                    }
                                    bey = (bey)this.q.get(n5 - 1);
                                    n4 = n5;
                                }
                                long n6 = n2;
                                while (true) {
                                    int n7 = 0;
                                    Label_0628: {
                                        if ((n7 = n4) >= this.q.size()) {
                                            break Label_0628;
                                        }
                                        bey bey2 = this.q.get(n4);
                                        int i;
                                        Object a2;
                                        while (true) {
                                            i = n4;
                                            a2 = bey2;
                                            if (bey2 == null) {
                                                break;
                                            }
                                            i = n4;
                                            a2 = bey2;
                                            if (bey2.d == null) {
                                                break;
                                            }
                                            final int b2 = bey2.b;
                                            if (b2 >= a) {
                                                i = n4;
                                                a2 = bey2;
                                                if (b2 != a) {
                                                    break;
                                                }
                                                i = n4;
                                                a2 = bey2;
                                                if (bey2.c > n2) {
                                                    break;
                                                }
                                            }
                                            ++n4;
                                            n6 = n2;
                                            if ((n7 = n4) >= this.q.size()) {
                                                break Label_0628;
                                            }
                                            bey2 = this.q.get(n4);
                                        }
                                        while (a2 != null && ((bey)a2).d != null && ((bey)a2).b == a) {
                                            final long c2 = ((bey)a2).c;
                                            if (c2 > n2 && c2 <= d3) {
                                                try {
                                                    this.C(((bey)a2).a);
                                                    final bfq a3 = ((bey)a2).a;
                                                    if (!a3.h && !a3.b()) {
                                                        ++i;
                                                    }
                                                    else {
                                                        this.q.remove(i);
                                                    }
                                                    if (i < this.q.size()) {
                                                        a2 = this.q.get(i);
                                                        continue Label_0639_Outer;
                                                    }
                                                    a2 = null;
                                                    continue Label_0639_Outer;
                                                }
                                                finally {
                                                    a2 = ((bey)a2).a;
                                                    if (((bfq)a2).h || ((bfq)a2).b()) {
                                                        this.q.remove(i);
                                                    }
                                                }
                                                break;
                                            }
                                            break;
                                        }
                                        this.I = i;
                                        break Label_0935;
                                    }
                                    bey bey2 = null;
                                    n4 = n7;
                                    n2 = n6;
                                    continue;
                                }
                            }
                            bey bey = null;
                            n2 = n3;
                            continue;
                        }
                    }
                }
            }
            this.w.o = d3;
        }
        this.w.m = this.s.f.a();
        this.w.n = this.h();
        final bfn w3 = this.w;
        if (w3.i && w3.d == 3 && this.W(w3.a, w3.q)) {
            final bfn w4 = this.w;
            final float b3 = w4.k.b;
            float o2 = 1.0f;
            if (b3 == 1.0f) {
                final bea m = this.M;
                final long g = this.g(w4.a, w4.q.a, w4.o);
                final long h = this.h();
                Label_1572: {
                    if (m.h != -9223372036854775807L) {
                        final long q = g - h;
                        final long q2 = m.q;
                        if (q2 == -9223372036854775807L) {
                            m.q = q;
                            m.r = 0L;
                        }
                        else {
                            final float g2 = m.g;
                            final long max = Math.max(q, bea.c(q2, q));
                            m.q = max;
                            final long abs = Math.abs(q - max);
                            final long r = m.r;
                            final float g3 = m.g;
                            m.r = bea.c(r, abs);
                        }
                        if (m.p != -9223372036854775807L) {
                            final long elapsedRealtime = SystemClock.elapsedRealtime();
                            final long p2 = m.p;
                            final long c3 = m.c;
                            if (elapsedRealtime - p2 < 1000L) {
                                o2 = m.o;
                                break Label_1572;
                            }
                        }
                        m.p = SystemClock.elapsedRealtime();
                        final long n8 = m.q + m.r * 3L;
                        long k;
                        if (m.l > n8) {
                            final long c4 = m.c;
                            final long w5 = bax.w(1000L);
                            final float o3 = m.o;
                            final float j = m.m;
                            final long[] array = { n8, m.i, 0L };
                            final long l = m.l;
                            final float n9 = (float)w5;
                            array[2] = l - ((long)((o3 - 1.0f) * n9) + (long)((j - 1.0f) * n9));
                            adkp.H(true);
                            k = array[0];
                            for (int n10 = n; n10 < 3; ++n10) {
                                final long n11 = array[n10];
                                if (n11 > k) {
                                    k = n11;
                                }
                            }
                            m.l = k;
                        }
                        else {
                            final float max2 = Math.max(0.0f, m.o - 1.0f);
                            final float d4 = m.d;
                            final long r2 = bax.r(g - (long)(max2 / 1.0E-7f), m.l, n8);
                            m.l = r2;
                            final long k2 = m.k;
                            k = r2;
                            if (k2 != -9223372036854775807L) {
                                k = r2;
                                if (r2 > k2) {
                                    m.l = k2;
                                    k = k2;
                                }
                            }
                        }
                        final long n12 = g - k;
                        if (Math.abs(n12) < m.e) {
                            m.o = 1.0f;
                        }
                        else {
                            final float d5 = m.d;
                            o2 = bax.a(n12 * 1.0E-7f + 1.0f, m.n, m.m);
                            m.o = o2;
                        }
                    }
                }
                if (this.p.kI().b != o2) {
                    this.p.kJ(new azc(o2, this.w.k.c));
                    this.t(this.w.k, this.p.kI().b, false, false);
                }
            }
        }
    }
    
    private final void K(final afaq afaq, final long n) {
        monitorenter(this);
        try {
            final long elapsedRealtime = SystemClock.elapsedRealtime();
            boolean b = false;
            for (long n2 = n; !(boolean)afaq.a() && n2 > 0L; n2 = elapsedRealtime + n - SystemClock.elapsedRealtime()) {
                try {
                    this.wait(n2);
                }
                catch (final InterruptedException ex) {
                    b = true;
                }
            }
            if (b) {
                Thread.currentThread().interrupt();
                monitorexit(this);
                return;
            }
            monitorexit(this);
        }
        finally {
            monitorexit(this);
            while (true) {}
        }
    }
    
    private final boolean L() {
        final bfe f = this.s.f;
        return f != null && f.b() != Long.MIN_VALUE;
    }
    
    private static boolean M(final bfr bfr) {
        return bfr.g() != 0;
    }
    
    private final boolean N() {
        final bfe d = this.s.d;
        final long d2 = d.f.d;
        final boolean d3 = d.d;
        boolean b = false;
        if (d3) {
            if (d2 != -9223372036854775807L && this.w.o >= d2) {
                if (!this.Q()) {
                    return true;
                }
                b = b;
            }
            else {
                b = true;
            }
        }
        return b;
    }
    
    private static boolean O(final bfn bfn, final azk azk) {
        final ayy q = bfn.q;
        final azm a = bfn.a;
        return a.p() || a.n(q.a, azk).f;
    }
    
    private static boolean P(final bey bey, final azm azm, final azm azm2, int a, final boolean b, final azl azl, final azk azk) {
        final Object d = bey.d;
        if (d == null) {
            final long w = bax.w(bey.a.g);
            final bfq a2 = bey.a;
            final Pair k = k(azm, new bez(a2.b, a2.f, w), false, a, b, azl, azk);
            if (k == null) {
                return false;
            }
            bey.a(azm.a(k.first), (long)k.second, k.first);
            final long g = bey.a.g;
            return true;
        }
        else {
            a = azm.a(d);
            if (a == -1) {
                return false;
            }
            final long g2 = bey.a.g;
            bey.b = a;
            azm2.n(bey.d, azk);
            if (azk.f && azm2.o(azk.c, azl).o == azm2.a(bey.d)) {
                final Pair i = azm.k(azl, azk, azm.n(bey.d, azk).c, bey.c + azk.e);
                bey.a(azm.a(i.first), (long)i.second, i.first);
            }
            return true;
        }
    }
    
    private final boolean Q() {
        final bfn w = this.w;
        return w.i && w.j == 0;
    }
    
    private static ayg[] R(final bqw bqw) {
        int i = 0;
        int g;
        if (bqw != null) {
            g = bqw.g();
        }
        else {
            g = 0;
        }
        final ayg[] array = new ayg[g];
        while (i < g) {
            array[i] = bqw.h(i);
            ++i;
        }
        return array;
    }
    
    private final long S(final ayy ayy, final long n, final boolean b) {
        final bfg s = this.s;
        return this.T(ayy, n, s.d != s.e, b);
    }
    
    private final long T(final ayy ayy, long n, final boolean b, final boolean b2) {
        this.H();
        this.z = false;
        if (b2 || this.w.d == 3) {
            this.E(2);
        }
        bfe bfe2;
        bfe bfe;
        for (bfe = (bfe2 = this.s.d); bfe2 != null && !ayy.equals((Object)bfe2.f.i); bfe2 = bfe2.h) {}
        if (b || bfe != bfe2 || (bfe2 != null && bfe2.e(n) < 0L)) {
            final bfr[] e = this.e;
            for (int length = e.length, i = 0; i < length; ++i) {
                this.l(e[i]);
            }
            if (bfe2 != null) {
                bfg s;
                while (true) {
                    s = this.s;
                    if (s.d == bfe2) {
                        break;
                    }
                    s.a();
                }
                s.h(bfe2);
                bfe2.j = 1000000000000L;
                this.n();
            }
        }
        if (bfe2 != null) {
            this.s.h(bfe2);
            long f;
            if (!bfe2.d) {
                bfe2.f = bfe2.f.b(n);
                f = n;
            }
            else {
                f = n;
                if (bfe2.e) {
                    f = bfe2.a.f(n);
                    bfe2.a.i(f - this.n, this.o);
                }
            }
            this.y(f);
            this.u();
            n = f;
        }
        else {
            this.s.d();
            this.y(n);
        }
        this.q(false);
        this.a.d(2);
        return n;
    }
    
    private final bfn U(final ayy ayy, final long n, final long n2, final long n3, final boolean b, final int e) {
        final boolean j = this.J;
        final boolean b2 = false;
        this.J = (j || n != this.w.o || !ayy.equals((Object)this.w.q));
        this.x();
        final bfn w = this.w;
        bpe bpe = w.g;
        aevd aevd = w.s;
        Object o = w.h;
        if (this.t.h) {
            final bfe d = this.s.d;
            if (d == null) {
                bpe = bpe.a;
            }
            else {
                bpe = d.i;
            }
            if (d == null) {
                aevd = this.O;
            }
            else {
                aevd = d.k;
            }
            final Object c = aevd.c;
            final afel afel = new afel();
            final bqw[] array = (bqw[])c;
            final int length = array.length;
            int i = 0;
            int n4 = 0;
            while (i < length) {
                final bqw bqw = array[i];
                int n5 = n4;
                if (bqw != null) {
                    final Metadata l = bqw.h(0).l;
                    if (l == null) {
                        afel.h(new Metadata(new Metadata$Entry[0]));
                        n5 = n4;
                    }
                    else {
                        afel.h(l);
                        n5 = 1;
                    }
                }
                ++i;
                n4 = n5;
            }
            if (n4 != 0) {
                o = afel.g();
            }
            else {
                o = afeq.q();
            }
            if (d != null) {
                final bff f = d.f;
                if (f.b != n2) {
                    d.f = f.a(n2);
                }
            }
        }
        else if (!ayy.equals((Object)w.q)) {
            bpe = bpe.a;
            aevd = this.O;
            o = afeq.q();
        }
        if (b) {
            final mbe n6 = this.N;
            if (n6.f && n6.e != 5) {
                boolean b3 = b2;
                if (e == 5) {
                    b3 = true;
                }
                dk.f(b3);
            }
            else {
                n6.d = true;
                n6.f = true;
                n6.e = e;
            }
        }
        return this.w.h(ayy, n, n2, n3, this.h(), bpe, aevd, (List)o);
    }
    
    private final void V(final azm azm, final ayy ayy, final azm azm2, final ayy ayy2, final long n) {
        if (!this.W(azm, ayy)) {
            azc azc;
            if (ayy.a()) {
                azc = azc.a;
            }
            else {
                azc = this.w.k;
            }
            if (!this.p.kI().equals((Object)azc)) {
                this.p.kJ(azc);
            }
            return;
        }
        azm.o(azm.n(ayy.a, this.m).c, this.l);
        final bea m = this.M;
        final ayp k = this.l.k;
        final int a = bax.a;
        m.h = bax.w(k.a);
        m.j = bax.w(k.b);
        m.k = bax.w(k.c);
        float d;
        if ((d = k.d) == -3.4028235E38f) {
            final float a2 = m.a;
            d = 0.97f;
        }
        m.n = d;
        float e;
        if ((e = k.e) == -3.4028235E38f) {
            final float b = m.b;
            e = 1.03f;
        }
        m.m = e;
        if (d == 1.0f && e == 1.0f) {
            m.h = -9223372036854775807L;
        }
        m.a();
        if (n != -9223372036854775807L) {
            this.M.b(this.g(azm, ayy.a, n));
            return;
        }
        final Object b2 = this.l.b;
        Object b3;
        if (!azm2.p()) {
            b3 = azm2.o(azm2.n(ayy2.a, this.m).c, this.l).b;
        }
        else {
            b3 = null;
        }
        if (!bax.aa(b3, b2)) {
            this.M.b(-9223372036854775807L);
        }
    }
    
    private final boolean W(final azm azm, final ayy ayy) {
        if (!ayy.a()) {
            if (!azm.p()) {
                azm.o(azm.n(ayy.a, this.m).c, this.l);
                if (this.l.d()) {
                    final azl l = this.l;
                    if (l.i && l.f != -9223372036854775807L) {
                        return true;
                    }
                }
            }
        }
        return false;
    }
    
    private static final void X(final bfr bfr) {
        if (bfr.g() == 2) {
            bfr.J();
        }
    }
    
    private static final void Y(final bfr bfr, final long d) {
        bfr.G();
        if (bfr instanceof bqc) {
            final bqc bqc = (bqc)bfr;
            dk.h(((bdx)bqc).c);
            bqc.d = d;
        }
    }
    
    private final void Z(final bpe bpe, final aevd aevd) {
        this.i.f(this.e, bpe, (bqw[])aevd.c);
    }
    
    static Object a(final azl azl, final azk azk, final int n, final boolean b, final Object o, final azm azm, final azm azm2) {
        int n2 = azm.a(o);
        final int b2 = azm.b();
        int n3 = 0;
        int a = -1;
        int n4;
        while (true) {
            n4 = a;
            if (n3 >= b2 || (n4 = a) != -1) {
                break;
            }
            n2 = azm.i(n2, azk, azl, n, b);
            if (n2 == -1) {
                n4 = -1;
                break;
            }
            a = azm2.a(azm.f(n2));
            ++n3;
        }
        if (n4 == -1) {
            return null;
        }
        return azm2.f(n4);
    }
    
    public static final void f(final bfq bfq) {
        if (!bfq.b()) {
            try {
                bfq.a.t(bfq.c, bfq.d);
            }
            finally {
                bfq.a(true);
            }
        }
    }
    
    private final long g(final azm azm, final Object o, final long n) {
        azm.o(azm.n(o, this.m).c, this.l);
        final azl l = this.l;
        if (l.f != -9223372036854775807L && l.d()) {
            final azl i = this.l;
            if (i.i) {
                return bax.w(bax.t(i.g) - this.l.f) - (n + this.m.e);
            }
        }
        return -9223372036854775807L;
    }
    
    private final long h() {
        return this.i(this.w.m);
    }
    
    private final long i(final long n) {
        final bfe f = this.s.f;
        if (f == null) {
            return 0L;
        }
        return Math.max(0L, n - f.d(this.H));
    }
    
    private final Pair j(final azm azm) {
        final boolean p = azm.p();
        final long n = 0L;
        if (p) {
            return Pair.create((Object)bfn.p, (Object)0L);
        }
        final Pair k = azm.k(this.l, this.m, azm.g(this.C), -9223372036854775807L);
        final ayy i = this.s.k(azm, k.first, 0L);
        long longValue = (long)k.second;
        if (i.a()) {
            azm.n(i.a, this.m);
            longValue = n;
            if (i.c == this.m.d(i.b)) {
                this.m.j();
                longValue = n;
            }
        }
        return Pair.create((Object)i, (Object)longValue);
    }
    
    private static Pair k(final azm azm, final bez bez, final boolean b, final int n, final boolean b2, final azl azl, final azk azk) {
        azm a = bez.a;
        if (azm.p()) {
            return null;
        }
        if (a.p()) {
            a = azm;
        }
        try {
            final Pair k = a.k(azl, azk, bez.b, bez.c);
            if (azm.equals((Object)a)) {
                return k;
            }
            if (azm.a(k.first) == -1) {
                if (b) {
                    final Object a2 = a(azl, azk, n, b2, k.first, a, azm);
                    if (a2 != null) {
                        return azm.k(azl, azk, azm.n(a2, azk).c, -9223372036854775807L);
                    }
                }
                return null;
            }
            if (a.n(k.first, azk).f && a.o(azk.c, azl).o == a.a(k.first)) {
                return azm.k(azl, azk, azm.n(k.first, azk).c, bez.c);
            }
            return k;
        }
        catch (final IndexOutOfBoundsException ex) {
            return null;
        }
    }
    
    private final void l(final bfr bfr) {
        if (!M(bfr)) {
            return;
        }
        final bed p = this.p;
        if (bfr == p.c) {
            p.d = null;
            p.c = null;
            p.e = true;
        }
        X(bfr);
        bfr.r();
        --this.F;
    }
    
    private final void m() {
        final long uptimeMillis = SystemClock.uptimeMillis();
        this.a.c();
        if (!this.w.a.p()) {
            if (this.t.h) {
                this.s.f(this.H);
                final bfg s = this.s;
                final bfe f = s.f;
                if (f == null || (!f.f.h && f.i() && s.f.f.d != -9223372036854775807L && s.g < 100)) {
                    final bfg s2 = this.s;
                    final long h = this.H;
                    final bfn w = this.w;
                    final bfe f2 = s2.f;
                    bff bff;
                    if (f2 == null) {
                        bff = s2.j(w.a, w.q, w.b, w.o);
                    }
                    else {
                        bff = s2.b(w.a, f2, h);
                    }
                    if (bff != null) {
                        final bfg s3 = this.s;
                        final bfs[] g = this.g;
                        final brb h2 = this.h;
                        final brf j = this.i.j();
                        final bfm t = this.t;
                        final aevd o = this.O;
                        final bfe f3 = s3.f;
                        long n;
                        if (f3 == null) {
                            n = 1000000000000L;
                        }
                        else {
                            n = f3.j + f3.f.d - bff.a;
                        }
                        final bfe f4 = new bfe(g, n, h2, j, t, bff, o, (byte[])null, (byte[])null, (byte[])null);
                        final bfe f5 = s3.f;
                        if (f5 != null) {
                            f5.g(f4);
                        }
                        else {
                            s3.d = f4;
                            s3.e = f4;
                        }
                        s3.h = null;
                        s3.f = f4;
                        ++s3.g;
                        s3.e();
                        f4.a.l((bnu)this, bff.a);
                        if (this.s.d == f4) {
                            this.y(bff.a);
                        }
                        this.q(false);
                    }
                }
                if (this.A) {
                    this.A = this.L();
                    this.I();
                }
                else {
                    this.u();
                }
                final bfe e = this.s.e;
                if (e != null) {
                    if (e.h != null && !this.y) {
                        if (e.d) {
                            int n2 = 0;
                            while (true) {
                                final bfr[] e2 = this.e;
                                if (n2 < e2.length) {
                                    final bfr bfr = e2[n2];
                                    final bow bow = e.c[n2];
                                    if (bfr.q() != bow) {
                                        break;
                                    }
                                    if (bow != null && !bfr.K()) {
                                        final boolean e3 = e.f.e;
                                        break;
                                    }
                                    ++n2;
                                }
                                else {
                                    final bfe h3 = e.h;
                                    if (!h3.d && this.H < h3.c()) {
                                        break;
                                    }
                                    final aevd k = e.k;
                                    final bfg s4 = this.s;
                                    final bfe e4 = s4.e;
                                    dk.h(e4 != null && e4.h != null);
                                    s4.e = s4.e.h;
                                    s4.e();
                                    final bfe e5 = s4.e;
                                    final aevd i = e5.k;
                                    final azm a = this.w.a;
                                    this.V(a, e5.f.i, a, e.f.i, -9223372036854775807L);
                                    if (e5.d && e5.a.e() != -9223372036854775807L) {
                                        final long c = e5.c();
                                        for (final bfr bfr2 : this.e) {
                                            if (bfr2.q() != null) {
                                                Y(bfr2, c);
                                            }
                                        }
                                        break;
                                    }
                                    for (int n3 = 0; n3 < this.e.length; ++n3) {
                                        final boolean m = k.i(n3);
                                        final boolean i2 = i.i(n3);
                                        if (m && !this.e[n3].L()) {
                                            this.g[n3].h();
                                            final bft bft = ((bft[])k.b)[n3];
                                            final bft bft2 = ((bft[])i.b)[n3];
                                            if (!i2 || !bft2.equals((Object)bft)) {
                                                Y(this.e[n3], e5.c());
                                            }
                                        }
                                    }
                                    break;
                                }
                            }
                        }
                    }
                    else if (e.f.h || this.y) {
                        int n4 = 0;
                        while (true) {
                            final bfr[] e7 = this.e;
                            if (n4 >= e7.length) {
                                break;
                            }
                            final bfr bfr3 = e7[n4];
                            final bow bow2 = e.c[n4];
                            if (bow2 != null && bfr3.q() == bow2 && bfr3.K()) {
                                final long d = e.f.d;
                                long n5;
                                if (d != -9223372036854775807L && d != Long.MIN_VALUE) {
                                    n5 = d + e.j;
                                }
                                else {
                                    n5 = -9223372036854775807L;
                                }
                                Y(bfr3, n5);
                            }
                            ++n4;
                        }
                    }
                }
                final bfg s5 = this.s;
                final bfe e8 = s5.e;
                if (e8 != null && s5.d != e8) {
                    if (!e8.g) {
                        final aevd k2 = e8.k;
                        int n6 = 0;
                        int n7 = 0;
                        while (true) {
                            final bfr[] e9 = this.e;
                            if (n6 >= e9.length) {
                                break;
                            }
                            final bfr bfr4 = e9[n6];
                            int n8 = n7;
                            Label_1221: {
                                if (M(bfr4)) {
                                    final bow q = bfr4.q();
                                    final bow bow3 = e8.c[n6];
                                    if (k2.i(n6)) {
                                        n8 = n7;
                                        if (q == bow3) {
                                            break Label_1221;
                                        }
                                    }
                                    if (!bfr4.L()) {
                                        bfr4.D(R(((bqw[])k2.c)[n6]), e8.c[n6], e8.c(), e8.j);
                                        n8 = n7;
                                    }
                                    else if (bfr4.S()) {
                                        this.l(bfr4);
                                        n8 = n7;
                                    }
                                    else {
                                        n8 = 1;
                                    }
                                }
                            }
                            ++n6;
                            n7 = n8;
                        }
                        if (n7 == 0) {
                            this.n();
                        }
                    }
                }
                int n9 = 0;
                while (this.Q() && !this.y) {
                    final bfe d2 = this.s.d;
                    if (d2 == null) {
                        break;
                    }
                    final bfe h4 = d2.h;
                    if (h4 == null || this.H < h4.c() || !h4.g) {
                        break;
                    }
                    if (n9 != 0) {
                        this.v();
                    }
                    final bfe a2 = this.s.a();
                    dk.d((Object)a2);
                    boolean b = false;
                    Label_1407: {
                        if (this.w.q.a.equals(a2.f.i.a)) {
                            final ayy q2 = this.w.q;
                            if (q2.b == -1) {
                                final ayy i3 = a2.f.i;
                                if (i3.b == -1 && q2.e != i3.e) {
                                    b = true;
                                    break Label_1407;
                                }
                            }
                        }
                        b = false;
                    }
                    final bff f6 = a2.f;
                    final ayy i4 = f6.i;
                    final long a3 = f6.a;
                    this.w = this.U(i4, a3, f6.b, a3, b ^ true, 0);
                    this.x();
                    this.J();
                    n9 = 1;
                }
            }
        }
        final int d3 = this.w.d;
        if (d3 != 1) {
            if (d3 != 4) {
                final bfe d4 = this.s.d;
                if (d4 == null) {
                    this.A(uptimeMillis, 10L);
                    return;
                }
                final int a4 = bax.a;
                this.J();
                int n13;
                int n14;
                if (d4.d) {
                    final long elapsedRealtime = SystemClock.elapsedRealtime();
                    d4.a.i(this.w.o - this.n, this.o);
                    int n10 = 0;
                    int n11 = 1;
                    int n12 = 1;
                    while (true) {
                        final bfr[] e10 = this.e;
                        n13 = n11;
                        n14 = n12;
                        if (n10 >= e10.length) {
                            break;
                        }
                        final bfr bfr5 = e10[n10];
                        int n15 = n11;
                        int n16 = n12;
                        if (M(bfr5)) {
                            bfr5.R(this.H, elapsedRealtime * 1000L);
                            int n17;
                            if (n12 != 0 && bfr5.S()) {
                                n17 = 1;
                            }
                            else {
                                n17 = 0;
                            }
                            final boolean b2 = d4.c[n10] != bfr5.q();
                            final boolean b3 = !b2 && bfr5.K();
                            final boolean b4 = b2 || b3 || bfr5.T() || bfr5.S();
                            int n18;
                            if (n11 != 0 && b4) {
                                n18 = 1;
                            }
                            else {
                                n18 = 0;
                            }
                            n15 = n18;
                            n16 = n17;
                            if (!b4) {
                                bfr5.v();
                                n16 = n17;
                                n15 = n18;
                            }
                        }
                        ++n10;
                        n11 = n15;
                        n12 = n16;
                    }
                }
                else {
                    d4.a.j();
                    n13 = 1;
                    n14 = 1;
                }
                final long d5 = d4.f.d;
                Label_2309: {
                    if (n14 != 0 && d4.d && (d5 == -9223372036854775807L || d5 <= this.w.o)) {
                        if (this.y) {
                            this.D(this.y = false, this.w.j, false, 5);
                        }
                        if (d4.f.h) {
                            this.E(4);
                            this.H();
                            break Label_2309;
                        }
                    }
                    final bfn w2 = this.w;
                    Label_2111: {
                        if (w2.d == 2) {
                            if (this.F == 0) {
                                if (!this.N()) {
                                    break Label_2111;
                                }
                            }
                            else {
                                if (n13 == 0) {
                                    break Label_2111;
                                }
                                if (w2.f) {
                                    long l2;
                                    if (this.W(w2.a, this.s.d.f.i)) {
                                        l2 = this.M.l;
                                    }
                                    else {
                                        l2 = -9223372036854775807L;
                                    }
                                    final bfe f7 = this.s.f;
                                    final boolean b5 = f7.i() && f7.f.h;
                                    final boolean b6 = f7.f.i.a() && !f7.d;
                                    if (!b5 && !b6 && !this.i.i(this.h(), this.p.kI().b, this.z, l2)) {
                                        break Label_2111;
                                    }
                                }
                            }
                            this.E(3);
                            this.K = null;
                            if (this.Q()) {
                                this.F();
                            }
                            break Label_2309;
                        }
                    }
                    if (this.w.d == 3) {
                        if (this.F == 0) {
                            if (this.N()) {
                                break Label_2309;
                            }
                        }
                        else if (n13 != 0) {
                            break Label_2309;
                        }
                        this.z = this.Q();
                        this.E(2);
                        if (this.z) {
                            for (bfe bfe = this.s.d; bfe != null; bfe = bfe.h) {
                                for (final bqw bqw : (bqw[])bfe.k.c) {}
                            }
                            final bea m2 = this.M;
                            final long l3 = m2.l;
                            if (l3 != -9223372036854775807L) {
                                final long l4 = l3 + m2.f;
                                m2.l = l4;
                                final long k3 = m2.k;
                                if (k3 != -9223372036854775807L && l4 > k3) {
                                    m2.l = k3;
                                }
                                m2.p = -9223372036854775807L;
                            }
                        }
                        this.H();
                    }
                }
                Label_2473: {
                    if (this.w.d == 2) {
                        int n20 = 0;
                        while (true) {
                            final bfr[] e11 = this.e;
                            if (n20 >= e11.length) {
                                break;
                            }
                            if (M(e11[n20]) && this.e[n20].q() == d4.c[n20]) {
                                this.e[n20].v();
                            }
                            ++n20;
                        }
                        final bfn w3 = this.w;
                        if (!w3.f && w3.n < 500000L && this.L()) {
                            if (this.L == -9223372036854775807L) {
                                this.L = SystemClock.elapsedRealtime();
                                break Label_2473;
                            }
                            if (SystemClock.elapsedRealtime() - this.L < 4000L) {
                                break Label_2473;
                            }
                            throw new IllegalStateException("Playback stuck buffering and not loading");
                        }
                    }
                    this.L = -9223372036854775807L;
                }
                final boolean b7 = this.Q() && this.w.d == 3;
                final boolean b8 = this.E && this.d && b7;
                final bfn w4 = this.w;
                if (w4.l != b8) {
                    this.w = new bfn(w4.a, w4.q, w4.b, w4.c, w4.d, w4.e, w4.f, w4.g, w4.s, w4.h, w4.r, w4.i, w4.j, w4.k, w4.m, w4.n, w4.o, b8, (byte[])null, (byte[])null, (byte[])null);
                }
                this.d = false;
                if (!b8) {
                    final int d6 = this.w.d;
                    if (d6 != 4) {
                        if (!b7 && d6 != 2) {
                            if (d6 == 3 && this.F != 0) {
                                this.A(uptimeMillis, 1000L);
                            }
                        }
                        else {
                            this.A(uptimeMillis, 10L);
                        }
                    }
                }
            }
        }
    }
    
    private final void n() {
        this.o(new boolean[this.e.length]);
    }
    
    private final void o(final boolean[] array) {
        final bfe e = this.s.e;
        final aevd k = e.k;
        for (int i = 0; i < this.e.length; ++i) {
            if (!k.i(i) && this.f.remove(this.e[i])) {
                this.e[i].E();
            }
        }
        for (int j = 0; j < this.e.length; ++j) {
            if (k.i(j)) {
                final boolean b = array[j];
                final bfr c = this.e[j];
                if (!M(c)) {
                    final bfg s = this.s;
                    final bfe e2 = s.e;
                    final boolean b2 = e2 == s.d;
                    final aevd l = e2.k;
                    final bft bft = ((bft[])l.b)[j];
                    final ayg[] r = R(((bqw[])l.c)[j]);
                    final boolean b3 = this.Q() && this.w.d == 3;
                    final boolean b4 = !b && b3;
                    ++this.F;
                    this.f.add(c);
                    c.s(bft, r, e2.c[j], this.H, b4, b2, e2.c(), e2.j);
                    c.t(11, (Object)new pvh(this));
                    final bed p = this.p;
                    final bfd n = c.n();
                    if (n != null) {
                        final bfd d = p.d;
                        if (n != d) {
                            if (d != null) {
                                throw bef.b(new IllegalStateException("Multiple renderer media clocks enabled."), 1000);
                            }
                            p.d = n;
                            p.c = c;
                            p.d.kJ(p.a.a);
                        }
                    }
                    if (b3) {
                        c.I();
                    }
                }
            }
        }
        e.g = true;
    }
    
    private final void p(final IOException ex, final int n) {
        final bef bef = new bef(0, ex, n);
        final bfe d = this.s.d;
        bef a = bef;
        if (d != null) {
            a = bef.a(d.f.i);
        }
        bap.b("ExoPlayerImplInternal", "Playback error", (Throwable)a);
        this.G(false, false);
        this.w = this.w.b(a);
    }
    
    private final void q(final boolean b) {
        final bfe f = this.s.f;
        ayy ayy;
        if (f == null) {
            ayy = this.w.q;
        }
        else {
            ayy = f.f.i;
        }
        final boolean b2 = this.w.r.equals((Object)ayy) ^ true;
        if (b2) {
            this.w = this.w.f(ayy);
        }
        final bfn w = this.w;
        long m;
        if (f == null) {
            m = w.o;
        }
        else {
            m = f.a();
        }
        w.m = m;
        this.w.n = this.h();
        if ((b2 || b) && f != null && f.d) {
            this.Z(f.i, f.k);
        }
    }
    
    private final void r(final azm p0, final boolean p1) {
        // 
        // This method could not be decompiled.
        // 
        // Original Bytecode:
        // 
        //     1: getfield        bfa.w:Lbfn;
        //     4: astore          33
        //     6: aload_0        
        //     7: getfield        bfa.G:Lbez;
        //    10: astore          36
        //    12: aload_0        
        //    13: getfield        bfa.s:Lbfg;
        //    16: astore          31
        //    18: aload_0        
        //    19: getfield        bfa.B:I
        //    22: istore_3       
        //    23: aload_0        
        //    24: getfield        bfa.C:Z
        //    27: istore          7
        //    29: aload_0        
        //    30: getfield        bfa.l:Lazl;
        //    33: astore          34
        //    35: aload_0        
        //    36: getfield        bfa.m:Lazk;
        //    39: astore          32
        //    41: aload_1        
        //    42: invokevirtual   azm.p:()Z
        //    45: istore          8
        //    47: ldc2_w          -9223372036854775807
        //    50: lstore          23
        //    52: iload           8
        //    54: ifeq            81
        //    57: getstatic       bfn.p:Layy;
        //    60: astore          30
        //    62: lconst_0       
        //    63: lstore          11
        //    65: ldc2_w          -9223372036854775807
        //    68: lstore          9
        //    70: iconst_0       
        //    71: istore_3       
        //    72: iconst_0       
        //    73: istore          7
        //    75: iconst_1       
        //    76: istore          5
        //    78: goto            905
        //    81: aload           33
        //    83: getfield        bfn.q:Layy;
        //    86: astore          30
        //    88: aload           30
        //    90: getfield        ayy.a:Ljava/lang/Object;
        //    93: astore          29
        //    95: aload           33
        //    97: aload           32
        //    99: invokestatic    bfa.O:(Lbfn;Lazk;)Z
        //   102: istore          8
        //   104: aload           33
        //   106: getfield        bfn.q:Layy;
        //   109: invokevirtual   ayy.a:()Z
        //   112: ifne            133
        //   115: iload           8
        //   117: ifeq            123
        //   120: goto            133
        //   123: aload           33
        //   125: getfield        bfn.o:J
        //   128: lstore          9
        //   130: goto            140
        //   133: aload           33
        //   135: getfield        bfn.b:J
        //   138: lstore          9
        //   140: aload           36
        //   142: ifnull          295
        //   145: aload_1        
        //   146: aload           36
        //   148: iconst_1       
        //   149: iload_3        
        //   150: iload           7
        //   152: aload           34
        //   154: aload           32
        //   156: invokestatic    bfa.k:(Lazm;Lbez;ZIZLazl;Lazk;)Landroid/util/Pair;
        //   159: astore          35
        //   161: aload           35
        //   163: ifnonnull       189
        //   166: aload_1        
        //   167: iload           7
        //   169: invokevirtual   azm.g:(Z)I
        //   172: istore_3       
        //   173: lload           9
        //   175: lstore          11
        //   177: iconst_0       
        //   178: istore          7
        //   180: iconst_1       
        //   181: istore          5
        //   183: iconst_0       
        //   184: istore          4
        //   186: goto            282
        //   189: aload           36
        //   191: getfield        bez.c:J
        //   194: ldc2_w          -9223372036854775807
        //   197: lcmp           
        //   198: ifne            226
        //   201: aload_1        
        //   202: aload           35
        //   204: getfield        android/util/Pair.first:Ljava/lang/Object;
        //   207: aload           32
        //   209: invokevirtual   azm.n:(Ljava/lang/Object;Lazk;)Lazk;
        //   212: getfield        azk.c:I
        //   215: istore          4
        //   217: lload           9
        //   219: lstore          11
        //   221: iconst_0       
        //   222: istore_3       
        //   223: goto            251
        //   226: aload           35
        //   228: getfield        android/util/Pair.first:Ljava/lang/Object;
        //   231: astore          29
        //   233: aload           35
        //   235: getfield        android/util/Pair.second:Ljava/lang/Object;
        //   238: checkcast       Ljava/lang/Long;
        //   241: invokevirtual   java/lang/Long.longValue:()J
        //   244: lstore          11
        //   246: iconst_1       
        //   247: istore_3       
        //   248: iconst_m1      
        //   249: istore          4
        //   251: aload           33
        //   253: getfield        bfn.d:I
        //   256: iconst_4       
        //   257: if_icmpne       266
        //   260: iconst_1       
        //   261: istore          7
        //   263: goto            269
        //   266: iconst_0       
        //   267: istore          7
        //   269: iload           4
        //   271: istore          6
        //   273: iconst_0       
        //   274: istore          5
        //   276: iload_3        
        //   277: istore          4
        //   279: iload           6
        //   281: istore_3       
        //   282: iload           5
        //   284: istore          6
        //   286: iload_3        
        //   287: istore          5
        //   289: iload           6
        //   291: istore_3       
        //   292: goto            569
        //   295: aload           33
        //   297: getfield        bfn.a:Lazm;
        //   300: invokevirtual   azm.p:()Z
        //   303: ifeq            337
        //   306: aload_1        
        //   307: iload           7
        //   309: invokevirtual   azm.g:(Z)I
        //   312: istore          4
        //   314: iconst_0       
        //   315: istore_3       
        //   316: lload           9
        //   318: lstore          11
        //   320: iconst_0       
        //   321: istore          7
        //   323: iconst_0       
        //   324: istore          6
        //   326: iload           4
        //   328: istore          5
        //   330: iload           6
        //   332: istore          4
        //   334: goto            569
        //   337: aload_1        
        //   338: aload           29
        //   340: invokevirtual   azm.a:(Ljava/lang/Object;)I
        //   343: iconst_m1      
        //   344: if_icmpne       403
        //   347: aload           34
        //   349: aload           32
        //   351: iload_3        
        //   352: iload           7
        //   354: aload           29
        //   356: aload           33
        //   358: getfield        bfn.a:Lazm;
        //   361: aload_1        
        //   362: invokestatic    bfa.a:(Lazl;Lazk;IZLjava/lang/Object;Lazm;Lazm;)Ljava/lang/Object;
        //   365: astore          35
        //   367: aload           35
        //   369: ifnonnull       385
        //   372: aload_1        
        //   373: iload           7
        //   375: invokevirtual   azm.g:(Z)I
        //   378: istore          4
        //   380: iconst_1       
        //   381: istore_3       
        //   382: goto            400
        //   385: aload_1        
        //   386: aload           35
        //   388: aload           32
        //   390: invokevirtual   azm.n:(Ljava/lang/Object;Lazk;)Lazk;
        //   393: getfield        azk.c:I
        //   396: istore          4
        //   398: iconst_0       
        //   399: istore_3       
        //   400: goto            316
        //   403: lload           9
        //   405: ldc2_w          -9223372036854775807
        //   408: lcmp           
        //   409: ifne            430
        //   412: aload_1        
        //   413: aload           29
        //   415: aload           32
        //   417: invokevirtual   azm.n:(Ljava/lang/Object;Lazk;)Lazk;
        //   420: getfield        azk.c:I
        //   423: istore          4
        //   425: iconst_0       
        //   426: istore_3       
        //   427: goto            316
        //   430: iload           8
        //   432: ifeq            563
        //   435: aload           33
        //   437: getfield        bfn.a:Lazm;
        //   440: astore          35
        //   442: aload           35
        //   444: aload           30
        //   446: getfield        ayy.a:Ljava/lang/Object;
        //   449: aload           32
        //   451: invokevirtual   azm.n:(Ljava/lang/Object;Lazk;)Lazk;
        //   454: pop            
        //   455: aload           33
        //   457: getfield        bfn.a:Lazm;
        //   460: aload           32
        //   462: getfield        azk.c:I
        //   465: aload           34
        //   467: invokevirtual   azm.o:(ILazl;)Lazl;
        //   470: getfield        azl.o:I
        //   473: aload           33
        //   475: getfield        bfn.a:Lazm;
        //   478: aload           30
        //   480: getfield        ayy.a:Ljava/lang/Object;
        //   483: invokevirtual   azm.a:(Ljava/lang/Object;)I
        //   486: if_icmpne       545
        //   489: aload           32
        //   491: getfield        azk.e:J
        //   494: lstore          11
        //   496: aload_1        
        //   497: aload           34
        //   499: aload           32
        //   501: aload_1        
        //   502: aload           29
        //   504: aload           32
        //   506: invokevirtual   azm.n:(Ljava/lang/Object;Lazk;)Lazk;
        //   509: getfield        azk.c:I
        //   512: lload           9
        //   514: lload           11
        //   516: ladd           
        //   517: invokevirtual   azm.k:(Lazl;Lazk;IJ)Landroid/util/Pair;
        //   520: astore          35
        //   522: aload           35
        //   524: getfield        android/util/Pair.first:Ljava/lang/Object;
        //   527: astore          29
        //   529: aload           35
        //   531: getfield        android/util/Pair.second:Ljava/lang/Object;
        //   534: checkcast       Ljava/lang/Long;
        //   537: invokevirtual   java/lang/Long.longValue:()J
        //   540: lstore          11
        //   542: goto            549
        //   545: lload           9
        //   547: lstore          11
        //   549: iconst_m1      
        //   550: istore          5
        //   552: iconst_0       
        //   553: istore          7
        //   555: iconst_0       
        //   556: istore_3       
        //   557: iconst_1       
        //   558: istore          4
        //   560: goto            569
        //   563: iconst_m1      
        //   564: istore          4
        //   566: goto            425
        //   569: iload           5
        //   571: iconst_m1      
        //   572: if_icmpeq       618
        //   575: aload_1        
        //   576: aload           34
        //   578: aload           32
        //   580: iload           5
        //   582: ldc2_w          -9223372036854775807
        //   585: invokevirtual   azm.k:(Lazl;Lazk;IJ)Landroid/util/Pair;
        //   588: astore          34
        //   590: aload           34
        //   592: getfield        android/util/Pair.first:Ljava/lang/Object;
        //   595: astore          29
        //   597: aload           34
        //   599: getfield        android/util/Pair.second:Ljava/lang/Object;
        //   602: checkcast       Ljava/lang/Long;
        //   605: invokevirtual   java/lang/Long.longValue:()J
        //   608: lstore          11
        //   610: ldc2_w          -9223372036854775807
        //   613: lstore          13
        //   615: goto            622
        //   618: lload           11
        //   620: lstore          13
        //   622: aload           31
        //   624: aload_1        
        //   625: aload           29
        //   627: lload           11
        //   629: invokevirtual   bfg.k:(Lazm;Ljava/lang/Object;J)Layy;
        //   632: astore          31
        //   634: aload           31
        //   636: getfield        ayy.e:I
        //   639: istore          6
        //   641: iload           6
        //   643: iconst_m1      
        //   644: if_icmpeq       676
        //   647: aload           30
        //   649: getfield        ayy.e:I
        //   652: istore          5
        //   654: iload           5
        //   656: iconst_m1      
        //   657: if_icmpeq       670
        //   660: iload           6
        //   662: iload           5
        //   664: if_icmplt       670
        //   667: goto            676
        //   670: iconst_0       
        //   671: istore          5
        //   673: goto            679
        //   676: iconst_1       
        //   677: istore          5
        //   679: aload           30
        //   681: getfield        ayy.a:Ljava/lang/Object;
        //   684: aload           29
        //   686: invokevirtual   java/lang/Object.equals:(Ljava/lang/Object;)Z
        //   689: ifeq            719
        //   692: aload           30
        //   694: invokevirtual   ayy.a:()Z
        //   697: ifne            719
        //   700: aload           31
        //   702: invokevirtual   ayy.a:()Z
        //   705: ifne            719
        //   708: iload           5
        //   710: ifeq            719
        //   713: iconst_1       
        //   714: istore          5
        //   716: goto            722
        //   719: iconst_0       
        //   720: istore          5
        //   722: aload_1        
        //   723: aload           29
        //   725: aload           32
        //   727: invokevirtual   azm.n:(Ljava/lang/Object;Lazk;)Lazk;
        //   730: astore          29
        //   732: iload           8
        //   734: ifne            800
        //   737: lload           9
        //   739: lload           13
        //   741: lcmp           
        //   742: ifne            800
        //   745: aload           30
        //   747: getfield        ayy.a:Ljava/lang/Object;
        //   750: aload           31
        //   752: getfield        ayy.a:Ljava/lang/Object;
        //   755: invokevirtual   java/lang/Object.equals:(Ljava/lang/Object;)Z
        //   758: ifne            764
        //   761: goto            800
        //   764: aload           30
        //   766: invokevirtual   ayy.a:()Z
        //   769: ifeq            782
        //   772: aload           29
        //   774: aload           30
        //   776: getfield        ayy.b:I
        //   779: invokevirtual   azk.k:(I)V
        //   782: aload           31
        //   784: invokevirtual   ayy.a:()Z
        //   787: ifeq            800
        //   790: aload           29
        //   792: aload           31
        //   794: getfield        ayy.b:I
        //   797: invokevirtual   azk.k:(I)V
        //   800: iconst_1       
        //   801: iload           5
        //   803: if_icmpeq       813
        //   806: aload           31
        //   808: astore          29
        //   810: goto            817
        //   813: aload           30
        //   815: astore          29
        //   817: lload           11
        //   819: lstore          9
        //   821: aload           29
        //   823: invokevirtual   ayy.a:()Z
        //   826: ifeq            887
        //   829: aload           29
        //   831: aload           30
        //   833: invokevirtual   ayy.equals:(Ljava/lang/Object;)Z
        //   836: ifeq            849
        //   839: aload           33
        //   841: getfield        bfn.o:J
        //   844: lstore          9
        //   846: goto            887
        //   849: aload_1        
        //   850: aload           29
        //   852: getfield        ayy.a:Ljava/lang/Object;
        //   855: aload           32
        //   857: invokevirtual   azm.n:(Ljava/lang/Object;Lazk;)Lazk;
        //   860: pop            
        //   861: aload           29
        //   863: getfield        ayy.c:I
        //   866: aload           32
        //   868: aload           29
        //   870: getfield        ayy.b:I
        //   873: invokevirtual   azk.d:(I)I
        //   876: if_icmpne       884
        //   879: aload           32
        //   881: invokevirtual   azk.j:()V
        //   884: lconst_0       
        //   885: lstore          9
        //   887: iload_3        
        //   888: istore          5
        //   890: lload           9
        //   892: lstore          11
        //   894: iload           4
        //   896: istore_3       
        //   897: lload           13
        //   899: lstore          9
        //   901: aload           29
        //   903: astore          30
        //   905: aload_0        
        //   906: getfield        bfa.w:Lbfn;
        //   909: getfield        bfn.q:Layy;
        //   912: aload           30
        //   914: invokevirtual   ayy.equals:(Ljava/lang/Object;)Z
        //   917: ifeq            942
        //   920: lload           11
        //   922: aload_0        
        //   923: getfield        bfa.w:Lbfn;
        //   926: getfield        bfn.o:J
        //   929: lcmp           
        //   930: ifeq            936
        //   933: goto            942
        //   936: iconst_0       
        //   937: istore          4
        //   939: goto            945
        //   942: iconst_1       
        //   943: istore          4
        //   945: iload           5
        //   947: ifeq            1004
        //   950: lload           9
        //   952: lstore          13
        //   954: aload_0        
        //   955: getfield        bfa.w:Lbfn;
        //   958: getfield        bfn.d:I
        //   961: iconst_1       
        //   962: if_icmpeq       977
        //   965: lload           9
        //   967: lstore          13
        //   969: aload_0        
        //   970: iconst_4       
        //   971: invokespecial   bfa.E:(I)V
        //   974: goto            977
        //   977: lload           9
        //   979: lstore          13
        //   981: aload_0        
        //   982: iconst_0       
        //   983: iconst_0       
        //   984: iconst_0       
        //   985: iconst_1       
        //   986: invokespecial   bfa.w:(ZZZZ)V
        //   989: goto            1004
        //   992: astore          29
        //   994: lload           13
        //   996: lstore          17
        //   998: iconst_4       
        //   999: istore          5
        //  1001: goto            2117
        //  1004: iload           4
        //  1006: ifne            1729
        //  1009: lload           9
        //  1011: lstore          13
        //  1013: aload_0        
        //  1014: getfield        bfa.s:Lbfg;
        //  1017: astore          33
        //  1019: lload           9
        //  1021: lstore          13
        //  1023: aload_0        
        //  1024: getfield        bfa.H:J
        //  1027: lstore          21
        //  1029: lload           9
        //  1031: lstore          13
        //  1033: aload           33
        //  1035: getfield        bfg.e:Lbfe;
        //  1038: astore          29
        //  1040: aload           29
        //  1042: ifnonnull       1051
        //  1045: lconst_0       
        //  1046: lstore          15
        //  1048: goto            1220
        //  1051: lload           9
        //  1053: lstore          13
        //  1055: aload           29
        //  1057: getfield        bfe.j:J
        //  1060: lstore          15
        //  1062: lload           9
        //  1064: lstore          13
        //  1066: aload           29
        //  1068: getfield        bfe.d:Z
        //  1071: ifeq            1220
        //  1074: iconst_0       
        //  1075: istore          5
        //  1077: lload           9
        //  1079: lstore          13
        //  1081: aload_0        
        //  1082: getfield        bfa.e:[Lbfr;
        //  1085: astore          31
        //  1087: lload           9
        //  1089: lstore          13
        //  1091: iload           5
        //  1093: aload           31
        //  1095: arraylength    
        //  1096: if_icmpge       1217
        //  1099: lload           9
        //  1101: lstore          13
        //  1103: aload           31
        //  1105: iload           5
        //  1107: aaload         
        //  1108: invokestatic    bfa.M:(Lbfr;)Z
        //  1111: ifeq            1203
        //  1114: lload           9
        //  1116: lstore          13
        //  1118: aload_0        
        //  1119: getfield        bfa.e:[Lbfr;
        //  1122: iload           5
        //  1124: aaload         
        //  1125: invokeinterface bfr.q:()Lbow;
        //  1130: aload           29
        //  1132: getfield        bfe.c:[Lbow;
        //  1135: iload           5
        //  1137: aaload         
        //  1138: if_acmpeq       1144
        //  1141: goto            1203
        //  1144: lload           9
        //  1146: lstore          13
        //  1148: aload_0        
        //  1149: getfield        bfa.e:[Lbfr;
        //  1152: iload           5
        //  1154: aaload         
        //  1155: invokeinterface bfr.k:()J
        //  1160: lstore          19
        //  1162: lload           19
        //  1164: ldc2_w          -9223372036854775808
        //  1167: lcmp           
        //  1168: ifne            1179
        //  1171: ldc2_w          -9223372036854775808
        //  1174: lstore          15
        //  1176: goto            1220
        //  1179: lload           9
        //  1181: lstore          17
        //  1183: lload           11
        //  1185: lstore          13
        //  1187: lload           19
        //  1189: lload           15
        //  1191: invokestatic    java/lang/Math.max:(JJ)J
        //  1194: lstore          15
        //  1196: lload           15
        //  1198: lstore          13
        //  1200: goto            1207
        //  1203: lload           15
        //  1205: lstore          13
        //  1207: iinc            5, 1
        //  1210: lload           13
        //  1212: lstore          15
        //  1214: goto            1077
        //  1217: goto            1220
        //  1220: lload           11
        //  1222: lstore          13
        //  1224: lload           9
        //  1226: lstore          17
        //  1228: aload           33
        //  1230: getfield        bfg.d:Lbfe;
        //  1233: astore          29
        //  1235: aconst_null    
        //  1236: astore          31
        //  1238: lload           11
        //  1240: lstore          13
        //  1242: aload           29
        //  1244: ifnull          1713
        //  1247: lload           11
        //  1249: lstore          13
        //  1251: lload           9
        //  1253: lstore          17
        //  1255: aload           29
        //  1257: getfield        bfe.f:Lbff;
        //  1260: astore          34
        //  1262: aload           31
        //  1264: ifnonnull       1288
        //  1267: lload           11
        //  1269: lstore          13
        //  1271: lload           9
        //  1273: lstore          17
        //  1275: aload           33
        //  1277: aload_1        
        //  1278: aload           34
        //  1280: invokevirtual   bfg.c:(Lazm;Lbff;)Lbff;
        //  1283: astore          31
        //  1285: goto            1407
        //  1288: lload           11
        //  1290: lstore          13
        //  1292: lload           9
        //  1294: lstore          17
        //  1296: aload           33
        //  1298: aload_1        
        //  1299: aload           31
        //  1301: lload           21
        //  1303: invokevirtual   bfg.b:(Lazm;Lbfe;J)Lbff;
        //  1306: astore          32
        //  1308: aload           32
        //  1310: ifnonnull       1341
        //  1313: lload           11
        //  1315: lstore          13
        //  1317: lload           9
        //  1319: lstore          17
        //  1321: aload           33
        //  1323: aload           31
        //  1325: invokevirtual   bfg.h:(Lbfe;)Z
        //  1328: ifne            1338
        //  1331: lload           11
        //  1333: lstore          13
        //  1335: goto            1713
        //  1338: goto            1689
        //  1341: lload           11
        //  1343: lstore          13
        //  1345: lload           9
        //  1347: lstore          17
        //  1349: aload           34
        //  1351: getfield        bff.a:J
        //  1354: lstore          25
        //  1356: lload           11
        //  1358: lstore          19
        //  1360: lload           9
        //  1362: lstore          17
        //  1364: lload           19
        //  1366: lstore          13
        //  1368: lload           25
        //  1370: aload           32
        //  1372: getfield        bff.a:J
        //  1375: lcmp           
        //  1376: ifne            1664
        //  1379: lload           9
        //  1381: lstore          17
        //  1383: lload           19
        //  1385: lstore          13
        //  1387: aload           34
        //  1389: getfield        bff.i:Layy;
        //  1392: aload           32
        //  1394: getfield        bff.i:Layy;
        //  1397: invokevirtual   ayy.equals:(Ljava/lang/Object;)Z
        //  1400: ifeq            1664
        //  1403: aload           32
        //  1405: astore          31
        //  1407: lload           11
        //  1409: lstore          19
        //  1411: lload           9
        //  1413: lstore          17
        //  1415: lload           19
        //  1417: lstore          13
        //  1419: aload           29
        //  1421: aload           31
        //  1423: aload           34
        //  1425: getfield        bff.b:J
        //  1428: invokevirtual   bff.a:(J)Lbff;
        //  1431: putfield        bfe.f:Lbff;
        //  1434: lload           9
        //  1436: lstore          17
        //  1438: lload           19
        //  1440: lstore          13
        //  1442: aload           34
        //  1444: getfield        bff.d:J
        //  1447: lstore          25
        //  1449: lload           9
        //  1451: lstore          17
        //  1453: lload           19
        //  1455: lstore          13
        //  1457: aload           31
        //  1459: getfield        bff.d:J
        //  1462: lstore          27
        //  1464: lload           25
        //  1466: ldc2_w          -9223372036854775807
        //  1469: lcmp           
        //  1470: ifeq            1634
        //  1473: lload           25
        //  1475: lload           27
        //  1477: lcmp           
        //  1478: ifne            1484
        //  1481: goto            1634
        //  1484: lload           9
        //  1486: lstore          17
        //  1488: lload           19
        //  1490: lstore          13
        //  1492: aload           29
        //  1494: invokevirtual   bfe.h:()V
        //  1497: lload           9
        //  1499: lstore          17
        //  1501: lload           19
        //  1503: lstore          13
        //  1505: aload           31
        //  1507: getfield        bff.d:J
        //  1510: lstore          21
        //  1512: lload           21
        //  1514: ldc2_w          -9223372036854775807
        //  1517: lcmp           
        //  1518: ifne            1529
        //  1521: ldc2_w          9223372036854775807
        //  1524: lstore          21
        //  1526: goto            1546
        //  1529: lload           9
        //  1531: lstore          17
        //  1533: lload           19
        //  1535: lstore          13
        //  1537: aload           29
        //  1539: lload           21
        //  1541: invokevirtual   bfe.e:(J)J
        //  1544: lstore          21
        //  1546: lload           9
        //  1548: lstore          17
        //  1550: lload           19
        //  1552: lstore          13
        //  1554: aload           29
        //  1556: aload           33
        //  1558: getfield        bfg.e:Lbfe;
        //  1561: if_acmpne       1605
        //  1564: lload           9
        //  1566: lstore          17
        //  1568: lload           19
        //  1570: lstore          13
        //  1572: aload           29
        //  1574: getfield        bfe.f:Lbff;
        //  1577: getfield        bff.e:Z
        //  1580: istore          7
        //  1582: lload           15
        //  1584: ldc2_w          -9223372036854775808
        //  1587: lcmp           
        //  1588: ifeq            1599
        //  1591: lload           15
        //  1593: lload           21
        //  1595: lcmp           
        //  1596: iflt            1605
        //  1599: iconst_1       
        //  1600: istore          5
        //  1602: goto            1608
        //  1605: iconst_0       
        //  1606: istore          5
        //  1608: lload           9
        //  1610: lstore          17
        //  1612: lload           19
        //  1614: lstore          13
        //  1616: aload           33
        //  1618: aload           29
        //  1620: invokevirtual   bfg.h:(Lbfe;)Z
        //  1623: ifne            1338
        //  1626: iload           5
        //  1628: ifne            1338
        //  1631: goto            1682
        //  1634: lload           9
        //  1636: lstore          17
        //  1638: lload           19
        //  1640: lstore          13
        //  1642: aload           29
        //  1644: getfield        bfe.h:Lbfe;
        //  1647: astore          32
        //  1649: aload           29
        //  1651: astore          31
        //  1653: lload           19
        //  1655: lstore          11
        //  1657: aload           32
        //  1659: astore          29
        //  1661: goto            1238
        //  1664: lload           9
        //  1666: lstore          17
        //  1668: lload           19
        //  1670: lstore          13
        //  1672: aload           33
        //  1674: aload           31
        //  1676: invokevirtual   bfg.h:(Lbfe;)Z
        //  1679: ifne            1338
        //  1682: lload           11
        //  1684: lstore          13
        //  1686: goto            1713
        //  1689: lload           9
        //  1691: lstore          17
        //  1693: lload           11
        //  1695: lstore          13
        //  1697: aload_0        
        //  1698: iconst_0       
        //  1699: invokespecial   bfa.B:(Z)V
        //  1702: lload           9
        //  1704: lstore          15
        //  1706: lload           11
        //  1708: lstore          19
        //  1710: goto            1878
        //  1713: lload           13
        //  1715: lstore          11
        //  1717: goto            1886
        //  1720: astore          29
        //  1722: lload           13
        //  1724: lstore          11
        //  1726: goto            998
        //  1729: lload           9
        //  1731: lstore          15
        //  1733: lload           11
        //  1735: lstore          19
        //  1737: lload           9
        //  1739: lstore          17
        //  1741: lload           11
        //  1743: lstore          13
        //  1745: aload_1        
        //  1746: invokevirtual   azm.p:()Z
        //  1749: ifne            1878
        //  1752: lload           9
        //  1754: lstore          17
        //  1756: lload           11
        //  1758: lstore          13
        //  1760: aload_0        
        //  1761: getfield        bfa.s:Lbfg;
        //  1764: getfield        bfg.d:Lbfe;
        //  1767: astore          29
        //  1769: aload           29
        //  1771: ifnull          1855
        //  1774: lload           9
        //  1776: lstore          17
        //  1778: lload           11
        //  1780: lstore          13
        //  1782: aload           29
        //  1784: getfield        bfe.f:Lbff;
        //  1787: getfield        bff.i:Layy;
        //  1790: aload           30
        //  1792: invokevirtual   ayy.equals:(Ljava/lang/Object;)Z
        //  1795: ifeq            1837
        //  1798: lload           9
        //  1800: lstore          17
        //  1802: lload           11
        //  1804: lstore          13
        //  1806: aload           29
        //  1808: aload_0        
        //  1809: getfield        bfa.s:Lbfg;
        //  1812: aload_1        
        //  1813: aload           29
        //  1815: getfield        bfe.f:Lbff;
        //  1818: invokevirtual   bfg.c:(Lazm;Lbff;)Lbff;
        //  1821: putfield        bfe.f:Lbff;
        //  1824: lload           9
        //  1826: lstore          17
        //  1828: lload           11
        //  1830: lstore          13
        //  1832: aload           29
        //  1834: invokevirtual   bfe.h:()V
        //  1837: lload           9
        //  1839: lstore          17
        //  1841: lload           11
        //  1843: lstore          13
        //  1845: aload           29
        //  1847: getfield        bfe.h:Lbfe;
        //  1850: astore          29
        //  1852: goto            1769
        //  1855: lload           11
        //  1857: lstore          13
        //  1859: lload           9
        //  1861: lstore          17
        //  1863: aload_0        
        //  1864: aload           30
        //  1866: lload           11
        //  1868: iload           7
        //  1870: invokespecial   bfa.S:(Layy;JZ)J
        //  1873: lstore          11
        //  1875: goto            1886
        //  1878: lload           19
        //  1880: lstore          11
        //  1882: lload           15
        //  1884: lstore          9
        //  1886: aload_0        
        //  1887: getfield        bfa.w:Lbfn;
        //  1890: astore          31
        //  1892: aload           31
        //  1894: getfield        bfn.a:Lazm;
        //  1897: astore          29
        //  1899: aload           31
        //  1901: getfield        bfn.q:Layy;
        //  1904: astore          31
        //  1906: iconst_1       
        //  1907: iload_3        
        //  1908: if_icmpeq       1919
        //  1911: ldc2_w          -9223372036854775807
        //  1914: lstore          13
        //  1916: goto            1923
        //  1919: lload           11
        //  1921: lstore          13
        //  1923: iconst_4       
        //  1924: istore_3       
        //  1925: aload_0        
        //  1926: aload_1        
        //  1927: aload           30
        //  1929: aload           29
        //  1931: aload           31
        //  1933: lload           13
        //  1935: invokespecial   bfa.V:(Lazm;Layy;Lazm;Layy;J)V
        //  1938: iload           4
        //  1940: ifne            1956
        //  1943: lload           9
        //  1945: aload_0        
        //  1946: getfield        bfa.w:Lbfn;
        //  1949: getfield        bfn.b:J
        //  1952: lcmp           
        //  1953: ifeq            2062
        //  1956: aload_0        
        //  1957: getfield        bfa.w:Lbfn;
        //  1960: astore          31
        //  1962: aload           31
        //  1964: getfield        bfn.q:Layy;
        //  1967: getfield        ayy.a:Ljava/lang/Object;
        //  1970: astore          29
        //  1972: aload           31
        //  1974: getfield        bfn.a:Lazm;
        //  1977: astore          31
        //  1979: iload           4
        //  1981: ifeq            2018
        //  1984: iload_2        
        //  1985: ifeq            2018
        //  1988: aload           31
        //  1990: invokevirtual   azm.p:()Z
        //  1993: ifne            2018
        //  1996: aload           31
        //  1998: aload           29
        //  2000: aload_0        
        //  2001: getfield        bfa.m:Lazk;
        //  2004: invokevirtual   azm.n:(Ljava/lang/Object;Lazk;)Lazk;
        //  2007: getfield        azk.f:Z
        //  2010: ifne            2018
        //  2013: iconst_1       
        //  2014: istore_2       
        //  2015: goto            2020
        //  2018: iconst_0       
        //  2019: istore_2       
        //  2020: aload_0        
        //  2021: getfield        bfa.w:Lbfn;
        //  2024: getfield        bfn.c:J
        //  2027: lstore          13
        //  2029: aload_1        
        //  2030: aload           29
        //  2032: invokevirtual   azm.a:(Ljava/lang/Object;)I
        //  2035: iconst_m1      
        //  2036: if_icmpne       2042
        //  2039: goto            2044
        //  2042: iconst_3       
        //  2043: istore_3       
        //  2044: aload_0        
        //  2045: aload_0        
        //  2046: aload           30
        //  2048: lload           11
        //  2050: lload           9
        //  2052: lload           13
        //  2054: iload_2        
        //  2055: iload_3        
        //  2056: invokespecial   bfa.U:(Layy;JJJZI)Lbfn;
        //  2059: putfield        bfa.w:Lbfn;
        //  2062: aload_0        
        //  2063: invokespecial   bfa.x:()V
        //  2066: aload_0        
        //  2067: aload_1        
        //  2068: aload_0        
        //  2069: getfield        bfa.w:Lbfn;
        //  2072: getfield        bfn.a:Lazm;
        //  2075: invokespecial   bfa.z:(Lazm;Lazm;)V
        //  2078: aload_0        
        //  2079: aload_0        
        //  2080: getfield        bfa.w:Lbfn;
        //  2083: aload_1        
        //  2084: invokevirtual   bfn.e:(Lazm;)Lbfn;
        //  2087: putfield        bfa.w:Lbfn;
        //  2090: aload_1        
        //  2091: invokevirtual   azm.p:()Z
        //  2094: ifne            2102
        //  2097: aload_0        
        //  2098: aconst_null    
        //  2099: putfield        bfa.G:Lbez;
        //  2102: aload_0        
        //  2103: iconst_0       
        //  2104: invokespecial   bfa.q:(Z)V
        //  2107: return         
        //  2108: astore          29
        //  2110: lload           13
        //  2112: lstore          11
        //  2114: goto            998
        //  2117: aload_0        
        //  2118: getfield        bfa.w:Lbfn;
        //  2121: astore          32
        //  2123: aload           32
        //  2125: getfield        bfn.a:Lazm;
        //  2128: astore          31
        //  2130: aload           32
        //  2132: getfield        bfn.q:Layy;
        //  2135: astore          32
        //  2137: iconst_1       
        //  2138: iload_3        
        //  2139: if_icmpeq       2149
        //  2142: lload           23
        //  2144: lstore          9
        //  2146: goto            2153
        //  2149: lload           11
        //  2151: lstore          9
        //  2153: iconst_1       
        //  2154: istore          7
        //  2156: aload_0        
        //  2157: aload_1        
        //  2158: aload           30
        //  2160: aload           31
        //  2162: aload           32
        //  2164: lload           9
        //  2166: invokespecial   bfa.V:(Lazm;Layy;Lazm;Layy;J)V
        //  2169: iload           4
        //  2171: ifne            2187
        //  2174: lload           17
        //  2176: aload_0        
        //  2177: getfield        bfa.w:Lbfn;
        //  2180: getfield        bfn.b:J
        //  2183: lcmp           
        //  2184: ifeq            2297
        //  2187: aload_0        
        //  2188: getfield        bfa.w:Lbfn;
        //  2191: astore          32
        //  2193: aload           32
        //  2195: getfield        bfn.q:Layy;
        //  2198: getfield        ayy.a:Ljava/lang/Object;
        //  2201: astore          31
        //  2203: aload           32
        //  2205: getfield        bfn.a:Lazm;
        //  2208: astore          32
        //  2210: iload           4
        //  2212: ifeq            2250
        //  2215: iload_2        
        //  2216: ifeq            2250
        //  2219: aload           32
        //  2221: invokevirtual   azm.p:()Z
        //  2224: ifne            2250
        //  2227: aload           32
        //  2229: aload           31
        //  2231: aload_0        
        //  2232: getfield        bfa.m:Lazk;
        //  2235: invokevirtual   azm.n:(Ljava/lang/Object;Lazk;)Lazk;
        //  2238: getfield        azk.f:Z
        //  2241: ifne            2250
        //  2244: iload           7
        //  2246: istore_2       
        //  2247: goto            2252
        //  2250: iconst_0       
        //  2251: istore_2       
        //  2252: aload_0        
        //  2253: getfield        bfa.w:Lbfn;
        //  2256: getfield        bfn.c:J
        //  2259: lstore          9
        //  2261: aload_1        
        //  2262: aload           31
        //  2264: invokevirtual   azm.a:(Ljava/lang/Object;)I
        //  2267: iconst_m1      
        //  2268: if_icmpne       2277
        //  2271: iload           5
        //  2273: istore_3       
        //  2274: goto            2279
        //  2277: iconst_3       
        //  2278: istore_3       
        //  2279: aload_0        
        //  2280: aload_0        
        //  2281: aload           30
        //  2283: lload           11
        //  2285: lload           17
        //  2287: lload           9
        //  2289: iload_2        
        //  2290: iload_3        
        //  2291: invokespecial   bfa.U:(Layy;JJJZI)Lbfn;
        //  2294: putfield        bfa.w:Lbfn;
        //  2297: aload_0        
        //  2298: invokespecial   bfa.x:()V
        //  2301: aload_0        
        //  2302: aload_1        
        //  2303: aload_0        
        //  2304: getfield        bfa.w:Lbfn;
        //  2307: getfield        bfn.a:Lazm;
        //  2310: invokespecial   bfa.z:(Lazm;Lazm;)V
        //  2313: aload_0        
        //  2314: aload_0        
        //  2315: getfield        bfa.w:Lbfn;
        //  2318: aload_1        
        //  2319: invokevirtual   bfn.e:(Lazm;)Lbfn;
        //  2322: putfield        bfa.w:Lbfn;
        //  2325: aload_1        
        //  2326: invokevirtual   azm.p:()Z
        //  2329: ifne            2337
        //  2332: aload_0        
        //  2333: aconst_null    
        //  2334: putfield        bfa.G:Lbez;
        //  2337: aload_0        
        //  2338: iconst_0       
        //  2339: invokespecial   bfa.q:(Z)V
        //  2342: goto            2348
        //  2345: aload           29
        //  2347: athrow         
        //  2348: goto            2345
        //    Exceptions:
        //  Try           Handler
        //  Start  End    Start  End    Type
        //  -----  -----  -----  -----  ----
        //  954    965    992    998    Any
        //  969    974    992    998    Any
        //  981    989    992    998    Any
        //  1013   1019   992    998    Any
        //  1023   1029   992    998    Any
        //  1033   1040   992    998    Any
        //  1055   1062   992    998    Any
        //  1066   1074   992    998    Any
        //  1081   1087   992    998    Any
        //  1091   1099   992    998    Any
        //  1103   1114   992    998    Any
        //  1118   1141   992    998    Any
        //  1148   1162   992    998    Any
        //  1187   1196   1720   1729   Any
        //  1228   1235   1720   1729   Any
        //  1255   1262   1720   1729   Any
        //  1275   1285   1720   1729   Any
        //  1296   1308   1720   1729   Any
        //  1321   1331   1720   1729   Any
        //  1349   1356   1720   1729   Any
        //  1368   1379   2108   2117   Any
        //  1387   1403   2108   2117   Any
        //  1419   1434   2108   2117   Any
        //  1442   1449   2108   2117   Any
        //  1457   1464   2108   2117   Any
        //  1492   1497   2108   2117   Any
        //  1505   1512   2108   2117   Any
        //  1537   1546   2108   2117   Any
        //  1554   1564   2108   2117   Any
        //  1572   1582   2108   2117   Any
        //  1616   1626   2108   2117   Any
        //  1642   1649   2108   2117   Any
        //  1672   1682   2108   2117   Any
        //  1697   1702   2108   2117   Any
        //  1745   1752   2108   2117   Any
        //  1760   1769   2108   2117   Any
        //  1782   1798   2108   2117   Any
        //  1806   1824   2108   2117   Any
        //  1832   1837   2108   2117   Any
        //  1845   1852   2108   2117   Any
        //  1863   1875   1720   1729   Any
        // 
        // The error that occurred was:
        // 
        // java.lang.IllegalStateException: Expression is linked from several locations: Label_1407:
        //     at com.strobel.decompiler.ast.Error.expressionLinkedFromMultipleLocations(Error.java:27)
        //     at com.strobel.decompiler.ast.AstOptimizer.mergeDisparateObjectInitializations(AstOptimizer.java:2604)
        //     at com.strobel.decompiler.ast.AstOptimizer.optimize(AstOptimizer.java:235)
        //     at com.strobel.decompiler.ast.AstOptimizer.optimize(AstOptimizer.java:42)
        //     at com.strobel.decompiler.languages.java.ast.AstMethodBodyBuilder.createMethodBody(AstMethodBodyBuilder.java:206)
        //     at com.strobel.decompiler.languages.java.ast.AstMethodBodyBuilder.createMethodBody(AstMethodBodyBuilder.java:93)
        //     at com.strobel.decompiler.languages.java.ast.AstBuilder.createMethodBody(AstBuilder.java:868)
        //     at com.strobel.decompiler.languages.java.ast.AstBuilder.createMethod(AstBuilder.java:761)
        //     at com.strobel.decompiler.languages.java.ast.AstBuilder.addTypeMembers(AstBuilder.java:638)
        //     at com.strobel.decompiler.languages.java.ast.AstBuilder.createTypeCore(AstBuilder.java:605)
        //     at com.strobel.decompiler.languages.java.ast.AstBuilder.createTypeNoCache(AstBuilder.java:195)
        //     at com.strobel.decompiler.languages.java.ast.AstBuilder.createType(AstBuilder.java:162)
        //     at com.strobel.decompiler.languages.java.ast.AstBuilder.addType(AstBuilder.java:137)
        //     at com.strobel.decompiler.languages.java.JavaLanguage.buildAst(JavaLanguage.java:71)
        //     at com.strobel.decompiler.languages.java.JavaLanguage.decompileType(JavaLanguage.java:59)
        //     at com.strobel.decompiler.DecompilerDriver.decompileType(DecompilerDriver.java:333)
        //     at com.strobel.decompiler.DecompilerDriver.decompileJar(DecompilerDriver.java:254)
        //     at com.strobel.decompiler.DecompilerDriver.main(DecompilerDriver.java:129)
        // 
        throw new IllegalStateException("An error occurred while decompiling this method.");
    }
    
    private final void s(final azc azc, final boolean b) {
        this.t(azc, azc.b, true, b);
    }
    
    private final void t(final azc azc, final float n, final boolean b, final boolean b2) {
        if (b) {
            if (b2) {
                this.N.b(1);
            }
            this.w = this.w.c(azc);
        }
        final float b3 = azc.b;
        bfe bfe = this.s.d;
        int n2;
        while (true) {
            n2 = 0;
            int i = 0;
            if (bfe == null) {
                break;
            }
            for (bqw[] array = (bqw[])bfe.k.c; i < array.length; ++i) {
                final bqw bqw = array[i];
                if (bqw != null) {
                    bqw.n(b3);
                }
            }
            bfe = bfe.h;
        }
        final bfr[] e = this.e;
        for (int length = e.length, j = n2; j < length; ++j) {
            final bfr bfr = e[j];
            if (bfr != null) {
                bfr.H(n, azc.b);
            }
        }
    }
    
    private final void u() {
        final boolean l = this.L();
        boolean a = false;
        if (l) {
            final bfe f = this.s.f;
            final long i = this.i(f.b());
            long d;
            if (f == this.s.d) {
                d = f.d(this.H);
            }
            else {
                d = f.d(this.H) - f.f.a;
            }
            a = this.i.h(d, i, this.p.kI().b);
            if (!a && i < 500000L && (this.n > 0L || this.o)) {
                this.s.d.a.i(this.w.o, false);
                a = this.i.h(d, i, this.p.kI().b);
            }
        }
        if (this.A = a) {
            final bfe f2 = this.s.f;
            final long h = this.H;
            dk.h(f2.j());
            f2.a.n(f2.d(h));
        }
        this.I();
    }
    
    private final void v() {
        final mbe n = this.N;
        final bfn w = this.w;
        final boolean d = n.d | n.g != w;
        n.d = d;
        n.g = w;
        if (d) {
            this.P.aa(n);
            this.N = new mbe(this.w);
        }
    }
    
    private final void w(final boolean b, final boolean b2, final boolean b3, final boolean b4) {
        this.a.c();
        final bef bef = null;
        this.K = null;
        this.z = false;
        this.p.d();
        this.H = 1000000000000L;
        for (final bfr bfr : this.e) {
            Label_0091: {
                try {
                    this.l(bfr);
                    break Label_0091;
                }
                catch (final RuntimeException bfr) {}
                catch (final bef bef2) {}
                bap.b("ExoPlayerImplInternal", "Disable failed.", (Throwable)bfr);
            }
        }
        if (b) {
            for (final bfr bfr2 : this.e) {
                if (this.f.remove(bfr2)) {
                    try {
                        bfr2.E();
                    }
                    catch (final RuntimeException ex) {
                        bap.b("ExoPlayerImplInternal", "Reset failed.", (Throwable)ex);
                    }
                }
            }
        }
        this.F = 0;
        final bfn w = this.w;
        ayy q = w.q;
        long o = w.o;
        long n;
        if (!this.w.q.a() && !O(this.w, this.m)) {
            n = this.w.o;
        }
        else {
            n = this.w.b;
        }
        long longValue = 0L;
        boolean b5 = false;
        Label_0348: {
            if (b2) {
                this.G = null;
                final Pair k = this.j(this.w.a);
                final ayy ayy = (ayy)k.first;
                longValue = (long)k.second;
                final boolean equals = ayy.equals((Object)this.w.q);
                final long n2 = -9223372036854775807L;
                q = ayy;
                o = longValue;
                n = n2;
                if (!equals) {
                    b5 = true;
                    q = ayy;
                    n = n2;
                    break Label_0348;
                }
            }
            b5 = false;
            longValue = o;
        }
        this.s.d();
        this.A = false;
        final bfn w2 = this.w;
        final azm a = w2.a;
        final int d = w2.d;
        bef e3;
        if (b4) {
            e3 = bef;
        }
        else {
            e3 = w2.e;
        }
        bpe bpe;
        if (b5) {
            bpe = bpe.a;
        }
        else {
            bpe = w2.g;
        }
        aevd aevd;
        if (b5) {
            aevd = this.O;
        }
        else {
            aevd = this.w.s;
        }
        Object o2;
        if (b5) {
            o2 = afeq.q();
        }
        else {
            o2 = this.w.h;
        }
        final bfn w3 = this.w;
        this.w = new bfn(a, q, n, longValue, d, e3, false, bpe, aevd, (List)o2, q, w3.i, w3.j, w3.k, longValue, 0L, longValue, false, (byte[])null, (byte[])null, (byte[])null);
        if (b3) {
            final bfm t = this.t;
            for (final aln aln : t.f.values()) {
                try {
                    ((bny)aln.c).z((bnx)aln.b);
                }
                catch (final RuntimeException ex2) {
                    bap.b("MediaSourceList", "Failed to release child source.", (Throwable)ex2);
                }
                ((bny)aln.c).B((boa)aln.a);
                ((bny)aln.c).A((bkn)aln.a);
            }
            t.f.clear();
            t.g.clear();
            t.h = false;
        }
    }
    
    private final void x() {
        final bfe d = this.s.d;
        boolean y;
        final boolean b = y = false;
        if (d != null) {
            y = b;
            if (d.f.g) {
                y = b;
                if (this.x) {
                    y = true;
                }
            }
        }
        this.y = y;
    }
    
    private final void y(long e) {
        final bfe d = this.s.d;
        if (d == null) {
            e += 1000000000000L;
        }
        else {
            e = d.e(e);
        }
        this.H = e;
        this.p.a.d(e);
        for (final bfr bfr : this.e) {
            if (M(bfr)) {
                bfr.F(this.H);
            }
        }
        for (bfe bfe = this.s.d; bfe != null; bfe = bfe.h) {
            for (final bqw bqw : (bqw[])bfe.k.c) {}
        }
    }
    
    private final void z(final azm azm, final azm azm2) {
        if (azm.p() && azm2.p()) {
            return;
        }
        int size = this.q.size();
        while (true) {
            final int n = size - 1;
            if (n < 0) {
                break;
            }
            size = n;
            if (P((bey)this.q.get(n), azm, azm2, this.B, this.C, this.l, this.m)) {
                continue;
            }
            ((bey)this.q.get(n)).a.a(false);
            this.q.remove(n);
            size = n;
        }
        Collections.sort((List<Comparable>)this.q);
    }
    
    public final /* bridge */ void b(final boy boy) {
        this.a.f(9, (Object)boy).r();
    }
    
    public final void d(final bfq bfq) {
        synchronized (this) {
            if (!this.c && this.k.isAlive()) {
                this.a.f(14, (Object)bfq).r();
                return;
            }
            bap.c("ExoPlayerImplInternal", "Ignoring messages sent after release.");
            bfq.a(false);
        }
    }
    
    public final boolean e() {
        synchronized (this) {
            if (!this.c && this.k.isAlive()) {
                this.a.d(7);
                this.K((afaq)new beh(this, 15), this.u);
                return this.c;
            }
            return true;
        }
    }
    
    public final boolean handleMessage(final Message p0) {
        // 
        // This method could not be decompiled.
        // 
        // Original Bytecode:
        // 
        //     1: getfield        android/os/Message.what:I
        //     4: tableswitch {
        //                0: 2749
        //                1: 2718
        //                2: 2711
        //                3: 2115
        //                4: 2084
        //                5: 2070
        //                6: 2061
        //                7: 2011
        //                8: 1746
        //                9: 1709
        //               10: 1234
        //               11: 1183
        //               12: 1118
        //               13: 989
        //               14: 845
        //               15: 765
        //               16: 750
        //               17: 615
        //               18: 547
        //               19: 462
        //               20: 368
        //               21: 271
        //               22: 256
        //               23: 194
        //               24: 134
        //               25: 126
        //          default: 124
        //        }
        //   124: iconst_0       
        //   125: ireturn        
        //   126: aload_0        
        //   127: iconst_1       
        //   128: invokespecial   bfa.B:(Z)V
        //   131: goto            3089
        //   134: aload_1        
        //   135: getfield        android/os/Message.arg1:I
        //   138: iconst_1       
        //   139: if_icmpne       148
        //   142: iconst_1       
        //   143: istore          13
        //   145: goto            151
        //   148: iconst_0       
        //   149: istore          13
        //   151: iload           13
        //   153: aload_0        
        //   154: getfield        bfa.E:Z
        //   157: if_icmpeq       3089
        //   160: aload_0        
        //   161: iload           13
        //   163: putfield        bfa.E:Z
        //   166: iload           13
        //   168: ifne            3089
        //   171: aload_0        
        //   172: getfield        bfa.w:Lbfn;
        //   175: getfield        bfn.l:Z
        //   178: ifeq            3089
        //   181: aload_0        
        //   182: getfield        bfa.a:Lbak;
        //   185: iconst_2       
        //   186: invokeinterface bak.d:(I)V
        //   191: goto            3089
        //   194: aload_1        
        //   195: getfield        android/os/Message.arg1:I
        //   198: ifeq            207
        //   201: iconst_1       
        //   202: istore          13
        //   204: goto            210
        //   207: iconst_0       
        //   208: istore          13
        //   210: aload_0        
        //   211: iload           13
        //   213: putfield        bfa.x:Z
        //   216: aload_0        
        //   217: invokespecial   bfa.x:()V
        //   220: aload_0        
        //   221: getfield        bfa.y:Z
        //   224: ifeq            3089
        //   227: aload_0        
        //   228: getfield        bfa.s:Lbfg;
        //   231: astore_1       
        //   232: aload_1        
        //   233: getfield        bfg.e:Lbfe;
        //   236: aload_1        
        //   237: getfield        bfg.d:Lbfe;
        //   240: if_acmpeq       3089
        //   243: aload_0        
        //   244: iconst_1       
        //   245: invokespecial   bfa.B:(Z)V
        //   248: aload_0        
        //   249: iconst_0       
        //   250: invokespecial   bfa.q:(Z)V
        //   253: goto            3089
        //   256: aload_0        
        //   257: aload_0        
        //   258: getfield        bfa.t:Lbfm;
        //   261: invokevirtual   bfm.b:()Lazm;
        //   264: iconst_1       
        //   265: invokespecial   bfa.r:(Lazm;Z)V
        //   268: goto            3089
        //   271: aload_1        
        //   272: getfield        android/os/Message.obj:Ljava/lang/Object;
        //   275: checkcast       Leg;
        //   278: astore          15
        //   280: aload_0        
        //   281: getfield        bfa.N:Lmbe;
        //   284: iconst_1       
        //   285: invokevirtual   mbe.b:(I)V
        //   288: aload_0        
        //   289: getfield        bfa.t:Lbfm;
        //   292: astore          16
        //   294: aload           16
        //   296: invokevirtual   bfm.a:()I
        //   299: istore_3       
        //   300: aload           15
        //   302: astore_1       
        //   303: aload           15
        //   305: invokevirtual   eg.v:()I
        //   308: iload_3        
        //   309: if_icmpeq       349
        //   312: new             Leg;
        //   315: astore_1       
        //   316: new             Ljava/util/Random;
        //   319: astore          17
        //   321: aload           17
        //   323: aload           15
        //   325: getfield        eg.b:Ljava/lang/Object;
        //   328: checkcast       Ljava/util/Random;
        //   331: invokevirtual   java/util/Random.nextLong:()J
        //   334: invokespecial   java/util/Random.<init>:(J)V
        //   337: aload_1        
        //   338: aload           17
        //   340: invokespecial   eg.<init>:(Ljava/util/Random;)V
        //   343: aload_1        
        //   344: iload_3        
        //   345: invokevirtual   eg.w:(I)Leg;
        //   348: astore_1       
        //   349: aload           16
        //   351: aload_1        
        //   352: putfield        bfm.j:Leg;
        //   355: aload_0        
        //   356: aload           16
        //   358: invokevirtual   bfm.b:()Lazm;
        //   361: iconst_0       
        //   362: invokespecial   bfa.r:(Lazm;Z)V
        //   365: goto            3089
        //   368: aload_1        
        //   369: getfield        android/os/Message.arg1:I
        //   372: istore_3       
        //   373: aload_1        
        //   374: getfield        android/os/Message.arg2:I
        //   377: istore          4
        //   379: aload_1        
        //   380: getfield        android/os/Message.obj:Ljava/lang/Object;
        //   383: checkcast       Leg;
        //   386: astore_1       
        //   387: aload_0        
        //   388: getfield        bfa.N:Lmbe;
        //   391: iconst_1       
        //   392: invokevirtual   mbe.b:(I)V
        //   395: aload_0        
        //   396: getfield        bfa.t:Lbfm;
        //   399: astore          15
        //   401: iload_3        
        //   402: iflt            427
        //   405: iload_3        
        //   406: iload           4
        //   408: if_icmpgt       427
        //   411: iload           4
        //   413: aload           15
        //   415: invokevirtual   bfm.a:()I
        //   418: if_icmpgt       427
        //   421: iconst_1       
        //   422: istore          13
        //   424: goto            430
        //   427: iconst_0       
        //   428: istore          13
        //   430: iload           13
        //   432: invokestatic    dk.f:(Z)V
        //   435: aload           15
        //   437: aload_1        
        //   438: putfield        bfm.j:Leg;
        //   441: aload           15
        //   443: iload_3        
        //   444: iload           4
        //   446: invokevirtual   bfm.f:(II)V
        //   449: aload_0        
        //   450: aload           15
        //   452: invokevirtual   bfm.b:()Lazm;
        //   455: iconst_0       
        //   456: invokespecial   bfa.r:(Lazm;Z)V
        //   459: goto            3089
        //   462: aload_1        
        //   463: getfield        android/os/Message.obj:Ljava/lang/Object;
        //   466: checkcast       Laetk;
        //   469: astore          15
        //   471: aload_0        
        //   472: getfield        bfa.N:Lmbe;
        //   475: iconst_1       
        //   476: invokevirtual   mbe.b:(I)V
        //   479: aload_0        
        //   480: getfield        bfa.t:Lbfm;
        //   483: astore_1       
        //   484: aload           15
        //   486: getfield        aetk.b:I
        //   489: istore_3       
        //   490: aload           15
        //   492: getfield        aetk.a:I
        //   495: istore_3       
        //   496: aload           15
        //   498: getfield        aetk.c:I
        //   501: istore_3       
        //   502: aload           15
        //   504: getfield        aetk.d:Ljava/lang/Object;
        //   507: astore          15
        //   509: aload_1        
        //   510: invokevirtual   bfm.a:()I
        //   513: iflt            522
        //   516: iconst_1       
        //   517: istore          13
        //   519: goto            525
        //   522: iconst_0       
        //   523: istore          13
        //   525: iload           13
        //   527: invokestatic    dk.f:(Z)V
        //   530: aload_1        
        //   531: aconst_null    
        //   532: putfield        bfm.j:Leg;
        //   535: aload_0        
        //   536: aload_1        
        //   537: invokevirtual   bfm.b:()Lazm;
        //   540: iconst_0       
        //   541: invokespecial   bfa.r:(Lazm;Z)V
        //   544: goto            3089
        //   547: aload_1        
        //   548: getfield        android/os/Message.obj:Ljava/lang/Object;
        //   551: checkcast       Lbnz;
        //   554: astore          15
        //   556: aload_1        
        //   557: getfield        android/os/Message.arg1:I
        //   560: istore          4
        //   562: aload_0        
        //   563: getfield        bfa.N:Lmbe;
        //   566: iconst_1       
        //   567: invokevirtual   mbe.b:(I)V
        //   570: aload_0        
        //   571: getfield        bfa.t:Lbfm;
        //   574: astore_1       
        //   575: iload           4
        //   577: istore_3       
        //   578: iload           4
        //   580: iconst_m1      
        //   581: if_icmpne       589
        //   584: aload_1        
        //   585: invokevirtual   bfm.a:()I
        //   588: istore_3       
        //   589: aload_0        
        //   590: aload_1        
        //   591: iload_3        
        //   592: aload           15
        //   594: getfield        bnz.c:Ljava/util/List;
        //   597: aload           15
        //   599: getfield        bnz.d:Ljava/lang/Object;
        //   602: checkcast       Leg;
        //   605: invokevirtual   bfm.g:(ILjava/util/List;Leg;)Lazm;
        //   608: iconst_0       
        //   609: invokespecial   bfa.r:(Lazm;Z)V
        //   612: goto            3089
        //   615: aload_1        
        //   616: getfield        android/os/Message.obj:Ljava/lang/Object;
        //   619: checkcast       Lbnz;
        //   622: astore_1       
        //   623: aload_0        
        //   624: getfield        bfa.N:Lmbe;
        //   627: iconst_1       
        //   628: invokevirtual   mbe.b:(I)V
        //   631: aload_1        
        //   632: getfield        bnz.a:I
        //   635: iconst_m1      
        //   636: if_icmpeq       688
        //   639: new             Lbez;
        //   642: astore          16
        //   644: new             Lbds;
        //   647: astore          15
        //   649: aload           15
        //   651: aload_1        
        //   652: getfield        bnz.c:Ljava/util/List;
        //   655: aload_1        
        //   656: getfield        bnz.d:Ljava/lang/Object;
        //   659: checkcast       Leg;
        //   662: aconst_null    
        //   663: aconst_null    
        //   664: invokespecial   bds.<init>:(Ljava/util/Collection;Leg;[B[B)V
        //   667: aload           16
        //   669: aload           15
        //   671: aload_1        
        //   672: getfield        bnz.a:I
        //   675: aload_1        
        //   676: getfield        bnz.b:J
        //   679: invokespecial   bez.<init>:(Lazm;IJ)V
        //   682: aload_0        
        //   683: aload           16
        //   685: putfield        bfa.G:Lbez;
        //   688: aload_0        
        //   689: getfield        bfa.t:Lbfm;
        //   692: astore          16
        //   694: aload_1        
        //   695: getfield        bnz.c:Ljava/util/List;
        //   698: astore          15
        //   700: aload_1        
        //   701: getfield        bnz.d:Ljava/lang/Object;
        //   704: astore_1       
        //   705: aload           16
        //   707: iconst_0       
        //   708: aload           16
        //   710: getfield        bfm.a:Ljava/util/List;
        //   713: invokeinterface java/util/List.size:()I
        //   718: invokevirtual   bfm.f:(II)V
        //   721: aload_0        
        //   722: aload           16
        //   724: aload           16
        //   726: getfield        bfm.a:Ljava/util/List;
        //   729: invokeinterface java/util/List.size:()I
        //   734: aload           15
        //   736: aload_1        
        //   737: checkcast       Leg;
        //   740: invokevirtual   bfm.g:(ILjava/util/List;Leg;)Lazm;
        //   743: iconst_0       
        //   744: invokespecial   bfa.r:(Lazm;Z)V
        //   747: goto            3089
        //   750: aload_0        
        //   751: aload_1        
        //   752: getfield        android/os/Message.obj:Ljava/lang/Object;
        //   755: checkcast       Lazc;
        //   758: iconst_0       
        //   759: invokespecial   bfa.s:(Lazc;Z)V
        //   762: goto            3089
        //   765: aload_1        
        //   766: getfield        android/os/Message.obj:Ljava/lang/Object;
        //   769: checkcast       Lbfq;
        //   772: astore_1       
        //   773: aload_1        
        //   774: getfield        bfq.e:Landroid/os/Looper;
        //   777: astore          15
        //   779: aload           15
        //   781: invokevirtual   android/os/Looper.getThread:()Ljava/lang/Thread;
        //   784: invokevirtual   java/lang/Thread.isAlive:()Z
        //   787: ifne            807
        //   790: ldc_w           "TAG"
        //   793: ldc_w           "Trying to send message on a dead thread."
        //   796: invokestatic    bap.c:(Ljava/lang/String;Ljava/lang/String;)V
        //   799: aload_1        
        //   800: iconst_0       
        //   801: invokevirtual   bfq.a:(Z)V
        //   804: goto            3089
        //   807: aload_0        
        //   808: getfield        bfa.r:Lbad;
        //   811: aload           15
        //   813: aconst_null    
        //   814: invokeinterface bad.b:(Landroid/os/Looper;Landroid/os/Handler$Callback;)Lbak;
        //   819: astore          15
        //   821: new             Laus;
        //   824: astore          16
        //   826: aload           16
        //   828: aload_1        
        //   829: iconst_4       
        //   830: invokespecial   aus.<init>:(Lbfq;I)V
        //   833: aload           15
        //   835: aload           16
        //   837: invokeinterface bak.b:(Ljava/lang/Runnable;)V
        //   842: goto            3089
        //   845: aload_1        
        //   846: getfield        android/os/Message.obj:Ljava/lang/Object;
        //   849: checkcast       Lbfq;
        //   852: astore_1       
        //   853: aload_1        
        //   854: getfield        bfq.g:J
        //   857: ldc2_w          -9223372036854775807
        //   860: lcmp           
        //   861: ifne            872
        //   864: aload_0        
        //   865: aload_1        
        //   866: invokespecial   bfa.C:(Lbfq;)V
        //   869: goto            3089
        //   872: aload_0        
        //   873: getfield        bfa.w:Lbfn;
        //   876: getfield        bfn.a:Lazm;
        //   879: invokevirtual   azm.p:()Z
        //   882: ifeq            913
        //   885: aload_0        
        //   886: getfield        bfa.q:Ljava/util/ArrayList;
        //   889: astore          16
        //   891: new             Lbey;
        //   894: astore          15
        //   896: aload           15
        //   898: aload_1        
        //   899: invokespecial   bey.<init>:(Lbfq;)V
        //   902: aload           16
        //   904: aload           15
        //   906: invokevirtual   java/util/ArrayList.add:(Ljava/lang/Object;)Z
        //   909: pop            
        //   910: goto            3089
        //   913: new             Lbey;
        //   916: astore          16
        //   918: aload           16
        //   920: aload_1        
        //   921: invokespecial   bey.<init>:(Lbfq;)V
        //   924: aload_0        
        //   925: getfield        bfa.w:Lbfn;
        //   928: getfield        bfn.a:Lazm;
        //   931: astore          15
        //   933: aload           16
        //   935: aload           15
        //   937: aload           15
        //   939: aload_0        
        //   940: getfield        bfa.B:I
        //   943: aload_0        
        //   944: getfield        bfa.C:Z
        //   947: aload_0        
        //   948: getfield        bfa.l:Lazl;
        //   951: aload_0        
        //   952: getfield        bfa.m:Lazk;
        //   955: invokestatic    bfa.P:(Lbey;Lazm;Lazm;IZLazl;Lazk;)Z
        //   958: ifeq            981
        //   961: aload_0        
        //   962: getfield        bfa.q:Ljava/util/ArrayList;
        //   965: aload           16
        //   967: invokevirtual   java/util/ArrayList.add:(Ljava/lang/Object;)Z
        //   970: pop            
        //   971: aload_0        
        //   972: getfield        bfa.q:Ljava/util/ArrayList;
        //   975: invokestatic    java/util/Collections.sort:(Ljava/util/List;)V
        //   978: goto            3089
        //   981: aload_1        
        //   982: iconst_0       
        //   983: invokevirtual   bfq.a:(Z)V
        //   986: goto            3089
        //   989: aload_1        
        //   990: getfield        android/os/Message.arg1:I
        //   993: ifeq            1002
        //   996: iconst_1       
        //   997: istore          13
        //   999: goto            1005
        //  1002: iconst_0       
        //  1003: istore          13
        //  1005: aload_1        
        //  1006: getfield        android/os/Message.obj:Ljava/lang/Object;
        //  1009: checkcast       Ljava/util/concurrent/atomic/AtomicBoolean;
        //  1012: astore          16
        //  1014: aload_0        
        //  1015: getfield        bfa.D:Z
        //  1018: iload           13
        //  1020: if_icmpeq       1091
        //  1023: aload_0        
        //  1024: iload           13
        //  1026: putfield        bfa.D:Z
        //  1029: iload           13
        //  1031: ifne            1091
        //  1034: aload_0        
        //  1035: getfield        bfa.e:[Lbfr;
        //  1038: astore_1       
        //  1039: aload_1        
        //  1040: arraylength    
        //  1041: istore          4
        //  1043: iconst_0       
        //  1044: istore_3       
        //  1045: iload_3        
        //  1046: iload           4
        //  1048: if_icmpge       1091
        //  1051: aload_1        
        //  1052: iload_3        
        //  1053: aaload         
        //  1054: astore          15
        //  1056: aload           15
        //  1058: invokestatic    bfa.M:(Lbfr;)Z
        //  1061: ifne            1085
        //  1064: aload_0        
        //  1065: getfield        bfa.f:Ljava/util/Set;
        //  1068: aload           15
        //  1070: invokeinterface java/util/Set.remove:(Ljava/lang/Object;)Z
        //  1075: ifeq            1085
        //  1078: aload           15
        //  1080: invokeinterface bfr.E:()V
        //  1085: iinc            3, 1
        //  1088: goto            1045
        //  1091: aload           16
        //  1093: ifnull          3089
        //  1096: aload_0        
        //  1097: monitorenter   
        //  1098: aload           16
        //  1100: iconst_1       
        //  1101: invokevirtual   java/util/concurrent/atomic/AtomicBoolean.set:(Z)V
        //  1104: aload_0        
        //  1105: invokevirtual   java/lang/Object.notifyAll:()V
        //  1108: aload_0        
        //  1109: monitorexit    
        //  1110: goto            3089
        //  1113: astore_1       
        //  1114: aload_0        
        //  1115: monitorexit    
        //  1116: aload_1        
        //  1117: athrow         
        //  1118: aload_1        
        //  1119: getfield        android/os/Message.arg1:I
        //  1122: ifeq            1131
        //  1125: iconst_1       
        //  1126: istore          13
        //  1128: goto            1134
        //  1131: iconst_0       
        //  1132: istore          13
        //  1134: aload_0        
        //  1135: iload           13
        //  1137: putfield        bfa.C:Z
        //  1140: aload_0        
        //  1141: getfield        bfa.s:Lbfg;
        //  1144: astore          15
        //  1146: aload_0        
        //  1147: getfield        bfa.w:Lbfn;
        //  1150: getfield        bfn.a:Lazm;
        //  1153: astore_1       
        //  1154: aload           15
        //  1156: iload           13
        //  1158: putfield        bfg.c:Z
        //  1161: aload           15
        //  1163: aload_1        
        //  1164: invokevirtual   bfg.i:(Lazm;)Z
        //  1167: ifne            1175
        //  1170: aload_0        
        //  1171: iconst_1       
        //  1172: invokespecial   bfa.B:(Z)V
        //  1175: aload_0        
        //  1176: iconst_0       
        //  1177: invokespecial   bfa.q:(Z)V
        //  1180: goto            3089
        //  1183: aload_1        
        //  1184: getfield        android/os/Message.arg1:I
        //  1187: istore_3       
        //  1188: aload_0        
        //  1189: iload_3        
        //  1190: putfield        bfa.B:I
        //  1193: aload_0        
        //  1194: getfield        bfa.s:Lbfg;
        //  1197: astore_1       
        //  1198: aload_0        
        //  1199: getfield        bfa.w:Lbfn;
        //  1202: getfield        bfn.a:Lazm;
        //  1205: astore          15
        //  1207: aload_1        
        //  1208: iload_3        
        //  1209: putfield        bfg.b:I
        //  1212: aload_1        
        //  1213: aload           15
        //  1215: invokevirtual   bfg.i:(Lazm;)Z
        //  1218: ifne            1226
        //  1221: aload_0        
        //  1222: iconst_1       
        //  1223: invokespecial   bfa.B:(Z)V
        //  1226: aload_0        
        //  1227: iconst_0       
        //  1228: invokespecial   bfa.q:(Z)V
        //  1231: goto            3089
        //  1234: aload_0        
        //  1235: getfield        bfa.p:Lbed;
        //  1238: invokevirtual   bed.kI:()Lazc;
        //  1241: getfield        azc.b:F
        //  1244: fstore_2       
        //  1245: aload_0        
        //  1246: getfield        bfa.s:Lbfg;
        //  1249: astore          15
        //  1251: aload           15
        //  1253: getfield        bfg.d:Lbfe;
        //  1256: astore_1       
        //  1257: aload           15
        //  1259: getfield        bfg.e:Lbfe;
        //  1262: astore          15
        //  1264: iconst_1       
        //  1265: istore_3       
        //  1266: aload_1        
        //  1267: ifnull          3089
        //  1270: aload_1        
        //  1271: getfield        bfe.d:Z
        //  1274: ifeq            3089
        //  1277: aload_1        
        //  1278: fload_2        
        //  1279: aload_0        
        //  1280: getfield        bfa.w:Lbfn;
        //  1283: getfield        bfn.a:Lazm;
        //  1286: invokevirtual   bfe.l:(FLazm;)Laevd;
        //  1289: astore          16
        //  1291: aload_1        
        //  1292: getfield        bfe.k:Laevd;
        //  1295: astore          17
        //  1297: aload           17
        //  1299: ifnull          1389
        //  1302: aload           17
        //  1304: getfield        aevd.c:Ljava/lang/Object;
        //  1307: checkcast       [Lbqw;
        //  1310: arraylength    
        //  1311: aload           16
        //  1313: getfield        aevd.c:Ljava/lang/Object;
        //  1316: checkcast       [Lbqw;
        //  1319: arraylength    
        //  1320: if_icmpeq       1326
        //  1323: goto            1389
        //  1326: iconst_0       
        //  1327: istore          4
        //  1329: iload           4
        //  1331: aload           16
        //  1333: getfield        aevd.c:Ljava/lang/Object;
        //  1336: checkcast       [Lbqw;
        //  1339: arraylength    
        //  1340: if_icmpge       1361
        //  1343: aload           16
        //  1345: aload           17
        //  1347: iload           4
        //  1349: invokevirtual   aevd.j:(Laevd;I)Z
        //  1352: ifeq            1389
        //  1355: iinc            4, 1
        //  1358: goto            1329
        //  1361: aload_1        
        //  1362: aload           15
        //  1364: if_acmpne       1373
        //  1367: iconst_0       
        //  1368: istore          4
        //  1370: goto            1376
        //  1373: iconst_1       
        //  1374: istore          4
        //  1376: iload_3        
        //  1377: iload           4
        //  1379: iand           
        //  1380: istore_3       
        //  1381: aload_1        
        //  1382: getfield        bfe.h:Lbfe;
        //  1385: astore_1       
        //  1386: goto            1266
        //  1389: iload_3        
        //  1390: ifeq            1631
        //  1393: aload_0        
        //  1394: getfield        bfa.s:Lbfg;
        //  1397: astore          15
        //  1399: aload           15
        //  1401: getfield        bfg.d:Lbfe;
        //  1404: astore_1       
        //  1405: aload           15
        //  1407: aload_1        
        //  1408: invokevirtual   bfg.h:(Lbfe;)Z
        //  1411: istore          13
        //  1413: aload_0        
        //  1414: getfield        bfa.e:[Lbfr;
        //  1417: arraylength    
        //  1418: newarray        Z
        //  1420: astore          15
        //  1422: aload_1        
        //  1423: aload           16
        //  1425: aload_0        
        //  1426: getfield        bfa.w:Lbfn;
        //  1429: getfield        bfn.o:J
        //  1432: iload           13
        //  1434: aload           15
        //  1436: invokevirtual   bfe.k:(Laevd;JZ[Z)J
        //  1439: lstore          5
        //  1441: aload_0        
        //  1442: getfield        bfa.w:Lbfn;
        //  1445: astore          16
        //  1447: aload           16
        //  1449: getfield        bfn.d:I
        //  1452: iconst_4       
        //  1453: if_icmpeq       1473
        //  1456: lload           5
        //  1458: aload           16
        //  1460: getfield        bfn.o:J
        //  1463: lcmp           
        //  1464: ifeq            1473
        //  1467: iconst_1       
        //  1468: istore          13
        //  1470: goto            1476
        //  1473: iconst_0       
        //  1474: istore          13
        //  1476: aload_0        
        //  1477: getfield        bfa.w:Lbfn;
        //  1480: astore          16
        //  1482: aload_0        
        //  1483: aload_0        
        //  1484: aload           16
        //  1486: getfield        bfn.q:Layy;
        //  1489: lload           5
        //  1491: aload           16
        //  1493: getfield        bfn.b:J
        //  1496: aload           16
        //  1498: getfield        bfn.c:J
        //  1501: iload           13
        //  1503: iconst_5       
        //  1504: invokespecial   bfa.U:(Layy;JJJZI)Lbfn;
        //  1507: putfield        bfa.w:Lbfn;
        //  1510: iload           13
        //  1512: ifeq            1521
        //  1515: aload_0        
        //  1516: lload           5
        //  1518: invokespecial   bfa.y:(J)V
        //  1521: aload_0        
        //  1522: getfield        bfa.e:[Lbfr;
        //  1525: arraylength    
        //  1526: newarray        Z
        //  1528: astore          16
        //  1530: iconst_0       
        //  1531: istore_3       
        //  1532: aload_0        
        //  1533: getfield        bfa.e:[Lbfr;
        //  1536: astore          17
        //  1538: iload_3        
        //  1539: aload           17
        //  1541: arraylength    
        //  1542: if_icmpge       1622
        //  1545: aload           17
        //  1547: iload_3        
        //  1548: aaload         
        //  1549: astore          17
        //  1551: aload           17
        //  1553: invokestatic    bfa.M:(Lbfr;)Z
        //  1556: istore          13
        //  1558: aload           16
        //  1560: iload_3        
        //  1561: iload           13
        //  1563: bastore        
        //  1564: aload_1        
        //  1565: getfield        bfe.c:[Lbow;
        //  1568: iload_3        
        //  1569: aaload         
        //  1570: astore          18
        //  1572: iload           13
        //  1574: ifeq            1616
        //  1577: aload           18
        //  1579: aload           17
        //  1581: invokeinterface bfr.q:()Lbow;
        //  1586: if_acmpeq       1598
        //  1589: aload_0        
        //  1590: aload           17
        //  1592: invokespecial   bfa.l:(Lbfr;)V
        //  1595: goto            1616
        //  1598: aload           15
        //  1600: iload_3        
        //  1601: baload         
        //  1602: ifeq            1616
        //  1605: aload           17
        //  1607: aload_0        
        //  1608: getfield        bfa.H:J
        //  1611: invokeinterface bfr.F:(J)V
        //  1616: iinc            3, 1
        //  1619: goto            1532
        //  1622: aload_0        
        //  1623: aload           16
        //  1625: invokespecial   bfa.o:([Z)V
        //  1628: goto            1672
        //  1631: aload_0        
        //  1632: getfield        bfa.s:Lbfg;
        //  1635: aload_1        
        //  1636: invokevirtual   bfg.h:(Lbfe;)Z
        //  1639: pop            
        //  1640: aload_1        
        //  1641: getfield        bfe.d:Z
        //  1644: ifeq            1672
        //  1647: aload_1        
        //  1648: aload           16
        //  1650: aload_1        
        //  1651: getfield        bfe.f:Lbff;
        //  1654: getfield        bff.a:J
        //  1657: aload_1        
        //  1658: aload_0        
        //  1659: getfield        bfa.H:J
        //  1662: invokevirtual   bfe.d:(J)J
        //  1665: invokestatic    java/lang/Math.max:(JJ)J
        //  1668: invokevirtual   bfe.m:(Laevd;J)J
        //  1671: pop2           
        //  1672: aload_0        
        //  1673: iconst_1       
        //  1674: invokespecial   bfa.q:(Z)V
        //  1677: aload_0        
        //  1678: getfield        bfa.w:Lbfn;
        //  1681: getfield        bfn.d:I
        //  1684: iconst_4       
        //  1685: if_icmpeq       3089
        //  1688: aload_0        
        //  1689: invokespecial   bfa.u:()V
        //  1692: aload_0        
        //  1693: invokespecial   bfa.J:()V
        //  1696: aload_0        
        //  1697: getfield        bfa.a:Lbak;
        //  1700: iconst_2       
        //  1701: invokeinterface bak.d:(I)V
        //  1706: goto            3089
        //  1709: aload_1        
        //  1710: getfield        android/os/Message.obj:Ljava/lang/Object;
        //  1713: checkcast       Lbnv;
        //  1716: astore_1       
        //  1717: aload_0        
        //  1718: getfield        bfa.s:Lbfg;
        //  1721: aload_1        
        //  1722: invokevirtual   bfg.g:(Lbnv;)Z
        //  1725: ifeq            3089
        //  1728: aload_0        
        //  1729: getfield        bfa.s:Lbfg;
        //  1732: aload_0        
        //  1733: getfield        bfa.H:J
        //  1736: invokevirtual   bfg.f:(J)V
        //  1739: aload_0        
        //  1740: invokespecial   bfa.u:()V
        //  1743: goto            3089
        //  1746: aload_1        
        //  1747: getfield        android/os/Message.obj:Ljava/lang/Object;
        //  1750: checkcast       Lbnv;
        //  1753: astore_1       
        //  1754: aload_0        
        //  1755: getfield        bfa.s:Lbfg;
        //  1758: aload_1        
        //  1759: invokevirtual   bfg.g:(Lbnv;)Z
        //  1762: ifeq            3089
        //  1765: aload_0        
        //  1766: getfield        bfa.s:Lbfg;
        //  1769: getfield        bfg.f:Lbfe;
        //  1772: astore_1       
        //  1773: aload_0        
        //  1774: getfield        bfa.p:Lbed;
        //  1777: invokevirtual   bed.kI:()Lazc;
        //  1780: getfield        azc.b:F
        //  1783: fstore_2       
        //  1784: aload_0        
        //  1785: getfield        bfa.w:Lbfn;
        //  1788: getfield        bfn.a:Lazm;
        //  1791: astore          15
        //  1793: aload_1        
        //  1794: iconst_1       
        //  1795: putfield        bfe.d:Z
        //  1798: aload_1        
        //  1799: aload_1        
        //  1800: getfield        bfe.a:Lbnv;
        //  1803: invokeinterface bnv.h:()Lbpe;
        //  1808: putfield        bfe.i:Lbpe;
        //  1811: aload_1        
        //  1812: fload_2        
        //  1813: aload           15
        //  1815: invokevirtual   bfe.l:(FLazm;)Laevd;
        //  1818: astore          16
        //  1820: aload_1        
        //  1821: getfield        bfe.f:Lbff;
        //  1824: astore          15
        //  1826: aload           15
        //  1828: getfield        bff.a:J
        //  1831: lstore          7
        //  1833: aload           15
        //  1835: getfield        bff.d:J
        //  1838: lstore          9
        //  1840: lload           7
        //  1842: lstore          5
        //  1844: lload           9
        //  1846: ldc2_w          -9223372036854775807
        //  1849: lcmp           
        //  1850: ifeq            1875
        //  1853: lload           7
        //  1855: lstore          5
        //  1857: lload           7
        //  1859: lload           9
        //  1861: lcmp           
        //  1862: iflt            1875
        //  1865: lconst_0       
        //  1866: lload           9
        //  1868: lconst_1       
        //  1869: lsub           
        //  1870: invokestatic    java/lang/Math.max:(JJ)J
        //  1873: lstore          5
        //  1875: aload_1        
        //  1876: aload           16
        //  1878: lload           5
        //  1880: invokevirtual   bfe.m:(Laevd;J)J
        //  1883: lstore          7
        //  1885: aload_1        
        //  1886: getfield        bfe.j:J
        //  1889: lstore          5
        //  1891: aload_1        
        //  1892: getfield        bfe.f:Lbff;
        //  1895: astore          15
        //  1897: aload_1        
        //  1898: lload           5
        //  1900: aload           15
        //  1902: getfield        bff.a:J
        //  1905: lload           7
        //  1907: lsub           
        //  1908: ladd           
        //  1909: putfield        bfe.j:J
        //  1912: aload_1        
        //  1913: aload           15
        //  1915: lload           7
        //  1917: invokevirtual   bff.b:(J)Lbff;
        //  1920: putfield        bfe.f:Lbff;
        //  1923: aload_0        
        //  1924: aload_1        
        //  1925: getfield        bfe.i:Lbpe;
        //  1928: aload_1        
        //  1929: getfield        bfe.k:Laevd;
        //  1932: invokespecial   bfa.Z:(Lbpe;Laevd;)V
        //  1935: aload_1        
        //  1936: aload_0        
        //  1937: getfield        bfa.s:Lbfg;
        //  1940: getfield        bfg.d:Lbfe;
        //  1943: if_acmpne       2004
        //  1946: aload_0        
        //  1947: aload_1        
        //  1948: getfield        bfe.f:Lbff;
        //  1951: getfield        bff.a:J
        //  1954: invokespecial   bfa.y:(J)V
        //  1957: aload_0        
        //  1958: invokespecial   bfa.n:()V
        //  1961: aload_0        
        //  1962: getfield        bfa.w:Lbfn;
        //  1965: astore          16
        //  1967: aload           16
        //  1969: getfield        bfn.q:Layy;
        //  1972: astore          15
        //  1974: aload_1        
        //  1975: getfield        bfe.f:Lbff;
        //  1978: getfield        bff.a:J
        //  1981: lstore          5
        //  1983: aload_0        
        //  1984: aload_0        
        //  1985: aload           15
        //  1987: lload           5
        //  1989: aload           16
        //  1991: getfield        bfn.b:J
        //  1994: lload           5
        //  1996: iconst_0       
        //  1997: iconst_5       
        //  1998: invokespecial   bfa.U:(Layy;JJJZI)Lbfn;
        //  2001: putfield        bfa.w:Lbfn;
        //  2004: aload_0        
        //  2005: invokespecial   bfa.u:()V
        //  2008: goto            3089
        //  2011: aload_0        
        //  2012: iconst_1       
        //  2013: iconst_0       
        //  2014: iconst_1       
        //  2015: iconst_0       
        //  2016: invokespecial   bfa.w:(ZZZZ)V
        //  2019: aload_0        
        //  2020: getfield        bfa.i:Lbfc;
        //  2023: invokeinterface bfc.d:()V
        //  2028: aload_0        
        //  2029: iconst_1       
        //  2030: invokespecial   bfa.E:(I)V
        //  2033: aload_0        
        //  2034: getfield        bfa.k:Landroid/os/HandlerThread;
        //  2037: invokevirtual   android/os/HandlerThread.quit:()Z
        //  2040: pop            
        //  2041: aload_0        
        //  2042: monitorenter   
        //  2043: aload_0        
        //  2044: iconst_1       
        //  2045: putfield        bfa.c:Z
        //  2048: aload_0        
        //  2049: invokevirtual   java/lang/Object.notifyAll:()V
        //  2052: aload_0        
        //  2053: monitorexit    
        //  2054: iconst_1       
        //  2055: ireturn        
        //  2056: astore_1       
        //  2057: aload_0        
        //  2058: monitorexit    
        //  2059: aload_1        
        //  2060: athrow         
        //  2061: aload_0        
        //  2062: iconst_0       
        //  2063: iconst_1       
        //  2064: invokespecial   bfa.G:(ZZ)V
        //  2067: goto            3089
        //  2070: aload_0        
        //  2071: aload_1        
        //  2072: getfield        android/os/Message.obj:Ljava/lang/Object;
        //  2075: checkcast       Lbfv;
        //  2078: putfield        bfa.v:Lbfv;
        //  2081: goto            3089
        //  2084: aload_1        
        //  2085: getfield        android/os/Message.obj:Ljava/lang/Object;
        //  2088: checkcast       Lazc;
        //  2091: astore_1       
        //  2092: aload_0        
        //  2093: getfield        bfa.p:Lbed;
        //  2096: aload_1        
        //  2097: invokevirtual   bed.kJ:(Lazc;)V
        //  2100: aload_0        
        //  2101: aload_0        
        //  2102: getfield        bfa.p:Lbed;
        //  2105: invokevirtual   bed.kI:()Lazc;
        //  2108: iconst_1       
        //  2109: invokespecial   bfa.s:(Lazc;Z)V
        //  2112: goto            3089
        //  2115: aload_1        
        //  2116: getfield        android/os/Message.obj:Ljava/lang/Object;
        //  2119: checkcast       Lbez;
        //  2122: astore          15
        //  2124: aload_0        
        //  2125: getfield        bfa.N:Lmbe;
        //  2128: iconst_1       
        //  2129: invokevirtual   mbe.b:(I)V
        //  2132: aload_0        
        //  2133: getfield        bfa.w:Lbfn;
        //  2136: getfield        bfn.a:Lazm;
        //  2139: aload           15
        //  2141: iconst_1       
        //  2142: aload_0        
        //  2143: getfield        bfa.B:I
        //  2146: aload_0        
        //  2147: getfield        bfa.C:Z
        //  2150: aload_0        
        //  2151: getfield        bfa.l:Lazl;
        //  2154: aload_0        
        //  2155: getfield        bfa.m:Lazk;
        //  2158: invokestatic    bfa.k:(Lazm;Lbez;ZIZLazl;Lazk;)Landroid/util/Pair;
        //  2161: astore          16
        //  2163: aload           16
        //  2165: ifnonnull       2225
        //  2168: aload_0        
        //  2169: aload_0        
        //  2170: getfield        bfa.w:Lbfn;
        //  2173: getfield        bfn.a:Lazm;
        //  2176: invokespecial   bfa.j:(Lazm;)Landroid/util/Pair;
        //  2179: astore          17
        //  2181: aload           17
        //  2183: getfield        android/util/Pair.first:Ljava/lang/Object;
        //  2186: checkcast       Layy;
        //  2189: astore_1       
        //  2190: aload           17
        //  2192: getfield        android/util/Pair.second:Ljava/lang/Object;
        //  2195: checkcast       Ljava/lang/Long;
        //  2198: invokevirtual   java/lang/Long.longValue:()J
        //  2201: lstore          5
        //  2203: aload_0        
        //  2204: getfield        bfa.w:Lbfn;
        //  2207: getfield        bfn.a:Lazm;
        //  2210: invokevirtual   azm.p:()Z
        //  2213: iconst_1       
        //  2214: ixor           
        //  2215: istore          13
        //  2217: ldc2_w          -9223372036854775807
        //  2220: lstore          7
        //  2222: goto            2371
        //  2225: aload           16
        //  2227: getfield        android/util/Pair.first:Ljava/lang/Object;
        //  2230: astore_1       
        //  2231: aload           16
        //  2233: getfield        android/util/Pair.second:Ljava/lang/Object;
        //  2236: checkcast       Ljava/lang/Long;
        //  2239: invokevirtual   java/lang/Long.longValue:()J
        //  2242: lstore          5
        //  2244: aload           15
        //  2246: getfield        bez.c:J
        //  2249: ldc2_w          -9223372036854775807
        //  2252: lcmp           
        //  2253: ifne            2264
        //  2256: ldc2_w          -9223372036854775807
        //  2259: lstore          7
        //  2261: goto            2268
        //  2264: lload           5
        //  2266: lstore          7
        //  2268: aload_0        
        //  2269: getfield        bfa.s:Lbfg;
        //  2272: aload_0        
        //  2273: getfield        bfa.w:Lbfn;
        //  2276: getfield        bfn.a:Lazm;
        //  2279: aload_1        
        //  2280: lload           5
        //  2282: invokevirtual   bfg.k:(Lazm;Ljava/lang/Object;J)Layy;
        //  2285: astore_1       
        //  2286: aload_1        
        //  2287: invokevirtual   ayy.a:()Z
        //  2290: ifeq            2346
        //  2293: aload_0        
        //  2294: getfield        bfa.w:Lbfn;
        //  2297: getfield        bfn.a:Lazm;
        //  2300: aload_1        
        //  2301: getfield        ayy.a:Ljava/lang/Object;
        //  2304: aload_0        
        //  2305: getfield        bfa.m:Lazk;
        //  2308: invokevirtual   azm.n:(Ljava/lang/Object;Lazk;)Lazk;
        //  2311: pop            
        //  2312: aload_0        
        //  2313: getfield        bfa.m:Lazk;
        //  2316: aload_1        
        //  2317: getfield        ayy.b:I
        //  2320: invokevirtual   azk.d:(I)I
        //  2323: aload_1        
        //  2324: getfield        ayy.c:I
        //  2327: if_icmpne       2337
        //  2330: aload_0        
        //  2331: getfield        bfa.m:Lazk;
        //  2334: invokevirtual   azk.j:()V
        //  2337: lconst_0       
        //  2338: lstore          5
        //  2340: iconst_1       
        //  2341: istore          13
        //  2343: goto            2371
        //  2346: aload           15
        //  2348: getfield        bez.c:J
        //  2351: lstore          9
        //  2353: lload           9
        //  2355: ldc2_w          -9223372036854775807
        //  2358: lcmp           
        //  2359: ifne            2368
        //  2362: iconst_1       
        //  2363: istore          13
        //  2365: goto            2371
        //  2368: iconst_0       
        //  2369: istore          13
        //  2371: aload_0        
        //  2372: getfield        bfa.w:Lbfn;
        //  2375: getfield        bfn.a:Lazm;
        //  2378: invokevirtual   azm.p:()Z
        //  2381: ifeq            2393
        //  2384: aload_0        
        //  2385: aload           15
        //  2387: putfield        bfa.G:Lbez;
        //  2390: goto            2422
        //  2393: aload           16
        //  2395: ifnonnull       2429
        //  2398: aload_0        
        //  2399: getfield        bfa.w:Lbfn;
        //  2402: getfield        bfn.d:I
        //  2405: iconst_1       
        //  2406: if_icmpeq       2414
        //  2409: aload_0        
        //  2410: iconst_4       
        //  2411: invokespecial   bfa.E:(I)V
        //  2414: aload_0        
        //  2415: iconst_0       
        //  2416: iconst_1       
        //  2417: iconst_0       
        //  2418: iconst_1       
        //  2419: invokespecial   bfa.w:(ZZZZ)V
        //  2422: lload           5
        //  2424: lstore          9
        //  2426: goto            2661
        //  2429: aload_1        
        //  2430: aload_0        
        //  2431: getfield        bfa.w:Lbfn;
        //  2434: getfield        bfn.q:Layy;
        //  2437: invokevirtual   ayy.equals:(Ljava/lang/Object;)Z
        //  2440: ifeq            2576
        //  2443: aload_0        
        //  2444: getfield        bfa.s:Lbfg;
        //  2447: getfield        bfg.d:Lbfe;
        //  2450: astore          15
        //  2452: aload           15
        //  2454: ifnull          2493
        //  2457: aload           15
        //  2459: getfield        bfe.d:Z
        //  2462: ifeq            2493
        //  2465: lload           5
        //  2467: lconst_0       
        //  2468: lcmp           
        //  2469: ifeq            2493
        //  2472: aload           15
        //  2474: getfield        bfe.a:Lbnv;
        //  2477: lload           5
        //  2479: aload_0        
        //  2480: getfield        bfa.v:Lbfv;
        //  2483: invokeinterface bnv.a:(JLbfv;)J
        //  2488: lstore          9
        //  2490: goto            2497
        //  2493: lload           5
        //  2495: lstore          9
        //  2497: lload           9
        //  2499: lstore          11
        //  2501: lload           9
        //  2503: invokestatic    bax.A:(J)J
        //  2506: aload_0        
        //  2507: getfield        bfa.w:Lbfn;
        //  2510: getfield        bfn.o:J
        //  2513: invokestatic    bax.A:(J)J
        //  2516: lcmp           
        //  2517: ifne            2580
        //  2520: aload_0        
        //  2521: getfield        bfa.w:Lbfn;
        //  2524: astore          15
        //  2526: aload           15
        //  2528: getfield        bfn.d:I
        //  2531: istore_3       
        //  2532: iload_3        
        //  2533: iconst_2       
        //  2534: if_icmpeq       2546
        //  2537: lload           9
        //  2539: lstore          11
        //  2541: iload_3        
        //  2542: iconst_3       
        //  2543: if_icmpne       2580
        //  2546: aload           15
        //  2548: getfield        bfn.o:J
        //  2551: lstore          9
        //  2553: aload_0        
        //  2554: aload_1        
        //  2555: lload           9
        //  2557: lload           7
        //  2559: lload           9
        //  2561: iload           13
        //  2563: iconst_2       
        //  2564: invokespecial   bfa.U:(Layy;JJJZI)Lbfn;
        //  2567: astore_1       
        //  2568: aload_0        
        //  2569: aload_1        
        //  2570: putfield        bfa.w:Lbfn;
        //  2573: goto            3089
        //  2576: lload           5
        //  2578: lstore          11
        //  2580: aload_0        
        //  2581: getfield        bfa.w:Lbfn;
        //  2584: getfield        bfn.d:I
        //  2587: iconst_4       
        //  2588: if_icmpne       2597
        //  2591: iconst_1       
        //  2592: istore          14
        //  2594: goto            2600
        //  2597: iconst_0       
        //  2598: istore          14
        //  2600: aload_0        
        //  2601: aload_1        
        //  2602: lload           11
        //  2604: iload           14
        //  2606: invokespecial   bfa.S:(Layy;JZ)J
        //  2609: lstore          9
        //  2611: lload           5
        //  2613: lload           9
        //  2615: lcmp           
        //  2616: ifeq            2624
        //  2619: iconst_1       
        //  2620: istore_3       
        //  2621: goto            2626
        //  2624: iconst_0       
        //  2625: istore_3       
        //  2626: iload           13
        //  2628: iload_3        
        //  2629: ior            
        //  2630: istore          13
        //  2632: aload_0        
        //  2633: getfield        bfa.w:Lbfn;
        //  2636: astore          16
        //  2638: aload           16
        //  2640: getfield        bfn.a:Lazm;
        //  2643: astore          15
        //  2645: aload_0        
        //  2646: aload           15
        //  2648: aload_1        
        //  2649: aload           15
        //  2651: aload           16
        //  2653: getfield        bfn.q:Layy;
        //  2656: lload           7
        //  2658: invokespecial   bfa.V:(Lazm;Layy;Lazm;Layy;J)V
        //  2661: aload_0        
        //  2662: aload_1        
        //  2663: lload           9
        //  2665: lload           7
        //  2667: lload           9
        //  2669: iload           13
        //  2671: iconst_2       
        //  2672: invokespecial   bfa.U:(Layy;JJJZI)Lbfn;
        //  2675: astore_1       
        //  2676: goto            2568
        //  2679: astore          15
        //  2681: goto            2690
        //  2684: astore          15
        //  2686: lload           5
        //  2688: lstore          9
        //  2690: aload_0        
        //  2691: aload_0        
        //  2692: aload_1        
        //  2693: lload           9
        //  2695: lload           7
        //  2697: lload           9
        //  2699: iload           13
        //  2701: iconst_2       
        //  2702: invokespecial   bfa.U:(Layy;JJJZI)Lbfn;
        //  2705: putfield        bfa.w:Lbfn;
        //  2708: aload           15
        //  2710: athrow         
        //  2711: aload_0        
        //  2712: invokespecial   bfa.m:()V
        //  2715: goto            3089
        //  2718: aload_1        
        //  2719: getfield        android/os/Message.arg1:I
        //  2722: ifeq            2731
        //  2725: iconst_1       
        //  2726: istore          13
        //  2728: goto            2734
        //  2731: iconst_0       
        //  2732: istore          13
        //  2734: aload_0        
        //  2735: iload           13
        //  2737: aload_1        
        //  2738: getfield        android/os/Message.arg2:I
        //  2741: iconst_1       
        //  2742: iconst_1       
        //  2743: invokespecial   bfa.D:(ZIZI)V
        //  2746: goto            3089
        //  2749: aload_0        
        //  2750: getfield        bfa.N:Lmbe;
        //  2753: iconst_1       
        //  2754: invokevirtual   mbe.b:(I)V
        //  2757: aload_0        
        //  2758: iconst_0       
        //  2759: iconst_0       
        //  2760: iconst_0       
        //  2761: iconst_1       
        //  2762: invokespecial   bfa.w:(ZZZZ)V
        //  2765: aload_0        
        //  2766: getfield        bfa.i:Lbfc;
        //  2769: invokeinterface bfc.c:()V
        //  2774: iconst_1       
        //  2775: aload_0        
        //  2776: getfield        bfa.w:Lbfn;
        //  2779: getfield        bfn.a:Lazm;
        //  2782: invokevirtual   azm.p:()Z
        //  2785: if_icmpeq       2793
        //  2788: iconst_2       
        //  2789: istore_3       
        //  2790: goto            2795
        //  2793: iconst_4       
        //  2794: istore_3       
        //  2795: aload_0        
        //  2796: iload_3        
        //  2797: invokespecial   bfa.E:(I)V
        //  2800: aload_0        
        //  2801: getfield        bfa.t:Lbfm;
        //  2804: astore_1       
        //  2805: aload_0        
        //  2806: getfield        bfa.j:Lbre;
        //  2809: invokeinterface bre.f:()Lbco;
        //  2814: astore          15
        //  2816: aload_1        
        //  2817: getfield        bfm.h:Z
        //  2820: iconst_1       
        //  2821: ixor           
        //  2822: invokestatic    dk.h:(Z)V
        //  2825: aload_1        
        //  2826: aload           15
        //  2828: putfield        bfm.i:Lbco;
        //  2831: iconst_0       
        //  2832: istore_3       
        //  2833: iload_3        
        //  2834: aload_1        
        //  2835: getfield        bfm.a:Ljava/util/List;
        //  2838: invokeinterface java/util/List.size:()I
        //  2843: if_icmpge       2885
        //  2846: aload_1        
        //  2847: getfield        bfm.a:Ljava/util/List;
        //  2850: iload_3        
        //  2851: invokeinterface java/util/List.get:(I)Ljava/lang/Object;
        //  2856: checkcast       Lbfk;
        //  2859: astore          15
        //  2861: aload_1        
        //  2862: aload           15
        //  2864: invokevirtual   bfm.d:(Lbfk;)V
        //  2867: aload_1        
        //  2868: getfield        bfm.g:Ljava/util/Set;
        //  2871: aload           15
        //  2873: invokeinterface java/util/Set.add:(Ljava/lang/Object;)Z
        //  2878: pop            
        //  2879: iinc            3, 1
        //  2882: goto            2833
        //  2885: aload_1        
        //  2886: iconst_1       
        //  2887: putfield        bfm.h:Z
        //  2890: aload_0        
        //  2891: getfield        bfa.a:Lbak;
        //  2894: iconst_2       
        //  2895: invokeinterface bak.d:(I)V
        //  2900: goto            3089
        //  2903: astore_1       
        //  2904: aload_1        
        //  2905: instanceof      Ljava/lang/IllegalStateException;
        //  2908: ifne            2928
        //  2911: aload_1        
        //  2912: instanceof      Ljava/lang/IllegalArgumentException;
        //  2915: ifeq            2921
        //  2918: goto            2928
        //  2921: sipush          1000
        //  2924: istore_3       
        //  2925: goto            2932
        //  2928: sipush          1004
        //  2931: istore_3       
        //  2932: aload_1        
        //  2933: iload_3        
        //  2934: invokestatic    bef.b:(Ljava/lang/RuntimeException;I)Lbef;
        //  2937: astore_1       
        //  2938: ldc_w           "ExoPlayerImplInternal"
        //  2941: ldc_w           "Playback error"
        //  2944: aload_1        
        //  2945: invokestatic    bap.b:(Ljava/lang/String;Ljava/lang/String;Ljava/lang/Throwable;)V
        //  2948: aload_0        
        //  2949: iconst_1       
        //  2950: iconst_0       
        //  2951: invokespecial   bfa.G:(ZZ)V
        //  2954: aload_0        
        //  2955: aload_0        
        //  2956: getfield        bfa.w:Lbfn;
        //  2959: aload_1        
        //  2960: invokevirtual   bfn.b:(Lbef;)Lbfn;
        //  2963: putfield        bfa.w:Lbfn;
        //  2966: goto            3089
        //  2969: astore_1       
        //  2970: aload_0        
        //  2971: aload_1        
        //  2972: sipush          2000
        //  2975: invokespecial   bfa.p:(Ljava/io/IOException;I)V
        //  2978: goto            3089
        //  2981: astore_1       
        //  2982: aload_0        
        //  2983: aload_1        
        //  2984: sipush          1002
        //  2987: invokespecial   bfa.p:(Ljava/io/IOException;I)V
        //  2990: goto            3089
        //  2993: astore_1       
        //  2994: aload_0        
        //  2995: aload_1        
        //  2996: aload_1        
        //  2997: getfield        bbm.a:I
        //  3000: invokespecial   bfa.p:(Ljava/io/IOException;I)V
        //  3003: goto            3089
        //  3006: astore_1       
        //  3007: aload_1        
        //  3008: getfield        aza.b:I
        //  3011: istore_3       
        //  3012: iload_3        
        //  3013: iconst_1       
        //  3014: if_icmpne       3039
        //  3017: iconst_1       
        //  3018: aload_1        
        //  3019: getfield        aza.a:Z
        //  3022: if_icmpeq       3032
        //  3025: sipush          3003
        //  3028: istore_3       
        //  3029: goto            3070
        //  3032: sipush          3001
        //  3035: istore_3       
        //  3036: goto            3070
        //  3039: iload_3        
        //  3040: iconst_4       
        //  3041: if_icmpne       3066
        //  3044: iconst_1       
        //  3045: aload_1        
        //  3046: getfield        aza.a:Z
        //  3049: if_icmpeq       3059
        //  3052: sipush          3004
        //  3055: istore_3       
        //  3056: goto            3070
        //  3059: sipush          3002
        //  3062: istore_3       
        //  3063: goto            3070
        //  3066: sipush          1000
        //  3069: istore_3       
        //  3070: aload_0        
        //  3071: aload_1        
        //  3072: iload_3        
        //  3073: invokespecial   bfa.p:(Ljava/io/IOException;I)V
        //  3076: goto            3089
        //  3079: astore_1       
        //  3080: aload_0        
        //  3081: aload_1        
        //  3082: aload_1        
        //  3083: getfield        bkl.a:I
        //  3086: invokespecial   bfa.p:(Ljava/io/IOException;I)V
        //  3089: goto            3275
        //  3092: astore          15
        //  3094: aload           15
        //  3096: astore_1       
        //  3097: aload           15
        //  3099: getfield        bef.c:I
        //  3102: iconst_1       
        //  3103: if_icmpne       3137
        //  3106: aload_0        
        //  3107: getfield        bfa.s:Lbfg;
        //  3110: getfield        bfg.e:Lbfe;
        //  3113: astore          16
        //  3115: aload           15
        //  3117: astore_1       
        //  3118: aload           16
        //  3120: ifnull          3137
        //  3123: aload           15
        //  3125: aload           16
        //  3127: getfield        bfe.f:Lbff;
        //  3130: getfield        bff.i:Layy;
        //  3133: invokevirtual   bef.a:(Layy;)Lbef;
        //  3136: astore_1       
        //  3137: aload_1        
        //  3138: getfield        bef.i:Z
        //  3141: ifeq            3192
        //  3144: aload_0        
        //  3145: getfield        bfa.K:Lbef;
        //  3148: ifnonnull       3192
        //  3151: ldc_w           "ExoPlayerImplInternal"
        //  3154: ldc_w           "Recoverable renderer error"
        //  3157: aload_1        
        //  3158: invokestatic    bap.d:(Ljava/lang/String;Ljava/lang/String;Ljava/lang/Throwable;)V
        //  3161: aload_0        
        //  3162: aload_1        
        //  3163: putfield        bfa.K:Lbef;
        //  3166: aload_0        
        //  3167: getfield        bfa.a:Lbak;
        //  3170: astore          15
        //  3172: aload           15
        //  3174: aload           15
        //  3176: bipush          25
        //  3178: aload_1        
        //  3179: invokeinterface bak.f:(ILjava/lang/Object;)Lelx;
        //  3184: invokeinterface bak.h:(Lelx;)V
        //  3189: goto            3089
        //  3192: aload_0        
        //  3193: getfield        bfa.K:Lbef;
        //  3196: astore          16
        //  3198: aload_1        
        //  3199: astore          15
        //  3201: aload           16
        //  3203: ifnull          3245
        //  3206: ldc_w           Ljava/lang/Throwable;.class
        //  3209: ldc_w           "addSuppressed"
        //  3212: iconst_1       
        //  3213: anewarray       Ljava/lang/Class;
        //  3216: dup            
        //  3217: iconst_0       
        //  3218: ldc_w           Ljava/lang/Throwable;.class
        //  3221: aastore        
        //  3222: invokevirtual   java/lang/Class.getDeclaredMethod:(Ljava/lang/String;[Ljava/lang/Class;)Ljava/lang/reflect/Method;
        //  3225: aload           16
        //  3227: iconst_1       
        //  3228: anewarray       Ljava/lang/Object;
        //  3231: dup            
        //  3232: iconst_0       
        //  3233: aload_1        
        //  3234: aastore        
        //  3235: invokevirtual   java/lang/reflect/Method.invoke:(Ljava/lang/Object;[Ljava/lang/Object;)Ljava/lang/Object;
        //  3238: pop            
        //  3239: aload_0        
        //  3240: getfield        bfa.K:Lbef;
        //  3243: astore          15
        //  3245: ldc_w           "ExoPlayerImplInternal"
        //  3248: ldc_w           "Playback error"
        //  3251: aload           15
        //  3253: invokestatic    bap.b:(Ljava/lang/String;Ljava/lang/String;Ljava/lang/Throwable;)V
        //  3256: aload_0        
        //  3257: iconst_1       
        //  3258: iconst_0       
        //  3259: invokespecial   bfa.G:(ZZ)V
        //  3262: aload_0        
        //  3263: aload_0        
        //  3264: getfield        bfa.w:Lbfn;
        //  3267: aload           15
        //  3269: invokevirtual   bfn.b:(Lbef;)Lbfn;
        //  3272: putfield        bfa.w:Lbfn;
        //  3275: aload_0        
        //  3276: invokespecial   bfa.v:()V
        //  3279: iconst_1       
        //  3280: ireturn        
        //  3281: astore_1       
        //  3282: goto            3239
        //    Exceptions:
        //  Try           Handler
        //  Start  End    Start  End    Type                        
        //  -----  -----  -----  -----  ----------------------------
        //  0      124    3092   3275   Lbef;
        //  0      124    3079   3089   Lbkl;
        //  0      124    3006   3079   Laza;
        //  0      124    2993   3006   Lbbm;
        //  0      124    2981   2993   Lbmt;
        //  0      124    2969   2981   Ljava/io/IOException;
        //  0      124    2903   2969   Ljava/lang/RuntimeException;
        //  126    131    3092   3275   Lbef;
        //  126    131    3079   3089   Lbkl;
        //  126    131    3006   3079   Laza;
        //  126    131    2993   3006   Lbbm;
        //  126    131    2981   2993   Lbmt;
        //  126    131    2969   2981   Ljava/io/IOException;
        //  126    131    2903   2969   Ljava/lang/RuntimeException;
        //  134    142    3092   3275   Lbef;
        //  134    142    3079   3089   Lbkl;
        //  134    142    3006   3079   Laza;
        //  134    142    2993   3006   Lbbm;
        //  134    142    2981   2993   Lbmt;
        //  134    142    2969   2981   Ljava/io/IOException;
        //  134    142    2903   2969   Ljava/lang/RuntimeException;
        //  151    166    3092   3275   Lbef;
        //  151    166    3079   3089   Lbkl;
        //  151    166    3006   3079   Laza;
        //  151    166    2993   3006   Lbbm;
        //  151    166    2981   2993   Lbmt;
        //  151    166    2969   2981   Ljava/io/IOException;
        //  151    166    2903   2969   Ljava/lang/RuntimeException;
        //  171    191    3092   3275   Lbef;
        //  171    191    3079   3089   Lbkl;
        //  171    191    3006   3079   Laza;
        //  171    191    2993   3006   Lbbm;
        //  171    191    2981   2993   Lbmt;
        //  171    191    2969   2981   Ljava/io/IOException;
        //  171    191    2903   2969   Ljava/lang/RuntimeException;
        //  194    201    3092   3275   Lbef;
        //  194    201    3079   3089   Lbkl;
        //  194    201    3006   3079   Laza;
        //  194    201    2993   3006   Lbbm;
        //  194    201    2981   2993   Lbmt;
        //  194    201    2969   2981   Ljava/io/IOException;
        //  194    201    2903   2969   Ljava/lang/RuntimeException;
        //  210    253    3092   3275   Lbef;
        //  210    253    3079   3089   Lbkl;
        //  210    253    3006   3079   Laza;
        //  210    253    2993   3006   Lbbm;
        //  210    253    2981   2993   Lbmt;
        //  210    253    2969   2981   Ljava/io/IOException;
        //  210    253    2903   2969   Ljava/lang/RuntimeException;
        //  256    268    3092   3275   Lbef;
        //  256    268    3079   3089   Lbkl;
        //  256    268    3006   3079   Laza;
        //  256    268    2993   3006   Lbbm;
        //  256    268    2981   2993   Lbmt;
        //  256    268    2969   2981   Ljava/io/IOException;
        //  256    268    2903   2969   Ljava/lang/RuntimeException;
        //  271    300    3092   3275   Lbef;
        //  271    300    3079   3089   Lbkl;
        //  271    300    3006   3079   Laza;
        //  271    300    2993   3006   Lbbm;
        //  271    300    2981   2993   Lbmt;
        //  271    300    2969   2981   Ljava/io/IOException;
        //  271    300    2903   2969   Ljava/lang/RuntimeException;
        //  303    349    3092   3275   Lbef;
        //  303    349    3079   3089   Lbkl;
        //  303    349    3006   3079   Laza;
        //  303    349    2993   3006   Lbbm;
        //  303    349    2981   2993   Lbmt;
        //  303    349    2969   2981   Ljava/io/IOException;
        //  303    349    2903   2969   Ljava/lang/RuntimeException;
        //  349    365    3092   3275   Lbef;
        //  349    365    3079   3089   Lbkl;
        //  349    365    3006   3079   Laza;
        //  349    365    2993   3006   Lbbm;
        //  349    365    2981   2993   Lbmt;
        //  349    365    2969   2981   Ljava/io/IOException;
        //  349    365    2903   2969   Ljava/lang/RuntimeException;
        //  368    401    3092   3275   Lbef;
        //  368    401    3079   3089   Lbkl;
        //  368    401    3006   3079   Laza;
        //  368    401    2993   3006   Lbbm;
        //  368    401    2981   2993   Lbmt;
        //  368    401    2969   2981   Ljava/io/IOException;
        //  368    401    2903   2969   Ljava/lang/RuntimeException;
        //  411    421    3092   3275   Lbef;
        //  411    421    3079   3089   Lbkl;
        //  411    421    3006   3079   Laza;
        //  411    421    2993   3006   Lbbm;
        //  411    421    2981   2993   Lbmt;
        //  411    421    2969   2981   Ljava/io/IOException;
        //  411    421    2903   2969   Ljava/lang/RuntimeException;
        //  430    459    3092   3275   Lbef;
        //  430    459    3079   3089   Lbkl;
        //  430    459    3006   3079   Laza;
        //  430    459    2993   3006   Lbbm;
        //  430    459    2981   2993   Lbmt;
        //  430    459    2969   2981   Ljava/io/IOException;
        //  430    459    2903   2969   Ljava/lang/RuntimeException;
        //  462    516    3092   3275   Lbef;
        //  462    516    3079   3089   Lbkl;
        //  462    516    3006   3079   Laza;
        //  462    516    2993   3006   Lbbm;
        //  462    516    2981   2993   Lbmt;
        //  462    516    2969   2981   Ljava/io/IOException;
        //  462    516    2903   2969   Ljava/lang/RuntimeException;
        //  525    544    3092   3275   Lbef;
        //  525    544    3079   3089   Lbkl;
        //  525    544    3006   3079   Laza;
        //  525    544    2993   3006   Lbbm;
        //  525    544    2981   2993   Lbmt;
        //  525    544    2969   2981   Ljava/io/IOException;
        //  525    544    2903   2969   Ljava/lang/RuntimeException;
        //  547    575    3092   3275   Lbef;
        //  547    575    3079   3089   Lbkl;
        //  547    575    3006   3079   Laza;
        //  547    575    2993   3006   Lbbm;
        //  547    575    2981   2993   Lbmt;
        //  547    575    2969   2981   Ljava/io/IOException;
        //  547    575    2903   2969   Ljava/lang/RuntimeException;
        //  584    589    3092   3275   Lbef;
        //  584    589    3079   3089   Lbkl;
        //  584    589    3006   3079   Laza;
        //  584    589    2993   3006   Lbbm;
        //  584    589    2981   2993   Lbmt;
        //  584    589    2969   2981   Ljava/io/IOException;
        //  584    589    2903   2969   Ljava/lang/RuntimeException;
        //  589    612    3092   3275   Lbef;
        //  589    612    3079   3089   Lbkl;
        //  589    612    3006   3079   Laza;
        //  589    612    2993   3006   Lbbm;
        //  589    612    2981   2993   Lbmt;
        //  589    612    2969   2981   Ljava/io/IOException;
        //  589    612    2903   2969   Ljava/lang/RuntimeException;
        //  615    688    3092   3275   Lbef;
        //  615    688    3079   3089   Lbkl;
        //  615    688    3006   3079   Laza;
        //  615    688    2993   3006   Lbbm;
        //  615    688    2981   2993   Lbmt;
        //  615    688    2969   2981   Ljava/io/IOException;
        //  615    688    2903   2969   Ljava/lang/RuntimeException;
        //  688    747    3092   3275   Lbef;
        //  688    747    3079   3089   Lbkl;
        //  688    747    3006   3079   Laza;
        //  688    747    2993   3006   Lbbm;
        //  688    747    2981   2993   Lbmt;
        //  688    747    2969   2981   Ljava/io/IOException;
        //  688    747    2903   2969   Ljava/lang/RuntimeException;
        //  750    762    3092   3275   Lbef;
        //  750    762    3079   3089   Lbkl;
        //  750    762    3006   3079   Laza;
        //  750    762    2993   3006   Lbbm;
        //  750    762    2981   2993   Lbmt;
        //  750    762    2969   2981   Ljava/io/IOException;
        //  750    762    2903   2969   Ljava/lang/RuntimeException;
        //  765    804    3092   3275   Lbef;
        //  765    804    3079   3089   Lbkl;
        //  765    804    3006   3079   Laza;
        //  765    804    2993   3006   Lbbm;
        //  765    804    2981   2993   Lbmt;
        //  765    804    2969   2981   Ljava/io/IOException;
        //  765    804    2903   2969   Ljava/lang/RuntimeException;
        //  807    842    3092   3275   Lbef;
        //  807    842    3079   3089   Lbkl;
        //  807    842    3006   3079   Laza;
        //  807    842    2993   3006   Lbbm;
        //  807    842    2981   2993   Lbmt;
        //  807    842    2969   2981   Ljava/io/IOException;
        //  807    842    2903   2969   Ljava/lang/RuntimeException;
        //  845    869    3092   3275   Lbef;
        //  845    869    3079   3089   Lbkl;
        //  845    869    3006   3079   Laza;
        //  845    869    2993   3006   Lbbm;
        //  845    869    2981   2993   Lbmt;
        //  845    869    2969   2981   Ljava/io/IOException;
        //  845    869    2903   2969   Ljava/lang/RuntimeException;
        //  872    910    3092   3275   Lbef;
        //  872    910    3079   3089   Lbkl;
        //  872    910    3006   3079   Laza;
        //  872    910    2993   3006   Lbbm;
        //  872    910    2981   2993   Lbmt;
        //  872    910    2969   2981   Ljava/io/IOException;
        //  872    910    2903   2969   Ljava/lang/RuntimeException;
        //  913    978    3092   3275   Lbef;
        //  913    978    3079   3089   Lbkl;
        //  913    978    3006   3079   Laza;
        //  913    978    2993   3006   Lbbm;
        //  913    978    2981   2993   Lbmt;
        //  913    978    2969   2981   Ljava/io/IOException;
        //  913    978    2903   2969   Ljava/lang/RuntimeException;
        //  981    986    3092   3275   Lbef;
        //  981    986    3079   3089   Lbkl;
        //  981    986    3006   3079   Laza;
        //  981    986    2993   3006   Lbbm;
        //  981    986    2981   2993   Lbmt;
        //  981    986    2969   2981   Ljava/io/IOException;
        //  981    986    2903   2969   Ljava/lang/RuntimeException;
        //  989    996    3092   3275   Lbef;
        //  989    996    3079   3089   Lbkl;
        //  989    996    3006   3079   Laza;
        //  989    996    2993   3006   Lbbm;
        //  989    996    2981   2993   Lbmt;
        //  989    996    2969   2981   Ljava/io/IOException;
        //  989    996    2903   2969   Ljava/lang/RuntimeException;
        //  1005   1029   3092   3275   Lbef;
        //  1005   1029   3079   3089   Lbkl;
        //  1005   1029   3006   3079   Laza;
        //  1005   1029   2993   3006   Lbbm;
        //  1005   1029   2981   2993   Lbmt;
        //  1005   1029   2969   2981   Ljava/io/IOException;
        //  1005   1029   2903   2969   Ljava/lang/RuntimeException;
        //  1034   1043   3092   3275   Lbef;
        //  1034   1043   3079   3089   Lbkl;
        //  1034   1043   3006   3079   Laza;
        //  1034   1043   2993   3006   Lbbm;
        //  1034   1043   2981   2993   Lbmt;
        //  1034   1043   2969   2981   Ljava/io/IOException;
        //  1034   1043   2903   2969   Ljava/lang/RuntimeException;
        //  1056   1085   3092   3275   Lbef;
        //  1056   1085   3079   3089   Lbkl;
        //  1056   1085   3006   3079   Laza;
        //  1056   1085   2993   3006   Lbbm;
        //  1056   1085   2981   2993   Lbmt;
        //  1056   1085   2969   2981   Ljava/io/IOException;
        //  1056   1085   2903   2969   Ljava/lang/RuntimeException;
        //  1096   1098   3092   3275   Lbef;
        //  1096   1098   3079   3089   Lbkl;
        //  1096   1098   3006   3079   Laza;
        //  1096   1098   2993   3006   Lbbm;
        //  1096   1098   2981   2993   Lbmt;
        //  1096   1098   2969   2981   Ljava/io/IOException;
        //  1096   1098   2903   2969   Ljava/lang/RuntimeException;
        //  1098   1110   1113   1118   Any
        //  1114   1116   1113   1118   Any
        //  1116   1118   3092   3275   Lbef;
        //  1116   1118   3079   3089   Lbkl;
        //  1116   1118   3006   3079   Laza;
        //  1116   1118   2993   3006   Lbbm;
        //  1116   1118   2981   2993   Lbmt;
        //  1116   1118   2969   2981   Ljava/io/IOException;
        //  1116   1118   2903   2969   Ljava/lang/RuntimeException;
        //  1118   1125   3092   3275   Lbef;
        //  1118   1125   3079   3089   Lbkl;
        //  1118   1125   3006   3079   Laza;
        //  1118   1125   2993   3006   Lbbm;
        //  1118   1125   2981   2993   Lbmt;
        //  1118   1125   2969   2981   Ljava/io/IOException;
        //  1118   1125   2903   2969   Ljava/lang/RuntimeException;
        //  1134   1175   3092   3275   Lbef;
        //  1134   1175   3079   3089   Lbkl;
        //  1134   1175   3006   3079   Laza;
        //  1134   1175   2993   3006   Lbbm;
        //  1134   1175   2981   2993   Lbmt;
        //  1134   1175   2969   2981   Ljava/io/IOException;
        //  1134   1175   2903   2969   Ljava/lang/RuntimeException;
        //  1175   1180   3092   3275   Lbef;
        //  1175   1180   3079   3089   Lbkl;
        //  1175   1180   3006   3079   Laza;
        //  1175   1180   2993   3006   Lbbm;
        //  1175   1180   2981   2993   Lbmt;
        //  1175   1180   2969   2981   Ljava/io/IOException;
        //  1175   1180   2903   2969   Ljava/lang/RuntimeException;
        //  1183   1226   3092   3275   Lbef;
        //  1183   1226   3079   3089   Lbkl;
        //  1183   1226   3006   3079   Laza;
        //  1183   1226   2993   3006   Lbbm;
        //  1183   1226   2981   2993   Lbmt;
        //  1183   1226   2969   2981   Ljava/io/IOException;
        //  1183   1226   2903   2969   Ljava/lang/RuntimeException;
        //  1226   1231   3092   3275   Lbef;
        //  1226   1231   3079   3089   Lbkl;
        //  1226   1231   3006   3079   Laza;
        //  1226   1231   2993   3006   Lbbm;
        //  1226   1231   2981   2993   Lbmt;
        //  1226   1231   2969   2981   Ljava/io/IOException;
        //  1226   1231   2903   2969   Ljava/lang/RuntimeException;
        //  1234   1264   3092   3275   Lbef;
        //  1234   1264   3079   3089   Lbkl;
        //  1234   1264   3006   3079   Laza;
        //  1234   1264   2993   3006   Lbbm;
        //  1234   1264   2981   2993   Lbmt;
        //  1234   1264   2969   2981   Ljava/io/IOException;
        //  1234   1264   2903   2969   Ljava/lang/RuntimeException;
        //  1270   1297   3092   3275   Lbef;
        //  1270   1297   3079   3089   Lbkl;
        //  1270   1297   3006   3079   Laza;
        //  1270   1297   2993   3006   Lbbm;
        //  1270   1297   2981   2993   Lbmt;
        //  1270   1297   2969   2981   Ljava/io/IOException;
        //  1270   1297   2903   2969   Ljava/lang/RuntimeException;
        //  1302   1323   3092   3275   Lbef;
        //  1302   1323   3079   3089   Lbkl;
        //  1302   1323   3006   3079   Laza;
        //  1302   1323   2993   3006   Lbbm;
        //  1302   1323   2981   2993   Lbmt;
        //  1302   1323   2969   2981   Ljava/io/IOException;
        //  1302   1323   2903   2969   Ljava/lang/RuntimeException;
        //  1329   1355   3092   3275   Lbef;
        //  1329   1355   3079   3089   Lbkl;
        //  1329   1355   3006   3079   Laza;
        //  1329   1355   2993   3006   Lbbm;
        //  1329   1355   2981   2993   Lbmt;
        //  1329   1355   2969   2981   Ljava/io/IOException;
        //  1329   1355   2903   2969   Ljava/lang/RuntimeException;
        //  1381   1386   3092   3275   Lbef;
        //  1381   1386   3079   3089   Lbkl;
        //  1381   1386   3006   3079   Laza;
        //  1381   1386   2993   3006   Lbbm;
        //  1381   1386   2981   2993   Lbmt;
        //  1381   1386   2969   2981   Ljava/io/IOException;
        //  1381   1386   2903   2969   Ljava/lang/RuntimeException;
        //  1393   1467   3092   3275   Lbef;
        //  1393   1467   3079   3089   Lbkl;
        //  1393   1467   3006   3079   Laza;
        //  1393   1467   2993   3006   Lbbm;
        //  1393   1467   2981   2993   Lbmt;
        //  1393   1467   2969   2981   Ljava/io/IOException;
        //  1393   1467   2903   2969   Ljava/lang/RuntimeException;
        //  1476   1510   3092   3275   Lbef;
        //  1476   1510   3079   3089   Lbkl;
        //  1476   1510   3006   3079   Laza;
        //  1476   1510   2993   3006   Lbbm;
        //  1476   1510   2981   2993   Lbmt;
        //  1476   1510   2969   2981   Ljava/io/IOException;
        //  1476   1510   2903   2969   Ljava/lang/RuntimeException;
        //  1515   1521   3092   3275   Lbef;
        //  1515   1521   3079   3089   Lbkl;
        //  1515   1521   3006   3079   Laza;
        //  1515   1521   2993   3006   Lbbm;
        //  1515   1521   2981   2993   Lbmt;
        //  1515   1521   2969   2981   Ljava/io/IOException;
        //  1515   1521   2903   2969   Ljava/lang/RuntimeException;
        //  1521   1530   3092   3275   Lbef;
        //  1521   1530   3079   3089   Lbkl;
        //  1521   1530   3006   3079   Laza;
        //  1521   1530   2993   3006   Lbbm;
        //  1521   1530   2981   2993   Lbmt;
        //  1521   1530   2969   2981   Ljava/io/IOException;
        //  1521   1530   2903   2969   Ljava/lang/RuntimeException;
        //  1532   1545   3092   3275   Lbef;
        //  1532   1545   3079   3089   Lbkl;
        //  1532   1545   3006   3079   Laza;
        //  1532   1545   2993   3006   Lbbm;
        //  1532   1545   2981   2993   Lbmt;
        //  1532   1545   2969   2981   Ljava/io/IOException;
        //  1532   1545   2903   2969   Ljava/lang/RuntimeException;
        //  1551   1558   3092   3275   Lbef;
        //  1551   1558   3079   3089   Lbkl;
        //  1551   1558   3006   3079   Laza;
        //  1551   1558   2993   3006   Lbbm;
        //  1551   1558   2981   2993   Lbmt;
        //  1551   1558   2969   2981   Ljava/io/IOException;
        //  1551   1558   2903   2969   Ljava/lang/RuntimeException;
        //  1564   1572   3092   3275   Lbef;
        //  1564   1572   3079   3089   Lbkl;
        //  1564   1572   3006   3079   Laza;
        //  1564   1572   2993   3006   Lbbm;
        //  1564   1572   2981   2993   Lbmt;
        //  1564   1572   2969   2981   Ljava/io/IOException;
        //  1564   1572   2903   2969   Ljava/lang/RuntimeException;
        //  1577   1595   3092   3275   Lbef;
        //  1577   1595   3079   3089   Lbkl;
        //  1577   1595   3006   3079   Laza;
        //  1577   1595   2993   3006   Lbbm;
        //  1577   1595   2981   2993   Lbmt;
        //  1577   1595   2969   2981   Ljava/io/IOException;
        //  1577   1595   2903   2969   Ljava/lang/RuntimeException;
        //  1605   1616   3092   3275   Lbef;
        //  1605   1616   3079   3089   Lbkl;
        //  1605   1616   3006   3079   Laza;
        //  1605   1616   2993   3006   Lbbm;
        //  1605   1616   2981   2993   Lbmt;
        //  1605   1616   2969   2981   Ljava/io/IOException;
        //  1605   1616   2903   2969   Ljava/lang/RuntimeException;
        //  1622   1628   3092   3275   Lbef;
        //  1622   1628   3079   3089   Lbkl;
        //  1622   1628   3006   3079   Laza;
        //  1622   1628   2993   3006   Lbbm;
        //  1622   1628   2981   2993   Lbmt;
        //  1622   1628   2969   2981   Ljava/io/IOException;
        //  1622   1628   2903   2969   Ljava/lang/RuntimeException;
        //  1631   1672   3092   3275   Lbef;
        //  1631   1672   3079   3089   Lbkl;
        //  1631   1672   3006   3079   Laza;
        //  1631   1672   2993   3006   Lbbm;
        //  1631   1672   2981   2993   Lbmt;
        //  1631   1672   2969   2981   Ljava/io/IOException;
        //  1631   1672   2903   2969   Ljava/lang/RuntimeException;
        //  1672   1706   3092   3275   Lbef;
        //  1672   1706   3079   3089   Lbkl;
        //  1672   1706   3006   3079   Laza;
        //  1672   1706   2993   3006   Lbbm;
        //  1672   1706   2981   2993   Lbmt;
        //  1672   1706   2969   2981   Ljava/io/IOException;
        //  1672   1706   2903   2969   Ljava/lang/RuntimeException;
        //  1709   1743   3092   3275   Lbef;
        //  1709   1743   3079   3089   Lbkl;
        //  1709   1743   3006   3079   Laza;
        //  1709   1743   2993   3006   Lbbm;
        //  1709   1743   2981   2993   Lbmt;
        //  1709   1743   2969   2981   Ljava/io/IOException;
        //  1709   1743   2903   2969   Ljava/lang/RuntimeException;
        //  1746   1840   3092   3275   Lbef;
        //  1746   1840   3079   3089   Lbkl;
        //  1746   1840   3006   3079   Laza;
        //  1746   1840   2993   3006   Lbbm;
        //  1746   1840   2981   2993   Lbmt;
        //  1746   1840   2969   2981   Ljava/io/IOException;
        //  1746   1840   2903   2969   Ljava/lang/RuntimeException;
        //  1865   1875   3092   3275   Lbef;
        //  1865   1875   3079   3089   Lbkl;
        //  1865   1875   3006   3079   Laza;
        //  1865   1875   2993   3006   Lbbm;
        //  1865   1875   2981   2993   Lbmt;
        //  1865   1875   2969   2981   Ljava/io/IOException;
        //  1865   1875   2903   2969   Ljava/lang/RuntimeException;
        //  1875   2004   3092   3275   Lbef;
        //  1875   2004   3079   3089   Lbkl;
        //  1875   2004   3006   3079   Laza;
        //  1875   2004   2993   3006   Lbbm;
        //  1875   2004   2981   2993   Lbmt;
        //  1875   2004   2969   2981   Ljava/io/IOException;
        //  1875   2004   2903   2969   Ljava/lang/RuntimeException;
        //  2004   2008   3092   3275   Lbef;
        //  2004   2008   3079   3089   Lbkl;
        //  2004   2008   3006   3079   Laza;
        //  2004   2008   2993   3006   Lbbm;
        //  2004   2008   2981   2993   Lbmt;
        //  2004   2008   2969   2981   Ljava/io/IOException;
        //  2004   2008   2903   2969   Ljava/lang/RuntimeException;
        //  2011   2043   3092   3275   Lbef;
        //  2011   2043   3079   3089   Lbkl;
        //  2011   2043   3006   3079   Laza;
        //  2011   2043   2993   3006   Lbbm;
        //  2011   2043   2981   2993   Lbmt;
        //  2011   2043   2969   2981   Ljava/io/IOException;
        //  2011   2043   2903   2969   Ljava/lang/RuntimeException;
        //  2043   2054   2056   2061   Any
        //  2057   2059   2056   2061   Any
        //  2059   2061   3092   3275   Lbef;
        //  2059   2061   3079   3089   Lbkl;
        //  2059   2061   3006   3079   Laza;
        //  2059   2061   2993   3006   Lbbm;
        //  2059   2061   2981   2993   Lbmt;
        //  2059   2061   2969   2981   Ljava/io/IOException;
        //  2059   2061   2903   2969   Ljava/lang/RuntimeException;
        //  2061   2067   3092   3275   Lbef;
        //  2061   2067   3079   3089   Lbkl;
        //  2061   2067   3006   3079   Laza;
        //  2061   2067   2993   3006   Lbbm;
        //  2061   2067   2981   2993   Lbmt;
        //  2061   2067   2969   2981   Ljava/io/IOException;
        //  2061   2067   2903   2969   Ljava/lang/RuntimeException;
        //  2070   2081   3092   3275   Lbef;
        //  2070   2081   3079   3089   Lbkl;
        //  2070   2081   3006   3079   Laza;
        //  2070   2081   2993   3006   Lbbm;
        //  2070   2081   2981   2993   Lbmt;
        //  2070   2081   2969   2981   Ljava/io/IOException;
        //  2070   2081   2903   2969   Ljava/lang/RuntimeException;
        //  2084   2112   3092   3275   Lbef;
        //  2084   2112   3079   3089   Lbkl;
        //  2084   2112   3006   3079   Laza;
        //  2084   2112   2993   3006   Lbbm;
        //  2084   2112   2981   2993   Lbmt;
        //  2084   2112   2969   2981   Ljava/io/IOException;
        //  2084   2112   2903   2969   Ljava/lang/RuntimeException;
        //  2115   2163   3092   3275   Lbef;
        //  2115   2163   3079   3089   Lbkl;
        //  2115   2163   3006   3079   Laza;
        //  2115   2163   2993   3006   Lbbm;
        //  2115   2163   2981   2993   Lbmt;
        //  2115   2163   2969   2981   Ljava/io/IOException;
        //  2115   2163   2903   2969   Ljava/lang/RuntimeException;
        //  2168   2217   3092   3275   Lbef;
        //  2168   2217   3079   3089   Lbkl;
        //  2168   2217   3006   3079   Laza;
        //  2168   2217   2993   3006   Lbbm;
        //  2168   2217   2981   2993   Lbmt;
        //  2168   2217   2969   2981   Ljava/io/IOException;
        //  2168   2217   2903   2969   Ljava/lang/RuntimeException;
        //  2225   2256   3092   3275   Lbef;
        //  2225   2256   3079   3089   Lbkl;
        //  2225   2256   3006   3079   Laza;
        //  2225   2256   2993   3006   Lbbm;
        //  2225   2256   2981   2993   Lbmt;
        //  2225   2256   2969   2981   Ljava/io/IOException;
        //  2225   2256   2903   2969   Ljava/lang/RuntimeException;
        //  2268   2337   3092   3275   Lbef;
        //  2268   2337   3079   3089   Lbkl;
        //  2268   2337   3006   3079   Laza;
        //  2268   2337   2993   3006   Lbbm;
        //  2268   2337   2981   2993   Lbmt;
        //  2268   2337   2969   2981   Ljava/io/IOException;
        //  2268   2337   2903   2969   Ljava/lang/RuntimeException;
        //  2346   2353   3092   3275   Lbef;
        //  2346   2353   3079   3089   Lbkl;
        //  2346   2353   3006   3079   Laza;
        //  2346   2353   2993   3006   Lbbm;
        //  2346   2353   2981   2993   Lbmt;
        //  2346   2353   2969   2981   Ljava/io/IOException;
        //  2346   2353   2903   2969   Ljava/lang/RuntimeException;
        //  2371   2390   2684   2690   Any
        //  2398   2414   2684   2690   Any
        //  2414   2422   2684   2690   Any
        //  2429   2452   2684   2690   Any
        //  2457   2465   2684   2690   Any
        //  2472   2490   2684   2690   Any
        //  2501   2532   2684   2690   Any
        //  2546   2553   2684   2690   Any
        //  2553   2568   3092   3275   Lbef;
        //  2553   2568   3079   3089   Lbkl;
        //  2553   2568   3006   3079   Laza;
        //  2553   2568   2993   3006   Lbbm;
        //  2553   2568   2981   2993   Lbmt;
        //  2553   2568   2969   2981   Ljava/io/IOException;
        //  2553   2568   2903   2969   Ljava/lang/RuntimeException;
        //  2568   2573   3092   3275   Lbef;
        //  2568   2573   3079   3089   Lbkl;
        //  2568   2573   3006   3079   Laza;
        //  2568   2573   2993   3006   Lbbm;
        //  2568   2573   2981   2993   Lbmt;
        //  2568   2573   2969   2981   Ljava/io/IOException;
        //  2568   2573   2903   2969   Ljava/lang/RuntimeException;
        //  2580   2591   2684   2690   Any
        //  2600   2611   2684   2690   Any
        //  2632   2661   2679   2684   Any
        //  2661   2676   3092   3275   Lbef;
        //  2661   2676   3079   3089   Lbkl;
        //  2661   2676   3006   3079   Laza;
        //  2661   2676   2993   3006   Lbbm;
        //  2661   2676   2981   2993   Lbmt;
        //  2661   2676   2969   2981   Ljava/io/IOException;
        //  2661   2676   2903   2969   Ljava/lang/RuntimeException;
        //  2690   2711   3092   3275   Lbef;
        //  2690   2711   3079   3089   Lbkl;
        //  2690   2711   3006   3079   Laza;
        //  2690   2711   2993   3006   Lbbm;
        //  2690   2711   2981   2993   Lbmt;
        //  2690   2711   2969   2981   Ljava/io/IOException;
        //  2690   2711   2903   2969   Ljava/lang/RuntimeException;
        //  2711   2715   3092   3275   Lbef;
        //  2711   2715   3079   3089   Lbkl;
        //  2711   2715   3006   3079   Laza;
        //  2711   2715   2993   3006   Lbbm;
        //  2711   2715   2981   2993   Lbmt;
        //  2711   2715   2969   2981   Ljava/io/IOException;
        //  2711   2715   2903   2969   Ljava/lang/RuntimeException;
        //  2718   2725   3092   3275   Lbef;
        //  2718   2725   3079   3089   Lbkl;
        //  2718   2725   3006   3079   Laza;
        //  2718   2725   2993   3006   Lbbm;
        //  2718   2725   2981   2993   Lbmt;
        //  2718   2725   2969   2981   Ljava/io/IOException;
        //  2718   2725   2903   2969   Ljava/lang/RuntimeException;
        //  2734   2746   3092   3275   Lbef;
        //  2734   2746   3079   3089   Lbkl;
        //  2734   2746   3006   3079   Laza;
        //  2734   2746   2993   3006   Lbbm;
        //  2734   2746   2981   2993   Lbmt;
        //  2734   2746   2969   2981   Ljava/io/IOException;
        //  2734   2746   2903   2969   Ljava/lang/RuntimeException;
        //  2749   2788   3092   3275   Lbef;
        //  2749   2788   3079   3089   Lbkl;
        //  2749   2788   3006   3079   Laza;
        //  2749   2788   2993   3006   Lbbm;
        //  2749   2788   2981   2993   Lbmt;
        //  2749   2788   2969   2981   Ljava/io/IOException;
        //  2749   2788   2903   2969   Ljava/lang/RuntimeException;
        //  2795   2831   3092   3275   Lbef;
        //  2795   2831   3079   3089   Lbkl;
        //  2795   2831   3006   3079   Laza;
        //  2795   2831   2993   3006   Lbbm;
        //  2795   2831   2981   2993   Lbmt;
        //  2795   2831   2969   2981   Ljava/io/IOException;
        //  2795   2831   2903   2969   Ljava/lang/RuntimeException;
        //  2833   2879   3092   3275   Lbef;
        //  2833   2879   3079   3089   Lbkl;
        //  2833   2879   3006   3079   Laza;
        //  2833   2879   2993   3006   Lbbm;
        //  2833   2879   2981   2993   Lbmt;
        //  2833   2879   2969   2981   Ljava/io/IOException;
        //  2833   2879   2903   2969   Ljava/lang/RuntimeException;
        //  2885   2900   3092   3275   Lbef;
        //  2885   2900   3079   3089   Lbkl;
        //  2885   2900   3006   3079   Laza;
        //  2885   2900   2993   3006   Lbbm;
        //  2885   2900   2981   2993   Lbmt;
        //  2885   2900   2969   2981   Ljava/io/IOException;
        //  2885   2900   2903   2969   Ljava/lang/RuntimeException;
        //  3206   3239   3281   3285   Ljava/lang/Exception;
        // 
        // The error that occurred was:
        // 
        // java.lang.IllegalStateException: Expression is linked from several locations: Label_3239:
        //     at com.strobel.decompiler.ast.Error.expressionLinkedFromMultipleLocations(Error.java:27)
        //     at com.strobel.decompiler.ast.AstOptimizer.mergeDisparateObjectInitializations(AstOptimizer.java:2604)
        //     at com.strobel.decompiler.ast.AstOptimizer.optimize(AstOptimizer.java:235)
        //     at com.strobel.decompiler.ast.AstOptimizer.optimize(AstOptimizer.java:42)
        //     at com.strobel.decompiler.languages.java.ast.AstMethodBodyBuilder.createMethodBody(AstMethodBodyBuilder.java:206)
        //     at com.strobel.decompiler.languages.java.ast.AstMethodBodyBuilder.createMethodBody(AstMethodBodyBuilder.java:93)
        //     at com.strobel.decompiler.languages.java.ast.AstBuilder.createMethodBody(AstBuilder.java:868)
        //     at com.strobel.decompiler.languages.java.ast.AstBuilder.createMethod(AstBuilder.java:761)
        //     at com.strobel.decompiler.languages.java.ast.AstBuilder.addTypeMembers(AstBuilder.java:638)
        //     at com.strobel.decompiler.languages.java.ast.AstBuilder.createTypeCore(AstBuilder.java:605)
        //     at com.strobel.decompiler.languages.java.ast.AstBuilder.createTypeNoCache(AstBuilder.java:195)
        //     at com.strobel.decompiler.languages.java.ast.AstBuilder.createType(AstBuilder.java:162)
        //     at com.strobel.decompiler.languages.java.ast.AstBuilder.addType(AstBuilder.java:137)
        //     at com.strobel.decompiler.languages.java.JavaLanguage.buildAst(JavaLanguage.java:71)
        //     at com.strobel.decompiler.languages.java.JavaLanguage.decompileType(JavaLanguage.java:59)
        //     at com.strobel.decompiler.DecompilerDriver.decompileType(DecompilerDriver.java:333)
        //     at com.strobel.decompiler.DecompilerDriver.decompileJar(DecompilerDriver.java:254)
        //     at com.strobel.decompiler.DecompilerDriver.main(DecompilerDriver.java:129)
        // 
        throw new IllegalStateException("An error occurred while decompiling this method.");
    }
    
    public final void kX(final bnv bnv) {
        this.a.f(8, (Object)bnv).r();
    }
}
