import android.view.View$MeasureSpec;
import java.util.concurrent.atomic.AtomicBoolean;
import com.facebook.litho.ComponentTree;
import android.content.Context;
import java.util.List;
import android.os.Build;

// 
// Decompiled by Procyon v0.6.0
// 

public final class dvc
{
    static final boolean a;
    
    static {
        a = "robolectric".equals(Build.FINGERPRINT);
    }
    
    public static dva a(final dsx dsx, final dst dst) {
        return c(dsx, dst, false, false, null);
    }
    
    static dva b(final dsx dsx, final dst dst, final boolean b) {
        return c(dsx, dst, b, false, null);
    }
    
    static dva c(final dsx p0, final dst p1, final boolean p2, final boolean p3, final String p4) {
        // 
        // This method could not be decompiled.
        // 
        // Original Bytecode:
        // 
        //     1: astore          8
        //     3: aconst_null    
        //     4: astore          10
        //     6: aload_1        
        //     7: astore          4
        //     9: aload_0        
        //    10: aload_1        
        //    11: iload_3        
        //    12: invokestatic    dvc.g:(Ldsx;Ldst;Z)Ldsx;
        //    15: astore          11
        //    17: aload_1        
        //    18: astore          4
        //    20: aload           11
        //    22: invokevirtual   dsx.h:()Ljava/lang/String;
        //    25: pop            
        //    26: aload_1        
        //    27: astore          4
        //    29: aload           11
        //    31: getfield        dsx.e:Ldst;
        //    34: astore          9
        //    36: aload           9
        //    38: astore          4
        //    40: aload           11
        //    42: aload           9
        //    44: invokestatic    dst.A:(Ldsx;Ldst;)Z
        //    47: ifeq            112
        //    50: iload_2        
        //    51: ifne            112
        //    54: aload           9
        //    56: astore          4
        //    58: aload           11
        //    60: invokestatic    bkv.d:(Ldsx;)Ldva;
        //    63: astore_1       
        //    64: aload           9
        //    66: astore          4
        //    68: aload           11
        //    70: getfield        dsx.k:Lcya;
        //    73: astore          7
        //    75: aload           9
        //    77: astore          4
        //    79: aload_1        
        //    80: checkcast       Ldty;
        //    83: invokevirtual   dty.ca:()Lpsb;
        //    86: iconst_1       
        //    87: putfield        psb.a:Z
        //    90: aload           9
        //    92: astore          4
        //    94: aload_1        
        //    95: checkcast       Ldty;
        //    98: invokevirtual   dty.ca:()Lpsb;
        //   101: aload           7
        //   103: invokestatic    cya.x:(Lcya;)Lcya;
        //   106: putfield        psb.c:Ljava/lang/Object;
        //   109: goto            302
        //   112: aload           9
        //   114: astore          4
        //   116: aload           9
        //   118: invokevirtual   dst.e:()Z
        //   121: ifeq            139
        //   124: aload           9
        //   126: astore          4
        //   128: aload           9
        //   130: aload           11
        //   132: invokevirtual   dtd.d:(Ldsx;)Ldva;
        //   135: astore_1       
        //   136: goto            302
        //   139: aload           9
        //   141: astore          4
        //   143: aload           9
        //   145: invokestatic    dst.y:(Ldst;)Z
        //   148: ifeq            175
        //   151: aload           9
        //   153: astore          4
        //   155: aload           11
        //   157: invokestatic    bkv.d:(Ldsx;)Ldva;
        //   160: astore_1       
        //   161: aload           9
        //   163: astore          4
        //   165: aload_1        
        //   166: iconst_1       
        //   167: invokeinterface dva.bO:(I)V
        //   172: goto            302
        //   175: aload           9
        //   177: astore          4
        //   179: aload           9
        //   181: invokestatic    dst.w:(Ldst;)Z
        //   184: ifeq            1951
        //   187: aload           9
        //   189: astore          4
        //   191: aload           9
        //   193: invokestatic    dst.x:(Ldst;)Z
        //   196: ifeq            224
        //   199: aload           9
        //   201: astore          4
        //   203: aload           9
        //   205: aload           11
        //   207: aload           11
        //   209: getfield        dsx.f:I
        //   212: aload           11
        //   214: getfield        dsx.g:I
        //   217: invokevirtual   dtd.L:(Ldsx;II)Ldst;
        //   220: astore_1       
        //   221: goto            236
        //   224: aload           9
        //   226: astore          4
        //   228: aload           9
        //   230: aload           11
        //   232: invokevirtual   dtd.c:(Ldsx;)Ldst;
        //   235: astore_1       
        //   236: aload_1        
        //   237: ifnull          254
        //   240: aload_1        
        //   241: astore          7
        //   243: aload           9
        //   245: astore          4
        //   247: aload_1        
        //   248: getfield        dst.j:I
        //   251: ifgt            257
        //   254: aconst_null    
        //   255: astore          7
        //   257: aload           7
        //   259: aload           9
        //   261: if_acmpne       279
        //   264: aload           9
        //   266: astore          4
        //   268: aload           7
        //   270: aload           11
        //   272: invokevirtual   dtd.d:(Ldsx;)Ldva;
        //   275: astore_1       
        //   276: goto            302
        //   279: aload           7
        //   281: ifnull          300
        //   284: aload           9
        //   286: astore          4
        //   288: aload           11
        //   290: aload           7
        //   292: iconst_0       
        //   293: invokestatic    dvc.b:(Ldsx;Ldst;Z)Ldva;
        //   296: astore_1       
        //   297: goto            302
        //   300: aconst_null    
        //   301: astore_1       
        //   302: aload_1        
        //   303: ifnull          1943
        //   306: aload           9
        //   308: astore          4
        //   310: getstatic       dsx.a:Ldva;
        //   313: astore          7
        //   315: aload_1        
        //   316: aload           7
        //   318: if_acmpne       324
        //   321: goto            1943
        //   324: aload_1        
        //   325: invokeinterface dva.ab:()Ldst;
        //   330: ifnonnull       375
        //   333: aload           9
        //   335: invokevirtual   dtd.af:()Z
        //   338: ifeq            352
        //   341: aload           9
        //   343: invokestatic    dst.y:(Ldst;)Z
        //   346: ifeq            352
        //   349: goto            366
        //   352: aload           11
        //   354: aload           9
        //   356: invokestatic    dst.A:(Ldsx;Ldst;)Z
        //   359: ifeq            375
        //   362: iload_2        
        //   363: ifne            375
        //   366: aload_1        
        //   367: invokestatic    dtd.aA:()Lbkv;
        //   370: invokeinterface dva.cc:(Lbkv;)V
        //   375: aload           9
        //   377: getfield        dst.u:Ldsq;
        //   380: astore_0       
        //   381: aload_0        
        //   382: ifnull          1901
        //   385: aload           9
        //   387: invokestatic    dst.x:(Ldst;)Z
        //   390: ifeq            397
        //   393: iload_2        
        //   394: ifne            1901
        //   397: aload_1        
        //   398: getstatic       dsx.a:Ldva;
        //   401: if_acmpne       407
        //   404: goto            1901
        //   407: aload_0        
        //   408: getfield        dsq.g:Ldtz;
        //   411: astore          4
        //   413: aload           4
        //   415: ifnull          429
        //   418: aload           4
        //   420: aload_1        
        //   421: invokeinterface dva.bi:()Ldtz;
        //   426: invokevirtual   dtz.D:(Ldtz;)V
        //   429: aload_0        
        //   430: getfield        dsq.a:B
        //   433: iconst_1       
        //   434: iand           
        //   435: i2l            
        //   436: lconst_0       
        //   437: lcmp           
        //   438: ifeq            451
        //   441: aload_1        
        //   442: aload_0        
        //   443: getfield        dsq.c:Landroid/graphics/drawable/Drawable;
        //   446: invokeinterface dva.bn:(Landroid/graphics/drawable/Drawable;)V
        //   451: aload_0        
        //   452: getfield        dsq.a:B
        //   455: iconst_2       
        //   456: iand           
        //   457: i2l            
        //   458: lconst_0       
        //   459: lcmp           
        //   460: ifeq            473
        //   463: aload_1        
        //   464: aload_0        
        //   465: getfield        dsq.d:Ljava/lang/String;
        //   468: invokeinterface dva.bF:(Ljava/lang/String;)V
        //   473: aload_0        
        //   474: getfield        dsq.f:Z
        //   477: ifne            493
        //   480: aload_0        
        //   481: getfield        dsq.a:B
        //   484: bipush          28
        //   486: iand           
        //   487: i2l            
        //   488: lconst_0       
        //   489: lcmp           
        //   490: ifeq            499
        //   493: aload_1        
        //   494: invokeinterface dva.bM:()V
        //   499: aload_0        
        //   500: getfield        dsq.h:Ldso;
        //   503: astore          4
        //   505: aload           4
        //   507: ifnull          1434
        //   510: aload           4
        //   512: getfield        dso.a:I
        //   515: iconst_1       
        //   516: iand           
        //   517: i2l            
        //   518: lconst_0       
        //   519: lcmp           
        //   520: ifeq            534
        //   523: aload_1        
        //   524: aload           4
        //   526: getfield        dso.b:I
        //   529: invokeinterface dve.u:(I)V
        //   534: aload           4
        //   536: getfield        dso.a:I
        //   539: iconst_2       
        //   540: iand           
        //   541: i2l            
        //   542: lconst_0       
        //   543: lcmp           
        //   544: ifeq            558
        //   547: aload_1        
        //   548: aload           4
        //   550: getfield        dso.c:F
        //   553: invokeinterface dve.t:(F)V
        //   558: aload           4
        //   560: getfield        dso.a:I
        //   563: iconst_4       
        //   564: iand           
        //   565: i2l            
        //   566: lconst_0       
        //   567: lcmp           
        //   568: ifeq            582
        //   571: aload_1        
        //   572: aload           4
        //   574: getfield        dso.d:I
        //   577: invokeinterface dve.s:(I)V
        //   582: aload           4
        //   584: getfield        dso.a:I
        //   587: bipush          8
        //   589: iand           
        //   590: i2l            
        //   591: lconst_0       
        //   592: lcmp           
        //   593: ifeq            607
        //   596: aload_1        
        //   597: aload           4
        //   599: getfield        dso.e:F
        //   602: invokeinterface dve.r:(F)V
        //   607: aload           4
        //   609: getfield        dso.a:I
        //   612: bipush          16
        //   614: iand           
        //   615: i2l            
        //   616: lconst_0       
        //   617: lcmp           
        //   618: ifeq            632
        //   621: aload_1        
        //   622: aload           4
        //   624: getfield        dso.f:I
        //   627: invokeinterface dve.o:(I)V
        //   632: aload           4
        //   634: getfield        dso.a:I
        //   637: bipush          32
        //   639: iand           
        //   640: i2l            
        //   641: lconst_0       
        //   642: lcmp           
        //   643: ifeq            657
        //   646: aload_1        
        //   647: aload           4
        //   649: getfield        dso.g:F
        //   652: invokeinterface dve.n:(F)V
        //   657: aload           4
        //   659: getfield        dso.a:I
        //   662: bipush          64
        //   664: iand           
        //   665: i2l            
        //   666: lconst_0       
        //   667: lcmp           
        //   668: ifeq            682
        //   671: aload_1        
        //   672: aload           4
        //   674: getfield        dso.h:I
        //   677: invokeinterface dve.j:(I)V
        //   682: aload           4
        //   684: getfield        dso.a:I
        //   687: sipush          128
        //   690: iand           
        //   691: i2l            
        //   692: lconst_0       
        //   693: lcmp           
        //   694: ifeq            708
        //   697: aload_1        
        //   698: aload           4
        //   700: getfield        dso.i:F
        //   703: invokeinterface dve.i:(F)V
        //   708: aload           4
        //   710: getfield        dso.a:I
        //   713: sipush          256
        //   716: iand           
        //   717: i2l            
        //   718: lconst_0       
        //   719: lcmp           
        //   720: ifeq            734
        //   723: aload_1        
        //   724: aload           4
        //   726: getfield        dso.j:I
        //   729: invokeinterface dve.q:(I)V
        //   734: aload           4
        //   736: getfield        dso.a:I
        //   739: sipush          512
        //   742: iand           
        //   743: i2l            
        //   744: lconst_0       
        //   745: lcmp           
        //   746: ifeq            760
        //   749: aload_1        
        //   750: aload           4
        //   752: getfield        dso.k:F
        //   755: invokeinterface dve.p:(F)V
        //   760: aload           4
        //   762: getfield        dso.a:I
        //   765: sipush          1024
        //   768: iand           
        //   769: i2l            
        //   770: lconst_0       
        //   771: lcmp           
        //   772: ifeq            786
        //   775: aload_1        
        //   776: aload           4
        //   778: getfield        dso.l:I
        //   781: invokeinterface dve.m:(I)V
        //   786: aload           4
        //   788: getfield        dso.a:I
        //   791: sipush          2048
        //   794: iand           
        //   795: i2l            
        //   796: lconst_0       
        //   797: lcmp           
        //   798: ifeq            812
        //   801: aload_1        
        //   802: aload           4
        //   804: getfield        dso.m:F
        //   807: invokeinterface dve.l:(F)V
        //   812: aload           4
        //   814: getfield        dso.a:I
        //   817: sipush          4096
        //   820: iand           
        //   821: i2l            
        //   822: lconst_0       
        //   823: lcmp           
        //   824: ifeq            838
        //   827: aload_1        
        //   828: aload           4
        //   830: getfield        dso.s:Legx;
        //   833: invokeinterface dve.k:(Legx;)V
        //   838: aload           4
        //   840: getfield        dso.a:I
        //   843: sipush          8192
        //   846: iand           
        //   847: i2l            
        //   848: lconst_0       
        //   849: lcmp           
        //   850: ifeq            864
        //   853: aload_1        
        //   854: aload           4
        //   856: getfield        dso.t:Legv;
        //   859: invokeinterface dve.b:(Legv;)V
        //   864: aload           4
        //   866: getfield        dso.a:I
        //   869: sipush          16384
        //   872: iand           
        //   873: i2l            
        //   874: lconst_0       
        //   875: lcmp           
        //   876: ifeq            885
        //   879: aload_1        
        //   880: invokeinterface dve.w:()V
        //   885: aload           4
        //   887: getfield        dso.a:I
        //   890: ldc_w           32768
        //   893: iand           
        //   894: i2l            
        //   895: lconst_0       
        //   896: lcmp           
        //   897: ifeq            911
        //   900: aload_1        
        //   901: aload           4
        //   903: getfield        dso.n:F
        //   906: invokeinterface dve.g:(F)V
        //   911: aload           4
        //   913: getfield        dso.a:I
        //   916: ldc_w           65536
        //   919: iand           
        //   920: i2l            
        //   921: lconst_0       
        //   922: lcmp           
        //   923: ifeq            937
        //   926: aload_1        
        //   927: aload           4
        //   929: getfield        dso.o:F
        //   932: invokeinterface dve.h:(F)V
        //   937: aload           4
        //   939: getfield        dso.a:I
        //   942: ldc_w           131072
        //   945: iand           
        //   946: i2l            
        //   947: lconst_0       
        //   948: lcmp           
        //   949: ifeq            963
        //   952: aload_1        
        //   953: aload           4
        //   955: getfield        dso.p:I
        //   958: invokeinterface dve.f:(I)V
        //   963: aload           4
        //   965: getfield        dso.a:I
        //   968: ldc_w           262144
        //   971: iand           
        //   972: i2l            
        //   973: lconst_0       
        //   974: lcmp           
        //   975: ifeq            989
        //   978: aload_1        
        //   979: aload           4
        //   981: getfield        dso.q:F
        //   984: invokeinterface dve.e:(F)V
        //   989: aload           4
        //   991: getfield        dso.a:I
        //   994: ldc_w           524288
        //   997: iand           
        //   998: i2l            
        //   999: lconst_0       
        //  1000: lcmp           
        //  1001: ifeq            1015
        //  1004: aload_1        
        //  1005: aload           4
        //  1007: getfield        dso.r:F
        //  1010: invokeinterface dve.c:(F)V
        //  1015: aload           4
        //  1017: getfield        dso.a:I
        //  1020: ldc_w           1048576
        //  1023: iand           
        //  1024: i2l            
        //  1025: lconst_0       
        //  1026: lcmp           
        //  1027: ifeq            1041
        //  1030: aload_1        
        //  1031: aload           4
        //  1033: getfield        dso.A:I
        //  1036: invokeinterface dve.v:(I)V
        //  1041: aload           4
        //  1043: getfield        dso.a:I
        //  1046: ldc_w           2097152
        //  1049: iand           
        //  1050: i2l            
        //  1051: lconst_0       
        //  1052: lcmp           
        //  1053: ifeq            1107
        //  1056: iconst_0       
        //  1057: istore          6
        //  1059: iload           6
        //  1061: getstatic       dui.a:I
        //  1064: if_icmpge       1107
        //  1067: aload           4
        //  1069: getfield        dso.u:Ldui;
        //  1072: iload           6
        //  1074: invokevirtual   dui.b:(I)F
        //  1077: fstore          5
        //  1079: fload           5
        //  1081: invokestatic    epf.N:(F)Z
        //  1084: ifne            1101
        //  1087: aload_1        
        //  1088: iload           6
        //  1090: invokestatic    egy.b:(I)I
        //  1093: fload           5
        //  1095: f2i            
        //  1096: invokeinterface dve.C:(II)V
        //  1101: iinc            6, 1
        //  1104: goto            1059
        //  1107: aload           4
        //  1109: getfield        dso.a:I
        //  1112: ldc_w           4194304
        //  1115: iand           
        //  1116: i2l            
        //  1117: lconst_0       
        //  1118: lcmp           
        //  1119: ifeq            1172
        //  1122: iconst_0       
        //  1123: istore          6
        //  1125: iload           6
        //  1127: getstatic       dui.a:I
        //  1130: if_icmpge       1172
        //  1133: aload           4
        //  1135: getfield        dso.z:Ldui;
        //  1138: iload           6
        //  1140: invokevirtual   dui.b:(I)F
        //  1143: fstore          5
        //  1145: fload           5
        //  1147: invokestatic    epf.N:(F)Z
        //  1150: ifne            1166
        //  1153: aload_1        
        //  1154: iload           6
        //  1156: invokestatic    egy.b:(I)I
        //  1159: fload           5
        //  1161: invokeinterface dve.B:(IF)V
        //  1166: iinc            6, 1
        //  1169: goto            1125
        //  1172: aload           4
        //  1174: getfield        dso.a:I
        //  1177: ldc_w           8388608
        //  1180: iand           
        //  1181: i2l            
        //  1182: lconst_0       
        //  1183: lcmp           
        //  1184: ifeq            1238
        //  1187: iconst_0       
        //  1188: istore          6
        //  1190: iload           6
        //  1192: getstatic       dui.a:I
        //  1195: if_icmpge       1238
        //  1198: aload           4
        //  1200: getfield        dso.x:Ldui;
        //  1203: iload           6
        //  1205: invokevirtual   dui.b:(I)F
        //  1208: fstore          5
        //  1210: fload           5
        //  1212: invokestatic    epf.N:(F)Z
        //  1215: ifne            1232
        //  1218: aload_1        
        //  1219: iload           6
        //  1221: invokestatic    egy.b:(I)I
        //  1224: fload           5
        //  1226: f2i            
        //  1227: invokeinterface dve.A:(II)V
        //  1232: iinc            6, 1
        //  1235: goto            1190
        //  1238: aload           4
        //  1240: getfield        dso.a:I
        //  1243: ldc_w           16777216
        //  1246: iand           
        //  1247: i2l            
        //  1248: lconst_0       
        //  1249: lcmp           
        //  1250: ifeq            1303
        //  1253: iconst_0       
        //  1254: istore          6
        //  1256: iload           6
        //  1258: getstatic       dui.a:I
        //  1261: if_icmpge       1303
        //  1264: aload           4
        //  1266: getfield        dso.y:Ldui;
        //  1269: iload           6
        //  1271: invokevirtual   dui.b:(I)F
        //  1274: fstore          5
        //  1276: fload           5
        //  1278: invokestatic    epf.N:(F)Z
        //  1281: ifne            1297
        //  1284: aload_1        
        //  1285: iload           6
        //  1287: invokestatic    egy.b:(I)I
        //  1290: fload           5
        //  1292: invokeinterface dve.z:(IF)V
        //  1297: iinc            6, 1
        //  1300: goto            1256
        //  1303: aload           4
        //  1305: getfield        dso.a:I
        //  1308: ldc_w           33554432
        //  1311: iand           
        //  1312: i2l            
        //  1313: lconst_0       
        //  1314: lcmp           
        //  1315: ifeq            1369
        //  1318: iconst_0       
        //  1319: istore          6
        //  1321: iload           6
        //  1323: getstatic       dui.a:I
        //  1326: if_icmpge       1369
        //  1329: aload           4
        //  1331: getfield        dso.v:Ldui;
        //  1334: iload           6
        //  1336: invokevirtual   dui.b:(I)F
        //  1339: fstore          5
        //  1341: fload           5
        //  1343: invokestatic    epf.N:(F)Z
        //  1346: ifne            1363
        //  1349: aload_1        
        //  1350: iload           6
        //  1352: invokestatic    egy.b:(I)I
        //  1355: fload           5
        //  1357: f2i            
        //  1358: invokeinterface dve.y:(II)V
        //  1363: iinc            6, 1
        //  1366: goto            1321
        //  1369: aload           4
        //  1371: getfield        dso.a:I
        //  1374: ldc_w           67108864
        //  1377: iand           
        //  1378: i2l            
        //  1379: lconst_0       
        //  1380: lcmp           
        //  1381: ifeq            1434
        //  1384: iconst_0       
        //  1385: istore          6
        //  1387: iload           6
        //  1389: getstatic       dui.a:I
        //  1392: if_icmpge       1434
        //  1395: aload           4
        //  1397: getfield        dso.w:Ldui;
        //  1400: iload           6
        //  1402: invokevirtual   dui.b:(I)F
        //  1405: fstore          5
        //  1407: fload           5
        //  1409: invokestatic    epf.N:(F)Z
        //  1412: ifne            1428
        //  1415: aload_1        
        //  1416: iload           6
        //  1418: invokestatic    egy.b:(I)I
        //  1421: fload           5
        //  1423: invokeinterface dve.x:(IF)V
        //  1428: iinc            6, 1
        //  1431: goto            1387
        //  1434: aload_0        
        //  1435: getfield        dsq.b:Ldsp;
        //  1438: astore_0       
        //  1439: aload_0        
        //  1440: ifnull          1901
        //  1443: aload_0        
        //  1444: getfield        dsp.a:I
        //  1447: iconst_1       
        //  1448: iand           
        //  1449: i2l            
        //  1450: lconst_0       
        //  1451: lcmp           
        //  1452: ifeq            1465
        //  1455: aload_1        
        //  1456: aload_0        
        //  1457: getfield        dsp.e:I
        //  1460: invokeinterface dva.bw:(I)V
        //  1465: aload_0        
        //  1466: getfield        dsp.a:I
        //  1469: iconst_2       
        //  1470: iand           
        //  1471: i2l            
        //  1472: lconst_0       
        //  1473: lcmp           
        //  1474: ifeq            1483
        //  1477: aload_1        
        //  1478: invokeinterface dva.bN:()V
        //  1483: aload_0        
        //  1484: getfield        dsp.a:I
        //  1487: ldc_w           262144
        //  1490: iand           
        //  1491: i2l            
        //  1492: lconst_0       
        //  1493: lcmp           
        //  1494: ifeq            1503
        //  1497: aload_1        
        //  1498: invokeinterface dva.br:()V
        //  1503: aload_0        
        //  1504: getfield        dsp.a:I
        //  1507: iconst_4       
        //  1508: iand           
        //  1509: i2l            
        //  1510: lconst_0       
        //  1511: lcmp           
        //  1512: ifeq            1521
        //  1515: aload_1        
        //  1516: invokeinterface dva.bP:()V
        //  1521: aload_0        
        //  1522: getfield        dsp.a:I
        //  1525: sipush          1024
        //  1528: iand           
        //  1529: i2l            
        //  1530: lconst_0       
        //  1531: lcmp           
        //  1532: ifeq            1541
        //  1535: aload_1        
        //  1536: invokeinterface dva.bM:()V
        //  1541: aload_0        
        //  1542: getfield        dsp.a:I
        //  1545: bipush          8
        //  1547: iand           
        //  1548: i2l            
        //  1549: lconst_0       
        //  1550: lcmp           
        //  1551: ifeq            1564
        //  1554: aload_1        
        //  1555: aload_0        
        //  1556: getfield        dsp.b:Ldun;
        //  1559: invokeinterface dva.bK:(Ldun;)V
        //  1564: aload_0        
        //  1565: getfield        dsp.a:I
        //  1568: ldc_w           1073741824
        //  1571: iand           
        //  1572: i2l            
        //  1573: lconst_0       
        //  1574: lcmp           
        //  1575: ifeq            1588
        //  1578: aload_1        
        //  1579: aload_0        
        //  1580: getfield        dsp.c:Ldun;
        //  1583: invokeinterface dva.bB:(Ldun;)V
        //  1588: aload_0        
        //  1589: getfield        dsp.a:I
        //  1592: bipush          16
        //  1594: iand           
        //  1595: i2l            
        //  1596: lconst_0       
        //  1597: lcmp           
        //  1598: ifeq            1608
        //  1601: aload_1        
        //  1602: aconst_null    
        //  1603: invokeinterface dva.bs:(Ldun;)V
        //  1608: aload_0        
        //  1609: getfield        dsp.a:I
        //  1612: bipush          32
        //  1614: iand           
        //  1615: i2l            
        //  1616: lconst_0       
        //  1617: lcmp           
        //  1618: ifeq            1628
        //  1621: aload_1        
        //  1622: aconst_null    
        //  1623: invokeinterface dva.bt:(Ldun;)V
        //  1628: aload_0        
        //  1629: getfield        dsp.a:I
        //  1632: bipush          64
        //  1634: iand           
        //  1635: i2l            
        //  1636: lconst_0       
        //  1637: lcmp           
        //  1638: ifeq            1651
        //  1641: aload_1        
        //  1642: aload_0        
        //  1643: getfield        dsp.d:Ldun;
        //  1646: invokeinterface dva.bx:(Ldun;)V
        //  1651: aload_0        
        //  1652: getfield        dsp.a:I
        //  1655: sipush          128
        //  1658: iand           
        //  1659: i2l            
        //  1660: lconst_0       
        //  1661: lcmp           
        //  1662: ifeq            1672
        //  1665: aload_1        
        //  1666: aconst_null    
        //  1667: invokeinterface dva.bI:(Ldun;)V
        //  1672: aload_0        
        //  1673: getfield        dsp.a:I
        //  1676: ldc_w           65536
        //  1679: iand           
        //  1680: ifeq            1690
        //  1683: aload_1        
        //  1684: aconst_null    
        //  1685: invokeinterface dva.bJ:(Ldun;)V
        //  1690: aload_0        
        //  1691: getfield        dsp.a:I
        //  1694: sipush          512
        //  1697: iand           
        //  1698: i2l            
        //  1699: lconst_0       
        //  1700: lcmp           
        //  1701: ifeq            1718
        //  1704: aload_1        
        //  1705: aload_0        
        //  1706: getfield        dsp.h:Ljava/lang/String;
        //  1709: aload_0        
        //  1710: getfield        dsp.g:Ljava/lang/String;
        //  1713: invokeinterface dva.bG:(Ljava/lang/String;Ljava/lang/String;)V
        //  1718: aload_0        
        //  1719: getfield        dsp.a:I
        //  1722: ldc_w           131072
        //  1725: iand           
        //  1726: i2l            
        //  1727: lconst_0       
        //  1728: lcmp           
        //  1729: ifeq            1742
        //  1732: aload_1        
        //  1733: aload_0        
        //  1734: getfield        dsp.i:Ldxe;
        //  1737: invokeinterface dva.bH:(Ldxe;)V
        //  1742: aload_0        
        //  1743: getfield        dsp.a:I
        //  1746: ldc_w           -2147483648
        //  1749: iand           
        //  1750: i2l            
        //  1751: lconst_0       
        //  1752: lcmp           
        //  1753: ifeq            1766
        //  1756: aload_1        
        //  1757: aload_0        
        //  1758: getfield        dsp.j:Ldxg;
        //  1761: invokeinterface dva.aD:(Ldxg;)V
        //  1766: aload_0        
        //  1767: getfield        dsp.a:I
        //  1770: sipush          256
        //  1773: iand           
        //  1774: i2l            
        //  1775: lconst_0       
        //  1776: lcmp           
        //  1777: ifeq            1830
        //  1780: iconst_0       
        //  1781: istore          6
        //  1783: iload           6
        //  1785: getstatic       dui.a:I
        //  1788: if_icmpge       1830
        //  1791: aload_0        
        //  1792: getfield        dsp.f:Ldui;
        //  1795: iload           6
        //  1797: invokevirtual   dui.b:(I)F
        //  1800: fstore          5
        //  1802: fload           5
        //  1804: invokestatic    epf.N:(F)Z
        //  1807: ifne            1824
        //  1810: aload_1        
        //  1811: iload           6
        //  1813: invokestatic    egy.b:(I)I
        //  1816: fload           5
        //  1818: f2i            
        //  1819: invokeinterface dva.bZ:(II)V
        //  1824: iinc            6, 1
        //  1827: goto            1783
        //  1830: aload_0        
        //  1831: getfield        dsp.a:I
        //  1834: sipush          8192
        //  1837: iand           
        //  1838: i2l            
        //  1839: lconst_0       
        //  1840: lcmp           
        //  1841: ifeq            1854
        //  1844: aload_1        
        //  1845: aload_0        
        //  1846: getfield        dsp.k:Ldsk;
        //  1849: invokeinterface dva.bo:(Ldsk;)V
        //  1854: aload_0        
        //  1855: getfield        dsp.a:I
        //  1858: sipush          16384
        //  1861: iand           
        //  1862: i2l            
        //  1863: lconst_0       
        //  1864: lcmp           
        //  1865: ifeq            1874
        //  1868: aload_1        
        //  1869: invokeinterface dva.bD:()V
        //  1874: aload_0        
        //  1875: getfield        dsp.a:I
        //  1878: ldc_w           32768
        //  1881: iand           
        //  1882: i2l            
        //  1883: lconst_0       
        //  1884: lcmp           
        //  1885: ifeq            1894
        //  1888: aload_1        
        //  1889: invokeinterface dva.bE:()V
        //  1894: aload_1        
        //  1895: iconst_m1      
        //  1896: invokeinterface dva.bA:(I)V
        //  1901: aload_1        
        //  1902: aload           9
        //  1904: aload           9
        //  1906: invokestatic    coy.l:(Ldst;)Ljava/lang/String;
        //  1909: invokeinterface dva.aF:(Ldst;Ljava/lang/String;)V
        //  1914: aload           11
        //  1916: invokestatic    dvc.e:(Ldsx;)Z
        //  1919: pop            
        //  1920: aload           9
        //  1922: invokestatic    dst.y:(Ldst;)Z
        //  1925: ifeq            1935
        //  1928: aload           9
        //  1930: aload           11
        //  1932: invokevirtual   dtd.ab:(Ldsx;)V
        //  1935: aload_1        
        //  1936: aload           9
        //  1938: invokestatic    dst.B:(Ldva;Ldst;)V
        //  1941: aload_1        
        //  1942: areturn        
        //  1943: aload           9
        //  1945: astore          4
        //  1947: getstatic       dsx.a:Ldva;
        //  1950: areturn        
        //  1951: aload           9
        //  1953: astore          4
        //  1955: new             Ljava/lang/IllegalArgumentException;
        //  1958: astore          7
        //  1960: aload           9
        //  1962: astore          4
        //  1964: aload           9
        //  1966: invokevirtual   dst.q:()Ljava/lang/String;
        //  1969: astore_1       
        //  1970: aload           9
        //  1972: astore          4
        //  1974: new             Ljava/lang/StringBuilder;
        //  1977: astore          11
        //  1979: aload           9
        //  1981: astore          4
        //  1983: aload           11
        //  1985: ldc_w           "component:"
        //  1988: invokespecial   java/lang/StringBuilder.<init>:(Ljava/lang/String;)V
        //  1991: aload           9
        //  1993: astore          4
        //  1995: aload           11
        //  1997: aload_1        
        //  1998: invokevirtual   java/lang/StringBuilder.append:(Ljava/lang/String;)Ljava/lang/StringBuilder;
        //  2001: pop            
        //  2002: aload           9
        //  2004: astore          4
        //  2006: aload           7
        //  2008: aload           11
        //  2010: invokevirtual   java/lang/StringBuilder.toString:()Ljava/lang/String;
        //  2013: invokespecial   java/lang/IllegalArgumentException.<init>:(Ljava/lang/String;)V
        //  2016: aload           9
        //  2018: astore          4
        //  2020: aload           7
        //  2022: athrow         
        //  2023: astore          7
        //  2025: goto            2032
        //  2028: astore_0       
        //  2029: goto            2170
        //  2032: aload_0        
        //  2033: invokevirtual   dsx.e:()Ldun;
        //  2036: astore          9
        //  2038: aload           7
        //  2040: instanceof      Ldwl;
        //  2043: ifeq            2061
        //  2046: aload           7
        //  2048: checkcast       Ldwl;
        //  2051: astore_1       
        //  2052: aconst_null    
        //  2053: astore_1       
        //  2054: aload           8
        //  2056: astore          7
        //  2058: goto            2081
        //  2061: aload           10
        //  2063: astore_1       
        //  2064: aload           7
        //  2066: instanceof      Ldvm;
        //  2069: ifeq            2081
        //  2072: aload           7
        //  2074: checkcast       Ldvm;
        //  2077: getfield        dvm.a:Ldun;
        //  2080: astore_1       
        //  2081: aload           7
        //  2083: instanceof      Ldvm;
        //  2086: ifeq            2099
        //  2089: aload           7
        //  2091: checkcast       Ldvm;
        //  2094: astore          8
        //  2096: goto            2111
        //  2099: new             Ldvm;
        //  2102: dup            
        //  2103: aload_0        
        //  2104: aload           7
        //  2106: invokespecial   dvm.<init>:(Ldsx;Ljava/lang/Throwable;)V
        //  2109: astore          8
        //  2111: aload           8
        //  2113: aload           4
        //  2115: invokevirtual   dvm.a:(Ldst;)V
        //  2118: aload_1        
        //  2119: aload           9
        //  2121: if_acmpeq       2161
        //  2124: aload           9
        //  2126: instanceof      Ldul;
        //  2129: ifeq            2140
        //  2132: aload           8
        //  2134: invokestatic    coy.h:(Ljava/lang/Exception;)V
        //  2137: goto            2146
        //  2140: aload_0        
        //  2141: aload           7
        //  2143: invokestatic    dtd.U:(Ldsx;Ljava/lang/Exception;)V
        //  2146: getstatic       dsx.a:Ldva;
        //  2149: areturn        
        //  2150: astore_0       
        //  2151: aload           8
        //  2153: aload           9
        //  2155: putfield        dvm.a:Ldun;
        //  2158: aload           8
        //  2160: athrow         
        //  2161: aload           8
        //  2163: aload_1        
        //  2164: putfield        dvm.a:Ldun;
        //  2167: aload           8
        //  2169: athrow         
        //  2170: goto            2175
        //  2173: aload_0        
        //  2174: athrow         
        //  2175: goto            2173
        //    Exceptions:
        //  Try           Handler
        //  Start  End    Start  End    Type                 
        //  -----  -----  -----  -----  ---------------------
        //  9      17     2023   2170   Ljava/lang/Exception;
        //  9      17     2028   2178   Any
        //  20     26     2023   2170   Ljava/lang/Exception;
        //  20     26     2028   2178   Any
        //  29     36     2023   2170   Ljava/lang/Exception;
        //  29     36     2028   2178   Any
        //  40     50     2023   2170   Ljava/lang/Exception;
        //  40     50     2028   2178   Any
        //  58     64     2023   2170   Ljava/lang/Exception;
        //  58     64     2028   2178   Any
        //  68     75     2023   2170   Ljava/lang/Exception;
        //  68     75     2028   2178   Any
        //  79     90     2023   2170   Ljava/lang/Exception;
        //  79     90     2028   2178   Any
        //  94     109    2023   2170   Ljava/lang/Exception;
        //  94     109    2028   2178   Any
        //  116    124    2023   2170   Ljava/lang/Exception;
        //  116    124    2028   2178   Any
        //  128    136    2023   2170   Ljava/lang/Exception;
        //  128    136    2028   2178   Any
        //  143    151    2023   2170   Ljava/lang/Exception;
        //  143    151    2028   2178   Any
        //  155    161    2023   2170   Ljava/lang/Exception;
        //  155    161    2028   2178   Any
        //  165    172    2023   2170   Ljava/lang/Exception;
        //  165    172    2028   2178   Any
        //  179    187    2023   2170   Ljava/lang/Exception;
        //  179    187    2028   2178   Any
        //  191    199    2023   2170   Ljava/lang/Exception;
        //  191    199    2028   2178   Any
        //  203    221    2023   2170   Ljava/lang/Exception;
        //  203    221    2028   2178   Any
        //  228    236    2023   2170   Ljava/lang/Exception;
        //  228    236    2028   2178   Any
        //  247    254    2023   2170   Ljava/lang/Exception;
        //  247    254    2028   2178   Any
        //  268    276    2023   2170   Ljava/lang/Exception;
        //  268    276    2028   2178   Any
        //  288    297    2023   2170   Ljava/lang/Exception;
        //  288    297    2028   2178   Any
        //  310    315    2023   2170   Ljava/lang/Exception;
        //  310    315    2028   2178   Any
        //  1947   1951   2023   2170   Ljava/lang/Exception;
        //  1947   1951   2028   2178   Any
        //  1955   1960   2023   2170   Ljava/lang/Exception;
        //  1955   1960   2028   2178   Any
        //  1964   1970   2023   2170   Ljava/lang/Exception;
        //  1964   1970   2028   2178   Any
        //  1974   1979   2023   2170   Ljava/lang/Exception;
        //  1974   1979   2028   2178   Any
        //  1983   1991   2023   2170   Ljava/lang/Exception;
        //  1983   1991   2028   2178   Any
        //  1995   2002   2023   2170   Ljava/lang/Exception;
        //  1995   2002   2028   2178   Any
        //  2006   2016   2023   2170   Ljava/lang/Exception;
        //  2006   2016   2028   2178   Any
        //  2020   2023   2023   2170   Ljava/lang/Exception;
        //  2020   2023   2028   2178   Any
        //  2032   2052   2028   2178   Any
        //  2064   2081   2028   2178   Any
        //  2081   2096   2028   2178   Any
        //  2099   2111   2028   2178   Any
        //  2111   2118   2028   2178   Any
        //  2124   2137   2028   2178   Any
        //  2140   2146   2150   2161   Ldwl;
        //  2140   2146   2028   2178   Any
        //  2146   2150   2028   2178   Any
        //  2151   2161   2028   2178   Any
        //  2161   2170   2028   2178   Any
        // 
        // The error that occurred was:
        // 
        // java.lang.IndexOutOfBoundsException: Index: 1023, Size: 1023
        //     at java.util.ArrayList.rangeCheck(Unknown Source)
        //     at java.util.ArrayList.get(Unknown Source)
        //     at com.strobel.decompiler.ast.AstBuilder.convertToAst(AstBuilder.java:3362)
        //     at com.strobel.decompiler.ast.AstBuilder.convertToAst(AstBuilder.java:3611)
        //     at com.strobel.decompiler.ast.AstBuilder.build(AstBuilder.java:112)
        //     at com.strobel.decompiler.languages.java.ast.AstMethodBodyBuilder.createMethodBody(AstMethodBodyBuilder.java:203)
        //     at com.strobel.decompiler.languages.java.ast.AstMethodBodyBuilder.createMethodBody(AstMethodBodyBuilder.java:93)
        //     at com.strobel.decompiler.languages.java.ast.AstBuilder.createMethodBody(AstBuilder.java:868)
        //     at com.strobel.decompiler.languages.java.ast.AstBuilder.createMethod(AstBuilder.java:761)
        //     at com.strobel.decompiler.languages.java.ast.AstBuilder.addTypeMembers(AstBuilder.java:638)
        //     at com.strobel.decompiler.languages.java.ast.AstBuilder.createTypeCore(AstBuilder.java:605)
        //     at com.strobel.decompiler.languages.java.ast.AstBuilder.createTypeNoCache(AstBuilder.java:195)
        //     at com.strobel.decompiler.languages.java.ast.AstBuilder.createType(AstBuilder.java:162)
        //     at com.strobel.decompiler.languages.java.ast.AstBuilder.addType(AstBuilder.java:137)
        //     at com.strobel.decompiler.languages.java.JavaLanguage.buildAst(JavaLanguage.java:71)
        //     at com.strobel.decompiler.languages.java.JavaLanguage.decompileType(JavaLanguage.java:59)
        //     at com.strobel.decompiler.DecompilerDriver.decompileType(DecompilerDriver.java:333)
        //     at com.strobel.decompiler.DecompilerDriver.decompileJar(DecompilerDriver.java:254)
        //     at com.strobel.decompiler.DecompilerDriver.main(DecompilerDriver.java:129)
        // 
        throw new IllegalStateException("An error occurred while decompiling this method.");
    }
    
    static void d(final dva dva) {
        final List ac = dva.aC();
        final int n = 0;
        if (ac != null) {
            for (int size = ac.size(), i = 0; i < size; ++i) {
                dva.bp((dst)ac.get(i));
            }
            dva.aC().clear();
        }
        for (int r = dva.R(), j = n; j < r; ++j) {
            d(dva.al(j));
        }
    }
    
    static boolean e(final dsx dsx) {
        if (dsx != null) {
            final ComponentTree h = dsx.h;
            if (h != null) {
                return h.c;
            }
        }
        return dsj.a(null);
    }
    
    public static boolean f(final int n, final int n2, final int n3, final int n4, final float n5, final float n6) {
        final int n7 = (int)n6;
        final boolean i = bkw.i(n, n3, (int)n5);
        final boolean j = bkw.i(n2, n4, n7);
        return i && j;
    }
    
    static dsx g(dsx h, final dst dst, final boolean b) {
        final AtomicBoolean o = dst.o;
        dst j = null;
        Label_0030: {
            if (o != null) {
                if (o.getAndSet(true)) {
                    j = dst.j();
                    break Label_0030;
                }
            }
            j = dst;
        }
        if (b) {
            j.l = coy.l(dst);
        }
        final cya k = h.k;
        ((dtd)j).aC(k);
        h = j.H(h);
        h.k = ((dtd)j).aB(h, k);
        if (dyp.a) {
            final dto dto = dtp.a.get(dtp.i(h, h.h()));
            if (dto != null) {
                dto.a();
                final dwr s = j.s;
                dto.c();
            }
        }
        return h;
    }
    
    public static dva h(dsx p5, final dva dva, final int f, final int g, final pa pa) {
        final dst ab = dva.ab();
        final String at = dva.at();
        final dva am = dva.am();
        final List ab2 = dva.aB();
        final List aa = dva.aA();
        if (ab2.size() > 1) {
            final int n = ab2.size() - 2;
            final dst dst = ab2.get(n);
            if (aa != null) {
                final String s = aa.get(n);
            }
            coy.l(dst);
            final pa i = p5.i;
            p5 = dst.p;
        }
        if (ab != null) {
            dva dva2 = null;
            Label_0457: {
                if (am != null) {
                    dva2 = am;
                    if (f(am.U(), am.T(), f, g, am.O(), am.N())) {
                        break Label_0457;
                    }
                }
                final dvf f2 = p5.f();
                if (f2 == null) {
                    throw new IllegalStateException(ab.q().concat(": Trying to access the cached InternalNode for a component outside of a LayoutState calculation. If that is what you must do, see Component#measureMightNotCacheInternalNode."));
                }
                dva c = f2.c(ab);
                Label_0286: {
                    if (c != null) {
                        f2.h(ab);
                        final boolean b = c.bb() || c.L() == dva.L();
                        final boolean f3 = f(c.U(), c.T(), f, g, c.O(), c.N());
                        if (b && f3) {
                            break Label_0286;
                        }
                    }
                    c = null;
                }
                dva dva3;
                if (c != null) {
                    dva3 = c;
                }
                else {
                    if (am != null && dyp.h) {
                        final int f4 = p5.f;
                        final int g2 = p5.g;
                    }
                    dsx d;
                    if (!dvc.a) {
                        d = p5;
                    }
                    else {
                        d = p5.d();
                    }
                    d.k = dva.cd();
                    d.f = f;
                    d.g = g;
                    final dva c2 = c(d, ab, true, true, at);
                    dva.d((Object)c2);
                    k(p5, c2, f, g, pa, dva.bg());
                    c2.aO(f);
                    c2.aL(g);
                    c2.aM((float)c2.a());
                    c2.aN((float)c2.H());
                    dva3 = c2;
                }
                dva.aP(dva3);
                dva2 = dva3;
            }
            dva2.aH();
            return dva2;
        }
        throw new IllegalArgumentException("A component is required to resolve a nested tree.");
    }
    
    static dva i(final pa pa, final dsx dsx, dst e, String s, final int f, final int g, final dva dva, final pa pa2, final dtw dtw, final dwk dwk) {
        if (dwk != null) {
            if (dva == null) {
                s = "start_create_layout";
            }
            else {
                s = "start_reconcile_layout";
            }
            dwk.b(s);
        }
        dsx.f = f;
        dsx.g = g;
        s = "end_create_layout";
        dva cb;
        if (dva == null) {
            final dva b = b(dsx, e, true);
            if (dsx.n()) {
                if (dwk != null) {
                    dwk.b("end_create_layout");
                }
                return b;
            }
            final pa i = dsx.i;
            cb = b;
            if (i != null) {
                final Object c = i.c;
                cb = b;
                if (c != null) {
                    ((dvf)c).A = false;
                    cb = b;
                }
            }
        }
        else {
            e = g(dsx, e, true).e;
            cb = dva.cb(pa, dsx, e, coy.l(e));
        }
        if (dwk != null) {
            String s2;
            if (dva == null) {
                s2 = s;
            }
            else {
                s2 = "end_reconcile_layout";
            }
            dwk.b(s2);
        }
        if (dwk != null) {
            dwk.b("start_measure");
        }
        k(dsx, cb, f, g, pa2, dtw);
        if (dwk != null) {
            dwk.b("end_measure");
        }
        return cb;
    }
    
    static void j(pa f, final dva dva, final pa pa, final dtw dtw) {
        try {
            final dva ao = dva.ao();
            if (dst.x(dva.ab()) && ao != null) {
                dva.bj(dtw);
                return;
            }
            if (dtw != null) {
                if (coy.k(dva.ab(), dtw.d)) {
                    dva.bj(dtw);
                    final int r = dva.R();
                    final int size = dtw.i.size();
                    if (r != 0 && size != 0) {
                        for (int n = 0; n < r && n < size; ++n) {
                            j(f, dva.al(n), pa, (dtw)dtw.i.get(n));
                        }
                    }
                    else {
                        final dst ab = dva.ab();
                        dva.at();
                        coy.l(ab);
                        if (ab != null) {
                            final dst d = dtw.d;
                            if (d != null) {
                                if (f != null) {
                                    final Object a = f.a;
                                    if (a != null) {
                                        final dvf u = ((ComponentTree)a).u;
                                        if (u == null) {
                                            f = null;
                                        }
                                        else {
                                            f = u.F;
                                        }
                                        if (f != null) {
                                            coy.l(d);
                                        }
                                    }
                                }
                            }
                            if (!((dtd)ab).az(dtw.d, ab)) {
                                final dst ab2 = dva.ab();
                                dva.at();
                                coy.l(ab2);
                                if (ab2 != null) {
                                    ab2.r(ab2.t, dtw.d.t);
                                }
                                dva.bC();
                            }
                        }
                    }
                }
            }
        }
        finally {
            final Throwable t;
            final dvm dvm = new dvm(dva.ac(), t);
            final dst ab3 = dva.ab();
            if (ab3 != null) {
                dvm.a(ab3);
            }
            throw dvm;
        }
    }
    
    static void k(final dsx dsx, final dva dva, final int n, final int n2, final pa pa, final dtw dtw) {
        if (dva.aq() == egx.a) {
            final Context b = dsx.b;
            if ((b.getApplicationInfo().flags & 0x400000) != 0x0 && b.getResources().getConfiguration().getLayoutDirection() == 1) {
                dva.k(egx.c);
            }
        }
        if (epf.N(dva.Q())) {
            dva.aR(n);
        }
        if (epf.N(dva.P())) {
            dva.aQ(n2);
        }
        if (dtw != null) {
            j(dsx.i, dva, pa, dtw);
        }
        final int mode = View$MeasureSpec.getMode(n);
        float n3 = Float.NaN;
        float n4;
        if (mode == 0) {
            n4 = Float.NaN;
        }
        else {
            n4 = (float)View$MeasureSpec.getSize(n);
        }
        if (View$MeasureSpec.getMode(n2) != 0) {
            n3 = (float)View$MeasureSpec.getSize(n2);
        }
        dva.aJ(n4, n3);
    }
    
    static void l(final dsx dsx, final dva dva, final int n, final int n2, final pa pa, final dtw dtw, final dwk dwk) {
        if (dva == dsx.a) {
            return;
        }
        d(dva);
        if (dwk != null) {
            dwk.b("start_measure");
        }
        k(dsx, dva, n, n2, pa, dtw);
        if (dwk != null) {
            dwk.b("end_measure");
        }
    }
}
