import android.net.Uri;
import com.google.android.libraries.youtube.edit.filters.model.FilterMapTable$FilterDescriptor;
import com.google.android.libraries.youtube.creation.music.ShortsCreationSelectedTrack;
import android.view.View;
import com.google.android.apps.youtube.app.extensions.reel.creation.shorts.edit.timeline.TimelineSeekBar;

// 
// Decompiled by Procyon v0.6.0
// 

public final class gwk implements Runnable
{
    public final Object a;
    public final Object b;
    private final int c;
    
    public gwk(final TimelineSeekBar b, final View a, final int c) {
        this.c = c;
        this.b = b;
        this.a = a;
    }
    
    public gwk(final gww a, final uby b, final int c) {
        this.c = c;
        this.a = a;
        this.b = b;
    }
    
    public gwk(final gww a, final upc b, final int c) {
        this.c = c;
        this.a = a;
        this.b = b;
    }
    
    public gwk(final gxj a, final ShortsCreationSelectedTrack b, final int c) {
        this.c = c;
        this.a = a;
        this.b = b;
    }
    
    public gwk(final gya b, final View a, final int c) {
        this.c = c;
        this.b = b;
        this.a = a;
    }
    
    public gwk(final hah a, final aeea b, final int c, final byte[] array, final byte[] array2, final byte[] array3, final byte[] array4, final byte[] array5, final byte[] array6) {
        this.c = c;
        this.a = a;
        this.b = b;
    }
    
    public gwk(final hao a, final FilterMapTable$FilterDescriptor b, final int c) {
        this.c = c;
        this.a = a;
        this.b = b;
    }
    
    public gwk(final hau a, final uby b, final int c) {
        this.c = c;
        this.a = a;
        this.b = b;
    }
    
    public gwk(final hbg a, final uby b, final int c) {
        this.c = c;
        this.a = a;
        this.b = b;
    }
    
    public gwk(final hbm a, final ucd b, final int c) {
        this.c = c;
        this.a = a;
        this.b = b;
    }
    
    public gwk(final hbp b, final argj a, final int c, final byte[] array, final byte[] array2, final byte[] array3) {
        this.c = c;
        this.b = b;
        this.a = a;
    }
    
    public gwk(final hbp a, final uby b, final int c) {
        this.c = c;
        this.a = a;
        this.b = b;
    }
    
    public gwk(final hcq a, final aezp b, final int c) {
        this.c = c;
        this.a = a;
        this.b = b;
    }
    
    public gwk(final hcq b, final Uri a, final int c) {
        this.c = c;
        this.b = b;
        this.a = a;
    }
    
    public gwk(final hdm a, final ShortsCreationSelectedTrack b, final int c) {
        this.c = c;
        this.a = a;
        this.b = b;
    }
    
    @Override
    public final void run() {
        // 
        // This method could not be decompiled.
        // 
        // Original Bytecode:
        // 
        //     1: getfield        gwk.c:I
        //     4: istore_3       
        //     5: iconst_1       
        //     6: istore_2       
        //     7: iload_3        
        //     8: tableswitch {
        //                0: 2091
        //                1: 2053
        //                2: 1616
        //                3: 1565
        //                4: 1522
        //                5: 1402
        //                6: 1359
        //                7: 1199
        //                8: 989
        //                9: 949
        //               10: 889
        //               11: 846
        //               12: 768
        //               13: 739
        //               14: 577
        //               15: 545
        //               16: 487
        //               17: 282
        //               18: 250
        //               19: 139
        //          default: 104
        //        }
        //   104: aload_0        
        //   105: getfield        gwk.a:Ljava/lang/Object;
        //   108: astore          9
        //   110: aload_0        
        //   111: getfield        gwk.b:Ljava/lang/Object;
        //   114: astore          8
        //   116: aload           9
        //   118: checkcast       Lhdm;
        //   121: getfield        hdm.x:Lhcz;
        //   124: aload           8
        //   126: checkcast       Lcom/google/android/libraries/youtube/creation/music/ShortsCreationSelectedTrack;
        //   129: invokevirtual   com/google/android/libraries/youtube/creation/music/ShortsCreationSelectedTrack.c:()J
        //   132: invokestatic    java/lang/Long.valueOf:(J)Ljava/lang/Long;
        //   135: putfield        hcz.d:Ljava/lang/Long;
        //   138: return         
        //   139: aload_0        
        //   140: getfield        gwk.a:Ljava/lang/Object;
        //   143: astore          8
        //   145: aload_0        
        //   146: getfield        gwk.b:Ljava/lang/Object;
        //   149: astore          10
        //   151: aload           8
        //   153: checkcast       Lhdm;
        //   156: astore          9
        //   158: aload           9
        //   160: getfield        hdm.f:Landroid/view/View;
        //   163: ldc             2131431497
        //   165: invokevirtual   android/view/View.findViewById:(I)Landroid/view/View;
        //   168: astore          8
        //   170: aload           8
        //   172: ifnonnull       176
        //   175: return         
        //   176: aload           10
        //   178: checkcast       Lcom/google/android/libraries/youtube/creation/music/ShortsCreationSelectedTrack;
        //   181: astore          10
        //   183: aload           10
        //   185: invokevirtual   com/google/android/libraries/youtube/creation/music/ShortsCreationSelectedTrack.f:()Laezp;
        //   188: invokevirtual   aezp.h:()Z
        //   191: ifeq            234
        //   194: aload           10
        //   196: invokevirtual   com/google/android/libraries/youtube/creation/music/ShortsCreationSelectedTrack.f:()Laezp;
        //   199: invokevirtual   aezp.c:()Ljava/lang/Object;
        //   202: checkcast       Ljava/lang/Long;
        //   205: invokevirtual   java/lang/Long.longValue:()J
        //   208: aload           9
        //   210: invokevirtual   hdm.m:()J
        //   213: lcmp           
        //   214: ifgt            234
        //   217: aload           8
        //   219: bipush          8
        //   221: invokevirtual   android/view/View.setVisibility:(I)V
        //   224: aload           9
        //   226: getfield        hdm.m:Lhdb;
        //   229: iconst_0       
        //   230: putfield        hdb.ah:Z
        //   233: return         
        //   234: aload           8
        //   236: iconst_0       
        //   237: invokevirtual   android/view/View.setVisibility:(I)V
        //   240: aload           9
        //   242: getfield        hdm.m:Lhdb;
        //   245: iconst_1       
        //   246: putfield        hdb.ah:Z
        //   249: return         
        //   250: aload_0        
        //   251: getfield        gwk.a:Ljava/lang/Object;
        //   254: astore          9
        //   256: aload_0        
        //   257: getfield        gwk.b:Ljava/lang/Object;
        //   260: astore          8
        //   262: aload           9
        //   264: checkcast       Lhdm;
        //   267: getfield        hdm.x:Lhcz;
        //   270: aload           8
        //   272: checkcast       Lcom/google/android/libraries/youtube/creation/music/ShortsCreationSelectedTrack;
        //   275: invokevirtual   com/google/android/libraries/youtube/creation/music/ShortsCreationSelectedTrack.j:()Laoek;
        //   278: invokevirtual   hcz.d:(Laoek;)V
        //   281: return         
        //   282: aload_0        
        //   283: getfield        gwk.a:Ljava/lang/Object;
        //   286: astore          9
        //   288: aload_0        
        //   289: getfield        gwk.b:Ljava/lang/Object;
        //   292: astore          8
        //   294: aload           9
        //   296: checkcast       Lhdm;
        //   299: astore          9
        //   301: aload           9
        //   303: getfield        hdm.v:Lachb;
        //   306: astore          10
        //   308: aload           10
        //   310: ifnonnull       316
        //   313: goto            408
        //   316: aload           9
        //   318: getfield        hdm.o:Z
        //   321: ifeq            371
        //   324: aload           8
        //   326: checkcast       Lcom/google/android/libraries/youtube/creation/music/ShortsCreationSelectedTrack;
        //   329: astore          11
        //   331: aload           11
        //   333: invokevirtual   com/google/android/libraries/youtube/creation/music/ShortsCreationSelectedTrack.k:()Laotp;
        //   336: ifnull          371
        //   339: aload           11
        //   341: invokevirtual   com/google/android/libraries/youtube/creation/music/ShortsCreationSelectedTrack.k:()Laotp;
        //   344: astore          11
        //   346: aload           11
        //   348: invokevirtual   java/lang/Object.getClass:()Ljava/lang/Class;
        //   351: pop            
        //   352: aload           10
        //   354: aload           11
        //   356: new             Lhdj;
        //   359: dup            
        //   360: aload           9
        //   362: invokespecial   hdj.<init>:(Lhdm;)V
        //   365: invokevirtual   achb.l:(Laotp;Ltpn;)V
        //   368: goto            378
        //   371: aload           10
        //   373: ldc             2131231811
        //   375: invokevirtual   achb.g:(I)V
        //   378: aload           9
        //   380: getfield        hdm.n:Landroid/widget/ImageView;
        //   383: getstatic       android/widget/ImageView$ScaleType.CENTER_CROP:Landroid/widget/ImageView$ScaleType;
        //   386: invokevirtual   android/widget/ImageView.setScaleType:(Landroid/widget/ImageView$ScaleType;)V
        //   389: aload           9
        //   391: getfield        hdm.n:Landroid/widget/ImageView;
        //   394: ldc             2131233260
        //   396: invokevirtual   android/widget/ImageView.setBackgroundResource:(I)V
        //   399: aload           9
        //   401: getfield        hdm.n:Landroid/widget/ImageView;
        //   404: iconst_1       
        //   405: invokevirtual   android/widget/ImageView.setClipToOutline:(Z)V
        //   408: aload           9
        //   410: getfield        hdm.f:Landroid/view/View;
        //   413: ldc             2131431510
        //   415: invokevirtual   android/view/View.findViewById:(I)Landroid/view/View;
        //   418: checkcast       Lcom/google/android/libraries/youtube/common/ui/YouTubeTextView;
        //   421: astore          10
        //   423: aload           9
        //   425: getfield        hdm.f:Landroid/view/View;
        //   428: ldc             2131431457
        //   430: invokevirtual   android/view/View.findViewById:(I)Landroid/view/View;
        //   433: checkcast       Lcom/google/android/libraries/youtube/common/ui/YouTubeTextView;
        //   436: astore          11
        //   438: aload           9
        //   440: getfield        hdm.o:Z
        //   443: ifeq            472
        //   446: aload           10
        //   448: aload           8
        //   450: checkcast       Lcom/google/android/libraries/youtube/creation/music/ShortsCreationSelectedTrack;
        //   453: invokevirtual   com/google/android/libraries/youtube/creation/music/ShortsCreationSelectedTrack.m:()Ljava/lang/String;
        //   456: invokevirtual   com/google/android/libraries/youtube/common/ui/YouTubeTextView.setText:(Ljava/lang/CharSequence;)V
        //   459: aload           10
        //   461: iconst_1       
        //   462: invokevirtual   com/google/android/libraries/youtube/common/ui/YouTubeTextView.setSelected:(Z)V
        //   465: aload           11
        //   467: iconst_0       
        //   468: invokevirtual   com/google/android/libraries/youtube/common/ui/YouTubeTextView.setVisibility:(I)V
        //   471: return         
        //   472: aload           10
        //   474: ldc             2132017679
        //   476: invokevirtual   com/google/android/libraries/youtube/common/ui/YouTubeTextView.setText:(I)V
        //   479: aload           11
        //   481: bipush          8
        //   483: invokevirtual   com/google/android/libraries/youtube/common/ui/YouTubeTextView.setVisibility:(I)V
        //   486: return         
        //   487: aload_0        
        //   488: getfield        gwk.a:Ljava/lang/Object;
        //   491: astore          8
        //   493: aload_0        
        //   494: getfield        gwk.b:Ljava/lang/Object;
        //   497: astore          9
        //   499: aload           8
        //   501: checkcast       Lhdm;
        //   504: getfield        hdm.x:Lhcz;
        //   507: astore          8
        //   509: aload           9
        //   511: checkcast       Lcom/google/android/libraries/youtube/creation/music/ShortsCreationSelectedTrack;
        //   514: astore          9
        //   516: aload           8
        //   518: aload           9
        //   520: invokevirtual   com/google/android/libraries/youtube/creation/music/ShortsCreationSelectedTrack.f:()Laezp;
        //   523: invokevirtual   aezp.c:()Ljava/lang/Object;
        //   526: checkcast       Ljava/lang/Long;
        //   529: invokevirtual   java/lang/Long.longValue:()J
        //   532: aload           9
        //   534: invokevirtual   com/google/android/libraries/youtube/creation/music/ShortsCreationSelectedTrack.b:()J
        //   537: lsub           
        //   538: invokestatic    java/lang/Long.valueOf:(J)Ljava/lang/Long;
        //   541: putfield        hcz.e:Ljava/lang/Long;
        //   544: return         
        //   545: aload_0        
        //   546: getfield        gwk.a:Ljava/lang/Object;
        //   549: astore          9
        //   551: aload_0        
        //   552: getfield        gwk.b:Ljava/lang/Object;
        //   555: astore          8
        //   557: aload           9
        //   559: checkcast       Lhdm;
        //   562: getfield        hdm.x:Lhcz;
        //   565: aload           8
        //   567: checkcast       Lcom/google/android/libraries/youtube/creation/music/ShortsCreationSelectedTrack;
        //   570: invokevirtual   com/google/android/libraries/youtube/creation/music/ShortsCreationSelectedTrack.j:()Laoek;
        //   573: invokevirtual   hcz.d:(Laoek;)V
        //   576: return         
        //   577: aload_0        
        //   578: getfield        gwk.a:Ljava/lang/Object;
        //   581: astore          9
        //   583: aload_0        
        //   584: getfield        gwk.b:Ljava/lang/Object;
        //   587: astore          8
        //   589: aload           9
        //   591: checkcast       Lhcq;
        //   594: astore          9
        //   596: aload           9
        //   598: getfield        hcq.c:Lhci;
        //   601: astore          10
        //   603: aload           10
        //   605: getfield        hci.e:Z
        //   608: ifeq            627
        //   611: aload           10
        //   613: aload           8
        //   615: checkcast       Laezp;
        //   618: invokevirtual   aezp.c:()Ljava/lang/Object;
        //   621: checkcast       Landroid/net/Uri;
        //   624: invokevirtual   hci.i:(Landroid/net/Uri;)V
        //   627: aload           9
        //   629: getfield        hcq.i:Z
        //   632: ifeq            684
        //   635: aload           9
        //   637: getfield        hcq.k:Lubk;
        //   640: astore          10
        //   642: aload           10
        //   644: ifnull          738
        //   647: aload           9
        //   649: getfield        hcq.b:Lativ;
        //   652: astore          9
        //   654: aload           10
        //   656: aload           8
        //   658: checkcast       Laezp;
        //   661: invokevirtual   aezp.c:()Ljava/lang/Object;
        //   664: checkcast       Landroid/net/Uri;
        //   667: putfield        ubk.g:Landroid/net/Uri;
        //   670: aload           9
        //   672: aload           10
        //   674: invokevirtual   ubk.a:()Lcom/google/android/libraries/youtube/creation/music/ShortsCreationSelectedTrack;
        //   677: invokestatic    aezp.k:(Ljava/lang/Object;)Laezp;
        //   680: invokevirtual   ativ.tu:(Ljava/lang/Object;)V
        //   683: return         
        //   684: aload           9
        //   686: invokevirtual   hcq.a:()Lcom/google/android/libraries/youtube/creation/music/ShortsCreationSelectedTrack;
        //   689: ifnull          738
        //   692: aload           9
        //   694: getfield        hcq.b:Lativ;
        //   697: astore          10
        //   699: aload           9
        //   701: invokevirtual   hcq.a:()Lcom/google/android/libraries/youtube/creation/music/ShortsCreationSelectedTrack;
        //   704: invokevirtual   com/google/android/libraries/youtube/creation/music/ShortsCreationSelectedTrack.e:()Lubk;
        //   707: astore          9
        //   709: aload           9
        //   711: aload           8
        //   713: checkcast       Laezp;
        //   716: invokevirtual   aezp.c:()Ljava/lang/Object;
        //   719: checkcast       Landroid/net/Uri;
        //   722: putfield        ubk.g:Landroid/net/Uri;
        //   725: aload           10
        //   727: aload           9
        //   729: invokevirtual   ubk.a:()Lcom/google/android/libraries/youtube/creation/music/ShortsCreationSelectedTrack;
        //   732: invokestatic    aezp.k:(Ljava/lang/Object;)Laezp;
        //   735: invokevirtual   ativ.tu:(Ljava/lang/Object;)V
        //   738: return         
        //   739: aload_0        
        //   740: getfield        gwk.b:Ljava/lang/Object;
        //   743: astore          8
        //   745: aload_0        
        //   746: getfield        gwk.a:Ljava/lang/Object;
        //   749: astore          9
        //   751: aload           8
        //   753: checkcast       Lhcq;
        //   756: getfield        hcq.c:Lhci;
        //   759: aload           9
        //   761: checkcast       Landroid/net/Uri;
        //   764: invokevirtual   hci.i:(Landroid/net/Uri;)V
        //   767: return         
        //   768: aload_0        
        //   769: getfield        gwk.a:Ljava/lang/Object;
        //   772: astore          9
        //   774: aload_0        
        //   775: getfield        gwk.b:Ljava/lang/Object;
        //   778: checkcast       Luby;
        //   781: astore          8
        //   783: aload           9
        //   785: checkcast       Lhbp;
        //   788: astore          9
        //   790: aload           9
        //   792: aload           8
        //   794: putfield        hbp.g:Luby;
        //   797: aload           9
        //   799: getfield        hbp.a:Lhbb;
        //   802: aload           8
        //   804: invokevirtual   hbb.d:(Luby;)V
        //   807: aload           8
        //   809: getfield        uby.m:Larbm;
        //   812: astore          8
        //   814: aload           9
        //   816: getfield        hbp.f:Lcom/google/android/apps/youtube/app/extensions/reel/creation/shorts/camera/ShortsCameraToolbarMicButton;
        //   819: astore          9
        //   821: aload           8
        //   823: ifnull          837
        //   826: aload           8
        //   828: getfield        arbm.k:Z
        //   831: ifeq            837
        //   834: goto            839
        //   837: iconst_2       
        //   838: istore_2       
        //   839: aload           9
        //   841: iload_2        
        //   842: invokevirtual   com/google/android/apps/youtube/app/extensions/reel/creation/shorts/camera/ShortsCameraToolbarMicButton.a:(I)V
        //   845: return         
        //   846: aload_0        
        //   847: getfield        gwk.b:Ljava/lang/Object;
        //   850: astore          8
        //   852: aload_0        
        //   853: getfield        gwk.a:Ljava/lang/Object;
        //   856: checkcast       Largj;
        //   859: astore          9
        //   861: aload           9
        //   863: getfield        argj.a:I
        //   866: istore_2       
        //   867: aload           9
        //   869: getfield        argj.b:Ljava/lang/Object;
        //   872: checkcast       Larbk;
        //   875: astore          9
        //   877: aload           8
        //   879: checkcast       Lhbp;
        //   882: iload_2        
        //   883: aload           9
        //   885: invokevirtual   hbp.e:(ILarbk;)V
        //   888: return         
        //   889: aload_0        
        //   890: getfield        gwk.a:Ljava/lang/Object;
        //   893: astore          9
        //   895: aload_0        
        //   896: getfield        gwk.b:Ljava/lang/Object;
        //   899: astore          8
        //   901: aload           9
        //   903: checkcast       Lhbm;
        //   906: astore          10
        //   908: aload           10
        //   910: getfield        hbm.h:I
        //   913: istore_2       
        //   914: aload           10
        //   916: getfield        hbm.i:I
        //   919: istore_3       
        //   920: aload           10
        //   922: getfield        hbm.e:Laitg;
        //   925: astore          9
        //   927: aload           10
        //   929: getfield        hbm.f:Lahfu;
        //   932: astore          10
        //   934: aload           8
        //   936: checkcast       Lucd;
        //   939: iload_2        
        //   940: iload_3        
        //   941: aload           9
        //   943: aload           10
        //   945: invokevirtual   ucd.A:(IILaitg;Lahfu;)V
        //   948: return         
        //   949: aload_0        
        //   950: getfield        gwk.a:Ljava/lang/Object;
        //   953: astore          9
        //   955: aload_0        
        //   956: getfield        gwk.b:Ljava/lang/Object;
        //   959: checkcast       Luby;
        //   962: astore          8
        //   964: aload           9
        //   966: checkcast       Lhbg;
        //   969: astore          9
        //   971: aload           9
        //   973: aload           8
        //   975: putfield        hbg.m:Luby;
        //   978: aload           9
        //   980: getfield        hbg.t:Lhbb;
        //   983: aload           8
        //   985: invokevirtual   hbb.d:(Luby;)V
        //   988: return         
        //   989: aload_0        
        //   990: getfield        gwk.a:Ljava/lang/Object;
        //   993: astore          9
        //   995: aload_0        
        //   996: getfield        gwk.b:Ljava/lang/Object;
        //   999: astore          8
        //  1001: aload           9
        //  1003: checkcast       Lhau;
        //  1006: astore          10
        //  1008: aload           10
        //  1010: getfield        hau.i:Ljava/util/List;
        //  1013: invokeinterface java/util/List.clear:()V
        //  1018: aload           8
        //  1020: checkcast       Luby;
        //  1023: invokevirtual   uby.r:()Lafeq;
        //  1026: astore          11
        //  1028: aload           11
        //  1030: invokeinterface java/util/List.size:()I
        //  1035: istore_3       
        //  1036: iconst_0       
        //  1037: istore_2       
        //  1038: iload_2        
        //  1039: iload_3        
        //  1040: if_icmpge       1148
        //  1043: aload           11
        //  1045: iload_2        
        //  1046: invokeinterface java/util/List.get:(I)Ljava/lang/Object;
        //  1051: checkcast       Larbk;
        //  1054: astore          8
        //  1056: aload           8
        //  1058: getfield        arbk.b:I
        //  1061: sipush          1024
        //  1064: iand           
        //  1065: ifeq            1128
        //  1068: aload           8
        //  1070: getfield        arbk.m:Larbh;
        //  1073: astore          9
        //  1075: aload           9
        //  1077: astore          8
        //  1079: aload           9
        //  1081: ifnonnull       1089
        //  1084: getstatic       arbh.a:Larbh;
        //  1087: astore          8
        //  1089: aload           8
        //  1091: getfield        arbh.c:Ljava/lang/String;
        //  1094: invokestatic    android/net/Uri.parse:(Ljava/lang/String;)Landroid/net/Uri;
        //  1097: aload           8
        //  1099: getfield        arbh.e:J
        //  1102: aload           8
        //  1104: getfield        arbh.d:J
        //  1107: invokestatic    hav.a:(Landroid/net/Uri;JJ)Lhav;
        //  1110: astore          8
        //  1112: aload           10
        //  1114: getfield        hau.i:Ljava/util/List;
        //  1117: aload           8
        //  1119: invokeinterface java/util/List.add:(Ljava/lang/Object;)Z
        //  1124: pop            
        //  1125: goto            1142
        //  1128: aload           10
        //  1130: getfield        hau.i:Ljava/util/List;
        //  1133: getstatic       hav.a:Lhav;
        //  1136: invokeinterface java/util/List.add:(Ljava/lang/Object;)Z
        //  1141: pop            
        //  1142: iinc            2, 1
        //  1145: goto            1038
        //  1148: aload           10
        //  1150: getfield        hau.n:I
        //  1153: aload           10
        //  1155: getfield        hau.i:Ljava/util/List;
        //  1158: invokeinterface java/util/List.size:()I
        //  1163: if_icmplt       1173
        //  1166: aload           10
        //  1168: aconst_null    
        //  1169: iconst_0       
        //  1170: invokevirtual   hau.n:(Landroid/net/Uri;Z)V
        //  1173: aload           10
        //  1175: aload           10
        //  1177: getfield        hau.i:Ljava/util/List;
        //  1180: invokeinterface java/util/List.size:()I
        //  1185: putfield        hau.n:I
        //  1188: aload           10
        //  1190: aload           10
        //  1192: invokevirtual   hau.i:()Lhav;
        //  1195: putfield        hau.j:Lhav;
        //  1198: return         
        //  1199: aload_0        
        //  1200: getfield        gwk.a:Ljava/lang/Object;
        //  1203: astore          8
        //  1205: aload_0        
        //  1206: getfield        gwk.b:Ljava/lang/Object;
        //  1209: checkcast       Lcom/google/android/libraries/youtube/edit/filters/model/FilterMapTable$FilterDescriptor;
        //  1212: astore          9
        //  1214: aload           8
        //  1216: checkcast       Lhao;
        //  1219: astore          8
        //  1221: aload           8
        //  1223: aload           9
        //  1225: putfield        hao.g:Lcom/google/android/libraries/youtube/edit/filters/model/FilterMapTable$FilterDescriptor;
        //  1228: aload           8
        //  1230: getfield        hao.g:Lcom/google/android/libraries/youtube/edit/filters/model/FilterMapTable$FilterDescriptor;
        //  1233: astore          11
        //  1235: new             Lpvh;
        //  1238: dup            
        //  1239: aload           8
        //  1241: invokespecial   pvh.<init>:(Lhao;)V
        //  1244: astore          10
        //  1246: aload           11
        //  1248: getfield        com/google/android/libraries/youtube/edit/filters/model/FilterMapTable$FilterDescriptor.c:Ljava/util/List;
        //  1251: astore          9
        //  1253: aload           9
        //  1255: monitorenter   
        //  1256: aload           11
        //  1258: getfield        com/google/android/libraries/youtube/edit/filters/model/FilterMapTable$FilterDescriptor.b:Z
        //  1261: ifeq            1283
        //  1264: aload           11
        //  1266: getfield        com/google/android/libraries/youtube/edit/filters/model/FilterMapTable$FilterDescriptor.c:Ljava/util/List;
        //  1269: aload           10
        //  1271: invokeinterface java/util/List.add:(Ljava/lang/Object;)Z
        //  1276: pop            
        //  1277: aload           9
        //  1279: monitorexit    
        //  1280: goto            1291
        //  1283: aload           9
        //  1285: monitorexit    
        //  1286: aload           10
        //  1288: invokevirtual   pvh.E:()V
        //  1291: aload           8
        //  1293: getfield        hao.j:Lupw;
        //  1296: astore          9
        //  1298: aload           9
        //  1300: ifnull          1350
        //  1303: aload           8
        //  1305: getfield        hao.m:Lhbn;
        //  1308: ifnull          1350
        //  1311: aload           9
        //  1313: invokeinterface upw.g:()Z
        //  1318: ifeq            1340
        //  1321: aload           8
        //  1323: getfield        hao.m:Lhbn;
        //  1326: aload           8
        //  1328: getfield        hao.b:F
        //  1331: aload           8
        //  1333: getfield        hao.c:F
        //  1336: invokevirtual   hbn.a:(FF)V
        //  1339: return         
        //  1340: aload           8
        //  1342: getfield        hao.m:Lhbn;
        //  1345: fconst_0       
        //  1346: fconst_0       
        //  1347: invokevirtual   hbn.a:(FF)V
        //  1350: return         
        //  1351: astore          8
        //  1353: aload           9
        //  1355: monitorexit    
        //  1356: aload           8
        //  1358: athrow         
        //  1359: aload_0        
        //  1360: getfield        gwk.a:Ljava/lang/Object;
        //  1363: astore          9
        //  1365: aload_0        
        //  1366: getfield        gwk.b:Ljava/lang/Object;
        //  1369: astore          8
        //  1371: aload           9
        //  1373: checkcast       Lhah;
        //  1376: iconst_1       
        //  1377: putfield        hah.b:Z
        //  1380: ldc_w           147678
        //  1383: invokestatic    xaa.c:(I)Lxab;
        //  1386: astore          9
        //  1388: aload           8
        //  1390: checkcast       Laeea;
        //  1393: aload           9
        //  1395: invokevirtual   aeea.cG:(Lxab;)Ltwx;
        //  1398: invokevirtual   twx.g:()V
        //  1401: return         
        //  1402: aload_0        
        //  1403: getfield        gwk.b:Ljava/lang/Object;
        //  1406: astore          9
        //  1408: aload_0        
        //  1409: getfield        gwk.a:Ljava/lang/Object;
        //  1412: astore          8
        //  1414: aload           9
        //  1416: checkcast       Lcom/google/android/apps/youtube/app/extensions/reel/creation/shorts/edit/timeline/TimelineSeekBar;
        //  1419: astore          9
        //  1421: aload           9
        //  1423: getfield        com/google/android/apps/youtube/app/extensions/reel/creation/shorts/edit/timeline/TimelineSeekBar.a:Landroid/graphics/drawable/Drawable;
        //  1426: invokevirtual   android/graphics/drawable/Drawable.copyBounds:()Landroid/graphics/Rect;
        //  1429: astore          10
        //  1431: aload           10
        //  1433: aload           10
        //  1435: getfield        android/graphics/Rect.top:I
        //  1438: aload           9
        //  1440: getfield        com/google/android/apps/youtube/app/extensions/reel/creation/shorts/edit/timeline/TimelineSeekBar.b:I
        //  1443: isub           
        //  1444: putfield        android/graphics/Rect.top:I
        //  1447: aload           10
        //  1449: aload           10
        //  1451: getfield        android/graphics/Rect.left:I
        //  1454: aload           9
        //  1456: getfield        com/google/android/apps/youtube/app/extensions/reel/creation/shorts/edit/timeline/TimelineSeekBar.b:I
        //  1459: isub           
        //  1460: putfield        android/graphics/Rect.left:I
        //  1463: aload           10
        //  1465: aload           10
        //  1467: getfield        android/graphics/Rect.bottom:I
        //  1470: aload           9
        //  1472: getfield        com/google/android/apps/youtube/app/extensions/reel/creation/shorts/edit/timeline/TimelineSeekBar.b:I
        //  1475: iadd           
        //  1476: putfield        android/graphics/Rect.bottom:I
        //  1479: aload           10
        //  1481: aload           10
        //  1483: getfield        android/graphics/Rect.right:I
        //  1486: aload           9
        //  1488: getfield        com/google/android/apps/youtube/app/extensions/reel/creation/shorts/edit/timeline/TimelineSeekBar.b:I
        //  1491: iadd           
        //  1492: putfield        android/graphics/Rect.right:I
        //  1495: new             Landroid/view/TouchDelegate;
        //  1498: dup            
        //  1499: aload           10
        //  1501: aload           9
        //  1503: getfield        com/google/android/apps/youtube/app/extensions/reel/creation/shorts/edit/timeline/TimelineSeekBar.c:Landroid/widget/SeekBar;
        //  1506: invokespecial   android/view/TouchDelegate.<init>:(Landroid/graphics/Rect;Landroid/view/View;)V
        //  1509: astore          9
        //  1511: aload           8
        //  1513: checkcast       Landroid/view/View;
        //  1516: aload           9
        //  1518: invokevirtual   android/view/View.setTouchDelegate:(Landroid/view/TouchDelegate;)V
        //  1521: return         
        //  1522: aload_0        
        //  1523: getfield        gwk.b:Ljava/lang/Object;
        //  1526: astore          8
        //  1528: iconst_1       
        //  1529: anewarray       Landroid/view/View;
        //  1532: dup            
        //  1533: iconst_0       
        //  1534: aload_0        
        //  1535: getfield        gwk.a:Ljava/lang/Object;
        //  1538: checkcast       Landroid/view/View;
        //  1541: aastore        
        //  1542: invokestatic    gxv.d:([Landroid/view/View;)V
        //  1545: aload           8
        //  1547: checkcast       Lgya;
        //  1550: astore          8
        //  1552: aload           8
        //  1554: iconst_0       
        //  1555: putfield        gya.e:Z
        //  1558: aload           8
        //  1560: iconst_0       
        //  1561: putfield        gya.g:Z
        //  1564: return         
        //  1565: aload_0        
        //  1566: getfield        gwk.b:Ljava/lang/Object;
        //  1569: astore          8
        //  1571: iconst_1       
        //  1572: anewarray       Landroid/view/View;
        //  1575: dup            
        //  1576: iconst_0       
        //  1577: aload_0        
        //  1578: getfield        gwk.a:Ljava/lang/Object;
        //  1581: checkcast       Landroid/view/View;
        //  1584: aastore        
        //  1585: invokestatic    gxv.c:([Landroid/view/View;)V
        //  1588: aload           8
        //  1590: checkcast       Lgya;
        //  1593: astore          8
        //  1595: aload           8
        //  1597: iconst_1       
        //  1598: putfield        gya.e:Z
        //  1601: aload           8
        //  1603: iconst_0       
        //  1604: putfield        gya.f:Z
        //  1607: aload           8
        //  1609: invokestatic    java/lang/System.currentTimeMillis:()J
        //  1612: putfield        gya.h:J
        //  1615: return         
        //  1616: aload_0        
        //  1617: getfield        gwk.a:Ljava/lang/Object;
        //  1620: astore          10
        //  1622: aload_0        
        //  1623: getfield        gwk.b:Ljava/lang/Object;
        //  1626: checkcast       Lcom/google/android/libraries/youtube/creation/music/ShortsCreationSelectedTrack;
        //  1629: astore          9
        //  1631: aload           9
        //  1633: invokevirtual   com/google/android/libraries/youtube/creation/music/ShortsCreationSelectedTrack.n:()Ljava/lang/String;
        //  1636: astore          8
        //  1638: aload           10
        //  1640: checkcast       Lgxj;
        //  1643: astore          10
        //  1645: aload           8
        //  1647: aload           10
        //  1649: getfield        gxj.p:Ljava/lang/String;
        //  1652: invokevirtual   java/lang/String.equals:(Ljava/lang/Object;)Z
        //  1655: ifne            1696
        //  1658: aload           10
        //  1660: getfield        gxj.o:Lcom/google/android/libraries/youtube/edit/ui/DurationMsSeekBar;
        //  1663: iconst_1       
        //  1664: invokevirtual   com/google/android/libraries/youtube/edit/ui/DurationMsSeekBar.j:(I)V
        //  1667: aload           10
        //  1669: getfield        gxj.o:Lcom/google/android/libraries/youtube/edit/ui/DurationMsSeekBar;
        //  1672: aload           9
        //  1674: invokevirtual   com/google/android/libraries/youtube/creation/music/ShortsCreationSelectedTrack.c:()J
        //  1677: invokevirtual   com/google/android/libraries/youtube/edit/ui/DurationMsSeekBar.k:(J)V
        //  1680: aload           10
        //  1682: aload           9
        //  1684: invokevirtual   com/google/android/libraries/youtube/creation/music/ShortsCreationSelectedTrack.n:()Ljava/lang/String;
        //  1687: putfield        gxj.p:Ljava/lang/String;
        //  1690: aload           10
        //  1692: lconst_0       
        //  1693: putfield        gxj.q:J
        //  1696: aload           9
        //  1698: invokevirtual   com/google/android/libraries/youtube/creation/music/ShortsCreationSelectedTrack.f:()Laezp;
        //  1701: invokevirtual   aezp.h:()Z
        //  1704: ifeq            2052
        //  1707: aload           9
        //  1709: invokevirtual   com/google/android/libraries/youtube/creation/music/ShortsCreationSelectedTrack.f:()Laezp;
        //  1712: invokevirtual   aezp.c:()Ljava/lang/Object;
        //  1715: checkcast       Ljava/lang/Long;
        //  1718: invokevirtual   java/lang/Long.longValue:()J
        //  1721: lstore          4
        //  1723: aload           10
        //  1725: getfield        gxj.q:J
        //  1728: lload           4
        //  1730: lcmp           
        //  1731: ifeq            2039
        //  1734: aload           10
        //  1736: lload           4
        //  1738: putfield        gxj.q:J
        //  1741: aload           10
        //  1743: getfield        gxj.r:Laujg;
        //  1746: invokevirtual   aujg.bo:()I
        //  1749: i2l            
        //  1750: lload           4
        //  1752: invokestatic    java/lang/Math.min:(JJ)J
        //  1755: lstore          6
        //  1757: lload           4
        //  1759: aload           10
        //  1761: getfield        gxj.r:Laujg;
        //  1764: invokevirtual   aujg.bo:()I
        //  1767: i2l            
        //  1768: lcmp           
        //  1769: ifgt            1784
        //  1772: aload           10
        //  1774: getfield        gxj.o:Lcom/google/android/libraries/youtube/edit/ui/DurationMsSeekBar;
        //  1777: iconst_0       
        //  1778: invokevirtual   com/google/android/libraries/youtube/edit/ui/DurationMsSeekBar.j:(I)V
        //  1781: goto            2039
        //  1784: aload           10
        //  1786: getfield        gxj.r:Laujg;
        //  1789: invokevirtual   aujg.bD:()Z
        //  1792: ifeq            2010
        //  1795: aload           9
        //  1797: invokevirtual   com/google/android/libraries/youtube/creation/music/ShortsCreationSelectedTrack.g:()Laezp;
        //  1800: invokevirtual   aezp.h:()Z
        //  1803: ifeq            2010
        //  1806: aload           10
        //  1808: getfield        gxj.o:Lcom/google/android/libraries/youtube/edit/ui/DurationMsSeekBar;
        //  1811: astore          11
        //  1813: aload           9
        //  1815: invokevirtual   com/google/android/libraries/youtube/creation/music/ShortsCreationSelectedTrack.g:()Laezp;
        //  1818: invokevirtual   aezp.c:()Ljava/lang/Object;
        //  1821: checkcast       [B
        //  1824: astore          8
        //  1826: new             Ljava/io/ByteArrayInputStream;
        //  1829: astore          12
        //  1831: aload           12
        //  1833: aload           8
        //  1835: invokespecial   java/io/ByteArrayInputStream.<init>:([B)V
        //  1838: aload           12
        //  1840: invokestatic    aewd.a:(Ljava/io/InputStream;)Laewd;
        //  1843: astore          8
        //  1845: aload           8
        //  1847: getfield        aewd.a:I
        //  1850: istore_2       
        //  1851: aload           8
        //  1853: getfield        aewd.d:Ljava/lang/Object;
        //  1856: astore          14
        //  1858: aload           11
        //  1860: getfield        com/google/android/libraries/youtube/edit/ui/DurationMsSeekBar.g:Lhdo;
        //  1863: astore          13
        //  1865: aload           11
        //  1867: getfield        com/google/android/libraries/youtube/edit/ui/DurationMsSeekBar.h:F
        //  1870: fstore_1       
        //  1871: invokestatic    afeq.q:()Lafeq;
        //  1874: astore          8
        //  1876: aload           14
        //  1878: checkcast       [B
        //  1881: astore          14
        //  1883: aload           13
        //  1885: lload           4
        //  1887: lload           6
        //  1889: fload_1        
        //  1890: aload           14
        //  1892: iload_2        
        //  1893: aload           8
        //  1895: invokevirtual   hdo.f:(JJF[BILafeq;)V
        //  1898: aload           11
        //  1900: fconst_0       
        //  1901: putfield        com/google/android/libraries/youtube/edit/ui/DurationMsSeekBar.i:F
        //  1904: aload           12
        //  1906: invokevirtual   java/io/InputStream.close:()V
        //  1909: goto            1990
        //  1912: astore          8
        //  1914: goto            1919
        //  1917: astore          8
        //  1919: aload           12
        //  1921: invokevirtual   java/io/InputStream.close:()V
        //  1924: goto            1963
        //  1927: astore          12
        //  1929: ldc_w           Ljava/lang/Throwable;.class
        //  1932: ldc_w           "addSuppressed"
        //  1935: iconst_1       
        //  1936: anewarray       Ljava/lang/Class;
        //  1939: dup            
        //  1940: iconst_0       
        //  1941: ldc_w           Ljava/lang/Throwable;.class
        //  1944: aastore        
        //  1945: invokevirtual   java/lang/Class.getDeclaredMethod:(Ljava/lang/String;[Ljava/lang/Class;)Ljava/lang/reflect/Method;
        //  1948: aload           8
        //  1950: iconst_1       
        //  1951: anewarray       Ljava/lang/Object;
        //  1954: dup            
        //  1955: iconst_0       
        //  1956: aload           12
        //  1958: aastore        
        //  1959: invokevirtual   java/lang/reflect/Method.invoke:(Ljava/lang/Object;[Ljava/lang/Object;)Ljava/lang/Object;
        //  1962: pop            
        //  1963: aload           8
        //  1965: athrow         
        //  1966: astore          8
        //  1968: goto            1973
        //  1971: astore          8
        //  1973: ldc_w           "Error reading the raw waveform bytes. "
        //  1976: aload           8
        //  1978: invokestatic    ttr.d:(Ljava/lang/String;Ljava/lang/Throwable;)V
        //  1981: aload           11
        //  1983: lload           6
        //  1985: lload           4
        //  1987: invokevirtual   com/google/android/libraries/youtube/edit/ui/DurationMsSeekBar.i:(JJ)V
        //  1990: aload           10
        //  1992: getfield        gxj.t:Laeea;
        //  1995: ldc_w           115551
        //  1998: invokestatic    xaa.c:(I)Lxab;
        //  2001: invokevirtual   aeea.cG:(Lxab;)Ltwx;
        //  2004: invokevirtual   twx.h:()V
        //  2007: goto            2039
        //  2010: aload           10
        //  2012: getfield        gxj.o:Lcom/google/android/libraries/youtube/edit/ui/DurationMsSeekBar;
        //  2015: lload           6
        //  2017: lload           4
        //  2019: invokevirtual   com/google/android/libraries/youtube/edit/ui/DurationMsSeekBar.i:(JJ)V
        //  2022: aload           10
        //  2024: getfield        gxj.t:Laeea;
        //  2027: ldc_w           115552
        //  2030: invokestatic    xaa.c:(I)Lxab;
        //  2033: invokevirtual   aeea.cG:(Lxab;)Ltwx;
        //  2036: invokevirtual   twx.h:()V
        //  2039: aload           10
        //  2041: getfield        gxj.o:Lcom/google/android/libraries/youtube/edit/ui/DurationMsSeekBar;
        //  2044: aload           9
        //  2046: invokevirtual   com/google/android/libraries/youtube/creation/music/ShortsCreationSelectedTrack.c:()J
        //  2049: invokevirtual   com/google/android/libraries/youtube/edit/ui/DurationMsSeekBar.k:(J)V
        //  2052: return         
        //  2053: aload_0        
        //  2054: getfield        gwk.a:Ljava/lang/Object;
        //  2057: astore          9
        //  2059: aload_0        
        //  2060: getfield        gwk.b:Ljava/lang/Object;
        //  2063: astore          8
        //  2065: aload           9
        //  2067: checkcast       Lgww;
        //  2070: getfield        gww.bC:Lhdf;
        //  2073: astore          9
        //  2075: aload           9
        //  2077: ifnull          2090
        //  2080: aload           9
        //  2082: aload           8
        //  2084: checkcast       Luby;
        //  2087: invokevirtual   hdf.i:(Luby;)V
        //  2090: return         
        //  2091: aload_0        
        //  2092: getfield        gwk.a:Ljava/lang/Object;
        //  2095: astore          10
        //  2097: aload_0        
        //  2098: getfield        gwk.b:Ljava/lang/Object;
        //  2101: checkcast       Lupc;
        //  2104: astore          9
        //  2106: aload           9
        //  2108: getfield        upc.a:Lcom/google/research/xeno/effect/Effect;
        //  2111: astore          8
        //  2113: aload           8
        //  2115: getfield        com/google/research/xeno/effect/Effect.b:Ljava/util/Map;
        //  2118: ldc_w           "input_video_frames"
        //  2121: invokeinterface java/util/Map.containsKey:(Ljava/lang/Object;)Z
        //  2126: ifne            2145
        //  2129: aload           8
        //  2131: getfield        com/google/research/xeno/effect/Effect.b:Ljava/util/Map;
        //  2134: ldc_w           "layout_mode"
        //  2137: invokeinterface java/util/Map.containsKey:(Ljava/lang/Object;)Z
        //  2142: ifeq            2154
        //  2145: aload           10
        //  2147: checkcast       Lgww;
        //  2150: iconst_1       
        //  2151: putfield        gww.U:Z
        //  2154: aload           10
        //  2156: checkcast       Lgww;
        //  2159: astore          8
        //  2161: aload           8
        //  2163: invokevirtual   gww.q:()V
        //  2166: aload           8
        //  2168: getfield        gww.bt:Lhao;
        //  2171: astore          8
        //  2173: aload           8
        //  2175: ifnull          2287
        //  2178: aload           8
        //  2180: aload           9
        //  2182: getfield        upc.a:Lcom/google/research/xeno/effect/Effect;
        //  2185: putfield        hao.h:Lcom/google/research/xeno/effect/Effect;
        //  2188: aload           8
        //  2190: getfield        hao.h:Lcom/google/research/xeno/effect/Effect;
        //  2193: astore          9
        //  2195: aload           9
        //  2197: ifnonnull       2203
        //  2200: goto            2287
        //  2203: aload           9
        //  2205: getfield        com/google/research/xeno/effect/Effect.b:Ljava/util/Map;
        //  2208: ldc_w           "input_video_frames"
        //  2211: invokeinterface java/util/Map.get:(Ljava/lang/Object;)Ljava/lang/Object;
        //  2216: checkcast       Lcom/google/research/xeno/effect/Control;
        //  2219: astore          9
        //  2221: aload           8
        //  2223: getfield        hao.h:Lcom/google/research/xeno/effect/Effect;
        //  2226: getfield        com/google/research/xeno/effect/Effect.b:Ljava/util/Map;
        //  2229: ldc_w           "layout_mode"
        //  2232: invokeinterface java/util/Map.get:(Ljava/lang/Object;)Ljava/lang/Object;
        //  2237: checkcast       Lcom/google/research/xeno/effect/Control;
        //  2240: astore          10
        //  2242: aload           9
        //  2244: ifnull          2287
        //  2247: aload           10
        //  2249: ifnull          2287
        //  2252: aload           8
        //  2254: getfield        hao.i:Lhau;
        //  2257: astore          8
        //  2259: aload           8
        //  2261: ifnull          2287
        //  2264: aload           8
        //  2266: aload           9
        //  2268: getfield        com/google/research/xeno/effect/Control.c:Lcom/google/research/xeno/effect/Control$GpuBufferSetting;
        //  2271: iconst_0       
        //  2272: invokevirtual   hau.l:(Lcom/google/research/xeno/effect/Control$GpuBufferSetting;Z)V
        //  2275: aload           10
        //  2277: getfield        com/google/research/xeno/effect/Control.d:Lcom/google/research/xeno/effect/Control$IntSetting;
        //  2280: getfield        com/google/research/xeno/effect/Control$IntSetting.a:J
        //  2283: iconst_3       
        //  2284: invokestatic    com/google/research/xeno/effect/Control.nativeSetIntValue:(JI)V
        //  2287: return         
        //  2288: astore          12
        //  2290: goto            1963
        //    Exceptions:
        //  Try           Handler
        //  Start  End    Start  End    Type                 
        //  -----  -----  -----  -----  ---------------------
        //  1256   1280   1351   1359   Any
        //  1283   1286   1351   1359   Any
        //  1353   1356   1351   1359   Any
        //  1826   1838   1971   1973   Ljava/io/IOException;
        //  1838   1883   1917   1919   Any
        //  1883   1904   1912   1917   Any
        //  1904   1909   1966   1971   Ljava/io/IOException;
        //  1919   1924   1927   1963   Any
        //  1929   1963   2288   2293   Ljava/lang/Exception;
        //  1963   1966   1966   1971   Ljava/io/IOException;
        // 
        // The error that occurred was:
        // 
        // java.lang.IllegalStateException: Expression is linked from several locations: Label_1963:
        //     at com.strobel.decompiler.ast.Error.expressionLinkedFromMultipleLocations(Error.java:27)
        //     at com.strobel.decompiler.ast.AstOptimizer.mergeDisparateObjectInitializations(AstOptimizer.java:2604)
        //     at com.strobel.decompiler.ast.AstOptimizer.optimize(AstOptimizer.java:235)
        //     at com.strobel.decompiler.ast.AstOptimizer.optimize(AstOptimizer.java:42)
        //     at com.strobel.decompiler.languages.java.ast.AstMethodBodyBuilder.createMethodBody(AstMethodBodyBuilder.java:206)
        //     at com.strobel.decompiler.languages.java.ast.AstMethodBodyBuilder.createMethodBody(AstMethodBodyBuilder.java:93)
        //     at com.strobel.decompiler.languages.java.ast.AstBuilder.createMethodBody(AstBuilder.java:868)
        //     at com.strobel.decompiler.languages.java.ast.AstBuilder.createMethod(AstBuilder.java:761)
        //     at com.strobel.decompiler.languages.java.ast.AstBuilder.addTypeMembers(AstBuilder.java:638)
        //     at com.strobel.decompiler.languages.java.ast.AstBuilder.createTypeCore(AstBuilder.java:605)
        //     at com.strobel.decompiler.languages.java.ast.AstBuilder.createTypeNoCache(AstBuilder.java:195)
        //     at com.strobel.decompiler.languages.java.ast.AstBuilder.createType(AstBuilder.java:162)
        //     at com.strobel.decompiler.languages.java.ast.AstBuilder.addType(AstBuilder.java:137)
        //     at com.strobel.decompiler.languages.java.JavaLanguage.buildAst(JavaLanguage.java:71)
        //     at com.strobel.decompiler.languages.java.JavaLanguage.decompileType(JavaLanguage.java:59)
        //     at com.strobel.decompiler.DecompilerDriver.decompileType(DecompilerDriver.java:333)
        //     at com.strobel.decompiler.DecompilerDriver.decompileJar(DecompilerDriver.java:254)
        //     at com.strobel.decompiler.DecompilerDriver.main(DecompilerDriver.java:129)
        // 
        throw new IllegalStateException("An error occurred while decompiling this method.");
    }
}
