import java.util.concurrent.Executor;
import java.util.concurrent.atomic.AtomicInteger;
import java.util.List;
import com.google.protos.youtube.api.innertube.OfflineVideoEndpointOuterClass$OfflineVideoEndpoint;
import com.google.common.util.concurrent.ListenableFuture;
import android.net.Uri;

// 
// Decompiled by Procyon v0.6.0
// 

public final class jlw implements afty
{
    public final Object a;
    public final Object b;
    public final Object c;
    private final int d;
    
    public jlw(final adgf c, final vvh a, final String b, final int d) {
        this.d = d;
        this.c = c;
        this.a = a;
        this.b = b;
    }
    
    public jlw(final adjv a, final asjr c, final String b, final int d) {
        this.d = d;
        this.a = a;
        this.c = c;
        this.b = b;
    }
    
    public jlw(final adjv c, final String b, final Uri a, final int d) {
        this.d = d;
        this.c = c;
        this.b = b;
        this.a = a;
    }
    
    public jlw(final adnx c, final adku a, final String b, final int d) {
        this.d = d;
        this.c = c;
        this.a = a;
        this.b = b;
    }
    
    public jlw(final adod c, final String b, final adku a, final int d) {
        this.d = d;
        this.c = c;
        this.b = b;
        this.a = a;
    }
    
    public jlw(final adoe c, final String b, final adku a, final int d) {
        this.d = d;
        this.c = c;
        this.b = b;
        this.a = a;
    }
    
    public jlw(final adof c, final String b, final adku a, final int d) {
        this.d = d;
        this.c = c;
        this.b = b;
        this.a = a;
    }
    
    public jlw(final adoj c, final adku a, final String b, final int d) {
        this.d = d;
        this.c = c;
        this.a = a;
        this.b = b;
    }
    
    public jlw(final adom c, final adku a, final String b, final int d) {
        this.d = d;
        this.c = c;
        this.a = a;
        this.b = b;
    }
    
    public jlw(final adqa c, final String b, final adku a, final int d) {
        this.d = d;
        this.c = c;
        this.b = b;
        this.a = a;
    }
    
    public jlw(final ListenableFuture c, final String b, final agoe a, final int d, final byte[] array) {
        this.d = d;
        this.c = c;
        this.b = b;
        this.a = a;
    }
    
    public jlw(final ListenableFuture a, final String b, final anyc c, final int d) {
        this.d = d;
        this.a = a;
        this.b = b;
        this.c = c;
    }
    
    public jlw(final ListenableFuture c, final ouf a, final ahab b, final int d, final byte[] array, final byte[] array2) {
        this.d = d;
        this.c = c;
        this.a = a;
        this.b = b;
    }
    
    public jlw(final jtr a, final amgp c, final OfflineVideoEndpointOuterClass$OfflineVideoEndpoint b, final int d) {
        this.d = d;
        this.a = a;
        this.c = c;
        this.b = b;
    }
    
    public jlw(final jvl c, final Uri a, final admv b, final int d) {
        this.d = d;
        this.c = c;
        this.a = a;
        this.b = b;
    }
    
    public jlw(final nyw a, final ListenableFuture c, final List b, final int d) {
        this.d = d;
        this.a = a;
        this.c = c;
        this.b = b;
    }
    
    public jlw(final ohf a, final String b, final ListenableFuture c, final int d, final byte[] array, final byte[] array2) {
        this.d = d;
        this.a = a;
        this.b = b;
        this.c = c;
    }
    
    public jlw(final qdl a, final AtomicInteger c, final atyz b, final int d) {
        this.d = d;
        this.a = a;
        this.c = c;
        this.b = b;
    }
    
    public jlw(final qqk a, final aftz c, final Executor b, final int d) {
        this.d = d;
        this.a = a;
        this.c = c;
        this.b = b;
    }
    
    public jlw(final snf a, final vai c, final aqae b, final int d) {
        this.d = d;
        this.a = a;
        this.c = c;
        this.b = b;
    }
    
    public jlw(final ziy a, final Object c, final Object b, final int d, final byte[] array, final byte[] array2, final byte[] array3) {
        this.d = d;
        this.a = a;
        this.c = c;
        this.b = b;
    }
    
    public final ListenableFuture a() {
        // 
        // This method could not be decompiled.
        // 
        // Original Bytecode:
        // 
        //     1: getfield        jlw.d:I
        //     4: istore          5
        //     6: aconst_null    
        //     7: astore          12
        //     9: iconst_1       
        //    10: istore          6
        //    12: iconst_0       
        //    13: istore          4
        //    15: iconst_0       
        //    16: istore_2       
        //    17: iconst_0       
        //    18: istore_1       
        //    19: iconst_0       
        //    20: istore_3       
        //    21: iload           5
        //    23: tableswitch {
        //                0: 2963
        //                1: 2601
        //                2: 2437
        //                3: 2234
        //                4: 2137
        //                5: 2019
        //                6: 1943
        //                7: 1706
        //                8: 1625
        //                9: 1555
        //               10: 1279
        //               11: 1087
        //               12: 991
        //               13: 807
        //               14: 723
        //               15: 574
        //               16: 508
        //               17: 377
        //               18: 293
        //               19: 157
        //          default: 116
        //        }
        //   116: aload_0        
        //   117: getfield        jlw.c:Ljava/lang/Object;
        //   120: astore          11
        //   122: aload_0        
        //   123: getfield        jlw.b:Ljava/lang/Object;
        //   126: astore          13
        //   128: aload_0        
        //   129: getfield        jlw.a:Ljava/lang/Object;
        //   132: checkcast       Ladku;
        //   135: astore          12
        //   137: aload           13
        //   139: checkcast       Ljava/lang/String;
        //   142: astore          13
        //   144: aload           11
        //   146: checkcast       Ladqa;
        //   149: aload           13
        //   151: aload           12
        //   153: invokevirtual   adqa.s:(Ljava/lang/String;Ladku;)Lcom/google/common/util/concurrent/ListenableFuture;
        //   156: areturn        
        //   157: aload_0        
        //   158: getfield        jlw.c:Ljava/lang/Object;
        //   161: astore          11
        //   163: aload_0        
        //   164: getfield        jlw.a:Ljava/lang/Object;
        //   167: astore          12
        //   169: aload_0        
        //   170: getfield        jlw.b:Ljava/lang/Object;
        //   173: checkcast       Ljava/lang/String;
        //   176: astore          13
        //   178: aload           12
        //   180: checkcast       Ladku;
        //   183: aload           13
        //   185: invokevirtual   adku.b:(Ljava/lang/String;)Ladmv;
        //   188: astore          12
        //   190: aload           12
        //   192: ifnull          241
        //   195: aload           12
        //   197: getfield        admv.b:I
        //   200: iconst_2       
        //   201: iand           
        //   202: ifeq            241
        //   205: aload           12
        //   207: getfield        admv.f:Ljava/lang/String;
        //   210: invokestatic    android/net/Uri.parse:(Ljava/lang/String;)Landroid/net/Uri;
        //   213: astore          14
        //   215: aload           11
        //   217: checkcast       Ladom;
        //   220: getfield        adom.a:Landroid/content/Context;
        //   223: invokevirtual   android/content/Context.getContentResolver:()Landroid/content/ContentResolver;
        //   226: astore          13
        //   228: aload           13
        //   230: aload           14
        //   232: iconst_1       
        //   233: invokevirtual   android/content/ContentResolver.releasePersistableUriPermission:(Landroid/net/Uri;I)V
        //   236: goto            241
        //   239: astore          13
        //   241: aload           12
        //   243: ifnull          270
        //   246: aload           12
        //   248: invokestatic    adkp.l:(Ladmv;)Z
        //   251: ifeq            270
        //   254: new             Ladkw;
        //   257: dup            
        //   258: iconst_0       
        //   259: invokespecial   adkw.<init>:(I)V
        //   262: invokestatic    afwm.m:(Ljava/lang/Object;)Lcom/google/common/util/concurrent/ListenableFuture;
        //   265: astore          11
        //   267: goto            290
        //   270: new             Ladok;
        //   273: dup            
        //   274: aload           11
        //   276: checkcast       Ladom;
        //   279: getfield        adom.b:Ladlp;
        //   282: invokespecial   adok.<init>:(Ladlp;)V
        //   285: invokestatic    afwm.m:(Ljava/lang/Object;)Lcom/google/common/util/concurrent/ListenableFuture;
        //   288: astore          11
        //   290: aload           11
        //   292: areturn        
        //   293: aload_0        
        //   294: getfield        jlw.c:Ljava/lang/Object;
        //   297: astore          11
        //   299: aload_0        
        //   300: getfield        jlw.a:Ljava/lang/Object;
        //   303: astore          12
        //   305: aload_0        
        //   306: getfield        jlw.b:Ljava/lang/Object;
        //   309: astore          13
        //   311: aload           13
        //   313: checkcast       Ljava/lang/String;
        //   316: astore          13
        //   318: aload           12
        //   320: checkcast       Ladku;
        //   323: aload           13
        //   325: invokevirtual   adku.b:(Ljava/lang/String;)Ladmv;
        //   328: astore          12
        //   330: aload           12
        //   332: ifnonnull       349
        //   335: getstatic       aphv.s:Laphv;
        //   338: invokestatic    adkn.a:(Laphv;)Ladkn;
        //   341: invokestatic    afwm.l:(Ljava/lang/Throwable;)Lcom/google/common/util/concurrent/ListenableFuture;
        //   344: astore          11
        //   346: goto            374
        //   349: aload           11
        //   351: checkcast       Ladoj;
        //   354: aload           12
        //   356: iconst_0       
        //   357: invokevirtual   adoj.s:(Ladmv;Z)Lcom/google/common/util/concurrent/ListenableFuture;
        //   360: astore          11
        //   362: goto            374
        //   365: astore          11
        //   367: aload           11
        //   369: invokestatic    afwm.l:(Ljava/lang/Throwable;)Lcom/google/common/util/concurrent/ListenableFuture;
        //   372: astore          11
        //   374: aload           11
        //   376: areturn        
        //   377: aload_0        
        //   378: getfield        jlw.c:Ljava/lang/Object;
        //   381: astore          11
        //   383: aload_0        
        //   384: getfield        jlw.b:Ljava/lang/Object;
        //   387: astore          13
        //   389: aload_0        
        //   390: getfield        jlw.a:Ljava/lang/Object;
        //   393: checkcast       Ladku;
        //   396: astore          12
        //   398: aload           13
        //   400: checkcast       Ljava/lang/String;
        //   403: astore          13
        //   405: aload           11
        //   407: checkcast       Ladoe;
        //   410: aload           13
        //   412: aload           12
        //   414: iconst_0       
        //   415: invokevirtual   adoe.o:(Ljava/lang/String;Ladku;Z)Ladmv;
        //   418: astore          12
        //   420: aload           11
        //   422: checkcast       Ladof;
        //   425: astore          14
        //   427: aload           14
        //   429: getfield        adof.a:Ladfq;
        //   432: aload           12
        //   434: getfield        admv.e:Ljava/lang/String;
        //   437: invokevirtual   adfq.b:(Ljava/lang/String;)Lvwo;
        //   440: astore          13
        //   442: aload           13
        //   444: invokevirtual   vkk.i:()V
        //   447: aload           13
        //   449: aload           12
        //   451: getfield        admv.ac:Ljava/lang/String;
        //   454: putfield        vwo.a:Ljava/lang/String;
        //   457: aload           14
        //   459: getfield        adof.a:Ladfq;
        //   462: aload           13
        //   464: invokevirtual   adfq.e:(Lvwo;)Lalds;
        //   467: getfield        alds.c:Z
        //   470: ifeq            498
        //   473: aload           14
        //   475: getfield        adof.e:Ladet;
        //   478: invokevirtual   adet.s:()Ladms;
        //   481: astore          12
        //   483: aload           11
        //   485: checkcast       Ladps;
        //   488: aload           12
        //   490: iconst_0       
        //   491: invokevirtual   adps.t:(Ladms;Z)Ladkx;
        //   494: invokestatic    afwm.m:(Ljava/lang/Object;)Lcom/google/common/util/concurrent/ListenableFuture;
        //   497: areturn        
        //   498: new             Lvmr;
        //   501: dup            
        //   502: ldc             "Video deletion failed"
        //   504: invokespecial   vmr.<init>:(Ljava/lang/String;)V
        //   507: athrow         
        //   508: aload_0        
        //   509: getfield        jlw.c:Ljava/lang/Object;
        //   512: astore          13
        //   514: aload_0        
        //   515: getfield        jlw.b:Ljava/lang/Object;
        //   518: astore          12
        //   520: aload_0        
        //   521: getfield        jlw.a:Ljava/lang/Object;
        //   524: checkcast       Ladku;
        //   527: astore          11
        //   529: aload           12
        //   531: checkcast       Ljava/lang/String;
        //   534: astore          12
        //   536: aload           13
        //   538: checkcast       Ladoe;
        //   541: astore          14
        //   543: aload           14
        //   545: aload           12
        //   547: aload           11
        //   549: iconst_1       
        //   550: invokevirtual   adoe.o:(Ljava/lang/String;Ladku;Z)Ladmv;
        //   553: astore          13
        //   555: aload           14
        //   557: aload           13
        //   559: invokevirtual   adoe.q:(Ladmv;)V
        //   562: aload           14
        //   564: aload           12
        //   566: aload           11
        //   568: aload           13
        //   570: invokevirtual   adoe.d:(Ljava/lang/String;Ladku;Ladmv;)Lcom/google/common/util/concurrent/ListenableFuture;
        //   573: areturn        
        //   574: aload_0        
        //   575: getfield        jlw.c:Ljava/lang/Object;
        //   578: astore          11
        //   580: aload_0        
        //   581: getfield        jlw.b:Ljava/lang/Object;
        //   584: astore          13
        //   586: aload_0        
        //   587: getfield        jlw.a:Ljava/lang/Object;
        //   590: checkcast       Ladku;
        //   593: astore          12
        //   595: aload           13
        //   597: checkcast       Ljava/lang/String;
        //   600: astore          13
        //   602: aload           11
        //   604: checkcast       Ladoe;
        //   607: aload           13
        //   609: aload           12
        //   611: iconst_0       
        //   612: invokevirtual   adoe.o:(Ljava/lang/String;Ladku;Z)Ladmv;
        //   615: astore          12
        //   617: aload           12
        //   619: getfield        admv.c:I
        //   622: ldc             2097152
        //   624: iand           
        //   625: ifeq            716
        //   628: aload           11
        //   630: checkcast       Ladod;
        //   633: astore          14
        //   635: aload           14
        //   637: getfield        adod.a:Ladfq;
        //   640: aload           12
        //   642: getfield        admv.e:Ljava/lang/String;
        //   645: invokevirtual   adfq.b:(Ljava/lang/String;)Lvwo;
        //   648: astore          13
        //   650: aload           13
        //   652: invokevirtual   vkk.i:()V
        //   655: aload           13
        //   657: aload           12
        //   659: getfield        admv.ac:Ljava/lang/String;
        //   662: putfield        vwo.a:Ljava/lang/String;
        //   665: aload           14
        //   667: getfield        adod.a:Ladfq;
        //   670: aload           13
        //   672: invokevirtual   adfq.e:(Lvwo;)Lalds;
        //   675: getfield        alds.c:Z
        //   678: ifeq            706
        //   681: aload           14
        //   683: getfield        adod.e:Ladet;
        //   686: invokevirtual   adet.s:()Ladms;
        //   689: astore          12
        //   691: aload           11
        //   693: checkcast       Ladps;
        //   696: aload           12
        //   698: iconst_0       
        //   699: invokevirtual   adps.t:(Ladms;Z)Ladkx;
        //   702: invokestatic    afwm.m:(Ljava/lang/Object;)Lcom/google/common/util/concurrent/ListenableFuture;
        //   705: areturn        
        //   706: new             Lvmr;
        //   709: dup            
        //   710: ldc             "Video deletion failed"
        //   712: invokespecial   vmr.<init>:(Ljava/lang/String;)V
        //   715: athrow         
        //   716: getstatic       aphv.t:Laphv;
        //   719: invokestatic    adkn.a:(Laphv;)Ladkn;
        //   722: athrow         
        //   723: aload_0        
        //   724: getfield        jlw.c:Ljava/lang/Object;
        //   727: astore          11
        //   729: aload_0        
        //   730: getfield        jlw.a:Ljava/lang/Object;
        //   733: astore          12
        //   735: aload_0        
        //   736: getfield        jlw.b:Ljava/lang/Object;
        //   739: astore          13
        //   741: aload           13
        //   743: checkcast       Ljava/lang/String;
        //   746: astore          13
        //   748: aload           12
        //   750: checkcast       Ladku;
        //   753: aload           13
        //   755: invokevirtual   adku.b:(Ljava/lang/String;)Ladmv;
        //   758: astore          12
        //   760: aload           12
        //   762: ifnonnull       779
        //   765: getstatic       aphv.s:Laphv;
        //   768: invokestatic    adkn.a:(Laphv;)Ladkn;
        //   771: invokestatic    afwm.l:(Ljava/lang/Throwable;)Lcom/google/common/util/concurrent/ListenableFuture;
        //   774: astore          11
        //   776: goto            804
        //   779: aload           11
        //   781: checkcast       Ladnx;
        //   784: aload           12
        //   786: iconst_0       
        //   787: invokevirtual   adnx.c:(Ladmv;Z)Lcom/google/common/util/concurrent/ListenableFuture;
        //   790: astore          11
        //   792: goto            804
        //   795: astore          11
        //   797: aload           11
        //   799: invokestatic    afwm.l:(Ljava/lang/Throwable;)Lcom/google/common/util/concurrent/ListenableFuture;
        //   802: astore          11
        //   804: aload           11
        //   806: areturn        
        //   807: aload_0        
        //   808: getfield        jlw.c:Ljava/lang/Object;
        //   811: astore          13
        //   813: aload_0        
        //   814: getfield        jlw.b:Ljava/lang/Object;
        //   817: astore          14
        //   819: aload_0        
        //   820: getfield        jlw.a:Ljava/lang/Object;
        //   823: astore          11
        //   825: aload           13
        //   827: checkcast       Ladjv;
        //   830: astore          13
        //   832: aload           13
        //   834: getfield        adjv.g:Ladku;
        //   837: astore          15
        //   839: aload           14
        //   841: checkcast       Ljava/lang/String;
        //   844: astore          14
        //   846: aload           15
        //   848: aload           14
        //   850: invokevirtual   adku.b:(Ljava/lang/String;)Ladmv;
        //   853: astore          15
        //   855: aload           15
        //   857: invokevirtual   java/lang/Object.getClass:()Ljava/lang/Class;
        //   860: pop            
        //   861: aload           11
        //   863: invokevirtual   java/lang/Object.getClass:()Ljava/lang/Class;
        //   866: pop            
        //   867: aload           15
        //   869: getfield        admv.b:I
        //   872: iconst_4       
        //   873: iand           
        //   874: ifeq            880
        //   877: goto            883
        //   880: iconst_0       
        //   881: istore          6
        //   883: iload           6
        //   885: ifeq            936
        //   888: aload           15
        //   890: getfield        admv.g:Ljava/lang/String;
        //   893: aload           11
        //   895: checkcast       Landroid/net/Uri;
        //   898: invokevirtual   android/net/Uri.toString:()Ljava/lang/String;
        //   901: invokevirtual   java/lang/String.equals:(Ljava/lang/Object;)Z
        //   904: ifne            910
        //   907: goto            936
        //   910: aload           12
        //   912: astore          11
        //   914: aload           15
        //   916: getfield        admv.aj:Z
        //   919: ifeq            966
        //   922: aload           13
        //   924: aload           14
        //   926: invokevirtual   adjv.L:(Ljava/lang/String;)V
        //   929: aload           12
        //   931: astore          11
        //   933: goto            966
        //   936: aload           13
        //   938: getfield        adjv.g:Ladku;
        //   941: aload           14
        //   943: new             Ladjo;
        //   946: dup            
        //   947: aload           13
        //   949: aload           11
        //   951: checkcast       Landroid/net/Uri;
        //   954: iload           6
        //   956: aload           14
        //   958: invokespecial   adjo.<init>:(Ladjv;Landroid/net/Uri;ZLjava/lang/String;)V
        //   961: invokevirtual   adku.a:(Ljava/lang/String;Ladkx;)Ladlq;
        //   964: astore          11
        //   966: new             Landroid/util/Pair;
        //   969: dup            
        //   970: aload           13
        //   972: aload           15
        //   974: aload           11
        //   976: invokevirtual   adjv.b:(Ladmv;Ladlq;)Ladjz;
        //   979: aload           11
        //   981: invokestatic    aezp.j:(Ljava/lang/Object;)Laezp;
        //   984: invokespecial   android/util/Pair.<init>:(Ljava/lang/Object;Ljava/lang/Object;)V
        //   987: invokestatic    afwm.m:(Ljava/lang/Object;)Lcom/google/common/util/concurrent/ListenableFuture;
        //   990: areturn        
        //   991: aload_0        
        //   992: getfield        jlw.a:Ljava/lang/Object;
        //   995: astore          12
        //   997: aload_0        
        //   998: getfield        jlw.c:Ljava/lang/Object;
        //  1001: astore          11
        //  1003: aload_0        
        //  1004: getfield        jlw.b:Ljava/lang/Object;
        //  1007: astore          13
        //  1009: aload           11
        //  1011: invokevirtual   java/lang/Object.getClass:()Ljava/lang/Class;
        //  1014: pop            
        //  1015: aload           12
        //  1017: checkcast       Ladjv;
        //  1020: astore          12
        //  1022: aload           12
        //  1024: getfield        adjv.g:Ladku;
        //  1027: astore          14
        //  1029: aload           13
        //  1031: checkcast       Ljava/lang/String;
        //  1034: astore          13
        //  1036: aload           14
        //  1038: aload           13
        //  1040: invokevirtual   adku.b:(Ljava/lang/String;)Ladmv;
        //  1043: astore          14
        //  1045: aload           14
        //  1047: invokevirtual   java/lang/Object.getClass:()Ljava/lang/Class;
        //  1050: pop            
        //  1051: aload           12
        //  1053: aload           14
        //  1055: aload           12
        //  1057: getfield        adjv.g:Ladku;
        //  1060: aload           13
        //  1062: new             Ladjm;
        //  1065: dup            
        //  1066: aload           14
        //  1068: aload           11
        //  1070: iconst_2       
        //  1071: invokespecial   adjm.<init>:(Ladmv;Lasjr;I)V
        //  1074: invokevirtual   adku.a:(Ljava/lang/String;Ladkx;)Ladlq;
        //  1077: invokevirtual   adjv.b:(Ladmv;Ladlq;)Ladjz;
        //  1080: invokestatic    aezp.k:(Ljava/lang/Object;)Laezp;
        //  1083: invokestatic    afwm.m:(Ljava/lang/Object;)Lcom/google/common/util/concurrent/ListenableFuture;
        //  1086: areturn        
        //  1087: aload_0        
        //  1088: getfield        jlw.c:Ljava/lang/Object;
        //  1091: astore          15
        //  1093: aload_0        
        //  1094: getfield        jlw.a:Ljava/lang/Object;
        //  1097: astore          13
        //  1099: aload_0        
        //  1100: getfield        jlw.b:Ljava/lang/Object;
        //  1103: astore          12
        //  1105: aload           15
        //  1107: checkcast       Ladgf;
        //  1110: astore          11
        //  1112: aload           11
        //  1114: getfield        adgf.e:Ljava/util/concurrent/Semaphore;
        //  1117: astore          14
        //  1119: aload           14
        //  1121: ifnull          1154
        //  1124: aload           14
        //  1126: invokevirtual   java/util/concurrent/Semaphore.availablePermits:()I
        //  1129: pop            
        //  1130: aload           15
        //  1132: checkcast       Ladgf;
        //  1135: getfield        adgf.e:Ljava/util/concurrent/Semaphore;
        //  1138: invokevirtual   java/util/concurrent/Semaphore.acquire:()V
        //  1141: goto            1154
        //  1144: astore          11
        //  1146: invokestatic    afwm.k:()Lcom/google/common/util/concurrent/ListenableFuture;
        //  1149: astore          11
        //  1151: goto            1276
        //  1154: aload           11
        //  1156: getfield        adgf.b:Loby;
        //  1159: invokeinterface oby.d:()J
        //  1164: l2i            
        //  1165: istore_1       
        //  1166: aload           11
        //  1168: getfield        adgf.g:Ladfq;
        //  1171: astore          14
        //  1173: aload           11
        //  1175: getfield        adgf.a:Ljava/util/concurrent/Executor;
        //  1178: astore          15
        //  1180: aload           14
        //  1182: getfield        adfq.d:Ljava/lang/Object;
        //  1185: checkcast       Lvml;
        //  1188: aload           13
        //  1190: checkcast       Lvls;
        //  1193: aload           15
        //  1195: invokevirtual   vml.b:(Lvls;Ljava/util/concurrent/Executor;)Lcom/google/common/util/concurrent/ListenableFuture;
        //  1198: astore          14
        //  1200: aload           14
        //  1202: new             Ladap;
        //  1205: dup            
        //  1206: aload           11
        //  1208: bipush          6
        //  1210: invokespecial   adap.<init>:(Ladgf;I)V
        //  1213: getstatic       afum.a:Lafum;
        //  1216: invokeinterface com/google/common/util/concurrent/ListenableFuture.addListener:(Ljava/lang/Runnable;Ljava/util/concurrent/Executor;)V
        //  1221: aload           11
        //  1223: getfield        adgf.b:Loby;
        //  1226: astore          15
        //  1228: aload           11
        //  1230: getfield        adgf.c:Ljava/util/List;
        //  1233: astore          13
        //  1235: aload           14
        //  1237: new             Labkr;
        //  1240: dup            
        //  1241: new             Ladge;
        //  1244: dup            
        //  1245: aload           12
        //  1247: checkcast       Ljava/lang/String;
        //  1250: aload           15
        //  1252: iload_1        
        //  1253: aload           13
        //  1255: invokespecial   adge.<init>:(Ljava/lang/String;Loby;ILjava/util/List;)V
        //  1258: bipush          14
        //  1260: invokespecial   abkr.<init>:(Ladge;I)V
        //  1263: aload           11
        //  1265: getfield        adgf.a:Ljava/util/concurrent/Executor;
        //  1268: invokestatic    aftq.e:(Lcom/google/common/util/concurrent/ListenableFuture;Laezf;Ljava/util/concurrent/Executor;)Lcom/google/common/util/concurrent/ListenableFuture;
        //  1271: invokestatic    afwm.n:(Lcom/google/common/util/concurrent/ListenableFuture;)Lcom/google/common/util/concurrent/ListenableFuture;
        //  1274: astore          11
        //  1276: aload           11
        //  1278: areturn        
        //  1279: aload_0        
        //  1280: getfield        jlw.a:Ljava/lang/Object;
        //  1283: astore          11
        //  1285: aload_0        
        //  1286: getfield        jlw.c:Ljava/lang/Object;
        //  1289: astore          13
        //  1291: aload_0        
        //  1292: getfield        jlw.b:Ljava/lang/Object;
        //  1295: astore          14
        //  1297: new             Ladem;
        //  1300: dup            
        //  1301: invokespecial   adem.<init>:()V
        //  1304: astore          12
        //  1306: aload           12
        //  1308: aload           14
        //  1310: putfield        adem.a:Ljava/lang/Object;
        //  1313: aload           12
        //  1315: iconst_1       
        //  1316: putfield        adem.c:I
        //  1319: aload           11
        //  1321: checkcast       Lziy;
        //  1324: astore          11
        //  1326: aload           11
        //  1328: getfield        ziy.e:Ljava/lang/Object;
        //  1331: checkcast       Ladek;
        //  1334: getfield        adek.a:Lxra;
        //  1337: getfield        xra.a:Ljava/lang/Object;
        //  1340: invokeinterface oby.c:()J
        //  1345: ldc2_w          3600000
        //  1348: ladd           
        //  1349: lstore          7
        //  1351: lload           7
        //  1353: lconst_0       
        //  1354: lcmp           
        //  1355: ifle            1410
        //  1358: aload           11
        //  1360: getfield        ziy.a:Ljava/lang/Object;
        //  1363: invokeinterface oby.d:()J
        //  1368: lload           7
        //  1370: aload           11
        //  1372: getfield        ziy.a:Ljava/lang/Object;
        //  1375: invokeinterface oby.c:()J
        //  1380: lsub           
        //  1381: ladd           
        //  1382: lstore          9
        //  1384: lload           9
        //  1386: lstore          7
        //  1388: lload           9
        //  1390: lconst_0       
        //  1391: lcmp           
        //  1392: ifgt            1400
        //  1395: ldc2_w          -1
        //  1398: lstore          7
        //  1400: aload           12
        //  1402: lload           7
        //  1404: putfield        adem.b:J
        //  1407: goto            1417
        //  1410: aload           12
        //  1412: lload           7
        //  1414: putfield        adem.b:J
        //  1417: aload           11
        //  1419: getfield        ziy.d:Ljava/lang/Object;
        //  1422: checkcast       Labn;
        //  1425: aload           13
        //  1427: aload           12
        //  1429: invokevirtual   abn.d:(Ljava/lang/Object;Ljava/lang/Object;)Ljava/lang/Object;
        //  1432: pop            
        //  1433: aload           11
        //  1435: getfield        ziy.b:Ljava/lang/Object;
        //  1438: astore          13
        //  1440: aload           12
        //  1442: getfield        adem.c:I
        //  1445: istore_1       
        //  1446: aload           13
        //  1448: checkcast       Ljava/util/concurrent/atomic/AtomicInteger;
        //  1451: iload_1        
        //  1452: invokevirtual   java/util/concurrent/atomic/AtomicInteger.addAndGet:(I)I
        //  1455: pop            
        //  1456: aload           11
        //  1458: getfield        ziy.b:Ljava/lang/Object;
        //  1461: checkcast       Ljava/util/concurrent/atomic/AtomicInteger;
        //  1464: invokevirtual   java/util/concurrent/atomic/AtomicInteger.get:()I
        //  1467: bipush          50
        //  1469: if_icmple       1550
        //  1472: aload           11
        //  1474: getfield        ziy.d:Ljava/lang/Object;
        //  1477: checkcast       Labn;
        //  1480: invokevirtual   abn.e:()Ljava/util/Map;
        //  1483: invokeinterface java/util/Map.keySet:()Ljava/util/Set;
        //  1488: invokeinterface java/util/Set.iterator:()Ljava/util/Iterator;
        //  1493: astore          12
        //  1495: aload           11
        //  1497: getfield        ziy.b:Ljava/lang/Object;
        //  1500: checkcast       Ljava/util/concurrent/atomic/AtomicInteger;
        //  1503: invokevirtual   java/util/concurrent/atomic/AtomicInteger.get:()I
        //  1506: bipush          50
        //  1508: if_icmple       1550
        //  1511: aload           12
        //  1513: invokeinterface java/util/Iterator.hasNext:()Z
        //  1518: ifeq            1495
        //  1521: aload           11
        //  1523: getfield        ziy.d:Ljava/lang/Object;
        //  1526: astore          13
        //  1528: aload           12
        //  1530: invokeinterface java/util/Iterator.next:()Ljava/lang/Object;
        //  1535: astore          14
        //  1537: aload           13
        //  1539: checkcast       Labn;
        //  1542: aload           14
        //  1544: invokevirtual   abn.i:(Ljava/lang/Object;)V
        //  1547: goto            1495
        //  1550: aconst_null    
        //  1551: invokestatic    afwm.m:(Ljava/lang/Object;)Lcom/google/common/util/concurrent/ListenableFuture;
        //  1554: areturn        
        //  1555: aload_0        
        //  1556: getfield        jlw.a:Ljava/lang/Object;
        //  1559: astore          11
        //  1561: aload_0        
        //  1562: getfield        jlw.c:Ljava/lang/Object;
        //  1565: astore          12
        //  1567: aload_0        
        //  1568: getfield        jlw.b:Ljava/lang/Object;
        //  1571: astore          13
        //  1573: aload           11
        //  1575: aload           12
        //  1577: checkcast       Lvai;
        //  1580: ldc2_w          45366285
        //  1583: invokevirtual   vai.f:(J)Z
        //  1586: invokeinterface snf.b:(Z)Lasht;
        //  1591: invokevirtual   asht.aM:()Ljava/lang/Object;
        //  1594: checkcast       Ljava/util/function/Function;
        //  1597: aload           13
        //  1599: invokeinterface java/util/function/Function.apply:(Ljava/lang/Object;)Ljava/lang/Object;
        //  1604: checkcast       Lsne;
        //  1607: getfield        sne.a:Lcom/google/android/libraries/blocks/Container;
        //  1610: new             Laewo;
        //  1613: dup            
        //  1614: iconst_3       
        //  1615: invokespecial   aewo.<init>:(I)V
        //  1618: invokevirtual   com/google/android/libraries/blocks/Container.d:(Lobo;)Lobq;
        //  1621: invokestatic    afwm.m:(Ljava/lang/Object;)Lcom/google/common/util/concurrent/ListenableFuture;
        //  1624: areturn        
        //  1625: aload_0        
        //  1626: getfield        jlw.c:Ljava/lang/Object;
        //  1629: astore          12
        //  1631: aload_0        
        //  1632: getfield        jlw.a:Ljava/lang/Object;
        //  1635: astore          11
        //  1637: aload_0        
        //  1638: getfield        jlw.b:Ljava/lang/Object;
        //  1641: astore          13
        //  1643: aload           12
        //  1645: invokestatic    afwm.u:(Ljava/util/concurrent/Future;)Ljava/lang/Object;
        //  1648: checkcast       [B
        //  1651: astore          12
        //  1653: aload           13
        //  1655: checkcast       Lahab;
        //  1658: invokevirtual   ahab.I:()[B
        //  1661: astore          13
        //  1663: aload           11
        //  1665: checkcast       Louf;
        //  1668: aload           13
        //  1670: aload           12
        //  1672: invokevirtual   ouf.c:([B[B)Lio/grpc/Status;
        //  1675: astore          11
        //  1677: aload           11
        //  1679: invokevirtual   io/grpc/Status.f:()Z
        //  1682: ifne            1698
        //  1685: aload           11
        //  1687: invokevirtual   io/grpc/Status.asException:()Lio/grpc/StatusException;
        //  1690: invokestatic    afwm.l:(Ljava/lang/Throwable;)Lcom/google/common/util/concurrent/ListenableFuture;
        //  1693: astore          11
        //  1695: goto            1703
        //  1698: getstatic       afvn.a:Lcom/google/common/util/concurrent/ListenableFuture;
        //  1701: astore          11
        //  1703: aload           11
        //  1705: areturn        
        //  1706: aload_0        
        //  1707: getfield        jlw.a:Ljava/lang/Object;
        //  1710: astore          13
        //  1712: aload_0        
        //  1713: getfield        jlw.c:Ljava/lang/Object;
        //  1716: astore          15
        //  1718: aload_0        
        //  1719: getfield        jlw.b:Ljava/lang/Object;
        //  1722: astore          14
        //  1724: aload           13
        //  1726: checkcast       Lqqk;
        //  1729: astore          11
        //  1731: aload           11
        //  1733: getfield        qqk.b:Lcom/google/common/util/concurrent/ListenableFuture;
        //  1736: invokestatic    afwm.u:(Ljava/util/concurrent/Future;)Ljava/lang/Object;
        //  1739: checkcast       Landroid/net/Uri;
        //  1742: astore          16
        //  1744: aload           11
        //  1746: getfield        qqk.q:Leg;
        //  1749: aload           16
        //  1751: invokestatic    qpa.b:()Lqpa;
        //  1754: invokevirtual   eg.ag:(Landroid/net/Uri;Lqnx;)Ljava/lang/Object;
        //  1757: checkcast       Ljava/io/Closeable;
        //  1760: invokestatic    qol.a:(Ljava/io/Closeable;)Lqol;
        //  1763: astore          12
        //  1765: aload           13
        //  1767: checkcast       Lqqk;
        //  1770: aload           16
        //  1772: invokevirtual   qqk.f:(Landroid/net/Uri;)Ljava/lang/Object;
        //  1775: invokestatic    afwm.m:(Ljava/lang/Object;)Lcom/google/common/util/concurrent/ListenableFuture;
        //  1778: astore          11
        //  1780: goto            1853
        //  1783: astore          11
        //  1785: goto            1923
        //  1788: astore          11
        //  1790: aload           13
        //  1792: checkcast       Lqqk;
        //  1795: getfield        qqk.f:Lqpq;
        //  1798: astore          17
        //  1800: aload           13
        //  1802: checkcast       Lqqk;
        //  1805: aload           11
        //  1807: aload           17
        //  1809: invokevirtual   qqk.c:(Ljava/io/IOException;Lqpq;)Lcom/google/common/util/concurrent/ListenableFuture;
        //  1812: astore          11
        //  1814: new             Lphy;
        //  1817: astore          17
        //  1819: aload           17
        //  1821: aload           13
        //  1823: checkcast       Lqqk;
        //  1826: aload           16
        //  1828: bipush          18
        //  1830: invokespecial   phy.<init>:(Lqqk;Landroid/net/Uri;I)V
        //  1833: aload           11
        //  1835: aload           17
        //  1837: invokestatic    aeun.d:(Laftz;)Laftz;
        //  1840: aload           13
        //  1842: checkcast       Lqqk;
        //  1845: getfield        qqk.c:Ljava/util/concurrent/Executor;
        //  1848: invokestatic    aftq.f:(Lcom/google/common/util/concurrent/ListenableFuture;Laftz;Ljava/util/concurrent/Executor;)Lcom/google/common/util/concurrent/ListenableFuture;
        //  1851: astore          11
        //  1853: aload           11
        //  1855: aload           15
        //  1857: aload           14
        //  1859: invokestatic    aftq.f:(Lcom/google/common/util/concurrent/ListenableFuture;Laftz;Ljava/util/concurrent/Executor;)Lcom/google/common/util/concurrent/ListenableFuture;
        //  1862: astore          14
        //  1864: new             Lqqg;
        //  1867: astore          15
        //  1869: aload           15
        //  1871: aload           13
        //  1873: checkcast       Lqqk;
        //  1876: aload           11
        //  1878: aload           14
        //  1880: iconst_0       
        //  1881: invokespecial   qqg.<init>:(Lqqk;Lcom/google/common/util/concurrent/ListenableFuture;Lcom/google/common/util/concurrent/ListenableFuture;I)V
        //  1884: aload           14
        //  1886: aload           15
        //  1888: invokestatic    aeun.d:(Laftz;)Laftz;
        //  1891: getstatic       afum.a:Lafum;
        //  1894: invokestatic    aftq.f:(Lcom/google/common/util/concurrent/ListenableFuture;Laftz;Ljava/util/concurrent/Executor;)Lcom/google/common/util/concurrent/ListenableFuture;
        //  1897: aload           12
        //  1899: invokevirtual   qol.b:()Ljava/io/Closeable;
        //  1902: aload           13
        //  1904: checkcast       Lqqk;
        //  1907: getfield        qqk.c:Ljava/util/concurrent/Executor;
        //  1910: invokestatic    qqk.b:(Lcom/google/common/util/concurrent/ListenableFuture;Ljava/io/Closeable;Ljava/util/concurrent/Executor;)Lcom/google/common/util/concurrent/ListenableFuture;
        //  1913: astore          11
        //  1915: aload           12
        //  1917: invokevirtual   qol.close:()V
        //  1920: aload           11
        //  1922: areturn        
        //  1923: aload           12
        //  1925: invokevirtual   qol.close:()V
        //  1928: goto            1940
        //  1931: astore          12
        //  1933: aload           11
        //  1935: aload           12
        //  1937: invokestatic    qua.b:(Ljava/lang/Throwable;Ljava/lang/Throwable;)V
        //  1940: aload           11
        //  1942: athrow         
        //  1943: aload_0        
        //  1944: getfield        jlw.a:Ljava/lang/Object;
        //  1947: astore          12
        //  1949: aload_0        
        //  1950: getfield        jlw.c:Ljava/lang/Object;
        //  1953: astore          13
        //  1955: aload_0        
        //  1956: getfield        jlw.b:Ljava/lang/Object;
        //  1959: astore          11
        //  1961: aload           13
        //  1963: checkcast       Ljava/util/concurrent/atomic/AtomicInteger;
        //  1966: invokevirtual   java/util/concurrent/atomic/AtomicInteger.getAndDecrement:()I
        //  1969: ifgt            1980
        //  1972: getstatic       afvn.a:Lcom/google/common/util/concurrent/ListenableFuture;
        //  1975: astore          11
        //  1977: goto            2016
        //  1980: aload           12
        //  1982: checkcast       Lqdl;
        //  1985: astore          13
        //  1987: aload           13
        //  1989: getfield        qdl.c:Larkg;
        //  1992: invokeinterface arkg.a:()Ljava/lang/Object;
        //  1997: checkcast       Lqdi;
        //  2000: astore          12
        //  2002: aload           13
        //  2004: aload           11
        //  2006: checkcast       Latyz;
        //  2009: aload           12
        //  2011: invokevirtual   qdl.f:(Latyz;Lqdi;)Lcom/google/common/util/concurrent/ListenableFuture;
        //  2014: astore          11
        //  2016: aload           11
        //  2018: areturn        
        //  2019: aload_0        
        //  2020: getfield        jlw.a:Ljava/lang/Object;
        //  2023: astore          14
        //  2025: aload_0        
        //  2026: getfield        jlw.b:Ljava/lang/Object;
        //  2029: astore          11
        //  2031: aload_0        
        //  2032: getfield        jlw.c:Ljava/lang/Object;
        //  2035: astore          13
        //  2037: aload           14
        //  2039: checkcast       Lohf;
        //  2042: getfield        ohf.d:Ljava/lang/Object;
        //  2045: astore          12
        //  2047: aload           14
        //  2049: checkcast       Lohf;
        //  2052: getfield        ohf.c:Ljava/lang/Object;
        //  2055: invokeinterface java/util/Map.size:()I
        //  2060: istore_1       
        //  2061: aload           12
        //  2063: aload           11
        //  2065: checkcast       Ljava/lang/String;
        //  2068: iload_1        
        //  2069: iconst_1       
        //  2070: iadd           
        //  2071: invokeinterface pki.a:(Ljava/lang/String;I)V
        //  2076: aload           14
        //  2078: checkcast       Lohf;
        //  2081: getfield        ohf.c:Ljava/lang/Object;
        //  2084: aload           11
        //  2086: aload           13
        //  2088: invokeinterface java/util/Map.put:(Ljava/lang/Object;Ljava/lang/Object;)Ljava/lang/Object;
        //  2093: pop            
        //  2094: getstatic       afvn.a:Lcom/google/common/util/concurrent/ListenableFuture;
        //  2097: astore          11
        //  2099: goto            2134
        //  2102: astore          12
        //  2104: aload           12
        //  2106: ldc_w           "%s: Failed to add download future (%s) to map"
        //  2109: iconst_2       
        //  2110: anewarray       Ljava/lang/Object;
        //  2113: dup            
        //  2114: iconst_0       
        //  2115: ldc_w           "DownloadFutureMap"
        //  2118: aastore        
        //  2119: dup            
        //  2120: iconst_1       
        //  2121: aload           11
        //  2123: aastore        
        //  2124: invokestatic    pjs.f:(Ljava/lang/Throwable;Ljava/lang/String;[Ljava/lang/Object;)V
        //  2127: aload           12
        //  2129: invokestatic    afwm.l:(Ljava/lang/Throwable;)Lcom/google/common/util/concurrent/ListenableFuture;
        //  2132: astore          11
        //  2134: aload           11
        //  2136: areturn        
        //  2137: aload_0        
        //  2138: getfield        jlw.a:Ljava/lang/Object;
        //  2141: astore          13
        //  2143: aload_0        
        //  2144: getfield        jlw.c:Ljava/lang/Object;
        //  2147: astore          12
        //  2149: aload_0        
        //  2150: getfield        jlw.b:Ljava/lang/Object;
        //  2153: astore          11
        //  2155: aload           12
        //  2157: invokestatic    afwm.u:(Ljava/util/concurrent/Future;)Ljava/lang/Object;
        //  2160: checkcast       Ljava/lang/Boolean;
        //  2163: invokevirtual   java/lang/Boolean.booleanValue:()Z
        //  2166: ifeq            2216
        //  2169: aload           13
        //  2171: checkcast       Lnyw;
        //  2174: astore          12
        //  2176: new             Lihc;
        //  2179: dup            
        //  2180: aload           12
        //  2182: getfield        nyw.c:Lcom/google/common/util/concurrent/SettableFuture;
        //  2185: invokestatic    afwm.u:(Ljava/util/concurrent/Future;)Ljava/lang/Object;
        //  2188: checkcast       Lnym;
        //  2191: aload           11
        //  2193: aload           12
        //  2195: getfield        nyw.d:Lcom/google/common/util/concurrent/SettableFuture;
        //  2198: invokestatic    afwm.u:(Ljava/util/concurrent/Future;)Ljava/lang/Object;
        //  2201: checkcast       Laqvb;
        //  2204: iconst_3       
        //  2205: invokespecial   ihc.<init>:(Lnym;Ljava/util/List;Laqvb;I)V
        //  2208: invokestatic    sl.c:(Lace;)Lcom/google/common/util/concurrent/ListenableFuture;
        //  2211: astore          11
        //  2213: goto            2231
        //  2216: new             Ljava/lang/RuntimeException;
        //  2219: dup            
        //  2220: ldc_w           "GPU not supported."
        //  2223: invokespecial   java/lang/RuntimeException.<init>:(Ljava/lang/String;)V
        //  2226: invokestatic    afwm.l:(Ljava/lang/Throwable;)Lcom/google/common/util/concurrent/ListenableFuture;
        //  2229: astore          11
        //  2231: aload           11
        //  2233: areturn        
        //  2234: aload_0        
        //  2235: getfield        jlw.c:Ljava/lang/Object;
        //  2238: astore          14
        //  2240: aload_0        
        //  2241: getfield        jlw.a:Ljava/lang/Object;
        //  2244: astore          12
        //  2246: aload_0        
        //  2247: getfield        jlw.b:Ljava/lang/Object;
        //  2250: astore          13
        //  2252: new             Landroid/graphics/Point;
        //  2255: dup            
        //  2256: sipush          640
        //  2259: sipush          360
        //  2262: invokespecial   android/graphics/Point.<init>:(II)V
        //  2265: astore          11
        //  2267: aload           14
        //  2269: checkcast       Ljvl;
        //  2272: astore          14
        //  2274: aload           14
        //  2276: getfield        jvl.m:Laekp;
        //  2279: astore          15
        //  2281: aload           12
        //  2283: checkcast       Landroid/net/Uri;
        //  2286: astore          12
        //  2288: aload           15
        //  2290: aload           12
        //  2292: invokevirtual   aekp.l:(Landroid/net/Uri;)Z
        //  2295: ifeq            2395
        //  2298: aload           14
        //  2300: getfield        jvl.m:Laekp;
        //  2303: astore          13
        //  2305: aload           12
        //  2307: invokevirtual   android/net/Uri.getScheme:()Ljava/lang/String;
        //  2310: astore          14
        //  2312: aload           14
        //  2314: ifnull          2384
        //  2317: aload           13
        //  2319: aload           14
        //  2321: invokevirtual   aekp.k:(Ljava/lang/String;)Z
        //  2324: ifeq            2384
        //  2327: aload           13
        //  2329: getfield        aekp.a:Ljava/lang/Object;
        //  2332: aload           14
        //  2334: invokeinterface java/util/Map.get:(Ljava/lang/Object;)Ljava/lang/Object;
        //  2339: checkcast       Ladni;
        //  2342: astore          14
        //  2344: aload           14
        //  2346: ifnull          2373
        //  2349: aload           14
        //  2351: aload           13
        //  2353: getfield        aekp.b:Ljava/lang/Object;
        //  2356: checkcast       Landroid/content/ContentResolver;
        //  2359: aload           12
        //  2361: aload           11
        //  2363: invokeinterface adni.a:(Landroid/content/ContentResolver;Landroid/net/Uri;Landroid/graphics/Point;)Landroid/graphics/Bitmap;
        //  2368: astore          11
        //  2370: goto            2428
        //  2373: new             Ljava/lang/UnsupportedOperationException;
        //  2376: dup            
        //  2377: ldc_w           "Resource extraction not available for scheme"
        //  2380: invokespecial   java/lang/UnsupportedOperationException.<init>:(Ljava/lang/String;)V
        //  2383: athrow         
        //  2384: new             Ljava/lang/UnsupportedOperationException;
        //  2387: dup            
        //  2388: ldc_w           "Uri scheme not supported for thumbnail extraction"
        //  2391: invokespecial   java/lang/UnsupportedOperationException.<init>:(Ljava/lang/String;)V
        //  2394: athrow         
        //  2395: aload           14
        //  2397: getfield        jvl.l:Laekp;
        //  2400: aload           12
        //  2402: invokevirtual   aekp.f:(Landroid/net/Uri;)Ladnj;
        //  2405: aload           13
        //  2407: checkcast       Ladmv;
        //  2410: iconst_1       
        //  2411: aload           12
        //  2413: aconst_null    
        //  2414: invokeinterface adnj.b:(Ladmv;ILandroid/net/Uri;Ladng;)Ladnh;
        //  2419: aload           11
        //  2421: invokeinterface adnh.c:(Landroid/graphics/Point;)Landroid/graphics/Bitmap;
        //  2426: astore          11
        //  2428: aload           11
        //  2430: invokestatic    aezp.j:(Ljava/lang/Object;)Laezp;
        //  2433: invokestatic    afwm.m:(Ljava/lang/Object;)Lcom/google/common/util/concurrent/ListenableFuture;
        //  2436: areturn        
        //  2437: aload_0        
        //  2438: getfield        jlw.a:Ljava/lang/Object;
        //  2441: astore          13
        //  2443: aload_0        
        //  2444: getfield        jlw.c:Ljava/lang/Object;
        //  2447: astore          12
        //  2449: aload_0        
        //  2450: getfield        jlw.b:Ljava/lang/Object;
        //  2453: astore          11
        //  2455: aload           13
        //  2457: checkcast       Ljtr;
        //  2460: astore          13
        //  2462: aload           13
        //  2464: getfield        jtr.b:Lfln;
        //  2467: astore          14
        //  2469: aload           11
        //  2471: checkcast       Lcom/google/protos/youtube/api/innertube/OfflineVideoEndpointOuterClass$OfflineVideoEndpoint;
        //  2474: astore          11
        //  2476: aload           11
        //  2478: getfield        com/google/protos/youtube/api/innertube/OfflineVideoEndpointOuterClass$OfflineVideoEndpoint.c:I
        //  2481: iconst_1       
        //  2482: if_icmpne       2498
        //  2485: aload           11
        //  2487: getfield        com/google/protos/youtube/api/innertube/OfflineVideoEndpointOuterClass$OfflineVideoEndpoint.d:Ljava/lang/Object;
        //  2490: checkcast       Ljava/lang/String;
        //  2493: astore          11
        //  2495: goto            2503
        //  2498: ldc_w           ""
        //  2501: astore          11
        //  2503: aload           14
        //  2505: aload           11
        //  2507: invokeinterface fln.b:(Ljava/lang/String;)Lashn;
        //  2512: new             Ljbe;
        //  2515: dup            
        //  2516: aload           13
        //  2518: bipush          16
        //  2520: invokespecial   jbe.<init>:(Ljtr;I)V
        //  2523: invokevirtual   ashn.w:(Lasjr;)Lashn;
        //  2526: astore          11
        //  2528: aload           12
        //  2530: checkcast       Lamgp;
        //  2533: astore          12
        //  2535: aload           11
        //  2537: new             Liov;
        //  2540: dup            
        //  2541: aload           13
        //  2543: aload           12
        //  2545: bipush          8
        //  2547: invokespecial   iov.<init>:(Ljtr;Lamgp;I)V
        //  2550: invokevirtual   ashn.C:(Lasjr;)Lashn;
        //  2553: new             Limy;
        //  2556: dup            
        //  2557: aload           13
        //  2559: aload           12
        //  2561: bipush          12
        //  2563: invokespecial   imy.<init>:(Ljtr;Lamgp;I)V
        //  2566: invokestatic    asie.F:(Ljava/util/concurrent/Callable;)Lasie;
        //  2569: invokevirtual   ashn.Y:(Lasih;)Lasie;
        //  2572: ldc2_w          4
        //  2575: getstatic       java/util/concurrent/TimeUnit.SECONDS:Ljava/util/concurrent/TimeUnit;
        //  2578: invokevirtual   asie.R:(JLjava/util/concurrent/TimeUnit;)Lasie;
        //  2581: new             Liov;
        //  2584: dup            
        //  2585: aload           13
        //  2587: aload           12
        //  2589: bipush          9
        //  2591: invokespecial   iov.<init>:(Ljtr;Lamgp;I)V
        //  2594: invokevirtual   asie.N:(Lasjr;)Lasie;
        //  2597: invokestatic    vdh.aY:(Lasie;)Lcom/google/common/util/concurrent/ListenableFuture;
        //  2600: areturn        
        //  2601: aload_0        
        //  2602: getfield        jlw.c:Ljava/lang/Object;
        //  2605: astore          13
        //  2607: aload_0        
        //  2608: getfield        jlw.b:Ljava/lang/Object;
        //  2611: astore          11
        //  2613: aload_0        
        //  2614: getfield        jlw.a:Ljava/lang/Object;
        //  2617: astore          15
        //  2619: getstatic       akyu.a:Lakyu;
        //  2622: astore          12
        //  2624: aload           11
        //  2626: checkcast       Ljava/lang/String;
        //  2629: astore          11
        //  2631: aload           13
        //  2633: new             Lagoe;
        //  2636: dup            
        //  2637: aload           11
        //  2639: aload           12
        //  2641: invokespecial   agoe.<init>:(Ljava/lang/String;Lakyu;)V
        //  2644: invokestatic    teu.h:(Ljava/util/concurrent/Future;Ljava/lang/Object;)Ljava/lang/Object;
        //  2647: checkcast       Lagoe;
        //  2650: astore          12
        //  2652: getstatic       anyc.a:Lanyc;
        //  2655: invokevirtual   ahbh.createBuilder:()Lahaz;
        //  2658: astore          13
        //  2660: new             Ljava/util/HashSet;
        //  2663: dup            
        //  2664: invokespecial   java/util/HashSet.<init>:()V
        //  2667: astore          14
        //  2669: aload           15
        //  2671: checkcast       Lagoe;
        //  2674: invokevirtual   agoe.c:()Lanyc;
        //  2677: astore          15
        //  2679: iload           4
        //  2681: istore_1       
        //  2682: aload           15
        //  2684: ifnull          2751
        //  2687: aload           15
        //  2689: getfield        anyc.b:Lahbx;
        //  2692: invokeinterface java/util/List.iterator:()Ljava/util/Iterator;
        //  2697: astore          16
        //  2699: iload_3        
        //  2700: istore_2       
        //  2701: iload_2        
        //  2702: istore_1       
        //  2703: aload           16
        //  2705: invokeinterface java/util/Iterator.hasNext:()Z
        //  2710: ifeq            2751
        //  2713: aload           16
        //  2715: invokeinterface java/util/Iterator.next:()Ljava/lang/Object;
        //  2720: checkcast       Lanyd;
        //  2723: astore          15
        //  2725: aload           14
        //  2727: aload           15
        //  2729: invokestatic    jlx.f:(Lanyd;)Ljava/lang/String;
        //  2732: invokeinterface java/util/Set.add:(Ljava/lang/Object;)Z
        //  2737: pop            
        //  2738: aload           13
        //  2740: aload           15
        //  2742: invokevirtual   ahaz.bz:(Lanyd;)V
        //  2745: iinc            2, 1
        //  2748: goto            2701
        //  2751: aload           12
        //  2753: invokevirtual   agoe.c:()Lanyc;
        //  2756: astore          15
        //  2758: aload           15
        //  2760: ifnull          2829
        //  2763: aload           15
        //  2765: getfield        anyc.b:Lahbx;
        //  2768: invokeinterface java/util/List.iterator:()Ljava/util/Iterator;
        //  2773: astore          16
        //  2775: aload           16
        //  2777: invokeinterface java/util/Iterator.hasNext:()Z
        //  2782: ifeq            2829
        //  2785: aload           16
        //  2787: invokeinterface java/util/Iterator.next:()Ljava/lang/Object;
        //  2792: checkcast       Lanyd;
        //  2795: astore          15
        //  2797: aload           14
        //  2799: aload           15
        //  2801: invokestatic    jlx.f:(Lanyd;)Ljava/lang/String;
        //  2804: invokeinterface java/util/Set.contains:(Ljava/lang/Object;)Z
        //  2809: ifne            2775
        //  2812: aload           13
        //  2814: aload           15
        //  2816: iload_1        
        //  2817: invokestatic    jlx.e:(Lanyd;I)Lanyd;
        //  2820: invokevirtual   ahaz.bz:(Lanyd;)V
        //  2823: iinc            1, 1
        //  2826: goto            2775
        //  2829: aload           12
        //  2831: getfield        agoe.a:Ljava/lang/Object;
        //  2834: checkcast       Lahbh;
        //  2837: invokevirtual   ahbh.toBuilder:()Lahaz;
        //  2840: astore          15
        //  2842: aload           15
        //  2844: invokevirtual   ahaz.copyOnWrite:()V
        //  2847: aload           15
        //  2849: getfield        ahaz.instance:Lahbh;
        //  2852: checkcast       Lakyu;
        //  2855: invokestatic    akyu.emptyProtobufList:()Lahbx;
        //  2858: putfield        akyu.c:Lahbx;
        //  2861: getstatic       akzb.a:Lakzb;
        //  2864: invokevirtual   ahbh.createBuilder:()Lahaz;
        //  2867: astore          14
        //  2869: aload           13
        //  2871: invokevirtual   ahaz.build:()Lahbh;
        //  2874: checkcast       Lanyc;
        //  2877: astore          16
        //  2879: aload           14
        //  2881: invokevirtual   ahaz.copyOnWrite:()V
        //  2884: aload           14
        //  2886: getfield        ahaz.instance:Lahbh;
        //  2889: checkcast       Lakzb;
        //  2892: astore          13
        //  2894: aload           16
        //  2896: invokevirtual   java/lang/Object.getClass:()Ljava/lang/Class;
        //  2899: pop            
        //  2900: aload           13
        //  2902: aload           16
        //  2904: putfield        akzb.c:Ljava/lang/Object;
        //  2907: aload           13
        //  2909: ldc_w           87359530
        //  2912: putfield        akzb.b:I
        //  2915: aload           15
        //  2917: aload           14
        //  2919: invokevirtual   ahaz.build:()Lahbh;
        //  2922: checkcast       Lakzb;
        //  2925: invokevirtual   ahaz.ba:(Lakzb;)V
        //  2928: new             Lagoe;
        //  2931: dup            
        //  2932: aload           11
        //  2934: aload           15
        //  2936: invokevirtual   ahaz.build:()Lahbh;
        //  2939: checkcast       Lakyu;
        //  2942: invokespecial   agoe.<init>:(Ljava/lang/String;Lakyu;)V
        //  2945: astore          11
        //  2947: aload           11
        //  2949: aload           12
        //  2951: getfield        agoe.b:I
        //  2954: putfield        agoe.b:I
        //  2957: aload           11
        //  2959: invokestatic    afwm.m:(Ljava/lang/Object;)Lcom/google/common/util/concurrent/ListenableFuture;
        //  2962: areturn        
        //  2963: aload_0        
        //  2964: getfield        jlw.a:Ljava/lang/Object;
        //  2967: astore          13
        //  2969: aload_0        
        //  2970: getfield        jlw.b:Ljava/lang/Object;
        //  2973: astore          11
        //  2975: aload_0        
        //  2976: getfield        jlw.c:Ljava/lang/Object;
        //  2979: astore          15
        //  2981: getstatic       akyu.a:Lakyu;
        //  2984: astore          12
        //  2986: aload           11
        //  2988: checkcast       Ljava/lang/String;
        //  2991: astore          11
        //  2993: aload           13
        //  2995: new             Lagoe;
        //  2998: dup            
        //  2999: aload           11
        //  3001: aload           12
        //  3003: invokespecial   agoe.<init>:(Ljava/lang/String;Lakyu;)V
        //  3006: invokestatic    teu.h:(Ljava/util/concurrent/Future;Ljava/lang/Object;)Ljava/lang/Object;
        //  3009: checkcast       Lagoe;
        //  3012: astore          12
        //  3014: getstatic       anyc.a:Lanyc;
        //  3017: invokevirtual   ahbh.createBuilder:()Lahaz;
        //  3020: astore          13
        //  3022: new             Ljava/util/HashSet;
        //  3025: dup            
        //  3026: invokespecial   java/util/HashSet.<init>:()V
        //  3029: astore          14
        //  3031: aload           15
        //  3033: ifnull          3101
        //  3036: aload           15
        //  3038: checkcast       Lanyc;
        //  3041: getfield        anyc.b:Lahbx;
        //  3044: invokeinterface java/util/List.iterator:()Ljava/util/Iterator;
        //  3049: astore          15
        //  3051: iload_2        
        //  3052: istore_1       
        //  3053: aload           15
        //  3055: invokeinterface java/util/Iterator.hasNext:()Z
        //  3060: ifeq            3101
        //  3063: aload           15
        //  3065: invokeinterface java/util/Iterator.next:()Ljava/lang/Object;
        //  3070: checkcast       Lanyd;
        //  3073: astore          16
        //  3075: aload           14
        //  3077: aload           16
        //  3079: invokestatic    jlx.f:(Lanyd;)Ljava/lang/String;
        //  3082: invokeinterface java/util/Set.add:(Ljava/lang/Object;)Z
        //  3087: pop            
        //  3088: aload           13
        //  3090: aload           16
        //  3092: invokevirtual   ahaz.bz:(Lanyd;)V
        //  3095: iinc            2, 1
        //  3098: goto            3051
        //  3101: aload           12
        //  3103: invokevirtual   agoe.c:()Lanyc;
        //  3106: astore          15
        //  3108: aload           15
        //  3110: ifnull          3179
        //  3113: aload           15
        //  3115: getfield        anyc.b:Lahbx;
        //  3118: invokeinterface java/util/List.iterator:()Ljava/util/Iterator;
        //  3123: astore          16
        //  3125: aload           16
        //  3127: invokeinterface java/util/Iterator.hasNext:()Z
        //  3132: ifeq            3179
        //  3135: aload           16
        //  3137: invokeinterface java/util/Iterator.next:()Ljava/lang/Object;
        //  3142: checkcast       Lanyd;
        //  3145: astore          15
        //  3147: aload           14
        //  3149: aload           15
        //  3151: invokestatic    jlx.f:(Lanyd;)Ljava/lang/String;
        //  3154: invokeinterface java/util/Set.contains:(Ljava/lang/Object;)Z
        //  3159: ifne            3125
        //  3162: aload           13
        //  3164: aload           15
        //  3166: iload_1        
        //  3167: invokestatic    jlx.e:(Lanyd;I)Lanyd;
        //  3170: invokevirtual   ahaz.bz:(Lanyd;)V
        //  3173: iinc            1, 1
        //  3176: goto            3125
        //  3179: aload           12
        //  3181: getfield        agoe.a:Ljava/lang/Object;
        //  3184: checkcast       Lahbh;
        //  3187: invokevirtual   ahbh.toBuilder:()Lahaz;
        //  3190: astore          14
        //  3192: aload           14
        //  3194: invokevirtual   ahaz.copyOnWrite:()V
        //  3197: aload           14
        //  3199: getfield        ahaz.instance:Lahbh;
        //  3202: checkcast       Lakyu;
        //  3205: invokestatic    akyu.emptyProtobufList:()Lahbx;
        //  3208: putfield        akyu.c:Lahbx;
        //  3211: getstatic       akzb.a:Lakzb;
        //  3214: invokevirtual   ahbh.createBuilder:()Lahaz;
        //  3217: astore          15
        //  3219: aload           13
        //  3221: invokevirtual   ahaz.build:()Lahbh;
        //  3224: checkcast       Lanyc;
        //  3227: astore          13
        //  3229: aload           15
        //  3231: invokevirtual   ahaz.copyOnWrite:()V
        //  3234: aload           15
        //  3236: getfield        ahaz.instance:Lahbh;
        //  3239: checkcast       Lakzb;
        //  3242: astore          16
        //  3244: aload           13
        //  3246: invokevirtual   java/lang/Object.getClass:()Ljava/lang/Class;
        //  3249: pop            
        //  3250: aload           16
        //  3252: aload           13
        //  3254: putfield        akzb.c:Ljava/lang/Object;
        //  3257: aload           16
        //  3259: ldc_w           87359530
        //  3262: putfield        akzb.b:I
        //  3265: aload           14
        //  3267: aload           15
        //  3269: invokevirtual   ahaz.build:()Lahbh;
        //  3272: checkcast       Lakzb;
        //  3275: invokevirtual   ahaz.ba:(Lakzb;)V
        //  3278: new             Lagoe;
        //  3281: dup            
        //  3282: aload           11
        //  3284: aload           14
        //  3286: invokevirtual   ahaz.build:()Lahbh;
        //  3289: checkcast       Lakyu;
        //  3292: invokespecial   agoe.<init>:(Ljava/lang/String;Lakyu;)V
        //  3295: astore          11
        //  3297: aload           11
        //  3299: aload           12
        //  3301: getfield        agoe.b:I
        //  3304: putfield        agoe.b:I
        //  3307: aload           11
        //  3309: invokestatic    afwm.m:(Ljava/lang/Object;)Lcom/google/common/util/concurrent/ListenableFuture;
        //  3312: areturn        
        //    Exceptions:
        //  Try           Handler
        //  Start  End    Start  End    Type                            
        //  -----  -----  -----  -----  --------------------------------
        //  228    236    239    241    Ljava/lang/SecurityException;
        //  311    330    365    374    Ladkv;
        //  335    346    365    374    Ladkv;
        //  349    362    365    374    Ladkv;
        //  741    760    795    804    Ladkv;
        //  765    776    795    804    Ladkv;
        //  779    792    795    804    Ladkv;
        //  1124   1141   1144   1154   Ljava/lang/InterruptedException;
        //  1765   1780   1788   1853   Ljava/io/IOException;
        //  1765   1780   1783   1943   Any
        //  1790   1853   1783   1943   Any
        //  1853   1915   1783   1943   Any
        //  1923   1928   1931   1940   Any
        //  2037   2094   2102   2134   Ljava/lang/Exception;
        // 
        // The error that occurred was:
        // 
        // java.lang.IllegalStateException: Expression is linked from several locations: Label_1923:
        //     at com.strobel.decompiler.ast.Error.expressionLinkedFromMultipleLocations(Error.java:27)
        //     at com.strobel.decompiler.ast.AstOptimizer.mergeDisparateObjectInitializations(AstOptimizer.java:2604)
        //     at com.strobel.decompiler.ast.AstOptimizer.optimize(AstOptimizer.java:235)
        //     at com.strobel.decompiler.ast.AstOptimizer.optimize(AstOptimizer.java:42)
        //     at com.strobel.decompiler.languages.java.ast.AstMethodBodyBuilder.createMethodBody(AstMethodBodyBuilder.java:206)
        //     at com.strobel.decompiler.languages.java.ast.AstMethodBodyBuilder.createMethodBody(AstMethodBodyBuilder.java:93)
        //     at com.strobel.decompiler.languages.java.ast.AstBuilder.createMethodBody(AstBuilder.java:868)
        //     at com.strobel.decompiler.languages.java.ast.AstBuilder.createMethod(AstBuilder.java:761)
        //     at com.strobel.decompiler.languages.java.ast.AstBuilder.addTypeMembers(AstBuilder.java:638)
        //     at com.strobel.decompiler.languages.java.ast.AstBuilder.createTypeCore(AstBuilder.java:605)
        //     at com.strobel.decompiler.languages.java.ast.AstBuilder.createTypeNoCache(AstBuilder.java:195)
        //     at com.strobel.decompiler.languages.java.ast.AstBuilder.createType(AstBuilder.java:162)
        //     at com.strobel.decompiler.languages.java.ast.AstBuilder.addType(AstBuilder.java:137)
        //     at com.strobel.decompiler.languages.java.JavaLanguage.buildAst(JavaLanguage.java:71)
        //     at com.strobel.decompiler.languages.java.JavaLanguage.decompileType(JavaLanguage.java:59)
        //     at com.strobel.decompiler.DecompilerDriver.decompileType(DecompilerDriver.java:333)
        //     at com.strobel.decompiler.DecompilerDriver.decompileJar(DecompilerDriver.java:254)
        //     at com.strobel.decompiler.DecompilerDriver.main(DecompilerDriver.java:129)
        // 
        throw new IllegalStateException("An error occurred while decompiling this method.");
    }
}
